Workbook
Name Additional_Factor: 'אפשרויות בחירה'!$C$701:$C$850
Name Amoritization: 'אפשרויות בחירה'!$C$546:$C$550
Name Capsule: 'אפשרויות בחירה'!$C$926:$C$928
Name Company_Name: 'File Name Info'!$A$34:$A$120
Name Company_Name_ID: 'File Name Info'!$A$34:$B$120
Name Consortium: 'אפשרויות בחירה'!$C$514:$C$515
Name Country_list: 'אפשרויות בחירה'!$C$4:$C$85
Name Country_list_funds: 'אפשרויות בחירה'!$C$4:$C$103
Name CSA: 'אפשרויות בחירה'!$C$688:$C$689
Name Delivery: 'אפשרויות בחירה'!$C$666:$C$667
Name Dependence_Independence: 'אפשרויות בחירה'!$C$654:$C$655
Name Duration_Underlying_Interest_Rate: 'אפשרויות בחירה'!$C$680:$C$687
Name File_Type: 'File Name Info'!$A$10:$A$12
Name Full_File_Type: 'File Name Info'!$A$11:$B$13
Name Full_Type: 'File Name Info'!$A$2:$B$8
Name Full_Type_Nostro: 'File Name Info'!$A$3:$B$6
Name Full_Year: 'File Name Info'!$A$22:$B$31
Name Fund_Strategy: 'אפשרויות בחירה'!$C$597:$C$621
Name Fund_type: 'אפשרויות בחירה'!$C$328:$C$498
Name Holding_interest: 'אפשרויות בחירה'!$C$146:$C$147
Name In_the_books: 'אפשרויות בחירה'!$C$656:$C$657
Name Industry_Sector: 'אפשרויות בחירה'!$C$1129:$C$1245
Name Industry_sector_all: 'אפשרויות בחירה'!$C$202:$C$327
Name Industry_sectors: 'אפשרויות בחירה'!$C$202:$C$327
Name israel_abroad: 'אפשרויות בחירה'!$C$2:$C$3
Name Issuer_Number_Banks: 'אפשרויות בחירה'!$C$111:$C$113
Name Issuer_Number_Fund: 'אפשרויות בחירה'!$C$114:$C$117
Name issuer_number_loan: 'אפשרויות בחירה'!$C$118:$C$126
Name Issuer_Number_Type: 'אפשרויות בחירה'!$C$104:$C$110
Name Issuer_Number_Type_2: 'אפשרויות בחירה'!$C$1076:$C$1079
Name Issuer_Number_Type_3: 'אפשרויות בחירה'!$C$1081:$C$1085
Name Issuer_Number_Type_V2: 'אפשרויות בחירה'!$C$104:$C$110
Name Issuer_Type_TFunds: 'אפשרויות בחירה'!$C$1087:$C$1089
Name Leading_factor: 'אפשרויות בחירה'!$C$692:$C$700
Name Linked_Type: 'אפשרויות בחירה'!$C$516:$C$519
Name other_investments: 'אפשרויות בחירה'!$C$1000:$C$1033
Name Penalty: 'אפשרויות בחירה'!$C$851:$C$852
Name QTR: 'File Name Info'!$A$15:$A$19
Name Rating_Agency: 'אפשרויות בחירה'!$C$188:$C$201
Name real_estate_lifestage: 'אפשרויות בחירה'!$C$634:$C$642
Name real_estate_loans: 'אפשרויות בחירה'!$C$553:$C$591
Name Real_Estate_Main_Use: 'אפשרויות בחירה'!$C$622:$C$633
Name Recourse_Nonrecourse: 'אפשרויות בחירה'!$C$544:$C$545
Name Repayment_Rights: 'אפשרויות בחירה'!$C$551:$C$552
Name Reset_frequency: 'אפשרויות בחירה'!$C$658:$C$665
Name Security_ID_Number_Type: 'אפשרויות בחירה'!$C$1113:$C$1116
Name Security_Number_Loans: 'אפשרויות בחירה'!$C$131
Name Stock_Exchange: 'אפשרויות בחירה'!$C$1283:$C$1315
Name Stock_Exchange_Gov_Bonds: 'אפשרויות בחירה'!$C$148:$C$181
Name Subordination_Risk: 'אפשרויות בחירה'!$C$186:$C$187
Name Tradeable_Status: 'אפשרויות בחירה'!$C$1272:$C$1281
Name Tradeable_Status_All: 'אפשרויות בחירה'!$C$135:$C$145
Name tradeable_status_bonds: 'אפשרויות בחירה'!$C$1248:$C$1253
Name tradeable_status_funds: 'אפשרויות בחירה'!$C$1118:$C$1119
Name tradeable_status_stock: 'אפשרויות בחירה'!$C$1255:$C$1259
Name Tradeable_Status_v2: 'אפשרויות בחירה'!$C$1121:$C$1126
Name tradeable_status_warrants: 'אפשרויות בחירה'!$C$1261:$C$1265
Name tradeable_status_warrants_v2: 'אפשרויות בחירה'!$C$1267:$C$1269
Name Transaction: 'אפשרויות בחירה'!$C$643:$C$646
Name Type: 'File Name Info'!$A$2:$A$8

Sheet עמוד פתיחה
A1: קובץ דיווח עבור רשימת נכסים ברמת הנכס הבודד (חוזר גופים מוסדיים 2015-9-14)
A3: יש לבחור תחום: | C3: נכסי אפיק השקעה מובטח תשואה
A5: האם מדובר בקובץ לממומנה או לציבור: | C5: לציבור
A7: יש לבחור את רבעון הדיווח: | C7: Q4
A9: יש לבחור את שנת הדיווח: | C9: 2025
A11: יש לבחור את הגוף המוסדי: | C11: מור גמל ופנסיה בע"מ
A13: ח.פ. הגוף המוסדי: | C13: =IFERROR(VLOOKUP(C11,'File Name Info'!A35:B121,2,0),"תא מחושב") -> 514956465
A15: שם קובץ לשמירה | C15: =IF(C5="לממונה",CONCATENATE(C13, "_",VLOOKUP(C3,Full_Type,2,0),"_",C7,VLOOKUP(C9,Full_Year,2,0),".xlxs"),IF(C5="לציבור",CONCATENATE(C13,"_",VLOOKUP(C3,Full_Type_Nostro,2,0),"_",VLOOKUP(C5,Full_File_Type,2,0),"_",C7,VLOOKUP(C9,Full_Year,2,0),".xlsx"),"שם קובץ לשמירה")) -> 514956465_ca_p_Q425.xlsx
A17: פרטי האחראי על הדיווח בגוף המוסדי | B17: שם: | C17: ליאת דוידוב
B19: מספר טלפון:
B21: כתובת מייל: | C21: liat.davidov@more.co.il
A23: הוראות למילוי הדיווח: | C23: יש לדווח לפי ההנחיות בחלק ג' לנספח 5.4.3.2 שבפרק 3 שבחלק 4 לשער 5 בחוזר המאוחד - "רשימת נכסים ברמת הנכס הבודד".

Sheet סכום נכסים
A1: Column1 | B1: Column2 | C1: ידווח בקבצי נכסי הנוסטרו בלבד | D1: Column3 | E1: Column4
A2: ריק במקור | B2: שווי הוגן | C2: עלות מופחתת | D2: השיטה שיושמה בדוח הכספי | E2: שיעור מסך נכסי השקעה
A3: מזומנים ושווי מזומנים | B3: 924895.26 | C3: ריק במקור | D3: ריק במקור | E3: 0.21461939
A4: איגרות חוב ממשלתיות | B4: 1042136.3 | C4: ריק במקור | D4: ריק במקור | E4: 0.24182484
A5: ניירות ערך מסחריים | B5: 0 | C5: ריק במקור | D5: ריק במקור | E5: 0
A6: איגרות חוב | B6: 530457.51 | C6: ריק במקור | D6: ריק במקור | E6: 0.1230912
A7: מניות, מניות בכורה ויחידות השתתפות | B7: 831025.92 | C7: ריק במקור | D7: ריק במקור | E7: 0.19283727
A8: קרנות סל | B8: 346255.48 | C8: ריק במקור | D8: ריק במקור | E8: 0.080347627
A9: קרנות נאמנות | B9: 650118.67 | C9: ריק במקור | D9: ריק במקור | E9: 0.15085824
A10: כתבי אופציה | B10: 3549.4365 | C10: ריק במקור | D10: ריק במקור | E10: 0.00082363693
A11: אופציות | B11: 0 | C11: ריק במקור | D11: ריק במקור | E11: 0
A12: חוזים עתידיים | B12: 4574.5952 | C12: ריק במקור | D12: ריק במקור | E12: 0.0010615222
A13: מוצרים מובנים | B13: 7.46292 | C13: ריק במקור | D13: ריק במקור | E13: 1.7317499e-06
A14: לא סחיר איגרות חוב ממשלתיות | B14: 0 | C14: ריק במקור | D14: ריק במקור | E14: 0
... A29: נכסים אחרים | B29: 1860.9746 | C29: ריק במקור | D29: ריק במקור | E29: 0.00043183401
A30: סך הכל נכסים | B30: 4309467.4 | C30: 0 | D30: ריק במקור | E30: 1
A31: מסגרות אשראי | B31: 58597.759 | C31: ריק במקור | D31: ריק במקור | E31: ריק במקור
A32: יתרות התחייבויות להשקעה | B32: 189226.27 | C32: ריק במקור | D32: ריק במקור | E32: ריק במקור
AZ10000: 1

Sheet מזומנים ושווי מזומנים
A1: מספר קופה/קרן/ח.פ. עבור חברת ביטוח | B1: מספר מסלול | C1: שם הבנק | D1: מספר מזהה בנק | E1: סוג מספר מזהה בנק | F1: מאפיין עיקרי | G1: ישראל/חו"ל | H1: בעל עניין/צד קשור | I1: דירוג הבנק | J1: שם מדרג | K1: מטבע פעילות | L1: שווי מטבעי | M1: שער חליפין | N1: שיעור ריבית | O1: שווי הוגן (באלפי ש"ח) | P1: שיעור מנכסי אפיק ההשקעה | Q1: שיעור מסך נכסי ההשקעה
A2: 13908 | B2: 13908 | C2: בנק הבינלאומי הראשון בע"מ | D2: 31 | E2: סימול בנק | F2: מזומן ועו"ש בש"ח | G2: ישראל | H2: לא | I2: ilAAA | J2: S&P מעלות | K2: ILS | L2: 668867.3 | M2: 1 | N2: ריק במקור | O2: 668867.3 | P2: 0.72318167 | Q2: 0.15520881
A3: 13908 | B3: 13908 | C3: בנק הבינלאומי הראשון בע"מ | D3: 31 | E3: סימול בנק | F3: מזומן ועו"ש נקוב במט"ח | G3: ישראל | H3: לא | I3: ilAAA | J3: S&P מעלות | K3: USD | L3: =44594.5536708464-175.90482 -> 44418.649 | M3: 3.19 | N3: ריק במקור | O3: =142256.62621-175.90482*3.19 -> 141695.49 | P3: 0.15380836 | Q3: 0.033010257
A4: 13908 | B4: 13908 | C4: בנק הבינלאומי הראשון בע"מ | D4: 31 | E4: סימול בנק | F4: מזומן ועו"ש נקוב במט"ח | G4: ישראל | H4: לא | I4: ilAAA | J4: S&P מעלות | K4: CHF | L4: 49.01082 | M4: 4.0213 | N4: ריק במקור | O4: 197.08721 | P4: 0.00021309138 | Q4: 4.5733542e-05
A5: 13908 | B5: 13908 | C5: בנק הבינלאומי הראשון בע"מ | D5: 31 | E5: סימול בנק | F5: מזומן ועו"ש נקוב במט"ח | G5: ישראל | H5: לא | I5: ilAAA | J5: S&P מעלות | K5: GBP | L5: 366.10246 | M5: 4.29 | N5: ריק במקור | O5: 1570.5795 | P5: 0.0016981161 | Q5: 0.00036444864
A6: 13908 | B6: 13908 | C6: בנק הבינלאומי הראשון בע"מ | D6: 31 | E6: סימול בנק | F6: מזומן ועו"ש נקוב במט"ח | G6: ישראל | H6: לא | I6: ilAAA | J6: S&P מעלות | K6: JPY | L6: 963382.37 | M6: 0.020365 | N6: ריק במקור | O6: 19619.282 | P6: 0.021212437 | Q6: 0.0045526001
A7: 13908 | B7: 13908 | C7: בנק הבינלאומי הראשון בע"מ | D7: 31 | E7: סימול בנק | F7: מזומן ועו"ש נקוב במט"ח | G7: ישראל | H7: לא | I7: ilAAA | J7: S&P מעלות | K7: CAD | L7: 13.840662 | M7: 2.3275 | N7: ריק במקור | O7: 32.21414 | P7: 3.4830041e-05 | Q7: 7.4752021e-06
A8: 13908 | B8: 13908 | C8: בנק הבינלאומי הראשון בע"מ | D8: 31 | E8: סימול בנק | F8: מזומן ועו"ש נקוב במט"ח | G8: ישראל | H8: לא | I8: ilAAA | J8: S&P מעלות | K8: EUR | L8: 1.0679482e-05 | M8: 3.7455 | N8: ריק במקור | O8: 4e-05 | P8: 4.324814e-11 | Q8: 9.2818894e-12
A9: 13908 | B9: 13908 | C9: בנק הבינלאומי הראשון בע"מ | D9: 31 | E9: סימול בנק | F9: מזומן ועו"ש נקוב במט"ח | G9: ישראל | H9: לא | I9: ilAAA | J9: S&P מעלות | K9: EUR | L9: 7065.94 | M9: 3.7455 | N9: ריק במקור | O9: 26465.478 | P9: 0.028614568 | Q9: 0.0061412411
A10: 13908 | B10: 13908 | C10: בנק הבינלאומי הראשון בע"מ | D10: 31 | E10: סימול בנק | F10: מזומן ועו"ש נקוב במט"ח | G10: ישראל | H10: לא | I10: ilAAA | J10: S&P מעלות | K10: USD | L10: -4.0176991 | M10: 3.19 | N10: ריק במקור | O10: -12.81646 | P10: -1.3857201e-05 | Q10: -2.9740241e-06
A11: 13908 | B11: 13908 | C11: בנק הבינלאומי הראשון בע"מ | D11: 31 | E11: סימול בנק | F11: מזומן ועו"ש נקוב במט"ח | G11: ישראל | H11: לא | I11: ilAAA | J11: S&P מעלות | K11: USD | L11: 470.8692 | M11: 3.19 | N11: ריק במקור | O11: 1502.0728 | P11: 0.0016240463 | Q11: 0.00034855183
A12: 13908 | B12: 13908 | C12: בנק הבינלאומי הראשון בע"מ | D12: 31 | E12: סימול בנק | F12: מזומן ועו"ש נקוב במט"ח | G12: ישראל | H12: לא | I12: ilAAA | J12: S&P מעלות | K12: AUD | L12: 47.942211 | M12: 2.1319 | N12: ריק במקור | O12: 102.208 | P12: 0.00011050765 | Q12: 2.3717084e-05
A13: 13908 | B13: 13908 | C13: בנק הבינלאומי הראשון בע"מ | D13: 31 | E13: סימול בנק | F13: מזומן ועו"ש בש"ח | G13: ישראל | H13: לא | I13: ilAAA | J13: S&P מעלות | K13: ILS | L13: 32395.23 | M13: 1 | N13: ריק במקור | O13: 32395.23 | P13: 0.035025836 | Q13: 0.0075172235
A14: 13908 | B14: 13908 | C14: בנק הבינלאומי הראשון בע"מ | D14: 31 | E14: סימול בנק | F14: מזומן ועו"ש נקוב במט"ח | G14: ישראל | H14: לא | I14: ilAAA | J14: S&P מעלות | K14: USD | L14: 10000 | M14: 3.19 | N14: ריק במקור | O14: 31900 | P14: 0.034490392 | Q14: 0.0074023068
A15: 13908 | B15: 13908 | C15: בנק מזרחי טפחות בע"מ | D15: 20 | E15: סימול בנק | F15: מזומן ועו"ש נקוב במט"ח | G15: ישראל | H15: לא | I15: ilAAA | J15: S&P מעלות | K15: USD | L15: 175.90482 | M15: 3.19 | N15: ריק במקור | O15: =175.90482*3.19 -> 561.13638 | P15: 0.15380836 | Q15: 0.033010257
AZ10000: 1

Sheet איגרות חוב ממשלתיות
A1: מספר קופה/קרן/ח.פ. עבור חברת ביטוח | B1: מספר מסלול | C1: שם מנפיק | D1: שם נייר ערך | E1: מספר נייר ערך | F1: מאפיין עיקרי | G1: ישראל/חו"ל | H1: מדינה לפי חשיפה כלכלית | I1: זירת מסחר | J1: דירוג | K1: שם מדרג | L1: מטבע פעילות | M1: מח"מ | N1: מועד פדיון | O1: שיעור ריבית | P1: תשואה לפדיון | Q1: סכום לקבל (במטבע הפעילות) | R1: ערך נקוב (יחידות) | S1: שער חליפין | T1: שער נייר הערך | U1: שווי הוגן (באלפי ש"ח) | V1: עלות מופחתת (באלפי ש"ח) | W1: השיטה שיושמה בדוח הכספי | X1: שיעור מערך נקוב מונפק | Y1: שיעור מנכסי אפיק ההשקעה | Z1: שיעור מסך נכסי ההשקעה
A2: 13908 | B2: 13908 | C2: מדינת ישראל | D2: ממשל שקלית 0142 | E2: IL0011254005 | F2: לא צמוד למדד המחירים לצרכן ריבית קבועה | G2: ישראל | H2: ישראל | I2: TASE | J2: NR | K2: NR | L2: ILS | M2: 10.981 | N2: 51897 | O2: 0.055 | P2: 0.0417 | Q2: 0 | R2: 3800000 | S2: 1 | T2: 120.4 | U2: 4575.2 | V2: ריק במקור | W2: שווי הוגן | X2: 0.00011746045 | Y2: 0.0043902128 | Z2: 0.0010616625
A3: 13908 | B3: 13908 | C3: מדינת ישראל | D3: ממשל שקלית 0327 | E3: IL0011393449 | F3: לא צמוד למדד המחירים לצרכן ריבית קבועה | G3: ישראל | H3: ישראל | I3: TASE | J3: NR | K3: NR | L3: ILS | M3: 1.224 | N3: 46477 | O3: 0.02 | P3: 0.0376 | Q3: 0 | R3: 8178400 | S3: 1 | T3: 99.41 | U3: 8130.1474 | V3: ריק במקור | W3: שווי הוגן | X3: 0.00028972246 | Y3: 0.0078014245 | Z3: 0.0018865782
A4: 13908 | B4: 13908 | C4: מדינת ישראל | D4: ממשל שקלית 0347 | E4: IL0011401937 | F4: לא צמוד למדד המחירים לצרכן ריבית קבועה | G4: ישראל | H4: ישראל | I4: TASE | J4: NR | K4: NR | L4: ILS | M4: 14.301 | N4: 53782 | O4: 0.0375 | P4: 0.0431 | Q4: 0 | R4: 5370250 | S4: 1 | T4: 95.14 | U4: 5109.2558 | V4: ריק במקור | W4: שווי הוגן | X4: 0.00019813948 | Y4: 0.0049026754 | Z4: 0.0011855887
A5: 13908 | B5: 13908 | C5: מדינת ישראל | D5: ממשל צמודה 0527 | E5: IL0011408478 | F5: צמוד למדד המחירים לצרכן בריבית קבועה | G5: ישראל | H5: ישראל | I5: TASE | J5: NR | K5: NR | L5: ILS | M5: 1.403 | N5: 46538 | O5: 0.0075 | P5: 0.0192 | Q5: 0 | R5: 94877805 | S5: 1 | T5: 117.85 | U5: 111813.49 | V5: ריק במקור | W5: שווי הוגן | X5: 0.0038953859 | Y5: 0.10729258 | Z5: 0.025946012
A6: 13908 | B6: 13908 | C6: מדינת ישראל | D6: ממשל שקלית 0928 | E6: IL0011508798 | F6: לא צמוד למדד המחירים לצרכן ריבית קבועה | G6: ישראל | H6: ישראל | I6: TASE | J6: NR | K6: NR | L6: ILS | M6: 2.676 | N6: 47024 | O6: 0.0225 | P6: 0.0373 | Q6: 0 | R6: 71135295 | S6: 1 | T6: 96.78 | U6: 68844.739 | V6: ריק במקור | W6: שווי הוגן | X6: 0.0020487379 | Y6: 0.066061167 | Z6: 0.015975231
A7: 13908 | B7: 13908 | C7: מדינת ישראל | D7: ממשל צמודה 0529 | E7: IL0011570236 | F7: צמוד למדד המחירים לצרכן בריבית קבועה | G7: ישראל | H7: ישראל | I7: TASE | J7: NR | K7: NR | L7: ILS | M7: 3.383 | N7: 47269 | O7: 0.005 | P7: 0.0171 | Q7: 0 | R7: 50817851 | S7: 1 | T7: 113.71 | U7: 57784.978 | V7: ריק במקור | W7: שווי הוגן | X7: 0.0016884101 | Y7: 0.055448582 | Z7: 0.013408844
A8: 13908 | B8: 13908 | C8: מדינת ישראל | D8: ממשל שקלית 0537 | E8: IL0011661803 | F8: לא צמוד למדד המחירים לצרכן ריבית קבועה | G8: ישראל | H8: ישראל | I8: TASE | J8: NR | K8: NR | L8: ILS | M8: 10.317 | N8: 50191 | O8: 0.015 | P8: 0.0404 | Q8: 0 | R8: 27617147 | S8: 1 | T8: 78 | U8: 21541.375 | V8: ריק במקור | W8: שווי הוגן | X8: 0.00065912066 | Y8: 0.020670401 | Z8: 0.0049986164
A9: 13908 | B9: 13908 | C9: מדינת ישראל | D9: ממשל משתנה 1130 | E9: IL0011665523 | F9: לא צמוד למדד המחירים לצרכן ריבית משתנה | G9: ישראל | H9: ישראל | I9: TASE | J9: NR | K9: NR | L9: ILS | M9: 4.485 | N9: 47816 | O9: 0.037843 | P9: 0.0422 | Q9: 0 | R9: 41429977 | S9: 1 | T9: 98.79 | U9: 40928.674 | V9: ריק במקור | W9: שווי הוגן | X9: 0.0012404804 | Y9: 0.039273822 | Z9: 0.0094973857
A10: 13908 | B10: 13908 | C10: מדינת ישראל | D10: ממשל צמודה 0726 | E10: IL0011695645 | F10: צמוד למדד המחירים לצרכן בריבית קבועה | G10: ישראל | H10: ישראל | I10: TASE | J10: NR | K10: NR | L10: ILS | M10: 0.578 | N10: 46234 | O10: 0.001 | P10: 0.0258 | Q10: 0 | R10: 70544896 | S10: 1 | T10: 116.46 | U10: 82156.586 | V10: ריק במקור | W10: שווי הוגן | X10: 0.0034915325 | Y10: 0.078834782 | Z10: 0.019064209
A11: 13908 | B11: 13908 | C11: מדינת ישראל | D11: ממשל צמודה 1131 | E11: IL0011722209 | F11: צמוד למדד המחירים לצרכן בריבית קבועה | G11: ישראל | H11: ישראל | I11: TASE | J11: NR | K11: NR | L11: ILS | M11: 5.899 | N11: 48182 | O11: 0.001 | P11: 0.017 | Q11: 0 | R11: 15892000 | S11: 1 | T11: 107.5 | U11: 17083.9 | V11: ריק במקור | W11: שווי הוגן | X11: 0.00046429175 | Y11: 0.016393154 | Z11: 0.0039642717
A12: 13908 | B12: 13908 | C12: מדינת ישראל | D12: ממשל שקלית 0432 | E12: IL0011806606 | F12: לא צמוד למדד המחירים לצרכן ריבית קבועה | G12: ישראל | H12: ישראל | I12: TASE | J12: NR | K12: NR | L12: ILS | M12: 6.04 | N12: 48334 | O12: 0.013 | P12: 0.0379 | Q12: 0 | R12: 82012941 | S12: 1 | T12: 87.06 | U12: 71400.466 | V12: ריק במקור | W12: שווי הוגן | X12: 0.0019959954 | Y12: 0.06851356 | Z12: 0.016568281
A13: 13908 | B13: 13908 | C13: מדינת ישראל | D13: ממשל שקלית 1152 | E13: IL0011840761 | F13: לא צמוד למדד המחירים לצרכן ריבית קבועה | G13: ישראל | H13: ישראל | I13: TASE | J13: NR | K13: NR | L13: ILS | M13: 17.816 | N13: 55852 | O13: 0.028 | P13: 0.0444 | Q13: 0 | R13: 3329807 | S13: 1 | T13: 74.76 | U13: 2489.3637 | V13: ריק במקור | W13: שווי הוגן | X13: 0.00011100171 | Y13: 0.0023887123 | Z13: 0.00057764996
... A31: 13908 | B31: 13908 | C31: STATE OF ISRAEL | D31: ISRAEL 5.625 2/35 | E31: US46514Y8B63 | F31: נקוב במט"ח | G31: חו"ל | H31: ישראל | I31: LSE | J31: Baa1 | K31: Moodys | L31: USD | M31: 7.17 | N31: 49359 | O31: 0.05625 | P31: 0.05007 | Q31: 0 | R31: 10519000 | S31: 3.19 | T31: 106.2986 | U31: 35669.144 | V31: ריק במקור | W31: שווי הוגן | X31: 0.0042076 | Y31: 0.034226948 | Z31: 0.0082769261
AZ10000: 1

Sheet ניירות ערך מסחריים
A1: מספר קופה/קרן/ח.פ. עבור חברת ביטוח | B1: מספר מסלול | C1: שם מנפיק | D1: מספר מנפיק | E1: סוג מספר מזהה מנפיק | F1: שם נייר ערך | G1: מספר נייר ערך | H1: סוג מספר נייר ערך | I1: מאפיין עיקרי | J1: ישראל/חו"ל | K1: מדינה לפי חשיפה כלכלית | L1: זירת מסחר | M1: ענף מסחר | N1: בעל עניין/צד קשור | O1: דירוג | P1: שם מדרג | Q1: דירוג נייר הערך/המנפיק | R1: מטבע פעילות | S1: מח"מ | T1: ריבית עוגן | U1: מועד פדיון | V1: שיעור ריבית | W1: תשואה לפדיון | X1: נחיתות חוזית | Y1: האם סווג כחוב בעייתי | Z1: ערך נקוב (יחידות) | AA1: שער חליפין | AB1: שער נייר הערך | AC1: סכום לקבל (במטבע הפעילות) | AD1: שווי הוגן (באלפי ש"ח) | AE1: עלות מופחתת (באלפי ש"ח) | AF1: עלות מופחתת (במטבע הפעילות) | AG1: השיטה שיושמה בדוח הכספי | AH1: שיעור מערך נקוב מונפק | AI1: שיעור מנכסי אפיק ההשקעה | AJ1: שיעור מסך נכסי ההשקעה

Sheet איגרות חוב
A1: מספר קופה/קרן/ח.פ. עבור חברת ביטוח | B1: מספר מסלול | C1: שם מנפיק | D1: מספר מנפיק | E1: סוג מספר מזהה מנפיק | F1: שם נייר ערך | G1: מספר נייר ערך | H1: סוג מספר נייר ערך | I1: מאפיין עיקרי | J1: ישראל/חו"ל | K1: מדינה לפי חשיפה כלכלית | L1: סטאטוס סחירות | M1: זירת מסחר | N1: ענף מסחר | O1: בעל עניין/צד קשור | P1: דירוג | Q1: שם מדרג | R1: דירוג נייר הערך/המנפיק | S1: מטבע פעילות | T1: מח"מ | U1: מועד פדיון | V1: שיעור ריבית | W1: תשואה לפדיון | X1: נחיתות חוזית | Y1: האם סווג כחוב בעייתי | Z1: ערך נקוב (יחידות) | AA1: שער חליפין | AB1: שער נייר הערך | AC1: סכום לקבל (במטבע הפעילות) | AD1: שווי הוגן (באלפי ש"ח) | AE1: עלות מופחתת (באלפי ש"ח) | AF1: עלות מופחתת (במטבע הפעילות) | AG1: השיטה שיושמה בדוח הכספי | AH1: שיעור מערך נקוב מונפק | AI1: שיעור מנכסי אפיק ההשקעה | AJ1: שיעור מסך נכסי ההשקעה
A2: 13908 | B2: 13908 | C2: אדמה פתרונות לחקלאות בע"מ | D2: 520043605 | E2: ח.פ. | F2: אדמה אגח ב | G2: IL0011109159 | H2: ISIN | I2: צמוד למדד המחירים לצרכן | J2: ישראל | K2: ישראל | L2: סחיר | M2: TASE | N2: כימיה, גומי ופלסטיק | O2: לא | P2: ilAA- | Q2: S&P מעלות | R2: נייר ערך | S2: ILS | T2: 5.134 | U2: 50009 | V2: 0.0515 | W2: 0.0337 | X2: החוב לא נחות | Y2: ריק במקור | Z2: 338274.88 | AA2: 1 | AB2: 156.17 | AC2: 0 | AD2: 528.28388 | AE2: ריק במקור | AF2: ריק במקור | AG2: שווי הוגן | AH2: 0.00019230142 | AI2: =+AD2/SUM(AD:AD) -> 0.00099590235 | AJ2: =+AD2/'סכום נכסים'!$B$30 -> 0.00012258681
A3: 13908 | B3: 13908 | C3: אמות השקעות בע"מ | D3: 520026683 | E3: ח.פ. | F3: אמות אגח ד | G3: IL0011331498 | H3: ISIN | I3: צמוד למדד המחירים לצרכן | J3: ישראל | K3: ישראל | L3: סחיר | M3: TASE | N3: נדל"ן מניב בישראל | O3: לא | P3: ilAA | Q3: S&P מעלות | R3: נייר ערך | S3: ILS | T3: 1.462 | U3: 46936 | V3: 0.032 | W3: 0.0261 | X3: החוב לא נחות | Y3: ריק במקור | Z3: 542283.75 | AA3: 1 | AB3: 120.58 | AC3: 0 | AD3: 653.88575 | AE3: ריק במקור | AF3: ריק במקור | AG3: שווי הוגן | AH3: 0.0013095458 | AI3: =+AD3/SUM(AD:AD) -> 0.0012326826 | AJ3: =+AD3/'סכום נכסים'!$B$30 -> 0.00015173238
A4: 13908 | B4: 13908 | C4: איירפורט סיטי בע"מ | D4: 511659401 | E4: ח.פ. | F4: ארפורט אגח ה | G4: IL0011334872 | H4: ISIN | I4: צמוד למדד המחירים לצרכן | J4: ישראל | K4: ישראל | L4: סחיר | M4: TASE | N4: נדל"ן מניב בישראל | O4: לא | P4: ilAA | Q4: S&P מעלות | R4: נייר ערך | S4: ILS | T4: 1.515 | U4: 47177 | V4: 0.0234 | W4: 0.0262 | X4: החוב לא נחות | Y4: ריק במקור | Z4: 2144034.4 | AA4: 1 | AB4: 119.52 | AC4: 0 | AD4: 2562.55 | AE4: ריק במקור | AF4: ריק במקור | AG4: שווי הוגן | AH4: 0.0013152679 | AI4: =+AD4/SUM(AD:AD) -> 0.0048308298 | AJ4: =+AD4/'סכום נכסים'!$B$30 -> 0.00059463263
A5: 13908 | B5: 13908 | C5: שיכון ובינוי בע"מ | D5: 520036104 | E5: ח.פ. | F5: שכון ובי אגח 8 | G5: IL0011358889 | H5: ISIN | I5: צמוד למדד המחירים לצרכן | J5: ישראל | K5: ישראל | L5: סחיר | M5: TASE | N5: בנייה | O5: לא | P5: ilA | Q5: S&P מעלות | R5: נייר ערך | S5: ILS | T5: 1.763 | U5: 47239 | V5: 0.039 | W5: 0.0296 | X5: החוב לא נחות | Y5: ריק במקור | Z5: 1563836.3 | AA5: 1 | AB5: 121.31 | AC5: 0 | AD5: 1897.0898 | AE5: ריק במקור | AF5: ריק במקור | AG5: שווי הוגן | AH5: 0.0011329611 | AI5: =+AD5/SUM(AD:AD) -> 0.0035763276 | AJ5: =+AD5/'סכום נכסים'!$B$30 -> 0.00044021445
A6: 13908 | B6: 13908 | C6: קרסו מוטורס בע"מ | D6: 514065283 | E6: ח.פ. | F6: קרסו מוט' אגח א | G6: IL0011364648 | H6: ISIN | I6: לא צמוד למדד המחירים לצרכן | J6: ישראל | K6: ישראל | L6: סחיר | M6: TASE | N6: מסחר | O6: לא | P6: ilAA- | Q6: S&P מעלות | R6: נייר ערך | S6: ILS | T6: 0.412 | U6: 46266 | V6: 0.0275 | W6: 0.049 | X6: החוב לא נחות | Y6: ריק במקור | Z6: 672514.62 | AA6: 1 | AB6: 100.07 | AC6: 0 | AD6: 672.98538 | AE6: ריק במקור | AF6: ריק במקור | AG6: שווי הוגן | AH6: 0.0074077452 | AI6: =+AD6/SUM(AD:AD) -> 0.0012686886 | AJ6: =+AD6/'סכום נכסים'!$B$30 -> 0.0001561644
A7: 13908 | B7: 13908 | C7: ריט 1 בע"מ | D7: 513821488 | E7: ח.פ. | F7: ריט 1 אגח ה | G7: IL0011367534 | H7: ISIN | I7: צמוד למדד המחירים לצרכן | J7: ישראל | K7: ישראל | L7: סחיר | M7: TASE | N7: נדל"ן מניב בישראל | O7: לא | P7: ilAA | Q7: S&P מעלות | R7: נייר ערך | S7: ILS | T7: 1.421 | U7: 47016 | V7: 0.04 | W7: 0.0261 | X7: החוב לא נחות | Y7: ריק במקור | Z7: 1821756.5 | AA7: 1 | AB7: 122.36 | AC7: 0 | AD7: 2229.1013 | AE7: ריק במקור | AF7: ריק במקור | AG7: שווי הוגן | AH7: 0.0025235064 | AI7: =+AD7/SUM(AD:AD) -> 0.004202224 | AJ7: =+AD7/'סכום נכסים'!$B$30 -> 0.00051725679
A8: 13908 | B8: 13908 | C8: ריט 1 בע"מ | D8: 513821488 | E8: ח.פ. | F8: ריט 1 אגח ו | G8: IL0011385445 | H8: ISIN | I8: צמוד למדד המחירים לצרכן | J8: ישראל | K8: ישראל | L8: סחיר | M8: TASE | N8: נדל"ן מניב בישראל | O8: לא | P8: ilAA | Q8: S&P מעלות | R8: נייר ערך | S8: ILS | T8: 2.8 | U8: 48112 | V8: 0.035 | W8: 0.025 | X8: החוב לא נחות | Y8: ריק במקור | Z8: 231988.13 | AA8: 1 | AB8: 124.44 | AC8: 0 | AD8: 288.68603 | AE8: ריק במקור | AF8: ריק במקור | AG8: שווי הוגן | AH8: 0.00031430709 | AI8: =+AD8/SUM(AD:AD) -> 0.00054422084 | AJ8: =+AD8/'סכום נכסים'!$B$30 -> 6.6988795e-05
A9: 13908 | B9: 13908 | C9: קבוצת עזריאלי בע"מ | D9: 510960719 | E9: ח.פ. | F9: עזריאלי אגח ד | G9: IL0011386500 | H9: ISIN | I9: צמוד למדד המחירים לצרכן | J9: ישראל | K9: ישראל | L9: סחיר | M9: TASE | N9: נדל"ן מניב בישראל | O9: לא | P9: Aa1.il | Q9: מידרוג Moodys | R9: נייר ערך | S9: ILS | T9: 2.447 | U9: 47669 | V9: 0.0134 | W9: 0.0255 | X9: החוב לא נחות | Y9: ריק במקור | Z9: 2803899.2 | AA9: 1 | AB9: 116.05 | AC9: 32.08477 | AD9: 3286.0098 | AE9: ריק במקור | AF9: ריק במקור | AG9: שווי הוגן | AH9: 0.0014104132 | AI9: =+AD9/SUM(AD:AD) -> 0.0061946711 | AJ9: =+AD9/'סכום נכסים'!$B$30 -> 0.00076250949
A10: 13908 | B10: 13908 | C10: ביג מרכזי קניות בע"מ | D10: 513623314 | E10: ח.פ. | F10: ביג אגח ח | G10: IL0011389249 | H10: ISIN | I10: צמוד למדד המחירים לצרכן | J10: ישראל | K10: ישראל | L10: סחיר | M10: TASE | N10: נדל"ן מניב בישראל | O10: לא | P10: ilAA | Q10: S&P מעלות | R10: נייר ערך | S10: ILS | T10: 0.277 | U10: 46124 | V10: 0.0134 | W10: 0.0518 | X10: החוב לא נחות | Y10: ריק במקור | Z10: 63642.87 | AA10: 1 | AB10: 118.26 | AC10: 0 | AD10: 75.26406 | AE10: ריק במקור | AF10: ריק במקור | AG10: שווי הוגן | AH10: 0.0001410666 | AI10: =+AD10/SUM(AD:AD) -> 0.00014188518 | AJ10: =+AD10/'סכום נכסים'!$B$30 -> 1.7464817e-05
A11: 13908 | B11: 13908 | C11: סלע קפיטל נדל"ן בע"מ | D11: 513992529 | E11: ח.פ. | F11: סלע נדלן אגח ג | G11: IL0011389736 | H11: ISIN | I11: צמוד למדד המחירים לצרכן | J11: ישראל | K11: ישראל | L11: סחיר | M11: TASE | N11: נדל"ן מניב בישראל | O11: לא | P11: Aa3.il | Q11: מידרוג Moodys | R11: נייר ערך | S11: ILS | T11: 1.731 | U11: 47221 | V11: 0.0196 | W11: 0.0269 | X11: החוב לא נחות | Y11: ריק במקור | Z11: 3000000 | AA11: 1 | AB11: 117.7 | AC11: 0 | AD11: 3531 | AE11: ריק במקור | AF11: ריק במקור | AG11: שווי הוגן | AH11: 0.0026198756 | AI11: =+AD11/SUM(AD:AD) -> 0.0066565181 | AJ11: =+AD11/'סכום נכסים'!$B$30 -> 0.00081935878
A12: 13908 | B12: 13908 | C12: קבוצת אשטרום בע"מ | D12: 510381601 | E12: ח.פ. | F12: אשטרום קב אגח ג | G12: IL0011401028 | H12: ISIN | I12: לא צמוד למדד המחירים לצרכן | J12: ישראל | K12: ישראל | L12: סחיר | M12: TASE | N12: בנייה | O12: לא | P12: ilA | Q12: S&P מעלות | R12: נייר ערך | S12: ILS | T12: 1.452 | U12: 47133 | V12: 0.043 | W12: 0.0468 | X12: החוב לא נחות | Y12: ריק במקור | Z12: 8022320.4 | AA12: 1 | AB12: 101.52 | AC12: 0 | AD12: 8144.2597 | AE12: ריק במקור | AF12: ריק במקור | AG12: שווי הוגן | AH12: 0.011355826 | AI12: =+AD12/SUM(AD:AD) -> 0.015353274 | AJ12: =+AD12/'סכום נכסים'!$B$30 -> 0.0018898529
A13: 13908 | B13: 13908 | C13: רבוע כחול נדל"ן בע"מ | D13: 513765859 | E13: ח.פ. | F13: רבוע נדלן אגח ו | G13: IL0011406076 | H13: ISIN | I13: צמוד למדד המחירים לצרכן | J13: ישראל | K13: ישראל | L13: סחיר | M13: TASE | N13: נדל"ן מניב בישראל | O13: לא | P13: ilAA | Q13: S&P מעלות | R13: נייר ערך | S13: ILS | T13: 0.907 | U13: 46356 | V13: 0.0215 | W13: 0.0279 | X13: החוב לא נחות | Y13: ריק במקור | Z13: 196428.57 | AA13: 1 | AB13: 119.17 | AC13: 0 | AD13: 234.08393 | AE13: ריק במקור | AF13: ריק במקור | AG13: שווי הוגן | AH13: 0.00028042636 | AI13: =+AD13/SUM(AD:AD) -> 0.00044128686 | AJ13: =+AD13/'סכום נכסים'!$B$30 -> 5.4318529e-05
... A102: 13908 | B102: 13908 | C102: וילאר אינטרנשיונל בע"מ | D102: 520038910 | E102: ח.פ. | F102: וילאר אגח י | G102: IL0011939522 | H102: ISIN | I102: לא צמוד למדד המחירים לצרכן | J102: ישראל | K102: ישראל | L102: סחיר | M102: TASE | N102: נדל"ן מניב בישראל | O102: כן | P102: ilAA | Q102: S&P מעלות | R102: נייר ערך | S102: ILS | T102: 3.654 | U102: 48213 | V102: 0.0489 | W102: 0.0432 | X102: החוב לא נחות | Y102: ריק במקור | Z102: 4042000 | AA102: 1 | AB102: 102.23 | AC102: 0 | AD102: 4132.1366 | AE102: ריק במקור | AF102: ריק במקור | AG102: שווי הוגן | AH102: 0.0087869947 | AI102: =+AD102/SUM(AD:AD) -> 0.0077897598 | AJ102: =+AD102/'סכום נכסים'!$B$30 -> 0.00095885087
A103: 13908 | B103: 13908 | C103: סיאון אינווסטמנט קורפוריישן | D103: D14242259 | E103: LEI | F103: סיאון אגח א | G103: IL0011940181 | H103: ISIN | I103: צמוד למט"ח | J103: ישראל | K103: ארה"ב | L103: סחיר | M103: TASE | N103: אשראי חוץ בנקאי | O103: לא | P103: A1.il | Q103: מידרוג Moodys | R103: נייר ערך | S103: ILS | T103: 0.649 | U103: 46265 | V103: 0.0753 | W103: 0.0886 | X103: החוב לא נחות | Y103: ריק במקור | Z103: 1201000 | AA103: 1 | AB103: 87 | AC103: 0 | AD103: 1044.87 | AE103: ריק במקור | AF103: ריק במקור | AG103: שווי הוגן | AH103: 0.0028526883 | AI103: =+AD103/SUM(AD:AD) -> 0.0019697525 | AJ103: =+AD103/'סכום נכסים'!$B$30 -> 0.00024245919
A104: 13908 | B104: 13908 | C104: מליסרון בע"מ | D104: 520037789 | E104: ח.פ. | F104: מליסרון אגח כא | G104: IL0011946386 | H104: ISIN | I104: צמוד למדד המחירים לצרכן | J104: ישראל | K104: ישראל | L104: סחיר | M104: TASE | N104: נדל"ן מניב בישראל | O104: לא | P104: ilAA | Q104: S&P מעלות | R104: נייר ערך | S104: ILS | T104: 5.32 | U104: 50041 | V104: 0.0361 | W104: 0.026 | X104: החוב לא נחות | Y104: ריק במקור | Z104: 2311884.2 | AA104: 1 | AB104: 114.15 | AC104: 42.36155 | AD104: 2681.3774 | AE104: ריק במקור | AF104: ריק במקור | AG104: שווי הוגן | AH104: 0.00094613179 | AI104: =+AD104/SUM(AD:AD) -> 0.0050548391 | AJ104: =+AD104/'סכום נכסים'!$B$30 -> 0.0006222062
A105: 13908 | B105: 13908 | C105: הפניקס גיוסי הון (2009)בע"מ | D105: 514290345 | E105: ח.פ. | F105: פניקס הון אגחיב | G105: IL0011955858 | H105: ISIN | I105: צמוד למדד המחירים לצרכן | J105: ישראל | K105: ישראל | L105: סחיר | M105: TASE | N105: ביטוח | O105: לא | P105: ilAA- | Q105: S&P מעלות | R105: נייר ערך | S105: ILS | T105: 5.704 | U105: 62494 | V105: 0.0209 | W105: 0.0248 | X105: החוב לא נחות | Y105: ריק במקור | Z105: 50000 | AA105: 1 | AB105: 114.75 | AC105: 0 | AD105: 57.375 | AE105: ריק במקור | AF105: ריק במקור | AG105: שווי הוגן | AH105: 3.2390762e-05 | AI105: =+AD105/SUM(AD:AD) -> 0.00010816135 | AJ105: =+AD105/'סכום נכסים'!$B$30 -> 1.331371e-05
A106: 13908 | B106: 13908 | C106: איירפורט סיטי בע"מ | D106: 511659401 | E106: ח.פ. | F106: ארפורט אגח י | G106: IL0011959819 | H106: ISIN | I106: לא צמוד למדד המחירים לצרכן | J106: ישראל | K106: ישראל | L106: סחיר | M106: TASE | N106: נדל"ן מניב בישראל | O106: לא | P106: ilAA | Q106: S&P מעלות | R106: נייר ערך | S106: ILS | T106: 1.936 | U106: 47238 | V106: 0.05 | W106: 0.0424 | X106: החוב לא נחות | Y106: ריק במקור | Z106: 306250 | AA106: 1 | AB106: 102.39 | AC106: 0 | AD106: 313.56937 | AE106: ריק במקור | AF106: ריק במקור | AG106: שווי הוגן | AH106: 0.00062103929 | AI106: =+AD106/SUM(AD:AD) -> 0.00059113004 | AJ106: =+AD106/'סכום נכסים'!$B$30 -> 7.2762905e-05
A107: 13908 | B107: 13908 | C107: איירפורט סיטי בע"מ | D107: 511659401 | E107: ח.פ. | F107: ארפורט אגח יא | G107: IL0011959991 | H107: ISIN | I107: צמוד למדד המחירים לצרכן | J107: ישראל | K107: ישראל | L107: סחיר | M107: TASE | N107: נדל"ן מניב בישראל | O107: לא | P107: ilAA | Q107: S&P מעלות | R107: נייר ערך | S107: ILS | T107: 7.184 | U107: 50891 | V107: 0.0264 | W107: 0.0239 | X107: החוב לא נחות | Y107: ריק במקור | Z107: 422000 | AA107: 1 | AB107: 110.34 | AC107: 0 | AD107: 465.6348 | AE107: ריק במקור | AF107: ריק במקור | AG107: שווי הוגן | AH107: 0.0014066667 | AI107: =+AD107/SUM(AD:AD) -> 0.00087779849 | AJ107: =+AD107/'סכום נכסים'!$B$30 -> 0.00010804927
A108: 13908 | B108: 13908 | C108: חברת החשמל לישראל בע"מ | D108: 520000472 | E108: ח.פ. | F108: חשמל אגח 34 | G108: IL0011967812 | H108: ISIN | I108: צמוד למדד המחירים לצרכן | J108: ישראל | K108: ישראל | L108: סחיר | M108: TASE | N108: אנרגיה | O108: לא | P108: ilAAA | Q108: S&P מעלות | R108: נייר ערך | S108: ILS | T108: 6.739 | U108: 48742 | V108: 0.03 | W108: 0.0238 | X108: החוב לא נחות | Y108: ריק במקור | Z108: 1017000 | AA108: 1 | AB108: 111.73 | AC108: 0 | AD108: 1136.2941 | AE108: ריק במקור | AF108: ריק במקור | AG108: שווי הוגן | AH108: 0.00024927668 | AI108: =+AD108/SUM(AD:AD) -> 0.002142102 | AJ108: =+AD108/'סכום נכסים'!$B$30 -> 0.0002636739
A109: 13908 | B109: 13908 | C109: חברת החשמל לישראל בע"מ | D109: 520000472 | E109: ח.פ. | F109: חשמל אגח 35 | G109: IL0011967994 | H109: ISIN | I109: צמוד למדד המחירים לצרכן | J109: ישראל | K109: ישראל | L109: סחיר | M109: TASE | N109: אנרגיה | O109: לא | P109: ilAAA | Q109: S&P מעלות | R109: נייר ערך | S109: ILS | T109: 9.728 | U109: 50203 | V109: 0.032 | W109: 0.0257 | X109: החוב לא נחות | Y109: ריק במקור | Z109: 1783900 | AA109: 1 | AB109: 113.96 | AC109: 0 | AD109: 2032.9324 | AE109: ריק במקור | AF109: ריק במקור | AG109: שווי הוגן | AH109: 0.00036226815 | AI109: =+AD109/SUM(AD:AD) -> 0.0038324134 | AJ109: =+AD109/'סכום נכסים'!$B$30 -> 0.00047173635
A110: 13908 | B110: 13908 | C110: מזרחי טפחות חברה להנפקות בע"מ | D110: 520032046 | E110: ח.פ. | F110: מז טפ הנ אגח 67 | G110: IL0011968075 | H110: ISIN | I110: צמוד למדד המחירים לצרכן | J110: ישראל | K110: ישראל | L110: סחיר | M110: TASE | N110: בנקים | O110: לא | P110: ilAAA | Q110: S&P מעלות | R110: נייר ערך | S110: ILS | T110: 3.732 | U110: 48742 | V110: 0.0206 | W110: 0.0222 | X110: החוב לא נחות | Y110: ריק במקור | Z110: 3413707.6 | AA110: 1 | AB110: 107.55 | AC110: 0 | AD110: 3671.4425 | AE110: ריק במקור | AF110: ריק במקור | AG110: שווי הוגן | AH110: 0.0021334638 | AI110: =+AD110/SUM(AD:AD) -> 0.0069212754 | AJ110: =+AD110/'סכום נכסים'!$B$30 -> 0.00085194808
A111: 13908 | B111: 13908 | C111: איסתא בע"מ | D111: 520042763 | E111: ח.פ. | F111: איסתא אג א | G111: IL0011971285 | H111: ISIN | I111: אג"ח להמרה לא צמוד למדד המחירים לצרכן | J111: ישראל | K111: ישראל | L111: סחיר | M111: TASE | N111: מלונאות ותיירות | O111: כן | P111: NR | Q111: NR | R111: NR | S111: ILS | T111: 2.39 | U111: 46934 | V111: 0.0485 | W111: -0.0159 | X111: החוב לא נחות | Y111: ריק במקור | Z111: 588000 | AA111: 1 | AB111: 116.5 | AC111: 0 | AD111: 685.02 | AE111: ריק במקור | AF111: ריק במקור | AG111: שווי הוגן | AH111: 0.00196 | AI111: =+AD111/SUM(AD:AD) -> 0.0012913758 | AJ111: =+AD111/'סכום נכסים'!$B$30 -> 0.000158957
A112: 13908 | B112: 13908 | C112: אלון רבוע כחול ישראל בע"מ | D112: 520042847 | E112: ח.פ. | F112: אלון רבוע אגח ח | G112: IL0011972762 | H112: ISIN | I112: לא צמוד למדד המחירים לצרכן | J112: ישראל | K112: ישראל | L112: סחיר | M112: TASE | N112: השקעה ואחזקות | O112: לא | P112: ilAA- | Q112: S&P מעלות | R112: נייר ערך | S112: ILS | T112: 2.881 | U112: 47664 | V112: 0.055 | W112: 0.0461 | X112: החוב לא נחות | Y112: ריק במקור | Z112: 885959.6 | AA112: 1 | AB112: 102.7 | AC112: 0 | AD112: 909.88051 | AE112: ריק במקור | AF112: ריק במקור | AG112: שווי הוגן | AH112: 0.00073092479 | AI112: =+AD112/SUM(AD:AD) -> 0.001715275 | AJ112: =+AD112/'סכום נכסים'!$B$30 -> 0.00021113526
A113: 13908 | B113: 13908 | C113: נאוויטס פטרוליום, שותפות מוגבל | D113: 550263107 | E113: מספר שותפות | F113: נאוויטס פט אגחה | G113: IL0011979122 | H113: ISIN | I113: לא צמוד למדד המחירים לצרכן | J113: ישראל | K113: ישראל | L113: סחיר | M113: TASE | N113: חיפושי נפט וגז | O113: לא | P113: ilA- | Q113: S&P מעלות | R113: נייר ערך | S113: ILS | T113: 2.121 | U113: 47118 | V113: 0.065 | W113: 0.0481 | X113: החוב לא נחות | Y113: ריק במקור | Z113: 150000 | AA113: 1 | AB113: 103.66 | AC113: 0 | AD113: 155.49 | AE113: ריק במקור | AF113: ריק במקור | AG113: שווי הוגן | AH113: 0.0003 | AI113: =+AD113/SUM(AD:AD) -> 0.00029312433 | AJ113: =+AD113/'סכום נכסים'!$B$30 -> 3.6081024e-05
A114: 13908 | B114: 13908 | C114: כלל ביטוח גיוסי הון בע"מ | D114: 513754069 | E114: ח.פ. | F114: כלל הון אגח יג | G114: IL0011979205 | H114: ISIN | I114: לא צמוד למדד המחירים לצרכן | J114: ישראל | K114: ישראל | L114: סחיר | M114: TASE | N114: ביטוח | O114: לא | P114: ilAA- | Q114: S&P מעלות | R114: נייר ערך | S114: ILS | T114: 6.918 | U114: 50252 | V114: 0.0531 | W114: 0.0446 | X114: החוב לא נחות | Y114: ריק במקור | Z114: 500000 | AA114: 1 | AB114: 108.58 | AC114: 0 | AD114: 542.9 | AE114: ריק במקור | AF114: ריק במקור | AG114: שווי הוגן | AH114: 0.00039265553 | AI114: =+AD114/SUM(AD:AD) -> 0.0010234562 | AJ114: =+AD114/'סכום נכסים'!$B$30 -> 0.00012597844
A115: 13908 | B115: 13908 | C115: ע.י. נופר אנרג'י בע"מ | D115: 514599943 | E115: ח.פ. | F115: נופר אנרג אגח ג | G115: IL0011980435 | H115: ISIN | I115: לא צמוד למדד המחירים לצרכן | J115: ישראל | K115: ישראל | L115: סחיר | M115: TASE | N115: אנרגיה מתחדשת | O115: לא | P115: A3.il | Q115: מידרוג Moodys | R115: נייר ערך | S115: ILS | T115: 2.841 | U115: 47664 | V115: 0.0695 | W115: 0.0557 | X115: החוב לא נחות | Y115: ריק במקור | Z115: 1406950 | AA115: 1 | AB115: 104.11 | AC115: 0 | AD115: 1464.7756 | AE115: ריק במקור | AF115: ריק במקור | AG115: שווי הוגן | AH115: 0.0017519972 | AI115: =+AD115/SUM(AD:AD) -> 0.002761344 | AJ115: =+AD115/'סכום נכסים'!$B$30 -> 0.00033989714
... A226: 13908 | B226: 13908 | C226: מזרחי טפחות חברה להנפקות בע"מ | D226: 520032046 | E226: ח.פ. | F226: מז טפ הנ אגח 62 | G226: IL0023104982 | H226: ISIN | I226: צמוד למדד המחירים לצרכן | J226: ישראל | K226: ישראל | L226: סחיר | M226: TASE | N226: בנקים | O226: לא | P226: ilAAA | Q226: S&P מעלות | R226: נייר ערך | S226: ILS | T226: 2.802 | U226: 47048 | V226: 0.001 | W226: 0.0219 | X226: החוב לא נחות | Y226: ריק במקור | Z226: 1111218 | AA226: 1 | AB226: 108.71 | AC226: 0 | AD226: 1208.0051 | AE226: ריק במקור | AF226: ריק במקור | AG226: שווי הוגן | AH226: 0.00032904406 | AI226: =+AD226/SUM(AD:AD) -> 0.0022772891 | AJ226: =+AD226/'סכום נכסים'!$B$30 -> 0.00028031424
A227: 13908 | B227: 13908 | C227: מזרחי טפחות חברה להנפקות בע"מ | D227: 520032046 | E227: ח.פ. | F227: מז טפ הנ אגח 63 | G227: IL0023105484 | H227: ISIN | I227: לא צמוד למדד המחירים לצרכן | J227: ישראל | K227: ישראל | L227: סחיר | M227: TASE | N227: בנקים | O227: לא | P227: ilAAA | Q227: S&P מעלות | R227: נייר ערך | S227: ILS | T227: 2.589 | U227: 47951 | V227: 0.0274 | W227: 0.0412 | X227: החוב לא נחות | Y227: ריק במקור | Z227: 5368077 | AA227: 1 | AB227: 98.49 | AC227: 0 | AD227: 5287.019 | AE227: ריק במקור | AF227: ריק במקור | AG227: שווי הוגן | AH227: 0.0016971531 | AI227: 0.009966904 | AJ227: 0.0012268381
A228: 13908 | B228: 13908 | C228: מזרחי טפחות חברה להנפקות בע"מ | D228: 520032046 | E228: ח.פ. | F228: מז טפ הנ אגח 64 | G228: IL0023105559 | H228: ISIN | I228: צמוד למדד המחירים לצרכן | J228: ישראל | K228: ישראל | L228: סחיר | M228: TASE | N228: בנקים | O228: לא | P228: ilAAA | Q228: S&P מעלות | R228: נייר ערך | S228: ILS | T228: 2.712 | U228: 47951 | V228: 0.001 | W228: 0.0222 | X228: החוב לא נחות | Y228: ריק במקור | Z228: 7054425 | AA228: 1 | AB228: 107.55 | AC228: 0 | AD228: 7587.0341 | AE228: ריק במקור | AF228: ריק במקור | AG228: שווי הוגן | AH228: 0.003161809 | AI228: 0.014302812 | AJ228: 0.0017605503
A229: 13908 | B229: 13908 | C229: אשטרום נכסים בע"מ | D229: 520036617 | E229: ח.פ. | F229: אשטרום נכ אגח13 | G229: IL0025103032 | H229: ISIN | I229: צמוד למדד המחירים לצרכן | J229: ישראל | K229: ישראל | L229: סחיר | M229: TASE | N229: נדל"ן מניב בישראל | O229: לא | P229: ilA | Q229: S&P מעלות | R229: נייר ערך | S229: ILS | T229: 3.755 | U229: 47848 | V229: 0.013 | W229: 0.0292 | X229: החוב לא נחות | Y229: ריק במקור | Z229: 180000 | AA229: 1 | AB229: 108.39 | AC229: 0 | AD229: 195.102 | AE229: ריק במקור | AF229: ריק במקור | AG229: שווי הוגן | AH229: 0.00048192771 | AI229: 0.00036779949 | AJ229: 4.527288e-05
A230: 13908 | B230: 13908 | C230: מליסרון בע"מ | D230: 520037789 | E230: ח.פ. | F230: מליסרון אגח טז | G230: IL0032302650 | H230: ISIN | I230: צמוד למדד המחירים לצרכן | J230: ישראל | K230: ישראל | L230: סחיר | M230: TASE | N230: נדל"ן מניב בישראל | O230: לא | P230: ilAA | Q230: S&P מעלות | R230: נייר ערך | S230: ILS | T230: 1.211 | U230: 46478 | V230: 0.0235 | W230: 0.0288 | X230: החוב לא נחות | Y230: ריק במקור | Z230: 659770.08 | AA230: 1 | AB230: 119.34 | AC230: 0 | AD230: 787.36961 | AE230: ריק במקור | AF230: ריק במקור | AG230: שווי הוגן | AH230: 0.00072824165 | AI230: 0.0014843217 | AJ230: 0.00018270694
A231: 13908 | B231: 13908 | C231: מליסרון בע"מ | D231: 520037789 | E231: ח.פ. | F231: מליסרון אגח יז | G231: IL0032302734 | H231: ISIN | I231: צמוד למדד המחירים לצרכן | J231: ישראל | K231: ישראל | L231: סחיר | M231: TASE | N231: נדל"ן מניב בישראל | O231: לא | P231: ilAA | Q231: S&P מעלות | R231: נייר ערך | S231: ILS | T231: 3.113 | U231: 48214 | V231: 0.0225 | W231: 0.0252 | X231: החוב לא נחות | Y231: ריק במקור | Z231: 4577453.4 | AA231: 1 | AB231: 118.56 | AC231: 64.7912 | AD231: 5491.82 | AE231: ריק במקור | AF231: ריק במקור | AG231: שווי הוגן | AH231: 0.0028544988 | AI231: 0.010352988 | AJ231: 0.0012743616
A232: 13908 | B232: 13908 | C232: מליסרון בע"מ | D232: 520037789 | E232: ח.פ. | F232: מליסרון אגח יט | G232: IL0032303989 | H232: ISIN | I232: צמוד למדד המחירים לצרכן | J232: ישראל | K232: ישראל | L232: סחיר | M232: TASE | N232: נדל"ן מניב בישראל | O232: לא | P232: ilAA | Q232: S&P מעלות | R232: נייר ערך | S232: ILS | T232: 3.307 | U232: 47300 | V232: 0.0143 | W232: 0.0246 | X232: החוב לא נחות | Y232: ריק במקור | Z232: 1140163.9 | AA232: 1 | AB232: 114.1 | AC232: 10.10296 | AD232: 1311.0299 | AE232: ריק במקור | AF232: ריק במקור | AG232: שווי הוגן | AH232: 0.00059798328 | AI232: 0.0024715079 | AJ232: 0.00030422087
A233: 13908 | B233: 13908 | C233: מליסרון בע"מ | D233: 520037789 | E233: ח.פ. | F233: מליסרון אגח כ | G233: IL0032304227 | H233: ISIN | I233: צמוד למדד המחירים לצרכן | J233: ישראל | K233: ישראל | L233: סחיר | M233: TASE | N233: נדל"ן מניב בישראל | O233: לא | P233: ilAA | Q233: S&P מעלות | R233: נייר ערך | S233: ILS | T233: 4.252 | U233: 47665 | V233: 0.0025 | W233: 0.0249 | X233: החוב לא נחות | Y233: ריק במקור | Z233: 710938.69 | AA233: 1 | AB233: 105.36 | AC233: 1.88733 | AD233: 750.93233 | AE233: ריק במקור | AF233: ריק במקור | AG233: שווי הוגן | AH233: 0.00053815262 | AI233: 0.0014156314 | AJ233: 0.00017425177
A234: 13908 | B234: 13908 | C234: ארי נדל"ן (ארנה) השקעות בע"מ | D234: 520038332 | E234: ח.פ. | F234: ארי נדלן אגח א | G234: IL0036601560 | H234: ISIN | I234: צמוד למדד המחירים לצרכן | J234: ישראל | K234: ישראל | L234: סחיר | M234: TASE | N234: נדל"ן מניב בישראל | O234: לא | P234: NR | Q234: NR | R234: NR | S234: ILS | T234: 1.208 | U234: 46478 | V234: 0.019 | W234: 0.0324 | X234: החוב לא נחות | Y234: ריק במקור | Z234: 96858.64 | AA234: 1 | AB234: 111.97 | AC234: 0 | AD234: 108.45262 | AE234: ריק במקור | AF234: ריק במקור | AG234: שווי הוגן | AH234: 0.0001442045 | AI234: 0.0002044511 | AJ234: 2.5166131e-05
A235: 13908 | B235: 13908 | C235: אלוני-חץ נכסים והשקעות בע"מ | D235: 520038506 | E235: ח.פ. | F235: אלוני חץ אגח ט | G235: IL0039003541 | H235: ISIN | I235: לא צמוד למדד המחירים לצרכן | J235: ישראל | K235: ישראל | L235: סחיר | M235: TASE | N235: נדל"ן מניב בישראל | O235: לא | P235: ilAA- | Q235: S&P מעלות | R235: נייר ערך | S235: ILS | T235: 0.64 | U235: 46446 | V235: 0.0385 | W235: 0.0463 | X235: החוב לא נחות | Y235: ריק במקור | Z235: 27263.5 | AA235: 1 | AB235: 102.73 | AC235: 0 | AD235: 28.00779 | AE235: ריק במקור | AF235: ריק במקור | AG235: שווי הוגן | AH235: 8.7459106e-05 | AI235: 5.2799309e-05 | AJ235: 6.4991302e-06
A236: 13908 | B236: 13908 | C236: אלוני-חץ נכסים והשקעות בע"מ | D236: 520038506 | E236: ח.פ. | F236: אלוני חץ אגח יב | G236: IL0039004952 | H236: ISIN | I236: לא צמוד למדד המחירים לצרכן | J236: ישראל | K236: ישראל | L236: סחיר | M236: TASE | N236: נדל"ן מניב בישראל | O236: לא | P236: ilAA- | Q236: S&P מעלות | R236: נייר ערך | S236: ILS | T236: 3.209 | U236: 47907 | V236: 0.0241 | W236: 0.0448 | X236: החוב לא נחות | Y236: ריק במקור | Z236: 205000 | AA236: 1 | AB236: 95.65 | AC236: 0 | AD236: 196.0825 | AE236: ריק במקור | AF236: ריק במקור | AG236: שווי הוגן | AH236: 9.975947e-05 | AI236: 0.00036964789 | AJ236: 4.5500402e-05
A237: 13908 | B237: 13908 | C237: ישראל קנדה (ט.ר) בע"מ | D237: 520039298 | E237: ח.פ. | F237: ישראל קנדה אגחז | G237: IL0043402127 | H237: ISIN | I237: לא צמוד למדד המחירים לצרכן | J237: ישראל | K237: ישראל | L237: סחיר | M237: TASE | N237: בנייה | O237: לא | P237: ilA- | Q237: S&P מעלות | R237: נייר ערך | S237: ILS | T237: 0.976 | U237: 46568 | V237: 0.0395 | W237: 0.0507 | X237: החוב לא נחות | Y237: ריק במקור | Z237: 538037.5 | AA237: 1 | AB237: 99.02 | AC237: 0 | AD237: 532.76473 | AE237: ריק במקור | AF237: ריק במקור | AG237: שווי הוגן | AH237: 0.00091675632 | AI237: 0.0010043495 | AJ237: 0.00012362658
A238: 13908 | B238: 13908 | C238: מידאס השקעות בנדל"ן בע"מ | D238: 520039496 | E238: ח.פ. | F238: מידאס אגח ד | G238: IL0054402842 | H238: ISIN | I238: צמוד למדד המחירים לצרכן | J238: ישראל | K238: ישראל | L238: סחיר | M238: TASE | N238: נדל"ן מניב בישראל | O238: לא | P238: NR | Q238: NR | R238: NR | S238: ILS | T238: 0.992 | U238: 46387 | V238: 0.019 | W238: 0.0744 | X238: החוב לא נחות | Y238: ריק במקור | Z238: 262500 | AA238: 1 | AB238: 109.19 | AC238: 0 | AD238: 286.62375 | AE238: ריק במקור | AF238: ריק במקור | AG238: שווי הוגן | AH238: 0.0075033872 | AI238: 0.0005403331 | AJ238: 6.6510248e-05
... A273: 13908 | B273: 13908 | C273: קבוצת חג'ג' ייזום נדל"ן בע"מ | D273: 520033309 | E273: ח.פ. | F273: חג'ג' אגח יא | G273: IL0082303285 | H273: ISIN | I273: לא צמוד למדד המחירים לצרכן | J273: ישראל | K273: ישראל | L273: סחיר | M273: TASE | N273: בנייה | O273: לא | P273: NR | Q273: NR | R273: NR | S273: ILS | T273: 0.976 | U273: 46569 | V273: 0.029 | W273: 0.0664 | X273: החוב לא נחות | Y273: ריק במקור | Z273: 666666.67 | AA273: 1 | AB273: 96.59 | AC273: 9.66667 | AD273: 653.60001 | AE273: ריק במקור | AF273: ריק במקור | AG273: שווי הוגן | AH273: 0.0027008778 | AI273: 0.001232144 | AJ273: 0.00015166607
A274: 13908 | B274: 13908 | C274: ISRAEL ELECTRIC CORP LTD | D274: 213800T8ZHTF | E274: LEI | F274: ISRELE 4.25 14/8/28 | G274: IL0060002446 | H274: ISIN | I274: צמוד למט"ח | J274: חו"ל | K274: ישראל | L274: סחיר | M274: NYSE | N274: Energy Equipment & Services | O274: לא | P274: Baa2 | Q274: Moodys | R274: נייר ערך | S274: USD | T274: 2.455 | U274: 46979 | V274: 0.0425 | W274: 0.04689 | X274: החוב לא נחות | Y274: ריק במקור | Z274: 3500000 | AA274: 3.19 | AB274: 100.1079 | AC274: 0 | AD274: 11177.047 | AE274: ריק במקור | AF274: ריק במקור | AG274: שווי הוגן | AH274: 0.0035 | AI274: 0.021070579 | AJ274: 0.0025936029
A275: 13908 | B275: 13908 | C275: Bank Leumi Le-Israel BM | D275: ZP6293796 | E275: LEI | F275: LUMIIT 3.275 1/31 | G275: IL0060404899 | H275: ISIN | I275: צמוד למט"ח | J275: חו"ל | K275: ישראל | L275: סחיר | M275: NYSE | N275: Banks | O275: לא | P275: NR | Q275: NR | R275: NR | S275: USD | T275: 0.067 | U275: 47877 | V275: 0.03275 | W275: 0.0553 | X275: החוב לא נחות | Y275: ריק במקור | Z275: 1214000 | AA275: 3.19 | AB275: 100.34 | AC275: 0 | AD275: 3885.827 | AE275: ריק במקור | AF275: ריק במקור | AG275: שווי הוגן | AH275: 0.0016186667 | AI275: 0.0073254257 | AJ275: 0.00090169542
A276: 13908 | B276: 13908 | C276: LEVIATHAN BOND LTD | D276: 68560480 | E276: LEI | F276: LVIATH 6.5 6/27 | G276: IL0011677825 | H276: ISIN | I276: לא צמוד למדד המחירים לצרכן | J276: חו"ל | K276: ישראל | L276: סחיר | M276: FWB | N276: Energy Equipment & Services | O276: לא | P276: Ba3 | Q276: Moodys | R276: נייר ערך | S276: USD | T276: 0.97 | U276: 46568 | V276: 0.065 | W276: 0.05939 | X276: החוב לא נחות | Y276: ריק במקור | Z276: 100000 | AA276: 3.19 | AB276: 102.9703 | AC276: 0 | AD276: 328.47526 | AE276: ריק במקור | AF276: ריק במקור | AG276: שווי הוגן | AH276: 0.00016666667 | AI276: 0.00061923011 | AJ276: 7.6221776e-05
A277: 13908 | B277: 13908 | C277: LEVIATHAN BOND LTD | D277: 68560480 | E277: LEI | F277: LVIATH 6.75 6/30 | G277: IL0011677908 | H277: ISIN | I277: לא צמוד למדד המחירים לצרכן | J277: חו"ל | K277: ישראל | L277: סחיר | M277: NYSE | N277: Oil, Gas & Consumable Fuels | O277: לא | P277: Ba3 | Q277: Moodys | R277: נייר ערך | S277: USD | T277: 3.562 | U277: 47664 | V277: 0.0675 | W277: 0.06273 | X277: החוב לא נחות | Y277: ריק במקור | Z277: 840000 | AA277: 3.19 | AB277: 103.57 | AC277: 0 | AD277: 2775.2617 | AE277: ריק במקור | AF277: ריק במקור | AG277: שווי הוגן | AH277: 0.0015272727 | AI277: 0.0052318266 | AJ277: 0.00064399181
A278: 13908 | B278: 13908 | C278: ENERGEAN ISRAEL FINANCE | D278: 549300RVMKU0 | E278: LEI | F278: ENOIGA 5.375 30/3/28 | G278: IL0011736738 | H278: ISIN | I278: צמוד למט"ח | J278: חו"ל | K278: ישראל | L278: סחיר | M278: NYSE | N278: Energy Equipment & Services | O278: לא | P278: ilA | Q278: S&P מעלות | R278: נייר ערך | S278: USD | T278: 2.116 | U278: 46842 | V278: 0.05375 | W278: 0.05985 | X278: החוב לא נחות | Y278: ריק במקור | Z278: 100000 | AA278: 3.19 | AB278: 99.0733 | AC278: 0 | AD278: 316.04383 | AE278: ריק במקור | AF278: ריק במקור | AG278: שווי הוגן | AH278: 0.00016 | AI278: 0.00059579481 | AJ278: 7.3337097e-05
A279: 13908 | B279: 13908 | C279: ENERGEAN ISRAEL FINANCE | D279: 549300RVMKU0 | E279: LEI | F279: ENOIGA 5.875 30/3/31 | G279: IL0011736811 | H279: ISIN | I279: צמוד למט"ח | J279: חו"ל | K279: ישראל | L279: סחיר | M279: NYSE | N279: Energy Equipment & Services | O279: לא | P279: Ba3 | Q279: Moodys | R279: נייר ערך | S279: USD | T279: 4.509 | U279: 47937 | V279: 0.05875 | W279: 0.06553 | X279: החוב לא נחות | Y279: ריק במקור | Z279: 340000 | AA279: 3.19 | AB279: 97.3285 | AC279: 0 | AD279: 1055.6249 | AE279: ריק במקור | AF279: ריק במקור | AG279: שווי הוגן | AH279: 0.000544 | AI279: 0.0019900273 | AJ279: 0.00024495484
A280: 13908 | B280: 13908 | C280: MIZRAHI TEFAHOT BANK LTD | D280: 191685 | E280: LEI | F280: MZRHIT 3.077 4/31 | G280: IL0069508369 | H280: ISIN | I280: צמוד למט"ח | J280: חו"ל | K280: ישראל | L280: סחיר | M280: NYSE | N280: Banks | O280: לא | P280: NR | Q280: NR | R280: NR | S280: USD | T280: 0.264 | U280: 47945 | V280: 0.03077 | W280: 0.05977 | X280: החוב לא נחות | Y280: ריק במקור | Z280: 368000 | AA280: 3.19 | AB280: 99.1945 | AC280: 0 | AD280: 1164.4641 | AE280: ריק במקור | AF280: ריק במקור | AG280: שווי הוגן | AH280: 0.00061333333 | AI280: 0.0021952071 | AJ280: 0.00027021067
A281: 13908 | B281: 13908 | C281: Bank Hapoalim BM | D281: 162474 | E281: LEI | F281: HAPOAL 3.255 1/32 | G281: IL0066204707 | H281: ISIN | I281: צמוד למט"ח | J281: חו"ל | K281: ישראל | L281: סחיר | M281: NYSE | N281: Banks | O281: לא | P281: NR | Q281: NR | R281: NR | S281: USD | T281: 0.775 | U281: 48234 | V281: 0.03255 | W281: 0.05725 | X281: החוב לא נחות | Y281: ריק במקור | Z281: 680000 | AA281: 3.19 | AB281: 99.0217 | AC281: 0 | AD281: 2147.9787 | AE281: ריק במקור | AF281: ריק במקור | AG281: שווי הוגן | AH281: 0.00068 | AI281: 0.0040492946 | AJ281: 0.00049843252
A282: 13908 | B282: 13908 | C282: ISRAEL ELECTRIC CORP LTD | D282: 199871 | E282: LEI | F282: ISRELE 3.75 2/32 | G282: IL0060004004 | H282: ISIN | I282: צמוד למט"ח | J282: חו"ל | K282: ישראל | L282: סחיר | M282: NYSE | N282: Electric Utilities | O282: לא | P282: Baa2 | Q282: Moodys | R282: נייר ערך | S282: USD | T282: 5.428 | U282: 48266 | V282: 0.0375 | W282: 0.04939 | X282: החוב לא נחות | Y282: ריק במקור | Z282: 1149000 | AA282: 3.19 | AB282: 94.7008 | AC282: 0 | AD282: 3471.0779 | AE282: ריק במקור | AF282: ריק במקור | AG282: שווי הוגן | AH282: 0.002298 | AI282: 0.006543555 | AJ282: 0.00080545402
A283: 13908 | B283: 13908 | C283: Israel Discount Bank Ltd | D283: 186044 | E283: LEI | F283: IDBILI 5.375 26/1/28 | G283: IL0011920878 | H283: ISIN | I283: לא צמוד למדד המחירים לצרכן | J283: חו"ל | K283: ישראל | L283: סחיר | M283: NYSE | N283: Banks | O283: לא | P283: Baa1 | Q283: Moodys | R283: נייר ערך | S283: USD | T283: 1.865 | U283: 46778 | V283: 0.05375 | W283: 0.04723 | X283: החוב לא נחות | Y283: ריק במקור | Z283: 433000 | AA283: 3.19 | AB283: 102.7688 | AC283: 0 | AD283: 1419.5146 | AE283: ריק במקור | AF283: ריק במקור | AG283: שווי הוגן | AH283: 0.00054125 | AI283: 0.0026760194 | AJ283: 0.00032939444
A284: 13908 | B284: 13908 | C284: TEVA PHARM FNC NL II | D284: ZL3198740 | E284: LEI | F284: TEVA 7.875 9/31 | G284: XS2592804194 | H284: ISIN | I284: צמוד למט"ח | J284: חו"ל | K284: ישראל | L284: סחיר | M284: EURONEXT | N284: Pharmaceuticals | O284: לא | P284: Ba1 | Q284: Moodys | R284: נייר ערך | S284: EUR | T284: 4.533 | U284: 48106 | V284: 0.07875 | W284: 0.03923 | X284: החוב לא נחות | Y284: ריק במקור | Z284: 8000 | AA284: 3.7455 | AB284: 122.3893 | AC284: 0 | AD284: 36.67273 | AE284: ריק במקור | AF284: ריק במקור | AG284: שווי הוגן | AH284: 1.6e-05 | AI284: 6.9134152e-05 | AJ284: 8.5098056e-06
A285: 13908 | B285: 13908 | C285: TEVA PHARM FNC NL II | D285: ZL3198740 | E285: LEI | F285: TEVA 7.375 15/9/29 | G285: XS2592804434 | H285: ISIN | I285: צמוד למט"ח | J285: חו"ל | K285: ישראל | L285: סחיר | M285: EURONEXT | N285: Pharmaceuticals | O285: לא | P285: Ba1 | Q285: Moodys | R285: נייר ערך | S285: EUR | T285: 3.066 | U285: 47376 | V285: 0.07375 | W285: 0.03624 | X285: החוב לא נחות | Y285: ריק במקור | Z285: 5067 | AA285: 3.7455 | AB285: 115.1075 | AC285: 0 | AD285: 21.84562 | AE285: ריק במקור | AF285: ריק במקור | AG285: שווי הוגן | AH285: 6.33375e-06 | AI285: 4.1182601e-05 | AJ285: 5.0692157e-06
A286: 13908 | B286: 13908 | C286: ENERGEAN ISRAEL FINANCE | D286: ZJ3123495 | E286: LEI | F286: ENOIGA 8.5 30/9/33 | G286: IL0011971442 | H286: ISIN | I286: לא צמוד למדד המחירים לצרכן | J286: חו"ל | K286: ישראל | L286: סחיר | M286: NYSE | N286: Oil, Gas & Consumable Fuels | O286: לא | P286: Ba3 | Q286: Moodys | R286: נייר ערך | S286: USD | T286: 3.954 | U286: 48852 | V286: 0.085 | W286: 0.07285 | X286: החוב לא נחות | Y286: ריק במקור | Z286: 3280000 | AA286: 3.19 | AB286: 107.6808 | AC286: 0 | AD286: 11266.857 | AE286: ריק במקור | AF286: ריק במקור | AG286: שווי הוגן | AH286: 0.0043733333 | AI286: 0.021239887 | AJ286: 0.0026144431
A287: 13908 | B287: 13908 | C287: ORMAT TECHNOLOGIES INC | D287: 5493000TSHHW | E287: LEI | F287: ORA 2.5 07/27 | G287: US686688AB85 | H287: ISIN | I287: צמוד למט"ח | J287: חו"ל | K287: ארה"ב | L287: סחיר | M287: FWB | N287: Electric Utilities | O287: לא | P287: NR | Q287: NR | R287: NR | S287: USD | T287: 1.94 | U287: 46583 | V287: 0.025 | W287: -0.0386 | X287: החוב לא נחות | Y287: ריק במקור | Z287: 700000 | AA287: 3.19 | AB287: 135.5642 | AC287: 0 | AD287: 3027.1486 | AE287: ריק במקור | AF287: ריק במקור | AG287: שווי הוגן | AH287: 0.0014692394 | AI287: 0.005706675 | AJ287: 0.00070244146
A288: 13908 | B288: 13908 | C288: ITHACA ENERGY NORTH | D288: YU4054158 | E288: LEI | F288: IAECN 8.125 10/29 | G288: US46567TAC80 | H288: ISIN | I288: צמוד למט"ח | J288: חו"ל | K288: בריטניה | L288: סחיר | M288: אחר | N288: Diversified Telecommunication Services | O288: לא | P288: B1 | Q288: Moodys | R288: נייר ערך | S288: USD | T288: 2.515 | U288: 47406 | V288: 0.08125 | W288: 0.06956 | X288: החוב לא נחות | Y288: ריק במקור | Z288: 206000 | AA288: 3.19 | AB288: 105.4172 | AC288: 0 | AD288: 692.73859 | AE288: ריק במקור | AF288: ריק במקור | AG288: שווי הוגן | AH288: 0.00027466667 | AI288: 0.0013059266 | AJ288: 0.00016074807
A289: 13908 | B289: 13908 | C289: ALLIANZ SE | D289: 529900K9B0N5 | E289: LEI | F289: ALVGR 6.55 PERP | G289: USX10001AE90 | H289: ISIN | I289: צמוד למט"ח | J289: חו"ל | K289: גרמניה | L289: סחיר | M289: NASDAQ | N289: Financial Services | O289: לא | P289: A3 | Q289: Moodys | R289: נייר ערך | S289: USD | T289: 6.254 | U289: 48882 | V289: 0.0655 | W289: 0.06021 | X289: החוב לא נחות | Y289: ריק במקור | Z289: 600000 | AA289: 3.19 | AB289: 104.8084 | AC289: 0 | AD289: 2006.0328 | AE289: ריק במקור | AF289: ריק במקור | AG289: שווי הוגן | AH289: 0.00048 | AI289: 0.0037817031 | AJ289: 0.00046549436
A290: 13908 | B290: 13908 | C290: FORD MOTORS | D290: 20S05OYHG0MQ | E290: LEI | F290: F 6.184 8/31 | G290: XS3162352630 | H290: ISIN | I290: צמוד למט"ח | J290: חו"ל | K290: ארה"ב | L290: סחיר | M290: NASDAQ | N290: Automobiles | O290: לא | P290: Ba1 | Q290: Moodys | R290: נייר ערך | S290: GBP | T290: 4.846 | U290: 48089 | V290: 0.06184 | W290: 0.05805 | X290: החוב לא נחות | Y290: ריק במקור | Z290: 200000 | AA290: 4.29 | AB290: 103.9296 | AC290: 0 | AD290: 891.71597 | AE290: ריק במקור | AF290: ריק במקור | AG290: שווי הוגן | AH290: 0.0005 | AI290: 0.0016810319 | AJ290: 0.00020692022
A291: 13908 | B291: 13908 | C291: VIVION INVESTMENTS | D291: ZI5969665 | E291: LEI | F291: VIVION 7.9 8/28 | G291: XS2658230094 | H291: ISIN | I291: צמוד למט"ח | J291: חו"ל | K291: לוכסמבורג | L291: סחיר | M291: EURONEXT | N291: Real Estate Management & Development | O291: לא | P291: NR | Q291: NR | R291: NR | S291: EUR | T291: 2.371 | U291: 46996 | V291: 0.079 | W291: 0.08701 | X291: החוב לא נחות | Y291: ריק במקור | Z291: 461216.39 | AA291: 3.7455 | AB291: 102.4534 | AC291: 0 | AD291: 1769.8681 | AE291: ריק במקור | AF291: ריק במקור | AG291: שווי הוגן | AH291: 0.00052347336 | AI291: 0.0033364937 | AJ291: 0.000410693
A292: 13908 | B292: 13908 | C292: Blue Owl Credit Income Corp | D292: ZB5574478 | E292: LEI | F292: OCINCC 7.95 6/28 | G292: US69120VBB62 | H292: ISIN | I292: צמוד למט"ח | J292: חו"ל | K292: ארה"ב | L292: סחיר | M292: NYSE | N292: Other | O292: לא | P292: Baa3 | Q292: Moodys | R292: נייר ערך | S292: USD | T292: 2.198 | U292: 46917 | V292: 0.0795 | W292: 0.05369 | X292: החוב לא נחות | Y292: ריק במקור | Z292: 300000 | AA292: 3.19 | AB292: 109.5163 | AC292: 0 | AD292: 1048.071 | AE292: ריק במקור | AF292: ריק במקור | AG292: שווי הוגן | AH292: 0.00046153846 | AI292: 0.0019757869 | AJ292: 0.00024320197
A293: 13908 | B293: 13908 | C293: APOLLO DEBT SOLUTIONS | D293: ZM9734348 | E293: LEI | F293: APODS 6.7 07/31 | G293: US03770DAD57 | H293: ISIN | I293: צמוד למט"ח | J293: חו"ל | K293: ארה"ב | L293: סחיר | M293: FWB | N293: Financial Services | O293: לא | P293: NR | Q293: NR | R293: NR | S293: USD | T293: 4.528 | U293: 48058 | V293: 0.067 | W293: 0.05509 | X293: החוב לא נחות | Y293: ריק במקור | Z293: 188000 | AA293: 3.19 | AB293: 106.7657 | AC293: 0 | AD293: 640.29526 | AE293: ריק במקור | AF293: ריק במקור | AG293: שווי הוגן | AH293: 0.00018903858 | AI293: 0.0012070623 | AJ293: 0.00014857874
A294: 13908 | B294: 13908 | C294: BLUE OWL CREDIT INCOME | D294: YQ9379492 | E294: LEI | F294: OCINCC 5.8 3/30 | G294: US09581CAD39 | H294: ISIN | I294: צמוד למט"ח | J294: חו"ל | K294: ארה"ב | L294: סחיר | M294: FWB | N294: Banks | O294: לא | P294: NR | Q294: NR | R294: NR | S294: USD | T294: 3.727 | U294: 47557 | V294: 0.058 | W294: 0.05799 | X294: החוב לא נחות | Y294: ריק במקור | Z294: 76200 | AA294: 3.19 | AB294: 101.1451 | AC294: 0 | AD294: 245.86149 | AE294: ריק במקור | AF294: ריק במקור | AG294: שווי הוגן | AH294: 7.62888e-05 | AI294: 0.00046348951 | AJ294: 5.7051479e-05
A295: 13908 | B295: 13908 | C295: Globalworth Real Estate Invest | D295: ZB6937823 | E295: LEI | F295: GWILN 6.25 3/29 | G295: XS2809858561 | H295: ISIN | I295: צמוד למט"ח | J295: חו"ל | K295: פולין | L295: סחיר | M295: NYSE | N295: Real Estate Management & Development | O295: לא | P295: NR | Q295: NR | R295: NR | S295: EUR | T295: 0.014 | U295: 47208 | V295: 0.0625 | W295: 0.06083 | X295: החוב לא נחות | Y295: ריק במקור | Z295: 837000 | AA295: 3.7455 | AB295: 89.4648 | AC295: 0 | AD295: 2804.7067 | AE295: ריק במקור | AF295: ריק במקור | AG295: שווי הוגן | AH295: 0.0027254149 | AI295: 0.0052873353 | AJ295: 0.00065082444
A296: 13908 | B296: 13908 | C296: South Bow USA Infrastructure Holdings LLC | D296: MSFSBD3QN1GS | E296: LEI | F296: SOBOCN 7.625 10/55 | G296: US836720AG73 | H296: ISIN | I296: צמוד למט"ח | J296: חו"ל | K296: אוסטרליה | L296: סחיר | M296: NYSE | N296: Financial Services | O296: לא | P296: Ba1 | Q296: Moodys | R296: נייר ערך | S296: USD | T296: 3.385 | U296: 47392 | V296: 0.05026 | W296: 0.07305 | X296: החוב לא נחות | Y296: ריק במקור | Z296: 22000 | AA296: 3.19 | AB296: 104.7735 | AC296: 0 | AD296: 73.53004 | AE296: ריק במקור | AF296: ריק במקור | AG296: שווי הוגן | AH296: 4.9285583e-05 | AI296: 0.00013861627 | AJ296: 1.7062442e-05
AZ10000: 1

Sheet מניות מבכ ויהש
A1: מספר קופה/קרן/ח.פ. עבור חברת ביטוח | B1: מספר מסלול | C1: שם מנפיק | D1: מספר מנפיק | E1: סוג מספר מזהה מנפיק | F1: שם נייר ערך | G1: מספר נייר ערך | H1: סוג מספר נייר ערך | I1: מאפיין עיקרי | J1: ישראל/חו"ל | K1: מדינה לפי חשיפה כלכלית | L1: סטאטוס סחירות | M1: זירת מסחר | N1: ענף מסחר | O1: בעל עניין/צד קשור | P1: מטבע פעילות | Q1: ערך נקוב (יחידות) | R1: שער חליפין | S1: שער נייר הערך | T1: סכום לקבל (במטבע הפעילות) | U1: שווי הוגן (באלפי ש"ח) | V1: שיעור מערך נקוב מונפק | W1: שיעור מנכסי אפיק ההשקעה | X1: שיעור מסך נכסי ההשקעה
A2: 13908 | B2: 13908 | C2: להב אל.אר רילאסטייט בע"מ | D2: 520034257 | E2: ח.פ. | F2: להב | G2: IL0001360101 | H2: ISIN | I2: מניות | J2: ישראל | K2: ישראל | L2: סחיר | M2: TASE | N2: השקעה ואחזקות | O2: כן | P2: ILS | Q2: 1600000 | R2: 1 | S2: 840 | T2: 0 | U2: 13440 | V2: 0.0059301714 | W2: 0.016172781 | X2: 0.0031187148
A3: 13908 | B3: 13908 | C3: וואן טכנולוגיות תוכנה בע"מ | D3: 520034695 | E3: ח.פ. | F3: וואן טכנולוגיות | G3: IL0001610182 | H3: ISIN | I3: מניות | J3: ישראל | K3: ישראל | L3: סחיר | M3: TASE | N3: שירותי מידע | O3: לא | P3: ILS | Q3: 42987 | R3: 1 | S3: 8801 | T3: 0 | U3: 3783.2859 | V3: 0.00058378623 | W3: 0.0045525486 | X3: 0.00087790102
A4: 13908 | B4: 13908 | C4: כלל החזקות עסקי ביטוח בע"מ | D4: 520036120 | E4: ח.פ. | F4: כלל עסקי ביטוח | G4: IL0002240146 | H4: ISIN | I4: מניות | J4: ישראל | K4: ישראל | L4: סחיר | M4: TASE | N4: ביטוח | O4: לא | P4: ILS | Q4: 127580 | R4: 1 | S4: 20570 | T4: 0 | U4: 26243.206 | V4: 0.0015938506 | W4: 0.031579287 | X4: 0.0060896634
A5: 13908 | B5: 13908 | C5: מבנה נדל"ן (כ.ד) בע"מ | D5: 520024126 | E5: ח.פ. | F5: מבנה | G5: IL0002260193 | H5: ISIN | I5: מניות | J5: ישראל | K5: ישראל | L5: סחיר | M5: TASE | N5: נדל"ן מניב בישראל | O5: לא | P5: ILS | Q5: 386595 | R5: 1 | S5: 1559 | T5: 0 | U5: 6027.0161 | V5: 0.00053424328 | W5: 0.0072525007 | X5: 0.0013985524
A6: 13908 | B6: 13908 | C6: בזק החברה הישראלית לתקשורת בע" | D6: 520031931 | E6: ח.פ. | F6: בזק | G6: IL0002300114 | H6: ISIN | I6: מניות | J6: ישראל | K6: ישראל | L6: סחיר | M6: TASE | N6: תקשורת ומדיה | O6: לא | P6: ILS | Q6: 2558142 | R6: 1 | S6: 709.9 | T6: 0 | U6: 18160.25 | V6: 0.00092193024 | W6: 0.021852808 | X6: 0.0042140358
A7: 13908 | B7: 13908 | C7: ישראמקו נגב 2 שותפות מוגבלת | D7: 550010003 | E7: מספר שותפות | F7: ישראמקו יהש | G7: IL0002320179 | H7: ISIN | I7: יחידות השתתפות | J7: ישראל | K7: ישראל | L7: סחיר | M7: TASE | N7: חיפושי נפט וגז | O7: לא | P7: ILS | Q7: 667292 | R7: 1 | S7: 245.5 | T7: 0 | U7: 1638.2019 | V7: 0.00025666876 | W7: 0.0019713006 | X7: 0.00038014021
A8: 13908 | B8: 13908 | C8: פורמולה מערכות (1985)בע"מ | D8: 520036690 | E8: ח.פ. | F8: פורמולה מערכות | G8: IL0002560162 | H8: ISIN | I8: מניות | J8: ישראל | K8: ישראל | L8: סחיר | M8: TASE | N8: שירותי מידע | O8: לא | P8: ILS | Q8: 3100 | R8: 1 | S8: 53730 | T8: 5.084 | U8: 1670.714 | V8: 0.0002021827 | W8: 0.0020104235 | X8: 0.00038768456
A9: 13908 | B9: 13908 | C9: אורביט טכנולוג'יס בע"מ | D9: 520036153 | E9: ח.פ. | F9: אורביט | G9: IL0002650179 | H9: ISIN | I9: מניות | J9: ישראל | K9: ישראל | L9: סחיר | M9: TASE | N9: ביטחוניות | O9: כן | P9: ILS | Q9: 70163 | R9: 1 | S9: 4134 | T9: 0 | U9: 2900.5384 | V9: 0.0027610203 | W9: 0.0034903104 | X9: 0.00067306192
A10: 13908 | B10: 13908 | C10: נייס בע"מ | D10: 520036872 | E10: ח.פ. | F10: נייס | G10: IL0002730112 | H10: ISIN | I10: מניות | J10: ישראל | K10: ישראל | L10: סחיר | M10: TASE | N10: תוכנה ואינטרנט | O10: לא | P10: ILS | Q10: 16810 | R10: 1 | S10: 35710 | T10: 0 | U10: 6002.851 | V10: 0.00027225548 | W10: 0.0072234221 | X10: 0.001392945
A11: 13908 | B11: 13908 | C11: איי.סי.אל גרופ בע"מ | D11: 520027830 | E11: ח.פ. | F11: איי.סי.אל | G11: IL0002810146 | H11: ISIN | I11: מניות | J11: ישראל | K11: ישראל | L11: סחיר | M11: TASE | N11: כימיה, גומי ופלסטיק | O11: לא | P11: ILS | Q11: 501190 | R11: 1 | S11: 1830 | T11: 0 | U11: 9171.777 | V11: 0.00038831687 | W11: 0.011036692 | X11: 0.0021282855
A12: 13908 | B12: 13908 | C12: קבוצת סקופ מתכות בע"מ | D12: 520037425 | E12: ח.פ. | F12: סקופ חסום | G12: IL0002880198 | H12: ISIN | I12: מניות | J12: ישראל | K12: ישראל | L12: חסום | M12: TASE | N12: מסחר | O12: לא | P12: ILS | Q12: 20000 | R12: 1 | S12: 17375.574 | T12: 0 | U12: 3475.1148 | V12: 0.0015114569 | W12: 0.0041817165 | X12: 0.00080639077
A13: 13908 | B13: 13908 | C13: מליסרון בע"מ | D13: 520037789 | E13: ח.פ. | F13: מליסרון | G13: IL0003230146 | H13: ISIN | I13: מניות | J13: ישראל | K13: ישראל | L13: סחיר | M13: TASE | N13: נדל"ן מניב בישראל | O13: לא | P13: ILS | Q13: 19576 | R13: 1 | S13: 41330 | T13: 0 | U13: 8090.7608 | V13: 0.00041074307 | W13: 0.0097358706 | X13: 0.0018774387
... A129: 13908 | B129: 13908 | C129: ITHACA ENERGY PLC | D129: 66296534 | E129: LEI | F129: ITHACA ENERGY PLC | G129: GB00BPJHV584 | H129: ISIN | I129: מניות | J129: חו"ל | K129: ישראל | L129: סחיר | M129: LSE | N129: Energy Equipment & Services | O129: לא | P129: GBP | Q129: 770255 | R129: 4.29 | S129: 165.8 | T129: 0 | U129: 5478.6852 | V129: 0.0004657676 | W129: 0.0065926767 | X129: 0.0012713137
AZ10000: 1

Sheet קרנות סל
A1: מספר קופה/קרן/ח.פ. עבור חברת ביטוח | B1: מספר מסלול | C1: שם מנפיק | D1: מספר מנפיק | E1: סוג מספר מזהה מנפיק | F1: שם נייר ערך | G1: מספר נייר ערך | H1: סוג מספר נייר ערך | I1: מאפיין עיקרי | J1: ישראל/חו"ל | K1: מדינה לפי חשיפה כלכלית | L1: זירת מסחר | M1: סיווג הקרן | N1: בעל עניין/צד קשור | O1: מטבע פעילות | P1: ערך נקוב (יחידות) | Q1: שער חליפין | R1: שער נייר הערך | S1: סכום לקבל (במטבע הפעילות) | T1: שווי הוגן (באלפי ש"ח) | U1: שיעור מערך נקוב מונפק | V1: שיעור מנכסי אפיק ההשקעה | W1: שיעור מסך נכסי ההשקעה
A2: 13908 | B2: 13908 | C2: מיטב קרנות נאמנות בע"מ | D2: 513534974 | E2: ח.פ. | F2: תכ.תא125 | G2: IL0011437188 | H2: ISIN | I2: עוקב אחר מדדי מניות בישראל | J2: ישראל | K2: ישראל | L2: TASE | M2: Large & Mid Cap מניות בארץ - מניות לפי שווי שוק-מניות | N2: לא | O2: ILS | P2: 1880000 | Q2: 1 | R2: 3583 | S2: 0 | T2: 67360.4 | U2: 0.0042841713 | V2: 0.19453959 | W2: 0.015630795
A3: 13908 | B3: 13908 | C3: מיטב קרנות נאמנות בע"מ | D3: 513534974 | E3: ח.פ. | F3: תכ.תלבונד60 | G3: IL0011451015 | H3: ISIN | I3: עוקב אחר מדדים אחרים בישראל | J3: ישראל | K3: ישראל | L3: TASE | M3: 60 אג"ח בארץ - חברות והמרה-תל בונד צמוד מדד-תל בונד | N3: לא | O3: ILS | P3: 15040200 | Q3: 1 | R3: 396.66 | S3: 0 | T3: 59658.457 | U3: 0.011045029 | V3: 0.17229607 | W3: 0.01384358
A4: 13908 | B4: 13908 | C4: קסם קרנות נאמנות בע"מ | D4: 510938608 | E4: ח.פ. | F4: קסם.תלבונד 20 צ | G4: IL0011459604 | H4: ISIN | I4: עוקב אחר מדדים אחרים בישראל | J4: ישראל | K4: ישראל | L4: TASE | M4: 20 אג"ח בארץ - חברות והמרה-תל בונד צמוד מדד-תל בונד | N4: לא | O4: ILS | P4: 3000 | Q4: 1 | R4: 4035.8 | S4: 0 | T4: 121.074 | U4: 5.7499699e-05 | V4: 0.00034966667 | W4: 2.8094887e-05
A5: 13908 | B5: 13908 | C5: קסם קרנות נאמנות בע"מ | D5: 510938608 | E5: ח.פ. | F5: STOX600.קסם | G5: IL0011462087 | H5: ISIN | I5: עוקב אחר מדדי מניות בחו"ל | J5: ישראל | K5: אירופה | L5: TASE | M5: מניות בחו"ל - מניות גיאוגרפי - חשופת מט"ח-אירופה - מדד אחר | N5: לא | O5: ILS | P5: 103320 | Q5: 1 | R5: 52500 | S5: 0 | T5: 54243 | U5: 0.052414773 | V5: 0.156656 | W5: 0.012586938
A6: 13908 | B6: 13908 | C6: קסם קרנות נאמנות בע"מ | D6: 510938608 | E6: ח.פ. | F6: קסם.תלבונד 60 צ | G6: IL0011462327 | H6: ISIN | I6: עוקב אחר מדדים אחרים בישראל | J6: ישראל | K6: ישראל | L6: TASE | M6: אג"ח בארץ - חברות והמרה-תל בונד צמוד מדד-תל בונד צמודות | N6: לא | O6: ILS | P6: 1559524 | Q6: 1 | R6: 3947.29 | S6: 0 | T6: 61558.935 | U6: 0.021654101 | V6: 0.17778472 | W6: 0.014284581
A7: 13908 | B7: 13908 | C7: אי.בי.אי קרנות נאמנות בעמ | D7: 513765339 | E7: ח.פ. | F7: IBI.תלבונד 60צד | G7: IL0011480063 | H7: ISIN | I7: עוקב אחר מדדים אחרים בישראל | J7: ישראל | K7: ישראל | L7: TASE | M7: 60 אג"ח בארץ - חברות והמרה-תל בונד צמוד מדד-תל בונד | N7: לא | O7: ILS | P7: 5495390 | Q7: 1 | R7: 397.01 | S7: 0 | T7: 21817.248 | U7: 0.0039974871 | V7: 0.063009105 | W7: 0.005062632
A8: 13908 | B8: 13908 | C8: אי.בי.אי קרנות נאמנות בעמ | D8: 513765339 | E8: ח.פ. | F8: IBI.תא 125 | G8: IL0011488082 | H8: ISIN | I8: עוקב אחר מדדי מניות בישראל | J8: ישראל | K8: ישראל | L8: TASE | M8: Large & Mid Cap מניות בארץ - מניות לפי שווי שוק-מניות | N8: לא | O8: ILS | P8: 160000 | Q8: 1 | R8: 3579 | S8: 0 | T8: 5726.4 | U8: 0.00039873037 | V8: 0.016538078 | W8: 0.0013287953
A9: 13908 | B9: 13908 | C9: הראל קרנות נאמנות בע"מ | D9: 511776783 | E9: ח.פ. | F9: SP500.הרל | G9: IL0011490203 | H9: ISIN | I9: עוקב אחר מדדי מניות בחו"ל | J9: ישראל | K9: ארה"ב | L9: TASE | M9: S&P 500 - מניות בחו"ל - מניות גיאוגרפי - מנוטרלת מט"ח-ארה"ב | N9: לא | O9: ILS | P9: 17250 | Q9: 1 | R9: 2567 | S9: 0 | T9: 442.8075 | U9: 4.5540018e-05 | V9: 0.0012788462 | W9: 0.00010275226
A10: 13908 | B10: 13908 | C10: מגדל קרנות נאמנות בע"מ | D10: 511303661 | E10: ח.פ. | F10: MTF.תא125 | G10: IL0011502833 | H10: ISIN | I10: עוקב אחר מדדי מניות בישראל | J10: ישראל | K10: ישראל | L10: TASE | M10: Large & Mid Cap מניות בארץ - מניות לפי שווי שוק-מניות | N10: לא | O10: ILS | P10: 5000 | Q10: 1 | R10: 5643 | S10: 0 | T10: 282.15 | U10: 5.2631579e-05 | V10: 0.00081486075 | W10: 6.5472127e-05
A11: 13908 | B11: 13908 | C11: מגדל קרנות נאמנות בע"מ | D11: 511303661 | E11: ח.פ. | F11: SP500.MTF | G11: IL0011503336 | H11: ISIN | I11: עוקב אחר מדדי מניות בחו"ל | J11: ישראל | K11: ארה"ב | L11: TASE | M11: S&P 500 - מניות בחו"ל - מניות גיאוגרפי - חשופת מט"ח-ארה"ב | N11: לא | O11: ILS | P11: 12400 | Q11: 1 | R11: 9445 | S11: 0 | T11: 1171.18 | U11: 0.00014203895 | V11: 0.0033824158 | W11: 0.00027176908
A12: 13908 | B12: 13908 | C12: הראל קרנות נאמנות בע"מ | D12: 511776783 | E12: ח.פ. | F12: הרל.תלבד- 60 צמ | G12: IL0011504730 | H12: ISIN | I12: עוקב אחר מדדים אחרים בישראל | J12: ישראל | K12: ישראל | L12: TASE | M12: אג"ח בארץ - חברות והמרה-תל בונד צמוד מדד-תל בונד צמודות | N12: לא | O12: ILS | P12: 5205892 | Q12: 1 | R12: 395.49 | S12: 0 | T12: 20588.782 | U12: 0.016850115 | V12: 0.059461246 | W12: 0.00477757
A13: 13908 | B13: 13908 | C13: קסם קרנות נאמנות בע"מ | D13: 510938608 | E13: ח.פ. | F13: קסם.תלבונד ש 50 | G13: IL0011507626 | H13: ISIN | I13: עוקב אחר מדדים אחרים בישראל | J13: ישראל | K13: ישראל | L13: TASE | M13: אג"ח בארץ - חברות והמרה-תל בונד שקלי-תל בונד- שקלי | N13: לא | O13: ILS | P13: 714515 | Q13: 1 | R13: 4341.57 | S13: 0 | T13: 31021.169 | U13: 0.018313036 | V13: 0.089590406 | W13: 0.0071983764
... A16: 13908 | B16: 13908 | C16: Ishares iBoxx $ Investment | D16: 78005 | E16: LEI | F16: ISHARES IBOXX H/Y CORP BOND | G16: US4642885135 | H16: ISIN | I16: עוקב אחר מדדים אחרים בחו"ל | J16: חו"ל | K16: ארה"ב | L16: NYSE | M16: Bond/Fixed Income Funds | N16: לא | O16: USD | P16: 42400 | Q16: 3.19 | R16: 8063 | S16: 0 | T16: 10905.691 | U16: 0.00017214779 | V16: 0.031496083 | W16: 0.0025306355
AZ10000: 1

Sheet קרנות נאמנות
A1: מספר קופה/קרן/ח.פ. עבור חברת ביטוח | B1: מספר מסלול | C1: שם מנפיק | D1: מספר מנפיק | E1: סוג מספר מזהה מנפיק | F1: שם נייר ערך | G1: מספר נייר ערך | H1: סוג מספר נייר ערך | I1: מאפיין עיקרי | J1: ישראל/חו"ל | K1: מדינה לפי חשיפה כלכלית | L1: סטאטוס סחירות | M1: זירת מסחר | N1: סיווג הקרן | O1: בעל עניין/צד קשור | P1: מטבע פעילות | Q1: ערך נקוב (יחידות) | R1: שער חליפין | S1: שער נייר הערך | T1: שווי הוגן (באלפי ש"ח) | U1: שיעור מערך נקוב מונפק | V1: שיעור מנכסי אפיק ההשקעה | W1: שיעור מסך נכסי ההשקעה
A2: 13908 | B2: 13908 | C2: מיטב קרנות נאמנות בע"מ | D2: 513534974 | E2: ח.פ. | F2: SP 500 תכלית | G2: IL0051139983 | H2: ISIN | I2: מניות | J2: ישראל | K2: ארה"ב | L2: סחיר | M2: TASE | N2: S&P 500 - מניות בחו"ל - מניות גיאוגרפי - חשופת מט"ח-ארה"ב | O2: לא | P2: ILS | Q2: 16874000 | R2: 1 | S2: 780.91 | T2: 131770.75 | U2: 0.01277209 | V2: 0.20268723 | W2: 0.030577039
A3: 13908 | B3: 13908 | C3: מיטב קרנות נאמנות בע"מ | D3: 513534974 | E3: ח.פ. | F3: תכלית ת"א 125 | G3: IL0051146574 | H3: ISIN | I3: מניות | J3: ישראל | K3: ישראל | L3: סחיר | M3: TASE | N3: Large & Mid Cap מניות בארץ - מניות לפי שווי שוק-מניות | O3: לא | P3: ILS | Q3: 20431000 | R3: 1 | S3: 323.18 | T3: 66028.906 | U3: 0.011282533 | V3: 0.10156439 | W3: 0.015321825
A4: 13908 | B4: 13908 | C4: מיטב קרנות נאמנות בע"מ | D4: 513534974 | E4: ח.פ. | F4: תכ.TTFתלבונד20 | G4: IL0051154727 | H4: ISIN | I4: אג"ח קונצרני | J4: ישראל | K4: ישראל | L4: סחיר | M4: TASE | N4: 20 אג"ח בארץ - חברות והמרה-תל בונד צמוד מדד-תל בונד | O4: לא | P4: ILS | Q4: 43850136 | R4: 1 | S4: 110.8 | T4: 48585.951 | U4: 0.24145351 | V4: 0.074733973 | W4: 0.011274235
A5: 13908 | B5: 13908 | C5: קסם קרנות נאמנות בע"מ | D5: 510938608 | E5: ח.פ. | F5: קסם תל בונד 20 | G5: IL0051155898 | H5: ISIN | I5: אג"ח קונצרני | J5: ישראל | K5: ישראל | L5: סחיר | M5: TASE | N5: 20 אג"ח בארץ - חברות והמרה-תל בונד צמוד מדד-תל בונד | O5: לא | P5: ILS | Q5: 19016000 | R5: 1 | S5: 151.94 | T5: 28892.91 | U5: 0.057663026 | V5: 0.044442518 | W5: 0.00670452
A6: 13908 | B6: 13908 | C6: הראל קרנות נאמנות בע"מ | D6: 511776783 | E6: ח.פ. | F6: הרל.תלבנד 20 צמ | G6: IL0051172703 | H6: ISIN | I6: אג"ח קונצרני | J6: ישראל | K6: ישראל | L6: סחיר | M6: TASE | N6: אג"ח בארץ - חברות והמרה-תל בונד צמוד מדד-תל בונד צמודות | O6: לא | P6: ILS | Q6: 34768000 | R6: 1 | S6: 147.73 | T6: 51362.766 | U6: 0.067512144 | V6: 0.079005217 | W6: 0.011918588
A7: 13908 | B7: 13908 | C7: מגדל קרנות נאמנות בע"מ | D7: 511303661 | E7: ח.פ. | F7: S&P 500 מח MTF | G7: IL0051226277 | H7: ISIN | I7: מניות | J7: ישראל | K7: ארה"ב | L7: סחיר | M7: TASE | N7: S&P 500 - מניות בחו"ל - מניות גיאוגרפי - חשופת מט"ח-ארה"ב | O7: לא | P7: ILS | Q7: 31459071 | R7: 1 | S7: 314.13 | T7: 98822.38 | U7: 0.014262216 | V7: 0.15200668 | W7: 0.02293146
A8: 13908 | B8: 13908 | C8: קסם קרנות נאמנות בע"מ | D8: 510938608 | E8: ח.פ. | F8: S&P 500 קסם | G8: IL0051244825 | H8: ISIN | I8: מניות | J8: ישראל | K8: ארה"ב | L8: סחיר | M8: TASE | N8: S&P 500 - מניות בחו"ל - מניות גיאוגרפי - חשופת מט"ח-ארה"ב | O8: לא | P8: ILS | Q8: 23113000 | R8: 1 | S8: 298.39 | T8: 68966.881 | U8: 0.0050583356 | V8: 0.10608353 | W8: 0.016003574
A9: 13908 | B9: 13908 | C9: אי.בי.אי קרנות נאמנות בעמ | D9: 513765339 | E9: ח.פ. | F9: S&P 500י.IBI | G9: IL0051274699 | H9: ISIN | I9: מניות | J9: ישראל | K9: ארה"ב | L9: סחיר | M9: TASE | N9: S&P 500 - מניות בחו"ל - מניות גיאוגרפי - חשופת מט"ח-ארה"ב | O9: לא | P9: ILS | Q9: 17528160 | R9: 1 | S9: 246.63 | T9: 43229.701 | U9: 0.011680811 | V9: 0.066495093 | W9: 0.010031333
A10: 13908 | B10: 13908 | C10: אי.בי.אי קרנות נאמנות בעמ | D10: 513765339 | E10: ח.פ. | F10: NASDAQ 100י.IBI | G10: IL0051277668 | H10: ISIN | I10: מניות | J10: ישראל | K10: ארה"ב | L10: סחיר | M10: TASE | N10: NASDAQ 100 - מניות בחו"ל - מניות גיאוגרפי - מנוטרלת מט"ח-ארה"ב | O10: לא | P10: ILS | Q10: 13119174 | R10: 1 | S10: 310.25 | T10: 40702.237 | U10: 0.015662513 | V10: 0.062607397 | W10: 0.0094448416
A11: 13908 | B11: 13908 | C11: הראל קרנות נאמנות בע"מ | D11: 511776783 | E11: ח.פ. | F11: NASDAQ 100 הראל | G11: IL0051292832 | H11: ISIN | I11: מניות | J11: ישראל | K11: ארה"ב | L11: סחיר | M11: TASE | N11: מניות בחו"ל - מניות גיאוגרפי - חשופת מט"ח-ארה"ב - מדד אחר | O11: לא | P11: ILS | Q11: 13860000 | R11: 1 | S11: 325.14 | T11: 45064.404 | U11: 0.0091288374 | V11: 0.069317197 | W11: 0.01045707
A12: 13908 | B12: 13908 | C12: אי.בי.אי קרנות נאמנות בעמ | D12: 513765339 | E12: ח.פ. | F12: STOXX-E600י.IBI | G12: IL0051307523 | H12: ISIN | I12: מניות | J12: ישראל | K12: אירופה | L12: סחיר | M12: TASE | N12: STOXX EUROPE 600 - מניות בחו"ל - מניות גיאוגרפי - מנוטרלת מט"ח-אירופה כללי | O12: לא | P12: ILS | Q12: 15622700 | R12: 1 | S12: 164.99 | T12: 25775.893 | U12: 0.097651495 | V12: 0.039647981 | W12: 0.0059812246
A13: 13908 | B13: 13908 | C13: CIFC Global Floating Rate Cred | D13: 635400NLI1L | E13: LEI | F13: CIFC GLBL FLT RT CR-B1 USD | G13: IE0009SO3I10 | H13: ISIN | I13: אחר | J13: חו"ל | K13: גלובלי | L13: סחיר | M13: אחר | N13: Bond/Fixed Income Funds | O13: לא | P13: USD | Q13: 193.86 | R13: 3.19 | S13: 148102.3 | T13: 915.88447 | U13: 0.0050052929 | V13: 0.0014087958 | W13: 0.00021252846
AZ10000: 1

Sheet כתבי אופציה
A1: מספר קופה/קרן/ח.פ. עבור חברת ביטוח | B1: מספר מסלול | C1: שם מנפיק | D1: מספר מנפיק | E1: סוג מספר מזהה מנפיק | F1: שם נייר ערך | G1: מספר נייר ערך | H1: סוג מספר נייר ערך | I1: ישראל/חו"ל | J1: מדינה לפי חשיפה כלכלית | K1: סטאטוס סחירות | L1: זירת מסחר | M1: נכס בסיס (כתב אופציה) | N1: ענף מסחר | O1: תאריך פקיעה | P1: בעל עניין/צד קשור | Q1: מטבע פעילות | R1: שער מימוש | S1: יחס המרה | T1: ערך נקוב (יחידות) | U1: שער חליפין | V1: שער נייר הערך | W1: שווי הוגן (באלפי ש"ח) | X1: שיעור מנכסי אפיק ההשקעה | Y1: שיעור מסך נכסי ההשקעה
A2: 13908 | B2: 13908 | C2: אלומיי קפיטל בע"מ | D2: 520039868 | E2: ח.פ. | F2: אלומיי אפ 2 | G2: IL0012030826 | H2: ISIN | I2: ישראל | J2: ישראל | K2: סחיר | L2: TASE | M2: IL0010826357 | N2: אנרגיה מתחדשת | O2: 46757 | P2: לא | Q2: ILS | R2: 8000 | S2: 1 | T2: 2304 | U2: 1 | V2: 1354 | W2: 31.19616 | X2: 0.0087890458 | Y2: 7.2389827e-06
A3: 13908 | B3: 13908 | C3: מיטב טרייד השקעות בע"מ | D3: 516854239 | E3: ח.פ. | F3: מיטב טרייד אפ 1 | G3: IL0012031998 | H3: ISIN | I3: ישראל | J3: ישראל | K3: סחיר | L3: TASE | M3: IL0012031816 | N3: שירותים פיננסיים | O3: 46770 | P3: כן | Q3: ILS | R3: 690.946 | S3: 1 | T3: 192000 | U3: 1 | V3: 1495 | W3: 2870.4 | X3: 0.80869174 | Y3: 0.00066606838
A4: 13908 | B4: 13908 | C4: אפי קפיטל נדל"ן בע"מ | D4: 513948216 | E4: ח.פ. | F4: אפי קפיטל אפ 1 | G4: IL0012042136 | H4: ISIN | I4: ישראל | J4: ישראל | K4: סחיר | L4: TASE | M4: IL0011814378 | N4: בנייה | O4: 46069 | P4: כן | Q4: ILS | R4: 1143.91 | S4: 1 | T4: 42500 | U4: 1 | V4: 646.1 | W4: 274.5925 | X4: 0.07736228 | Y4: 6.371843e-05
A5: 13908 | B5: 13908 | C5: שובל הנדסה ובניין בע"מ | D5: 512951518 | E5: ח.פ. | F5: שובל הנדסה אפ 1 | G5: IL0012159617 | H5: ISIN | I5: ישראל | J5: ישראל | K5: סחיר | L5: TASE | M5: IL0012079682 | N5: בנייה | O5: 46398 | P5: כן | Q5: ILS | R5: 1023 | S5: 1 | T5: 2500 | U5: 1 | V5: 113.2 | W5: 2.83 | X5: 0.00079730966 | Y5: 6.5669367e-07
A6: 13908 | B6: 13908 | C6: קבוצת חג'ג' ייזום נדל"ן בע"מ | D6: 520033309 | E6: ח.פ. | F6: חג'ג' אפ 1 | G6: IL0012166547 | H6: ISIN | I6: ישראל | J6: ישראל | K6: סחיר | L6: TASE | M6: IL0008230133 | N6: בנייה | O6: 46233 | P6: לא | Q6: ILS | R6: 3230 | S6: 1 | T6: 15856 | U6: 1 | V6: 123.3 | W6: 19.55045 | X6: 0.0055080433 | Y6: 4.5366279e-06
A7: 13908 | B7: 13908 | C7: מגידו י.ק. בע"מ | D7: 510542855 | E7: ח.פ. | F7: מגידו אפ 1 | G7: IL0012251844 | H7: ISIN | I7: ישראל | J7: ישראל | K7: סחיר | L7: TASE | M7: IL0012166059 | N7: בנייה | O7: 47311 | P7: כן | Q7: ILS | R7: 850 | S7: 1 | T7: 60500 | U7: 1 | V7: 262.4 | W7: 158.752 | X7: 0.044725973 | Y7: 3.6837963e-05
A8: 13908 | B8: 13908 | C8: נאוויטס פטרוליום, שותפות מוגבל | D8: 550263107 | E8: ח.פ. | F8: נאוויטס פט אפ 6 | G8: IL0012288242 | H8: ISIN | I8: ישראל | J8: ישראל | K8: סחיר | L8: TASE | M8: IL0011419699 | N8: חיפושי נפט וגז | O8: 46265 | P8: לא | Q8: ILS | R8: 11422.076 | S8: 1 | T8: 10793 | U8: 1 | V8: 1780 | W8: 192.1154 | X8: 0.054125605 | Y8: 4.4579847e-05
AZ10000: 1

Sheet אופציות
A1: מספר קופה/קרן/ח.פ. עבור חברת ביטוח | B1: מספר מסלול | C1: שם מנפיק | D1: מספר מנפיק | E1: סוג מספר מזהה מנפיק | F1: שם נייר ערך | G1: מספר נייר ערך | H1: סוג מספר נייר ערך | I1: מאפיין עיקרי | J1: ישראל/חו"ל | K1: מדינה לפי חשיפה כלכלית | L1: זירת מסחר | M1: ענף מסחר | N1: נכס בסיס | O1: תאריך פקיעה | P1: בעל עניין/צד קשור | Q1: מטבע פעילות | R1: שער מימוש | S1: ערך נקוב (יחידות) | T1: שער חליפין | U1: שער נייר הערך | V1: שווי הוגן (באלפי ש"ח) | W1: שיעור מנכסי אפיק ההשקעה | X1: שיעור מסך נכסי ההשקעה

Sheet חוזים עתידיים
A1: מספר קופה/קרן/ח.פ. עבור חברת ביטוח | B1: מספר מסלול | C1: שם מנפיק | D1: מספר מנפיק | E1: סוג מספר מזהה מנפיק | F1: שם נייר ערך | G1: מספר נייר ערך | H1: סוג מספר נייר ערך | I1: ישראל/חו"ל | J1: מדינה לפי חשיפה כלכלית | K1: זירת מסחר | L1: נכס בסיס | M1: בעל עניין/צד קשור | N1: מטבע פעילות | O1: ערך נקוב (יחידות) | P1: שער חליפין | Q1: שער נייר הערך | R1: שווי הוגן (באלפי ש"ח) | S1: שיעור מנכסי אפיק ההשקעה | T1: שיעור מסך נכסי ההשקעה
A2: 13908 | B2: 13908 | C2: NIFTY | D2: BBG01Y5TTG71 | E2: LEI | F2: NIFTY 50 IFSC | G2: JGSF6 INDEX | H2: אחר | I2: חו"ל | J2: הודו | K2: BSE | L2: מניות לרבות מדדי מניות | M2: לא | N2: USD | O2: 20 | P2: 3.19 | Q2: 2634750 | R2: 27.26499 | S2: 0.0059600881 | T2: 6.3267655e-06
A3: 13908 | B3: 13908 | C3: Chicago Board of Trade | D3: BBG01VKPGYH2 | E3: LEI | F3: ULTRA10 YR 03/26 | G3: UXYH6 COMDTY | H3: אחר | I3: חו"ל | J3: ארה"ב | K3: CBOE | L3: מניות לרבות מדדי מניות | M3: לא | N3: USD | O3: 12 | P3: 3.19 | Q3: 11501.56 | R3: -33.64429 | S3: -0.007354594 | T3: -7.8070644e-06
A4: 13908 | B4: 13908 | C4: Osaka Exchange | D4: BBG01PQDVM85 | E4: LEI | F4: NIKKEI 225 MINI 03/26 | G4: NOH6 INDEX | H4: אחר | I4: חו"ל | J4: יפן | K4: JPX | L4: מניות לרבות מדדי מניות | M4: לא | N4: JPY | O4: 295 | P4: 0.020365 | Q4: 5040000 | R4: -122.85695 | S4: -0.026856355 | T4: -2.8508615e-05
A5: 13908 | B5: 13908 | C5: Osaka Exchange | D5: BBG01R87XK04 | E5: LEI | F5: TOPIX INDX FUT 03/26 | G5: TPH6 | H5: אחר | I5: חו"ל | J5: יפן | K5: JPX | L5: מניות לרבות מדדי מניות | M5: לא | N5: JPY | O5: 22 | P5: 0.020365 | Q5: 341350 | R5: 121.86416 | S5: 0.026639332 | T5: 2.8278241e-05
A6: 13908 | B6: 13908 | C6: Chicago Mercantile Exchange | D6: BBG01HZQ8FZ5 | E6: LEI | F6: S&P500 EMINI FUT 03/26 | G6: ESH6 INDEX | H6: אחר | I6: חו"ל | J6: ארה"ב | K6: CME | L6: מניות לרבות מדדי מניות | M6: לא | N6: USD | O6: 594 | P6: 3.19 | Q6: 689250 | R6: 1112.4439 | S6: 0.24317865 | T6: 0.00025813953
A7: 13908 | B7: 13908 | C7: ICE Futures US Indices | D7: BBG013V2S5R2 | E7: LEI | F7: MSCI EmgMkt 03/26 | G7: MESH6 INDEX | H7: אחר | I7: חו"ל | J7: ארה"ב | K7: ICE | L7: מניות לרבות מדדי מניות | M7: לא | N7: USD | O7: 400 | P7: 3.19 | Q7: 141140 | R7: 1426.568 | S7: 0.31184574 | T7: 0.00033103116
A8: 13908 | B8: 13908 | C8: Chicago Mercantile Exchange | D8: BBG01PSLN5G2 | E8: LEI | F8: FUTURE MINI NASDAQ 03/26 | G8: NQH6 INDEX | H8: אחר | I8: חו"ל | J8: ארה"ב | K8: CME | L8: מניות לרבות מדדי מניות | M8: לא | N8: USD | O8: 54 | P8: 3.19 | Q8: 2545675 | R8: 394.99562 | S8: 0.086345481 | T8: 9.1657641e-05
A9: 13908 | B9: 13908 | C9: Eurex | D9: BBG01FZGYB27 | E9: LEI | F9: STOXX600 03/26 | G9: SXOH6 INDEX | H9: אחר | I9: חו"ל | J9: גרמניה | K9: EUREX | L9: מניות לרבות מדדי מניות | M9: לא | N9: EUR | O9: 1058 | P9: 3.7455 | Q9: 59500 | R9: 2053.1347 | S9: 0.44881233 | T9: 0.00047642423
A10: 13908 | B10: 13908 | C10: Chicago Board of Trade | D10: BBG01SWCT5P5 | E10: LEI | F10: FT MINI DOW 03/26 | G10: DMH6 INDEX | H10: אחר | I10: חו"ל | J10: ארה"ב | K10: CBOE | L10: מניות לרבות מדדי מניות | M10: לא | N10: USD | O10: 48 | P10: 3.19 | Q10: 4833600 | R10: -405.17496 | S10: -0.088570671 | T10: -9.4019729e-05
AZ10000: 1

Sheet מוצרים מובנים
A1: מספר קופה/קרן/ח.פ. עבור חברת ביטוח | B1: מספר מסלול | C1: שם מנפיק | D1: מספר מנפיק | E1: סוג מספר מזהה מנפיק | F1: שם נייר ערך | G1: מספר נייר ערך | H1: סוג מספר נייר ערך | I1: מאפיין עיקרי | J1: ישראל/חו"ל | K1: מדינה לפי חשיפה כלכלית | L1: סטאטוס סחירות | M1: זירת מסחר | N1: נכס בסיס | O1: בעל עניין/צד קשור | P1: מח"מ | Q1: שיעור ריבית | R1: תשואה לפדיון | S1: דירוג | T1: שם מדרג | U1: דירוג נייר הערך/המנפיק | V1: מטבע פעילות | W1: ערך נקוב (יחידות) | X1: שער חליפין | Y1: שער נייר הערך | Z1: שווי הוגן (באלפי ש"ח) | AA1: שיעור מנכסי אפיק ההשקעה | AB1: שיעור מסך נכסי ההשקעה
A2: 13908 | B2: 13908 | C2: אלה פקדונות בע"מ | D2: 515666881 | E2: ח.פ. | F2: אלה פקדון אגח ה | G2: IL0011625774 | H2: ISIN | I2: קרן מובטחת | J2: ישראל | K2: ישראל | L2: סחיר | M2: TASE | N2: מדד המחירים לצרכן | O2: לא | P2: 2.537 | Q2: 0.0005 | R2: 0.0252 | S2: ilAAAs | T2: S&P מעלות | U2: נייר ערך | V2: ILS | W2: 6774 | X2: 1 | Y2: 110.17 | Z2: 7.46292 | AA2: 1 | AB2: 1.7317499e-06
AZ10000: 1

Sheet לא סחיר איגרות חוב ממשלתיות
A1: מספר קופה/קרן/ח.פ. עבור חברת ביטוח | B1: מספר מסלול | C1: שם מנפיק | D1: שם נייר ערך | E1: מספר נייר ערך | F1: סוג מספר נייר ערך | G1: מאפיין עיקרי | H1: ישראל/חו"ל | I1: מדינה לפי חשיפה כלכלית | J1: תאריך רכישה | K1: דירוג | L1: שם מדרג | M1: מטבע פעילות | N1: מח"מ | O1: מועד פדיון | P1: שיעור ריבית | Q1: תשואה לפדיון | R1: ערך נקוב (יחידות) | S1: שער חליפין | T1: שער נייר הערך | U1: שווי הוגן (באלפי ש"ח) | V1: עלות מופחתת (באלפי ש"ח) | W1: השיטה שיושמה בדוח הכספי | X1: שיעור מנכסי אפיק ההשקעה | Y1: שיעור מסך נכסי ההשקעה

Sheet לא סחיר איגרות חוב מיועדות
A1: מספר קופה/קרן/ח.פ. עבור חברת ביטוח | B1: מספר מסלול | C1: מאפיין עיקרי | D1: שם נייר ערך | E1: מספר נייר ערך | F1: תאריך רכישה | G1: מח"מ | H1: סוג הצמדה | I1: מועד פדיון | J1: שיעור ריבית | K1: תשואה לפדיון | L1: ערך נקוב (יחידות) | M1: שער נייר הערך | N1: שווי הוגן (באלפי ש"ח) | O1: עלות מופחתת (באלפי ש"ח) | P1: השיטה שיושמה בדוח הכספי | Q1: שיעור מנכסי אפיק ההשקעה | R1: שיעור מסך נכסי ההשקעה

Sheet אפיק השקעה מובטח תשואה
A1: מספר קרן | B1: מספר מסלול | C1: מאפיין עיקרי | D1: חודש הנפקת שכבה | E1: חודש הבדיקה | F1: שווי הנכסים באפיק (באלפי ש"ח) | G1: שיעור מסך נכסי ההשקעה
A2: 13908 | B2: 1001 | C2: נכס או התחייבות בגין השלמת המדינה לתשואת היעד | D2: 44835 | E2: 46691 | F2: -13917.949 | G2: -0.0032296216
A3: 13908 | B3: 1001 | C3: נכס או התחייבות בגין השלמת המדינה לתשואת היעד | D3: 44866 | E3: 46721 | F3: -10071.984 | G3: -0.002337176
A4: 13908 | B4: 1001 | C4: נכס או התחייבות בגין השלמת המדינה לתשואת היעד | D4: 44896 | E4: 46752 | F4: -15328.317 | G4: -0.0035568936
A5: 13908 | B5: 1001 | C5: נכס או התחייבות בגין השלמת המדינה לתשואת היעד | D5: 44927 | E5: 46783 | F5: -11543.964 | G5: -0.0026787449
A6: 13908 | B6: 1001 | C6: נכס או התחייבות בגין השלמת המדינה לתשואת היעד | D6: 44958 | E6: 46812 | F6: -13311.294 | G6: -0.003088849
A7: 13908 | B7: 1001 | C7: נכס או התחייבות בגין השלמת המדינה לתשואת היעד | D7: 44986 | E7: 46843 | F7: -11439.825 | G7: -0.0026545798
A8: 13908 | B8: 1001 | C8: נכס או התחייבות בגין השלמת המדינה לתשואת היעד | D8: 45017 | E8: 46873 | F8: -11493.474 | G8: -0.0026670289
A9: 13908 | B9: 1001 | C9: נכס או התחייבות בגין השלמת המדינה לתשואת היעד | D9: 45047 | E9: 46904 | F9: -11607.998 | G9: -0.0026936038
A10: 13908 | B10: 1001 | C10: נכס או התחייבות בגין השלמת המדינה לתשואת היעד | D10: 45078 | E10: 46934 | F10: -12645.127 | G10: -0.0029342667
A11: 13908 | B11: 1001 | C11: נכס או התחייבות בגין השלמת המדינה לתשואת היעד | D11: 45108 | E11: 46965 | F11: -14075.342 | G11: -0.0032661442
A12: 13908 | B12: 1001 | C12: נכס או התחייבות בגין השלמת המדינה לתשואת היעד | D12: 45139 | E12: 46996 | F12: -18748.81 | G12: -0.0043506095
A13: 13908 | B13: 1001 | C13: נכס או התחייבות בגין השלמת המדינה לתשואת היעד | D13: 45170 | E13: 47026 | F13: -18311.026 | G13: -0.0042490229
... A40: 13908 | B40: 1001 | C40: נכס או התחייבות בגין השלמת המדינה לתשואת היעד | D40: 45901 | E40: 47756 | F40: -765.79 | G40: -0.00017769945
AZ10000: 1

Sheet לא סחיר ניירות ערך מסחריים
A1: מספר קופה/קרן/ח.פ. עבור חברת ביטוח | B1: מספר מסלול | C1: שם מנפיק | D1: מספר מנפיק | E1: סוג מספר מזהה מנפיק | F1: שם נייר ערך | G1: מספר נייר ערך | H1: סוג מספר נייר ערך | I1: מאפיין עיקרי | J1: ישראל/חו"ל | K1: מדינה לפי חשיפה כלכלית | L1: ענף מסחר | M1: בעל עניין/צד קשור | N1: תאריך רכישה | O1: דירוג | P1: שם מדרג | Q1: דירוג נייר הערך/המנפיק | R1: מטבע פעילות | S1: מח"מ | T1: סוג הצמדה | U1: ריבית עוגן | V1: מועד פדיון | W1: שיעור ריבית | X1: תשואה לפדיון | Y1: נחיתות חוזית | Z1: האם סווג כחוב בעייתי | AA1: סוג גורם משערך | AB1: תלות/אי-תלות המשערך | AC1: שם גורם משערך | AD1: תאריך שערוך אחרון | AE1: תאריך אחרון בו נבחנה בפועל ירידת ערך | AF1: ערך נקוב (יחידות) | AG1: שער חליפין | AH1: שער נייר הערך | AI1: שווי הוגן (באלפי ש"ח) | AJ1: עלות מופחתת (באלפי ש"ח) | AK1: עלות מופחתת (במטבע הפעילות) | AL1: השיטה שיושמה בדוח הכספי | AM1: שיעור מנכסי אפיק ההשקעה | AN1: שיעור מסך נכסי ההשקעה
A2: 13908 | B2: 13908 | C2: שיכון ובינוי בע"מ | D2: 520036104 | E2: ח.פ. | F2: נעמ שכון ובנוי3 | G2: 11020132 | H2: פנימי | I2: לא צמוד למדד המחירים לצרכן | J2: ישראל | K2: ישראל | L2: בנייה | M2: לא | N2: 45657 | O2: A1.il | P2: מידרוג Moodys | Q2: נייר ערך | R2: ILS | S2: 2.05 | T2: לא צמוד | U2: ללא | V2: 46172 | W2: 0.071 | X2: 0.064 | Y2: החוב לא נחות | Z2: ריק במקור | AA2: חברת ציטוט | AB2: אי-תלות | AC2: ריק במקור | AD2: 46022 | AE2: ריק במקור | AF2: 4740000 | AG2: 1 | AH2: 95.36 | AI2: 4520.064 | AJ2: ריק במקור | AK2: ריק במקור | AL2: שווי הוגן | AM2: 1 | AN2: 0.0010488684
AZ10000: 1

Sheet לא סחיר איגרות חוב
A1: מספר קופה/קרן/ח.פ. עבור חברת ביטוח | B1: מספר מסלול | C1: שם מנפיק | D1: מספר מנפיק | E1: סוג מספר מזהה מנפיק | F1: שם נייר ערך | G1: מספר נייר ערך | H1: סוג מספר נייר ערך | I1: מאפיין עיקרי | J1: ישראל/חו"ל | K1: מדינה לפי חשיפה כלכלית | L1: סטאטוס סחירות | M1: ענף מסחר | N1: בעל עניין/צד קשור | O1: תאריך רכישה | P1: דירוג | Q1: שם מדרג | R1: דירוג נייר הערך/המנפיק | S1: מטבע פעילות | T1: מח"מ | U1: מועד פדיון | V1: תשואה לפדיון | W1: שיעור ריבית | X1: נחיתות חוזית | Y1: האם סווג כחוב בעייתי | Z1: סוג גורם משערך | AA1: תלות/אי-תלות המשערך | AB1: תאריך שערוך אחרון | AC1: תאריך אחרון בו נבחנה בפועל ירידת ערך | AD1: ערך נקוב (יחידות) | AE1: שער חליפין | AF1: שער נייר הערך | AG1: שווי הוגן (באלפי ש"ח) | AH1: עלות מופחתת (באלפי ש"ח) | AI1: עלות מופחתת (במטבע הפעילות) | AJ1: השיטה שיושמה בדוח הכספי | AK1: שיעור מנכסי אפיק ההשקעה | AL1: שיעור מסך נכסי ההשקעה
A2: 13908 | B2: 13908 | C2: מקורות חברת מים בע"מ | D2: 520010869 | E2: ח.פ. | F2: מקורות אגח -6רמ | G2: IL0011009086 | H2: ISIN | I2: צמוד למדד המחירים לצרכן | J2: ישראל | K2: ישראל | L2: לא סחיר | M2: שירותים | N2: לא | O2: 45753 | P2: ilAAA | Q2: S&P מעלות | R2: נייר ערך | S2: ILS | T2: 5.37 | U2: 50034 | V2: 0.0256 | W2: 0.049 | X2: החוב לא נחות | Y2: ריק במקור | Z2: חברת ציטוט | AA2: אי-תלות | AB2: 46022 | AC2: ריק במקור | AD2: 3735417.2 | AE2: 1 | AF2: 163.76 | AG2: 6117.1192 | AH2: ריק במקור | AI2: ריק במקור | AJ2: שווי הוגן | AK2: 0.05785749 | AL2: 0.0014194606
A3: 13908 | B3: 13908 | C3: מקורות חברת מים בע"מ | D3: 520010869 | E3: ח.פ. | F3: מקורות אגח -8רמ | G3: IL0011243461 | H3: ISIN | I3: צמוד למדד המחירים לצרכן | J3: ישראל | K3: ישראל | L3: לא סחיר | M3: שירותים | N3: לא | O3: 45657 | P3: ilAAA | Q3: S&P מעלות | R3: נייר ערך | S3: ILS | T3: 9.27 | U3: 54253 | V3: 0.0282 | W3: 0.041 | X3: החוב לא נחות | Y3: ריק במקור | Z3: חברת ציטוט | AA3: אי-תלות | AB3: 46022 | AC3: ריק במקור | AD3: 353846.21 | AE3: 1 | AF3: 140.13 | AG3: 495.84469 | AH3: ריק במקור | AI3: ריק במקור | AJ3: שווי הוגן | AK3: 0.0046898431 | AL3: 0.00011505939
A4: 13908 | B4: 13908 | C4: מת"ם - מרכז תעשיות מדע חיפה בע | D4: 510687403 | E4: ח.פ. | F4: מת"ם אגח א -רמ | G4: IL0011389991 | H4: ISIN | I4: לא צמוד למדד המחירים לצרכן | J4: ישראל | K4: ישראל | L4: לא סחיר | M4: נדל"ן מניב בישראל | N4: לא | O4: 45657 | P4: Aa2.il | Q4: מידרוג Moodys | R4: נייר ערך | S4: ILS | T4: 0.98 | U4: 46568 | V4: 0.0464 | W4: 0.031 | X4: החוב לא נחות | Y4: ריק במקור | Z4: חברת ציטוט | AA4: אי-תלות | AB4: 46022 | AC4: ריק במקור | AD4: 1846153.9 | AE4: 1 | AF4: 96.3 | AG4: 1777.8462 | AH4: ריק במקור | AI4: ריק במקור | AJ4: שווי הוגן | AK4: 0.016815386 | AL4: 0.0004125443
A5: 13908 | B5: 13908 | C5: רפאל מערכות לחימה מתקדמות בע"מ | D5: 520042185 | E5: ח.פ. | F5: רפאל אגח ד-רמ | G5: IL0011402844 | H5: ISIN | I5: לא צמוד למדד המחירים לצרכן | J5: ישראל | K5: ישראל | L5: לא סחיר | M5: ביטחוניות | N5: לא | O5: 45657 | P5: Aaa.il | Q5: מידרוג Moodys | R5: נייר ערך | S5: ILS | T5: 4.18 | U5: 49202 | V5: 0.0501 | W5: 0.0374 | X5: החוב לא נחות | Y5: ריק במקור | Z5: חברת ציטוט | AA5: אי-תלות | AB5: 46022 | AC5: ריק במקור | AD5: 1595937.8 | AE5: 1 | AF5: 95.99 | AG5: 1531.9407 | AH5: ריק במקור | AI5: ריק במקור | AJ5: שווי הוגן | AK5: 0.01448954 | AL5: 0.0003554826
A6: 13908 | B6: 13908 | C6: אורמת טכנולוגיות, אינק | D6: 880326081 | E6: LEI | F6: אורמת אגח 4 -רמ | G6: IL0011672123 | H6: ISIN | I6: לא צמוד למדד המחירים לצרכן | J6: ישראל | K6: ארה"ב | L6: לא סחיר | M6: אנרגיה מתחדשת | N6: לא | O6: 45657 | P6: ilAA- | Q6: S&P מעלות | R6: נייר ערך | S6: ILS | T6: 2.75 | U6: 48014 | V6: 0.0594 | W6: 0.0335 | X6: החוב לא נחות | Y6: ריק במקור | Z6: חברת ציטוט | AA6: אי-תלות | AB6: 46022 | AC6: ריק במקור | AD6: 100000 | AE6: 1 | AF6: 92 | AG6: 92 | AH6: ריק במקור | AI6: ריק במקור | AJ6: שווי הוגן | AK6: 0.00087016272 | AL6: 2.1348346e-05
A7: 13908 | B7: 13908 | C7: רשות שדות התעופה בישראל. | D7: 500102868 | E7: ח.פ. | F7: רש"ת אגח א-רמ | G7: IL0011873358 | H7: ISIN | I7: צמוד למדד המחירים לצרכן | J7: ישראל | K7: ישראל | L7: לא סחיר | M7: שירותים | N7: לא | O7: 45657 | P7: Aaa.il | Q7: מידרוג Moodys | R7: נייר ערך | S7: ILS | T7: 3.45 | U7: 48213 | V7: 0.0258 | W7: 0.0155 | X7: החוב לא נחות | Y7: ריק במקור | Z7: חברת ציטוט | AA7: אי-תלות | AB7: 46022 | AC7: ריק במקור | AD7: 349762.4 | AE7: 1 | AF7: 101.4 | AG7: 354.65907 | AH7: ריק במקור | AI7: ריק במקור | AJ7: שווי הוגן | AK7: 0.0033544685 | AL7: 8.2297656e-05
A8: 13908 | B8: 13908 | C8: רשות שדות התעופה בישראל. | D8: 500102868 | E8: ח.פ. | F8: רש"ת אגח ב-רמ | G8: IL0011873432 | H8: ISIN | I8: צמוד למדד המחירים לצרכן | J8: ישראל | K8: ישראל | L8: לא סחיר | M8: שירותים | N8: לא | O8: 45657 | P8: Aaa.il | Q8: מידרוג Moodys | R8: נייר ערך | S8: ILS | T8: 6.37 | U8: 50040 | V8: 0.026 | W8: 0.0175 | X8: החוב לא נחות | Y8: ריק במקור | Z8: חברת ציטוט | AA8: אי-תלות | AB8: 46022 | AC8: ריק במקור | AD8: 2793368.3 | AE8: 1 | AF8: 106.5 | AG8: 2974.9372 | AH8: ריק במקור | AI8: ריק במקור | AJ8: שווי הוגן | AK8: 0.02813782 | AL8: 0.00069032596
A9: 13908 | B9: 13908 | C9: איילון חברה לביטוח בע"מ | D9: 520030677 | E9: ח.פ. | F9: איילון אגח ג-רמ | G9: IL0011955775 | H9: ISIN | I9: לא צמוד למדד המחירים לצרכן | J9: ישראל | K9: ישראל | L9: לא סחיר | M9: ביטוח | N9: לא | O9: 45657 | P9: A3.il | Q9: מידרוג Moodys | R9: נייר ערך | S9: ILS | T9: 1.89 | U9: 47848 | V9: 0.0726 | W9: 0.0775 | X9: החוב לא נחות | Y9: ריק במקור | Z9: חברת ציטוט | AA9: אי-תלות | AB9: 46022 | AC9: ריק במקור | AD9: 105000 | AE9: 1 | AF9: 105.18 | AG9: 110.439 | AH9: ריק במקור | AI9: ריק במקור | AJ9: שווי הוגן | AK9: 0.0010445641 | AL9: 2.5627065e-05
A10: 13908 | B10: 13908 | C10: עוגן-אג"ח חברתית 2 בע"מ (חל"צ) | D10: 516556545 | E10: ח.פ. | F10: עוגן אגחא-רמ | G10: IL0011968315 | H10: ISIN | I10: לא צמוד למדד המחירים לצרכן | J10: ישראל | K10: ישראל | L10: לא סחיר | M10: אשראי חוץ בנקאי | N10: לא | O10: 45657 | P10: Aa2.il | Q10: מידרוג Moodys | R10: נייר ערך | S10: ILS | T10: 0.2 | U10: 46096 | V10: 0.067 | W10: 0.065 | X10: החוב לא נחות | Y10: ריק במקור | Z10: חברת ציטוט | AA10: אי-תלות | AB10: 46022 | AC10: ריק במקור | AD10: 37005.84 | AE10: 1 | AF10: 100 | AG10: 37.00584 | AH10: ריק במקור | AI10: ריק במקור | AJ10: שווי הוגן | AK10: 0.00035001198 | AL10: 8.5871028e-06
A11: 13908 | B11: 13908 | C11: מקס איט פיננסים בע"מ | D11: 512905423 | E11: ח.פ. | F11: מקס איט הת ד-רמ | G11: IL0011979536 | H11: ISIN | I11: לא צמוד למדד המחירים לצרכן | J11: ישראל | K11: ישראל | L11: לא סחיר | M11: שירותים פיננסיים | N11: לא | O11: 45657 | P11: A1.il | Q11: מידרוג Moodys | R11: נייר ערך | S11: ILS | T11: 2.62 | U11: 47073 | V11: 0.0667 | W11: 0.0733 | X11: החוב לא נחות | Y11: ריק במקור | Z11: חברת ציטוט | AA11: אי-תלות | AB11: 46022 | AC11: ריק במקור | AD11: 300000 | AE11: 1 | AF11: 108.56 | AG11: 325.68 | AH11: ריק במקור | AI11: ריק במקור | AJ11: שווי הוגן | AK11: 0.003080376 | AL11: 7.5573143e-05
A12: 13908 | B12: 13908 | C12: בנק לאומי לישראל בע"מ | D12: 520018078 | E12: ח.פ. | F12: לאומי אגח 1 ר-מ | G12: IL0011986390 | H12: ISIN | I12: לא צמוד למדד המחירים לצרכן | J12: ישראל | K12: ישראל | L12: לא סחיר | M12: בנקים | N12: לא | O12: 45657 | P12: ilA- | Q12: S&P מעלות | R12: נייר ערך | S12: ILS | T12: 0.95 | U12: 46380 | V12: 0.0639 | W12: 0.068 | X12: החוב לא נחות | Y12: ריק במקור | Z12: חברת ציטוט | AA12: אי-תלות | AB12: 46022 | AC12: ריק במקור | AD12: 89023.47 | AE12: 1 | AF12: 100 | AG12: 89.02347 | AH12: ריק במקור | AI12: ריק במקור | AJ12: שווי הוגן | AK12: 0.00084200983 | AL12: 2.065765e-05
A13: 13908 | B13: 13908 | C13: אגד חברה לתחבורה בע"מ | D13: 516041118 | E13: ח.פ. | F13: אגד אגח -1רמ | G13: IL0011987877 | H13: ISIN | I13: צמוד למדד המחירים לצרכן | J13: ישראל | K13: ישראל | L13: לא סחיר | M13: שירותים | N13: לא | O13: 45657 | P13: ilAA- | Q13: S&P מעלות | R13: נייר ערך | S13: ILS | T13: 2.54 | U13: 47483 | V13: 0.0286 | W13: 0.0364 | X13: החוב לא נחות | Y13: ריק במקור | Z13: חברת ציטוט | AA13: אי-תלות | AB13: 46022 | AC13: ריק במקור | AD13: 1050000 | AE13: 1 | AF13: 109.72 | AG13: 1152.06 | AH13: ריק במקור | AI13: ריק במקור | AJ13: שווי הוגן | AK13: 0.010896518 | AL13: 0.00026733233
... A32: 13908 | B32: 13908 | C32: כלל תעשיות בע"מ | D32: 520021874 | E32: ח.פ. | F32: כלל תעשאג טז-רמ | G32: IL0060802381 | H32: ISIN | I32: לא צמוד למדד המחירים לצרכן | J32: ישראל | K32: ישראל | L32: לא סחיר | M32: השקעה ואחזקות | N32: לא | O32: 45657 | P32: A2.il | Q32: מידרוג Moodys | R32: נייר ערך | S32: ILS | T32: 1.34 | U32: 46568 | V32: 0.053 | W32: 0.0447 | X32: החוב לא נחות | Y32: ריק במקור | Z32: חברת ציטוט | AA32: אי-תלות | AB32: 46022 | AC32: ריק במקור | AD32: 3450000.8 | AE32: 1 | AF32: 101 | AG32: 3484.5008 | AH32: ריק במקור | AI32: ריק במקור | AJ32: שווי הוגן | AK32: 0.03295742 | AL32: 0.00080856877
A33: 13908 | B33: 13908 | C33: קבוצת נונו ניהול ואחזקות בע?מ | D33: 516481561 | E33: ח.פ. | F33: אגח להמרה נונו | G33: 11022551 | H33: פנימי | I33: אג"ח להמרה לא צמוד למדד | J33: ישראל | K33: ישראל | L33: לא סחיר | M33: מזון | N33: לא | O33: 46021 | P33: NR | Q33: NR | R33: NR | S33: ILS | T33: 7.992 | U33: 48939 | V33: 0.12 | W33: 0.12 | X33: החוב לא נחות | Y33: ריק במקור | Z33: חברת ציטוט | AA33: אי-תלות | AB33: 46022 | AC33: ריק במקור | AD33: 1730769.2 | AE33: 1 | AF33: 100 | AG33: 1730.7692 | AH33: ריק במקור | AI33: ריק במקור | AJ33: שווי הוגן | AK33: 0.016370118 | AL33: 0.00040162021
AZ10000: 1

Sheet לא סחיר מניות מבכ ויהש
A1: מספר קופה/קרן/ח.פ. עבור חברת ביטוח | B1: מספר מסלול | C1: שם מנפיק | D1: מספר מנפיק | E1: סוג מספר מזהה מנפיק | F1: שם נייר ערך | G1: מספר נייר ערך | H1: סוג מספר נייר ערך | I1: מאפיין עיקרי | J1: ישראל/חו"ל | K1: מדינה לפי חשיפה כלכלית | L1: סטאטוס סחירות | M1: ענף מסחר | N1: בעל עניין/צד קשור | O1: תאריך רכישה | P1: מטבע פעילות | Q1: סוג גורם משערך | R1: תלות/אי-תלות המשערך | S1: תאריך שערוך אחרון | T1: תאריך אחרון בו נבחנה בפועל ירידת ערך | U1: ערך נקוב (יחידות) | V1: שער חליפין | W1: שער נייר הערך | X1: שווי הוגן (באלפי ש"ח) | Y1: שיעור מנכסי אפיק ההשקעה | Z1: שיעור מסך נכסי ההשקעה
A2: 13908 | B2: 13908 | C2: HUMANZ | D2: 515599009 | E2: ח.פ. | F2: HUMANZ | G2: 11019400 | H2: פנימי | I2: מניות לא סחירות | J2: ישראל | K2: גרמניה | L2: לא סחיר | M2: תוכנה ואינטרנט | N2: לא | O2: 45657 | P2: USD | Q2: מומחה בלתי תלוי | R2: אי-תלות | S2: 46022 | T2: ריק במקור | U2: 617 | V2: 3.19 | W2: 8620 | X2: 169.66143 | Y2: 0.0056869127 | Z2: 3.9369466e-05
A3: 13908 | B3: 13908 | C3: CANDID | D3: 540300662 | E3: מספר שותפות | F3: CANDID 2 | G3: 11019989 | H3: פנימי | I3: מניות לא סחירות | J3: ישראל | K3: ארה"ב | L3: לא סחיר | M3: שירותים | N3: לא | O3: 45657 | P3: USD | Q3: דיווח מנהל הקרן | R3: אי-תלות | S3: 46022 | T3: ריק במקור | U3: 70928.24 | V3: 3.19 | W3: 122 | X3: 276.03852 | Y3: 0.009252586 | Z3: 6.4053975e-05
A4: 13908 | B4: 13908 | C4: CANDID | D4: 540300662 | E4: מספר שותפות | F4: CANDID 2 | G4: 11020458 | H4: פנימי | I4: מניות לא סחירות | J4: ישראל | K4: ארה"ב | L4: לא סחיר | M4: מכשור רפואי | N4: לא | O4: 45657 | P4: USD | Q4: דיווח מנהל הקרן | R4: אי-תלות | S4: 46022 | T4: ריק במקור | U4: 24318.29 | V4: 3.19 | W4: 122 | X4: 94.64192 | Y4: 0.00317232 | Z4: 2.1961396e-05
A5: 13908 | B5: 13908 | C5: קרדיט 360 | D5: 516491776 | E5: ח.פ. | F5: קרדיט 360 ל.ס | G5: 11021113 | H5: פנימי | I5: מניות לא סחירות | J5: ישראל | K5: ישראל | L5: לא סחיר | M5: שירותים פיננסיים | N5: לא | O5: 45657 | P5: ILS | Q5: מומחה בלתי תלוי | R5: אי-תלות | S5: 46022 | T5: ריק במקור | U5: 648150.94 | V5: 1 | W5: 167.27 | X5: 1084.1621 | Y5: 0.036340229 | Z5: 0.00025157681
A6: 13908 | B6: 13908 | C6: AGORA | D6: 515859049 | E6: ח.פ. | F6: AGORA ל.ס | G6: 11021257 | H6: פנימי | I6: מניות לא סחירות | J6: ישראל | K6: ארה"ב | L6: לא סחיר | M6: תוכנה ואינטרנט | N6: לא | O6: 45657 | P6: USD | Q6: דיווח מנהל הקרן | R6: אי-תלות | S6: 46022 | T6: ריק במקור | U6: 84186 | V6: 3.19 | W6: 671.13 | X6: 1802.342 | Y6: 0.060413035 | Z6: 0.00041822848
A7: 13908 | B7: 13908 | C7: HUMANZ LTD | D7: 515599009 | E7: ח.פ. | F7: HUMANZ SAFE | G7: 11021301 | H7: פנימי | I7: מניות לא סחירות | J7: ישראל | K7: ארה"ב | L7: לא סחיר | M7: השקעות בהיי-טק | N7: לא | O7: 45657 | P7: USD | Q7: דיווח מנהל הקרן | R7: אי-תלות | S7: 46022 | T7: ריק במקור | U7: 650000 | V7: 3.19 | W7: 100 | X7: 2073.5 | Y7: 0.069502029 | Z7: 0.00048114994
A8: 13908 | B8: 13908 | C8: Sunbit Inc | D8: 515446821 | E8: ח.פ. | F8: SUNBIT 3 | G8: 11021306 | H8: פנימי | I8: מניות לא סחירות | J8: ישראל | K8: ארה"ב | L8: לא סחיר | M8: שירותים פיננסיים | N8: לא | O8: 45657 | P8: USD | Q8: דיווח מנהל הקרן | R8: אי-תלות | S8: 46022 | T8: ריק במקור | U8: 300000 | V8: 3.19 | W8: 173.1427 | X8: 1656.9756 | Y8: 0.055540472 | Z8: 0.00038449661
A9: 13908 | B9: 13908 | C9: (KSP פי.אס.די.אס יזמות בע"מ (קבוצת | D9: 513591115 | E9: ח.פ. | F9: KSP פי אס די אס | G9: 11022486 | H9: פנימי | I9: מניות לא סחירות | J9: ישראל | K9: ישראל | L9: לא סחיר | M9: רשתות שיווק | N9: לא | O9: 45875 | P9: ILS | Q9: דיווח מנהל הקרן | R9: אי-תלות | S9: 46022 | T9: ריק במקור | U9: 9000000 | V9: 1 | W9: 100 | X9: 9000 | Y9: 0.30167266 | Z9: 0.0020884251
A10: 13908 | B10: 13908 | C10: לואן ווייז בע"מ | D10: 516961604 | E10: ח.פ. | F10: לואן ווייז | G10: 11022516 | H10: פנימי | I10: מניות לא סחירות | J10: ישראל | K10: ישראל | L10: לא סחיר | M10: שירותים פיננסיים | N10: לא | O10: 45897 | P10: ILS | Q10: דיווח מנהל הקרן | R10: אי-תלות | S10: 46022 | T10: ריק במקור | U10: 16293.33 | V10: 1 | W10: 14400 | X10: 2346.2395 | Y10: 0.078644035 | Z10: 0.00054443839
A11: 13908 | B11: 13908 | C11: קרדיט 360 בע"מ | D11: 516491776 | E11: ח.פ. | F11: קרדיט 360 | G11: 11022519 | H11: פנימי | I11: מניות לא סחירות | J11: ישראל | K11: ישראל | L11: לא סחיר | M11: שירותים פיננסיים | N11: לא | O11: 45930 | P11: ILS | Q11: דיווח מנהל הקרן | R11: אי-תלות | S11: 46022 | T11: ריק במקור | U11: 1825568.1 | V11: 1 | W11: 100 | X11: 1825.5681 | Y11: 0.061191554 | Z11: 0.00042361803
A12: 13908 | B12: 13908 | C12: CANDID | D12: 540300662 | E12: מספר שותפות | F12: CANDID 4 SAFE | G12: 11022827 | H12: פנימי | I12: מניות לא סחירות | J12: ישראל | K12: ארה"ב | L12: לא סחיר | M12: ביטוח | N12: לא | O12: 45853 | P12: USD | Q12: דיווח מנהל הקרן | R12: אי-תלות | S12: 46022 | T12: ריק במקור | U12: 15624.83 | V12: 3.19 | W12: 100 | X12: 49.84321 | Y12: 0.0016707037 | Z12: 1.1565979e-05
A13: 13908 | B13: 13908 | C13: UVEYE LTD | D13: 514234202 | E13: ח.פ. | F13: UVEYE - CLA | G13: 11022831 | H13: פנימי | I13: מניות לא סחירות | J13: ישראל | K13: ארה"ב | L13: לא סחיר | M13: תוכנה ואינטרנט | N13: לא | O13: 45880 | P13: USD | Q13: דיווח מנהל הקרן | R13: אי-תלות | S13: 46022 | T13: ריק במקור | U13: 362900 | V13: 3.19 | W13: 100 | X13: 1157.651 | Y13: 0.038803517 | Z13: 0.00026862971
A14: 13908 | B14: 13908 | C14: UVEYE | D14: 54254180 | E14: מספר תאגיד או שותפות בחו"ל | F14: UVEYE (PENSIA) | G14: 11019758 | H14: פנימי | I14: מניות לא סחירות | J14: חו"ל | K14: ארה"ב | L14: לא סחיר | M14: Software | N14: לא | O14: 45699 | P14: USD | Q14: דיווח מנהל הקרן | R14: אי-תלות | S14: 46022 | T14: ריק במקור | U14: 66260.84 | V14: 3.19 | W14: 1129 | X14: 2386.3908 | Y14: 0.079989872 | Z14: 0.00055375538
A15: 13908 | B15: 13908 | C15: Sauce Inc | D15: 549300JHLCR4 | E15: LEI | F15: SAUCE 1 | G15: 11021270 | H15: פנימי | I15: מניות לא סחירות | J15: חו"ל | K15: ארה"ב | L15: לא סחיר | M15: Technology Hardware, Storage & Peripherals | N15: לא | O15: 45657 | P15: USD | Q15: דיווח מנהל הקרן | R15: אי-תלות | S15: 46022 | T15: ריק במקור | U15: 900000 | V15: 3.19 | W15: 100 | X15: 2871 | Y15: 0.096233578 | Z15: 0.00066620761
A16: 13908 | B16: 13908 | C16: BitSight Technologies, Inc | D16: 20213498049 | E16: מספר תאגיד או שותפות בחו"ל | F16: BITSIGHT | G16: 11022807 | H16: פנימי | I16: מניות לא סחירות | J16: חו"ל | K16: ארה"ב | L16: לא סחיר | M16: Other | N16: לא | O16: 45775 | P16: USD | Q16: דיווח מנהל הקרן | R16: אי-תלות | S16: 46022 | T16: ריק במקור | U16: 1007 | V16: 3.19 | W16: 5250 | X16: 168.64732 | Y16: 0.0056529206 | Z16: 3.9134144e-05
A17: 13908 | B17: 13908 | C17: Seal Cybersecurity | D17: 7310928 | E17: מספר תאגיד או שותפות בחו"ל | F17: SEAL CYBER | G17: 11022824 | H17: פנימי | I17: מניות לא סחירות | J17: חו"ל | K17: ארה"ב | L17: לא סחיר | M17: Capital Markets | N17: לא | O17: 45806 | P17: USD | Q17: דיווח מנהל הקרן | R17: אי-תלות | S17: 46022 | T17: ריק במקור | U17: 1214083.4 | V17: 3.19 | W17: 74.13 | X17: 2871 | Y17: 0.096233577 | Z17: 0.0006662076
AZ10000: 1

Sheet קרנות השקעה
A1: מספר קופה/קרן/ח.פ. עבור חברת ביטוח | B1: מספר מסלול | C1: שם שותף כללי קרן השקעות | D1: מספר מזהה שותף כללי קרן השקעות | E1: סוג מספר מזהה שותף כללי קרן השקעות | F1: שם קרן השקעה | G1: מספר מזהה קרן השקעה | H1: סוג מספר מזהה קרן השקעות | I1: מאפיין עיקרי | J1: אסטרטגיית קרן ההשקעה | K1: ישראל/חו"ל | L1: מדינת התאגדות קרן השקעה | M1: מיקום משרד השותף הכללי | N1: מדינה לפי חשיפה כלכלית | O1: בעל עניין/צד קשור | P1: תאריך רכישה | Q1: מטבע פעילות | R1: סוג גורם משערך | S1: תלות/אי-תלות המשערך | T1: תאריך שערוך אחרון | U1: שער חליפין | V1: NAV (במטבע הדיווח של קרן ההשקעה) | W1: שווי הוגן (באלפי ש"ח) | X1: שיעור החזקה בקרן השקעה | Y1: שיעור מנכסי אפיק ההשקעה | Z1: שיעור מסך נכסי ההשקעה
A2: 13908 | B2: 13908 | C2: Scintilla Holdings Ltd | D2: ריק במקור | E2: ריק במקור | F2: SCINTILLA | G2: 11020474 | H2: פנימי | I2: קרן השקעה אחרת | J2: ריק במקור | K2: ישראל | L2: ריק במקור | M2: ריק במקור | N2: ישראל | O2: לא | P2: 45657 | Q2: USD | R2: דיווח מנהל הקרן | S2: אי-תלות | T2: 46022 | U2: 3.19 | V2: 714.74553 | W2: 2280.0382 | X2: 0 | Y2: 0.013511861 | Z2: 0.00052907657
A3: 13908 | B3: 13908 | C3: Viola Credit GL II (UVCI) | D3: ריק במקור | E3: ריק במקור | F3: VIOLA CREDIT UVCI | G3: 11020490 | H3: פנימי | I3: קרן השקעה אחרת | J3: ריק במקור | K3: ישראל | L3: ריק במקור | M3: ריק במקור | N3: ארה"ב | O3: לא | P3: 45657 | Q3: USD | R3: דיווח מנהל הקרן | S3: אי-תלות | T3: 46022 | U3: 3.19 | V3: 56.285621 | W3: 179.55113 | X3: 0 | Y3: 0.0010640479 | Z3: 4.1664343e-05
A4: 13908 | B4: 13908 | C4: קוגיטו קפיטל פאנד 2 ניהול בע"מ | D4: ריק במקור | E4: ריק במקור | F4: סיג'י השקעות | G4: 11021127 | H4: פנימי | I4: קרן חוב | J4: ריק במקור | K4: ישראל | L4: ריק במקור | M4: ריק במקור | N4: קנדה | O4: לא | P4: 45657 | Q4: ILS | R4: דיווח מנהל הקרן | S4: אי-תלות | T4: 46022 | U4: 1 | V4: 922.32436 | W4: 922.32436 | X4: 0 | Y4: 0.0054658373 | Z4: 0.00021402282
A5: 13908 | B5: 13908 | C5: Rakia Capital Fund, LP | D5: ריק במקור | E5: ריק במקור | F5: RS TACTIC GEAR | G5: 11021133 | H5: פנימי | I5: פרייבט אקוויטי | J5: ריק במקור | K5: ישראל | L5: ריק במקור | M5: ריק במקור | N5: Developed Markets - Pacific | O5: לא | P5: 45657 | Q5: ILS | R5: דיווח מנהל הקרן | S5: אי-תלות | T5: 46022 | U5: 1 | V5: 3914.7249 | W5: 3914.7249 | X5: 0 | Y5: 0.023199267 | Z5: 0.00090840108
A6: 13908 | B6: 13908 | C6: CERCA OPPORTUNITIES GP, LIMITED PARTNERSHIP | D6: ריק במקור | E6: ריק במקור | F6: CERCA גמל | G6: 11021279 | H6: פנימי | I6: קרן השקעה אחרת | J6: ריק במקור | K6: ישראל | L6: ריק במקור | M6: ריק במקור | N6: ישראל | O6: לא | P6: 45657 | Q6: USD | R6: דיווח מנהל הקרן | S6: אי-תלות | T6: 46022 | U6: 3.19 | V6: 243.02381 | W6: 775.24596 | X6: 0 | Y6: 0.0045942279 | Z6: 0.00017989368
A7: 13908 | B7: 13908 | C7: ג.ש.אחזקות אי.בי.סי בע"מ | D7: ריק במקור | E7: ריק במקור | F7: שותפות פייבר | G7: 11022492 | H7: פנימי | I7: קרן השקעה אחרת | J7: ריק במקור | K7: ישראל | L7: ריק במקור | M7: ריק במקור | N7: ישראל | O7: לא | P7: 45960 | Q7: ILS | R7: דיווח מנהל הקרן | S7: אי-תלות | T7: 46022 | U7: 1 | V7: 15112.498 | W7: 15112.498 | X7: 0 | Y7: 0.089559009 | Z7: 0.0035068134
A8: 13908 | B8: 13908 | C8: Green Lantern Management | D8: ריק במקור | E8: ריק במקור | F8: GREEN LANTERN | G8: 11022549 | H8: פנימי | I8: קרן השקעה אחרת | J8: ריק במקור | K8: ישראל | L8: ריק במקור | M8: ריק במקור | N8: ישראל | O8: לא | P8: 46019 | Q8: ILS | R8: דיווח מנהל הקרן | S8: אי-תלות | T8: 46022 | U8: 1 | V8: 4741.4829 | W8: 4741.4829 | X8: 0 | Y8: 0.028098764 | Z8: 0.001100248
A9: 13908 | B9: 13908 | C9: HIA Capital Partners Ltd | D9: ריק במקור | E9: ריק במקור | F9: SHARK TOPCO 1 | G9: 11022778 | H9: פנימי | I9: פרייבט אקוויטי | J9: ריק במקור | K9: ישראל | L9: ריק במקור | M9: ריק במקור | N9: ארה"ב | O9: לא | P9: 45673 | Q9: USD | R9: דיווח מנהל הקרן | S9: אי-תלות | T9: 46022 | U9: 3.19 | V9: 603.75 | W9: 1925.9625 | X9: 0 | Y9: 0.011413553 | Z9: 0.00044691427
A10: 13908 | B10: 13908 | C10: Red Dot III General Partner L.P. | D10: ריק במקור | E10: ריק במקור | F10: RED DOT 3 CAPITAL | G10: 11022812 | H10: פנימי | I10: קרן השקעה אחרת | J10: ריק במקור | K10: ישראל | L10: ריק במקור | M10: ריק במקור | N10: ישראל | O10: לא | P10: 45771 | Q10: USD | R10: דיווח מנהל הקרן | S10: אי-תלות | T10: 46022 | U10: 3.19 | V10: 793.3322 | W10: 2530.7297 | X10: 0 | Y10: 0.014997497 | Z10: 0.00058724883
A11: 13908 | B11: 13908 | C11: TBD VC GP LP | D11: ריק במקור | E11: ריק במקור | F11: TBD VC, L.P | G11: 11022813 | H11: פנימי | I11: קרן השקעה אחרת | J11: ריק במקור | K11: ישראל | L11: ריק במקור | M11: ריק במקור | N11: ישראל | O11: לא | P11: 45771 | Q11: USD | R11: דיווח מנהל הקרן | S11: אי-תלות | T11: 46022 | U11: 3.19 | V11: 49.70542 | W11: 158.56029 | X11: 0 | Y11: 0.00093965289 | Z11: 3.6793477e-05
A12: 13908 | B12: 13908 | C12: Cerca Capital 4 GP, Limited Partnership | D12: ריק במקור | E12: ריק במקור | F12: 4CECRA | G12: 11022819 | H12: פנימי | I12: פרייבט אקוויטי | J12: ריק במקור | K12: ישראל | L12: ריק במקור | M12: ריק במקור | N12: ישראל | O12: לא | P12: 45797 | Q12: USD | R12: דיווח מנהל הקרן | S12: אי-תלות | T12: 46022 | U12: 3.19 | V12: 35.391511 | W12: 112.89892 | X12: 0 | Y12: 0.00066905653 | Z12: 2.6197882e-05
A13: 13908 | B13: 13908 | C13: נבונא בע"מ | D13: ריק במקור | E13: ריק במקור | F13: ROM POP LP - AVATRADE | G13: 11022828 | H13: פנימי | I13: קרן השקעה אחרת | J13: ריק במקור | K13: ישראל | L13: ריק במקור | M13: ריק במקור | N13: ישראל | O13: לא | P13: 45868 | Q13: USD | R13: דיווח מנהל הקרן | S13: אי-תלות | T13: 46022 | U13: 3.19 | V13: 1100 | W13: 3509 | X13: 0 | Y13: 0.020794879 | Z13: 0.00081425375
... A52: 13908 | B52: 13908 | C52: Lindsay Goldberg | D52: ריק במקור | E52: ריק במקור | F52: LINDSAY GOLDBERG | G52: 11022859 | H52: פנימי | I52: קרן השקעה אחרת | J52: ריק במקור | K52: חו"ל | L52: ריק במקור | M52: ריק במקור | N52: ארה"ב | O52: לא | P52: 46015 | Q52: USD | R52: דיווח מנהל הקרן | S52: אי-תלות | T52: 46022 | U52: 3.19 | V52: 73.521799 | W52: 234.53454 | X52: 0 | Y52: 0.0013898881 | Z52: 5.4423091e-05
A53: 13908 | B53: 13908 | C53: 1L-MORE ALTERNATIVE CREDIT GP LTD | D53: ריק במקור | E53: ריק במקור | F53: 1L MORE ALT CR FD LP (E) USD S | G53: XD1493478915 | H53: פנימי | I53: קרן גידור (Hedge Fund) | J53: ריק במקור | K53: חו"ל | L53: ריק במקור | M53: ריק במקור | N53: ארה"ב | O53: כן | P53: 45963 | Q53: USD | R53: דיווח מנהל הקרן | S53: אי-תלות | T53: 46022 | U53: 3.19 | V53: 1258.3682 | W53: 4014.1945 | X53: 0 | Y53: 0.02378874 | Z53: 0.00093148274
A54: 13908 | B54: 13908 | C54: MORE Alternative Credit Fund | D54: ריק במקור | E54: ריק במקור | F54: MORE 8/23 | G54: XD1489193247 | H54: פנימי | I54: קרן גידור (Hedge Fund) | J54: ריק במקור | K54: חו"ל | L54: ריק במקור | M54: ריק במקור | N54: ישראל | O54: כן | P54: 45169 | Q54: USD | R54: דיווח מנהל הקרן | S54: אי-תלות | T54: 46022 | U54: 3.19 | V54: 174.72283 | W54: 557.36584 | X54: 0 | Y54: 0.0033030365 | Z54: 0.0001293352
A55: 13908 | B55: 13908 | C55: MORE Alternative Credit Fund | D55: ריק במקור | E55: ריק במקור | F55: MORE 2/23 | G55: XD1489193254 | H55: פנימי | I55: קרן גידור (Hedge Fund) | J55: ריק במקור | K55: חו"ל | L55: ריק במקור | M55: ריק במקור | N55: ישראל | O55: כן | P55: 44985 | Q55: USD | R55: דיווח מנהל הקרן | S55: אי-תלות | T55: 46022 | U55: 3.19 | V55: 327.19071 | W55: 1043.7384 | X55: 0 | Y55: 0.0061853556 | Z55: 0.0002421966
A56: 13908 | B56: 13908 | C56: MORE Alternative Credit Fund | D56: ריק במקור | E56: ריק במקור | F56: MORE 3/23 | G56: XD1489193262 | H56: פנימי | I56: קרן גידור (Hedge Fund) | J56: ריק במקור | K56: חו"ל | L56: ריק במקור | M56: ריק במקור | N56: ישראל | O56: כן | P56: 45016 | Q56: USD | R56: דיווח מנהל הקרן | S56: אי-תלות | T56: 46022 | U56: 3.19 | V56: 463.21192 | W56: 1477.646 | X56: 0 | Y56: 0.0087567598 | Z56: 0.00034288368
A57: 13908 | B57: 13908 | C57: MORE Alternative Credit Fund | D57: ריק במקור | E57: ריק במקור | F57: MORE 10/24 | G57: XD1489461263 | H57: פנימי | I57: קרן גידור (Hedge Fund) | J57: ריק במקור | K57: חו"ל | L57: ריק במקור | M57: ריק במקור | N57: ישראל | O57: כן | P57: 45596 | Q57: USD | R57: דיווח מנהל הקרן | S57: אי-תלות | T57: 46022 | U57: 3.19 | V57: 907.50102 | W57: 2894.9282 | X57: 0 | Y57: 0.017155794 | Z57: 0.00067176009
A58: 13908 | B58: 13908 | C58: MORE Alternative Credit Fund | D58: ריק במקור | E58: ריק במקור | F58: 1L MORE 11 | G58: XD1488921812 | H58: פנימי | I58: קרן גידור (Hedge Fund) | J58: ריק במקור | K58: חו"ל | L58: ריק במקור | M58: ריק במקור | N58: ישראל | O58: כן | P58: 45657 | Q58: ILS | R58: דיווח מנהל הקרן | S58: אי-תלות | T58: 46022 | U58: 1 | V58: 671.19821 | W58: 671.19821 | X58: 0 | Y58: 0.0039776248 | Z58: 0.00015574969
AZ10000: 1

Sheet לא סחיר כתבי אופציה
A1: מספר קופה/קרן/ח.פ. עבור חברת ביטוח | B1: מספר מסלול | C1: שם מנפיק | D1: מספר מנפיק | E1: סוג מספר מזהה מנפיק | F1: שם נייר ערך | G1: מספר נייר ערך | H1: סוג מספר נייר ערך | I1: ישראל/חו"ל | J1: מדינה לפי חשיפה כלכלית | K1: סטאטוס סחירות | L1: נכס בסיס (כתב אופציה) | M1: ענף מסחר | N1: תאריך פקיעה | O1: בעל עניין/צד קשור | P1: תאריך רכישה | Q1: מטבע פעילות | R1: סוג גורם משערך | S1: תלות/אי-תלות המשערך | T1: תאריך שערוך אחרון | U1: שער מימוש | V1: יחס המרה | W1: ערך נקוב (יחידות) | X1: שער נייר הערך | Y1: שער חליפין | Z1: שווי הוגן (באלפי ש"ח) | AA1: שיעור מנכסי אפיק ההשקעה | AB1: שיעור מסך נכסי ההשקעה
A2: 13908 | B2: 13908 | C2: מצלאוי חברה לבנין בע"מ | D2: 512726712 | E2: ח.פ. | F2: מצלאוי אופ ל.ס | G2: 11019773 | H2: פנימי | I2: ישראל | J2: ישראל | K2: לא סחיר | L2: IL0011067498 | M2: בנייה | N2: 46329 | O2: לא | P2: 45657 | Q2: ILS | R2: אחר | S2: אי-תלות | T2: 46022 | U2: 1004.64 | V2: 1 | W2: 100000 | X2: 9.1848 | Y2: 1 | Z2: 9.1848 | AA2: 0.0033055619 | AB2: 2.1313074e-06
A3: 13908 | B3: 13908 | C3: סולאיר אנרגיות מתחדשות בע"מ | D3: 516046307 | E3: ח.פ. | F3: סולאיר אופ ל.ס2 | G3: 11019939 | H3: פנימי | I3: ישראל | J3: ישראל | K3: לא סחיר | L3: IL0011722878 | M3: אנרגיה מתחדשת | N3: 46747 | O3: לא | P3: 45657 | Q3: ILS | R3: אחר | S3: אי-תלות | T3: 46022 | U3: 4560 | V3: 1 | W3: 52500 | X3: 1910.1293 | Y3: 1 | Z3: 1002.8179 | AA3: 0.36090896 | AB3: 0.00023270112
A4: 13908 | B4: 13908 | C4: רב-בריח(08) תעשיות בע"מ | D4: 514160530 | E4: ח.פ. | F4: רב בריח אופ ל.ס | G4: 11022283 | H4: פנימי | I4: ישראל | J4: ישראל | K4: לא סחיר | L4: IL0011799934 | M4: מתכת ומוצרי בניה | N4: 46947 | O4: לא | P4: 45851 | Q4: ILS | R4: אחר | S4: אי-תלות | T4: 46022 | U4: 130 | V4: 1 | W4: 303100 | X4: 36.3908 | Y4: 1 | Z4: 110.30051 | AA4: 0.039696582 | AB4: 2.5594928e-05
A5: 13908 | B5: 13908 | C5: קבוצת אקרו בע"מ | D5: 511996803 | E5: ח.פ. | F5: אקרו אופ ל.ס | G5: 11022448 | H5: פנימי | I5: ישראל | J5: ישראל | K5: לא סחיר | L5: IL0011849028 | M5: בנייה | N5: 46239 | O5: לא | P5: 45698 | Q5: ILS | R5: אחר | S5: אי-תלות | T5: 46022 | U5: 7000 | V5: 1 | W5: 6000 | X5: 74.3826 | Y5: 1 | Z5: 4.46296 | AA5: 0.0016061962 | AB5: 1.0356175e-06
A6: 13908 | B6: 13908 | C6: קבוצת גבאי קיקר | D6: 516316775 | E6: ח.פ. | F6: קבוצת גבאי קיקר | G6: 11022462 | H6: פנימי | I6: ישראל | J6: ישראל | K6: לא סחיר | L6: ריק במקור | M6: נדל"ן מניב בישראל | N6: 47664 | O6: לא | P6: 45746 | Q6: ILS | R6: אחר | S6: אי-תלות | T6: 46022 | U6: 10 | V6: 1 | W6: 310602.88 | X6: 100 | Y6: 1 | Z6: 310.60288 | AA6: 0.11178437 | AB6: 7.2074539e-05
A7: 13908 | B7: 13908 | C7: קרסו נדל"ן בע"מ | D7: 510488190 | E7: ח.פ. | F7: קרסו נדלן ל.ס | G7: 11022496 | H7: פנימי | I7: ישראל | J7: ישראל | K7: לא סחיר | L7: IL0011879629 | M7: בנייה | N7: 46202 | O7: לא | P7: 45837 | Q7: ILS | R7: אחר | S7: אי-תלות | T7: 46022 | U7: 4000 | V7: 1 | W7: 4000 | X7: 392.5603 | Y7: 1 | Z7: 15.70241 | AA7: 0.005651216 | AB7: 3.6437008e-06
A8: 13908 | B8: 13908 | C8: איסתא אופציה לס | D8: 513754812 | E8: ח.פ. | F8: איסתא אופציה לס | G8: 11022502 | H8: פנימי | I8: ישראל | J8: ישראל | K8: לא סחיר | L8: IL0010810740 | M8: מלונאות ותיירות | N8: 47309 | O8: לא | P8: 45853 | Q8: ILS | R8: אחר | S8: אי-תלות | T8: 46022 | U8: 16000 | V8: 1 | W8: 2965 | X8: 1919.6063 | Y8: 1 | Z8: 56.91633 | AA8: 0.020483892 | AB8: 1.3207277e-05
A9: 13908 | B9: 13908 | C9: פז קמעונאות ואנרגיה בע"מ | D9: 510216054 | E9: ח.פ. | F9: פז נפט אופ ל.ס | G9: 11022509 | H9: פנימי | I9: ישראל | J9: ישראל | K9: לא סחיר | L9: IL0011000077 | M9: אנרגיה | N9: 46053 | O9: לא | P9: 45866 | Q9: ILS | R9: אחר | S9: אי-תלות | T9: 46022 | U9: 67000 | V9: 0.111 | W9: 3132 | X9: 5308.6919 | Y9: 1 | Z9: 166.26823 | AA9: 0.059839075 | AB9: 3.8582083e-05
A10: 13908 | B10: 13908 | C10: ג'נריישן קפיטל בע"מ | D10: 515846558 | E10: ח.פ. | F10: גנרשן קפ אפ לס | G10: 11022534 | H10: פנימי | I10: ישראל | J10: ישראל | K10: לא סחיר | L10: IL0011569261 | M10: השקעה ואחזקות | N10: 47141 | O10: לא | P10: 45953 | Q10: ILS | R10: אחר | S10: אי-תלות | T10: 46022 | U10: 140 | V10: 1 | W10: 2000000 | X10: 34.5178 | Y10: 1 | Z10: 690.356 | AA10: 0.24845555 | AB10: 0.0001601952
A11: 13908 | B11: 13908 | C11: הכשרת הישוב מקבוצת נמרודי בע"מ | D11: 520020116 | E11: ח.פ. | F11: הכשרת ישוב אופ | G11: 11022539 | H11: פנימי | I11: ישראל | J11: ישראל | K11: לא סחיר | L11: IL0006120104 | M11: פארמה | N11: 46508 | O11: לא | P11: 45970 | Q11: ILS | R11: אחר | S11: אי-תלות | T11: 46022 | U11: 5000 | V11: 1 | W11: 22500 | X11: 408.573 | Y11: 1 | Z11: 91.92892 | AA11: 0.033084742 | AB11: 2.1331852e-05
A12: 13908 | B12: 13908 | C12: CANDID 2 WARRANTS | D12: 70390929 | E12: מספר תאגיד או שותפות בחו"ל | F12: CANDID 2 WARRANTS | G12: 11019990 | H12: פנימי | I12: חו"ל | J12: ארה"ב | K12: לא סחיר | L12: BBG01PNPZ3H9 | M12: Pharmaceuticals | N12: 47788 | O12: לא | P12: 45657 | Q12: USD | R12: אחר | S12: אי-תלות | T12: 46022 | U12: 0.001 | V12: 1 | W12: 82236.67 | X12: 122 | Y12: 3.19 | Z12: 320.04867 | AA12: 0.11518386 | AB12: 7.4266409e-05
AZ10000: 1

Sheet לא סחיר אופציות
A1: מספר קופה/קרן/ח.פ. עבור חברת ביטוח | B1: מספר מסלול | C1: שם מנפיק | D1: מספר מנפיק | E1: סוג מספר מזהה מנפיק | F1: שם נייר ערך | G1: מספר נייר ערך | H1: סוג מספר נייר ערך | I1: מאפיין עיקרי | J1: ישראל/חו"ל | K1: מדינה לפי חשיפה כלכלית | L1: ענף מסחר | M1: נכס בסיס | N1: תאריך פקיעה | O1: בעל עניין/צד קשור | P1: תאריך רכישה | Q1: מטבע פעילות | R1: סוג גורם משערך | S1: תלות/אי-תלות המשערך | T1: תאריך שערוך אחרון | U1: שער מימוש | V1: יחס המרה | W1: ערך נקוב (יחידות) | X1: שער נייר הערך | Y1: שער חליפין | Z1: שווי הוגן (בש"ח) | AA1: שיעור מנכסי אפיק ההשקעה | AB1: שיעור מסך נכסי ההשקעה

Sheet לא סחיר נגזרים אחרים
A1: מספר קופה/קרן/ח.פ. עבור חברת ביטוח | B1: מספר מסלול | C1: מאפיין עיקרי | D1: מספר עסקה (רגל 1) | E1: מטבע פעילות (רגל 1) | F1: שער חליפין | G1: ערך נקוב (רגל 1) | H1: שווי הוגן במטבע הנסחר (רגל 1) | I1: שיעור מנכסי אפיק ההשקעה (רגל 1) | J1: שיעור מסך נכסי ההשקעה (רגל 1) | K1: מספר עסקה (רגל 2) | L1: מטבע פעילות (רגל 2) | M1: שער חליפין2 | N1: ערך נקוב (רגל 2) | O1: שווי הוגן במטבע הנסחר (רגל 2) | P1: שיעור מנכסי ההשקעה (רגל 2) | Q1: שיעור מסך אפיק ההשקעה (רגל 2) | R1: שווי הוגן (נטו באלפי ש"ח) | S1: ישראל/חו"ל | T1: מדינה לפי חשיפה כלכלית | U1: סוג הנכס | V1: פקטור מוביל | W1: פקטור נוסף | X1: טיקר | Y1: בעל עניין/צד קשור | Z1: מועד ההתקשרות בעסקה | AA1: מועד סיום חוזי | AB1: תדירות Reset | AC1: סוג הסליקה | AD1: נספח התחשבנות בטחונות - CSA | AE1: גורם מצטט | AF1: ריבית עוגן | AG1: תקופת ריבית עוגן | AH1: שיעור ריבית עוגן | AI1: שער נכס הבסיס במועד ההתקשרות בעסקה | AJ1: שער הנגזר במועד ההתקשרות בעסקה | AK1: האם קיים קנס בגין יציאה מוקדמת | AL1: שיעור הקנס בגין יציאה מוקדמת | AM1: צד נגדי - Counterparty | AN1: שיעור מנכסי אפיק ההשקעה | AO1: שיעור מסך נכסי ההשקעה
A2: 13908 | B2: 13908 | C2: Unfunded Total Return/Equity Swap | D2: MIZ EQ.SW 1 P | E2: USD | F2: 3.69 | G2: -38970 | H2: -3149.6555 | I2: 0.10410148 | J2: -0.002696906 | K2: MIZ EQ.SW 1 R | L2: USD | M2: 3.69 | N2: 38970 | O2: 3142.1511 | P2: 0.0026904804 | Q2: 0.03182738 | R2: -23.93896 | S2: ישראל | T2: ארה"ב | U2: ריבית ואג"ח | V2: אחר | W2: ריביות | X2: HYGUS | Y2: לא | Z2: 45762 | AA2: 46122 | AB2: רבעוני | AC2: No-delivery | AD2: לא | AE2: הצד הנגדי | AF2: SOFR | AG2: רבעוני | AH2: ריק במקור | AI2: 7733 | AJ2: ריק במקור | AK2: ריק במקור | AL2: ריק במקור | AM2: MIZBILIT | AN2: -0.0046459307 | AO2: -5.5549695e-06
A3: 13908 | B3: 13908 | C3: Unfunded Forward | D3: 502295 | E3: USD | F3: 3.647 | G3: -2760000 | H3: -3034.5491 | I3: 0.0010029702 | J3: -0.0025680668 | K3: 502295 | L3: ILS | M3: 1 | N3: 10065720 | O3: 10065.72 | P3: 0.0023357225 | Q3: 0.10195738 | R3: 385.50852 | S3: ישראל | T3: ישראל | U3: מט"ח | V3: אחר | W3: מט"ח/₪ | X3: ILSUSD | Y3: לא | Z3: 45657 | AA3: 47083 | AB3: ללא | AC3: Delivery | AD3: לא | AE3: הצד הנגדי | AF3: ללא | AG3: ללא | AH3: ריק במקור | AI3: 3.647 | AJ3: ריק במקור | AK3: ריק במקור | AL3: ריק במקור | AM3: MIZBILIT | AN3: 0.074817197 | AO3: 8.9456186e-05
A4: 13908 | B4: 13908 | C4: Unfunded Forward | D4: 502296 | E4: EUR | F4: 3.7964 | G4: -2370000 | H4: -2282.8849 | I4: 0.00075453236 | J4: -0.002011094 | K4: 502296 | L4: ILS | M4: 1 | N4: 8997468 | O4: 8997.468 | P4: 0.0020878376 | Q4: 0.091136876 | R4: 446.92275 | S4: ישראל | T4: ישראל | U4: מט"ח | V4: אחר | W4: מט"ח/₪ | X4: ILSEUR | Y4: לא | Z4: 45657 | AA4: 47083 | AB4: ללא | AC4: Delivery | AD4: לא | AE4: הצד הנגדי | AF4: ללא | AG4: ללא | AH4: ריק במקור | AI4: 3.7964 | AJ4: ריק במקור | AK4: ריק במקור | AL4: ריק במקור | AM4: MIZBILIT | AN4: 0.086736105 | AO4: 0.00010370719
A5: 13908 | B5: 13908 | C5: Unfunded Forward | D5: 903776 | E5: USD | F5: 3.366 | G5: -2800000 | H5: -2815.5369 | I5: 0.00093058294 | J5: -0.0021991342 | K5: 903776 | L5: ILS | M5: 1 | N5: 9424800 | O5: 9424.8 | P5: 0.0021869988 | Q5: 0.095465395 | R5: 443.23726 | S5: ישראל | T5: ישראל | U5: מט"ח | V5: אחר | W5: מט"ח/₪ | X5: ILSUSD | Y5: לא | Z5: 45868 | AA5: 46233 | AB5: ללא | AC5: Delivery | AD5: לא | AE5: הצד הנגדי | AF5: ללא | AG5: ללא | AH5: ריק במקור | AI5: 3.366 | AJ5: ריק במקור | AK5: ריק במקור | AL5: ריק במקור | AM5: FIRBILIT | AN5: 0.086020847 | AO5: 0.00010285198
A6: 13908 | B6: 13908 | C6: Unfunded Forward | D6: 903784 | E6: EUR | F6: 3.8825 | G6: -2400000 | H6: -2384.6842 | I6: 0.00078817876 | J6: -0.0021484177 | K6: 903784 | L6: ILS | M6: 1 | N6: 9318000 | O6: 9318 | P6: 0.0021622161 | Q6: 0.094383599 | R6: 386.16545 | S6: ישראל | T6: ישראל | U6: מט"ח | V6: אחר | W6: מט"ח/₪ | X6: ILSEUR | Y6: לא | Z6: 45868 | AA6: 46233 | AB6: ללא | AC6: Delivery | AD6: לא | AE6: הצד הנגדי | AF6: ללא | AG6: ללא | AH6: ריק במקור | AI6: 3.8825 | AJ6: ריק במקור | AK6: ריק במקור | AL6: ריק במקור | AM6: FIRBILIT | AN6: 0.07494469 | AO6: 8.9608625e-05
A7: 13908 | B7: 13908 | C7: Unfunded Forward | D7: 502297 | E7: USD | F7: 3.354 | G7: -2750000 | H7: -2744.4009 | I7: 0.00090707126 | J7: -0.0021359299 | K7: 502297 | L7: ILS | M7: 1 | N7: 9223500 | O7: 9223.5 | P7: 0.0021402877 | Q7: 0.093426393 | R7: 468.86125 | S7: ישראל | T7: ישראל | U7: מט"ח | V7: אחר | W7: מט"ח/₪ | X7: USDILS | Y7: לא | Z7: 45860 | AA7: 46238 | AB7: ללא | AC7: Delivery | AD7: לא | AE7: הצד הנגדי | AF7: ללא | AG7: ללא | AH7: ריק במקור | AI7: 3.354 | AJ7: ריק במקור | AK7: ריק במקור | AL7: ריק במקור | AM7: MIZBILIT | AN7: 0.090993798 | AO7: 0.00010879796
A8: 13908 | B8: 13908 | C8: Unfunded Forward | D8: 502298 | E8: EUR | F8: 3.9261 | G8: -2400000 | H8: -2421.4882 | I8: 0.00080034312 | J8: -0.0022060742 | K8: 502298 | L8: ILS | M8: 1 | N8: 9422640 | O8: 9422.64 | P8: 0.0021864976 | Q8: 0.095443516 | R8: 352.956 | S8: ישראל | T8: ישראל | U8: מט"ח | V8: אחר | W8: מט"ח/₪ | X8: EURILS | Y8: לא | Z8: 45860 | AA8: 46238 | AB8: ללא | AC8: Delivery | AD8: לא | AE8: הצד הנגדי | AF8: ללא | AG8: ללא | AH8: ריק במקור | AI8: 3.9261 | AJ8: ריק במקור | AK8: ריק במקור | AL8: ריק במקור | AM8: MIZBILIT | AN8: 0.068499598 | AO8: 8.1902464e-05
A9: 13908 | B9: 13908 | C9: Unfunded Forward | D9: 961365 | E9: USD | F9: 3.448 | G9: -5700000 | H9: -5725.9916 | I9: 0.0018925378 | J9: -0.0045813594 | K9: 961365 | L9: ILS | M9: 1 | N9: 19653600 | O9: 19653.6 | P9: 0.0045605635 | Q9: 0.19907464 | R9: 1387.6869 | S9: ישראל | T9: ישראל | U9: מט"ח | V9: אחר | W9: מט"ח/₪ | X9: USDILS | Y9: לא | Z9: 45875 | AA9: 46149 | AB9: ללא | AC9: Delivery | AD9: לא | AE9: הצד הנגדי | AF9: ללא | AG9: ללא | AH9: ריק במקור | AI9: 3.448 | AJ9: ריק במקור | AK9: ריק במקור | AL9: ריק במקור | AM9: FIRBILIT | AN9: 0.269314 | AO9: 0.0003220089
A10: 13908 | B10: 13908 | C10: Unfunded Forward | D10: 975548 | E10: USD | F10: 3.417 | G10: -5700000 | H10: -5696.4347 | I10: 0.0018827687 | J10: -0.0045167338 | K10: 975548 | L10: ILS | M10: 1 | N10: 19476900 | O10: 19476.9 | P10: 0.0045195608 | Q10: 0.19728482 | R10: 1305.2734 | S10: ישראל | T10: ישראל | U10: מט"ח | V10: אחר | W10: מט"ח/₪ | X10: USDILS | Y10: לא | Z10: 45876 | AA10: 46244 | AB10: ללא | AC10: Delivery | AD10: לא | AE10: הצד הנגדי | AF10: ללא | AG10: ללא | AH10: ריק במקור | AI10: 3.417 | AJ10: ריק במקור | AK10: ריק במקור | AL10: ריק במקור | AM10: FIRBILIT | AN10: 0.25331969 | AO10: 0.00030288509
AZ10000: 1

Sheet הלוואות
A1: מספר קופה/קרן/ח.פ. עבור חברת ביטוח | B1: מספר מסלול | C1: מספר מזהה לווה | D1: סוג מספר מזהה לווה | E1: שם הלוואה | F1: מספר הלוואה | G1: מאפיין עיקרי | H1: מאפיין הלוואות מתואמות עבור זכויות מקרקעין | I1: ישראל/חו"ל | J1: מדינה לפי חשיפה כלכלית | K1: ענף מסחר | L1: בעל עניין/צד קשור | M1: קונסורציום/ סינדיקציה | N1: מספר קונסורציום/ סינדיקציה | O1: תאריך העמדת הלוואה | P1: דירוג | Q1: שם מדרג | R1: דירוג הלוואה/המנפיק | S1: מטבע פעילות | T1: מח"מ | U1: סוג הריבית | V1: שיעור ריבית | W1: סוג הצמדה | X1: ריבית עוגן | Y1: שיעור תוספת/הפחתה לריבית העוגן | Z1: תשואה לפדיון | AA1: מועד פדיון | AB1: נחיתות חוזית | AC1: סוג בטוחה | AD1: שווי הבטוחות העומדות כנגד ההלוואה | AE1: שיעור הבטוחות מהחוב | AF1: מועד עדכון אחרון לשווי הבטוחות | AG1: זכות חזרה | AH1: מבנה לוח סילוקין | AI1: יעוד הלוואה | AJ1: זכות פירעון מוקדם | AK1: סוג גורם משערך | AL1: שם גורם משערך | AM1: תלות/אי-תלות המשערך | AN1: תאריך שערוך אחרון | AO1: תאריך אחרון בו נבחנה בפועל ירידת ערך | AP1: שיעור ריבית בגין אי-ניצול מסגרת האשראי | AQ1: ערך נקוב | AR1: שער הלוואה | AS1: שער חליפין | AT1: שווי הוגן (באלפי ש"ח) | AU1: שווי הוגן (במטבע הפעילות) | AV1: עלות מופחתת (באלפי ש"ח) | AW1: עלות מופחתת (במטבע הפעילות) | AX1: האם סווג כחוב בעייתי | AY1: השיטה שיושמה בדוח הכספי | AZ1: שיעור מנכסי אפיק ההשקעה | BA1: שיעור מסך נכסי ההשקעה
A2: 13908 | B2: 13908 | C2: ריק במקור | D2: ריק במקור | E2: הלוואה 1 | F2: 11020447 | G2: תאגיד | H2: פעילות שוטפת של התאגיד - מגורים (כולל דיור מוגן) | I2: ישראל | J2: ריק במקור | K2: נדל"ן מניב בישראל | L2: לא | M2: לא | N2: ריק במקור | O2: 45657 | P2: NR | Q2: NR | R2: NR | S2: ILS | T2: 1.11 | U2: קבועה | V2: 0.11 | W2: ריק במקור | X2: ריק במקור | Y2: ריק במקור | Z2: 0.0732 | AA2: 46445 | AB2: החוב נחות | AC2: ריק במקור | AD2: ריק במקור | AE2: ריק במקור | AF2: 45473 | AG2: ריק במקור | AH2: ריק במקור | AI2: ריק במקור | AJ2: כן | AK2: חברת ציטוט | AL2: ריק במקור | AM2: אי-תלות | AN2: 46022 | AO2: 46022 | AP2: ריק במקור | AQ2: 1190994.4 | AR2: 104.32 | AS2: 1 | AT2: 1242.4454 | AU2: 1242.4454 | AV2: ריק במקור | AW2: ריק במקור | AX2: ריק במקור | AY2: שווי הוגן | AZ2: 0.024872151 | BA2: 0.00028830602
A3: 13908 | B3: 13908 | C3: ריק במקור | D3: ריק במקור | E3: הלוואה 2 | F3: 11020451 | G3: תאגיד | H3: פעילות שוטפת של התאגיד - מגורים (כולל דיור מוגן) | I3: ישראל | J3: ריק במקור | K3: נדל"ן מניב בישראל | L3: לא | M3: לא | N3: ריק במקור | O3: 45657 | P3: NR | Q3: NR | R3: NR | S3: ILS | T3: 1.11 | U3: קבועה | V3: 0.11 | W3: ריק במקור | X3: ריק במקור | Y3: ריק במקור | Z3: 0.0837 | AA3: 46445 | AB3: החוב נחות | AC3: ריק במקור | AD3: ריק במקור | AE3: ריק במקור | AF3: 45473 | AG3: ריק במקור | AH3: ריק במקור | AI3: ריק במקור | AJ3: כן | AK3: חברת ציטוט | AL3: ריק במקור | AM3: אי-תלות | AN3: 46022 | AO3: 46022 | AP3: ריק במקור | AQ3: 2056307.7 | AR3: 103.2 | AS3: 1 | AT3: 2122.1095 | AU3: 2122.1095 | AV3: ריק במקור | AW3: ריק במקור | AX3: ריק במקור | AY3: שווי הוגן | AZ3: 0.04248189 | BA3: 0.00049242965
A4: 13908 | B4: 13908 | C4: ריק במקור | D4: ריק במקור | E4: הלוואה 3 | F4: 11021112 | G4: תאגיד | H4: ריק במקור | I4: ישראל | J4: ריק במקור | K4: שירותים פיננסיים | L4: לא | M4: לא | N4: ריק במקור | O4: 45657 | P4: NR | Q4: NR | R4: NR | S4: ILS | T4: 1.63 | U4: משתנה | V4: 0.107 | W4: ריק במקור | X4: ריק במקור | Y4: ריק במקור | Z4: 0.1425 | AA4: 47223 | AB4: החוב נחות | AC4: ריק במקור | AD4: ריק במקור | AE4: ריק במקור | AF4: ריק במקור | AG4: ריק במקור | AH4: ריק במקור | AI4: ריק במקור | AJ4: כן | AK4: חברת ציטוט | AL4: ריק במקור | AM4: אי-תלות | AN4: 46022 | AO4: 46022 | AP4: ריק במקור | AQ4: 1400000 | AR4: 102.41 | AS4: 1 | AT4: 1433.74 | AU4: 1433.74 | AV4: ריק במקור | AW4: ריק במקור | AX4: ריק במקור | AY4: שווי הוגן | AZ4: 0.028701622 | BA4: 0.0003326954
A5: 13908 | B5: 13908 | C5: ריק במקור | D5: ריק במקור | E5: הלוואה 4 | F5: 11021116 | G5: תאגיד | H5: פעילות שוטפת של התאגיד - מגורים (כולל דיור מוגן) | I5: ישראל | J5: ריק במקור | K5: נדל"ן מניב בישראל | L5: לא | M5: לא | N5: ריק במקור | O5: 45657 | P5: NR | Q5: NR | R5: NR | S5: ILS | T5: 1.1 | U5: קבועה | V5: 0.11 | W5: ריק במקור | X5: ריק במקור | Y5: ריק במקור | Z5: 0.1268 | AA5: 46445 | AB5: החוב נחות | AC5: ריק במקור | AD5: ריק במקור | AE5: ריק במקור | AF5: 45473 | AG5: ריק במקור | AH5: ריק במקור | AI5: ריק במקור | AJ5: כן | AK5: חברת ציטוט | AL5: ריק במקור | AM5: אי-תלות | AN5: 46022 | AO5: 46022 | AP5: ריק במקור | AQ5: 1003076.9 | AR5: 98.82 | AS5: 1 | AT5: 991.24061 | AU5: 991.24061 | AV5: ריק במקור | AW5: ריק במקור | AX5: ריק במקור | AY5: שווי הוגן | AZ5: 0.019843356 | BA5: 0.00023001464
A6: 13908 | B6: 13908 | C6: ריק במקור | D6: ריק במקור | E6: הלוואה 5 | F6: 11021122 | G6: תאגיד | H6: ייזום נדל"ן לבניה של נכס ספציפי - מגורים (כולל דיור מוגן) | I6: ישראל | J6: ריק במקור | K6: בנייה | L6: לא | M6: לא | N6: ריק במקור | O6: 45657 | P6: NR | Q6: NR | R6: NR | S6: ILS | T6: 2.22 | U6: קבועה | V6: 0.1085 | W6: ריק במקור | X6: ריק במקור | Y6: ריק במקור | Z6: 0.1432 | AA6: 46935 | AB6: החוב נחות | AC6: ריק במקור | AD6: ריק במקור | AE6: ריק במקור | AF6: 45443 | AG6: ריק במקור | AH6: ריק במקור | AI6: ריק במקור | AJ6: כן | AK6: חברת ציטוט | AL6: ריק במקור | AM6: אי-תלות | AN6: 46022 | AO6: 46022 | AP6: ריק במקור | AQ6: 1227272.7 | AR6: 102.72 | AS6: 1 | AT6: 1260.6545 | AU6: 1260.6545 | AV6: ריק במקור | AW6: ריק במקור | AX6: ריק במקור | AY6: שווי הוגן | AZ6: 0.025236675 | BA6: 0.0002925314
A7: 13908 | B7: 13908 | C7: ריק במקור | D7: ריק במקור | E7: הלוואה 6 | F7: 11021130 | G7: תאגיד | H7: ייזום נדל"ן לבניה של נכס ספציפי - מגורים (כולל דיור מוגן) | I7: ישראל | J7: ריק במקור | K7: בנייה | L7: לא | M7: לא | N7: ריק במקור | O7: 45657 | P7: NR | Q7: NR | R7: NR | S7: ILS | T7: 1.49 | U7: קבועה | V7: 0.0925 | W7: ריק במקור | X7: ריק במקור | Y7: ריק במקור | Z7: 0.0967 | AA7: 46599 | AB7: החוב נחות | AC7: ריק במקור | AD7: ריק במקור | AE7: ריק במקור | AF7: 45493 | AG7: ריק במקור | AH7: ריק במקור | AI7: ריק במקור | AJ7: כן | AK7: חברת ציטוט | AL7: ריק במקור | AM7: אי-תלות | AN7: 46022 | AO7: 46022 | AP7: ריק במקור | AQ7: 3078571 | AR7: 99.92 | AS7: 1 | AT7: 3076.1081 | AU7: 3076.1081 | AV7: ריק במקור | AW7: ריק במקור | AX7: ריק במקור | AY7: שווי הוגן | AZ7: 0.061579709 | BA7: 0.00071380239
A8: 13908 | B8: 13908 | C8: ריק במקור | D8: ריק במקור | E8: הלוואה 7 | F8: 11021131 | G8: תאגיד | H8: ריק במקור | I8: ישראל | J8: ריק במקור | K8: שירותים פיננסיים | L8: לא | M8: לא | N8: ריק במקור | O8: 45657 | P8: NR | Q8: NR | R8: NR | S8: ILS | T8: 1.62 | U8: משתנה | V8: 0.107 | W8: ריק במקור | X8: ריק במקור | Y8: ריק במקור | Z8: 0.045 | AA8: 47223 | AB8: החוב נחות | AC8: ריק במקור | AD8: ריק במקור | AE8: ריק במקור | AF8: ריק במקור | AG8: ריק במקור | AH8: ריק במקור | AI8: ריק במקור | AJ8: כן | AK8: חברת ציטוט | AL8: ריק במקור | AM8: אי-תלות | AN8: 46022 | AO8: 46022 | AP8: ריק במקור | AQ8: 1400000 | AR8: 102.24 | AS8: 1 | AT8: 1431.36 | AU8: 1431.36 | AV8: ריק במקור | AW8: ריק במקור | AX8: ריק במקור | AY8: שווי הוגן | AZ8: 0.028653977 | BA8: 0.00033214313
A9: 13908 | B9: 13908 | C9: ריק במקור | D9: ריק במקור | E9: הלוואה 8 | F9: 11022433 | G9: תאגיד | H9: פעילות שוטפת של התאגיד - מגורים (כולל דיור מוגן) | I9: ישראל | J9: ריק במקור | K9: נדל"ן מניב בישראל | L9: לא | M9: לא | N9: ריק במקור | O9: 45657 | P9: NR | Q9: NR | R9: NR | S9: ILS | T9: 1.1 | U9: קבועה | V9: 0.11 | W9: ריק במקור | X9: ריק במקור | Y9: ריק במקור | Z9: 0.1464 | AA9: 46445 | AB9: החוב נחות | AC9: ריק במקור | AD9: ריק במקור | AE9: ריק במקור | AF9: 45473 | AG9: ריק במקור | AH9: ריק במקור | AI9: ריק במקור | AJ9: כן | AK9: חברת ציטוט | AL9: ריק במקור | AM9: אי-תלות | AN9: 46022 | AO9: 46022 | AP9: ריק במקור | AQ9: 1504615.4 | AR9: 96.95 | AS9: 1 | AT9: 1458.7246 | AU9: 1458.7246 | AV9: ריק במקור | AW9: ריק במקור | AX9: ריק במקור | AY9: שווי הוגן | AZ9: 0.029201781 | BA9: 0.00033849301
A10: 13908 | B10: 13908 | C10: ריק במקור | D10: ריק במקור | E10: הלוואה 9 | F10: 11022434 | G10: תאגיד | H10: פעילות שוטפת של התאגיד - מגורים (כולל דיור מוגן) | I10: ישראל | J10: ריק במקור | K10: בנייה | L10: לא | M10: לא | N10: ריק במקור | O10: 45657 | P10: NR | Q10: NR | R10: NR | S10: ILS | T10: 1.49 | U10: קבועה | V10: 0.0925 | W10: ריק במקור | X10: ריק במקור | Y10: ריק במקור | Z10: 0.1219 | AA10: 46599 | AB10: החוב נחות | AC10: ריק במקור | AD10: ריק במקור | AE10: ריק במקור | AF10: 45493 | AG10: ריק במקור | AH10: ריק במקור | AI10: ריק במקור | AJ10: כן | AK10: חברת ציטוט | AL10: ריק במקור | AM10: אי-תלות | AN10: 46022 | AO10: 46022 | AP10: ריק במקור | AQ10: 1231429 | AR10: 96.6 | AS10: 1 | AT10: 1189.5604 | AU10: 1189.5604 | AV10: ריק במקור | AW10: ריק במקור | AX10: ריק במקור | AY10: שווי הוגן | AZ10: 0.023813462 | BA10: 0.0002760342
A11: 13908 | B11: 13908 | C11: ריק במקור | D11: ריק במקור | E11: הלוואה 10 | F11: 11022435 | G11: תאגיד | H11: קרקעות - מגורים (כולל דיור מוגן) | I11: ישראל | J11: ריק במקור | K11: בנייה | L11: לא | M11: לא | N11: ריק במקור | O11: 45665 | P11: NR | Q11: NR | R11: NR | S11: ILS | T11: 3.42 | U11: קבועה | V11: 0.038 | W11: ריק במקור | X11: ריק במקור | Y11: ריק במקור | Z11: 0.0755 | AA11: 47664 | AB11: החוב לא נחות | AC11: ריק במקור | AD11: ריק במקור | AE11: ריק במקור | AF11: ריק במקור | AG11: ריק במקור | AH11: ריק במקור | AI11: ריק במקור | AJ11: לא | AK11: חברת ציטוט | AL11: ריק במקור | AM11: אי-תלות | AN11: 46022 | AO11: 46022 | AP11: ריק במקור | AQ11: 74343.09 | AR11: 99.59 | AS11: 1 | AT11: 74.03828 | AU11: 74.03828 | AV11: ריק במקור | AW11: ריק במקור | AX11: ריק במקור | AY11: שווי הוגן | AZ11: 0.0014821507 | BA11: 1.7180378e-05
A12: 13908 | B12: 13908 | C12: ריק במקור | D12: ריק במקור | E12: הלוואה 11 | F12: 11022442 | G12: תאגיד | H12: פעילות שוטפת של התאגיד - מגורים (כולל דיור מוגן) | I12: ישראל | J12: ריק במקור | K12: נדל"ן מניב בישראל | L12: לא | M12: לא | N12: ריק במקור | O12: 45685 | P12: NR | Q12: NR | R12: NR | S12: ILS | T12: 1.1 | U12: קבועה | V12: 0.11 | W12: ריק במקור | X12: ריק במקור | Y12: ריק במקור | Z12: 0.1756 | AA12: 46446 | AB12: החוב נחות | AC12: ריק במקור | AD12: ריק במקור | AE12: ריק במקור | AF12: 45473 | AG12: ריק במקור | AH12: ריק במקור | AI12: ריק במקור | AJ12: כן | AK12: חברת ציטוט | AL12: ריק במקור | AM12: אי-תלות | AN12: 46022 | AO12: 46022 | AP12: ריק במקור | AQ12: 200615.38 | AR12: 94.3 | AS12: 1 | AT12: 189.1803 | AU12: 189.1803 | AV12: ריק במקור | AW12: ריק במקור | AX12: ריק במקור | AY12: שווי הוגן | AZ12: 0.0037871451 | BA12: 4.3898765e-05
A13: 13908 | B13: 13908 | C13: ריק במקור | D13: ריק במקור | E13: הלוואה 12 | F13: 11022458 | G13: תאגיד | H13: ריק במקור | I13: ישראל | J13: ריק במקור | K13: נדל"ן מניב בישראל | L13: לא | M13: לא | N13: ריק במקור | O13: 45739 | P13: NR | Q13: NR | R13: NR | S13: ILS | T13: 2.02 | U13: קבועה | V13: 0.1 | W13: ריק במקור | X13: ריק במקור | Y13: ריק במקור | Z13: 0.1316 | AA13: 46835 | AB13: החוב לא נחות | AC13: ריק במקור | AD13: ריק במקור | AE13: ריק במקור | AF13: ריק במקור | AG13: ריק במקור | AH13: ריק במקור | AI13: ריק במקור | AJ13: כן | AK13: אחר | AL13: ריק במקור | AM13: אי-תלות | AN13: 46022 | AO13: 46022 | AP13: ריק במקור | AQ13: 6250000 | AR13: 95.1 | AS13: 1 | AT13: 5943.75 | AU13: 5943.75 | AV13: ריק במקור | AW13: ריק במקור | AX13: ריק במקור | AY13: שווי הוגן | AZ13: 0.11898619 | BA13: 0.0013792307
A14: 13908 | B14: 13908 | C14: ריק במקור | D14: ריק במקור | E14: הלוואה 13 | F14: 11022460 | G14: תאגיד | H14: קרקעות - מגורים (כולל דיור מוגן) | I14: ישראל | J14: ריק במקור | K14: בנייה | L14: לא | M14: לא | N14: ריק במקור | O14: 45741 | P14: NR | Q14: NR | R14: NR | S14: ILS | T14: 3.42 | U14: קבועה | V14: 0.09 | W14: ריק במקור | X14: ריק במקור | Y14: ריק במקור | Z14: 0.1091 | AA14: 47664 | AB14: החוב לא נחות | AC14: ריק במקור | AD14: ריק במקור | AE14: ריק במקור | AF14: ריק במקור | AG14: ריק במקור | AH14: ריק במקור | AI14: ריק במקור | AJ14: לא | AK14: חברת ציטוט | AL14: ריק במקור | AM14: אי-תלות | AN14: 46022 | AO14: 46022 | AP14: ריק במקור | AQ14: 530769.23 | AR14: 100.7 | AS14: 1 | AT14: 534.48461 | AU14: 534.48461 | AV14: ריק במקור | AW14: ריק במקור | AX14: ריק במקור | AY14: שווי הוגן | AZ14: 0.010699691 | BA14: 0.00012402568
A15: 13908 | B15: 13908 | C15: ריק במקור | D15: ריק במקור | E15: הלוואה 14 | F15: 11022466 | G15: תאגיד | H15: ריק במקור | I15: ישראל | J15: ריק במקור | K15: אנרגיה | L15: לא | M15: לא | N15: ריק במקור | O15: 45748 | P15: NR | Q15: NR | R15: NR | S15: ILS | T15: 3.42 | U15: משתנה | V15: 0 | W15: ריק במקור | X15: ריק במקור | Y15: ריק במקור | Z15: 0.021 | AA15: 46026 | AB15: החוב לא נחות | AC15: ריק במקור | AD15: ריק במקור | AE15: ריק במקור | AF15: ריק במקור | AG15: ריק במקור | AH15: ריק במקור | AI15: ריק במקור | AJ15: כן | AK15: אחר | AL15: ריק במקור | AM15: אי-תלות | AN15: 46022 | AO15: 46022 | AP15: ריק במקור | AQ15: 2957142.9 | AR15: 95.44 | AS15: 1 | AT15: 2822.2971 | AU15: 2822.2971 | AV15: ריק במקור | AW15: ריק במקור | AX15: ריק במקור | AY15: שווי הוגן | AZ15: 0.056498741 | BA15: 0.00065490625
A16: 13908 | B16: 13908 | C16: ריק במקור | D16: ריק במקור | E16: הלוואה 15 | F16: 11022468 | G16: תאגיד | H16: ריק במקור | I16: ישראל | J16: ריק במקור | K16: שירותים פיננסיים | L16: לא | M16: לא | N16: ריק במקור | O16: 45755 | P16: NR | Q16: NR | R16: NR | S16: ILS | T16: 2.48 | U16: משתנה | V16: 0.101 | W16: ריק במקור | X16: ריק במקור | Y16: ריק במקור | Z16: 0.1229 | AA16: 47580 | AB16: החוב נחות | AC16: ריק במקור | AD16: ריק במקור | AE16: ריק במקור | AF16: ריק במקור | AG16: ריק במקור | AH16: ריק במקור | AI16: ריק במקור | AJ16: כן | AK16: חברת ציטוט | AL16: ריק במקור | AM16: אי-תלות | AN16: 46022 | AO16: 46022 | AP16: ריק במקור | AQ16: 1400000 | AR16: 96.06 | AS16: 1 | AT16: 1344.84 | AU16: 1344.84 | AV16: ריק במקור | AW16: ריק במקור | AX16: ריק במקור | AY16: שווי הוגן | AZ16: 0.026921959 | BA16: 0.0003120664
A17: 13908 | B17: 13908 | C17: ריק במקור | D17: ריק במקור | E17: הלוואה 16 | F17: 11022473 | G17: תאגיד | H17: קרקעות - מגורים (כולל דיור מוגן) | I17: ישראל | J17: ריק במקור | K17: בנייה | L17: לא | M17: לא | N17: ריק במקור | O17: 45781 | P17: NR | Q17: NR | R17: NR | S17: ILS | T17: 3.42 | U17: קבועה | V17: 0.09 | W17: ריק במקור | X17: ריק במקור | Y17: ריק במקור | Z17: 0.0994 | AA17: 47664 | AB17: החוב לא נחות | AC17: ריק במקור | AD17: ריק במקור | AE17: ריק במקור | AF17: ריק במקור | AG17: ריק במקור | AH17: ריק במקור | AI17: ריק במקור | AJ17: לא | AK17: חברת ציטוט | AL17: ריק במקור | AM17: אי-תלות | AN17: 46022 | AO17: 46022 | AP17: ריק במקור | AQ17: 815665.03 | AR17: 102.79 | AS17: 1 | AT17: 838.42208 | AU17: 838.42208 | AV17: ריק במקור | AW17: ריק במקור | AX17: ריק במקור | AY17: שווי הוגן | AZ17: 0.016784126 | BA17: 0.00019455352
A18: 13908 | B18: 13908 | C18: ריק במקור | D18: ריק במקור | E18: הלוואה 17 | F18: 11022481 | G18: תאגיד | H18: ייזום נדל"ן לבניה של נכס ספציפי - מגורים (כולל דיור מוגן) | I18: ישראל | J18: ריק במקור | K18: בנייה | L18: לא | M18: לא | N18: ריק במקור | O18: 45803 | P18: NR | Q18: NR | R18: NR | S18: ILS | T18: 2.23 | U18: קבועה | V18: 0.1085 | W18: ריק במקור | X18: ריק במקור | Y18: ריק במקור | Z18: 0.0997 | AA18: 46990 | AB18: החוב נחות | AC18: ריק במקור | AD18: ריק במקור | AE18: ריק במקור | AF18: 45443 | AG18: ריק במקור | AH18: ריק במקור | AI18: ריק במקור | AJ18: כן | AK18: חברת ציטוט | AL18: ריק במקור | AM18: אי-תלות | AN18: 46022 | AO18: 46022 | AP18: ריק במקור | AQ18: 1227272.7 | AR18: 94.24 | AS18: 1 | AT18: 1156.5818 | AU18: 1156.5818 | AV18: ריק במקור | AW18: ריק במקור | AX18: ריק במקור | AY18: שווי הוגן | AZ18: 0.023153273 | BA18: 0.00026838161
A19: 13908 | B19: 13908 | C19: ריק במקור | D19: ריק במקור | E19: הלוואה 18 | F19: 11022535 | G19: תאגיד | H19: ריק במקור | I19: ישראל | J19: ריק במקור | K19: שירותים פיננסיים | L19: לא | M19: לא | N19: ריק במקור | O19: 45959 | P19: NR | Q19: NR | R19: NR | S19: ILS | T19: 8.71 | U19: משתנה | V19: 0.09 | W19: ריק במקור | X19: ריק במקור | Y19: ריק במקור | Z19: 0.1203 | AA19: 47788 | AB19: החוב נחות | AC19: ריק במקור | AD19: ריק במקור | AE19: ריק במקור | AF19: ריק במקור | AG19: ריק במקור | AH19: ריק במקור | AI19: ריק במקור | AJ19: כן | AK19: חברת ציטוט | AL19: ריק במקור | AM19: אי-תלות | AN19: 46022 | AO19: 46022 | AP19: ריק במקור | AQ19: 3400000 | AR19: 109.48 | AS19: 1 | AT19: 3722.32 | AU19: 3722.32 | AV19: ריק במקור | AW19: ריק במקור | AX19: ריק במקור | AY19: שווי הוגן | AZ19: 0.074516035 | BA19: 0.00086375406
A20: 13908 | B20: 13908 | C20: ריק במקור | D20: ריק במקור | E20: הלוואה 19 | F20: 11022536 | G20: תאגיד | H20: פעילות שוטפת של התאגיד - מגורים (כולל דיור מוגן) | I20: ישראל | J20: ריק במקור | K20: בנייה | L20: לא | M20: לא | N20: ריק במקור | O20: 45960 | P20: NR | Q20: NR | R20: NR | S20: ILS | T20: 2.33 | U20: קבועה | V20: 0 | W20: ריק במקור | X20: ריק במקור | Y20: ריק במקור | Z20: 0.1665 | AA20: 47056 | AB20: החוב לא נחות | AC20: ריק במקור | AD20: ריק במקור | AE20: ריק במקור | AF20: ריק במקור | AG20: ריק במקור | AH20: ריק במקור | AI20: ריק במקור | AJ20: כן | AK20: חברת ציטוט | AL20: ריק במקור | AM20: אי-תלות | AN20: 46022 | AO20: 46022 | AP20: ריק במקור | AQ20: 4000000 | AR20: 96.98 | AS20: 1 | AT20: 3879.2 | AU20: 3879.2 | AV20: ריק במקור | AW20: ריק במקור | AX20: ריק במקור | AY20: שווי הוגן | AZ20: 0.07765657 | BA20: 0.00090015763
A21: 13908 | B21: 13908 | C21: ריק במקור | D21: ריק במקור | E21: הלוואה 20 | F21: 11022540 | G21: תאגיד | H21: ריק במקור | I21: ישראל | J21: ריק במקור | K21: שירותים פיננסיים | L21: לא | M21: לא | N21: ריק במקור | O21: 45971 | P21: NR | Q21: NR | R21: NR | S21: ILS | T21: 2.48 | U21: משתנה | V21: 0.107 | W21: ריק במקור | X21: ריק במקור | Y21: ריק במקור | Z21: 0.1229 | AA21: 47580 | AB21: החוב נחות | AC21: ריק במקור | AD21: ריק במקור | AE21: ריק במקור | AF21: ריק במקור | AG21: ריק במקור | AH21: ריק במקור | AI21: ריק במקור | AJ21: כן | AK21: חברת ציטוט | AL21: ריק במקור | AM21: אי-תלות | AN21: 46022 | AO21: 46022 | AP21: ריק במקור | AQ21: 1400000 | AR21: 96.74 | AS21: 1 | AT21: 1354.36 | AU21: 1354.36 | AV21: ריק במקור | AW21: ריק במקור | AX21: ריק במקור | AY21: שווי הוגן | AZ21: 0.027112537 | BA21: 0.00031427549
A22: 13908 | B22: 13908 | C22: ריק במקור | D22: ריק במקור | E22: הלוואה 21 | F22: 11022552 | G22: תאגיד | H22: ריק במקור | I22: ישראל | J22: ריק במקור | K22: בנייה | L22: לא | M22: לא | N22: ריק במקור | O22: 46021 | P22: NR | Q22: NR | R22: NR | S22: ILS | T22: 7.99 | U22: קבועה | V22: 0.12 | W22: ריק במקור | X22: ריק במקור | Y22: ריק במקור | Z22: 0.122 | AA22: 48939 | AB22: החוב לא נחות | AC22: ריק במקור | AD22: ריק במקור | AE22: ריק במקור | AF22: 46022 | AG22: ריק במקור | AH22: ריק במקור | AI22: ריק במקור | AJ22: לא | AK22: חברת ציטוט | AL22: ריק במקור | AM22: אי-תלות | AN22: 46022 | AO22: 46022 | AP22: ריק במקור | AQ22: 769230.77 | AR22: 100.11 | AS22: 1 | AT22: 770.07692 | AU22: 770.07692 | AV22: ריק במקור | AW22: ריק במקור | AX22: ריק במקור | AY22: שווי הוגן | AZ22: 0.015415945 | BA22: 0.00017869422
A23: 13908 | B23: 13908 | C23: ריק במקור | D23: ריק במקור | E23: הלוואה 22 | F23: 11022808 | G23: תאגיד | H23: ריק במקור | I23: ישראל | J23: ריק במקור | K23: שירותים פיננסיים | L23: לא | M23: לא | N23: ריק במקור | O23: 45750 | P23: NR | Q23: NR | R23: NR | S23: USD | T23: 2.19 | U23: משתנה | V23: 0.0525 | W23: ריק במקור | X23: ריק במקור | Y23: ריק במקור | Z23: 0.0424 | AA23: 46990 | AB23: החוב לא נחות | AC23: ריק במקור | AD23: ריק במקור | AE23: ריק במקור | AF23: ריק במקור | AG23: ריק במקור | AH23: ריק במקור | AI23: ריק במקור | AJ23: כן | AK23: חברת ציטוט | AL23: ריק במקור | AM23: אי-תלות | AN23: 46022 | AO23: 46022 | AP23: ריק במקור | AQ23: 901944.04 | AR23: 100.08 | AS23: 3.19 | AT23: 2879.5033 | AU23: 902.6656 | AV23: ריק במקור | AW23: ריק במקור | AX23: ריק במקור | AY23: שווי הוגן | AZ23: 0.057643933 | BA23: 0.00066818077
A24: 13908 | B24: 13908 | C24: ריק במקור | D24: ריק במקור | E24: הלוואה 23 | F24: 11021291 | G24: תאגיד | H24: אשראי אחר בענף הנדל"ן (לרבות אשראי לכל מטרה) - אחר/לא מסווג | I24: חו"ל | J24: ריק במקור | K24: Consumer Finance | L24: לא | M24: לא | N24: ריק במקור | O24: 45657 | P24: A1.il | Q24: מידרוג Moodys | R24: מנפיק | S24: USD | T24: 1.61 | U24: משתנה | V24: 0.0496 | W24: ריק במקור | X24: ריק במקור | Y24: ריק במקור | Z24: 0.1142 | AA24: 46660 | AB24: החוב נחות | AC24: ריק במקור | AD24: ריק במקור | AE24: ריק במקור | AF24: ריק במקור | AG24: ריק במקור | AH24: ריק במקור | AI24: ריק במקור | AJ24: כן | AK24: חברת ציטוט | AL24: ריק במקור | AM24: אי-תלות | AN24: 46022 | AO24: 46022 | AP24: ריק במקור | AQ24: 1620000 | AR24: 100.8 | AS24: 3.19 | AT24: 5209.1424 | AU24: 1632.96 | AV24: ריק במקור | AW24: ריק במקור | AX24: ריק במקור | AY24: שווי הוגן | AZ24: 0.1042803 | BA24: 0.0012087671
A25: 13908 | B25: 13908 | C25: ריק במקור | D25: ריק במקור | E25: הלוואה 24 | F25: 11022780 | G25: תאגיד | H25: ריק במקור | I25: חו"ל | J25: ריק במקור | K25: Energy Equipment & Services | L25: לא | M25: כן | N25: ריק במקור | O25: 45685 | P25: ilA- | Q25: S&P מעלות | R25: מנפיק | S25: USD | T25: 1.61 | U25: משתנה | V25: 0.0968 | W25: ריק במקור | X25: ריק במקור | Y25: ריק במקור | Z25: 0.0778 | AA25: 46990 | AB25: החוב לא נחות | AC25: ריק במקור | AD25: ריק במקור | AE25: ריק במקור | AF25: 45108 | AG25: ריק במקור | AH25: ריק במקור | AI25: ריק במקור | AJ25: כן | AK25: חברת ציטוט | AL25: ריק במקור | AM25: אי-תלות | AN25: 46022 | AO25: 46022 | AP25: ריק במקור | AQ25: 240992.76 | AR25: 99.86 | AS25: 3.19 | AT25: 767.69063 | AU25: 240.65537 | AV25: ריק במקור | AW25: ריק במקור | AX25: ריק במקור | AY25: שווי הוגן | AZ25: 0.015368174 | BA25: 0.00017814049
A26: 13908 | B26: 13908 | C26: ריק במקור | D26: ריק במקור | E26: הלוואה 25 | F26: 11022782 | G26: תאגיד | H26: ריק במקור | I26: חו"ל | J26: ריק במקור | K26: Energy Equipment & Services | L26: לא | M26: כן | N26: ריק במקור | O26: 45685 | P26: ilA- | Q26: S&P מעלות | R26: מנפיק | S26: USD | T26: 1.6 | U26: משתנה | V26: 0.0969 | W26: ריק במקור | X26: ריק במקור | Y26: ריק במקור | Z26: 0.088 | AA26: 46990 | AB26: החוב לא נחות | AC26: ריק במקור | AD26: ריק במקור | AE26: ריק במקור | AF26: 45108 | AG26: ריק במקור | AH26: ריק במקור | AI26: ריק במקור | AJ26: כן | AK26: חברת ציטוט | AL26: ריק במקור | AM26: אי-תלות | AN26: 46022 | AO26: 46022 | AP26: ריק במקור | AQ26: 158101.14 | AR26: 98.55 | AS26: 3.19 | AT26: 497.02967 | AU26: 155.80867 | AV26: ריק במקור | AW26: ריק במקור | AX26: ריק במקור | AY26: שווי הוגן | AZ26: 0.0099498915 | BA26: 0.00011533436
A27: 13908 | B27: 13908 | C27: ריק במקור | D27: ריק במקור | E27: הלוואה 26 | F27: 11022788 | G27: תאגיד | H27: ריק במקור | I27: חו"ל | J27: ריק במקור | K27: Energy Equipment & Services | L27: לא | M27: כן | N27: ריק במקור | O27: 45713 | P27: ilA- | Q27: S&P מעלות | R27: מנפיק | S27: USD | T27: 1.6 | U27: משתנה | V27: 0.0969 | W27: ריק במקור | X27: ריק במקור | Y27: ריק במקור | Z27: 0.088 | AA27: 46990 | AB27: החוב לא נחות | AC27: ריק במקור | AD27: ריק במקור | AE27: ריק במקור | AF27: 45108 | AG27: ריק במקור | AH27: ריק במקור | AI27: ריק במקור | AJ27: כן | AK27: חברת ציטוט | AL27: ריק במקור | AM27: אי-תלות | AN27: 46022 | AO27: 46022 | AP27: ריק במקור | AQ27: 154482.85 | AR27: 98.55 | AS27: 3.19 | AT27: 485.65469 | AU27: 152.24285 | AV27: ריק במקור | AW27: ריק במקור | AX27: ריק במקור | AY27: שווי הוגן | AZ27: 0.0097221792 | BA27: 0.00011269483
A28: 13908 | B28: 13908 | C28: ריק במקור | D28: ריק במקור | E28: הלוואה 27 | F28: 11022790 | G28: תאגיד | H28: ריק במקור | I28: חו"ל | J28: ריק במקור | K28: Energy Equipment & Services | L28: לא | M28: כן | N28: ריק במקור | O28: 45713 | P28: ilA- | Q28: S&P מעלות | R28: מנפיק | S28: USD | T28: 1.61 | U28: משתנה | V28: 0.0968 | W28: ריק במקור | X28: ריק במקור | Y28: ריק במקור | Z28: 0.0778 | AA28: 46990 | AB28: החוב לא נחות | AC28: ריק במקור | AD28: ריק במקור | AE28: ריק במקור | AF28: 45108 | AG28: ריק במקור | AH28: ריק במקור | AI28: ריק במקור | AJ28: כן | AK28: חברת ציטוט | AL28: ריק במקור | AM28: אי-תלות | AN28: 46022 | AO28: 46022 | AP28: ריק במקור | AQ28: 318839.04 | AR28: 99.86 | AS28: 3.19 | AT28: 1015.6726 | AU28: 318.39266 | AV28: ריק במקור | AW28: ריק במקור | AX28: ריק במקור | AY28: שווי הוגן | AZ28: 0.020332453 | BA28: 0.00023568402
A29: 13908 | B29: 13908 | C29: ריק במקור | D29: ריק במקור | E29: הלוואה 28 | F29: 11022801 | G29: תאגיד | H29: ריק במקור | I29: חו"ל | J29: ריק במקור | K29: Energy Equipment & Services | L29: לא | M29: כן | N29: ריק במקור | O29: 45741 | P29: ilA- | Q29: S&P מעלות | R29: מנפיק | S29: USD | T29: 1.61 | U29: משתנה | V29: 0.0968 | W29: ריק במקור | X29: ריק במקור | Y29: ריק במקור | Z29: 0.0778 | AA29: 46990 | AB29: החוב לא נחות | AC29: ריק במקור | AD29: ריק במקור | AE29: ריק במקור | AF29: 45108 | AG29: ריק במקור | AH29: ריק במקור | AI29: ריק במקור | AJ29: כן | AK29: חברת ציטוט | AL29: ריק במקור | AM29: אי-תלות | AN29: 46022 | AO29: 46022 | AP29: ריק במקור | AQ29: 244724.89 | AR29: 99.86 | AS29: 3.19 | AT29: 779.57946 | AU29: 244.38228 | AV29: ריק במקור | AW29: ריק במקור | AX29: ריק במקור | AY29: שווי הוגן | AZ29: 0.015606173 | BA29: 0.00018089926
A30: 13908 | B30: 13908 | C30: ריק במקור | D30: ריק במקור | E30: הלוואה 29 | F30: 11022805 | G30: תאגיד | H30: ריק במקור | I30: חו"ל | J30: ריק במקור | K30: Energy Equipment & Services | L30: לא | M30: כן | N30: ריק במקור | O30: 45743 | P30: ilA- | Q30: S&P מעלות | R30: מנפיק | S30: USD | T30: 1.6 | U30: משתנה | V30: 0.0969 | W30: ריק במקור | X30: ריק במקור | Y30: ריק במקור | Z30: 0.088 | AA30: 46990 | AB30: החוב לא נחות | AC30: ריק במקור | AD30: ריק במקור | AE30: ריק במקור | AF30: 45108 | AG30: ריק במקור | AH30: ריק במקור | AI30: ריק במקור | AJ30: כן | AK30: חברת ציטוט | AL30: ריק במקור | AM30: אי-תלות | AN30: 46022 | AO30: 46022 | AP30: ריק במקור | AQ30: 126662.36 | AR30: 98.55 | AS30: 3.19 | AT30: 398.19416 | AU30: 124.82576 | AV30: ריק במקור | AW30: ריק במקור | AX30: ריק במקור | AY30: שווי הוגן | AZ30: 0.0079713324 | BA30: 9.2399854e-05
A31: 13908 | B31: 13908 | C31: ריק במקור | D31: ריק במקור | E31: הלוואה 30 | F31: 11022815 | G31: תאגיד | H31: ריק במקור | I31: חו"ל | J31: ריק במקור | K31: Energy Equipment & Services | L31: לא | M31: כן | N31: ריק במקור | O31: 45775 | P31: ilA- | Q31: S&P מעלות | R31: מנפיק | S31: USD | T31: 1.6 | U31: משתנה | V31: 0.09686 | W31: ריק במקור | X31: ריק במקור | Y31: ריק במקור | Z31: 0.088 | AA31: 46990 | AB31: החוב לא נחות | AC31: ריק במקור | AD31: ריק במקור | AE31: ריק במקור | AF31: 45108 | AG31: ריק במקור | AH31: ריק במקור | AI31: ריק במקור | AJ31: כן | AK31: חברת ציטוט | AL31: ריק במקור | AM31: אי-תלות | AN31: 46022 | AO31: 46022 | AP31: ריק במקור | AQ31: 70558.77 | AR31: 98.55 | AS31: 3.19 | AT31: 221.81878 | AU31: 69.535668 | AV31: ריק במקור | AW31: ריק במקור | AX31: ריק במקור | AY31: שווי הוגן | AZ31: 0.0044405253 | BA31: 5.1472434e-05
A32: 13908 | B32: 13908 | C32: ריק במקור | D32: ריק במקור | E32: הלוואה 31 | F32: 11022816 | G32: תאגיד | H32: ריק במקור | I32: חו"ל | J32: ריק במקור | K32: Energy Equipment & Services | L32: לא | M32: כן | N32: ריק במקור | O32: 45775 | P32: ilA- | Q32: S&P מעלות | R32: מנפיק | S32: USD | T32: 1.61 | U32: משתנה | V32: 0.09686 | W32: ריק במקור | X32: ריק במקור | Y32: ריק במקור | Z32: 0.0778 | AA32: 46990 | AB32: החוב לא נחות | AC32: ריק במקור | AD32: ריק במקור | AE32: ריק במקור | AF32: 45108 | AG32: ריק במקור | AH32: ריק במקור | AI32: ריק במקור | AJ32: כן | AK32: חברת ציטוט | AL32: ריק במקור | AM32: אי-תלות | AN32: 46022 | AO32: 46022 | AP32: ריק במקור | AQ32: 208377.97 | AR32: 99.86 | AS32: 3.19 | AT32: 663.79511 | AU32: 208.08624 | AV32: ריק במקור | AW32: ריק במקור | AX32: ריק במקור | AY32: שווי הוגן | AZ32: 0.01328832 | BA32: 0.00015403182
A33: 13908 | B33: 13908 | C33: ריק במקור | D33: ריק במקור | E33: הלוואה 32 | F33: 11022822 | G33: תאגיד | H33: ריק במקור | I33: חו"ל | J33: ריק במקור | K33: Energy Equipment & Services | L33: לא | M33: כן | N33: ריק במקור | O33: 45804 | P33: ilA- | Q33: S&P מעלות | R33: מנפיק | S33: USD | T33: 1.61 | U33: משתנה | V33: 0.09686 | W33: ריק במקור | X33: ריק במקור | Y33: ריק במקור | Z33: 0.0778 | AA33: 46990 | AB33: החוב לא נחות | AC33: ריק במקור | AD33: ריק במקור | AE33: ריק במקור | AF33: 45108 | AG33: ריק במקור | AH33: ריק במקור | AI33: ריק במקור | AJ33: כן | AK33: חברת ציטוט | AL33: ריק במקור | AM33: אי-תלות | AN33: 46022 | AO33: 46022 | AP33: ריק במקור | AQ33: 62689.63 | AR33: 99.86 | AS33: 3.19 | AT33: 199.69995 | AU33: 62.601865 | AV33: ריק במקור | AW33: ריק במקור | AX33: ריק במקור | AY33: שווי הוגן | AZ33: 0.0039977349 | BA33: 4.6339821e-05
AZ10000: 1

Sheet לא סחיר מוצרים מובנים
A1: מספר קופה/קרן/ח.פ. עבור חברת ביטוח | B1: מספר מסלול | C1: שם מנפיק | D1: מספר מנפיק | E1: סוג מספר מזהה מנפיק | F1: שם נייר ערך | G1: מספר נייר ערך | H1: סוג מספר נייר ערך | I1: מאפיין עיקרי | J1: ישראל/חו"ל | K1: מדינה לפי חשיפה כלכלית | L1: בעל עניין/צד קשור | M1: נכס בסיס | N1: תאריך רכישה | O1: דירוג | P1: שם מדרג | Q1: דירוג נייר הערך/המנפיק | R1: מטבע פעילות | S1: מח"מ | T1: שיעור ריבית | U1: תשואה לפדיון | V1: סוג גורם משערך | W1: תלות/אי-תלות המשערך | X1: תאריך שערוך אחרון | Y1: ערך נקוב (יחידות) | Z1: שער חליפין | AA1: שער נייר הערך | AB1: שווי הוגן (באלפי ש"ח) | AC1: שיעור מנכסי אפיק ההשקעה | AD1: שיעור מסך נכסי ההשקעה
A2: 13908 | B2: 13908 | C2: JPM 7.95 01/34 | D2: ZD6998698 | E2: LEI | F2: JPM 7.95 01/34 | G2: 62012463 | H2: פנימי | I2: שכבת הון (Equity Tranch) | J2: חו"ל | K2: ארה"ב | L2: לא | M2: אחר | N2: 45657 | O2: A | P2: S&P | Q2: נייר ערך | R2: USD | S2: 10.19 | T2: 0.0795 | U2: 0.07176 | V2: דיווח מנהל הקרן | W2: אי-תלות | X2: 46022 | Y2: 1103000 | Z2: 3.19 | AA2: 106.2063 | AB2: 3736.943 | AC2: 1 | AD2: 0.00086714729
AZ10000: 1

Sheet פיקדונות מעל 3 חודשים
A1: מספר קופה/קרן/ח.פ. עבור חברת ביטוח | B1: מספר מסלול | C1: שם הבנק | D1: מספר מזהה בנק | E1: סוג מספר מזהה בנק | F1: מאפיין עיקרי | G1: תאריך פקיעת פיקדון | H1: ישראל/חו"ל | I1: מדינה לפי חשיפה כלכלית | J1: בעל עניין/צד קשור | K1: דירוג הבנק | L1: שם מדרג | M1: מטבע פעילות | N1: מח"מ | O1: שיעור ריבית | P1: תשואה לפדיון | Q1: שווי מטבעי | R1: שער חליפין | S1: שער פיקדון | T1: שווי הוגן (באלפי ש"ח) | U1: שיעור מנכסי אפיק ההשקעה | V1: שיעור מסך נכסי ההשקעה
A2: 13908 | B2: 13908 | C2: בנק הבינלאומי הראשון לישראל | D2: 31 | E2: סימול בנק | F2: לא צמוד למדד המחירים לצרכן | G2: 46150 | H2: ישראל | I2: ישראל | J2: כן | K2: ilAAA | L2: S&P מעלות | M2: ILS | N2: 0.351 | O2: ריק במקור | P2: 0.0386 | Q2: 431850 | R2: 1 | S2: ריק במקור | T2: 43185 | U2: 1 | V2: 0.01002096
AZ10000: 1

Sheet זכויות מקרקעין
A1: מספר קופה/קרן/ח.פ. עבור חברת ביטוח | B1: מספר מסלול | C1: שם הנכס | D1: מאפיין עיקרי | E1: מדינת מיקום נדל"ן | F1: בעל עניין/צד קשור | G1: תאריך רכישה | H1: שימוש עיקרי בנכס | I1: מחזור חיי הנכס | J1: כתובת הנכס | K1: שיעור תשואה בפועל במהלך הרבעון | L1: השיטה שבאמצעותה נקבע שווי הנכס | M1: סוג גורם משערך | N1: שם גורם משערך | O1: תלות/אי-תלות המשערך | P1: תאריך שערוך אחרון | Q1: מטבע פעילות | R1: שווי הוגן (במטבע הפעילות) | S1: שווי הוגן (באלפי ש"ח) | T1: עלות מופחתת (באלפי ש"ח) | U1: עלות מופחתת (במטבע הפעילות) | V1: השיטה שיושמה בדוח הכספי | W1: שיעור מנכסי אפיק ההשקעה | X1: שיעור מסך נכסי ההשקעה
A2: 13908 | B2: 13908 | C2: כנפי רוח בניית ירושלים 2 | D2: נדל"ן לא מניב | E2: ישראל | F2: לא | G2: 45196 | H2: קרקע/זכויות מקרקעין | I2: בתכנון/בהיתרים | J2: פינת הרחובות כנפי נשרים, פרבשטיין , בית הדפוס א.ת. גבעת שאול, ירושלים | K2: 0 | L2: ריק במקור | M2: מומחה בלתי תלוי | N2: ריק במקור | O2: אי-תלות | P2: 45777 | Q2: ILS | R2: 9553.8461 | S2: 9553.8461 | T2: ריק במקור | U2: ריק במקור | V2: שווי הוגן | W2: 0.42766734 | X2: 0.0022169436
A3: 13908 | B3: 13908 | C3: לוזון רונסון | D3: נדל"ן לא מניב | E3: ישראל | F3: לא | G3: 45741 | H3: מגורים (כולל דיור מוגן) | I3: בתכנון/בהיתרים | J3: רחוב כרמל 20, גני תקווה | K3: 0 | L3: ריק במקור | M3: מומחה בלתי תלוי | N3: ריק במקור | O3: אי-תלות | P3: 45741 | Q3: ILS | R3: 8354.9927 | S3: 8354.9927 | T3: ריק במקור | U3: ריק במקור | V3: שווי הוגן | W3: 0.37400199 | X3: 0.0019387529
A4: 13908 | B4: 13908 | C4: כנפי רוח 2 | D4: נדל"ן לא מניב | E4: ישראל | F4: לא | G4: 45782 | H4: קרקע/זכויות מקרקעין | I4: בתכנון/בהיתרים | J4: פינת הרחובות כנפי נשרים, פרבשטיין , בית הדפוס א.ת. גבעת שאול, ירושלים | K4: 0 | L4: ריק במקור | M4: מומחה בלתי תלוי | N4: ריק במקור | O4: אי-תלות | P4: 45782 | Q4: ILS | R4: 4430.5949 | S4: 4430.5949 | T4: ריק במקור | U4: ריק במקור | V4: שווי הוגן | W4: 0.19833067 | X4: 0.0010281073
AZ10000: 1

Sheet השקעה בחברות מוחזקות
A1: מספר קופה/קרן/ח.פ. עבור חברת ביטוח | B1: מספר מסלול | C1: שם מנפיק | D1: מספר מנפיק | E1: סוג מספר מזהה מנפיק | F1: שם נייר ערך | G1: מספר נייר ערך | H1: סוג מספר נייר ערך | I1: מאפיין עיקרי | J1: ישראל/חו"ל | K1: מדינה לפי חשיפה כלכלית | L1: ענף מסחר | M1: בעל עניין/צד קשור | N1: מטבע פעילות | O1: סוג גורם משערך | P1: תלות/אי-תלות המשערך | Q1: תאריך שערוך אחרון | R1: תאריך אחרון בו נבחנה בפועל ירידת ערך | S1: שיעור אחזקה באמצעי שליטה | T1: שווי מאזני (באלפי ש"ח) | U1: שווי הוגן (באלפי ש"ח) | V1: שיעור מנכסי אפיק ההשקעה | W1: שיעור מסך נכסי ההשקעה

Sheet נכסים אחרים
A1: מספר קופה/קרן/ח.פ. עבור חברת ביטוח | B1: מספר מסלול | C1: שם הנכס האחר | D1: מספר הנכס האחר | E1: מאפיין עיקרי | F1: ישראל/חו"ל | G1: מדינה לפי חשיפה כלכלית | H1: בעל עניין/צד קשור | I1: תאריך עסקה | J1: מטבע פעילות | K1: תאריך שערוך אחרון | L1: שווי מטבעי | M1: שער חליפין | N1: שווי הוגן (באלפי ש"ח) | O1: עלות מופחתת (באלפי ש"ח) | P1: השיטה שיושמה בדוח הכספי | Q1: שיעור מנכסי אפיק ההשקעה | R1: שיעור מסך נכסי ההשקעה
A2: 13908 | B2: 13908 | C2: חוז עמלות | D2: 9042 | E2: חייבים בגין תקבולים | F2: ישראל | G2: ישראל | H2: לא | I2: 46022 | J2: ILS | K2: 46022 | L2: 513.18379 | M2: 1 | N2: 513.18379 | O2: ריק במקור | P2: שווי הוגן | Q2: 0.27576077 | R2: 0.00011908288
A3: 13908 | B3: 13908 | C3: חוז שונות | D3: 9082 | E3: חייבים וזכאים | F3: ישראל | G3: ישראל | H3: לא | I3: 46022 | J3: ILS | K3: 46022 | L3: 893.26742 | M3: 1 | N3: 893.26742 | O3: ריק במקור | P3: שווי הוגן | Q3: 0.47999979 | R3: 0.00020728023
A4: 13908 | B4: 13908 | C4: TEMP_MATACH $ | D4: 11018712 | E4: חייבים בגין תקבולים | F4: ישראל | G4: ישראל | H4: לא | I4: 46022 | J4: USD | K4: 46022 | L4: 20.87771 | M4: 3.19 | N4: 66.59989 | O4: ריק במקור | P4: שווי הוגן | Q4: 0.03578764 | R4: 1.545432e-05
A5: 13908 | B5: 13908 | C5: SIXGILL נאמנות | D5: 11022806 | E5: חייבים בנאמנות | F5: ישראל | G5: ישראל | H5: לא | I5: 46022 | J5: USD | K5: 46022 | L5: 121.60612 | M5: 3.19 | N5: 387.92352 | O5: ריק במקור | P5: שווי הוגן | Q5: 0.20845181 | R5: 9.001658e-05
AZ10000: 1

Sheet מסגרות אשראי
A1: מספר קופה/קרן/ח.פ. עבור חברת ביטוח | B1: מספר מסלול | C1: מספר מזהה לווה | D1: סוג מספר מזהה לווה | E1: שם הלוואה | F1: מספר הלוואה | G1: תאריך העמדת מסגרת אשראי | H1: ישראל/חו"ל | I1: מדינה לפי חשיפה כלכלית | J1: בעל עניין/צד קשור | K1: דירוג | L1: שם מדרג | M1: דירוג הלוואה/המנפיק | N1: מטבע פעילות | O1: שער חליפין | P1: שיעור ריבית | Q1: סוג הריבית | R1: סכום מסגרת האשראי הראשוני (במטבע הפעילות) | S1: סכום מסגרת האשראי הראשוני (באלפי ש"ח) | T1: שיעור יתרת מסגרת אשראי
A2: 13908 | B2: 1001 | C2: ריק במקור | D2: ריק במקור | E2: ריק במקור | F2: 11022460 | G2: 45741 | H2: ישראל | I2: ריק במקור | J2: לא | K2: NR | L2: NR | M2: NR | N2: ILS | O2: 1 | P2: 0.09 | Q2: קבועה | R2: 1380159.2 | S2: 1380.1592 | T2: 0.024435568
A3: 13908 | B3: 1001 | C3: ריק במקור | D3: ריק במקור | E3: ריק במקור | F3: 11022458 | G3: 45739 | H3: ישראל | I3: ריק במקור | J3: לא | K3: NR | L3: NR | M3: NR | N3: ILS | O3: 1 | P3: 0.1 | Q3: קבועה | R3: 7500000 | S3: 7500 | T3: 0.16666667
A4: 13908 | B4: 1001 | C4: ריק במקור | D4: ריק במקור | E4: ריק במקור | F4: 11022466 | G4: 45748 | H4: ישראל | I4: ריק במקור | J4: לא | K4: NR | L4: NR | M4: NR | N4: ILS | O4: 1 | P4: 0.005 | Q4: משתנה | R4: 10350000 | S4: 10350 | T4: 0.71428571
A5: 13908 | B5: 1001 | C5: ריק במקור | D5: ריק במקור | E5: ריק במקור | F5: 11022808 | G5: 45750 | H5: חו"ל | I5: ריק במקור | J5: לא | K5: NR | L5: NR | M5: NR | N5: USD | O5: 3.19 | P5: 0.0525 | Q5: משתנה | R5: 2100000 | S5: 6942.6 | T5: 0.806125
A6: 13908 | B6: 1001 | C6: ריק במקור | D6: ריק במקור | E6: ריק במקור | F6: 11022535 | G6: 45962 | H6: ישראל | I6: ריק במקור | J6: לא | K6: NR | L6: NR | M6: NR | N6: ILS | O6: 1 | P6: 0.057 | Q6: משתנה | R6: 8500000 | S6: =R6/1000 -> 8500 | T6: 0.6
A7: 13908 | B7: 1001 | C7: ריק במקור | D7: ריק במקור | E7: ריק במקור | F7: 11022865 | G7: 46007 | H7: בריטניה | I7: ריק במקור | J7: ריק במקור | K7: NR | L7: NR | M7: NR | N7: USD | O7: 3.19 | P7: 0.0525 | Q7: משתנה | R7: 4875000 | S7: =R7*O7/1000 -> 15551.25 | T7: 1
A8: 13908 | B8: 1001 | C8: ריק במקור | D8: ריק במקור | E8: ריק במקור | F8: 11022866 | G8: 46007 | H8: בריטניה | I8: ריק במקור | J8: ריק במקור | K8: NR | L8: NR | M8: NR | N8: USD | O8: 3.19 | P8: 0.0525 | Q8: משתנה | R8: 2625000 | S8: =R8*O8/1000 -> 8373.75 | T8: 1
AZ10000: 1

Sheet יתרות התחייבות להשקעה
A1: מספר קופה/קרן/ח.פ. עבור חברת ביטוח | B1: מספר מסלול | C1: מאפיין עיקרי | D1: שם שותף כללי קרן השקעות | E1: מספר מזהה שותף כללי קרן השקעות | F1: סוג מספר מזהה שותף כללי קרן השקעות | G1: שם קרן ההשקעה | H1: מספר מזהה קרן השקעה | I1: סוג מספר מזהה קרן השקעות | J1: מטבע הפעילות | K1: תאריך העמדת התחייבות לקרן השקעה | L1: סכום המחויבות הראשוני (במטבע הדיווח של קרן ההשקעה) | M1: סכום המחויבות הראשוני (באלפי ש"ח) | N1: יתרת המחויבות לתקופת הדיווח (במטבע הדיווח של קרן ההשקעה) | O1: יתרת המחויבות לתקופת הדיווח (באלפי ש"ח) | P1: שיעור יתרת המחויבות | Q1: תאריך פקיעת מחויבות להשקעה
A2: 13908 | B2: 1001 | C2: קרן השקעה אחרת | D2: HGI Multifamily Credit Fund GP LLC | E2: ריק במקור | F2: ריק במקור | G2: HGI Multifamily Credit Fund LP HGI Multifamily Cr | H2: 11019991 | I2: פנימי | J2: USD | K2: 44935 | L2: 318500 | M2: 1016.015 | N2: 31500 | O2: 100.485 | P2: 0.00031549451 | Q2: 46203
A3: 13908 | B3: 1001 | C3: קרן השקעה אחרת | D3: HarbourVest GP LLC | E3: ריק במקור | F3: ריק במקור | G3: Dover Street XI L.P Dover Street XI L.P | H3: 11019995 | I3: פנימי | J3: USD | K3: 44971 | L3: 72000 | M3: 229.68 | N3: 98000 | O3: 312.62 | P3: 0.0043419444 | Q3: 46607
A4: 13908 | B4: 1001 | C4: קרן נדל"ן | D4: Oak Street Real Estate Capital Fund VI, LP | E4: ריק במקור | F4: ריק במקור | G4: Oak Street Real Estate Capital Fund VI, LP | H4: 11020012 | I4: פנימי | J4: USD | K4: 45032 | L4: 390067.99 | M4: 1244.3169 | N4: 289851.48 | O4: 924.62621 | P4: 0.0023704232 | Q4: 46203
A5: 13908 | B5: 1001 | C5: קרן השקעה אחרת | D5: PANTHEON PGIF IV GP | E5: ריק במקור | F5: ריק במקור | G5: Pantheon Global Infrastructure Fund IV -Luxembourg | H5: 11020456 | I5: פנימי | J5: USD | K5: 45089 | L5: 695487.82 | M5: 2218.6062 | N5: 214012.18 | O5: 682.69886 | P5: 0.00098161152 | Q5: 46310
A6: 13908 | B6: 1001 | C6: פרייבט אקוויטי | D6: Scintilla Tech Ltd | E6: ריק במקור | F6: ריק במקור | G6: MORETECH VENTURES II, L.P | H6: 11020463 | I6: פנימי | J6: USD | K6: 45124 | L6: 120524.87 | M6: 384.47433 | N6: 162771.56 | O6: 519.24126 | P6: 0.004308167 | Q6: 48021
A7: 13908 | B7: 1001 | C7: קרן השקעה אחרת | D7: HPS GP Lux Sarl | E7: ריק במקור | F7: ריק במקור | G7: HPS Specialty Loan International Fund VI-L, SCSp | H7: 11020470 | I7: פנימי | J7: USD | K7: 45135 | L7: 153247.47 | M7: 488.85943 | N7: 327992.07 | O7: 1046.2947 | P7: 0.0068274843 | Q7: 46660
A8: 13908 | B8: 1001 | C8: קרן נדל"ן | D8: Henderson Park Real Estate Fund II GP S.? r.l | E8: ריק במקור | F8: ריק במקור | G8: Henderson Park Real Estate Fund II | H8: 11020471 | I8: פנימי | J8: EUR | K8: 45139 | L8: 879980.73 | M8: 3295.9678 | N8: 339757.62 | O8: 1272.5622 | P8: 0.001446125 | Q8: 49141
A9: 13908 | B9: 1001 | C9: קרן השקעה אחרת | D9: HARBOURVEST GP LLC | E9: ריק במקור | F9: ריק במקור | G9: HV Gondor Feeder L.P | H9: 11020502 | I9: פנימי | J9: USD | K9: 45278 | L9: 681630.57 | M9: 2174.4015 | N9: 418369.44 | O9: 1334.5985 | P9: 0.0019579499 | Q9: 48633
A10: 13908 | B10: 1001 | C10: קרן השקעה אחרת | D10: Pantheon Zilker GP LLC | E10: ריק במקור | F10: ריק במקור | G10: Pantheon Zilker, L.P | H10: 11020508 | I10: פנימי | J10: USD | K10: 45313 | L10: 918500 | M10: 2930.015 | N10: 81500 | O10: 259.985 | P10: 0.00028305389 | Q10: 47870
A11: 13908 | B11: 1001 | C11: קרן אנרגיה ותשתיות | D11: EQT Infrastructure VI (General Partner) S.à r.l. | E11: ריק במקור | F11: ריק במקור | G11: EQT Infrastructure VI Co-Investment | H11: 11020523 | I11: פנימי | J11: USD | K11: 45385 | L11: 1041666.7 | M11: 3322.9167 | N11: 159921.78 | O11: 510.15049 | P11: 0.00048974447 | Q11: 47118
A12: 13908 | B12: 1001 | C12: קרן נדל"ן | D12: LCN European Fund IV GP S.a.r.l | E12: ריק במקור | F12: ריק במקור | G12: LCN European Fund IV SLP | H12: 11019351 | I12: פנימי | J12: EUR | K12: 45419 | L12: 951099.24 | M12: 3562.3422 | N12: 385998.43 | O12: 1445.7571 | P12: 0.0015200907 | Q12: 46475
A13: 13908 | B13: 1001 | C13: קרן אנרגיה ותשתיות | D13: EQT Infrastructure VI (General Partner) S.à r.l. | E13: ריק במקור | F13: ריק במקור | G13: EQT Infrastructure VI (No.1) USD SCSp | H13: 11020525 | I13: פנימי | J13: USD | K13: 45420 | L13: 957555.11 | M13: 3054.6008 | N13: 1785523.6 | O13: 5695.8203 | P13: 0.0059482949 | Q13: 47663
... A34: 13908 | B34: 1001 | C34: קרן נדל"ן | D34: Digital Realty DC Partners NA GP, LP | E34: ריק במקור | F34: ריק במקור | G34: Digital Realty DC Partners NA F | H34: 11022830 | I34: פנימי | J34: USD | K34: 45855 | L34: 3600000 | M34: 11484 | N34: 3600000 | O34: 11484 | P34: 0.00319 | Q34: 47681
A35: 13908 | B35: 1001 | C35: קרן נדל"ן | D35: Starlight Bond 2 GP Ltd | E35: ריק במקור | F35: ריק במקור | G35: Starlight Bond FP 2 LP | H35: 11022949 | I35: פנימי | J35: GBP | K35: 45753 | L35: 1900000 | M35: 8151 | N35: 1900000 | O35: 8151 | P35: 0.00429 | Q35: ריק במקור
A36: 13908 | B36: 1001 | C36: קרן נדל"ן | D36: HGI Multifamily Credit Fund GP, LLC | E36: ריק במקור | F36: ריק במקור | G36: HGI Multifamily Credit Fund II, LP | H36: 11022823 | I36: פנימי | J36: USD | K36: 45899 | L36: 4700000 | M36: 14993 | N36: 4700000 | O36: 14993 | P36: 0.00319 | Q36: 47421
A37: 13908 | B37: 1001 | C37: פרייבט אקוויטי | D37: Thoma Bravo Partners XVI, L.P. | E37: ריק במקור | F37: ריק במקור | G37: Thoma Bravo Fund XVI-A, L.P. | H37: 11022818 | I37: פנימי | J37: USD | K37: 45695 | L37: 4000000 | M37: 12760 | N37: 3622846.6 | O37: 11556.881 | P37: 0.0028892201 | Q37: 49095
A38: 13908 | B38: 1001 | C38: פרייבט אקוויטי | D38: Trident Capital X L. P | E38: ריק במקור | F38: ריק במקור | G38: Trident X Parallel Fund L.P | H38: 11022809 | I38: פנימי | J38: USD | K38: 45743 | L38: 3700000 | M38: 11803 | N38: 3700000 | O38: 11803 | P38: 0.00319 | Q38: 50556
A39: 13908 | B39: 1001 | C39: (Hedge Fund) קרן גידור | D39: LUCID ALTERNATIVE GP LTD | E39: ריק במקור | F39: ריק במקור | G39: LUCID ALTERNATI | H39: 11020009 | I39: פנימי | J39: USD | K39: 45008 | L39: 220000 | M39: 701.8 | N39: 6248 | O39: 19.93112 | P39: 9.0596e-05 | Q39: ריק במקור
A40: 13908 | B40: 1001 | C40: קרנות השקעה אחרות | D40: Secret Chord Ventures II G.P., Ltd. | E40: ריק במקור | F40: ריק במקור | G40: Secret Chord Ventures II - Limi | H40: 11022851 | I40: פנימי | J40: USD | K40: 45882 | L40: 1200000 | M40: 3828 | N40: 1056000 | O40: 3368.64 | P40: 0.0028072 | Q40: 47827
A41: 13908 | B41: 1001 | C41: קרן נדל"ן | D41: TruAmerica Workforce Housing Fund II GP, LLC | E41: ריק במקור | F41: ריק במקור | G41: TruAmerica Workforce Housing Fund II-C | H41: 11022855 | I41: פנימי | J41: USD | K41: 45931 | L41: 2105657.4 | M41: 6717.0471 | N41: 1152489 | O41: 3676.44 | P41: 0.0017459821 | Q41: 46783
A42: 13908 | B42: 1001 | C42: פרייבט אקוויטי | D42: Lindsay Goldberg GP VI LLC | E42: ריק במקור | F42: ריק במקור | G42: Lindsay Goldberg VI L.P. | H42: 11022859 | I42: פנימי | J42: USD | K42: 45992 | L42: 4300000 | M42: 13717 | N42: 4216639.2 | O42: 13451.079 | P42: 0.0031281579 | Q42: 47818
A43: 13908 | B43: 1001 | C43: פרייבט אקוויטי | D43: New Mountain Strategic Investments GP II, L.L.C. | E43: ריק במקור | F43: ריק במקור | G43: New Mountain Strategic Equity Fund II | H43: 11022861 | I43: פנימי | J43: USD | K43: 45992 | L43: 5500000 | M43: 17545 | N43: 5500000 | O43: 17545 | P43: 0.00319 | Q43: 47818
A44: 13908 | B44: 1001 | C44: אשראי תשואה גבוהה | D44: ויולה קרדיט איי.אל.אף 3 ג'י.פי ג'י.פי בע"מ | E44: ריק במקור | F44: ריק במקור | G44: Viola Credit ALF III , L.P. | H44: 11022864 | I44: פנימי | J44: USD | K44: 45992 | L44: 5000000 | M44: 15950 | N44: 3000000 | O44: 9570 | P44: 0.001914 | Q44: 47088
A45: 13908 | B45: 1001 | C45: פרייבט אקוויטי | D45: Green Lantern Management VI Ltd. | E45: ריק במקור | F45: ריק במקור | G45: Green Lantern VI Tapugan Limited Partnership | H45: 11022549 | I45: פנימי | J45: ILS | K45: 46007 | L45: 7000000 | M45: 7000 | N45: 2059838.6 | O45: 2059.8386 | P45: 0.00029426266 | Q45: 47833
A46: 13908 | B46: 1001 | C46: קרן השקעה אחרת | D46: Vine Ventures III GP LLC | E46: ריק במקור | F46: ריק במקור | G46: Vine Ventures III-B, LP | H46: 11022868 | I46: פנימי | J46: USD | K46: 45978 | L46: 2900000 | M46: 9251 | N46: 2900000 | O46: 9251 | P46: 0.00319 | Q46: 49919
AZ10000: 1

Sheet אפשרויות בחירה
A1: שם גיליון (רלוונטי לגיליונות עם עמודה "מאפיין עיקרי") | B1: שם עמודה | C1: אפשרות בחירה | D1: הערות והסברים
A2: ריק במקור | B2: ישראל/חו"ל | C2: ישראל | D2: ריק במקור
A3: ריק במקור | B3: ריק במקור | C3: חו"ל | D3: ריק במקור
A4: ריק במקור | B4: מדינה לפי חשיפה כלכלית; מדינת התאגדות קרן השקעה, מיקום משרד השותף הכללי, מדינת מיקום נדל"ן | C4: ישראל | D4: ריק במקור
A5: ריק במקור | B5: ריק במקור | C5: אוסטריה | D5: ריק במקור
A6: ריק במקור | B6: ריק במקור | C6: אוסטרליה | D6: ריק במקור
A7: ריק במקור | B7: ריק במקור | C7: אזור תעלת פנמה | D7: ריק במקור
A8: ריק במקור | B8: ריק במקור | C8: אזרביג'אן | D8: ריק במקור
A9: ריק במקור | B9: ריק במקור | C9: איחוד האמירויות הערביות | D9: ריק במקור
A10: ריק במקור | B10: ריק במקור | C10: איטליה | D10: ריק במקור
A11: ריק במקור | B11: ריק במקור | C11: איי הבתולה הבריטיים | D11: ריק במקור | E11: נוסף במסגרת עדכון הרשימה
A12: ריק במקור | B12: ריק במקור | C12: איי הבתולה של ארצות הברית | D12: ריק במקור | E12: נוסף במסגרת עדכון הרשימה
A13: ריק במקור | B13: ריק במקור | C13: איי סיישל | D13: ריק במקור
A14: ריק במקור | B14: ריק במקור | C14: איי קיימן | D14: ריק במקור
A15: ריק במקור | B15: ריק במקור | C15: איי שלמה הבריטיים | D15: ריק במקור
A16: ריק במקור | B16: ריק במקור | C16: איסלנד | D16: ריק במקור
A17: ריק במקור | B17: ריק במקור | C17: אירלנד | D17: ריק במקור
A18: ריק במקור | B18: ריק במקור | C18: אנדורה | D18: ריק במקור
A19: ריק במקור | B19: ריק במקור | C19: אסטוניה | D19: ריק במקור
A20: ריק במקור | B20: ריק במקור | C20: ארגנטינה | D20: ריק במקור
A21: ריק במקור | B21: ריק במקור | C21: ארה"ב | D21: ריק במקור
A22: ריק במקור | B22: ריק במקור | C22: אתיופיה | D22: ריק במקור
A23: ריק במקור | B23: ריק במקור | C23: בהמס | D23: ריק במקור
A24: ריק במקור | B24: ריק במקור | C24: בולגריה | D24: ריק במקור
... A35: ריק במקור | B35: ריק במקור | C35: גרמניה | D35: ריק במקור
A36: ריק במקור | B36: ריק במקור | C36: ג'רזי (Jersey) | D36: ריק במקור | E36: נוסף במסגרת עדכון הרשימה
A37: ריק במקור | B37: ריק במקור | C37: גרנזי (Guernsey) | D37: ריק במקור | E37: נוסף במסגרת עדכון הרשימה
A38: ריק במקור | B38: ריק במקור | C38: דנמרק | D38: ריק במקור
A39: ריק במקור | B39: ריק במקור | C39: דרום אפריקה | D39: ריק במקור
A40: ריק במקור | B40: ריק במקור | C40: דרום קוריאה | D40: ריק במקור | E40: נוסף במסגרת עדכון הרשימה
A41: ריק במקור | B41: ריק במקור | C41: הודו | D41: ריק במקור
A42: ריק במקור | B42: ריק במקור | C42: הולנד | D42: ריק במקור
A43: ריק במקור | B43: ריק במקור | C43: הונג קונג | D43: ריק במקור
A44: ריק במקור | B44: ריק במקור | C44: הונגריה | D44: ריק במקור
A45: ריק במקור | B45: ריק במקור | C45: הונדורס | D45: ריק במקור
A46: ריק במקור | B46: ריק במקור | C46: טייוואן | D46: ריק במקור | E46: נוסף במסגרת עדכון הרשימה
A47: ריק במקור | B47: ריק במקור | C47: יוון | D47: ריק במקור
A48: ריק במקור | B48: ריק במקור | C48: יפן | D48: ריק במקור
A49: ריק במקור | B49: ריק במקור | C49: ירדן | D49: ריק במקור
A50: ריק במקור | B50: ריק במקור | C50: לוכסמבורג | D50: ריק במקור
A51: ריק במקור | B51: ריק במקור | C51: לטביה | D51: ריק במקור
A52: ריק במקור | B52: ריק במקור | C52: ליטא | D52: ריק במקור
A53: ריק במקור | B53: ריק במקור | C53: ליכטנשטיין | D53: ריק במקור
A54: ריק במקור | B54: ריק במקור | C54: מאוריציוס | D54: ריק במקור
A55: ריק במקור | B55: ריק במקור | C55: מולדובה | D55: ריק במקור
A56: ריק במקור | B56: ריק במקור | C56: מונקו | D56: ריק במקור
A57: ריק במקור | B57: ריק במקור | C57: מלדיבים | D57: ריק במקור
A58: ריק במקור | B58: ריק במקור | C58: מלטה | D58: ריק במקור
... A62: ריק במקור | B62: ריק במקור | C62: מרוקו | D62: ריק במקור
A63: ריק במקור | B63: ריק במקור | C63: נורבגיה | D63: ריק במקור | E63: נוסף במסגרת עדכון הרשימה
A64: ריק במקור | B64: ריק במקור | C64: ניו זילנד | D64: ריק במקור
A65: ריק במקור | B65: ריק במקור | C65: סין | D65: ריק במקור
A66: ריק במקור | B66: ריק במקור | C66: סינגפור | D66: ריק במקור
A67: ריק במקור | B67: ריק במקור | C67: סלובניה | D67: ריק במקור
A68: ריק במקור | B68: ריק במקור | C68: סלובקיה | D68: ריק במקור
A69: ריק במקור | B69: ריק במקור | C69: ספרד | D69: ריק במקור
A70: ריק במקור | B70: ריק במקור | C70: סרביה | D70: ריק במקור
A71: ריק במקור | B71: ריק במקור | C71: ערב הסעודית | D71: ריק במקור
A72: ריק במקור | B72: ריק במקור | C72: פולין | D72: ריק במקור
A73: ריק במקור | B73: ריק במקור | C73: פורטוגל | D73: ריק במקור
A74: ריק במקור | B74: ריק במקור | C74: פינלנד | D74: ריק במקור
A75: ריק במקור | B75: ריק במקור | C75: פנמה | D75: ריק במקור
... A93: ריק במקור | B93: ריק במקור | C93: גלובלי | D93: ריק במקור
A94: ריק במקור | B94: ריק במקור | C94: Emerging Markets - Americas | D94: שווקים מתעוררים לפי הגדרת MSCI | E94: נוסף במסגרת עדכון הרשימה
A95: ריק במקור | B95: ריק במקור | C95: Emerging Markets - Euope, Middle East & Africa | D95: לפי הגדרת MSCI | E95: נוסף במסגרת עדכון הרשימה
A96: ריק במקור | B96: ריק במקור | C96: Emerging Markets - Asia | D96: לפי הגדרת MSCI | E96: נוסף במסגרת עדכון הרשימה
A97: ריק במקור | B97: ריק במקור | C97: Developed Markets - Americas | D97: לפי הגדרת MSCI | E97: נוסף במסגרת עדכון הרשימה
A98: ריק במקור | B98: ריק במקור | C98: Developed Markets - Europe | D98: לפי הגדרת MSCI | E98: נוסף במסגרת עדכון הרשימה
A99: ריק במקור | B99: ריק במקור | C99: Developed Markets - Pacific | D99: לפי הגדרת MSCI | E99: נוסף במסגרת עדכון הרשימה
A100: ריק במקור | B100: ריק במקור | C100: Frontier Markets - Euope | D100: לפי הגדרת MSCI | E100: נוסף במסגרת עדכון הרשימה
A101: ריק במקור | B101: ריק במקור | C101: Frontier Markets - Africa | D101: לפי הגדרת MSCI | E101: נוסף במסגרת עדכון הרשימה
A102: ריק במקור | B102: ריק במקור | C102: Frontier Markets - Middle East | D102: לפי הגדרת MSCI | E102: נוסף במסגרת עדכון הרשימה
A103: ריק במקור | B103: ריק במקור | C103: Frontier Markets - Asia | D103: לפי הגדרת MSCI | E103: נוסף במסגרת עדכון הרשימה
A104: ריק במקור | B104: סוג מספר מזהה מנפיק | C104: ח.פ. | D104: ריק במקור
A105: ריק במקור | B105: ריק במקור | C105: מספר מנפיק | D105: ריק במקור
A106: ריק במקור | B106: ריק במקור | C106: מספר שותפות | D106: ריק במקור
A107: ריק במקור | B107: ריק במקור | C107: מספר תאגיד או שותפות בחו"ל | D107: ריק במקור
A108: ריק במקור | B108: ריק במקור | C108: פנימי | D108: ריק במקור
A109: ריק במקור | B109: ריק במקור | C109: LEI | D109: ריק במקור
A110: ריק במקור | B110: ריק במקור | C110: אחר | D110: ריק במקור
A111: ריק במקור | B111: סוג מספר מזהה בנק | C111: ח.פ. | D111: ריק במקור
A112: ריק במקור | B112: ריק במקור | C112: סימול בנק | D112: ריק במקור
A113: ריק במקור | B113: ריק במקור | C113: SWIFT | D113: ריק במקור
A114: ריק במקור | B114: סוג מספר מזהה מנהל קרן השקעות | C114: ח.פ. | D114: ריק במקור
A115: ריק במקור | B115: ריק במקור | C115: מספר שותפות | D115: ריק במקור
... A135: ריק במקור | B135: סטאטוס סחירות | C135: סחיר | D135: ריק במקור
A136: ריק במקור | B136: ריק במקור | C136: לא סחיר | D136: ריק במקור | E136: נוסף במסגרת עדכון הרשימה
A137: ריק במקור | B137: ריק במקור | C137: חסום | D137: ני"ע אשר מכירתו מוגבלת לפי הוראות דין או חוזה לתקופה שנקבעה.
A138: ריק במקור | B138: ריק במקור | C138: השעיה | D138: ני"ע שהמסחר בו בזירת המסחר בה הור נסחר הופסק לפרק זמן
A139: ריק במקור | B139: ריק במקור | C139: בהשאלה | D139: ריק במקור
A140: ריק במקור | B140: ריק במקור | C140: לא חסום בהשעיה | D140: ריק במקור
A141: ריק במקור | B141: ריק במקור | C141: לא חסום בהשאלה | D141: ריק במקור
A142: ריק במקור | B142: ריק במקור | C142: חסום בהשעיה | D142: ריק במקור
A143: ריק במקור | B143: ריק במקור | C143: חסום בהשאלה | D143: ריק במקור
A144: ריק במקור | B144: ריק במקור | C144: בשלבי רישום למסחר | D144: ריק במקור
A145: ריק במקור | B145: ריק במקור | C145: אחר | D145: ריק במקור
A146: ריק במקור | B146: בעל עניין/צד קשור | C146: כן | D146: ריק במקור
A147: ריק במקור | B147: ריק במקור | C147: לא | D147: ריק במקור
A148: ריק במקור | B148: זירת מסחר | C148: TASE | D148: TASE - Tel Aviv Stock Exchange
... A179: ריק במקור | B179: ריק במקור | C179: TSX | D179: TSX - Toronto Stock Exchange
...

Sheet מיפוי סעיפים
A1: שם גיליון | B1: שם סעיף | C1: מספר סעיף | D1: מידע שניתן לדווח רק לרשות
A2: מזומנים ושווי מזומנים | B2: מספר קופה/קרן/ח.פ. עבור חברת ביטוח | C2: 5.1 | D2: ריק במקור
A3: מזומנים ושווי מזומנים | B3: מספר מסלול | C3: 5.2 | D3: ריק במקור
A4: מזומנים ושווי מזומנים | B4: שם הבנק | C4: 5.4 | D4: ריק במקור
A5: מזומנים ושווי מזומנים | B5: מספר מזהה בנק | C5: 5.7 | D5: ריק במקור
A6: מזומנים ושווי מזומנים | B6: סוג מספר מזהה בנק | C6: 5.11 | D6: ריק במקור
A7: מזומנים ושווי מזומנים | B7: מאפיין עיקרי | C7: 5.26 | D7: ריק במקור
A8: מזומנים ושווי מזומנים | B8: ישראל/חו"ל | C8: 5.27 | D8: ריק במקור
A9: מזומנים ושווי מזומנים | B9: בעל עניין/צד קשור | C9: 5.36 | D9: ריק במקור
A10: מזומנים ושווי מזומנים | B10: דירוג הבנק | C10: 5.5 | D10: ריק במקור
A11: מזומנים ושווי מזומנים | B11: שם מדרג | C11: 5.51 | D11: ריק במקור
A12: מזומנים ושווי מזומנים | B12: מטבע פעילות | C12: 5.53 | D12: ריק במקור
A13: מזומנים ושווי מזומנים | B13: שווי מטבעי | C13: 5.59 | D13: ריק במקור
... A18: מזומנים ושווי מזומנים | B18: שיעור מסך נכסי ההשקעה | C18: 5.48 | D18: ריק במקור
A19: מזומנים ושווי מזומנים | B19: ריק במקור | C19: ריק במקור | D19: ריק במקור
A20: איגרות חוב ממשלתיות | B20: מספר קופה/קרן/ח.פ. עבור חברת ביטוח | C20: 5.1 | D20: ריק במקור
A21: איגרות חוב ממשלתיות | B21: מספר מסלול | C21: 5.2 | D21: ריק במקור
A22: איגרות חוב ממשלתיות | B22: שם מנפיק | C22: 5.3 | D22: ריק במקור
A23: איגרות חוב ממשלתיות | B23: שם נייר ערך | C23: 5.14 | D23: ריק במקור
A24: איגרות חוב ממשלתיות | B24: מספר נייר ערך | C24: 5.19 | D24: ריק במקור
A25: איגרות חוב ממשלתיות | B25: מאפיין עיקרי | C25: 5.26 | D25: ריק במקור
A26: איגרות חוב ממשלתיות | B26: ישראל/חו"ל | C26: 5.27 | D26: ריק במקור
A27: איגרות חוב ממשלתיות | B27: מדינה לפי חשיפה כלכלית | C27: 5.28 | D27: ריק במקור
A28: איגרות חוב ממשלתיות | B28: זירת מסחר | C28: 5.3 | D28: ריק במקור
A29: איגרות חוב ממשלתיות | B29: דירוג | C29: 5.49 | D29: ריק במקור
A30: איגרות חוב ממשלתיות | B30: שם מדרג | C30: 5.51 | D30: ריק במקור
A31: איגרות חוב ממשלתיות | B31: מטבע פעילות | C31: 5.53 | D31: ריק במקור
... A45: איגרות חוב ממשלתיות | B45: שיעור מסך נכסי ההשקעה | C45: 5.48 | D45: ריק במקור
A46: איגרות חוב ממשלתיות | B46: ריק במקור | C46: ריק במקור | D46: ריק במקור
A47: ניירות ערך מסחריים | B47: מספר קופה/קרן/ח.פ. עבור חברת ביטוח | C47: 5.1 | D47: ריק במקור
A48: ניירות ערך מסחריים | B48: מספר מסלול | C48: 5.2 | D48: ריק במקור
A49: ניירות ערך מסחריים | B49: שם מנפיק | C49: 5.3 | D49: ריק במקור
A50: ניירות ערך מסחריים | B50: מספר מנפיק | C50: 5.6 | D50: ריק במקור
A51: ניירות ערך מסחריים | B51: סוג מספר מזהה מנפיק | C51: 5.1 | D51: ריק במקור
A52: ניירות ערך מסחריים | B52: שם נייר ערך | C52: 5.14 | D52: ריק במקור
A53: ניירות ערך מסחריים | B53: מספר נייר ערך | C53: 5.19 | D53: ריק במקור
A54: ניירות ערך מסחריים | B54: סוג מספר נייר ערך | C54: 5.24 | D54: ריק במקור
A55: ניירות ערך מסחריים | B55: מאפיין עיקרי | C55: 5.26 | D55: ריק במקור
A56: ניירות ערך מסחריים | B56: ישראל/חו"ל | C56: 5.27 | D56: ריק במקור
A57: ניירות ערך מסחריים | B57: מדינה לפי חשיפה כלכלית | C57: 5.28 | D57: ריק במקור
A58: ניירות ערך מסחריים | B58: זירת מסחר | C58: 5.3 | D58: ריק במקור
... A82: ניירות ערך מסחריים | B82: שיעור מסך נכסי ההשקעה | C82: 5.48 | D82: ריק במקור
A83: ניירות ערך מסחריים | B83: ריק במקור | C83: ריק במקור | D83: ריק במקור
A84: איגרות חוב | B84: מספר קופה/קרן/ח.פ. עבור חברת ביטוח | C84: 5.1 | D84: ריק במקור
A85: איגרות חוב | B85: מספר מסלול | C85: 5.2 | D85: ריק במקור
A86: איגרות חוב | B86: שם מנפיק | C86: 5.3 | D86: ריק במקור
A87: איגרות חוב | B87: מספר מנפיק | C87: 5.6 | D87: ריק במקור
A88: איגרות חוב | B88: סוג מספר מזהה מנפיק | C88: 5.1 | D88: ריק במקור
A89: איגרות חוב | B89: שם נייר ערך | C89: 5.14 | D89: ריק במקור
A90: איגרות חוב | B90: מספר נייר ערך | C90: 5.19 | D90: ריק במקור
A91: איגרות חוב | B91: סוג מספר נייר ערך | C91: 5.24 | D91: ריק במקור
A92: איגרות חוב | B92: מאפיין עיקרי | C92: 5.26 | D92: ריק במקור
A93: איגרות חוב | B93: ישראל/חו"ל | C93: 5.27 | D93: ריק במקור
A94: איגרות חוב | B94: מדינה לפי חשיפה כלכלית | C94: 5.28 | D94: ריק במקור
A95: איגרות חוב | B95: סטאטוס סחירות | C95: 5.29 | D95: ריק במקור
... A118: איגרות חוב | B118: שיעור מסך נכסי ההשקעה | C118: 5.48 | D118: ריק במקור
A119: איגרות חוב | B119: ריק במקור | C119: ריק במקור | D119: ריק במקור
A120: מניות, מב"כ ויה"ש | B120: מספר קופה/קרן/ח.פ. עבור חברת ביטוח | C120: 5.1 | D120: ריק במקור
A121: מניות, מב"כ ויה"ש | B121: מספר מסלול | C121: 5.2 | D121: ריק במקור
A122: מניות, מב"כ ויה"ש | B122: שם מנפיק | C122: 5.3 | D122: ריק במקור
A123: מניות, מב"כ ויה"ש | B123: מספר מנפיק | C123: 5.6 | D123: ריק במקור
A124: מניות, מב"כ ויה"ש | B124: סוג מספר מזהה מנפיק | C124: 5.1 | D124: ריק במקור
A125: מניות, מב"כ ויה"ש | B125: שם נייר ערך | C125: 5.14 | D125: ריק במקור
A126: מניות, מב"כ ויה"ש | B126: מספר נייר ערך | C126: 5.19 | D126: ריק במקור
A127: מניות, מב"כ ויה"ש | B127: סוג מספר נייר ערך | C127: 5.24 | D127: ריק במקור
A128: מניות, מב"כ ויה"ש | B128: מאפיין עיקרי | C128: 5.26 | D128: ריק במקור
A129: מניות, מב"כ ויה"ש | B129: ישראל/חו"ל | C129: 5.27 | D129: ריק במקור
A130: מניות, מב"כ ויה"ש | B130: מדינה לפי חשיפה כלכלית | C130: 5.28 | D130: ריק במקור
A131: מניות, מב"כ ויה"ש | B131: סטאטוס סחירות | C131: 5.29 | D131: ריק במקור
... A143: מניות, מב"כ ויה"ש | B143: שיעור מסך נכסי ההשקעה | C143: 5.48 | D143: ריק במקור
A144: מניות, מב"כ ויה"ש | B144: ריק במקור | C144: ריק במקור | D144: ריק במקור
A145: קרנות סל | B145: מספר קופה/קרן/ח.פ. עבור חברת ביטוח | C145: 5.1 | D145: ריק במקור
A146: קרנות סל | B146: מספר מסלול | C146: 5.2 | D146: ריק במקור
A147: קרנות סל | B147: שם מנפיק | C147: 5.3 | D147: ריק במקור
A148: קרנות סל | B148: מספר מנפיק | C148: 5.6 | D148: ריק במקור
A149: קרנות סל | B149: סוג מספר מזהה מנפיק | C149: 5.1 | D149: ריק במקור
A150: קרנות סל | B150: שם נייר ערך | C150: 5.14 | D150: ריק במקור
A151: קרנות סל | B151: מספר נייר ערך | C151: 5.19 | D151: ריק במקור
A152: קרנות סל | B152: סוג מספר נייר ערך | C152: 5.24 | D152: ריק במקור
A153: קרנות סל | B153: מאפיין עיקרי | C153: 5.26 | D153: ריק במקור
A154: קרנות סל | B154: ישראל/חו"ל | C154: 5.27 | D154: ריק במקור
A155: קרנות סל | B155: מדינה לפי חשיפה כלכלית | C155: 5.28 | D155: ריק במקור
A156: קרנות סל | B156: זירת מסחר | C156: 5.3 | D156: ריק במקור
... A162: קרנות סל | B162: שער נייר הערך | C162: 5.55 | D162: ריק במקור
A163: קרנות סל | B163: סכום לקבל (במטבע הפעילות) | C163: 5.62 | D163: ריק במקור | E163: נוסף במהדורה 12
A164: קרנות סל | B164: שווי הוגן (באלפי ש"ח) | C164: 5.63 | D164: ריק במקור
A165: קרנות סל | B165: שיעור מערך נקוב מונפק | C165: 5.45 | D165: ריק במקור
A166: קרנות סל | B166: שיעור מנכסי אפיק ההשקעה | C166: 5.47 | D166: ריק במקור
A167: קרנות סל | B167: שיעור מסך נכסי ההשקעה | C167: 5.48 | D167: ריק במקור
A168: קרנות סל | B168: ריק במקור | C168: ריק במקור | D168: ריק במקור
A169: קרנות נאמנות | B169: מספר קופה/קרן/ח.פ. עבור חברת ביטוח | C169: 5.1 | D169: ריק במקור
A170: קרנות נאמנות | B170: מספר מסלול | C170: 5.2 | D170: ריק במקור
A171: קרנות נאמנות | B171: שם מנפיק | C171: 5.3 | D171: ריק במקור
A172: קרנות נאמנות | B172: מספר מנפיק | C172: 5.6 | D172: ריק במקור
A173: קרנות נאמנות | B173: סוג מספר מזהה מנפיק | C173: 5.1 | D173: ריק במקור
A174: קרנות נאמנות | B174: שם נייר ערך | C174: 5.14 | D174: ריק במקור
A175: קרנות נאמנות | B175: מספר נייר ערך | C175: 5.19 | D175: ריק במקור
A176: קרנות נאמנות | B176: סוג מספר נייר ערך | C176: 5.24 | D176: ריק במקור
A177: קרנות נאמנות | B177: מאפיין עיקרי | C177: 5.26 | D177: ריק במקור
A178: קרנות נאמנות | B178: ישראל/חו"ל | C178: 5.27 | D178: ריק במקור
...

Sheet File Name Info
A2: סוג קובץ
A3: נכסי מבוטחים - חברת ביטוח | B3: in
A4: נכסי עמיתים - קופות גמל | B4: gm
A5: נכסי עמיתים - קרנות פנסיה | B5: pn
A6: נכסי אפיק השקעה מובטח תשואה | B6: ca
A7: נכסי נוסטרו - חברת ביטוח | B7: ni
A8: נכסי נוסטרו - חברה מנהלת | B8: nf
A10: יעוד הקובץ
A11: לממונה
A12: לציבור | B12: p
A15: רבעון
A16: 01
A17: 02
A18: 03
A19: 04
A21: שנה
A22: 2022 | B22: 22
A23: 2023 | B23: 23
A24: 2024 | B24: 24
A25: 2025 | B25: 25
A26: 2026 | B26: 26
A27: 2027 | B27: 27
A28: 2028 | B28: 28
A29: 2029 | B29: 29
A30: 2030 | B30: 30
A31: 2031 | B31: 31
A34: שם גוף מוסדי | B34: ח.פ.
A35: אי. אם. איי - עזר חברה לביטוח משכנתאות בע"מ | B35: 512310509
A36: איי. די. איי. חברה לביטוח בע"מ | B36: 513910703
A37: איי.אי.ג'י חברה לביטוח בע"מ | B37: 512304882
A38: איילון חברה לביטוח בע"מ | B38: 520030677
A39: אינפיניטי השתלמות, גמל ופנסיה בע"מ | B39: 513621110
A40: אלטשולר שחם גמל ופנסיה בע"מ | B40: 513173393
A41: אנליסט קופות גמל בע"מ | B41: 511880460
A42: ארם גמולים - חברה לניהול קופות גמל בע''מ | B42: 510773922
A43: אשרא - החברה הישראלית לביטוח יצוא בע"מ | B43: 520021916
A44: ב.ס.ס.ח. - החברה הישראלית לביטוח אשראי בע"מ | B44: 520044025
A45: ביטוח חקלאי אגודה מרכזית בע"מ | B45: 570003152
A46: גילעד גימלאות לעובדים דתיים בע"מ | B46: 520023094
... A121: תגמולים של עובדים בעירית ת"א-יפו א.ש. בע"מ | B121: 570002618
