Workbook
Name Additional_Factor: 'אפשרויות בחירה'!$C$706:$C$854
Name Amoritization: 'אפשרויות בחירה'!$C$544:$C$548
Name Capsule: 'אפשרויות בחירה'!$C$934:$C$936
Name Company_Name: 'File Name Info'!$A$34:$A$130
Name Company_Name_ID: 'File Name Info'!$A$34:$B$130
Name Consortium: 'אפשרויות בחירה'!$C$512:$C$513
Name Country_list: 'אפשרויות בחירה'!$C$4:$C$85
Name Country_list_funds: 'אפשרויות בחירה'!$C$4:$C$103
Name CSA: 'אפשרויות בחירה'!$C$693:$C$694
Name Delivery: 'אפשרויות בחירה'!$C$670:$C$671
Name Dependence_Independence: 'אפשרויות בחירה'!$C$658:$C$659
Name Duration_Underlying_Interest_Rate: 'אפשרויות בחירה'!$C$685:$C$692
Name File_Type: 'File Name Info'!$A$10:$A$12
Name Full_File_Type: 'File Name Info'!$A$11:$B$13
Name Full_Type: 'File Name Info'!$A$2:$B$8
Name Full_Type_Nostro: 'File Name Info'!$A$3:$B$6
Name Full_Year: 'File Name Info'!$A$22:$B$31
Name Fund_Strategy: 'אפשרויות בחירה'!$C$595:$C$625
Name Fund_type: 'אפשרויות בחירה'!$C$326:$C$496
Name Holding_interest: 'אפשרויות בחירה'!$C$146:$C$147
Name In_the_books: 'אפשרויות בחירה'!$C$660:$C$661
Name Industry_Sector: 'אפשרויות בחירה'!#REF!
Name Industry_sector_all: 'אפשרויות בחירה'!$C$202:$C$325
Name Industry_sectors: 'אפשרויות בחירה'!$C$202:$C$325
Name israel_abroad: 'אפשרויות בחירה'!$C$2:$C$3
Name Issuer_Number_Banks: 'אפשרויות בחירה'!$C$111:$C$113
Name Issuer_Number_Fund: 'אפשרויות בחירה'!$C$114:$C$117
Name issuer_number_loan: 'אפשרויות בחירה'!$C$118:$C$126
Name Issuer_Number_Type: 'אפשרויות בחירה'!$C$104:$C$110
Name Issuer_Number_Type_2: 'אפשרויות בחירה'!#REF!
Name Issuer_Number_Type_3: 'אפשרויות בחירה'!#REF!
Name Issuer_Number_Type_V2: 'אפשרויות בחירה'!$C$104:$C$110
Name Issuer_Type_TFunds: 'אפשרויות בחירה'!#REF!
Name Leading_factor: 'אפשרויות בחירה'!$C$697:$C$705
Name Linked_Type: 'אפשרויות בחירה'!$C$514:$C$517
Name other_investments: 'אפשרויות בחירה'!$C$1018:$C$1051
Name Penalty: 'אפשרויות בחירה'!$C$855:$C$856
Name QTR: 'File Name Info'!$A$15:$A$19
Name Rating_Agency: 'אפשרויות בחירה'!$C$188:$C$201
Name real_estate_lifestage: 'אפשרויות בחירה'!$C$638:$C$646
Name real_estate_loans: 'אפשרויות בחירה'!$C$551:$C$589
Name Real_Estate_Main_Use: 'אפשרויות בחירה'!$C$626:$C$637
Name Recourse_Nonrecourse: 'אפשרויות בחירה'!$C$542:$C$543
Name Repayment_Rights: 'אפשרויות בחירה'!$C$549:$C$550
Name Reset_frequency: 'אפשרויות בחירה'!$C$662:$C$669
Name Security_ID_Number_Type: 'אפשרויות בחירה'!#REF!
Name Security_Number_Loans: 'אפשרויות בחירה'!$C$131
Name Stock_Exchange: 'אפשרויות בחירה'!#REF!
Name Stock_Exchange_Gov_Bonds: 'אפשרויות בחירה'!$C$148:$C$181
Name Subordination_Risk: 'אפשרויות בחירה'!$C$186:$C$187
Name Tradeable_Status: 'אפשרויות בחירה'!#REF!
Name Tradeable_Status_All: 'אפשרויות בחירה'!$C$135:$C$145
Name tradeable_status_bonds: 'אפשרויות בחירה'!#REF!
Name tradeable_status_funds: 'אפשרויות בחירה'!#REF!
Name tradeable_status_stock: 'אפשרויות בחירה'!#REF!
Name Tradeable_Status_v2: 'אפשרויות בחירה'!#REF!
Name tradeable_status_warrants: 'אפשרויות בחירה'!#REF!
Name tradeable_status_warrants_v2: 'אפשרויות בחירה'!#REF!
Name Transaction: 'אפשרויות בחירה'!$C$647:$C$650
Name Type: 'File Name Info'!$A$2:$A$8

Sheet עמוד פתיחה
A1: קובץ דיווח עבור רשימת נכסים ברמת הנכס הבודד (חוזר גופים מוסדיים 2015-9-14)
A3: יש לבחור תחום: | D3: נכסי אפיק השקעה מובטח תשואה
A5: האם מדובר בקובץ לממומנה או לציבור: | D5: לציבור
A7: יש לבחור את רבעון הדיווח: | D7: Q2
A9: יש לבחור את שנת הדיווח: | D9: 2026
A11: יש לבחור את הגוף המוסדי: | D11: מור גמל ופנסיה בע"מ
A13: ח.פ. הגוף המוסדי: | D13: =IFERROR(VLOOKUP(D11,'File Name Info'!A35:B130,2,0),"תא מחושב") -> 514956465
A15: שם קובץ לשמירה | D15: =IF(D5="לממונה",CONCATENATE(D13, "_",VLOOKUP(D3,Full_Type,2,0),"_",D7,VLOOKUP(D9,Full_Year,2,0),".xlxs"),IF(D5="לציבור",CONCATENATE(D13,"_",VLOOKUP(D3,Full_Type_Nostro,2,0),"_",VLOOKUP(D5,Full_File_Type,2,0),"_",D7,VLOOKUP(D9,Full_Year,2,0),".xlsx"),"שם קובץ לשמירה")) -> 514956465_ca_p_Q226.xlsx
A17: פרטי האחראי על הדיווח בגוף המוסדי | B17: שם: | D17: לירון פיכמן
B19: מספר טלפון:
B21: כתובת מייל: | D21: Liron.Fichman@more.co.il
A23: הוראות למילוי הדיווח: | D23: יש לדווח לפי ההנחיות בחלק ג' לנספח 5.4.3.2 שבפרק 3 שבחלק 4 לשער 5 בחוזר המאוחד - "רשימת נכסים ברמת הנכס הבודד".

Sheet סכום נכסים
C1: ידווח בקבצי נכסי הנוסטרו בלבד
A2: אפיק | B2: שווי הוגן (באלפי ש"ח) | C2: עלות מופחתת (באלפי ש"ח) | D2: השיטה שיושמה בדוח הכספי | E2: שיעור מסך נכסי השקעה
A3: מזומנים ושווי מזומנים | B3: 1211658.9 | D3: שווי הוגן | E3: 0.21814623
A4: איגרות חוב ממשלתיות | B4: 1319085 | D4: שווי הוגן | E4: 0.23748716
A5: ניירות ערך מסחריים | B5: 0 | E5: 0
A6: איגרות חוב | B6: 670120.2 | D6: שווי הוגן | E6: 0.12064798
A7: מניות מבכ ויהש | B7: 1053135.6 | D7: NA | E7: 0.18960581
A8: קרנות סל | B8: 434231.39 | D8: NA | E8: 0.07817872
A9: קרנות נאמנות | B9: 673326.51 | D9: שווי הוגן | E9: 0.12122524
A10: כתבי אופציה | B10: 4648.3922 | D10: שווי הוגן | E10: 0.00083689333
A11: אופציות | B11: 0 | E11: 0
A12: חוזים עתידיים | B12: 16087.609 | D12: שווי הוגן | E12: 0.002896402
A13: מוצרים מובנים | B13: 6.32804 | D13: שווי הוגן | E13: 1.139296e-06
A14: לא סחיר איגרות חוב ממשלתיות | B14: 0 | E14: 0
A15: לא סחיר איגרות חוב מיועדות | B15: 0 | E15: 0
A16: אפיק השקעה מובטח תשואה | B16: -654959 | E16: -0.11791837
A17: לא סחיר ניירות ערך מסחריים | B17: 4778.868 | D17: שווי הוגן | E17: 0.0008603841
A18: לא סחיר איגרות חוב | B18: 123882.53 | D18: שווי הוגן | E18: 0.022303726
A19: לא סחיר מניות מבכ ויהש | B19: 68647.391 | D19: שווי הוגן | E19: 0.012359229
A20: קרנות השקעה | B20: 295131.11 | D20: שווי הוגן | E20: 0.053135202
A21: לא סחיר כתבי אופציה | B21: 8975.9961 | D21: שווי הוגן | E21: 0.0016160322
A22: לא סחיר אופציות | B22: 0 | E22: 0
A23: לא סחיר נגזרים אחרים | B23: 9356.8167 | D23: NA | E23: 0.0016845948
A24: הלוואות | B24: 66662.564 | D24: שווי הוגן | E24: 0.012001882
A25: לא סחיר מוצרים מובנים | B25: 3718.7689 | D25: שווי הוגן | E25: 0.00066952459
A26: פיקדונות מעל 3 חודשים | B26: 214699.96 | D26: שווי הוגן | E26: 0.038654432
A27: זכויות מקרקעין | B27: 23449.037 | D27: שווי הוגן | E27: 0.0042217484
A28: השקעה בחברות מוחזקות | B28: 0 | E28: 0
A29: נכסים אחרים | B29: 7698.5325 | D29: שווי הוגן | E29: 0.0013860385
A30: סך הכל נכסים | B30: =SUM(B3:B29) -> 5554342.5 | C30: =SUM(C3:C29) -> 0 | D30: =SUM(D3:D29) -> 0 | E30: =SUM(E3:E29) -> 1
A31: מסגרות אשראי | B31: 64944.498
A32: יתרות התחייבות להשקעה | B32: 275918.68

Sheet מזומנים ושווי מזומנים
A1: מספר קופה/קרן/ח.פ. עבור חברת ביטוח | B1: מספר מסלול | C1: שם הבנק | D1: מספר מזהה בנק | E1: סוג מספר מזהה בנק | F1: מאפיין עיקרי | G1: ישראל/חו"ל | H1: בעל עניין/צד קשור | I1: דירוג הבנק | J1: שם מדרג | K1: מטבע פעילות | L1: שווי מטבעי | M1: שער חליפין | N1: שיעור ריבית | O1: שווי הוגן (באלפי ש"ח) | P1: שיעור מנכסי אפיק ההשקעה | Q1: שיעור מסך נכסי ההשקעה
A2: 13908 | B2: 13908 | C2: בנק הבינלאומי הראשון לישראל בע"מ | D2: 31 | E2: סימול בנק | F2: מזומן ועו"ש בש"ח | G2: ישראל | H2: לא | I2: ilAAA | J2: S&P מעלות | K2: ILS | L2: 872843.96 | M2: 1 | O2: 872843.96 | P2: 0.72037102 | Q2: 0.15714622
A3: 13908 | B3: 13908 | C3: בנק המזרחי המאוחד בע"מ | D3: 20 | E3: סימול בנק | F3: מזומן ועו"ש בש"ח | G3: ישראל | H3: לא | I3: ilAAA | J3: S&P מעלות | K3: ILS | L3: 0.01674 | M3: 1 | O3: 0.01674 | P3: 1.3815769e-08 | Q3: 3.0138581e-09
A4: 13908 | B4: 13908 | C4: בנק הבינלאומי הראשון לישראל בע"מ | D4: 31 | E4: סימול בנק | F4: מזומן ועו"ש נקוב במט"ח | G4: ישראל | H4: לא | I4: ilAAA | J4: S&P מעלות | K4: USD | L4: 67268.578 | M4: 2.978 | O4: 200325.83 | P4: 0.16533186 | Q4: 0.036066523
A5: 13908 | B5: 13908 | C5: בנק המזרחי המאוחד בע"מ | D5: 20 | E5: סימול בנק | F5: מזומן ועו"ש נקוב במט"ח | G5: ישראל | H5: לא | I5: ilAAA | J5: S&P מעלות | K5: USD | L5: 216.47349 | M5: 2.978 | O5: 644.65805 | P5: 0.00053204582 | Q5: 0.00011606379
A6: 13908 | B6: 13908 | C6: בנק הבינלאומי הראשון לישראל בע"מ | D6: 31 | E6: סימול בנק | F6: מזומן ועו"ש נקוב במט"ח | G6: ישראל | H6: לא | I6: ilAAA | J6: S&P מעלות | K6: CHF | L6: 49.01082 | M6: 3.6802 | O6: 180.36962 | P6: 0.00014886171 | Q6: 3.2473622e-05
A7: 13908 | B7: 13908 | C7: בנק הבינלאומי הראשון לישראל בע"מ | D7: 31 | E7: סימול בנק | F7: מזומן ועו"ש נקוב במט"ח | G7: ישראל | H7: לא | I7: ilAAA | J7: S&P מעלות | K7: GBP | L7: 435.87909 | M7: 3.9389 | O7: 1716.8842 | P7: 0.0014169699 | Q7: 0.00030910664
A8: 13908 | B8: 13908 | C8: בנק הבינלאומי הראשון לישראל בע"מ | D8: 31 | E8: סימול בנק | F8: מזומן ועו"ש נקוב במט"ח | G8: ישראל | H8: לא | I8: ilAAA | J8: S&P מעלות | K8: JPY | L8: 1548214.4 | M8: 0.018341 | O8: 28395.8 | P8: 0.023435474 | Q8: 0.0051123603
A9: 13908 | B9: 13908 | C9: בנק הבינלאומי הראשון לישראל בע"מ | D9: 31 | E9: סימול בנק | F9: מזומן ועו"ש נקוב במט"ח | G9: ישראל | H9: לא | I9: ilAAA | J9: S&P מעלות | K9: CAD | L9: 0.010001434 | M9: 2.0917 | O9: 0.02092 | P9: 1.7265585e-08 | Q9: 3.7664224e-09
A10: 13908 | B10: 13908 | C10: בנק הבינלאומי הראשון לישראל בע"מ | D10: 31 | E10: סימול בנק | F10: מזומן ועו"ש נקוב במט"ח | G10: ישראל | H10: לא | I10: ilAAA | J10: S&P מעלות | K10: EUR | L10: 8.8378259e-06 | M10: 3.3945 | O10: 3e-05 | P10: 2.4759443e-11 | Q10: 5.4011793e-12
A11: 13908 | B11: 13908 | C11: בנק הבינלאומי הראשון לישראל בע"מ | D11: 31 | E11: סימול בנק | F11: מזומן ועו"ש נקוב במט"ח | G11: ישראל | H11: לא | I11: ilAAA | J11: S&P מעלות | K11: EUR | L11: 13291.655 | M11: 3.3945 | O11: 45118.524 | P11: 0.037236985 | Q11: 0.008123108
A12: 13908 | B12: 13908 | C12: בנק הבינלאומי הראשון לישראל בע"מ | D12: 31 | E12: סימול בנק | F12: מזומן ועו"ש נקוב במט"ח | G12: ישראל | H12: לא | I12: ilAAA | J12: S&P מעלות | K12: USD | L12: -108.34041 | M12: 2.978 | O12: -322.63774 | P12: -0.0002662777 | Q12: -5.8087476e-05
A13: 13908 | B13: 13908 | C13: בנק הבינלאומי הראשון לישראל בע"מ | D13: 31 | E13: סימול בנק | F13: מזומן ועו"ש נקוב במט"ח | G13: ישראל | H13: לא | I13: ilAAA | J13: S&P מעלות | K13: USD | L13: 101.824 | M13: 2.978 | O13: 303.23187 | P13: 0.00025026174 | Q13: 5.4593657e-05
... A16: 13908 | B16: 13908 | C16: בנק הבינלאומי הראשון לישראל בע"מ | D16: 31 | E16: סימול בנק | F16: מזומן ועו"ש נקוב במט"ח | G16: ישראל | H16: לא | I16: ilAAA | J16: S&P מעלות | K16: USD | L16: 10060 | M16: 2.978 | O16: 29958.68 | P16: 0.024725341 | Q16: 0.0053937401

Sheet איגרות חוב ממשלתיות
A1: מספר קופה/קרן/ח.פ. עבור חברת ביטוח | B1: מספר מסלול | C1: שם מנפיק | D1: שם נייר ערך | E1: מספר נייר ערך | F1: מאפיין עיקרי | G1: ישראל/חו"ל | H1: מדינה לפי חשיפה כלכלית | I1: זירת מסחר | J1: דירוג | K1: שם מדרג | L1: מטבע פעילות | M1: מח"מ | N1: מועד פדיון | O1: שיעור ריבית | P1: תשואה לפדיון | Q1: סכום לקבל (במטבע הפעילות) | R1: ערך נקוב (יחידות) | S1: שער חליפין | T1: שער נייר הערך | U1: שווי הוגן (באלפי ש"ח) | V1: עלות מופחתת (באלפי ש"ח) | W1: השיטה שיושמה בדוח הכספי | X1: שיעור מערך נקוב מונפק | Y1: שיעור מנכסי אפיק ההשקעה | Z1: שיעור מסך נכסי ההשקעה
A2: 13908 | B2: 13908 | C2: מדינת ישראל | D2: ממשל שקלית 0142 | E2: IL0011254005 | F2: לא צמוד למדד המחירים לצרכן ריבית קבועה | G2: ישראל | H2: ישראל | I2: TASE | J2: NR | K2: NR | L2: ILS | M2: 11.065 | N2: 51897 | O2: 0.055 | P2: 0.0394 | Q2: 0 | R2: 16725000 | S2: 1 | T2: 120.13 | U2: 20091.743 | W2: שווי הוגן | X2: 0.00045415522 | Y2: 0.015231575 | Z2: 0.0036173035
A3: 13908 | B3: 13908 | C3: מדינת ישראל | D3: ממשל שקלית 0327 | E3: IL0011393449 | F3: לא צמוד למדד המחירים לצרכן ריבית קבועה | G3: ישראל | H3: ישראל | I3: TASE | J3: NR | K3: NR | L3: ILS | M3: 0.748 | N3: 46477 | O3: 0.02 | P3: 0.0319 | Q3: 0 | R3: 41342100 | S3: 1 | T3: 99.63 | U3: 41189.134 | W3: שווי הוגן | X3: 0.0014645573 | Y3: 0.031225534 | Z3: 0.0074156633
A4: 13908 | B4: 13908 | C4: מדינת ישראל | D4: ממשל שקלית 0347 | E4: IL0011401937 | F4: לא צמוד למדד המחירים לצרכן ריבית קבועה | G4: ישראל | H4: ישראל | I4: TASE | J4: NR | K4: NR | L4: ILS | M4: 14.465 | N4: 53782 | O4: 0.0375 | P4: 0.0413 | Q4: 0 | R4: 8370250 | S4: 1 | T4: 95.7 | U4: 8010.3292 | W4: שווי הוגן | X4: 0.00029762104 | Y4: 0.0060726407 | Z4: 0.0014421742
A5: 13908 | B5: 13908 | C5: מדינת ישראל | D5: ממשל צמודה 0527 | E5: IL0011408478 | F5: צמוד למדד המחירים לצרכן בריבית קבועה | G5: ישראל | H5: ישראל | I5: TASE | J5: NR | K5: NR | L5: ILS | M5: 0.915 | N5: 46538 | O5: 0.0075 | P5: 0.0172 | Q5: 0 | R5: 119572805 | S5: 1 | T5: 119.65 | U5: 143068.86 | W5: שווי הוגן | X5: 0.0049092853 | Y5: 0.10846068 | Z5: 0.025758019
A6: 13908 | B6: 13908 | C6: מדינת ישראל | D6: ממשל שקלית 0928 | E6: IL0011508798 | F6: לא צמוד למדד המחירים לצרכן ריבית קבועה | G6: ישראל | H6: ישראל | I6: TASE | J6: NR | K6: NR | L6: ILS | M6: 2.18 | N6: 47024 | O6: 0.0225 | P6: 0.0328 | Q6: 0 | R6: 76135295 | S6: 1 | T6: 99.5 | U6: 75754.619 | W6: שווי הוגן | X6: 0.0021927408 | Y6: 0.057429671 | Z6: 0.013638809
A7: 13908 | B7: 13908 | C7: מדינת ישראל | D7: ממשל צמודה 0529 | E7: IL0011570236 | F7: צמוד למדד המחירים לצרכן בריבית קבועה | G7: ישראל | H7: ישראל | I7: TASE | J7: NR | K7: NR | L7: ILS | M7: 2.903 | N7: 47269 | O7: 0.005 | P7: 0.0163 | Q7: 0 | R7: 106977651 | S7: 1 | T7: 115.67 | U7: 123741.05 | W7: שווי הוגן | X7: 0.0032274144 | Y7: 0.093808245 | Z7: 0.022278253
A8: 13908 | B8: 13908 | C8: מדינת ישראל | D8: ממשל שקלית 0537 | E8: IL0011661803 | F8: לא צמוד למדד המחירים לצרכן ריבית קבועה | G8: ישראל | H8: ישראל | I8: TASE | J8: NR | K8: NR | L8: ILS | M8: 10.026 | N8: 50191 | O8: 0.015 | P8: 0.0381 | Q8: 0 | R8: 31517147 | S8: 1 | T8: 79.78 | U8: 25144.38 | W8: שווי הוגן | X8: 0.00075219945 | Y8: 0.019061986 | Z8: 0.0045269768
A9: 13908 | B9: 13908 | C9: מדינת ישראל | D9: ממשל משתנה 1130 | E9: IL0011665523 | F9: לא צמוד למדד המחירים לצרכן ריבית משתנה | G9: ישראל | H9: ישראל | I9: TASE | J9: NR | K9: NR | L9: ILS | M9: 4.121 | N9: 47816 | O9: 0.0356 | P9: 0.0356 | Q9: 0 | R9: 41429977 | S9: 1 | T9: 99.01 | U9: 41019.82 | W9: שווי הוגן | X9: 0.0011304245 | Y9: 0.031097177 | Z9: 0.0073851802
A10: 13908 | B10: 13908 | C10: מדינת ישראל | D10: ממשל צמודה 1131 | E10: IL0011722209 | F10: צמוד למדד המחירים לצרכן בריבית קבועה | G10: ישראל | H10: ישראל | I10: TASE | J10: NR | K10: NR | L10: ILS | M10: 5.403 | N10: 48182 | O10: 0.001 | P10: 0.0165 | Q10: 0 | R10: 16031800 | S10: 1 | T10: 109.97 | U10: 17630.17 | W10: שווי הוגן | X10: 0.00046837607 | Y10: 0.013365454 | Z10: 0.0031741237
A11: 13908 | B11: 13908 | C11: מדינת ישראל | D11: ממשל שקלית 0432 | E11: IL0011806606 | F11: לא צמוד למדד המחירים לצרכן ריבית קבועה | G11: ישראל | H11: ישראל | I11: TASE | J11: NR | K11: NR | L11: ILS | M11: 5.632 | N11: 48334 | O11: 0.013 | P11: 0.0347 | Q11: 0 | R11: 82012941 | S11: 1 | T11: 88.94 | U11: 72942.31 | W11: שווי הוגן | X11: 0.0019959954 | Y11: 0.055297657 | Z11: 0.013132483
A12: 13908 | B12: 13908 | C12: מדינת ישראל | D12: ממשל שקלית 1152 | E12: IL0011840761 | F12: לא צמוד למדד המחירים לצרכן ריבית קבועה | G12: ישראל | H12: ישראל | I12: TASE | J12: NR | K12: NR | L12: ILS | M12: 17.441 | N12: 55852 | O12: 0.028 | P12: 0.043 | Q12: 0 | R12: 3329807 | S12: 1 | T12: 78.16 | U12: 2602.5772 | W12: שווי הוגן | X12: 9.1604576e-05 | Y12: 0.001973017 | Z12: 0.0004685662
A13: 13908 | B13: 13908 | C13: מדינת ישראל | D13: ממשל שקלית 0229 | E13: IL0011948028 | F13: לא צמוד למדד המחירים לצרכן ריבית קבועה | G13: ישראל | H13: ישראל | I13: TASE | J13: NR | K13: NR | L13: ILS | M13: 2.559 | N13: 47177 | O13: 0.0375 | P13: 0.033 | Q13: 0 | R13: 40715544 | S13: 1 | T13: 102.39 | U13: 41688.645 | W13: שווי הוגן | X13: 0.0011624588 | Y13: 0.031604214 | Z13: 0.007505595
... A38: 13908 | B38: 13908 | C38: STATE OF ISRAEL | D38: ISRAEL 5.8 1/56 | E38: US46515CKR42 | F38: נקוב במט"ח | G38: ישראל | H38: ישראל | I38: FWB | J38: Baa1 | K38: Moodys | L38: USD | M38: 13.753 | N38: 56992 | O38: 0.058 | P38: 0.06086 | Q38: 0 | R38: 300000 | S38: 2.978 | T38: 99.88 | U38: 892.32792 | W38: שווי הוגן | X38: 0.00017142857 | Y38: 0.00067647492 | Z38: 0.0001606541

Sheet ניירות ערך מסחריים
A1: מספר קופה/קרן/ח.פ. עבור חברת ביטוח | B1: מספר מסלול | C1: שם מנפיק | D1: מספר מנפיק | E1: סוג מספר מזהה מנפיק | F1: שם נייר ערך | G1: מספר נייר ערך | H1: סוג מספר נייר ערך | I1: מאפיין עיקרי | J1: ישראל/חו"ל | K1: מדינה לפי חשיפה כלכלית | L1: זירת מסחר | M1: ענף מסחר | N1: בעל עניין/צד קשור | O1: דירוג | P1: שם מדרג | Q1: דירוג נייר הערך/המנפיק | R1: מטבע פעילות | S1: מח"מ | T1: ריבית עוגן | U1: מועד פדיון | V1: שיעור ריבית | W1: תשואה לפדיון | X1: נחיתות חוזית | Y1: האם סווג כחוב בעייתי | Z1: ערך נקוב (יחידות) | AA1: שער חליפין | AB1: שער נייר הערך | AC1: סכום לקבל (במטבע הפעילות) | AD1: שווי הוגן (באלפי ש"ח) | AE1: עלות מופחתת (באלפי ש"ח) | AF1: עלות מופחתת (במטבע הפעילות) | AG1: השיטה שיושמה בדוח הכספי | AH1: שיעור מערך נקוב מונפק | AI1: שיעור מנכסי אפיק ההשקעה | AJ1: שיעור מסך נכסי ההשקעה

Sheet איגרות חוב
A1: מספר קופה/קרן/ח.פ. עבור חברת ביטוח | B1: מספר מסלול | C1: שם מנפיק | D1: מספר מנפיק | E1: סוג מספר מזהה מנפיק | F1: שם נייר ערך | G1: מספר נייר ערך | H1: סוג מספר נייר ערך | I1: מאפיין עיקרי | J1: ישראל/חו"ל | K1: מדינה לפי חשיפה כלכלית | L1: סטאטוס סחירות | M1: זירת מסחר | N1: ענף מסחר | O1: בעל עניין/צד קשור | P1: דירוג | Q1: שם מדרג | R1: דירוג נייר הערך/המנפיק | S1: מטבע פעילות | T1: מח"מ | U1: מועד פדיון | V1: שיעור ריבית | W1: תשואה לפדיון | X1: נחיתות חוזית | Y1: האם סווג כחוב בעייתי | Z1: ערך נקוב (יחידות) | AA1: שער חליפין | AB1: שער נייר הערך | AC1: סכום לקבל (במטבע הפעילות) | AD1: שווי הוגן (באלפי ש"ח) | AE1: עלות מופחתת (באלפי ש"ח) | AF1: עלות מופחתת (במטבע הפעילות) | AG1: השיטה שיושמה בדוח הכספי | AH1: שיעור מערך נקוב מונפק | AI1: שיעור מנכסי אפיק ההשקעה | AJ1: שיעור מסך נכסי ההשקעה
A2: 13908 | B2: 13908 | C2: אדמה פתרונות לחקלאות בע"מ | D2: 520043605 | E2: ח.פ. | F2: אדמה אגח ב | G2: IL0011109159 | H2: ISIN | I2: צמוד למדד המחירים לצרכן | J2: ישראל | K2: ישראל | L2: סחיר | M2: TASE | N2: כימיה, גומי ופלסטיק | O2: לא | P2: ilAA- | Q2: S&P מעלות | R2: נייר ערך | S2: ILS | T2: 4.78 | U2: 50009 | V2: 0.0515 | W2: 0.0304 | X2: החוב לא נחות | Z2: 338274.88 | AA2: 1 | AB2: 159.3 | AC2: 0 | AD2: 538.87188 | AG2: שווי הוגן | AH2: 0.00019230142 | AI2: 0.00080414212 | AJ2: =AD2/'סכום נכסים'!$B$30 -> 9.7018122e-05
A3: 13908 | B3: 13908 | C3: אמות השקעות בע"מ | D3: 520026683 | E3: ח.פ. | F3: אמות אגח ד | G3: IL0011331498 | H3: ISIN | I3: צמוד למדד המחירים לצרכן | J3: ישראל | K3: ישראל | L3: סחיר | M3: TASE | N3: נדל"ן מניב בישראל | O3: לא | P3: ilAA | Q3: S&P מעלות | R3: נייר ערך | S3: ILS | T3: 1.491 | U3: 46936 | V3: 0.032 | W3: 0.0223 | X3: החוב לא נחות | Z3: 542283.75 | AA3: 1 | AB3: 120.75 | AC3: 17.62677 | AD3: 672.4344 | AG3: שווי הוגן | AH3: 0.0019643186 | AI3: 0.0010034534 | AJ3: =AD3/'סכום נכסים'!$B$30 -> 0.00012106463
A4: 13908 | B4: 13908 | C4: איירפורט סיטי בע"מ | D4: 511659401 | E4: ח.פ. | F4: ארפורט אגח ה | G4: IL0011334872 | H4: ISIN | I4: צמוד למדד המחירים לצרכן | J4: ישראל | K4: ישראל | L4: סחיר | M4: TASE | N4: נדל"ן מניב בישראל | O4: לא | P4: ilAA | Q4: S&P מעלות | R4: נייר ערך | S4: ILS | T4: 1.633 | U4: 47177 | V4: 0.0234 | W4: 0.0243 | X4: החוב לא נחות | Z4: 3278142.2 | AA4: 1 | AB4: 119.82 | AC4: 0 | AD4: 3927.8699 | AG4: שווי הוגן | AH4: 0.0028489047 | AI4: 0.0058614409 | AJ4: =AD4/'סכום נכסים'!$B$30 -> 0.000707171
A5: 13908 | B5: 13908 | C5: שיכון ובינוי בע"מ | D5: 520036104 | E5: ח.פ. | F5: שכון ובי אגח 8 | G5: IL0011358889 | H5: ISIN | I5: צמוד למדד המחירים לצרכן | J5: ישראל | K5: ישראל | L5: סחיר | M5: TASE | N5: בנייה | O5: לא | P5: ilA | Q5: S&P מעלות | R5: נייר ערך | S5: ILS | T5: 1.775 | U5: 47239 | V5: 0.039 | W5: 0.0266 | X5: החוב לא נחות | Z5: 4172877.2 | AA5: 1 | AB5: 123.35 | AC5: 0 | AD5: 5147.2441 | AG5: שווי הוגן | AH5: 0.0040308631 | AI5: 0.0076810758 | AJ5: =AD5/'סכום נכסים'!$B$30 -> 0.00092670627
A6: 13908 | B6: 13908 | C6: קרסו מוטורס בע"מ | D6: 514065283 | E6: ח.פ. | F6: קרסו מוט' אגח א | G6: IL0011364648 | H6: ISIN | I6: לא צמוד למדד המחירים לצרכן | J6: ישראל | K6: ישראל | L6: סחיר | M6: TASE | N6: מסחר | O6: לא | P6: ilAA- | Q6: S&P מעלות | R6: נייר ערך | S6: ILS | T6: 0.17 | U6: 46266 | V6: 0.0275 | W6: 0.0359 | X6: החוב לא נחות | Z6: 340643.25 | AA6: 1 | AB6: 100.77 | AC6: 0 | AD6: 343.2662 | AG6: שווי הוגן | AH6: 0.0074077447 | AI6: 0.00051224571 | AJ6: =AD6/'סכום נכסים'!$B$30 -> 6.180141e-05
A7: 13908 | B7: 13908 | C7: ריט 1 בע"מ | D7: 513821488 | E7: ח.פ. | F7: ריט 1 אגח ה | G7: IL0011367534 | H7: ISIN | I7: צמוד למדד המחירים לצרכן | J7: ישראל | K7: ישראל | L7: סחיר | M7: TASE | N7: נדל"ן מניב בישראל | O7: לא | P7: ilAA | Q7: S&P מעלות | R7: נייר ערך | S7: ILS | T7: 1.192 | U7: 47016 | V7: 0.04 | W7: 0.0235 | X7: החוב לא נחות | Z7: 1518130.4 | AA7: 1 | AB7: 123.73 | AC7: 0 | AD7: 1878.3827 | AG7: שווי הוגן | AH7: 0.0025235063 | AI7: 0.0028030534 | AJ7: =AD7/'סכום נכסים'!$B$30 -> 0.00033818273
A8: 13908 | B8: 13908 | C8: ריט 1 בע"מ | D8: 513821488 | E8: ח.פ. | F8: ריט 1 אגח ו | G8: IL0011385445 | H8: ISIN | I8: צמוד למדד המחירים לצרכן | J8: ישראל | K8: ישראל | L8: סחיר | M8: TASE | N8: נדל"ן מניב בישראל | O8: לא | P8: ilAA | Q8: S&P מעלות | R8: נייר ערך | S8: ILS | T8: 2.584 | U8: 48112 | V8: 0.035 | W8: 0.0239 | X8: החוב לא נחות | Z8: 212655.79 | AA8: 1 | AB8: 125.94 | AC8: 0 | AD8: 267.8187 | AG8: שווי הוגן | AH8: 0.0003143071 | AI8: 0.0003996577 | AJ8: =AD8/'סכום נכסים'!$B$30 -> 4.8217894e-05
A9: 13908 | B9: 13908 | C9: קבוצת עזריאלי בע"מ | D9: 510960719 | E9: ח.פ. | F9: עזריאלי אגח ד | G9: IL0011386500 | H9: ISIN | I9: צמוד למדד המחירים לצרכן | J9: ישראל | K9: ישראל | L9: סחיר | M9: TASE | N9: נדל"ן מניב בישראל | O9: לא | P9: Aa1.il | Q9: מידרוג Moodys | R9: נייר ערך | S9: ILS | T9: 2.218 | U9: 47669 | V9: 0.0134 | W9: 0.0231 | X9: החוב לא נחות | Z9: 2523509.4 | AA9: 1 | AB9: 118.34 | AC9: 27.53381 | AD9: 3013.8548 | AG9: שווי הוגן | AH9: 0.0014280434 | AI9: 0.0044974839 | AJ9: =AD9/'סכום נכסים'!$B$30 -> 0.00054261235
A10: 13908 | B10: 13908 | C10: סלע קפיטל נדל"ן בע"מ | D10: 513992529 | E10: ח.פ. | F10: סלע נדלן אגח ג | G10: IL0011389736 | H10: ISIN | I10: צמוד למדד המחירים לצרכן | J10: ישראל | K10: ישראל | L10: סחיר | M10: TASE | N10: נדל"ן מניב בישראל | O10: לא | P10: Aa3.il | Q10: מידרוג Moodys | R10: נייר ערך | S10: ILS | T10: 1.747 | U10: 47221 | V10: 0.0196 | W10: 0.024 | X10: החוב לא נחות | Z10: 2250000 | AA10: 1 | AB10: 119.64 | AC10: 0 | AD10: 2691.9 | AG10: שווי הוגן | AH10: 0.0026198756 | AI10: 0.0040170405 | AJ10: =AD10/'סכום נכסים'!$B$30 -> 0.00048464782
A11: 13908 | B11: 13908 | C11: קבוצת אשטרום בע"מ | D11: 510381601 | E11: ח.פ. | F11: אשטרום קב אגח ג | G11: IL0011401028 | H11: ISIN | I11: לא צמוד למדד המחירים לצרכן | J11: ישראל | K11: ישראל | L11: סחיר | M11: TASE | N11: בנייה | O11: לא | P11: ilA | Q11: S&P מעלות | R11: נייר ערך | S11: ILS | T11: 1.233 | U11: 47133 | V11: 0.043 | W11: 0.041 | X11: החוב לא נחות | Z11: 6876275 | AA11: 1 | AB11: 102.27 | AC11: 0 | AD11: 7032.3664 | AG11: שווי הוגן | AH11: 0.011355827 | AI11: 0.010494187 | AJ11: =AD11/'סכום נכסים'!$B$30 -> 0.0012661024
A12: 13908 | B12: 13908 | C12: רבוע כחול נדל"ן בע"מ | D12: 513765859 | E12: ח.פ. | F12: רבוע נדלן אגח ו | G12: IL0011406076 | H12: ISIN | I12: צמוד למדד המחירים לצרכן | J12: ישראל | K12: ישראל | L12: סחיר | M12: TASE | N12: נדל"ן מניב בישראל | O12: לא | P12: ilAA | Q12: S&P מעלות | R12: נייר ערך | S12: ILS | T12: 0.416 | U12: 46356 | V12: 0.0215 | W12: 0.0348 | X12: החוב לא נחות | Z12: 196428.57 | AA12: 1 | AB12: 120.56 | AC12: 0 | AD12: 236.81428 | AG12: שווי הוגן | AH12: 0.00028042636 | AI12: 0.00035339075 | AJ12: =AD12/'סכום נכסים'!$B$30 -> 4.263588e-05
A13: 13908 | B13: 13908 | C13: ביג מרכזי קניות בע"מ | D13: 513623314 | E13: ח.פ. | F13: ביג אגח ט | G13: IL0011410508 | H13: ISIN | I13: צמוד למדד המחירים לצרכן | J13: ישראל | K13: ישראל | L13: סחיר | M13: TASE | N13: נדל"ן מניב בישראל | O13: לא | P13: Aa3.il | Q13: מידרוג Moodys | R13: נייר ערך | S13: ILS | T13: 0.471 | U13: 46376 | V13: 0.0195 | W13: 0.0381 | X13: החוב לא נחות | Z13: 66676.05 | AA13: 1 | AB13: 119.44 | AC13: 0 | AD13: 79.63787 | AG13: שווי הוגן | AH13: 0.00039599536 | AI13: 0.00011884117 | AJ13: =AD13/'סכום נכסים'!$B$30 -> 1.4337947e-05
... A272: 13908 | B272: 13908 | C272: קבוצת חג'ג' ייזום נדל"ן בע"מ | D272: 520033309 | E272: ח.פ. | F272: חג'ג' אגח יא | G272: IL0082303285 | H272: ISIN | I272: לא צמוד למדד המחירים לצרכן | J272: ישראל | K272: ישראל | L272: סחיר | M272: TASE | N272: בנייה | O272: לא | P272: NR | Q272: NR | R272: NR | S272: ILS | T272: 0.993 | U272: 46569 | V272: 0.029 | W272: 0.0638 | X272: החוב לא נחות | Z272: 666666.67 | AA272: 1 | AB272: 96.77 | AC272: 20.43334 | AD272: 665.56668 | AG272: שווי הוגן | AH272: 0.0054017556 | AI272: 0.00099320492 | AJ272: =AD272/'סכום נכסים'!$B$30 -> 0.00011982817
A273: 13908 | B273: 13908 | C273: ISRAEL ELECTRIC CORP LTD | D273: 213800T8ZHTFZIBYPE21 | E273: LEI | F273: ISRELE 4.25 14/8/28 | G273: IL0060002446 | H273: ISIN | I273: צמוד למט"ח | J273: חו"ל | K273: ישראל | L273: סחיר | M273: NYSE | N273: Energy Equipment & Services | O273: לא | P273: Baa2 | Q273: Moodys | R273: נייר ערך | S273: USD | T273: 2.003 | U273: 46979 | V273: 0.0425 | W273: 0.05015 | X273: החוב לא נחות | Z273: 3500000 | AA273: 2.978 | AB273: 100.1624 | AC273: 0 | AD273: 10439.927 | AG273: שווי הוגן | AH273: 0.0035 | AI273: 0.015579186 | AJ273: =AD273/'סכום נכסים'!$B$30 -> 0.0018795973
A274: 13908 | B274: 13908 | C274: LEVIATHAN BOND LTD | D274: 213800CYKA4XE2HZZB09 | E274: LEI | F274: LVIATH 6.5 6/27 | G274: IL0011677825 | H274: ISIN | I274: לא צמוד למדד המחירים לצרכן | J274: חו"ל | K274: ישראל | L274: סחיר | M274: FWB | N274: Energy Equipment & Services | O274: לא | P274: Ba3 | Q274: Moodys | R274: נייר ערך | S274: USD | T274: 0.483 | U274: 46568 | V274: 0.065 | W274: 0.05981 | X274: החוב לא נחות | Z274: 100000 | AA274: 2.978 | AB274: 100.5963 | AC274: 0 | AD274: 299.57578 | AG274: שווי הוגן | AH274: 0.00016666667 | AI274: 0.00044704783 | AJ274: =AD274/'סכום נכסים'!$B$30 -> 5.3935417e-05
A275: 13908 | B275: 13908 | C275: LEVIATHAN BOND LTD | D275: 213800CYKA4XE2HZZB09 | E275: LEI | F275: LVIATH 6.75 6/30 | G275: IL0011677908 | H275: ISIN | I275: לא צמוד למדד המחירים לצרכן | J275: חו"ל | K275: ישראל | L275: סחיר | M275: NYSE | N275: Oil, Gas & Consumable Fuels | O275: לא | P275: Ba3 | Q275: Moodys | R275: נייר ערך | S275: USD | T275: 3.164 | U275: 47664 | V275: 0.0675 | W275: 0.05876 | X275: החוב לא נחות | Z275: 840000 | AA275: 2.978 | AB275: 103.1745 | AC275: 0 | AD275: 2580.9307 | AG275: שווי הוגן | AH275: 0.0015272727 | AI275: 0.0038514445 | AJ275: =AD275/'סכום נכסים'!$B$30 -> 0.00046466899
A276: 13908 | B276: 13908 | C276: ENERGEAN ISRAEL FINANCE | D276: 549300RVMKU0CYUZBB05 | E276: LEI | F276: ENOIGA 5.875 30/3/31 | G276: IL0011736811 | H276: ISIN | I276: צמוד למט"ח | J276: חו"ל | K276: ישראל | L276: סחיר | M276: NYSE | N276: Energy Equipment & Services | O276: לא | P276: Ba3 | Q276: Moodys | R276: נייר ערך | S276: USD | T276: 4.134 | U276: 47937 | V276: 0.05875 | W276: 0.06865 | X276: החוב לא נחות | Z276: 440000 | AA276: 2.978 | AB276: 97.5364 | AC276: 0 | AD276: 1278.039 | AG276: שווי הוגן | AH276: 0.000704 | AI276: 0.0019071787 | AJ276: =AD276/'סכום נכסים'!$B$30 -> 0.00023009725
A277: 13908 | B277: 13908 | C277: Bank Hapoalim BM | D277: B6ARUI4946ST4S7WOU88 | E277: LEI | F277: HAPOAL 3.255 1/32 | G277: IL0066204707 | H277: ISIN | I277: צמוד למט"ח | J277: חו"ל | K277: ישראל | L277: סחיר | M277: NYSE | N277: Banks | O277: לא | P277: NR | Q277: NR | R277: NR | S277: USD | T277: 0.285 | U277: 48234 | V277: 0.03255 | W277: 0.06166 | X277: החוב לא נחות | Z277: 680000 | AA277: 2.978 | AB277: 100.7149 | AC277: 0 | AD277: 2039.517 | AG277: שווי הוגן | AH277: 0.00068 | AI277: 0.0030435092 | AJ277: =AD277/'סכום נכסים'!$B$30 -> 0.00036719324
A278: 13908 | B278: 13908 | C278: ISRAEL ELECTRIC CORP LTD | D278: 213800T8ZHTFZIBYPE21 | E278: LEI | F278: ISRELE 3.75 2/32 | G278: IL0060004004 | H278: ISIN | I278: צמוד למט"ח | J278: חו"ל | K278: ישראל | L278: סחיר | M278: NYSE | N278: Electric Utilities | O278: לא | P278: Baa2 | Q278: Moodys | R278: נייר ערך | S278: USD | T278: 5.023 | U278: 48266 | V278: 0.0375 | W278: 0.05329 | X278: החוב לא נחות | Z278: 2149000 | AA278: 2.978 | AB278: 93.8153 | AC278: 0 | AD278: 6003.9184 | AG278: שווי הוגן | AH278: 0.004298 | AI278: 0.0089594649 | AJ278: =AD278/'סכום נכסים'!$B$30 -> 0.0010809413
A279: 13908 | B279: 13908 | C279: Israel Discount Bank Ltd | D279: 549300XWZ7BG5G23OF51 | E279: LEI | F279: IDBILI 5.375 26/1/28 | G279: IL0011920878 | H279: ISIN | I279: לא צמוד למדד המחירים לצרכן | J279: חו"ל | K279: ישראל | L279: סחיר | M279: NYSE | N279: Banks | O279: לא | P279: Baa1 | Q279: Moodys | R279: נייר ערך | S279: USD | T279: 1.413 | U279: 46778 | V279: 0.05375 | W279: 0.05116 | X279: החוב לא נחות | Z279: 433000 | AA279: 2.978 | AB279: 102.7112 | AC279: 0 | AD279: 1324.4342 | AG279: שווי הוגן | AH279: 0.00054125 | AI279: 0.0019764129 | AJ279: =AD279/'סכום נכסים'!$B$30 -> 0.00023845022
A280: 13908 | B280: 13908 | C280: TEVA PHARM FNC NL II | D280: 549300BAFGM4RC74ZJ94 | E280: LEI | F280: TEVA 7.875 9/31 | G280: XS2592804194 | H280: ISIN | I280: צמוד למט"ח | J280: חו"ל | K280: ישראל | L280: סחיר | M280: EURONEXT | N280: Pharmaceuticals | O280: לא | P280: Ba1 | Q280: Moodys | R280: נייר ערך | S280: EUR | T280: 4.178 | U280: 48106 | V280: 0.07875 | W280: 0.04148 | X280: החוב לא נחות | Z280: 8000 | AA280: 3.3945 | AB280: 119.6265 | AC280: 0 | AD280: 32.48577 | AG280: שווי הוגן | AH280: 1.6e-05 | AI280: 4.8477527e-05 | AJ280: =AD280/'סכום נכסים'!$B$30 -> 5.8487156e-06
A281: 13908 | B281: 13908 | C281: TEVA PHARM FNC NL II | D281: 549300BAFGM4RC74ZJ94 | E281: LEI | F281: TEVA 7.375 15/9/29 | G281: XS2592804434 | H281: ISIN | I281: צמוד למט"ח | J281: חו"ל | K281: ישראל | L281: סחיר | M281: EURONEXT | N281: Pharmaceuticals | O281: לא | P281: Ba1 | Q281: Moodys | R281: נייר ערך | S281: EUR | T281: 2.665 | U281: 47376 | V281: 0.07375 | W281: 0.03882 | X281: החוב לא נחות | Z281: 5067 | AA281: 3.3945 | AB281: 112.6215 | AC281: 0 | AD281: 19.37082 | AG281: שווי הוגן | AH281: 6.33375e-06 | AI281: 2.8906486e-05 | AJ281: =AD281/'סכום נכסים'!$B$30 -> 3.4875091e-06
A282: 13908 | B282: 13908 | C282: ENERGEAN ISRAEL FINANCE | D282: 549300RVMKU0CYUZBB05 | E282: LEI | F282: ENOIGA 8.5 30/9/33 | G282: IL0011971442 | H282: ISIN | I282: צמוד למט"ח | J282: חו"ל | K282: ישראל | L282: סחיר | M282: NYSE | N282: Energy Equipment & Services | O282: לא | P282: Ba3 | Q282: Moodys | R282: נייר ערך | S282: USD | T282: 3.599 | U282: 48852 | V282: 0.085 | W282: 0.07433 | X282: החוב לא נחות | Z282: 3280000 | AA282: 2.978 | AB282: 108.0482 | AC282: 0 | AD282: 10553.975 | AG282: שווי הוגן | AH282: 0.0043733333 | AI282: 0.015749376 | AJ282: =AD282/'סכום נכסים'!$B$30 -> 0.0019001304
A283: 13908 | B283: 13908 | C283: ORMAT TECHNOLOGIES INC | D283: 5493000TSHHWY24VHM09 | E283: LEI | F283: ORA 2.5 07/27 | G283: US686688AB85 | H283: ISIN | I283: צמוד למט"ח | J283: חו"ל | K283: ארה"ב | L283: סחיר | M283: FWB | N283: Electric Utilities | O283: לא | P283: NR | Q283: NR | R283: NR | S283: USD | T283: 1.94 | U283: 46583 | V283: 0.025 | W283: -0.0386 | X283: החוב לא נחות | Z283: 700000 | AA283: 2.978 | AB283: 139.4989 | AC283: 0 | AD283: 2907.9941 | AG283: שווי הוגן | AH283: 0.0014692394 | AI283: 0.0043395111 | AJ283: =AD283/'סכום נכסים'!$B$30 -> 0.00052355325
A284: 13908 | B284: 13908 | C284: ITHACA ENERGY NORTH | D284: 213800CYKA4XE2HZZB09 | E284: LEI | F284: IAECN 8.125 10/29 | G284: US46567TAC80 | H284: ISIN | I284: צמוד למט"ח | J284: חו"ל | K284: בריטניה | L284: סחיר | M284: אחר | N284: Diversified Telecommunication Services | O284: לא | P284: B1 | Q284: Moodys | R284: נייר ערך | S284: USD | T284: 2.103 | U284: 47406 | V284: 0.08125 | W284: 0.06822 | X284: החוב לא נחות | Z284: 206000 | AA284: 2.978 | AB284: 105.4988 | AC284: 0 | AD284: 647.20138 | AG284: שווי הוגן | AH284: 0.00027466667 | AI284: 0.00096579894 | AJ284: =AD284/'סכום נכסים'!$B$30 -> 0.00011652169
... A296: 13908 | B296: 13908 | C296: South Bow USA Infrastructure Holdings LLC | D296: 529900MUF4C20K50JS49 | E296: LEI | F296: SOBOCN 7.625 10/55 | G296: US836720AG73 | H296: ISIN | I296: צמוד למט"ח | J296: חו"ל | K296: אוסטרליה | L296: סחיר | M296: NYSE | N296: Financial Services | O296: לא | P296: Ba1 | Q296: Moodys | R296: נייר ערך | S296: USD | T296: 3.005 | U296: 47392 | V296: 0.05026 | W296: 0.07599 | X296: החוב לא נחות | Z296: 22000 | AA296: 2.978 | AB296: 107.1978 | AC296: 0 | AD296: 70.23171 | AG296: שווי הוגן | AH296: 4.9285583e-05 | AI296: 0.00010480465 | AJ296: =AD296/'סכום נכסים'!$B$30 -> 1.2644469e-05

Sheet מניות מבכ ויהש
A1: מספר קופה/קרן/ח.פ. עבור חברת ביטוח | B1: מספר מסלול | C1: שם מנפיק | D1: מספר מנפיק | E1: סוג מספר מזהה מנפיק | F1: שם נייר ערך | G1: מספר נייר ערך | H1: סוג מספר נייר ערך | I1: מאפיין עיקרי | J1: ישראל/חו"ל | K1: מדינה לפי חשיפה כלכלית | L1: סטאטוס סחירות | M1: זירת מסחר | N1: ענף מסחר | O1: בעל עניין/צד קשור | P1: מטבע פעילות | Q1: ערך נקוב (יחידות) | R1: שער חליפין | S1: שער נייר הערך | T1: סכום לקבל (במטבע הפעילות) | U1: שווי הוגן (באלפי ש"ח) | V1: שיעור מערך נקוב מונפק | W1: שיעור מנכסי אפיק ההשקעה | X1: שיעור מסך נכסי ההשקעה
A2: 13908 | B2: 13908 | C2: מבטח שמיר אחזקות בע"מ | D2: 520034125 | E2: ח.פ. | F2: מבטח שמיר | G2: IL0001270193 | H2: ISIN | I2: מניות | J2: ישראל | K2: ישראל | L2: סחיר | M2: TASE | N2: השקעה ואחזקות | O2: לא | P2: ILS | Q2: 1000 | R2: 1 | S2: 41980 | T2: 0 | U2: 419.8 | V2: 0.00010280405 | W2: 0.00039861913 | X2: =U2/'סכום נכסים'!$B$30 -> 7.5580503e-05
A3: 13908 | B3: 13908 | C3: להב אל.אר רילאסטייט בע"מ | D3: 520034257 | E3: ח.פ. | F3: להב | G3: IL0001360101 | H3: ISIN | I3: מניות | J3: ישראל | K3: ישראל | L3: סחיר | M3: TASE | N3: השקעה ואחזקות | O3: לא | P3: ILS | Q3: 1600000 | R3: 1 | S3: 1110 | T3: 0 | U3: 17760 | V3: 0.0054581421 | W3: 0.016863925 | X3: =U3/'סכום נכסים'!$B$30 -> 0.0031974982
A4: 13908 | B4: 13908 | C4: וואן טכנולוגיות תוכנה בע"מ | D4: 520034695 | E4: ח.פ. | F4: וואן טכנולוגיות | G4: IL0001610182 | H4: ISIN | I4: מניות | J4: ישראל | K4: ישראל | L4: סחיר | M4: TASE | N4: שרותי מידע | O4: לא | P4: ILS | Q4: 196974 | R4: 1 | S4: 5681 | T4: 0 | U4: 11190.093 | V4: 0.0026744803 | W4: 0.0106255 | X4: =U4/'סכום נכסים'!$B$30 -> 0.0020146566
A5: 13908 | B5: 13908 | C5: כלל החזקות עסקי ביטוח בע"מ | D5: 520036120 | E5: ח.פ. | F5: כלל עסקי ביטוח | G5: IL0002240146 | H5: ISIN | I5: מניות | J5: ישראל | K5: ישראל | L5: סחיר | M5: TASE | N5: ביטוח | O5: לא | P5: ILS | Q5: 124630 | R5: 1 | S5: 22840 | T5: 0 | U5: 28465.492 | V5: 0.0015330095 | W5: 0.027029275 | X5: =U5/'סכום נכסים'!$B$30 -> 0.0051249076
A6: 13908 | B6: 13908 | C6: מבנה נדל"ן (כ.ד) בע"מ | D6: 520024126 | E6: ח.פ. | F6: מבנה | G6: IL0002260193 | H6: ISIN | I6: מניות | J6: ישראל | K6: ישראל | L6: סחיר | M6: TASE | N6: נדל"ן מניב בישראל | O6: לא | P6: ILS | Q6: 390542 | R6: 1 | S6: 1300 | T6: 0 | U6: 5077.046 | V6: 0.0005395146 | W6: 0.0048208853 | X6: =U6/'סכום נכסים'!$B$30 -> 0.00091406786
A7: 13908 | B7: 13908 | C7: בזק החברה הישראלית לתקשורת בע" | D7: 520031931 | E7: ח.פ. | F7: בזק | G7: IL0002300114 | H7: ISIN | I7: מניות | J7: ישראל | K7: ישראל | L7: סחיר | M7: TASE | N7: תקשורת ומדיה | O7: לא | P7: ILS | Q7: 2948142 | R7: 1 | S7: 702.7 | T7: 0 | U7: 20716.594 | V7: 0.0010685327 | W7: 0.019671345 | X7: =U7/'סכום נכסים'!$B$30 -> 0.0037298013
A8: 13908 | B8: 13908 | C8: ישראמקו נגב 2 שותפות מוגבלת | D8: 550010003 | E8: ח.פ. | F8: ישראמקו יהש | G8: IL0002320179 | H8: ISIN | I8: יחידות השתתפות | J8: ישראל | K8: ישראל | L8: סחיר | M8: TASE | N8: חיפושי נפט וגז | O8: לא | P8: ILS | Q8: 667292 | R8: 1 | S8: 187 | T8: 0 | U8: 1247.836 | V8: 0.00025633892 | W8: 0.0011848769 | X8: =U8/'סכום נכסים'!$B$30 -> 0.00022465954
A9: 13908 | B9: 13908 | C9: פורמולה מערכות (1985)בע"מ | D9: 520036690 | E9: ח.פ. | F9: פורמולה מערכות | G9: IL0002560162 | H9: ISIN | I9: מניות | J9: ישראל | K9: ישראל | L9: סחיר | M9: TASE | N9: שרותי מידע | O9: לא | P9: ILS | Q9: 3100 | R9: 1 | S9: 30990 | T9: 0 | U9: 960.69 | V9: 0.00020215633 | W9: 0.00091221869 | X9: =U9/'סכום נכסים'!$B$30 -> 0.00017296197
A10: 13908 | B10: 13908 | C10: נייס בע"מ | D10: 520036872 | E10: ח.פ. | F10: נייס | G10: IL0002730112 | H10: ISIN | I10: מניות | J10: ישראל | K10: ישראל | L10: סחיר | M10: TASE | N10: תוכנה ואינטרנט | O10: לא | P10: ILS | Q10: 16810 | R10: 1 | S10: 26760 | T10: 0 | U10: 4498.356 | V10: 0.00028687383 | W10: 0.0042713929 | X10: =U10/'סכום נכסים'!$B$30 -> 0.00080988091
A11: 13908 | B11: 13908 | C11: איי.סי.אל גרופ בע"מ | D11: 520027830 | E11: ח.פ. | F11: איי.סי.אל | G11: IL0002810146 | H11: ISIN | I11: מניות | J11: ישראל | K11: ישראל | L11: סחיר | M11: TASE | N11: כימיה, גומי ופלסטיק | O11: לא | P11: ILS | Q11: 501190 | R11: 1 | S11: 1494 | T11: 0 | U11: 7487.7786 | V11: 0.00038830315 | W11: 0.0071099851 | X11: =U11/'סכום נכסים'!$B$30 -> 0.0013480945
A12: 13908 | B12: 13908 | C12: קבוצת סקופ מתכות בע"מ | D12: 520037425 | E12: ח.פ. | F12: סקופ | G12: IL0002880198 | H12: ISIN | I12: מניות | J12: ישראל | K12: ישראל | L12: סחיר | M12: TASE | N12: מסחר | O12: לא | P12: ILS | Q12: 20000 | R12: 1 | S12: 28200 | T12: 0 | U12: 5640 | V12: 0.0015114569 | W12: 0.0053554356 | X12: =U12/'סכום נכסים'!$B$30 -> 0.0010154217
A13: 13908 | B13: 13908 | C13: עשות - אשקלון תעשיות בע"מ | D13: 520037581 | E13: ח.פ. | F13: עשות | G13: IL0003120172 | H13: ISIN | I13: מניות | J13: ישראל | K13: ישראל | L13: סחיר | M13: TASE | N13: מתכת ומוצרי בניה | O13: לא | P13: ILS | Q13: 1047 | R13: 1 | S13: 8351 | T13: 0 | U13: 87.43497 | V13: 4.1312265e-05 | W13: 8.3023467e-05 | X13: =U13/'סכום נכסים'!$B$30 -> 1.5741732e-05
... A35: 13908 | B35: 13908 | C35: בנק מזרחי טפחות בע"מ | D35: 520000522 | E35: ח.פ. | F35: מזרחי טפחות | G35: IL0006954379 | H35: ISIN | I35: מניות | J35: ישראל | K35: ישראל | L35: סחיר | M35: TASE | N35: בנקים | O35: לא | P35: ILS | Q35: 77261 | R35: 1 | S35: 19700 | T35: 0 | U35: 15220.417 | V35: 0.00029705346 | W35: 0.014452476 | X35: =U35/'סכום נכסים'!$B$30 -> 0.0027402734
A36: 13908 | B36: 13908 | C36: אזורים-חברה להשקעות בפתוח ובבנ | D36: 520025990 | E36: ח.פ. | F36: אזורים חסום | G36: 7150130 | H36: פנימי | I36: מניות | J36: ישראל | K36: ישראל | L36: חסום | M36: TASE | N36: בנייה | O36: לא | P36: ILS | Q36: 240000 | R36: 1 | S36: 1707.0055 | T36: 0 | U36: 4096.8132 | V36: 0 | W36: 0.0038901098 | X36: =U36/'סכום נכסים'!$B$30 -> 0.00073758742
A37: 13908 | B37: 13908 | C37: אנלייט אנרגיה מתחדשת בע"מ | D37: 520041146 | E37: ח.פ. | F37: אנלייט אנרגיה | G37: IL0007200111 | H37: ISIN | I37: מניות | J37: ישראל | K37: ישראל | L37: סחיר | M37: TASE | N37: אנרגיה מתחדשת | O37: לא | P37: ILS | Q37: 230904 | R37: 1 | S37: 26300 | T37: 0 | U37: 60727.752 | V37: 0.0016521754 | W37: 0.057663753 | X37: =U37/'סכום נכסים'!$B$30 -> 0.010933383
A38: 13908 | B38: 13908 | C38: חברת גב ים לקרקעות בע"מ | D38: 520001736 | E38: ח.פ. | F38: גב ים | G38: IL0007590198 | H38: ISIN | I38: מניות | J38: ישראל | K38: ישראל | L38: סחיר | M38: TASE | N38: נדל"ן מניב בישראל | O38: לא | P38: ILS | Q38: 30000 | R38: 1 | S38: 3662 | T38: 0 | U38: 1098.6 | V38: 0.000135994 | W38: 0.0010431705 | X38: =U38/'סכום נכסים'!$B$30 -> 0.00019779119
A39: 13908 | B39: 13908 | C39: הפניקס פיננסים בע"מ | D39: 520017450 | E39: ח.פ. | F39: הפניקס | G39: IL0007670123 | H39: ISIN | I39: מניות | J39: ישראל | K39: ישראל | L39: סחיר | M39: TASE | N39: ביטוח | O39: לא | P39: ILS | Q39: 221601 | R39: 1 | S39: 16460 | T39: 0 | U39: 36475.525 | V39: 0.00087909568 | W39: 0.034635164 | X39: =U39/'סכום נכסים'!$B$30 -> 0.0065670283
A40: 13908 | B40: 13908 | C40: שופרסל בע"מ | D40: 520022732 | E40: ח.פ. | F40: שופרסל | G40: IL0007770378 | H40: ISIN | I40: מניות | J40: ישראל | K40: ישראל | L40: סחיר | M40: TASE | N40: רשתות שיווק | O40: לא | P40: ILS | Q40: 61290 | R40: 1 | S40: 4261 | T40: 0 | U40: 2611.5669 | V40: 0.00022971951 | W40: 0.0024798011 | X40: =U40/'סכום נכסים'!$B$30 -> 0.0004701847
A41: 13908 | B41: 13908 | C41: כהן פיתוח גז ונפט בע"מ | D41: 520032970 | E41: ח.פ. | F41: כהן פיתוח | G41: IL0008100104 | H41: ISIN | I41: מניות | J41: ישראל | K41: ישראל | L41: סחיר | M41: TASE | N41: חיפושי נפט וגז | O41: לא | P41: ILS | Q41: 19750 | R41: 1 | S41: 15340 | T41: 0 | U41: 3029.65 | V41: 0.0027720835 | W41: 0.00287679 | X41: =U41/'סכום נכסים'!$B$30 -> 0.0005454561
A42: 13908 | B42: 13908 | C42: סנו-מפעלי ברונוס בע"מ | D42: 520032988 | E42: ח.פ. | F42: סנו | G42: IL0008130143 | H42: ISIN | I42: מניות | J42: ישראל | K42: ישראל | L42: סחיר | M42: TASE | N42: כימיה, גומי ופלסטיק | O42: לא | P42: ILS | Q42: 12651 | R42: 1 | S42: 36970 | T42: 0 | U42: 4677.0747 | V42: 0.001029541 | W42: 0.0044410944 | X42: =U42/'סכום נכסים'!$B$30 -> 0.0008420573
A43: 13908 | B43: 13908 | C43: דלק מערכות רכב בע"מ | D43: 520033291 | E43: ח.פ. | F43: דלק רכב | G43: IL0008290103 | H43: ISIN | I43: מניות | J43: ישראל | K43: ישראל | L43: סחיר | M43: TASE | N43: מסחר | O43: לא | P43: ILS | Q43: 234311 | R43: 1 | S43: 1611 | T43: 0 | U43: 3774.7502 | V43: 0.0024161762 | W43: 0.0035842964 | X43: =U43/'סכום נכסים'!$B$30 -> 0.00067960343
A44: 13908 | B44: 13908 | C44: COGNYTE SOFTWARE LTD | D44: 516196425 | E44: ח.פ. | F44: COGNYTE SOFTWARE LTD | G44: IL0011691438 | H44: ISIN | I44: מניות | J44: ישראל | K44: ישראל | L44: סחיר | M44: NASDAQ | N44: תוכנה ואינטרנט | O44: לא | P44: USD | Q44: 20000 | R44: 2.978 | S44: 878 | T44: 0 | U44: 522.9368 | V44: 0.00027134867 | W44: 0.00049655219 | X44: =U44/'סכום נכסים'!$B$30 -> 9.4149181e-05
A45: 13908 | B45: 13908 | C45: אנליסט אי.אמ.אס.-שרותי ניהול ה | D45: 520041963 | E45: ח.פ. | F45: אנליסט | G45: IL0010806136 | H45: ISIN | I45: מניות | J45: ישראל | K45: ישראל | L45: סחיר | M45: TASE | N45: שרותים פיננסיים | O45: לא | P45: ILS | Q45: 15000 | R45: 1 | S45: 14950 | T45: 0 | U45: 2242.5 | V45: 0.0011919909 | W45: 0.0021293554 | X45: =U45/'סכום נכסים'!$B$30 -> 0.00040373815
A46: 13908 | B46: 13908 | C46: ישרוטל בע"מ | D46: 520042482 | E46: ח.פ. | F46: ישרוטל | G46: IL0010809858 | H46: ISIN | I46: מניות | J46: ישראל | K46: ישראל | L46: סחיר | M46: TASE | N46: מלונאות ותיירות | O46: לא | P46: ILS | Q46: 14685 | R46: 1 | S46: 13750 | T46: 0 | U46: 2019.1875 | V46: 0.00024450985 | W46: 0.00191731 | X46: =U46/'סכום נכסים'!$B$30 -> 0.00036353313
A47: 13908 | B47: 13908 | C47: איסתא בע"מ | D47: 520042763 | E47: ח.פ. | F47: איסתא | G47: IL0010810740 | H47: ISIN | I47: מניות | J47: ישראל | K47: ישראל | L47: סחיר | M47: TASE | N47: מלונאות ותיירות | O47: לא | P47: ILS | Q47: 13815 | R47: 1 | S47: 9248 | T47: 41.445 | U47: 1319.0562 | V47: 0.00082441126 | W47: 0.0012525036 | X47: =U47/'סכום נכסים'!$B$30 -> 0.00023748197
A48: 13908 | B48: 13908 | C48: אלביט מערכות בע"מ | D48: 520043027 | E48: ח.פ. | F48: אלביט מערכות | G48: IL0010811243 | H48: ISIN | I48: מניות | J48: ישראל | K48: ישראל | L48: סחיר | M48: TASE | N48: ביטחוניות | O48: לא | P48: ILS | Q48: 13007 | R48: 1 | S48: 226000 | T48: 38.74785 | U48: 29434.568 | V48: 0.00027763977 | W48: 0.027949456 | X48: =U48/'סכום נכסים'!$B$30 -> 0.0052993793
... A129: 13908 | B129: 13908 | C129: בתי זקוק לנפט בע"מ | D129: 520036658 | E129: ח.פ. | F129: בזן | G129: IL0025902482 | H129: ISIN | I129: מניות | J129: ישראל | K129: ישראל | L129: סחיר | M129: TASE | N129: אנרגיה | O129: לא | P129: ILS | Q129: 3058572 | R129: 1 | S129: 157.5 | T129: 0 | U129: 4817.2509 | V129: 0.00097996999 | W129: 0.0045741981 | X129: =U129/'סכום נכסים'!$B$30 -> 0.00086729453
A130: 13908 | B130: 13908 | C130: SOLAREDGE TECHNOLOGIES INC | D130: 5493000K6Y58XXPDF853 | E130: LEI | F130: SOLAREDGE TECHNOLOGIES INC | G130: US83417M1045 | H130: ISIN | I130: מניות | J130: חו"ל | K130: ארה"ב | L130: סחיר | M130: NASDAQ | N130: Semiconductors & Semiconductor Equipment | O130: לא | P130: USD | Q130: 5000 | R130: 2.978 | S130: 5844 | T130: 0 | U130: 870.1716 | V130: 8.221223e-05 | W130: 0.00082626737 | X130: =U130/'סכום נכסים'!$B$30 -> 0.00015666509
A131: 13908 | B131: 13908 | C131: ODDITY TECH LTD NO TRADE | D131: 254900QH12XZS53G0V57 | E131: LEI | F131: ODDITY TECH LTD NO TRADE | G131: IL0011974909 | H131: ISIN | I131: מניות | J131: חו"ל | K131: ישראל | L131: סחיר | M131: NASDAQ | N131: Software | O131: לא | P131: USD | Q131: 5542.55 | R131: 2.978 | S131: 1513 | T131: 0 | U131: 249.73145 | V131: 0 | W131: 0.00023713133 | X131: =U131/'סכום נכסים'!$B$30 -> 4.4961478e-05
A132: 13908 | B132: 13908 | C132: SHL TELEMEDICINE LTD | D132: 1729029 | E132: מספר תאגיד או שותפות בחו"ל | F132: SHL TELEMEDICINE LTD | G132: IL0010855885 | H132: ISIN | I132: מניות | J132: חו"ל | K132: שוויץ | L132: סחיר | M132: SIX | N132: Health Care Providers & Services | O132: לא | P132: CHF | Q132: 25000 | R132: 3.6802 | S132: 102 | T132: 0 | U132: 93.8451 | V132: 0.00067458274 | W132: 8.9110176e-05 | X132: =U132/'סכום נכסים'!$B$30 -> 1.6895807e-05
A133: 13908 | B133: 13908 | C133: PALO ALTO NETWORKS INC | D133: 549300QXR2YVZV231H43 | E133: LEI | F133: PALO ALTO NETWORKS INC | G133: US6974351057 | H133: ISIN | I133: מניות | J133: חו"ל | K133: ארה"ב | L133: סחיר | M133: NASDAQ | N133: Software | O133: לא | P133: USD | Q133: 7700 | R133: 2.978 | S133: 34102 | T133: 0 | U133: 7819.7932 | V133: 9.4478528e-06 | W133: 0.0074252481 | X133: =U133/'סכום נכסים'!$B$30 -> 0.0014078702
A134: 13908 | B134: 13908 | C134: ITHACA ENERGY PLC | D134: 213800CYKA4XE2HZZB09 | E134: LEI | F134: ITHACA ENERGY PLC | G134: GB00BPJHV584 | H134: ISIN | I134: מניות | J134: חו"ל | K134: ישראל | L134: סחיר | M134: LSE | N134: Energy Equipment & Services | O134: לא | P134: GBP | Q134: 770255 | R134: 3.9389 | S134: 217 | T134: 0 | U134: 6583.6876 | V134: 0.0004657676 | W134: 0.0062515098 | X134: =U134/'סכום נכסים'!$B$30 -> 0.0011853226
A135: 13908 | B135: 13908 | C135: SHL TELEMEDICINE LTD - RTS | D135: EQ0000000099507916 | E135: מספר תאגיד או שותפות בחו"ל | F135: RTS - LTD TELEMEDICINE SHL | G135: CH1501961093 | H135: ISIN | I135: מניות | J135: חו"ל | K135: שוויץ | L135: סחיר | M135: SIX | N135: Other | O135: לא | P135: CHF | Q135: 20754 | R135: 3.6802 | S135: 0.0001 | T135: 0 | U135: 0 | V135: 0.0012660472 | W135: 0 | X135: =U135/'סכום נכסים'!$B$30 -> 0
A136: 13908 | B136: 13908 | C136: CSG NV | D136: 315700RSAZS0EH10E702 | E136: LEI | F136: CSV NV | G136: NL0015073TS8 | H136: ISIN | I136: מניות | J136: חו"ל | K136: צכיה | L136: סחיר | M136: EURONEXT | N136: Industrial REITs | O136: לא | P136: EUR | Q136: 28350 | R136: 3.3945 | S136: 1277.4 | T136: 0 | U136: 1229.2941 | V136: 2.835e-05 | W136: 0.0011672704 | X136: =U136/'סכום נכסים'!$B$30 -> 0.00022132126

Sheet קרנות סל
A1: מספר קופה/קרן/ח.פ. עבור חברת ביטוח | B1: מספר מסלול | C1: שם מנפיק | D1: מספר מנפיק | E1: סוג מספר מזהה מנפיק | F1: שם נייר ערך | G1: מספר נייר ערך | H1: סוג מספר נייר ערך | I1: מאפיין עיקרי | J1: ישראל/חו"ל | K1: מדינה לפי חשיפה כלכלית | L1: זירת מסחר | M1: סיווג הקרן | N1: בעל עניין/צד קשור | O1: מטבע פעילות | P1: ערך נקוב (יחידות) | Q1: שער חליפין | R1: שער נייר הערך | S1: סכום לקבל (במטבע הפעילות) | T1: שווי הוגן (באלפי ש"ח) | U1: שיעור מערך נקוב מונפק | V1: שיעור מנכסי אפיק ההשקעה | W1: שיעור מסך נכסי ההשקעה
A2: 13908 | B2: 13908 | C2: מיטב קרנות נאמנות בע"מ | D2: 513534974 | E2: ח.פ. | F2: תכ.תא125 | G2: IL0011437188 | H2: ISIN | I2: עוקב אחר מדדי מניות בישראל | J2: ישראל | K2: ישראל | L2: TASE | M2: Large & Mid Cap מניות בארץ - מניות לפי שווי שוק-מניות | N2: לא | O2: ILS | P2: 1880000 | Q2: 1 | R2: 3930 | S2: 0 | T2: 73884 | U2: 0.0042841713 | V2: 0.17014892 | W2: =T2/'סכום נכסים'!$B$30 -> 0.013302024
A3: 13908 | B3: 13908 | C3: מיטב קרנות נאמנות בע"מ | D3: 513534974 | E3: ח.פ. | F3: תכ.תלבונד60 | G3: IL0011451015 | H3: ISIN | I3: עוקב אחר מדדים אחרים בישראל | J3: ישראל | K3: ישראל | L3: TASE | M3: 60 אג"ח בארץ - חברות והמרה-תל בונד צמוד מדד-תל בונד | N3: לא | O3: ILS | P3: 15040200 | Q3: 1 | R3: 407.77 | S3: 0 | T3: 61329.424 | U3: 0.011045029 | V3: 0.14123674 | W3: =T3/'סכום נכסים'!$B$30 -> 0.011041707
A4: 13908 | B4: 13908 | C4: קסם קרנות נאמנות בע"מ | D4: 510938608 | E4: ח.פ. | F4: קסם.תלבונד 20 צ | G4: IL0011459604 | H4: ISIN | I4: עוקב אחר מדדים אחרים בישראל | J4: ישראל | K4: ישראל | L4: TASE | M4: 20 אג"ח בארץ - חברות והמרה-תל בונד צמוד מדד-תל בונד | N4: לא | O4: ILS | P4: 3000 | Q4: 1 | R4: 4135.78 | S4: 0 | T4: 124.0734 | U4: 5.7499699e-05 | V4: 0.00028573107 | W4: =T4/'סכום נכסים'!$B$30 -> 2.2338089e-05
A5: 13908 | B5: 13908 | C5: קסם קרנות נאמנות בע"מ | D5: 510938608 | E5: ח.פ. | F5: STOX600.קסם | G5: IL0011462087 | H5: ISIN | I5: עוקב אחר מדדי מניות בחו"ל | J5: ישראל | K5: אירופה | L5: TASE | M5: מניות בחו"ל - מניות גיאוגרפי - חשופת מט"ח-אירופה - מדד אחר | N5: לא | O5: ILS | P5: 103320 | Q5: 1 | R5: 52590 | S5: 0 | T5: 54335.988 | U5: 0.052414773 | V5: 0.12513142 | W5: =T5/'סכום נכסים'!$B$30 -> 0.0097826138
A6: 13908 | B6: 13908 | C6: קסם קרנות נאמנות בע"מ | D6: 510938608 | E6: ח.פ. | F6: קסם.תלבונד 60 צ | G6: IL0011462327 | H6: ISIN | I6: עוקב אחר מדדים אחרים בישראל | J6: ישראל | K6: ישראל | L6: TASE | M6: אג"ח בארץ - חברות והמרה-תל בונד צמוד מדד-תל בונד צמודות | N6: לא | O6: ILS | P6: 1559524 | Q6: 1 | R6: 4056.02 | S6: 0 | T6: 63254.605 | U6: 0.021654101 | V6: 0.14567027 | W6: =T6/'סכום נכסים'!$B$30 -> 0.011388316
A7: 13908 | B7: 13908 | C7: אי.בי.אי קרנות נאמנות בעמ | D7: 513765339 | E7: ח.פ. | F7: IBI.תלבונד 60צד | G7: IL0011480063 | H7: ISIN | I7: עוקב אחר מדדים אחרים בישראל | J7: ישראל | K7: ישראל | L7: TASE | M7: 60 אג"ח בארץ - חברות והמרה-תל בונד צמוד מדד-תל בונד | N7: לא | O7: ILS | P7: 5495390 | Q7: 1 | R7: 408.38 | S7: 0 | T7: 22442.074 | U7: 0.0039974871 | V7: 0.051682293 | W7: =T7/'סכום נכסים'!$B$30 -> 0.0040404555
A8: 13908 | B8: 13908 | C8: אי.בי.אי קרנות נאמנות בעמ | D8: 513765339 | E8: ח.פ. | F8: IBI.תא 125 | G8: IL0011488082 | H8: ISIN | I8: עוקב אחר מדדי מניות בישראל | J8: ישראל | K8: ישראל | L8: TASE | M8: Large & Mid Cap מניות בארץ - מניות לפי שווי שוק-מניות | N8: לא | O8: ILS | P8: 160000 | Q8: 1 | R8: 3889 | S8: 0 | T8: 6222.4 | U8: 0.00039873037 | V8: 0.014329687 | W8: =T8/'סכום נכסים'!$B$30 -> 0.0011202766
A9: 13908 | B9: 13908 | C9: הראל קרנות נאמנות בע"מ | D9: 511776783 | E9: ח.פ. | F9: SP500.הרל | G9: IL0011490203 | H9: ISIN | I9: עוקב אחר מדדי מניות בחו"ל | J9: ישראל | K9: ארה"ב | L9: TASE | M9: S&P 500 - מניות בחו"ל - מניות גיאוגרפי - מנוטרלת מט"ח-ארה"ב | N9: לא | O9: ILS | P9: 145764 | Q9: 1 | R9: 2600 | S9: 0 | T9: 3789.864 | U9: 0.00038481711 | V9: 0.0087277523 | W9: =T9/'סכום נכסים'!$B$30 -> 0.0006823245
A10: 13908 | B10: 13908 | C10: מגדל קרנות נאמנות בע"מ | D10: 511303661 | E10: ח.פ. | F10: MTF.תא125 | G10: IL0011502833 | H10: ISIN | I10: עוקב אחר מדדי מניות בישראל | J10: ישראל | K10: ישראל | L10: TASE | M10: Large & Mid Cap מניות בארץ - מניות לפי שווי שוק-מניות | N10: לא | O10: ILS | P10: 5000 | Q10: 1 | R10: 6154 | S10: 0 | T10: 307.7 | U10: 4.7619048e-05 | V10: 0.00070860838 | W10: =T10/'סכום נכסים'!$B$30 -> 5.5398096e-05
A11: 13908 | B11: 13908 | C11: מגדל קרנות נאמנות בע"מ | D11: 511303661 | E11: ח.פ. | F11: SP500.MTF | G11: IL0011503336 | H11: ISIN | I11: עוקב אחר מדדי מניות בחו"ל | J11: ישראל | K11: ארה"ב | L11: TASE | M11: S&P 500 - מניות בחו"ל - מניות גיאוגרפי - חשופת מט"ח-ארה"ב | N11: לא | O11: ILS | P11: 12400 | Q11: 1 | R11: 9608 | S11: 0 | T11: 1191.392 | U11: 0.00014203895 | V11: 0.0027436801 | W11: =T11/'סכום נכסים'!$B$30 -> 0.00021449739
A12: 13908 | B12: 13908 | C12: הראל קרנות נאמנות בע"מ | D12: 511776783 | E12: ח.פ. | F12: הרל.תלבד- 60 צמ | G12: IL0011504730 | H12: ISIN | I12: עוקב אחר מדדים אחרים בישראל | J12: ישראל | K12: ישראל | L12: TASE | M12: אג"ח בארץ - חברות והמרה-תל בונד צמוד מדד-תל בונד צמודות | N12: לא | O12: ILS | P12: 5205892 | Q12: 1 | R12: 406.34 | S12: 0 | T12: 21153.622 | U12: 0.016850115 | V12: 0.048715091 | W12: =T12/'סכום נכסים'!$B$30 -> 0.0038084834
A13: 13908 | B13: 13908 | C13: קסם קרנות נאמנות בע"מ | D13: 510938608 | E13: ח.פ. | F13: קסם.תלבונד ש 50 | G13: IL0011507626 | H13: ISIN | I13: עוקב אחר מדדים אחרים בישראל | J13: ישראל | K13: ישראל | L13: TASE | M13: אג"ח בארץ - חברות והמרה-תל בונד שקלי-תל בונד- שקלי | N13: לא | O13: ILS | P13: 714515 | Q13: 1 | R13: 4502.02 | S13: 0 | T13: 32167.608 | U13: 0.018313036 | V13: 0.074079417 | W13: =T13/'סכום נכסים'!$B$30 -> 0.005791434
... A17: 13908 | B17: 13908 | C17: קסם קרנות נאמנות בע"מ | D17: 510938608 | E17: ח.פ. | F17: CSI300.קסם | G17: IL0011627838 | H17: ISIN | I17: עוקב אחר מדדי מניות בחו"ל | J17: ישראל | K17: סין | L17: TASE | M17: מניות בחו"ל - מניות גיאוגרפי - חשופת מט"ח-אסיה - מדד אחר | N17: לא | O17: ILS | P17: 3801 | Q17: 1 | R17: 28170 | S17: 0 | T17: 1070.7417 | U17: 0.0013229382 | V17: 0.0024658321 | W17: =T17/'סכום נכסים'!$B$30 -> 0.0001927756
A18: 13908 | B18: 13908 | C18: Invesco QQQ Trust Series 1 | D18: ECPGFXU8A2SHKVVGJI15 | E18: LEI | F18: INVESCO QQQ TRUST SERIES 1 | G18: US46090E1038 | H18: ISIN | I18: עוקב אחר מדדי מניות בחו"ל | J18: חו"ל | K18: ארה"ב | L18: NASDAQ | M18: Equity Funds | N18: לא | O18: USD | P18: 750 | Q18: 2.978 | R18: 73640 | S18: 0.61012089 | T18: 1646.5663 | U18: 1.1269722e-06 | V18: 0.00379191 | W18: =T18/'סכום נכסים'!$B$30 -> 0.00029644667
A19: 13908 | B19: 13908 | C19: ISHARES EXPANDED TECH-SOFTWA | D19: 529900VBK42Y5HHRMD23 | E19: LEI | F19: ISHARES SEMICONDUCTOR | G19: US4642875235 | H19: ISIN | I19: עוקב אחר מדדי מניות בחו"ל | J19: חו"ל | K19: ארה"ב | L19: NASDAQ | M19: Equity Funds | N19: לא | O19: USD | P19: 3330 | Q19: 2.978 | R19: 64076 | S19: 0 | T19: 6354.2503 | U19: 4.4608171e-05 | V19: 0.014633328 | W19: =T19/'סכום נכסים'!$B$30 -> 0.0011440148
A20: 13908 | B20: 13908 | C20: Ishares iBoxx $ Investment | D20: 78005 | E20: מספר מנפיק | F20: ISHARES IBOXX H/Y CORP BOND | G20: US4642885135 | H20: ISIN | I20: עוקב אחר מדדים אחרים בחו"ל | J20: חו"ל | K20: ארה"ב | L20: NYSE | M20: Bond/Fixed Income Funds | N20: לא | O20: USD | P20: 42400 | Q20: 2.978 | R20: 7997 | S20: 0 | T20: 10097.588 | U20: 0.00019220308 | V20: 0.023253934 | W20: =T20/'סכום נכסים'!$B$30 -> 0.0018179628

Sheet קרנות נאמנות
A1: מספר קופה/קרן/ח.פ. עבור חברת ביטוח | B1: מספר מסלול | C1: שם מנפיק | D1: מספר מנפיק | E1: סוג מספר מזהה מנפיק | F1: שם נייר ערך | G1: מספר נייר ערך | H1: סוג מספר נייר ערך | I1: מאפיין עיקרי | J1: ישראל/חו"ל | K1: מדינה לפי חשיפה כלכלית | L1: סטאטוס סחירות | M1: זירת מסחר | N1: סיווג הקרן | O1: בעל עניין/צד קשור | P1: מטבע פעילות | Q1: ערך נקוב (יחידות) | R1: שער חליפין | S1: שער נייר הערך | T1: שווי הוגן (באלפי ש"ח) | U1: שיעור מערך נקוב מונפק | V1: שיעור מנכסי אפיק ההשקעה | W1: שיעור מסך נכסי ההשקעה
A2: 13908 | B2: 13908 | C2: מיטב קרנות נאמנות בע"מ | D2: 513534974 | E2: ח.פ. | F2: SP 500 תכלית | G2: IL0051139983 | H2: ISIN | I2: מניות | J2: ישראל | K2: ארה"ב | L2: סחיר | M2: TASE | N2: S&P 500 - מניות בחו"ל - מניות גיאוגרפי - חשופת מט"ח-ארה"ב | O2: לא | P2: ILS | Q2: 16874000 | R2: 1 | S2: 792.53 | T2: 133731.51 | U2: 0.013597696 | V2: 0.19861317 | W2: =T2/'סכום נכסים'!$B$30 -> 0.024076929
A3: 13908 | B3: 13908 | C3: מיטב קרנות נאמנות בע"מ | D3: 513534974 | E3: ח.פ. | F3: תכלית ת"א 125 | G3: IL0051146574 | H3: ISIN | I3: מניות | J3: ישראל | K3: ישראל | L3: סחיר | M3: TASE | N3: Large & Mid Cap מניות בארץ - מניות לפי שווי שוק-מניות | O3: לא | P3: ILS | Q3: 20431000 | R3: 1 | S3: 353.59 | T3: 72241.973 | U3: 0.008316307 | V3: 0.10729115 | W3: =T3/'סכום נכסים'!$B$30 -> 0.013006395
A4: 13908 | B4: 13908 | C4: מיטב קרנות נאמנות בע"מ | D4: 513534974 | E4: ח.פ. | F4: תכ.TTFתלבונד20 | G4: IL0051154727 | H4: ISIN | I4: אג"ח קונצרני | J4: ישראל | K4: ישראל | L4: סחיר | M4: TASE | N4: 20 אג"ח בארץ - חברות והמרה-תל בונד צמוד מדד-תל בונד | O4: לא | P4: ILS | Q4: 43850136 | R4: 1 | S4: 113.54 | T4: 49787.444 | U4: 0.22278908 | V4: 0.073942498 | W4: =T4/'סכום נכסים'!$B$30 -> 0.0089636972
A5: 13908 | B5: 13908 | C5: קסם קרנות נאמנות בע"מ | D5: 510938608 | E5: ח.פ. | F5: קסם תל בונד 20 | G5: IL0051155898 | H5: ISIN | I5: אג"ח קונצרני | J5: ישראל | K5: ישראל | L5: סחיר | M5: TASE | N5: 20 אג"ח בארץ - חברות והמרה-תל בונד צמוד מדד-תל בונד | O5: לא | P5: ILS | Q5: 19016000 | R5: 1 | S5: 155.66 | T5: 29600.306 | U5: 0.058702184 | V5: 0.043961295 | W5: =T5/'סכום נכסים'!$B$30 -> 0.0053292186
A6: 13908 | B6: 13908 | C6: הראל קרנות נאמנות בע"מ | D6: 511776783 | E6: ח.פ. | F6: הרל.תלבנד 20 צמ | G6: IL0051172703 | H6: ISIN | I6: אג"ח קונצרני | J6: ישראל | K6: ישראל | L6: סחיר | M6: TASE | N6: אג"ח בארץ - חברות והמרה-תל בונד צמוד מדד-תל בונד צמודות | O6: לא | P6: ILS | Q6: 34768000 | R6: 1 | S6: 151.47 | T6: 52663.09 | U6: 0.051118812 | V6: 0.078213302 | W6: =T6/'סכום נכסים'!$B$30 -> 0.0094814263
A7: 13908 | B7: 13908 | C7: מגדל קרנות נאמנות בע"מ | D7: 511303661 | E7: ח.פ. | F7: S&P 500 מח MTF | G7: IL0051226277 | H7: ISIN | I7: מניות | J7: ישראל | K7: ארה"ב | L7: סחיר | M7: TASE | N7: S&P 500 - מניות בחו"ל - מניות גיאוגרפי - חשופת מט"ח-ארה"ב | O7: לא | P7: ILS | Q7: 31459071 | R7: 1 | S7: 319.28 | T7: 100442.52 | U7: 0.016070705 | V7: 0.14917357 | W7: =T7/'סכום נכסים'!$B$30 -> 0.018083602
A8: 13908 | B8: 13908 | C8: קסם קרנות נאמנות בע"מ | D8: 510938608 | E8: ח.פ. | F8: S&P 500 קסם | G8: IL0051244825 | H8: ISIN | I8: מניות | J8: ישראל | K8: ארה"ב | L8: סחיר | M8: TASE | N8: S&P 500 - מניות בחו"ל - מניות גיאוגרפי - חשופת מט"ח-ארה"ב | O8: לא | P8: ILS | Q8: 23113000 | R8: 1 | S8: 303.78 | T8: 70212.671 | U8: 0.0060566678 | V8: 0.1042773 | W8: =T8/'סכום נכסים'!$B$30 -> 0.012641041
A9: 13908 | B9: 13908 | C9: אי.בי.אי קרנות נאמנות בעמ | D9: 513765339 | E9: ח.פ. | F9: S&P 500י.IBI | G9: IL0051274699 | H9: ISIN | I9: מניות | J9: ישראל | K9: ארה"ב | L9: סחיר | M9: TASE | N9: S&P 500 - מניות בחו"ל - מניות גיאוגרפי - חשופת מט"ח-ארה"ב | O9: לא | P9: ILS | Q9: 17528160 | R9: 1 | S9: 250.35 | T9: 43881.749 | U9: 0.014784492 | V9: 0.065171574 | W9: =T9/'סכום נכסים'!$B$30 -> 0.0079004398
A10: 13908 | B10: 13908 | C10: אי.בי.אי קרנות נאמנות בעמ | D10: 513765339 | E10: ח.פ. | F10: NASDAQ 100י.IBI | G10: IL0051277668 | H10: ISIN | I10: מניות | J10: ישראל | K10: ארה"ב | L10: סחיר | M10: TASE | N10: NASDAQ 100 - מניות בחו"ל - מניות גיאוגרפי - מנוטרלת מט"ח-ארה"ב | O10: לא | P10: ILS | Q10: 13119174 | R10: 1 | S10: 343.68 | T10: 45087.977 | U10: 0.017008663 | V10: 0.066963021 | W10: =T10/'סכום נכסים'!$B$30 -> 0.0081176083
A11: 13908 | B11: 13908 | C11: הראל קרנות נאמנות בע"מ | D11: 511776783 | E11: ח.פ. | F11: NASDAQ 100 הראל | G11: IL0051292832 | H11: ISIN | I11: מניות | J11: ישראל | K11: ארה"ב | L11: סחיר | M11: TASE | N11: מניות בחו"ל - מניות גיאוגרפי - חשופת מט"ח-ארה"ב - מדד אחר | O11: לא | P11: ILS | Q11: 13860000 | R11: 1 | S11: 360.67 | T11: 49988.862 | U11: 0.0093238609 | V11: 0.074241636 | W11: =T11/'סכום נכסים'!$B$30 -> 0.0089999603
A12: 13908 | B12: 13908 | C12: אי.בי.אי קרנות נאמנות בעמ | D12: 513765339 | E12: ח.פ. | F12: STOXX-E600י.IBI | G12: IL0051307523 | H12: ISIN | I12: מניות | J12: ישראל | K12: אירופה | L12: סחיר | M12: TASE | N12: STOXX EUROPE 600 - מניות בחו"ל - מניות גיאוגרפי - מנוטרלת מט"ח-אירופה כללי | O12: לא | P12: ILS | Q12: 15622700 | R12: 1 | S12: 164.43 | T12: 25688.406 | U12: 0.10761057 | V12: 0.038151484 | W12: =T12/'סכום נכסים'!$B$30 -> 0.0046249228

Sheet כתבי אופציה
A1: מספר קופה/קרן/ח.פ. עבור חברת ביטוח | B1: מספר מסלול | C1: שם מנפיק | D1: מספר מנפיק | E1: סוג מספר מזהה מנפיק | F1: שם נייר ערך | G1: מספר נייר ערך | H1: סוג מספר נייר ערך | I1: ישראל/חו"ל | J1: מדינה לפי חשיפה כלכלית | K1: סטאטוס סחירות | L1: זירת מסחר | M1: נכס בסיס (כתב אופציה) | N1: ענף מסחר | O1: תאריך פקיעה | P1: בעל עניין/צד קשור | Q1: מטבע פעילות | R1: שער מימוש | S1: יחס המרה | T1: ערך נקוב (יחידות) | U1: שער חליפין | V1: שער נייר הערך | W1: שווי הוגן (באלפי ש"ח) | X1: שיעור מנכסי אפיק ההשקעה | Y1: שיעור מסך נכסי ההשקעה
A2: 13908 | B2: 13908 | C2: אלומיי קפיטל בע"מ | D2: 520039868 | E2: ח.פ. | F2: אלומיי אפ 2 | G2: IL0012030826 | H2: ISIN | I2: ישראל | J2: ישראל | K2: סחיר | L2: TASE | M2: IL0010826357 | N2: אנרגיה מתחדשת | O2: 46757 | P2: לא | Q2: ILS | R2: 8000 | S2: 1 | T2: 2304 | U2: 1 | V2: 513.4 | W2: 11.82874 | X2: 0.0025446949 | Y2: =W2/'סכום נכסים'!$B$30 -> 2.1296382e-06
A3: 13908 | B3: 13908 | C3: מיטב טרייד השקעות בע"מ | D3: 516854239 | E3: ח.פ. | F3: מיטב טרייד אפ 1 | G3: IL0012031998 | H3: ISIN | I3: ישראל | J3: ישראל | K3: סחיר | L3: TASE | M3: IL0012031816 | N3: שרותים פיננסיים | O3: 46770 | P3: לא | Q3: ILS | R3: 673.666 | S3: 1 | T3: 192000 | U3: 1 | V3: 1846 | W3: 3544.32 | X3: 0.76248299 | Y3: =W3/'סכום נכסים'!$B$30 -> 0.00063811693
A4: 13908 | B4: 13908 | C4: שובל הנדסה ובניין בע"מ | D4: 512951518 | E4: ח.פ. | F4: שובל הנדסה אפ 1 | G4: IL0012159617 | H4: ISIN | I4: ישראל | J4: ישראל | K4: סחיר | L4: TASE | M4: IL0012079682 | N4: בנייה | O4: 46398 | P4: לא | Q4: ILS | R4: 1023 | S4: 1 | T4: 2500 | U4: 1 | V4: 53 | W4: 1.325 | X4: 0.00028504479 | Y4: =W4/'סכום נכסים'!$B$30 -> 2.3855209e-07
A5: 13908 | B5: 13908 | C5: קבוצת חג'ג' ייזום נדל"ן בע"מ | D5: 520033309 | E5: ח.פ. | F5: חג'ג' אפ 1 | G5: IL0012166547 | H5: ISIN | I5: ישראל | J5: ישראל | K5: סחיר | L5: TASE | M5: IL0008230133 | N5: בנייה | O5: 46233 | P5: לא | Q5: ILS | R5: 3174.866 | S5: 1 | T5: 15856 | U5: 1 | V5: 161.9 | W5: 25.67086 | X5: 0.0055225245 | Y5: =W5/'סכום נכסים'!$B$30 -> 4.6217639e-06
A6: 13908 | B6: 13908 | C6: מגידו י.ק. בע"מ | D6: 510542855 | E6: ח.פ. | F6: מגידו אפ 1 | G6: IL0012251844 | H6: ISIN | I6: ישראל | J6: ישראל | K6: סחיר | L6: TASE | M6: IL0012166059 | N6: בנייה | O6: 47311 | P6: לא | Q6: ILS | R6: 850 | S6: 1 | T6: 60500 | U6: 1 | V6: 321.7 | W6: 194.6285 | X6: 0.041870068 | Y6: =W6/'סכום נכסים'!$B$30 -> 3.5040781e-05
A7: 13908 | B7: 13908 | C7: נאוויטס פטרוליום, שותפות מוגבל | D7: 550263107 | E7: ח.פ. | F7: נאוויטס פט אפ 6 | G7: IL0012288242 | H7: ISIN | I7: ישראל | J7: ישראל | K7: סחיר | L7: TASE | M7: IL0011419699 | N7: חיפושי נפט וגז | O7: 46265 | P7: לא | Q7: ILS | R7: 10370.1 | S7: 1 | T7: 10793 | U7: 1 | V7: 1619 | W7: 174.73867 | X7: 0.037591206 | Y7: =W7/'סכום נכסים'!$B$30 -> 3.145983e-05
A8: 13908 | B8: 13908 | C8: מגוריט ישראל בע"מ | D8: 515434074 | E8: ח.פ. | F8: מגוריט אפ 1 | G8: IL0012361320 | H8: ISIN | I8: ישראל | J8: ישראל | K8: סחיר | L8: TASE | M8: IL0011391955 | N8: נדל"ן מניב בישראל | O8: 47330 | P8: לא | Q8: ILS | R8: 1077.672 | S8: 1 | T8: 141425.04 | U8: 1 | V8: 108.1 | W8: 152.88047 | X8: 0.032888892 | Y8: =W8/'סכום נכסים'!$B$30 -> 2.7524494e-05
A9: 13908 | B9: 13908 | C9: עלמדב ריל אסטייט אינק | D9: 2548 | E9: מספר מנפיק | F9: עלמדב ריל אפ 1 | G9: IL0012432527 | H9: ISIN | I9: ישראל | J9: ישראל | K9: סחיר | L9: TASE | M9: IL0012432451 | N9: נדל"ן מניב בחו"ל | O9: 47631 | P9: לא | Q9: ILS | R9: 850 | S9: 1 | T9: 300000 | U9: 1 | V9: 181 | W9: 543 | X9: 0.11681458 | Y9: =W9/'סכום נכסים'!$B$30 -> 9.7761346e-05

Sheet אופציות
A1: מספר קופה/קרן/ח.פ. עבור חברת ביטוח | B1: מספר מסלול | C1: שם מנפיק | D1: מספר מנפיק | E1: סוג מספר מזהה מנפיק | F1: שם נייר ערך | G1: מספר נייר ערך | H1: סוג מספר נייר ערך | I1: מאפיין עיקרי | J1: ישראל/חו"ל | K1: מדינה לפי חשיפה כלכלית | L1: זירת מסחר | M1: ענף מסחר | N1: נכס בסיס | O1: תאריך פקיעה | P1: בעל עניין/צד קשור | Q1: מטבע פעילות | R1: שער מימוש | S1: ערך נקוב (יחידות) | T1: שער חליפין | U1: שער נייר הערך | V1: שווי הוגן (באלפי ש"ח) | W1: שיעור מנכסי אפיק ההשקעה | X1: שיעור מסך נכסי ההשקעה

Sheet חוזים עתידיים
A1: מספר קופה/קרן/ח.פ. עבור חברת ביטוח | B1: מספר מסלול | C1: שם מנפיק | D1: מספר מנפיק | E1: סוג מספר מזהה מנפיק | F1: שם נייר ערך | G1: מספר נייר ערך | H1: סוג מספר נייר ערך | I1: ישראל/חו"ל | J1: מדינה לפי חשיפה כלכלית | K1: זירת מסחר | L1: נכס בסיס | M1: בעל עניין/צד קשור | N1: מטבע פעילות | O1: ערך נקוב (יחידות) | P1: שער חליפין | Q1: שער נייר הערך | R1: שווי הוגן (באלפי ש"ח) | S1: שיעור מנכסי אפיק ההשקעה | T1: שיעור מסך נכסי ההשקעה
A2: 13908 | B2: 13908 | C2: Chcago Board of Trade | D2: BBG01Z2DZQ77 | E2: מספר מנפיק | F2: ULTRA10 YR 09/26 | G2: UXYU6 COMDTY | H2: אחר | I2: חו"ל | J2: ארה"ב | K2: CBOE | L2: מניות לרבות מדדי מניות | M2: לא | N2: USD | O2: 264 | P2: 2.978 | Q2: 11246.88 | R2: 565.1148 | S2: 0.035127333 | T2: =R2/'סכום נכסים'!$B$30 -> 0.00010174288
A3: 13908 | B3: 13908 | C3: Osaka Exchange | D3: BBG01V7ZXTP8 | E3: מספר מנפיק | F3: TOPIX INDX FUT 09/26 | G3: TPU6 INDEX | H3: אחר | I3: חו"ל | J3: יפן | K3: JPX | L3: מניות לרבות מדדי מניות | M3: לא | N3: JPY | O3: 22 | P3: 0.018341 | Q3: 400300 | R3: 566.99979 | S3: 0.035244503 | T3: =R3/'סכום נכסים'!$B$30 -> 0.00010208225
A4: 13908 | B4: 13908 | C4: Osaka Exchange | D4: BBG01SV6FT81 | E4: מספר מנפיק | F4: NIKKEI 225 MINI 09/26 | G4: NOU6 INDEX | H4: אחר | I4: חו"ל | J4: יפן | K4: JPX | L4: מניות לרבות מדדי מניות | M4: לא | N4: JPY | O4: 430 | P4: 0.018341 | Q4: 7019000 | R4: 4572.6793 | S4: 0.2842361 | T4: =R4/'סכום נכסים'!$B$30 -> 0.00082326203
A5: 13908 | B5: 13908 | C5: Chicago Mercantile Exchange | D5: BBG01HZQ8JX9 | E5: מספר מנפיק | F5: S&P500 EMINI FUT 09/26 | G5: ESU6 INDEX | H5: אחר | I5: חו"ל | J5: ארה"ב | K5: CME | L5: מניות לרבות מדדי מניות | M5: לא | N5: USD | O5: 901 | P5: 2.978 | Q5: 754825 | R5: 6697.9698 | S5: 0.4163434 | T5: =R5/'סכום נכסים'!$B$30 -> 0.0012058979
A6: 13908 | B6: 13908 | C6: Chicago Mercantile Exchange | D6: BBG01SWCTGH0 | E6: מספר מנפיק | F6: FUTURE MINI NASDAQ 09/26 | G6: NQU6 INDEX | H6: אחר | I6: חו"ל | J6: ארה"ב | K6: CME | L6: מניות לרבות מדדי מניות | M6: לא | N6: USD | O6: 139 | P6: 2.978 | Q6: 3052350 | R6: 4593.5897 | S6: 0.28553589 | T6: =R6/'סכום נכסים'!$B$30 -> 0.00082702673
A7: 13908 | B7: 13908 | C7: ICE Futures US Indiced | D7: BBG013V2S5T0 | E7: מספר מנפיק | F7: MSCI EmgMkt 09/26 | G7: MESU6 INDEX | H7: אחר | I7: חו"ל | J7: ארה"ב | K7: ICE | L7: מניות לרבות מדדי מניות | M7: לא | N7: USD | O7: 589 | P7: 2.978 | Q7: 175730 | R7: -2417.6895 | S7: -0.15028271 | T7: =R7/'סכום נכסים'!$B$30 -> -0.00043527915
A8: 13908 | B8: 13908 | C8: Eurex | D8: BBG01JFBR337 | E8: מספר מנפיק | F8: STOXX600 09/26 | G8: SXOU6 INDEX | H8: אחר | I8: חו"ל | J8: גרמניה | K8: EUREX | L8: מניות לרבות מדדי מניות | M8: לא | N8: EUR | O8: 1453 | P8: 3.3945 | Q8: 64430 | R8: 1126.8863 | S8: 0.07004685 | T8: =R8/'סכום נכסים'!$B$30 -> 0.00020288384
A9: 13908 | B9: 13908 | C9: Chicago Board of Trade | D9: BBG01X9RNBP0 | E9: מספר מנפיק | F9: FT MINI DOW 09/26 | G9: DMU6 INDEX | H9: אחר | I9: חו"ל | J9: ארה"ב | K9: CME | L9: מניות לרבות מדדי מניות | M9: לא | N9: USD | O9: 48 | P9: 2.978 | Q9: 5267000 | R9: 387.18519 | S9: 0.024067292 | T9: =R9/'סכום נכסים'!$B$30 -> 6.9708555e-05
A10: 13908 | B10: 13908 | C10: NIFTY | D10: BBG021YZDYN6 | E10: מספר מנפיק | F10: NIFTY 50 IFSC | G10: JGSN6 INDEX | H10: אחר | I10: חו"ל | J10: הודו | K10: NSE | L10: מניות לרבות מדדי מניות | M10: לא | N10: USD | O10: 20 | P10: 2.978 | Q10: 2398550 | R10: -5.12647 | S10: -0.00031865953 | T10: =R10/'סכום נכסים'!$B$30 -> -9.2296612e-07

Sheet מוצרים מובנים
A1: מספר קופה/קרן/ח.פ. עבור חברת ביטוח | B1: מספר מסלול | C1: שם מנפיק | D1: מספר מנפיק | E1: סוג מספר מזהה מנפיק | F1: שם נייר ערך | G1: מספר נייר ערך | H1: סוג מספר נייר ערך | I1: מאפיין עיקרי | J1: ישראל/חו"ל | K1: מדינה לפי חשיפה כלכלית | L1: סטאטוס סחירות | M1: זירת מסחר | N1: נכס בסיס | O1: בעל עניין/צד קשור | P1: מח"מ | Q1: שיעור ריבית | R1: תשואה לפדיון | S1: דירוג | T1: שם מדרג | U1: דירוג נייר הערך/המנפיק | V1: מטבע פעילות | W1: ערך נקוב (יחידות) | X1: שער חליפין | Y1: שער נייר הערך | Z1: שווי הוגן (באלפי ש"ח) | AA1: שיעור מנכסי אפיק ההשקעה | AB1: שיעור מסך נכסי ההשקעה
A2: 13908 | B2: 13908 | C2: אלה פקדונות בע"מ | D2: 515666881 | E2: ח.פ. | F2: אלה פקדון אגח ה | G2: IL0011625774 | H2: ISIN | I2: קרן מובטחת | J2: ישראל | K2: ישראל | L2: סחיר | M2: TASE | N2: מדד המחירים לצרכן | O2: לא | P2: 2.57 | Q2: 0.0005 | R2: 0.0226 | S2: ilAAAs | T2: S&P מעלות | U2: נייר ערך | V2: ILS | W2: 5645 | X2: 1 | Y2: 112.1 | Z2: 6.32804 | AA2: 1 | AB2: =Z2/'סכום נכסים'!$B$30 -> 1.139296e-06

Sheet לא סחיר איגרות חוב ממשלתיות
A1: מספר קופה/קרן/ח.פ. עבור חברת ביטוח | B1: מספר מסלול | C1: שם מנפיק | D1: שם נייר ערך | E1: מספר נייר ערך | F1: סוג מספר נייר ערך | G1: מאפיין עיקרי | H1: ישראל/חו"ל | I1: מדינה לפי חשיפה כלכלית | J1: תאריך רכישה | K1: דירוג | L1: שם מדרג | M1: מטבע פעילות | N1: מח"מ | O1: מועד פדיון | P1: שיעור ריבית | Q1: תשואה לפדיון | R1: ערך נקוב (יחידות) | S1: שער חליפין | T1: שער נייר הערך | U1: שווי הוגן (באלפי ש"ח) | V1: עלות מופחתת (באלפי ש"ח) | W1: השיטה שיושמה בדוח הכספי | X1: שיעור מנכסי אפיק ההשקעה | Y1: שיעור מסך נכסי ההשקעה

Sheet לא סחיר איגרות חוב מיועדות
A1: מספר קופה/קרן/ח.פ. עבור חברת ביטוח | B1: מספר מסלול | C1: מאפיין עיקרי | D1: שם נייר ערך | E1: מספר נייר ערך | F1: תאריך רכישה | G1: מח"מ | H1: סוג הצמדה | I1: מועד פדיון | J1: שיעור ריבית | K1: תשואה לפדיון | L1: ערך נקוב (יחידות) | M1: שער נייר הערך | N1: שווי הוגן (באלפי ש"ח) | O1: עלות מופחתת (באלפי ש"ח) | P1: השיטה שיושמה בדוח הכספי | Q1: שיעור מנכסי אפיק ההשקעה | R1: שיעור מסך נכסי ההשקעה

Sheet אפיק השקעה מובטח תשואה
A1: מספר קרן | B1: מספר מסלול | C1: מאפיין עיקרי | D1: חודש הנפקת שכבה | E1: חודש הבדיקה | F1: שווי הנכסים באפיק (באלפי ש"ח) | G1: שיעור מסך נכסי ההשקעה
A2: 13908 | B2: 13909 | C2: נכס או התחייבות בגין השלמת המדינה לתשואת היעד | D2: 44835 | E2: 46661 | F2: -9495.795 | G2: 0.014498305
A3: 13908 | B3: 13909 | C3: נכס או התחייבות בגין השלמת המדינה לתשואת היעד | D3: 44866 | E3: 46692 | F3: -5715.541 | G3: 0.0087265631
A4: 13908 | B4: 13909 | C4: נכס או התחייבות בגין השלמת המדינה לתשואת היעד | D4: 44896 | E4: 46722 | F4: -8811.888 | G4: 0.013454106
A5: 13908 | B5: 13909 | C5: נכס או התחייבות בגין השלמת המדינה לתשואת היעד | D5: 44927 | E5: 46753 | F5: -7051.923 | G5: 0.010766969
A6: 13908 | B6: 13909 | C6: נכס או התחייבות בגין השלמת המדינה לתשואת היעד | D6: 44958 | E6: 46784 | F6: -6468.769 | G6: 0.0098766015
A7: 13908 | B7: 13909 | C7: נכס או התחייבות בגין השלמת המדינה לתשואת היעד | D7: 44986 | E7: 46813 | F7: -6994.308 | G7: 0.010679001
A8: 13908 | B8: 13909 | C8: נכס או התחייבות בגין השלמת המדינה לתשואת היעד | D8: 45017 | E8: 46844 | F8: -7294.595 | G8: 0.011137483
A9: 13908 | B9: 13909 | C9: נכס או התחייבות בגין השלמת המדינה לתשואת היעד | D9: 45047 | E9: 46874 | F9: -8191.998 | G9: 0.01250765
A10: 13908 | B10: 13909 | C10: נכס או התחייבות בגין השלמת המדינה לתשואת היעד | D10: 45078 | E10: 46905 | F10: -5860.268 | G10: 0.0089475341
A11: 13908 | B11: 13909 | C11: נכס או התחייבות בגין השלמת המדינה לתשואת היעד | D11: 45108 | E11: 46935 | F11: -8137.376 | G11: 0.012424253
A12: 13908 | B12: 13909 | C12: נכס או התחייבות בגין השלמת המדינה לתשואת היעד | D12: 45139 | E12: 46966 | F12: -11597.782 | G12: 0.017707646
A13: 13908 | B13: 13909 | C13: נכס או התחייבות בגין השלמת המדינה לתשואת היעד | D13: 45170 | E13: 46997 | F13: -9555.005 | G13: 0.014588707
... A676: 13908 | B676: 15267 | C676: נכס או התחייבות בגין השלמת המדינה לתשואת היעד | D676: 46174 | E676: 48000 | F676: 6.177 | G676: -9.4311247e-06

Sheet לא סחיר ניירות ערך מסחריים
A1: מספר קופה/קרן/ח.פ. עבור חברת ביטוח | B1: מספר מסלול | C1: שם מנפיק | D1: מספר מנפיק | E1: סוג מספר מזהה מנפיק | F1: שם נייר ערך | G1: מספר נייר ערך | H1: סוג מספר נייר ערך | I1: מאפיין עיקרי | J1: ישראל/חו"ל | K1: מדינה לפי חשיפה כלכלית | L1: ענף מסחר | M1: בעל עניין/צד קשור | N1: תאריך רכישה | O1: דירוג | P1: שם מדרג | Q1: דירוג נייר הערך/המנפיק | R1: מטבע פעילות | S1: מח"מ | T1: סוג הצמדה | U1: ריבית עוגן | V1: מועד פדיון | W1: שיעור ריבית | X1: תשואה לפדיון | Y1: נחיתות חוזית | Z1: האם סווג כחוב בעייתי | AA1: סוג גורם משערך | AB1: תלות/אי-תלות המשערך | AC1: שם גורם משערך | AD1: תאריך שערוך אחרון | AE1: תאריך אחרון בו נבחנה בפועל ירידת ערך | AF1: ערך נקוב (יחידות) | AG1: שער חליפין | AH1: שער נייר הערך | AI1: שווי הוגן (באלפי ש"ח) | AJ1: עלות מופחתת (באלפי ש"ח) | AK1: עלות מופחתת (במטבע הפעילות) | AL1: השיטה שיושמה בדוח הכספי | AM1: שיעור מנכסי אפיק ההשקעה | AN1: שיעור מסך נכסי ההשקעה
A2: 13908 | B2: 13908 | C2: שיכון ובינוי בע"מ | D2: 520036104 | E2: ח.פ. | F2: נעמ שכון ובנוי3 | G2: 11020132 | H2: פנימי | I2: לא צמוד למדד המחירים לצרכן | J2: ישראל | K2: ישראל | L2: בנייה | M2: לא | N2: 45657 | O2: A1.il | P2: מידרוג Moodys | Q2: נייר ערך | R2: ILS | S2: 0.165 | T2: לא צמוד | U2: ללא | V2: 46537 | W2: 0.071 | X2: 0.071 | Y2: החוב לא נחות | AA2: חברת ציטוט | AB2: אי-תלות | AD2: 46203 | AE2: 46203 | AF2: 4740000 | AG2: 1 | AH2: 100.82 | AI2: 4778.868 | AL2: שווי הוגן | AM2: 1 | AN2: =AI2/'סכום נכסים'!$B$30 -> 0.0008603841

Sheet לא סחיר איגרות חוב
A1: מספר קופה/קרן/ח.פ. עבור חברת ביטוח | B1: מספר מסלול | C1: שם מנפיק | D1: מספר מנפיק | E1: סוג מספר מזהה מנפיק | F1: שם נייר ערך | G1: מספר נייר ערך | H1: סוג מספר נייר ערך | I1: מאפיין עיקרי | J1: ישראל/חו"ל | K1: מדינה לפי חשיפה כלכלית | L1: סטאטוס סחירות | M1: ענף מסחר | N1: בעל עניין/צד קשור | O1: תאריך רכישה | P1: דירוג | Q1: שם מדרג | R1: דירוג נייר הערך/המנפיק | S1: מטבע פעילות | T1: מח"מ | U1: מועד פדיון | V1: תשואה לפדיון | W1: שיעור ריבית | X1: נחיתות חוזית | Y1: האם סווג כחוב בעייתי | Z1: סוג גורם משערך | AA1: תלות/אי-תלות המשערך | AB1: תאריך שערוך אחרון | AC1: תאריך אחרון בו נבחנה בפועל ירידת ערך | AD1: ערך נקוב (יחידות) | AE1: שער חליפין | AF1: שער נייר הערך | AG1: שווי הוגן (באלפי ש"ח) | AH1: עלות מופחתת (באלפי ש"ח) | AI1: עלות מופחתת (במטבע הפעילות) | AJ1: השיטה שיושמה בדוח הכספי | AK1: שיעור מנכסי אפיק ההשקעה | AL1: שיעור מסך נכסי ההשקעה
A2: 13908 | B2: 13908 | C2: מקורות חברת מים בע"מ | D2: 520010869 | E2: ח.פ. | F2: מקורות אגח -6רמ | G2: IL0011009086 | H2: ISIN | I2: צמוד למדד המחירים לצרכן | J2: ישראל | K2: ישראל | L2: לא סחיר | M2: שרותים | N2: לא | O2: 45753 | P2: ilAAA | Q2: S&P מעלות | R2: נייר ערך | S2: ILS | T2: 4.89 | U2: 50034 | V2: 0.0256 | W2: 0.049 | X2: החוב לא נחות | Z2: חברת ציטוט | AA2: אי-תלות | AB2: 46203 | AC2: 46203 | AD2: 3735417.2 | AE2: 1 | AF2: 166.62 | AG2: 6223.9522 | AJ2: שווי הוגן | AK2: 0.050240756 | AL2: =AG2/'סכום נכסים'!$B$30 -> 0.0011205561
A3: 13908 | B3: 13908 | C3: מקורות חברת מים בע"מ | D3: 520010869 | E3: ח.פ. | F3: מקורות אגח -8רמ | G3: IL0011243461 | H3: ISIN | I3: צמוד למדד המחירים לצרכן | J3: ישראל | K3: ישראל | L3: לא סחיר | M3: שרותים | N3: לא | O3: 45657 | P3: ilAAA | Q3: S&P מעלות | R3: נייר ערך | S3: ILS | T3: 8.75 | U3: 54253 | V3: 0.0282 | W3: 0.041 | X3: החוב לא נחות | Z3: חברת ציטוט | AA3: אי-תלות | AB3: 46203 | AC3: 46203 | AD3: 353846.21 | AE3: 1 | AF3: 144.82 | AG3: 512.44008 | AJ3: שווי הוגן | AK3: 0.0041364998 | AL3: =AG3/'סכום נכסים'!$B$30 -> 9.2259359e-05
A4: 13908 | B4: 13908 | C4: מת"ם - מרכז תעשיות מדע חיפה בע | D4: 510687403 | E4: ח.פ. | F4: מת"ם אגח א -רמ | G4: IL0011389991 | H4: ISIN | I4: לא צמוד למדד המחירים לצרכן | J4: ישראל | K4: ישראל | L4: לא סחיר | M4: נדל"ן מניב בישראל | N4: לא | O4: 45657 | P4: Aa2.il | Q4: מידרוג Moodys | R4: נייר ערך | S4: ILS | T4: 0.99 | U4: 46568 | V4: 0.0464 | W4: 0.031 | X4: החוב לא נחות | Z4: חברת ציטוט | AA4: אי-תלות | AB4: 46203 | AC4: 46203 | AD4: 923076.97 | AE4: 1 | AF4: 99.43 | AG4: 917.81543 | AJ4: שווי הוגן | AK4: 0.0074087557 | AL4: =AG4/'סכום נכסים'!$B$30 -> 0.00016524286
A5: 13908 | B5: 13908 | C5: רפאל מערכות לחימה מתקדמות בע"מ | D5: 520042185 | E5: ח.פ. | F5: רפאל אגח ד-רמ | G5: IL0011402844 | H5: ISIN | I5: לא צמוד למדד המחירים לצרכן | J5: ישראל | K5: ישראל | L5: לא סחיר | M5: ביטחוניות | N5: לא | O5: 45657 | P5: Aaa.il | Q5: מידרוג Moodys | R5: נייר ערך | S5: ILS | T5: 3.8 | U5: 49202 | V5: 0.0501 | W5: 0.0374 | X5: החוב לא נחות | Z5: חברת ציטוט | AA5: אי-תלות | AB5: 46203 | AC5: 46203 | AD5: 1595937.8 | AE5: 1 | AF5: 101.13 | AG5: 1613.9719 | AJ5: שווי הוגן | AK5: 0.013028244 | AL5: =AG5/'סכום נכסים'!$B$30 -> 0.00029057839
A6: 13908 | B6: 13908 | C6: אורמת טכנולוגיות, אינק | D6: 880326081 | E6: מספר תאגיד או שותפות בחו"ל | F6: אורמת אגח 4 -רמ | G6: IL0011672123 | H6: ISIN | I6: לא צמוד למדד המחירים לצרכן | J6: ישראל | K6: ארה"ב | L6: לא סחיר | M6: אנרגיה מתחדשת | N6: לא | O6: 45657 | P6: ilAA- | Q6: S&P מעלות | R6: נייר ערך | S6: ILS | T6: 2.79 | U6: 48014 | V6: 0.0594 | W6: 0.0335 | X6: החוב לא נחות | Z6: חברת ציטוט | AA6: אי-תלות | AB6: 46203 | AC6: 46203 | AD6: 83333.33 | AE6: 1 | AF6: 97.65 | AG6: 81.375 | AJ6: שווי הוגן | AK6: 0.00065687226 | AL6: =AG6/'סכום נכסים'!$B$30 -> 1.4650699e-05
A7: 13908 | B7: 13908 | C7: רשות שדות התעופה בישראל. | D7: 500102868 | E7: ח.פ. | F7: רש"ת אגח א-רמ | G7: IL0011873358 | H7: ISIN | I7: צמוד למדד המחירים לצרכן | J7: ישראל | K7: ישראל | L7: לא סחיר | M7: שרותים | N7: לא | O7: 45657 | P7: Aaa.il | Q7: מידרוג Moodys | R7: נייר ערך | S7: ILS | T7: 2.98 | U7: 48213 | V7: 0.0258 | W7: 0.0155 | X7: החוב לא נחות | Z7: חברת ציטוט | AA7: אי-תלות | AB7: 46203 | AC7: 46203 | AD7: 349762.4 | AE7: 1 | AF7: 110.35 | AG7: 385.96281 | AJ7: שווי הוגן | AK7: 0.0031155547 | AL7: =AG7/'סכום נכסים'!$B$30 -> 6.9488478e-05
A8: 13908 | B8: 13908 | C8: רשות שדות התעופה בישראל. | D8: 500102868 | E8: ח.פ. | F8: רש"ת אגח ב-רמ | G8: IL0011873432 | H8: ISIN | I8: צמוד למדד המחירים לצרכן | J8: ישראל | K8: ישראל | L8: לא סחיר | M8: שרותים | N8: לא | O8: 45657 | P8: Aaa.il | Q8: מידרוג Moodys | R8: נייר ערך | S8: ILS | T8: 5.94 | U8: 50040 | V8: 0.0247 | W8: 0.0175 | X8: החוב לא נחות | Z8: חברת ציטוט | AA8: אי-תלות | AB8: 46203 | AC8: 46203 | AD8: 2793368.3 | AE8: 1 | AF8: 108.39 | AG8: 3027.7319 | AJ8: שווי הוגן | AK8: 0.024440345 | AL8: =AG8/'סכום נכסים'!$B$30 -> 0.00054511076
A9: 13908 | B9: 13908 | C9: איילון חברה לביטוח בע"מ | D9: 520030677 | E9: ח.פ. | F9: איילון אגח ג-רמ | G9: IL0011955775 | H9: ISIN | I9: לא צמוד למדד המחירים לצרכן | J9: ישראל | K9: ישראל | L9: לא סחיר | M9: ביטוח | N9: לא | O9: 45657 | P9: A3.il | Q9: מידרוג Moodys | R9: נייר ערך | S9: ILS | T9: 1.45 | U9: 47848 | V9: 0.0726 | W9: 0.0775 | X9: החוב לא נחות | Z9: חברת ציטוט | AA9: אי-תלות | AB9: 46203 | AC9: 46203 | AD9: 105000 | AE9: 1 | AF9: 103.97 | AG9: 109.1685 | AJ9: שווי הוגן | AK9: 0.00088122592 | AL9: =AG9/'סכום נכסים'!$B$30 -> 1.9654621e-05
A10: 13908 | B10: 13908 | C10: מקס איט פיננסים בע"מ | D10: 512905423 | E10: ח.פ. | F10: מקס איט הת ד-רמ | G10: IL0011979536 | H10: ISIN | I10: לא צמוד למדד המחירים לצרכן | J10: ישראל | K10: ישראל | L10: לא סחיר | M10: שרותים פיננסיים | N10: לא | O10: 45657 | P10: A1.il | Q10: מידרוג Moodys | R10: נייר ערך | S10: ILS | T10: 2.06 | U10: 47073 | V10: 0.0667 | W10: 0.0733 | X10: החוב לא נחות | Z10: חברת ציטוט | AA10: אי-תלות | AB10: 46203 | AC10: 46203 | AD10: 300000 | AE10: 1 | AF10: 112.57 | AG10: 337.71 | AJ10: שווי הוגן | AK10: 0.0027260501 | AL10: =AG10/'סכום נכסים'!$B$30 -> 6.0801076e-05
A11: 13908 | B11: 13908 | C11: בנק לאומי לישראל בע"מ | D11: 520018078 | E11: ח.פ. | F11: לאומי אגח 1 ר-מ | G11: IL0011986390 | H11: ISIN | I11: לא צמוד למדד המחירים לצרכן | J11: ישראל | K11: ישראל | L11: לא סחיר | M11: בנקים | N11: לא | O11: 45657 | P11: ilA- | Q11: S&P מעלות | R11: נייר ערך | S11: ILS | T11: 0.48 | U11: 46380 | V11: 0.0639 | W11: 0.068 | X11: החוב לא נחות | Z11: חברת ציטוט | AA11: אי-תלות | AB11: 46203 | AC11: 46203 | AD11: 39847.74 | AE11: 1 | AF11: 100.3 | AG11: 39.96728 | AJ11: שווי הוגן | AK11: 0.00032262239 | AL11: =AG11/'סכום נכסים'!$B$30 -> 7.1956815e-06
A12: 13908 | B12: 13908 | C12: אגד חברה לתחבורה בע"מ | D12: 516041118 | E12: ח.פ. | F12: אגד אגח -1רמ | G12: IL0011987877 | H12: ISIN | I12: צמוד למדד המחירים לצרכן | J12: ישראל | K12: ישראל | L12: לא סחיר | M12: שרותים | N12: לא | O12: 45657 | P12: ilAA- | Q12: S&P מעלות | R12: נייר ערך | S12: ILS | T12: 2.08 | U12: 47483 | V12: 0.0286 | W12: 0.0364 | X12: החוב לא נחות | Z12: חברת ציטוט | AA12: אי-תלות | AB12: 46203 | AC12: 46203 | AD12: 1050000 | AE12: 1 | AF12: 109.78 | AG12: 1152.69 | AJ12: שווי הוגן | AK12: 0.0093047013 | AL12: =AG12/'סכום נכסים'!$B$30 -> 0.00020752951
A13: 13908 | B13: 13908 | C13: בנק לאומי לישראל בע"מ | D13: 520018078 | E13: ח.פ. | F13: לאומי אגח -2רמ | G13: IL0012058975 | H13: ISIN | I13: לא צמוד למדד המחירים לצרכן | J13: ישראל | K13: ישראל | L13: לא סחיר | M13: בנקים | N13: לא | O13: 45657 | P13: ilA- | Q13: S&P מעלות | R13: נייר ערך | S13: ILS | T13: 3.72 | U13: 47720 | V13: 0.0543 | W13: 0.068 | X13: החוב לא נחות | Z13: חברת ציטוט | AA13: אי-תלות | AB13: 46203 | AC13: 46203 | AD13: 2204319.6 | AE13: 1 | AF13: 101.24 | AG13: 2231.6531 | AJ13: שווי הוגן | AK13: 0.018014268 | AL13: =AG13/'סכום נכסים'!$B$30 -> 0.00040178529
... A36: 13908 | B36: 13908 | C36: לידר החזקות והשקעות בע"מ | D36: 520037664 | E36: ח.פ. | F36: לידר אגח ח- רמ | G36: IL0031803617 | H36: ISIN | I36: לא צמוד למדד המחירים לצרכן | J36: ישראל | K36: ישראל | L36: לא סחיר | M36: השקעה ואחזקות | N36: לא | O36: 45657 | P36: A1.il | Q36: מידרוג Moodys | R36: נייר ערך | S36: ILS | T36: 1.12 | U36: 46798 | V36: 0.0477 | W36: 0.021 | X36: החוב לא נחות | Z36: חברת ציטוט | AA36: אי-תלות | AB36: 46203 | AC36: 46203 | AD36: 445992.48 | AE36: 1 | AF36: 99.04 | AG36: 441.71095 | AJ36: שווי הוגן | AK36: 0.0035655627 | AL36: =AG36/'סכום נכסים'!$B$30 -> 7.9525335e-05
A37: 13908 | B37: 13908 | C37: קבוצת נונו ניהול ואחזקות בע?מ | D37: 516481561 | E37: ח.פ. | F37: אגח להמרה נונו | G37: 11022551 | H37: פנימי | I37: אג"ח להמרה צמוד למדד המחירים לצרכן | J37: ישראל | K37: ישראל | L37: לא סחיר | M37: מזון | N37: לא | O37: 46021 | P37: NR | Q37: NR | R37: NR | S37: ILS | T37: 7.992 | U37: 48939 | V37: 0.091 | W37: 0.12 | X37: החוב לא נחות | Z37: חברת ציטוט | AA37: אי-תלות | AB37: 46203 | AC37: 46203 | AD37: 1730769.2 | AE37: 1 | AF37: 104.9 | AG37: 1815.5769 | AJ37: שווי הוגן | AK37: 0.014655633 | AL37: =AG37/'סכום נכסים'!$B$30 -> 0.00032687522

Sheet לא סחיר מניות מבכ ויהש
A1: מספר קופה/קרן/ח.פ. עבור חברת ביטוח | B1: מספר מסלול | C1: שם מנפיק | D1: מספר מנפיק | E1: סוג מספר מזהה מנפיק | F1: שם נייר ערך | G1: מספר נייר ערך | H1: סוג מספר נייר ערך | I1: מאפיין עיקרי | J1: ישראל/חו"ל | K1: מדינה לפי חשיפה כלכלית | L1: סטאטוס סחירות | M1: ענף מסחר | N1: בעל עניין/צד קשור | O1: תאריך רכישה | P1: מטבע פעילות | Q1: סוג גורם משערך | R1: תלות/אי-תלות המשערך | S1: תאריך שערוך אחרון | T1: תאריך אחרון בו נבחנה בפועל ירידת ערך | U1: ערך נקוב (יחידות) | V1: שער חליפין | W1: שער נייר הערך | X1: שווי הוגן (באלפי ש"ח) | Y1: שיעור מנכסי אפיק ההשקעה | Z1: שיעור מסך נכסי ההשקעה
A2: 13908 | B2: 13908 | C2: HUMANZ LTD | D2: 515599009 | E2: ח.פ. | F2: HUMANZ | G2: 11019400 | H2: פנימי | I2: מניות לא סחירות | J2: ישראל | K2: גרמניה | L2: לא סחיר | M2: תוכנה ואינטרנט | N2: לא | O2: 45657 | P2: USD | Q2: מומחה בלתי תלוי | R2: אי-תלות | S2: 46203 | T2: 46203 | U2: 617 | V2: 2.978 | W2: 4310.8686 | X2: 79.20902 | Y2: 0.0011538533 | Z2: =X2/'סכום נכסים'!$B$30 -> 1.4260737e-05
A3: 13908 | B3: 13908 | C3: CANDID | D3: 540300662 | E3: מספר שותפות | F3: CANDID 2 | G3: 11019989 | H3: פנימי | I3: מניות לא סחירות | J3: ישראל | K3: ארה"ב | L3: לא סחיר | M3: שרותים | N3: לא | O3: 45657 | P3: USD | Q3: דיווח מנהל הקרן | R3: אי-תלות | S3: 46203 | T3: 46203 | U3: 178442.41 | V3: 2.978 | W3: 144.232 | X3: 766.45101 | Y3: 0.011165042 | Z3: =X3/'סכום נכסים'!$B$30 -> 0.00013799131
A4: 13908 | B4: 13908 | C4: קרדיט 360 בע"מ | D4: 516491776 | E4: ח.פ. | F4: קרדיט 360 ל.ס | G4: 11021113 | H4: פנימי | I4: מניות לא סחירות | J4: ישראל | K4: ישראל | L4: לא סחיר | M4: שרותים פיננסיים | N4: לא | O4: 45657 | P4: ILS | Q4: מומחה בלתי תלוי | R4: אי-תלות | S4: 46203 | T4: 46203 | U4: 648150.94 | V4: 1 | W4: 358.4271 | X4: 2323.1486 | Y4: 0.033841761 | Z4: =X4/'סכום נכסים'!$B$30 -> 0.00041825808
A5: 13908 | B5: 13908 | C5: AGORA | D5: 515859049 | E5: ח.פ. | F5: AGORA ל.ס | G5: 11021257 | H5: פנימי | I5: מניות לא סחירות | J5: ישראל | K5: ארה"ב | L5: לא סחיר | M5: תוכנה ואינטרנט | N5: לא | O5: 45657 | P5: USD | Q5: דיווח מנהל הקרן | R5: אי-תלות | S5: 46203 | T5: 46203 | U5: 96312 | V5: 2.978 | W5: 994.3749 | X5: 2852.0376 | Y5: 0.041546191 | Z5: =X5/'סכום נכסים'!$B$30 -> 0.00051347889
A6: 13908 | B6: 13908 | C6: HUMANZ LTD | D6: 515599009 | E6: ח.פ. | F6: HUMANZ SAFE | G6: 11021301 | H6: פנימי | I6: מניות לא סחירות | J6: ישראל | K6: ארה"ב | L6: לא סחיר | M6: השקעות בהייטק | N6: לא | O6: 45657 | P6: USD | Q6: דיווח מנהל הקרן | R6: אי-תלות | S6: 46203 | T6: 46203 | U6: 650000 | V6: 2.978 | W6: 296.3521 | X6: 5736.4876 | Y6: 0.08356454 | Z6: =X6/'סכום נכסים'!$B$30 -> 0.0010327933
A7: 13908 | B7: 13908 | C7: Sunbit Inc | D7: 515446821 | E7: ח.פ. | F7: SUNBIT 3 | G7: 11021306 | H7: פנימי | I7: מניות לא סחירות | J7: ישראל | K7: ארה"ב | L7: לא סחיר | M7: שרותים פיננסיים | N7: לא | O7: 45657 | P7: USD | Q7: דיווח מנהל הקרן | R7: אי-תלות | S7: 46203 | T7: 46203 | U7: 300000 | V7: 2.978 | W7: 173.1427 | X7: 1546.8569 | Y7: 0.022533367 | Z7: =X7/'סכום נכסים'!$B$30 -> 0.00027849505
A8: 13908 | B8: 13908 | C8: (KSP פי.אס.די.אס יזמות בע"מ (קבוצת | D8: 513591115 | E8: ח.פ. | F8: KSP פי אס די אס | G8: 11022486 | H8: פנימי | I8: מניות לא סחירות | J8: ישראל | K8: ישראל | L8: לא סחיר | M8: רשתות שיווק | N8: לא | O8: 45875 | P8: ILS | Q8: דיווח מנהל הקרן | R8: אי-תלות | S8: 46203 | T8: 46203 | U8: 9000000 | V8: 1 | W8: 148.5236 | X8: 13367.124 | Y8: 0.19472152 | Z8: =X8/'סכום נכסים'!$B$30 -> 0.0024066078
A9: 13908 | B9: 13908 | C9: לואן ווייז בע"מ | D9: 516961604 | E9: ח.פ. | F9: לואן ווייז | G9: 11022516 | H9: פנימי | I9: מניות לא סחירות | J9: ישראל | K9: ישראל | L9: לא סחיר | M9: שרותים פיננסיים | N9: לא | O9: 45897 | P9: ILS | Q9: דיווח מנהל הקרן | R9: אי-תלות | S9: 46203 | T9: 46203 | U9: 16293.33 | V9: 1 | W9: 14400 | X9: 2346.2395 | Y9: 0.034178131 | Z9: =X9/'סכום נכסים'!$B$30 -> 0.00042241535
A10: 13908 | B10: 13908 | C10: קרדיט 360 בע"מ | D10: 516491776 | E10: ח.פ. | F10: קרדיט 360 | G10: 11022519 | H10: פנימי | I10: מניות לא סחירות | J10: ישראל | K10: ישראל | L10: לא סחיר | M10: שרותים פיננסיים | N10: לא | O10: 45930 | P10: ILS | Q10: דיווח מנהל הקרן | R10: אי-תלות | S10: 46203 | T10: 46203 | U10: 1825568.1 | V10: 1 | W10: 100 | X10: 1825.5681 | Y10: 0.026593409 | Z10: =X10/'סכום נכסים'!$B$30 -> 0.00032867403
A11: 13908 | B11: 13908 | C11: CANDID | D11: 540300662 | E11: מספר שותפות | F11: CANDID 4 SAFE | G11: 11022827 | H11: פנימי | I11: מניות לא סחירות | J11: ישראל | K11: ארה"ב | L11: לא סחיר | M11: ביטוח | N11: לא | O11: 45853 | P11: USD | Q11: דיווח מנהל הקרן | R11: אי-תלות | S11: 46203 | T11: 46203 | U11: 15624.83 | V11: 2.978 | W11: 82.1551 | X11: 38.22738 | Y11: 0.00055686574 | Z11: =X11/'סכום נכסים'!$B$30 -> 6.8824311e-06
A12: 13908 | B12: 13908 | C12: UVEYE LTD | D12: 514234202 | E12: ח.פ. | F12: UVEYE - CLA | G12: 11022831 | H12: פנימי | I12: מניות לא סחירות | J12: ישראל | K12: ארה"ב | L12: לא סחיר | M12: תוכנה ואינטרנט | N12: לא | O12: 45880 | P12: USD | Q12: דיווח מנהל הקרן | R12: אי-תלות | S12: 46203 | T12: 46203 | U12: 362900 | V12: 2.978 | W12: 100 | X12: 1080.7162 | Y12: 0.015743005 | Z12: =X12/'סכום נכסים'!$B$30 -> 0.0001945714
A13: 13908 | B13: 13908 | C13: Ener-T International Ltd. | D13: 514301712 | E13: ח.פ. | F13: Ener-T International Ltd. | G13: 11150030 | H13: פנימי | I13: מניות לא סחירות | J13: ישראל | K13: ישראל | L13: לא סחיר | M13: אנרגיה מתחדשת | N13: לא | O13: 46198 | P13: ILS | Q13: דיווח מנהל הקרן | R13: אי-תלות | S13: 46203 | T13: 46203 | U13: 2240 | V13: 1 | W13: 1000000 | X13: 22400 | Y13: 0.32630519 | Z13: =X13/'סכום נכסים'!$B$30 -> 0.0040328806
A14: 13908 | B14: 13908 | C14: UVEYE LTD | D14: 514234202 | E14: ח.פ. | F14: UVEYE (PENSIA) | G14: 11019758 | H14: פנימי | I14: מניות לא סחירות | J14: חו"ל | K14: ארה"ב | L14: לא סחיר | M14: Software | N14: לא | O14: 45699 | P14: USD | Q14: דיווח מנהל הקרן | R14: אי-תלות | S14: 46203 | T14: 46203 | U14: 66260.84 | V14: 2.978 | W14: 1129 | X14: 2227.7968 | Y14: 0.032452752 | Z14: =X14/'סכום נכסים'!$B$30 -> 0.000401091
A15: 13908 | B15: 13908 | C15: Sauce Inc | D15: 549300JHLCR4 | E15: מספר תאגיד או שותפות בחו"ל | F15: SAUCE 1 | G15: 11021270 | H15: פנימי | I15: מניות לא סחירות | J15: חו"ל | K15: ארה"ב | L15: לא סחיר | M15: Technology Hardware, Storage & Peripherals | N15: לא | O15: 45657 | P15: USD | Q15: דיווח מנהל הקרן | R15: אי-תלות | S15: 46203 | T15: 46203 | U15: 900000 | V15: 2.978 | W15: 100 | X15: 2680.2 | Y15: 0.039042999 | Z15: =X15/'סכום נכסים'!$B$30 -> 0.00048254136
A16: 13908 | B16: 13908 | C16: BitSight Technologies, Inc | D16: 20213498049 | E16: מספר תאגיד או שותפות בחו"ל | F16: BITSIGHT | G16: 11022807 | H16: פנימי | I16: מניות לא סחירות | J16: חו"ל | K16: ארה"ב | L16: לא סחיר | M16: Other | N16: לא | O16: 45775 | P16: USD | Q16: דיווח מנהל הקרן | R16: אי-תלות | S16: 46203 | T16: 46203 | U16: 1007 | V16: 2.978 | W16: 5250 | X16: 157.43941 | Y16: 0.0022934508 | Z16: =X16/'סכום נכסים'!$B$30 -> 2.8345283e-05
A17: 13908 | B17: 13908 | C17: Seal Cybersecurity | D17: 7310928 | E17: מספר תאגיד או שותפות בחו"ל | F17: SEAL CYBER | G17: 11022824 | H17: פנימי | I17: מניות לא סחירות | J17: חו"ל | K17: ארה"ב | L17: לא סחיר | M17: Capital Markets | N17: לא | O17: 45806 | P17: USD | Q17: דיווח מנהל הקרן | R17: אי-תלות | S17: 46203 | T17: 46203 | U17: 1214083.4 | V17: 2.978 | W17: 74.13 | X17: 2680.2 | Y17: 0.039042998 | Z17: =X17/'סכום נכסים'!$B$30 -> 0.00048254135
A18: 13908 | B18: 13908 | C18: WONDERFULL OPORTUNITY | D18: 984500C7B6D | E18: מספר תאגיד או שותפות בחו"ל | F18: WONDERFULL OPORTUNITY | G18: 11150005 | H18: פנימי | I18: מניות לא סחירות | J18: חו"ל | K18: ישראל | L18: לא סחיר | M18: Other | N18: לא | O18: 46110 | P18: USD | Q18: דיווח מנהל הקרן | R18: אי-תלות | S18: 46203 | T18: 46203 | U18: 606000.23 | V18: 2.978 | W18: 100 | X18: 1804.6687 | Y18: 0.026288962 | Z18: =X18/'סכום נכסים'!$B$30 -> 0.00032491131
A19: 13908 | B19: 13908 | C19: MORE 7VTECH, LIMITED PARTNERSHIP | D19: 540300233 | E19: מספר שותפות | F19: WEKA (MTV1) | G19: 11150023 | H19: פנימי | I19: מניות לא סחירות | J19: חו"ל | K19: ארה"ב | L19: לא סחיר | M19: Technology Hardware, Storage & Peripherals | N19: לא | O19: 46174 | P19: USD | Q19: דיווח מנהל הקרן | R19: אי-תלות | S19: 46203 | T19: 46203 | U19: 1590000 | V19: 2.978 | W19: 100 | X19: 4735.02 | Y19: 0.068975965 | Z19: =X19/'סכום נכסים'!$B$30 -> 0.00085248974

Sheet קרנות השקעה
A1: מספר קופה/קרן/ח.פ. עבור חברת ביטוח | B1: מספר מסלול | C1: שם שותף כללי קרן השקעות | D1: מספר מזהה שותף כללי קרן השקעות | E1: סוג מספר מזהה שותף כללי קרן השקעות | F1: שם קרן השקעה | G1: מספר מזהה קרן השקעה | H1: סוג מספר מזהה קרן השקעות | I1: מאפיין עיקרי | J1: אסטרטגיית קרן ההשקעה | K1: ישראל/חו"ל | L1: מדינת התאגדות קרן השקעה | M1: מיקום משרד השותף הכללי | N1: מדינה לפי חשיפה כלכלית | O1: בעל עניין/צד קשור | P1: תאריך רכישה | Q1: מטבע פעילות | R1: סוג גורם משערך | S1: תלות/אי-תלות המשערך | T1: תאריך שערוך אחרון | U1: שער חליפין | V1: NAV (במטבע הדיווח של קרן ההשקעה) | W1: שווי הוגן (באלפי ש"ח) | X1: שיעור החזקה בקרן השקעה | Y1: שיעור מנכסי אפיק ההשקעה | Z1: שיעור מסך נכסי ההשקעה
A2: 13908 | B2: 13908 | C2: Scintilla Holdings Ltd | F2: SCINTILLA | G2: 11020474 | H2: פנימי | I2: קרן השקעה אחרת | K2: ישראל | N2: ישראל | O2: לא | P2: 45657 | Q2: USD | R2: דיווח מנהל הקרן | S2: אי-תלות | T2: 46203 | U2: 2.978 | V2: 145.31473 | W2: 432.74726 | X2: 0 | Y2: 0.0014662882 | Z2: =W2/'סכום נכסים'!$B$30 -> 7.7911518e-05
A3: 13908 | B3: 13908 | C3: Viola Credit GL II (UVCI) | F3: VIOLA CREDIT UVCI | G3: 11020490 | H3: פנימי | I3: קרן השקעה אחרת | K3: ישראל | N3: ארה"ב | O3: לא | P3: 45657 | Q3: USD | R3: דיווח מנהל הקרן | S3: אי-תלות | T3: 46203 | U3: 2.978 | V3: 53.21905 | W3: 158.48633 | X3: 0 | Y3: 0.00053700313 | Z3: =W3/'סכום נכסים'!$B$30 -> 2.853377e-05
A4: 13908 | B4: 13908 | C4: Rakia Capital Fund, LP | F4: RS TACTIC GEAR | G4: 11021133 | H4: פנימי | I4: פרייבט אקוויטי | K4: ישראל | N4: Developed Markets - Pacific | O4: לא | P4: 45657 | Q4: ILS | R4: דיווח מנהל הקרן | S4: אי-תלות | T4: 46203 | U4: 1 | V4: 3625.7627 | W4: 3625.7627 | X4: 0 | Y4: 0.012285261 | Z4: =W4/'סכום נכסים'!$B$30 -> 0.00065277981
A5: 13908 | B5: 13908 | C5: CERCA OPPORTUNITIES GP, LIMITED PARTNERSHIP | F5: CERCA גמל | G5: 11021279 | H5: פנימי | I5: קרן השקעה אחרת | K5: ישראל | N5: ישראל | O5: לא | P5: 45657 | Q5: USD | R5: דיווח מנהל הקרן | S5: אי-תלות | T5: 46203 | U5: 2.978 | V5: 328.94492 | W5: 979.59796 | X5: 0 | Y5: 0.0033191958 | Z5: =W5/'סכום נכסים'!$B$30 -> 0.00017636614
A6: 13908 | B6: 13908 | C6: ג.ש.אחזקות אי.בי.סי בע"מ | F6: שותפות פייבר | G6: 11022492 | H6: פנימי | I6: קרן השקעה אחרת | K6: ישראל | N6: ישראל | O6: לא | P6: 45960 | Q6: ILS | R6: דיווח מנהל הקרן | S6: אי-תלות | T6: 46203 | U6: 1 | V6: 15501.77 | W6: 15501.77 | X6: 0 | Y6: 0.052525028 | Z6: =W6/'סכום נכסים'!$B$30 -> 0.002790928
A7: 13908 | B7: 13908 | C7: קוגיטו קפיטל 3 שותף כללי בע"מ | F7: קוגיטו קפיטל 3 | G7: 11022538 | H7: פנימי | I7: קרן השקעה אחרת | K7: ישראל | N7: ישראל | O7: לא | P7: 46139 | Q7: ILS | R7: דיווח מנהל הקרן | S7: אי-תלות | T7: 46203 | U7: 1 | V7: 593.13479 | W7: 593.13479 | X7: 0 | Y7: 0.0020097332 | Z7: =W7/'סכום נכסים'!$B$30 -> 0.00010678758
A8: 13908 | B8: 13908 | C8: Green Lantern Management | F8: GREEN LANTERN | G8: 11022549 | H8: פנימי | I8: קרן השקעה אחרת | K8: ישראל | N8: ישראל | O8: לא | P8: 46019 | Q8: ILS | R8: דיווח מנהל הקרן | S8: אי-תלות | T8: 46203 | U8: 1 | V8: 4741.4829 | W8: 4741.4829 | X8: 0 | Y8: 0.016065683 | Z8: =W8/'סכום נכסים'!$B$30 -> 0.00085365332
A9: 13908 | B9: 13908 | C9: I.L.P Legacy Ltd | F9: LEGACY FUND II | G9: 11022557 | H9: פנימי | I9: קרן השקעה אחרת | K9: ישראל | N9: ישראל | O9: לא | P9: 46056 | Q9: ILS | R9: דיווח מנהל הקרן | S9: אי-תלות | T9: 46203 | U9: 1 | V9: 7153.845 | W9: 7153.845 | X9: 0 | Y9: 0.024239549 | Z9: =W9/'סכום נכסים'!$B$30 -> 0.0012879733
A10: 13908 | B10: 13908 | C10: HIA Capital Partners Ltd | F10: SHARK TOPCO 1 | G10: 11022778 | H10: פנימי | I10: פרייבט אקוויטי | K10: ישראל | N10: ארה"ב | O10: לא | P10: 45673 | Q10: USD | R10: דיווח מנהל הקרן | S10: אי-תלות | T10: 46203 | U10: 2.978 | V10: 603.75 | W10: 1797.9675 | X10: 0 | Y10: 0.0060920975 | Z10: =W10/'סכום נכסים'!$B$30 -> 0.00032370483
A11: 13908 | B11: 13908 | C11: Red Dot III General Partner L.P. | F11: RED DOT 3 CAPITAL | G11: 11022812 | H11: פנימי | I11: קרן השקעה אחרת | K11: ישראל | N11: ישראל | O11: לא | P11: 45771 | Q11: USD | R11: דיווח מנהל הקרן | S11: אי-תלות | T11: 46203 | U11: 2.978 | V11: 1132.6931 | W11: 3373.16 | X11: 0 | Y11: 0.011429361 | Z11: =W11/'סכום נכסים'!$B$30 -> 0.00060730141
A12: 13908 | B12: 13908 | C12: TBD VC GP LP | F12: TBD VC, L.P | G12: 11022813 | H12: פנימי | I12: קרן השקעה אחרת | K12: ישראל | N12: ישראל | O12: לא | P12: 45771 | Q12: USD | R12: דיווח מנהל הקרן | S12: אי-תלות | T12: 46203 | U12: 2.978 | V12: 120.70456 | W12: 359.45817 | X12: 0 | Y12: 0.001217961 | Z12: =W12/'סכום נכסים'!$B$30 -> 6.4716601e-05
A13: 13908 | B13: 13908 | C13: CERCA OPPORTUNITIES GP, LIMITED PARTNERSHIP | F13: 4CECRA | G13: 11022819 | H13: פנימי | I13: פרייבט אקוויטי | K13: ישראל | N13: ישראל | O13: לא | P13: 45797 | Q13: USD | R13: דיווח מנהל הקרן | S13: אי-תלות | T13: 46203 | U13: 2.978 | V13: 56.659265 | W13: 168.73129 | X13: 0 | Y13: 0.00057171638 | Z13: =W13/'סכום נכסים'!$B$30 -> 3.0378265e-05
... A23: 13908 | B23: 13908 | C23: HP Islazul Co-Invest GP S.?.r.l., | F23: HENDERSON ISLAZU | G23: 11019352 | H23: פנימי | I23: קרן השקעה אחרת | K23: חו"ל | N23: ספרד | O23: לא | P23: 45657 | Q23: EUR | R23: דיווח מנהל הקרן | S23: אי-תלות | T23: 46203 | U23: 3.3945 | V23: 270.59804 | W23: 918.54504 | X23: 0 | Y23: 0.0031123287 | Z23: =W23/'סכום נכסים'!$B$30 -> 0.00016537422
A24: 13908 | B24: 13908 | C24: F.S. TRANSIT | F24: F.S. TRANSIT MUTUAL FUND -USD | G24: XS1234567890 | H24: ISIN | I24: קרן השקעה אחרת | K24: חו"ל | N24: ארה"ב | O24: לא | P24: 46198 | Q24: USD | R24: דיווח מנהל הקרן | S24: אי-תלות | T24: 46203 | U24: 2.978 | V24: 984 | W24: 2930.352 | X24: 0 | Y24: 0.0099289837 | Z24: =W24/'סכום נכסים'!$B$30 -> 0.00052757855
A25: 13908 | B25: 13908 | C25: HGI Multifamily Credit Fund GP LLC | F25: HGI MULTIFAMILY | G25: 11019991 | H25: פנימי | I25: קרן השקעה אחרת | K25: חו"ל | N25: ארה"ב | O25: לא | P25: 45657 | Q25: USD | R25: דיווח מנהל הקרן | S25: אי-תלות | T25: 46203 | U25: 2.978 | V25: 273.49663 | W25: 814.47297 | X25: 0 | Y25: 0.0027596988 | Z25: =W25/'סכום נכסים'!$B$30 -> 0.00014663715
A26: 13908 | B26: 13908 | C26: HARBOURVEST GP LLC | F26: DOVER STREET XL | G26: 11019995 | H26: פנימי | I26: קרן השקעה אחרת | K26: חו"ל | N26: ארה"ב | O26: לא | P26: 45657 | Q26: USD | R26: דיווח מנהל הקרן | S26: אי-תלות | T26: 46203 | U26: 2.978 | V26: 132.04107 | W26: 393.21832 | X26: 0 | Y26: 0.0013323513 | Z26: =W26/'סכום נכסים'!$B$30 -> 7.0794755e-05
A27: 13908 | B27: 13908 | C27: Sheva Growth Investments L.P | F27: SHEVA GROWTH INVESTMENTS S1 | G27: 11020002 | H27: פנימי | I27: קרן השקעה אחרת | K27: חו"ל | N27: ארה"ב | O27: לא | P27: 45657 | Q27: USD | R27: דיווח מנהל הקרן | S27: אי-תלות | T27: 46203 | U27: 2.978 | V27: 60.163801 | W27: 179.1678 | X27: 0 | Y27: 0.00060707866 | Z27: =W27/'סכום נכסים'!$B$30 -> 3.2257247e-05
A28: 13908 | B28: 13908 | C28: LUCID ALTERNATIVE FUND, LP | F28: LUCID ALTERNATIVE FUND | G28: 11020009 | H28: פנימי | I28: קרן גידור (Hedge Fund) | K28: חו"ל | N28: איי קיימן | O28: לא | P28: 45657 | Q28: USD | R28: דיווח מנהל הקרן | S28: אי-תלות | T28: 46203 | U28: 2.978 | V28: 352.89619 | W28: 1050.9249 | X28: 0 | Y28: 0.0035608745 | Z28: =W28/'סכום נכסים'!$B$30 -> 0.00018920779
A29: 13908 | B29: 13908 | C29: Oak Street Real Estate Capital Fund VI, LP | F29: OAK STREET REAL ESTATE VI | G29: 11020012 | H29: פנימי | I29: קרן נדל"ן | K29: חו"ל | N29: ארה"ב | O29: לא | P29: 45657 | Q29: USD | R29: דיווח מנהל הקרן | S29: אי-תלות | T29: 46203 | U29: 2.978 | V29: 568.99935 | W29: 1694.4801 | X29: 0 | Y29: 0.0057414485 | Z29: =W29/'סכום נכסים'!$B$30 -> 0.00030507302
A30: 13908 | B30: 13908 | C30: PANTHEON PGIF IV GP | F30: PANTHEON GLOBAL INFRASTRUCTURE | G30: 11020456 | H30: פנימי | I30: קרן השקעה אחרת | K30: חו"ל | N30: לוכסמבורג | O30: לא | P30: 45657 | Q30: USD | R30: דיווח מנהל הקרן | S30: אי-תלות | T30: 46203 | U30: 2.978 | V30: 884.03424 | W30: 2632.654 | X30: 0 | Y30: 0.0089202861 | Z30: =W30/'סכום נכסים'!$B$30 -> 0.0004739812
A31: 13908 | B31: 13908 | C31: Scintilla Tech Ltd | F31: MORETECH VENTURES II | G31: 11020463 | H31: פנימי | I31: פרייבט אקוויטי | K31: חו"ל | N31: ישראל | O31: לא | P31: 45657 | Q31: USD | R31: דיווח מנהל הקרן | S31: אי-תלות | T31: 46203 | U31: 2.978 | V31: 227.54877 | W31: 677.64023 | X31: 0 | Y31: 0.002296065 | Z31: =W31/'סכום נכסים'!$B$30 -> 0.00012200188
A32: 13908 | B32: 13908 | C32: HPS GP Lux Sarl | F32: HPS SPECIALTY LOAN | G32: 11020470 | H32: פנימי | I32: קרן השקעה אחרת | K32: חו"ל | N32: ארה"ב | O32: לא | P32: 45657 | Q32: USD | R32: דיווח מנהל הקרן | S32: אי-תלות | T32: 46203 | U32: 2.978 | V32: 256.33677 | W32: 763.3709 | X32: 0 | Y32: 0.0025865484 | Z32: =W32/'סכום נכסים'!$B$30 -> 0.00013743677
A33: 13908 | B33: 13908 | C33: Henderson Park Real Estate Fund II GP S.? r.l | F33: HENDERSON PARK REAL | G33: 11020471 | H33: פנימי | I33: קרן נדל"ן | K33: חו"ל | N33: לוכסמבורג | O33: לא | P33: 45657 | Q33: EUR | R33: דיווח מנהל הקרן | S33: אי-תלות | T33: 46203 | U33: 3.3945 | V33: 1102.605 | W33: 3742.7928 | X33: 0 | Y33: 0.012681797 | Z33: =W33/'סכום נכסים'!$B$30 -> 0.00067384983
A34: 13908 | B34: 13908 | C34: Sheva Growth Investments L.P | F34: SHEVA GROWTH 2 | G34: 11020475 | H34: פנימי | I34: קרן השקעה אחרת | K34: חו"ל | N34: ארה"ב | O34: לא | P34: 45657 | Q34: USD | R34: דיווח מנהל הקרן | S34: אי-תלות | T34: 46203 | U34: 2.978 | V34: 1374.0277 | W34: 4091.8546 | X34: 0 | Y34: 0.013864531 | Z34: =W34/'סכום נכסים'!$B$30 -> 0.00073669467
A35: 13908 | B35: 13908 | C35: Target Global Selected Opportunities LLC | F35: TARGET GLOBAL BOHRIUM | G35: 11020481 | H35: פנימי | I35: פרייבט אקוויטי | K35: חו"ל | N35: ארה"ב | O35: לא | P35: 45657 | Q35: USD | R35: דיווח מנהל הקרן | S35: אי-תלות | T35: 46203 | U35: 2.978 | V35: 0.6890094 | W35: 2.05187 | X35: 0 | Y35: 6.9524016e-06 | Z35: =W35/'סכום נכסים'!$B$30 -> 3.6941726e-07
A36: 13908 | B36: 13908 | C36: HARBOURVEST GP LLC | F36: HV GONDOR FEEDER | G36: 11020502 | H36: פנימי | I36: קרן השקעה אחרת | K36: חו"ל | N36: איי קיימן | O36: לא | P36: 45657 | Q36: USD | R36: דיווח מנהל הקרן | S36: אי-תלות | T36: 46203 | U36: 2.978 | V36: 813.35268 | W36: 2422.1643 | X36: 0 | Y36: 0.0082070788 | Z36: =W36/'סכום נכסים'!$B$30 -> 0.00043608479
... A76: 13908 | B76: 13908 | C76: EQT AI Infrastructure (General Partner) | F76: SCSp Infrastructure AI - פנסיה | G76: 11150032 | H76: פנימי | I76: קרן השקעה אחרת | K76: חו"ל | N76: גלובלי | O76: לא | P76: 46198 | Q76: USD | R76: דיווח מנהל הקרן | S76: אי-תלות | T76: 46203 | U76: 2.978 | V76: 8500 | W76: 25313 | X76: 0.002125 | Y76: 0.08576866 | Z76: =W76/'סכום נכסים'!$B$30 -> 0.0045573351
A77: 13908 | B77: 13908 | C77: 1L-MORE ALTERNATIVE CREDIT GP LTD | F77: MORE 8/23 | G77: XD1489193247 | H77: ISIN | I77: קרן גידור (Hedge Fund) | K77: חו"ל | N77: ישראל | O77: כן | P77: 45923 | Q77: USD | R77: דיווח מנהל הקרן | S77: אי-תלות | T77: 46203 | U77: 2.978 | V77: 22.073586 | W77: 65.73514 | X77: 0 | Y77: 0.00022273199 | Z77: =W77/'סכום נכסים'!$B$30 -> 1.1834909e-05
A78: 13908 | B78: 13908 | C78: 1L-MORE ALTERNATIVE CREDIT GP LTD | F78: MORE 2/23 | G78: XD1489193254 | H78: ISIN | I78: קרן גידור (Hedge Fund) | K78: חו"ל | N78: ישראל | O78: כן | P78: 45923 | Q78: USD | R78: דיווח מנהל הקרן | S78: אי-תלות | T78: 46203 | U78: 2.978 | V78: 41.353439 | W78: 123.15054 | X78: 0 | Y78: 0.000417274 | Z78: =W78/'סכום נכסים'!$B$30 -> 2.2171938e-05
A79: 13908 | B79: 13908 | C79: 1L-MORE ALTERNATIVE CREDIT GP LTD | F79: MORE 3/23 | G79: XD1489193262 | H79: פנימי | I79: קרן השקעה אחרת | K79: חו"ל | N79: ישראל | O79: כן | P79: 45923 | Q79: USD | R79: דיווח מנהל הקרן | S79: אי-תלות | T79: 46203 | U79: 2.978 | V79: 58.514963 | W79: 174.25756 | X79: 0 | Y79: 0.00059044117 | Z79: =W79/'סכום נכסים'!$B$30 -> 3.1373211e-05
A80: 13908 | B80: 13908 | C80: 1L-MORE ALTERNATIVE CREDIT GP LTD | F80: MORE 10/24 | G80: XD1489461263 | H80: ISIN | I80: קרן גידור (Hedge Fund) | K80: חו"ל | N80: ישראל | O80: כן | P80: 45923 | Q80: USD | R80: דיווח מנהל הקרן | S80: אי-תלות | T80: 46203 | U80: 2.978 | V80: 114.65064 | W80: 341.42962 | X80: 0 | Y80: 0.0011568744 | Z80: =W80/'סכום נכסים'!$B$30 -> 6.1470753e-05
A81: 13908 | B81: 13908 | C81: 1L-MORE ALTERNATIVE CREDIT GP LTD | F81: 1L MORE 11 | G81: XD1488921812 | H81: ISIN | I81: קרן גידור (Hedge Fund) | K81: חו"ל | N81: ישראל | O81: כן | P81: 45923 | Q81: ILS | R81: דיווח מנהל הקרן | S81: אי-תלות | T81: 46203 | U81: 1 | V81: 670.63106 | W81: 670.63106 | X81: 0 | Y81: 0.0022723157 | Z81: =W81/'סכום נכסים'!$B$30 -> 0.00012073995
A82: 13908 | B82: 13908 | C82: 1L-MORE ALTERNATIVE CREDIT GP LTD | F82: 1L MORE ALT CR FD LP (E) USD S | G82: XD1493478915 | H82: ISIN | I82: קרן השקעה אחרת | K82: חו"ל | N82: ארה"ב | O82: כן | P82: 45963 | Q82: USD | R82: דיווח מנהל הקרן | S82: אי-תלות | T82: 46203 | U82: 2.978 | V82: 158.99737 | W82: 473.49417 | X82: 0 | Y82: 0.0016043519 | Z82: =W82/'סכום נכסים'!$B$30 -> 8.5247564e-05
A83: 13908 | B83: 13908 | C83: CONVERTECH FUND | F83: CONVERTECH FUND (E) SERIES 6/2 | G83: KYG2524W1399 | H83: פנימי | I83: קרן גידור (Hedge Fund) | K83: חו"ל | N83: ארה"ב | O83: לא | P83: 46174 | Q83: USD | R83: דיווח מנהל הקרן | S83: אי-תלות | T83: 46203 | U83: 2.978 | V83: 1574.4 | W83: 4688.5632 | X83: 0 | Y83: 0.015886374 | Z83: =W83/'סכום נכסים'!$B$30 -> 0.00084412569

Sheet לא סחיר כתבי אופציה
A1: מספר קופה/קרן/ח.פ. עבור חברת ביטוח | B1: מספר מסלול | C1: שם מנפיק | D1: מספר מנפיק | E1: סוג מספר מזהה מנפיק | F1: שם נייר ערך | G1: מספר נייר ערך | H1: סוג מספר נייר ערך | I1: ישראל/חו"ל | J1: מדינה לפי חשיפה כלכלית | K1: סטאטוס סחירות | L1: נכס בסיס (כתב אופציה) | M1: ענף מסחר | N1: תאריך פקיעה | O1: בעל עניין/צד קשור | P1: תאריך רכישה | Q1: מטבע פעילות | R1: סוג גורם משערך | S1: תלות/אי-תלות המשערך | T1: תאריך שערוך אחרון | U1: שער מימוש | V1: יחס המרה | W1: ערך נקוב (יחידות) | X1: שער נייר הערך | Y1: שער חליפין | Z1: שווי הוגן (באלפי ש"ח) | AA1: שיעור מנכסי אפיק ההשקעה | AB1: שיעור מסך נכסי ההשקעה
A2: 13908 | B2: 13908 | C2: מצלאוי חברה לבנין בע"מ | D2: 512726712 | E2: ח.פ. | F2: מצלאוי אופ ל.ס | G2: 11019773 | H2: פנימי | I2: ישראל | J2: ישראל | K2: לא סחיר | L2: IL0011067498 | M2: בנייה | N2: 46329 | O2: לא | P2: 45657 | Q2: ILS | R2: אחר | S2: אי-תלות | T2: 46203 | U2: 1004.64 | V2: 1 | W2: 100000 | X2: 12.7573 | Y2: 1 | Z2: 12.7573 | AA2: 0.0014212684 | AB2: =Z2/'סכום נכסים'!$B$30 -> 2.2968155e-06
A3: 13908 | B3: 13908 | C3: אזורים-חברה להשקעות בפתוח ובבנ | D3: 520025990 | E3: ח.פ. | F3: אזורים אופ ל.ס | G3: 11019774 | H3: פנימי | I3: ישראל | J3: ישראל | K3: לא סחיר | L3: IL0007150118 | M3: פארמה | N3: 46802 | O3: לא | P3: 46078 | Q3: ILS | R3: אחר | S3: אי-תלות | T3: 46203 | U3: 3000 | V3: 1 | W3: 120000 | X3: 115.4366 | Y3: 1 | Z3: 138.52392 | AA3: 0.015432707 | AB3: =Z3/'סכום נכסים'!$B$30 -> 2.4939751e-05
A4: 13908 | B4: 13908 | C4: סולאיר אנרגיות מתחדשות בע"מ | D4: 516046307 | E4: ח.פ. | F4: סולאיר אופ ל.ס2 | G4: 11019939 | H4: פנימי | I4: ישראל | J4: ישראל | K4: לא סחיר | L4: IL0011722878 | M4: אנרגיה מתחדשת | N4: 46747 | O4: לא | P4: 45657 | Q4: ILS | R4: אחר | S4: אי-תלות | T4: 46203 | U4: 4560 | V4: 1 | W4: 52500 | X4: 4494.701 | Y4: 1 | Z4: 2359.718 | AA4: 0.26289205 | AB4: =Z4/'סכום נכסים'!$B$30 -> 0.00042484201
A5: 13908 | B5: 13908 | C5: מגוריט ישראל בע"מ | D5: 515434074 | E5: ח.פ. | F5: מגוריט אופ ל.ס | G5: 11021157 | H5: פנימי | I5: ישראל | J5: ישראל | K5: לא סחיר | L5: IL0011391955 | M5: נדל"ן מניב בישראל | N5: 47360 | O5: לא | P5: 46056 | Q5: ILS | R5: אחר | S5: אי-תלות | T5: 46203 | U5: 1100 | V5: 1 | W5: 218100 | X5: 109.9423 | Y5: 1 | Z5: 239.78416 | AA5: 0.026713933 | AB5: =Z5/'סכום נכסים'!$B$30 -> 4.3170575e-05
A6: 13908 | B6: 13908 | C6: רב-בריח(08) תעשיות בע"מ | D6: 514160530 | E6: ח.פ. | F6: רב בריח אופ ל.ס | G6: 11022283 | H6: פנימי | I6: ישראל | J6: ישראל | K6: לא סחיר | L6: IL0011799934 | M6: מתכת ומוצרי בניה | N6: 46947 | O6: לא | P6: 45851 | Q6: ILS | R6: אחר | S6: אי-תלות | T6: 46203 | U6: 130 | V6: 1 | W6: 303100 | X6: 10.6648 | Y6: 1 | Z6: 32.32501 | AA6: 0.0036012727 | AB6: =Z6/'סכום נכסים'!$B$30 -> 5.8197725e-06
A7: 13908 | B7: 13908 | C7: קבוצת אקרו בע"מ | D7: 511996803 | E7: ח.פ. | F7: אקרו אופ ל.ס | G7: 11022448 | H7: פנימי | I7: ישראל | J7: ישראל | K7: לא סחיר | L7: IL0011849028 | M7: בנייה | N7: 46239 | O7: לא | P7: 45698 | Q7: ILS | R7: אחר | S7: אי-תלות | T7: 46203 | U7: 7000 | V7: 1 | W7: 6000 | X7: 0.1008 | Y7: 1 | Z7: 0.00605 | AA7: 6.740199e-07 | AB7: =Z7/'סכום נכסים'!$B$30 -> 1.0892378e-09
A8: 13908 | B8: 13908 | C8: קבוצת גבאי-בניה,יזום,ניהול ואח | D8: 513609131 | E8: ח.פ. | F8: קבוצת גבאי קיקר | G8: 11022462 | H8: פנימי | I8: ישראל | J8: ישראל | K8: לא סחיר | L8: IL0012246414 | M8: נדל"ן מניב בישראל | N8: 47188 | O8: לא | P8: 45746 | Q8: ILS | R8: אחר | S8: אי-תלות | T8: 46203 | U8: 6061.5 | V8: 1 | W8: 53969.25 | X8: 1470.0721 | Y8: 1 | Z8: 793.38689 | AA8: 0.088389843 | AB8: =Z8/'סכום נכסים'!$B$30 -> 0.00014284083
A9: 13908 | B9: 13908 | C9: איסתא אופציה לס | D9: 513754812 | E9: ח.פ. | F9: איסתא אופציה לס | G9: 11022502 | H9: פנימי | I9: ישראל | J9: ישראל | K9: לא סחיר | L9: IL0010810740 | M9: מלונאות ותיירות | N9: 47309 | O9: לא | P9: 45853 | Q9: ILS | R9: אחר | S9: אי-תלות | T9: 46203 | U9: 16000 | V9: 1 | W9: 2965 | X9: 716.0489 | Y9: 1 | Z9: 21.23085 | AA9: 0.0023652918 | AB9: =Z9/'סכום נכסים'!$B$30 -> 3.8223876e-06
A10: 13908 | B10: 13908 | C10: ג'נריישן קפיטל בע"מ | D10: 515846558 | E10: ח.פ. | F10: גנרשן קפ אפ לס | G10: 11022534 | H10: פנימי | I10: ישראל | J10: ישראל | K10: לא סחיר | L10: IL0011569261 | M10: השקעה ואחזקות | N10: 47141 | O10: לא | P10: 45953 | Q10: ILS | R10: אחר | S10: אי-תלות | T10: 46203 | U10: 140 | V10: 1 | W10: 2000000 | X10: 153.8384 | Y10: 1 | Z10: 3076.768 | AA10: 0.34277733 | AB10: =Z10/'סכום נכסים'!$B$30 -> 0.00055393919
A11: 13908 | B11: 13908 | C11: הכשרת הישוב מקבוצת נמרודי בע"מ | D11: 520020116 | E11: ח.פ. | F11: הכשרת ישוב אופ | G11: 11022539 | H11: פנימי | I11: ישראל | J11: ישראל | K11: לא סחיר | L11: IL0006120104 | M11: פארמה | N11: 46508 | O11: לא | P11: 45970 | Q11: ILS | R11: אחר | S11: אי-תלות | T11: 46203 | U11: 5000 | V11: 1 | W11: 22500 | X11: 104.3575 | Y11: 1 | Z11: 23.48044 | AA11: 0.0026159147 | AB11: =Z11/'סכום נכסים'!$B$30 -> 4.2274022e-06
A12: 13908 | B12: 13908 | C12: Ener-T International Ltd. | D12: 514301712 | E12: ח.פ. | F12: Ener-T International Ltd OPT | G12: 11022296 | H12: פנימי | I12: חו"ל | J12: ישראל | K12: לא סחיר | L12: IL0011150030 | M12: Other | N12: 48024 | O12: לא | P12: 46202 | Q12: ILS | R12: דיווח מנהל הקרן | S12: אי-תלות | T12: 46203 | U12: 1000000 | V12: 1 | W12: 746.67 | X12: 305090 | Y12: 1 | Z12: 2278.0155 | AA12: 0.25378971 | AB12: =Z12/'סכום נכסים'!$B$30 -> 0.00041013234

Sheet לא סחיר אופציות
A1: מספר קופה/קרן/ח.פ. עבור חברת ביטוח | B1: מספר מסלול | C1: שם מנפיק | D1: מספר מנפיק | E1: סוג מספר מזהה מנפיק | F1: שם נייר ערך | G1: מספר נייר ערך | H1: סוג מספר נייר ערך | I1: מאפיין עיקרי | J1: ישראל/חו"ל | K1: מדינה לפי חשיפה כלכלית | L1: ענף מסחר | M1: נכס בסיס | N1: תאריך פקיעה | O1: בעל עניין/צד קשור | P1: תאריך רכישה | Q1: מטבע פעילות | R1: סוג גורם משערך | S1: תלות/אי-תלות המשערך | T1: תאריך שערוך אחרון | U1: שער מימוש | V1: יחס המרה | W1: ערך נקוב (יחידות) | X1: שער נייר הערך | Y1: שער חליפין | Z1: שווי הוגן (באלפי ש"ח) | AA1: שיעור מנכסי אפיק ההשקעה | AB1: שיעור מסך נכסי ההשקעה

Sheet לא סחיר נגזרים אחרים
A1: מספר קופה/קרן/ח.פ. עבור חברת ביטוח | B1: מספר מסלול | C1: מאפיין עיקרי | D1: מספר עסקה (רגל 1) | E1: מטבע פעילות (רגל 1) | F1: שער חליפין (רגל 1) | G1: ערך נקוב (רגל 1) | H1: שווי הוגן במטבע הנסחר (רגל 1) | I1: שיעור מנכסי אפיק ההשקעה (רגל 1) | J1: שיעור מסך נכסי ההשקעה (רגל 1) | K1: מספר עסקה (רגל 2) | L1: מטבע פעילות (רגל 2) | M1: שער חליפין (רגל 2) | N1: ערך נקוב (רגל 2) | O1: שווי הוגן במטבע הנסחר (רגל 2) | P1: שיעור מנכסי אפיק ההשקעה (רגל 2) | Q1: שיעור מסך נכסי ההשקעה (רגל 2) | R1: שווי הוגן (נטו באלפי ש"ח) | S1: ישראל/חו"ל | T1: מדינה לפי חשיפה כלכלית | U1: סוג הנכס | V1: פקטור מוביל | W1: פקטור נוסף | X1: טיקר | Y1: בעל עניין/צד קשור | Z1: מועד ההתקשרות בעסקה | AA1: מועד סיום חוזי | AB1: תדירות Reset | AC1: סוג הסליקה | AD1: נספח התחשבנות בטחונות - CSA | AE1: גורם מצטט | AF1: ריבית עוגן | AG1: תקופת ריבית עוגן | AH1: שיעור ריבית עוגן | AI1: שער נכס הבסיס במועד ההתקשרות בעסקה | AJ1: שער הנגזר במועד ההתקשרות בעסקה | AK1: האם קיים קנס בגין יציאה מוקדמת | AL1: שיעור הקנס בגין יציאה מוקדמת | AM1: צד נגדי - Counterparty | AN1: שיעור מנכסי אפיק ההשקעה | AO1: שיעור מסך נכסי ההשקעה
A2: 13908 | B2: 13908 | C2: Unfunded Forward | D2: 903776 | E2: USD | F2: 3.366 | G2: -2800000 | H2: -2817.8822 | I2: 0.047339078 | J2: =H2/'סכום נכסים'!$B$30 -> -0.00050732956 | K2: 903776 | L2: ILS | M2: 1 | N2: 9424800 | O2: 9424.8 | P2: 0.074001482 | Q2: =O2/'סכום נכסים'!$B$30 -> 0.0016968345 | R2: 1033.1469 | S2: ישראל | T2: ישראל | U2: מט"ח | V2: אחר | W2: מט"ח/₪ | X2: USDILS | Y2: לא | Z2: 45868 | AA2: 46233 | AB2: ללא | AC2: Delivery | AD2: לא | AE2: הצד הנגדי | AF2: ללא | AG2: ללא | AI2: 336.6 | AM2: FIRBILIT | AN2: 0.11041649 | AO2: =R2/'סכום נכסים'!$B$30 -> 0.00018600705
A3: 13908 | B3: 13908 | C3: Unfunded Forward | D3: 903784 | E3: EUR | F3: 3.8825 | G3: -2400000 | H3: -2362.7412 | I3: 0.039692927 | J3: =H3/'סכום נכסים'!$B$30 -> -0.0004253863 | K3: 903784 | L3: ILS | M3: 1 | N3: 9318000 | O3: 9318 | P3: 0.073162911 | Q3: =O3/'סכום נכסים'!$B$30 -> 0.0016776063 | R3: 1297.6749 | S3: ישראל | T3: ישראל | U3: מט"ח | V3: אחר | W3: מט"ח/₪ | X3: EURILS | Y3: לא | Z3: 45868 | AA3: 46233 | AB3: ללא | AC3: Delivery | AD3: לא | AE3: הצד הנגדי | AF3: ללא | AG3: ללא | AI3: 388.25 | AM3: FIRBILIT | AN3: 0.13868765 | AO3: =R3/'סכום נכסים'!$B$30 -> 0.0002336325
A4: 13908 | B4: 13908 | C4: Unfunded Forward | D4: 975548 | E4: USD | F4: 3.417 | G4: -5700000 | H4: -5695.8195 | I4: 0.095687055 | J4: =H4/'סכום נכסים'!$B$30 -> -0.0010254714 | K4: 975548 | L4: ILS | M4: 1 | N4: 19476900 | O4: 19476.9 | P4: 0.15292839 | Q4: =O4/'סכום נכסים'!$B$30 -> 0.0035066076 | R4: 2514.7494 | S4: ישראל | T4: ישראל | U4: מט"ח | V4: אחר | W4: מט"ח/₪ | X4: USDILS | Y4: לא | Z4: 45876 | AA4: 46244 | AB4: ללא | AC4: Delivery | AD4: לא | AE4: הצד הנגדי | AF4: ללא | AG4: ללא | AI4: 341.7 | AM4: FIRBILIT | AN4: 0.26876122 | AO4: =R4/'סכום נכסים'!$B$30 -> 0.00045275375
A5: 13908 | B5: 13908 | C5: Unfunded Forward | D5: 8493604 | E5: USD | F5: 2.979 | G5: -2760000 | H5: -2437.3064 | I5: 0.040945586 | J5: =H5/'סכום נכסים'!$B$30 -> -0.00043881096 | K5: 8493604 | L5: ILS | M5: 1 | N5: 8222040 | O5: 8222.04 | P5: 0.064557672 | Q5: =O5/'סכום נכסים'!$B$30 -> 0.0014802904 | R5: 963.74163 | S5: ישראל | T5: ישראל | U5: מט"ח | V5: אחר | W5: מט"ח/₪ | X5: USDILS | Y5: לא | Z5: 46198 | AA5: 46230 | AB5: ללא | AC5: Delivery | AD5: לא | AE5: הצד הנגדי | AF5: ללא | AG5: ללא | AI5: 297.9 | AM5: MIZBILIT | AN5: 0.10299888 | AO5: =R5/'סכום נכסים'!$B$30 -> 0.00017351138
A6: 13908 | B6: 13908 | C6: Unfunded Forward | D6: 8493613 | E6: EUR | F6: 3.3768 | G6: -2370000 | H6: -1961.6322 | I6: 0.032954486 | J6: =H6/'סכום נכסים'!$B$30 -> -0.0003531709 | K6: 8493613 | L6: ILS | M6: 1 | N6: 8003016 | O6: 8003.016 | P6: 0.062837943 | Q6: =O6/'סכום נכסים'!$B$30 -> 0.0014408575 | R6: 1344.2556 | S6: ישראל | T6: ישראל | U6: מט"ח | V6: אחר | W6: מט"ח/₪ | X6: EURILS | Y6: לא | Z6: 46198 | AA6: 46230 | AB6: ללא | AC6: Delivery | AD6: לא | AE6: הצד הנגדי | AF6: ללא | AG6: ללא | AI6: 337.68 | AM6: MIZBILIT | AN6: 0.14366591 | AO6: =R6/'סכום נכסים'!$B$30 -> 0.00024201885
A7: 13908 | B7: 13908 | C7: Unfunded Forward | D7: 8504482 | E7: USD | F7: 2.979 | G7: -2750000 | H7: -2399.4614 | I7: 0.040309808 | J7: =H7/'סכום נכסים'!$B$30 -> -0.00043199737 | K7: 8504482 | L7: ILS | M7: 1 | N7: 8192250 | O7: 8192.25 | P7: 0.064323767 | Q7: =O7/'סכום נכסים'!$B$30 -> 0.001474927 | R7: 1046.654 | S7: ישראל | T7: ישראל | U7: מט"ח | V7: אחר | W7: מט"ח/₪ | X7: USDILS | Y7: לא | Z7: 46198 | AA7: 46238 | AB7: ללא | AC7: Delivery | AD7: לא | AE7: הצד הנגדי | AF7: ללא | AG7: ללא | AI7: 297.9 | AM7: MIZBILIT | AN7: 0.11186006 | AO7: =R7/'סכום נכסים'!$B$30 -> 0.00018843887
A8: 13908 | B8: 13908 | C8: Unfunded Forward | D8: 8504486 | E8: EUR | F8: 3.3768 | G8: -2400000 | H8: -2016.3406 | I8: 0.033873561 | J8: =H8/'סכום נכסים'!$B$30 -> -0.00036302056 | K8: 8504486 | L8: ILS | M8: 1 | N8: 8104320 | O8: 8104.32 | P8: 0.06363336 | Q8: =O8/'סכום נכסים'!$B$30 -> 0.0014590962 | R8: 1259.852 | S8: ישראל | T8: ישראל | U8: מט"ח | V8: אחר | W8: מט"ח/₪ | X8: EURILS | Y8: לא | Z8: 46198 | AA8: 46238 | AB8: ללא | AC8: Delivery | AD8: לא | AE8: הצד הנגדי | AF8: ללא | AG8: ללא | AI8: 337.68 | AM8: MIZBILIT | AN8: 0.13464536 | AO8: =R8/'סכום נכסים'!$B$30 -> 0.00022682288
A9: 13908 | B9: 13908 | C9: Unfunded Forward | D9: 450223 | E9: USD | F9: 2.979 | G9: -2900000 | H9: -2893.2299 | I9: 0.048604885 | J9: =H9/'סכום נכסים'!$B$30 -> -0.00052089512 | K9: 450223 | L9: ILS | M9: 1 | N9: 8639100 | O9: 8639.1 | P9: 0.067832336 | Q9: =O9/'סכום נכסים'!$B$30 -> 0.0015553776 | R9: 23.06129 | S9: ישראל | T9: ישראל | U9: מט"ח | V9: אחר | W9: מט"ח/₪ | X9: USDILS | Y9: לא | Z9: 46198 | AA9: 46288 | AB9: ללא | AC9: Delivery | AD9: לא | AE9: הצד הנגדי | AF9: ללא | AG9: ללא | AI9: 297.9 | AM9: FIRBILIT | AN9: 0.0024646513 | AO9: =R9/'סכום נכסים'!$B$30 -> 4.1519388e-06
A10: 13908 | B10: 13908 | C10: Unfunded Forward | D10: 450284 | E10: USD | F10: 2.979 | G10: -2800000 | H10: -2793.8636 | I10: 0.046935577 | J10: =H10/'סכום נכסים'!$B$30 -> -0.00050300527 | K10: 450284 | L10: ILS | M10: 1 | N10: 8341200 | O10: 8341.2 | P10: 0.06549329 | Q10: =O10/'סכום נכסים'!$B$30 -> 0.0015017439 | R10: 21.07428 | S10: ישראל | T10: ישראל | U10: מט"ח | V10: אחר | W10: מט"ח/₪ | X10: USDILS | Y10: לא | Z10: 46198 | AA10: 46351 | AB10: ללא | AC10: Delivery | AD10: לא | AE10: הצד הנגדי | AF10: ללא | AG10: ללא | AI10: 297.9 | AM10: FIRBILIT | AN10: 0.0022522916 | AO10: =R10/'סכום נכסים'!$B$30 -> 3.7941988e-06
A11: 13908 | B11: 13908 | C11: Unfunded Forward | D11: 450343 | E11: USD | F11: 2.979 | G11: -2800000 | H11: -2794.5589 | I11: 0.046947259 | J11: =H11/'סכום נכסים'!$B$30 -> -0.00050313047 | K11: 450343 | L11: ILS | M11: 1 | N11: 8341200 | O11: 8341.2 | P11: 0.06549329 | Q11: =O11/'סכום נכסים'!$B$30 -> 0.0015017439 | R11: 19.00346 | S11: ישראל | T11: ישראל | U11: מט"ח | V11: אחר | W11: מט"ח/₪ | X11: USDILS | Y11: לא | Z11: 46198 | AA11: 46561 | AB11: ללא | AC11: Delivery | AD11: לא | AE11: הצד הנגדי | AF11: ללא | AG11: ללא | AI11: 297.9 | AM11: FIRBILIT | AN11: 0.0020309749 | AO11: =R11/'סכום נכסים'!$B$30 -> 3.4213698e-06
A12: 13908 | B12: 13908 | C12: Funded Total Return/Equity Swap | D12: DJP#14P | E12: USD | F12: 2.907 | G12: -117806 | H12: -15432.586 | I12: 0.25926009 | J12: =H12/'סכום נכסים'!$B$30 -> -0.0027784721 | K12: DJP#14R | L12: USD | M12: 2.907 | N12: 117806 | O12: 15459.681 | P12: 0.12138606 | Q12: =O12/'סכום נכסים'!$B$30 -> 0.0027833504 | R12: 80.69004 | S12: ישראל | T12: ארה"ב | U12: מניות לרבות מדדי מניות | V12: מדדי מניות | W12: ריביות | X12: JPMMOREM IND | Y12: לא | Z12: 46152 | AA12: 46377 | AB12: רבעוני | AC12: No-delivery | AD12: לא | AE12: הצד הנגדי | AF12: SOFR | AG12: רבעוני | AI12: 9574 | AM12: CHASUS33 | AN12: 0.0086236637 | AO12: =R12/'סכום נכסים'!$B$30 -> 1.4527379e-05
A13: 13908 | B13: 13908 | C13: Funded Total Return/Equity Swap | D13: DJP#15P | E13: USD | F13: 2.907 | G13: -132119 | H13: -15920.075 | I13: 0.26744968 | J13: =H13/'סכום נכסים'!$B$30 -> -0.0028662394 | K13: DJP#15R | L13: USD | M13: 2.907 | N13: 132119 | O13: 15837.105 | P13: 0.1243495 | Q13: =O13/'סכום נכסים'!$B$30 -> 0.0028513014 | R13: -247.08684 | S13: ישראל | T13: ארה"ב | U13: מניות לרבות מדדי מניות | V13: מדדי מניות | W13: ריביות | X13: JPMOREM2 IND | Y13: לא | Z13: 46152 | AA13: 46422 | AB13: רבעוני | AC13: No-delivery | AD13: לא | AE13: הצד הנגדי | AF13: SOFR | AG13: רבעוני | AI13: 9574 | AM13: CHASUS33 | AN13: -0.026407148 | AO13: =R13/'סכום נכסים'!$B$30 -> -4.4485344e-05

Sheet הלוואות
A1: מספר קופה/קרן/ח.פ. עבור חברת ביטוח | B1: מספר מסלול | C1: מספר מזהה לווה | D1: סוג מספר מזהה לווה | E1: שם הלוואה | F1: מספר הלוואה | G1: מאפיין עיקרי | H1: מאפיין הלוואות מתואמות עבור זכויות מקרקעין | I1: ישראל/חו"ל | J1: מדינה לפי חשיפה כלכלית | K1: ענף מסחר | L1: בעל עניין/צד קשור | M1: קונסורציום/ סינדיקציה | N1: מספר קונסורציום/ סינדיקציה | O1: תאריך העמדת הלוואה | P1: דירוג | Q1: שם מדרג | R1: דירוג הלוואה/המנפיק | S1: מטבע פעילות | T1: מח"מ | U1: סוג הריבית | V1: שיעור ריבית | W1: סוג הצמדה | X1: ריבית עוגן | Y1: שיעור תוספת/הפחתה לריבית העוגן | Z1: תשואה לפדיון | AA1: מועד פדיון | AB1: נחיתות חוזית | AC1: סוג בטוחה | AD1: שווי הבטוחות העומדות כנגד ההלוואה | AE1: שיעור הבטוחות מהחוב | AF1: מועד עדכון אחרון לשווי הבטוחות | AG1: זכות חזרה | AH1: מבנה לוח סילוקין | AI1: יעוד הלוואה | AJ1: זכות פירעון מוקדם | AK1: סוג גורם משערך | AL1: שם גורם משערך | AM1: תלות/אי-תלות המשערך | AN1: תאריך שערוך אחרון | AO1: תאריך אחרון בו נבחנה בפועל ירידת ערך | AP1: שיעור ריבית בגין אי-ניצול מסגרת האשראי | AQ1: ערך נקוב | AR1: שער הלוואה | AS1: שער חליפין | AT1: שווי הוגן (באלפי ש"ח) | AU1: שווי הוגן (במטבע הפעילות) | AV1: עלות מופחתת (באלפי ש"ח) | AW1: עלות מופחתת (במטבע הפעילות) | AX1: האם סווג כחוב בעייתי | AY1: השיטה שיושמה בדוח הכספי | AZ1: שיעור מנכסי אפיק ההשקעה | BA1: שיעור מסך נכסי ההשקעה
A2: 13908 | B2: 13908 | E2: הלוואה 1 | F2: 11020447 | G2: תאגיד | H2: פעילות שוטפת של התאגיד - מגורים (כולל דיור מוגן) | I2: ישראל | K2: נדל"ן מניב בישראל | L2: לא | M2: לא | O2: 45657 | P2: NR | Q2: NR | R2: NR | S2: ILS | T2: 0.65 | U2: קבועה | V2: 0.11 | Z2: 0.0732 | AA2: 46445 | AB2: החוב נחות | AJ2: כן | AK2: חברת ציטוט | AM2: אי-תלות | AN2: 46203 | AO2: 46203 | AQ2: -0.03 | AR2: 102.39 | AS2: 1 | AT2: -3e-05 | AU2: -3e-05 | AY2: שווי הוגן | AZ2: -4.500277e-10 | BA2: =AT2/'סכום נכסים'!$B$30 -> -5.4011793e-12
A3: 13908 | B3: 13908 | E3: הלוואה 2 | F3: 11021112 | G3: תאגיד | I3: ישראל | K3: שרותים פיננסיים | L3: לא | M3: לא | O3: 45657 | P3: NR | Q3: NR | R3: NR | S3: ILS | T3: 1.51 | U3: משתנה | V3: 0.107 | Z3: 0.0989 | AA3: 47223 | AB3: החוב נחות | AJ3: כן | AK3: חברת ציטוט | AM3: אי-תלות | AN3: 46203 | AO3: 46203 | AQ3: 1302000 | AR3: 102.91 | AS3: 1 | AT3: 1339.8882 | AU3: 1339.8882 | AY3: שווי הוגן | AZ3: 0.02009956 | BA3: =AT3/'סכום נכסים'!$B$30 -> 0.00024123255
A4: 13908 | B4: 13908 | E4: הלוואה 3 | F4: 11021122 | G4: תאגיד | H4: ייזום נדל"ן לבניה של נכס ספציפי - מגורים (כולל דיור מוגן) | I4: ישראל | K4: בנייה | L4: לא | M4: לא | O4: 45657 | P4: NR | Q4: NR | R4: NR | S4: ILS | T4: 1.83 | U4: קבועה | V4: 0.1085 | Z4: 0.1027 | AA4: 46935 | AB4: החוב נחות | AF4: 45443 | AJ4: כן | AK4: חברת ציטוט | AM4: אי-תלות | AN4: 46203 | AO4: 46203 | AQ4: 1227272.7 | AR4: 101.76 | AS4: 1 | AT4: 1248.8727 | AU4: 1248.8727 | AY4: שווי הוגן | AZ4: 0.018734244 | BA4: =AT4/'סכום נכסים'!$B$30 -> 0.00022484619
A5: 13908 | B5: 13908 | E5: הלוואה 4 | F5: 11021130 | G5: תאגיד | H5: ייזום נדל"ן לבניה של נכס ספציפי - מגורים (כולל דיור מוגן) | I5: ישראל | K5: בנייה | L5: לא | M5: לא | O5: 45657 | P5: NR | Q5: NR | R5: NR | S5: ILS | T5: 1.04 | U5: קבועה | V5: 0.0925 | Z5: 0.0967 | AA5: 46599 | AB5: החוב נחות | AF5: 45493 | AJ5: כן | AK5: חברת ציטוט | AM5: אי-תלות | AN5: 46203 | AO5: 46203 | AQ5: 3078571 | AR5: 99.71 | AS5: 1 | AT5: 3069.6431 | AU5: 3069.6431 | AY5: שווי הוגן | AZ5: 0.046047481 | BA5: =AT5/'סכום נכסים'!$B$30 -> 0.00055265643
A6: 13908 | B6: 13908 | E6: הלוואה 5 | F6: 11021131 | G6: תאגיד | I6: ישראל | K6: שרותים פיננסיים | L6: לא | M6: לא | O6: 45657 | P6: NR | Q6: NR | R6: NR | S6: ILS | T6: 1.5 | U6: משתנה | V6: 0.107 | Z6: 0.045 | AA6: 47223 | AB6: החוב נחות | AJ6: כן | AK6: חברת ציטוט | AM6: אי-תלות | AN6: 46203 | AO6: 46203 | AQ6: 1302000 | AR6: 102.78 | AS6: 1 | AT6: 1338.1956 | AU6: 1338.1956 | AY6: שווי הוגן | AZ6: 0.020074169 | BA6: =AT6/'סכום נכסים'!$B$30 -> 0.00024092781
A7: 13908 | B7: 13908 | E7: הלוואה 6 | F7: 11021161 | G7: תאגיד | I7: ישראל | K7: שרותים פיננסיים | L7: לא | M7: לא | O7: 46111 | P7: NR | Q7: NR | R7: NR | S7: ILS | T7: 2.88 | U7: משתנה | V7: 0.101 | Z7: 0.096 | AA7: 47937 | AB7: החוב לא נחות | AJ7: כן | AK7: חברת ציטוט | AM7: אי-תלות | AN7: 46203 | AO7: 46203 | AQ7: 1700000 | AR7: 102.31 | AS7: 1 | AT7: 1739.27 | AU7: 1739.27 | AY7: שווי הוגן | AZ7: 0.026090656 | BA7: =AT7/'סכום נכסים'!$B$30 -> 0.00031313697
A8: 13908 | B8: 13908 | E8: הלוואה 7 | F8: 11022433 | G8: תאגיד | H8: פעילות שוטפת של התאגיד - מגורים (כולל דיור מוגן) | I8: ישראל | K8: נדל"ן מניב בישראל | L8: לא | M8: לא | O8: 45657 | P8: NR | Q8: NR | R8: NR | S8: ILS | T8: 0.65 | U8: קבועה | V8: 0.11 | Z8: 0.1503 | AA8: 46445 | AB8: החוב נחות | AJ8: כן | AK8: חברת ציטוט | AM8: אי-תלות | AN8: 46203 | AO8: 46203 | AQ8: -0.03 | AR8: 98.05 | AS8: 1 | AT8: -3e-05 | AU8: -3e-05 | AY8: שווי הוגן | AZ8: -4.500277e-10 | BA8: =AT8/'סכום נכסים'!$B$30 -> -5.4011793e-12
A9: 13908 | B9: 13908 | E9: הלוואה 8 | F9: 11022434 | G9: תאגיד | H9: פעילות שוטפת של התאגיד - מגורים (כולל דיור מוגן) | I9: ישראל | K9: בנייה | L9: לא | M9: לא | O9: 45657 | P9: NR | Q9: NR | R9: NR | S9: ILS | T9: 1.04 | U9: קבועה | V9: 0.0925 | Z9: 0.1251 | AA9: 46599 | AB9: החוב נחות | AF9: 45493 | AJ9: כן | AK9: חברת ציטוט | AM9: אי-תלות | AN9: 46203 | AO9: 46203 | AQ9: 1231429 | AR9: 97.38 | AS9: 1 | AT9: 1199.1656 | AU9: 1199.1656 | AY9: שווי הוגן | AZ9: 0.017988591 | BA9: =AT9/'סכום נכסים'!$B$30 -> 0.00021589694
A10: 13908 | B10: 13908 | E10: הלוואה 9 | F10: 11022435 | G10: תאגיד | H10: קרקעות - מגורים (כולל דיור מוגן) | I10: ישראל | K10: בנייה | L10: לא | M10: לא | O10: 45665 | P10: NR | Q10: NR | R10: NR | S10: ILS | T10: 2.92 | U10: קבועה | V10: 0.038 | Z10: 0.0755 | AA10: 47269 | AB10: החוב לא נחות | AJ10: לא | AK10: חברת ציטוט | AM10: אי-תלות | AN10: 46203 | AO10: 46203 | AQ10: 74343.09 | AR10: 100.7 | AS10: 1 | AT10: 74.86349 | AU10: 74.86349 | AY10: שווי הוגן | AZ10: 0.0011230215 | BA10: =AT10/'סכום נכסים'!$B$30 -> 1.3478371e-05
A11: 13908 | B11: 13908 | E11: הלוואה 10 | F11: 11022458 | G11: תאגיד | I11: ישראל | K11: נדל"ן מניב בישראל | L11: לא | M11: לא | O11: 45739 | P11: NR | Q11: NR | R11: NR | S11: ILS | T11: 1.61 | U11: קבועה | V11: 0.1 | Z11: 0.1358 | AA11: 46835 | AB11: החוב לא נחות | AJ11: כן | AK11: חברת ציטוט | AM11: אי-תלות | AN11: 46203 | AO11: 46203 | AQ11: 6250000 | AR11: 95.74 | AS11: 1 | AT11: 5983.75 | AU11: 5983.75 | AY11: שווי הוגן | AZ11: 0.089761774 | BA11: =AT11/'סכום נכסים'!$B$30 -> 0.0010773102
A12: 13908 | B12: 13908 | E12: הלוואה 11 | F12: 11022460 | G12: תאגיד | H12: קרקעות - מגורים (כולל דיור מוגן) | I12: ישראל | K12: בנייה | L12: לא | M12: לא | O12: 45741 | P12: NR | Q12: NR | R12: NR | S12: ILS | T12: 2.92 | U12: קבועה | V12: 0.09 | Z12: 0.1108 | AA12: 47269 | AB12: החוב לא נחות | AJ12: לא | AK12: חברת ציטוט | AM12: אי-תלות | AN12: 46203 | AO12: 46203 | AQ12: 530769.23 | AR12: 95.92 | AS12: 1 | AT12: 509.11385 | AU12: 509.11385 | AY12: שווי הוגן | AZ12: 0.0076371778 | BA12: =AT12/'סכום נכסים'!$B$30 -> 9.1660507e-05
A13: 13908 | B13: 13908 | E13: הלוואה 12 | F13: 11022466 | G13: תאגיד | I13: ישראל | K13: אנרגיה | L13: לא | M13: לא | O13: 45748 | P13: NR | Q13: NR | R13: NR | S13: ILS | T13: 2.92 | U13: משתנה | V13: 0.0575 | Z13: 0.021 | AA13: 47269 | AB13: החוב לא נחות | AJ13: כן | AK13: חברת ציטוט | AM13: אי-תלות | AN13: 46203 | AO13: 46203 | AQ13: 2957142.9 | AR13: 99.7 | AS13: 1 | AT13: 2948.2714 | AU13: 2948.2714 | AY13: שווי הוגן | AZ13: 0.044226793 | BA13: =AT13/'סכום נכסים'!$B$30 -> 0.00053080475
A14: 13908 | B14: 13908 | E14: הלוואה 13 | F14: 11022468 | G14: תאגיד | I14: ישראל | K14: שרותים פיננסיים | L14: לא | M14: לא | O14: 45755 | P14: NR | Q14: NR | R14: NR | S14: ILS | T14: 2.1 | U14: משתנה | V14: 0.101 | Z14: 0.1262 | AA14: 47580 | AB14: החוב נחות | AJ14: כן | AK14: חברת ציטוט | AM14: אי-תלות | AN14: 46203 | AO14: 46203 | AQ14: 1302000 | AR14: 97.65 | AS14: 1 | AT14: 1271.403 | AU14: 1271.403 | AY14: שווי הוגן | AZ14: 0.019072219 | BA14: =AT14/'סכום נכסים'!$B$30 -> 0.00022890252
A15: 13908 | B15: 13908 | E15: הלוואה 14 | F15: 11022473 | G15: תאגיד | H15: קרקעות - מגורים (כולל דיור מוגן) | I15: ישראל | K15: בנייה | L15: לא | M15: לא | O15: 45781 | P15: NR | Q15: NR | R15: NR | S15: ILS | T15: 3.17 | U15: קבועה | V15: 0.09 | Z15: 0.0389 | AA15: 47269 | AB15: החוב לא נחות | AJ15: לא | AK15: חברת ציטוט | AM15: אי-תלות | AN15: 46203 | AO15: 46203 | AQ15: 815665.03 | AR15: 99.97 | AS15: 1 | AT15: 815.42033 | AU15: 815.42033 | AY15: שווי הוגן | AZ15: 0.012232058 | BA15: =AT15/'סכום נכסים'!$B$30 -> 0.00014680771
A16: 13908 | B16: 13908 | E16: הלוואה 15 | F16: 11022481 | G16: תאגיד | H16: ייזום נדל"ן לבניה של נכס ספציפי - מגורים (כולל דיור מוגן) | I16: ישראל | K16: בנייה | L16: לא | M16: לא | O16: 45803 | P16: NR | Q16: NR | R16: NR | S16: ILS | T16: 1.82 | U16: קבועה | V16: 0.1085 | Z16: 0.0997 | AA16: 46936 | AB16: החוב נחות | AF16: 45443 | AJ16: כן | AK16: חברת ציטוט | AM16: אי-תלות | AN16: 46203 | AO16: 46203 | AQ16: 1227272.7 | AR16: 94.62 | AS16: 1 | AT16: 1161.2455 | AU16: 1161.2455 | AY16: שווי הוגן | AZ16: 0.017419754 | BA16: =AT16/'סכום נכסים'!$B$30 -> 0.00020906983
A17: 13908 | B17: 13908 | E17: הלוואה 16 | F17: 11022535 | G17: תאגיד | I17: ישראל | K17: שרותים פיננסיים | L17: לא | M17: לא | O17: 45959 | P17: NR | Q17: NR | R17: NR | S17: ILS | T17: 3.64 | U17: משתנה | V17: 0.09 | Z17: 0.1067 | AA17: 47788 | AB17: החוב נחות | AJ17: כן | AK17: חברת ציטוט | AM17: אי-תלות | AN17: 46203 | AO17: 46203 | AQ17: 3400000 | AR17: 99.97 | AS17: 1 | AT17: 3398.98 | AU17: 3398.98 | AY17: שווי הוגן | AZ17: 0.050987838 | BA17: =AT17/'סכום נכסים'!$B$30 -> 0.00061195002
A18: 13908 | B18: 13908 | E18: הלוואה 17 | F18: 11022536 | G18: תאגיד | H18: פעילות שוטפת של התאגיד - מגורים (כולל דיור מוגן) | I18: ישראל | K18: בנייה | L18: לא | M18: לא | O18: 45960 | P18: NR | Q18: NR | R18: NR | S18: ILS | T18: 2.09 | U18: קבועה | V18: 0.094 | Z18: 0.1175 | AA18: 47056 | AB18: החוב לא נחות | AJ18: כן | AK18: חברת ציטוט | AM18: אי-תלות | AN18: 46203 | AO18: 46203 | AQ18: 4000000 | AR18: 96.9 | AS18: 1 | AT18: 3876 | AU18: 3876 | AY18: שווי הוגן | AZ18: 0.058143578 | BA18: =AT18/'סכום נכסים'!$B$30 -> 0.00069783237
A19: 13908 | B19: 13908 | E19: הלוואה 18 | F19: 11022540 | G19: תאגיד | I19: ישראל | K19: שרותים פיננסיים | L19: לא | M19: לא | O19: 45971 | P19: NR | Q19: NR | R19: NR | S19: ILS | T19: 2.1 | U19: משתנה | V19: 0.107 | Z19: 0.1219 | AA19: 47580 | AB19: החוב נחות | AJ19: כן | AK19: חברת ציטוט | AM19: אי-תלות | AN19: 46203 | AO19: 46203 | AQ19: 1302000 | AR19: 98.42 | AS19: 1 | AT19: 1281.4284 | AU19: 1281.4284 | AY19: שווי הוגן | AZ19: 0.019222609 | BA19: =AT19/'סכום נכסים'!$B$30 -> 0.00023070749
A20: 13908 | B20: 13908 | E20: הלוואה 19 | F20: 11022552 | G20: תאגיד | I20: ישראל | K20: בנייה | L20: לא | M20: לא | O20: 46021 | P20: NR | Q20: NR | R20: NR | S20: ILS | T20: 7.5 | U20: קבועה | V20: 0.12 | Z20: 0.1249 | AA20: 48939 | AB20: החוב לא נחות | AJ20: לא | AK20: חברת ציטוט | AM20: אי-תלות | AN20: 46203 | AO20: 46203 | AQ20: 769230.77 | AR20: 105.38 | AS20: 1 | AT20: 810.61539 | AU20: 810.61539 | AY20: שווי הוגן | AZ20: 0.012159979 | BA20: =AT20/'סכום נכסים'!$B$30 -> 0.00014594264
A21: 13908 | B21: 13908 | E21: הלוואה 20 | F21: 11022553 | G21: תאגיד | H21: קרקעות - מגורים (כולל דיור מוגן) | I21: ישראל | K21: בנייה | L21: לא | M21: לא | O21: 46044 | P21: NR | Q21: NR | R21: NR | S21: ILS | T21: 4.57 | U21: קבועה | V21: 0.038 | Z21: 0.0426 | AA21: 47870 | AB21: החוב לא נחות | AJ21: כן | AK21: חברת ציטוט | AM21: אי-תלות | AN21: 46203 | AO21: 46203 | AQ21: 3184615.4 | AR21: 99.3 | AS21: 1 | AT21: 3162.3231 | AU21: 3162.3231 | AY21: שווי הוגן | AZ21: 0.047437766 | BA21: =AT21/'סכום נכסים'!$B$30 -> 0.00056934247
A22: 13908 | B22: 13908 | E22: הלוואה 21 | F22: 11022556 | G22: תאגיד | I22: ישראל | K22: שרותים | L22: לא | M22: לא | O22: 46051 | P22: NR | Q22: NR | R22: NR | S22: ILS | T22: 4.59 | U22: קבועה | V22: 0.085 | Z22: 0.0848 | AA22: 47876 | AB22: החוב לא נחות | AF22: 46049 | AJ22: כן | AK22: חברת ציטוט | AM22: אי-תלות | AN22: 46203 | AO22: 46203 | AQ22: 219496.05 | AR22: 102.86 | AS22: 1 | AT22: 225.77364 | AU22: 225.77364 | AY22: שווי הוגן | AZ22: 0.003386813 | BA22: =AT22/'סכום נכסים'!$B$30 -> 4.0648131e-05
A23: 13908 | B23: 13908 | E23: הלוואה 22 | F23: 11022808 | G23: תאגיד | I23: ישראל | K23: שרותים פיננסיים | L23: לא | M23: לא | O23: 45750 | P23: NR | Q23: NR | R23: NR | S23: USD | T23: 1.95 | U23: משתנה | V23: 0.0525 | Z23: 0.0424 | AA23: 47715 | AB23: החוב לא נחות | AJ23: כן | AK23: חברת ציטוט | AM23: אי-תלות | AN23: 46203 | AO23: 46203 | AQ23: 1860388.6 | AR23: 98.85 | AS23: 2.978 | AT23: 5476.5245 | AU23: 1838.9941 | AY23: שווי הוגן | AZ23: 0.082152923 | BA23: =AT23/'סכום נכסים'!$B$30 -> 0.00098598969
A24: 13908 | B24: 13908 | E24: הלוואה 23 | F24: 11150015 | G24: תאגיד | I24: ישראל | K24: שרותים פיננסיים | L24: לא | M24: לא | O24: 46142 | P24: NR | Q24: NR | R24: NR | S24: ILS | T24: 3.82 | U24: משתנה | V24: 0.101 | Z24: 0.1056 | AA24: 47937 | AB24: החוב לא נחות | AF24: 46098 | AJ24: כן | AK24: חברת ציטוט | AM24: אי-תלות | AN24: 46203 | AO24: 46203 | AQ24: 1700000 | AR24: 101.99 | AS24: 1 | AT24: 1733.83 | AU24: 1733.83 | AY24: שווי הוגן | AZ24: 0.026009051 | BA24: =AT24/'סכום נכסים'!$B$30 -> 0.00031215756
A25: 13908 | B25: 13908 | E25: הלוואה 24 | F25: 11150017 | G25: תאגיד | I25: ישראל | K25: שרותים פיננסיים | L25: לא | M25: לא | O25: 46155 | P25: NR | Q25: NR | R25: NR | S25: EUR | T25: 4.4 | U25: קבועה | V25: 0.0575 | Z25: 0.0518 | AA25: 47981 | AB25: החוב לא נחות | AF25: 46155 | AJ25: כן | AK25: חברת ציטוט | AM25: אי-תלות | AN25: 46203 | AO25: 46203 | AQ25: 193800 | AR25: 101.5 | AS25: 3.3945 | AT25: 667.72191 | AU25: 196.707 | AY25: שווי הוגן | AZ25: 0.010016445 | BA25: =AT25/'סכום נכסים'!$B$30 -> 0.00012021619
A26: 13908 | B26: 13908 | E26: הלוואה 25 | F26: 11150029 | G26: תאגיד | I26: ישראל | K26: שרותים פיננסיים | L26: לא | M26: לא | O26: 46198 | P26: NR | Q26: NR | R26: NR | S26: ILS | T26: 3.82 | U26: משתנה | V26: 0.101 | Z26: 0.1056 | AA26: 47937 | AB26: החוב לא נחות | AF26: 46098 | AJ26: כן | AK26: חברת ציטוט | AM26: אי-תלות | AN26: 46203 | AO26: 46203 | AQ26: 1600000 | AR26: 99.75 | AS26: 1 | AT26: 1596 | AU26: 1596 | AY26: שווי הוגן | AZ26: 0.023941473 | BA26: =AT26/'סכום נכסים'!$B$30 -> 0.00028734274
A27: 13908 | B27: 13908 | E27: הלוואה 26 | F27: 11021291 | G27: תאגיד | H27: אשראי אחר בענף הנדל"ן (לרבות אשראי לכל מטרה) - אחר/לא מסווג | I27: חו"ל | K27: Consumer Finance | L27: לא | M27: לא | O27: 45657 | P27: A1.il | Q27: מידרוג Moodys | R27: מנפיק | S27: USD | T27: 1.43 | U27: משתנה | V27: 0.0496 | Z27: 0.0794 | AA27: 46660 | AB27: החוב נחות | AJ27: כן | AK27: חברת ציטוט | AM27: אי-תלות | AN27: 46203 | AO27: 46203 | AQ27: 1620000 | AR27: 99.93 | AS27: 2.978 | AT27: 4820.9829 | AU27: 1618.866 | AY27: שווי הוגן | AZ27: 0.072319195 | BA27: =AT27/'סכום נכסים'!$B$30 -> 0.00086796645
A28: 13908 | B28: 13908 | E28: הלוואה 27 | F28: 11022815 | G28: תאגיד | I28: חו"ל | K28: Energy Equipment & Services | L28: לא | M28: כן | O28: 45775 | P28: ilA- | Q28: S&P מעלות | R28: מנפיק | S28: USD | T28: 2.49 | U28: משתנה | V28: 0.09686 | Z28: 0.0923 | AA28: 46990 | AB28: החוב לא נחות | AF28: 45108 | AJ28: כן | AK28: חברת ציטוט | AM28: אי-תלות | AN28: 46203 | AO28: 46203 | AQ28: 221805.23 | AR28: 97.12 | AS28: 2.978 | AT28: 641.51254 | AU28: 215.41724 | AY28: שווי הוגן | AZ28: 0.0096232804 | BA28: =AT28/'סכום נכסים'!$B$30 -> 0.00011549748
A29: 13908 | B29: 13908 | E29: הלוואה 28 | F29: 11022822 | G29: תאגיד | I29: חו"ל | K29: Energy Equipment & Services | L29: לא | M29: כן | O29: 45804 | P29: ilA- | Q29: S&P מעלות | R29: מנפיק | S29: USD | T29: 0 | U29: משתנה | V29: 0.09686 | Z29: 0.0778 | AA29: 46990 | AB29: החוב לא נחות | AJ29: כן | AK29: חברת ציטוט | AM29: אי-תלות | AN29: 46203 | AO29: 46203 | AQ29: -0.09 | AR29: 100 | AS29: 2.978 | AT29: -0.00027 | AU29: -9.0664876e-05 | AY29: שווי הוגן | AZ29: -4.0502493e-09 | BA29: =AT29/'סכום נכסים'!$B$30 -> -4.8610614e-11
A30: 13908 | B30: 13908 | E30: הלוואה 29 | F30: 11022869 | G30: תאגיד | I30: חו"ל | K30: Energy Equipment & Services | L30: לא | M30: כן | O30: 46042 | P30: ilBBB | Q30: S&P מעלות | R30: הלוואה | S30: USD | T30: 2.66 | U30: משתנה | V30: 0.0791 | Z30: 0.0895 | AA30: 48599 | AB30: החוב לא נחות | AF30: 46041 | AJ30: כן | AK30: חברת ציטוט | AM30: אי-תלות | AN30: 46203 | AO30: 46203 | AQ30: 4522222.2 | AR30: 98.29 | AS30: 2.978 | AT30: 13236.889 | AU30: 4444.8922 | AY30: שווי הוגן | AZ30: 0.19856556 | BA30: =AT30/'סכום נכסים'!$B$30 -> 0.0023831604
A31: 13908 | B31: 13908 | E31: הלוואה 30 | F31: 11150010 | G31: תאגיד | I31: חו"ל | K31: Financial Services | L31: לא | M31: לא | O31: 46126 | P31: NR | Q31: NR | R31: NR | S31: USD | T31: 3.77 | U31: קבועה | V31: 0.1 | Z31: 0.105 | AA31: 47952 | AB31: החוב נחות | AJ31: כן | AK31: חברת ציטוט | AM31: אי-תלות | AN31: 46203 | AO31: 46203 | AQ31: 1000000 | AR31: 101.91 | AS31: 2.978 | AT31: 3034.8798 | AU31: 1019.1 | AY31: שווי הוגן | AZ31: 0.045525999 | BA31: =AT31/'סכום נכסים'!$B$30 -> 0.00054639767

Sheet לא סחיר מוצרים מובנים
A1: מספר קופה/קרן/ח.פ. עבור חברת ביטוח | B1: מספר מסלול | C1: שם מנפיק | D1: מספר מנפיק | E1: סוג מספר מזהה מנפיק | F1: שם נייר ערך | G1: מספר נייר ערך | H1: סוג מספר נייר ערך | I1: מאפיין עיקרי | J1: ישראל/חו"ל | K1: מדינה לפי חשיפה כלכלית | L1: בעל עניין/צד קשור | M1: נכס בסיס | N1: תאריך רכישה | O1: דירוג | P1: שם מדרג | Q1: דירוג נייר הערך/המנפיק | R1: מטבע פעילות | S1: מח"מ | T1: שיעור ריבית | U1: תשואה לפדיון | V1: סוג גורם משערך | W1: תלות/אי-תלות המשערך | X1: תאריך שערוך אחרון | Y1: ערך נקוב (יחידות) | Z1: שער חליפין | AA1: שער נייר הערך | AB1: שווי הוגן (באלפי ש"ח) | AC1: שיעור מנכסי אפיק ההשקעה | AD1: שיעור מסך נכסי ההשקעה
A2: 13908 | B2: 13908 | C2: JPM 7.95 01/34 | D2: 8I5DZWZKVSZI1NUHU748 | E2: LEI | F2: JPM 7.95 01/34 | G2: 62012463 | H2: פנימי | I2: שכבת הון (Equity Tranch) | J2: חו"ל | K2: ארה"ב | L2: לא | M2: אחר | N2: 45657 | O2: A | P2: S&P | Q2: נייר ערך | R2: USD | S2: 9.94 | T2: 0.0795 | U2: 0.07176 | V2: דיווח מנהל הקרן | W2: אי-תלות | X2: 46203 | Y2: 1103000 | Z2: 2.978 | AA2: 113.2137 | AB2: 3718.7689 | AC2: 1 | AD2: =AB2/'סכום נכסים'!$B$30 -> 0.00066952459

Sheet פיקדונות מעל 3 חודשים
A1: מספר קופה/קרן/ח.פ. עבור חברת ביטוח | B1: מספר מסלול | C1: שם הבנק | D1: מספר מזהה בנק | E1: סוג מספר מזהה בנק | F1: מאפיין עיקרי | G1: תאריך פקיעת פיקדון | H1: ישראל/חו"ל | I1: מדינה לפי חשיפה כלכלית | J1: בעל עניין/צד קשור | K1: דירוג הבנק | L1: שם מדרג | M1: מטבע פעילות | N1: מח"מ | O1: שיעור ריבית | P1: תשואה לפדיון | Q1: שווי מטבעי | R1: שער חליפין | S1: שער פיקדון | T1: שווי הוגן (באלפי ש"ח) | U1: שיעור מנכסי אפיק ההשקעה | V1: שיעור מסך נכסי ההשקעה
A2: 13908 | B2: 13908 | C2: בנק הבינלאומי הראשון לישראל בע"מ | D2: 31 | E2: סימול בנק | F2: לא צמוד למדד המחירים לצרכן | G2: 46321 | H2: ישראל | I2: ישראל | J2: לא | K2: ilAAA | L2: S&P מעלות | M2: ILS | N2: 0.323 | P2: 0.0358 | Q2: 431850 | R2: 1 | S2: 100 | T2: 43197.955 | U2: 0.20120151 | V2: =T2/'סכום נכסים'!$B$30 -> 0.0077773301
A3: 13908 | B3: 13908 | C3: בנק הבינלאומי הראשון לישראל בע"מ | D3: 31 | E3: סימול בנק | F3: לא צמוד למדד המחירים לצרכן | G3: 46277 | H3: ישראל | I3: ישראל | J3: לא | K3: ilAAA | L3: S&P מעלות | M3: ILS | N3: 0.203 | P3: 0.035 | Q3: 1000000 | R3: 1 | S3: 100 | T3: 100620 | U3: 0.46865403 | V3: =T3/'סכום נכסים'!$B$30 -> 0.018115555
A4: 13908 | B4: 13908 | C4: בנק הבינלאומי הראשון לישראל בע"מ | D4: 31 | E4: סימול בנק | F4: לא צמוד למדד המחירים לצרכן | G4: 46212 | H4: ישראל | I4: ישראל | J4: לא | K4: ilAAA | L4: S&P מעלות | M4: ILS | N4: 0.025 | P4: 0.0395 | Q4: 700000 | R4: 1 | S4: 100 | T4: 70882 | U4: 0.33014446 | V4: =T4/'סכום נכסים'!$B$30 -> 0.012761546

Sheet זכויות מקרקעין
A1: מספר קופה/קרן/ח.פ. עבור חברת ביטוח | B1: מספר מסלול | C1: שם הנכס | D1: מאפיין עיקרי | E1: מדינת מיקום נדל"ן | F1: בעל עניין/צד קשור | G1: תאריך רכישה | H1: שימוש עיקרי בנכס | I1: מחזור חיי הנכס | J1: כתובת הנכס | K1: שיעור תשואה בפועל במהלך הרבעון | L1: השיטה שבאמצעותה נקבע שווי הנכס | M1: סוג גורם משערך | N1: שם גורם משערך | O1: תלות/אי-תלות המשערך | P1: תאריך שערוך אחרון | Q1: מטבע פעילות | R1: שווי הוגן (במטבע הפעילות) | S1: שווי הוגן (באלפי ש"ח) | T1: עלות מופחתת (באלפי ש"ח) | U1: עלות מופחתת (במטבע הפעילות) | V1: השיטה שיושמה בדוח הכספי | W1: שיעור מנכסי אפיק ההשקעה | X1: שיעור מסך נכסי ההשקעה
A2: 13908 | B2: 13908 | C2: כנפי רוח בניית ירושלים 2 | D2: נדל"ן לא מניב | E2: ישראל | F2: לא | G2: 45196 | H2: קרקע/זכויות מקרקעין | I2: בתכנון/בהיתרים | J2: פינת הרחובות כנפי נשרים, פרבשטיין , בית הדפוס א.ת. גבעת שאול, ירושלים | K2: 0.055555 | M2: מומחה בלתי תלוי | O2: אי-תלות | P2: 45914 | Q2: ILS | R2: 10084.617 | S2: 10084.617 | V2: שווי הוגן | W2: 0.4300653 | X2: =S2/'סכום נכסים'!$B$30 -> 0.0018156275
A3: 13908 | B3: 13908 | C3: לוזון רונסון | D3: נדל"ן לא מניב | E3: ישראל | F3: לא | G3: 45741 | H3: מגורים (כולל דיור מוגן) | I3: בתכנון/בהיתרים | J3: רחוב כרמל 20, גני תקווה | K3: 0 | M3: מומחה בלתי תלוי | O3: אי-תלות | P3: 45729 | Q3: ILS | R3: 8952.4001 | S3: 8952.4001 | V3: שווי הוגן | W3: 0.38178114 | X3: =S3/'סכום נכסים'!$B$30 -> 0.0016117839
A4: 13908 | B4: 13908 | C4: כנפי רוח 2 | D4: נדל"ן לא מניב | E4: ישראל | F4: לא | G4: 45782 | H4: קרקע/זכויות מקרקעין | I4: בתכנון/בהיתרים | J4: פינת הרחובות כנפי נשרים, פרבשטיין , בית הדפוס א.ת. גבעת שאול, ירושלים | K4: -0.004193 | M4: מומחה בלתי תלוי | O4: אי-תלות | P4: 45914 | Q4: ILS | R4: 4412.0197 | S4: 4412.0197 | V4: שווי הוגן | W4: 0.18815356 | X4: =S4/'סכום נכסים'!$B$30 -> 0.00079433698

Sheet השקעה בחברות מוחזקות
A1: מספר קופה/קרן/ח.פ. עבור חברת ביטוח | B1: מספר מסלול | C1: שם מנפיק | D1: מספר מנפיק | E1: סוג מספר מזהה מנפיק | F1: שם נייר ערך | G1: מספר נייר ערך | H1: סוג מספר נייר ערך | I1: מאפיין עיקרי | J1: ישראל/חו"ל | K1: מדינה לפי חשיפה כלכלית | L1: ענף מסחר | M1: בעל עניין/צד קשור | N1: מטבע פעילות | O1: סוג גורם משערך | P1: תלות/אי-תלות המשערך | Q1: תאריך שערוך אחרון | R1: תאריך אחרון בו נבחנה בפועל ירידת ערך | S1: שיעור אחזקה באמצעי שליטה | T1: שווי מאזני (באלפי ש"ח) | U1: שווי הוגן (באלפי ש"ח) | V1: שיעור מנכסי אפיק ההשקעה | W1: שיעור מסך נכסי ההשקעה

Sheet נכסים אחרים
A1: מספר קופה/קרן/ח.פ. עבור חברת ביטוח | B1: מספר מסלול | C1: שם הנכס האחר | D1: מספר הנכס האחר | E1: מאפיין עיקרי | F1: ישראל/חו"ל | G1: מדינה לפי חשיפה כלכלית | H1: בעל עניין/צד קשור | I1: תאריך עסקה | J1: מטבע פעילות | K1: תאריך שערוך אחרון | L1: שווי מטבעי | M1: שער חליפין | N1: שווי הוגן (באלפי ש"ח) | O1: עלות מופחתת (באלפי ש"ח) | P1: השיטה שיושמה בדוח הכספי | Q1: שיעור מנכסי אפיק ההשקעה | R1: שיעור מסך נכסי ההשקעה
A2: 13908 | B2: 13908 | C2: חוז עמלות | D2: 9042 | E2: חייבים בגין תקבולים | F2: ישראל | G2: ישראל | H2: לא | I2: 46203 | J2: ILS | K2: 46203 | L2: 534.82812 | M2: 1 | N2: 534.82812 | P2: שווי הוגן | Q2: 0.069471437 | R2: =N2/'סכום נכסים'!$B$30 -> 9.6290086e-05
A3: 13908 | B3: 13908 | C3: חוז שונות | D3: 9082 | E3: חייבים וזכאים | F3: ישראל | G3: ישראל | H3: לא | I3: 46203 | J3: ILS | K3: 46203 | L3: -1.74448 | M3: 1 | N3: -1.74448 | P3: שווי הוגן | Q3: -0.00022659903 | R3: =N3/'סכום נכסים'!$B$30 -> -3.1407498e-07
A4: 13908 | B4: 13908 | C4: ריבית עוש לקבל | D4: 9088 | E4: הכנסות עו"ש לקבל | F4: ישראל | G4: ישראל | H4: לא | I4: 46203 | J4: ILS | K4: 46203 | L4: 2846.0183 | M4: 1 | N4: 2846.0183 | P4: שווי הוגן | Q4: 0.36968323 | R4: =N4/'סכום נכסים'!$B$30 -> 0.00051239518
A5: 13908 | B5: 13908 | C5: TEMP_MATACH $ | D5: 11018712 | E5: חייבים בגין תקבולים | F5: ישראל | G5: ישראל | H5: לא | I5: 46203 | J5: USD | K5: 46203 | L5: 1090 | M5: 2.978 | N5: 3246.02 | P5: שווי הוגן | Q5: 0.4216414 | R5: =N5/'סכום נכסים'!$B$30 -> 0.0005844112
A6: 13908 | B6: 13908 | C6: TEMP_INTEREST$ | D6: 11020527 | E6: הכנסות עו"ש לקבל | F6: ישראל | G6: ישראל | H6: לא | I6: 46203 | J6: USD | K6: 46203 | L6: 360.4468 | M6: 2.978 | N6: 1073.4106 | P6: שווי הוגן | Q6: 0.13943054 | R6: =N6/'סכום נכסים'!$B$30 -> 0.0001932561
A7: 13908 | B7: 13908 | C7: SIXGILL נאמנות | D7: 11022806 | E7: חייבים בנאמנות | F7: ישראל | G7: ישראל | H7: לא | I7: 46203 | J7: USD | K7: 46203 | L7: -1e-05 | M7: 2.978 | N7: -3e-05 | P7: שווי הוגן | Q7: -3.8968466e-09 | R7: =N7/'סכום נכסים'!$B$30 -> -5.4011793e-12

Sheet מסגרות אשראי
A1: מספר קופה/קרן/ח.פ. עבור חברת ביטוח | B1: מספר מסלול | C1: מספר מזהה לווה | D1: סוג מספר מזהה לווה | E1: שם הלוואה | F1: מספר הלוואה | G1: תאריך העמדת מסגרת אשראי | H1: ישראל/חו"ל | I1: מדינה לפי חשיפה כלכלית | J1: בעל עניין/צד קשור | K1: דירוג | L1: שם מדרג | M1: דירוג הלוואה/המנפיק | N1: מטבע פעילות | O1: שער חליפין | P1: שיעור ריבית | Q1: סוג הריבית | R1: סכום מסגרת האשראי הראשוני (במטבע הפעילות) | S1: סכום מסגרת האשראי הראשוני (באלפי ש"ח) | T1: שיעור יתרת מסגרת אשראי
A2: 13908 | B2: 13908 | F2: 11022808 | G2: 45750 | H2: חו"ל | J2: לא | K2: NR | L2: NR | M2: NR | N2: USD | O2: 2.978 | P2: 0.0525 | Q2: משתנה | R2: 2100 | S2: 6253.8 | T2: 0.11
A3: 13908 | B3: 13908 | F3: 11022466 | G3: 45748 | H3: ישראל | J3: לא | K3: NR | L3: NR | M3: NR | N3: ILS | O3: 1 | P3: 0.005 | Q3: משתנה | R3: 10350 | S3: 10350 | T3: 0.71428571
A4: 13908 | B4: 13908 | F4: 11022460 | G4: 45741 | H4: ישראל | J4: לא | K4: NR | L4: NR | M4: NR | N4: ILS | O4: 1 | P4: 0.09 | Q4: קבועה | R4: 1380.1592 | S4: 1380.1592 | T4: 0.024435565
A5: 13908 | B5: 13908 | F5: 11022458 | G5: 45739 | H5: ישראל | J5: לא | K5: NR | L5: NR | M5: NR | N5: ILS | O5: 1 | P5: 0.1 | Q5: קבועה | R5: 7500 | S5: 7500 | T5: 0.1667
A6: 13908 | B6: 13908 | F6: 11022535 | G6: 45962 | H6: ישראל | J6: לא | K6: NR | L6: NR | M6: NR | N6: ILS | O6: 1 | P6: 0.057 | Q6: משתנה | R6: 8500 | S6: 8500 | T6: 0.6
A7: 13908 | B7: 13908 | F7: 11022865 | G7: 46007 | H7: חו"ל | J7: לא | K7: NR | L7: NR | M7: NR | N7: USD | O7: 2.978 | P7: 0.0525 | Q7: משתנה | R7: 4875 | S7: 14517.75 | T7: 1
A8: 13908 | B8: 13908 | F8: 11022866 | G8: 46007 | H8: חו"ל | J8: לא | K8: NR | L8: NR | M8: NR | N8: USD | O8: 2.978 | P8: 0.0525 | Q8: משתנה | R8: 2625 | S8: 7817.25 | T8: 1
A9: 13908 | B9: 13908 | F9: 11021161 | G9: 46111 | H9: ישראל | J9: לא | K9: NR | L9: NR | M9: NR | N9: ILS | O9: 1 | P9: 0.101 | Q9: משתנה | R9: 5000 | S9: 5000 | T9: 0.005
A10: 13908 | B10: 13908 | F10: 11150017 | G10: 46155 | H10: ישראל | J10: לא | K10: NR | L10: NR | M10: NR | N10: EUR | O10: 3.3945 | P10: 0.0575 | Q10: משתנה | R10: 1068.0628 | S10: 3625.5393 | T10: 0.27

Sheet יתרות התחייבות להשקעה
A1: מספר קופה/קרן/ח.פ. עבור חברת ביטוח | B1: מספר מסלול | C1: מאפיין עיקרי | D1: שם שותף כללי קרן השקעות | E1: מספר מזהה שותף כללי קרן השקעות | F1: סוג מספר מזהה שותף כללי קרן השקעות | G1: שם קרן השקעה | H1: מספר מזהה קרן השקעה | I1: סוג מספר מזהה קרן השקעות | J1: מטבע פעילות | K1: תאריך העמדת התחייבות לקרן השקעה | L1: סכום המחויבות הראשוני (במטבע הדיווח של קרן ההשקעה) | M1: סכום המחויבות הראשוני (באלפי ש"ח) | N1: יתרת המחויבות לתקופת הדיווח (במטבע הדיווח של קרן ההשקעה) | O1: יתרת המחויבות לתקופת הדיווח (באלפי ש"ח) | P1: שיעור יתרת המחויבות | Q1: תאריך פקיעת מחויבות להשקעה
A2: 13908 | B2: 13908 | C2: התחייבות להשקעה | D2: HGI Multifamily Credit Fund GP LLC | G2: HGI Multifamily Credit Fund LP HGI Multifamily Cr | H2: 11019991 | I2: פנימי | J2: USD | K2: 44935 | L2: 318.5 | M2: 948.493 | N2: 31.5 | O2: 93.807 | P2: 0.098901099 | Q2: 48029
A3: 13908 | B3: 13908 | C3: התחייבות להשקעה | D3: HarbourVest GP LLC | G3: Dover Street XI L.P Dover Street XI L.P | H3: 11019995 | I3: פנימי | J3: USD | K3: 44971 | L3: 200 | M3: 595.6 | N3: 77 | O3: 229.306 | P3: 0.385 | Q3: 46607
A4: 13908 | B4: 13908 | C4: התחייבות להשקעה | D4: Oak Street Real Estate Capital Fund VI, LP | G4: Oak Street Real Estate Capital Fund VI, LP | H4: 11020012 | I4: פנימי | J4: USD | K4: 45032 | L4: 390.06799 | M4: 1161.6225 | N4: 274.35722 | O4: 817.03579 | P4: 0.70335742 | Q4: 47526
A5: 13908 | B5: 13908 | C5: התחייבות להשקעה | D5: PANTHEON PGIF IV GP | G5: Pantheon Global Infrastructure Fund IV -Luxembourg | H5: 11020456 | I5: פנימי | J5: USD | K5: 45089 | L5: 695.48782 | M5: 2071.1627 | N5: 178.21218 | O5: 530.71588 | P5: 0.25624055 | Q5: 46310
A6: 13908 | B6: 13908 | C6: התחייבות להשקעה | D6: Scintilla Tech Ltd | G6: MORETECH VENTURES II, L.P | H6: 11020463 | I6: פנימי | J6: USD | K6: 45124 | L6: 120.52487 | M6: 358.92306 | N6: 116.54578 | O6: 347.07333 | P6: 0.96698532 | Q6: 48021
A7: 13908 | B7: 13908 | C7: התחייבות להשקעה | D7: HPS GP Lux Sarl | G7: HPS Specialty Loan International Fund VI-L, SCSp | H7: 11020470 | I7: פנימי | J7: USD | K7: 45135 | L7: 550 | M7: 1637.9 | N7: 314.24207 | O7: 935.81287 | P7: 0.57134921 | Q7: 46660
A8: 13908 | B8: 13908 | C8: התחייבות להשקעה | D8: Henderson Park North America Real Estate Fund I GP LLC | G8: Henderson Park Real Estate Fund II | H8: 11020471 | I8: פנימי | J8: EUR | K8: 45139 | L8: 879.98073 | M8: 2987.0946 | N8: 339.75762 | O8: 1153.3072 | P8: 0.38609666 | Q8: 49141
A9: 13908 | B9: 13908 | C9: התחייבות להשקעה | D9: HARBOURVEST GP LLC | G9: HV Gondor Feeder L.P | H9: 11020502 | I9: פנימי | J9: USD | K9: 45278 | L9: 681.63057 | M9: 2029.8958 | N9: 87.857606 | O9: 261.63995 | P9: 0.12889329 | Q9: 48633
A10: 13908 | B10: 13908 | C10: התחייבות להשקעה | D10: Pantheon Zilker GP LLC | G10: Pantheon Zilker, L.P | H10: 11020508 | I10: פנימי | J10: USD | K10: 45313 | L10: 918.5 | M10: 2735.293 | N10: 81.5 | O10: 242.707 | P10: 0.088731628 | Q10: 47870
A11: 13908 | B11: 13908 | C11: התחייבות להשקעה | D11: EQT Infrastructure VI (General Partner) S.à r.l. | G11: EQT Infrastructure VI Co-Investment | H11: 11020523 | I11: פנימי | J11: USD | K11: 45385 | L11: 1041.6667 | M11: 3102.0833 | N11: 159.92178 | O11: 476.24707 | P11: 0.15352491 | Q11: 47118
A12: 13908 | B12: 13908 | C12: התחייבות להשקעה | D12: LCN European Fund IV GP S.a.r.l | G12: LCN European Fund IV SLP | H12: 11019351 | I12: פנימי | J12: EUR | K12: 45419 | L12: 951.09924 | M12: 3228.5064 | N12: 313.9436 | O12: 1065.6816 | P12: 0.33008501 | Q12: 46475
A13: 13908 | B13: 13908 | C13: התחייבות להשקעה | D13: EQT Infrastructure VI (General Partner) S.à r.l. | G13: EQT Infrastructure VI (No.1) USD SCSp | H13: 11020525 | I13: פנימי | J13: USD | K13: 45420 | L13: 3125 | M13: 9306.25 | N13: 1417.4289 | O13: 4221.1032 | P13: 0.45357724 | Q13: 47663
... A59: 13908 | B59: 13908 | C59: התחייבות להשקעה | D59: LLCP LMM IV GP, L.P | G59: LLCP Lower Middle Market Fund IV | H59: 10381355 | I59: אחר | J59: USD | K59: 46203 | L59: 9700 | M59: 28886.6 | N59: 9700 | O59: 28886.6 | P59: 1 | Q59: 49856

Sheet אפשרויות בחירה
A1: שם גיליון (רלוונטי לגיליונות עם עמודה "מאפיין עיקרי") | B1: שם עמודה | C1: אפשרות בחירה | D1: שם רשימה | E1: הערות והסברים
B2: ישראל/חו"ל | C2: ישראל | D2: ישראל/חו"ל
C3: חו"ל
B4: מדינה לפי חשיפה כלכלית, מדינת התאגדות קרן השקעה, מיקום משרד השותף הכללי, מדינת מיקום נדל"ן | C4: ישראל | D4: מדינות
C5: אוסטריה
C6: אוסטרליה
C7: אזור תעלת פנמה
C8: אזרביג'אן
C9: איחוד האמירויות הערביות
C10: איטליה
C11: איי הבתולה הבריטיים | F11: נוסף במסגרת עדכון הרשימה
C12: איי הבתולה של ארצות הברית | F12: נוסף במסגרת עדכון הרשימה
C13: איי סיישל
C14: איי קיימן
C15: איי שלמה הבריטיים
C16: איסלנד
C17: אירלנד
C18: אנדורה
C19: אסטוניה
C20: ארגנטינה
C21: ארה"ב
C22: אתיופיה
C23: בהמס
C24: בולגריה
... C35: גרמניה
C36: ג'רזי (Jersey) | F36: נוסף במסגרת עדכון הרשימה
C37: גרנזי (Guernsey) | F37: נוסף במסגרת עדכון הרשימה
C38: דנמרק
C39: דרום אפריקה
C40: דרום קוריאה | F40: נוסף במסגרת עדכון הרשימה
C41: הודו
C42: הולנד
C43: הונג קונג
C44: הונגריה
C45: הונדורס
C46: טייוואן | F46: נוסף במסגרת עדכון הרשימה
C47: יוון
C48: יפן
C49: ירדן
C50: לוכסמבורג
C51: לטביה
C52: ליטא
C53: ליכטנשטיין
C54: מאוריציוס
C55: מולדובה
C56: מונקו
C57: מלדיבים
C58: מלטה
... C62: מרוקו
C63: נורבגיה | F63: נוסף במסגרת עדכון הרשימה
C64: ניו זילנד
C65: סין
C66: סינגפור
C67: סלובניה
C68: סלובקיה
C69: ספרד
C70: סרביה
C71: ערב הסעודית
C72: פולין
C73: פורטוגל
C74: פינלנד
C75: פנמה
... C93: גלובלי
C94: Emerging Markets - Americas | E94: שווקים מתעוררים לפי הגדרת MSCI | F94: נוסף במסגרת עדכון הרשימה
C95: Emerging Markets - Europe, Middle East & Africa | E95: לפי הגדרת MSCI | F95: נוסף במסגרת עדכון הרשימה
C96: Emerging Markets - Asia | E96: לפי הגדרת MSCI | F96: נוסף במסגרת עדכון הרשימה
C97: Developed Markets - Americas | E97: לפי הגדרת MSCI | F97: נוסף במסגרת עדכון הרשימה
C98: Developed Markets - Europe | E98: לפי הגדרת MSCI | F98: נוסף במסגרת עדכון הרשימה
C99: Developed Markets - Pacific | E99: לפי הגדרת MSCI | F99: נוסף במסגרת עדכון הרשימה
C100: Frontier Markets - Europe | E100: לפי הגדרת MSCI | F100: נוסף במסגרת עדכון הרשימה
C101: Frontier Markets - Africa | E101: לפי הגדרת MSCI | F101: נוסף במסגרת עדכון הרשימה
C102: Frontier Markets - Middle East | E102: לפי הגדרת MSCI | F102: נוסף במסגרת עדכון הרשימה
C103: Frontier Markets - Asia | E103: לפי הגדרת MSCI | F103: נוסף במסגרת עדכון הרשימה
B104: סוג מספר מזהה מנפיק | C104: ח.פ. | D104: סוג מספר מזהה מנפיק
C105: מספר מנפיק
C106: מספר שותפות
C107: מספר תאגיד או שותפות בחו"ל
C108: פנימי
C109: LEI
C110: אחר
B111: סוג מספר מזהה בנק | C111: ח.פ. | D111: סוג מספר מזהה בנק
C112: סימול בנק
C113: SWIFT
B114: סוג מספר מזהה שותף כללי קרן השקעות | C114: ח.פ. | D114: סוג מספר מזהה שותף כללי קרן השקעות
C115: מספר שותפות
C116: מספר תאגיד או שותפות בחו"ל
C117: LEI
B118: סוג מספר מזהה לווה | C118: ח.פ. | D118: סוג מספר מזהה לווה
C119: מרשם
C120: מספר תאגיד או שותפות בחו"ל
C121: פנימי
C122: מספר שותפות
C123: ת"ז
C124: דרכון
C125: LEI
C126: אחר
B127: סוג מספר נייר ערך | C127: ISIN | D127: סוג מספר נייר ערך
C128: OCC
C129: FIGI
C130: טיקר
...

Sheet מיפוי סעיפים
A1: שם גיליון | B1: שם סעיף | C1: מספר סעיף | D1: מידע שניתן לדווח רק לרשות
A2: מזומנים ושווי מזומנים | B2: מספר קופה/קרן/ח.פ. עבור חברת ביטוח | C2: 5.1
A3: מזומנים ושווי מזומנים | B3: מספר מסלול | C3: 5.2
A4: מזומנים ושווי מזומנים | B4: שם הבנק | C4: 5.4
A5: מזומנים ושווי מזומנים | B5: מספר מזהה בנק | C5: 5.7
A6: מזומנים ושווי מזומנים | B6: סוג מספר מזהה בנק | C6: 5.11
A7: מזומנים ושווי מזומנים | B7: מאפיין עיקרי | C7: 5.26
A8: מזומנים ושווי מזומנים | B8: ישראל/חו"ל | C8: 5.27
A9: מזומנים ושווי מזומנים | B9: בעל עניין/צד קשור | C9: 5.36
A10: מזומנים ושווי מזומנים | B10: דירוג הבנק | C10: 5.5
A11: מזומנים ושווי מזומנים | B11: שם מדרג | C11: 5.51
A12: מזומנים ושווי מזומנים | B12: מטבע פעילות | C12: 5.53
A13: מזומנים ושווי מזומנים | B13: שווי מטבעי | C13: 5.59
A14: מזומנים ושווי מזומנים | B14: שער חליפין | C14: 5.54
A15: מזומנים ושווי מזומנים | B15: שיעור ריבית | C15: 5.7 | D15: ü
A16: מזומנים ושווי מזומנים | B16: שווי הוגן (באלפי ש"ח) | C16: 5.63
A17: מזומנים ושווי מזומנים | B17: שיעור מנכסי אפיק ההשקעה | C17: 5.47
A18: מזומנים ושווי מזומנים | B18: שיעור מסך נכסי ההשקעה | C18: 5.48
A19: מזומנים ושווי מזומנים
A20: איגרות חוב ממשלתיות | B20: מספר קופה/קרן/ח.פ. עבור חברת ביטוח | C20: 5.1
A21: איגרות חוב ממשלתיות | B21: מספר מסלול | C21: 5.2
A22: איגרות חוב ממשלתיות | B22: שם מנפיק | C22: 5.3
A23: איגרות חוב ממשלתיות | B23: שם נייר ערך | C23: 5.14
A24: איגרות חוב ממשלתיות | B24: מספר נייר ערך | C24: 5.19
A25: איגרות חוב ממשלתיות | B25: מאפיין עיקרי | C25: 5.26
A26: איגרות חוב ממשלתיות | B26: ישראל/חו"ל | C26: 5.27
A27: איגרות חוב ממשלתיות | B27: מדינה לפי חשיפה כלכלית | C27: 5.28
A28: איגרות חוב ממשלתיות | B28: זירת מסחר | C28: 5.3
A29: איגרות חוב ממשלתיות | B29: דירוג | C29: 5.49
A30: איגרות חוב ממשלתיות | B30: שם מדרג | C30: 5.51
A31: איגרות חוב ממשלתיות | B31: מטבע פעילות | C31: 5.53
... A45: איגרות חוב ממשלתיות | B45: שיעור מסך נכסי ההשקעה | C45: 5.48
A46: איגרות חוב ממשלתיות
A47: ניירות ערך מסחריים | B47: מספר קופה/קרן/ח.פ. עבור חברת ביטוח | C47: 5.1
A48: ניירות ערך מסחריים | B48: מספר מסלול | C48: 5.2
A49: ניירות ערך מסחריים | B49: שם מנפיק | C49: 5.3
A50: ניירות ערך מסחריים | B50: מספר מנפיק | C50: 5.6
A51: ניירות ערך מסחריים | B51: סוג מספר מזהה מנפיק | C51: 5.1
A52: ניירות ערך מסחריים | B52: שם נייר ערך | C52: 5.14
A53: ניירות ערך מסחריים | B53: מספר נייר ערך | C53: 5.19
A54: ניירות ערך מסחריים | B54: סוג מספר נייר ערך | C54: 5.24
A55: ניירות ערך מסחריים | B55: מאפיין עיקרי | C55: 5.26
A56: ניירות ערך מסחריים | B56: ישראל/חו"ל | C56: 5.27
A57: ניירות ערך מסחריים | B57: מדינה לפי חשיפה כלכלית | C57: 5.28
A58: ניירות ערך מסחריים | B58: זירת מסחר | C58: 5.3
... A70: ניירות ערך מסחריים | B70: נחיתות חוזית | C70: 5.76
A71: ניירות ערך מסחריים | B71: האם סווג כחוב בעייתי | C71: 5.89 | D71: ü
A72: ניירות ערך מסחריים | B72: ערך נקוב (יחידות) | C72: 5.58
A73: ניירות ערך מסחריים | B73: סכום לקבל (במטבע הפעילות) | C73: 5.62
A74: ניירות ערך מסחריים | B74: שער חליפין | C74: 5.54
A75: ניירות ערך מסחריים | B75: שער נייר הערך | C75: 5.55
A76: ניירות ערך מסחריים | B76: שווי הוגן (באלפי ש"ח) | C76: 5.63
A77: ניירות ערך מסחריים | B77: עלות מופחתת (באלפי ש"ח) | C77: 5.65
A78: ניירות ערך מסחריים | B78: עלות מופחתת (במטבע הפעילות) | C78: 5.66
A79: ניירות ערך מסחריים | B79: השיטה שיושמה בדוח הכספי | C79: 5.68
A80: ניירות ערך מסחריים | B80: שיעור מערך נקוב מונפק | C80: 5.45
A81: ניירות ערך מסחריים | B81: שיעור מנכסי אפיק ההשקעה | C81: 5.47
A82: ניירות ערך מסחריים | B82: שיעור מסך נכסי ההשקעה | C82: 5.48
A83: ניירות ערך מסחריים
A84: איגרות חוב | B84: מספר קופה/קרן/ח.פ. עבור חברת ביטוח | C84: 5.1
A85: איגרות חוב | B85: מספר מסלול | C85: 5.2
A86: איגרות חוב | B86: שם מנפיק | C86: 5.3
A87: איגרות חוב | B87: מספר מנפיק | C87: 5.6
A88: איגרות חוב | B88: סוג מספר מזהה מנפיק | C88: 5.1
A89: איגרות חוב | B89: שם נייר ערך | C89: 5.14
A90: איגרות חוב | B90: מספר נייר ערך | C90: 5.19
A91: איגרות חוב | B91: סוג מספר נייר ערך | C91: 5.24
A92: איגרות חוב | B92: מאפיין עיקרי | C92: 5.26
A93: איגרות חוב | B93: ישראל/חו"ל | C93: 5.27
A94: איגרות חוב | B94: מדינה לפי חשיפה כלכלית | C94: 5.28
A95: איגרות חוב | B95: סטאטוס סחירות | C95: 5.29
... A107: איגרות חוב | B107: נחיתות חוזית | C107: 5.76
A108: איגרות חוב | B108: האם סווג כחוב בעייתי | C108: 5.89 | D108: ü
A109: איגרות חוב | B109: ערך נקוב (יחידות) | C109: 5.58
A110: איגרות חוב | B110: סכום לקבל (במטבע הפעילות) | C110: 5.62
A111: איגרות חוב | B111: שער חליפין | C111: 5.54
A112: איגרות חוב | B112: שער נייר הערך | C112: 5.55
A113: איגרות חוב | B113: עלות מופחתת (באלפי ש"ח) | C113: 5.65
A114: איגרות חוב | B114: עלות מופחתת (במטבע הפעילות) | C114: 5.66
A115: איגרות חוב | B115: השיטה שיושמה בדוח הכספי | C115: 5.68
A116: איגרות חוב | B116: שיעור מערך נקוב מונפק | C116: 5.45
A117: איגרות חוב | B117: שיעור מנכסי אפיק ההשקעה | C117: 5.47
A118: איגרות חוב | B118: שיעור מסך נכסי ההשקעה | C118: 5.48
A119: איגרות חוב
A120: מניות מבכ ויהש | B120: מספר קופה/קרן/ח.פ. עבור חברת ביטוח | C120: 5.1
A121: מניות מבכ ויהש | B121: מספר מסלול | C121: 5.2
A122: מניות מבכ ויהש | B122: שם מנפיק | C122: 5.3
A123: מניות מבכ ויהש | B123: מספר מנפיק | C123: 5.6
A124: מניות מבכ ויהש | B124: סוג מספר מזהה מנפיק | C124: 5.1
A125: מניות מבכ ויהש | B125: שם נייר ערך | C125: 5.14
A126: מניות מבכ ויהש | B126: מספר נייר ערך | C126: 5.19
A127: מניות מבכ ויהש | B127: סוג מספר נייר ערך | C127: 5.24
A128: מניות מבכ ויהש | B128: מאפיין עיקרי | C128: 5.26
A129: מניות מבכ ויהש | B129: ישראל/חו"ל | C129: 5.27
A130: מניות מבכ ויהש | B130: מדינה לפי חשיפה כלכלית | C130: 5.28
A131: מניות מבכ ויהש | B131: סטאטוס סחירות | C131: 5.29
... A143: מניות מבכ ויהש | B143: שיעור מסך נכסי ההשקעה | C143: 5.48
A144: מניות מבכ ויהש
A145: קרנות סל | B145: מספר קופה/קרן/ח.פ. עבור חברת ביטוח | C145: 5.1
A146: קרנות סל | B146: מספר מסלול | C146: 5.2
...

Sheet UPDATE
A1: גיליון | B1: סוג עדכון | C1: עדכון
A2: אפשרויות בחירה | B2: הוספת אפשרויות | C2: אסטרטגיית קרן השקעה: CLO Debt, CLO Equity, Long Biased Hedge Fund, Long/Short Hedge Fund, Macro Hedge Fund, Real Estate Sale and Leaseback.
A3: אפשרויות בחירה | B3: הוספת אפשרויות | C3: ריבית עוגן: Shekel Overnight Risk Free Rate.
A4: אפשרויות בחירה | B4: הוספת אפשרויות | C4: רשימת המדינות/פקטור נוסף: דנמרק, דרום אפריקה.
A5: אפשרויות בחירה | B5: הוספת אפשרויות | C5: מטבע והצמדה: נוספה האפשרות "נקוב במט"ח", ודויק הפירוט של אג"ח להמרה ונש"ר.
A6: אפשרויות בחירה | B6: הוספת אפשרויות | C6: סוגי מדדים: המונח הכללי "מדד" שונה ל-"מדד מניות", ונוספה האפשרות "מדד אחר".
A7: אפשרויות בחירה | B7: תיקוני טעות סופר | C7: C95, C100 (תוקן Euope ל-Europe), C889 (תוקן "ביון" ל-"בין").
A8: אפשרויות בחירה | B8: מחיקת רווחים ומעברי שורה | C8: B2, B146, B512, B647, C552:C557, C561, C588:C589, C648:C649, C895, C936, C1027:C1029.
A9: אפשרויות בחירה | B9: דיוק הפרדת כותרות עמודות שונות בפסיק | C9: B4, B182, B497.
A10: אפשרויות בחירה | B10: תיקונים קלים בשמות עמודות/גליונות | C10: A891, A963, B114, B132, B551, B693.
A11: אפשרויות בחירה | B11: תיקוני טעות סופר | C11: "היי-טק"/"היי טק" שונה ל"הייטק", "שירותים" שונה ל"שרותים", "בלי ארה"ב" שונה ל"ללא ארה"ב". נמחקו המילים "לא סחיר" מהאפשרות "אג"ח לא סחיר שנרכש בין 04/11/2008 ועד 31/03/2015...".
A12: אפשרויות בחירה | B12: עדכון רשימה | C12: בוצעה האחדה של רשימת ענפי המסחר עם הרשימה כפי שמפרסמת הבורסה בת"א, וכן בוצעה האחדה של האפשרויות ברשימת "פקטור נוסף" עם רשימת ענפי מסחר ורשימת המדינות. (נמחקו אפשרויות הבחירה: אחסנה, כווית, קרנות סל.)
... A17: סכום נכסים | B17: עדכון כותרות | C17: עודכנו כותרות השורות והעמודות בהתאמה לשמות הגליונות.

Sheet File Name Info
A2: סוג קובץ
A3: נכסי מבוטחים - חברת ביטוח | B3: in
A4: נכסי עמיתים - קופות גמל | B4: gm
A5: נכסי עמיתים - קרנות פנסיה | B5: pn
A6: נכסי אפיק השקעה מובטח תשואה | B6: ca
A7: נכסי נוסטרו - חברת ביטוח | B7: ni
A8: נכסי נוסטרו - חברה מנהלת | B8: nf
A10: יעוד הקובץ
A11: לממונה
A12: לציבור | B12: p
A15: רבעון
A16: 01
A17: 02
A18: 03
A19: 04
A21: שנה
A22: 2022 | B22: 22
A23: 2023 | B23: 23
A24: 2024 | B24: 24
A25: 2025 | B25: 25
A26: 2026 | B26: 26
A27: 2027 | B27: 27
A28: 2028 | B28: 28
A29: 2029 | B29: 29
A30: 2030 | B30: 30
A31: 2031 | B31: 31
A34: שם גוף מוסדי | B34: ח.פ.
A35: הפניקס חברה לביטוח בע"מ | B35: 520023185
A36: כלל חברה לביטוח בע"מ | B36: 520024647
A37: מגדל חברה לביטוח בע"מ | B37: 520004896
A38: מנורה מבטחים ביטוח בע"מ | B38: 520042540
A39: אשרא החברה הישראלית לביטוח סיכוני סחר חוץ בע"מ | B39: 520021916
A40: שומרה חברה לביטוח בע"מ | B40: 510015951
A41: כלל ביטוח אשראי בע"מ | B41: 510888985
A42: הכשרה חברה לביטוח בע"מ | B42: 520042177
A43: ענבל חברה לביטוח בע"מ | B43: 520031030
A44: איילון חברה לביטוח בע"מ | B44: 520030677
A45: ש. שלמה חברה לביטוח בע"מ | B45: 513879189
A46: קנט - קרן לביטוח נזקי טבע בחקלאות | B46: 520027848
... A130: אקטיון בע"מ | B130: 515977338
