Workbook
Name Additional_Factor: 'אפשרויות בחירה'!$C$701:$C$850
Name Amoritization: 'אפשרויות בחירה'!$C$546:$C$550
Name Capsule: 'אפשרויות בחירה'!$C$926:$C$928
Name Company_Name: 'File Name Info'!$A$34:$A$120
Name Company_Name_ID: 'File Name Info'!$A$34:$B$120
Name Consortium: 'אפשרויות בחירה'!$C$514:$C$515
Name Country_list: 'אפשרויות בחירה'!$C$4:$C$85
Name Country_list_funds: 'אפשרויות בחירה'!$C$4:$C$103
Name CSA: 'אפשרויות בחירה'!$C$688:$C$689
Name Delivery: 'אפשרויות בחירה'!$C$666:$C$667
Name Dependence_Independence: 'אפשרויות בחירה'!$C$654:$C$655
Name Duration_Underlying_Interest_Rate: 'אפשרויות בחירה'!$C$680:$C$687
Name File_Type: 'File Name Info'!$A$10:$A$12
Name Full_File_Type: 'File Name Info'!$A$11:$B$13
Name Full_Type: 'File Name Info'!$A$2:$B$8
Name Full_Type_Nostro: 'File Name Info'!$A$3:$B$6
Name Full_Year: 'File Name Info'!$A$22:$B$31
Name Fund_Strategy: 'אפשרויות בחירה'!$C$597:$C$621
Name Fund_type: 'אפשרויות בחירה'!$C$328:$C$498
Name Holding_interest: 'אפשרויות בחירה'!$C$146:$C$147
Name In_the_books: 'אפשרויות בחירה'!$C$656:$C$657
Name Industry_Sector: 'אפשרויות בחירה'!$C$1129:$C$1245
Name Industry_sector_all: 'אפשרויות בחירה'!$C$202:$C$327
Name Industry_sectors: 'אפשרויות בחירה'!$C$202:$C$327
Name israel_abroad: 'אפשרויות בחירה'!$C$2:$C$3
Name Issuer_Number_Banks: 'אפשרויות בחירה'!$C$111:$C$113
Name Issuer_Number_Fund: 'אפשרויות בחירה'!$C$114:$C$117
Name issuer_number_loan: 'אפשרויות בחירה'!$C$118:$C$126
Name Issuer_Number_Type: 'אפשרויות בחירה'!$C$104:$C$110
Name Issuer_Number_Type_2: 'אפשרויות בחירה'!$C$1076:$C$1079
Name Issuer_Number_Type_3: 'אפשרויות בחירה'!$C$1081:$C$1085
Name Issuer_Number_Type_V2: 'אפשרויות בחירה'!$C$104:$C$110
Name Issuer_Type_TFunds: 'אפשרויות בחירה'!$C$1087:$C$1089
Name Leading_factor: 'אפשרויות בחירה'!$C$692:$C$700
Name Linked_Type: 'אפשרויות בחירה'!$C$516:$C$519
Name other_investments: 'אפשרויות בחירה'!$C$1000:$C$1033
Name Penalty: 'אפשרויות בחירה'!$C$851:$C$852
Name QTR: 'File Name Info'!$A$15:$A$19
Name Rating_Agency: 'אפשרויות בחירה'!$C$188:$C$201
Name real_estate_lifestage: 'אפשרויות בחירה'!$C$634:$C$642
Name real_estate_loans: 'אפשרויות בחירה'!$C$553:$C$591
Name Real_Estate_Main_Use: 'אפשרויות בחירה'!$C$622:$C$633
Name Recourse_Nonrecourse: 'אפשרויות בחירה'!$C$544:$C$545
Name Repayment_Rights: 'אפשרויות בחירה'!$C$551:$C$552
Name Reset_frequency: 'אפשרויות בחירה'!$C$658:$C$665
Name Security_ID_Number_Type: 'אפשרויות בחירה'!$C$1113:$C$1116
Name Security_Number_Loans: 'אפשרויות בחירה'!$C$131
Name Stock_Exchange: 'אפשרויות בחירה'!$C$1283:$C$1315
Name Stock_Exchange_Gov_Bonds: 'אפשרויות בחירה'!$C$148:$C$181
Name Subordination_Risk: 'אפשרויות בחירה'!$C$186:$C$187
Name Tradeable_Status: 'אפשרויות בחירה'!$C$1272:$C$1281
Name Tradeable_Status_All: 'אפשרויות בחירה'!$C$135:$C$145
Name tradeable_status_bonds: 'אפשרויות בחירה'!$C$1248:$C$1253
Name tradeable_status_funds: 'אפשרויות בחירה'!$C$1118:$C$1119
Name tradeable_status_stock: 'אפשרויות בחירה'!$C$1255:$C$1259
Name Tradeable_Status_v2: 'אפשרויות בחירה'!$C$1121:$C$1126
Name tradeable_status_warrants: 'אפשרויות בחירה'!$C$1261:$C$1265
Name tradeable_status_warrants_v2: 'אפשרויות בחירה'!$C$1267:$C$1269
Name Transaction: 'אפשרויות בחירה'!$C$643:$C$646
Name Type: 'File Name Info'!$A$2:$A$8

Sheet עמוד פתיחה
A1: קובץ דיווח עבור רשימת נכסים ברמת הנכס הבודד (חוזר גופים מוסדיים 2015-9-14)
A3: יש לבחור תחום: | D3: נכסי עמיתים - קרנות פנסיה
A5: האם מדובר בקובץ לממומנה או לציבור: | D5: לציבור
A7: יש לבחור את רבעון הדיווח: | D7: Q1
A9: יש לבחור את שנת הדיווח: | D9: 2025
A11: יש לבחור את הגוף המוסדי: | D11: מור פנסיה נכסים
A13: ח.פ. הגוף המוסדי: | D13: 514956465
A15: שם קובץ לשמירה | D15: =IF(D5="לממונה",CONCATENATE(D13, "_",VLOOKUP(D3,Full_Type,2,0),"_",D7,VLOOKUP(D9,Full_Year,2,0),".xlxs"),IF(D5="לציבור",CONCATENATE(D13,"_",VLOOKUP(D3,Full_Type_Nostro,2,0),"_",VLOOKUP(D5,Full_File_Type,2,0),"_",D7,VLOOKUP(D9,Full_Year,2,0),".xlsx"),"שם קובץ לשמירה")) -> 514956465_pn_p_Q125.xlsx
A17: פרטי האחראי על הדיווח בגוף המוסדי | B17: שם: | D17: סיוון לוי, רו"ח
B19: מספר טלפון:
B21: כתובת מייל:
A23: הוראות למילוי הדיווח: | D23: יש לדווח לפי ההנחיות בחלק ג' לנספח 5.4.3.2 שבפרק 3 שבחלק 4 לשער 5 בחוזר המאוחד - "רשימת נכסים ברמת הנכס הבודד".

Sheet סכום נכסים
C1: ידווח בקבצי נכסי הנוסטרו בלבד
B2: שווי הוגן | C2: עלות מופחתת | D2: השיטה שיושמה בדוח הכספי | E2: שיעור מסך נכסי השקעה
A3: מזומנים ושווי מזומנים | B3: 2094300 | E3: =+B3/$B$30 -> 0.19096883
A4: איגרות חוב ממשלתיות | B4: 1711552 | E4: =+B4/$B$30 -> 0.15606794
A5: ניירות ערך מסחריים | B5: 6047.535 | E5: =+B5/$B$30 -> 0.00055144472
A6: איגרות חוב | B6: 1290790.9 | E6: =+B6/$B$30 -> 0.11770082
A7: מניות, מניות בכורה ויחידות השתתפות | B7: 1561297.5 | E7: =+B7/$B$30 -> 0.14236697
A8: קרנות סל | B8: 226765.35 | E8: =+B8/$B$30 -> 0.020677608
A9: קרנות נאמנות | B9: =SUM('קרנות נאמנות'!T:T) -> 373786.8 | E9: =+B9/$B$30 -> 0.034083764
A10: כתבי אופציה | B10: 20380.259 | E10: =+B10/$B$30 -> 0.0018583747
A11: אופציות | B11: 0 | E11: =+B11/$B$30 -> 0
A12: חוזים עתידיים | B12: -71145.368 | E12: =+B12/$B$30 -> -0.0064873932
A13: מוצרים מובנים | B13: 238.56796 | E13: =+B13/$B$30 -> 2.1753829e-05
A14: לא סחיר איגרות חוב ממשלתיות | B14: 0 | E14: =+B14/$B$30 -> 0
A15: לא סחיר איגרות חוב מיועדות | B15: 197260.09 | E15: =+B15/$B$30 -> 0.01798717
A16: אפיק השקעה מובטח תשואה | B16: 2854013.5 | E16: =+B16/$B$30 -> 0.26024334
A17: לא סחיר ניירות ערך מסחריים | B17: 14281.02 | E17: =+B17/$B$30 -> 0.0013022154
A18: לא סחיר איגרות חוב | B18: 158740.63 | E18: =+B18/$B$30 -> 0.014474771
A19: לא סחיר מניות, מניות בכורה ויחידות השתתפות | B19: 54112.782 | E19: =+B19/$B$30 -> 0.0049342762
A20: קרנות השקעה | B20: 310819.53 | E20: =+B20/$B$30 -> 0.028342092
A21: לא סחיר כתבי אופציה | B21: 8363.9073 | E21: =+B21/$B$30 -> 0.00076266322
... A23: לא סחיר נגזרים אחרים | B23: 6219.0533 | E23: =+B23/$B$30 -> 0.00056708463
A24: הלוואות | B24: =SUM(הלוואות!AT:AT) -> 99475.038 | E24: =+B24/$B$30 -> 0.0090706353
A25: לא סחיר מוצרים מובנים | B25: 11439.529 | E25: =+B25/$B$30 -> 0.0010431139
A26: פיקדונות מעל 3 חודשים | B26: 0 | E26: =+B26/$B$30 -> 0
A27: זכויות מקרקעין | B27: 33410.519 | E27: =+B27/$B$30 -> 0.0030465395
A28: השקעה בחברות מוחזקות | B28: 0 | E28: =+B28/$B$30 -> 0
A29: נכסים אחרים | B29: =SUM('נכסים אחרים'!N:N) -> 4562.0069 | E29: =+B29/$B$30 -> 0.00041598679
A30: סך הכל נכסים | B30: =SUM(B3:B29) -> 10966711 | E30: =SUM(E3:E29) -> 1
A31: מסגרות אשראי | B31: =+SUM('מסגרות אשראי'!S:S) -> 142676.91
A32: יתרות התחייבויות להשקעה | B32: =+SUM('יתרות התחייבות להשקעה'!O:O) -> 187879.46

Sheet מזומנים ושווי מזומנים
A1: מספר קופה/קרן/ח.פ. עבור חברת ביטוח | B1: מספר מסלול | C1: שם הבנק | D1: מספר מזהה בנק | E1: סוג מספר מזהה בנק | F1: מאפיין עיקרי | G1: ישראל/חו"ל | H1: בעל עניין/צד קשור | I1: דירוג הבנק | J1: שם מדרג | K1: מטבע פעילות | L1: שווי מטבעי | M1: שער חליפין | N1: שיעור ריבית | O1: שווי הוגן (באלפי ש"ח) | P1: שיעור מנכסי אפיק ההשקעה | Q1: שיעור מסך נכסי ההשקעה
A2: 13908 | B2: 13909 | C2: בנק הבינלאומי הראשון בע"מ | D2: 31 | E2: סימול בנק | F2: מזומן ועו"ש בש"ח | G2: ישראל | H2: לא | I2: ilAAA | J2: S&P מעלות | K2: ILS | L2: -1e-05 | M2: 1 | O2: -1e-05 | P2: -1.2322235e-11 | Q2: -2.4364448e-12
A3: 13908 | B3: 13909 | C3: בנק הבינלאומי הראשון בע"מ | D3: 31 | E3: סימול בנק | F3: מזומן ועו"ש בש"ח | G3: ישראל | H3: לא | I3: ilAAA | J3: S&P מעלות | K3: ILS | L3: 417024.65 | M3: 1 | O3: 417024.65 | P3: 0.51386756 | Q3: 0.10160576
A4: 13908 | B4: 13909 | C4: בנק המזרחי המאוחד בע"מ | D4: 20 | E4: סימול בנק | F4: מזומן ועו"ש בש"ח | G4: ישראל | H4: לא | I4: ilAAA | J4: S&P מעלות | K4: ILS | L4: 263.94606 | M4: 1 | O4: 263.94606 | P4: 0.00032524053 | Q4: 6.4309002e-05
A5: 13908 | B5: 13909 | C5: בנק הבינלאומי הראשון בע"מ | D5: 31 | E5: סימול בנק | F5: מזומן ועו"ש נקוב במט"ח | G5: ישראל | H5: לא | I5: ilAAA | J5: S&P מעלות | K5: USD | L5: 96449.892 | M5: 3.718 | O5: 358600.7 | P5: 0.4418762 | Q5: 0.087371083
A6: 13908 | B6: 13909 | C6: בנק המזרחי המאוחד בע"מ | D6: 20 | E6: סימול בנק | F6: מזומן ועו"ש נקוב במט"ח | G6: ישראל | H6: לא | I6: ilAAA | J6: S&P מעלות | K6: USD | L6: 0.00025013448 | M6: 3.718 | O6: 0.00093 | P6: 1.1459678e-09 | Q6: 2.2658937e-10
A7: 13908 | B7: 13909 | C7: בנק הבינלאומי הראשון בע"מ | D7: 31 | E7: סימול בנק | F7: מזומן ועו"ש נקוב במט"ח | G7: ישראל | H7: לא | I7: ilAAA | J7: S&P מעלות | K7: CHF | L7: 54.34228 | M7: 4.2171 | O7: 229.16683 | P7: 0.00028238475 | Q7: 5.5835234e-05
A8: 13908 | B8: 13909 | C8: בנק הבינלאומי הראשון בע"מ | D8: 31 | E8: סימול בנק | F8: מזומן ועו"ש נקוב במט"ח | G8: ישראל | H8: לא | I8: ilAAA | J8: S&P מעלות | K8: GBP | L8: 693.79711 | M8: 4.8108 | O8: 3337.7191 | P8: 0.0041128159 | Q8: 0.00081321686
A9: 13908 | B9: 13909 | C9: בנק הבינלאומי הראשון בע"מ | D9: 31 | E9: סימול בנק | F9: מזומן ועו"ש נקוב במט"ח | G9: ישראל | H9: לא | I9: ilAAA | J9: S&P מעלות | K9: JPY | L9: 87393.79 | M9: 0.024893 | O9: 2175.4936 | P9: 0.0026806943 | Q9: 0.00053004702
A10: 13908 | B10: 13909 | C10: בנק המזרחי המאוחד בע"מ | D10: 20 | E10: סימול בנק | F10: מזומן ועו"ש נקוב במט"ח | G10: ישראל | H10: לא | I10: ilAAA | J10: S&P מעלות | K10: JPY | L10: 0.00080343872 | M10: 0.024893 | O10: 2e-05 | P10: 2.4644469e-11 | Q10: 4.8728897e-12
A11: 13908 | B11: 13909 | C11: בנק הבינלאומי הראשון בע"מ | D11: 31 | E11: סימול בנק | F11: מזומן ועו"ש נקוב במט"ח | G11: ישראל | H11: לא | I11: ilAAA | J11: S&P מעלות | K11: CAD | L11: 311.6101 | M11: 2.589 | O11: 806.75855 | P11: 0.00099410682 | Q11: 0.00019656227
A12: 13908 | B12: 13909 | C12: בנק הבינלאומי הראשון בע"מ | D12: 31 | E12: סימול בנק | F12: מזומן ועו"ש נקוב במט"ח | G12: ישראל | H12: לא | I12: ilAAA | J12: S&P מעלות | K12: EUR | L12: 7153.9733 | M12: 4.0219 | O12: 28772.565 | P12: 0.03545423 | Q12: 0.0070102768
A13: 13908 | B13: 13909 | C13: בנק הבינלאומי הראשון בע"מ | D13: 31 | E13: סימול בנק | F13: מזומן ועו"ש נקוב במט"ח | G13: ישראל | H13: לא | I13: ilAAA | J13: S&P מעלות | K13: USD | L13: -9.9480689 | M13: 3.718 | O13: -36.98692 | P13: -4.5576151e-05 | Q13: -9.0116591e-06
... A237: 13918 | B237: 15273 | C237: בנק הבינלאומי הראשון בע"מ | D237: 31 | E237: סימול בנק | F237: מזומן ועו"ש נקוב במט"ח | G237: ישראל | H237: לא | I237: ilAAA | J237: S&P מעלות | K237: USD | L237: -0.039661108 | M237: 3.718 | O237: -0.14746 | P237: -2.2053101e-05 | Q237: -6.1912642e-06
A238: 13908 | B238: 15267
A239: 13918 | B239: 15274

Sheet איגרות חוב ממשלתיות
A1: מספר קופה/קרן/ח.פ. עבור חברת ביטוח | B1: מספר מסלול | C1: שם מנפיק | D1: שם נייר ערך | E1: מספר נייר ערך | F1: מאפיין עיקרי | G1: ישראל/חו"ל | H1: מדינה לפי חשיפה כלכלית | I1: זירת מסחר | J1: דירוג | K1: שם מדרג | L1: מטבע פעילות | M1: מח"מ | N1: מועד פדיון | O1: שיעור ריבית | P1: תשואה לפדיון | Q1: סכום לקבל (במטבע הפעילות) | R1: ערך נקוב (יחידות) | S1: שער חליפין | T1: שער נייר הערך | U1: שווי הוגן (באלפי ש"ח) | V1: עלות מופחתת (באלפי ש"ח) | W1: השיטה שיושמה בדוח הכספי | X1: שיעור מערך נקוב מונפק | Y1: שיעור מנכסי אפיק ההשקעה | Z1: שיעור מסך נכסי ההשקעה
A2: 13908 | B2: 13909 | C2: מדינת ישראל | D2: ממשל צמודה 1025 | E2: IL0011359127 | F2: צמוד למדד המחירים לצרכן בריבית קבועה | G2: ישראל | H2: ישראל | I2: TASE | J2: NR | K2: NR | L2: ILS | M2: 0.584 | N2: 31/10/2025 | O2: 0.0075 | P2: 0.0124 | Q2: 0 | R2: 32061125 | S2: 1 | T2: 116.16 | U2: 37242.203 | W2: שווי הוגן | X2: 0.0014772855 | Y2: 0.09128584 | Z2: 0.0090738573
A3: 13908 | B3: 13909 | C3: מדינת ישראל | D3: ממשל שקלית 0327 | E3: IL0011393449 | F3: לא צמוד למדד המחירים לצרכן ריבית קבועה | G3: ישראל | H3: ישראל | I3: TASE | J3: NR | K3: NR | L3: ILS | M3: 1.977 | N3: 31/03/2027 | O3: 0.02 | P3: 0.0422 | Q3: 0 | R3: 15425980 | S3: 1 | T3: 95.83 | U3: 14782.717 | W3: שווי הוגן | X3: 0.00054647033 | Y3: 0.036234503 | Z3: 0.0036017274
A4: 13908 | B4: 13909 | C4: מדינת ישראל | D4: ממשל שקלית 0347 | E4: IL0011401937 | F4: לא צמוד למדד המחירים לצרכן ריבית קבועה | G4: ישראל | H4: ישראל | I4: TASE | J4: NR | K4: NR | L4: ILS | M4: 14.743 | N4: 31/03/2047 | O4: 0.0375 | P4: 0.0486 | Q4: 0 | R4: 6360000 | S4: 1 | T4: 85.21 | U4: 5419.356 | W4: שווי הוגן | X4: 0.00024231946 | Y4: 0.013283598 | Z4: 0.0013203962
A5: 13908 | B5: 13909 | C5: מדינת ישראל | D5: ממשל צמודה 0527 | E5: IL0011408478 | F5: צמוד למדד המחירים לצרכן בריבית קבועה | G5: ישראל | H5: ישראל | I5: TASE | J5: NR | K5: NR | L5: ILS | M5: 2.142 | N5: 31/05/2027 | O5: 0.0075 | P5: 0.0194 | Q5: 0 | R5: 44377464 | S5: 1 | T5: 114.63 | U5: 50869.887 | W5: שווי הוגן | X5: 0.0018219999 | Y5: 0.1246892 | Z5: 0.012394167
A6: 13908 | B6: 13909 | C6: מדינת ישראל | D6: ממשל שקלית 0928 | E6: IL0011508798 | F6: לא צמוד למדד המחירים לצרכן ריבית קבועה | G6: ישראל | H6: ישראל | I6: TASE | J6: NR | K6: NR | L6: ILS | M6: 3.36 | N6: 28/09/2028 | O6: 0.0225 | P6: 0.0426 | Q6: 0 | R6: 27884049 | S6: 1 | T6: 94.71 | U6: 26408.983 | W6: שווי הוגן | X6: 0.00080307685 | Y6: 0.064732105 | Z6: 0.006434403
A7: 13908 | B7: 13909 | C7: מדינת ישראל | D7: ממשל צמודה 0529 | E7: IL0011570236 | F7: צמוד למדד המחירים לצרכן בריבית קבועה | G7: ישראל | H7: ישראל | I7: TASE | J7: NR | K7: NR | L7: ILS | M7: 4.115 | N7: 31/05/2029 | O7: 0.005 | P7: 0.0197 | Q7: 0 | R7: 15612315 | S7: 1 | T7: 109.42 | U7: 17082.995 | W7: שווי הוגן | X7: 0.0005679711 | Y7: 0.041872807 | Z7: 0.0041621775
A8: 13908 | B8: 13909 | C8: מדינת ישראל | D8: ממשל שקלית 0330 | E8: IL0011609851 | F8: לא צמוד למדד המחירים לצרכן ריבית קבועה | G8: ישראל | H8: ישראל | I8: TASE | J8: NR | K8: NR | L8: ILS | M8: 4.892 | N8: 31/03/2030 | O8: 0.01 | P8: 0.0429 | Q8: 0 | R8: 423156 | S8: 1 | T8: 85.48 | U8: 361.71375 | W8: שווי הוגן | X8: 1.1207812e-05 | Y8: 0.00088661092 | Z8: 8.812956e-05
A9: 13908 | B9: 13909 | C9: מדינת ישראל | D9: ממשל שקלית 0537 | E9: IL0011661803 | F9: לא צמוד למדד המחירים לצרכן ריבית קבועה | G9: ישראל | H9: ישראל | I9: TASE | J9: NR | K9: NR | L9: ILS | M9: 10.807 | N9: 31/05/2037 | O9: 0.015 | P9: 0.0461 | Q9: 0 | R9: 3150000 | S9: 1 | T9: 72.72 | U9: 2290.68 | W9: שווי הוגן | X9: 9.6430962e-05 | Y9: 0.0056147766 | Z9: 0.00055811155
A10: 13908 | B10: 13909 | C10: מדינת ישראל | D10: ממשל צמודה 0726 | E10: IL0011695645 | F10: צמוד למדד המחירים לצרכן בריבית קבועה | G10: ישראל | H10: ישראל | I10: TASE | J10: NR | K10: NR | L10: ILS | M10: 1.33 | N10: 31/07/2026 | O10: 0.001 | P10: 0.0196 | Q10: 0 | R10: 49712765 | S10: 1 | T10: 112.95 | U10: 56150.568 | W10: שווי הוגן | X10: 0.0024604719 | Y10: 0.13763288 | Z10: 0.013680776
A11: 13908 | B11: 13909 | C11: מדינת ישראל | D11: ממשל צמודה 1131 | E11: IL0011722209 | F11: צמוד למדד המחירים לצרכן בריבית קבועה | G11: ישראל | H11: ישראל | I11: TASE | J11: NR | K11: NR | L11: ILS | M11: 6.646 | N11: 30/11/2031 | O11: 0.001 | P11: 0.0203 | Q11: 0 | R11: 29107525 | S11: 1 | T11: 101.91 | U11: 29663.479 | W11: שווי הוגן | X11: 0.00094800192 | Y11: 0.072709329 | Z11: 0.007227343
A12: 13908 | B12: 13909 | C12: מדינת ישראל | D12: ממשל שקלית 0432 | E12: IL0011806606 | F12: לא צמוד למדד המחירים לצרכן ריבית קבועה | G12: ישראל | H12: ישראל | I12: TASE | J12: NR | K12: NR | L12: ILS | M12: 6.681 | N12: 30/04/2032 | O12: 0.013 | P12: 0.0438 | Q12: 0 | R12: 6000000 | S12: 1 | T12: 82.78 | U12: 4966.8 | W12: שווי הוגן | X12: 0.0001733631 | Y12: 0.01217432 | Z12: 0.0012101334
A13: 13908 | B13: 13909 | C13: מדינת ישראל | D13: ממשל שקלית 1152 | E13: IL0011840761 | F13: לא צמוד למדד המחירים לצרכן ריבית קבועה | G13: ישראל | H13: ישראל | I13: TASE | J13: NR | K13: NR | L13: ILS | M13: 17.432 | N13: 29/11/2052 | O13: 0.028 | P13: 0.0494 | Q13: 0 | R13: 300000 | S13: 1 | T13: 68.95 | U13: 206.85 | W13: שווי הוגן | X13: 1.2954577e-05 | Y13: 0.00050701824 | Z13: 5.0397862e-05
... A18: 13908 | B18: 13909 | C18: מדינת ישראל | D18: ממשל צמודה 1033 | E18: IL0012043795 | F18: צמוד למדד המחירים לצרכן בריבית קבועה | G18: ישראל | H18: ישראל | I18: TASE | J18: NR | K18: NR | L18: ILS | M18: 8.028 | N18: 31/10/2033 | O18: 0.016 | P18: 0.021 | Q18: 0 | R18: 14429000 | S18: 1 | T18: 100.49 | U18: 14499.702 | W18: שווי הוגן | X18: 0.00071543051 | Y18: 0.035540795 | Z18: 0.0035327724
A19: 13908 | B19: 13909 | C19: STATE OF ISRAEL | D19: ISRAEL 6.5 31 | E19: XS2715285230 | F19: נקוב במט"ח | G19: חו"ל | H19: ישראל | I19: LSE | J19: A2 | K19: Moodys | L19: USD | M19: 5.37 | N19: 48010 | O19: 0.065 | P19: 0.05395 | Q19: 0 | R19: 100000 | S19: 3.718 | T19: 108.7112 | U19: 404.18824 | W19: שווי הוגן | X19: 6.6666667e-05 | Y19: 0.00099072182 | Z19: 9.8478235e-05
A20: 13908 | B20: 13909 | C20: STATE OF ISRAEL | D20: ISRAEL 5.75 54 | E20: US46514BRM18 | F20: נקוב במט"ח | G20: חו"ל | H20: ישראל | I20: NR | J20: A2 | K20: Moodys | L20: USD | M20: 13.788 | N20: 56586 | O20: 0.0575 | P20: 0.06361 | Q20: 0 | R20: 600000 | S20: 3.718 | T20: 92.2754 | U20: 2058.4796 | W20: שווי הוגן | X20: 0.0002 | Y20: 0.005045621 | Z20: 0.00050153721
A21: 13908 | B21: 13909 | C21: STATE OF ISRAEL | D21: ISRAEL 5.5 34 | E21: US46514BRL35 | F21: נקוב במט"ח | G21: חו"ל | H21: ישראל | I21: NR | J21: A2 | K21: Moodys | L21: USD | M21: 7.153 | N21: 49281 | O21: 0.055 | P21: 0.05617 | Q21: 0 | R21: 2229000 | S21: 3.718 | T21: 99.4856 | U21: 8244.7915 | W21: שווי הוגן | X21: 0.000743 | Y21: 0.020209135 | Z21: 0.002008798
A22: 13908 | B22: 13909 | C22: STATE OF ISRAEL | D22: ISRAEL 5.375 29 | E22: US46514BRN90 | F22: נקוב במט"ח | G22: חו"ל | H22: ישראל | I22: NR | J22: A2 | K22: Moodys | L22: USD | M22: 3.598 | N22: 47455 | O22: 0.05375 | P22: 0.05129 | Q22: 0 | R22: 633000 | S22: 3.718 | T22: 101.1626 | U22: 2380.8557 | W22: שווי הוגן | X22: 0.0003165 | Y22: 0.0058358099 | Z22: 0.00058008237
A23: 13908 | B23: 13909 | C23: STATE OF ISRAEL | D23: ISRAEL 5.625 2/35 | E23: US46514Y8B63 | F23: נקוב במט"ח | G23: חו"ל | H23: ישראל | I23: LSE | J23: Baa1 | K23: Moodys | L23: USD | M23: 7.655 | N23: 19/02/2035 | O23: 0.05625 | P23: 0.05703 | Q23: 0 | R23: 5863000 | S23: 3.718 | T23: 100.0819 | U23: 21816.487 | W23: שווי הוגן | X23: 0.0023452 | Y23: 0.053475257 | Z23: 0.0053154668
A24: 13908 | B24: 13910 | C24: מדינת ישראל | D24: ממשל שקלית 0142 | E24: IL0011254005 | F24: לא צמוד למדד המחירים לצרכן ריבית קבועה | G24: ישראל | H24: ישראל | I24: TASE | J24: NR | K24: NR | L24: ILS | M24: 11.556 | N24: 31/01/2042 | O24: 0.055 | P24: 0.0473 | Q24: 0 | R24: 300000 | S24: 1 | T24: 109.69 | U24: 329.07 | W24: שווי הוגן | X24: 1.1053939e-05 | Y24: 0.0013655706 | Z24: 0.00017501462
A25: 13908 | B25: 13910 | C25: מדינת ישראל | D25: ממשל צמודה 1025 | E25: IL0011359127 | F25: צמוד למדד המחירים לצרכן בריבית קבועה | G25: ישראל | H25: ישראל | I25: TASE | J25: NR | K25: NR | L25: ILS | M25: 0.584 | N25: 31/10/2025 | O25: 0.0075 | P25: 0.0124 | Q25: 0 | R25: 18111670 | S25: 1 | T25: 116.16 | U25: 21038.516 | W25: שווי הוגן | X25: 0.00083453426 | Y25: 0.08730537 | Z25: 0.011189254
A26: 13908 | B26: 13910 | C26: מדינת ישראל | D26: ממשל שקלית 0327 | E26: IL0011393449 | F26: לא צמוד למדד המחירים לצרכן ריבית קבועה | G26: ישראל | H26: ישראל | I26: TASE | J26: NR | K26: NR | L26: ILS | M26: 1.977 | N26: 31/03/2027 | O26: 0.02 | P26: 0.0422 | Q26: 0 | R26: 5256000 | S26: 1 | T26: 95.83 | U26: 5036.8248 | W26: שווי הוגן | X26: 0.0001861955 | Y26: 0.020901753 | Z26: 0.0026788159
A27: 13908 | B27: 13910 | C27: מדינת ישראל | D27: ממשל שקלית 0347 | E27: IL0011401937 | F27: לא צמוד למדד המחירים לצרכן ריבית קבועה | G27: ישראל | H27: ישראל | I27: TASE | J27: NR | K27: NR | L27: ILS | M27: 14.743 | N27: 31/03/2047 | O27: 0.0375 | P27: 0.0486 | Q27: 0 | R27: 3380897 | S27: 1 | T27: 85.21 | U27: 2880.8623 | W27: שווי הוגן | X27: 0.00012881401 | Y27: 0.011954966 | Z27: 0.0015321756
A28: 13908 | B28: 13910 | C28: מדינת ישראל | D28: ממשל צמודה 0527 | E28: IL0011408478 | F28: צמוד למדד המחירים לצרכן בריבית קבועה | G28: ישראל | H28: ישראל | I28: TASE | J28: NR | K28: NR | L28: ILS | M28: 2.142 | N28: 31/05/2027 | O28: 0.0075 | P28: 0.0194 | Q28: 0 | R28: 20461660 | S28: 1 | T28: 114.63 | U28: 23455.201 | W28: שווי הוגן | X28: 0.00084009175 | Y28: 0.097334099 | Z28: 0.012474558
A29: 13908 | B29: 13910 | C29: מדינת ישראל | D29: ממשל שקלית 0928 | E29: IL0011508798 | F29: לא צמוד למדד המחירים לצרכן ריבית קבועה | G29: ישראל | H29: ישראל | I29: TASE | J29: NR | K29: NR | L29: ILS | M29: 3.36 | N29: 28/09/2028 | O29: 0.0225 | P29: 0.0426 | Q29: 0 | R29: 15536870 | S29: 1 | T29: 94.71 | U29: 14714.97 | W29: שווי הוגן | X29: 0.0004474709 | Y29: 0.061063997 | Z29: 0.0078261
A30: 13908 | B30: 13910 | C30: מדינת ישראל | D30: ממשל צמודה 0529 | E30: IL0011570236 | F30: צמוד למדד המחירים לצרכן בריבית קבועה | G30: ישראל | H30: ישראל | I30: TASE | J30: NR | K30: NR | L30: ILS | M30: 4.115 | N30: 31/05/2029 | O30: 0.005 | P30: 0.0197 | Q30: 0 | R30: 4869210 | S30: 1 | T30: 109.42 | U30: 5327.8896 | W30: שווי הוגן | X30: 0.00017714033 | Y30: 0.02210961 | Z30: 0.0028336176
A31: 13908 | B31: 13910 | C31: מדינת ישראל | D31: ממשל שקלית 0330 | E31: IL0011609851 | F31: לא צמוד למדד המחירים לצרכן ריבית קבועה | G31: ישראל | H31: ישראל | I31: TASE | J31: NR | K31: NR | L31: ILS | M31: 4.892 | N31: 31/03/2030 | O31: 0.01 | P31: 0.0429 | Q31: 0 | R31: 665765 | S31: 1 | T31: 85.48 | U31: 569.09592 | W31: שווי הוגן | X31: 1.7633613e-05 | Y31: 0.0023616271 | Z31: 0.00030267148
A32: 13908 | B32: 13910 | C32: מדינת ישראל | D32: ממשל שקלית 0537 | E32: IL0011661803 | F32: לא צמוד למדד המחירים לצרכן ריבית קבועה | G32: ישראל | H32: ישראל | I32: TASE | J32: NR | K32: NR | L32: ILS | M32: 10.807 | N32: 31/05/2037 | O32: 0.015 | P32: 0.0461 | Q32: 0 | R32: 9800000 | S32: 1 | T32: 72.72 | U32: 7126.56 | W32: שווי הוגן | X32: 0.00030000744 | Y32: 0.02957371 | Z32: 0.0037902336
A33: 13908 | B33: 13910 | C33: מדינת ישראל | D33: ממשל צמודה 0726 | E33: IL0011695645 | F33: צמוד למדד המחירים לצרכן בריבית קבועה | G33: ישראל | H33: ישראל | I33: TASE | J33: NR | K33: NR | L33: ILS | M33: 1.33 | N33: 31/07/2026 | O33: 0.001 | P33: 0.0196 | Q33: 0 | R33: 24047400 | S33: 1 | T33: 112.95 | U33: 27161.538 | W33: שווי הוגן | X33: 0.0011901964 | Y33: 0.11271461 | Z33: 0.01444576
A34: 13908 | B34: 13910 | C34: מדינת ישראל | D34: ממשל צמודה 1131 | E34: IL0011722209 | F34: צמוד למדד המחירים לצרכן בריבית קבועה | G34: ישראל | H34: ישראל | I34: TASE | J34: NR | K34: NR | L34: ILS | M34: 6.646 | N34: 30/11/2031 | O34: 0.001 | P34: 0.0203 | Q34: 0 | R34: 16340000 | S34: 1 | T34: 101.91 | U34: 16652.094 | W34: שווי הוגן | X34: 0.00053217686 | Y34: 0.069102651 | Z34: 0.0088563522
... A41: 13908 | B41: 13910 | C41: מדינת ישראל | D41: ממשל צמודה 1033 | E41: IL0012043795 | F41: צמוד למדד המחירים לצרכן בריבית קבועה | G41: ישראל | H41: ישראל | I41: TASE | J41: NR | K41: NR | L41: ILS | M41: 8.028 | N41: 31/10/2033 | O41: 0.016 | P41: 0.021 | Q41: 0 | R41: 13535000 | S41: 1 | T41: 100.49 | U41: 13601.322 | W41: שווי הוגן | X41: 0.00067110347 | Y41: 0.056442594 | Z41: 0.0072338106
A42: 13908 | B42: 13910 | C42: STATE OF ISRAEL | D42: ISRAEL 6.5 31 | E42: XS2715285230 | F42: נקוב במט"ח | G42: חו"ל | H42: ישראל | I42: LSE | J42: A2 | K42: Moodys | L42: USD | M42: 5.37 | N42: 48010 | O42: 0.065 | P42: 0.05395 | Q42: 0 | R42: 180000 | S42: 3.718 | T42: 108.7112 | U42: 727.53883 | W42: שווי הוגן | X42: 0.00012 | Y42: 0.0030191315 | Z42: 0.00038693873
A43: 13908 | B43: 13910 | C43: STATE OF ISRAEL | D43: ISRAEL 5.75 54 | E43: US46514BRM18 | F43: נקוב במט"ח | G43: חו"ל | H43: ישראל | I43: NR | J43: A2 | K43: Moodys | L43: USD | M43: 13.788 | N43: 56586 | O43: 0.0575 | P43: 0.06361 | Q43: 0 | R43: 400000 | S43: 3.718 | T43: 92.2754 | U43: 1372.3198 | W43: שווי הוגן | X43: 0.00013333333 | Y43: 0.0056948353 | Z43: 0.00072986299
A44: 13908 | B44: 13910 | C44: STATE OF ISRAEL | D44: ISRAEL 5.5 34 | E44: US46514BRL35 | F44: נקוב במט"ח | G44: חו"ל | H44: ישראל | I44: NR | J44: A2 | K44: Moodys | L44: USD | M44: 7.153 | N44: 49281 | O44: 0.055 | P44: 0.05617 | Q44: 0 | R44: 900000 | S44: 3.718 | T44: 99.4856 | U44: 3328.9871 | W44: שווי הוגן | X44: 0.0003 | Y44: 0.013814589 | Z44: 0.001770509
A45: 13908 | B45: 13910 | C45: STATE OF ISRAEL | D45: ISRAEL 5.375 29 | E45: US46514BRN90 | F45: נקוב במט"ח | G45: חו"ל | H45: ישראל | I45: NR | J45: A2 | K45: Moodys | L45: USD | M45: 3.598 | N45: 47455 | O45: 0.05375 | P45: 0.05129 | Q45: 0 | R45: 313000 | S45: 3.718 | T45: 101.1626 | U45: 1177.2636 | W45: שווי הוגן | X45: 0.0001565 | Y45: 0.0048853936 | Z45: 0.00062612311
A46: 13908 | B46: 13910 | C46: STATE OF ISRAEL | D46: ISRAEL 5.625 2/35 | E46: US46514Y8B63 | F46: נקוב במט"ח | G46: חו"ל | H46: ישראל | I46: LSE | J46: Baa1 | K46: Moodys | L46: USD | M46: 7.655 | N46: 19/02/2035 | O46: 0.05625 | P46: 0.05703 | Q46: 0 | R46: 3688000 | S46: 3.718 | T46: 100.0819 | U46: 13723.214 | W46: שווי הוגן | X46: 0.0014752 | Y46: 0.056948422 | Z46: 0.0072986387
A47: 13908 | B47: 13911 | C47: מדינת ישראל | D47: ממשל שקלית 0142 | E47: IL0011254005 | F47: לא צמוד למדד המחירים לצרכן ריבית קבועה | G47: ישראל | H47: ישראל | I47: TASE | J47: NR | K47: NR | L47: ILS | M47: 11.556 | N47: 31/01/2042 | O47: 0.055 | P47: 0.0473 | Q47: 0 | R47: 1750000 | S47: 1 | T47: 109.69 | U47: 1919.575 | W47: שווי הוגן | X47: 6.448131e-05 | Y47: 0.014860825 | Z47: 0.0032111644
A48: 13908 | B48: 13911 | C48: מדינת ישראל | D48: ממשל צמודה 1025 | E48: IL0011359127 | F48: צמוד למדד המחירים לצרכן בריבית קבועה | G48: ישראל | H48: ישראל | I48: TASE | J48: NR | K48: NR | L48: ILS | M48: 0.584 | N48: 31/10/2025 | O48: 0.0075 | P48: 0.0124 | Q48: 0 | R48: 7654972 | S48: 1 | T48: 116.16 | U48: 8892.0155 | W48: שווי הוגן | X48: 0.00035271935 | Y48: 0.068839552 | Z48: 0.014875024
A49: 13908 | B49: 13911 | C49: מדינת ישראל | D49: ממשל שקלית 0327 | E49: IL0011393449 | F49: לא צמוד למדד המחירים לצרכן ריבית קבועה | G49: ישראל | H49: ישראל | I49: TASE | J49: NR | K49: NR | L49: ILS | M49: 1.977 | N49: 31/03/2027 | O49: 0.02 | P49: 0.0422 | Q49: 0 | R49: 3048450 | S49: 1 | T49: 95.83 | U49: 2921.3296 | W49: שווי הוגן | X49: 0.00010799233 | Y49: 0.022616135 | Z49: 0.0048869513
A50: 13908 | B50: 13911 | C50: מדינת ישראל | D50: ממשל שקלית 0347 | E50: IL0011401937 | F50: לא צמוד למדד המחירים לצרכן ריבית קבועה | G50: ישראל | H50: ישראל | I50: TASE | J50: NR | K50: NR | L50: ILS | M50: 14.743 | N50: 31/03/2047 | O50: 0.0375 | P50: 0.0486 | Q50: 0 | R50: 1000000 | S50: 1 | T50: 85.21 | U50: 852.1 | W50: שווי הוגן | X50: 3.8100544e-05 | Y50: 0.0065967251 | Z50: 0.001425437
A51: 13908 | B51: 13911 | C51: מדינת ישראל | D51: ממשל צמודה 0527 | E51: IL0011408478 | F51: צמוד למדד המחירים לצרכן בריבית קבועה | G51: ישראל | H51: ישראל | I51: TASE | J51: NR | K51: NR | L51: ILS | M51: 2.142 | N51: 31/05/2027 | O51: 0.0075 | P51: 0.0194 | Q51: 0 | R51: 9000064 | S51: 1 | T51: 114.63 | U51: 10316.773 | W51: שווי הוגן | X51: 0.00036951447 | Y51: 0.079869638 | Z51: 0.017258432
A52: 13908 | B52: 13911 | C52: מדינת ישראל | D52: ממשל שקלית 0928 | E52: IL0011508798 | F52: לא צמוד למדד המחירים לצרכן ריבית קבועה | G52: ישראל | H52: ישראל | I52: TASE | J52: NR | K52: NR | L52: ILS | M52: 3.36 | N52: 28/09/2028 | O52: 0.0225 | P52: 0.0426 | Q52: 0 | R52: 4924450 | S52: 1 | T52: 94.71 | U52: 4663.9466 | W52: שווי הוגן | X52: 0.00014182703 | Y52: 0.036106999 | Z52: 0.0078020911
A53: 13908 | B53: 13911 | C53: מדינת ישראל | D53: ממשל צמודה 0529 | E53: IL0011570236 | F53: צמוד למדד המחירים לצרכן בריבית קבועה | G53: ישראל | H53: ישראל | I53: TASE | J53: NR | K53: NR | L53: ILS | M53: 4.115 | N53: 31/05/2029 | O53: 0.005 | P53: 0.0197 | Q53: 0 | R53: 3690066 | S53: 1 | T53: 109.42 | U53: 4037.6702 | W53: שווי הוגן | X53: 0.00013424344 | Y53: 0.031258539 | Z53: 0.0067544236
A54: 13908 | B54: 13911 | C54: מדינת ישראל | D54: ממשל שקלית 0425 | E54: IL0011626681 | F54: לא צמוד למדד המחירים לצרכן ריבית קבועה | G54: ישראל | H54: ישראל | I54: TASE | J54: NR | K54: NR | L54: ILS | M54: 0.079 | N54: 30/04/2025 | O54: 0.005 | P54: 0.0436 | Q54: 0 | R54: 1101333 | S54: 1 | T54: 100.16 | U54: 1103.0951 | W54: שווי הוגן | X54: 0.0001091126 | Y54: 0.0085398608 | Z54: 0.0018453146
A55: 13908 | B55: 13911 | C55: מדינת ישראל | D55: ממשל שקלית 0537 | E55: IL0011661803 | F55: לא צמוד למדד המחירים לצרכן ריבית קבועה | G55: ישראל | H55: ישראל | I55: TASE | J55: NR | K55: NR | L55: ILS | M55: 10.807 | N55: 31/05/2037 | O55: 0.015 | P55: 0.0461 | Q55: 0 | R55: 1900484 | S55: 1 | T55: 72.72 | U55: 1382.032 | W55: שווי הוגן | X55: 5.8179524e-05 | Y55: 0.010699313 | Z55: 0.0023119346
A56: 13908 | B56: 13911 | C56: מדינת ישראל | D56: ממשל צמודה 0726 | E56: IL0011695645 | F56: צמוד למדד המחירים לצרכן בריבית קבועה | G56: ישראל | H56: ישראל | I56: TASE | J56: NR | K56: NR | L56: ILS | M56: 1.33 | N56: 31/07/2026 | O56: 0.001 | P56: 0.0196 | Q56: 0 | R56: 9948235 | S56: 1 | T56: 112.95 | U56: 11236.531 | W56: שווי הוגן | X56: 0.00049237561 | Y56: 0.086990153 | Z56: 0.018797051
A57: 13908 | B57: 13911 | C57: מדינת ישראל | D57: ממשל צמודה 1131 | E57: IL0011722209 | F57: צמוד למדד המחירים לצרכן בריבית קבועה | G57: ישראל | H57: ישראל | I57: TASE | J57: NR | K57: NR | L57: ILS | M57: 6.646 | N57: 30/11/2031 | O57: 0.001 | P57: 0.0203 | Q57: 0 | R57: 16428433 | S57: 1 | T57: 101.91 | U57: 16742.216 | W57: שווי הוגן | X57: 0.00053505704 | Y57: 0.12961366 | Z57: 0.028007245
... A63: 13908 | B63: 13911 | C63: מדינת ישראל | D63: ממשל צמודה 1033 | E63: IL0012043795 | F63: צמוד למדד המחירים לצרכן בריבית קבועה | G63: ישראל | H63: ישראל | I63: TASE | J63: NR | K63: NR | L63: ILS | M63: 8.028 | N63: 31/10/2033 | O63: 0.016 | P63: 0.021 | Q63: 0 | R63: 6252461 | S63: 1 | T63: 100.49 | U63: 6283.0981 | W63: שווי הוגן | X63: 0.00031001465 | Y63: 0.048642027 | Z63: 0.010510691
A64: 13908 | B64: 13911 | C64: STATE OF ISRAEL | D64: ISRAEL 6.5 31 | E64: XS2715285230 | F64: נקוב במט"ח | G64: חו"ל | H64: ישראל | I64: LSE | J64: A2 | K64: Moodys | L64: USD | M64: 5.37 | N64: 48010 | O64: 0.065 | P64: 0.05395 | Q64: 0 | R64: 68000 | S64: 3.718 | T64: 108.7112 | U64: 274.848 | W64: שווי הוגן | X64: 4.5333333e-05 | Y64: 0.002127798 | Z64: 0.00045977995
A65: 13908 | B65: 13911 | C65: STATE OF ISRAEL | D65: ISRAEL 5.75 54 | E65: US46514BRM18 | F65: נקוב במט"ח | G65: חו"ל | H65: ישראל | I65: NR | J65: A2 | K65: Moodys | L65: USD | M65: 13.788 | N65: 56586 | O65: 0.0575 | P65: 0.06361 | Q65: 0 | R65: 100000 | S65: 3.718 | T65: 92.2754 | U65: 343.07994 | W65: שווי הוגן | X65: 3.3333333e-05 | Y65: 0.0026560311 | Z65: 0.00057392187
A66: 13908 | B66: 13911 | C66: STATE OF ISRAEL | D66: ISRAEL 5.5 34 | E66: US46514BRL35 | F66: נקוב במט"ח | G66: חו"ל | H66: ישראל | I66: NR | J66: A2 | K66: Moodys | L66: USD | M66: 7.153 | N66: 49281 | O66: 0.055 | P66: 0.05617 | Q66: 0 | R66: 350000 | S66: 3.718 | T66: 99.4856 | U66: 1294.6061 | W66: שווי הוגן | X66: 0.00011666667 | Y66: 0.010022486 | Z66: 0.0021656841
A67: 13908 | B67: 13911 | C67: STATE OF ISRAEL | D67: ISRAEL 5.375 29 | E67: US46514BRN90 | F67: נקוב במט"ח | G67: חו"ל | H67: ישראל | I67: NR | J67: A2 | K67: Moodys | L67: USD | M67: 3.598 | N67: 47455 | O67: 0.05375 | P67: 0.05129 | Q67: 0 | R67: 150000 | S67: 3.718 | T67: 101.1626 | U67: 564.18382 | W67: שווי הוגן | X67: 7.5e-05 | Y67: 0.0043677568 | Z67: 0.00094379588
A68: 13908 | B68: 13911 | C68: STATE OF ISRAEL | D68: ISRAEL 5.625 2/35 | E68: US46514Y8B63 | F68: נקוב במט"ח | G68: חו"ל | H68: ישראל | I68: LSE | J68: Baa1 | K68: Moodys | L68: USD | M68: 7.655 | N68: 19/02/2035 | O68: 0.05625 | P68: 0.05703 | Q68: 0 | R68: 926000 | S68: 3.718 | T68: 100.0819 | U68: 3445.6877 | W68: שווי הוגן | X68: 0.0003704 | Y68: 0.026675572 | Z68: 0.0057641247
A69: 13908 | B69: 13912 | C69: מדינת ישראל | D69: ממשל צמודה 1025 | E69: IL0011359127 | F69: צמוד למדד המחירים לצרכן בריבית קבועה | G69: ישראל | H69: ישראל | I69: TASE | J69: NR | K69: NR | L69: ILS | M69: 0.584 | N69: 31/10/2025 | O69: 0.0075 | P69: 0.0124 | Q69: 0 | R69: 10315000 | S69: 1 | T69: 116.16 | U69: 11981.904 | W69: שווי הוגן | X69: 0.00047528588 | Y69: 0.024567245 | Z69: 0.004932916
A70: 13908 | B70: 13912 | C70: מדינת ישראל | D70: ממשל שקלית 0327 | E70: IL0011393449 | F70: לא צמוד למדד המחירים לצרכן ריבית קבועה | G70: ישראל | H70: ישראל | I70: TASE | J70: NR | K70: NR | L70: ILS | M70: 1.977 | N70: 31/03/2027 | O70: 0.02 | P70: 0.0422 | Q70: 0 | R70: 54700000 | S70: 1 | T70: 95.83 | U70: 52419.01 | W70: שווי הוגן | X70: 0.0019377652 | Y70: 0.10747797 | Z70: 0.021580758
A71: 13908 | B71: 13912 | C71: מדינת ישראל | D71: ממשל צמודה 0726 | E71: IL0011695645 | F71: צמוד למדד המחירים לצרכן בריבית קבועה | G71: ישראל | H71: ישראל | I71: TASE | J71: NR | K71: NR | L71: ILS | M71: 1.33 | N71: 31/07/2026 | O71: 0.001 | P71: 0.0196 | Q71: 0 | R71: 4000000 | S71: 1 | T71: 112.95 | U71: 4518 | W71: שווי הוגן | X71: 0.00019797506 | Y71: 0.0092635372 | Z71: 0.0018600478
A72: 13908 | B72: 13912 | C72: מדינת ישראל | D72: ממשל שקלית 0927 | E72: IL0012035791 | F72: לא צמוד למדד המחירים לצרכן ריבית קבועה | G72: ישראל | H72: ישראל | I72: TASE | J72: NR | K72: NR | L72: ILS | M72: 2.391 | N72: 30/09/2027 | O72: 0.0375 | P72: 0.0426 | Q72: 0 | R72: 58540248 | S72: 1 | T72: 100.68 | U72: 58938.322 | W72: שווי הוגן | X72: 0.0019718411 | Y72: 0.12084492 | Z72: 0.02426474
A73: 13908 | B73: 13912 | C73: מדינת ישראל | D73: ממשל קצרה 11/25 | E73: IL0012153263 | F73: לא צמוד למדד המחירים לצרכן ריבית קבועה | G73: ישראל | H73: ישראל | I73: TASE | J73: NR | K73: NR | L73: ILS | M73: 0.666 | N73: 30/11/2025 | O73: 0 | P73: 0.0424 | Q73: 0 | R73: 49324000 | S73: 1 | T73: 97.27 | U73: 47977.455 | W73: שווי הוגן | X73: 0.0077755648 | Y73: 0.098371168 | Z73: 0.019752183
A74: 13908 | B74: 13912 | C74: בנק ישראל | D74: מ.ק.מ. 415 | E74: IL0082504171 | F74: מק"מ קצר משנים עשר חודשים | G74: ישראל | H74: ישראל | I74: TASE | J74: NR | K74: NR | L74: ILS | M74: 0 | N74: 45749 | O74: 0 | P74: 0.1157 | Q74: 0 | R74: 41600000 | S74: 1 | T74: 99.97 | U74: 41587.52 | W74: שווי הוגן | X74: 0.0011885714 | Y74: 0.085269486 | Z74: 0.017121464
A75: 13908 | B75: 13912 | C75: בנק ישראל | D75: מ.ק.מ. 615 | E75: IL0082506150 | F75: מק"מ קצר משנים עשר חודשים | G75: ישראל | H75: ישראל | I75: TASE | J75: NR | K75: NR | L75: ILS | M75: 0.18 | N75: 45812 | O75: 0 | P75: 0.0433 | Q75: 0 | R75: 2669971 | S75: 1 | T75: 99.26 | U75: 2650.2132 | W75: שווי הוגן | X75: 8.8999033e-05 | Y75: 0.0054338975 | Z75: 0.0010910853
A76: 13908 | B76: 13912 | C76: בנק ישראל | D76: מ.ק.מ. 715 | E76: IL0082507141 | F76: מק"מ קצר משנים עשר חודשים | G76: ישראל | H76: ישראל | I76: TASE | J76: NR | K76: NR | L76: ILS | M76: 0.25 | N76: 45840 | O76: 0 | P76: 0.0428 | Q76: 0 | R76: 1843628 | S76: 1 | T76: 98.95 | U76: 1824.2699 | W76: שווי הוגן | X76: 0.00015363567 | Y76: 0.0037404144 | Z76: 0.00075104677
A77: 13908 | B77: 13912 | C77: בנק ישראל | D77: מ.ק.מ. 815 | E77: IL0082508131 | F77: מק"מ קצר משנים עשר חודשים | G77: ישראל | H77: ישראל | I77: TASE | J77: NR | K77: NR | L77: ILS | M77: 0.35 | N77: 45875 | O77: 0 | P77: 0.0429 | Q77: 0 | R77: 48555000 | S77: 1 | T77: 98.55 | U77: 47850.952 | W77: שווי הוגן | X77: 0.00404625 | Y77: 0.098111793 | Z77: 0.019700102
A78: 13908 | B78: 13912 | C78: בנק ישראל | D78: מ.ק.מ. 915 | E78: IL0082509121 | F78: מק"מ קצר משנים עשר חודשים | G78: ישראל | H78: ישראל | I78: TASE | J78: NR | K78: NR | L78: ILS | M78: 0.42 | N78: 45903 | O78: 0 | P78: 0.0427 | Q78: 0 | R78: 1500000 | S78: 1 | T78: 98.24 | U78: 1473.6 | W78: שווי הוגן | X78: 0.000125 | Y78: 0.003021414 | Z78: 0.00060667696
A79: 13908 | B79: 13912 | C79: בנק ישראל | D79: מ.ק.מ. 1015 | E79: IL0082510194 | F79: מק"מ קצר משנים עשר חודשים | G79: ישראל | H79: ישראל | I79: TASE | J79: NR | K79: NR | L79: ILS | M79: 0.51 | N79: 45933 | O79: 0 | P79: 0.0428 | Q79: 0 | R79: 26100000 | S79: 1 | T79: 97.9 | U79: 25551.9 | W79: שווי הוגן | X79: 0.0018642857 | Y79: 0.052390654 | Z79: 0.010519645
A80: 13908 | B80: 13912 | C80: בנק ישראל | D80: מ.ק.מ. 1215 | E80: IL0082512174 | F80: מק"מ קצר משנים עשר חודשים | G80: ישראל | H80: ישראל | I80: TASE | J80: NR | K80: NR | L80: ILS | M80: 0.67 | N80: 45994 | O80: 0 | P80: 0.0424 | Q80: 0 | R80: 39000000 | S80: 1 | T80: 97.24 | U80: 37923.6 | W80: שווי הוגן | X80: 0.0027857143 | Y80: 0.077757123 | Z80: 0.015613039
A81: 13908 | B81: 13912 | C81: בנק ישראל | D81: מ.ק.מ. 116 | E81: IL0082601191 | F81: מק"מ קצר משנים עשר חודשים | G81: ישראל | H81: ישראל | I81: TASE | J81: NR | K81: NR | L81: ILS | M81: 0.77 | N81: 46204 | O81: 0 | P81: 0.0426 | Q81: 0 | R81: 68264000 | S81: 1 | T81: 96.84 | U81: 66106.858 | W81: שווי הוגן | X81: 0.0042665 | Y81: 0.13554301 | Z81: 0.027216006
A82: 13908 | B82: 13912 | C82: בנק ישראל | D82: מ.ק.מ 216 | E82: IL0082602181 | F82: מק"מ קצר משנים עשר חודשים | G82: ישראל | H82: ישראל | I82: TASE | J82: NR | K82: NR | L82: ILS | M82: 0.85 | N82: 46114 | O82: 0 | P82: 0.0426 | Q82: 0 | R82: 40200000 | S82: 1 | T82: 96.53 | U82: 38805.06 | W82: שווי הוגן | X82: 0.0022333333 | Y82: 0.079564435 | Z82: 0.015975934
A83: 13908 | B83: 13912 | C83: בנק ישראל | D83: מ.ק.מ. 316 | E83: IL0082603171 | F83: מק"מ קצר משנים עשר חודשים | G83: ישראל | H83: ישראל | I83: TASE | J83: NR | K83: NR | L83: ILS | M83: 0.92 | N83: 46115 | O83: 0 | P83: 0.0426 | Q83: 0 | R83: 50000000 | S83: 1 | T83: 96.22 | U83: 48110 | W83: שווי הוגן | X83: 0.0027777778 | Y83: 0.098642934 | Z83: 0.019806751
A84: 13908 | B84: 13913 | C84: מדינת ישראל | D84: ממשל שקלית 0825 | E84: IL0011355570 | F84: לא צמוד למדד המחירים לצרכן ריבית קבועה | G84: ישראל | H84: ישראל | I84: TASE | J84: NR | K84: NR | L84: ILS | M84: 0.416 | N84: 31/08/2025 | O84: 0.0175 | P84: 0.0399 | Q84: 0 | R84: 150000 | S84: 1 | T84: 100.11 | U84: 150.165 | W84: שווי הוגן | X84: 1.0544162e-05 | Y84: 0.036414143 | Z84: 0.005689712
A85: 13908 | B85: 13913 | C85: מדינת ישראל | D85: ממשל צמודה 1025 | E85: IL0011359127 | F85: צמוד למדד המחירים לצרכן בריבית קבועה | G85: ישראל | H85: ישראל | I85: TASE | J85: NR | K85: NR | L85: ILS | M85: 0.584 | N85: 31/10/2025 | O85: 0.0075 | P85: 0.0124 | Q85: 0 | R85: 216500 | S85: 1 | T85: 116.16 | U85: 251.4864 | W85: שווי הוגן | X85: 9.9757045e-06 | Y85: 0.060983996 | Z85: 0.009528753
A86: 13908 | B86: 13913 | C86: מדינת ישראל | D86: ממשל שקלית 0327 | E86: IL0011393449 | F86: לא צמוד למדד המחירים לצרכן ריבית קבועה | G86: ישראל | H86: ישראל | I86: TASE | J86: NR | K86: NR | L86: ILS | M86: 1.977 | N86: 31/03/2027 | O86: 0.02 | P86: 0.0422 | Q86: 0 | R86: 158800 | S86: 1 | T86: 95.83 | U86: 152.17804 | W86: שווי הוגן | X86: 5.6255413e-06 | Y86: 0.036902294 | Z86: 0.0057659856
A87: 13908 | B87: 13913 | C87: מדינת ישראל | D87: ממשל צמודה 0527 | E87: IL0011408478 | F87: צמוד למדד המחירים לצרכן בריבית קבועה | G87: ישראל | H87: ישראל | I87: TASE | J87: NR | K87: NR | L87: ILS | M87: 2.142 | N87: 31/05/2027 | O87: 0.0075 | P87: 0.0194 | Q87: 0 | R87: 554000 | S87: 1 | T87: 114.63 | U87: 635.0502 | W87: שווי הוגן | X87: 2.2745507e-05 | Y87: 0.153996 | Z87: 0.024061884
A88: 13908 | B88: 13913 | C88: מדינת ישראל | D88: ממשל שקלית 0928 | E88: IL0011508798 | F88: לא צמוד למדד המחירים לצרכן ריבית קבועה | G88: ישראל | H88: ישראל | I88: TASE | J88: NR | K88: NR | L88: ILS | M88: 3.36 | N88: 28/09/2028 | O88: 0.0225 | P88: 0.0426 | Q88: 0 | R88: 247920 | S88: 1 | T88: 94.71 | U88: 234.80503 | W88: שווי הוגן | X88: 7.1402404e-06 | Y88: 0.056938861 | Z88: 0.0088967003
A89: 13908 | B89: 13913 | C89: מדינת ישראל | D89: ממשל צמודה 0529 | E89: IL0011570236 | F89: צמוד למדד המחירים לצרכן בריבית קבועה | G89: ישראל | H89: ישראל | I89: TASE | J89: NR | K89: NR | L89: ILS | M89: 4.115 | N89: 31/05/2029 | O89: 0.005 | P89: 0.0197 | Q89: 0 | R89: 158600 | S89: 1 | T89: 109.42 | U89: 173.54012 | W89: שווי הוגן | X89: 5.7698181e-06 | Y89: 0.042082475 | Z89: 0.0065753891
A90: 13908 | B90: 13913 | C90: מדינת ישראל | D90: ממשל צמודה 0726 | E90: IL0011695645 | F90: צמוד למדד המחירים לצרכן בריבית קבועה | G90: ישראל | H90: ישראל | I90: TASE | J90: NR | K90: NR | L90: ILS | M90: 1.33 | N90: 31/07/2026 | O90: 0.001 | P90: 0.0196 | Q90: 0 | R90: 514000 | S90: 1 | T90: 112.95 | U90: 580.563 | W90: שווי הוגן | X90: 2.5439795e-05 | Y90: 0.14078317 | Z90: 0.021997378
A91: 13908 | B91: 13913 | C91: מדינת ישראל | D91: ממשל צמודה 1131 | E91: IL0011722209 | F91: צמוד למדד המחירים לצרכן בריבית קבועה | G91: ישראל | H91: ישראל | I91: TASE | J91: NR | K91: NR | L91: ILS | M91: 6.646 | N91: 30/11/2031 | O91: 0.001 | P91: 0.0203 | Q91: 0 | R91: 165000 | S91: 1 | T91: 101.91 | U91: 168.1515 | W91: שווי הוגן | X91: 5.373879e-06 | Y91: 0.040775765 | Z91: 0.0063712158
A92: 13908 | B92: 13913 | C92: מדינת ישראל | D92: ממשל שקלית 0229 | E92: IL0011948028 | F92: לא צמוד למדד המחירים לצרכן ריבית קבועה | G92: ישראל | H92: ישראל | I92: TASE | J92: NR | K92: NR | L92: ILS | M92: 3.701 | N92: 28/02/2029 | O92: 0.0375 | P92: 0.0426 | Q92: 0 | R92: 265979 | S92: 1 | T92: 98.49 | U92: 261.96272 | W92: שווי הוגן | X92: 7.5128942e-06 | Y92: 0.063524443 | Z92: 0.009925698
A93: 13908 | B93: 13913 | C93: מדינת ישראל | D93: ממשל צמודה 1028 | E93: IL0011973265 | F93: צמוד למדד המחירים לצרכן בריבית קבועה | G93: ישראל | H93: ישראל | I93: TASE | J93: NR | K93: NR | L93: ILS | M93: 3.52 | N93: 31/10/2028 | O93: 0.011 | P93: 0.0198 | Q93: 0 | R93: 600900 | S93: 1 | T93: 101.93 | U93: 612.49737 | W93: שווי הוגן | X93: 2.0289507e-05 | Y93: 0.14852707 | Z93: 0.023207363
A94: 13908 | B94: 13913 | C94: מדינת ישראל | D94: ממשל שקלית 0335 | E94: IL0012023326 | F94: לא צמוד למדד המחירים לצרכן ריבית קבועה | G94: ישראל | H94: ישראל | I94: TASE | J94: NR | K94: NR | L94: ILS | M94: 8.399 | N94: 30/03/2035 | O94: 0.04 | P94: 0.0448 | Q94: 0 | R94: 535692 | S94: 1 | T94: 96.17 | U94: 515.175 | W94: שווי הוגן | X94: 1.8107921e-05 | Y94: 0.12492696 | Z94: 0.019519844
A95: 13908 | B95: 13913 | C95: מדינת ישראל | D95: ממשל שקלית 0927 | E95: IL0012035791 | F95: לא צמוד למדד המחירים לצרכן ריבית קבועה | G95: ישראל | H95: ישראל | I95: TASE | J95: NR | K95: NR | L95: ILS | M95: 2.391 | N95: 30/09/2027 | O95: 0.0375 | P95: 0.0426 | Q95: 0 | R95: 10000 | S95: 1 | T95: 100.68 | U95: 10.068 | W95: שווי הוגן | X95: 3.368351e-07 | Y95: 0.0024414317 | Z95: 0.00038147385
A96: 13908 | B96: 13913 | C96: מדינת ישראל | D96: ממשל צמודה 1033 | E96: IL0012043795 | F96: צמוד למדד המחירים לצרכן בריבית קבועה | G96: ישראל | H96: ישראל | I96: TASE | J96: NR | K96: NR | L96: ILS | M96: 8.028 | N96: 31/10/2033 | O96: 0.016 | P96: 0.021 | Q96: 0 | R96: 117000 | S96: 1 | T96: 100.49 | U96: 117.5733 | W96: שווי הוגן | X96: 5.8011899e-06 | Y96: 0.028510845 | Z96: 0.0044548212
A97: 13908 | B97: 13913 | C97: STATE OF ISRAEL | D97: ISRAEL 6.5 31 | E97: XS2715285230 | F97: נקוב במט"ח | G97: חו"ל | H97: ישראל | I97: LSE | J97: A2 | K97: Moodys | L97: USD | M97: 5.37 | N97: 48010 | O97: 0.065 | P97: 0.05395 | Q97: 0 | R97: 10000 | S97: 3.718 | T97: 108.7112 | U97: 40.41882 | W97: שווי הוגן | X97: 6.6666667e-06 | Y97: 0.0098013299 | Z97: 0.0015314584
A98: 13908 | B98: 13913 | C98: STATE OF ISRAEL | D98: ISRAEL 5.75 54 | E98: US46514BRM18 | F98: נקוב במט"ח | G98: חו"ל | H98: ישראל | I98: NR | J98: A2 | K98: Moodys | L98: USD | M98: 13.788 | N98: 56586 | O98: 0.0575 | P98: 0.06361 | Q98: 0 | R98: 11000 | S98: 3.718 | T98: 92.2754 | U98: 37.73879 | W98: שווי הוגן | X98: 3.6666667e-06 | Y98: 0.0091514381 | Z98: 0.0014299128
A99: 13908 | B99: 13913 | C99: STATE OF ISRAEL | D99: ISRAEL 5.5 34 | E99: US46514BRL35 | F99: נקוב במט"ח | G99: חו"ל | H99: ישראל | I99: NR | J99: A2 | K99: Moodys | L99: USD | M99: 7.153 | N99: 49281 | O99: 0.055 | P99: 0.05617 | Q99: 0 | R99: 17000 | S99: 3.718 | T99: 99.4856 | U99: 62.88087 | W99: שווי הוגן | X99: 5.6666667e-06 | Y99: 0.015248247 | Z99: 0.0023825395
A100: 13908 | B100: 13913 | C100: STATE OF ISRAEL | D100: ISRAEL 5.375 29 | E100: US46514BRN90 | F100: נקוב במט"ח | G100: חו"ל | H100: ישראל | I100: NR | J100: A2 | K100: Moodys | L100: USD | M100: 3.598 | N100: 47455 | O100: 0.05375 | P100: 0.05129 | Q100: 0 | R100: 12000 | S100: 3.718 | T100: 101.1626 | U100: 45.13471 | W100: שווי הוגן | X100: 6e-06 | Y100: 0.010944906 | Z100: 0.0017101422
A101: 13908 | B101: 13913 | C101: STATE OF ISRAEL | D101: ISRAEL 5.625 2/35 | E101: US46514Y8B63 | F101: נקוב במט"ח | G101: חו"ל | H101: ישראל | I101: LSE | J101: Baa1 | K101: Moodys | L101: USD | M101: 7.655 | N101: 19/02/2035 | O101: 0.05625 | P101: 0.05703 | Q101: 0 | R101: 20000 | S101: 3.718 | T101: 100.0819 | U101: 74.4209 | W101: שווי הוגן | X101: 8e-06 | Y101: 0.018046637 | Z101: 0.0028197882
A102: 13908 | B102: 13914 | C102: בנק ישראל | D102: מ.ק.מ. 415 | E102: IL0082504171 | F102: מק"מ קצר משנים עשר חודשים | G102: ישראל | H102: ישראל | I102: TASE | J102: NR | K102: NR | L102: ILS | M102: 0 | N102: 45749 | O102: 0 | P102: 0.1157 | Q102: 0 | R102: 276575 | S102: 1 | T102: 99.97 | U102: 276.49203 | W102: שווי הוגן | X102: 7.9021429e-06 | Y102: 0.022684387 | Z102: 0.016178434
A103: 13908 | B103: 13914 | C103: בנק ישראל | D103: מ.ק.מ. 715 | E103: IL0082507141 | F103: מק"מ קצר משנים עשר חודשים | G103: ישראל | H103: ישראל | I103: TASE | J103: NR | K103: NR | L103: ILS | M103: 0.25 | N103: 45840 | O103: 0 | P103: 0.0428 | Q103: 0 | R103: 835350 | S103: 1 | T103: 98.95 | U103: 826.57882 | W103: שווי הוגן | X103: 6.96125e-05 | Y103: 0.06781546 | Z103: 0.048365773
A104: 13908 | B104: 13914 | C104: בנק ישראל | D104: מ.ק.מ. 815 | E104: IL0082508131 | F104: מק"מ קצר משנים עשר חודשים | G104: ישראל | H104: ישראל | I104: TASE | J104: NR | K104: NR | L104: ILS | M104: 0.35 | N104: 45875 | O104: 0 | P104: 0.0429 | Q104: 0 | R104: 950660 | S104: 1 | T104: 98.55 | U104: 936.87543 | W104: שווי הוגן | X104: 7.9221667e-05 | Y104: 0.076864585 | Z104: 0.05481958
A105: 13908 | B105: 13914 | C105: בנק ישראל | D105: מ.ק.מ. 915 | E105: IL0082509121 | F105: מק"מ קצר משנים עשר חודשים | G105: ישראל | H105: ישראל | I105: TASE | J105: NR | K105: NR | L105: ILS | M105: 0.42 | N105: 45903 | O105: 0 | P105: 0.0427 | Q105: 0 | R105: 793130 | S105: 1 | T105: 98.24 | U105: 779.17091 | W105: שווי הוגן | X105: 6.6094167e-05 | Y105: 0.063925947 | Z105: 0.045591784
A106: 13908 | B106: 13914 | C106: בנק ישראל | D106: מ.ק.מ. 1015 | E106: IL0082510194 | F106: מק"מ קצר משנים עשר חודשים | G106: ישראל | H106: ישראל | I106: TASE | J106: NR | K106: NR | L106: ILS | M106: 0.51 | N106: 45933 | O106: 0 | P106: 0.0428 | Q106: 0 | R106: 1870000 | S106: 1 | T106: 97.9 | U106: 1830.73 | W106: שווי הוגן | X106: 0.00013357143 | Y106: 0.15019959 | Z106: 0.10712187
A107: 13908 | B107: 13914 | C107: בנק ישראל | D107: מ.ק.מ. 1115 | E107: IL0082511184 | F107: מק"מ קצר משנים עשר חודשים | G107: ישראל | H107: ישראל | I107: TASE | J107: NR | K107: NR | L107: ILS | M107: 0.6 | N107: 45966 | O107: 0 | P107: 0.0426 | Q107: 0 | R107: 2000000 | S107: 1 | T107: 97.54 | U107: 1950.8 | W107: שווי הוגן | X107: 0.00014285714 | Y107: 0.16005055 | Z107: 0.11414755
A108: 13908 | B108: 13914 | C108: בנק ישראל | D108: מ.ק.מ. 1215 | E108: IL0082512174 | F108: מק"מ קצר משנים עשר חודשים | G108: ישראל | H108: ישראל | I108: TASE | J108: NR | K108: NR | L108: ILS | M108: 0.67 | N108: 45994 | O108: 0 | P108: 0.0424 | Q108: 0 | R108: 1163450 | S108: 1 | T108: 97.24 | U108: 1131.3388 | W108: שווי הוגן | X108: 8.3103571e-05 | Y108: 0.092819048 | Z108: 0.066198253
A109: 13908 | B109: 13914 | C109: בנק ישראל | D109: מ.ק.מ. 116 | E109: IL0082601191 | F109: מק"מ קצר משנים עשר חודשים | G109: ישראל | H109: ישראל | I109: TASE | J109: NR | K109: NR | L109: ILS | M109: 0.77 | N109: 46204 | O109: 0 | P109: 0.0426 | Q109: 0 | R109: 652000 | S109: 1 | T109: 96.84 | U109: 631.3968 | W109: שווי הוגן | X109: 4.075e-05 | Y109: 0.051802034 | Z109: 0.036945048
A110: 13908 | B110: 13914 | C110: בנק ישראל | D110: מ.ק.מ 216 | E110: IL0082602181 | F110: מק"מ קצר משנים עשר חודשים | G110: ישראל | H110: ישראל | I110: TASE | J110: NR | K110: NR | L110: ILS | M110: 0.85 | N110: 46114 | O110: 0 | P110: 0.0426 | Q110: 0 | R110: 1720000 | S110: 1 | T110: 96.53 | U110: 1660.316 | W110: שווי הוגן | X110: 9.5555556e-05 | Y110: 0.13621822 | Z110: 0.097150404
A111: 13908 | B111: 13914 | C111: בנק ישראל | D111: מ.ק.מ. 316 | E111: IL0082603171 | F111: מק"מ קצר משנים עשר חודשים | G111: ישראל | H111: ישראל | I111: TASE | J111: NR | K111: NR | L111: ILS | M111: 0.92 | N111: 46115 | O111: 0 | P111: 0.0426 | Q111: 0 | R111: 2250000 | S111: 1 | T111: 96.22 | U111: 2164.95 | W111: שווי הוגן | X111: 0.000125 | Y111: 0.17762018 | Z111: 0.12667815
A112: 13908 | B112: 13915 | C112: בנק ישראל | D112: מ.ק.מ. 815 | E112: IL0082508131 | F112: מק"מ קצר משנים עשר חודשים | G112: ישראל | H112: ישראל | I112: TASE | J112: NR | K112: NR | L112: ILS | M112: 0.35 | N112: 45875 | O112: 0 | P112: 0.0429 | Q112: 0 | R112: 25683245 | S112: 1 | T112: 98.55 | U112: 25310.838 | W112: שווי הוגן | X112: 0.0021402704 | Y112: 0.22419816 | Z112: 0.064378628
A113: 13908 | B113: 13915 | C113: בנק ישראל | D113: מ.ק.מ. 915 | E113: IL0082509121 | F113: מק"מ קצר משנים עשר חודשים | G113: ישראל | H113: ישראל | I113: TASE | J113: NR | K113: NR | L113: ILS | M113: 0.42 | N113: 45903 | O113: 0 | P113: 0.0427 | Q113: 0 | R113: 42267429 | S113: 1 | T113: 98.24 | U113: 41523.522 | W113: שווי הוגן | X113: 0.0035222858 | Y113: 0.36780675 | Z113: 0.10561592
... A116: 13908 | B116: 13915 | C116: TREASURY BILL | D116: B 0 06/12/25 | E116: US912797LN52 | F116: נקוב במט"ח | G116: חו"ל | H116: ארה"ב | I116: FWB | J116: AA+ | K116: S&P | L116: USD | M116: 0.195 | N116: 45997 | O116: 0 | P116: 0.04284 | Q116: 0 | R116: 5000000 | S116: 3.718 | T116: 99.1504 | U116: 18432.059 | W116: שווי הוגן | X116: 2.5395664e-05 | Y116: 0.16326736 | Z116: 0.046882316
A117: 13908 | B117: 13916 | C117: מדינת ישראל | D117: ממשל שקלית 0327 | E117: IL0011393449 | F117: לא צמוד למדד המחירים לצרכן ריבית קבועה | G117: ישראל | H117: ישראל | I117: TASE | J117: NR | K117: NR | L117: ILS | M117: 1.977 | N117: 31/03/2027 | O117: 0.02 | P117: 0.0422 | Q117: 0 | R117: 428000 | S117: 1 | T117: 95.83 | U117: 410.1524 | W117: שווי הוגן | X117: 1.5162038e-05 | Y117: 0.088630103 | Z117: 0.0020877365
...

Sheet ניירות ערך מסחריים
A1: מספר קופה/קרן/ח.פ. עבור חברת ביטוח | B1: מספר מסלול | C1: שם מנפיק | D1: מספר מנפיק | E1: סוג מספר מזהה מנפיק | F1: שם נייר ערך | G1: מספר נייר ערך | H1: סוג מספר נייר ערך | I1: מאפיין עיקרי | J1: ישראל/חו"ל | K1: מדינה לפי חשיפה כלכלית | L1: זירת מסחר | M1: ענף מסחר | N1: בעל עניין/צד קשור | O1: דירוג | P1: שם מדרג | Q1: דירוג נייר הערך/המנפיק | R1: מטבע פעילות | S1: מח"מ | T1: ריבית עוגן | U1: מועד פדיון | V1: שיעור ריבית | W1: תשואה לפדיון | X1: נחיתות חוזית | Y1: האם סווג כחוב בעייתי | Z1: ערך נקוב (יחידות) | AA1: שער חליפין | AB1: שער נייר הערך | AC1: סכום לקבל (במטבע הפעילות) | AD1: שווי הוגן (באלפי ש"ח) | AE1: עלות מופחתת (באלפי ש"ח) | AF1: עלות מופחתת (במטבע הפעילות) | AG1: השיטה שיושמה בדוח הכספי | AH1: שיעור מערך נקוב מונפק | AI1: שיעור מנכסי אפיק ההשקעה | AJ1: שיעור מסך נכסי ההשקעה
A2: 13908 | B2: 13912 | C2: קבוצת עזריאלי בע"מ | D2: 510960719 | E2: ח.פ. | F2: עזריאלי מסחרי 1 | G2: IL0012086281 | H2: ISIN | I2: לא צמוד למדד המחירים לצרכן ריבית קבועה | J2: ישראל | K2: ישראל | L2: TASE | M2: נדל"ן מניב בישראל | N2: לא | O2: Aa1.il | P2: מידרוג Moodys | Q2: נייר ערך | R2: ILS | S2: 0.268 | T2: ללא | U2: 45876 | V2: 0.0462 | W2: 0.0468 | X2: החוב לא נחות | Z2: 164800 | AA2: 1 | AB2: 1033.3 | AC2: 0 | AD2: 1702.8784 | AG2: שווי הוגן | AH2: 0.0025830033 | AI2: 0.33318286 | AJ2: 0.00070112803
A3: 13908 | B3: 13912 | C3: חברת גב ים לקרקעות בע"מ | D3: 520001736 | E3: ח.פ. | F3: גב ים מסחרי 2 | G3: IL0012086448 | H3: ISIN | I3: לא צמוד למדד המחירים לצרכן ריבית קבועה | J3: ישראל | K3: ישראל | L3: TASE | M3: נדל"ן מניב בישראל | N3: לא | O3: ilA-1+ | P3: S&P מעלות | Q3: נייר ערך | R3: ILS | S3: 0.268 | T3: ללא | U3: 45876 | V3: 0.0466 | W3: 0.0494 | X3: החוב לא נחות | Z3: 164800 | AA3: 1 | AB3: 1033 | AC3: 0 | AD3: 1702.384 | AG3: שווי הוגן | AH3: 0.0054933333 | AI3: 0.33308613 | AJ3: 0.00070092447
A4: 13908 | B4: 13912 | C4: אפי נכסים בע"מ | D4: 510560188 | E4: ח.פ. | F4: אפי נכס מסחרי 4 | G4: IL0012086513 | H4: ISIN | I4: לא צמוד למדד המחירים לצרכן ריבית קבועה | J4: ישראל | K4: ישראל | L4: TASE | M4: נדל"ן מניב בחו"ל | N4: לא | O4: ilA-1 | P4: S&P מעלות | Q4: נייר ערך | R4: ILS | S4: 0.266 | T4: ללא | U4: 45845 | V4: 0.0495 | W4: 0.0527 | X4: החוב לא נחות | Z4: 164800 | AA4: 1 | AB4: 1035 | AC4: 0 | AD4: 1705.68 | AG4: שווי הוגן | AH4: 0.010069903 | AI4: 0.33373102 | AJ4: 0.00070228153
A5: 13918 | B5: 13922 | C5: קבוצת עזריאלי בע"מ | D5: 510960719 | E5: ח.פ. | F5: עזריאלי מסחרי 1 | G5: IL0012086281 | H5: ISIN | I5: לא צמוד למדד המחירים לצרכן ריבית קבועה | J5: ישראל | K5: ישראל | L5: TASE | M5: נדל"ן מניב בישראל | N5: לא | O5: Aa1.il | P5: מידרוג Moodys | Q5: נייר ערך | R5: ILS | S5: 0.268 | T5: ללא | U5: 45876 | V5: 0.0462 | W5: 0.0468 | X5: החוב לא נחות | Z5: 30000 | AA5: 1 | AB5: 1033.3 | AC5: 0 | AD5: 309.99 | AG5: שווי הוגן | AH5: 0.00047020691 | AI5: 0.33318286 | AJ5: 0.0027296241
A6: 13918 | B6: 13922 | C6: חברת גב ים לקרקעות בע"מ | D6: 520001736 | E6: ח.פ. | F6: גב ים מסחרי 2 | G6: IL0012086448 | H6: ISIN | I6: לא צמוד למדד המחירים לצרכן ריבית קבועה | J6: ישראל | K6: ישראל | L6: TASE | M6: נדל"ן מניב בישראל | N6: לא | O6: ilA-1+ | P6: S&P מעלות | Q6: נייר ערך | R6: ILS | S6: 0.268 | T6: ללא | U6: 45876 | V6: 0.0466 | W6: 0.0494 | X6: החוב לא נחות | Z6: 30000 | AA6: 1 | AB6: 1033 | AC6: 0 | AD6: 309.9 | AG6: שווי הוגן | AH6: 0.001 | AI6: 0.33308613 | AJ6: 0.0027288316
A7: 13918 | B7: 13922 | C7: אפי נכסים בע"מ | D7: 510560188 | E7: ח.פ. | F7: אפי נכס מסחרי 4 | G7: IL0012086513 | H7: ISIN | I7: לא צמוד למדד המחירים לצרכן ריבית קבועה | J7: ישראל | K7: ישראל | L7: TASE | M7: נדל"ן מניב בחו"ל | N7: לא | O7: ilA-1 | P7: S&P מעלות | Q7: נייר ערך | R7: ILS | S7: 0.266 | T7: ללא | U7: 45845 | V7: 0.0495 | W7: 0.0527 | X7: החוב לא נחות | Z7: 30000 | AA7: 1 | AB7: 1035 | AC7: 0 | AD7: 310.5 | AG7: שווי הוגן | AH7: 0.0018331134 | AI7: 0.33373102 | AJ7: 0.002734115
A8: 13918 | B8: 13926 | C8: קבוצת עזריאלי בע"מ | D8: 510960719 | E8: ח.פ. | F8: עזריאלי מסחרי 1 | G8: IL0012086281 | H8: ISIN | I8: לא צמוד למדד המחירים לצרכן ריבית קבועה | J8: ישראל | K8: ישראל | L8: TASE | M8: נדל"ן מניב בישראל | N8: לא | O8: Aa1.il | P8: מידרוג Moodys | Q8: נייר ערך | R8: ILS | S8: 0.268 | T8: ללא | U8: 45876 | V8: 0.0462 | W8: 0.0468 | X8: החוב לא נחות | Z8: 200 | AA8: 1 | AB8: 1033.3 | AC8: 0 | AD8: 2.0666 | AG8: שווי הוגן | AH8: 3.1347127e-06 | AI8: 0.33318286 | AJ8: 0.0019892988
A9: 13918 | B9: 13926 | C9: חברת גב ים לקרקעות בע"מ | D9: 520001736 | E9: ח.פ. | F9: גב ים מסחרי 2 | G9: IL0012086448 | H9: ISIN | I9: לא צמוד למדד המחירים לצרכן ריבית קבועה | J9: ישראל | K9: ישראל | L9: TASE | M9: נדל"ן מניב בישראל | N9: לא | O9: ilA-1+ | P9: S&P מעלות | Q9: נייר ערך | R9: ILS | S9: 0.268 | T9: ללא | U9: 45876 | V9: 0.0466 | W9: 0.0494 | X9: החוב לא נחות | Z9: 200 | AA9: 1 | AB9: 1033 | AC9: 0 | AD9: 2.066 | AG9: שווי הוגן | AH9: 6.6666667e-06 | AI9: 0.33308613 | AJ9: 0.0019887212
A10: 13918 | B10: 13926 | C10: אפי נכסים בע"מ | D10: 510560188 | E10: ח.פ. | F10: אפי נכס מסחרי 4 | G10: IL0012086513 | H10: ISIN | I10: לא צמוד למדד המחירים לצרכן ריבית קבועה | J10: ישראל | K10: ישראל | L10: TASE | M10: נדל"ן מניב בחו"ל | N10: לא | O10: ilA-1 | P10: S&P מעלות | Q10: נייר ערך | R10: ILS | S10: 0.266 | T10: ללא | U10: 45845 | V10: 0.0495 | W10: 0.0527 | X10: החוב לא נחות | Z10: 200 | AA10: 1 | AB10: 1035 | AC10: 0 | AD10: 2.07 | AG10: שווי הוגן | AH10: 1.2220756e-05 | AI10: 0.33373102 | AJ10: 0.0019925716

Sheet איגרות חוב
A1: מספר קופה/קרן/ח.פ. עבור חברת ביטוח | B1: מספר מסלול | C1: שם מנפיק | D1: מספר מנפיק | E1: סוג מספר מזהה מנפיק | F1: שם נייר ערך | G1: מספר נייר ערך | H1: סוג מספר נייר ערך | I1: מאפיין עיקרי | J1: ישראל/חו"ל | K1: מדינה לפי חשיפה כלכלית | L1: סטאטוס סחירות | M1: זירת מסחר | N1: ענף מסחר | O1: בעל עניין/צד קשור | P1: דירוג | Q1: שם מדרג | R1: דירוג נייר הערך/המנפיק | S1: מטבע פעילות | T1: מח"מ | U1: מועד פדיון | V1: שיעור ריבית | W1: תשואה לפדיון | X1: נחיתות חוזית | Y1: האם סווג כחוב בעייתי | Z1: ערך נקוב (יחידות) | AA1: שער חליפין | AB1: שער נייר הערך | AC1: סכום לקבל (במטבע הפעילות) | AD1: שווי הוגן (באלפי ש"ח) | AE1: עלות מופחתת (באלפי ש"ח) | AF1: עלות מופחתת (במטבע הפעילות) | AG1: השיטה שיושמה בדוח הכספי | AH1: שיעור מערך נקוב מונפק | AI1: שיעור מנכסי אפיק ההשקעה | AJ1: שיעור מסך נכסי ההשקעה
A2: 13908 | B2: 13909 | C2: אדמה פתרונות לחקלאות בע"מ | D2: 520043605 | E2: ח.פ. | F2: אדמה אגח ב | G2: IL0011109159 | H2: ISIN | I2: צמוד למדד המחירים לצרכן | J2: ישראל | K2: ישראל | L2: סחיר | M2: TASE | N2: כימיה, גומי ופלסטיק | O2: לא | P2: ilAA- | Q2: S&P מעלות | R2: נייר ערך | S2: ILS | T2: 5.128 | U2: 30/11/2036 | V2: 0.0515 | W2: 0.0452 | X2: החוב לא נחות | Z2: 1491473.2 | AA2: 1 | AB2: 146.6 | AC2: 0 | AD2: 2186.4997 | AG2: שווי הוגן | AH2: 0.00058227654 | AI2: 0.0042161231 | AJ2: 0.00053291107
A3: 13908 | B3: 13909 | C3: שיכון ובינוי בע"מ | D3: 520036104 | E3: ח.פ. | F3: שכון ובי אגח 6 | G3: IL0011297335 | H3: ISIN | I3: צמוד למדד המחירים לצרכן | J3: ישראל | K3: ישראל | L3: סחיר | M3: TASE | N3: בנייה | O3: לא | P3: ilA | Q3: S&P מעלות | R3: נייר ערך | S3: ILS | T3: 0 | U3: 45748 | V3: 0.0434 | W3: 0 | X3: החוב לא נחות | Z3: 779945.16 | AA3: 1 | AB3: 117.97 | AC3: 0.65938 | AD3: 920.76069 | AG3: שווי הוגן | AH3: 0.0017930608 | AI3: 0.0017754589 | AJ3: 0.0002244151
A4: 13908 | B4: 13909 | C4: שיכון ובינוי בע"מ | D4: 520036104 | E4: ח.פ. | F4: שכון ובי אגח 7 | G4: IL0011297418 | H4: ISIN | I4: לא צמוד למדד המחירים לצרכן | J4: ישראל | K4: ישראל | L4: סחיר | M4: TASE | N4: בנייה | O4: לא | P4: ilA | Q4: S&P מעלות | R4: נייר ערך | S4: ILS | T4: 0 | U4: 45748 | V4: 0.0623 | W4: 0 | X4: החוב לא נחות | Z4: 50000 | AA4: 1 | AB4: 103 | AC4: 0.0575 | AD4: 51.5575 | AG4: שווי הוגן | AH4: 0.00031442409 | AI4: 9.9415868e-05 | AJ4: 1.2566003e-05
A5: 13908 | B5: 13909 | C5: אמות השקעות בע"מ | D5: 520026683 | E5: ח.פ. | F5: אמות אגח ד | G5: IL0011331498 | H5: ISIN | I5: צמוד למדד המחירים לצרכן | J5: ישראל | K5: ישראל | L5: סחיר | M5: TASE | N5: נדל"ן מניב בישראל | O5: לא | P5: ilAA | Q5: S&P מעלות | R5: נייר ערך | S5: ILS | T5: 1.682 | U5: 46790 | V5: 0.032 | W5: 0.0275 | X5: החוב לא נחות | Z5: 180800 | AA5: 1 | AB5: 118.93 | AC5: 0 | AD5: 215.02544 | AG5: שווי הוגן | AH5: 0.00032745662 | AI5: 0.0004146233 | AJ5: 5.2407707e-05
A6: 13908 | B6: 13909 | C6: איירפורט סיטי בע"מ | D6: 511659401 | E6: ח.פ. | F6: ארפורט אגח ה | G6: IL0011334872 | H6: ISIN | I6: צמוד למדד המחירים לצרכן | J6: ישראל | K6: ישראל | L6: סחיר | M6: TASE | N6: נדל"ן מניב בישראל | O6: לא | P6: ilAA | Q6: S&P מעלות | R6: נייר ערך | S6: ILS | T6: 2.267 | U6: 28/02/2029 | V6: 0.0234 | W6: 0.028 | X6: החוב לא נחות | Z6: 2764493.6 | AA6: 1 | AB6: 114.39 | AC6: 0 | AD6: 3162.3042 | AG6: שווי הוגן | AH6: 0.0016958915 | AI6: 0.0060977204 | AJ6: 0.00077074188
A7: 13908 | B7: 13909 | C7: קבוצת עזריאלי בע"מ | D7: 510960719 | E7: ח.פ. | F7: עזריאלי אגח ב | G7: IL0011344368 | H7: ISIN | I7: צמוד למדד המחירים לצרכן | J7: ישראל | K7: ישראל | L7: סחיר | M7: TASE | N7: נדל"ן מניב בישראל | O7: לא | P7: ilAA+ | Q7: S&P מעלות | R7: נייר ערך | S7: ILS | T7: 0 | U7: 45748 | V7: 0.0065 | W7: 0 | X7: החוב לא נחות | Z7: 2120924 | AA7: 1 | AB7: 115.85 | AC7: 1.54187 | AD7: 2458.6323 | AG7: שווי הוגן | AH7: 0.0038852685 | AI7: 0.0047408634 | AJ7: 0.00059923738
A8: 13908 | B8: 13909 | C8: שיכון ובינוי בע"מ | D8: 520036104 | E8: ח.פ. | F8: שכון ובי אגח 8 | G8: IL0011358889 | H8: ISIN | I8: צמוד למדד המחירים לצרכן | J8: ישראל | K8: ישראל | L8: סחיר | M8: TASE | N8: בנייה | O8: לא | P8: ilA | Q8: S&P מעלות | R8: נייר ערך | S8: ILS | T8: 2.348 | U8: 47123 | V8: 0.039 | W8: 0.0384 | X8: החוב לא נחות | Z8: 851325.76 | AA8: 1 | AB8: 118.27 | AC8: 0 | AD8: 1006.863 | AG8: שווי הוגן | AH8: 0.00059686902 | AI8: 0.0019414859 | AJ8: 0.00024540064
A9: 13908 | B9: 13909 | C9: קרסו מוטורס בע"מ | D9: 514065283 | E9: ח.פ. | F9: קרסו מוט' אגח א | G9: IL0011364648 | H9: ISIN | I9: לא צמוד למדד המחירים לצרכן | J9: ישראל | K9: ישראל | L9: סחיר | M9: TASE | N9: מסחר | O9: לא | P9: ilAA- | Q9: S&P מעלות | R9: נייר ערך | S9: ILS | T9: 0.909 | U9: 46031 | V9: 0.0275 | W9: 0.0519 | X9: החוב לא נחות | Z9: 1004385.9 | AA9: 1 | AB9: 98.12 | AC9: 0 | AD9: 985.50346 | AG9: שווי הוגן | AH9: 0.0074077448 | AI9: 0.0019002993 | AJ9: 0.00024019473
A10: 13908 | B10: 13909 | C10: ריט 1 בע"מ | D10: 513821488 | E10: ח.פ. | F10: ריט 1 אגח ה | G10: IL0011367534 | H10: ISIN | I10: צמוד למדד המחירים לצרכן | J10: ישראל | K10: ישראל | L10: סחיר | M10: TASE | N10: נדל"ן מניב בישראל | O10: לא | P10: ilAA | Q10: S&P מעלות | R10: נייר ערך | S10: ILS | T10: 1.906 | U10: 20/09/2028 | V10: 0.04 | W10: 0.0281 | X10: החוב לא נחות | Z10: 1639791.7 | AA10: 1 | AB10: 119.04 | AC10: 0 | AD10: 1952.008 | AG10: שווי הוגן | AH10: 0.0019469552 | AI10: 0.0037639639 | AJ10: 0.00047575888
A11: 13908 | B11: 13909 | C11: אמות השקעות בע"מ | D11: 520026683 | E11: ח.פ. | F11: אמות אגח ה | G11: IL0011381147 | H11: ISIN | I11: לא צמוד למדד המחירים לצרכן | J11: ישראל | K11: ישראל | L11: סחיר | M11: TASE | N11: נדל"ן מניב בישראל | O11: לא | P11: ilAA | Q11: S&P מעלות | R11: נייר ערך | S11: ILS | T11: 0.762 | U11: 46113 | V11: 0.0339 | W11: 0.0446 | X11: החוב לא נחות | Z11: 2500 | AA11: 1 | AB11: 100.01 | AC11: 0 | AD11: 2.50025 | AG11: שווי הוגן | AH11: 1.5301799e-05 | AI11: 4.8211128e-06 | AJ11: 6.0938077e-07
A12: 13908 | B12: 13909 | C12: ריט 1 בע"מ | D12: 513821488 | E12: ח.פ. | F12: ריט 1 אגח ו | G12: IL0011385445 | H12: ISIN | I12: צמוד למדד המחירים לצרכן | J12: ישראל | K12: ישראל | L12: סחיר | M12: TASE | N12: נדל"ן מניב בישראל | O12: לא | P12: ilAA | Q12: S&P מעלות | R12: נייר ערך | S12: ILS | T12: 3.261 | U12: 21/09/2031 | V12: 0.035 | W12: 0.0294 | X12: החוב לא נחות | Z12: 492735.01 | AA12: 1 | AB12: 119.75 | AC12: 0 | AD12: 590.05017 | AG12: שווי הוגן | AH12: 0.00061622559 | AI12: 0.0011377656 | AJ12: 0.00014381171
A13: 13908 | B13: 13909 | C13: קבוצת עזריאלי בע"מ | D13: 510960719 | E13: ח.פ. | F13: עזריאלי אגח ד | G13: IL0011386500 | H13: ISIN | I13: צמוד למדד המחירים לצרכן | J13: ישראל | K13: ישראל | L13: סחיר | M13: TASE | N13: נדל"ן מניב בישראל | O13: לא | P13: Aa1.il | Q13: מידרוג Moodys | R13: נייר ערך | S13: ILS | T13: 2.662 | U13: 47610 | V13: 0.0134 | W13: 0.0281 | X13: החוב לא נחות | Z13: 7492038.8 | AA13: 1 | AB13: 113.01 | AC13: 0 | AD13: 8466.753 | AG13: שווי הוגן | AH13: 0.0030834279 | AI13: 0.016326036 | AJ13: 0.0020635842
A14: 13908 | B14: 13909 | C14: ביג מרכזי קניות בע"מ | D14: 513623314 | E14: ח.פ. | F14: ביג אגח ח | G14: IL0011389249 | H14: ISIN | I14: צמוד למדד המחירים לצרכן | J14: ישראל | K14: ישראל | L14: סחיר | M14: TASE | N14: נדל"ן מניב בישראל | O14: לא | P14: ilAA | Q14: S&P מעלות | R14: נייר ערך | S14: ILS | T14: 0.937 | U14: 46360 | V14: 0.0134 | W14: 0.0281 | X14: החוב לא נחות | Z14: 314571.42 | AA14: 1 | AB14: 115.87 | AC14: 0 | AD14: 364.4939 | AG14: שווי הוגן | AH14: 0.00063915349 | AI14: 0.0007028362 | AJ14: 8.8837346e-05
A15: 13908 | B15: 13909 | C15: סלע קפיטל נדל"ן בע"מ | D15: 513992529 | E15: ח.פ. | F15: סלע נדלן אגח ג | G15: IL0011389736 | H15: ISIN | I15: צמוד למדד המחירים לצרכן | J15: ישראל | K15: ישראל | L15: סחיר | M15: TASE | N15: נדל"ן מניב בישראל | O15: לא | P15: Aa3.il | Q15: מידרוג Moodys | R15: נייר ערך | S15: ILS | T15: 2.439 | U15: 13/04/2029 | V15: 0.0196 | W15: 0.0288 | X15: החוב לא נחות | Z15: 144000 | AA15: 1 | AB15: 114.79 | AC15: 0 | AD15: 165.2976 | AG15: שווי הוגן | AH15: 0.00012575403 | AI15: 0.00031873548 | AJ15: 4.0287643e-05
A16: 13908 | B16: 13909 | C16: הפניקס גיוסי הון (2009)בע"מ | D16: 514290345 | E16: ח.פ. | F16: פניקס הון אגח ח | G16: IL0011398158 | H16: ISIN | I16: לא צמוד למדד המחירים לצרכן | J16: ישראל | K16: ישראל | L16: סחיר | M16: TASE | N16: ביטוח | O16: לא | P16: ilAA | Q16: S&P מעלות | R16: נייר ערך | S16: ILS | T16: 0.332 | U16: 31/07/2028 | V16: 0.0361 | W16: 0.0507 | X16: החוב לא נחות | Z16: 1000000 | AA16: 1 | AB16: 100.15 | AC16: 0 | AD16: 1001.5 | AG16: שווי הוגן | AH16: 0.0013029316 | AI16: 0.0019311447 | AJ16: 0.00024409353
A17: 13908 | B17: 13909 | C17: קבוצת אשטרום בע"מ | D17: 510381601 | E17: ח.פ. | F17: אשטרום קב אגח ג | G17: IL0011401028 | H17: ISIN | I17: לא צמוד למדד המחירים לצרכן | J17: ישראל | K17: ישראל | L17: סחיר | M17: TASE | N17: בנייה | O17: לא | P17: ilA | Q17: S&P מעלות | R17: נייר ערך | S17: ILS | T17: 1.919 | U17: 15/01/2029 | V17: 0.043 | W17: 0.0552 | X17: החוב לא נחות | Z17: 1232720 | AA17: 1 | AB17: 98.75 | AC17: 0 | AD17: 1217.311 | AG17: שווי הוגן | AH17: 0.001526832 | AI17: 0.0023472828 | AJ17: 0.0002966927
A18: 13908 | B18: 13909 | C18: רבוע כחול נדל"ן בע"מ | D18: 513765859 | E18: ח.פ. | F18: רבוע נדלן אגח ו | G18: IL0011406076 | H18: ISIN | I18: צמוד למדד המחירים לצרכן | J18: ישראל | K18: ישראל | L18: סחיר | M18: TASE | N18: נדל"ן מניב בישראל | O18: לא | P18: ilAA- | Q18: S&P מעלות | R18: נייר ערך | S18: ILS | T18: 1.146 | U18: 30/11/2026 | V18: 0.0215 | W18: 0.0282 | X18: החוב לא נחות | Z18: 571428.57 | AA18: 1 | AB18: 117.16 | AC18: 0 | AD18: 669.48571 | AG18: שווי הוגן | AH18: 0.00040789289 | AI18: 0.0012909374 | AJ18: 0.00016317237
A19: 13908 | B19: 13909 | C19: תמר פטרוליום בע"מ | D19: 515334662 | E19: ח.פ. | F19: תמר פטרו אגח א | G19: IL0011413320 | H19: ISIN | I19: צמוד למט"ח | J19: ישראל | K19: ישראל | L19: סחיר | M19: TASE | N19: חיפושי נפט וגז | O19: לא | P19: A1.il | Q19: מידרוג Moodys | R19: נייר ערך | S19: ILS | T19: 2.673 | U19: 30/08/2028 | V19: 0.0469 | W19: 0.0664 | X19: החוב לא נחות | Z19: 4117405.9 | AA19: 1 | AB19: 101 | AC19: 0 | AD19: 4158.58 | AG19: שווי הוגן | AH19: 0.0031805405 | AI19: 0.0080187914 | AJ19: 0.0010135621
A20: 13908 | B20: 13909 | C20: קרסו מוטורס בע"מ | D20: 514065283 | E20: ח.פ. | F20: קרסו מוט' אגח ג | G20: IL0011418295 | H20: ISIN | I20: לא צמוד למדד המחירים לצרכן | J20: ישראל | K20: ישראל | L20: סחיר | M20: TASE | N20: מסחר | O20: לא | P20: ilAA- | Q20: S&P מעלות | R20: נייר ערך | S20: ILS | T20: 1.518 | U20: 46396 | V20: 0.023 | W20: 0.0516 | X20: החוב לא נחות | Z20: 1392201 | AA20: 1 | AB20: 96.07 | AC20: 0 | AD20: 1337.4875 | AG20: שווי הוגן | AH20: 0.0012866991 | AI20: 0.0025790133 | AJ20: 0.00032598307
A21: 13908 | B21: 13909 | C21: תמר פטרוליום בע"מ | D21: 515334662 | E21: ח.פ. | F21: תמר פטרו אגח ב | G21: IL0011435935 | H21: ISIN | I21: צמוד למט"ח | J21: ישראל | K21: ישראל | L21: סחיר | M21: TASE | N21: חיפושי נפט וגז | O21: לא | P21: A1.il | Q21: מידרוג Moodys | R21: נייר ערך | S21: ILS | T21: 2.832 | U21: 30/08/2028 | V21: 0.0469 | W21: 0.0656 | X21: החוב לא נחות | Z21: 1524701.6 | AA21: 1 | AB21: 102.77 | AC21: 0 | AD21: 1566.9358 | AG21: שווי הוגן | AH21: 0.0013821036 | AI21: 0.0030214476 | AJ21: 0.00038190603
A22: 13908 | B22: 13909 | C22: חברת נמלי ישראל-פיתוח נכסים בע | D22: 513569780 | E22: ח.פ. | F22: נמלי ישראל אגחב | G22: IL0011455727 | H22: ISIN | I22: צמוד למדד המחירים לצרכן | J22: ישראל | K22: ישראל | L22: סחיר | M22: TASE | N22: נדל"ן מניב בישראל | O22: לא | P22: ilAAA | Q22: S&P מעלות | R22: נייר ערך | S22: ILS | T22: 4.536 | U22: 31/12/2031 | V22: 0.0165 | W22: 0.0258 | X22: החוב לא נחות | Z22: 3686848 | AA22: 1 | AB22: 112.36 | AC22: 0 | AD22: 4142.5424 | AG22: שווי הוגן | AH22: 0.0017426764 | AI22: 0.0079878669 | AJ22: 0.0010096533
A23: 13908 | B23: 13909 | C23: נתיבי הגז הטבעי לישראל בע"מ | D23: 513436394 | E23: ח.פ. | F23: נתיבי גז אגח ד | G23: IL0011475030 | H23: ISIN | I23: צמוד למדד המחירים לצרכן | J23: ישראל | K23: ישראל | L23: סחיר | M23: TASE | N23: שירותים | O23: לא | P23: Aa1.il | Q23: מידרוג Moodys | R23: נייר ערך | S23: ILS | T23: 5.093 | U23: 30/06/2033 | V23: 0.0265 | W23: 0.0255 | X23: החוב לא נחות | Z23: 3473570.7 | AA23: 1 | AB23: 117.66 | AC23: 0 | AD23: 4087.0032 | AG23: שווי הוגן | AH23: 0.0023782499 | AI23: 0.0078807734 | AJ23: 0.00099611687
A24: 13908 | B24: 13909 | C24: מגה אור החזקות בע"מ | D24: 513257873 | E24: ח.פ. | F24: מגה אור אגח ח | G24: IL0011476020 | H24: ISIN | I24: צמוד למדד המחירים לצרכן | J24: ישראל | K24: ישראל | L24: סחיר | M24: TASE | N24: נדל"ן מניב בישראל | O24: לא | P24: ilAA- | Q24: S&P מעלות | R24: נייר ערך | S24: ILS | T24: 1.646 | U24: 31/03/2027 | V24: 0.014 | W24: 0.0266 | X24: החוב לא נחות | Z24: 42592.8 | AA24: 1 | AB24: 113.81 | AC24: 0 | AD24: 48.47487 | AG24: שווי הוגן | AH24: 7.0382709e-05 | AI24: 9.347178e-05 | AJ24: 1.181468e-05
A25: 13908 | B25: 13909 | C25: פתאל החזקות (1998) בע"מ | D25: 512607888 | E25: ח.פ. | F25: פתאל החז אגח ב | G25: IL0011508129 | H25: ISIN | I25: לא צמוד למדד המחירים לצרכן | J25: ישראל | K25: ישראל | L25: סחיר | M25: TASE | N25: מלונאות ותיירות | O25: לא | P25: A2.il | Q25: מידרוג Moodys | R25: נייר ערך | S25: ILS | T25: 0.972 | U25: 31/12/2026 | V25: 0.0325 | W25: 0.0571 | X25: החוב לא נחות | Z25: 472230.06 | AA25: 1 | AB25: 98.55 | AC25: 0 | AD25: 465.38272 | AG25: שווי הוגן | AH25: 0.0022350901 | AI25: 0.0008973753 | AJ25: 0.00011342677
A26: 13908 | B26: 13909 | C26: ביג מרכזי קניות בע"מ | D26: 513623314 | E26: ח.פ. | F26: ביג אגח יא | G26: IL0011511172 | H26: ISIN | I26: צמוד למדד המחירים לצרכן | J26: ישראל | K26: ישראל | L26: סחיר | M26: TASE | N26: נדל"ן מניב בישראל | O26: לא | P26: ilAA | Q26: S&P מעלות | R26: נייר ערך | S26: ILS | T26: 2.421 | U26: 20/10/2027 | V26: 0.0182 | W26: 0.026 | X26: החוב לא נחות | Z26: 870738.97 | AA26: 1 | AB26: 114.28 | AC26: 0 | AD26: 995.08049 | AG26: שווי הוגן | AH26: 0.0017398707 | AI26: 0.0019187662 | AJ26: 0.00024252891
A27: 13908 | B27: 13909 | C27: מניבים קרן הריט החדשה בע"מ | D27: 515327120 | E27: ח.פ. | F27: מניבים ריט אגחב | G27: IL0011559288 | H27: ISIN | I27: צמוד למדד המחירים לצרכן | J27: ישראל | K27: ישראל | L27: סחיר | M27: TASE | N27: נדל"ן מניב בישראל | O27: לא | P27: Aa3.il | Q27: מידרוג Moodys | R27: נייר ערך | S27: ILS | T27: 2.473 | U27: 31/12/2027 | V27: 0.0275 | W27: 0.0274 | X27: החוב לא נחות | Z27: 643446.9 | AA27: 1 | AB27: 115.76 | AC27: 0 | AD27: 744.85413 | AG27: שווי הוגן | AH27: 0.001262776 | AI27: 0.0014362667 | AJ27: 0.00018154176
A28: 13908 | B28: 13909 | C28: שמוס אינטרנשיונל לימיטד | D28: 633896 | E28: LEI | F28: שמוס אגח א | G28: IL0011559510 | H28: ISIN | I28: צמוד למט"ח | J28: ישראל | K28: בריטניה | L28: סחיר | M28: TASE | N28: נדל"ן מניב בחו"ל | O28: לא | P28: Aa3.il | Q28: מידרוג Moodys | R28: נייר ערך | S28: ILS | T28: 2.611 | U28: 47033 | V28: 0.043 | W28: 0.0861 | X28: החוב לא נחות | Z28: 2050344.4 | AA28: 1 | AB28: 91.56 | AC28: 0 | AD28: 1877.2954 | AG28: שווי הוגן | AH28: 0.0019150525 | AI28: 0.0036198991 | AJ28: 0.00045754933
A29: 13908 | B29: 13909 | C29: חברת פרטנר תקשורת בע"מ | D29: 520044314 | E29: ח.פ. | F29: פרטנר אגח ז | G29: IL0011563975 | H29: ISIN | I29: לא צמוד למדד המחירים לצרכן | J29: ישראל | K29: ישראל | L29: סחיר | M29: TASE | N29: תקשורת ומדיה | O29: לא | P29: ilAA- | Q29: S&P מעלות | R29: נייר ערך | S29: ILS | T29: 1.58 | U29: 25/06/2027 | V29: 0.04 | W29: 0.0493 | X29: החוב לא נחות | Z29: 1680000 | AA29: 1 | AB29: 101.61 | AC29: 0 | AD29: 1707.048 | AG29: שווי הוגן | AH29: 0.0028207598 | AI29: 0.0032916192 | AJ29: 0.00041605529
A30: 13908 | B30: 13909 | C30: קבוצת עזריאלי בע"מ | D30: 510960719 | E30: ח.פ. | F30: עזריאלי אגח ה | G30: IL0011566036 | H30: ISIN | I30: צמוד למדד המחירים לצרכן | J30: ישראל | K30: ישראל | L30: סחיר | M30: TASE | N30: נדל"ן מניב בישראל | O30: לא | P30: Aa1.il | Q30: מידרוג Moodys | R30: נייר ערך | S30: ILS | T30: 2.068 | U30: 30/06/2028 | V30: 0.0177 | W30: 0.0275 | X30: החוב לא נחות | Z30: 1301721.2 | AA30: 1 | AB30: 113.81 | AC30: 0 | AD30: 1481.4889 | AG30: שווי הוגן | AH30: 0.00050168221 | AI30: 0.0028566845 | AJ30: 0.00036108025
A31: 13908 | B31: 13909 | C31: קבוצת עזריאלי בע"מ | D31: 510960719 | E31: ח.פ. | F31: עזריאלי אגח ו | G31: IL0011566119 | H31: ISIN | I31: צמוד למדד המחירים לצרכן | J31: ישראל | K31: ישראל | L31: סחיר | M31: TASE | N31: נדל"ן מניב בישראל | O31: לא | P31: Aa1.il | Q31: מידרוג Moodys | R31: נייר ערך | S31: ILS | T31: 5.046 | U31: 31/12/2032 | V31: 0.0248 | W31: 0.0294 | X31: החוב לא נחות | Z31: 989000 | AA31: 1 | AB31: 113.77 | AC31: 0 | AD31: 1125.1853 | AG31: שווי הוגן | AH31: 0.00030019821 | AI31: 0.0021696411 | AJ31: 0.00027423909
A32: 13908 | B32: 13909 | C32: רבוע כחול נדל"ן בע"מ | D32: 513765859 | E32: ח.פ. | F32: רבוע נדלן אגח ח | G32: IL0011575698 | H32: ISIN | I32: צמוד למדד המחירים לצרכן | J32: ישראל | K32: ישראל | L32: סחיר | M32: TASE | N32: נדל"ן מניב בישראל | O32: לא | P32: ilAA | Q32: S&P מעלות | R32: נייר ערך | S32: ILS | T32: 2.289 | U32: 31/10/2028 | V32: 0.0142 | W32: 0.0279 | X32: החוב לא נחות | Z32: 750987.44 | AA32: 1 | AB32: 112.72 | AC32: 0 | AD32: 846.51304 | AG32: שווי הוגן | AH32: 0.0007395515 | AI32: 0.0016322907 | AJ32: 0.00020631888
A33: 13908 | B33: 13909 | C33: ש.י.ר שלמה נדל"ן בע"מ | D33: 513957472 | E33: ח.פ. | F33: שלמה נדלן אגח ד | G33: IL0011576688 | H33: ISIN | I33: לא צמוד למדד המחירים לצרכן | J33: ישראל | K33: ישראל | L33: סחיר | M33: TASE | N33: נדל"ן מניב בישראל | O33: לא | P33: A3.il | Q33: מידרוג Moodys | R33: נייר ערך | S33: ILS | T33: 2.787 | U33: 31/10/2030 | V33: 0.041 | W33: 0.0563 | X33: החוב לא נחות | Z33: 1176100 | AA33: 1 | AB33: 97.74 | AC33: 0 | AD33: 1149.5201 | AG33: שווי הוגן | AH33: 0.0025767482 | AI33: 0.0022165649 | AJ33: 0.00028017017
A34: 13908 | B34: 13909 | C34: מקורות חברת מים בע"מ | D34: 520010869 | E34: ח.פ. | F34: מקורות אגח 11 | G34: IL0011584765 | H34: ISIN | I34: צמוד למדד המחירים לצרכן | J34: ישראל | K34: ישראל | L34: סחיר | M34: TASE | N34: שירותים | O34: לא | P34: ilAAA | Q34: S&P מעלות | R34: נייר ערך | S34: ILS | T34: 11.713 | U34: 31/12/2053 | V34: 0.0207 | W34: 0.0299 | X34: החוב לא נחות | Z34: 3046153.9 | AA34: 1 | AB34: 102.91 | AC34: 0 | AD34: 3134.7969 | AG34: שווי הוגן | AH34: 0.00055717912 | AI34: 0.0060446794 | AJ34: 0.00076403759
A35: 13908 | B35: 13909 | C35: חלל-תקשורת בע"מ | D35: 511396046 | E35: ח.פ. | F35: חלל תקש אגח יח | G35: IL0011585184 | H35: ISIN | I35: צמוד למדד המחירים לצרכן | J35: ישראל | K35: ישראל | L35: סחיר | M35: TASE | N35: תקשורת ומדיה | O35: לא | P35: NR | Q35: NR | R35: נייר ערך | S35: ILS | T35: 1.751 | U35: 31/12/2026 | V35: 0.053 | W35: 0.05 | X35: החוב לא נחות | Z35: 437500 | AA35: 1 | AB35: 104.53 | AC35: 0 | AD35: 457.31875 | AG35: שווי הוגן | AH35: 0.0029069767 | AI35: 0.00088182593 | AJ35: 0.00011146136
A36: 13908 | B36: 13909 | C36: אמות השקעות בע"מ | D36: 520026683 | E36: ח.פ. | F36: אמות אגח ו | G36: IL0011586091 | H36: ISIN | I36: צמוד למדד המחירים לצרכן | J36: ישראל | K36: ישראל | L36: סחיר | M36: TASE | N36: נדל"ן מניב בישראל | O36: לא | P36: ilAA | Q36: S&P מעלות | R36: נייר ערך | S36: ILS | T36: 2.83 | U36: 47187 | V36: 0.0114 | W36: 0.0279 | X36: החוב לא נחות | Z36: 2965559 | AA36: 1 | AB36: 109.34 | AC36: 0 | AD36: 3242.5422 | AG36: שווי הוגן | AH36: 0.0012550065 | AI36: 0.0062524395 | AJ36: 0.00079029812
A37: 13908 | B37: 13909 | C37: אלבר שירותי מימונית בע"מ | D37: 512025891 | E37: ח.פ. | F37: אלבר אגח יז | G37: IL0011587321 | H37: ISIN | I37: צמוד למדד המחירים לצרכן | J37: ישראל | K37: ישראל | L37: סחיר | M37: TASE | N37: שירותים | O37: לא | P37: ilA+ | Q37: S&P מעלות | R37: נייר ערך | S37: ILS | T37: 0.915 | U37: 20/01/2027 | V37: 0.0185 | W37: 0.0304 | X37: החוב לא נחות | Z37: 59228.34 | AA37: 1 | AB37: 113.07 | AC37: 0 | AD37: 66.96948 | AG37: שווי הוגן | AH37: 0.00013359319 | AI37: 0.00012913405 | AJ37: 1.6322333e-05
A38: 13908 | B38: 13909 | C38: אלבר שירותי מימונית בע"מ | D38: 512025891 | E38: ח.פ. | F38: אלבר אגח יח | G38: IL0011587404 | H38: ISIN | I38: לא צמוד למדד המחירים לצרכן | J38: ישראל | K38: ישראל | L38: סחיר | M38: TASE | N38: שירותים | O38: לא | P38: ilA+ | Q38: S&P מעלות | R38: נייר ערך | S38: ILS | T38: 0.884 | U38: 13/01/2027 | V38: 0.0325 | W38: 0.056 | X38: החוב לא נחות | Z38: 48808.14 | AA38: 1 | AB38: 98.74 | AC38: 0 | AD38: 48.19316 | AG38: שווי הוגן | AH38: 0.00014962465 | AI38: 9.2928572e-05 | AJ38: 1.1746019e-05
A39: 13908 | B39: 13909 | C39: אלומיי קפיטל בע"מ | D39: 520039868 | E39: ח.פ. | F39: אלומיי אגח ג | G39: IL0011593758 | H39: ISIN | I39: לא צמוד למדד המחירים לצרכן | J39: ישראל | K39: ישראל | L39: סחיר | M39: TASE | N39: אנרגיה מתחדשת | O39: לא | P39: NR | Q39: NR | R39: נייר ערך | S39: ILS | T39: 0.247 | U39: 30/06/2025 | V39: 0.0355 | W39: 0.0674 | X39: החוב לא נחות | Z39: 304501 | AA39: 1 | AB39: 100.15 | AC39: 0 | AD39: 304.95775 | AG39: שווי הוגן | AH39: 0.0021263858 | AI39: 0.00058803548 | AJ39: 7.4326723e-05
A40: 13908 | B40: 13909 | C40: ביג מרכזי קניות בע"מ | D40: 513623314 | E40: ח.פ. | F40: ביג אגח יג | G40: IL0011595167 | H40: ISIN | I40: צמוד למדד המחירים לצרכן | J40: ישראל | K40: ישראל | L40: סחיר | M40: TASE | N40: נדל"ן מניב בישראל | O40: לא | P40: ilAA | Q40: S&P מעלות | R40: נייר ערך | S40: ILS | T40: 3.19 | U40: 25/03/2029 | V40: 0.0078 | W40: 0.0279 | X40: החוב לא נחות | Z40: 151000.15 | AA40: 1 | AB40: 107.52 | AC40: 0 | AD40: 162.35536 | AG40: שווי הוגן | AH40: 0.00026036394 | AI40: 0.0003130621 | AJ40: 3.9570537e-05
A41: 13908 | B41: 13909 | C41: נמקו ריאלטי לטד | D41: 1905761 | E41: LEI | F41: נמקו אגח ב | G41: IL0011602583 | H41: ISIN | I41: לא צמוד למדד המחירים לצרכן | J41: ישראל | K41: ארה"ב | L41: סחיר | M41: TASE | N41: נדל"ן מניב בחו"ל | O41: לא | P41: ilAA- | Q41: S&P מעלות | R41: נייר ערך | S41: ILS | T41: 3.281 | U41: 15/10/2032 | V41: 0.045 | W41: 0.0601 | X41: החוב לא נחות | Z41: 1440579.3 | AA41: 1 | AB41: 97.47 | AC41: 0 | AD41: 1404.1327 | AG41: שווי הוגן | AH41: 0.0016678934 | AI41: 0.0027075221 | AJ41: 0.00034222636
A42: 13908 | B42: 13909 | C42: סילברסטין נכסים לימיטד | D42: 1970336 | E42: LEI | F42: סילברסטין אגח ב | G42: IL0011605974 | H42: ISIN | I42: לא צמוד למדד המחירים לצרכן | J42: ישראל | K42: ארה"ב | L42: סחיר | M42: TASE | N42: נדל"ן מניב בחו"ל | O42: לא | P42: ilAA | Q42: S&P מעלות | R42: נייר ערך | S42: ILS | T42: 1.674 | U42: 31/12/2027 | V42: 0.0349 | W42: 0.0586 | X42: החוב לא נחות | Z42: 1450000 | AA42: 1 | AB42: 97.15 | AC42: 0 | AD42: 1408.675 | AG42: שווי הוגן | AH42: 0.0015335763 | AI42: 0.0027162808 | AJ42: 0.00034333345
A43: 13908 | B43: 13909 | C43: יוניברסל מוטורס ישראל בע"מ | D43: 511809071 | E43: ח.פ. | F43: יוניברסל אגח ג | G43: IL0011606709 | H43: ISIN | I43: צמוד למדד המחירים לצרכן | J43: ישראל | K43: ישראל | L43: סחיר | M43: TASE | N43: מסחר | O43: לא | P43: ilAA- | Q43: S&P מעלות | R43: נייר ערך | S43: ILS | T43: 1.215 | U43: 46668 | V43: 0.0105 | W43: 0.0289 | X43: החוב לא נחות | Z43: 1083333.3 | AA43: 1 | AB43: 112.32 | AC43: 0 | AD43: 1216.8 | AG43: שווי הוגן | AH43: 0.0023659375 | AI43: 0.0023462974 | AJ43: 0.00029656815
A44: 13908 | B44: 13909 | C44: אמ.ג'י.ג'י (בי.וי.אי) לימיטד | D44: 1981143 | E44: LEI | F44: אמ.ג'יג'י אגח ב | G44: IL0011608119 | H44: ISIN | I44: לא צמוד למדד המחירים לצרכן | J44: ישראל | K44: ארה"ב | L44: סחיר | M44: TASE | N44: אשראי חוץ בנקאי | O44: לא | P44: A1.il | Q44: מידרוג Moodys | R44: נייר ערך | S44: ILS | T44: 0.474 | U44: 21/09/2025 | V44: 0.0475 | W44: 0.0595 | X44: החוב לא נחות | Z44: 380952.38 | AA44: 1 | AB44: 99.61 | AC44: 0 | AD44: 379.46667 | AG44: שווי הוגן | AH44: 0.00060363788 | AI44: 0.00073170748 | AJ44: 9.2486629e-05
A45: 13908 | B45: 13909 | C45: איירפורט סיטי בע"מ | D45: 511659401 | E45: ח.פ. | F45: ארפורט אגח ט | G45: IL0011609448 | H45: ISIN | I45: צמוד למדד המחירים לצרכן | J45: ישראל | K45: ישראל | L45: סחיר | M45: TASE | N45: נדל"ן מניב בישראל | O45: לא | P45: ilAA | Q45: S&P מעלות | R45: נייר ערך | S45: ILS | T45: 4.91 | U45: 30/08/2035 | V45: 0.0065 | W45: 0.0297 | X45: החוב לא נחות | Z45: 60561.8 | AA45: 1 | AB45: 102.5 | AC45: 0 | AD45: 62.07584 | AG45: שווי הוגן | AH45: 2.6812806e-05 | AI45: 0.00011969788 | AJ45: 1.5129616e-05
A46: 13908 | B46: 13909 | C46: ווסטדייל אמריקה לימיטד | D46: 1991033 | E46: LEI | F46: ווסטדייל אגח ב | G46: IL0011613226 | H46: ISIN | I46: לא צמוד למדד המחירים לצרכן | J46: ישראל | K46: ארה"ב | L46: סחיר | M46: TASE | N46: נדל"ן מניב בחו"ל | O46: לא | P46: ilA+ | Q46: S&P מעלות | R46: נייר ערך | S46: ILS | T46: 1.724 | U46: 31/07/2028 | V46: 0.0435 | W46: 0.0612 | X46: החוב לא נחות | Z46: 352000 | AA46: 1 | AB46: 97.91 | AC46: 0 | AD46: 344.6432 | AG46: שווי הוגן | AH46: 0.00090721649 | AI46: 0.00066455904 | AJ46: 8.3999176e-05
A47: 13908 | B47: 13909 | C47: אמות השקעות בע"מ | D47: 520026683 | E47: ח.פ. | F47: אמות אגח ז | G47: IL0011628661 | H47: ISIN | I47: לא צמוד למדד המחירים לצרכן | J47: ישראל | K47: ישראל | L47: סחיר | M47: TASE | N47: נדל"ן מניב בישראל | O47: לא | P47: ilAA | Q47: S&P מעלות | R47: נייר ערך | S47: ILS | T47: 4.914 | U47: 48335 | V47: 0.0244 | W47: 0.0515 | X47: החוב לא נחות | Z47: 532905 | AA47: 1 | AB47: 88.38 | AC47: 0 | AD47: 470.98144 | AG47: שווי הוגן | AH47: 0.00043848296 | AI47: 0.00090817104 | AJ47: 0.00011479133
A48: 13908 | B48: 13909 | C48: הבינלאומי הראשון הנפקות בע"מ | D48: 513141879 | E48: ח.פ. | F48: בינל הנפק התחכה | G48: IL0011670309 | H48: ISIN | I48: צמוד למדד המחירים לצרכן | J48: ישראל | K48: ישראל | L48: סחיר | M48: TASE | N48: בנקים | O48: לא | P48: ilAA- | Q48: S&P מעלות | R48: נייר ערך | S48: ILS | T48: 1.205 | U48: 23/06/2031 | V48: 0.0232 | W48: 0.0281 | X48: החוב לא נחות | Z48: 100000 | AA48: 1 | AB48: 117.07 | AC48: 0 | AD48: 117.07 | AG48: שווי הוגן | AH48: 0.00033333333 | AI48: 0.0002257405 | AJ48: 2.853323e-05
A49: 13908 | B49: 13909 | C49: סלע קפיטל נדל"ן בע"מ | D49: 513992529 | E49: ח.פ. | F49: סלע נדלן אגח ד | G49: IL0011671471 | H49: ISIN | I49: צמוד למדד המחירים לצרכן | J49: ישראל | K49: ישראל | L49: סחיר | M49: TASE | N49: נדל"ן מניב בישראל | O49: לא | P49: Aa3.il | Q49: מידרוג Moodys | R49: נייר ערך | S49: ILS | T49: 6.149 | U49: 27/03/2033 | V49: 0.0158 | W49: 0.0316 | X49: החוב לא נחות | Z49: 623050.06 | AA49: 1 | AB49: 105.26 | AC49: 0 | AD49: 655.82249 | AG49: שווי הוגן | AH49: 0.00056498571 | AI49: 0.0012645912 | AJ49: 0.00015984226
A50: 13908 | B50: 13909 | C50: שיכון ובינוי בע"מ | D50: 520036104 | E50: ח.פ. | F50: שכון ובי אגח 9 | G50: IL0011673865 | H50: ISIN | I50: צמוד למדד המחירים לצרכן | J50: ישראל | K50: ישראל | L50: סחיר | M50: TASE | N50: בנייה | O50: לא | P50: ilA | Q50: S&P מעלות | R50: נייר ערך | S50: ILS | T50: 3.986 | U50: 31/03/2031 | V50: 0.0325 | W50: 0.0372 | X50: החוב לא נחות | Z50: 86363.64 | AA50: 1 | AB50: 113.73 | AC50: 0 | AD50: 98.22137 | AG50: שווי הוגן | AH50: 0.00025290026 | AI50: 0.00018939558 | AJ50: 2.3939292e-05
A51: 13908 | B51: 13909 | C51: מגוריט ישראל בע"מ | D51: 515434074 | E51: ח.פ. | F51: מגוריט אגח ב | G51: IL0011683500 | H51: ISIN | I51: צמוד למדד המחירים לצרכן | J51: ישראל | K51: ישראל | L51: סחיר | M51: TASE | N51: נדל"ן מניב בישראל | O51: לא | P51: ilA- | Q51: S&P מעלות | R51: נייר ערך | S51: ILS | T51: 0.75 | U51: 31/12/2025 | V51: 0.001 | W51: 0.0434 | X51: החוב לא נחות | Z51: 11000 | AA51: 1 | AB51: 116.52 | AC51: 0 | AD51: 12.8172 | AG51: שווי הוגן | AH51: 1.9111822e-05 | AI51: 2.4714795e-05 | AJ51: 3.1239097e-06
A52: 13908 | B52: 13909 | C52: אנרג'יקס-אנרגיות מתחדשות בע"מ | D52: 513901371 | E52: ח.פ. | F52: אנרג'יקס אג ב | G52: IL0011684839 | H52: ISIN | I52: אג"ח להמרה לא צמוד למדד המחירים לצרכן | J52: ישראל | K52: ישראל | L52: סחיר | M52: TASE | N52: אנרגיה מתחדשת | O52: לא | P52: ilA | Q52: S&P מעלות | R52: נייר ערך | S52: ILS | T52: 2.328 | U52: 46395 | V52: 0.0025 | W52: 0.0552 | X52: החוב לא נחות | Z52: 1000000 | AA52: 1 | AB52: 88.8 | AC52: 0 | AD52: 888 | AG52: שווי הוגן | AH52: 0.0017649073 | AI52: 0.001712288 | AJ52: 0.00021643041
A53: 13908 | B53: 13909 | C53: אלון רבוע כחול ישראל בע"מ | D53: 520042847 | E53: ח.פ. | F53: אלון רבוע אגח ו | G53: IL0011691271 | H53: ISIN | I53: לא צמוד למדד המחירים לצרכן | J53: ישראל | K53: ישראל | L53: סחיר | M53: TASE | N53: השקעה ואחזקות | O53: לא | P53: ilA+ | Q53: S&P מעלות | R53: נייר ערך | S53: ILS | T53: 0.981 | U53: 30/09/2026 | V53: 0.039 | W53: 0.0546 | X53: החוב לא נחות | Z53: 1082400 | AA53: 1 | AB53: 98.59 | AC53: 0 | AD53: 1067.1382 | AG53: שווי הוגן | AH53: 0.0018781802 | AI53: 0.0020577116 | AJ53: 0.00026009138
A54: 13908 | B54: 13909 | C54: מימון ישיר מקבוצת ישיר (2006) | D54: 513893123 | E54: ח.פ. | F54: מימון ישיר אגחג | G54: IL0011712143 | H54: ISIN | I54: צמוד למדד המחירים לצרכן | J54: ישראל | K54: ישראל | L54: סחיר | M54: TASE | N54: אשראי חוץ בנקאי | O54: לא | P54: A1.il | Q54: מידרוג Moodys | R54: נייר ערך | S54: ILS | T54: 0.531 | U54: 31/12/2025 | V54: 0.0185 | W54: 0.0296 | X54: החוב לא נחות | Z54: 3500000 | AA54: 1 | AB54: 115.43 | AC54: 0 | AD54: 4040.05 | AG54: שווי הוגן | AH54: 0.013557484 | AI54: 0.0077902357 | AJ54: 0.00098467305
A55: 13908 | B55: 13909 | C55: ריט 1 בע"מ | D55: 513821488 | E55: ח.פ. | F55: ריט 1 אגח ז | G55: IL0011712713 | H55: ISIN | I55: צמוד למדד המחירים לצרכן | J55: ישראל | K55: ישראל | L55: סחיר | M55: TASE | N55: נדל"ן מניב בישראל | O55: לא | P55: ilAA | Q55: S&P מעלות | R55: נייר ערך | S55: ILS | T55: 6.243 | U55: 20/09/2034 | V55: 0.025 | W55: 0.0319 | X55: החוב לא נחות | Z55: 1417566.6 | AA55: 1 | AB55: 111 | AC55: 0 | AD55: 1573.4989 | AG55: שווי הוגן | AH55: 0.0010504496 | AI55: 0.0030341028 | AJ55: 0.00038350564
A56: 13908 | B56: 13909 | C56: ירושלים מימון והנפקות (2005) ב | D56: 513682146 | E56: ח.פ. | F56: ירושליםהנ אגחטז | G56: IL0011721706 | H56: ISIN | I56: צמוד למדד המחירים לצרכן | J56: ישראל | K56: ישראל | L56: סחיר | M56: TASE | N56: בנקים | O56: לא | P56: ilAA- | Q56: S&P מעלות | R56: נייר ערך | S56: ILS | T56: 1.712 | U56: 30/06/2028 | V56: 0.002 | W56: 0.0267 | X56: החוב לא נחות | Z56: 500000 | AA56: 1 | AB56: 111.08 | AC56: 0 | AD56: 555.4 | AG56: שווי הוגן | AH56: 0.00059339715 | AI56: 0.0010709513 | AJ56: 0.0001353665
A57: 13908 | B57: 13909 | C57: אמות השקעות בע"מ | D57: 520026683 | E57: ח.פ. | F57: אמות אגח ח | G57: IL0011727828 | H57: ISIN | I57: צמוד למדד המחירים לצרכן | J57: ישראל | K57: ישראל | L57: סחיר | M57: TASE | N57: נדל"ן מניב בישראל | O57: לא | P57: ilAA | Q57: S&P מעלות | R57: נייר ערך | S57: ILS | T57: 5.118 | U57: 48335 | V57: 0.0092 | W57: 0.0298 | X57: החוב לא נחות | Z57: 2630000 | AA57: 1 | AB57: 104.6 | AC57: 0 | AD57: 2750.98 | AG57: שווי הוגן | AH57: 0.0010167344 | AI57: 0.0053045835 | AJ57: 0.00067049068
A58: 13908 | B58: 13909 | C58: קרסו מוטורס בע"מ | D58: 514065283 | E58: ח.פ. | F58: קרסו מוט' אגח ד | G58: IL0011735664 | H58: ISIN | I58: לא צמוד למדד המחירים לצרכן | J58: ישראל | K58: ישראל | L58: סחיר | M58: TASE | N58: מסחר | O58: לא | P58: ilAA- | Q58: S&P מעלות | R58: נייר ערך | S58: ILS | T58: 1.807 | U58: 46762 | V58: 0.0215 | W58: 0.0519 | X58: החוב לא נחות | Z58: 2639469.7 | AA58: 1 | AB58: 94.82 | AC58: 23.2839 | AD58: 2526.0291 | AG58: שווי הוגן | AH58: 0.0034741612 | AI58: 0.0048708214 | AJ58: 0.00061566386
A59: 13908 | B59: 13909 | C59: אפי נכסים בע"מ | D59: 510560188 | E59: ח.פ. | F59: אפי נכסים אגחיב | G59: IL0011737645 | H59: ISIN | I59: לא צמוד למדד המחירים לצרכן | J59: ישראל | K59: ישראל | L59: סחיר | M59: TASE | N59: נדל"ן מניב בחו"ל | O59: לא | P59: ilA+ | Q59: S&P מעלות | R59: נייר ערך | S59: ILS | T59: 2.251 | U59: 15/09/2027 | V59: 0.023 | W59: 0.0528 | X59: החוב לא נחות | Z59: 95057.86 | AA59: 1 | AB59: 93.84 | AC59: 0 | AD59: 89.2023 | AG59: שווי הוגן | AH59: 0.00013178055 | AI59: 0.00017200454 | AJ59: 2.1741093e-05
A60: 13908 | B60: 13909 | C60: רותם שני יזמות והשקעות בע"מ | D60: 512287517 | E60: ח.פ. | F60: רותם שני אגח א | G60: IL0011739963 | H60: ISIN | I60: לא צמוד למדד המחירים לצרכן | J60: ישראל | K60: ישראל | L60: סחיר | M60: TASE | N60: בנייה | O60: לא | P60: NR | Q60: NR | R60: נייר ערך | S60: ILS | T60: 0.247 | U60: 30/06/2025 | V60: 0.0449 | W60: 0.0806 | X60: החוב לא נחות | Z60: 74810.29 | AA60: 1 | AB60: 100.31 | AC60: 0 | AD60: 75.0422 | AG60: שווי הוגן | AH60: 0.0021165113 | AI60: 0.00014470029 | AJ60: 1.8289881e-05
A61: 13908 | B61: 13909 | C61: שיכון ובינוי בע"מ | D61: 520036104 | E61: ח.פ. | F61: שכון ובי אגח 10 | G61: IL0011751323 | H61: ISIN | I61: לא צמוד למדד המחירים לצרכן | J61: ישראל | K61: ישראל | L61: סחיר | M61: TASE | N61: בנייה | O61: לא | P61: ilA | Q61: S&P מעלות | R61: נייר ערך | S61: ILS | T61: 2.85 | U61: 30/04/2030 | V61: 0.028 | W61: 0.0597 | X61: החוב לא נחות | Z61: 3000865 | AA61: 1 | AB61: 92.74 | AC61: 0 | AD61: 2783.0022 | AG61: שווי הוגן | AH61: 0.0024431461 | AI61: 0.0053663304 | AJ61: 0.00067829538
A62: 13908 | B62: 13909 | C62: מימון ישיר מקבוצת ישיר (2006) | D62: 513893123 | E62: ח.פ. | F62: מימון ישיר אגחד | G62: IL0011756603 | H62: ISIN | I62: צמוד למדד המחירים לצרכן | J62: ישראל | K62: ישראל | L62: סחיר | M62: TASE | N62: אשראי חוץ בנקאי | O62: לא | P62: A1.il | Q62: מידרוג Moodys | R62: נייר ערך | S62: ILS | T62: 0.431 | U62: 46024 | V62: 0.01 | W62: 0.0287 | X62: החוב לא נחות | Z62: 316492.33 | AA62: 1 | AB62: 113.7 | AC62: 0 | AD62: 359.85178 | AG62: שווי הוגן | AH62: 0.0018713402 | AI62: 0.00069388502 | AJ62: 8.7705932e-05
A63: 13908 | B63: 13909 | C63: מגוריט ישראל בע"מ | D63: 515434074 | E63: ח.פ. | F63: מגוריט אגח ג | G63: IL0011759755 | H63: ISIN | I63: צמוד למדד המחירים לצרכן | J63: ישראל | K63: ישראל | L63: סחיר | M63: TASE | N63: נדל"ן מניב בישראל | O63: לא | P63: ilA- | Q63: S&P מעלות | R63: נייר ערך | S63: ILS | T63: 3.485 | U63: 46762 | V63: 0.003 | W63: 0.0312 | X63: החוב לא נחות | Z63: 144220 | AA63: 1 | AB63: 103.87 | AC63: 0 | AD63: 149.80131 | AG63: שווי הוגן | AH63: 0.00030600856 | AI63: 0.00028885472 | AJ63: 3.6510764e-05
A64: 13908 | B64: 13909 | C64: ג'נריישן קפיטל בע"מ | D64: 515846558 | E64: ח.פ. | F64: ג'נרישן קפ אגחב | G64: IL0011775264 | H64: ISIN | I64: צמוד למדד המחירים לצרכן | J64: ישראל | K64: ישראל | L64: סחיר | M64: TASE | N64: השקעה ואחזקות | O64: לא | P64: ilA+ | Q64: S&P מעלות | R64: נייר ערך | S64: ILS | T64: 3.342 | U64: 30/06/2031 | V64: 0.0075 | W64: 0.0319 | X64: החוב לא נחות | Z64: 10320 | AA64: 1 | AB64: 105.31 | AC64: 0 | AD64: 10.86799 | AG64: שווי הוגן | AH64: 2.2833049e-05 | AI64: 2.0956227e-05 | AJ64: 2.6488328e-06
A65: 13908 | B65: 13909 | C65: בי קומיוניקיישנס בע"מ | D65: 512832742 | E65: ח.פ. | F65: בי קומיונק אגחו | G65: IL0011781510 | H65: ISIN | I65: לא צמוד למדד המחירים לצרכן | J65: ישראל | K65: ישראל | L65: סחיר | M65: TASE | N65: תקשורת ומדיה | O65: לא | P65: A3.il | Q65: מידרוג Moodys | R65: נייר ערך | S65: ILS | T65: 0.167 | U65: 30/11/2026 | V65: 0.0365 | W65: 0.0624 | X65: החוב לא נחות | Z65: 195815 | AA65: 1 | AB65: 100.8 | AC65: 0 | AD65: 197.38152 | AG65: שווי הוגן | AH65: 0.0001937647 | AI65: 0.00038060137 | AJ65: 4.8107391e-05
A66: 13908 | B66: 13909 | C66: קבוצת עזריאלי בע"מ | D66: 510960719 | E66: ח.פ. | F66: עזריאלי אגח ז | G66: IL0011786725 | H66: ISIN | I66: צמוד למדד המחירים לצרכן | J66: ישראל | K66: ישראל | L66: סחיר | M66: TASE | N66: נדל"ן מניב בישראל | O66: לא | P66: ilAA+ | Q66: S&P מעלות | R66: נייר ערך | S66: ILS | T66: 6.472 | U66: 49712 | V66: 0.009 | W66: 0.0307 | X66: החוב לא נחות | Z66: 2136400 | AA66: 1 | AB66: 99.26 | AC66: 0 | AD66: 2120.5906 | AG66: שווי הוגן | AH66: 0.00077637281 | AI66: 0.0040890338 | AJ66: 0.00051684718
A67: 13908 | B67: 13909 | C67: קבוצת עזריאלי בע"מ | D67: 510960719 | E67: ח.פ. | F67: עזריאלי אגח ח | G67: IL0011786808 | H67: ISIN | I67: צמוד למדד המחירים לצרכן | J67: ישראל | K67: ישראל | L67: סחיר | M67: TASE | N67: נדל"ן מניב בישראל | O67: לא | P67: ilAA+ | Q67: S&P מעלות | R67: נייר ערך | S67: ILS | T67: 9.994 | U67: 51533 | V67: 0.0169 | W67: 0.0329 | X67: החוב לא נחות | Z67: 2150000 | AA67: 1 | AB67: 97.7 | AC67: 0 | AD67: 2100.55 | AG67: שווי הוגן | AH67: 0.00049278471 | AI67: 0.0040503904 | AJ67: 0.00051196272
A68: 13908 | B68: 13909 | C68: דה לסר גרופ לימיטד | D68: 1427976 | E68: LEI | F68: דה לסר אגח ז | G68: IL0011789208 | H68: ISIN | I68: לא צמוד למדד המחירים לצרכן | J68: ישראל | K68: ארה"ב | L68: סחיר | M68: TASE | N68: נדל"ן מניב בחו"ל | O68: לא | P68: ilA- | Q68: S&P מעלות | R68: נייר ערך | S68: ILS | T68: 1.607 | U68: 30/06/2028 | V68: 0.0775 | W68: 0.0695 | X68: החוב לא נחות | Z68: 238400 | AA68: 1 | AB68: 103.4 | AC68: 0 | AD68: 246.5056 | AG68: שווי הוגן | AH68: 0.00055498546 | AI68: 0.00047532499 | AJ68: 6.0080301e-05
A69: 13908 | B69: 13909 | C69: סטרוברי פילדס ריט לימיטד | D69: 1654 | E69: מספר מנפיק | F69: סטרוברי ג חסום | G69: IL0011790198 | H69: ISIN | I69: לא צמוד למדד המחירים לצרכן | J69: ישראל | K69: ארה"ב | L69: חסום | M69: TASE | N69: נדל"ן מניב בחו"ל | O69: לא | P69: NR | Q69: NR | R69: נייר ערך | S69: ILS | T69: 1.607 | U69: 31/07/2026 | V69: 0.0775 | W69: 0.0695 | X69: החוב לא נחות | Z69: 750000 | AA69: 1 | AB69: 100.1569 | AC69: 0 | AD69: 751.17675 | AG69: שווי הוגן | AH69: 0.0028042246 | AI69: 0.0014484583 | AJ69: 0.00018308276
A70: 13908 | B70: 13909 | C70: סטרוברי פילדס ריט לימיטד | D70: 1863501 | E70: LEI | F70: סטרוברי אגח ג | G70: IL0011790198 | H70: ISIN | I70: לא צמוד למדד המחירים לצרכן | J70: ישראל | K70: ארה"ב | L70: סחיר | M70: TASE | N70: נדל"ן מניב בחו"ל | O70: לא | P70: ilAA- | Q70: S&P מעלות | R70: נייר ערך | S70: ILS | T70: 1.22 | U70: 31/07/2026 | V70: 0.057 | W70: 0.0635 | X70: החוב לא נחות | Z70: 738872.34 | AA70: 1 | AB70: 100.29 | AC70: 0 | AD70: 741.01507 | AG70: שווי הוגן | AH70: 0.0027626186 | AI70: 0.001428864 | AJ70: 0.00018060607
A71: 13908 | B71: 13909 | C71: קבוצת דוראל משאבי אנרגיה מתחדש | D71: 515364891 | E71: ח.פ. | F71: דוראל אגח א | G71: IL0011791345 | H71: ISIN | I71: צמוד למדד המחירים לצרכן | J71: ישראל | K71: ישראל | L71: סחיר | M71: TASE | N71: אנרגיה מתחדשת | O71: לא | P71: NR | Q71: NR | R71: נייר ערך | S71: ILS | T71: 2.236 | U71: 30/06/2028 | V71: 0.0158 | W71: 0.0371 | X71: החוב לא נחות | Z71: 1866661.8 | AA71: 1 | AB71: 109.09 | AC71: 0 | AD71: 2036.3413 | AG71: שווי הוגן | AH71: 0.0049841221 | AI71: 0.0039265798 | AJ71: 0.00049631327
A72: 13908 | B72: 13909 | C72: ע.י. נופר אנרג'י בע"מ | D72: 514599943 | E72: ח.פ. | F72: נופר אנרג אגח א | G72: IL0011793408 | H72: ISIN | I72: צמוד למדד המחירים לצרכן | J72: ישראל | K72: ישראל | L72: סחיר | M72: TASE | N72: אנרגיה מתחדשת | O72: לא | P72: A3.il | Q72: מידרוג Moodys | R72: נייר ערך | S72: ILS | T72: 2.21 | U72: 31/12/2027 | V72: 0.0148 | W72: 0.0311 | X72: החוב לא נחות | Z72: 3888337.1 | AA72: 1 | AB72: 109.88 | AC72: 0 | AD72: 4272.5048 | AG72: שווי הוגן | AH72: 0.012254016 | AI72: 0.0082384671 | AJ72: 0.0010413288
A73: 13908 | B73: 13909 | C73: ביג מרכזי קניות בע"מ | D73: 513623314 | E73: ח.פ. | F73: ביג אגח יט חסום | G73: IL0010972607 | H73: ISIN | I73: לא צמוד למדד המחירים לצרכן | J73: ישראל | K73: ישראל | L73: חסום | M73: TASE | N73: נדל"ן מניב בישראל | O73: לא | P73: NR | Q73: NR | R73: נייר ערך | S73: ILS | T73: 6.681 | U73: 30/10/2029 | V73: 0.013 | W73: 0.0438 | X73: החוב לא נחות | Z73: 2000000 | AA73: 1 | AB73: 89.6376 | AC73: 0 | AD73: 1792.752 | AG73: שווי הוגן | AH73: 0.081071309 | AI73: 0.0034568782 | AJ73: 0.00043694375
A74: 13908 | B74: 13909 | C74: מימון ישיר מקבוצת ישיר (2006) | D74: 513893123 | E74: ח.פ. | F74: מימון ישיר אגחה | G74: IL0011828311 | H74: ISIN | I74: צמוד למדד המחירים לצרכן | J74: ישראל | K74: ישראל | L74: סחיר | M74: TASE | N74: אשראי חוץ בנקאי | O74: לא | P74: A1.il | Q74: מידרוג Moodys | R74: נייר ערך | S74: ILS | T74: 3.027 | U74: 31/07/2031 | V74: 0.01 | W74: 0.0334 | X74: החוב לא נחות | Z74: 3811353.6 | AA74: 1 | AB74: 105.29 | AC74: 0 | AD74: 4012.9742 | AG74: שווי הוגן | AH74: 0.0021175966 | AI74: 0.0077380268 | AJ74: 0.00097807393
A75: 13908 | B75: 13909 | C75: סולאיר אנרגיות מתחדשות בע"מ | D75: 516046307 | E75: ח.פ. | F75: סולאיר אגח א | G75: IL0011837304 | H75: ISIN | I75: צמוד למדד המחירים לצרכן | J75: ישראל | K75: ישראל | L75: סחיר | M75: TASE | N75: אנרגיה מתחדשת | O75: לא | P75: NR | Q75: NR | R75: נייר ערך | S75: ILS | T75: 2.022 | U75: 31/12/2027 | V75: 0.023 | W75: 0.0342 | X75: החוב לא נחות | Z75: 876962.53 | AA75: 1 | AB75: 110.71 | AC75: 0 | AD75: 970.88522 | AG75: שווי הוגן | AH75: 0.010591335 | AI75: 0.0018721117 | AJ75: 0.00023663185
A76: 13908 | B76: 13909 | C76: סאמיט אחזקות נדל"ן בע"מ | D76: 520043720 | E76: ח.פ. | F76: סאמיט אגח יב | G76: IL0011839201 | H76: ISIN | I76: לא צמוד למדד המחירים לצרכן | J76: ישראל | K76: ישראל | L76: סחיר | M76: TASE | N76: נדל"ן מניב בחו"ל | O76: לא | P76: Aa2.il | Q76: מידרוג Moodys | R76: נייר ערך | S76: ILS | T76: 5.511 | U76: 47858 | V76: 0.028 | W76: 0.0544 | X76: החוב לא נחות | Z76: 863265.3 | AA76: 1 | AB76: 86.97 | AC76: 12.08571 | AD76: 762.86754 | AG76: שווי הוגן | AH76: 0.0015909051 | AI76: 0.0014710011 | AJ76: 0.00018593213
A77: 13908 | B77: 13909 | C77: אפי נכסים בע"מ | D77: 510560188 | E77: ח.פ. | F77: אפי נכסים אגחיד | G77: IL0011845307 | H77: ISIN | I77: צמוד למדד המחירים לצרכן | J77: ישראל | K77: ישראל | L77: סחיר | M77: TASE | N77: נדל"ן מניב בחו"ל | O77: לא | P77: ilA+ | Q77: S&P מעלות | R77: נייר ערך | S77: ILS | T77: 4.702 | U77: 30/03/2031 | V77: 0.0154 | W77: 0.0328 | X77: החוב לא נחות | Z77: 474000 | AA77: 1 | AB77: 103.7 | AC77: 0 | AD77: 491.538 | AG77: שווי הוגן | AH77: 0.00079471398 | AI77: 0.00094780928 | AJ77: 0.00011980154
A78: 13908 | B78: 13909 | C78: אלדן תחבורה בע"מ | D78: 510454333 | E78: ח.פ. | F78: אלדן תחבו אגח ז | G78: IL0011847790 | H78: ISIN | I78: צמוד למדד המחירים לצרכן | J78: ישראל | K78: ישראל | L78: סחיר | M78: TASE | N78: שירותים | O78: לא | P78: ilA+ | Q78: S&P מעלות | R78: נייר ערך | S78: ILS | T78: 1.884 | U78: 47125 | V78: 0.01 | W78: 0.0292 | X78: החוב לא נחות | Z78: 325000 | AA78: 1 | AB78: 108.64 | AC78: 0 | AD78: 353.08 | AG78: שווי הוגן | AH78: 0.0010832124 | AI78: 0.00068082732 | AJ78: 8.605546e-05
A79: 13908 | B79: 13909 | C79: מניף-שירותים פיננסיים בע"מ | D79: 512764408 | E79: ח.פ. | F79: מניף אגח א | G79: IL0011858839 | H79: ISIN | I79: לא צמוד למדד המחירים לצרכן | J79: ישראל | K79: ישראל | L79: סחיר | M79: TASE | N79: אשראי חוץ בנקאי | O79: לא | P79: A3.il | Q79: מידרוג Moodys | R79: נייר ערך | S79: ILS | T79: 0.984 | U79: 30/09/2026 | V79: 0.069 | W79: 0.0574 | X79: החוב לא נחות | Z79: 335000 | AA79: 1 | AB79: 101.2 | AC79: 0 | AD79: 339.02 | AG79: שווי הוגן | AH79: 0.0013858093 | AI79: 0.00065371609 | AJ79: 8.2628645e-05
A80: 13908 | B80: 13909 | C80: גמא ניהול וסליקה בע"מ | D80: 512711789 | E80: ח.פ. | F80: גמא אגח ג | G80: IL0011859415 | H80: ISIN | I80: לא צמוד למדד המחירים לצרכן | J80: ישראל | K80: ישראל | L80: סחיר | M80: TASE | N80: שירותים פיננסיים | O80: לא | P80: ilAA | Q80: S&P מעלות | R80: נייר ערך | S80: ILS | T80: 0.326 | U80: 19/10/2025 | V80: 0.0585 | W80: 0.0466 | X80: החוב לא נחות | Z80: 1 | AA80: 1 | AB80: 103.05 | AC80: 0 | AD80: 0.00103 | AG80: שווי הוגן | AH80: 3.7085523e-09 | AI80: 1.9860999e-09 | AJ80: 2.5103978e-10
A81: 13908 | B81: 13909 | C81: פאוורג'ן סולאר איי בע"מ | D81: 512882747 | E81: ח.פ. | F81: פאוורג'ן אגח ב | G81: IL0011862468 | H81: ISIN | I81: צמוד למדד המחירים לצרכן | J81: ישראל | K81: ישראל | L81: סחיר | M81: TASE | N81: אנרגיה מתחדשת | O81: לא | P81: NR | Q81: NR | R81: נייר ערך | S81: ILS | T81: 1.989 | U81: 31/12/2027 | V81: 0.0295 | W81: 0.0386 | X81: החוב לא נחות | Z81: 761557.9 | AA81: 1 | AB81: 109.81 | AC81: 0 | AD81: 836.26673 | AG81: שווי הוגן | AH81: 0.003124609 | AI81: 0.0016125332 | AJ81: 0.00020382156
A82: 13908 | B82: 13909 | C82: צ.מ.ח המרמן בע"מ | D82: 512531203 | E82: ח.פ. | F82: צמח המרמן אגח ז | G82: IL0011864027 | H82: ISIN | I82: לא צמוד למדד המחירים לצרכן | J82: ישראל | K82: ישראל | L82: סחיר | M82: TASE | N82: בנייה | O82: לא | P82: Baa1.il | Q82: מידרוג Moodys | R82: נייר ערך | S82: ILS | T82: 1.68 | U82: 31/12/2027 | V82: 0.0555 | W82: 0.0583 | X82: החוב לא נחות | Z82: 270000 | AA82: 1 | AB82: 100.9 | AC82: 0 | AD82: 272.43 | AG82: שווי הוגן | AH82: 0.001875 | AI82: 0.00052531377 | AJ82: 6.6398802e-05
A83: 13908 | B83: 13909 | C83: קבוצת יובלים השקעות בע"מ | D83: 514625094 | E83: ח.פ. | F83: יובלים אגח ב | G83: IL0011869075 | H83: ISIN | I83: לא צמוד למדד המחירים לצרכן | J83: ישראל | K83: ישראל | L83: סחיר | M83: TASE | N83: בנייה | O83: לא | P83: NR | Q83: NR | R83: נייר ערך | S83: ILS | T83: 1.027 | U83: 46149 | V83: 0.056 | W83: 0.065 | X83: החוב לא נחות | Z83: 306987 | AA83: 1 | AB83: 100.53 | AC83: 0 | AD83: 308.61403 | AG83: שווי הוגן | AH83: 0.0018058059 | AI83: 0.00059508571 | AJ83: 7.5217861e-05
A84: 13908 | B84: 13909 | C84: מכלול מימון בע"מ | D84: 515763845 | E84: ח.פ. | F84: מכלול אגח א | G84: IL0011872772 | H84: ISIN | I84: לא צמוד למדד המחירים לצרכן | J84: ישראל | K84: ישראל | L84: סחיר | M84: TASE | N84: אשראי חוץ בנקאי | O84: לא | P84: A3.il | Q84: מידרוג Moodys | R84: נייר ערך | S84: ILS | T84: 0.733 | U84: 30/06/2026 | V84: 0.092 | W84: 0.0382 | X84: החוב לא נחות | Z84: 180000 | AA84: 1 | AB84: 103.99 | AC84: 0 | AD84: 187.182 | AG84: שווי הוגן | AH84: 0.0025806452 | AI84: 0.00036093412 | AJ84: 4.5621483e-05
A85: 13908 | B85: 13909 | C85: עמרם אברהם חברה לבנין בע"מ | D85: 513201582 | E85: ח.פ. | F85: עמרם אברהם אגחא | G85: IL0011880445 | H85: ISIN | I85: לא צמוד למדד המחירים לצרכן | J85: ישראל | K85: ישראל | L85: סחיר | M85: TASE | N85: בנייה | O85: לא | P85: A3.il | Q85: מידרוג Moodys | R85: נייר ערך | S85: ILS | T85: 1.134 | U85: 31/05/2027 | V85: 0.06 | W85: 0.0552 | X85: החוב לא נחות | Z85: 1635022.2 | AA85: 1 | AB85: 102.62 | AC85: 0 | AD85: 1677.8598 | AG85: שווי הוגן | AH85: 0.0065430754 | AI85: 0.003235337 | AJ85: 0.00040894131
A86: 13908 | B86: 13909 | C86: קבוצת אקרו בע"מ | D86: 511996803 | E86: ח.פ. | F86: אקרו אגח א | G86: IL0011885725 | H86: ISIN | I86: לא צמוד למדד המחירים לצרכן | J86: ישראל | K86: ישראל | L86: סחיר | M86: TASE | N86: בנייה | O86: לא | P86: A3.il | Q86: מידרוג Moodys | R86: נייר ערך | S86: ILS | T86: 2.025 | U86: 31/12/2027 | V86: 0.0453 | W86: 0.0586 | X86: החוב לא נחות | Z86: 720000 | AA86: 1 | AB86: 98.67 | AC86: 0 | AD86: 710.424 | AG86: שווי הוגן | AH86: 0.0011428571 | AI86: 0.0013698767 | AJ86: 0.00017315018
A87: 13908 | B87: 13909 | C87: אלמוגים החזקות בע"מ | D87: 513988824 | E87: ח.פ. | F87: אלמוגים אגח ט | G87: IL0011892242 | H87: ISIN | I87: לא צמוד למדד המחירים לצרכן | J87: ישראל | K87: ישראל | L87: סחיר | M87: TASE | N87: בנייה | O87: לא | P87: NR | Q87: NR | R87: נייר ערך | S87: ILS | T87: 1.3 | U87: 31/03/2027 | V87: 0.067 | W87: 0.0601 | X87: החוב לא נחות | Z87: 800000.01 | AA87: 1 | AB87: 101 | AC87: 0 | AD87: 808.00001 | AG87: שווי הוגן | AH87: 0.0085785168 | AI87: 0.0015580279 | AJ87: 0.00019693218
A88: 13908 | B88: 13909 | C88: הבינלאומי הראשון הנפקות בע"מ | D88: 513141879 | E88: ח.פ. | F88: בינל הנפ התח כז | G88: IL0011894974 | H88: ISIN | I88: צמוד למדד המחירים לצרכן | J88: ישראל | K88: ישראל | L88: סחיר | M88: TASE | N88: בנקים | O88: לא | P88: ilAA- | Q88: S&P מעלות | R88: נייר ערך | S88: ILS | T88: 3.779 | U88: 13/03/2034 | V88: 0.0299 | W88: 0.0306 | X88: החוב לא נחות | Z88: 1000000 | AA88: 1 | AB88: 107.65 | AC88: 0 | AD88: 1076.5 | AG88: שווי הוגן | AH88: 0.00125 | AI88: 0.0020757636 | AJ88: 0.00026237312
A89: 13908 | B89: 13909 | C89: קבוצת צילו-בלו בע"מ | D89: 513605519 | E89: ח.פ. | F89: צילו-בלו אגח טו | G89: IL0011898512 | H89: ISIN | I89: צמוד למדד המחירים לצרכן | J89: ישראל | K89: ישראל | L89: סחיר | M89: TASE | N89: בנייה | O89: לא | P89: NR | Q89: NR | R89: נייר ערך | S89: ILS | T89: 3.094 | U89: 46762 | V89: 0.0389 | W89: 0.0465 | X89: החוב לא נחות | Z89: 434549.93 | AA89: 1 | AB89: 111.44 | AC89: 0 | AD89: 484.26244 | AG89: שווי הוגן | AH89: 0.0036781542 | AI89: 0.00093378016 | AJ89: 0.00011802829
A90: 13908 | B90: 13909 | C90: תנופורט (1990) בע"מ | D90: 511519829 | E90: ח.פ. | F90: תנופורט ב2 חסום | G90: IL0011899197 | H90: ISIN | I90: צמוד למדד המחירים לצרכן | J90: ישראל | K90: ישראל | L90: חסום | M90: TASE | N90: נדל"ן מניב בישראל | O90: לא | P90: NR | Q90: NR | R90: נייר ערך | S90: ILS | T90: 3.094 | U90: 31/12/2026 | V90: 0.0389 | W90: 0.0465 | X90: החוב לא נחות | Z90: 1000000 | AA90: 1 | AB90: 108.4371 | AC90: 0 | AD90: 1084.371 | AG90: שווי הוגן | AH90: 0.0014388489 | AI90: 0.0020909409 | AJ90: 0.00026429151
A91: 13908 | B91: 13909 | C91: תנופורט (1990) בע"מ | D91: 511519829 | E91: ח.פ. | F91: תנופורט אגח ב | G91: IL0011899197 | H91: ISIN | I91: צמוד למדד המחירים לצרכן | J91: ישראל | K91: ישראל | L91: סחיר | M91: TASE | N91: נדל"ן מניב בישראל | O91: לא | P91: NR | Q91: NR | R91: נייר ערך | S91: ILS | T91: 1.676 | U91: 31/12/2026 | V91: 0.0343 | W91: 0.0361 | X91: החוב לא נחות | Z91: 2546000 | AA91: 1 | AB91: 108.75 | AC91: 0 | AD91: 2768.775 | AG91: שווי הוגן | AH91: 0.0036633094 | AI91: 0.0053388968 | AJ91: 0.00067482782
A92: 13908 | B92: 13909 | C92: קרסו נדל"ן בע"מ | D92: 510488190 | E92: ח.פ. | F92: קרסו נדלן אגח א | G92: IL0011900086 | H92: ISIN | I92: לא צמוד למדד המחירים לצרכן | J92: ישראל | K92: ישראל | L92: סחיר | M92: TASE | N92: בנייה | O92: לא | P92: ilA | Q92: S&P מעלות | R92: נייר ערך | S92: ILS | T92: 2.426 | U92: 30/11/2029 | V92: 0.0534 | W92: 0.0573 | X92: החוב לא נחות | Z92: 249000 | AA92: 1 | AB92: 101.03 | AC92: 0 | AD92: 251.5647 | AG92: שווי הוגן | AH92: 0.00035743508 | AI92: 0.00048508021 | AJ92: 6.1313345e-05
A93: 13908 | B93: 13909 | C93: קבוצת חג'ג' ייזום נדל"ן בע"מ | D93: 520033309 | E93: ח.פ. | F93: חג'ג' אגח יג | G93: IL0011900409 | H93: ISIN | I93: לא צמוד למדד המחירים לצרכן | J93: ישראל | K93: ישראל | L93: סחיר | M93: TASE | N93: בנייה | O93: לא | P93: NR | Q93: NR | R93: נייר ערך | S93: ILS | T93: 0 | U93: 45748 | V93: 0.0562 | W93: 0 | X93: החוב לא נחות | Z93: 756500 | AA93: 1 | AB93: 101.14 | AC93: 1.89125 | AD93: 767.01535 | AG93: שווי הוגן | AH93: 0.0037672277 | AI93: 0.0014789991 | AJ93: 0.00018694307
A94: 13908 | B94: 13909 | C94: לייטסטון אנטרפרייזס לימיטד | D94: 1630 | E94: מספר מנפיק | F94: לייטסטון אגח ג | G94: IL0011900995 | H94: ISIN | I94: לא צמוד למדד המחירים לצרכן | J94: ישראל | K94: ישראל | L94: סחיר | M94: TASE | N94: נדל"ן מניב בחו"ל | O94: לא | P94: ilA+ | Q94: S&P מעלות | R94: נייר ערך | S94: ILS | T94: 1.916 | U94: 30/04/2028 | V94: 0.0575 | W94: 0.0618 | X94: החוב לא נחות | Z94: 668000 | AA94: 1 | AB94: 101.76 | AC94: 0 | AD94: 679.7568 | AG94: שווי הוגן | AH94: 0.00074222222 | AI94: 0.0013107426 | AJ94: 0.00016567572
A95: 13908 | B95: 13909 | C95: משולם לוינשטין הנדסה וקבלנות ב | D95: 520033424 | E95: ח.פ. | F95: לונשטן הנד אגחה | G95: IL0011905861 | H95: ISIN | I95: לא צמוד למדד המחירים לצרכן | J95: ישראל | K95: ישראל | L95: סחיר | M95: TASE | N95: בנייה | O95: לא | P95: ilA+ | Q95: S&P מעלות | R95: נייר ערך | S95: ILS | T95: 2.827 | U95: 30/06/2031 | V95: 0.05 | W95: 0.0532 | X95: החוב לא נחות | Z95: 1800000 | AA95: 1 | AB95: 100.54 | AC95: 0 | AD95: 1809.72 | AG95: שווי הוגן | AH95: 0.0067720855 | AI95: 0.0034895968 | AJ95: 0.00044107932
A96: 13908 | B96: 13909 | C96: דיסקונט מנפיקים בע"מ | D96: 520029935 | E96: ח.פ. | F96: דיסקונט מנ נד ט | G96: IL0011912461 | H96: ISIN | I96: צמוד למדד המחירים לצרכן | J96: ישראל | K96: ישראל | L96: סחיר | M96: TASE | N96: בנקים | O96: לא | P96: ilAA- | Q96: S&P מעלות | R96: נייר ערך | S96: ILS | T96: 3.488 | U96: 30/11/2033 | V96: 0.0317 | W96: 0.0302 | X96: החוב לא נחות | Z96: 5760843 | AA96: 1 | AB96: 108.94 | AC96: 0 | AD96: 6275.8624 | AG96: שווי הוגן | AH96: 0.0068216021 | AI96: 0.012101446 | AJ96: 0.001529603
A97: 13908 | B97: 13909 | C97: בנק הפועלים בע"מ | D97: 520000118 | E97: ח.פ. | F97: פועלים אגח 101 | G97: IL0011913378 | H97: ISIN | I97: לא צמוד למדד המחירים לצרכן | J97: ישראל | K97: ישראל | L97: סחיר | M97: TASE | N97: בנקים | O97: לא | P97: ilAAA | Q97: S&P מעלות | R97: נייר ערך | S97: ILS | T97: 0.159 | U97: 29/05/2025 | V97: 0.0376 | W97: 0.045 | X97: החוב לא נחות | Z97: 700000 | AA97: 1 | AB97: 101.17 | AC97: 0 | AD97: 708.19 | AG97: שווי הוגן | AH97: 0.00058049519 | AI97: 0.001365569 | AJ97: 0.00017260569
A98: 13908 | B98: 13909 | C98: בנק הפועלים בע"מ | D98: 520000118 | E98: ח.פ. | F98: פועלים אגח 201 | G98: IL0011913451 | H98: ISIN | I98: צמוד למדד המחירים לצרכן | J98: ישראל | K98: ישראל | L98: סחיר | M98: TASE | N98: בנקים | O98: לא | P98: ilAAA | Q98: S&P מעלות | R98: נייר ערך | S98: ILS | T98: 3.966 | U98: 29/11/2032 | V98: 0.0139 | W98: 0.0253 | X98: החוב לא נחות | Z98: 1651530.4 | AA98: 1 | AB98: 103.09 | AC98: 0 | AD98: 1702.5627 | AG98: שווי הוגן | AH98: 0.0010322065 | AI98: 0.0032829704 | AJ98: 0.00041496209
A99: 13908 | B99: 13909 | C99: הכשרת הישוב מקבוצת נמרודי בע"מ | D99: 520020116 | E99: ח.פ. | F99: הכשרת ישוב אג24 | G99: IL0011915191 | H99: ISIN | I99: צמוד למדד המחירים לצרכן | J99: ישראל | K99: ישראל | L99: סחיר | M99: TASE | N99: נדל"ן מניב בישראל | O99: לא | P99: ilA- | Q99: S&P מעלות | R99: נייר ערך | S99: ILS | T99: 2.139 | U99: 31/12/2028 | V99: 0.0365 | W99: 0.0364 | X99: החוב לא נחות | Z99: 240000 | AA99: 1 | AB99: 108.36 | AC99: 0 | AD99: 260.064 | AG99: שווי הוגן | AH99: 0.00092007606 | AI99: 0.00050146901 | AJ99: 6.3384862e-05
A100: 13908 | B100: 13909 | C100: הכשרת הישוב מקבוצת נמרודי בע"מ | D100: 520020116 | E100: ח.פ. | F100: הכשרת ישוב אג25 | G100: IL0011915274 | H100: ISIN | I100: צמוד למדד המחירים לצרכן | J100: ישראל | K100: ישראל | L100: סחיר | M100: TASE | N100: נדל"ן מניב בישראל | O100: לא | P100: ilA | Q100: S&P מעלות | R100: נייר ערך | S100: ILS | T100: 3.077 | U100: 31/12/2029 | V100: 0.027 | W100: 0.0331 | X100: החוב לא נחות | Z100: 1746000 | AA100: 1 | AB100: 106.11 | AC100: 0 | AD100: 1852.6806 | AG100: שווי הוגן | AH100: 0.0044331103 | AI100: 0.0035724356 | AJ100: 0.00045155002
...

Sheet מניות מבכ ויהש
A1: מספר קופה/קרן/ח.פ. עבור חברת ביטוח | B1: מספר מסלול | C1: שם מנפיק | D1: מספר מנפיק | E1: סוג מספר מזהה מנפיק | F1: שם נייר ערך | G1: מספר נייר ערך | H1: סוג מספר נייר ערך | I1: מאפיין עיקרי | J1: ישראל/חו"ל | K1: מדינה לפי חשיפה כלכלית | L1: סטאטוס סחירות | M1: זירת מסחר | N1: ענף מסחר | O1: בעל עניין/צד קשור | P1: מטבע פעילות | Q1: ערך נקוב (יחידות) | R1: שער חליפין | S1: שער נייר הערך | T1: סכום לקבל (במטבע הפעילות) | U1: שווי הוגן (באלפי ש"ח) | V1: שיעור מערך נקוב מונפק | W1: שיעור מנכסי אפיק ההשקעה | X1: שיעור מסך נכסי ההשקעה
A2: 13908 | B2: 13909 | C2: ג'י סיטי בע"מ | D2: 520033234 | E2: ח.פ. | F2: ג'י סיטי | G2: IL0001260111 | H2: ISIN | I2: מניות | J2: ישראל | K2: ישראל | L2: בהשאלה | M2: TASE | N2: נדל"ן מניב בחו"ל | O2: לא | P2: ILS | Q2: 115000 | R2: 1 | S2: -1139 | T2: 0 | U2: -1309.85 | V2: 0.00057709078 | W2: -0.0021643988 | X2: -0.00031924704
A3: 13908 | B3: 13909 | C3: להב אל.אר רילאסטייט בע"מ | D3: 520034257 | E3: ח.פ. | F3: להב | G3: IL0001360101 | H3: ISIN | I3: מניות | J3: ישראל | K3: ישראל | L3: סחיר | M3: TASE | N3: השקעה ואחזקות | O3: לא | P3: ILS | Q3: 4000820 | R3: 1 | S3: 461 | T3: 0 | U3: 18443.78 | V3: 0.014954446 | W3: 0.030476539 | X3: 0.0044952645
A4: 13908 | B4: 13909 | C4: וואן טכנולוגיות תוכנה בע"מ | D4: 520034695 | E4: ח.פ. | F4: וואן טכנולוגיות | G4: IL0001610182 | H4: ISIN | I4: מניות | J4: ישראל | K4: ישראל | L4: סחיר | M4: TASE | N4: שירותי מידע | O4: לא | P4: ILS | Q4: 42688 | R4: 1 | S4: 6861 | T4: 26.59729 | U4: 2955.421 | V4: 0.00059635183 | W4: 0.0048835435 | X4: 0.00072031866
A5: 13908 | B5: 13909 | C5: איילון חברה לביטוח בע"מ | D5: 520030677 | E5: ח.פ. | F5: איילון | G5: IL0002090152 | H5: ISIN | I5: מניות | J5: ישראל | K5: ישראל | L5: סחיר | M5: TASE | N5: ביטוח | O5: לא | P5: ILS | Q5: 60000 | R5: 1 | S5: 4458 | T5: 72.11848 | U5: 2746.9185 | V5: 0.0024039495 | W5: 0.0045390136 | X5: 0.00066950077
A6: 13908 | B6: 13909 | C6: כלל החזקות עסקי ביטוח בע"מ | D6: 520036120 | E6: ח.פ. | F6: כלל עסקי ביטוח | G6: IL0002240146 | H6: ISIN | I6: מניות | J6: ישראל | K6: ישראל | L6: סחיר | M6: TASE | N6: ביטוח | O6: לא | P6: ILS | Q6: 161622 | R6: 1 | S6: 9094 | T6: 0 | U6: 14697.905 | V6: 0.0020327801 | W6: 0.024286847 | X6: 0.00358229
A7: 13908 | B7: 13909 | C7: מבנה נדל"ן (כ.ד) בע"מ | D7: 520024126 | E7: ח.פ. | F7: מבנה | G7: IL0002260193 | H7: ISIN | I7: מניות | J7: ישראל | K7: ישראל | L7: סחיר | M7: TASE | N7: נדל"ן מניב בישראל | O7: לא | P7: ILS | Q7: 510967 | R7: 1 | S7: 992.1 | T7: 48.51805 | U7: 5117.8217 | V7: 0.00069317601 | W7: 0.0084566988 | X7: 0.0012473561
A8: 13908 | B8: 13909 | C8: בזק החברה הישראלית לתקשורת בע" | D8: 520031931 | E8: ח.פ. | F8: בזק | G8: IL0002300114 | H8: ISIN | I8: מניות | J8: ישראל | K8: ישראל | L8: סחיר | M8: TASE | N8: תקשורת ומדיה | O8: לא | P8: ILS | Q8: 3358705 | R8: 1 | S8: 546.6 | T8: 0 | U8: 18358.682 | V8: 0.001212138 | W8: 0.030335922 | X8: 0.0044745236
A9: 13908 | B9: 13909 | C9: ישראמקו נגב 2 שותפות מוגבלת | D9: 550010003 | E9: ח.פ. | F9: ישראמקו יהש | G9: IL0002320179 | H9: ISIN | I9: יחידות השתתפות | J9: ישראל | K9: ישראל | L9: סחיר | M9: TASE | N9: חיפושי נפט וגז | O9: לא | P9: ILS | Q9: 1960119 | R9: 1 | S9: 203 | T9: 0 | U9: 3979.0416 | V9: 0.00075394476 | W9: 0.0065749763 | X9: 0.00096980359
A10: 13908 | B10: 13909 | C10: פורמולה מערכות (1985)בע"מ | D10: 520036690 | E10: ח.פ. | F10: פורמולה מערכות | G10: IL0002560162 | H10: ISIN | I10: מניות | J10: ישראל | K10: ישראל | L10: סחיר | M10: TASE | N10: שירותי מידע | O10: לא | P10: ILS | Q10: 3955 | R10: 1 | S10: 32170 | T10: 0 | U10: 1272.3235 | V10: 0.00025794599 | W10: 0.0021023899 | X10: 0.00031010078
A11: 13908 | B11: 13909 | C11: אורביט טכנולוג'יס בע"מ | D11: 520036153 | E11: ח.פ. | F11: אורביט | G11: IL0002650179 | H11: ISIN | I11: מניות | J11: ישראל | K11: ישראל | L11: סחיר | M11: TASE | N11: ביטחוניות | O11: לא | P11: ILS | Q11: 130200 | R11: 1 | S11: 3094 | T11: 0 | U11: 4028.388 | V11: 0.0051713888 | W11: 0.0066565164 | X11: 0.0009818307
A12: 13908 | B12: 13909 | C12: נייס בע"מ | D12: 520036872 | E12: ח.פ. | F12: נייס | G12: IL0002730112 | H12: ISIN | I12: מניות | J12: ישראל | K12: ישראל | L12: סחיר | M12: TASE | N12: תוכנה ואינטרנט | O12: לא | P12: ILS | Q12: 13701 | R12: 1 | S12: 56600 | T12: 0 | U12: 7754.766 | V12: 0.000217929 | W12: 0.012813991 | X12: 0.0018900531
A13: 13908 | B13: 13909 | C13: איי.סי.אל גרופ בע"מ | D13: 520027830 | E13: ח.פ. | F13: איי.סי.אל | G13: IL0002810146 | H13: ISIN | I13: מניות | J13: ישראל | K13: ישראל | L13: סחיר | M13: TASE | N13: כימיה, גומי ופלסטיק | O13: לא | P13: ILS | Q13: 321215 | R13: 1 | S13: 2089 | T13: 0 | U13: 6710.1813 | V13: 0.00024891452 | W13: 0.011087917 | X13: 0.0016354587
... A1469: 13918 | B1469: 15271 | C1469: קבוצת אקרו בע"מ | D1469: 511996803 | E1469: ח.פ. | F1469: אקרו2 - חסום | G1469: IL0011849028 | H1469: ISIN | I1469: מניות | J1469: ישראל | K1469: ישראל | L1469: חסום | M1469: TASE | N1469: בנייה | O1469: לא | P1469: ILS | Q1469: 20 | R1469: 1 | S1469: 4480.5667 | T1469: 0 | U1469: 0.89611 | V1469: 3.172408e-07 | W1469: 0.033255265 | X1469: 0.00086209915

Sheet קרנות סל
A1: מספר קופה/קרן/ח.פ. עבור חברת ביטוח | B1: מספר מסלול | C1: שם מנפיק | D1: מספר מנפיק | E1: סוג מספר מזהה מנפיק | F1: שם נייר ערך | G1: מספר נייר ערך | H1: סוג מספר נייר ערך | I1: מאפיין עיקרי | J1: ישראל/חו"ל | K1: מדינה לפי חשיפה כלכלית | L1: זירת מסחר | M1: סיווג הקרן | N1: בעל עניין/צד קשור | O1: מטבע פעילות | P1: ערך נקוב (יחידות) | Q1: שער חליפין | R1: שער נייר הערך | S1: סכום לקבל (במטבע הפעילות) | T1: שווי הוגן (באלפי ש"ח) | U1: שיעור מערך נקוב מונפק | V1: שיעור מנכסי אפיק ההשקעה | W1: שיעור מסך נכסי ההשקעה
A2: 13908 | B2: 13909 | C2: מיטב קרנות נאמנות בע"מ | D2: 513534974 | E2: ח.פ. | F2: תכ.תלבונד60 | G2: IL0011451015 | H2: ISIN | I2: עוקב אחר מדדים אחרים בישראל | J2: ישראל | K2: ישראל | L2: TASE | M2: 60 אג"ח בארץ - חברות והמרה-תל בונד צמוד מדד-תל בונד | N2: לא | O2: ILS | P2: 4538180 | Q2: 1 | R2: 373.81 | S2: 0 | T2: 16964.171 | U2: 0.0033326905 | V2: 0.28459376 | W2: 0.0041346423
A3: 13908 | B3: 13909 | C3: קסם קרנות נאמנות בע"מ | D3: 510938608 | E3: ח.פ. | F3: קסם.תלבונד 20 צ | G3: IL0011459604 | H3: ISIN | I3: עוקב אחר מדדים אחרים בישראל | J3: ישראל | K3: ישראל | L3: TASE | M3: 20 אג"ח בארץ - חברות והמרה-תל בונד צמוד מדד-תל בונד | N3: לא | O3: ILS | P3: 7700 | Q3: 1 | R3: 3786.32 | S3: 0 | T3: 291.54664 | U3: 0.00014758256 | V3: 0.0048910352 | W3: 7.1058061e-05
A4: 13908 | B4: 13909 | C4: אי.בי.אי קרנות נאמנות בעמ | D4: 513765339 | E4: ח.פ. | F4: IBI.תלבונד 60צד | G4: IL0011480063 | H4: ISIN | I4: עוקב אחר מדדים אחרים בישראל | J4: ישראל | K4: ישראל | L4: TASE | M4: 60 אג"ח בארץ - חברות והמרה-תל בונד צמוד מדד-תל בונד | N4: לא | O4: ILS | P4: 7718742 | Q4: 1 | R4: 374.2 | S4: 0 | T4: 28883.533 | U4: 0.0056148101 | V4: 0.48455497 | W4: 0.0070397238
A5: 13908 | B5: 13909 | C5: מגדל קרנות נאמנות בע"מ | D5: 511303661 | E5: ח.פ. | F5: SP500.MTF | G5: IL0011503336 | H5: ISIN | I5: עוקב אחר מדדי מניות בחו"ל | J5: ישראל | K5: ארה"ב | L5: TASE | M5: S&P 500 - מניות בחו"ל - מניות גיאוגרפי - חשופת מט"ח-ארה"ב | N5: לא | O5: ILS | P5: 18000 | Q5: 1 | R5: 8809 | S5: 0 | T5: 1585.62 | U5: 0.00020618557 | V5: 0.026600626 | W5: 0.00038645989
A6: 13908 | B6: 13909 | C6: קסם קרנות נאמנות בע"מ | D6: 510938608 | E6: ח.פ. | F6: CSI300.קסם | G6: IL0011627838 | H6: ISIN | I6: עוקב אחר מדדי מניות בחו"ל | J6: ישראל | K6: סין | L6: TASE | M6: מניות בחו"ל - מניות גיאוגרפי - חשופת מט"ח-אסיה - מדד אחר | N6: לא | O6: ILS | P6: 30593 | Q6: 1 | R6: 24710 | S6: 0 | T6: 7559.5303 | U6: 0.010647895 | V6: 0.12681994 | W6: 0.0018424687
A7: 13908 | B7: 13909 | C7: Ishares iBoxx $ Investment | D7: 78005 | E7: LEI | F7: ISHARES GS$ INVESTOP CORP | G7: US4642872422 | H7: ISIN | I7: עוקב אחר מדדים אחרים בחו"ל | J7: חו"ל | K7: ארה"ב | L7: NYSE | M7: Bond/Fixed Income Funds | N7: לא | O7: USD | P7: 10700 | Q7: 3.718 | R7: 10869 | S7: 0 | T7: 4323.9708 | U7: 3.9338235e-05 | V7: 0.072539657 | W7: 0.0010538725
A8: 13908 | B8: 13910 | C8: מיטב קרנות נאמנות בע"מ | D8: 513534974 | E8: ח.פ. | F8: תכ.תלבונד60 | G8: IL0011451015 | H8: ISIN | I8: עוקב אחר מדדים אחרים בישראל | J8: ישראל | K8: ישראל | L8: TASE | M8: 60 אג"ח בארץ - חברות והמרה-תל בונד צמוד מדד-תל בונד | N8: לא | O8: ILS | P8: 100000 | Q8: 1 | R8: 373.81 | S8: 0 | T8: 373.81 | U8: 7.3436718e-05 | V8: 0.047158669 | W8: 0.00019887056
A9: 13908 | B9: 13910 | C9: אי.בי.אי קרנות נאמנות בעמ | D9: 513765339 | E9: ח.פ. | F9: IBI.תלבונד 60צד | G9: IL0011480063 | H9: ISIN | I9: עוקב אחר מדדים אחרים בישראל | J9: ישראל | K9: ישראל | L9: TASE | M9: 60 אג"ח בארץ - חברות והמרה-תל בונד צמוד מדד-תל בונד | N9: לא | O9: ILS | P9: 1298733 | Q9: 1 | R9: 374.2 | S9: 0 | T9: 4859.8589 | U9: 0.00094473156 | V9: 0.61310419 | W9: 0.0025854922
A10: 13908 | B10: 13910 | C10: קסם קרנות נאמנות בע"מ | D10: 510938608 | E10: ח.פ. | F10: CSI300.קסם | G10: IL0011627838 | H10: ISIN | I10: עוקב אחר מדדי מניות בחו"ל | J10: ישראל | K10: סין | L10: TASE | M10: מניות בחו"ל - מניות גיאוגרפי - חשופת מט"ח-אסיה - מדד אחר | N10: לא | O10: ILS | P10: 4602 | Q10: 1 | R10: 24710 | S10: 0 | T10: 1137.1542 | U10: 0.0016017263 | V10: 0.14345972 | W10: 0.00060497709
A11: 13908 | B11: 13910 | C11: Ishares iBoxx $ Investment | D11: 78005 | E11: LEI | F11: ISHARES GS$ INVESTOP CORP | G11: US4642872422 | H11: ISIN | I11: עוקב אחר מדדים אחרים בחו"ל | J11: חו"ל | K11: ארה"ב | L11: NYSE | M11: Bond/Fixed Income Funds | N11: לא | O11: USD | P11: 3850 | Q11: 3.718 | R11: 10869 | S11: 0 | T11: 1555.8213 | U11: 1.4154412e-05 | V11: 0.19627742 | W11: 0.00082771205
A12: 13908 | B12: 13912 | C12: קסם קרנות נאמנות בע"מ | D12: 510938608 | E12: ח.פ. | F12: CSI300.קסם | G12: IL0011627838 | H12: ISIN | I12: עוקב אחר מדדי מניות בחו"ל | J12: ישראל | K12: סין | L12: TASE | M12: מניות בחו"ל - מניות גיאוגרפי - חשופת מט"ח-אסיה - מדד אחר | N12: לא | O12: ILS | P12: 18457 | Q12: 1 | R12: 24710 | S12: 0 | T12: 4560.7247 | U12: 0.0064239598 | V12: 1 | W12: 0.0018777923
A13: 13908 | B13: 13915 | C13: מיטב קרנות נאמנות בע"מ | D13: 513534974 | E13: ח.פ. | F13: SP500.תכ | G13: IL0011443855 | H13: ISIN | I13: עוקב אחר מדדי מניות בחו"ל | J13: ישראל | K13: ארה"ב | L13: TASE | M13: S&P 500 - מניות בחו"ל - מניות גיאוגרפי - חשופת מט"ח-ארה"ב | N13: לא | O13: ILS | P13: 69201 | Q13: 1 | R13: 24020 | S13: 0 | T13: 16622.08 | U13: 0.0019435091 | V13: 0.30926368 | W13: 0.042286755
... A99: 13918 | B99: 15273 | C99: מגדל קרנות נאמנות בע"מ | D99: 511303661 | E99: ח.פ. | F99: SP500.MTF | G99: IL0011503336 | H99: ISIN | I99: עוקב אחר מדדי מניות בחו"ל | J99: ישראל | K99: ארה"ב | L99: TASE | M99: S&P 500 - מניות בחו"ל - מניות גיאוגרפי - חשופת מט"ח-ארה"ב | N99: לא | O99: ILS | P99: 23409 | Q99: 1 | R99: 8809 | S99: 0 | T99: 2062.0988 | U99: 0.00026814433 | V99: 0.20024569 | W99: 0.086631861

Sheet קרנות נאמנות
A1: מספר קופה/קרן/ח.פ. עבור חברת ביטוח | B1: מספר מסלול | C1: שם מנפיק | D1: מספר מנפיק | E1: סוג מספר מזהה מנפיק | F1: שם נייר ערך | G1: מספר נייר ערך | H1: סוג מספר נייר ערך | I1: מאפיין עיקרי | J1: ישראל/חו"ל | K1: מדינה לפי חשיפה כלכלית | L1: סטאטוס סחירות | M1: זירת מסחר | N1: סיווג הקרן | O1: בעל עניין/צד קשור | P1: מטבע פעילות | Q1: ערך נקוב (יחידות) | R1: שער חליפין | S1: שער נייר הערך | T1: שווי הוגן (באלפי ש"ח) | U1: שיעור מערך נקוב מונפק | V1: שיעור מנכסי אפיק ההשקעה | W1: שיעור מסך נכסי ההשקעה
A2: 13908 | B2: 13909 | C2: קסם קרנות נאמנות בע"מ | D2: 5017 | E2: מספר מנפיק | F2: קסם ת"א 125 | G2: IL0051133457 | H2: ISIN | I2: מניות | J2: ישראל | K2: ישראל | L2: סחיר | M2: TASE | N2: Large & Mid Cap מניות בארץ - מניות לפי שווי שוק-מניות | O2: לא | P2: ILS | Q2: 800000 | R2: 1 | S2: 242.99 | T2: 1943.92 | U2: 0.00076892373 | V2: =T2/SUMIFS(T:T,B:B,B2) -> 0.015299562 | W2: 0.00047362539
A3: 13908 | B3: 13909 | C3: מיטב קרנות נאמנות בע"מ | D3: 513534974 | E3: ח.פ. | F3: SP 500 תכלית | G3: IL0051139983 | H3: ISIN | I3: מניות | J3: ישראל | K3: ארה"ב | L3: סחיר | M3: TASE | N3: S&P 500 - מניות בחו"ל - מניות גיאוגרפי - חשופת מט"ח-ארה"ב | O3: לא | P3: ILS | Q3: 10284000 | R3: 1 | S3: 739.54 | T3: 76054.294 | U3: 0.0071981106 | V3: =T3/SUMIFS(T:T,B:B,B3) -> 0.59858295 | W3: 0.018530209
A4: 13908 | B4: 13909 | C4: מיטב קרנות נאמנות בע"מ | D4: 513534974 | E4: ח.פ. | F4: תכלית ת"א 125 | G4: IL0051146574 | H4: ISIN | I4: מניות | J4: ישראל | K4: ישראל | L4: סחיר | M4: TASE | N4: Large & Mid Cap מניות בארץ - מניות לפי שווי שוק-מניות | O4: לא | P4: ILS | Q4: 10121800 | R4: 1 | S4: 216.03 | T4: 21866.125 | U4: 0.0077336078 | V4: =T4/SUMIFS(T:T,B:B,B4) -> 0.17209665 | W4: 0.0053275606
A5: 13908 | B5: 13909 | C5: קסם קרנות נאמנות בע"מ | D5: 510938608 | E5: ח.פ. | F5: קסם תל בונד 20 | G5: IL0051155898 | H5: ISIN | I5: מניות | J5: ישראל | K5: ישראל | L5: סחיר | M5: TASE | N5: 20 אג"ח בארץ - חברות והמרה-תל בונד צמוד מדד-תל בונד | O5: לא | P5: ILS | Q5: 17872000 | R5: 1 | S5: 142.48 | T5: 25464.026 | U5: 0.052890172 | V5: =T5/SUMIFS(T:T,B:B,B5) -> 0.20041383 | W5: 0.0062041695
A6: 13908 | B6: 13909 | C6: CIFC Global Floating Rate Cred | D6: 635400NLI1L | E6: LEI | F6: CIFC GLBL FLT RT CR-B1 USD | G6: IE0009SO3I10 | H6: ISIN | I6: אחר | J6: חו"ל | K6: גלובלי | L6: סחיר | M6: אחר | N6: Bond/Fixed Income Funds | O6: לא | P6: USD | Q6: 333.6 | R6: 3.718 | S6: 139388.4 | T6: 1728.8689 | U6: 0.0086132555 | V6: =T6/SUMIFS(T:T,B:B,B6) -> 0.013607009 | W6: 0.00042122937
A7: 13908 | B7: 13910 | C7: מיטב קרנות נאמנות בע"מ | D7: 513534974 | E7: ח.פ. | F7: SP 500 תכלית | G7: IL0051139983 | H7: ISIN | I7: מניות | J7: ישראל | K7: ארה"ב | L7: סחיר | M7: TASE | N7: S&P 500 - מניות בחו"ל - מניות גיאוגרפי - חשופת מט"ח-ארה"ב | O7: לא | P7: ILS | Q7: 1683000 | R7: 1 | S7: 739.54 | T7: 12446.458 | U7: 0.0011779872 | V7: =T7/SUMIFS(T:T,B:B,B7) -> 0.36278268 | W7: 0.006619601
A8: 13908 | B8: 13910 | C8: מיטב קרנות נאמנות בע"מ | D8: 513534974 | E8: ח.פ. | F8: תכלית ת"א 125 | G8: IL0051146574 | H8: ISIN | I8: מניות | J8: ישראל | K8: ישראל | L8: סחיר | M8: TASE | N8: Large & Mid Cap מניות בארץ - מניות לפי שווי שוק-מניות | O8: לא | P8: ILS | Q8: 3895700 | R8: 1 | S8: 216.03 | T8: 8415.8807 | U8: 0.0029765275 | V8: =T8/SUMIFS(T:T,B:B,B8) -> 0.24530157 | W8: 0.0044759538
A9: 13908 | B9: 13910 | C9: מיטב קרנות נאמנות בע"מ | D9: 513534974 | E9: ח.פ. | F9: תכ.TTFתלבונד20 | G9: IL0051154727 | H9: ISIN | I9: מניות | J9: ישראל | K9: ישראל | L9: סחיר | M9: TASE | N9: 20 אג"ח בארץ - חברות והמרה-תל בונד צמוד מדד-תל בונד | O9: לא | P9: ILS | Q9: 8468000 | R9: 1 | S9: 103.87 | T9: 8795.7116 | U9: 0.048576196 | V9: =T9/SUMIFS(T:T,B:B,B9) -> 0.25637268 | W9: 0.0046779654
A10: 13908 | B10: 13910 | C10: הראל קרנות נאמנות בע"מ | D10: 511776783 | E10: ח.פ. | F10: הרל.תלבנד 20 צמ | G10: IL0051172703 | H10: ISIN | I10: אג"ח ממשלתי | J10: ישראל | K10: ישראל | L10: סחיר | M10: TASE | N10: אג"ח בארץ - חברות והמרה-תל בונד צמוד מדד-תל בונד צמודות | O10: לא | P10: ILS | Q10: 1870000 | R10: 1 | S10: 138.26 | T10: 2585.462 | U10: 0.0046395795 | V10: =T10/SUMIFS(T:T,B:B,B10) -> 0.075359658 | W10: 0.001375068
A11: 13908 | B11: 13910 | C11: אי.בי.אי קרנות נאמנות בעמ | D11: 513765339 | E11: ח.פ. | F11: NASDAQ 100י.IBI | G11: IL0051277668 | H11: ISIN | I11: מניות | J11: ישראל | K11: ארה"ב | L11: סחיר | M11: TASE | N11: NASDAQ 100 - מניות בחו"ל - מניות גיאוגרפי - מנוטרלת מט"ח-ארה"ב | O11: לא | P11: ILS | Q11: 445000 | R11: 1 | S11: 274.25 | T11: 1220.4125 | U11: 0.000578931 | V11: =T11/SUMIFS(T:T,B:B,B11) -> 0.035571928 | W11: 0.0006490717
A12: 13908 | B12: 13910 | C12: CIFC Global Floating Rate Cred | D12: 635400NLI1L | E12: LEI | F12: CIFC GLBL FLT RT CR-B1 USD | G12: IE0009SO3I10 | H12: ISIN | I12: אחר | J12: חו"ל | K12: גלובלי | L12: סחיר | M12: אחר | N12: Bond/Fixed Income Funds | O12: לא | P12: USD | Q12: 162.93 | R12: 3.718 | S12: 139388.4 | T12: 844.37832 | U12: 0.0042067078 | V12: =T12/SUMIFS(T:T,B:B,B12) -> 0.024611486 | W12: 0.00044907937
A13: 13908 | B13: 13911 | C13: מיטב קרנות נאמנות בע"מ | D13: 513534974 | E13: ח.פ. | F13: SP 500 תכלית | G13: IL0051139983 | H13: ISIN | I13: מניות | J13: ישראל | K13: ארה"ב | L13: סחיר | M13: TASE | N13: S&P 500 - מניות בחו"ל - מניות גיאוגרפי - חשופת מט"ח-ארה"ב | O13: לא | P13: ILS | Q13: 652000 | R13: 1 | S13: 739.54 | T13: 4821.8008 | U13: 0.00045635629 | V13: =T13/SUMIFS(T:T,B:B,B13) -> 0.7877919 | W13: 0.0080661578
A14: 13908 | B14: 13911 | C14: אי.בי.אי קרנות נאמנות בעמ | D14: 513765339 | E14: ח.פ. | F14: S&P 500י.IBI | G14: IL0051274699 | H14: ISIN | I14: מניות | J14: ישראל | K14: ארה"ב | L14: סחיר | M14: TASE | N14: S&P 500 - מניות בחו"ל - מניות גיאוגרפי - חשופת מט"ח-ארה"ב | O14: לא | P14: ILS | Q14: 343000 | R14: 1 | S14: 233.44 | T14: 800.6992 | U14: 0.00022710414 | V14: =T14/SUMIFS(T:T,B:B,B14) -> 0.13081925 | W14: 0.001339451
A15: 13908 | B15: 13911 | C15: אי.בי.אי קרנות נאמנות בעמ | D15: 513765339 | E15: ח.פ. | F15: NASDAQ 100י.IBI | G15: IL0051277668 | H15: ISIN | I15: מניות | J15: ישראל | K15: ארה"ב | L15: סחיר | M15: TASE | N15: NASDAQ 100 - מניות בחו"ל - מניות גיאוגרפי - מנוטרלת מט"ח-ארה"ב | O15: לא | P15: ILS | Q15: 92959 | R15: 1 | S15: 274.25 | T15: 254.94006 | U15: 0.00012093673 | V15: =T15/SUMIFS(T:T,B:B,B15) -> 0.041652429 | W15: 0.00042647692
A16: 13908 | B16: 13911 | C16: CIFC Global Floating Rate Cred | D16: 635400NLI1L | E16: LEI | F16: CIFC GLBL FLT RT CR-B1 USD | G16: IE0009SO3I10 | H16: ISIN | I16: אחר | J16: חו"ל | K16: גלובלי | L16: סחיר | M16: אחר | N16: Bond/Fixed Income Funds | O16: לא | P16: USD | Q16: 46.93 | R16: 3.718 | S16: 139388.4 | T16: 243.21288 | U16: 0.0012116909 | V16: =T16/SUMIFS(T:T,B:B,B16) -> 0.039736427 | W16: 0.00040685909
A17: 13908 | B17: 13912 | C17: מיטב קרנות נאמנות בע"מ | D17: 513534974 | E17: ח.פ. | F17: SP 500 תכלית | G17: IL0051139983 | H17: ISIN | I17: מניות | J17: ישראל | K17: ארה"ב | L17: סחיר | M17: TASE | N17: S&P 500 - מניות בחו"ל - מניות גיאוגרפי - חשופת מט"ח-ארה"ב | O17: לא | P17: ILS | Q17: 8440200 | R17: 1 | S17: 739.54 | T17: 62418.655 | U17: 0.0059075742 | V17: =T17/SUMIFS(T:T,B:B,B17) -> 0.80226079 | W17: 0.025697584
A18: 13908 | B18: 13912 | C18: מיטב קרנות נאמנות בע"מ | D18: 513534974 | E18: ח.פ. | F18: תכלית ת"א 125 | G18: IL0051146574 | H18: ISIN | I18: מניות | J18: ישראל | K18: ישראל | L18: סחיר | M18: TASE | N18: Large & Mid Cap מניות בארץ - מניות לפי שווי שוק-מניות | O18: לא | P18: ILS | Q18: 7121600 | R18: 1 | S18: 216.03 | T18: 15384.792 | U18: 0.0054412912 | V18: =T18/SUMIFS(T:T,B:B,B18) -> 0.19773921 | W18: 0.0063338756
A19: 13908 | B19: 13913 | C19: מיטב קרנות נאמנות בע"מ | D19: 513534974 | E19: ח.פ. | F19: תכ.TTFתלבונד20 | G19: IL0051154727 | H19: ISIN | I19: מניות | J19: ישראל | K19: ישראל | L19: סחיר | M19: TASE | N19: 20 אג"ח בארץ - חברות והמרה-תל בונד צמוד מדד-תל בונד | O19: לא | P19: ILS | Q19: 960000 | R19: 1 | S19: 103.87 | T19: 997.152 | U19: 0.0055069849 | V19: =T19/SUMIFS(T:T,B:B,B19) -> 0.50102628 | W19: 0.037781825
A20: 13908 | B20: 13913 | C20: קסם קרנות נאמנות בע"מ | D20: 510938608 | E20: ח.פ. | F20: קסם תל בונד 20 | G20: IL0051155898 | H20: ISIN | I20: מניות | J20: ישראל | K20: ישראל | L20: סחיר | M20: TASE | N20: 20 אג"ח בארץ - חברות והמרה-תל בונד צמוד מדד-תל בונד | O20: לא | P20: ILS | Q20: 680000.62 | R20: 1 | S20: 142.48 | T20: 968.86488 | U20: 0.0020123852 | V20: =T20/SUMIFS(T:T,B:B,B20) -> 0.48681321 | W20: 0.036710033
A21: 13908 | B21: 13913 | C21: CIFC Global Floating Rate Cred | D21: 635400NLI1L | E21: LEI | F21: CIFC GLBL FLT RT CR-B1 USD | G21: IE0009SO3I10 | H21: ISIN | I21: אחר | J21: חו"ל | K21: גלובלי | L21: סחיר | M21: אחר | N21: Bond/Fixed Income Funds | O21: לא | P21: USD | Q21: 4.67 | R21: 3.718 | S21: 139388.4 | T21: 24.20209 | U21: 0.00012057525 | V21: =T21/SUMIFS(T:T,B:B,B21) -> 0.012160516 | W21: 0.00091701078
A22: 13908 | B22: 13915 | C22: מגדל קרנות נאמנות בע"מ | D22: 511303661 | E22: ח.פ. | F22: S&P 500 מח MTF | G22: IL0051226277 | H22: ISIN | I22: מניות | J22: ישראל | K22: ארה"ב | L22: סחיר | M22: TASE | N22: S&P 500 - מניות בחו"ל - מניות גיאוגרפי - חשופת מט"ח-ארה"ב | O22: לא | P22: ILS | Q22: 6125885 | R22: 1 | S22: 297.11 | T22: 18200.617 | U22: 0.0028589036 | V22: =T22/SUMIFS(T:T,B:B,B22) -> 0.41529883 | W22: 0.046293637
A23: 13908 | B23: 13915 | C23: אי.בי.אי קרנות נאמנות בעמ | D23: 513765339 | E23: ח.פ. | F23: NASDAQ 100י.IBI | G23: IL0051277668 | H23: ISIN | I23: מניות | J23: ישראל | K23: ארה"ב | L23: סחיר | M23: TASE | N23: NASDAQ 100 - מניות בחו"ל - מניות גיאוגרפי - מנוטרלת מט"ח-ארה"ב | O23: לא | P23: ILS | Q23: 6284300 | R23: 1 | S23: 274.25 | T23: 17234.693 | U23: 0.0081756765 | V23: =T23/SUMIFS(T:T,B:B,B23) -> 0.39325852 | W23: 0.043836789
A24: 13908 | B24: 13915 | C24: הראל קרנות נאמנות בע"מ | D24: 511776783 | E24: ח.פ. | F24: S&P 500 הראל | G24: IL0051292758 | H24: ISIN | I24: מניות | J24: ישראל | K24: ארה"ב | L24: סחיר | M24: TASE | N24: S&P 500 - מניות בחו"ל - מניות גיאוגרפי - חשופת מט"ח-ארה"ב | O24: לא | P24: ILS | Q24: 2533000 | R24: 1 | S24: 227.9 | T24: 5772.707 | U24: 0.00077469414 | V24: =T24/SUMIFS(T:T,B:B,B24) -> 0.13172072 | W24: 0.014682997
A25: 13908 | B25: 13915 | C25: אי.בי.אי קרנות נאמנות בעמ | D25: 513765339 | E25: ח.פ. | F25: STOXX-E600י.IBI | G25: IL0051307523 | H25: ISIN | I25: מניות | J25: ישראל | K25: אירופה | L25: סחיר | M25: TASE | N25: STOXX EUROPE 600 - מניות בחו"ל - מניות גיאוגרפי - מנוטרלת מט"ח-אירופה כללי | O25: לא | P25: ILS | Q25: 1671030 | R25: 1 | S25: 156.63 | T25: 2617.3343 | U25: 0.0076866703 | V25: =T25/SUMIFS(T:T,B:B,B25) -> 0.059721924 | W25: 0.0066572427
A26: 13908 | B26: 13916 | C26: מגדל קרנות נאמנות בע"מ | D26: 511303661 | E26: ח.פ. | F26: S&P 500 מח MTF | G26: IL0051226277 | H26: ISIN | I26: מניות | J26: ישראל | K26: ארה"ב | L26: סחיר | M26: TASE | N26: S&P 500 - מניות בחו"ל - מניות גיאוגרפי - חשופת מט"ח-ארה"ב | O26: לא | P26: ILS | Q26: 6620 | R26: 1 | S26: 297.11 | T26: 19.66868 | U26: 3.0895033e-06 | V26: =T26/SUMIFS(T:T,B:B,B26) -> 0.014264664 | W26: 0.0001001165
A27: 13908 | B27: 13916 | C27: קסם קרנות נאמנות בע"מ | D27: 510938608 | E27: ח.פ. | F27: S&P 500 קסם | G27: IL0051244825 | H27: ISIN | I27: מניות | J27: ישראל | K27: ארה"ב | L27: סחיר | M27: TASE | N27: S&P 500 - מניות בחו"ל - מניות גיאוגרפי - חשופת מט"ח-ארה"ב | O27: לא | P27: ILS | Q27: 30000 | R27: 1 | S27: 281.63 | T27: 84.489 | U27: 7.1038625e-06 | V27: =T27/SUMIFS(T:T,B:B,B27) -> 0.061275448 | W27: 0.00043006153
A28: 13908 | B28: 13916 | C28: אי.בי.אי קרנות נאמנות בעמ | D28: 513765339 | E28: ח.פ. | F28: S&P 500י.IBI | G28: IL0051274699 | H28: ISIN | I28: מניות | J28: ישראל | K28: ארה"ב | L28: סחיר | M28: TASE | N28: S&P 500 - מניות בחו"ל - מניות גיאוגרפי - חשופת מט"ח-ארה"ב | O28: לא | P28: ILS | Q28: 499075 | R28: 1 | S28: 233.44 | T28: 1165.0407 | U28: 0.00033044315 | V28: =T28/SUMIFS(T:T,B:B,B28) -> 0.84494301 | W28: 0.0059302297
A29: 13908 | B29: 13916 | C29: אי.בי.אי קרנות נאמנות בעמ | D29: 513765339 | E29: ח.פ. | F29: STOXX-E600י.IBI | G29: IL0051307523 | H29: ISIN | I29: מניות | J29: ישראל | K29: אירופה | L29: סחיר | M29: TASE | N29: STOXX EUROPE 600 - מניות בחו"ל - מניות גיאוגרפי - מנוטרלת מט"ח-אירופה כללי | O29: לא | P29: ILS | Q29: 70000 | R29: 1 | S29: 156.63 | T29: 109.641 | U29: 0.00032199716 | V29: =T29/SUMIFS(T:T,B:B,B29) -> 0.079516877 | W29: 0.00055808894
A30: 13918 | B30: 13919 | C30: מיטב קרנות נאמנות בע"מ | D30: 513534974 | E30: ח.פ. | F30: SP 500 תכלית | G30: IL0051139983 | H30: ISIN | I30: מניות | J30: ישראל | K30: ארה"ב | L30: סחיר | M30: TASE | N30: S&P 500 - מניות בחו"ל - מניות גיאוגרפי - חשופת מט"ח-ארה"ב | O30: לא | P30: ILS | Q30: 1281190 | R30: 1 | S30: 739.54 | T30: 9474.9125 | U30: 0.00089674711 | V30: =T30/SUMIFS(T:T,B:B,B30) -> 0.6361868 | W30: 0.057872054
A31: 13918 | B31: 13919 | C31: הראל קרנות נאמנות בע"מ | D31: 511776783 | E31: ח.פ. | F31: הרל.תלבנד 20 צמ | G31: IL0051172703 | H31: ISIN | I31: אג"ח ממשלתי | J31: ישראל | K31: ישראל | L31: סחיר | M31: TASE | N31: אג"ח בארץ - חברות והמרה-תל בונד צמוד מדד-תל בונד צמודות | O31: לא | P31: ILS | Q31: 89937 | R31: 1 | S31: 138.26 | T31: 124.3469 | U31: 0.00022313896 | V31: =T31/SUMIFS(T:T,B:B,B31) -> 0.0083491912 | W31: 0.00075950152
A32: 13918 | B32: 13919 | C32: אי.בי.אי קרנות נאמנות בעמ | D32: 513765339 | E32: ח.פ. | F32: NASDAQ 100י.IBI | G32: IL0051277668 | H32: ISIN | I32: מניות | J32: ישראל | K32: ארה"ב | L32: סחיר | M32: TASE | N32: NASDAQ 100 - מניות בחו"ל - מניות גיאוגרפי - מנוטרלת מט"ח-ארה"ב | O32: לא | P32: ILS | Q32: 1517580 | R32: 1 | S32: 274.25 | T32: 4161.9631 | U32: 0.0019743238 | V32: =T32/SUMIFS(T:T,B:B,B32) -> 0.27945229 | W32: 0.025420958
A33: 13918 | B33: 13919 | C33: קסם קרנות נאמנות בע"מ | D33: 510938608 | E33: ח.פ. | F33: NIKKEI 225 קסם | G33: IL0051360647 | H33: ISIN | I33: מניות | J33: ישראל | K33: יפן | L33: סחיר | M33: TASE | N33: NIKKEI 225 - מניות בחו"ל - מניות גיאוגרפי - מנוטרלת מט"ח-אסיה יפן | O33: לא | P33: ILS | Q33: 4650 | R33: 1 | S33: 22182.21 | T33: 1031.4728 | U33: 0.00011543885 | V33: =T33/SUMIFS(T:T,B:B,B33) -> 0.069257563 | W33: 0.0063001581
A34: 13918 | B34: 13919 | C34: CIFC Global Floating Rate Cred | D34: 635400NLI1L | E34: LEI | F34: CIFC GLBL FLT RT CR-B1 USD | G34: IE0009SO3I10 | H34: ISIN | I34: אחר | J34: חו"ל | K34: גלובלי | L34: סחיר | M34: אחר | N34: Bond/Fixed Income Funds | O34: לא | P34: USD | Q34: 19.41 | R34: 3.718 | S34: 139388.4 | T34: 100.59156 | U34: 0.00050114895 | V34: =T34/SUMIFS(T:T,B:B,B34) -> 0.0067541545 | W34: 0.00061440569
A35: 13918 | B35: 13920 | C35: מיטב קרנות נאמנות בע"מ | D35: 513534974 | E35: ח.פ. | F35: SP 500 תכלית | G35: IL0051139983 | H35: ISIN | I35: מניות | J35: ישראל | K35: ארה"ב | L35: סחיר | M35: TASE | N35: S&P 500 - מניות בחו"ל - מניות גיאוגרפי - חשופת מט"ח-ארה"ב | O35: לא | P35: ILS | Q35: 296000 | R35: 1 | S35: 739.54 | T35: 2189.0384 | U35: 0.00020718016 | V35: =T35/SUMIFS(T:T,B:B,B35) -> 0.58873201 | W35: 0.030283405
A36: 13918 | B36: 13920 | C36: אי.בי.אי קרנות נאמנות בעמ | D36: 513765339 | E36: ח.פ. | F36: NASDAQ 100י.IBI | G36: IL0051277668 | H36: ISIN | I36: מניות | J36: ישראל | K36: ארה"ב | L36: סחיר | M36: TASE | N36: NASDAQ 100 - מניות בחו"ל - מניות גיאוגרפי - מנוטרלת מט"ח-ארה"ב | O36: לא | P36: ILS | Q36: 307400 | R36: 1 | S36: 274.25 | T36: 843.0445 | U36: 0.00039991773 | V36: =T36/SUMIFS(T:T,B:B,B36) -> 0.22673302 | W36: 0.011662773
A37: 13918 | B37: 13920 | C37: אי.בי.אי קרנות נאמנות בעמ | D37: 513765339 | E37: ח.פ. | F37: STOXX-E600י.IBI | G37: IL0051307523 | H37: ISIN | I37: מניות | J37: ישראל | K37: אירופה | L37: סחיר | M37: TASE | N37: STOXX EUROPE 600 - מניות בחו"ל - מניות גיאוגרפי - מנוטרלת מט"ח-אירופה כללי | O37: לא | P37: ILS | Q37: 404350 | R37: 1 | S37: 156.63 | T37: 633.3334 | U37: 0.0018599936 | V37: =T37/SUMIFS(T:T,B:B,B37) -> 0.17033216 | W37: 0.0087616059
A38: 13918 | B38: 13920 | C38: CIFC Global Floating Rate Cred | D38: 635400NLI1L | E38: LEI | F38: CIFC GLBL FLT RT CR-B1 USD | G38: IE0009SO3I10 | H38: ISIN | I38: אחר | J38: חו"ל | K38: גלובלי | L38: סחיר | M38: אחר | N38: Bond/Fixed Income Funds | O38: לא | P38: USD | Q38: 10.19 | R38: 3.718 | S38: 139388.4 | T38: 52.80927 | U38: 0.00026309674 | V38: =T38/SUMIFS(T:T,B:B,B38) -> 0.014202815 | W38: 0.00073056941
A39: 13918 | B39: 13921 | C39: מיטב קרנות נאמנות בע"מ | D39: 513534974 | E39: ח.פ. | F39: SP 500 תכלית | G39: IL0051139983 | H39: ISIN | I39: מניות | J39: ישראל | K39: ארה"ב | L39: סחיר | M39: TASE | N39: S&P 500 - מניות בחו"ל - מניות גיאוגרפי - חשופת מט"ח-ארה"ב | O39: לא | P39: ILS | Q39: 171400 | R39: 1 | S39: 739.54 | T39: 1267.5716 | U39: 0.00011996851 | V39: =T39/SUMIFS(T:T,B:B,B39) -> 0.62495809 | W39: 0.040146892
A40: 13918 | B40: 13921 | C40: אי.בי.אי קרנות נאמנות בעמ | D40: 513765339 | E40: ח.פ. | F40: NASDAQ 100י.IBI | G40: IL0051277668 | H40: ISIN | I40: מניות | J40: ישראל | K40: ארה"ב | L40: סחיר | M40: TASE | N40: NASDAQ 100 - מניות בחו"ל - מניות גיאוגרפי - מנוטרלת מט"ח-ארה"ב | O40: לא | P40: ILS | Q40: 175800 | R40: 1 | S40: 274.25 | T40: 482.1315 | U40: 0.00022871027 | V40: =T40/SUMIFS(T:T,B:B,B40) -> 0.23770806 | W40: 0.015270208
A41: 13918 | B41: 13921 | C41: אי.בי.אי קרנות נאמנות בעמ | D41: 513765339 | E41: ח.פ. | F41: STOXX-E600י.IBI | G41: IL0051307523 | H41: ISIN | I41: מניות | J41: ישראל | K41: אירופה | L41: סחיר | M41: TASE | N41: STOXX EUROPE 600 - מניות בחו"ל - מניות גיאוגרפי - מנוטרלת מט"ח-אירופה כללי | O41: לא | P41: ILS | Q41: 165000 | R41: 1 | S41: 156.63 | T41: 258.4395 | U41: 0.00075899331 | V41: =T41/SUMIFS(T:T,B:B,B41) -> 0.12741991 | W41: 0.0081853705
A42: 13918 | B42: 13921 | C42: CIFC Global Floating Rate Cred | D42: 635400NLI1L | E42: LEI | F42: CIFC GLBL FLT RT CR-B1 USD | G42: IE0009SO3I10 | H42: ISIN | I42: אחר | J42: חו"ל | K42: גלובלי | L42: סחיר | M42: אחר | N42: Bond/Fixed Income Funds | O42: לא | P42: USD | Q42: 3.88 | R42: 3.718 | S42: 139388.4 | T42: 20.10795 | U42: 0.00010017815 | V42: =T42/SUMIFS(T:T,B:B,B42) -> 0.0099139381 | W42: 0.0006368648
A43: 13918 | B43: 13922 | C43: מיטב קרנות נאמנות בע"מ | D43: 513534974 | E43: ח.פ. | F43: SP 500 תכלית | G43: IL0051139983 | H43: ISIN | I43: מניות | J43: ישראל | K43: ארה"ב | L43: סחיר | M43: TASE | N43: S&P 500 - מניות בחו"ל - מניות גיאוגרפי - חשופת מט"ח-ארה"ב | O43: לא | P43: ILS | Q43: 507310 | R43: 1 | S43: 739.54 | T43: 3751.7604 | U43: 0.00035508299 | V43: =T43/SUMIFS(T:T,B:B,B43) -> 0.40444934 | W43: 0.033022579
A44: 13918 | B44: 13922 | C44: מיטב קרנות נאמנות בע"מ | D44: 513534974 | E44: ח.פ. | F44: תכלית ת"א 125 | G44: IL0051146574 | H44: ISIN | I44: מניות | J44: ישראל | K44: ישראל | L44: סחיר | M44: TASE | N44: Large & Mid Cap מניות בארץ - מניות לפי שווי שוק-מניות | O44: לא | P44: ILS | Q44: 125000 | R44: 1 | S44: 216.03 | T44: 270.0375 | U44: 9.5506824e-05 | V44: =T44/SUMIFS(T:T,B:B,B44) -> 0.029110731 | W44: 0.0023768401
A45: 13918 | B45: 13922 | C45: אי.בי.אי קרנות נאמנות בעמ | D45: 513765339 | E45: ח.פ. | F45: S&P 500י.IBI | G45: IL0051274699 | H45: ISIN | I45: מניות | J45: ישראל | K45: ארה"ב | L45: סחיר | M45: TASE | N45: S&P 500 - מניות בחו"ל - מניות גיאוגרפי - חשופת מט"ח-ארה"ב | O45: לא | P45: ILS | Q45: 555235 | R45: 1 | S45: 233.44 | T45: 1296.1406 | U45: 0.00036762731 | V45: =T45/SUMIFS(T:T,B:B,B45) -> 0.13972726 | W45: 0.011408486
A46: 13918 | B46: 13922 | C46: אי.בי.אי קרנות נאמנות בעמ | D46: 513765339 | E46: ח.פ. | F46: NASDAQ 100י.IBI | G46: IL0051277668 | H46: ISIN | I46: מניות | J46: ישראל | K46: ארה"ב | L46: סחיר | M46: TASE | N46: NASDAQ 100 - מניות בחו"ל - מניות גיאוגרפי - מנוטרלת מט"ח-ארה"ב | O46: לא | P46: ILS | Q46: 1251000 | R46: 1 | S46: 274.25 | T46: 3430.8675 | U46: 0.0016275116 | V46: =T46/SUMIFS(T:T,B:B,B46) -> 0.36985627 | W46: 0.030198115
A47: 13918 | B47: 13922 | C47: אי.בי.אי קרנות נאמנות בעמ | D47: 513765339 | E47: ח.פ. | F47: STOXX-E600י.IBI | G47: IL0051307523 | H47: ISIN | I47: מניות | J47: ישראל | K47: אירופה | L47: סחיר | M47: TASE | N47: STOXX EUROPE 600 - מניות בחו"ל - מניות גיאוגרפי - מנוטרלת מט"ח-אירופה כללי | O47: לא | P47: ILS | Q47: 336725 | R47: 1 | S47: 156.63 | T47: 527.41237 | U47: 0.0015489214 | V47: =T47/SUMIFS(T:T,B:B,B47) -> 0.056856399 | W47: 0.0046422252
A48: 13918 | B48: 13923 | C48: קסם קרנות נאמנות בע"מ | D48: 510938608 | E48: ח.פ. | F48: קסם תל בונד 20 | G48: IL0051155898 | H48: ISIN | I48: מניות | J48: ישראל | K48: ישראל | L48: סחיר | M48: TASE | N48: 20 אג"ח בארץ - חברות והמרה-תל בונד צמוד מדד-תל בונד | O48: לא | P48: ILS | Q48: 0.52 | R48: 1 | S48: 142.48 | T48: 0.00074 | U48: 1.5388814e-09 | V48: =T48/SUMIFS(T:T,B:B,B48) -> 0.00034814519 | W48: 4.7851881e-07
A49: 13918 | B49: 13923 | C49: CIFC Global Floating Rate Cred | D49: 635400NLI1L | E49: LEI | F49: CIFC GLBL FLT RT CR-B1 USD | G49: IE0009SO3I10 | H49: ISIN | I49: אחר | J49: חו"ל | K49: גלובלי | L49: סחיר | M49: אחר | N49: Bond/Fixed Income Funds | O49: לא | P49: USD | Q49: 0.41 | R49: 3.718 | S49: 139388.4 | T49: 2.12481 | U49: 1.0585836e-05 | V49: =T49/SUMIFS(T:T,B:B,B49) -> 0.99965185 | W49: 0.0013740021
A50: 13918 | B50: 13925 | C50: הראל קרנות נאמנות בע"מ | D50: 511776783 | E50: ח.פ. | F50: NASDAQ 100 הראל | G50: IL0051292832 | H50: ISIN | I50: מניות | J50: ישראל | K50: ארה"ב | L50: סחיר | M50: TASE | N50: מניות בחו"ל - מניות גיאוגרפי - חשופת מט"ח-ארה"ב - מדד אחר | O50: לא | P50: ILS | Q50: 260300 | R50: 1 | S50: 286.89 | T50: 746.77467 | U50: 0.0002092113 | V50: =T50/SUMIFS(T:T,B:B,B50) -> 0.33837528 | W50: 0.028370078
A51: 13918 | B51: 13925 | C51: אי.בי.אי קרנות נאמנות בעמ | D51: 513765339 | E51: ח.פ. | F51: STOXX-E600י.IBI | G51: IL0051307523 | H51: ISIN | I51: מניות | J51: ישראל | K51: אירופה | L51: סחיר | M51: TASE | N51: STOXX EUROPE 600 - מניות בחו"ל - מניות גיאוגרפי - מנוטרלת מט"ח-אירופה כללי | O51: לא | P51: ILS | Q51: 932240 | R51: 1 | S51: 156.63 | T51: 1460.1675 | U51: 0.0042882662 | V51: =T51/SUMIFS(T:T,B:B,B51) -> 0.66162472 | W51: 0.055471975
A52: 13918 | B52: 13927 | C52: קסם קרנות נאמנות בע"מ | D52: 510938608 | E52: ח.פ. | F52: S&P 500 קסם | G52: IL0051244825 | H52: ISIN | I52: מניות | J52: ישראל | K52: ארה"ב | L52: סחיר | M52: TASE | N52: S&P 500 - מניות בחו"ל - מניות גיאוגרפי - חשופת מט"ח-ארה"ב | O52: לא | P52: ILS | Q52: 39000 | R52: 1 | S52: 281.63 | T52: 109.8357 | U52: 9.2350213e-06 | V52: =T52/SUMIFS(T:T,B:B,B52) -> 0.23547082 | W52: 0.0065761428
A53: 13918 | B53: 13927 | C53: אי.בי.אי קרנות נאמנות בעמ | D53: 513765339 | E53: ח.פ. | F53: S&P 500י.IBI | G53: IL0051274699 | H53: ISIN | I53: מניות | J53: ישראל | K53: ארה"ב | L53: סחיר | M53: TASE | N53: S&P 500 - מניות בחו"ל - מניות גיאוגרפי - חשופת מט"ח-ארה"ב | O53: לא | P53: ILS | Q53: 92100 | R53: 1 | S53: 233.44 | T53: 214.99824 | U53: 6.0980442e-05 | V53: =T53/SUMIFS(T:T,B:B,B53) -> 0.46092311 | W53: 0.012872492
A54: 13918 | B54: 13927 | C54: הראל קרנות נאמנות בע"מ | D54: 511776783 | E54: ח.פ. | F54: S&P 500 הראל | G54: IL0051292758 | H54: ISIN | I54: מניות | J54: ישראל | K54: ארה"ב | L54: סחיר | M54: TASE | N54: S&P 500 - מניות בחו"ל - מניות גיאוגרפי - חשופת מט"ח-ארה"ב | O54: לא | P54: ILS | Q54: 9220 | R54: 1 | S54: 227.9 | T54: 21.01238 | U54: 2.81985e-06 | V54: =T54/SUMIFS(T:T,B:B,B54) -> 0.045047306 | W54: 0.0012580646
A55: 13918 | B55: 13927 | C55: אי.בי.אי קרנות נאמנות בעמ | D55: 513765339 | E55: ח.פ. | F55: STOXX-E600י.IBI | G55: IL0051307523 | H55: ISIN | I55: מניות | J55: ישראל | K55: אירופה | L55: סחיר | M55: TASE | N55: STOXX EUROPE 600 - מניות בחו"ל - מניות גיאוגרפי - מנוטרלת מט"ח-אירופה כללי | O55: לא | P55: ILS | Q55: 77000 | R55: 1 | S55: 156.63 | T55: 120.6051 | U55: 0.00035419688 | V55: =T55/SUMIFS(T:T,B:B,B55) -> 0.25855876 | W55: 0.0072209341
A56: 13918 | B56: 14337 | C56: מיטב קרנות נאמנות בע"מ | D56: 513534974 | E56: ח.פ. | F56: SP 500 תכלית | G56: IL0051139983 | H56: ISIN | I56: מניות | J56: ישראל | K56: ארה"ב | L56: סחיר | M56: TASE | N56: S&P 500 - מניות בחו"ל - מניות גיאוגרפי - חשופת מט"ח-ארה"ב | O56: לא | P56: ILS | Q56: 31350 | R56: 1 | S56: 739.54 | T56: 231.84579 | U56: 2.1942898e-05 | V56: =T56/SUMIFS(T:T,B:B,B56) -> 0.25542697 | W56: 0.057095225
A57: 13918 | B57: 14337 | C57: מגדל קרנות נאמנות בע"מ | D57: 511303661 | E57: ח.פ. | F57: S&P 500 מח MTF | G57: IL0051226277 | H57: ISIN | I57: מניות | J57: ישראל | K57: ארה"ב | L57: סחיר | M57: TASE | N57: S&P 500 - מניות בחו"ל - מניות גיאוגרפי - חשופת מט"ח-ארה"ב | O57: לא | P57: ILS | Q57: 57200 | R57: 1 | S57: 297.11 | T57: 169.94692 | U57: 2.6694802e-05 | V57: =T57/SUMIFS(T:T,B:B,B57) -> 0.18723233 | W57: 0.041851774
A58: 13918 | B58: 14337 | C58: מגדל קרנות נאמנות בע"מ | D58: 511303661 | E58: ח.פ. | F58: MTF מח SP500 ממ | G58: IL0051258692 | H58: ISIN | I58: אחר | J58: ישראל | K58: ארה"ב | L58: סחיר | M58: TASE | N58: מניות בחו"ל - מניות גיאוגרפי - מנוטרלת מט"ח-ארה"ב - מדד אחר | O58: לא | P58: ILS | Q58: 90490 | R58: 1 | S58: 194.84 | T58: 176.31072 | U58: 7.4995319e-05 | V58: =T58/SUMIFS(T:T,B:B,B58) -> 0.19424339 | W58: 0.043418948
A59: 13918 | B59: 14337 | C59: אי.בי.אי קרנות נאמנות בעמ | D59: 513765339 | E59: ח.פ. | F59: NASDAQ 100י.IBI | G59: IL0051277668 | H59: ISIN | I59: מניות | J59: ישראל | K59: ארה"ב | L59: סחיר | M59: TASE | N59: NASDAQ 100 - מניות בחו"ל - מניות גיאוגרפי - מנוטרלת מט"ח-ארה"ב | O59: לא | P59: ILS | Q59: 41170 | R59: 1 | S59: 274.25 | T59: 112.90872 | U59: 5.3560874e-05 | V59: =T59/SUMIFS(T:T,B:B,B59) -> 0.12439274 | W59: 0.02780533
A60: 13918 | B60: 14337 | C60: הראל קרנות נאמנות בע"מ | D60: 511776783 | E60: ח.פ. | F60: NASDAQ 100 הראל | G60: IL0051292832 | H60: ISIN | I60: מניות | J60: ישראל | K60: ארה"ב | L60: סחיר | M60: TASE | N60: מניות בחו"ל - מניות גיאוגרפי - חשופת מט"ח-ארה"ב - מדד אחר | O60: לא | P60: ILS | Q60: 16390 | R60: 1 | S60: 286.89 | T60: 47.02127 | U60: 1.3173159e-05 | V60: =T60/SUMIFS(T:T,B:B,B60) -> 0.051803832 | W60: 0.011579637
A61: 13918 | B61: 14337 | C61: אי.בי.אי קרנות נאמנות בעמ | D61: 513765339 | E61: ח.פ. | F61: STOXX-E600י.IBI | G61: IL0051307523 | H61: ISIN | I61: מניות | J61: ישראל | K61: אירופה | L61: סחיר | M61: TASE | N61: STOXX EUROPE 600 - מניות בחו"ל - מניות גיאוגרפי - מנוטרלת מט"ח-אירופה כללי | O61: לא | P61: ILS | Q61: 108310 | R61: 1 | S61: 156.63 | T61: 169.64595 | U61: 0.00049822161 | V61: =T61/SUMIFS(T:T,B:B,B61) -> 0.18690074 | W61: 0.041777656
... A85: 13918 | B85: 15271 | C85: הראל קרנות נאמנות בע"מ | D85: 511776783 | E85: ח.פ. | F85: הרל.תלבנד 20 צמ | G85: IL0051172703 | H85: ISIN | I85: אג"ח ממשלתי | J85: ישראל | K85: ישראל | L85: סחיר | M85: TASE | N85: אג"ח בארץ - חברות והמרה-תל בונד צמוד מדד-תל בונד צמודות | O85: לא | P85: ILS | Q85: 39630 | R85: 1 | S85: 138.26 | T85: 54.79244 | U85: 9.832435e-05 | V85: =T85/SUMIFS(T:T,B:B,B85) -> 0.2821029 | W85: 0.052707084

Sheet כתבי אופציה
A1: מספר קופה/קרן/ח.פ. עבור חברת ביטוח | B1: מספר מסלול | C1: שם מנפיק | D1: מספר מנפיק | E1: סוג מספר מזהה מנפיק | F1: שם נייר ערך | G1: מספר נייר ערך | H1: סוג מספר נייר ערך | I1: ישראל/חו"ל | J1: מדינה לפי חשיפה כלכלית | K1: סטאטוס סחירות | L1: זירת מסחר | M1: נכס בסיס (כתב אופציה) | N1: ענף מסחר | O1: תאריך פקיעה | P1: בעל עניין/צד קשור | Q1: מטבע פעילות | R1: שער מימוש | S1: יחס המרה | T1: ערך נקוב (יחידות) | U1: שער חליפין | V1: שער נייר הערך | W1: שווי הוגן (באלפי ש"ח) | X1: שיעור מנכסי אפיק ההשקעה | Y1: שיעור מסך נכסי ההשקעה
A2: 13908 | B2: 13909 | C2: פרקומט אינטרנשיונל בע"מ | D2: 514259183 | E2: ח.פ. | F2: פרקומט אפ 1 | G2: IL0011876575 | H2: ISIN | I2: ישראל | J2: ישראל | K2: סחיר | L2: TASE | M2: 1187640 | N2: רובוטיקה ותלת מימד | O2: 45752 | P2: לא | Q2: ILS | R2: 521.049 | S2: 1 | T2: 108800 | U2: 1 | V2: 171.5 | W2: 186.592 | X2: 0.032424158 | Y2: 4.5477683e-05
A3: 13908 | B3: 13909 | C3: טופ גאם תעשיות בע"מ | D3: 513561399 | E3: ח.פ. | F3: טופ גאם אפ א | G3: IL0012007402 | H3: ISIN | I3: ישראל | J3: ישראל | K3: סחיר | L3: TASE | M3: 1179142 | N3: פודטק | O3: 45996 | P3: לא | Q3: ILS | R3: 745 | S3: 1 | T3: 52900 | U3: 1 | V3: 140 | W3: 74.06 | X3: 0.012869432 | Y3: 1.8050491e-05
A4: 13908 | B4: 13909 | C4: אלומיי קפיטל בע"מ | D4: 520039868 | E4: ח.פ. | F4: אלומיי אפ 2 | G4: IL0012030826 | H4: ISIN | I4: ישראל | J4: ישראל | K4: סחיר | L4: TASE | M4: 1082635 | N4: אנרגיה מתחדשת | O4: 46874 | P4: לא | Q4: ILS | R4: 8000 | S4: 1 | T4: 4608 | U4: 1 | V4: 682.7 | W4: 31.45882 | X4: 0.0054666102 | Y4: 7.6673933e-06
A5: 13908 | B5: 13909 | C5: מיטב טרייד השקעות בע"מ | D5: 516854239 | E5: ח.פ. | F5: מיטב טרייד אפ 1 | G5: IL0012031998 | H5: ISIN | I5: ישראל | J5: ישראל | K5: סחיר | L5: TASE | M5: 1203181 | N5: שירותים פיננסיים | O5: 18/01/2028 | P5: לא | Q5: ILS | R5: 715.068 | S5: 1 | T5: 352000 | U5: 1 | V5: 1408 | W5: 4956.16 | X5: 0.86123367 | Y5: 0.0012079547
A6: 13908 | B6: 13909 | C6: אפי קפיטל נדל"ן בע"מ | D6: 513948216 | E6: ח.פ. | F6: אפי קפיטל אפ 1 | G6: IL0012042136 | H6: ISIN | I6: ישראל | J6: ישראל | K6: סחיר | L6: TASE | M6: 1181437 | N6: בנייה | O6: 15/02/2026 | P6: לא | Q6: ILS | R6: 1157.91 | S6: 1 | T6: 75000 | U6: 1 | V6: 500 | W6: 375 | X6: 0.065163882 | Y6: 9.1397976e-05
A7: 13908 | B7: 13909 | C7: שובל הנדסה ובניין בע"מ | D7: 512951518 | E7: ח.פ. | F7: שובל הנדסה אפ 1 | G7: IL0012159617 | H7: ISIN | I7: ישראל | J7: ישראל | K7: סחיר | L7: TASE | M7: 1207968 | N7: בנייה | O7: 46661 | P7: לא | Q7: ILS | R7: 1023 | S7: 1 | T7: 20000 | U7: 1 | V7: 383.5 | W7: 76.7 | X7: 0.013328186 | Y7: 1.8693933e-05
A8: 13908 | B8: 13909 | C8: קבוצת חג'ג' ייזום נדל"ן בע"מ | D8: 520033309 | E8: ח.פ. | F8: חג'ג' אפ 1 | G8: IL0012166547 | H8: ISIN | I8: ישראל | J8: ישראל | K8: סחיר | L8: TASE | M8: 823013 | N8: בנייה | O8: 46395 | P8: לא | Q8: ILS | R8: 3230 | S8: 1 | T8: 15856 | U8: 1 | V8: 345.3 | W8: 54.75077 | X8: 0.0095140606 | Y8: 1.3344292e-05
A9: 13908 | B9: 13910 | C9: פרקומט אינטרנשיונל בע"מ | D9: 514259183 | E9: ח.פ. | F9: פרקומט אפ 1 | G9: IL0011876575 | H9: ISIN | I9: ישראל | J9: ישראל | K9: סחיר | L9: TASE | M9: 1187640 | N9: רובוטיקה ותלת מימד | O9: 45752 | P9: לא | Q9: ILS | R9: 521.049 | S9: 1 | T9: 16400 | U9: 1 | V9: 171.5 | W9: 28.126 | X9: 0.011406185 | Y9: 1.4963306e-05
A10: 13908 | B10: 13910 | C10: טופ גאם תעשיות בע"מ | D10: 513561399 | E10: ח.פ. | F10: טופ גאם אפ א | G10: IL0012007402 | H10: ISIN | I10: ישראל | J10: ישראל | K10: סחיר | L10: TASE | M10: 1179142 | N10: פודטק | O10: 45996 | P10: לא | Q10: ILS | R10: 745 | S10: 1 | T10: 12500 | U10: 1 | V10: 140 | W10: 17.5 | X10: 0.0070969297 | Y10: 9.3101702e-06
A11: 13908 | B11: 13910 | C11: אלומיי קפיטל בע"מ | D11: 520039868 | E11: ח.פ. | F11: אלומיי אפ 2 | G11: IL0012030826 | H11: ISIN | I11: ישראל | J11: ישראל | K11: סחיר | L11: TASE | M11: 1082635 | N11: אנרגיה מתחדשת | O11: 46874 | P11: לא | Q11: ILS | R11: 8000 | S11: 1 | T11: 1980 | U11: 1 | V11: 682.7 | W11: 13.51746 | X11: 0.0054818551 | Y11: 7.1914202e-06
A12: 13908 | B12: 13910 | C12: מיטב טרייד השקעות בע"מ | D12: 516854239 | E12: ח.פ. | F12: מיטב טרייד אפ 1 | G12: IL0012031998 | H12: ISIN | I12: ישראל | J12: ישראל | K12: סחיר | L12: TASE | M12: 1203181 | N12: שירותים פיננסיים | O12: 18/01/2028 | P12: לא | Q12: ILS | R12: 715.068 | S12: 1 | T12: 154000 | U12: 1 | V12: 1408 | W12: 2168.32 | X12: 0.87933798 | Y12: 0.0011535673
A13: 13908 | B13: 13910 | C13: אפי קפיטל נדל"ן בע"מ | D13: 513948216 | E13: ח.פ. | F13: אפי קפיטל אפ 1 | G13: IL0012042136 | H13: ISIN | I13: ישראל | J13: ישראל | K13: סחיר | L13: TASE | M13: 1181437 | N13: בנייה | O13: 15/02/2026 | P13: לא | Q13: ILS | R13: 1157.91 | S13: 1 | T13: 18750 | U13: 1 | V13: 500 | W13: 93.75 | X13: 0.038019266 | Y13: 4.9875912e-05
A14: 13908 | B14: 13910 | C14: ארי נדל"ן (ארנה) השקעות בע"מ | D14: 520038332 | E14: ח.פ. | F14: ארי נדלן אפ 1 | G14: IL0012123498 | H14: ISIN | I14: ישראל | J14: ישראל | K14: סחיר | L14: TASE | M14: 366013 | N14: נדל"ן מניב בישראל | O14: 27/09/2027 | P14: לא | Q14: ILS | R14: 285.24 | S14: 1 | T14: 46250 | U14: 1 | V14: 43.4 | W14: 20.0725 | X14: 0.0081401784 | Y14: 1.0678765e-05
A15: 13908 | B15: 13910 | C15: שובל הנדסה ובניין בע"מ | D15: 512951518 | E15: ח.פ. | F15: שובל הנדסה אפ 1 | G15: IL0012159617 | H15: ISIN | I15: ישראל | J15: ישראל | K15: סחיר | L15: TASE | M15: 1207968 | N15: בנייה | O15: 46661 | P15: לא | Q15: ILS | R15: 1023 | S15: 1 | T15: 10000 | U15: 1 | V15: 383.5 | W15: 38.35 | X15: 0.015552415 | Y15: 2.0402573e-05
A16: 13908 | B16: 13910 | C16: קבוצת חג'ג' ייזום נדל"ן בע"מ | D16: 520033309 | E16: ח.פ. | F16: חג'ג' אפ 1 | G16: IL0012166547 | H16: ISIN | I16: ישראל | J16: ישראל | K16: סחיר | L16: TASE | M16: 823013 | N16: בנייה | O16: 46395 | P16: לא | Q16: ILS | R16: 3230 | S16: 1 | T16: 15856 | U16: 1 | V16: 345.3 | W16: 54.75077 | X16: 0.022203564 | Y16: 2.9127942e-05
A17: 13908 | B17: 13910 | C17: נאייקס בע"מ | D17: 513639013 | E17: ח.פ. | F17: נאייקס אפ 1 | G17: IL0012189812 | H17: ISIN | I17: ישראל | J17: ישראל | K17: סחיר | L17: TASE | M17: 1175116 | N17: תוכנה ואינטרנט | O17: 31/03/2027 | P17: לא | Q17: ILS | R17: 18134.417 | S17: 1 | T17: 2952 | U17: 1 | V17: 1066 | W17: 31.46832 | X17: 0.012761626 | Y17: 1.6741452e-05
A18: 13908 | B18: 13911 | C18: פרקומט אינטרנשיונל בע"מ | D18: 514259183 | E18: ח.פ. | F18: פרקומט אפ 1 | G18: IL0011876575 | H18: ISIN | I18: ישראל | J18: ישראל | K18: סחיר | L18: TASE | M18: 1187640 | N18: רובוטיקה ותלת מימד | O18: 45752 | P18: לא | Q18: ILS | R18: 521.049 | S18: 1 | T18: 3600 | U18: 1 | V18: 171.5 | W18: 6.174 | X18: 0.011146273 | Y18: 1.0329863e-05
A19: 13908 | B19: 13911 | C19: טופ גאם תעשיות בע"מ | D19: 513561399 | E19: ח.פ. | F19: טופ גאם אפ א | G19: IL0012007402 | H19: ISIN | I19: ישראל | J19: ישראל | K19: סחיר | L19: TASE | M19: 1179142 | N19: פודטק | O19: 45996 | P19: לא | Q19: ILS | R19: 745 | S19: 1 | T19: 2400 | U19: 1 | V19: 140 | W19: 3.36 | X19: 0.0060659988 | Y19: 5.621694e-06
A20: 13908 | B20: 13911 | C20: אלומיי קפיטל בע"מ | D20: 520039868 | E20: ח.פ. | F20: אלומיי אפ 2 | G20: IL0012030826 | H20: ISIN | I20: ישראל | J20: ישראל | K20: סחיר | L20: TASE | M20: 1082635 | N20: אנרגיה מתחדשת | O20: 46874 | P20: לא | Q20: ILS | R20: 8000 | S20: 1 | T20: 576 | U20: 1 | V20: 682.7 | W20: 3.93235 | X20: 0.0070992948 | Y20: 6.579306e-06
A21: 13908 | B21: 13911 | C21: מיטב טרייד השקעות בע"מ | D21: 516854239 | E21: ח.פ. | F21: מיטב טרייד אפ 1 | G21: IL0012031998 | H21: ISIN | I21: ישראל | J21: ישראל | K21: סחיר | L21: TASE | M21: 1203181 | N21: שירותים פיננסיים | O21: 18/01/2028 | P21: לא | Q21: ILS | R21: 715.068 | S21: 1 | T21: 32000 | U21: 1 | V21: 1408 | W21: 450.56 | X21: 0.81342156 | Y21: 0.00075384239
A22: 13908 | B22: 13911 | C22: אפי קפיטל נדל"ן בע"מ | D22: 513948216 | E22: ח.פ. | F22: אפי קפיטל אפ 1 | G22: IL0012042136 | H22: ISIN | I22: ישראל | J22: ישראל | K22: סחיר | L22: TASE | M22: 1181437 | N22: בנייה | O22: 15/02/2026 | P22: לא | Q22: ILS | R22: 1157.91 | S22: 1 | T22: 5000 | U22: 1 | V22: 500 | W22: 25 | X22: 0.04513392 | Y22: 4.182808e-05
A23: 13908 | B23: 13911 | C23: ארי נדל"ן (ארנה) השקעות בע"מ | D23: 520038332 | E23: ח.פ. | F23: ארי נדלן אפ 1 | G23: IL0012123498 | H23: ISIN | I23: ישראל | J23: ישראל | K23: סחיר | L23: TASE | M23: 366013 | N23: נדל"ן מניב בישראל | O23: 27/09/2027 | P23: לא | Q23: ILS | R23: 285.24 | S23: 1 | T23: 17390 | U23: 1 | V23: 43.4 | W23: 7.54726 | X23: 0.013625497 | Y23: 1.2627496e-05
A24: 13908 | B24: 13911 | C24: שובל הנדסה ובניין בע"מ | D24: 512951518 | E24: ח.פ. | F24: שובל הנדסה אפ 1 | G24: IL0012159617 | H24: ISIN | I24: ישראל | J24: ישראל | K24: סחיר | L24: TASE | M24: 1207968 | N24: בנייה | O24: 46661 | P24: לא | Q24: ILS | R24: 1023 | S24: 1 | T24: 2500 | U24: 1 | V24: 383.5 | W24: 9.5875 | X24: 0.017308858 | Y24: 1.6041069e-05
A25: 13908 | B25: 13911 | C25: קבוצת חג'ג' ייזום נדל"ן בע"מ | D25: 520033309 | E25: ח.פ. | F25: חג'ג' אפ 1 | G25: IL0012166547 | H25: ISIN | I25: ישראל | J25: ישראל | K25: סחיר | L25: TASE | M25: 823013 | N25: בנייה | O25: 46395 | P25: לא | Q25: ILS | R25: 3230 | S25: 1 | T25: 7904 | U25: 1 | V25: 345.3 | W25: 27.29251 | X25: 0.049272718 | Y25: 4.5663732e-05
A26: 13908 | B26: 13911 | C26: סולאיר אנרגיות מתחדשות בע"מ | D26: 516046307 | E26: ח.פ. | F26: סולאיר אפ 1 | G26: IL0012179185 | H26: ISIN | I26: ישראל | J26: ישראל | K26: סחיר | L26: TASE | M26: 1172287 | N26: אנרגיה מתחדשת | O26: 31/08/2026 | P26: לא | Q26: ILS | R26: 4152 | S26: 1 | T26: 7070 | U26: 1 | V26: 289.3 | W26: 20.45351 | X26: 0.036925883 | Y26: 3.4221242e-05
A27: 13908 | B27: 13912 | C27: פרקומט אינטרנשיונל בע"מ | D27: 514259183 | E27: ח.פ. | F27: פרקומט אפ 1 | G27: IL0011876575 | H27: ISIN | I27: ישראל | J27: ישראל | K27: סחיר | L27: TASE | M27: 1187640 | N27: רובוטיקה ותלת מימד | O27: 45752 | P27: לא | Q27: ILS | R27: 521.049 | S27: 1 | T27: 60400 | U27: 1 | V27: 171.5 | W27: 103.586 | X27: 0.010661777 | Y27: 4.264958e-05
A28: 13908 | B28: 13912 | C28: טופ גאם תעשיות בע"מ | D28: 513561399 | E28: ח.פ. | F28: טופ גאם אפ א | G28: IL0012007402 | H28: ISIN | I28: ישראל | J28: ישראל | K28: סחיר | L28: TASE | M28: 1179142 | N28: פודטק | O28: 45996 | P28: לא | Q28: ILS | R28: 745 | S28: 1 | T28: 57800 | U28: 1 | V28: 140 | W28: 80.92 | X28: 0.008328838 | Y28: 3.3317282e-05
A29: 13908 | B29: 13912 | C29: מיטב טרייד השקעות בע"מ | D29: 516854239 | E29: ח.פ. | F29: מיטב טרייד אפ 1 | G29: IL0012031998 | H29: ISIN | I29: ישראל | J29: ישראל | K29: סחיר | L29: TASE | M29: 1203181 | N29: שירותים פיננסיים | O29: 18/01/2028 | P29: לא | Q29: ILS | R29: 715.068 | S29: 1 | T29: 592000 | U29: 1 | V29: 1408 | W29: 8335.36 | X29: 0.85793207 | Y29: 0.0034319271
A30: 13908 | B30: 13912 | C30: אפי קפיטל נדל"ן בע"מ | D30: 513948216 | E30: ח.פ. | F30: אפי קפיטל אפ 1 | G30: IL0012042136 | H30: ISIN | I30: ישראל | J30: ישראל | K30: סחיר | L30: TASE | M30: 1181437 | N30: בנייה | O30: 15/02/2026 | P30: לא | Q30: ILS | R30: 1157.91 | S30: 1 | T30: 92500 | U30: 1 | V30: 500 | W30: 462.5 | X30: 0.047603653 | Y30: 0.00019042564
A31: 13908 | B31: 13912 | C31: שובל הנדסה ובניין בע"מ | D31: 512951518 | E31: ח.פ. | F31: שובל הנדסה אפ 1 | G31: IL0012159617 | H31: ISIN | I31: ישראל | J31: ישראל | K31: סחיר | L31: TASE | M31: 1207968 | N31: בנייה | O31: 46661 | P31: לא | Q31: ILS | R31: 1023 | S31: 1 | T31: 15000 | U31: 1 | V31: 383.5 | W31: 57.525 | X31: 0.0059208651 | Y31: 2.3684833e-05
A32: 13908 | B32: 13912 | C32: בלדי בע"מ | D32: 511226136 | E32: ח.פ. | F32: בלדי אפ 1 | G32: IL0012166620 | H32: ISIN | I32: ישראל | J32: ישראל | K32: סחיר | L32: TASE | M32: 1212539 | N32: מסחר | O32: 31/01/2028 | P32: לא | Q32: ILS | R32: 2800 | S32: 1 | T32: 125000 | U32: 1 | V32: 540.6 | W32: 675.75 | X32: 0.069552796 | Y32: 0.0002782273
A33: 13908 | B33: 13913 | C33: אלומיי קפיטל בע"מ | D33: 520039868 | E33: ח.פ. | F33: אלומיי אפ 2 | G33: IL0012030826 | H33: ISIN | I33: ישראל | J33: ישראל | K33: סחיר | L33: TASE | M33: 1082635 | N33: אנרגיה מתחדשת | O33: 46874 | P33: לא | Q33: ILS | R33: 8000 | S33: 1 | T33: 240 | U33: 1 | V33: 682.7 | W33: 1.63848 | X33: 0.13980324 | Y33: 6.2148614e-05
A34: 13908 | B34: 13913 | C34: ארי נדל"ן (ארנה) השקעות בע"מ | D34: 520038332 | E34: ח.פ. | F34: ארי נדלן אפ 1 | G34: IL0012123498 | H34: ISIN | I34: ישראל | J34: ישראל | K34: סחיר | L34: TASE | M34: 366013 | N34: נדל"ן מניב בישראל | O34: 27/09/2027 | P34: לא | Q34: ILS | R34: 285.24 | S34: 1 | T34: 1110 | U34: 1 | V34: 43.4 | W34: 0.48174 | X34: 0.041104446 | Y34: 1.8272712e-05
A35: 13908 | B35: 13913 | C35: שובל הנדסה ובניין בע"מ | D35: 512951518 | E35: ח.פ. | F35: שובל הנדסה אפ 1 | G35: IL0012159617 | H35: ISIN | I35: ישראל | J35: ישראל | K35: סחיר | L35: TASE | M35: 1207968 | N35: בנייה | O35: 46661 | P35: לא | Q35: ILS | R35: 1023 | S35: 1 | T35: 500 | U35: 1 | V35: 383.5 | W35: 1.9175 | X35: 0.16361061 | Y35: 7.2732025e-05
A36: 13908 | B36: 13913 | C36: קבוצת חג'ג' ייזום נדל"ן בע"מ | D36: 520033309 | E36: ח.פ. | F36: חג'ג' אפ 1 | G36: IL0012166547 | H36: ISIN | I36: ישראל | J36: ישראל | K36: סחיר | L36: TASE | M36: 823013 | N36: בנייה | O36: 46395 | P36: לא | Q36: ILS | R36: 3230 | S36: 1 | T36: 560 | U36: 1 | V36: 345.3 | W36: 1.93368 | X36: 0.16499117 | Y36: 7.3345743e-05
A37: 13908 | B37: 13913 | C37: בלדי בע"מ | D37: 511226136 | E37: ח.פ. | F37: בלדי אפ 1 | G37: IL0012166620 | H37: ISIN | I37: ישראל | J37: ישראל | K37: סחיר | L37: TASE | M37: 1212539 | N37: מסחר | O37: 31/01/2028 | P37: לא | Q37: ILS | R37: 2800 | S37: 1 | T37: 500 | U37: 1 | V37: 540.6 | W37: 2.703 | X37: 0.23063337 | Y37: 0.00010252655
A38: 13908 | B38: 13913 | C38: סולאיר אנרגיות מתחדשות בע"מ | D38: 516046307 | E38: ח.פ. | F38: סולאיר אפ 1 | G38: IL0012179185 | H38: ISIN | I38: ישראל | J38: ישראל | K38: סחיר | L38: TASE | M38: 1172287 | N38: אנרגיה מתחדשת | O38: 31/08/2026 | P38: לא | Q38: ILS | R38: 4152 | S38: 1 | T38: 500 | U38: 1 | V38: 289.3 | W38: 1.4465 | X38: 0.12342255 | Y38: 5.4866688e-05
A39: 13908 | B39: 13913 | C39: נאייקס בע"מ | D39: 513639013 | E39: ח.פ. | F39: נאייקס אפ 1 | G39: IL0012189812 | H39: ISIN | I39: ישראל | J39: ישראל | K39: סחיר | L39: TASE | M39: 1175116 | N39: תוכנה ואינטרנט | O39: 31/03/2027 | P39: לא | Q39: ILS | R39: 18134.417 | S39: 1 | T39: 150 | U39: 1 | V39: 1066 | W39: 1.599 | X39: 0.13643461 | Y39: 6.0651112e-05
A40: 13908 | B40: 13916 | C40: אלומיי קפיטל בע"מ | D40: 520039868 | E40: ח.פ. | F40: אלומיי אפ 2 | G40: IL0012030826 | H40: ISIN | I40: ישראל | J40: ישראל | K40: סחיר | L40: TASE | M40: 1082635 | N40: אנרגיה מתחדשת | O40: 46874 | P40: לא | Q40: ILS | R40: 8000 | S40: 1 | T40: 576 | U40: 1 | V40: 682.7 | W40: 3.93235 | X40: 0.45064233 | Y40: 1.9792844e-05
A41: 13908 | B41: 13916 | C41: שובל הנדסה ובניין בע"מ | D41: 512951518 | E41: ח.פ. | F41: שובל הנדסה אפ 1 | G41: IL0012159617 | H41: ISIN | I41: ישראל | J41: ישראל | K41: סחיר | L41: TASE | M41: 1207968 | N41: בנייה | O41: 46661 | P41: לא | Q41: ILS | R41: 1023 | S41: 1 | T41: 1250 | U41: 1 | V41: 383.5 | W41: 4.79375 | X41: 0.54935767 | Y41: 2.4128561e-05
A42: 13918 | B42: 13919 | C42: פרקומט אינטרנשיונל בע"מ | D42: 514259183 | E42: ח.פ. | F42: פרקומט אפ 1 | G42: IL0011876575 | H42: ISIN | I42: ישראל | J42: ישראל | K42: סחיר | L42: TASE | M42: 1187640 | N42: רובוטיקה ותלת מימד | O42: 45752 | P42: לא | Q42: ILS | R42: 521.049 | S42: 1 | T42: 3200 | U42: 1 | V42: 171.5 | W42: 5.488 | X42: 0.040580511 | Y42: 3.3530754e-05
A43: 13918 | B43: 13919 | C43: טופ גאם תעשיות בע"מ | D43: 513561399 | E43: ח.פ. | F43: טופ גאם אפ א | G43: IL0012007402 | H43: ISIN | I43: ישראל | J43: ישראל | K43: סחיר | L43: TASE | M43: 1179142 | N43: פודטק | O43: 45996 | P43: לא | Q43: ILS | R43: 745 | S43: 1 | T43: 1700 | U43: 1 | V43: 140 | W43: 2.38 | X43: 0.017598691 | Y43: 1.4541398e-05
A44: 13918 | B44: 13919 | C44: אלומיי קפיטל בע"מ | D44: 520039868 | E44: ח.פ. | F44: אלומיי אפ 2 | G44: IL0012030826 | H44: ISIN | I44: ישראל | J44: ישראל | K44: סחיר | L44: TASE | M44: 1082635 | N44: אנרגיה מתחדשת | O44: 46874 | P44: לא | Q44: ILS | R44: 8000 | S44: 1 | T44: 576 | U44: 1 | V44: 682.7 | W44: 3.93235 | X44: 0.0290774 | Y44: 2.4025995e-05
A45: 13918 | B45: 13919 | C45: אפי קפיטל נדל"ן בע"מ | D45: 513948216 | E45: ח.פ. | F45: אפי קפיטל אפ 1 | G45: IL0012042136 | H45: ISIN | I45: ישראל | J45: ישראל | K45: סחיר | L45: TASE | M45: 1181437 | N45: בנייה | O45: 15/02/2026 | P45: לא | Q45: ILS | R45: 1157.91 | S45: 1 | T45: 2500 | U45: 1 | V45: 500 | W45: 12.5 | X45: 0.0924301 | Y45: 7.637289e-05
A46: 13918 | B46: 13919 | C46: ארי נדל"ן (ארנה) השקעות בע"מ | D46: 520038332 | E46: ח.פ. | F46: ארי נדלן אפ 1 | G46: IL0012123498 | H46: ISIN | I46: ישראל | J46: ישראל | K46: סחיר | L46: TASE | M46: 366013 | N46: נדל"ן מניב בישראל | O46: 27/09/2027 | P46: לא | Q46: ILS | R46: 285.24 | S46: 1 | T46: 3700 | U46: 1 | V46: 43.4 | W46: 1.6058 | X46: 0.01187394 | Y46: 9.8111669e-06
A47: 13918 | B47: 13919 | C47: שובל הנדסה ובניין בע"מ | D47: 512951518 | E47: ח.פ. | F47: שובל הנדסה אפ 1 | G47: IL0012159617 | H47: ISIN | I47: ישראל | J47: ישראל | K47: סחיר | L47: TASE | M47: 1207968 | N47: בנייה | O47: 46661 | P47: לא | Q47: ILS | R47: 1023 | S47: 1 | T47: 2500 | U47: 1 | V47: 383.5 | W47: 9.5875 | X47: 0.070893887 | Y47: 5.8578006e-05
A48: 13918 | B48: 13919 | C48: קבוצת חג'ג' ייזום נדל"ן בע"מ | D48: 520033309 | E48: ח.פ. | F48: חג'ג' אפ 1 | G48: IL0012166547 | H48: ISIN | I48: ישראל | J48: ישראל | K48: סחיר | L48: TASE | M48: 823013 | N48: בנייה | O48: 46395 | P48: לא | Q48: ILS | R48: 3230 | S48: 1 | T48: 3168 | U48: 1 | V48: 345.3 | W48: 10.9391 | X48: 0.080888169 | Y48: 6.6836054e-05
A49: 13918 | B49: 13919 | C49: בלדי בע"מ | D49: 511226136 | E49: ח.פ. | F49: בלדי אפ 1 | G49: IL0012166620 | H49: ISIN | I49: ישראל | J49: ישראל | K49: סחיר | L49: TASE | M49: 1212539 | N49: מסחר | O49: 31/01/2028 | P49: לא | Q49: ILS | R49: 2800 | S49: 1 | T49: 15000 | U49: 1 | V49: 540.6 | W49: 81.09 | X49: 0.59961255 | Y49: 0.00049544621
A50: 13918 | B50: 13919 | C50: סולאיר אנרגיות מתחדשות בע"מ | D50: 516046307 | E50: ח.פ. | F50: סולאיר אפ 1 | G50: IL0012179185 | H50: ISIN | I50: ישראל | J50: ישראל | K50: סחיר | L50: TASE | M50: 1172287 | N50: אנרגיה מתחדשת | O50: 31/08/2026 | P50: לא | Q50: ILS | R50: 4152 | S50: 1 | T50: 500 | U50: 1 | V50: 289.3 | W50: 1.4465 | X50: 0.010696011 | Y50: 8.8378708e-06
A51: 13918 | B51: 13919 | C51: נאייקס בע"מ | D51: 513639013 | E51: ח.פ. | F51: נאייקס אפ 1 | G51: IL0012189812 | H51: ISIN | I51: ישראל | J51: ישראל | K51: סחיר | L51: TASE | M51: 1175116 | N51: תוכנה ואינטרנט | O51: 31/03/2027 | P51: לא | Q51: ILS | R51: 18134.417 | S51: 1 | T51: 588 | U51: 1 | V51: 1066 | W51: 6.26808 | X51: 0.046348741 | Y51: 3.8296911e-05
A52: 13918 | B52: 13920 | C52: טופ גאם תעשיות בע"מ | D52: 513561399 | E52: ח.פ. | F52: טופ גאם אפ א | G52: IL0012007402 | H52: ISIN | I52: ישראל | J52: ישראל | K52: סחיר | L52: TASE | M52: 1179142 | N52: פודטק | O52: 45996 | P52: לא | Q52: ILS | R52: 745 | S52: 1 | T52: 400 | U52: 1 | V52: 140 | W52: 0.56 | X52: 0.015141667 | Y52: 7.7505305e-06
A53: 13918 | B53: 13920 | C53: אלומיי קפיטל בע"מ | D53: 520039868 | E53: ח.פ. | F53: אלומיי אפ 2 | G53: IL0012030826 | H53: ISIN | I53: ישראל | J53: ישראל | K53: סחיר | L53: TASE | M53: 1082635 | N53: אנרגיה מתחדשת | O53: 46874 | P53: לא | Q53: ILS | R53: 8000 | S53: 1 | T53: 288 | U53: 1 | V53: 682.7 | W53: 1.96618 | X53: 0.053162932 | Y53: 2.721239e-05
A54: 13918 | B54: 13920 | C54: אפי קפיטל נדל"ן בע"מ | D54: 513948216 | E54: ח.פ. | F54: אפי קפיטל אפ 1 | G54: IL0012042136 | H54: ISIN | I54: ישראל | J54: ישראל | K54: סחיר | L54: TASE | M54: 1181437 | N54: בנייה | O54: 15/02/2026 | P54: לא | Q54: ILS | R54: 1157.91 | S54: 1 | T54: 1000 | U54: 1 | V54: 500 | W54: 5 | X54: 0.13519345 | Y54: 6.9201166e-05
A55: 13918 | B55: 13920 | C55: ארי נדל"ן (ארנה) השקעות בע"מ | D55: 520038332 | E55: ח.פ. | F55: ארי נדלן אפ 1 | G55: IL0012123498 | H55: ISIN | I55: ישראל | J55: ישראל | K55: סחיר | L55: TASE | M55: 366013 | N55: נדל"ן מניב בישראל | O55: 27/09/2027 | P55: לא | Q55: ILS | R55: 285.24 | S55: 1 | T55: 2405 | U55: 1 | V55: 43.4 | W55: 1.04377 | X55: 0.028222174 | Y55: 1.444602e-05
A56: 13918 | B56: 13920 | C56: שובל הנדסה ובניין בע"מ | D56: 512951518 | E56: ח.פ. | F56: שובל הנדסה אפ 1 | G56: IL0012159617 | H56: ISIN | I56: ישראל | J56: ישראל | K56: סחיר | L56: TASE | M56: 1207968 | N56: בנייה | O56: 46661 | P56: לא | Q56: ILS | R56: 1023 | S56: 1 | T56: 1250 | U56: 1 | V56: 383.5 | W56: 4.79375 | X56: 0.12961672 | Y56: 6.6346617e-05
A57: 13918 | B57: 13920 | C57: קבוצת חג'ג' ייזום נדל"ן בע"מ | D57: 520033309 | E57: ח.פ. | F57: חג'ג' אפ 1 | G57: IL0012166547 | H57: ISIN | I57: ישראל | J57: ישראל | K57: סחיר | L57: TASE | M57: 823013 | N57: בנייה | O57: 46395 | P57: לא | Q57: ILS | R57: 3230 | S57: 1 | T57: 1600 | U57: 1 | V57: 345.3 | W57: 5.5248 | X57: 0.14938336 | Y57: 7.646452e-05
A58: 13918 | B58: 13920 | C58: בלדי בע"מ | D58: 511226136 | E58: ח.פ. | F58: בלדי אפ 1 | G58: IL0012166620 | H58: ISIN | I58: ישראל | J58: ישראל | K58: סחיר | L58: TASE | M58: 1212539 | N58: מסחר | O58: 31/01/2028 | P58: לא | Q58: ILS | R58: 2800 | S58: 1 | T58: 2500 | U58: 1 | V58: 540.6 | W58: 13.515 | X58: 0.3654279 | Y58: 0.00018705075
A59: 13918 | B59: 13920 | C59: סולאיר אנרגיות מתחדשות בע"מ | D59: 516046307 | E59: ח.פ. | F59: סולאיר אפ 1 | G59: IL0012179185 | H59: ISIN | I59: ישראל | J59: ישראל | K59: סחיר | L59: TASE | M59: 1172287 | N59: אנרגיה מתחדשת | O59: 31/08/2026 | P59: לא | Q59: ILS | R59: 4152 | S59: 1 | T59: 500 | U59: 1 | V59: 289.3 | W59: 1.4465 | X59: 0.039111465 | Y59: 2.0019897e-05
A60: 13918 | B60: 13920 | C60: נאייקס בע"מ | D60: 513639013 | E60: ח.פ. | F60: נאייקס אפ 1 | G60: IL0012189812 | H60: ISIN | I60: ישראל | J60: ישראל | K60: סחיר | L60: TASE | M60: 1175116 | N60: תוכנה ואינטרנט | O60: 31/03/2027 | P60: לא | Q60: ILS | R60: 18134.417 | S60: 1 | T60: 294 | U60: 1 | V60: 1066 | W60: 3.13404 | X60: 0.084740337 | Y60: 4.3375844e-05
A61: 13918 | B61: 13921 | C61: טופ גאם תעשיות בע"מ | D61: 513561399 | E61: ח.פ. | F61: טופ גאם אפ א | G61: IL0012007402 | H61: ISIN | I61: ישראל | J61: ישראל | K61: סחיר | L61: TASE | M61: 1179142 | N61: פודטק | O61: 45996 | P61: לא | Q61: ILS | R61: 745 | S61: 1 | T61: 100 | U61: 1 | V61: 140 | W61: 0.14 | X61: 0.011661098 | Y61: 4.4354558e-06
A62: 13918 | B62: 13921 | C62: אלומיי קפיטל בע"מ | D62: 520039868 | E62: ח.פ. | F62: אלומיי אפ 2 | G62: IL0012030826 | H62: ISIN | I62: ישראל | J62: ישראל | K62: סחיר | L62: TASE | M62: 1082635 | N62: אנרגיה מתחדשת | O62: 46874 | P62: לא | Q62: ILS | R62: 8000 | S62: 1 | T62: 120 | U62: 1 | V62: 682.7 | W62: 0.81924 | X62: 0.068237417 | Y62: 2.595502e-05
A63: 13918 | B63: 13921 | C63: אפי קפיטל נדל"ן בע"מ | D63: 513948216 | E63: ח.פ. | F63: אפי קפיטל אפ 1 | G63: IL0012042136 | H63: ISIN | I63: ישראל | J63: ישראל | K63: סחיר | L63: TASE | M63: 1181437 | N63: בנייה | O63: 15/02/2026 | P63: לא | Q63: ILS | R63: 1157.91 | S63: 1 | T63: 250 | U63: 1 | V63: 500 | W63: 1.25 | X63: 0.10411695 | Y63: 3.9602284e-05
A64: 13918 | B64: 13921 | C64: ארי נדל"ן (ארנה) השקעות בע"מ | D64: 520038332 | E64: ח.פ. | F64: ארי נדלן אפ 1 | G64: IL0012123498 | H64: ISIN | I64: ישראל | J64: ישראל | K64: סחיר | L64: TASE | M64: 366013 | N64: נדל"ן מניב בישראל | O64: 27/09/2027 | P64: לא | Q64: ILS | R64: 285.24 | S64: 1 | T64: 1110 | U64: 1 | V64: 43.4 | W64: 0.48174 | X64: 0.04012584 | Y64: 1.5262403e-05
A65: 13918 | B65: 13921 | C65: שובל הנדסה ובניין בע"מ | D65: 512951518 | E65: ח.פ. | F65: שובל הנדסה אפ 1 | G65: IL0012159617 | H65: ISIN | I65: ישראל | J65: ישראל | K65: סחיר | L65: TASE | M65: 1207968 | N65: בנייה | O65: 46661 | P65: לא | Q65: ILS | R65: 1023 | S65: 1 | T65: 500 | U65: 1 | V65: 383.5 | W65: 1.9175 | X65: 0.1597154 | Y65: 6.0749904e-05
A66: 13918 | B66: 13921 | C66: קבוצת חג'ג' ייזום נדל"ן בע"מ | D66: 520033309 | E66: ח.פ. | F66: חג'ג' אפ 1 | G66: IL0012166547 | H66: ISIN | I66: ישראל | J66: ישראל | K66: סחיר | L66: TASE | M66: 823013 | N66: בנייה | O66: 46395 | P66: לא | Q66: ILS | R66: 3230 | S66: 1 | T66: 784 | U66: 1 | V66: 345.3 | W66: 2.70715 | X66: 0.22548816 | Y66: 8.5767459e-05
A67: 13918 | B67: 13921 | C67: בלדי בע"מ | D67: 511226136 | E67: ח.פ. | F67: בלדי אפ 1 | G67: IL0012166620 | H67: ISIN | I67: ישראל | J67: ישראל | K67: סחיר | L67: TASE | M67: 1212539 | N67: מסחר | O67: 31/01/2028 | P67: לא | Q67: ILS | R67: 2800 | S67: 1 | T67: 600 | U67: 1 | V67: 540.6 | W67: 3.2436 | X67: 0.27017099 | Y67: 0.00010276317
A68: 13918 | B68: 13921 | C68: סולאיר אנרגיות מתחדשות בע"מ | D68: 516046307 | E68: ח.פ. | F68: סולאיר אפ 1 | G68: IL0012179185 | H68: ISIN | I68: ישראל | J68: ישראל | K68: סחיר | L68: TASE | M68: 1172287 | N68: אנרגיה מתחדשת | O68: 31/08/2026 | P68: לא | Q68: ILS | R68: 4152 | S68: 1 | T68: 500 | U68: 1 | V68: 289.3 | W68: 1.4465 | X68: 0.12048414 | Y68: 4.5827763e-05
A69: 13918 | B69: 13922 | C69: פרקומט אינטרנשיונל בע"מ | D69: 514259183 | E69: ח.פ. | F69: פרקומט אפ 1 | G69: IL0011876575 | H69: ISIN | I69: ישראל | J69: ישראל | K69: סחיר | L69: TASE | M69: 1187640 | N69: רובוטיקה ותלת מימד | O69: 45752 | P69: לא | Q69: ILS | R69: 521.049 | S69: 1 | T69: 3200 | U69: 1 | V69: 171.5 | W69: 5.488 | X69: 0.047064675 | Y69: 4.8324711e-05
A70: 13918 | B70: 13922 | C70: טופ גאם תעשיות בע"מ | D70: 513561399 | E70: ח.פ. | F70: טופ גאם אפ א | G70: IL0012007402 | H70: ISIN | I70: ישראל | J70: ישראל | K70: סחיר | L70: TASE | M70: 1179142 | N70: פודטק | O70: 45996 | P70: לא | Q70: ILS | R70: 745 | S70: 1 | T70: 2100 | U70: 1 | V70: 140 | W70: 2.94 | X70: 0.025213219 | Y70: 2.5888238e-05
A71: 13918 | B71: 13922 | C71: אפי קפיטל נדל"ן בע"מ | D71: 513948216 | E71: ח.פ. | F71: אפי קפיטל אפ 1 | G71: IL0012042136 | H71: ISIN | I71: ישראל | J71: ישראל | K71: סחיר | L71: TASE | M71: 1181437 | N71: בנייה | O71: 15/02/2026 | P71: לא | Q71: ILS | R71: 1157.91 | S71: 1 | T71: 3500 | U71: 1 | V71: 500 | W71: 17.5 | X71: 0.15007868 | Y71: 0.00015409666
A72: 13918 | B72: 13922 | C72: שובל הנדסה ובניין בע"מ | D72: 512951518 | E72: ח.פ. | F72: שובל הנדסה אפ 1 | G72: IL0012159617 | H72: ISIN | I72: ישראל | J72: ישראל | K72: סחיר | L72: TASE | M72: 1207968 | N72: בנייה | O72: 46661 | P72: לא | Q72: ILS | R72: 1023 | S72: 1 | T72: 2500 | U72: 1 | V72: 383.5 | W72: 9.5875 | X72: 0.082221679 | Y72: 8.4422954e-05
A73: 13918 | B73: 13922 | C73: בלדי בע"מ | D73: 511226136 | E73: ח.פ. | F73: בלדי אפ 1 | G73: IL0012166620 | H73: ISIN | I73: ישראל | J73: ישראל | K73: סחיר | L73: TASE | M73: 1212539 | N73: מסחר | O73: 31/01/2028 | P73: לא | Q73: ILS | R73: 2800 | S73: 1 | T73: 15000 | U73: 1 | V73: 540.6 | W73: 81.09 | X73: 0.69542174 | Y73: 0.00071403988
A74: 13918 | B74: 13923 | C74: אלומיי קפיטל בע"מ | D74: 520039868 | E74: ח.פ. | F74: אלומיי אפ 2 | G74: IL0012030826 | H74: ISIN | I74: ישראל | J74: ישראל | K74: סחיר | L74: TASE | M74: 1082635 | N74: אנרגיה מתחדשת | O74: 46874 | P74: לא | Q74: ILS | R74: 8000 | S74: 1 | T74: 24 | U74: 1 | V74: 682.7 | W74: 0.16385 | X74: 0.11390258 | Y74: 0.00010595691
A75: 13918 | B75: 13923 | C75: ארי נדל"ן (ארנה) השקעות בע"מ | D75: 520038332 | E75: ח.פ. | F75: ארי נדלן אפ 1 | G75: IL0012123498 | H75: ISIN | I75: ישראל | J75: ישראל | K75: סחיר | L75: TASE | M75: 366013 | N75: נדל"ן מניב בישראל | O75: 27/09/2027 | P75: לא | Q75: ILS | R75: 285.24 | S75: 1 | T75: 185 | U75: 1 | V75: 43.4 | W75: 0.08029 | X75: 0.055814697 | Y75: 5.192115e-05
A76: 13918 | B76: 13923 | C76: שובל הנדסה ובניין בע"מ | D76: 512951518 | E76: ח.פ. | F76: שובל הנדסה אפ 1 | G76: IL0012159617 | H76: ISIN | I76: ישראל | J76: ישראל | K76: סחיר | L76: TASE | M76: 1207968 | N76: בנייה | O76: 46661 | P76: לא | Q76: ILS | R76: 1023 | S76: 1 | T76: 50 | U76: 1 | V76: 383.5 | W76: 0.19175 | X76: 0.13329765 | Y76: 0.00012399901
A77: 13918 | B77: 13923 | C77: קבוצת חג'ג' ייזום נדל"ן בע"מ | D77: 520033309 | E77: ח.פ. | F77: חג'ג' אפ 1 | G77: IL0012166547 | H77: ISIN | I77: ישראל | J77: ישראל | K77: סחיר | L77: TASE | M77: 823013 | N77: בנייה | O77: 46395 | P77: לא | Q77: ILS | R77: 3230 | S77: 1 | T77: 80 | U77: 1 | V77: 345.3 | W77: 0.27624 | X77: 0.19203203 | Y77: 0.00017863617
A78: 13918 | B78: 13923 | C78: בלדי בע"מ | D78: 511226136 | E78: ח.פ. | F78: בלדי אפ 1 | G78: IL0012166620 | H78: ISIN | I78: ישראל | J78: ישראל | K78: סחיר | L78: TASE | M78: 1212539 | N78: מסחר | O78: 31/01/2028 | P78: לא | Q78: ILS | R78: 2800 | S78: 1 | T78: 100 | U78: 1 | V78: 540.6 | W78: 0.5406 | X78: 0.37580552 | Y78: 0.00034958991
A79: 13918 | B79: 13923 | C79: סולאיר אנרגיות מתחדשות בע"מ | D79: 516046307 | E79: ח.פ. | F79: סולאיר אפ 1 | G79: IL0012179185 | H79: ISIN | I79: ישראל | J79: ישראל | K79: סחיר | L79: TASE | M79: 1172287 | N79: אנרגיה מתחדשת | O79: 31/08/2026 | P79: לא | Q79: ILS | R79: 4152 | S79: 1 | T79: 20 | U79: 1 | V79: 289.3 | W79: 0.05786 | X79: 0.040222174 | Y79: 3.7416337e-05
A80: 13918 | B80: 13923 | C80: נאייקס בע"מ | D80: 513639013 | E80: ח.פ. | F80: נאייקס אפ 1 | G80: IL0012189812 | H80: ISIN | I80: ישראל | J80: ישראל | K80: סחיר | L80: TASE | M80: 1175116 | N80: תוכנה ואינטרנט | O80: 31/03/2027 | P80: לא | Q80: ILS | R80: 18134.417 | S80: 1 | T80: 12 | U80: 1 | V80: 1066 | W80: 0.12792 | X80: 0.088925346 | Y80: 8.2722051e-05
A81: 13918 | B81: 13927 | C81: אלומיי קפיטל בע"מ | D81: 520039868 | E81: ח.פ. | F81: אלומיי אפ 2 | G81: IL0012030826 | H81: ISIN | I81: ישראל | J81: ישראל | K81: סחיר | L81: TASE | M81: 1082635 | N81: אנרגיה מתחדשת | O81: 46874 | P81: לא | Q81: ILS | R81: 8000 | S81: 1 | T81: 228 | U81: 1 | V81: 682.7 | W81: 1.55656 | X81: 0.16245507 | Y81: 7.8640169e-05
A82: 13918 | B82: 13927 | C82: ארי נדל"ן (ארנה) השקעות בע"מ | D82: 520038332 | E82: ח.פ. | F82: ארי נדלן אפ 1 | G82: IL0012123498 | H82: ISIN | I82: ישראל | J82: ישראל | K82: סחיר | L82: TASE | M82: 366013 | N82: נדל"ן מניב בישראל | O82: 27/09/2027 | P82: לא | Q82: ILS | R82: 285.24 | S82: 1 | T82: 740 | U82: 1 | V82: 43.4 | W82: 0.32116 | X82: 0.03351883 | Y82: 1.6225572e-05
A83: 13918 | B83: 13927 | C83: שובל הנדסה ובניין בע"מ | D83: 512951518 | E83: ח.פ. | F83: שובל הנדסה אפ 1 | G83: IL0012159617 | H83: ISIN | I83: ישראל | J83: ישראל | K83: סחיר | L83: TASE | M83: 1207968 | N83: בנייה | O83: 46661 | P83: לא | Q83: ILS | R83: 1023 | S83: 1 | T83: 250 | U83: 1 | V83: 383.5 | W83: 0.95875 | X83: 0.10006283 | Y83: 4.8437748e-05
A84: 13918 | B84: 13927 | C84: קבוצת חג'ג' ייזום נדל"ן בע"מ | D84: 520033309 | E84: ח.פ. | F84: חג'ג' אפ 1 | G84: IL0012166547 | H84: ISIN | I84: ישראל | J84: ישראל | K84: סחיר | L84: TASE | M84: 823013 | N84: בנייה | O84: 46395 | P84: לא | Q84: ILS | R84: 3230 | S84: 1 | T84: 304 | U84: 1 | V84: 345.3 | W84: 1.04971 | X84: 0.10955614 | Y84: 5.3033209e-05
A85: 13918 | B85: 13927 | C85: בלדי בע"מ | D85: 511226136 | E85: ח.פ. | F85: בלדי אפ 1 | G85: IL0012166620 | H85: ISIN | I85: ישראל | J85: ישראל | K85: סחיר | L85: TASE | M85: 1212539 | N85: מסחר | O85: 31/01/2028 | P85: לא | Q85: ILS | R85: 2800 | S85: 1 | T85: 1000 | U85: 1 | V85: 540.6 | W85: 5.406 | X85: 0.56421346 | Y85: 0.0002731207
A86: 13918 | B86: 13927 | C86: סולאיר אנרגיות מתחדשות בע"מ | D86: 516046307 | E86: ח.פ. | F86: סולאיר אפ 1 | G86: IL0012179185 | H86: ISIN | I86: ישראל | J86: ישראל | K86: סחיר | L86: TASE | M86: 1172287 | N86: אנרגיה מתחדשת | O86: 31/08/2026 | P86: לא | Q86: ILS | R86: 4152 | S86: 1 | T86: 100 | U86: 1 | V86: 289.3 | W86: 0.2893 | X86: 0.030193665 | Y86: 1.4615949e-05
A87: 13918 | B87: 14337 | C87: ארי נדל"ן (ארנה) השקעות בע"מ | D87: 520038332 | E87: ח.פ. | F87: ארי נדלן אפ 1 | G87: IL0012123498 | H87: ISIN | I87: ישראל | J87: ישראל | K87: סחיר | L87: TASE | M87: 366013 | N87: נדל"ן מניב בישראל | O87: 27/09/2027 | P87: לא | Q87: ILS | R87: 285.24 | S87: 1 | T87: 185 | U87: 1 | V87: 43.4 | W87: 0.08029 | X87: 0.026679648 | Y87: 1.9777799e-05
A88: 13918 | B88: 14337 | C88: שובל הנדסה ובניין בע"מ | D88: 512951518 | E88: ח.פ. | F88: שובל הנדסה אפ 1 | G88: IL0012159617 | H88: ISIN | I88: ישראל | J88: ישראל | K88: סחיר | L88: TASE | M88: 1207968 | N88: בנייה | O88: 46661 | P88: לא | Q88: ILS | R88: 1023 | S88: 1 | T88: 250 | U88: 1 | V88: 383.5 | W88: 0.95875 | X88: 0.31858404 | Y88: 0.00023616845
A89: 13918 | B89: 14337 | C89: קבוצת חג'ג' ייזום נדל"ן בע"מ | D89: 520033309 | E89: ח.פ. | F89: חג'ג' אפ 1 | G89: IL0012166547 | H89: ISIN | I89: ישראל | J89: ישראל | K89: סחיר | L89: TASE | M89: 823013 | N89: בנייה | O89: 46395 | P89: לא | Q89: ILS | R89: 3230 | S89: 1 | T89: 80 | U89: 1 | V89: 345.3 | W89: 0.27624 | X89: 0.091792079 | Y89: 6.8046075e-05
A90: 13918 | B90: 14337 | C90: בלדי בע"מ | D90: 511226136 | E90: ח.פ. | F90: בלדי אפ 1 | G90: IL0012166620 | H90: ISIN | I90: ישראל | J90: ישראל | K90: סחיר | L90: TASE | M90: 1212539 | N90: מסחר | O90: 31/01/2028 | P90: לא | Q90: ILS | R90: 2800 | S90: 1 | T90: 250 | U90: 1 | V90: 540.6 | W90: 1.3515 | X90: 0.44909135 | Y90: 0.00033291438
A91: 13918 | B91: 14337 | C91: סולאיר אנרגיות מתחדשות בע"מ | D91: 516046307 | E91: ח.פ. | F91: סולאיר אפ 1 | G91: IL0012179185 | H91: ISIN | I91: ישראל | J91: ישראל | K91: סחיר | L91: TASE | M91: 1172287 | N91: אנרגיה מתחדשת | O91: 31/08/2026 | P91: לא | Q91: ILS | R91: 4152 | S91: 1 | T91: 30 | U91: 1 | V91: 289.3 | W91: 0.08679 | X91: 0.02883954 | Y91: 2.1378942e-05
A92: 13918 | B92: 14337 | C92: נאייקס בע"מ | D92: 513639013 | E92: ח.פ. | F92: נאייקס אפ 1 | G92: IL0012189812 | H92: ISIN | I92: ישראל | J92: ישראל | K92: סחיר | L92: TASE | M92: 1175116 | N92: תוכנה ואינטרנט | O92: 31/03/2027 | P92: לא | Q92: ILS | R92: 18134.417 | S92: 1 | T92: 24 | U92: 1 | V92: 1066 | W92: 0.25584 | X92: 0.085013341 | Y92: 6.3020952e-05
A93: 13908 | B93: 14339 | C93: מיטב טרייד השקעות בע"מ | D93: 516854239 | E93: ח.פ. | F93: מיטב טרייד אפ 1 | G93: IL0012031998 | H93: ISIN | I93: ישראל | J93: ישראל | K93: סחיר | L93: TASE | M93: 1203181 | N93: שירותים פיננסיים | O93: 18/01/2028 | P93: לא | Q93: ILS | R93: 715.068 | S93: 1 | T93: 25000 | U93: 1 | V93: 1408 | W93: 352 | X93: 0.86492481 | Y93: 0.0045031883
A94: 13908 | B94: 14339 | C94: ארי נדל"ן (ארנה) השקעות בע"מ | D94: 520038332 | E94: ח.פ. | F94: ארי נדלן אפ 1 | G94: IL0012123498 | H94: ISIN | I94: ישראל | J94: ישראל | K94: סחיר | L94: TASE | M94: 366013 | N94: נדל"ן מניב בישראל | O94: 27/09/2027 | P94: לא | Q94: ILS | R94: 285.24 | S94: 1 | T94: 740 | U94: 1 | V94: 43.4 | W94: 0.32116 | X94: 0.00078914561 | Y94: 4.1086476e-06
A95: 13908 | B95: 14339 | C95: שובל הנדסה ובניין בע"מ | D95: 512951518 | E95: ח.פ. | F95: שובל הנדסה אפ 1 | G95: IL0012159617 | H95: ISIN | I95: ישראל | J95: ישראל | K95: סחיר | L95: TASE | M95: 1207968 | N95: בנייה | O95: 46661 | P95: לא | Q95: ILS | R95: 1023 | S95: 1 | T95: 3750 | U95: 1 | V95: 383.5 | W95: 14.38125 | X95: 0.035337216 | Y95: 0.00018398147
A96: 13908 | B96: 14339 | C96: קבוצת חג'ג' ייזום נדל"ן בע"מ | D96: 520033309 | E96: ח.פ. | F96: חג'ג' אפ 1 | G96: IL0012166547 | H96: ISIN | I96: ישראל | J96: ישראל | K96: סחיר | L96: TASE | M96: 823013 | N96: בנייה | O96: 46395 | P96: לא | Q96: ILS | R96: 3230 | S96: 1 | T96: 1600 | U96: 1 | V96: 345.3 | W96: 5.5248 | X96: 0.013575388 | Y96: 7.0679587e-05
A97: 13908 | B97: 14339 | C97: בלדי בע"מ | D97: 511226136 | E97: ח.פ. | F97: בלדי אפ 1 | G97: IL0012166620 | H97: ISIN | I97: ישראל | J97: ישראל | K97: סחיר | L97: TASE | M97: 1212539 | N97: מסחר | O97: 31/01/2028 | P97: לא | Q97: ILS | R97: 2800 | S97: 1 | T97: 5000 | U97: 1 | V97: 540.6 | W97: 27.03 | X97: 0.06641738 | Y97: 0.0003457988
A98: 13908 | B98: 14339 | C98: סולאיר אנרגיות מתחדשות בע"מ | D98: 516046307 | E98: ח.פ. | F98: סולאיר אפ 1 | G98: IL0012179185 | H98: ISIN | I98: ישראל | J98: ישראל | K98: סחיר | L98: TASE | M98: 1172287 | N98: אנרגיה מתחדשת | O98: 31/08/2026 | P98: לא | Q98: ILS | R98: 4152 | S98: 1 | T98: 500 | U98: 1 | V98: 289.3 | W98: 1.4465 | X98: 0.0035543004 | Y98: 1.8505289e-05
A99: 13908 | B99: 14339 | C99: נאייקס בע"מ | D99: 513639013 | E99: ח.פ. | F99: נאייקס אפ 1 | G99: IL0012189812 | H99: ISIN | I99: ישראל | J99: ישראל | K99: סחיר | L99: TASE | M99: 1175116 | N99: תוכנה ואינטרנט | O99: 31/03/2027 | P99: לא | Q99: ILS | R99: 18134.417 | S99: 1 | T99: 588 | U99: 1 | V99: 1066 | W99: 6.26808 | X99: 0.015401755 | Y99: 8.0188478e-05
A100: 13908 | B100: 15263 | C100: מיטב טרייד השקעות בע"מ | D100: 516854239 | E100: ח.פ. | F100: מיטב טרייד אפ 1 | G100: IL0012031998 | H100: ISIN | I100: ישראל | J100: ישראל | K100: סחיר | L100: TASE | M100: 1203181 | N100: שירותים פיננסיים | O100: 18/01/2028 | P100: לא | Q100: ILS | R100: 715.068 | S100: 1 | T100: 50000 | U100: 1 | V100: 1408 | W100: 704 | X100: 0.6800027 | Y100: 0.0020342198
...

Sheet אופציות
A1: מספר קופה/קרן/ח.פ. עבור חברת ביטוח | B1: מספר מסלול | C1: שם מנפיק | D1: מספר מנפיק | E1: סוג מספר מזהה מנפיק | F1: שם נייר ערך | G1: מספר נייר ערך | H1: סוג מספר נייר ערך | I1: מאפיין עיקרי | J1: ישראל/חו"ל | K1: מדינה לפי חשיפה כלכלית | L1: זירת מסחר | M1: ענף מסחר | N1: נכס בסיס | O1: תאריך פקיעה | P1: בעל עניין/צד קשור | Q1: מטבע פעילות | R1: שער מימוש | S1: ערך נקוב (יחידות) | T1: שער חליפין | U1: שער נייר הערך | V1: שווי הוגן (באלפי ש"ח) | W1: שיעור מנכסי אפיק ההשקעה | X1: שיעור מסך נכסי ההשקעה

Sheet חוזים עתידיים
A1: מספר קופה/קרן/ח.פ. עבור חברת ביטוח | B1: מספר מסלול | C1: שם מנפיק | D1: מספר מנפיק | E1: סוג מספר מזהה מנפיק | F1: שם נייר ערך | G1: מספר נייר ערך | H1: סוג מספר נייר ערך | I1: ישראל/חו"ל | J1: מדינה לפי חשיפה כלכלית | K1: זירת מסחר | L1: נכס בסיס | M1: בעל עניין/צד קשור | N1: מטבע פעילות | O1: ערך נקוב (יחידות) | P1: שער חליפין | Q1: שער נייר הערך | R1: שווי הוגן (באלפי ש"ח) | S1: שיעור מנכסי אפיק ההשקעה | T1: שיעור מסך נכסי ההשקעה
A2: 13908 | B2: 13909 | C2: ULTRA10 YR 06/25 | D2: BBG01PSLLQ32 | E2: LEI | F2: ULTRA10 YR 06/25 | G2: UXYM5 COMDTY | H2: ISIN | I2: חו"ל | J2: ארה"ב | K2: CBOE | L2: מניות לרבות מדדי מניות | M2: לא | N2: USD | O2: 63 | P2: 3.718 | Q2: 11412.5 | R2: 218.65743 | S2: -0.0080817898 | T2: 5.3292924e-05
A3: 13908 | B3: 13909 | C3: NIKKEI 225 MINI 06/25 | D3: BBG00VFJK9B9 | E3: LEI | F3: NIKKEI 225 MINI 06/25 | G3: NOM5 INDEX | H3: ISIN | I3: חו"ל | J3: יפן | K3: NYSE | L3: מניות לרבות מדדי מניות | M3: לא | N3: JPY | O3: 390 | P3: 0.024893 | Q3: 3566000 | R3: -884.06322 | S3: 0.032675831 | T3: -0.0002154709
A4: 13908 | B4: 13909 | C4: Mini TPX IDX FUT Jun25 | D4: BBG01PQDV4P6 | E4: LEI | F4: TMIM5 INDEX | G4: TMIM5 INDEX | H4: ISIN | I4: חו"ל | J4: יפן | K4: NASDAQ | L4: מניות לרבות מדדי מניות | M4: לא | N4: JPY | O4: 60 | P4: 0.024893 | Q4: 266200 | R4: 27.58313 | S4: -0.0010194991 | T4: 6.7227794e-06
A5: 13908 | B5: 13909 | C5: FT MINI DOW 06/25 | D5: BBG01NC6V863 | E5: LEI | F5: FT MINI DOW 06/25 | G5: DMM5 INDEX | H5: ISIN | I5: חו"ל | J5: ארה"ב | K5: CME | L5: מניות לרבות מדדי מניות | M5: לא | N5: USD | O5: 38 | P5: 3.718 | Q5: 4225900 | R5: 24.78114 | S5: -0.00091593487 | T5: 6.0398561e-06
A6: 13908 | B6: 13909 | C6: FUTURE MINI NASDAQ 06/25 | D6: BBG01KJ7X5T9 | E6: LEI | F6: FUTURE MINI NASDAQ 06/25 | G6: NQM5 INDEX | H6: ISIN | I6: חו"ל | J6: ארה"ב | K6: NASDAQ | L6: מניות לרבות מדדי מניות | M6: לא | N6: USD | O6: 90 | P6: 3.718 | Q6: 1943950 | R6: -4011.6601 | S6: 0.14827483 | T6: -0.00097775365
A7: 13908 | B7: 13909 | C7: STOXX600 06/25 | D7: BBG018BS33N2 | E7: LEI | F7: STOXX600 06/25 | G7: SXOM5 INDEX | H7: ISIN | I7: חו"ל | J7: גרמניה | K7: EUREX | L7: מניות לרבות מדדי מניות | M7: לא | N7: EUR | O7: 1420 | P7: 4.0219 | Q7: 53160 | R7: -5065.8581 | S7: 0.18723901 | T7: -0.0012346912
A8: 13908 | B8: 13909 | C8: S&P500 EMINI FUT 06/25 | D8: BBG01FTN83M4 | E8: LEI | F8: S&P500 EMINI FUT 06/25 | G8: ESM5 INDEX | H8: ISIN | I8: חו"ל | J8: ארה"ב | K8: CME | L8: מניות לרבות מדדי מניות | M8: לא | N8: USD | O8: 925 | P8: 3.718 | Q8: 565325 | R8: -13579.226 | S8: 0.5019013 | T8: -0.0033096367
A9: 13908 | B9: 13909 | C9: MSCI EmgMkt 06/25 | D9: BBG013V2S5C8 | E9: LEI | F9: MSCI EmgMkt 06/25 | G9: MESM5 INDEX | H9: ISIN | I9: חו"ל | J9: ארה"ב | K9: CME | L9: מניות לרבות מדדי מניות | M9: לא | N9: USD | O9: 380 | P9: 3.718 | Q9: 111080 | R9: -2604.8319 | S9: 0.096277104 | T9: -0.00063487031
A10: 13908 | B10: 13909 | C10: F-RUSSELL 06/25 | D10: BBG01LX7ZV67 | E10: LEI | F10: F-RUSSELL 06/25 | G10: RTYM5 INDEX | H10: ISIN | I10: חו"ל | J10: ארה"ב | K10: CME | L10: מניות לרבות מדדי מניות | M10: לא | N10: USD | O10: 50 | P10: 3.718 | Q10: 202710 | R10: -546.84436 | S10: 0.020211896 | T10: -0.00013328125
A11: 13908 | B11: 13909 | C11: SP MICRO 06/25 | D11: BBG01LX7ZWS1 | E11: LEI | F11: SP MICRO 06/25 | G11: HWAM5 INDEX | H11: ISIN | I11: חו"ל | J11: ארה"ב | K11: CME | L11: מניות לרבות מדדי מניות | M11: לא | N11: USD | O11: 385 | P11: 3.718 | Q11: 565325 | R11: -565.52864 | S11: 0.020902485 | T11: -0.00013783513
A12: 13908 | B12: 13909 | C12: IFSC NIFTY 50 FUT Apr25 | D12: BBG01S1W55H0 | E12: LEI | F12: NIFTY 50 IFSC | G12: JGSJ5 INDEX | H12: ISIN | I12: חו"ל | J12: הודו | K12: NASDAQ | L12: מניות לרבות מדדי מניות | M12: לא | N12: USD | O12: 25 | P12: 3.718 | Q12: 2351800 | R12: -68.57943 | S12: 0.002534762 | T12: -1.6714723e-05
A13: 13908 | B13: 13910 | C13: ULTRA10 YR 06/25 | D13: BBG01PSLLQ32 | E13: LEI | F13: ULTRA10 YR 06/25 | G13: UXYM5 COMDTY | H13: ISIN | I13: חו"ל | J13: ארה"ב | K13: CBOE | L13: מניות לרבות מדדי מניות | M13: לא | N13: USD | O13: 22 | P13: 3.718 | Q13: 11412.5 | R13: 76.35656 | S13: -0.0072898933 | T13: 4.0622432e-05
... A115: 13918 | B115: 15273 | C115: S&P500 EMINI FUT 06/25 | D115: BBG01FTN83M4 | E115: LEI | F115: S&P500 EMINI FUT 06/25 | G115: ESM5 INDEX | H115: ISIN | I115: חו"ל | J115: ארה"ב | K115: CME | L115: מניות לרבות מדדי מניות | M115: לא | N115: USD | O115: 13 | P115: 3.718 | Q115: 565325 | R115: -244.12109 | S115: 1 | T115: -0.010255893

Sheet מוצרים מובנים
A1: מספר קופה/קרן/ח.פ. עבור חברת ביטוח | B1: מספר מסלול | C1: שם מנפיק | D1: מספר מנפיק | E1: סוג מספר מזהה מנפיק | F1: שם נייר ערך | G1: מספר נייר ערך | H1: סוג מספר נייר ערך | I1: מאפיין עיקרי | J1: ישראל/חו"ל | K1: מדינה לפי חשיפה כלכלית | L1: סטאטוס סחירות | M1: זירת מסחר | N1: נכס בסיס | O1: בעל עניין/צד קשור | P1: מח"מ | Q1: שיעור ריבית | R1: תשואה לפדיון | S1: דירוג | T1: שם מדרג | U1: דירוג נייר הערך/המנפיק | V1: מטבע פעילות | W1: ערך נקוב (יחידות) | X1: שער חליפין | Y1: שער נייר הערך | Z1: שווי הוגן (באלפי ש"ח) | AA1: שיעור מנכסי אפיק ההשקעה | AB1: שיעור מסך נכסי ההשקעה
A2: 13908 | B2: 13909 | C2: אלה פקדונות בע"מ | D2: 515666881 | E2: ח.פ. | F2: אלה פקדון אגח ד | G2: IL0011623043 | H2: ISIN | I2: קרן לא מובטחת | J2: ישראל | K2: ישראל | L2: סחיר | M2: TASE | N2: מט"ח | O2: לא | P2: 1.007 | Q2: 0.052036 | R2: 0.056 | S2: ilAAAs | T2: S&P מעלות | U2: נייר ערך | V2: ILS | W2: 153279 | X2: 1 | Y2: 108.32 | Z2: 166.03181 | AA2: 0.72280995 | AB2: 4.0466591e-05
A3: 13908 | B3: 13909 | C3: אלה פקדונות בע"מ | D3: 515666881 | E3: ח.פ. | F3: אלה פקדון אגח ה | G3: IL0011625774 | H3: ISIN | I3: קרן מובטחת | J3: ישראל | K3: ישראל | L3: סחיר | M3: TASE | N3: מט"ח | O3: לא | P3: 3.291 | Q3: 0.0005 | R3: 0.0249 | S3: ilAAAs | T3: S&P מעלות | U3: נייר ערך | V3: ILS | W3: 60050.42 | X3: 1 | Y3: 106.03 | Z3: 63.67146 | AA3: 0.27719005 | AB3: 1.5518514e-05
A4: 13908 | B4: 13910 | C4: אלה פקדונות בע"מ | D4: 515666881 | E4: ח.פ. | F4: אלה פקדון אגח ה | G4: IL0011625774 | H4: ISIN | I4: קרן מובטחת | J4: ישראל | K4: ישראל | L4: סחיר | M4: TASE | N4: מט"ח | O4: לא | P4: 3.291 | Q4: 0.0005 | R4: 0.0249 | S4: ilAAAs | T4: S&P מעלות | U4: נייר ערך | V4: ILS | W4: 0.33 | X4: 1 | Y4: 106.03 | Z4: 0.00035 | AA4: 1 | AB4: 1.862034e-10
A5: 13908 | B5: 13911 | C5: אלה פקדונות בע"מ | D5: 515666881 | E5: ח.פ. | F5: אלה פקדון אגח ה | G5: IL0011625774 | H5: ISIN | I5: קרן מובטחת | J5: ישראל | K5: ישראל | L5: סחיר | M5: TASE | N5: מט"ח | O5: לא | P5: 3.291 | Q5: 0.0005 | R5: 0.0249 | S5: ilAAAs | T5: S&P מעלות | U5: נייר ערך | V5: ILS | W5: 0.58 | X5: 1 | Y5: 106.03 | Z5: 0.00061 | AA5: 1 | AB5: 1.0206052e-09
A6: 13918 | B6: 13920 | C6: אלה פקדונות בע"מ | D6: 515666881 | E6: ח.פ. | F6: אלה פקדון אגח ה | G6: IL0011625774 | H6: ISIN | I6: קרן מובטחת | J6: ישראל | K6: ישראל | L6: סחיר | M6: TASE | N6: מט"ח | O6: לא | P6: 3.291 | Q6: 0.0005 | R6: 0.0249 | S6: ilAAAs | T6: S&P מעלות | U6: נייר ערך | V6: ILS | W6: 8175 | X6: 1 | Y6: 106.03 | Z6: 8.66795 | AA6: 1 | AB6: 0.00011996645
A7: 13918 | B7: 13923 | C7: אלה פקדונות בע"מ | D7: 515666881 | E7: ח.פ. | F7: אלה פקדון אגח ד | G7: IL0011623043 | H7: ISIN | I7: קרן לא מובטחת | J7: ישראל | K7: ישראל | L7: סחיר | M7: TASE | N7: מט"ח | O7: לא | P7: 1.007 | Q7: 0.052036 | R7: 0.056 | S7: ilAAAs | T7: S&P מעלות | U7: נייר ערך | V7: ILS | W7: 100 | X7: 1 | Y7: 108.32 | Z7: 0.10832 | AA7: 0.55327408 | AB7: 7.0047315e-05
A8: 13918 | B8: 13923 | C8: אלה פקדונות בע"מ | D8: 515666881 | E8: ח.פ. | F8: אלה פקדון אגח ה | G8: IL0011625774 | H8: ISIN | I8: קרן מובטחת | J8: ישראל | K8: ישראל | L8: סחיר | M8: TASE | N8: מט"ח | O8: לא | P8: 3.291 | Q8: 0.0005 | R8: 0.0249 | S8: ilAAAs | T8: S&P מעלות | U8: נייר ערך | V8: ILS | W8: 82.49 | X8: 1 | Y8: 106.03 | Z8: 0.08746 | AA8: 0.44672592 | AB8: 5.6557775e-05

Sheet לא סחיר איגרות חוב ממשלתיות
A1: מספר קופה/קרן/ח.פ. עבור חברת ביטוח | B1: מספר מסלול | C1: שם מנפיק | D1: שם נייר ערך | E1: מספר נייר ערך | F1: סוג מספר נייר ערך | G1: מאפיין עיקרי | H1: ישראל/חו"ל | I1: מדינה לפי חשיפה כלכלית | J1: תאריך רכישה | K1: דירוג | L1: שם מדרג | M1: מטבע פעילות | N1: מח"מ | O1: מועד פדיון | P1: שיעור ריבית | Q1: תשואה לפדיון | R1: ערך נקוב (יחידות) | S1: שער חליפין | T1: שער נייר הערך | U1: שווי הוגן (באלפי ש"ח) | V1: עלות מופחתת (באלפי ש"ח) | W1: השיטה שיושמה בדוח הכספי | X1: שיעור מנכסי אפיק ההשקעה | Y1: שיעור מסך נכסי ההשקעה

Sheet לא סחיר איגרות חוב מיועדות
A1: מספר קופה/קרן/ח.פ. עבור חברת ביטוח | B1: מספר מסלול | C1: מאפיין עיקרי | D1: שם נייר ערך | E1: מספר נייר ערך | F1: תאריך רכישה | G1: מח"מ | H1: סוג הצמדה | I1: מועד פדיון | J1: שיעור ריבית | K1: תשואה לפדיון | L1: ערך נקוב (יחידות) | M1: שער נייר הערך | N1: שווי הוגן (באלפי ש"ח) | O1: עלות מופחתת (באלפי ש"ח) | P1: השיטה שיושמה בדוח הכספי | Q1: שיעור מנכסי אפיק ההשקעה | R1: שיעור מסך נכסי ההשקעה
A2: 13908 | B2: 13909 | C2: ערד בקרן פנסיה מקיפה חדשה | D2: ערד סדרה 8909 | E2: 8289092 | F2: 44713 | G2: 8.574 | H2: צמוד למדד המחירים לצרכן | I2: 50192 | J2: 0.048 | K2: 0.0486 | L2: 497316 | M2: 111.8012 | N2: 556.00526 | P2: שווי הוגן | Q2: 0.0052190947 | R2: 0.00013551402
A3: 13908 | B3: 13909 | C3: ערד בקרן פנסיה מקיפה חדשה | D3: ערד סדרה 8910 | E3: 8289100 | F3: 44743 | G3: 8.529 | H3: צמוד למדד המחירים לצרכן | I3: 50222 | J3: 0.048 | K3: 0.0486 | L3: 23126176 | M3: 110.7193 | N3: 25605.14 | P3: שווי הוגן | Q3: 0.24034962 | R3: 0.0062406879
A4: 13908 | B4: 13909 | C4: ערד בקרן פנסיה מקיפה חדשה | D4: ערד סדרה 8911 | E4: 8289118 | F4: 44774 | G4: 8.484 | H4: צמוד למדד המחירים לצרכן | I4: 50253 | J4: 0.048 | K4: 0.0486 | L4: 42529120 | M4: 109.8423 | N4: 46714.963 | P4: שווי הוגן | Q4: 0.43850272 | R4: 0.011385742
A5: 13908 | B5: 13909 | C5: ערד בקרן פנסיה מקיפה חדשה | D5: ערד סדרה 8912 | E5: 8289126 | F5: 44805 | G5: 8.439 | H5: צמוד למדד המחירים לצרכן | I5: 50284 | J5: 0.048 | K5: 0.0486 | L5: 31101860 | M5: 108.2147 | N5: 33656.784 | P5: שווי הוגן | Q5: 0.31592857 | R5: 0.0082030987
A6: 13908 | B6: 13910 | C6: ערד בקרן פנסיה מקיפה חדשה | D6: ערד סדרה 8909 | E6: 8289092 | F6: 44713 | G6: 8.574 | H6: צמוד למדד המחירים לצרכן | I6: 50192 | J6: 0.048 | K6: 0.0486 | L6: 445034 | M6: 111.8012 | N6: 497.55335 | P6: שווי הוגן | Q6: 0.019065162 | R6: 0.00026470322
A7: 13908 | B7: 13910 | C7: ערד בקרן פנסיה מקיפה חדשה | D7: ערד סדרה 8910 | E7: 8289100 | F7: 44743 | G7: 8.529 | H7: צמוד למדד המחירים לצרכן | I7: 50222 | J7: 0.048 | K7: 0.0486 | L7: 1606880.3 | M7: 110.7193 | N7: 1779.1267 | P7: שווי הוגן | Q7: 0.068172263 | R7: 0.00094651268
A8: 13908 | B8: 13910 | C8: ערד בקרן פנסיה מקיפה חדשה | D8: ערד סדרה 8911 | E8: 8289118 | F8: 44774 | G8: 8.484 | H8: צמוד למדד המחירים לצרכן | I8: 50253 | J8: 0.048 | K8: 0.0486 | L8: 9602710.2 | M8: 109.8423 | N8: 10547.838 | P8: שווי הוגן | Q8: 0.4041702 | R8: 0.0056115522
A9: 13908 | B9: 13910 | C9: ערד בקרן פנסיה מקיפה חדשה | D9: ערד סדרה 8912 | E9: 8289126 | F9: 44805 | G9: 8.439 | H9: צמוד למדד המחירים לצרכן | I9: 50284 | J9: 0.048 | K9: 0.0486 | L9: 12265429 | M9: 108.2147 | N9: 13272.997 | P9: שווי הוגן | Q9: 0.50859238 | R9: 0.0070613636
A10: 13908 | B10: 13911 | C10: ערד בקרן פנסיה מקיפה חדשה | D10: ערד סדרה 8909 | E10: 8289092 | F10: 44713 | G10: 8.574 | H10: צמוד למדד המחירים לצרכן | I10: 50192 | J10: 0.048 | K10: 0.0486 | L10: 1268 | M10: 111.8012 | N10: 1.41764 | P10: שווי הוגן | Q10: 0.00020932412 | R10: 2.3718864e-06
A11: 13908 | B11: 13911 | C11: ערד בקרן פנסיה מקיפה חדשה | D11: ערד סדרה 8910 | E11: 8289100 | F11: 44743 | G11: 8.529 | H11: צמוד למדד המחירים לצרכן | I11: 50222 | J11: 0.048 | K11: 0.0486 | L11: 815901.34 | M11: 110.7193 | N11: 903.36025 | P11: שווי הוגן | Q11: 0.13338724 | R11: 0.001511433
A12: 13908 | B12: 13911 | C12: ערד בקרן פנסיה מקיפה חדשה | D12: ערד סדרה 8911 | E12: 8289118 | F12: 44774 | G12: 8.484 | H12: צמוד למדד המחירים לצרכן | I12: 50253 | J12: 0.048 | K12: 0.0486 | L12: 2185359.2 | M12: 109.8423 | N12: 2400.4488 | P12: שווי הוגן | Q12: 0.35444249 | R12: 0.0040162466
A13: 13908 | B13: 13911 | C13: ערד בקרן פנסיה מקיפה חדשה | D13: ערד סדרה 8912 | E13: 8289126 | F13: 44805 | G13: 8.439 | H13: צמוד למדד המחירים לצרכן | I13: 50284 | J13: 0.048 | K13: 0.0486 | L13: 3204035 | M13: 108.2147 | N13: 3467.2369 | P13: שווי הוגן | Q13: 0.51196095 | R13: 0.0058011145
... A25: 13908 | B25: 13915 | C25: ערד בקרן פנסיה מקיפה חדשה | D25: ערד סדרה 8912 | E25: 8289126 | F25: 44805 | G25: 8.439 | H25: צמוד למדד המחירים לצרכן | I25: 50284 | J25: 0.048 | K25: 0.0486 | L25: 145465 | M25: 108.2147 | N25: 157.41451 | P25: שווי הוגן | Q25: 0.6398493 | R25: 0.00040046425

Sheet אפיק השקעה מובטח תשואה
A1: מספר קרן | B1: מספר מסלול | C1: מאפיין עיקרי | D1: חודש הנפקת שכבה | E1: חודש הבדיקה | F1: שווי הנכסים באפיק (באלפי ש"ח) | G1: שיעור מסך נכסי ההשקעה
A2: 13908 | B2: 13909 | C2: נכס או התחייבות בגין השלמת המדינה לתשואת היעד | D2: 44835 | E2: 46661 | F2: 36002.139 | G2: 0.008774727
A3: 13908 | B3: 13909 | C3: נכס או התחייבות בגין השלמת המדינה לתשואת היעד | D3: 44866 | E3: 46692 | F3: 23728.01 | G3: 0.005783179
A4: 13908 | B4: 13909 | C4: נכס או התחייבות בגין השלמת המדינה לתשואת היעד | D4: 44896 | E4: 46722 | F4: 36076.942 | G4: 0.0087929586
A5: 13908 | B5: 13909 | C5: נכס או התחייבות בגין השלמת המדינה לתשואת היעד | D5: 44927 | E5: 46753 | F5: 27257.878 | G5: 0.0066435064
A6: 13908 | B6: 13909 | C6: נכס או התחייבות בגין השלמת המדינה לתשואת היעד | D6: 44958 | E6: 46784 | F6: 25526.64 | G6: 0.0062215553
A7: 13908 | B7: 13909 | C7: נכס או התחייבות בגין השלמת המדינה לתשואת היעד | D7: 44986 | E7: 46813 | F7: 25520.587 | G7: 0.00622008
A8: 13908 | B8: 13909 | C8: נכס או התחייבות בגין השלמת המדינה לתשואת היעד | D8: 45017 | E8: 46844 | F8: 26278.807 | G8: 0.0064048795
A9: 13908 | B9: 13909 | C9: נכס או התחייבות בגין השלמת המדינה לתשואת היעד | D9: 45047 | E9: 46874 | F9: 31128.772 | G9: 0.0075869514
A10: 13908 | B10: 13909 | C10: נכס או התחייבות בגין השלמת המדינה לתשואת היעד | D10: 45078 | E10: 46905 | F10: 22482.233 | G10: 0.0054795483
A11: 13908 | B11: 13909 | C11: נכס או התחייבות בגין השלמת המדינה לתשואת היעד | D11: 45108 | E11: 46935 | F11: 34892.057 | G11: 0.008504169
A12: 13908 | B12: 13909 | C12: נכס או התחייבות בגין השלמת המדינה לתשואת היעד | D12: 45139 | E12: 46966 | F12: 57500.358 | G12: 0.014014444
A13: 13908 | B13: 13909 | C13: נכס או התחייבות בגין השלמת המדינה לתשואת היעד | D13: 45170 | E13: 46997 | F13: 45169.61 | G13: 0.011009096
... A312: 13908 | B312: 15266 | C312: נכס או התחייבות בגין השלמת המדינה לתשואת היעד | D312: 45717 | E312: 47543 | F312: 9631.2228 | G312: 0.025698563

Sheet לא סחיר ניירות ערך מסחריים
A1: מספר קופה/קרן/ח.פ. עבור חברת ביטוח | B1: מספר מסלול | C1: שם מנפיק | D1: מספר מנפיק | E1: סוג מספר מזהה מנפיק | F1: שם נייר ערך | G1: מספר נייר ערך | H1: סוג מספר נייר ערך | I1: מאפיין עיקרי | J1: ישראל/חו"ל | K1: מדינה לפי חשיפה כלכלית | L1: ענף מסחר | M1: בעל עניין/צד קשור | N1: תאריך רכישה | O1: דירוג | P1: שם מדרג | Q1: דירוג נייר הערך/המנפיק | R1: מטבע פעילות | S1: מח"מ | T1: סוג הצמדה | U1: ריבית עוגן | V1: מועד פדיון | W1: שיעור ריבית | X1: תשואה לפדיון | Y1: נחיתות חוזית | Z1: האם סווג כחוב בעייתי | AA1: סוג גורם משערך | AB1: תלות/אי-תלות המשערך | AC1: שם גורם משערך | AD1: תאריך שערוך אחרון | AE1: תאריך אחרון בו נבחנה בפועל ירידת ערך | AF1: ערך נקוב (יחידות) | AG1: שער חליפין | AH1: שער נייר הערך | AI1: שווי הוגן (באלפי ש"ח) | AJ1: עלות מופחתת (באלפי ש"ח) | AK1: עלות מופחתת (במטבע הפעילות) | AL1: השיטה שיושמה בדוח הכספי | AM1: שיעור מנכסי אפיק ההשקעה | AN1: שיעור מסך נכסי ההשקעה
A2: 13908 | B2: 13909 | C2: שיכון ובינוי בע"מ | D2: 520036104 | E2: ח.פ. | F2: נעמ שכון ובנוי3 | G2: 11020132 | H2: פנימי | I2: לא צמוד למדד המחירים לצרכן | J2: ישראל | K2: ישראל | L2: בנייה | M2: לא | N2: 22/11/2022 | O2: NR | P2: NR | Q2: נייר ערך | R2: ILS | S2: 0.16 | T2: לא צמוד | U2: ללא | V2: 30/05/2025 | W2: 0.071 | X2: 0.0713 | Y2: החוב לא נחות | AA2: חברת ציטוט | AB2: אי-תלות | AD2: 31/03/2025 | AE2: 31/03/2025 | AF2: 4499800 | AG2: 1 | AH2: 107.7 | AI2: 4846.2846 | AL2: שווי הוגן | AM2: 1 | AN2: 0.0011811749
A3: 13908 | B3: 13910 | C3: שיכון ובינוי בע"מ | D3: 520036104 | E3: ח.פ. | F3: נעמ שכון ובנוי3 | G3: 11020132 | H3: פנימי | I3: לא צמוד למדד המחירים לצרכן | J3: ישראל | K3: ישראל | L3: בנייה | M3: לא | N3: 22/11/2022 | O3: NR | P3: NR | Q3: נייר ערך | R3: ILS | S3: 0.16 | T3: לא צמוד | U3: ללא | V3: 30/05/2025 | W3: 0.071 | X3: 0.0713 | Y3: החוב לא נחות | AA3: חברת ציטוט | AB3: אי-תלות | AD3: 31/03/2025 | AE3: 31/03/2025 | AF3: 1400000 | AG3: 1 | AH3: 107.7 | AI3: 1507.8 | AL3: שווי הוגן | AM3: 1 | AN3: 0.00080216426
A4: 13908 | B4: 13911 | C4: שיכון ובינוי בע"מ | D4: 520036104 | E4: ח.פ. | F4: נעמ שכון ובנוי3 | G4: 11020132 | H4: פנימי | I4: לא צמוד למדד המחירים לצרכן | J4: ישראל | K4: ישראל | L4: בנייה | M4: לא | N4: 22/11/2022 | O4: NR | P4: NR | Q4: נייר ערך | R4: ILS | S4: 0.16 | T4: לא צמוד | U4: ללא | V4: 30/05/2025 | W4: 0.071 | X4: 0.0713 | Y4: החוב לא נחות | AA4: חברת ציטוט | AB4: אי-תלות | AD4: 31/03/2025 | AE4: 31/03/2025 | AF4: 299700 | AG4: 1 | AH4: 107.7 | AI4: 322.7769 | AL4: שווי הוגן | AM4: 1 | AN4: 0.00054004552
A5: 13908 | B5: 13912 | C5: שיכון ובינוי בע"מ | D5: 520036104 | E5: ח.פ. | F5: נעמ שכון ובנוי3 | G5: 11020132 | H5: פנימי | I5: לא צמוד למדד המחירים לצרכן | J5: ישראל | K5: ישראל | L5: בנייה | M5: לא | N5: 22/11/2022 | O5: NR | P5: NR | Q5: נייר ערך | R5: ILS | S5: 0.16 | T5: לא צמוד | U5: ללא | V5: 30/05/2025 | W5: 0.071 | X5: 0.0713 | Y5: החוב לא נחות | AA5: חברת ציטוט | AB5: אי-תלות | AD5: 31/03/2025 | AE5: 31/03/2025 | AF5: 6495000 | AG5: 1 | AH5: 107.7 | AI5: 6995.115 | AL5: שווי הוגן | AM5: 1 | AN5: 0.0028801065
A6: 13908 | B6: 13913 | C6: שיכון ובינוי בע"מ | D6: 520036104 | E6: ח.פ. | F6: נעמ שכון ובנוי3 | G6: 11020132 | H6: פנימי | I6: לא צמוד למדד המחירים לצרכן | J6: ישראל | K6: ישראל | L6: בנייה | M6: לא | N6: 22/11/2022 | O6: NR | P6: NR | Q6: נייר ערך | R6: ILS | S6: 0.16 | T6: לא צמוד | U6: ללא | V6: 30/05/2025 | W6: 0.071 | X6: 0.0713 | Y6: החוב לא נחות | AA6: חברת ציטוט | AB6: אי-תלות | AD6: 31/03/2025 | AE6: 31/03/2025 | AF6: 15000 | AG6: 1 | AH6: 107.7 | AI6: 16.155 | AL6: שווי הוגן | AM6: 1 | AN6: 0.00061276968
