Workbook
Name Additional_Factor: 'אפשרויות בחירה'!$C$701:$C$850
Name Amoritization: 'אפשרויות בחירה'!$C$546:$C$550
Name Capsule: 'אפשרויות בחירה'!$C$926:$C$928
Name Company_Name: 'File Name Info'!$A$34:$A$120
Name Company_Name_ID: 'File Name Info'!$A$34:$B$120
Name Consortium: 'אפשרויות בחירה'!$C$514:$C$515
Name Country_list: 'אפשרויות בחירה'!$C$4:$C$85
Name Country_list_funds: 'אפשרויות בחירה'!$C$4:$C$103
Name CSA: 'אפשרויות בחירה'!$C$688:$C$689
Name Delivery: 'אפשרויות בחירה'!$C$666:$C$667
Name Dependence_Independence: 'אפשרויות בחירה'!$C$654:$C$655
Name Duration_Underlying_Interest_Rate: 'אפשרויות בחירה'!$C$680:$C$687
Name File_Type: 'File Name Info'!$A$10:$A$12
Name Full_File_Type: 'File Name Info'!$A$11:$B$13
Name Full_Type: 'File Name Info'!$A$2:$B$8
Name Full_Type_Nostro: 'File Name Info'!$A$3:$B$6
Name Full_Year: 'File Name Info'!$A$22:$B$31
Name Fund_Strategy: 'אפשרויות בחירה'!$C$597:$C$621
Name Fund_type: 'אפשרויות בחירה'!$C$328:$C$498
Name Holding_interest: 'אפשרויות בחירה'!$C$146:$C$147
Name In_the_books: 'אפשרויות בחירה'!$C$656:$C$657
Name Industry_Sector: 'אפשרויות בחירה'!$C$1129:$C$1245
Name Industry_sector_all: 'אפשרויות בחירה'!$C$202:$C$327
Name Industry_sectors: 'אפשרויות בחירה'!$C$202:$C$327
Name israel_abroad: 'אפשרויות בחירה'!$C$2:$C$3
Name Issuer_Number_Banks: 'אפשרויות בחירה'!$C$111:$C$113
Name Issuer_Number_Fund: 'אפשרויות בחירה'!$C$114:$C$117
Name issuer_number_loan: 'אפשרויות בחירה'!$C$118:$C$126
Name Issuer_Number_Type: 'אפשרויות בחירה'!$C$104:$C$110
Name Issuer_Number_Type_2: 'אפשרויות בחירה'!$C$1076:$C$1079
Name Issuer_Number_Type_3: 'אפשרויות בחירה'!$C$1081:$C$1085
Name Issuer_Number_Type_V2: 'אפשרויות בחירה'!$C$104:$C$110
Name Issuer_Type_TFunds: 'אפשרויות בחירה'!$C$1087:$C$1089
Name Leading_factor: 'אפשרויות בחירה'!$C$692:$C$700
Name Linked_Type: 'אפשרויות בחירה'!$C$516:$C$519
Name other_investments: 'אפשרויות בחירה'!$C$1000:$C$1033
Name Penalty: 'אפשרויות בחירה'!$C$851:$C$852
Name QTR: 'File Name Info'!$A$15:$A$19
Name Rating_Agency: 'אפשרויות בחירה'!$C$188:$C$201
Name real_estate_lifestage: 'אפשרויות בחירה'!$C$634:$C$642
Name real_estate_loans: 'אפשרויות בחירה'!$C$553:$C$591
Name Real_Estate_Main_Use: 'אפשרויות בחירה'!$C$622:$C$633
Name Recourse_Nonrecourse: 'אפשרויות בחירה'!$C$544:$C$545
Name Repayment_Rights: 'אפשרויות בחירה'!$C$551:$C$552
Name Reset_frequency: 'אפשרויות בחירה'!$C$658:$C$665
Name Security_ID_Number_Type: 'אפשרויות בחירה'!$C$1113:$C$1116
Name Security_Number_Loans: 'אפשרויות בחירה'!$C$131
Name Stock_Exchange: 'אפשרויות בחירה'!$C$1283:$C$1315
Name Stock_Exchange_Gov_Bonds: 'אפשרויות בחירה'!$C$148:$C$181
Name Subordination_Risk: 'אפשרויות בחירה'!$C$186:$C$187
Name Tradeable_Status: 'אפשרויות בחירה'!$C$1272:$C$1281
Name Tradeable_Status_All: 'אפשרויות בחירה'!$C$135:$C$145
Name tradeable_status_bonds: 'אפשרויות בחירה'!$C$1248:$C$1253
Name tradeable_status_funds: 'אפשרויות בחירה'!$C$1118:$C$1119
Name tradeable_status_stock: 'אפשרויות בחירה'!$C$1255:$C$1259
Name Tradeable_Status_v2: 'אפשרויות בחירה'!$C$1121:$C$1126
Name tradeable_status_warrants: 'אפשרויות בחירה'!$C$1261:$C$1265
Name tradeable_status_warrants_v2: 'אפשרויות בחירה'!$C$1267:$C$1269
Name Transaction: 'אפשרויות בחירה'!$C$643:$C$646
Name Type: 'File Name Info'!$A$2:$A$8

Sheet עמוד פתיחה
A1: קובץ דיווח עבור רשימת נכסים ברמת הנכס הבודד (חוזר גופים מוסדיים 2015-9-14)
A3: יש לבחור תחום: | D3: נכסי עמיתים - קופות גמל
A5: האם מדובר בקובץ לממומנה או לציבור: | D5: לציבור
A7: יש לבחור את רבעון הדיווח: | D7: 01
A9: יש לבחור את שנת הדיווח: | D9: 2025
A11: יש לבחור את הגוף המוסדי: | D11: החברה לניהול קרן ההשתלמות לעובדי המדינה בע"מ
A13: ח.פ. הגוף המוסדי: | D13: =IFERROR(VLOOKUP(D11,'File Name Info'!A35:B121,2,0),"תא מחושב") -> 520032269
A15: שם קובץ לשמירה | D15: =IF(D5="לממונה",CONCATENATE(D13, "_",VLOOKUP(D3,Full_Type,2,0),"_",D7,VLOOKUP(D9,Full_Year,2,0),".xlxs"),IF(D5="לציבור",CONCATENATE(D13,"_",VLOOKUP(D3,Full_Type_Nostro,2,0),"_",VLOOKUP(D5,Full_File_Type,2,0),"_",D7,VLOOKUP(D9,Full_Year,2,0),".xlsx"),"שם קובץ לשמירה")) -> 520032269_gm_p_0125.xlsx
A17: פרטי האחראי על הדיווח בגוף המוסדי | B17: שם: | D17: שירן נזרי
B19: מספר טלפון: | D19: 546481151
B21: כתובת מייל: | D21: shiran@ovdeimedina.co.il
A23: הוראות למילוי הדיווח: | D23: יש לדווח לפי ההנחיות בחלק ג' לנספח 5.4.3.2 שבפרק 3 שבחלק 4 לשער 5 בחוזר המאוחד - "רשימת נכסים ברמת הנכס הבודד".

Sheet סכום נכסים
C1: ידווח בקבצי נכסי הנוסטרו בלבד
B2: שווי הוגן | C2: עלות מופחתת | D2: השיטה שיושמה בדוח הכספי
A3: מזומנים ושווי מזומנים | B3: =SUM('מזומנים ושווי מזומנים'!O:O) -> 45832.806 | D3: =B3+C3 -> 45832.806
A4: איגרות חוב ממשלתיות | B4: =SUM('איגרות חוב ממשלתיות'!U:U) -> 676525.5 | D4: =B4+C4 -> 676525.5
A5: ניירות ערך מסחריים | B5: =SUM('ניירות ערך מסחריים'!AD:AD) -> 0 | D5: =B5+C5 -> 0
A6: איגרות חוב | B6: =SUM('איגרות חוב'!AD:AD) -> 303113.12 | D6: =B6+C6 -> 303113.12
A7: מניות, מניות בכורה ויחידות השתתפות | B7: =SUM('מניות מבכ ויהש'!U:U) -> 420287.74 | D7: =B7+C7 -> 420287.74
A8: קרנות סל | B8: =SUM('קרנות סל'!T:T) -> 913154.63 | D8: =B8+C8 -> 913154.63
A9: קרנות נאמנות | B9: =SUM('קרנות נאמנות'!T:T) -> 106995.01 | D9: =B9+C9 -> 106995.01
A10: כתבי אופציה | B10: =SUM('כתבי אופציה'!W:W) -> 237.854 | D10: =B10+C10 -> 237.854
A11: אופציות | B11: =SUM(אופציות!V:V) -> -17.92 | D11: =B11+C11 -> -17.92
A12: חוזים עתידיים | B12: =SUM('חוזים עתידיים'!R:R) -> -1077.421 | D12: =B12+C12 -> -1077.421
A13: מוצרים מובנים | B13: =SUM('מוצרים מובנים'!Z:Z) -> 0 | D13: =B13+C13 -> 0
A14: לא סחיר איגרות חוב ממשלתיות | B14: =SUM('לא סחיר איגרות חוב ממשלתיות'!U:U) -> 0 | D14: =B14+C14 -> 0
A15: לא סחיר איגרות חוב מיועדות | B15: =SUM('לא סחיר איגרות חוב מיועדות'!N:N) -> 0 | D15: =B15+C15 -> 0
A16: אפיק השקעה מובטח תשואה | B16: =SUM('אפיק השקעה מובטח תשואה'!F:F) -> 0 | D16: =B16+C16 -> 0
A17: לא סחיר ניירות ערך מסחריים | B17: =SUM('לא סחיר ניירות ערך מסחריים'!AI:AI) -> 0 | D17: =B17+C17 -> 0
A18: לא סחיר איגרות חוב | B18: =SUM('לא סחיר איגרות חוב'!AG:AG) -> 18589.276 | D18: =B18+C18 -> 18589.276
A19: לא סחיר מניות, מניות בכורה ויחידות השתתפות | B19: =SUM('לא סחיר מניות מבכ ויהש'!X:X) -> 2852.566 | D19: =B19+C19 -> 2852.566
A20: קרנות השקעה | B20: =SUM('קרנות השקעה'!W:W) -> 465760.12 | D20: =B20+C20 -> 465760.12
A21: לא סחיר כתבי אופציה | B21: =SUM('לא סחיר כתבי אופציה'!Z:Z) -> 0.408 | D21: =B21+C21 -> 0.408
A22: לא סחיר אופציות | B22: =SUM('לא סחיר אופציות'!Z:Z) -> 0 | D22: =B22+C22 -> 0
A23: לא סחיר נגזרים אחרים | B23: =SUM('לא סחיר נגזרים אחרים'!R:R) -> -9048.5812 | D23: =B23+C23 -> -9048.5812
A24: הלוואות | B24: =SUM(הלוואות!AT:AT) -> 88847.242 | D24: =B24+C24 -> 88847.242
A25: לא סחיר מוצרים מובנים | B25: =SUM('לא סחיר מוצרים מובנים'!AB:AB) -> 0 | D25: =B25+C25 -> 0
A26: פיקדונות מעל 3 חודשים | B26: =SUM('פיקדונות מעל 3 חודשים'!T:T) -> 0 | D26: =B26+C26 -> 0
A27: זכויות מקרקעין | B27: =SUM('זכויות מקרקעין'!S:S) -> 0 | D27: =B27+C27 -> 0
A28: השקעה בחברות מוחזקות | B28: =SUM('השקעה בחברות מוחזקות'!U:U) -> 0 | D28: =B28+C28 -> 0
A29: נכסים אחרים | B29: =SUM('נכסים אחרים'!N:N) -> -1028.181 | D29: =B29+C29 -> -1028.181
A30: סך הכל נכסים | B30: =IF(SUM(B3:B29)=0,0.0001,SUM(B3:B29)) -> 3031024.2 | C30: =SUM(C3:C29) -> 0 | D30: =SUM(D3:D29) -> 3031024.2
A31: מסגרות אשראי
A32: יתרות התחייבויות להשקעה | B32: =SUM('יתרות התחייבות להשקעה'!O:O) -> 122295.42

Sheet מזומנים ושווי מזומנים
A1: מספר קופה/קרן/ח.פ. עבור חברת ביטוח | B1: מספר מסלול | C1: שם הבנק | D1: מספר מזהה בנק | E1: סוג מספר מזהה בנק | F1: מאפיין עיקרי | G1: ישראל/חו"ל | H1: בעל עניין/צד קשור | I1: דירוג הבנק | J1: שם מדרג | K1: מטבע פעילות | L1: שווי מטבעי | M1: שער חליפין | N1: שיעור ריבית | O1: שווי הוגן (באלפי ש"ח) | P1: שיעור מנכסי אפיק ההשקעה | Q1: שיעור מסך נכסי ההשקעה
A2: 382 | B2: 382 | C2: בנק לאומי לישראל בע"מ | D2: 10-800 | E2: סימול בנק | F2: מזומן ועו"ש נקוב במט"ח | G2: ישראל | H2: לא | I2: AAA | J2: S&P מעלות | K2: USD | L2: 0.002 | M2: 3.718 | N2: 0 | O2: 0.008 | P2: 2.0234624e-07 | Q2: 2.8420165e-09
A3: 382 | B3: 382 | C3: בנק לאומי לישראל בע"מ | D3: 10-800 | E3: סימול בנק | F3: מזומן ועו"ש בש"ח | G3: ישראל | H3: לא | I3: AAA | J3: S&P מעלות | K3: ILS | L3: 0.002 | M3: 1 | N3: 0 | O3: 0.002 | P3: 4.2356682e-08 | Q3: 5.949129e-10
A4: 382 | B4: 382 | C4: בנק לאומי לישראל בע"מ | D4: 10-800 | E4: סימול בנק | F4: מזומן ועו"ש בש"ח | G4: ישראל | H4: לא | I4: AAA | J4: S&P מעלות | K4: ILS | L4: 0 | M4: 1 | N4: 0.038 | O4: 0 | P4: -5.9102346e-09 | Q4: -8.3011103e-11
A5: 382 | B5: 382 | C5: בנק לאומי לישראל בע"מ | D5: 10-800 | E5: סימול בנק | F5: מזומן ועו"ש נקוב במט"ח | G5: ישראל | H5: לא | I5: AAA | J5: S&P מעלות | K5: USD | L5: 911.862 | M5: 3.718 | N5: 0 | O5: 3390.304 | P5: 0.083489546 | Q5: 0.0011726369
A6: 382 | B6: 382 | C6: בנק לאומי לישראל בע"מ | D6: 10-800 | E6: סימול בנק | F6: מזומן ועו"ש נקוב במט"ח | G6: ישראל | H6: לא | I6: AAA | J6: S&P מעלות | K6: EUR | L6: 6.192 | M6: 4.0219 | N6: 0 | O6: 24.905 | P6: 0.00061329938 | Q6: 8.6139826e-06
A7: 382 | B7: 382 | C7: בנק לאומי לישראל בע"מ | D7: 10-800 | E7: סימול בנק | F7: מזומן ועו"ש נקוב במט"ח | G7: ישראל | H7: לא | I7: AAA | J7: S&P מעלות | K7: JPY | L7: -1.473 | M7: 0.024893 | N7: 0 | O7: -0.037 | P7: -9.0322164e-07 | Q7: -1.2686032e-08
A8: 382 | B8: 382 | C8: בנק לאומי לישראל בע"מ | D8: 10-800 | E8: סימול בנק | F8: מזומן ועו"ש נקוב במט"ח | G8: ישראל | H8: לא | I8: AAA | J8: S&P מעלות | K8: GBP | L8: 0.966 | M8: 4.8108 | N8: 0 | O8: 4.649 | P8: 0.00011448649 | Q8: 1.6079987e-06
A9: 382 | B9: 382 | C9: בנק לאומי לישראל בע"מ | D9: 10-800 | E9: סימול בנק | F9: מזומן ועו"ש בש"ח | G9: ישראל | H9: לא | I9: AAA | J9: S&P מעלות | K9: ILS | L9: 37187.695 | M9: 1 | N9: 0.038 | O9: 37187.695 | P9: 0.91578333 | Q9: 0.012862465
A10: 382 | B10: 382 | C10: בנק לאומי לישראל בע"מ | D10: 10-800 | E10: סימול בנק | F10: מזומן ועו"ש בש"ח | G10: ישראל | H10: לא | I10: AAA | J10: S&P מעלות | K10: ILS | L10: 0 | M10: 1 | N10: 0 | O10: 0 | P10: 2.4625978e-10 | Q10: 3.458796e-12
A11: 382 | B11: 1404 | C11: בנק לאומי לישראל בע"מ | D11: 10-800 | E11: סימול בנק | F11: מזומן ועו"ש בש"ח | G11: ישראל | H11: לא | I11: AAA | J11: S&P מעלות | K11: ILS | L11: 0 | M11: 1 | N11: 0.038 | O11: 0 | P11: -1.9013104e-07 | Q11: -3.7403184e-09
A12: 382 | B12: 1404 | C12: בנק לאומי לישראל בע"מ | D12: 10-800 | E12: סימול בנק | F12: מזומן ועו"ש נקוב במט"ח | G12: ישראל | H12: לא | I12: AAA | J12: S&P מעלות | K12: USD | L12: 8.39 | M12: 3.718 | N12: 0 | O12: 31.196 | P12: 0.059312907 | Q12: 0.0011668224
A13: 382 | B13: 1404 | C13: בנק לאומי לישראל בע"מ | D13: 10-800 | E13: סימול בנק | F13: מזומן ועו"ש בש"ח | G13: ישראל | H13: לא | I13: AAA | J13: S&P מעלות | K13: ILS | L13: 494.757 | M13: 1 | N13: 0.038 | O13: 494.757 | P13: 0.94068728 | Q13: 0.0185055
... A29: 382 | B29: 15404 | C29: בנק לאומי לישראל בע"מ | D29: 10-800 | E29: סימול בנק | F29: מזומן ועו"ש בש"ח | G29: ישראל | H29: לא | I29: AAA | J29: S&P מעלות | K29: ILS | L29: 0 | M29: 1 | N29: 0 | O29: 0 | P29: 1.8566589e-07 | Q29: 2.999459e-09

Sheet איגרות חוב ממשלתיות
A1: מספר קופה/קרן/ח.פ. עבור חברת ביטוח | B1: מספר מסלול | C1: שם מנפיק | D1: שם נייר ערך | E1: מספר נייר ערך | F1: מאפיין עיקרי | G1: ישראל/חו"ל | H1: מדינה לפי חשיפה כלכלית | I1: זירת מסחר | J1: דירוג | K1: שם מדרג | L1: מטבע פעילות | M1: מח"מ | N1: מועד פדיון | O1: שיעור ריבית | P1: תשואה לפדיון | Q1: סכום לקבל (במטבע הפעילות) | R1: ערך נקוב (יחידות) | S1: שער חליפין | T1: שער נייר הערך | U1: שווי הוגן (באלפי ש"ח) | V1: עלות מופחתת (באלפי ש"ח) | W1: השיטה שיושמה בדוח הכספי | X1: שיעור מערך נקוב מונפק | Y1: שיעור מנכסי אפיק ההשקעה | Z1: שיעור מסך נכסי ההשקעה
A2: 382 | B2: 382 | C2: בנק ישראל- מק"מ | D2: מ.ק.מ. 915 | E2: IL0082509121 | F2: מק"מ קצר משנים עשר חודשים | G2: ישראל | H2: ישראל | I2: TASE | J2: RF | K2: פנימי | L2: ILS | M2: 0.425 | N2: 03/09/2025 | O2: 0 | P2: 0.0427 | R2: 31000000 | S2: 1 | T2: 98.24 | U2: 30454.4 | W2: שווי הוגן | X2: 0.002583 | Y2: 0.048577417 | Z2: 0.010533556
A3: 382 | B3: 382 | C3: בנק ישראל- מק"מ | D3: מלווה קצר מועד 1015 | E3: IL0082510194 | F3: מק"מ קצר משנים עשר חודשים | G3: ישראל | H3: ישראל | I3: TASE | J3: RF | K3: פנימי | L3: ILS | M3: 0.507 | N3: 01/10/2025 | O3: 0 | P3: 0.04276 | R3: 6800000 | S3: 1 | T3: 97.9 | U3: 6657.2 | W3: שווי הוגן | X3: 0.000486 | Y3: 0.010618813 | Z3: 0.0023025896
A4: 382 | B4: 382 | C4: בנק ישראל- מק"מ | D4: מלווה קצר מועד 515 | E4: IL0082505160 | F4: מק"מ קצר משנים עשר חודשים | G4: ישראל | H4: ישראל | I4: TASE | J4: RF | K4: פנימי | L4: ILS | M4: 0.099 | N4: 07/05/2025 | O4: 0 | P4: 0.04254 | R4: 84500000 | S4: 1 | T4: 99.59 | U4: 84153.55 | W4: שווי הוגן | X4: 0.002284 | Y4: 0.13423223 | Z4: 0.029106996
A5: 382 | B5: 382 | C5: גליל | D5: ממשל צמודה 0527 | E5: IL0011408478 | F5: צמוד למדד המחירים לצרכן בריבית קבועה | G5: ישראל | H5: ישראל | I5: TASE | J5: RF | K5: פנימי | L5: ILS | M5: 2.142 | N5: 31/05/2027 | O5: 0.0075 | P5: 0.01945 | R5: 46800000 | S5: 1 | T5: 114.63 | U5: 53646.84 | W5: שווי הוגן | X5: 0.001921 | Y5: 0.085571377 | Z5: 0.018555347
A6: 382 | B6: 382 | C6: גליל | D6: ממשל צמודה 1131 | E6: IL0011722209 | F6: צמוד למדד המחירים לצרכן בריבית קבועה | G6: ישראל | H6: ישראל | I6: TASE | J6: RF | K6: פנימי | L6: ILS | M6: 6.646 | N6: 30/11/2031 | O6: 0.001 | P6: 0.02031 | R6: 35675000 | S6: 1 | T6: 101.91 | U6: 36356.393 | W6: שווי הוגן | X6: 0.001162 | Y6: 0.057991609 | Z6: 0.012574934
A7: 382 | B7: 382 | C7: שחר | D7: ממשל שיקלית 0928 | E7: IL0011508798 | F7: לא צמוד למדד המחירים לצרכן ריבית קבועה | G7: ישראל | H7: ישראל | I7: TASE | J7: RF | K7: פנימי | L7: ILS | M7: 3.36 | N7: 28/09/2028 | O7: 0.0225 | P7: 0.04261 | R7: 7510000 | S7: 1 | T7: 94.71 | U7: 7112.721 | W7: שווי הוגן | X7: 0.000216 | Y7: 0.011345409 | Z7: 0.0024601451
A8: 382 | B8: 382 | C8: שחר | D8: ממשל שקלית 0226 | E8: IL0011746976 | F8: לא צמוד למדד המחירים לצרכן ריבית קבועה | G8: ישראל | H8: ישראל | I8: TASE | J8: RF | K8: פנימי | L8: ILS | M8: 0.91 | N8: 27/02/2026 | O8: 0.005 | P8: 0.04161 | R8: 15550000 | S8: 1 | T8: 96.84 | U8: 15058.62 | W8: שווי הוגן | X8: 0.00056 | Y8: 0.024019809 | Z8: 0.0052084694
A9: 382 | B9: 382 | C9: שחר | D9: ממשל שקלית 0335 | E9: IL0012023326 | F9: לא צמוד למדד המחירים לצרכן ריבית קבועה | G9: ישראל | H9: ישראל | I9: TASE | J9: RF | K9: פנימי | L9: ILS | M9: 8.398 | N9: 30/03/2035 | O9: 0.04 | P9: 0.04485 | R9: 34622000 | S9: 1 | T9: 96.17 | U9: 33295.977 | W9: שווי הוגן | X9: 0.00117 | Y9: 0.053109981 | Z9: 0.011516399
A10: 382 | B10: 382 | C10: שחר | D10: ממשל שקלית 0347 | E10: IL0011401937 | F10: לא צמוד למדד המחירים לצרכן ריבית קבועה | G10: ישראל | H10: ישראל | I10: TASE | J10: RF | K10: פנימי | L10: ILS | M10: 14.74 | N10: 31/03/2047 | O10: 0.0375 | P10: 0.0486 | R10: 19320000 | S10: 1 | T10: 85.21 | U10: 16462.572 | W10: שווי הוגן | X10: 0.000736 | Y10: 0.026259235 | Z10: 0.0056940677
A11: 382 | B11: 382 | C11: שחר | D11: ממשלתי שקלית 0142 | E11: IL0011254005 | F11: לא צמוד למדד המחירים לצרכן ריבית קבועה | G11: ישראל | H11: ישראל | I11: TASE | J11: RF | K11: פנימי | L11: ILS | M11: 11.552 | N11: 31/01/2042 | O11: 0.055 | P11: 0.0473 | R11: 18600000 | S11: 1 | T11: 109.69 | U11: 20402.34 | W11: שווי הוגן | X11: 0.000685 | Y11: 0.032543507 | Z11: 0.0070567531
A12: 382 | B12: 382 | C12: גליל | D12: ממשלתית צמודה 0.5% 0529 | E12: IL0011570236 | F12: צמוד למדד המחירים לצרכן בריבית קבועה | G12: ישראל | H12: ישראל | I12: TASE | J12: RF | K12: פנימי | L12: ILS | M12: 4.115 | N12: 31/05/2029 | O12: 0.005 | P12: 0.01969 | R12: 54149000 | S12: 1 | T12: 109.42 | U12: 59249.836 | W12: שווי הוגן | X12: 0.00197 | Y12: 0.094508643 | Z12: 0.020493309
A13: 382 | B13: 382 | C13: גליל | D13: ממשלתית צמודה 0726 | E13: IL0011695645 | F13: צמוד למדד המחירים לצרכן בריבית קבועה | G13: ישראל | H13: ישראל | I13: TASE | J13: RF | K13: פנימי | L13: ILS | M13: 1.331 | N13: 31/07/2026 | O13: 0.001 | P13: 0.0196 | R13: 24007000 | S13: 1 | T13: 112.95 | U13: 27115.907 | W13: שווי הוגן | X13: 0.001188 | Y13: 0.04325223 | Z13: 0.0093788388
... A75: 382 | B75: 11414 | C75: בנק ישראל- מק"מ | D75: מקמ 815 | E75: IL0082508131 | F75: מק"מ קצר משנים עשר חודשים | G75: ישראל | H75: ישראל | I75: TASE | J75: RF | K75: פנימי | L75: ILS | M75: 0.348 | N75: 06/08/2025 | O75: 0 | P75: 0.04287 | R75: 780000 | S75: 1 | T75: 98.55 | U75: 768.69 | W75: שווי הוגן | X75: 6.5e-05 | Y75: 0.073786892 | Z75: 0.049884504

Sheet ניירות ערך מסחריים
A1: מספר קופה/קרן/ח.פ. עבור חברת ביטוח | B1: מספר מסלול | C1: שם מנפיק | D1: מספר מנפיק | E1: סוג מספר מזהה מנפיק | F1: שם נייר ערך | G1: מספר נייר ערך | H1: סוג מספר נייר ערך | I1: מאפיין עיקרי | J1: ישראל/חו"ל | K1: מדינה לפי חשיפה כלכלית | L1: זירת מסחר | M1: ענף מסחר | N1: בעל עניין/צד קשור | O1: דירוג | P1: שם מדרג | Q1: דירוג נייר הערך/המנפיק | R1: מטבע פעילות | S1: מח"מ | T1: ריבית עוגן | U1: מועד פדיון | V1: שיעור ריבית | W1: תשואה לפדיון | X1: נחיתות חוזית | Y1: האם סווג כחוב בעייתי | Z1: ערך נקוב (יחידות) | AA1: שער חליפין | AB1: שער נייר הערך | AC1: סכום לקבל (במטבע הפעילות) | AD1: שווי הוגן (באלפי ש"ח) | AE1: עלות מופחתת (באלפי ש"ח) | AF1: עלות מופחתת (במטבע הפעילות) | AG1: השיטה שיושמה בדוח הכספי | AH1: שיעור מערך נקוב מונפק | AI1: שיעור מנכסי אפיק ההשקעה | AJ1: שיעור מסך נכסי ההשקעה

Sheet איגרות חוב
A1: מספר קופה/קרן/ח.פ. עבור חברת ביטוח | B1: מספר מסלול | C1: שם מנפיק | D1: מספר מנפיק | E1: סוג מספר מזהה מנפיק | F1: שם נייר ערך | G1: מספר נייר ערך | H1: סוג מספר נייר ערך | I1: מאפיין עיקרי | J1: ישראל/חו"ל | K1: מדינה לפי חשיפה כלכלית | L1: סטאטוס סחירות | M1: זירת מסחר | N1: ענף מסחר | O1: בעל עניין/צד קשור | P1: דירוג | Q1: שם מדרג | R1: דירוג נייר הערך/המנפיק | S1: מטבע פעילות | T1: מח"מ | U1: מועד פדיון | V1: שיעור ריבית | W1: תשואה לפדיון | X1: נחיתות חוזית | Y1: האם סווג כחוב בעייתי | Z1: ערך נקוב (יחידות) | AA1: שער חליפין | AB1: שער נייר הערך | AC1: סכום לקבל (במטבע הפעילות) | AD1: שווי הוגן (באלפי ש"ח) | AE1: עלות מופחתת (באלפי ש"ח) | AF1: עלות מופחתת (במטבע הפעילות) | AG1: השיטה שיושמה בדוח הכספי | AH1: שיעור מערך נקוב מונפק | AI1: שיעור מנכסי אפיק ההשקעה | AJ1: שיעור מסך נכסי ההשקעה
A2: 382 | B2: 382 | C2: איירפורט סיטי בע"מ | D2: 511659401 | E2: ח.פ | F2: איירפורט אגח ה | G2: IL0011334872 | H2: ISIN | I2: צמוד למדד המחירים לצרכן | J2: ישראל | K2: ישראל | L2: סחיר | M2: TASE | N2: נדל"ן מניב בישראל | O2: לא | P2: AA | Q2: S&P מעלות | R2: נייר ערך | S2: ILS | T2: 2.267 | U2: 28/02/2029 | V2: 0.0234 | W2: 0.02797 | X2: החוב לא נחות | Y2: לא | Z2: 4080000.3 | AA2: 1 | AB2: 114.39 | AD2: 4667.112 | AG2: שווי הוגן | AH2: 0.002503 | AI2: 0.015874363 | AJ2: 0.0016142589
A3: 382 | B3: 382 | C3: אלוני-חץ נכסים והשקעות בע"מ | D3: 520038506 | E3: ח.פ | F3: אלוני חץ אגח טו | G3: IL0011894149 | H3: ISIN | I3: צמוד למדד המחירים לצרכן | J3: ישראל | K3: ישראל | L3: סחיר | M3: TASE | N3: נדל"ן מניב בישראל | O3: לא | P3: AA- | Q3: S&P מעלות | R3: נייר ערך | S3: ILS | T3: 6.663 | U3: 01/03/2037 | V3: 0.0256 | W3: 0.03503 | X3: החוב לא נחות | Y3: לא | Z3: 2700000 | AA3: 1 | AB3: 101.59 | AD3: 2742.93 | AG3: שווי הוגן | AH3: 0.00257 | AI3: 0.0093295944 | AJ3: 0.00094872352
A4: 382 | B4: 382 | C4: אלוני-חץ נכסים והשקעות בע"מ | D4: 520038506 | E4: ח.פ | F4: אלוני חץ אגח יב | G4: IL0039004952 | H4: ISIN | I4: לא צמוד למדד המחירים לצרכן | J4: ישראל | K4: ישראל | L4: סחיר | M4: TASE | N4: נדל"ן מניב בישראל | O4: לא | P4: AA- | Q4: S&P מעלות | R4: נייר ערך | S4: ILS | T4: 3.951 | U4: 28/02/2031 | V4: 0.0241 | W4: 0.05291 | X4: החוב לא נחות | Y4: לא | Z4: 3685500 | AA4: 1 | AB4: 89.75 | AD4: 3307.736 | AG4: שווי הוגן | AH4: 0.001793 | AI4: 0.011250684 | AJ4: 0.0011440785
A5: 382 | B5: 382 | C5: אלקטרה בע"מ | D5: 520028911 | E5: ח.פ | F5: אלקטרה אגח ד | G5: IL0073901493 | H5: ISIN | I5: לא צמוד למדד המחירים לצרכן | J5: ישראל | K5: ישראל | L5: סחיר | M5: TASE | N5: השקעה ואחזקות | O5: לא | P5: A+ | Q5: S&P מעלות | R5: נייר ערך | S5: ILS | T5: 0.729 | U5: 30/06/2026 | V5: 0.04 | W5: 0.05407 | X5: החוב לא נחות | Y5: לא | Z5: 1166669.5 | AA5: 1 | AB5: 100.05 | AD5: 1167.253 | AG5: שווי הוגן | AH5: 0.008855 | AI5: 0.0039702053 | AJ5: 0.00040372893
A6: 382 | B6: 382 | C6: אלקטרה בע"מ | D6: 520028911 | E6: ח.פ | F6: אלקטרה אגח ה | G6: IL0073902228 | H6: ISIN | I6: לא צמוד למדד המחירים לצרכן | J6: ישראל | K6: ישראל | L6: סחיר | M6: TASE | N6: השקעה ואחזקות | O6: לא | P6: A+ | Q6: S&P מעלות | R6: נייר ערך | S6: ILS | T6: 2.996 | U6: 10/01/2031 | V6: 0.04 | W6: 0.0524 | X6: החוב לא נחות | Y6: לא | Z6: 1950000.6 | AA6: 1 | AB6: 97.45 | AD6: 1900.276 | AG6: שווי הוגן | AH6: 0.003358 | AI6: 0.0064634533 | AJ6: 0.00065726653
A7: 382 | B7: 382 | C7: אמות השקעות בע"מ | D7: 520026683 | E7: ח.פ | F7: אמות אגח ד | G7: IL0011331498 | H7: ISIN | I7: צמוד למדד המחירים לצרכן | J7: ישראל | K7: ישראל | L7: סחיר | M7: TASE | N7: נדל"ן מניב בישראל | O7: לא | P7: AA | Q7: S&P מעלות | R7: נייר ערך | S7: ILS | T7: 1.682 | U7: 02/07/2028 | V7: 0.032 | W7: 0.02754 | X7: החוב לא נחות | Y7: לא | Z7: 3120000 | AA7: 1 | AB7: 118.93 | AD7: 3710.616 | AG7: שווי הוגן | AH7: 0.005651 | AI7: 0.012621008 | AJ7: 0.0012834264
A8: 382 | B8: 382 | C8: אנלייט אנרגיה מתחדשת בע"מ | D8: 520041146 | E8: ח.פ | F8: אנלייט אנר אגח ו | G8: IL0072001733 | H8: ISIN | I8: לא צמוד למדד המחירים לצרכן | J8: ישראל | K8: ארה"ב | L8: סחיר | M8: TASE | N8: אנרגיה מתחדשת | O8: לא | P8: A2 | Q8: מידרוג Moodys | R8: נייר ערך | S8: ILS | T8: 1.261 | U8: 01/09/2026 | V8: 0.0345 | W8: 0.05499 | X8: החוב לא נחות | Y8: לא | Z8: 2608695.5 | AA8: 1 | AB8: 97.86 | AD8: 2552.869 | AG8: שווי הוגן | AH8: 0.004059 | AI8: 0.0086831366 | AJ8: 0.00088298543
A9: 382 | B9: 382 | C9: בתי זקוק לנפט בע"מ | D9: 520036658 | E9: ח.פ | F9: בזן אגח ט | G9: IL0025904611 | H9: ISIN | I9: צמוד למט"ח | J9: ישראל | K9: ישראל | L9: סחיר | M9: TASE | N9: אנרגיה | O9: לא | P9: A+ | Q9: S&P מעלות | R9: נייר ערך | S9: ILS | T9: 0.499 | U9: 30/09/2025 | V9: 0.047 | W9: 0.07732 | X9: החוב לא נחות | Y9: לא | Z9: 563616.51 | AA9: 1 | AB9: 100.8 | AD9: 568.125 | AG9: שווי הוגן | AH9: 0.002298 | AI9: 0.0019323789 | AJ9: 0.000196503
A10: 382 | B10: 382 | C10: ביג מרכזי קניות (2004) בע"מ | D10: 513623314 | E10: ח.פ | F10: ביג אגח ז | G10: IL0011360844 | H10: ISIN | I10: צמוד למדד המחירים לצרכן | J10: ישראל | K10: ישראל | L10: סחיר | M10: TASE | N10: נדל"ן מניב בישראל | O10: לא | P10: AA- | Q10: S&P מעלות | R10: נייר ערך | S10: ILS | T10: 0.11 | U10: 11/05/2025 | V10: 0.025 | W10: 0.03762 | X10: החוב לא נחות | Y10: לא | Z10: 1500379.7 | AA10: 1 | AB10: 116.75 | AD10: 1751.693 | AG10: שווי הוגן | AH10: 0.006371 | AI10: 0.0059580771 | AJ10: 0.00060587499
A11: 382 | B11: 382 | C11: ביג מרכזי קניות (2004) בע"מ | D11: 513623314 | E11: ח.פ | F11: ביג אגח כ | G11: IL0011861882 | H11: ISIN | I11: צמוד למדד המחירים לצרכן | J11: ישראל | K11: ישראל | L11: סחיר | M11: TASE | N11: נדל"ן מניב בישראל | O11: לא | P11: AA- | Q11: S&P מעלות | R11: נייר ערך | S11: ILS | T11: 4.878 | U11: 01/05/2033 | V11: 0.0187 | W11: 0.03163 | X11: החוב לא נחות | Y11: לא | Z11: 6786300 | AA11: 1 | AB11: 105.08 | AD11: 7131.044 | AG11: שווי הוגן | AH11: 0.006631 | AI11: 0.024254993 | AJ11: 0.0024664826
A12: 382 | B12: 382 | C12: הבינלאומי הראשון הנפקות בע"מ | D12: 513141879 | E12: ח.פ | F12: בינל הנפק אגח י | G12: IL0011602906 | H12: ISIN | I12: צמוד למדד המחירים לצרכן | J12: ישראל | K12: ישראל | L12: סחיר | M12: TASE | N12: בנקים | O12: לא | P12: AAA | Q12: S&P מעלות | R12: נייר ערך | S12: ILS | T12: 0.444 | U12: 10/09/2025 | V12: 0.001 | W12: 0.0226 | X12: החוב לא נחות | Y12: לא | Z12: 2000000 | AA12: 1 | AB12: 113.85 | AD12: 2277 | AG12: שווי הוגן | AH12: 0.001333 | AI12: 0.0077448154 | AJ12: 0.00078756784
A13: 382 | B13: 382 | C13: פז בית זיקוק לנפט-אשדוד בע"מ | D13: 513775163 | E13: ח.פ | F13: בית זיקוק אשדוד אגח 2 | G13: IL0011994881 | H13: ISIN | I13: לא צמוד למדד המחירים לצרכן | J13: ישראל | K13: ישראל | L13: סחיר | M13: TASE | N13: אנרגיה | O13: לא | P13: A3 | Q13: מידרוג Moodys | R13: נייר ערך | S13: ILS | T13: 2.621 | U13: 30/04/2029 | V13: 0.0725 | W13: 0.05692 | X13: החוב לא נחות | Y13: לא | Z13: 2150052.3 | AA13: 1 | AB13: 107.37 | AD13: 2308.511 | AG13: שווי הוגן | AH13: 0.002986 | AI13: 0.007851995 | AJ13: 0.0007984669
... A22: 382 | B22: 382 | C22: וילאר אינטרנשיונל בע"מ | D22: 520038910 | E22: ח.פ | F22: וילאר אינטרנ' ח' | G22: IL0041601563 | H22: ISIN | I22: לא צמוד למדד המחירים לצרכן | J22: ישראל | K22: ישראל | L22: סחיר | M22: TASE | N22: נדל"ן מניב בישראל | O22: לא | P22: AA | Q22: S&P מעלות | R22: נייר ערך | S22: ILS | T22: 0.238 | U22: 27/06/2025 | V22: 0.0255 | W22: 0.03017 | X22: החוב לא נחות | Y22: לא | Z22: 1399999.9 | AA22: 1 | AB22: 100.56 | AD22: 1407.84 | AG22: שווי הוגן | AH22: 0.020862 | AI22: 0.0047885201 | AJ22: 0.00048694311
A23: 382 | B23: 382 | C23: חברת החשמל לישראל בע"מ | D23: 520000472 | E23: ח.פ | F23: חשמל אגח 27 | G23: IL0060002107 | H23: ISIN | I23: צמוד למדד המחירים לצרכן | J23: ישראל | K23: ישראל | L23: סחיר | M23: TASE | N23: אנרגיה | O23: לא | P23: AAA | Q23: S&P מעלות | R23: נייר ערך | S23: ILS | T23: 3.022 | U23: 12/04/2029 | V23: 0.0385 | W23: 0.02566 | X23: החוב לא נחות | Y23: לא | Z23: 3719173 | AA23: 1 | AB23: 120.79 | AC23: 131.631 | AD23: 4624.02 | AG23: שווי הוגן | AH23: 0.001456 | AI23: 0.015727793 | AJ23: 0.0015993543
A24: 382 | B24: 382 | C24: חברת החשמל לישראל בע"מ | D24: 520000472 | E24: ח.פ | F24: חשמל אגח 33 | G24: IL0060003923 | H24: ISIN | I24: צמוד למדד המחירים לצרכן | J24: ישראל | K24: ישראל | L24: סחיר | M24: TASE | N24: אנרגיה | O24: לא | P24: AAA | Q24: S&P מעלות | R24: נייר ערך | S24: ILS | T24: 10.281 | U24: 30/05/2036 | V24: 0.0125 | W24: 0.0311 | X24: החוב לא נחות | Y24: לא | Z24: 7800000 | AA24: 1 | AB24: 95.3 | AD24: 7433.4 | AG24: שווי הוגן | AH24: 0.001817 | AI24: 0.025283404 | AJ24: 0.0025710614
A25: 382 | B25: 382 | C25: חברת החשמל לישראל בע"מ | D25: 520000472 | E25: ח.פ | F25: חשמל אגח 34 | G25: IL0011967812 | H25: ISIN | I25: צמוד למדד המחירים לצרכן | J25: ישראל | K25: ישראל | L25: סחיר | M25: TASE | N25: אנרגיה | O25: לא | P25: AAA | Q25: S&P מעלות | R25: נייר ערך | S25: ILS | T25: 7.271 | U25: 12/06/2033 | V25: 0.03 | W25: 0.02951 | X25: החוב לא נחות | Y25: לא | Z25: 6125000 | AA25: 1 | AB25: 106.29 | AD25: 6510.262 | AG25: שווי הוגן | AH25: 0.001501 | AI25: 0.022143514 | AJ25: 0.002251767
A26: 382 | B26: 382 | C26: יוניברסל מוטורס ישראל בע"מ | D26: 511809071 | E26: ח.פ | F26: יוניברסל אגח ד | G26: IL0011722530 | H26: ISIN | I26: לא צמוד למדד המחירים לצרכן | J26: ישראל | K26: ישראל | L26: סחיר | M26: TASE | N26: מסחר | O26: לא | P26: AA- | Q26: S&P מעלות | R26: נייר ערך | S26: ILS | T26: 1.891 | U26: 11/02/2029 | V26: 0.0218 | W26: 0.0518 | X26: החוב לא נחות | Y26: לא | Z26: 3200000 | AA26: 1 | AB26: 94.94 | AD26: 3038.08 | AG26: שווי הוגן | AH26: 0.010508 | AI26: 0.010333495 | AJ26: 0.0010508099
A27: 382 | B27: 382 | C27: בנק לאומי לישראל בע"מ | D27: 520018078 | E27: ח.פ | F27: לאומי אגח 179 | G27: IL0060403727 | H27: ISIN | I27: צמוד למדד המחירים לצרכן | J27: ישראל | K27: ישראל | L27: סחיר | M27: TASE | N27: בנקים | O27: לא | P27: AAA | Q27: S&P מעלות | R27: נייר ערך | S27: ILS | T27: 1.238 | U27: 30/06/2026 | V27: 0.0083 | W27: 0.0229 | X27: החוב לא נחות | Y27: לא | Z27: 7750000 | AA27: 1 | AB27: 114.23 | AD27: 8852.825 | AG27: שווי הוגן | AH27: 0.005096 | AI27: 0.030111329 | AJ27: 0.0030620115
A28: 382 | B28: 382 | C28: בנק לאומי לישראל בע"מ | D28: 520018078 | E28: ח.פ | F28: לאומי אגח 184 | G28: IL0060406043 | H28: ISIN | I28: לא צמוד למדד המחירים לצרכן | J28: ישראל | K28: ישראל | L28: סחיר | M28: TASE | N28: בנקים | O28: לא | P28: AAA | Q28: S&P מעלות | R28: נייר ערך | S28: ILS | T28: 2.663 | U28: 05/05/2030 | V28: 0.0276 | W28: 0.04668 | X28: החוב לא נחות | Y28: לא | Z28: 14500000 | AA28: 1 | AB28: 96.29 | AD28: 13962.05 | AG28: שווי הוגן | AH28: 0.010851 | AI28: 0.04748946 | AJ28: 0.0048291882
A29: 382 | B29: 382 | C29: בנק לאומי לישראל בע"מ | D29: 520018078 | E29: ח.פ | F29: לאומי אגח 186 | G29: IL0012018391 | H29: ISIN | I29: צמוד למדד המחירים לצרכן | J29: ישראל | K29: ישראל | L29: סחיר | M29: TASE | N29: בנקים | O29: לא | P29: AAA | Q29: S&P מעלות | R29: נייר ערך | S29: ILS | T29: 4.597 | U29: 30/11/2033 | V29: 0.0202 | W29: 0.02582 | X29: החוב לא נחות | Y29: לא | Z29: 13300000 | AA29: 1 | AB29: 101.85 | AD29: 13546.05 | AG29: שווי הוגן | AH29: 0.003728 | AI29: 0.046074509 | AJ29: 0.0046853023
A30: 382 | B30: 382 | C30: בנק לאומי לישראל בע"מ | D30: 520018078 | E30: ח.פ | F30: לאומי התח נדח' סד' 405 | G30: IL0060406209 | H30: ISIN | I30: צמוד למדד המחירים לצרכן | J30: ישראל | K30: ישראל | L30: סחיר | M30: TASE | N30: בנקים | O30: לא | P30: AA- | Q30: S&P מעלות | R30: נייר ערך | S30: ILS | T30: 2.944 | U30: 27/03/2028 | V30: 0.015 | W30: 0.03046 | X30: החוב לא נחות | Y30: לא | Z30: 9000000 | AA30: 1 | AB30: 106.7 | AD30: 9603 | AG30: שווי הוגן | AH30: 0.006411 | AI30: 0.032662917 | AJ30: 0.0033214818
A31: 382 | B31: 382 | C31: בנק לאומי לישראל בע"מ | D31: 520018078 | E31: ח.פ | F31: לאומי התח נדח' סד' 406 | G31: IL0012164237 | H31: ISIN | I31: צמוד למדד המחירים לצרכן | J31: ישראל | K31: ישראל | L31: סחיר | M31: TASE | N31: בנקים | O31: לא | P31: AA- | Q31: S&P מעלות | R31: נייר ערך | S31: ILS | T31: 5.481 | U31: 28/02/2036 | V31: 0.031 | W31: 0.03103 | X31: החוב לא נחות | Y31: לא | Z31: 7200000 | AA31: 1 | AB31: 100.81 | AD31: 7258.32 | AG31: שווי הוגן | AH31: 0.00469 | AI31: 0.0246879 | AJ31: 0.0025105048
A32: 382 | B32: 382 | C32: מבנה נדל"ן (כ.ד) בע"מ | D32: 520024126 | E32: ח.פ | F32: מבני תעש אגח כג | G32: IL0022605450 | H32: ISIN | I32: צמוד למדד המחירים לצרכן | J32: ישראל | K32: ישראל | L32: סחיר | M32: TASE | N32: נדל"ן מניב בישראל | O32: לא | P32: AA | Q32: S&P מעלות | R32: נייר ערך | S32: ILS | T32: 1.409 | U32: 30/09/2026 | V32: 0.024 | W32: 0.026 | X32: החוב לא נחות | Y32: לא | Z32: 3221180.4 | AA32: 1 | AB32: 115.95 | AD32: 3734.959 | AG32: שווי הוגן | AH32: 0.005993 | AI32: 0.012703806 | AJ32: 0.001291846
A33: 382 | B33: 382 | C33: מבנה נדל"ן (כ.ד) בע"מ | D33: 520024126 | E33: ח.פ | F33: מבני תעשיה אגח יז | G33: IL0022604461 | H33: ISIN | I33: צמוד למדד המחירים לצרכן | J33: ישראל | K33: ישראל | L33: סחיר | M33: TASE | N33: נדל"ן מניב בישראל | O33: לא | P33: AA | Q33: S&P מעלות | R33: נייר ערך | S33: ILS | T33: 1.683 | U33: 30/06/2028 | V33: 0.037 | W33: 0.02848 | X33: החוב לא נחות | Y33: לא | Z33: 2600000.5 | AA33: 1 | AB33: 118.43 | AD33: 3079.181 | AG33: שווי הוגן | AH33: 0.008645 | AI33: 0.010473292 | AJ33: 0.0010650257
A34: 382 | B34: 382 | C34: מגדל ביטוח גיוס הון בע"מ | D34: 513230029 | E34: ח.פ | F34: מגדל ביטוח הון אגח יד | G34: IL0012075219 | H34: ISIN | I34: לא צמוד למדד המחירים לצרכן | J34: ישראל | K34: ישראל | L34: סחיר | M34: TASE | N34: ביטוח | O34: לא | P34: A1 | Q34: מידרוג Moodys | R34: נייר ערך | S34: ILS | T34: 6.867 | U34: 01/01/2034 | V34: 0.0607 | W34: 0.05528 | X34: החוב לא נחות | Y34: לא | Z34: 1408500 | AA34: 1 | AB34: 105.72 | AD34: 1489.066 | AG34: שווי הוגן | AH34: 0.003112 | AI34: 0.005064797 | AJ34: 0.00051503762
A35: 382 | B35: 382 | C35: מגדל ביטוח גיוס הון בע"מ | D35: 513230029 | E35: ח.פ | F35: מגדל הון אגח יג 31/12/2032 | G35: IL0012075136 | H35: ISIN | I35: לא צמוד למדד המחירים לצרכן | J35: ישראל | K35: ישראל | L35: סחיר | M35: TASE | N35: ביטוח | O35: לא | P35: A+ | Q35: S&P מעלות | R35: נייר ערך | S35: ILS | T35: 6.247 | U35: 31/12/2032 | V35: 0.0607 | W35: 0.05457 | X35: החוב לא נחות | Y35: לא | Z35: 1408500 | AA35: 1 | AB35: 105.78 | AD35: 1489.911 | AG35: שווי הוגן | AH35: 0.003112 | AI35: 0.0050676715 | AJ35: 0.00051532992
... A60: 382 | B60: 382 | C60: שופר-סל בע"מ | D60: 520022732 | E60: ח.פ | F60: שופרסל אגח ו | G60: IL0077702178 | H60: ISIN | I60: צמוד למדד המחירים לצרכן | J60: ישראל | K60: ישראל | L60: סחיר | M60: TASE | N60: רשתות שיווק | O60: לא | P60: AA | Q60: S&P מעלות | R60: נייר ערך | S60: ILS | T60: 1.941 | U60: 08/10/2028 | V60: 0.043 | W60: 0.02547 | X60: החוב לא נחות | Y60: לא | Z60: 1645835.4 | AA60: 1 | AB60: 121.82 | AD60: 2004.957 | AG60: שווי הוגן | AH60: 0.004035 | AI60: 0.0068195078 | AJ60: 0.00069347361
A61: 382 | B61: 382 | C61: שיכון ובינוי בע"מ | D61: 520036104 | E61: ח.פ | F61: שיכון ובינוי אגח 6 | G61: IL0011297335 | H61: ISIN | I61: צמוד למדד המחירים לצרכן | J61: ישראל | K61: ישראל | L61: סחיר | M61: TASE | N61: בנייה | O61: לא | P61: A | Q61: S&P מעלות | R61: נייר ערך | S61: ILS | T61: 0.003 | U61: 01/04/2025 | V61: 0.0434 | W61: 0.29883 | X61: החוב לא נחות | Y61: לא | Z61: 0 | AA61: 1 | AB61: 0 | AC61: 2050.421 | AD61: 2050.421 | AG61: שווי הוגן | AH61: 0 | AI61: 0.0069741464 | AJ61: 0.00070919875
A62: 382 | B62: 382 | C62: שיכון ובינוי אנרגיה בע"מ | D62: 510459928 | E62: ח.פ | F62: שיכון ובינוי אנרגיה אגח א' | G62: IL0011985715 | H62: ISIN | I62: לא צמוד למדד המחירים לצרכן | J62: ישראל | K62: ישראל | L62: סחיר | M62: TASE | N62: אנרגיה | O62: לא | P62: A3 | Q62: מידרוג Moodys | R62: נייר ערך | S62: ILS | T62: 3.958 | U62: 30/06/2034 | V62: 0.0677 | W62: 0.05684 | X62: החוב לא נחות | Y62: לא | Z62: 4900000 | AA62: 1 | AB62: 106.28 | AD62: 5207.72 | AG62: שווי הוגן | AH62: 0.006533 | AI62: 0.017713144 | AJ62: 0.0018012441
A63: 382 | B63: 382 | C63: תומר תמלוגי אנרגיה (2012) בע"מ | D63: 514837111 | E63: ח.פ | F63: תומר אנרגיה אגח א | G63: IL0011474793 | H63: ISIN | I63: צמוד למט"ח | J63: ישראל | K63: ישראל | L63: סחיר | M63: TASE | N63: חיפושי נפט וגז | O63: לא | P63: Aa3 | Q63: מידרוג Moodys | R63: נייר ערך | S63: ILS | T63: 2.477 | U63: 30/08/2028 | V63: 0.0548 | W63: 0.06529 | X63: החוב לא נחות | Y63: לא | Z63: 925100.04 | AA63: 1 | AB63: 102.76 | AD63: 950.633 | AG63: שווי הוגן | AH63: 0.003444 | AI63: 0.0032334104 | AJ63: 0.00032880449
A64: 382 | B64: 382 | C64: תמר פטרוליום בעמ | D64: 515334662 | E64: ח.פ | F64: תמר פטרוליום אגח א | G64: IL0011413320 | H64: ISIN | I64: צמוד למט"ח | J64: ישראל | K64: ישראל | L64: סחיר | M64: TASE | N64: חיפושי נפט וגז | O64: לא | P64: A1 | Q64: מידרוג Moodys | R64: נייר ערך | S64: ILS | T64: 2.672 | U64: 30/08/2028 | V64: 0.0469 | W64: 0.06766 | X64: החוב לא נחות | Y64: לא | Z64: 7076100 | AA64: 1 | AB64: 101 | AD64: 7146.861 | AG64: שווי הוגן | AH64: 0.005237 | AI64: 0.024308792 | AJ64: 0.0024719534
A65: 382 | B65: 382 | C65: בנק הפועלים בע"מ | D65: 520000118 | E65: ח.פ | F65: HAPOAL 3.255 01/21/32 | G65: IL0066204707 | H65: ISIN | I65: צמוד למט"ח | J65: ישראל | K65: ישראל | L65: סחיר | M65: TASE | N65: Banks | O65: לא | P65: BBB- | Q65: S&P | R65: נייר ערך | S65: USD | T65: 1.748 | U65: 21/01/2032 | V65: 0.03255 | W65: 0.06056 | X65: החוב לא נחות | Y65: לא | Z65: 2000000 | AA65: 3.718 | AB65: 96.148 | AD65: 7149.556 | AG65: שווי הוגן | AH65: 0.002 | AI65: 0.024317958 | AJ65: 0.0024728855
A66: 382 | B66: 382 | C66: בנק לאומי לישראל בע"מ | D66: 520018078 | E66: ח.פ | F66: LUMIIT 3.275 01/29/3 | G66: IL0060404899 | H66: ISIN | I66: צמוד למט"ח | J66: ישראל | K66: ישראל | L66: סחיר | M66: TASE | N66: Banks | O66: לא | P66: BBB- | Q66: S&P | R66: נייר ערך | S66: USD | T66: 5.09 | U66: 29/01/2031 | V66: 0.03275 | W66: 0.05732 | X66: החוב לא נחות | Y66: לא | Z66: 1900000 | AA66: 3.718 | AB66: 98.468 | AD66: 6955.985 | AG66: שווי הוגן | AH66: 0.002533 | AI66: 0.023659562 | AJ66: 0.0024059334
A67: 382 | B67: 1404 | C67: איירפורט סיטי בע"מ | D67: 511659401 | E67: ח.פ | F67: איירפורט אגח ה | G67: IL0011334872 | H67: ISIN | I67: צמוד למדד המחירים לצרכן | J67: ישראל | K67: ישראל | L67: סחיר | M67: TASE | N67: נדל"ן מניב בישראל | O67: לא | P67: AA | Q67: S&P מעלות | R67: נייר ערך | S67: ILS | T67: 2.267 | U67: 28/02/2029 | V67: 0.0234 | W67: 0.02797 | X67: החוב לא נחות | Y67: לא | Z67: 50000 | AA67: 1 | AB67: 114.39 | AD67: 57.195 | AG67: שווי הוגן | AH67: 3.1e-05 | AI67: 0.013602703 | AJ67: 0.0021392751
A68: 382 | B68: 1404 | C68: איירפורט סיטי בע"מ | D68: 511659401 | E68: ח.פ | F68: איירפורט אגח י | G68: IL0011959819 | H68: ISIN | I68: לא צמוד למדד המחירים לצרכן | J68: ישראל | K68: ישראל | L68: סחיר | M68: TASE | N68: נדל"ן מניב בישראל | O68: לא | P68: AA | Q68: S&P מעלות | R68: נייר ערך | S68: ILS | T68: 2.256 | U68: 30/04/2029 | V68: 0.05 | W68: 0.05058 | X68: החוב לא נחות | Y68: לא | Z68: 80000 | AA68: 1 | AB68: 102.1 | AD68: 81.68 | AG68: שווי הוגן | AH68: 0.0002 | AI68: 0.019425977 | AJ68: 0.0030550921
A69: 382 | B69: 1404 | C69: אלביט מערכות בע"מ | D69: 520043027 | E69: ח.פ | F69: אלביט מערכות ב' 1.08% | G69: IL0011782351 | H69: ISIN | I69: לא צמוד למדד המחירים לצרכן | J69: ישראל | K69: ישראל | L69: סחיר | M69: TASE | N69: ביטחוניות | O69: לא | P69: AA | Q69: S&P מעלות | R69: נייר ערך | S69: ILS | T69: 2.141 | U69: 01/07/2029 | V69: 0.0108 | W69: 0.04714 | X69: החוב לא נחות | Y69: לא | Z69: 38541.67 | AA69: 1 | AB69: 92.86 | AD69: 35.79 | AG69: שווי הוגן | AH69: 4.1e-05 | AI69: 0.0085118969 | AJ69: 0.0013386523
A70: 382 | B70: 1404 | C70: אלוני-חץ נכסים והשקעות בע"מ | D70: 520038506 | E70: ח.פ | F70: אלוני חץ אגח ט | G70: IL0039003541 | H70: ISIN | I70: לא צמוד למדד המחירים לצרכן | J70: ישראל | K70: ישראל | L70: סחיר | M70: TASE | N70: נדל"ן מניב בישראל | O70: לא | P70: AA- | Q70: S&P מעלות | R70: נייר ערך | S70: ILS | T70: 1.392 | U70: 28/02/2027 | V70: 0.0385 | W70: 0.05029 | X70: החוב לא נחות | Y70: לא | Z70: 47357.15 | AA70: 1 | AB70: 98.76 | AD70: 46.77 | AG70: שווי הוגן | AH70: 0.000152 | AI70: 0.011123303 | AJ70: 0.001749344
A71: 382 | B71: 1404 | C71: אלוני-חץ נכסים והשקעות בע"מ | D71: 520038506 | E71: ח.פ | F71: אלוני חץ אגח טו | G71: IL0011894149 | H71: ISIN | I71: צמוד למדד המחירים לצרכן | J71: ישראל | K71: ישראל | L71: סחיר | M71: TASE | N71: נדל"ן מניב בישראל | O71: לא | P71: AA- | Q71: S&P מעלות | R71: נייר ערך | S71: ILS | T71: 6.663 | U71: 01/03/2037 | V71: 0.0256 | W71: 0.03503 | X71: החוב לא נחות | Y71: לא | Z71: 30000 | AA71: 1 | AB71: 101.59 | AD71: 30.477 | AG71: שווי הוגן | AH71: 2.9e-05 | AI71: 0.0072483534 | AJ71: 0.0011399369
A72: 382 | B72: 1404 | C72: אלוני-חץ נכסים והשקעות בע"מ | D72: 520038506 | E72: ח.פ | F72: אלוני חץ אגח יב | G72: IL0039004952 | H72: ISIN | I72: לא צמוד למדד המחירים לצרכן | J72: ישראל | K72: ישראל | L72: סחיר | M72: TASE | N72: נדל"ן מניב בישראל | O72: לא | P72: AA- | Q72: S&P מעלות | R72: נייר ערך | S72: ILS | T72: 3.951 | U72: 28/02/2031 | V72: 0.0241 | W72: 0.05291 | X72: החוב לא נחות | Y72: לא | Z72: 84240 | AA72: 1 | AB72: 89.75 | AD72: 75.605 | AG72: שווי הוגן | AH72: 4.1e-05 | AI72: 0.017981253 | AJ72: 0.0028278827
A73: 382 | B73: 1404 | C73: אלקטרה בע"מ | D73: 520028911 | E73: ח.פ | F73: אלקטרה אגח ה | G73: IL0073902228 | H73: ISIN | I73: לא צמוד למדד המחירים לצרכן | J73: ישראל | K73: ישראל | L73: סחיר | M73: TASE | N73: השקעה ואחזקות | O73: לא | P73: A+ | Q73: S&P מעלות | R73: נייר ערך | S73: ILS | T73: 2.996 | U73: 10/01/2031 | V73: 0.04 | W73: 0.0524 | X73: החוב לא נחות | Y73: לא | Z73: 30000 | AA73: 1 | AB73: 97.45 | AD73: 29.235 | AG73: שווי הוגן | AH73: 5.2e-05 | AI73: 0.0069529682 | AJ73: 0.0010934821
... A104: 382 | B104: 1404 | C104: קבוצת עזריאלי בע"מ (לשעבר קנית מימון) | D104: 510960719 | E104: ח.פ | F104: עזריאלי אגח ז | G104: IL0011786725 | H104: ISIN | I104: צמוד למדד המחירים לצרכן | J104: ישראל | K104: ישראל | L104: סחיר | M104: TASE | N104: נדל"ן מניב בישראל | O104: לא | P104: AA+ | Q104: S&P מעלות | R104: נייר ערך | S104: ILS | T104: 6.473 | U104: 02/07/2036 | V104: 0.009 | W104: 0.03072 | X104: החוב לא נחות | Y104: לא | Z104: 58800 | AA104: 1 | AB104: 99.26 | AD104: 58.365 | AG104: שווי הוגן | AH104: 2.1e-05 | AI104: 0.013880936 | AJ104: 0.0021830324
A105: 382 | B105: 1404 | C105: קבוצת עזריאלי בע"מ (לשעבר קנית מימון) | D105: 510960719 | E105: ח.פ | F105: עזריאלי קבוצה אגח ב סחיר | G105: IL0011344368 | H105: ISIN | I105: צמוד למדד המחירים לצרכן | J105: ישראל | K105: ישראל | L105: סחיר | M105: TASE | N105: נדל"ן מניב בישראל | O105: לא | P105: AA+ | Q105: S&P מעלות | R105: נייר ערך | S105: ILS | T105: 0.003 | U105: 01/04/2025 | V105: 0.0065 | W105: 0.25729 | X105: החוב לא נחות | Y105: לא | Z105: 0 | AA105: 1 | AB105: 0 | AC105: 69.554 | AD105: 69.554 | AG105: שווי הוגן | AH105: 0 | AI105: 0.016541957 | AJ105: 0.0026015269
A106: 382 | B106: 1404 | C106: בנק הפועלים בע"מ | D106: 520000118 | E106: ח.פ | F106: פועלים אגח 202 | G106: IL0011998502 | H106: ISIN | I106: צמוד למדד המחירים לצרכן | J106: ישראל | K106: ישראל | L106: סחיר | M106: TASE | N106: בנקים | O106: לא | P106: AAA | Q106: S&P מעלות | R106: נייר ערך | S106: ILS | T106: 1.54 | U106: 30/04/2028 | V106: 0.006 | W106: 0.02446 | X106: החוב לא נחות | Y106: לא | Z106: 239083.34 | AA106: 1 | AB106: 113.98 | AD106: 272.507 | AG106: שווי הוגן | AH106: 0.000269 | AI106: 0.064810461 | AJ106: 0.010192637
A107: 382 | B107: 1404 | C107: בנק הפועלים בע"מ | D107: 520000118 | E107: ח.פ | F107: פועלים אגח 203 | G107: IL0011998684 | H107: ISIN | I107: צמוד למדד המחירים לצרכן | J107: ישראל | K107: ישראל | L107: סחיר | M107: TASE | N107: בנקים | O107: לא | P107: AAA | Q107: S&P מעלות | R107: נייר ערך | S107: ILS | T107: 3.053 | U107: 02/12/2030 | V107: 0.0175 | W107: 0.02554 | X107: החוב לא נחות | Y107: לא | Z107: 189057.27 | AA107: 1 | AB107: 112.78 | AD107: 213.219 | AG107: שווי הוגן | AH107: 8.5e-05 | AI107: 0.050709884 | AJ107: 0.0079750617
A108: 382 | B108: 1404 | C108: בנק הפועלים בע"מ | D108: 520000118 | E108: ח.פ | F108: פועלים התח נד יב | G108: IL0012141219 | H108: ISIN | I108: צמוד למדד המחירים לצרכן | J108: ישראל | K108: ישראל | L108: סחיר | M108: TASE | N108: בנקים | O108: לא | P108: AA- | Q108: S&P מעלות | R108: נייר ערך | S108: ILS | T108: 6.802 | U108: 28/11/2032 | V108: 0.0345 | W108: 0.03191 | X108: החוב לא נחות | Y108: לא | Z108: 90000 | AA108: 1 | AB108: 102.77 | AD108: 92.493 | AG108: שווי הוגן | AH108: 9.8e-05 | AI108: 0.021997636 | AJ108: 0.0034595327
A109: 382 | B109: 1404 | C109: הפניקס גיוסי הון (2009) בע"מ | D109: 514290345 | E109: ח.פ | F109: פניקס הון אגח טו | G109: IL0012019530 | H109: ISIN | I109: לא צמוד למדד המחירים לצרכן | J109: ישראל | K109: ישראל | L109: סחיר | M109: TASE | N109: ביטוח | O109: לא | P109: AA | Q109: S&P מעלות | R109: נייר ערך | S109: ILS | T109: 4.679 | U109: 30/06/2030 | V109: 0.0469 | W109: 0.05033 | X109: החוב לא נחות | Y109: לא | Z109: 99982 | AA109: 1 | AB109: 98.85 | AD109: 98.832 | AG109: שווי הוגן | AH109: 0.0002 | AI109: 0.023505291 | AJ109: 0.0036966393
A110: 382 | B110: 1404 | C110: קרסו מוטורס בע"מ | D110: 514065283 | E110: ח.פ | F110: קרסו מוטורס אגח ג | G110: IL0011418295 | H110: ISIN | I110: לא צמוד למדד המחירים לצרכן | J110: ישראל | K110: ישראל | L110: סחיר | M110: TASE | N110: מסחר | O110: לא | P110: AA- | Q110: S&P מעלות | R110: נייר ערך | S110: ILS | T110: 1.518 | U110: 01/09/2027 | V110: 0.023 | W110: 0.05165 | X110: החוב לא נחות | Y110: לא | Z110: 47419.36 | AA110: 1 | AB110: 96.07 | AD110: 45.556 | AG110: שווי הוגן | AH110: 4.4e-05 | AI110: 0.010834544 | AJ110: 0.0017039312
A111: 382 | B111: 1404 | C111: רבוע כחול נדל"ן בע"מ | D111: 513765859 | E111: ח.פ | F111: רבוע נדלן אגח ו | G111: IL0011406076 | H111: ISIN | I111: צמוד למדד המחירים לצרכן | J111: ישראל | K111: ישראל | L111: סחיר | M111: TASE | N111: נדל"ן מניב בישראל | O111: לא | P111: AA- | Q111: S&P מעלות | R111: נייר ערך | S111: ILS | T111: 1.146 | U111: 30/11/2026 | V111: 0.0215 | W111: 0.02817 | X111: החוב לא נחות | Y111: לא | Z111: 64285.71 | AA111: 1 | AB111: 117.16 | AD111: 75.317 | AG111: שווי הוגן | AH111: 4.6e-05 | AI111: 0.017912696 | AJ111: 0.0028171008
A112: 382 | B112: 1404 | C112: ש.שלמה החזקות בע"מ | D112: 520034372 | E112: ח.פ | F112: שלמה החז אגח כ | G112: IL0011927493 | H112: ISIN | I112: צמוד למדד המחירים לצרכן | J112: ישראל | K112: ישראל | L112: סחיר | M112: TASE | N112: שירותים | O112: לא | P112: AA | Q112: S&P מעלות | R112: נייר ערך | S112: ILS | T112: 3.284 | U112: 21/12/2031 | V112: 0.022 | W112: 0.02956 | X112: החוב לא נחות | Y112: לא | Z112: 76500.03 | AA112: 1 | AB112: 104.45 | AD112: 79.904 | AG112: שווי הוגן | AH112: 0.000128 | AI112: 0.019003658 | AJ112: 0.0029886746
A113: 382 | B113: 7635 | C113: איירפורט סיטי בע"מ | D113: 511659401 | E113: ח.פ | F113: איירפורט אגח ה | G113: IL0011334872 | H113: ISIN | I113: צמוד למדד המחירים לצרכן | J113: ישראל | K113: ישראל | L113: סחיר | M113: TASE | N113: נדל"ן מניב בישראל | O113: לא | P113: AA | Q113: S&P מעלות | R113: נייר ערך | S113: ILS | T113: 2.267 | U113: 28/02/2029 | V113: 0.0234 | W113: 0.02797 | X113: החוב לא נחות | Y113: לא | Z113: 43081.25 | AA113: 1 | AB113: 114.39 | AD113: 49.281 | AG113: שווי הוגן | AH113: 2.6e-05 | AI113: 0.014430103 | AJ113: 0.0026535151
A114: 382 | B114: 7635 | C114: איירפורט סיטי בע"מ | D114: 511659401 | E114: ח.פ | F114: איירפורט אגח י | G114: IL0011959819 | H114: ISIN | I114: לא צמוד למדד המחירים לצרכן | J114: ישראל | K114: ישראל | L114: סחיר | M114: TASE | N114: נדל"ן מניב בישראל | O114: לא | P114: AA | Q114: S&P מעלות | R114: נייר ערך | S114: ILS | T114: 2.256 | U114: 30/04/2029 | V114: 0.05 | W114: 0.05058 | X114: החוב לא נחות | Y114: לא | Z114: 30000 | AA114: 1 | AB114: 102.1 | AD114: 30.63 | AG114: שווי הוגן | AH114: 7.5e-05 | AI114: 0.0089689184 | AJ114: 0.0016492717
A115: 382 | B115: 7635 | C115: אלבר שירותי מימונית בע"מ | D115: 512025891 | E115: ח.פ | F115: אלבר אג"ח יח | G115: IL0011587404 | H115: ISIN | I115: לא צמוד למדד המחירים לצרכן | J115: ישראל | K115: ישראל | L115: סחיר | M115: TASE | N115: שירותים | O115: לא | P115: A+ | Q115: S&P מעלות | R115: נייר ערך | S115: ILS | T115: 0.884 | U115: 13/01/2027 | V115: 0.0325 | W115: 0.05604 | X115: החוב לא נחות | Y115: לא | Z115: 10546.88 | AA115: 1 | AB115: 98.74 | AD115: 10.414 | AG115: שווי הוגן | AH115: 3.2e-05 | AI115: 0.0030493706 | AJ115: 0.00056074104
A116: 382 | B116: 7635 | C116: אלוני-חץ נכסים והשקעות בע"מ | D116: 520038506 | E116: ח.פ | F116: אלוני חץ אגח ט | G116: IL0039003541 | H116: ISIN | I116: לא צמוד למדד המחירים לצרכן | J116: ישראל | K116: ישראל | L116: סחיר | M116: TASE | N116: נדל"ן מניב בישראל | O116: לא | P116: AA- | Q116: S&P מעלות | R116: נייר ערך | S116: ILS | T116: 1.392 | U116: 28/02/2027 | V116: 0.0385 | W116: 0.05029 | X116: החוב לא נחות | Y116: לא | Z116: 18833.33 | AA116: 1 | AB116: 98.76 | AD116: 18.6 | AG116: שווי הוגן | AH116: 6e-05 | AI116: 0.0054462964 | AJ116: 0.0010015057
A117: 382 | B117: 7635 | C117: אלוני-חץ נכסים והשקעות בע"מ | D117: 520038506 | E117: ח.פ | F117: אלוני חץ אגח טו | G117: IL0011894149 | H117: ISIN | I117: צמוד למדד המחירים לצרכן | J117: ישראל | K117: ישראל | L117: סחיר | M117: TASE | N117: נדל"ן מניב בישראל | O117: לא | P117: AA- | Q117: S&P מעלות | R117: נייר ערך | S117: ILS | T117: 6.663 | U117: 01/03/2037 | V117: 0.0256 | W117: 0.03503 | X117: החוב לא נחות | Y117: לא | Z117: 15000 | AA117: 1 | AB117: 101.59 | AD117: 15.239 | AG117: שווי הוגן | AH117: 1.4e-05 | AI117: 0.0044620589 | AJ117: 0.00082051672
... A186: 382 | B186: 7635 | C186: שטראוס גרופ בע"מ | D186: 520003781 | E186: ח.פ | F186: שטראוס אגח ה | G186: IL0074603890 | H186: ISIN | I186: לא צמוד למדד המחירים לצרכן | J186: ישראל | K186: ישראל | L186: סחיר | M186: TASE | N186: מזון | O186: לא | P186: AA+ | Q186: S&P מעלות | R186: נייר ערך | S186: ILS | T186: 1.206 | U186: 30/06/2027 | V186: 0.0261 | W186: 0.04583 | X186: החוב לא נחות | Y186: לא | Z186: 37894.73 | AA186: 1 | AB186: 98.38 | AD186: 37.281 | AG186: שווי הוגן | AH186: 0.000105 | AI186: 0.010916382 | AJ186: 0.0020073858
A187: 382 | B187: 7635 | C187: שיכון ובינוי בע"מ | D187: 520036104 | E187: ח.פ | F187: שיכון ובינוי אגח 7 | G187: IL0011297418 | H187: ISIN | I187: לא צמוד למדד המחירים לצרכן | J187: ישראל | K187: ישראל | L187: סחיר | M187: TASE | N187: בנייה | O187: לא | P187: A | Q187: S&P מעלות | R187: נייר ערך | S187: ILS | T187: 0.003 | U187: 01/04/2025 | V187: 0.0623 | W187: 0.50275 | X187: החוב לא נחות | Y187: לא | Z187: 0 | AA187: 1 | AB187: 0 | AC187: 10.312 | AD187: 10.312 | AG187: שווי הוגן | AH187: 0 | AI187: 0.0030193982 | AJ187: 0.0005552295
A188: 382 | B188: 7635 | C188: שיכון ובינוי בע"מ | D188: 520036104 | E188: ח.פ | F188: שיכון ובינוי אגח 8 | G188: IL0011358889 | H188: ISIN | I188: צמוד למדד המחירים לצרכן | J188: ישראל | K188: ישראל | L188: סחיר | M188: TASE | N188: בנייה | O188: לא | P188: A | Q188: S&P מעלות | R188: נייר ערך | S188: ILS | T188: 2.349 | U188: 01/05/2029 | V188: 0.039 | W188: 0.03839 | X188: החוב לא נחות | Y188: לא | Z188: 51235.29 | AA188: 1 | AB188: 118.27 | AD188: 60.596 | AG188: שווי הוגן | AH188: 3.6e-05 | AI188: 0.017743401 | AJ188: 0.0032627892
A189: 382 | B189: 7635 | C189: שיכון ובינוי אנרגיה בע"מ | D189: 510459928 | E189: ח.פ | F189: שיכון ובינוי אנרגיה אגח א' | G189: IL0011985715 | H189: ISIN | I189: לא צמוד למדד המחירים לצרכן | J189: ישראל | K189: ישראל | L189: סחיר | M189: TASE | N189: אנרגיה | O189: לא | P189: A3 | Q189: מידרוג Moodys | R189: נייר ערך | S189: ILS | T189: 3.958 | U189: 30/06/2034 | V189: 0.0677 | W189: 0.05684 | X189: החוב לא נחות | Y189: לא | Z189: 25000 | AA189: 1 | AB189: 106.28 | AD189: 26.57 | AG189: שווי הוגן | AH189: 3.3e-05 | AI189: 0.0077800902 | AJ189: 0.0014306611
A190: 382 | B190: 7635 | C190: ש.שלמה החזקות בע"מ | D190: 520034372 | E190: ח.פ | F190: שלמה החז אגח יז | G190: IL0014102995 | H190: ISIN | I190: לא צמוד למדד המחירים לצרכן | J190: ישראל | K190: ישראל | L190: סחיר | M190: TASE | N190: שירותים | O190: לא | P190: AA | Q190: S&P מעלות | R190: נייר ערך | S190: ILS | T190: 0.711 | U190: 21/06/2026 | V190: 0.027 | W190: 0.05194 | X190: החוב לא נחות | Y190: לא | Z190: 19109.53 | AA190: 1 | AB190: 98.4 | AD190: 18.804 | AG190: שווי הוגן | AH190: 0.000244 | AI190: 0.005506025 | AJ190: 0.001012489
A191: 382 | B191: 7635 | C191: ש.שלמה החזקות בע"מ | D191: 520034372 | E191: ח.פ | F191: שלמה החז אגח יח | G191: IL0014103076 | H191: ISIN | I191: צמוד למדד המחירים לצרכן | J191: ישראל | K191: ישראל | L191: סחיר | M191: TASE | N191: שירותים | O191: לא | P191: AA | Q191: S&P מעלות | R191: נייר ערך | S191: ILS | T191: 0.716 | U191: 21/06/2026 | V191: 0.018 | W191: 0.02519 | X191: החוב לא נחות | Y191: לא | Z191: 4825.29 | AA191: 1 | AB191: 115.62 | AD191: 5.579 | AG191: שווי הוגן | AH191: 1.2e-05 | AI191: 0.0016336141 | AJ191: 0.00030040116
A192: 382 | B192: 7635 | C192: תמר פטרוליום בעמ | D192: 515334662 | E192: ח.פ | F192: תמר פטרוליום אגח א | G192: IL0011413320 | H192: ISIN | I192: צמוד למט"ח | J192: ישראל | K192: ישראל | L192: סחיר | M192: TASE | N192: חיפושי נפט וגז | O192: לא | P192: A1 | Q192: מידרוג Moodys | R192: נייר ערך | S192: ILS | T192: 2.672 | U192: 30/08/2028 | V192: 0.0469 | W192: 0.06766 | X192: החוב לא נחות | Y192: לא | Z192: 56434.95 | AA192: 1 | AB192: 101 | AD192: 56.999 | AG192: שווי הוגן | AH192: 4.2e-05 | AI192: 0.016690241 | AJ192: 0.0030691261
A193: 382 | B193: 11414 | C193: אלקטרה בע"מ | D193: 520028911 | E193: ח.פ | F193: אלקטרה אגח ה | G193: IL0073902228 | H193: ISIN | I193: לא צמוד למדד המחירים לצרכן | J193: ישראל | K193: ישראל | L193: סחיר | M193: TASE | N193: השקעה ואחזקות | O193: לא | P193: A+ | Q193: S&P מעלות | R193: נייר ערך | S193: ILS | T193: 2.996 | U193: 10/01/2031 | V193: 0.04 | W193: 0.0524 | X193: החוב לא נחות | Y193: לא | Z193: 117500.01 | AA193: 1 | AB193: 97.45 | AD193: 114.504 | AG193: שווי הוגן | AH193: 0.000202 | AI193: 0.076838846 | AJ193: 0.007430776
A194: 382 | B194: 11414 | C194: אמות השקעות בע"מ | D194: 520026683 | E194: ח.פ | F194: אמות אגח ד | G194: IL0011331498 | H194: ISIN | I194: צמוד למדד המחירים לצרכן | J194: ישראל | K194: ישראל | L194: סחיר | M194: TASE | N194: נדל"ן מניב בישראל | O194: לא | P194: AA | Q194: S&P מעלות | R194: נייר ערך | S194: ILS | T194: 1.682 | U194: 02/07/2028 | V194: 0.032 | W194: 0.02754 | X194: החוב לא נחות | Y194: לא | Z194: 121250 | AA194: 1 | AB194: 118.93 | AD194: 144.203 | AG194: שווי הוגן | AH194: 0.00022 | AI194: 0.096768554 | AJ194: 0.009358098
A195: 382 | B195: 11414 | C195: אנלייט אנרגיה מתחדשת בע"מ | D195: 520041146 | E195: ח.פ | F195: אנלייט אנר אגח ו | G195: IL0072001733 | H195: ISIN | I195: לא צמוד למדד המחירים לצרכן | J195: ישראל | K195: ארה"ב | L195: סחיר | M195: TASE | N195: אנרגיה מתחדשת | O195: לא | P195: A2 | Q195: מידרוג Moodys | R195: נייר ערך | S195: ILS | T195: 1.261 | U195: 01/09/2026 | V195: 0.0345 | W195: 0.05499 | X195: החוב לא נחות | Y195: לא | Z195: 117857.14 | AA195: 1 | AB195: 97.86 | AD195: 115.335 | AG195: שווי הוגן | AH195: 0.000183 | AI195: 0.077396656 | AJ195: 0.0074847196
A196: 382 | B196: 11414 | C196: אנרג'יקס אנרגיות מתחדשות בע"מ | D196: 513901371 | E196: ח.פ | F196: אנרג'יקס אגח א | G196: IL0011617516 | H196: ISIN | I196: לא צמוד למדד המחירים לצרכן | J196: ישראל | K196: ישראל | L196: סחיר | M196: TASE | N196: אנרגיה מתחדשת | O196: לא | P196: A | Q196: S&P מעלות | R196: נייר ערך | S196: ILS | T196: 2.656 | U196: 01/08/2030 | V196: 0.0205 | W196: 0.05492 | X196: החוב לא נחות | Y196: לא | Z196: 50000 | AA196: 1 | AB196: 91.77 | AD196: 45.885 | AG196: שווי הוגן | AH196: 5.2e-05 | AI196: 0.030791569 | AJ196: 0.0029777289
A197: 382 | B197: 11414 | C197: קבוצת אשטרום | D197: 510381601 | E197: ח.פ | F197: אשטרום קב אגח ב | G197: IL0011323313 | H197: ISIN | I197: לא צמוד למדד המחירים לצרכן | J197: ישראל | K197: ישראל | L197: סחיר | M197: TASE | N197: בנייה | O197: לא | P197: A | Q197: S&P מעלות | R197: נייר ערך | S197: ILS | T197: 0.11 | U197: 11/05/2025 | V197: 0.042 | W197: 0.05715 | X197: החוב לא נחות | Y197: לא | Z197: 110560 | AA197: 1 | AB197: 101.48 | AD197: 112.196 | AG197: שווי הוגן | AH197: 0.000916 | AI197: 0.075290395 | AJ197: 0.0072810315
A198: 382 | B198: 11414 | C198: חברת גב-ים לקרקעות בע"מ | D198: 520001736 | E198: ח.פ | F198: גב ים אגח י | G198: IL0075902846 | H198: ISIN | I198: צמוד למדד המחירים לצרכן | J198: ישראל | K198: ישראל | L198: סחיר | M198: TASE | N198: נדל"ן מניב בישראל | O198: לא | P198: AA | Q198: S&P מעלות | R198: נייר ערך | S198: ILS | T198: 4.673 | U198: 01/07/2035 | V198: 0.0059 | W198: 0.03078 | X198: החוב לא נחות | Y198: לא | Z198: 110000 | AA198: 1 | AB198: 100.11 | AD198: 110.121 | AG198: שווי הוגן | AH198: 7.9e-05 | AI198: 0.073897753 | AJ198: 0.0071463547
A199: 382 | B199: 11414 | C199: דור אלון אנרגיה בישראל (1988) בע"מ | D199: 520043878 | E199: ח.פ | F199: דור אלון אגח ו | G199: IL0011406563 | H199: ISIN | I199: לא צמוד למדד המחירים לצרכן | J199: ישראל | K199: ישראל | L199: סחיר | M199: TASE | N199: אנרגיה | O199: לא | P199: A2 | Q199: מידרוג Moodys | R199: נייר ערך | S199: ILS | T199: 0.167 | U199: 01/06/2025 | V199: 0.0295 | W199: 0.0639 | X199: החוב לא נחות | Y199: לא | Z199: 7300.01 | AA199: 1 | AB199: 100.43 | AD199: 7.331 | AG199: שווי הוגן | AH199: 0.000122 | AI199: 0.0049198063 | AJ199: 0.0004757747
... A203: 382 | B203: 11414 | C203: חברת החשמל לישראל בע"מ | D203: 520000472 | E203: ח.פ | F203: חשמל אגח 29 | G203: IL0060002362 | H203: ISIN | I203: צמוד למדד המחירים לצרכן | J203: ישראל | K203: ישראל | L203: סחיר | M203: TASE | N203: אנרגיה | O203: לא | P203: AAA | Q203: S&P מעלות | R203: נייר ערך | S203: ILS | T203: 0.904 | U203: 01/03/2026 | V203: 0.045 | W203: 0.02397 | X203: החוב לא נחות | Y203: לא | Z203: 77000 | AA203: 1 | AB203: 119.86 | AD203: 92.292 | AG203: שווי הוגן | AH203: 5.2e-05 | AI203: 0.061933566 | AJ203: 0.0059893463
A204: 382 | B204: 11414 | C204: חברת החשמל לישראל בע"מ | D204: 520000472 | E204: ח.פ | F204: חשמל אגח 27 | G204: IL0060002107 | H204: ISIN | I204: צמוד למדד המחירים לצרכן | J204: ישראל | K204: ישראל | L204: סחיר | M204: TASE | N204: אנרגיה | O204: לא | P204: AAA | Q204: S&P מעלות | R204: נייר ערך | S204: ILS | T204: 3.022 | U204: 12/04/2029 | V204: 0.0385 | W204: 0.02566 | X204: החוב לא נחות | Y204: לא | Z204: 81468.46 | AA204: 1 | AB204: 120.79 | AC204: 2.867 | AD204: 101.273 | AG204: שווי הוגן | AH204: 3.2e-05 | AI204: 0.067960105 | AJ204: 0.0065721487
A205: 382 | B205: 11414 | C205: בנק לאומי לישראל בע"מ | D205: 520018078 | E205: ח.פ | F205: לאומי אגח 186 | G205: IL0012018391 | H205: ISIN | I205: צמוד למדד המחירים לצרכן | J205: ישראל | K205: ישראל | L205: סחיר | M205: TASE | N205: בנקים | O205: לא | P205: AAA | Q205: S&P מעלות | R205: נייר ערך | S205: ILS | T205: 4.597 | U205: 30/11/2033 | V205: 0.0202 | W205: 0.02582 | X205: החוב לא נחות | Y205: לא | Z205: 50000 | AA205: 1 | AB205: 101.85 | AD205: 50.925 | AG205: שווי הוגן | AH205: 1.4e-05 | AI205: 0.03417371 | AJ205: 0.0033048021
A206: 382 | B206: 11414 | C206: מבנה נדל"ן (כ.ד) בע"מ | D206: 520024126 | E206: ח.פ | F206: מבני תעשיה אגח יז | G206: IL0022604461 | H206: ISIN | I206: צמוד למדד המחירים לצרכן | J206: ישראל | K206: ישראל | L206: סחיר | M206: TASE | N206: נדל"ן מניב בישראל | O206: לא | P206: AA | Q206: S&P מעלות | R206: נייר ערך | S206: ILS | T206: 1.683 | U206: 30/06/2028 | V206: 0.037 | W206: 0.02848 | X206: החוב לא נחות | Y206: לא | Z206: 100554.62 | AA206: 1 | AB206: 118.43 | AD206: 119.087 | AG206: שווי הוגן | AH206: 0.000334 | AI206: 0.079914363 | AJ206: 0.007728197
A207: 382 | B207: 11414 | C207: עמידר | D207: 520017393 | E207: ח.פ | F207: עמידר אגח א | G207: IL0011435851 | H207: ISIN | I207: לא צמוד למדד המחירים לצרכן | J207: ישראל | K207: ישראל | L207: סחיר | M207: TASE | N207: נדל"ן מניב בישראל | O207: לא | P207: AAA | Q207: S&P מעלות | R207: נייר ערך | S207: ILS | T207: 1.705 | U207: 31/03/2028 | V207: 0.0144 | W207: 0.04646 | X207: החוב לא נחות | Y207: לא | Z207: 138486.82 | AA207: 1 | AB207: 94.81 | AD207: 131.299 | AG207: שווי הוגן | AH207: 0.000462 | AI207: 0.08810969 | AJ207: 0.0085207341
A208: 382 | B208: 11414 | C208: שיכון ובינוי בע"מ | D208: 520036104 | E208: ח.פ | F208: שיכון ובינוי אגח 6 | G208: IL0011297335 | H208: ISIN | I208: צמוד למדד המחירים לצרכן | J208: ישראל | K208: ישראל | L208: סחיר | M208: TASE | N208: בנייה | O208: לא | P208: A | Q208: S&P מעלות | R208: נייר ערך | S208: ILS | T208: 0.003 | U208: 01/04/2025 | V208: 0.0434 | W208: 0.29883 | X208: החוב לא נחות | Y208: לא | Z208: 0 | AA208: 1 | AB208: 0 | AC208: 13.642 | AD208: 13.642 | AG208: שווי הוגן | AH208: 0 | AI208: 0.0091546352 | AJ208: 0.00088530798

Sheet מניות מבכ ויהש
A1: מספר קופה/קרן/ח.פ. עבור חברת ביטוח | B1: מספר מסלול | C1: שם מנפיק | D1: מספר מנפיק | E1: סוג מספר מזהה מנפיק | F1: שם נייר ערך | G1: מספר נייר ערך | H1: סוג מספר נייר ערך | I1: מאפיין עיקרי | J1: ישראל/חו"ל | K1: מדינה לפי חשיפה כלכלית | L1: סטאטוס סחירות | M1: זירת מסחר | N1: ענף מסחר | O1: בעל עניין/צד קשור | P1: מטבע פעילות | Q1: ערך נקוב (יחידות) | R1: שער חליפין | S1: שער נייר הערך | T1: סכום לקבל (במטבע הפעילות) | U1: שווי הוגן (באלפי ש"ח) | V1: שיעור מערך נקוב מונפק | W1: שיעור מנכסי אפיק ההשקעה | X1: שיעור מסך נכסי ההשקעה
A2: 382 | B2: 382 | C2: אלביט מערכות בע"מ | D2: 520043027 | E2: ח.פ | F2: אלביט מערכות | G2: IL0010811243 | H2: ISIN | I2: מניות | J2: ישראל | K2: ישראל | L2: סחיר | M2: TASE | N2: ביטחוניות | O2: לא | P2: ILS | Q2: 7450.37 | R2: 1 | S2: 142500 | U2: 10616.777 | V2: 0.000167 | W2: 0.02599331 | X2: 0.0036721266
A3: 382 | B3: 382 | C3: אלוני-חץ נכסים והשקעות בע"מ | D3: 520038506 | E3: ח.פ | F3: אלוני חץ | G3: IL0003900136 | H3: ISIN | I3: מניות | J3: ישראל | K3: ישראל | L3: סחיר | M3: TASE | N3: נדל"ן מניב בישראל | O3: לא | P3: ILS | Q3: 267700 | R3: 1 | S3: 2900 | T3: 64.184 | U3: 7827.484 | V3: 0.001244 | W3: 0.019164216 | X3: 0.0027073669
A4: 382 | B4: 382 | C4: אמות השקעות בע"מ | D4: 520026683 | E4: ח.פ | F4: אמות | G4: IL0010972789 | H4: ISIN | I4: מניות | J4: ישראל | K4: ישראל | L4: סחיר | M4: TASE | N4: נדל"ן מניב בישראל | O4: לא | P4: ILS | Q4: 396470 | R4: 1 | S4: 1796 | U4: 7120.601 | V4: 0.000841 | W4: 0.017433538 | X4: 0.0024628707
A5: 382 | B5: 382 | C5: אנלייט אנרגיה מתחדשת בע"מ | D5: 520041146 | E5: ח.פ | F5: אנלייט אנרגיה | G5: IL0007200111 | H5: ISIN | I5: מניות | J5: ישראל | K5: ארה"ב | L5: סחיר | M5: TASE | N5: אנרגיה מתחדשת | O5: לא | P5: ILS | Q5: 138367.9 | R5: 1 | S5: 5941 | U5: 8220.437 | V5: 0.001162 | W5: 0.020126292 | X5: 0.0028432814
A6: 382 | B6: 382 | C6: אנרג'יקס אנרגיות מתחדשות בע"מ | D6: 513901371 | E6: ח.פ | F6: אנרג'יקס | G6: IL0011233553 | H6: ISIN | I6: מניות | J6: ישראל | K6: ישראל | L6: סחיר | M6: TASE | N6: אנרגיה מתחדשת | O6: לא | P6: ILS | Q6: 885500 | R6: 1 | S6: 1013 | T6: 88.461 | U6: 9058.576 | V6: 0.001611 | W6: 0.022178329 | X6: 0.0031331768
A7: 382 | B7: 382 | C7: בזק החברה הישראלית לתקשורת בע"מ | D7: 520031931 | E7: ח.פ | F7: בזק | G7: IL0002300114 | H7: ISIN | I7: מניות | J7: ישראל | K7: ישראל | L7: סחיר | M7: TASE | N7: תקשורת ומדיה | O7: לא | P7: ILS | Q7: 2201567 | R7: 1 | S7: 546.6 | U7: 12033.765 | V7: 0.000795 | W7: 0.029462555 | X7: 0.0041622338
A8: 382 | B8: 382 | C8: בית וגג יזמות ונדל"ן בע"מ | D8: 516501640 | E8: ח.פ | F8: בית וגג | G8: IL0011853624 | H8: ISIN | I8: מניות | J8: ישראל | K8: ישראל | L8: סחיר | M8: TASE | N8: בנייה | O8: לא | P8: ILS | Q8: 285800 | R8: 1 | S8: 809.9 | U8: 2314.694 | V8: 0.005194 | W8: 0.0056671212 | X8: 0.00080060549
A9: 382 | B9: 382 | C9: אחים דוניץ בע"מ | D9: 520038605 | E9: ח.פ | F9: דוניץ | G9: IL0004000100 | H9: ISIN | I9: מניות | J9: ישראל | K9: ישראל | L9: סחיר | M9: TASE | N9: בנייה | O9: לא | P9: ILS | Q9: 5776 | R9: 1 | S9: 20100 | U9: 1160.976 | V9: 0.00064 | W9: 0.0028424453 | X9: 0.00040155791
A10: 382 | B10: 382 | C10: בנק דיסקונט לישראל בע"מ | D10: 520007030 | E10: ח.פ | F10: דיסקונט | G10: IL0006912120 | H10: ISIN | I10: מניות | J10: ישראל | K10: ישראל | L10: סחיר | M10: TASE | N10: בנקים | O10: לא | P10: ILS | Q10: 1067459.8 | R10: 1 | S10: 2572 | T10: 272.577 | U10: 27727.643 | V10: 0.000863 | W10: 0.067886252 | X10: 0.009590426
A11: 382 | B11: 382 | C11: י.ח.דמרי בניה ופיתוח בע"מ | D11: 511399388 | E11: ח.פ | F11: דמרי | G11: IL0010903156 | H11: ISIN | I11: מניות | J11: ישראל | K11: ישראל | L11: סחיר | M11: TASE | N11: בנייה | O11: לא | P11: ILS | Q11: 31550 | R11: 1 | S11: 30010 | U11: 9468.155 | V11: 0.00151 | W11: 0.02318111 | X11: 0.0032748416
A12: 382 | B12: 382 | C12: הפניקס אחזקות בע"מ | D12: 520017450 | E12: ח.פ | F12: הפניקס | G12: IL0007670123 | H12: ISIN | I12: מניות | J12: ישראל | K12: ישראל | L12: סחיר | M12: TASE | N12: ביטוח | O12: לא | P12: ILS | Q12: 132998 | R12: 1 | S12: 6881 | U12: 9151.592 | V12: 0.000507 | W12: 0.022406063 | X12: 0.0031653491
A13: 382 | B13: 382 | C13: טבע תעשיות פרמצבטיות בע"מ | D13: 520013954 | E13: ח.פ | F13: טבע | G13: IL0006290147 | H13: ISIN | I13: מניות | J13: ישראל | K13: ארה"ב | L13: סחיר | M13: TASE | N13: פארמה | O13: לא | P13: ILS | Q13: 220830 | R13: 1 | S13: 5587 | U13: 12337.772 | V13: 0.000176 | W13: 0.030206863 | X13: 0.0042673836
A14: 382 | B14: 382 | C14: טרמינל איקס אונליין בע"מ | D14: 515722536 | E14: ח.פ | F14: טרמינל איקס אונליין בעמ | G14: IL0011787145 | H14: ISIN | I14: מניות | J14: ישראל | K14: ישראל | L14: סחיר | M14: TASE | N14: רשתות שיווק | O14: לא | P14: ILS | Q14: 170543 | R14: 1 | S14: 443.7 | U14: 756.699 | V14: 0.001345 | W14: 0.001852645 | X14: 0.00026172684
A15: 382 | B15: 382 | C15: ישראל קנדה (ט.ר) בעמ | D15: 520039298 | E15: ח.פ | F15: ישראל קנדה | G15: IL0004340191 | H15: ISIN | I15: מניות | J15: ישראל | K15: ישראל | L15: סחיר | M15: TASE | N15: בנייה | O15: לא | P15: ILS | Q15: 356000 | R15: 1 | S15: 1157 | U15: 4118.92 | V15: 0.001076 | W15: 0.01008445 | X15: 0.0014246504
A16: 382 | B16: 382 | C16: כלל החזקות עסקי ביטוח בע"מ | D16: 520036120 | E16: ח.פ | F16: כלל ביטוח | G16: IL0002240146 | H16: ISIN | I16: מניות | J16: ישראל | K16: ישראל | L16: סחיר | M16: TASE | N16: ביטוח | O16: לא | P16: ILS | Q16: 98550 | R16: 1 | S16: 9094 | U16: 8962.137 | V16: 0.00124 | W16: 0.021942214 | X16: 0.0030998203
A17: 382 | B17: 382 | C17: בנק לאומי לישראל בע"מ | D17: 520018078 | E17: ח.פ | F17: לאומי | G17: IL0006046119 | H17: ISIN | I17: מניות | J17: ישראל | K17: ישראל | L17: סחיר | M17: TASE | N17: בנקים | O17: לא | P17: ILS | Q17: 840606 | R17: 1 | S17: 4982 | U17: 41878.991 | V17: 0.00052 | W17: 0.10253334 | X17: 0.014485088
A18: 382 | B18: 382 | C18: י.ד. מור השקעות בע"מ | D18: 513834606 | E18: ח.פ | F18: מור השקעות | G18: IL0011414641 | H18: ISIN | I18: מניות | J18: ישראל | K18: ישראל | L18: סחיר | M18: TASE | N18: שירותים פיננסיים | O18: לא | P18: ILS | Q18: 350000 | R18: 1 | S18: 1483 | U18: 5190.5 | V18: 0.004904 | W18: 0.012708025 | X18: 0.001795288
A19: 382 | B19: 382 | C19: בנק מזרחי טפחות בע"מ | D19: 520000522 | E19: ח.פ | F19: מזרחי טפחות | G19: IL0006954379 | H19: ISIN | I19: מניות | J19: ישראל | K19: ישראל | L19: סחיר | M19: TASE | N19: בנקים | O19: לא | P19: ILS | Q19: 76569 | R19: 1 | S19: 16650 | U19: 12748.738 | V19: 0.000295 | W19: 0.031213041 | X19: 0.0044095285
A20: 382 | B20: 382 | C20: מליסרון בע"מ | D20: 520037789 | E20: ח.פ | F20: מליסרון | G20: IL0003230146 | H20: ISIN | I20: מניות | J20: ישראל | K20: ישראל | L20: סחיר | M20: TASE | N20: נדל"ן מניב בישראל | O20: לא | P20: ILS | Q20: 26850 | R20: 1 | S20: 28940 | T20: 50.733 | U20: 7821.123 | V20: 0.000564 | W20: 0.019148643 | X20: 0.002705167
A21: 382 | B21: 382 | C21: מניבים קרן הריט החדשה בע"מ | D21: 515327120 | E21: ח.פ | F21: מניבים ריט | G21: IL0011405730 | H21: ISIN | I21: מניות | J21: ישראל | K21: ישראל | L21: סחיר | M21: TASE | N21: נדל"ן מניב בישראל | O21: לא | P21: ILS | Q21: 1349479 | R21: 1 | S21: 184 | U21: 2483.041 | V21: 0.001776 | W21: 0.0060792896 | X21: 0.00085883334
A22: 382 | B22: 382 | C22: נאוויטס פטרוליום, שותפות מוגבלת | D22: 550263107 | E22: מספר שותפות | F22: נאוויטס פט יהש | G22: IL0011419699 | H22: ISIN | I22: מניות | J22: ישראל | K22: ארה"ב | L22: סחיר | M22: TASE | N22: חיפושי נפט וגז | O22: לא | P22: ILS | Q22: 85130 | R22: 1 | S22: 8700 | U22: 7406.31 | V22: 0.000835 | W22: 0.018133046 | X22: 0.0025616915
A23: 382 | B23: 382 | C23: ניו-מד אנרג'י- שותפות מוגבלת | D23: 550013098 | E23: מספר שותפות | F23: ניו-מד אנרג'י יהש | G23: IL0004750209 | H23: ISIN | I23: מניות | J23: ישראל | K23: ישראל | L23: סחיר | M23: TASE | N23: חיפושי נפט וגז | O23: לא | P23: ILS | Q23: 200000 | R23: 1 | S23: 1249 | T23: 37.842 | U23: 2535.842 | V23: 0.00017 | W23: 0.0062085628 | X23: 0.00087709602
A24: 382 | B24: 382 | C24: נייס מערכות בע"מ | D24: 520036872 | E24: ח.פ | F24: נייס | G24: IL0002730112 | H24: ISIN | I24: מניות | J24: ישראל | K24: ארה"ב | L24: סחיר | M24: TASE | N24: תוכנה ואינטרנט | O24: לא | P24: ILS | Q24: 17198 | R24: 1 | S24: 56600 | U24: 9734.068 | V24: 0.00023 | W24: 0.023832152 | X24: 0.0033668155
A25: 382 | B25: 382 | C25: נקסט ויז'ן | D25: 514259019 | E25: ח.פ | F25: נקסט ויז'ן | G25: IL0011765935 | H25: ISIN | I25: מניות | J25: ישראל | K25: ישראל | L25: סחיר | M25: TASE | N25: אלקטרוניקה ואופטיקה | O25: לא | P25: ILS | Q25: 106000 | R25: 1 | S25: 8478 | U25: 8986.68 | V25: 0.001318 | W25: 0.022002304 | X25: 0.0031083092
A26: 382 | B26: 382 | C26: קבוצת עזריאלי בע"מ (לשעבר קנית מימון) | D26: 510960719 | E26: ח.פ | F26: עזריאלי קבוצה | G26: IL0011194789 | H26: ISIN | I26: מניות | J26: ישראל | K26: ישראל | L26: סחיר | M26: TASE | N26: נדל"ן מניב בישראל | O26: לא | P26: ILS | Q26: 29250 | R26: 1 | S26: 24920 | U26: 7289.1 | V26: 0.000241 | W26: 0.017846078 | X26: 0.002521151
A27: 382 | B27: 382 | C27: בנק הפועלים בע"מ | D27: 520000118 | E27: ח.פ | F27: פועלים | G27: IL0006625771 | H27: ISIN | I27: מניות | J27: ישראל | K27: ישראל | L27: סחיר | M27: TASE | N27: בנקים | O27: לא | P27: ILS | Q27: 692368 | R27: 1 | S27: 5008 | U27: 34673.789 | V27: 0.000518 | W27: 0.084892668 | X27: 0.011992956
A28: 382 | B28: 382 | C28: פוקס-ויזל בע"מ | D28: 512157603 | E28: ח.פ | F28: פוקס- ויזל | G28: IL0010870223 | H28: ISIN | I28: מניות | J28: ישראל | K28: ישראל | L28: סחיר | M28: TASE | N28: רשתות שיווק | O28: לא | P28: ILS | Q28: 14950 | R28: 1 | S28: 30240 | U28: 4520.88 | V28: 0.00108 | W28: 0.011068579 | X28: 0.0015636801
A29: 382 | B29: 382 | C29: פורמולה מערכות (1985)בע"מ | D29: 520036690 | E29: ח.פ | F29: פורמולה מערכות | G29: IL0002560162 | H29: ISIN | I29: מניות | J29: ישראל | K29: ישראל | L29: סחיר | M29: TASE | N29: שירותי מידע | O29: לא | P29: ILS | Q29: 16800 | R29: 1 | S29: 32170 | U29: 5404.56 | V29: 0.001057 | W29: 0.013232114 | X29: 0.001869327
A30: 382 | B30: 382 | C30: קבוצת אקרשטיין בע"מ | D30: 512714494 | E30: ח.פ | F30: קבוצת אקרשטיין | G30: IL0011762056 | H30: ISIN | I30: מניות | J30: ישראל | K30: ישראל | L30: סחיר | M30: TASE | N30: מתכת ומוצרי בניה | O30: לא | P30: ILS | Q30: 612206 | R30: 1 | S30: 682.4 | T30: 106.157 | U30: 4283.851 | V30: 0.002125 | W30: 0.010488254 | X30: 0.0014816966
A31: 382 | B31: 382 | C31: שופר-סל בע"מ | D31: 520022732 | E31: ח.פ | F31: שופרסל | G31: IL0007770378 | H31: ISIN | I31: מניות | J31: ישראל | K31: ישראל | L31: סחיר | M31: TASE | N31: רשתות שיווק | O31: לא | P31: ILS | Q31: 107000 | R31: 1 | S31: 3511 | U31: 3756.77 | V31: 0.000389 | W31: 0.0091977899 | X31: 0.0012993901
A32: 382 | B32: 382 | C32: Advanced Micro Devices inc | D32: R2I72C950HOYXII45366 | E32: LEI | F32: Advanced Micro Devices | G32: US0079031078 | H32: ISIN | I32: מניות | J32: חו"ל | K32: אסיה | L32: סחיר | M32: NASDAQ | N32: Semiconductors & Semiconductor Equipment | O32: לא | P32: USD | Q32: 9225 | R32: 3.718 | S32: 10274 | U32: 3523.833 | V32: 6e-06 | W32: 0.0086274847 | X32: 0.0012188219
A33: 382 | B33: 382 | C33: ALPHABET INC | D33: 5493006MHB84DD0ZWV18 | E33: LEI | F33: ALPHABET INC-A | G33: US02079K3059 | H33: ISIN | I33: מניות | J33: חו"ל | K33: ארה"ב | L33: סחיר | M33: NASDAQ | N33: Software | O33: לא | P33: USD | Q33: 23200 | R33: 3.718 | S33: 15464 | U33: 13338.875 | V33: 4e-06 | W33: 0.032657887 | X33: 0.0046136448
A34: 382 | B34: 382 | C34: amazon.com | D34: ZXTILKJKG63JELOEG630 | E34: LEI | F34: Amazon inc | G34: US0231351067 | H34: ISIN | I34: מניות | J34: חו"ל | K34: ארה"ב | L34: סחיר | M34: NASDAQ | N34: Commercial Services & Supplies | O34: לא | P34: USD | Q34: 9950 | R34: 3.718 | S34: 19026 | U34: 7038.497 | V34: 1e-06 | W34: 0.017232522 | X34: 0.0024344727
A35: 382 | B35: 382 | C35: ASML HOLDING NV-NY | D35: 724500Y6DUVHQD6OXN27 | E35: LEI | F35: asml holding nv-ny | G35: USN070592100 | H35: ISIN | I35: מניות | J35: חו"ל | K35: ארה"ב | L35: סחיר | M35: NASDAQ | N35: Semiconductors & Semiconductor Equipment | O35: לא | P35: USD | Q35: 4677 | R35: 3.718 | S35: 66263 | U35: 11522.53 | V35: 1.2e-05 | W35: 0.028210886 | X35: 0.003985408
A36: 382 | B36: 382 | C36: Broadcom Inc | D36: 549300WV6GIDOZJTV909 | E36: LEI | F36: BROADCOM INC | G36: US11135F1012 | H36: ISIN | I36: מניות | J36: חו"ל | K36: ארה"ב | L36: סחיר | M36: NASDAQ | N36: Semiconductors & Semiconductor Equipment | O36: לא | P36: USD | Q36: 7750 | R36: 3.718 | S36: 16743 | T36: 4.572 | U36: 4841.412 | V36: 1.7e-05 | W36: 0.011853346 | X36: 0.0016745457
A37: 382 | B37: 382 | C37: קמטק בע"מ | D37: 511235434 | E37: ח.פ | F37: Camtek Ltd | G37: IL0010952641 | H37: ISIN | I37: מניות | J37: חו"ל | K37: גלובלי | L37: סחיר | M37: NASDAQ | N37: Semiconductors & Semiconductor Equipment | O37: לא | P37: USD | Q37: 28700 | R37: 3.718 | S37: 5863 | U37: 6256.208 | V37: 0.000663 | W37: 0.015317224 | X37: 0.0021638947
A38: 382 | B38: 382 | C38: COSTCO WHOLESAL | D38: 29DX7H14B9S6O3FD6V18 | E38: LEI | F38: COSTCO WHOLESALE CORP | G38: US22160K1051 | H38: ISIN | I38: מניות | J38: חו"ל | K38: ארה"ב | L38: סחיר | M38: NASDAQ | N38: Food & Staples Retailing Consumer Staples Distribution & Retail | O38: לא | P38: USD | Q38: 2180 | R38: 3.718 | S38: 94578 | U38: 7665.774 | V38: 5e-06 | W38: 0.018768298 | X38: 0.0026514348
A39: 382 | B39: 382 | C39: פייבר אינטרנשיונל בע"מ | D39: 514440874 | E39: ח.פ | F39: FIVERR INTERNATI | G39: IL0011582033 | H39: ISIN | I39: מניות | J39: חו"ל | K39: ארה"ב | L39: סחיר | M39: NYSE | N39: Commercial Services & Supplies | O39: לא | P39: USD | Q39: 3797 | R39: 3.718 | S39: 2368 | U39: 334.296 | V39: 9.8e-05 | W39: 0.00081846584 | X39: 0.0001156263
A40: 382 | B40: 382 | C40: JD.com Inc | D40: 549300HVTWB0GJZ16V92 | E40: LEI | F40: JD.COM INC-CL A | G40: KYG8208B1014 | H40: ISIN | I40: מניות | J40: חו"ל | K40: סין | L40: סחיר | M40: HKSE | N40: Textiles, Apparel & Luxury Goods | O40: לא | P40: HKD | Q40: 1964 | R40: 0.4776 | S40: 16080 | U40: 150.831 | V40: 1e-06 | W40: 0.0003692842 | X40: 5.2169514e-05
A41: 382 | B41: 382 | C41: MASTERCARD INC | D41: AR5L2ODV9HN37376R084 | E41: LEI | F41: Mastercard inc-cla | G41: US57636Q1040 | H41: ISIN | I41: מניות | J41: חו"ל | K41: ארה"ב | L41: סחיר | M41: NYSE | N41: Diversified Financial Services Financial Services | O41: לא | P41: USD | Q41: 4727 | R41: 3.718 | S41: 54812 | U41: 9633.201 | V41: 3e-06 | W41: 0.023585197 | X41: 0.0033319278
A42: 382 | B42: 382 | C42: MICROSOFT CORP | D42: INR2EJN1ERAN0W5ZP974 | E42: LEI | F42: Microsoft corp | G42: US5949181045 | H42: ISIN | I42: מניות | J42: חו"ל | K42: ארה"ב | L42: סחיר | M42: NASDAQ | N42: Software | O42: לא | P42: USD | Q42: 5540 | R42: 3.718 | S42: 37539 | U42: 7732.178 | V42: 1e-06 | W42: 0.018930877 | X42: 0.0026744026
A43: 382 | B43: 382 | C43: נובה מכשירי מדידה בע"מ | D43: 511812463 | E43: ח.פ | F43: Nova measuring inst | G43: IL0010845571 | H43: ISIN | I43: מניות | J43: חו"ל | K43: גלובלי | L43: סחיר | M43: NASDAQ | N43: מוליכים למחצה | O43: לא | P43: USD | Q43: 10228 | R43: 3.718 | S43: 18433 | U43: 7009.647 | V43: 0.000352 | W43: 0.017161886 | X43: 0.0024244938
A44: 382 | B44: 382 | C44: NVIDIA CORP | D44: 549300S4KLFTLO7GSQ80 | E44: LEI | F44: Nvidia crop | G44: US67066G1040 | H44: ISIN | I44: מניות | J44: חו"ל | K44: ארה"ב | L44: סחיר | M44: NASDAQ | N44: Semiconductors & Semiconductor Equipment | O44: לא | P44: USD | Q44: 22110 | R44: 3.718 | S44: 10838 | T44: 0.164 | U44: 8909.986 | V44: 1e-06 | W44: 0.021814532 | X44: 0.0030817824
A45: 382 | B45: 382 | C45: אורמת טכנולגיות אינק | D45: 5493000TSHHWY24VHM09 | E45: LEI | F45: Ormat Technologies | G45: US6866881021 | H45: ISIN | I45: מניות | J45: חו"ל | K45: ארה"ב | L45: סחיר | M45: NYSE | N45: Water Utilities | O45: לא | P45: USD | Q45: 41250 | R45: 3.718 | S45: 7077 | U45: 10853.818 | V45: 0.00068 | W45: 0.026573662 | X45: 0.0037541142
A46: 382 | B46: 382 | C46: Samsung Electronics co ltd | D46: 9884007ER46L6N7EI764 | E46: LEI | F46: Samsung electronics | G46: US7960508882 | H46: ISIN | I46: מניות | J46: חו"ל | K46: אסיה | L46: סחיר | M46: LSE | N46: Technology Hardware, Storage & Peripherals | O46: לא | P46: USD | Q46: 0 | R46: 3.718 | S46: 0 | T46: 0.007 | U46: 0.028 | V46: 0 | W46: 6.8089455e-08 | X46: 9.6191329e-09
A47: 382 | B47: 382 | C47: TAIWAN Semiconductor | D47: 549300KB6NK5SBD14S87 | E47: LEI | F47: Taiwan Semiconductor Adr | G47: US8740391003 | H47: ISIN | I47: מניות | J47: חו"ל | K47: טיוואן | L47: סחיר | M47: NYSE | N47: Semiconductors & Semiconductor Equipment | O47: לא | P47: USD | Q47: 11300 | R47: 3.718 | S47: 16600 | T47: 6.189 | U47: 6997.235 | V47: 2e-06 | W47: 0.017131498 | X47: 0.0024202009
A48: 382 | B48: 382 | C48: TESLA MOTORS INC | D48: 54930043XZGB27CTOV49 | E48: LEI | F48: TESLA MOTORS INC | G48: US88160R1014 | H48: ISIN | I48: מניות | J48: חו"ל | K48: ארה"ב | L48: סחיר | M48: NASDAQ | N48: Automobiles | O48: לא | P48: USD | Q48: 2800 | R48: 3.718 | S48: 25916 | U48: 2697.959 | V48: 1e-06 | W48: 0.0066054782 | X48: 0.00093316906
A49: 382 | B49: 382 | C49: VISA Inc - CLASS A | D49: 549300JZ4OKEHW3DPJ59 | E49: LEI | F49: VISA inc-class a | G49: US92826C8394 | H49: ISIN | I49: מניות | J49: חו"ל | K49: ארה"ב | L49: סחיר | M49: NYSE | N49: Diversified Financial Services Financial Services | O49: לא | P49: USD | Q49: 7940 | R49: 3.718 | S49: 35046 | U49: 10345.902 | V49: 5e-06 | W49: 0.025330118 | X49: 0.0035784363
A50: 382 | B50: 7635 | C50: אלביט מערכות בע"מ | D50: 520043027 | E50: ח.פ | F50: אלביט מערכות | G50: IL0010811243 | H50: ISIN | I50: מניות | J50: ישראל | K50: ישראל | L50: סחיר | M50: TASE | N50: ביטחוניות | O50: לא | P50: ILS | Q50: 15 | R50: 1 | S50: 142500 | U50: 21.375 | V50: 0 | W50: 0.044103142 | X50: 0.0011509364
A51: 382 | B51: 7635 | C51: אלוני-חץ נכסים והשקעות בע"מ | D51: 520038506 | E51: ח.פ | F51: אלוני חץ | G51: IL0003900136 | H51: ISIN | I51: מניות | J51: ישראל | K51: ישראל | L51: סחיר | M51: TASE | N51: נדל"ן מניב בישראל | O51: לא | P51: ILS | Q51: 440 | R51: 1 | S51: 2900 | T51: 0.097 | U51: 12.857 | V51: 2e-06 | W51: 0.026528118 | X51: 0.00069229028
A52: 382 | B52: 7635 | C52: אנלייט אנרגיה מתחדשת בע"מ | D52: 520041146 | E52: ח.פ | F52: אנלייט אנרגיה | G52: IL0007200111 | H52: ISIN | I52: מניות | J52: ישראל | K52: ארה"ב | L52: סחיר | M52: TASE | N52: אנרגיה מתחדשת | O52: לא | P52: ILS | Q52: 96.9 | R52: 1 | S52: 5941 | U52: 5.757 | V52: 1e-06 | W52: 0.011878094 | X52: 0.00030997634
A53: 382 | B53: 7635 | C53: אנרג'יקס אנרגיות מתחדשות בע"מ | D53: 513901371 | E53: ח.פ | F53: אנרג'יקס | G53: IL0011233553 | H53: ISIN | I53: מניות | J53: ישראל | K53: ישראל | L53: סחיר | M53: TASE | N53: אנרגיה מתחדשת | O53: לא | P53: ILS | Q53: 900 | R53: 1 | S53: 1013 | T53: 0.082 | U53: 9.198 | V53: 2e-06 | W53: 0.01897931 | X53: 0.00049529304
A54: 382 | B54: 7635 | C54: אחים דוניץ בע"מ | D54: 520038605 | E54: ח.פ | F54: דוניץ | G54: IL0004000100 | H54: ISIN | I54: מניות | J54: ישראל | K54: ישראל | L54: סחיר | M54: TASE | N54: בנייה | O54: לא | P54: ILS | Q54: 28 | R54: 1 | S54: 20100 | U54: 5.628 | V54: 3e-06 | W54: 0.01161228 | X54: 0.00030303954
A55: 382 | B55: 7635 | C55: בנק דיסקונט לישראל בע"מ | D55: 520007030 | E55: ח.פ | F55: דיסקונט | G55: IL0006912120 | H55: ISIN | I55: מניות | J55: ישראל | K55: ישראל | L55: סחיר | M55: TASE | N55: בנקים | O55: לא | P55: ILS | Q55: 1730 | R55: 1 | S55: 2572 | T55: 0.434 | U55: 44.929 | V55: 1e-06 | W55: 0.092702845 | X55: 0.0024192172
A56: 382 | B56: 7635 | C56: הפניקס אחזקות בע"מ | D56: 520017450 | E56: ח.פ | F56: הפניקס | G56: IL0007670123 | H56: ISIN | I56: מניות | J56: ישראל | K56: ישראל | L56: סחיר | M56: TASE | N56: ביטוח | O56: לא | P56: ILS | Q56: 340 | R56: 1 | S56: 6881 | U56: 23.395 | V56: 1e-06 | W56: 0.048271844 | X56: 0.0012597248
A57: 382 | B57: 7635 | C57: טבע תעשיות פרמצבטיות בע"מ | D57: 520013954 | E57: ח.פ | F57: טבע | G57: IL0006290147 | H57: ISIN | I57: מניות | J57: ישראל | K57: ארה"ב | L57: סחיר | M57: TASE | N57: פארמה | O57: לא | P57: ILS | Q57: 870 | R57: 1 | S57: 5587 | U57: 48.607 | V57: 1e-06 | W57: 0.10029086 | X57: 0.0026172375
A58: 382 | B58: 7635 | C58: כלל החזקות עסקי ביטוח בע"מ | D58: 520036120 | E58: ח.פ | F58: כלל ביטוח | G58: IL0002240146 | H58: ISIN | I58: מניות | J58: ישראל | K58: ישראל | L58: סחיר | M58: TASE | N58: ביטוח | O58: לא | P58: ILS | Q58: 150 | R58: 1 | S58: 9094 | U58: 13.641 | V58: 2e-06 | W58: 0.028145542 | X58: 0.00073449936
A59: 382 | B59: 7635 | C59: בנק לאומי לישראל בע"מ | D59: 520018078 | E59: ח.פ | F59: לאומי | G59: IL0006046119 | H59: ISIN | I59: מניות | J59: ישראל | K59: ישראל | L59: סחיר | M59: TASE | N59: בנקים | O59: לא | P59: ILS | Q59: 1124 | R59: 1 | S59: 4982 | U59: 55.998 | V59: 1e-06 | W59: 0.11554029 | X59: 0.0030151939
A60: 382 | B60: 7635 | C60: בנק מזרחי טפחות בע"מ | D60: 520000522 | E60: ח.פ | F60: מזרחי טפחות | G60: IL0006954379 | H60: ISIN | I60: מניות | J60: ישראל | K60: ישראל | L60: סחיר | M60: TASE | N60: בנקים | O60: לא | P60: ILS | Q60: 124 | R60: 1 | S60: 16650 | U60: 20.646 | V60: 0 | W60: 0.042598993 | X60: 0.0011116834
A61: 382 | B61: 7635 | C61: מליסרון בע"מ | D61: 520037789 | E61: ח.פ | F61: מליסרון | G61: IL0003230146 | H61: ISIN | I61: מניות | J61: ישראל | K61: ישראל | L61: סחיר | M61: TASE | N61: נדל"ן מניב בישראל | O61: לא | P61: ILS | Q61: 150 | R61: 1 | S61: 28940 | T61: 0.275 | U61: 43.685 | V61: 3e-06 | W61: 0.090135908 | X61: 0.0023522292
A62: 382 | B62: 7635 | C62: נאוויטס פטרוליום, שותפות מוגבלת | D62: 550263107 | E62: מספר שותפות | F62: נאוויטס פט יהש | G62: IL0011419699 | H62: ISIN | I62: מניות | J62: ישראל | K62: ארה"ב | L62: סחיר | M62: TASE | N62: חיפושי נפט וגז | O62: לא | P62: ILS | Q62: 275 | R62: 1 | S62: 8700 | U62: 23.925 | V62: 3e-06 | W62: 0.04936457 | X62: 0.0012882411
A63: 382 | B63: 7635 | C63: קבוצת עזריאלי בע"מ (לשעבר קנית מימון) | D63: 510960719 | E63: ח.פ | F63: עזריאלי קבוצה | G63: IL0011194789 | H63: ISIN | I63: מניות | J63: ישראל | K63: ישראל | L63: סחיר | M63: TASE | N63: נדל"ן מניב בישראל | O63: לא | P63: ILS | Q63: 70 | R63: 1 | S63: 24920 | U63: 17.444 | V63: 1e-06 | W63: 0.035992291 | X63: 0.00093927182
A64: 382 | B64: 7635 | C64: בנק הפועלים בע"מ | D64: 520000118 | E64: ח.פ | F64: פועלים | G64: IL0006625771 | H64: ISIN | I64: מניות | J64: ישראל | K64: ישראל | L64: סחיר | M64: TASE | N64: בנקים | O64: לא | P64: ILS | Q64: 905 | R64: 1 | S64: 5008 | U64: 45.322 | V64: 1e-06 | W64: 0.09351393 | X64: 0.0024403837
A65: 382 | B65: 7635 | C65: פוקס-ויזל בע"מ | D65: 512157603 | E65: ח.פ | F65: פוקס- ויזל | G65: IL0010870223 | H65: ISIN | I65: מניות | J65: ישראל | K65: ישראל | L65: סחיר | M65: TASE | N65: רשתות שיווק | O65: לא | P65: ILS | Q65: 45 | R65: 1 | S65: 30240 | U65: 13.608 | V65: 3e-06 | W65: 0.028077453 | X65: 0.00073272248
A66: 382 | B66: 7635 | C66: פורמולה מערכות (1985)בע"מ | D66: 520036690 | E66: ח.פ | F66: פורמולה מערכות | G66: IL0002560162 | H66: ISIN | I66: מניות | J66: ישראל | K66: ישראל | L66: סחיר | M66: TASE | N66: שירותי מידע | O66: לא | P66: ILS | Q66: 35 | R66: 1 | S66: 32170 | U66: 11.259 | V66: 2e-06 | W66: 0.023231782 | X66: 0.00060626754
A67: 382 | B67: 7635 | C67: קבוצת אקרשטיין בע"מ | D67: 512714494 | E67: ח.פ | F67: קבוצת אקרשטיין | G67: IL0011762056 | H67: ISIN | I67: מניות | J67: ישראל | K67: ישראל | L67: סחיר | M67: TASE | N67: מתכת ומוצרי בניה | O67: לא | P67: ILS | Q67: 1924 | R67: 1 | S67: 682.4 | T67: 0.325 | U67: 13.455 | V67: 7e-06 | W67: 0.027761429 | X67: 0.00072447537
A68: 382 | B68: 7635 | C68: שופר-סל בע"מ | D68: 520022732 | E68: ח.פ | F68: שופרסל | G68: IL0007770378 | H68: ISIN | I68: מניות | J68: ישראל | K68: ישראל | L68: סחיר | M68: TASE | N68: רשתות שיווק | O68: לא | P68: ILS | Q68: 310 | R68: 1 | S68: 3511 | U68: 10.884 | V68: 1e-06 | W68: 0.022457217 | X68: 0.00058605414
A69: 382 | B69: 7635 | C69: NVIDIA CORP | D69: 549300S4KLFTLO7GSQ80 | E69: LEI | F69: Nvidia crop | G69: US67066G1040 | H69: ISIN | I69: מניות | J69: חו"ל | K69: ארה"ב | L69: סחיר | M69: NASDAQ | N69: Semiconductors & Semiconductor Equipment | O69: לא | P69: USD | Q69: 30 | R69: 3.718 | S69: 10838 | T69: 0 | U69: 12.089 | V69: 0 | W69: 0.024943989 | X69: 0.00065095011
A70: 382 | B70: 7635 | C70: TAIWAN Semiconductor | D70: 549300KB6NK5SBD14S87 | E70: LEI | F70: Taiwan Semiconductor Adr | G70: US8740391003 | H70: ISIN | I70: מניות | J70: חו"ל | K70: טיוואן | L70: סחיר | M70: NYSE | N70: Semiconductors & Semiconductor Equipment | O70: לא | P70: USD | Q70: 50 | R70: 3.718 | S70: 16600 | T70: 0.026 | U70: 30.955 | V70: 0 | W70: 0.063870119 | X70: 0.0016667848
A71: 382 | B71: 9479 | C71: אלביט מערכות בע"מ | D71: 520043027 | E71: ח.פ | F71: אלביט מערכות | G71: IL0010811243 | H71: ISIN | I71: מניות | J71: ישראל | K71: ישראל | L71: סחיר | M71: TASE | N71: ביטחוניות | O71: לא | P71: ILS | Q71: 355 | R71: 1 | S71: 142500 | U71: 505.875 | V71: 8e-06 | W71: 0.044529679 | X71: 0.0070745175
A72: 382 | B72: 9479 | C72: אלוני-חץ נכסים והשקעות בע"מ | D72: 520038506 | E72: ח.פ | F72: אלוני חץ | G72: IL0003900136 | H72: ISIN | I72: מניות | J72: ישראל | K72: ישראל | L72: סחיר | M72: TASE | N72: נדל"ן מניב בישראל | O72: לא | P72: ILS | Q72: 9200 | R72: 1 | S72: 2900 | T72: 2.2 | U72: 269 | V72: 4.3e-05 | W72: 0.023678698 | X72: 0.0037618812
A73: 382 | B73: 9479 | C73: אמות השקעות בע"מ | D73: 520026683 | E73: ח.פ | F73: אמות | G73: IL0010972789 | H73: ISIN | I73: מניות | J73: ישראל | K73: ישראל | L73: סחיר | M73: TASE | N73: נדל"ן מניב בישראל | O73: לא | P73: ILS | Q73: 8400 | R73: 1 | S73: 1796 | U73: 150.864 | V73: 1.8e-05 | W73: 0.013279813 | X73: 0.00210979
A74: 382 | B74: 9479 | C74: אנלייט אנרגיה מתחדשת בע"מ | D74: 520041146 | E74: ח.פ | F74: אנלייט אנרגיה | G74: IL0007200111 | H74: ISIN | I74: מניות | J74: ישראל | K74: ארה"ב | L74: סחיר | M74: TASE | N74: אנרגיה מתחדשת | O74: לא | P74: ILS | Q74: 3794.1 | R74: 1 | S74: 5941 | U74: 225.407 | V74: 3.2e-05 | W74: 0.019841508 | X74: 0.0031522593
A75: 382 | B75: 9479 | C75: אנרג'יקס אנרגיות מתחדשות בע"מ | D75: 513901371 | E75: ח.פ | F75: אנרג'יקס | G75: IL0011233553 | H75: ISIN | I75: מניות | J75: ישראל | K75: ישראל | L75: סחיר | M75: TASE | N75: אנרגיה מתחדשת | O75: לא | P75: ILS | Q75: 20520 | R75: 1 | S75: 1013 | T75: 2.043 | U75: 209.911 | V75: 3.7e-05 | W75: 0.018477438 | X75: 0.0029355468
A76: 382 | B76: 9479 | C76: בזק החברה הישראלית לתקשורת בע"מ | D76: 520031931 | E76: ח.פ | F76: בזק | G76: IL0002300114 | H76: ISIN | I76: מניות | J76: ישראל | K76: ישראל | L76: סחיר | M76: TASE | N76: תקשורת ומדיה | O76: לא | P76: ILS | Q76: 69325 | R76: 1 | S76: 546.6 | U76: 378.93 | V76: 2.5e-05 | W76: 0.033355377 | X76: 0.0052992342
A77: 382 | B77: 9479 | C77: אחים דוניץ בע"מ | D77: 520038605 | E77: ח.פ | F77: דוניץ | G77: IL0004000100 | H77: ISIN | I77: מניות | J77: ישראל | K77: ישראל | L77: סחיר | M77: TASE | N77: בנייה | O77: לא | P77: ILS | Q77: 296 | R77: 1 | S77: 20100 | U77: 59.496 | V77: 3.3e-05 | W77: 0.0052371391 | X77: 0.00083203457
A78: 382 | B78: 9479 | C78: בנק דיסקונט לישראל בע"מ | D78: 520007030 | E78: ח.פ | F78: דיסקונט | G78: IL0006912120 | H78: ISIN | I78: מניות | J78: ישראל | K78: ישראל | L78: סחיר | M78: TASE | N78: בנקים | O78: לא | P78: ILS | Q78: 21834 | R78: 1 | S78: 2572 | T78: 5.572 | U78: 567.143 | V78: 1.8e-05 | W78: 0.04992279 | X78: 0.0079313315
A79: 382 | B79: 9479 | C79: י.ח.דמרי בניה ופיתוח בע"מ | D79: 511399388 | E79: ח.פ | F79: דמרי | G79: IL0010903156 | H79: ISIN | I79: מניות | J79: ישראל | K79: ישראל | L79: סחיר | M79: TASE | N79: בנייה | O79: לא | P79: ILS | Q79: 553 | R79: 1 | S79: 30010 | U79: 165.955 | V79: 2.6e-05 | W79: 0.014608226 | X79: 0.0023208375
A80: 382 | B80: 9479 | C80: הפניקס אחזקות בע"מ | D80: 520017450 | E80: ח.פ | F80: הפניקס | G80: IL0007670123 | H80: ISIN | I80: מניות | J80: ישראל | K80: ישראל | L80: סחיר | M80: TASE | N80: ביטוח | O80: לא | P80: ILS | Q80: 2895 | R80: 1 | S80: 6881 | U80: 199.205 | V80: 1.1e-05 | W80: 0.017535028 | X80: 0.0027858244
A81: 382 | B81: 9479 | C81: קבוצת חג'ג' ייזום נדל"ן בע"מ | D81: 520033309 | E81: ח.פ | F81: חג'ג' נדלן | G81: IL0008230133 | H81: ISIN | I81: מניות | J81: ישראל | K81: ישראל | L81: סחיר | M81: TASE | N81: בנייה | O81: לא | P81: ILS | Q81: 11500 | R81: 1 | S81: 1708 | U81: 196.42 | V81: 0.000185 | W81: 0.017289883 | X81: 0.0027468776
A82: 382 | B82: 9479 | C82: טבע תעשיות פרמצבטיות בע"מ | D82: 520013954 | E82: ח.פ | F82: טבע | G82: IL0006290147 | H82: ISIN | I82: מניות | J82: ישראל | K82: ארה"ב | L82: סחיר | M82: TASE | N82: פארמה | O82: לא | P82: ILS | Q82: 6905 | R82: 1 | S82: 5587 | U82: 385.782 | V82: 6e-06 | W82: 0.033958516 | X82: 0.005395056
A83: 382 | B83: 9479 | C83: טרמינל איקס אונליין בע"מ | D83: 515722536 | E83: ח.פ | F83: טרמינל איקס אונליין בעמ | G83: IL0011787145 | H83: ISIN | I83: מניות | J83: ישראל | K83: ישראל | L83: סחיר | M83: TASE | N83: רשתות שיווק | O83: לא | P83: ILS | Q83: 3750 | R83: 1 | S83: 443.7 | U83: 16.639 | V83: 3e-05 | W83: 0.001464627 | X83: 0.00023268817
A84: 382 | B84: 9479 | C84: ישראל קנדה (ט.ר) בעמ | D84: 520039298 | E84: ח.פ | F84: ישראל קנדה | G84: IL0004340191 | H84: ISIN | I84: מניות | J84: ישראל | K84: ישראל | L84: סחיר | M84: TASE | N84: בנייה | O84: לא | P84: ILS | Q84: 10800 | R84: 1 | S84: 1157 | U84: 124.956 | V84: 3.3e-05 | W84: 0.01099926 | X84: 0.001747474
A85: 382 | B85: 9479 | C85: כלל החזקות עסקי ביטוח בע"מ | D85: 520036120 | E85: ח.פ | F85: כלל ביטוח | G85: IL0002240146 | H85: ISIN | I85: מניות | J85: ישראל | K85: ישראל | L85: סחיר | M85: TASE | N85: ביטוח | O85: לא | P85: ILS | Q85: 3600 | R85: 1 | S85: 9094 | U85: 327.384 | V85: 4.5e-05 | W85: 0.028817997 | X85: 0.0045783718
A86: 382 | B86: 9479 | C86: בנק לאומי לישראל בע"מ | D86: 520018078 | E86: ח.פ | F86: לאומי | G86: IL0006046119 | H86: ISIN | I86: מניות | J86: ישראל | K86: ישראל | L86: סחיר | M86: TASE | N86: בנקים | O86: לא | P86: ILS | Q86: 17810 | R86: 1 | S86: 4982 | U86: 887.294 | V86: 1.1e-05 | W86: 0.078104128 | X86: 0.012408556
A87: 382 | B87: 9479 | C87: י.ד. מור השקעות בע"מ | D87: 513834606 | E87: ח.פ | F87: מור השקעות | G87: IL0011414641 | H87: ISIN | I87: מניות | J87: ישראל | K87: ישראל | L87: סחיר | M87: TASE | N87: שירותים פיננסיים | O87: לא | P87: ILS | Q87: 3000 | R87: 1 | S87: 1483 | U87: 44.49 | V87: 4.2e-05 | W87: 0.0039162351 | X87: 0.00062217995
A88: 382 | B88: 9479 | C88: בנק מזרחי טפחות בע"מ | D88: 520000522 | E88: ח.פ | F88: מזרחי טפחות | G88: IL0006954379 | H88: ISIN | I88: מניות | J88: ישראל | K88: ישראל | L88: סחיר | M88: TASE | N88: בנקים | O88: לא | P88: ILS | Q88: 1972 | R88: 1 | S88: 16650 | U88: 328.338 | V88: 8e-06 | W88: 0.028901973 | X88: 0.0045917132
A89: 382 | B89: 9479 | C89: מליסרון בע"מ | D89: 520037789 | E89: ח.פ | F89: מליסרון | G89: IL0003230146 | H89: ISIN | I89: מניות | J89: ישראל | K89: ישראל | L89: סחיר | M89: TASE | N89: נדל"ן מניב בישראל | O89: לא | P89: ILS | Q89: 1225 | R89: 1 | S89: 28940 | T89: 2.308 | U89: 356.823 | V89: 2.6e-05 | W89: 0.031409408 | X89: 0.0049900742
A90: 382 | B90: 9479 | C90: מניבים קרן הריט החדשה בע"מ | D90: 515327120 | E90: ח.פ | F90: מניבים ריט | G90: IL0011405730 | H90: ISIN | I90: מניות | J90: ישראל | K90: ישראל | L90: סחיר | M90: TASE | N90: נדל"ן מניב בישראל | O90: לא | P90: ILS | Q90: 23600 | R90: 1 | S90: 184 | U90: 43.424 | V90: 3.1e-05 | W90: 0.0038224003 | X90: 0.00060727224
A91: 382 | B91: 9479 | C91: נאוויטס פטרוליום, שותפות מוגבלת | D91: 550263107 | E91: מספר שותפות | F91: נאוויטס פט יהש | G91: IL0011419699 | H91: ISIN | I91: מניות | J91: ישראל | K91: ארה"ב | L91: סחיר | M91: TASE | N91: חיפושי נפט וגז | O91: לא | P91: ILS | Q91: 3993 | R91: 1 | S91: 8700 | U91: 347.391 | V91: 3.9e-05 | W91: 0.030579115 | X91: 0.004858164
A92: 382 | B92: 9479 | C92: נובה מכשירי מדידה בע"מ | D92: 511812463 | E92: ח.פ | F92: נובה | G92: IL0010845571 | H92: ISIN | I92: מניות | J92: ישראל | K92: גלובלי | L92: סחיר | M92: TASE | N92: מוליכים למחצה | O92: לא | P92: ILS | Q92: 70 | R92: 1 | S92: 68020 | U92: 47.614 | V92: 2e-06 | W92: 0.0041912253 | X92: 0.0006658682
A93: 382 | B93: 9479 | C93: ניו-מד אנרג'י- שותפות מוגבלת | D93: 550013098 | E93: מספר שותפות | F93: ניו-מד אנרג'י יהש | G93: IL0004750209 | H93: ISIN | I93: מניות | J93: ישראל | K93: ישראל | L93: סחיר | M93: TASE | N93: חיפושי נפט וגז | O93: לא | P93: ILS | Q93: 7300 | R93: 1 | S93: 1249 | T93: 1.374 | U93: 92.551 | V93: 6e-06 | W93: 0.0081468102 | X93: 0.0012942997
A94: 382 | B94: 9479 | C94: נייס מערכות בע"מ | D94: 520036872 | E94: ח.פ | F94: נייס | G94: IL0002730112 | H94: ISIN | I94: מניות | J94: ישראל | K94: ארה"ב | L94: סחיר | M94: TASE | N94: תוכנה ואינטרנט | O94: לא | P94: ILS | Q94: 543 | R94: 1 | S94: 56600 | U94: 307.338 | V94: 7e-06 | W94: 0.027053447 | X94: 0.0042980342
A95: 382 | B95: 9479 | C95: נקסט ויז'ן | D95: 514259019 | E95: ח.פ | F95: נקסט ויז'ן | G95: IL0011765935 | H95: ISIN | I95: מניות | J95: ישראל | K95: ישראל | L95: סחיר | M95: TASE | N95: אלקטרוניקה ואופטיקה | O95: לא | P95: ILS | Q95: 4500 | R95: 1 | S95: 8478 | U95: 381.51 | V95: 5.6e-05 | W95: 0.033582442 | X95: 0.0053353084
A96: 382 | B96: 9479 | C96: קבוצת עזריאלי בע"מ (לשעבר קנית מימון) | D96: 510960719 | E96: ח.פ | F96: עזריאלי קבוצה | G96: IL0011194789 | H96: ISIN | I96: מניות | J96: ישראל | K96: ישראל | L96: סחיר | M96: TASE | N96: נדל"ן מניב בישראל | O96: לא | P96: ILS | Q96: 665 | R96: 1 | S96: 24920 | U96: 165.718 | V96: 5e-06 | W96: 0.014587337 | X96: 0.0023175189
A97: 382 | B97: 9479 | C97: בנק הפועלים בע"מ | D97: 520000118 | E97: ח.פ | F97: פועלים | G97: IL0006625771 | H97: ISIN | I97: מניות | J97: ישראל | K97: ישראל | L97: סחיר | M97: TASE | N97: בנקים | O97: לא | P97: ILS | Q97: 18238 | R97: 1 | S97: 5008 | U97: 913.359 | V97: 1.4e-05 | W97: 0.080398487 | X97: 0.012773065
A98: 382 | B98: 9479 | C98: פוקס-ויזל בע"מ | D98: 512157603 | E98: ח.פ | F98: פוקס- ויזל | G98: IL0010870223 | H98: ISIN | I98: מניות | J98: ישראל | K98: ישראל | L98: סחיר | M98: TASE | N98: רשתות שיווק | O98: לא | P98: ILS | Q98: 387 | R98: 1 | S98: 30240 | U98: 117.029 | V98: 2.8e-05 | W98: 0.010301467 | X98: 0.0016366144
A99: 382 | B99: 9479 | C99: פורמולה מערכות (1985)בע"מ | D99: 520036690 | E99: ח.פ | F99: פורמולה מערכות | G99: IL0002560162 | H99: ISIN | I99: מניות | J99: ישראל | K99: ישראל | L99: סחיר | M99: TASE | N99: שירותי מידע | O99: לא | P99: ILS | Q99: 355 | R99: 1 | S99: 32170 | U99: 114.204 | V99: 2.2e-05 | W99: 0.01005277 | X99: 0.0015971033
A100: 382 | B100: 9479 | C100: קבוצת אקרשטיין בע"מ | D100: 512714494 | E100: ח.פ | F100: קבוצת אקרשטיין | G100: IL0011762056 | H100: ISIN | I100: מניות | J100: ישראל | K100: ישראל | L100: סחיר | M100: TASE | N100: מתכת ומוצרי בניה | O100: לא | P100: ILS | Q100: 30610 | R100: 1 | S100: 682.4 | T100: 5.305 | U100: 214.187 | V100: 0.000106 | W100: 0.018853847 | X100: 0.0029953477
...

Sheet קרנות סל
A1: מספר קופה/קרן/ח.פ. עבור חברת ביטוח | B1: מספר מסלול | C1: שם מנפיק | D1: מספר מנפיק | E1: סוג מספר מזהה מנפיק | F1: שם נייר ערך | G1: מספר נייר ערך | H1: סוג מספר נייר ערך | I1: מאפיין עיקרי | J1: ישראל/חו"ל | K1: מדינה לפי חשיפה כלכלית | L1: זירת מסחר | M1: סיווג הקרן | N1: בעל עניין/צד קשור | O1: מטבע פעילות | P1: ערך נקוב (יחידות) | Q1: שער חליפין | R1: שער נייר הערך | S1: סכום לקבל (במטבע הפעילות) | T1: שווי הוגן (באלפי ש"ח) | U1: שיעור מערך נקוב מונפק | V1: שיעור מנכסי אפיק ההשקעה | W1: שיעור מסך נכסי ההשקעה
A2: 382 | B2: 382 | C2: מגדל קרנות נאמנות בע"מ | D2: 511303661 | E2: ח.פ | F2: MTF סל Nasdaq 100 (4D) | G2: IL0011813875 | H2: ISIN | I2: עוקב אחר מדדי מניות בחו"ל | J2: ישראל | K2: ארה"ב | L2: TASE | M2: מניות בחו"ל חשופות מט"ח | N2: לא | O2: ILS | P2: 92333.33 | Q2: 1 | R2: 9860 | T2: 9104.066 | U2: 0.009233 | V2: 0.010832848 | W2: 0.0031489108
A3: 382 | B3: 382 | C3: מגדל קרנות נאמנות בע"מ | D3: 511303661 | E3: ח.פ | F3: MTF סל תא 125 | G3: IL0011502833 | H3: ISIN | I3: עוקב אחר מדדי מניות בישראל | J3: ישראל | K3: ישראל | L3: TASE | M3: מניות בישראל | N3: לא | O3: ILS | P3: 789763 | Q3: 1 | R3: 3763 | T3: 29718.782 | U3: 0.009291 | V3: 0.035362115 | W3: 0.01027912
A4: 382 | B4: 382 | C4: מגדל קרנות נאמנות בע"מ | D4: 511303661 | E4: ח.פ | F4: MTF סל תא 90 | G4: IL0011502593 | H4: ISIN | I4: עוקב אחר מדדי מניות בישראל | J4: ישראל | K4: ישראל | L4: TASE | M4: מניות בישראל | N4: לא | O4: ILS | P4: 625000 | Q4: 1 | R4: 3593 | T4: 22456.25 | U4: 0.010417 | V4: 0.026720493 | W4: 0.0077671587
A5: 382 | B5: 382 | C5: הראל קרנות נאמנות בע"מ | D5: 511776783 | E5: ח.פ | F5: הראל סל תא 90 | G5: IL0011489312 | H5: ISIN | I5: עוקב אחר מדדי מניות בישראל | J5: ישראל | K5: ישראל | L5: TASE | M5: מניות בישראל | N5: לא | O5: ILS | P5: 398500 | Q5: 1 | R5: 2395 | T5: 9544.075 | U5: 0.001593 | V5: 0.01135641 | W5: 0.0033011008
A6: 382 | B6: 382 | C6: הראל קרנות נאמנות בע"מ | D6: 511776783 | E6: ח.פ | F6: הראל סל תל בונד שקלי | G6: IL0011505232 | H6: ISIN | I6: עוקב אחר מדדים אחרים בישראל | J6: ישראל | K6: ישראל | L6: TASE | M6: אג"ח בישראל - חברות והמרה | N6: לא | O6: ILS | P6: 7220000 | Q6: 1 | R6: 404.49 | T6: 29204.178 | U6: 0.026452 | V6: 0.034749793 | W6: 0.010101129
A7: 382 | B7: 382 | C7: הראל קרנות נאמנות בע"מ | D7: 511776783 | E7: ח.פ | F7: הראל קרן סל תא 125 | G7: IL0011488991 | H7: ISIN | I7: עוקב אחר מדדי מניות בישראל | J7: ישראל | K7: ישראל | L7: TASE | M7: מניות בישראל | N7: לא | O7: ILS | P7: 477000 | Q7: 1 | R7: 2397 | T7: 11433.69 | U7: 0.00231 | V7: 0.013604847 | W7: 0.0039546801
A8: 382 | B8: 382 | C8: מור ניהול קרנות נאמנות בע"מ | D8: 514884485 | E8: ח.פ | F8: מור סל (A4) ת"א -125 | G8: IL0011961534 | H8: ISIN | I8: עוקב אחר מדדי מניות בישראל | J8: ישראל | K8: ישראל | L8: TASE | M8: מניות בישראל | N8: לא | O8: ILS | P8: 411000 | Q8: 1 | R8: 6632 | T8: 27257.52 | U8: 0.03288 | V8: 0.032433482 | W8: 0.00942782
A9: 382 | B9: 382 | C9: קסם קרנות נאמנות בע"מ | D9: 510938608 | E9: ח.פ | F9: קסם 50 EURO PR STOXX | G9: IL0011464067 | H9: ISIN | I9: עוקב אחר מדדי מניות בחו"ל | J9: ישראל | K9: אירופה | L9: TASE | M9: מניות בחו"ל חשופות מט"ח | N9: לא | O9: ILS | P9: 40000 | Q9: 1 | R9: 22720 | T9: 9088 | U9: 0.014795 | V9: 0.010813731 | W9: 0.0031433538
A10: 382 | B10: 382 | C10: קסם קרנות נאמנות בע"מ | D10: 510938608 | E10: ח.פ | F10: קסם S&P 500 (4D) ETF | G10: IL0011464711 | H10: ISIN | I10: עוקב אחר מדדי מניות בחו"ל | J10: ישראל | K10: ארה"ב | L10: TASE | M10: מניות בחו"ל חשופות מט"ח | N10: לא | O10: ILS | P10: 221380 | Q10: 1 | R10: 22550 | T10: 49921.19 | U10: 0.007541 | V10: 0.059400782 | W10: 0.017266721
A11: 382 | B11: 382 | C11: קסם קרנות נאמנות בע"מ | D11: 510938608 | E11: ח.פ | F11: קסם קרן סל תא 125 | G11: IL0011463564 | H11: ISIN | I11: עוקב אחר מדדי מניות בישראל | J11: ישראל | K11: ישראל | L11: TASE | M11: מניות בישראל | N11: לא | O11: ILS | P11: 42250 | Q11: 1 | R11: 23890 | T11: 10093.525 | U11: 0.001193 | V11: 0.012010196 | W11: 0.0034911443
A12: 382 | B12: 382 | C12: קסם קרנות נאמנות בע"מ | D12: 510938608 | E12: ח.פ | F12: קסם תא 90 | G12: IL0011463317 | H12: ISIN | I12: עוקב אחר מדדי מניות בישראל | J12: ישראל | K12: ישראל | L12: TASE | M12: מניות בישראל | N12: לא | O12: ILS | P12: 61012 | Q12: 1 | R12: 22890 | T12: 13965.647 | U12: 0.002019 | V12: 0.0166176 | W12: 0.0048304323
A13: 382 | B13: 382 | C13: קסם קרנות נאמנות בע"מ | D13: 510938608 | E13: ח.פ | F13: קסם תא נדלן | G13: IL0011465478 | H13: ISIN | I13: עוקב אחר מדדי מניות בישראל | J13: ישראל | K13: ישראל | L13: TASE | M13: מניות בישראל | N13: לא | O13: ILS | P13: 105000 | Q13: 1 | R13: 9440 | T13: 9912 | U13: 0.011467 | V13: 0.011794201 | W13: 0.0034283586
... A17: 382 | B17: 382 | C17: BlackRock Asset Managment | D17: 254900UWHMJRRODS3Z64 | E17: LEI | F17: CEF ishares russell | G17: US4642876555 | H17: ISIN | I17: עוקב אחר מדדי מניות בחו"ל | J17: חו"ל | K17: ארה"ב | L17: NYSE | M17: Equity Funds | N17: לא | O17: USD | P17: 18600 | Q17: 3.718 | R17: 19949 | T17: 13795.691 | U17: 6.5e-05 | V17: 0.016415371 | W17: 0.004771648
A18: 382 | B18: 382 | C18: State Street Corp | D18: 07F5H7W3ET8ZLWNMFP29 | E18: LEI | F18: Financial sel sector spdr | G18: US81369Y6059 | H18: ISIN | I18: עוקב אחר מדדי מניות בחו"ל | J18: חו"ל | K18: ארה"ב | L18: NYSE | M18: Equity Funds | N18: לא | O18: USD | P18: 45500 | Q18: 3.718 | R18: 4981 | S18: 0 | T18: 8426.307 | U18: 5.1e-05 | V18: 0.010026388 | W18: 0.0029144877
A19: 382 | B19: 382 | C19: HSBC Holdings PLC | D19: MLU0ZO3ML4LN2LL2TL39 | E19: LEI | F19: HANG SENG | G19: HK2828013055 | H19: ISIN | I19: עוקב אחר מדדי מניות בחו"ל | J19: חו"ל | K19: סין | L19: HKSE | M19: Equity Funds | N19: לא | O19: HKD | P19: 99000 | Q19: 0.4776 | R19: 8700 | T19: 4113.569 | U19: 0.000209 | V19: 0.0048946991 | W19: 0.0014227995
A20: 382 | B20: 382 | C20: Invesco investment management limited | D20: ECPGFXU8A2SHKVVGJI15 | E20: LEI | F20: INVESCO S&P 500 EQUITY | G20: IE00B3YCGJ38 | H20: ISIN | I20: עוקב אחר מדדי מניות בחו"ל | J20: חו"ל | K20: ארה"ב | L20: LSE | M20: Equity Funds | N20: לא | O20: USD | P20: 1415 | Q20: 3.718 | R20: 109783 | T20: 5775.651 | U20: 6.5e-05 | V20: 0.0068723957 | W20: 0.0019976797
A21: 382 | B21: 382 | C21: BlackRock Asset Managment | D21: 254900UWHMJRRODS3Z64 | E21: LEI | F21: ISH $ CORP BD $A | G21: IE00BYXYYJ35 | H21: ISIN | I21: עוקב אחר מדדים אחרים בחו"ל | J21: חו"ל | K21: גלובלי | L21: LSE | M21: Bond/Fixed Income Funds | N21: לא | O21: USD | P21: 792600 | Q21: 3.718 | R21: 597.45 | T21: 17606.175 | U21: 0.002338 | V21: 0.020949432 | W21: 0.0060896168
A22: 382 | B22: 382 | C22: BlackRock Asset Managment | D22: 254900UWHMJRRODS3Z64 | E22: LEI | F22: ISH CORE ERSTX50 | G22: DE0005933956 | H22: ISIN | I22: עוקב אחר מדדי מניות בחו"ל | J22: חו"ל | K22: אירופה | L22: FWB | M22: Equity Funds | N22: לא | O22: EUR | P22: 204900 | Q22: 4.0219 | R22: 5318 | T22: 43824.963 | U22: 0.001443 | V22: 0.052146936 | W22: 0.015158161
A23: 382 | B23: 382 | C23: BlackRock Asset Managment | D23: 254900UWHMJRRODS3Z64 | E23: LEI | F23: ISH S&P US BANKS | G23: IE00BD3V0B10 | H23: ISIN | I23: עוקב אחר מדדי מניות בחו"ל | J23: חו"ל | K23: ארה"ב | L23: NYSE | M23: Equity Funds | N23: לא | O23: USD | P23: 570320 | Q23: 3.718 | R23: 601.75 | T23: 12759.806 | U23: 0 | V23: 0.015182781 | W23: 0.0044133567
A24: 382 | B24: 382 | C24: BlackRock Asset Managment | D24: 254900UWHMJRRODS3Z64 | E24: LEI | F24: ISH S&P500 | G24: IE00B4LN9N13 | H24: ISIN | I24: עוקב אחר מדדי מניות בחו"ל | J24: חו"ל | K24: ארה"ב | L24: LSE | M24: Equity Funds | N24: לא | O24: USD | P24: 323390 | Q24: 3.718 | R24: 1088.834 | T24: 13091.754 | U24: 0.009859 | V24: 0.015577763 | W24: 0.0045281707
A25: 382 | B25: 382 | C25: BlackRock Asset Managment | D25: 254900UWHMJRRODS3Z64 | E25: LEI | F25: Ishares $ Short Duration Corp Bond | G25: IE00BYXYYP94 | H25: ISIN | I25: עוקב אחר מדדים אחרים בחו"ל | J25: חו"ל | K25: ארה"ב | L25: LSE | M25: Bond/Fixed Income Funds | N25: לא | O25: USD | P25: 260000 | Q25: 3.718 | R25: 605.15 | T25: 5849.864 | U25: 0 | V25: 0.0069607015 | W25: 0.0020233486
A26: 382 | B26: 382 | C26: BlackRock Asset Managment | D26: 254900UWHMJRRODS3Z64 | E26: LEI | F26: Ishares dax | G26: DE0005933931 | H26: ISIN | I26: עוקב אחר מדדי מניות בחו"ל | J26: חו"ל | K26: גלובלי | L26: FWB | M26: Equity Funds | N26: לא | O26: EUR | P26: 21860 | Q26: 4.0219 | R26: 18554 | T26: 16312.442 | U26: 0.000512 | V26: 0.01941003 | W26: 0.0056421408
A27: 382 | B27: 382 | C27: BlackRock Asset Managment | D27: 254900UWHMJRRODS3Z64 | E27: LEI | F27: Ishares DJ construction | G27: US4642887529 | H27: ISIN | I27: עוקב אחר מדדי מניות בחו"ל | J27: חו"ל | K27: ארה"ב | L27: NYSE | M27: Equity Funds | N27: לא | O27: USD | P27: 31500 | Q27: 3.718 | R27: 9521 | T27: 11150.71 | U27: 0.00123 | V27: 0.013268131 | W27: 0.0038568029
A28: 382 | B28: 382 | C28: BlackRock Asset Managment | D28: 254900UWHMJRRODS3Z64 | E28: LEI | F28: ISHARES NASDAQ100 ETF USD | G28: IE00B53SZB19 | H28: ISIN | I28: עוקב אחר מדדי מניות בחו"ל | J28: חו"ל | K28: ארה"ב | L28: LSE | M28: Equity Funds | N28: לא | O28: USD | P28: 2600 | Q28: 3.718 | R28: 108968 | T28: 10533.719 | U28: 0.000245 | V28: 0.012533979 | W28: 0.0036433983
A29: 382 | B29: 382 | C29: LYXOR ETF | D29: 213800VZW861M5FHMD50 | E29: LEI | F29: LYXETF S&P500 | G29: LU1135865084 | H29: ISIN | I29: עוקב אחר מדדי מניות בחו"ל | J29: חו"ל | K29: ארה"ב | L29: LSE | M29: Equity Funds | N29: לא | O29: USD | P29: 38611 | Q29: 3.718 | R29: 39730 | T29: 57034.679 | U29: 0.004352 | V29: 0.06786506 | W29: 0.019727132
A30: 382 | B30: 382 | C30: Nomura asset management | D30: 549300LNIUIPKJOPIK90 | E30: LEI | F30: NOMURA ETF | G30: JP3027630007 | H30: ISIN | I30: עוקב אחר מדדי מניות בחו"ל | J30: חו"ל | K30: יפן | L30: JPX | M30: Equity Funds | N30: לא | O30: JPY | P30: 234300 | Q30: 2.4893 | R30: 2824 | T30: 16470.782 | U30: 2.9e-05 | V30: 0.019598438 | W30: 0.0056969074
... A39: 382 | B39: 382 | C39: Vanguard Group | D39: 549300Y88GQ3VLJIBX57 | E39: LEI | F39: VANG FTSE EM $A | G39: IE00BK5BR733 | H39: ISIN | I39: עוקב אחר מדדי מניות בחו"ל | J39: חו"ל | K39: שווקים מתעוררים | L39: LSE | M39: Equity Funds | N39: לא | O39: USD | P39: 41790 | Q39: 3.718 | R39: 6449 | T39: 10020.148 | U39: 0 | V39: 0.011922885 | W39: 0.0034657647
A40: 382 | B40: 382 | C40: Vanguard Group | D40: 549300Y88GQ3VLJIBX57 | E40: LEI | F40: Vanguard S&P 500 etf | G40: US9229083632 | H40: ISIN | I40: עוקב אחר מדדי מניות בחו"ל | J40: חו"ל | K40: ארה"ב | L40: NYSE | M40: Equity Funds | N40: לא | O40: USD | P40: 20012 | Q40: 3.718 | R40: 51391 | S40: 36.264 | T40: 38372.105 | U40: 2.3e-05 | V40: 0.045658628 | W40: 0.013272128
A41: 382 | B41: 382 | C41: WisdomTree Europe ltd | D41: 213800B789JS6Y4H8936 | E41: LEI | F41: Wisdomtree Japan | G41: US97717W8516 | H41: ISIN | I41: עוקב אחר מדדי מניות בחו"ל | J41: חו"ל | K41: יפן | L41: NYSE | M41: Equity Funds | N41: לא | O41: USD | P41: 18400 | Q41: 3.718 | R41: 11018 | T41: 7537.546 | U41: 0.000583 | V41: 0.0089688593 | W41: 0.0026070834
A42: 382 | B42: 382 | C42: WisdomTree Europe ltd | D42: 213800B789JS6Y4H8936 | E42: LEI | F42: WSDMTR JP USD H | G42: IE00BYQCZD50 | H42: ISIN | I42: עוקב אחר מדדי מניות בחו"ל | J42: חו"ל | K42: ארה"ב | L42: LSE | M42: Equity Funds | N42: לא | O42: USD | P42: 77000 | Q42: 3.718 | R42: 4283 | T42: 12261.629 | U42: 0 | V42: 0.014590004 | W42: 0.0042410474
A43: 382 | B43: 1404 | C43: הראל קרנות נאמנות בע"מ | D43: 511776783 | E43: ח.פ | F43: הראל סל תל בונד שקלי | G43: IL0011505232 | H43: ISIN | I43: עוקב אחר מדדים אחרים בישראל | J43: ישראל | K43: ישראל | L43: TASE | M43: אג"ח בישראל - חברות והמרה | N43: לא | O43: ILS | P43: 48000 | Q43: 1 | R43: 404.49 | T43: 194.155 | U43: 0.000176 | V43: 0.22564964 | W43: 0.0072620228
A44: 382 | B44: 1404 | C44: BlackRock Asset Managment | D44: 254900UWHMJRRODS3Z64 | E44: LEI | F44: ISH $ CORP BD $A | G44: IE00BYXYYJ35 | H44: ISIN | I44: עוקב אחר מדדים אחרים בחו"ל | J44: חו"ל | K44: גלובלי | L44: LSE | M44: Bond/Fixed Income Funds | N44: לא | O44: USD | P44: 13300 | Q44: 3.718 | R44: 597.45 | T44: 295.435 | U44: 3.9e-05 | V44: 0.34335883 | W44: 0.011050226
A45: 382 | B45: 1404 | C45: State Street Corp | D45: 07F5H7W3ET8ZLWNMFP29 | E45: LEI | F45: SPDR SASB US CORP | G45: IE00BLF7VX27 | H45: ISIN | I45: עוקב אחר מדדים אחרים בחו"ל | J45: חו"ל | K45: ארה"ב | L45: LSE | M45: Bond/Fixed Income Funds | N45: לא | O45: USD | P45: 1850 | Q45: 3.718 | R45: 2882 | T45: 198.233 | U45: 7e-06 | V45: 0.23038846 | W45: 0.0074145307
A46: 382 | B46: 1404 | C46: Vanguard Group | D46: 549300Y88GQ3VLJIBX57 | E46: LEI | F46: VANG $CORPBD $A | G46: IE00BGYWFK87 | H46: ISIN | I46: עוקב אחר מדדים אחרים בחו"ל | J46: חו"ל | K46: ארה"ב | L46: LSE | M46: Bond/Fixed Income Funds | N46: לא | O46: USD | P46: 800 | Q46: 3.718 | R46: 5803 | T46: 172.604 | U46: 0 | V46: 0.20060307 | W46: 0.0064559554
A47: 382 | B47: 7635 | C47: מגדל קרנות נאמנות בע"מ | D47: 511303661 | E47: ח.פ | F47: MTF סל תא 125 | G47: IL0011502833 | H47: ISIN | I47: עוקב אחר מדדי מניות בישראל | J47: ישראל | K47: ישראל | L47: TASE | M47: מניות בישראל | N47: לא | O47: ILS | P47: 2267 | Q47: 1 | R47: 3763 | T47: 85.307 | U47: 2.7e-05 | V47: 0.011913743 | W47: 0.004593365
A48: 382 | B48: 7635 | C48: מגדל קרנות נאמנות בע"מ | D48: 511303661 | E48: ח.פ | F48: MTF סל תא 90 | G48: IL0011502593 | H48: ISIN | I48: עוקב אחר מדדי מניות בישראל | J48: ישראל | K48: ישראל | L48: TASE | M48: מניות בישראל | N48: לא | O48: ILS | P48: 1380 | Q48: 1 | R48: 3593 | T48: 49.583 | U48: 2.3e-05 | V48: 0.0069246655 | W48: 0.0026698171
A49: 382 | B49: 7635 | C49: הראל קרנות נאמנות בע"מ | D49: 511776783 | E49: ח.פ | F49: הראל סל 4DMSCI AC World | G49: IL0011493355 | H49: ISIN | I49: עוקב אחר מדדי מניות בחו"ל | J49: ישראל | K49: שווקים מתעוררים | L49: TASE | M49: מניות בחו"ל חשופות מט"ח | N49: לא | O49: ILS | P49: 12900 | Q49: 1 | R49: 3482 | T49: 449.178 | U49: 0.000612 | V49: 0.062730821 | W49: 0.02418598
A50: 382 | B50: 7635 | C50: הראל קרנות נאמנות בע"מ | D50: 511776783 | E50: ח.פ | F50: הראל סל תל בונד שקלי | G50: IL0011505232 | H50: ISIN | I50: עוקב אחר מדדים אחרים בישראל | J50: ישראל | K50: ישראל | L50: TASE | M50: אג"ח בישראל - חברות והמרה | N50: לא | O50: ILS | P50: 113000 | Q50: 1 | R50: 404.49 | T50: 457.074 | U50: 0.000414 | V50: 0.063833511 | W50: 0.024611124
A51: 382 | B51: 7635 | C51: מור ניהול קרנות נאמנות בע"מ | D51: 514884485 | E51: ח.פ | F51: מור סל (A4) ת"א -125 | G51: IL0011961534 | H51: ISIN | I51: עוקב אחר מדדי מניות בישראל | J51: ישראל | K51: ישראל | L51: TASE | M51: מניות בישראל | N51: לא | O51: ILS | P51: 2200 | Q51: 1 | R51: 6632 | T51: 145.904 | U51: 0.000176 | V51: 0.020376505 | W51: 0.0078561979
A52: 382 | B52: 7635 | C52: קסם קרנות נאמנות בע"מ | D52: 510938608 | E52: ח.פ | F52: קסם 500 P&S PR מנוטרלת מטבע | G52: IL0011466047 | H52: ISIN | I52: עוקב אחר מדדי מניות בחו"ל | J52: ישראל | K52: ארה"ב | L52: TASE | M52: מניות בחו"ל משולבת | N52: לא | O52: ILS | P52: 3300 | Q52: 1 | R52: 5283 | T52: 174.339 | U52: 4.7e-05 | V52: 0.02434765 | W52: 0.0093872798
... A61: 382 | B61: 7635 | C61: Amundi Asset Management | D61: 213800VZW861M5FHMD50 | E61: LEI | F61: AMUNDI S&P 500 | G61: LU1681049018 | H61: ISIN | I61: עוקב אחר מדדי מניות בחו"ל | J61: חו"ל | K61: ארה"ב | L61: EURONEXT | M61: Equity Funds | N61: לא | O61: USD | P61: 449 | Q61: 3.718 | R61: 10928.02 | T61: 182.43 | U61: 1e-05 | V61: 0.02547767 | W61: 0.009822961
A62: 382 | B62: 7635 | C62: State Street Corp | D62: 07F5H7W3ET8ZLWNMFP29 | E62: LEI | F62: Financial sel sector spdr | G62: US81369Y6059 | H62: ISIN | I62: עוקב אחר מדדי מניות בחו"ל | J62: חו"ל | K62: ארה"ב | L62: NYSE | M62: Equity Funds | N62: לא | O62: USD | P62: 250 | Q62: 3.718 | R62: 4981 | S62: 0 | T62: 46.298 | U62: 0 | V62: 0.0064658866 | W62: 0.0024929341
A63: 382 | B63: 7635 | C63: Invesco investment management limited | D63: ECPGFXU8A2SHKVVGJI15 | E63: LEI | F63: Invesco QQQ trust NAS1 | G63: US46090E1038 | H63: ISIN | I63: עוקב אחר מדדי מניות בחו"ל | J63: חו"ל | K63: ארה"ב | L63: NASDAQ | M63: Equity Funds | N63: לא | O63: USD | P63: 143 | Q63: 3.718 | R63: 46892 | S63: 0.075 | T63: 249.592 | U63: 0 | V63: 0.034857245 | W63: 0.013439273
A64: 382 | B64: 7635 | C64: Invesco investment management limited | D64: ECPGFXU8A2SHKVVGJI15 | E64: LEI | F64: INVESCO S&P 500 EQUITY | G64: IE00B3YCGJ38 | H64: ISIN | I64: עוקב אחר מדדי מניות בחו"ל | J64: חו"ל | K64: ארה"ב | L64: LSE | M64: Equity Funds | N64: לא | O64: USD | P64: 113 | Q64: 3.718 | R64: 109783 | T64: 461.236 | U64: 5e-06 | V64: 0.064414764 | W64: 0.024835227
A65: 382 | B65: 7635 | C65: Invesco investment management limited | D65: ECPGFXU8A2SHKVVGJI15 | E65: LEI | F65: INVESCO S&P 500 UCITS ETF | G65: IE00B3YCGJ38 | H65: ISIN | I65: עוקב אחר מדדי מניות בחו"ל | J65: חו"ל | K65: ארה"ב | L65: LSE | M65: Equity Funds | N65: לא | O65: ILS | P65: 17 | Q65: 1 | R65: 407500 | T65: 69.275 | U65: 1e-06 | V65: 0.0096747339 | W65: 0.0037301109
A66: 382 | B66: 7635 | C66: BlackRock Asset Managment | D66: 254900UWHMJRRODS3Z64 | E66: LEI | F66: ISH $ CORP BD $A | G66: IE00BYXYYJ35 | H66: ISIN | I66: עוקב אחר מדדים אחרים בחו"ל | J66: חו"ל | K66: גלובלי | L66: LSE | M66: Bond/Fixed Income Funds | N66: לא | O66: USD | P66: 34780 | Q66: 3.718 | R66: 597.45 | T66: 772.575 | U66: 0.000103 | V66: 0.10789542 | W66: 0.041599273
A67: 382 | B67: 7635 | C67: BlackRock Asset Managment | D67: 254900UWHMJRRODS3Z64 | E67: LEI | F67: ISH CORE ERSTX50 | G67: DE0005933956 | H67: ISIN | I67: עוקב אחר מדדי מניות בחו"ל | J67: חו"ל | K67: אירופה | L67: FWB | M67: Equity Funds | N67: לא | O67: EUR | P67: 360 | Q67: 4.0219 | R67: 5318 | T67: 76.998 | U67: 3e-06 | V67: 0.01075337 | W67: 0.0041459811
A68: 382 | B68: 7635 | C68: BlackRock Asset Managment | D68: 254900UWHMJRRODS3Z64 | E68: LEI | F68: ISH S&P US BANKS | G68: IE00BD3V0B10 | H68: ISIN | I68: עוקב אחר מדדי מניות בחו"ל | J68: חו"ל | K68: ארה"ב | L68: NYSE | M68: Equity Funds | N68: לא | O68: USD | P68: 1725 | Q68: 3.718 | R68: 601.75 | T68: 38.594 | U68: 0 | V68: 0.005389855 | W68: 0.0020780682
A69: 382 | B69: 7635 | C69: BlackRock Asset Managment | D69: 254900UWHMJRRODS3Z64 | E69: LEI | F69: ISH S&P500 | G69: IE00B4LN9N13 | H69: ISIN | I69: עוקב אחר מדדי מניות בחו"ל | J69: חו"ל | K69: ארה"ב | L69: LSE | M69: Equity Funds | N69: לא | O69: USD | P69: 980 | Q69: 3.718 | R69: 1088.834 | T69: 39.673 | U69: 3e-05 | V69: 0.0055406387 | W69: 0.0021362031
A70: 382 | B70: 7635 | C70: BlackRock Asset Managment | D70: 254900UWHMJRRODS3Z64 | E70: LEI | F70: Ishares $ Short Duration Corp Bond | G70: IE00BYXYYP94 | H70: ISIN | I70: עוקב אחר מדדים אחרים בחו"ל | J70: חו"ל | K70: ארה"ב | L70: LSE | M70: Bond/Fixed Income Funds | N70: לא | O70: USD | P70: 3525 | Q70: 3.718 | R70: 605.15 | T70: 79.311 | U70: 0 | V70: 0.011076283 | W70: 0.0042704806
A71: 382 | B71: 7635 | C71: BlackRock Asset Managment | D71: 254900UWHMJRRODS3Z64 | E71: LEI | F71: Ishares core s&p 500 etf | G71: US4642872000 | H71: ISIN | I71: עוקב אחר מדדי מניות בחו"ל | J71: חו"ל | K71: ארה"ב | L71: NYSE | M71: Equity Funds | N71: לא | O71: USD | P71: 87 | Q71: 3.718 | R71: 56190 | T71: 181.756 | U71: 0 | V71: 0.025383422 | W71: 0.0097866236
A72: 382 | B72: 7635 | C72: BlackRock Asset Managment | D72: 254900UWHMJRRODS3Z64 | E72: LEI | F72: Ishares DJ construction | G72: US4642887529 | H72: ISIN | I72: עוקב אחר מדדי מניות בחו"ל | J72: חו"ל | K72: ארה"ב | L72: NYSE | M72: Equity Funds | N72: לא | O72: USD | P72: 160 | Q72: 3.718 | R72: 9521 | T72: 56.639 | U72: 6e-06 | V72: 0.0079099626 | W72: 0.0030497002
A73: 382 | B73: 7635 | C73: Nomura asset management | D73: 549300LNIUIPKJOPIK90 | E73: LEI | F73: NOMURA ETF | G73: JP3027630007 | H73: ISIN | I73: עוקב אחר מדדי מניות בחו"ל | J73: חו"ל | K73: יפן | L73: JPX | M73: Equity Funds | N73: לא | O73: JPY | P73: 330 | Q73: 2.4893 | R73: 2824 | T73: 23.198 | U73: 0 | V73: 0.0032398012 | W73: 0.0012491112
A74: 382 | B74: 7635 | C74: State Street Corp | D74: 07F5H7W3ET8ZLWNMFP29 | E74: LEI | F74: SPDR BLOOMBERG SASB | G74: IE0004TYCC17 | H74: ISIN | I74: עוקב אחר מדדים אחרים בחו"ל | J74: חו"ל | K74: ארה"ב | L74: EUREX | M74: Bond/Fixed Income Funds | N74: לא | O74: USD | P74: 780 | Q74: 3.718 | R74: 1086.2 | T74: 31.5 | U74: 4.8e-05 | V74: 0.0043992261 | W74: 0.0016961295
A75: 382 | B75: 7635 | C75: State Street Corp | D75: 07F5H7W3ET8ZLWNMFP29 | E75: LEI | F75: SPDR PORT SP 500 | G75: US78464A8541 | H75: ISIN | I75: עוקב אחר מדדי מניות בחו"ל | J75: חו"ל | K75: ארה"ב | L75: NYSE | M75: Equity Funds | N75: לא | O75: USD | P75: 1090 | Q75: 3.718 | R75: 6576 | T75: 266.5 | U75: 4e-06 | V75: 0.037218613 | W75: 0.014349703
... A79: 382 | B79: 7635 | C79: Vanguard Group | D79: 549300Y88GQ3VLJIBX57 | E79: LEI | F79: VANG FTSE EM $A | G79: IE00BK5BR733 | H79: ISIN | I79: עוקב אחר מדדי מניות בחו"ל | J79: חו"ל | K79: שווקים מתעוררים | L79: LSE | M79: Equity Funds | N79: לא | O79: USD | P79: 17 | Q79: 3.718 | R79: 6449 | T79: 4.076 | U79: 0 | V79: 0.00056926329 | W79: 0.00021948048
A80: 382 | B80: 7635 | C80: Vanguard Group | D80: 549300Y88GQ3VLJIBX57 | E80: LEI | F80: Vanguard S&P 500 etf | G80: US9229083632 | H80: ISIN | I80: עוקב אחר מדדי מניות בחו"ל | J80: חו"ל | K80: ארה"ב | L80: NYSE | M80: Equity Funds | N80: לא | O80: USD | P80: 163 | Q80: 3.718 | R80: 51391 | S80: 0.295 | T80: 312.545 | U80: 0 | V80: 0.043649092 | W80: 0.016828985
A81: 382 | B81: 9479 | C81: מגדל קרנות נאמנות בע"מ | D81: 511303661 | E81: ח.פ | F81: MTF סל תא 125 | G81: IL0011502833 | H81: ISIN | I81: עוקב אחר מדדי מניות בישראל | J81: ישראל | K81: ישראל | L81: TASE | M81: מניות בישראל | N81: לא | O81: ILS | P81: 45670 | Q81: 1 | R81: 3763 | T81: 1718.562 | U81: 0.000537 | V81: 0.037554804 | W81: 0.0240336
A82: 382 | B82: 9479 | C82: מגדל קרנות נאמנות בע"מ | D82: 511303661 | E82: ח.פ | F82: MTF סל תא 90 | G82: IL0011502593 | H82: ISIN | I82: עוקב אחר מדדי מניות בישראל | J82: ישראל | K82: ישראל | L82: TASE | M82: מניות בישראל | N82: לא | O82: ILS | P82: 51500 | Q82: 1 | R82: 3593 | T82: 1850.395 | U82: 0.000858 | V82: 0.040435677 | W82: 0.025877246
A83: 382 | B83: 9479 | C83: הראל קרנות נאמנות בע"מ | D83: 511776783 | E83: ח.פ | F83: הראל סל 4A S&P 500 מנוטרלת | G83: IL0011491375 | H83: ISIN | I83: עוקב אחר מדדי מניות בחו"ל | J83: ישראל | K83: ארה"ב | L83: TASE | M83: מניות בחו"ל משולבת | N83: לא | O83: ILS | P83: 12000 | Q83: 1 | R83: 5366 | T83: 643.92 | U83: 9.9e-05 | V83: 0.014071234 | W83: 0.0090050374
A84: 382 | B84: 9479 | C84: הראל קרנות נאמנות בע"מ | D84: 511776783 | E84: ח.פ | F84: הראל סל תא 90 | G84: IL0011489312 | H84: ISIN | I84: עוקב אחר מדדי מניות בישראל | J84: ישראל | K84: ישראל | L84: TASE | M84: מניות בישראל | N84: לא | O84: ILS | P84: 87520 | Q84: 1 | R84: 2395 | T84: 2096.104 | U84: 0.00035 | V84: 0.045805022 | W84: 0.029313416
A85: 382 | B85: 9479 | C85: הראל קרנות נאמנות בע"מ | D85: 511776783 | E85: ח.פ | F85: הראל קרן סל תא 125 | G85: IL0011488991 | H85: ISIN | I85: עוקב אחר מדדי מניות בישראל | J85: ישראל | K85: ישראל | L85: TASE | M85: מניות בישראל | N85: לא | O85: ILS | P85: 91100 | Q85: 1 | R85: 2397 | T85: 2183.667 | U85: 0.000441 | V85: 0.047718489 | W85: 0.03053796
A86: 382 | B86: 9479 | C86: מור ניהול קרנות נאמנות בע"מ | D86: 514884485 | E86: ח.פ | F86: מור סל (A4) ת"א -125 | G86: IL0011961534 | H86: ISIN | I86: עוקב אחר מדדי מניות בישראל | J86: ישראל | K86: ישראל | L86: TASE | M86: מניות בישראל | N86: לא | O86: ILS | P86: 14200 | Q86: 1 | R86: 6632 | T86: 941.744 | U86: 0.001136 | V86: 0.02057942 | W86: 0.013170021
A87: 382 | B87: 9479 | C87: מור ניהול קרנות נאמנות בע"מ | D87: 514884485 | E87: ח.פ | F87: מור סל )4A(י NASDAQ 100 מנוטרל | G87: IL0011658445 | H87: ISIN | I87: עוקב אחר מדדי מניות בחו"ל | J87: ישראל | K87: ארה"ב | L87: TASE | M87: מניות בחו"ל משולבת | N87: לא | O87: ILS | P87: 22300 | Q87: 1 | R87: 8917 | T87: 1988.491 | U87: 0.001677 | V87: 0.043453414 | W87: 0.027808479
A88: 382 | B88: 9479 | C88: קסם קרנות נאמנות בע"מ | D88: 510938608 | E88: ח.פ | F88: קסם 500 P&S PR מנוטרלת מטבע | G88: IL0011466047 | H88: ISIN | I88: עוקב אחר מדדי מניות בחו"ל | J88: ישראל | K88: ארה"ב | L88: TASE | M88: מניות בחו"ל משולבת | N88: לא | O88: ILS | P88: 38300 | Q88: 1 | R88: 5283 | T88: 2023.389 | U88: 0.00055 | V88: 0.044216021 | W88: 0.028296518
A89: 382 | B89: 9479 | C89: קסם קרנות נאמנות בע"מ | D89: 510938608 | E89: ח.פ | F89: קסם S&P 500 (4D) ETF | G89: IL0011464711 | H89: ISIN | I89: עוקב אחר מדדי מניות בחו"ל | J89: ישראל | K89: ארה"ב | L89: TASE | M89: מניות בחו"ל חשופות מט"ח | N89: לא | O89: ILS | P89: 10400 | Q89: 1 | R89: 22550 | T89: 2345.2 | U89: 0.000354 | V89: 0.051248382 | W89: 0.032796952
A90: 382 | B90: 9479 | C90: קסם קרנות נאמנות בע"מ | D90: 510938608 | E90: ח.פ | F90: קסם קרן סל תא 125 | G90: IL0011463564 | H90: ISIN | I90: עוקב אחר מדדי מניות בישראל | J90: ישראל | K90: ישראל | L90: TASE | M90: מניות בישראל | N90: לא | O90: ILS | P90: 3224 | Q90: 1 | R90: 23890 | T90: 770.214 | U90: 9.1e-05 | V90: 0.016831059 | W90: 0.010771217
A91: 382 | B91: 9479 | C91: קסם קרנות נאמנות בע"מ | D91: 510938608 | E91: ח.פ | F91: קסם תא 90 | G91: IL0011463317 | H91: ISIN | I91: עוקב אחר מדדי מניות בישראל | J91: ישראל | K91: ישראל | L91: TASE | M91: מניות בישראל | N91: לא | O91: ILS | P91: 2928 | Q91: 1 | R91: 22890 | T91: 670.219 | U91: 9.7e-05 | V91: 0.014645936 | W91: 0.0093728242
A92: 382 | B92: 9479 | C92: קסם קרנות נאמנות בע"מ | D92: 510938608 | E92: ח.פ | F92: קסם תא נדלן | G92: IL0011465478 | H92: ISIN | I92: עוקב אחר מדדי מניות בישראל | J92: ישראל | K92: ישראל | L92: TASE | M92: מניות בישראל | N92: לא | O92: ILS | P92: 8680 | Q92: 1 | R92: 9440 | T92: 819.392 | U92: 0.000948 | V92: 0.017905728 | W92: 0.011458963
... A97: 382 | B97: 9479 | C97: BlackRock Asset Managment | D97: 254900UWHMJRRODS3Z64 | E97: LEI | F97: CEF ishares russell | G97: US4642876555 | H97: ISIN | I97: עוקב אחר מדדי מניות בחו"ל | J97: חו"ל | K97: ארה"ב | L97: NYSE | M97: Equity Funds | N97: לא | O97: USD | P97: 450 | Q97: 3.718 | R97: 19949 | T97: 333.767 | U97: 2e-06 | V97: 0.0072936228 | W97: 0.0046676323
A98: 382 | B98: 9479 | C98: State Street Corp | D98: 07F5H7W3ET8ZLWNMFP29 | E98: LEI | F98: Financial sel sector spdr | G98: US81369Y6059 | H98: ISIN | I98: עוקב אחר מדדי מניות בחו"ל | J98: חו"ל | K98: ארה"ב | L98: NYSE | M98: Equity Funds | N98: לא | O98: USD | P98: 1990 | Q98: 3.718 | R98: 4981 | S98: 0 | T98: 368.535 | U98: 2e-06 | V98: 0.0080533993 | W98: 0.0051538594
A99: 382 | B99: 9479 | C99: Global X Management Co LLc | D99: 213800R3E823B1UBIA81 | E99: LEI | F99: Global X Cybersecurity | G99: US37954Y3844 | H99: ISIN | I99: עוקב אחר מדדי מניות בחו"ל | J99: חו"ל | K99: גלובלי | L99: NASDAQ | M99: Equity Funds | N99: לא | O99: USD | P99: 1120 | Q99: 3.718 | R99: 3234 | T99: 134.669 | U99: 2.6e-05 | V99: 0.0029428471 | W99: 0.0018833066
A100: 382 | B100: 9479 | C100: Invesco investment management limited | D100: ECPGFXU8A2SHKVVGJI15 | E100: LEI | F100: Invesco QQQ trust NAS1 | G100: US46090E1038 | H100: ISIN | I100: עוקב אחר מדדי מניות בחו"ל | J100: חו"ל | K100: ארה"ב | L100: NASDAQ | M100: Equity Funds | N100: לא | O100: USD | P100: 484 | Q100: 3.718 | R100: 46892 | S100: 0.258 | T100: 844.787 | U100: 1e-06 | V100: 0.018460673 | W100: 0.011814106
A101: 382 | B101: 9479 | C101: Invesco investment management limited | D101: ECPGFXU8A2SHKVVGJI15 | E101: LEI | F101: INVESCO S&P 500 EQUITY | G101: IE00B3YCGJ38 | H101: ISIN | I101: עוקב אחר מדדי מניות בחו"ל | J101: חו"ל | K101: ארה"ב | L101: LSE | M101: Equity Funds | N101: לא | O101: USD | P101: 910 | Q101: 3.718 | R101: 109783 | T101: 3714.376 | U101: 4.2e-05 | V101: 0.081168243 | W101: 0.051944489
A102: 382 | B102: 9479 | C102: BlackRock Asset Managment | D102: 254900UWHMJRRODS3Z64 | E102: LEI | F102: ISH CORE ERSTX50 | G102: DE0005933956 | H102: ISIN | I102: עוקב אחר מדדי מניות בחו"ל | J102: חו"ל | K102: אירופה | L102: FWB | M102: Equity Funds | N102: לא | O102: EUR | P102: 10900 | Q102: 4.0219 | R102: 5318 | T102: 2331.343 | U102: 7.7e-05 | V102: 0.050945564 | W102: 0.032603161
A103: 382 | B103: 9479 | C103: BlackRock Asset Managment | D103: 254900UWHMJRRODS3Z64 | E103: LEI | F103: ISH S&P US BANKS | G103: IE00BD3V0B10 | H103: ISIN | I103: עוקב אחר מדדי מניות בחו"ל | J103: חו"ל | K103: ארה"ב | L103: NYSE | M103: Equity Funds | N103: לא | O103: USD | P103: 23590 | Q103: 3.718 | R103: 601.75 | T103: 527.781 | U103: 0 | V103: 0.011533303 | W103: 0.0073808611
A104: 382 | B104: 9479 | C104: BlackRock Asset Managment | D104: 254900UWHMJRRODS3Z64 | E104: LEI | F104: ISH S&P500 | G104: IE00B4LN9N13 | H104: ISIN | I104: עוקב אחר מדדי מניות בחו"ל | J104: חו"ל | K104: ארה"ב | L104: LSE | M104: Equity Funds | N104: לא | O104: USD | P104: 13370 | Q104: 3.718 | R104: 1088.834 | T104: 541.256 | U104: 0.000408 | V104: 0.011827772 | W104: 0.0075693096
A105: 382 | B105: 9479 | C105: BlackRock Asset Managment | D105: 254900UWHMJRRODS3Z64 | E105: LEI | F105: Ishares core s&p 500 etf | G105: US4642872000 | H105: ISIN | I105: עוקב אחר מדדי מניות בחו"ל | J105: חו"ל | K105: ארה"ב | L105: NYSE | M105: Equity Funds | N105: לא | O105: USD | P105: 607 | Q105: 3.718 | R105: 56190 | T105: 1268.111 | U105: 1e-06 | V105: 0.027711331 | W105: 0.017734164
A106: 382 | B106: 9479 | C106: BlackRock Asset Managment | D106: 254900UWHMJRRODS3Z64 | E106: LEI | F106: Ishares DJ construction | G106: US4642887529 | H106: ISIN | I106: עוקב אחר מדדי מניות בחו"ל | J106: חו"ל | K106: ארה"ב | L106: NYSE | M106: Equity Funds | N106: לא | O106: USD | P106: 610 | Q106: 3.718 | R106: 9521 | T106: 215.934 | U106: 2.4e-05 | V106: 0.0047186966 | W106: 0.0030197806
A107: 382 | B107: 9479 | C107: BlackRock Asset Managment | D107: 254900UWHMJRRODS3Z64 | E107: LEI | F107: Ishares Msci Asia ex Japn | G107: US4642881829 | H107: ISIN | I107: עוקב אחר מדדי מניות בחו"ל | J107: חו"ל | K107: יפן | L107: NASDAQ | M107: Equity Funds | N107: לא | O107: USD | P107: 300 | Q107: 3.718 | R107: 7400 | T107: 82.54 | U107: 6e-06 | V107: 0.0018036931 | W107: 0.0011542927
A108: 382 | B108: 9479 | C108: BlackRock Asset Managment | D108: 254900UWHMJRRODS3Z64 | E108: LEI | F108: ISHARES NASDAQ100 ETF USD | G108: IE00B53SZB19 | H108: ISIN | I108: עוקב אחר מדדי מניות בחו"ל | J108: חו"ל | K108: ארה"ב | L108: LSE | M108: Equity Funds | N108: לא | O108: USD | P108: 38 | Q108: 3.718 | R108: 108968 | T108: 153.954 | U108: 4e-06 | V108: 0.0033642808 | W108: 0.0021530076
A109: 382 | B109: 9479 | C109: KRANESHARES | D109: 549300VLDRC0RUX0E553 | E109: LEI | F109: KraneShares Csi China Internet Etf | G109: US5007673065 | H109: ISIN | I109: עוקב אחר מדדי מניות בחו"ל | J109: חו"ל | K109: סין | L109: NYSE | M109: Equity Funds | N109: לא | O109: USD | P109: 2400 | Q109: 3.718 | R109: 3491 | T109: 311.509 | U109: 1e-05 | V109: 0.0068072351 | W109: 0.0043563632
A110: 382 | B110: 9479 | C110: LYXOR ETF | D110: 213800VZW861M5FHMD50 | E110: LEI | F110: LYX CORE EURSTX | G110: LU0908500753 | H110: ISIN | I110: עוקב אחר מדדי מניות בחו"ל | J110: חו"ל | K110: אירופה | L110: EURONEXT | M110: Equity Funds | N110: לא | O110: EUR | P110: 1430 | Q110: 4.0219 | R110: 25113 | T110: 1444.328 | U110: 4.2e-05 | V110: 0.031562121 | W110: 0.020198518
A111: 382 | B111: 9479 | C111: LYXOR ETF | D111: 213800VZW861M5FHMD50 | E111: LEI | F111: LYXETF S&P500 | G111: LU1135865084 | H111: ISIN | I111: עוקב אחר מדדי מניות בחו"ל | J111: חו"ל | K111: ארה"ב | L111: LSE | M111: Equity Funds | N111: לא | O111: USD | P111: 1317 | Q111: 3.718 | R111: 39730 | T111: 1945.422 | U111: 0.000148 | V111: 0.042512241 | W111: 0.027206165
A112: 382 | B112: 9479 | C112: Nomura asset management | D112: 549300LNIUIPKJOPIK90 | E112: LEI | F112: NOMURA ETF | G112: JP3027630007 | H112: ISIN | I112: עוקב אחר מדדי מניות בחו"ל | J112: חו"ל | K112: יפן | L112: JPX | M112: Equity Funds | N112: לא | O112: JPY | P112: 1510 | Q112: 2.4893 | R112: 2824 | T112: 106.15 | U112: 0 | V112: 0.0023196323 | W112: 0.0014844736
... A118: 382 | B118: 9479 | C118: Vanguard Group | D118: 549300Y88GQ3VLJIBX57 | E118: LEI | F118: VANG FTSE EM $A | G118: IE00BK5BR733 | H118: ISIN | I118: עוקב אחר מדדי מניות בחו"ל | J118: חו"ל | K118: שווקים מתעוררים | L118: LSE | M118: Equity Funds | N118: לא | O118: USD | P118: 228 | Q118: 3.718 | R118: 6449 | T118: 54.668 | U118: 0 | V118: 0.0011946395 | W118: 0.0007645224
A119: 382 | B119: 9479 | C119: Vanguard Group | D119: 549300Y88GQ3VLJIBX57 | E119: LEI | F119: Vanguard S&P 500 etf | G119: US9229083632 | H119: ISIN | I119: עוקב אחר מדדי מניות בחו"ל | J119: חו"ל | K119: ארה"ב | L119: NYSE | M119: Equity Funds | N119: לא | O119: USD | P119: 768 | Q119: 3.718 | R119: 51391 | S119: 1.392 | T119: 1472.605 | U119: 1e-06 | V119: 0.032180043 | W119: 0.020593964
A120: 382 | B120: 9479 | C120: WisdomTree Europe ltd | D120: 213800B789JS6Y4H8936 | E120: LEI | F120: Wisdomtree Japan | G120: US97717W8516 | H120: ISIN | I120: עוקב אחר מדדי מניות בחו"ל | J120: חו"ל | K120: יפן | L120: NYSE | M120: Equity Funds | N120: לא | O120: USD | P120: 2180 | Q120: 3.718 | R120: 11018 | T120: 893.035 | U120: 6.9e-05 | V120: 0.019515016 | W120: 0.012488844
A121: 382 | B121: 9479 | C121: WisdomTree Europe ltd | D121: 213800B789JS6Y4H8936 | E121: LEI | F121: WSDMTR JP USD H | G121: IE00BYQCZD50 | H121: ISIN | I121: עוקב אחר מדדי מניות בחו"ל | J121: חו"ל | K121: ארה"ב | L121: LSE | M121: Equity Funds | N121: לא | O121: USD | P121: 2600 | Q121: 3.718 | R121: 4283 | T121: 414.029 | U121: 0 | V121: 0.0090475518 | W121: 0.005790078
A122: 382 | B122: 11414 | C122: הראל קרנות נאמנות בע"מ | D122: 511776783 | E122: ח.פ | F122: הראל סל NDX 100 | G122: IL0011490385 | H122: ISIN | I122: עוקב אחר מדדי מניות בחו"ל | J122: ישראל | K122: ארה"ב | L122: TASE | M122: מניות בחו"ל חשופות מט"ח | N122: לא | O122: ILS | P122: 7255 | Q122: 1 | R122: 7512 | T122: 544.996 | U122: 7.3e-05 | V122: 0.21336396 | W122: 0.035367749
A123: 382 | B123: 11414 | C123: הראל קרנות נאמנות בע"מ | D123: 511776783 | E123: ח.פ | F123: הראל סל SP500 | G123: IL0011490203 | H123: ISIN | I123: עוקב אחר מדדי מניות בחו"ל | J123: ישראל | K123: ארה"ב | L123: TASE | M123: מניות בחו"ל חשופות מט"ח | N123: לא | O123: ILS | P123: 41470 | Q123: 1 | R123: 2404 | T123: 996.939 | U123: 0.000109 | V123: 0.39029822 | W123: 0.064696818
A124: 382 | B124: 11414 | C124: הראל קרנות נאמנות בע"מ | D124: 511776783 | E124: ח.פ | F124: הראל סל גרמניה DAX 30 | G124: IL0011490534 | H124: ISIN | I124: עוקב אחר מדדי מניות בחו"ל | J124: ישראל | K124: גרמניה | L124: TASE | M124: מניות בחו"ל חשופות מט"ח | N124: לא | O124: ILS | P124: 2951 | Q124: 1 | R124: 8172 | T124: 241.156 | U124: 0.000201 | V124: 0.094411662 | W124: 0.015649915
A125: 382 | B125: 11414 | C125: קסם קרנות נאמנות בע"מ | D125: 510938608 | E125: ח.פ | F125: קסם S&P 500 (4D) ETF | G125: IL0011464711 | H125: ISIN | I125: עוקב אחר מדדי מניות בחו"ל | J125: ישראל | K125: ארה"ב | L125: TASE | M125: מניות בחו"ל חשופות מט"ח | N125: לא | O125: ILS | P125: 3420 | Q125: 1 | R125: 22550 | T125: 771.21 | U125: 0.000117 | V125: 0.30192615 | W125: 0.05004804
A126: 382 | B126: 15404 | C126: מגדל קרנות נאמנות בע"מ | D126: 511303661 | E126: ח.פ | F126: MTF סל (S&P 500 (4D | G126: IL0011503336 | H126: ISIN | I126: עוקב אחר מדדי מניות בחו"ל | J126: ישראל | K126: ארה"ב | L126: TASE | M126: מניות בחו"ל חשופות מט"ח | N126: לא | O126: ILS | P126: 23460 | Q126: 1 | R126: 8809 | T126: 2066.591 | U126: 0.000269 | V126: 0.1259729 | W126: 0.12397312
A127: 382 | B127: 15404 | C127: BlackRock Asset Managment | D127: 254900UWHMJRRODS3Z64 | E127: LEI | F127: איישרס חוץ S&P500 INDEX | G127: IE00B5BMR087 | H127: ISIN | I127: עוקב אחר מדדי מניות בחו"ל | J127: ישראל | K127: ארה"ב | L127: TASE | M127: מניות בחו"ל חשופות מט"ח | N127: לא | O127: ILS | P127: 926 | Q127: 1 | R127: 219130 | T127: 2029.144 | U127: 0.000348 | V127: 0.12369022 | W127: 0.12172667
A128: 382 | B128: 15404 | C128: הראל קרנות נאמנות בע"מ | D128: 511776783 | E128: ח.פ | F128: הראל סל SP500 | G128: IL0011490203 | H128: ISIN | I128: עוקב אחר מדדי מניות בחו"ל | J128: ישראל | K128: ארה"ב | L128: TASE | M128: מניות בחו"ל חשופות מט"ח | N128: לא | O128: ILS | P128: 86008 | Q128: 1 | R128: 2404 | T128: 2067.632 | U128: 0.000227 | V128: 0.12603636 | W128: 0.12403557
A129: 382 | B129: 15404 | C129: ילין לפידות ניהול קרנות נאמנות | D129: 513846808 | E129: ח.פ | F129: י.ל סל S&P | G129: IL0012016569 | H129: ISIN | I129: עוקב אחר מדדי מניות בחו"ל | J129: ישראל | K129: ארה"ב | L129: TASE | M129: מניות בחו"ל חשופות מט"ח | N129: לא | O129: ILS | P129: 35901 | Q129: 1 | R129: 5763 | T129: 2068.975 | U129: 0.003264 | V129: 0.12611818 | W129: 0.12411609
A130: 382 | B130: 15404 | C130: מור ניהול קרנות נאמנות בע"מ | D130: 514884485 | E130: ח.פ | F130: מור סל )4D(י S&P 500 | G130: IL0011658106 | H130: ISIN | I130: עוקב אחר מדדי מניות בחו"ל | J130: ישראל | K130: ארה"ב | L130: TASE | M130: מניות בחו"ל חשופות מט"ח | N130: לא | O130: ILS | P130: 20330 | Q130: 1 | R130: 10210 | T130: 2075.693 | U130: 0.000297 | V130: 0.12652771 | W130: 0.12451912
A131: 382 | B131: 15404 | C131: קסם קרנות נאמנות בע"מ | D131: 510938608 | E131: ח.פ | F131: קסם S&P 500 (4D) ETF | G131: IL0011464711 | H131: ISIN | I131: עוקב אחר מדדי מניות בחו"ל | J131: ישראל | K131: ארה"ב | L131: TASE | M131: מניות בחו"ל חשופות מט"ח | N131: לא | O131: ILS | P131: 9159 | Q131: 1 | R131: 22550 | T131: 2065.354 | U131: 0.000312 | V131: 0.12589751 | W131: 0.12389892
...

Sheet קרנות נאמנות
A1: מספר קופה/קרן/ח.פ. עבור חברת ביטוח | B1: מספר מסלול | C1: שם מנפיק | D1: מספר מנפיק | E1: סוג מספר מזהה מנפיק | F1: שם נייר ערך | G1: מספר נייר ערך | H1: סוג מספר נייר ערך | I1: מאפיין עיקרי | J1: ישראל/חו"ל | K1: מדינה לפי חשיפה כלכלית | L1: סטאטוס סחירות | M1: זירת מסחר | N1: סיווג הקרן | O1: בעל עניין/צד קשור | P1: מטבע פעילות | Q1: ערך נקוב (יחידות) | R1: שער חליפין | S1: שער נייר הערך | T1: שווי הוגן (באלפי ש"ח) | U1: שיעור מערך נקוב מונפק | V1: שיעור מנכסי אפיק ההשקעה | W1: שיעור מסך נכסי ההשקעה
A2: 382 | B2: 382 | C2: Nomura asset management | D2: 549300LNIUIPKJOPIK90 | E2: LEI | F2: NOMURA-US HIGH YLD BD-I USD | G2: IE00B3RW8498 | H2: ISIN | I2: אג"ח קונצרני | J2: חו"ל | K2: ארה"ב | L2: סחיר | M2: אחר | N2: Bond/Fixed Income Funds | O2: לא | P2: USD | Q2: 16550 | R2: 3.718 | S2: 40351.97 | T2: 24829.737 | U2: 0.003281 | V2: 0.23242559 | W2: 0.0085880995
A3: 382 | B3: 382 | C3: אי בי אי ניהול קרנות נאמנות בע"מ | D3: 510791031 | E3: ח.פ | F3: איביאי טכנולגיית עילית | G3: IL0011425381 | H3: ISIN | I3: מניות | J3: ישראל | K3: ישראל | L3: סחיר | M3: TASE | N3: מניות בישראל | O3: כן | P3: ILS | Q3: 7395360 | R3: 1 | S3: 69.4 | T3: 5132.38 | U3: 0.023883 | V3: 0.048043054 | W3: 0.0017751855
A4: 382 | B4: 382 | C4: APS Fund SICAV - APS China A S | D4: 549300045D2ZRM2NYN79 | E4: LEI | F4: $APS-CHINA A S-F | G4: LU1987754873 | H4: ISIN | I4: מניות | J4: חו"ל | K4: סין | L4: סחיר | M4: אחר | N4: Equity Funds | O4: לא | P4: USD | Q4: 25762.48 | R4: 3.718 | S4: 13550 | T4: 12978.854 | U4: 0.153476 | V4: 0.12149214 | W4: 0.0044891208
A5: 382 | B5: 382 | C5: CIFC Senior Secured Corporate | D5: 3912000TN89ESDWHS93 | E5: LEI | F5: CIFC SEN.SEC.COR | G5: KYG2139S1194 | H5: ISIN | I5: אג"ח קונצרני | J5: חו"ל | K5: ארה"ב | L5: סחיר | M5: אחר | N5: Bond/Fixed Income Funds | O5: לא | P5: USD | Q5: 4539.28 | R5: 3.718 | S5: 170087.17 | T5: 28705.685 | U5: 0 | V5: 0.26870746 | W5: 0.0099287107
A6: 382 | B6: 382 | C6: Fidelity Fund Management | D6: 549300JFYFTF85QAQR28 | E6: LEI | F6: FIDELITY US HIGH | G6: LU0891474172 | H6: ISIN | I6: אג"ח קונצרני | J6: חו"ל | K6: ארה"ב | L6: סחיר | M6: אחר | N6: Bond/Fixed Income Funds | O6: לא | P6: USD | Q6: 378000 | R6: 3.718 | S6: 1740 | T6: 24454.03 | U6: 2.9e-05 | V6: 0.22890867 | W6: 0.0084581499
A7: 382 | B7: 382 | C7: Invesco investment management limited | D7: ECPGFXU8A2SHKVVGJI15 | E7: LEI | F7: INV-US SEN-G | G7: LU0564079282 | H7: ISIN | I7: אג"ח קונצרני | J7: חו"ל | K7: גלובלי | L7: סחיר | M7: אחר | N7: Bond/Fixed Income Funds | O7: לא | P7: USD | Q7: 15450 | R7: 3.718 | S7: 18676 | T7: 10728.073 | U7: 0.001695 | V7: 0.10042308 | W7: 0.0037106217
A8: 382 | B8: 7635 | C8: Nomura asset management | D8: 549300LNIUIPKJOPIK90 | E8: LEI | F8: NOMURA-US HIGH YLD BD-I USD | G8: IE00B3RW8498 | H8: ISIN | I8: אג"ח קונצרני | J8: חו"ל | K8: ארה"ב | L8: סחיר | M8: אחר | N8: Bond/Fixed Income Funds | O8: לא | P8: USD | Q8: 35 | R8: 3.718 | S8: 40351.97 | T8: 52.51 | U8: 7e-06 | V8: 0.31585407 | W8: 0.0028274009
A9: 382 | B9: 7635 | C9: CIFC Senior Secured Corporate | D9: 3912000TN89ESDWHS93 | E9: LEI | F9: CIFC SEN.SEC.COR | G9: KYG2139S1194 | H9: ISIN | I9: אג"ח קונצרני | J9: חו"ל | K9: ארה"ב | L9: סחיר | M9: אחר | N9: Bond/Fixed Income Funds | O9: לא | P9: USD | Q9: 9.29 | R9: 3.718 | S9: 170087.17 | T9: 58.748 | U9: 0 | V9: 0.35337918 | W9: 0.0031633108
A10: 382 | B10: 7635 | C10: Fidelity Fund Management | D10: 549300JFYFTF85QAQR28 | E10: LEI | F10: FIDELITY US HIGH | G10: LU0891474172 | H10: ISIN | I10: אג"ח קונצרני | J10: חו"ל | K10: ארה"ב | L10: סחיר | M10: אחר | N10: Bond/Fixed Income Funds | O10: לא | P10: USD | Q10: 850 | R10: 3.718 | S10: 1740 | T10: 54.989 | U10: 0 | V10: 0.33076676 | W10: 0.0029608934

Sheet כתבי אופציה
A1: מספר קופה/קרן/ח.פ. עבור חברת ביטוח | B1: מספר מסלול | C1: שם מנפיק | D1: מספר מנפיק | E1: סוג מספר מזהה מנפיק | F1: שם נייר ערך | G1: מספר נייר ערך | H1: סוג מספר נייר ערך | I1: ישראל/חו"ל | J1: מדינה לפי חשיפה כלכלית | K1: סטאטוס סחירות | L1: זירת מסחר | M1: נכס בסיס (כתב אופציה) | N1: ענף מסחר | O1: תאריך פקיעה | P1: בעל עניין/צד קשור | Q1: מטבע פעילות | R1: שער מימוש | S1: יחס המרה | T1: ערך נקוב (יחידות) | U1: שער חליפין | V1: שער נייר הערך | W1: שווי הוגן (באלפי ש"ח) | X1: שיעור מנכסי אפיק ההשקעה | Y1: שיעור מסך נכסי ההשקעה
A2: 382 | B2: 382 | C2: ביג מרכזי קניות (2004) בע"מ | D2: 513623314 | E2: ח.פ | F2: ביג אפ 7 | G2: IL0012143454 | H2: ISIN | I2: ישראל | J2: ישראל | K2: סחיר | L2: TASE | M2: IL0010972607 | N2: נדל"ן מניב בישראל | O2: 01/06/2026 | P2: לא | Q2: ILS | R2: 58000 | S2: 1 | T2: 6606 | U2: 1 | V2: 3573 | W2: 236.032 | X2: 1 | Y2: 8.1638784e-05
A3: 382 | B3: 7635 | C3: ביג מרכזי קניות (2004) בע"מ | D3: 513623314 | E3: ח.פ | F3: ביג אפ 7 | G3: IL0012143454 | H3: ISIN | I3: ישראל | J3: ישראל | K3: סחיר | L3: TASE | M3: IL0010972607 | N3: נדל"ן מניב בישראל | O3: 01/06/2026 | P3: לא | Q3: ILS | R3: 58000 | S3: 1 | T3: 51 | U3: 1 | V3: 3573 | W3: 1.822 | X3: 1 | Y3: 9.8117937e-05

Sheet אופציות
A1: מספר קופה/קרן/ח.פ. עבור חברת ביטוח | B1: מספר מסלול | C1: שם מנפיק | D1: מספר מנפיק | E1: סוג מספר מזהה מנפיק | F1: שם נייר ערך | G1: מספר נייר ערך | H1: סוג מספר נייר ערך | I1: מאפיין עיקרי | J1: ישראל/חו"ל | K1: מדינה לפי חשיפה כלכלית | L1: זירת מסחר | M1: ענף מסחר | N1: נכס בסיס | O1: תאריך פקיעה | P1: בעל עניין/צד קשור | Q1: מטבע פעילות | R1: שער מימוש | S1: ערך נקוב (יחידות) | T1: שער חליפין | U1: שער נייר הערך | V1: שווי הוגן (באלפי ש"ח) | W1: שיעור מנכסי אפיק ההשקעה | X1: שיעור מסך נכסי ההשקעה
A2: 382 | B2: 11414 | C2: מסלקת הבורסה | D2: 520027152 | E2: ח.פ | F2: תC002440M504-35 | G2: IL0854664724 | H2: ISIN | I2: מניה | J2: ישראל | K2: ישראל | L2: TASE | M2: נגזרים | N2: מניות לרבות מדדי מניות | O2: 25/04/2025 | P2: לא | Q2: ILS | R2: 2440 | S2: 20 | T2: 1 | U2: 158900 | V2: 31.78 | W2: -1.7734375 | X2: 0.0020623782
A3: 382 | B3: 11414 | C3: מסלקת הבורסה | D3: 520027152 | E3: ח.פ | F3: תP002440M504-35 | G3: IL0854674624 | H3: ISIN | I3: מניה | J3: ישראל | K3: ישראל | L3: TASE | M3: נגזרים | N3: מניות לרבות מדדי מניות | O3: 25/04/2025 | P3: לא | Q3: ILS | R3: 2440 | S3: -20 | T3: 1 | U3: 248500 | V3: -49.7 | W3: 2.7734375 | X3: -0.0032253052

Sheet חוזים עתידיים
A1: מספר קופה/קרן/ח.פ. עבור חברת ביטוח | B1: מספר מסלול | C1: שם מנפיק | D1: מספר מנפיק | E1: סוג מספר מזהה מנפיק | F1: שם נייר ערך | G1: מספר נייר ערך | H1: סוג מספר נייר ערך | I1: ישראל/חו"ל | J1: מדינה לפי חשיפה כלכלית | K1: זירת מסחר | L1: נכס בסיס | M1: בעל עניין/צד קשור | N1: מטבע פעילות | O1: ערך נקוב (יחידות) | P1: שער חליפין | Q1: שער נייר הערך | R1: שווי הוגן (באלפי ש"ח) | S1: שיעור מנכסי אפיק ההשקעה | T1: שיעור מסך נכסי ההשקעה
A2: 382 | B2: 382 | C2: חוזים עתידיים בחול | D2: 10527 | E2: פנימי | F2: ESM5 S&P500 EMINI FUT JUN 25 | G2: ESM5 | H2: אחר | I2: חו"ל | J2: ארה"ב | K2: CME | L2: מניות לרבות מדדי מניות | M2: לא | N2: USD | O2: 137 | P2: 3.718 | Q2: 5653.25 | R2: -990.717 | S2: 1 | T2: -0.00034266875
A3: 382 | B3: 9479 | C3: חוזים עתידיים בחול | D3: 10527 | E3: פנימי | F3: ESM5 S&P500 EMINI FUT JUN 25 | G3: ESM5 | H3: אחר | I3: חו"ל | J3: ארה"ב | K3: CME | L3: מניות לרבות מדדי מניות | M3: לא | N3: USD | O3: 10 | P3: 3.718 | Q3: 5653.25 | R3: -72.222 | S3: 1 | T3: -0.0010100061
A4: 382 | B4: 11414 | C4: חוזים עתידיים בחול | D4: 10527 | E4: פנימי | F4: ESM5 S&P500 EMINI FUT JUN 25 | G4: ESM5 | H4: אחר | I4: חו"ל | J4: ארה"ב | K4: CME | L4: מניות לרבות מדדי מניות | M4: לא | N4: USD | O4: 2 | P4: 3.718 | Q4: 5653.25 | R4: -14.482 | S4: 1 | T4: -0.00093979098

Sheet מוצרים מובנים
A1: מספר קופה/קרן/ח.פ. עבור חברת ביטוח | B1: מספר מסלול | C1: שם מנפיק | D1: מספר מנפיק | E1: סוג מספר מזהה מנפיק | F1: שם נייר ערך | G1: מספר נייר ערך | H1: סוג מספר נייר ערך | I1: מאפיין עיקרי | J1: ישראל/חו"ל | K1: מדינה לפי חשיפה כלכלית | L1: סטאטוס סחירות | M1: זירת מסחר | N1: נכס בסיס | O1: בעל עניין/צד קשור | P1: מח"מ | Q1: שיעור ריבית | R1: תשואה לפדיון | S1: דירוג | T1: שם מדרג | U1: דירוג נייר הערך/המנפיק | V1: מטבע פעילות | W1: ערך נקוב (יחידות) | X1: שער חליפין | Y1: שער נייר הערך | Z1: שווי הוגן (באלפי ש"ח) | AA1: שיעור מנכסי אפיק ההשקעה | AB1: שיעור מסך נכסי ההשקעה

Sheet לא סחיר איגרות חוב ממשלתיות
A1: מספר קופה/קרן/ח.פ. עבור חברת ביטוח | B1: מספר מסלול | C1: שם מנפיק | D1: שם נייר ערך | E1: מספר נייר ערך | F1: סוג מספר נייר ערך | G1: מאפיין עיקרי | H1: ישראל/חו"ל | I1: מדינה לפי חשיפה כלכלית | J1: תאריך רכישה | K1: דירוג | L1: שם מדרג | M1: מטבע פעילות | N1: מח"מ | O1: מועד פדיון | P1: שיעור ריבית | Q1: תשואה לפדיון | R1: ערך נקוב (יחידות) | S1: שער חליפין | T1: שער נייר הערך | U1: שווי הוגן (באלפי ש"ח) | V1: עלות מופחתת (באלפי ש"ח) | W1: השיטה שיושמה בדוח הכספי | X1: שיעור מנכסי אפיק ההשקעה | Y1: שיעור מסך נכסי ההשקעה

Sheet לא סחיר איגרות חוב מיועדות
A1: מספר קופה/קרן/ח.פ. עבור חברת ביטוח | B1: מספר מסלול | C1: מאפיין עיקרי | D1: שם נייר ערך | E1: מספר נייר ערך | F1: תאריך רכישה | G1: מח"מ | H1: סוג הצמדה | I1: מועד פדיון | J1: שיעור ריבית | K1: תשואה לפדיון | L1: ערך נקוב (יחידות) | M1: שער נייר הערך | N1: שווי הוגן (באלפי ש"ח) | O1: עלות מופחתת (באלפי ש"ח) | P1: השיטה שיושמה בדוח הכספי | Q1: שיעור מנכסי אפיק ההשקעה | R1: שיעור מסך נכסי ההשקעה

Sheet אפיק השקעה מובטח תשואה
A1: מספר קרן | B1: מספר מסלול | C1: מאפיין עיקרי | D1: חודש הנפקת שכבה | E1: חודש הבדיקה | F1: שווי הנכסים באפיק (באלפי ש"ח) | G1: שיעור מסך נכסי ההשקעה

Sheet לא סחיר ניירות ערך מסחריים
A1: מספר קופה/קרן/ח.פ. עבור חברת ביטוח | B1: מספר מסלול | C1: שם מנפיק | D1: מספר מנפיק | E1: סוג מספר מזהה מנפיק | F1: שם נייר ערך | G1: מספר נייר ערך | H1: סוג מספר נייר ערך | I1: מאפיין עיקרי | J1: ישראל/חו"ל | K1: מדינה לפי חשיפה כלכלית | L1: ענף מסחר | M1: בעל עניין/צד קשור | N1: תאריך רכישה | O1: דירוג | P1: שם מדרג | Q1: דירוג נייר הערך/המנפיק | R1: מטבע פעילות | S1: מח"מ | T1: סוג הצמדה | U1: ריבית עוגן | V1: מועד פדיון | W1: שיעור ריבית | X1: תשואה לפדיון | Y1: נחיתות חוזית | Z1: האם סווג כחוב בעייתי | AA1: סוג גורם משערך | AB1: תלות/אי-תלות המשערך | AC1: שם גורם משערך | AD1: תאריך שערוך אחרון | AE1: תאריך אחרון בו נבחנה בפועל ירידת ערך | AF1: ערך נקוב (יחידות) | AG1: שער חליפין | AH1: שער נייר הערך | AI1: שווי הוגן (באלפי ש"ח) | AJ1: עלות מופחתת (באלפי ש"ח) | AK1: עלות מופחתת (במטבע הפעילות) | AL1: השיטה שיושמה בדוח הכספי | AM1: שיעור מנכסי אפיק ההשקעה | AN1: שיעור מסך נכסי ההשקעה

Sheet לא סחיר איגרות חוב
A1: מספר קופה/קרן/ח.פ. עבור חברת ביטוח | B1: מספר מסלול | C1: שם מנפיק | D1: מספר מנפיק | E1: סוג מספר מזהה מנפיק | F1: שם נייר ערך | G1: מספר נייר ערך | H1: סוג מספר נייר ערך | I1: מאפיין עיקרי | J1: ישראל/חו"ל | K1: מדינה לפי חשיפה כלכלית | L1: סטאטוס סחירות | M1: ענף מסחר | N1: בעל עניין/צד קשור | O1: תאריך רכישה | P1: דירוג | Q1: שם מדרג | R1: דירוג נייר הערך/המנפיק | S1: מטבע פעילות | T1: מח"מ | U1: מועד פדיון | V1: תשואה לפדיון | W1: שיעור ריבית | X1: נחיתות חוזית | Y1: האם סווג כחוב בעייתי | Z1: סוג גורם משערך | AA1: תלות/אי-תלות המשערך | AB1: תאריך שערוך אחרון | AC1: תאריך אחרון בו נבחנה בפועל ירידת ערך | AD1: ערך נקוב (יחידות) | AE1: שער חליפין | AF1: שער נייר הערך | AG1: שווי הוגן (באלפי ש"ח) | AH1: עלות מופחתת (באלפי ש"ח) | AI1: עלות מופחתת (במטבע הפעילות) | AJ1: השיטה שיושמה בדוח הכספי | AK1: שיעור מנכסי אפיק ההשקעה | AL1: שיעור מסך נכסי ההשקעה
A2: 382 | B2: 382 | C2: NEON CAPITAL LTD | D2: 549300K1NZTY5QS1NO76 | E2: LEI | F2: NEONCA 0 01/04/41 | G2: XS0207404343 | H2: ISIN | I2: צמוד למט"ח | J2: חו"ל | K2: איי קיימן | L2: לא סחיר | M2: Food & Staples Retailing Consumer Staples Distribution & Retail | N2: לא | O2: 01/08/2019 | P2: NR | Q2: NR | R2: NR | S2: USD | T2: 17.51 | U2: 04/01/2041 | V2: 0.01104 | W2: 0 | X2: החוב לא נחות | Y2: לא | Z2: אחר | AA2: אי-תלות | AB2: 08/08/2019 | AC2: 31/03/2025 | AD2: 400000 | AE2: 3.718 | AF2: 0.1 | AG2: 1.487 | AJ2: שווי הוגן | AK2: 8.0003121e-05 | AL2: 5.1439213e-07
A3: 382 | B3: 382 | C3: אידיבי חברה לאחזקות בע"מ | D3: 520028283 | E3: ח.פ | F3: אידיבי אגח ב (מחוק) | G3: IL0073600350 | H3: ISIN | I3: צמוד למדד המחירים לצרכן | J3: ישראל | K3: ישראל | L3: לא סחיר | M3: השקעה ואחזקות | N3: לא | O3: 04/08/2014 | P3: D | Q3: S&P מעלות | R3: נייר ערך | S3: ILS | T3: 0.01 | U3: 06/09/2013 | V3: 0.0001 | W3: 0.057 | X3: החוב נחות | Y3: כן | Z3: אחר | AA3: אי-תלות | AB3: 31/03/2020 | AC3: 31/03/2025 | AD3: 296667.31 | AE3: 1 | AF3: 0 | AG3: 0 | AJ3: שווי הוגן | AK3: 1.5959058e-10 | AL3: 1.0261117e-12
A4: 382 | B4: 382 | C4: אלון חברת הדלק לישראל בע"מ | D4: 520041690 | E4: ח.פ | F4: אלון דלק אגח א מופחת | G4: IL0011015679 | H4: ISIN | I4: צמוד למדד המחירים לצרכן | J4: ישראל | K4: ישראל | L4: לא סחיר | M4: השקעה ואחזקות | N4: לא | O4: 21/07/2016 | P4: R/S | Q4: S&P מעלות | R4: נייר ערך | S4: ILS | T4: 0.01 | U4: 31/12/2025 | V4: 0.0341 | W4: 0.0535 | X4: החוב נחות | Y4: לא | Z4: אחר | AA4: אי תלות | AB4: 31/03/2025 | AC4: 31/03/2025 | AD4: 2218959.5 | AE4: 1 | AF4: 15.04 | AG4: 333.732 | AJ4: שווי הוגן | AK4: 0.017952906 | AL4: 0.00011543092
A5: 382 | B5: 382 | C5: לידר החזקות והשקעות בע"מ | D5: 520037664 | E5: ח.פ | F5: לידר אגח ח - רמ | G5: IL0031803617 | H5: ISIN | I5: לא צמוד למדד המחירים לצרכן | J5: ישראל | K5: ישראל | L5: לא סחיר | M5: השקעה ואחזקות | N5: לא | O5: 28/02/2021 | P5: A1 | Q5: מידרוג Moodys | R5: נייר ערך | S5: ILS | T5: 1.83 | U5: 15/02/2028 | V5: 0.051 | W5: 0.021 | X5: החוב לא נחות | Y5: לא | Z5: חברת ציטוט | AA5: אי תלות | AB5: 31/03/2025 | AC5: 31/03/2025 | AD5: 1736145.1 | AE5: 1 | AF5: 95.05 | AG5: 1650.206 | AJ5: שווי הוגן | AK5: 0.088771935 | AL5: 0.00057077255
A6: 382 | B6: 382 | C6: מפעלי פלדה מאוחדים בע"מ | D6: 520022492 | E6: ח.פ | F6: מ.פלדה אג-1 מפ1/00 | G6: IL0039800425 | H6: ISIN | I6: לא צמוד למדד המחירים לצרכן | J6: ישראל | K6: ישראל | L6: לא סחיר | M6: מתכת ומוצרי בניה | N6: לא | O6: 31/12/2013 | P6: NR | Q6: NR | R6: NR | S6: ILS | T6: 0 | U6: 31/01/2001 | V6: 0 | W6: 0 | X6: החוב נחות | Y6: כן | Z6: אחר | AA6: אי-תלות | AB6: 10/12/2018 | AC6: 31/03/2025 | AD6: 43880.43 | AE6: 1 | AF6: 0 | AG6: 0 | AJ6: שווי הוגן | AK6: 2.360524e-11 | AL6: 1.5177345e-13
A7: 382 | B7: 382 | C7: מימון ישיר נדל"ן ומשכנתאות בעמ | D7: 516100153 | E7: ח.פ | F7: מימוןמשכ אגא-רמ | G7: IL0012088188 | H7: ISIN | I7: צמוד למדד המחירים לצרכן | J7: ישראל | K7: ישראל | L7: לא סחיר | M7: שירותים פיננסיים | N7: לא | O7: 15/07/2024 | P7: A3 | Q7: מידרוג Moodys | R7: נייר ערך | S7: ILS | T7: 3.48 | U7: 31/12/2031 | V7: 0.04 | W7: 0.0445 | X7: החוב לא נחות | Y7: לא | Z7: חברת ציטוט | AA7: אי-תלות | AB7: 31/03/2025 | AC7: 31/03/2025 | AD7: 2660000 | AE7: 1 | AF7: 104.62 | AG7: 2782.892 | AJ7: שווי הוגן | AK7: 0.14970417 | AL7: 0.00096254556
A8: 382 | B8: 382 | C8: מפעלי פלדה מאוחדים בע"מ | D8: 520022492 | E8: ח.פ | F8: מפעלי פלדה אג1 | G8: IL0039800185 | H8: ISIN | I8: צמוד למדד המחירים לצרכן | J8: ישראל | K8: ישראל | L8: לא סחיר | M8: מתכת ומוצרי בניה | N8: לא | O8: 31/12/2013 | P8: NR | Q8: NR | R8: NR | S8: ILS | T8: 0 | U8: 31/01/2001 | V8: 0 | W8: 0 | X8: החוב נחות | Y8: כן | Z8: אחר | AA8: אי-תלות | AB8: 10/12/2018 | AC8: 31/03/2025 | AD8: 32173.6 | AE8: 1 | AF8: 0 | AG8: 0 | AJ8: שווי הוגן | AK8: 1.7307614e-11 | AL8: 1.1128192e-13
A9: 382 | B9: 382 | C9: מקס איט פיננסים בע"מ לשעבר לאומי קארד | D9: 512905423 | E9: ח.פ | F9: מקס איט התח אגח ד-רמ | G9: IL0011979536 | H9: ISIN | I9: לא צמוד למדד המחירים לצרכן | J9: ישראל | K9: ישראל | L9: לא סחיר | M9: שירותים פיננסיים | N9: לא | O9: 17/07/2023 | P9: A1 | Q9: מידרוג Moodys | R9: נייר ערך | S9: ILS | T9: 3.17 | U9: 16/10/2028 | V9: 0.06103 | W9: 0.0731 | X9: החוב לא נחות | Y9: לא | Z9: חברת ציטוט | AA9: אי תלות | AB9: 31/03/2025 | AC9: 31/03/2025 | AD9: 6300000 | AE9: 1 | AF9: 109.05 | AG9: 6870.15 | AJ9: שווי הוגן | AK9: 0.36957601 | AL9: 0.0023762447
A10: 382 | B10: 382 | C10: נתיבי הגז הטבעי לישראל בע"מ | D10: 513436394 | E10: ח.פ | F10: נתיבי גז אג"ח א - רמ | G10: IL0011030843 | H10: ISIN | I10: צמוד למדד המחירים לצרכן | J10: ישראל | K10: ישראל | L10: לא סחיר | M10: שירותים | N10: לא | O10: 31/12/2013 | P10: AA+ | Q10: S&P מעלות | R10: נייר ערך | S10: ILS | T10: 0.83 | U10: 29/12/2026 | V10: 0.0282 | W10: 0.056 | X10: החוב לא נחות | Y10: לא | Z10: חברת ציטוט | AA10: אי תלות | AB10: 31/03/2025 | AC10: 31/03/2025 | AD10: 800773.72 | AE10: 1 | AF10: 144.82 | AG10: 1159.681 | AJ10: שווי הוגן | AK10: 0.062384386 | AL10: 0.00040110982
A11: 382 | B11: 382 | C11: רפאל-רשות לפיתוח אמצעי לחימה בע"מ | D11: 520042185 | E11: ח.פ | F11: רפאל אגח ג ר.מ. | G11: IL0011402760 | H11: ISIN | I11: צמוד למדד המחירים לצרכן | J11: ישראל | K11: ישראל | L11: לא סחיר | M11: ביטחוניות | N11: לא | O11: 05/05/2021 | P11: AAA | Q11: S&P מעלות | R11: נייר ערך | S11: ILS | T11: 4.62 | U11: 15/09/2034 | V11: 0.0256 | W11: 0.0214 | X11: החוב לא נחות | Y11: לא | Z11: חברת ציטוט | AA11: אי תלות | AB11: 31/03/2025 | AC11: 31/03/2025 | AD11: 1790052.6 | AE11: 1 | AF11: 115.11 | AG11: 2060.53 | AJ11: שווי הוגן | AK11: 0.11084507 | AL11: 0.00071269511
A12: 382 | B12: 382 | C12: רפאל-רשות לפיתוח אמצעי לחימה בע"מ | D12: 520042185 | E12: ח.פ | F12: רפאל סד' ד 2020/2034 | G12: IL0011402844 | H12: ISIN | I12: לא צמוד למדד המחירים לצרכן | J12: ישראל | K12: ישראל | L12: לא סחיר | M12: ביטחוניות | N12: לא | O12: 04/05/2021 | P12: AAA | Q12: S&P מעלות | R12: נייר ערך | S12: ILS | T12: 4.35 | U12: 15/09/2034 | V12: 0.0505 | W12: 0.0374 | X12: החוב לא נחות | Y12: לא | Z12: חברת ציטוט | AA12: אי תלות | AB12: 31/03/2025 | AC12: 31/03/2025 | AD12: 3930255.2 | AE12: 1 | AF12: 94.92 | AG12: 3730.598 | AJ12: שווי הוגן | AK12: 0.20068552 | AL12: 0.0012903378

Sheet לא סחיר מניות מבכ ויהש
A1: מספר קופה/קרן/ח.פ. עבור חברת ביטוח | B1: מספר מסלול | C1: שם מנפיק | D1: מספר מנפיק | E1: סוג מספר מזהה מנפיק | F1: שם נייר ערך | G1: מספר נייר ערך | H1: סוג מספר נייר ערך | I1: מאפיין עיקרי | J1: ישראל/חו"ל | K1: מדינה לפי חשיפה כלכלית | L1: סטאטוס סחירות | M1: ענף מסחר | N1: בעל עניין/צד קשור | O1: תאריך רכישה | P1: מטבע פעילות | Q1: סוג גורם משערך | R1: תלות/אי-תלות המשערך | S1: תאריך שערוך אחרון | T1: תאריך אחרון בו נבחנה בפועל ירידת ערך | U1: ערך נקוב (יחידות) | V1: שער חליפין | W1: שער נייר הערך | X1: שווי הוגן (באלפי ש"ח) | Y1: שיעור מנכסי אפיק ההשקעה | Z1: שיעור מסך נכסי ההשקעה
A2: 382 | B2: 382 | C2: אפאר | D2: 516072931 | E2: ח.פ | F2: אפאר | G2: IL0002940174 | H2: ISIN | I2: מניות לא סחירות | J2: ישראל | K2: ישראל | L2: לא סחיר | M2: עץ, נייר ודפוס | N2: לא | O2: 31/12/2013 | P2: ILS | Q2: אחר | R2: אי-תלות | S2: 10/11/2024 | T2: 31/03/2024 | U2: 12282 | V2: 1 | W2: 0 | X2: 0 | Y2: 4.3055978e-11 | Z2: 4.2480932e-14
A3: 382 | B3: 382 | C3: ג'נריישן ניהול בע"מ | D3: 515785012 | E3: ח.פ | F3: ויולה ג'נריישן ניהול | G3: 560931 | H3: פנימי | I3: מניות לא סחירות | J3: ישראל | K3: ישראל | L3: לא סחיר | M3: שירותים פיננסיים | N3: לא | O3: 11/02/2020 | P3: ILS | Q3: אחר | R3: אי-תלות | S3: 21/02/2025 | T3: 26/12/2024 | U3: 1325 | V3: 1 | W3: 124567.09 | X3: 1650.514 | Y3: 0.57860686 | Z3: 0.00057087911
A4: 382 | B4: 382 | C4: מניבים קרן הריט החדשה בע"מ | D4: 515327120 | E4: ח.פ | F4: מניבים ניהול הר | G4: 364751 | H4: פנימי | I4: מניות לא סחירות | J4: ישראל | K4: ישראל | L4: לא סחיר | M4: נדל"ן מניב בישראל | N4: לא | O4: 11/02/2020 | P4: ILS | Q4: אחר | R4: אי-תלות | S4: 26/12/2024 | T4: 21/02/2025 | U4: 150 | V4: 1 | W4: 570012 | X4: 855.018 | Y4: 0.2997365 | Z4: 0.00029573328
A5: 382 | B5: 382 | C5: צים שירותי ספנות משולבים בע"מ | D5: 21380089EIJRELKAIL21 | E5: LEI | F5: צים מניה הסדר חוב | G5: IL0065100286 | H5: ISIN | I5: מניות לא סחירות | J5: ישראל | K5: ישראל | L5: לא סחיר | M5: שירותים | N5: לא | O5: 03/06/2021 | P5: USD | Q5: אחר | R5: אי-תלות | S5: 03/06/2021 | T5: 31/03/2025 | U5: 820 | V5: 3.718 | W5: 40.9 | X5: 1.247 | Y5: 0.0004371303 | Z5: 4.3129209e-07
A6: 382 | B6: 382 | C6: רייכרט תעשיות בע"מ | D6: 520039652 | E6: ח.פ | F6: רייכרט | G6: 4760101 | H6: פנימי | I6: מניות לא סחירות | J6: ישראל | K6: ישראל | L6: לא סחיר | M6: בנייה | N6: לא | O6: 31/12/2013 | P6: ILS | Q6: אחר | R6: אי-תלות | S6: 30/09/2015 | T6: 31/03/2025 | U6: 2156 | V6: 1 | W6: 0 | X6: 0 | Y6: 7.5581085e-12 | Z6: 7.4571641e-15
A7: 382 | B7: 382 | C7: ALESCO PREF FUNDING IX | D7: 549300FP1ZNOHOUNLV32 | E7: LEI | F7: ALESC 0 06/23/36 | G7: KYG0158U1067 | H7: ISIN | I7: מניות לא סחירות | J7: חו"ל | K7: ארה"ב | L7: לא סחיר | M7: Diversified Financial Services Financial Services | N7: לא | O7: 01/08/2019 | P7: USD | Q7: אחר | R7: אי-תלות | S7: 25/12/2023 | T7: 31/03/2025 | U7: 89 | V7: 3.718 | W7: 0 | X7: 0 | Y7: 1.1600154e-12 | Z7: 1.1445225e-15
A8: 382 | B8: 382 | C8: ALESCO PREF FUNDING IX | D8: 549300FP1ZNOHOUNLV32 | E8: LEI | F8: ALESC 7X INC | G8: USG0158NAA03 | H8: ISIN | I8: מניות לא סחירות | J8: חו"ל | K8: ארה"ב | L8: לא סחיר | M8: Diversified Financial Services Financial Services | N8: לא | O8: 01/08/2019 | P8: USD | Q8: אחר | R8: אי-תלות | S8: 07/08/2019 | T8: 31/03/2025 | U8: 0 | V8: 3.718 | W8: 0 | X8: 345.774 | Y8: 0.12121509 | Z8: 0.00011959617
A9: 382 | B9: 382 | C9: ALESCO PREF FUNDING IX | D9: 549300FP1ZNOHOUNLV32 | E9: LEI | F9: ALESCO PFD V | G9: KYG0158H1056 | H9: ISIN | I9: מניות לא סחירות | J9: חו"ל | K9: ארה"ב | L9: לא סחיר | M9: Construction Materials | N9: לא | O9: 08/09/2020 | P9: USD | Q9: אחר | R9: אי-תלות | S9: 31/03/2025 | T9: 31/03/2025 | U9: 133 | V9: 3.718 | W9: 0 | X9: 0.013 | Y9: 4.4185323e-06 | Z9: 4.3595193e-09

Sheet קרנות השקעה
A1: מספר קופה/קרן/ח.פ. עבור חברת ביטוח | B1: מספר מסלול | C1: שם שותף כללי קרן השקעות | D1: מספר מזהה שותף כללי קרן השקעות | E1: סוג מספר מזהה שותף כללי קרן השקעות | F1: שם קרן השקעה | G1: מספר מזהה קרן השקעה | H1: סוג מספר מזהה קרן השקעות | I1: מאפיין עיקרי | J1: אסטרטגיית קרן ההשקעה | K1: ישראל/חו"ל | L1: מדינת התאגדות קרן השקעה | M1: מיקום משרד השותף הכללי | N1: מדינה לפי חשיפה כלכלית | O1: בעל עניין/צד קשור | P1: תאריך רכישה | Q1: מטבע פעילות | R1: סוג גורם משערך | S1: תלות/אי-תלות המשערך | T1: תאריך שערוך אחרון | U1: שער חליפין | V1: NAV (במטבע הדיווח של קרן ההשקעה) | W1: שווי הוגן (באלפי ש"ח) | X1: שיעור החזקה בקרן השקעה | Y1: שיעור מנכסי אפיק ההשקעה | Z1: שיעור מסך נכסי ההשקעה
A2: 382 | B2: 382 | C2: Ami Opportunities | D2: 512712548 | E2: פנימי | F2: AMI OPPORTUNITY | G2: 603978741 | H2: פנימי | I2: פרייבט אקוויטי | J2: Co-Investment/Direct | K2: חו"ל | L2: ג'רנסי | M2: Address: 1 Glategny Esplanade , St Peter Port , Guernsey , GY12HJ | N2: ישראל | O2: לא | P2: 25/02/2020 | Q2: USD | R2: מומחה בלתי תלוי | S2: אי-תלות | T2: 19/03/2025 | U2: 3.718 | V2: 1731.466 | W2: 6437.589 | X2: 0 | Y2: 0.013832228 | Z2: 0.0022266308
A3: 382 | B3: 382 | C3: הראל | D3: 213800P4S1KTTPIB9T76 | E3: LEI | F3: Harel Alternative Credit Co-In | G3: 27940028 | H3: פנימי | I3: פרייבט אקוויטי | J3: Venture Debt | K3: ישראל | L3: איי קיימן | M3: כתובת: החילזון 12 , רמת גן | N3: ישראל | O3: לא | P3: 24/04/2023 | Q3: ILS | R3: מומחה בלתי תלוי | S3: אי-תלות | T3: 27/02/2025 | U3: 1 | V3: 3686.312 | W3: 3686.312 | X3: 0 | Y3: 0.0079206526 | Z3: 0.0012750201
A4: 382 | B4: 382 | C4: תש"י | D4: 540278751 | E4: ח.פ | F4: IIF IV | G4: 27940008 | H4: פנימי | I4: פרייבט אקוויטי | J4: Value Added Infrastructure | K4: ישראל | L4: ישראל | M4: כתובת: השלושה 2 ת, תל אביב | N4: ישראל | O4: לא | P4: 13/10/2020 | Q4: USD | R4: דיווח מנהל הקרן | S4: קיימת תלות | T4: 31/03/2025 | U4: 3.718 | V4: 2823.707 | W4: 10498.542 | X4: 0.011908 | Y4: 0.022557857 | Z4: 0.0036312314
A5: 382 | B5: 382 | C5: Kedma Capital | D5: 540286333 | E5: ח.פ | F5: KEDMA CAPITAL IV | G5: 27940039 | H5: פנימי | I5: פרייבט אקוויטי | J5: Other | K5: ישראל | L5: ישראל | M5: מנחם בגין 132, מגדלי עזריאלי, תל אביב | N5: ישראל | O5: לא | P5: 19/02/2025 | Q5: USD | R5: אחר | T5: 19/02/2025 | U5: 3.718 | V5: 769.263 | W5: 2860.12 | X5: 0 | Y5: 0.0061454416 | Z5: 0.00098925709
A6: 382 | B6: 382 | C6: קדמה | D6: 540286333 | E6: ח.פ | F6: KEDMA CAPITAL PARTNERS III LTD | G6: 620120592 | H6: פנימי | I6: פרייבט אקוויטי | J6: Co-Investment/Direct | K6: ישראל | L6: ישראל | M6: כתובת: מנחם בגין 132, מגדלי עזריאלי, תל אביב | N6: ישראל | O6: לא | P6: 29/04/2021 | Q6: USD | R6: דיווח מנהל הקרן | S6: קיימת תלות | T6: 31/12/2024 | U6: 3.718 | V6: 1808.901 | W6: 6725.493 | X6: 0 | Y6: 0.014450836 | Z6: 0.0023262108
A7: 382 | B7: 382 | C7: Klirmark | D7: CO-101523 | E7: מספר תאגיד או שותפות בחו"ל | F7: KLIRMARK FUND III | G7: 27940001 | H7: פנימי | I7: פרייבט אקוויטי | J7: Special Situations Debt | K7: ישראל | L7: איי קיימן | M7: כתובת: ז'בוטינסקי 2 , רמת גן , ישראל | N7: ישראל | O7: לא | P7: 13/11/2019 | Q7: ILS | R7: דיווח מנהל הקרן | S7: קיימת תלות | T7: 27/02/2025 | U7: 1 | V7: 3487.285 | W7: 3487.285 | X7: 0 | Y7: 0.0074930099 | Z7: 0.0012061807
A8: 382 | B8: 382 | C8: Klirmark | D8: CO-101523 | E8: מספר תאגיד או שותפות בחו"ל | F8: Klirmark Fund IV | G8: 27940027 | H8: פנימי | I8: פרייבט אקוויטי | J8: Special Situations Debt | K8: ישראל | L8: איי קיימן | M8: כתובת: ז'בוטינסקי 2 , רמת גן , ישראל | N8: ישראל | O8: לא | P8: 17/04/2023 | Q8: ILS | R8: דיווח מנהל הקרן | S8: קיימת תלות | T8: 30/12/2024 | U8: 1 | V8: 3729.935 | W8: 3729.935 | X8: 0 | Y8: 0.0080143832 | Z8: 0.0012901083
A9: 382 | B9: 382 | C9: Pitango Growth | D9: MC-103097 | E9: מספר תאגיד או שותפות בחו"ל | F9: Pitango Growth II | G9: 27940011 | H9: פנימי | I9: פרייבט אקוויטי | J9: Growth Venture Capital | K9: ישראל | L9: איי קיימן | M9: Address: 11 HaMenofim st. Herzliya | N9: ישראל | O9: לא | P9: 07/06/2021 | Q9: USD | R9: דיווח מנהל הקרן | S9: קיימת תלות | T9: 30/03/2025 | U9: 3.718 | V9: 2385.413 | W9: 8868.967 | X9: 0 | Y9: 0.019056445 | Z9: 0.0030675946
A10: 382 | B10: 382 | C10: Somv | D10: 27843 | E10: פנימי | F10: SOMV 2 | G10: 62006168 | H10: פנימי | I10: פרייבט אקוויטי | J10: Value Added Infrastructure | K10: ישראל | L10: איי קיימן | M10: כתובת: מדינת היהודים 85 , הרצליה, ישראל | N10: ישראל | O10: לא | P10: 20/03/2018 | Q10: USD | R10: דיווח מנהל הקרן | S10: קיימת תלות | T10: 31/03/2025 | U10: 3.718 | V10: 314.861 | W10: 1170.652 | X10: 0 | Y10: 0.0025153399 | Z10: 0.00040490464
A11: 382 | B11: 382 | C11: אלפא | D11: 550225288 | E11: ח.פ | F11: אלפא- השתלמות עובדי מדינה | G11: 27940015 | H11: פנימי | I11: פרייבט אקוויטי | J11: Buyout | K11: ישראל | L11: איי קיימן | M11: כתובת: אבא אבן 10 , הרצליה | N11: ישראל | O11: לא | P11: 26/08/2021 | Q11: ILS | R11: מומחה בלתי תלוי | S11: אי-תלות | T11: 20/03/2025 | U11: 1 | V11: 4607.905 | W11: 4607.905 | X11: 0 | Y11: 0.0099008477 | Z11: 0.0015937803
A12: 382 | B12: 382 | C12: יסודות נדלן | D12: 550257125 | E12: מספר שותפות | F12: יסודות נדלן ג | G12: 27940003 | H12: פנימי | I12: פרייבט אקוויטי | J12: Venture Debt | K12: ישראל | L12: ישראל | M12: כתובת: בר כוכבא 23, בני ברק, ישראל | N12: ישראל | O12: לא | P12: 02/12/2019 | Q12: ILS | R12: מומחה בלתי תלוי | S12: אי-תלות | T12: 30/03/2025 | U12: 1 | V12: 5908.42 | W12: 5908.42 | X12: 0.002954 | Y12: 0.01269522 | Z12: 0.0020436019
A13: 382 | B13: 382 | C13: נוי 1 | D13: 540294725 | E13: ח.פ | F13: נוי 1 קרן תשתיות פרטית | G13: 32623 | H13: פנימי | I13: פרייבט אקוויטי | J13: Value Added Infrastructure | K13: ישראל | L13: ישראל | M13: כתובת: דרך מנחם בגין 132, תל אביב | N13: ישראל | O13: לא | P13: 31/12/2013 | Q13: ILS | R13: דיווח מנהל הקרן | S13: קיימת תלות | T13: 10/12/2024 | U13: 1 | V13: 1.131 | W13: 1.131 | X13: 0 | Y13: 2.4295315e-06 | Z13: 3.9109171e-07
A14: 382 | B14: 382 | C14: ספרה | D14: 540305869 | E14: ח.פ | F14: ספירה יתר קרן השקעה | G14: 34934 | H14: פנימי | I14: פרייבט אקוויטי | J14: Buyout | K14: ישראל | L14: איי קיימן | M14: כתובת: יצחק שדה 4 , תל אביב | N14: ישראל | O14: לא | P14: 31/12/2013 | Q14: ILS | R14: מומחה בלתי תלוי | S14: אי-תלות | T14: 20/03/2025 | U14: 1 | V14: 25161.192 | W14: 25161.192 | X14: 0 | Y14: 0.054062993 | Z14: 0.0087027431
A15: 382 | B15: 382 | C15: ספרה פארקינג | D15: 540305869 | E15: ח.פ | F15: ספרה פארקינג | G15: 27940018 | H15: פנימי | I15: פרייבט אקוויטי | J15: Value Added Real Estate | K15: ישראל | L15: ישראל | M15: כתובת: הארבעה 21 תל אביב | N15: ישראל | O15: לא | P15: 06/12/2021 | Q15: ILS | R15: מומחה בלתי תלוי | S15: אי-תלות | T15: 29/01/2025 | U15: 1 | V15: 6425.974 | W15: 6425.974 | X15: 0 | Y15: 0.01380727 | Z15: 0.0022226133
A16: 382 | B16: 382 | C16: Alpha Global L.P | D16: 27512 | E16: פנימי | F16: קרן אלפא | G16: 27940035 | H16: פנימי | I16: פרייבט אקוויטי | J16: Other | K16: ישראל | L16: ישראל | M16: אבא אבן 10 , הרצליה | N16: ישראל | O16: לא | P16: 25/03/2024 | Q16: ILS | R16: אחר | T16: 20/03/2025 | U16: 1 | V16: 2603.48 | W16: 2603.48 | X16: 0 | Y16: 0.0055940083 | Z16: 0.00090049061
A17: 382 | B17: 382 | C17: אלפא | D17: 550225288 | E17: ח.פ | F17: קרן אלפא | G17: 35170 | H17: פנימי | I17: פרייבט אקוויטי | J17: Buyout | K17: ישראל | L17: איי קיימן | M17: כתובת: אבא אבן 10 , הרצליה | N17: ישראל | O17: לא | P17: 31/12/2013 | Q17: ILS | R17: מומחה בלתי תלוי | S17: אי-תלות | T17: 20/03/2025 | U17: 1 | V17: 16632.223 | W17: 16632.223 | X17: 0 | Y17: 0.035737088 | Z17: 0.0057527466
A18: 382 | B18: 382 | C18: אלפא | D18: 513834986 | E18: ח.פ | F18: קרן אלפא אופציה | G18: 36996 | H18: פנימי | I18: פרייבט אקוויטי | J18: Buyout | K18: ישראל | L18: איי קיימן | M18: כתובת: אבא אבן 10 , הרצליה | N18: ישראל | O18: לא | P18: 04/07/2017 | Q18: ILS | R18: מומחה בלתי תלוי | S18: אי-תלות | T18: 20/03/2025 | U18: 1 | V18: 9663.989 | W18: 9663.989 | X18: 0 | Y18: 0.020764682 | Z18: 0.0033425766
A19: 382 | B19: 382 | C19: ארבל | D19: 540307832 | E19: ח.פ | F19: קרן ארבל פאנד בע"מ | G19: 18978 | H19: פנימי | I19: פרייבט אקוויטי | J19: Buyout | K19: ישראל | L19: ישראל | M19: כתובת: אריאל שרון 4 , גבעתיים, ישראל | N19: ישראל | O19: לא | P19: 20/12/2017 | Q19: ILS | R19: דיווח מנהל הקרן | S19: קיימת תלות | T19: 31/03/2025 | U19: 1 | V19: 3178.79 | W19: 3178.79 | X19: 0 | Y19: 0.006830158 | Z19: 0.0010994787
A20: 382 | B20: 382 | C20: פורטיסימו | D20: 530278514 | E20: ח.פ | F20: קרן בלקסטון | G20: 201400031 | H20: פנימי | I20: פרייבט אקוויטי | J20: Co-Investment/Direct | K20: ישראל | L20: ישראל | M20: כתובת: הארבעה 30 , תל אביב, ישראל | N20: ישראל | O20: לא | P20: 16/04/2020 | Q20: USD | R20: דיווח מנהל הקרן | S20: קיימת תלות | T20: 31/03/2025 | U20: 3.718 | V20: 4000.3 | W20: 14873.115 | X20: 0 | Y20: 0.031957354 | Z20: 0.0051443072
A21: 382 | B21: 382 | C21: פורטיסימו | D21: 530278514 | E21: ח.פ | F21: קרן בלקסטון | G21: 27940032 | H21: פנימי | I21: פרייבט אקוויטי | J21: Co-Investment/Direct | K21: ישראל | L21: ישראל | M21: כתובת: הארבעה 30 , תל אביב, ישראל | N21: ישראל | O21: לא | P21: 23/10/2023 | Q21: USD | R21: דיווח מנהל הקרן | S21: קיימת תלות | T21: 31/03/2025 | U21: 3.718 | V21: 1661.068 | W21: 6175.852 | X21: 0 | Y21: 0.013269842 | Z21: 0.0021361013
A22: 382 | B22: 382 | C22: ברוש | D22: 774636625 | E22: פנימי | F22: קרן ברוש | G22: 27940005 | H22: פנימי | I22: קרן גידור (Hedge Fund) | J22: Buyout | K22: ישראל | L22: איי קיימן | M22: כתובת: אריאל שרון 4 , גבעתיים | N22: ישראל | O22: לא | P22: 17/06/2020 | Q22: ILS | R22: מומחה בלתי תלוי | S22: אי-תלות | T22: 20/03/2025 | U22: 1 | V22: 6754.277 | W22: 6754.277 | X22: 0 | Y22: 0.014512684 | Z22: 0.0023361666
A23: 382 | B23: 382 | C23: ברוש | D23: 774636625 | E23: פנימי | F23: קרן ברוש - השתלמות עובדי מדינה | G23: 500052 | H23: פנימי | I23: קרן גידור (Hedge Fund) | J23: Buyout | K23: ישראל | L23: איי קיימן | M23: כתובת: אריאל שרון 4 , גבעתיים | N23: ישראל | O23: לא | P23: 24/01/2021 | Q23: ILS | R23: מומחה בלתי תלוי | S23: אי-תלות | T23: 20/03/2025 | U23: 1 | V23: 16543.255 | W23: 16543.255 | X23: 0 | Y23: 0.035545926 | Z23: 0.0057219744
A24: 382 | B24: 382 | C24: נוקד | D24: 515419356 | E24: ח.פ | F24: קרן גידור נוקד | G24: 36459 | H24: פנימי | I24: קרן גידור (Hedge Fund) | J24: Buyout | K24: ישראל | L24: ישראל | M24: כתובת: הארבעה 30 תל אביב | N24: ישראל | O24: לא | P24: 03/11/2015 | Q24: ILS | R24: מומחה בלתי תלוי | S24: אי-תלות | T24: 20/03/2025 | U24: 1 | V24: 11118.715 | W24: 11118.715 | X24: 0 | Y24: 0.023890402 | Z24: 0.0038457366
A25: 382 | B25: 382 | C25: נוי | D25: 550241467 | E25: מספר שותפות | F25: קרן נוי 2 השקעה | G25: 47852 | H25: פנימי | I25: פרייבט אקוויטי | J25: Value Added Infrastructure | K25: חו"ל | L25: ישראל | M25: כתובת: דרך מנחם בגין 132, תל אביב | N25: אירופה | O25: לא | P25: 19/11/2015 | Q25: ILS | R25: דיווח מנהל הקרן | S25: קיימת תלות | T25: 30/03/2025 | U25: 1 | V25: 4638.482 | W25: 4638.482 | X25: 0 | Y25: 0.0099665474 | Z25: 0.0016043563
A26: 382 | B26: 382 | C26: ספרה | D26: 540305869 | E26: ח.פ | F26: קרן ספרה .אי. | G26: 36384 | H26: פנימי | I26: פרייבט אקוויטי | J26: Buyout | K26: ישראל | L26: איי קיימן | M26: כתובת: יצחק שדה 4 , תל אביב | N26: ישראל | O26: לא | P26: 31/07/2017 | Q26: ILS | R26: מומחה בלתי תלוי | S26: אי-תלות | T26: 20/03/2025 | U26: 1 | V26: 4641.618 | W26: 4641.618 | X26: 0 | Y26: 0.0099732852 | Z26: 0.0016054409
A27: 382 | B27: 382 | C27: Alto | D27: 27092 | E27: מספר תאגיד או שותפות בחו"ל | F27: ALTO 3 | G27: 620000732 | H27: פנימי | I27: קרן נדל"ן | J27: Value Added Real Estate | K27: חו"ל | L27: ארה"ב | M27: Address: 8 Raul Valenberg , Tel Aviv , Israel | N27: ארה"ב | O27: לא | P27: 06/10/2019 | Q27: USD | R27: דיווח מנהל הקרן | S27: קיימת תלות | T27: 31/03/2025 | U27: 3.718 | V27: 1067.287 | W27: 3968.175 | X27: 0 | Y27: 0.0085262816 | Z27: 0.0013725107
A28: 382 | B28: 382 | C28: Alto II | D28: 27092 | E28: מספר תאגיד או שותפות בחו"ל | F28: Alto II | G28: 603880223 | H28: פנימי | I28: פרייבט אקוויטי | J28: Value Added Real Estate | K28: חו"ל | L28: ארה"ב | M28: Address: 8 Raul Valenberg , Tel Aviv , Israel | N28: ארה"ב | O28: לא | P28: 26/12/2019 | Q28: USD | R28: דיווח מנהל הקרן | S28: קיימת תלות | T28: 04/02/2025 | U28: 3.718 | V28: 793.14 | W28: 2948.895 | X28: 0 | Y28: 0.0063361887 | Z28: 0.0010199624
... A30: 382 | B30: 382 | C30: בראק קפיטל | D30: 724500GB8DLC6CHUX916 | E30: LEI | F30: BRACK CAPITAL | G30: 9840572 | H30: פנימי | I30: קרן נדל"ן | J30: Value Added Real Estate | K30: חו"ל | L30: קפריסין | M30: Address: Lophitis Business Centre, 28th October Street, CY-3035 Limassol, Cyprus | N30: ישראל | O30: לא | P30: 15/10/2018 | Q30: USD | R30: דיווח מנהל הקרן | S30: קיימת תלות | T30: 20/06/2024 | U30: 3.718 | V30: 95.277 | W30: 354.24 | X30: 0 | Y30: 0.00076114234 | Z30: 0.00012252422
A31: 382 | B31: 382 | C31: Coller International | D31: 10087 | E31: פנימי | F31: Coller IX-B | G31: 27940040 | H31: פנימי | I31: פרייבט אקוויטי | J31: Other | K31: חו"ל | L31: ארה"ב | M31: Trafalgar Court, Les Banques, st Peter Port, Guernsey | N31: ארה"ב | O31: לא | P31: 03/03/2025 | Q31: USD | R31: אחר | T31: 03/03/2025 | U31: 3.718 | V31: 822.861 | W31: 3059.396 | X31: 0 | Y31: 0.0065736186 | Z31: 0.0010581825
A32: 382 | B32: 382 | C32: Direct Lending | D32: B216569 | E32: LEI | F32: Direct Lending IV | G32: 27940026 | H32: פנימי | I32: קרן חוב | J32: Co-Investment/Direct | K32: חו"ל | L32: לוקסמבורג | M32: Address: 11-13 Boulevard de la Foire, L-1528, Luxembourg | N32: אירופה | O32: לא | P32: 15/12/2022 | Q32: EUR | R32: מומחה בלתי תלוי | S32: אי-תלות | T32: 24/03/2025 | U32: 4.0219 | V32: 3521.291 | W32: 14162.282 | X32: 0 | Y32: 0.03043001 | Z32: 0.0048984444
A33: 382 | B33: 382 | C33: Electra | D33: 520028911 | E33: ח.פ | F33: Electra Capital PM Feeder 4 | G33: 27940007 | H33: פנימי | I33: פרייבט אקוויטי | J33: Other | K33: חו"ל | L33: איי קיימן | M33: Address: 4890 West Kennedy blvd. Tampa, FL 33609 USA | N33: ארה"ב | O33: לא | P33: 25/06/2020 | Q33: USD | R33: מומחה בלתי תלוי | S33: אי-תלות | T33: 31/03/2025 | U33: 3.718 | V33: 1427.559 | W33: 5307.664 | X33: 0.000525 | Y33: 0.011404397 | Z33: 0.0018358128
A34: 382 | B34: 382 | C34: Electra | D34: 520028911 | E34: ח.פ | F34: Electra Capital PM II Feeder | G34: 27940029 | H34: פנימי | I34: פרייבט אקוויטי | J34: Other | K34: חו"ל | L34: איי קיימן | M34: Address: 4890 West Kennedy blvd. Tampa, FL 33609 USA | N34: ארה"ב | O34: לא | P34: 08/05/2023 | Q34: USD | R34: מומחה בלתי תלוי | S34: אי-תלות | T34: 31/03/2025 | U34: 3.718 | V34: 1517.418 | W34: 5641.76 | X34: 0 | Y34: 0.012122257 | Z34: 0.0019513697
A35: 382 | B35: 382 | C35: אלקטרה נדל"ן 1 | D35: 9975491116 | E35: פנימי | F35: Electra UK Fund I | G35: 27940034 | H35: פנימי | I35: פרייבט אקוויטי | J35: Other | K35: חו"ל | L35: איי קיימן | M35: 1331 South Killian Drive, Suite A, Lake Park, FL 33403 Grand Cayman, KY1-1001 | N35: בריטניה | O35: לא | P35: 20/03/2024 | Q35: GBP | R35: אחר | T35: 31/03/2025 | U35: 4.8108 | V35: 256.844 | W35: 1235.625 | X35: 0 | Y35: 0.0026549454 | Z35: 0.00042737752
A36: 382 | B36: 382 | C36: EQT | D36: 2020 2423 842 | E36: ח.פ | F36: EQT Infrastructure V | G36: 27940014 | H36: פנימי | I36: פרייבט אקוויטי | J36: Value Added Infrastructure | K36: חו"ל | L36: לוקסמבורג | M36: Address: 51A Boulevard Royal, L-2449 , Luxembourg | N36: אירופה | O36: לא | P36: 12/08/2021 | Q36: EUR | R36: דיווח מנהל הקרן | S36: קיימת תלות | T36: 27/02/2025 | U36: 4.0219 | V36: 3000.461 | W36: 12067.554 | X36: 0 | Y36: 0.02592914 | Z36: 0.0041739207
A37: 382 | B37: 382 | C37: EQT Infrastructure V | D37: 2020 2423 842 | E37: ח.פ | F37: EQT Infrastructure VI | G37: 27940033 | H37: פנימי | I37: פרייבט אקוויטי | J37: Other | K37: חו"ל | L37: אירופה | M37: 51A Boulevard Royal, L-2449 , Luxembourg | N37: אירופה | O37: לא | P37: 23/01/2024 | Q37: EUR | R37: אחר | T37: 11/03/2025 | U37: 4.0219 | V37: 834.678 | W37: 3356.99 | X37: 0 | Y37: 0.0072130493 | Z37: 0.0011611143
A38: 382 | B38: 382 | C38: EQT | D38: 2020 2423 842 | E38: ח.פ | F38: EQT X Buyout | G38: 27940031 | H38: פנימי | I38: פרייבט אקוויטי | J38: Co-Investment/Direct | K38: חו"ל | L38: לוקסמבורג | M38: Address: 51A Boulevard Royal, L-2449 , Luxembourg | N38: אירופה | O38: לא | P38: 04/09/2023 | Q38: EUR | R38: דיווח מנהל הקרן | S38: קיימת תלות | T38: 11/03/2025 | U38: 4.0219 | V38: 1008.644 | W38: 4056.666 | X38: 0 | Y38: 0.0087164186 | Z38: 0.0014031179
A39: 382 | B39: 382 | C39: Faro Point | D39: 86-2034928 | E39: מספר תאגיד או שותפות בחו"ל | F39: Faro Point FIVF III (F-5) | G39: 27940030 | H39: פנימי | I39: פרייבט אקוויטי | J39: Value Added Real Estate | K39: חו"ל | L39: ארה"ב | M39: Address: 5 Marine View Plz. , Hoboken, NJ 07030, USA | N39: ארה"ב | O39: לא | P39: 23/05/2023 | Q39: USD | R39: מומחה בלתי תלוי | S39: אי-תלות | T39: 31/03/2025 | U39: 3.718 | V39: 1241.419 | W39: 4615.596 | X39: 0 | Y39: 0.0099173726 | Z39: 0.0015964404
A40: 382 | B40: 382 | C40: פורמה | D40: 530278654 | E40: ח.פ | F40: FORMA FUND | G40: 620020351 | H40: פנימי | I40: קרן נדל"ן | J40: Value Added Real Estate | K40: חו"ל | L40: אירופה | M40: Address: 20 Raul Valenberg , Tel Aviv, Israel | N40: אירופה | O40: לא | P40: 03/12/2019 | Q40: EUR | R40: דיווח מנהל הקרן | S40: קיימת תלות | T40: 10/03/2025 | U40: 4.0219 | V40: 1489.066 | W40: 5988.875 | X40: 0 | Y40: 0.01286809 | Z40: 0.0020714295
A41: 382 | B41: 382 | C41: פורמה | D41: 530278654 | E41: ח.פ | F41: FORMA FUND 2 | G41: 620020352 | H41: פנימי | I41: קרן נדל"ן | J41: Value Added Real Estate | K41: חו"ל | L41: ישראל | M41: Address: 20 Raul Valenberg , Tel Aviv, Israel | N41: אירופה | O41: לא | P41: 08/07/2021 | Q41: EUR | R41: דיווח מנהל הקרן | S41: קיימת תלות | T41: 10/03/2025 | U41: 4.0219 | V41: 920.764 | W41: 3703.221 | X41: 0 | Y41: 0.0079569849 | Z41: 0.0012808687
A42: 382 | B42: 382 | C42: Hamilton | D42: 98-1588386 | E42: מספר תאגיד או שותפות בחו"ל | F42: Hamilton Strategic Opp 2020 | G42: 27940009 | H42: פנימי | I42: קרן חוב | J42: Co-Investment/Direct | K42: חו"ל | L42: איי קיימן | M42: Address: 610 Fifth Avenue , New York , NY 10020 | N42: ארה"ב | O42: לא | P42: 24/03/2021 | Q42: USD | R42: מומחה בלתי תלוי | S42: אי-תלות | T42: 13/02/2025 | U42: 3.718 | V42: 1142.666 | W42: 4248.431 | X42: 0 | Y42: 0.0091284582 | Z42: 0.0014694456
A43: 382 | B43: 382 | C43: Hamilton | D43: 98-1588386 | E43: מספר תאגיד או שותפות בחו"ל | F43: Hamilton Strategic Opp VII | G43: 27940023 | H43: פנימי | I43: קרן חוב | J43: Co-Investment/Direct | K43: חו"ל | L43: איי קיימן | M43: Address: 610 Fifth Avenue , New York , NY 10020 | N43: איי קיימן | O43: לא | P43: 14/06/2022 | Q43: USD | R43: מומחה בלתי תלוי | S43: אי-תלות | T43: 23/01/2025 | U43: 3.718 | V43: 3012.395 | W43: 11200.084 | X43: 0 | Y43: 0.024065236 | Z43: 0.0038738804
A44: 382 | B44: 382 | C44: Hamilton | D44: 98-1588386 | E44: מספר תאגיד או שותפות בחו"ל | F44: HAMILTON2016 | G44: 60408895 | H44: פנימי | I44: קרן חוב | J44: Co-Investment/Direct | K44: חו"ל | L44: איי קיימן | M44: Address: 610 Fifth Avenue , New York , NY 10020 | N44: איי קיימן | O44: לא | P44: 16/06/2016 | Q44: USD | R44: מומחה בלתי תלוי | S44: אי-תלות | T44: 24/12/2024 | U44: 3.718 | V44: 109.417 | W44: 406.812 | X44: 0 | Y44: 0.00087410384 | Z44: 0.0001407081
A45: 382 | B45: 382 | C45: HarbourVest | D45: 27330 | E45: פנימי | F45: HARBOURVEST CO INVEST | G45: 62010971 | H45: פנימי | I45: פרייבט אקוויטי | J45: Co-Investment/Direct | K45: חו"ל | L45: איי קיימן | M45: Address: One Financial Center, Boston, Massachusetts 02111 | N45: גלובלי | O45: לא | P45: 16/09/2019 | Q45: USD | R45: דיווח מנהל הקרן | S45: קיימת תלות | T45: 29/01/2025 | U45: 3.718 | V45: 3136.171 | W45: 11660.283 | X45: 0 | Y45: 0.025054051 | Z45: 0.004033054
A46: 382 | B46: 382 | C46: HarbourVest | D46: 27330 | E46: פנימי | F46: HARBOURVEST DOVER X | G46: 27940004 | H46: פנימי | I46: פרייבט אקוויטי | J46: Secondaries | K46: חו"ל | L46: איי קיימן | M46: Address: One Financial Center, Boston, Massachusetts 02111 | N46: גלובלי | O46: לא | P46: 31/12/2019 | Q46: USD | R46: דיווח מנהל הקרן | S46: קיימת תלות | T46: 25/03/2025 | U46: 3.718 | V46: 3755.209 | W46: 13961.867 | X46: 0 | Y46: 0.029999386 | Z46: 0.0048291249
A47: 382 | B47: 382 | C47: IBI | D47: 27841 | E47: פנימי | F47: IBI CCF | G47: 27940010 | H47: פנימי | I47: פרייבט אקוויטי | J47: Venture Debt | K47: חו"ל | L47: איי קיימן | M47: כתובת: אחד העם 9 תל אביב | N47: ארה"ב | O47: כן | P47: 26/05/2021 | Q47: USD | R47: מומחה בלתי תלוי | S47: אי-תלות | T47: 13/03/2025 | U47: 3.718 | V47: 2157.364 | W47: 8021.078 | X47: 0 | Y47: 0.017234615 | Z47: 0.0027743271
A48: 382 | B48: 382 | C48: BI קונסיומר קרדיט | D48: 27841 | E48: פנימי | F48: IBI NEW CCF | G48: 620022591 | H48: פנימי | I48: פרייבט אקוויטי | J48: Other | K48: חו"ל | L48: ישראל | M48: אחד העם 9 תל אביב | N48: ארה"ב | O48: לא | P48: 05/05/2024 | Q48: USD | R48: אחר | T48: 26/02/2025 | U48: 3.718 | V48: 1873.516 | W48: 6965.731 | X48: 0 | Y48: 0.014967028 | Z48: 0.0024093043
A49: 382 | B49: 382 | C49: IBI | D49: 550270045 | E49: מספר שותפות | F49: IBI Pillar Gatingen | G49: 27940016 | H49: פנימי | I49: פרייבט אקוויטי | J49: Value Added Real Estate | K49: חו"ל | L49: ישראל | M49: כתובת: אחד העם 9 תל אביב | N49: אירופה | O49: לא | P49: 13/09/2021 | Q49: EUR | R49: מומחה בלתי תלוי | S49: אי-תלות | T49: 19/01/2025 | U49: 4.0219 | V49: 713.064 | W49: 2867.873 | X49: 0 | Y49: 0.0061621003 | Z49: 0.00099193873
A50: 382 | B50: 382 | C50: Insight Partners | D50: 851058800 | E50: פנימי | F50: INSIGHT PARTNERS XII | G50: 27940012 | H50: פנימי | I50: פרייבט אקוויטי | J50: Value Added Infrastructure | K50: חו"ל | L50: ארה"ב | M50: Address: 1114 Avenue of the Americas , New York , NY | N50: גלובלי | O50: לא | P50: 12/07/2021 | Q50: USD | R50: דיווח מנהל הקרן | S50: קיימת תלות | T50: 11/03/2025 | U50: 3.718 | V50: 3706.436 | W50: 13780.527 | X50: 0 | Y50: 0.029609747 | Z50: 0.0047664032
A51: 382 | B51: 382 | C51: Invesco Credit Partners | D51: ECPGFXU8A2SHKVVGJI15 | E51: LEI | F51: Invesco Credit Partners II | G51: 27940024 | H51: פנימי | I51: קרן חוב | J51: Special Situations Debt | K51: חו"ל | L51: איי קיימן | M51: Address: 225 Liberty st. , New York, NY , 10281 | N51: ארה"ב | O51: לא | P51: 13/07/2022 | Q51: USD | R51: מומחה בלתי תלוי | S51: אי-תלות | T51: 20/03/2025 | U51: 3.718 | V51: 1705.843 | W51: 6342.325 | X51: 0 | Y51: 0.013627536 | Z51: 0.0021936807
A52: 382 | B52: 382 | C52: invesco | D52: 549300FEA3DT84FOZ304 | E52: LEI | F52: Invesco Direct Lending II | G52: 27940036 | H52: פנימי | I52: קרן חוב | J52: Other | K52: חו"ל | L52: לוכסמבורג | M52: 225 Liberty st. , New York, NY , 10281 | N52: ארה"ב | O52: לא | P52: 10/04/2024 | Q52: USD | R52: אחר | T52: 02/03/2025 | U52: 3.718 | V52: 693.152 | W52: 2577.14 | X52: 0 | Y52: 0.0055374133 | Z52: 0.00089138027
A53: 382 | B53: 382 | C53: MIP | D53: ACMHD8HWFMFUIQQ8Y590 | E53: LEI | F53: MACQUARIE | G53: 620109701 | H53: פנימי | I53: פרייבט אקוויטי | J53: Value Added Infrastructure | K53: חו"ל | L53: ארה"ב | M53: Address: 125 west 55th street, New York, NY 10019 | N53: ארה"ב | O53: לא | P53: 15/10/2019 | Q53: USD | R53: דיווח מנהל הקרן | S53: קיימת תלות | T53: 30/03/2025 | U53: 3.718 | V53: 4069.962 | W53: 15132.117 | X53: 0 | Y53: 0.032513862 | Z53: 0.0052338905
A54: 382 | B54: 382 | C54: MIDEAL FUND | D54: 540305869 | E54: ח.פ | F54: MIDEAL FUND | G54: 620005541 | H54: פנימי | I54: פרייבט אקוויטי | J54: Other | K54: חו"ל | L54: לוכסמבורג | M54: ראול ולנברג 20 , תל אביב , ישראל | N54: גרמניה | O54: לא | P54: 12/02/2017 | Q54: EUR | R54: אחר | T54: 31/03/2025 | U54: 4.0219 | V54: 1524.242 | W54: 6130.347 | X54: 0 | Y54: 0.013172067 | Z54: 0.0021203621
A55: 382 | B55: 382 | C55: מונטה | D55: 540296522 | E55: ח.פ | F55: MONETA CAPITAL | G55: 620107071 | H55: פנימי | I55: פרייבט אקוויטי | J55: Value Added Infrastructure | K55: ישראל | L55: ישראל | M55: כתובת: וייצמן 2 , תל אביב , ישראל | N55: ישראל | O55: לא | P55: 06/10/2019 | Q55: USD | R55: דיווח מנהל הקרן | S55: קיימת תלות | T55: 18/02/2025 | U55: 3.718 | V55: 1494.39 | W55: 5556.14 | X55: 0 | Y55: 0.011938288 | Z55: 0.0019217556
A56: 382 | B56: 382 | C56: MORE L1 Alternative Credit Fund LP | D56: 13364 | E56: פנימי | F56: More Alternative Credit CLO | G56: 27940037 | H56: פנימי | I56: קרן גידור (Hedge Fund) | J56: Other | K56: חו"ל | L56: ארה"ב | M56: דרך דוד בן גוריון 2 , רמת גן | N56: ארה"ב | O56: לא | P56: 29/07/2024 | Q56: USD | R56: אחר | T56: 20/03/2025 | U56: 3.718 | V56: 1926.223 | W56: 7161.698 | X56: 0 | Y56: 0.015388096 | Z56: 0.0024770854
A57: 382 | B57: 382 | C57: MV Credit | D57: 13175 | E57: פנימי | F57: MV Credit Senior II | G57: 27940013 | H57: פנימי | I57: פרייבט אקוויטי | J57: Direct Lending Debt | K57: חו"ל | L57: לוקסמבורג | M57: Address: 8 rue lou Hemmer, L-1748 senningerberg, Luxembourg | N57: אירופה | O57: לא | P57: 26/07/2021 | Q57: EUR | R57: מומחה בלתי תלוי | S57: אי-תלות | T57: 04/03/2025 | U57: 4.0219 | V57: 766.203 | W57: 3081.59 | X57: 0 | Y57: 0.0066213074 | Z57: 0.0010658592
A58: 382 | B58: 382 | C58: פאגאיה | E58: אחר | F58: pagaya auto loans | G58: 27940020 | H58: פנימי | I58: פרייבט אקוויטי | J58: Venture Debt | K58: חו"ל | L58: איי קיימן | M58: Address: P.O. Box 309, Ugland House, Grand Cayman, KY1-1104, Cayman Islands | N58: ארה"ב | O58: לא | P58: 30/12/2021 | Q58: USD | R58: מומחה בלתי תלוי | S58: אי-תלות | T58: 20/03/2025 | U58: 3.718 | V58: 1865.83 | W58: 6937.157 | X58: 0 | Y58: 0.014905632 | Z58: 0.0023994211
A59: 382 | B59: 382 | C59: פאגאיה | D59: 28593 | E59: פנימי | F59: Pagaya Opportunity | G59: 27940017 | H59: פנימי | I59: פרייבט אקוויטי | J59: Venture Debt | K59: חו"ל | L59: איי קיימן | M59: Address: P.O. Box 309, Ugland House, Grand Cayman, KY1-1104, Cayman Islands | N59: ארה"ב | O59: לא | P59: 01/11/2021 | Q59: USD | R59: מומחה בלתי תלוי | S59: אי-תלות | T59: 20/03/2025 | U59: 3.718 | V59: 4056.354 | W59: 15081.526 | X59: 0.000458 | Y59: 0.032405158 | Z59: 0.005216392
A60: 382 | B60: 382 | C60: פנתאון | D60: 28055 | E60: פנימי | F60: PGSF VI | G60: 27940000 | H60: פנימי | I60: פרייבט אקוויטי | J60: Secondaries | K60: חו"ל | L60: לוקסמבורג | M60: Address: 10 Finsbury Square, London | N60: ארה"ב | O60: לא | P60: 15/10/2019 | Q60: USD | R60: דיווח מנהל הקרן | S60: קיימת תלות | T60: 31/03/2025 | U60: 3.718 | V60: 2751.565 | W60: 10230.319 | X60: 0 | Y60: 0.021981535 | Z60: 0.0035384585
A61: 382 | B61: 382 | C61: PHOENIX CO INVEST | D61: 13139 | E61: פנימי | F61: THE PHOENIX ANCHOR | G61: 27940038 | H61: פנימי | I61: קרן גידור (Hedge Fund) | J61: Other | K61: חו"ל | L61: ארה"ב | M61: דרך השלום 53 , גבעתיים | N61: ארה"ב | O61: לא | P61: 19/08/2024 | Q61: USD | R61: אחר | T61: 27/02/2025 | U61: 3.718 | V61: 1894.795 | W61: 7044.846 | X61: 0 | Y61: 0.01513702 | Z61: 0.0024366686
A62: 382 | B62: 382 | C62: ויולה | D62: 12169 | E62: פנימי | F62: Viola Credit ALF II | G62: 27940021 | H62: פנימי | I62: פרייבט אקוויטי | J62: Buyout | K62: חו"ל | L62: איי קיימן | M62: Address: 12 Aba Even, Herzelia Pituach, Israel | N62: איי קיימן | O62: לא | P62: 20/01/2022 | Q62: USD | R62: דיווח מנהל הקרן | S62: קיימת תלות | T62: 16/02/2025 | U62: 3.718 | V62: 3346.752 | W62: 12443.224 | X62: 0 | Y62: 0.026736329 | Z62: 0.0043038573
A63: 382 | B63: 382 | C63: פאגאיה | E63: אחר | F63: פאגאיה auto loans | G63: 27940022 | H63: פנימי | I63: פרייבט אקוויטי | J63: Venture Debt | K63: חו"ל | L63: איי קיימן | M63: Address: P.O. Box 309, Ugland House, Grand Cayman, KY1-1104, Cayman Islands | N63: ארה"ב | O63: לא | P63: 24/01/2022 | Q63: USD | R63: מומחה בלתי תלוי | S63: אי-תלות | T63: 20/03/2025 | U63: 3.718 | V63: 1859.738 | W63: 6914.505 | X63: 0 | Y63: 0.014856961 | Z63: 0.0023915864
A64: 382 | B64: 382 | C64: פאגאיה | D64: 28593 | E64: פנימי | F64: פאגאיה אופורטוניטי | G64: 27940025 | H64: פנימי | I64: פרייבט אקוויטי | J64: Venture Debt | K64: חו"ל | L64: איי קיימן | M64: Address: P.O. Box 309, Ugland House, Grand Cayman, KY1-1104, Cayman Islands | N64: ארה"ב | O64: לא | P64: 01/08/2022 | Q64: USD | R64: מומחה בלתי תלוי | S64: אי-תלות | T64: 20/03/2025 | U64: 3.718 | V64: 1424.497 | W64: 5296.281 | X64: 0 | Y64: 0.011379939 | Z64: 0.0018318757
A65: 382 | B65: 382 | C65: פנתאון | D65: 232962336 | E65: פנימי | F65: פנתאון PGCO IV | G65: 27940002 | H65: פנימי | I65: פרייבט אקוויטי | J65: Co-Investment/Direct | K65: חו"ל | L65: לוקסמבורג | M65: Address: 10 Finsbury Square, London | N65: ארה"ב | O65: לא | P65: 18/11/2019 | Q65: USD | R65: דיווח מנהל הקרן | S65: קיימת תלות | T65: 24/03/2025 | U65: 3.718 | V65: 4157.423 | W65: 15457.299 | X65: 0 | Y65: 0.033212569 | Z65: 0.0053463643
A66: 382 | B66: 9479 | C66: Alpha Global L.P | D66: 27512 | E66: פנימי | F66: קרן אלפא | G66: 27940035 | H66: פנימי | I66: פרייבט אקוויטי | J66: Other | K66: ישראל | L66: ישראל | M66: אבא אבן 10 , הרצליה | N66: ישראל | O66: לא | P66: 25/03/2024 | Q66: ILS | R66: אחר | T66: 20/03/2025 | U66: 1 | V66: 355.02 | W66: 355.02 | X66: 0 | Y66: 1 | Z66: 0.0049648533

Sheet לא סחיר כתבי אופציה
A1: מספר קופה/קרן/ח.פ. עבור חברת ביטוח | B1: מספר מסלול | C1: שם מנפיק | D1: מספר מנפיק | E1: סוג מספר מזהה מנפיק | F1: שם נייר ערך | G1: מספר נייר ערך | H1: סוג מספר נייר ערך | I1: ישראל/חו"ל | J1: מדינה לפי חשיפה כלכלית | K1: סטאטוס סחירות | L1: נכס בסיס (כתב אופציה) | M1: ענף מסחר | N1: תאריך פקיעה | O1: בעל עניין/צד קשור | P1: תאריך רכישה | Q1: מטבע פעילות | R1: סוג גורם משערך | S1: תלות/אי-תלות המשערך | T1: תאריך שערוך אחרון | U1: שער מימוש | V1: יחס המרה | W1: ערך נקוב (יחידות) | X1: שער נייר הערך | Y1: שער חליפין | Z1: שווי הוגן (באלפי ש"ח) | AA1: שיעור מנכסי אפיק ההשקעה | AB1: שיעור מסך נכסי ההשקעה
A2: 382 | B2: 382 | C2: אחים דוניץ בע"מ | D2: 520038605 | E2: ח.פ | F2: דוניץ אופציה לא סחירה | G2: 4000101 | H2: פנימי | I2: ישראל | K2: אחר | L2: IL0004000100 | M2: בנייה | O2: לא | P2: 24/02/2025 | Q2: ILS | R2: אחר | S2: קיימת תלות | T2: 27/02/2025 | U2: 0 | V2: 0 | W2: 4332 | X2: 8.9 | Y2: 1 | Z2: 0.386 | AA2: 1 | AB2: 1.3335319e-07
A3: 382 | B3: 7635 | C3: אחים דוניץ בע"מ | D3: 520038605 | E3: ח.פ | F3: דוניץ אופציה לא סחירה | G3: 4000101 | H3: פנימי | I3: ישראל | K3: אחר | L3: IL0004000100 | M3: בנייה | O3: לא | P3: 24/02/2025 | Q3: ILS | R3: אחר | S3: קיימת תלות | T3: 27/02/2025 | U3: 0 | V3: 0 | W3: 21 | X3: 8.9 | Y3: 1 | Z3: 0.002 | AA3: 1 | AB3: 1.0063627e-07
A4: 382 | B4: 9479 | C4: אחים דוניץ בע"מ | D4: 520038605 | E4: ח.פ | F4: דוניץ אופציה לא סחירה | G4: 4000101 | H4: פנימי | I4: ישראל | K4: אחר | L4: IL0004000100 | M4: בנייה | O4: לא | P4: 24/02/2025 | Q4: ILS | R4: אחר | S4: קיימת תלות | T4: 27/02/2025 | U4: 0 | V4: 0 | W4: 222 | X4: 8.9 | Y4: 1 | Z4: 0.02 | AA4: 1 | AB4: 2.7630999e-07

Sheet לא סחיר אופציות
A1: מספר קופה/קרן/ח.פ. עבור חברת ביטוח | B1: מספר מסלול | C1: שם מנפיק | D1: מספר מנפיק | E1: סוג מספר מזהה מנפיק | F1: שם נייר ערך | G1: מספר נייר ערך | H1: סוג מספר נייר ערך | I1: מאפיין עיקרי | J1: ישראל/חו"ל | K1: מדינה לפי חשיפה כלכלית | L1: ענף מסחר | M1: נכס בסיס | N1: תאריך פקיעה | O1: בעל עניין/צד קשור | P1: תאריך רכישה | Q1: מטבע פעילות | R1: סוג גורם משערך | S1: תלות/אי-תלות המשערך | T1: תאריך שערוך אחרון | U1: שער מימוש | V1: יחס המרה | W1: ערך נקוב (יחידות) | X1: שער נייר הערך | Y1: שער חליפין | Z1: שווי הוגן (בש"ח) | AA1: שיעור מנכסי אפיק ההשקעה | AB1: שיעור מסך נכסי ההשקעה

Sheet לא סחיר נגזרים אחרים
A1: מספר קופה/קרן/ח.פ. עבור חברת ביטוח | B1: מספר מסלול | C1: מאפיין עיקרי | D1: מספר עסקה (רגל 1) | E1: מטבע פעילות (רגל 1) | F1: שער חליפין | G1: ערך נקוב (רגל 1) | H1: שווי הוגן במטבע הנסחר (רגל 1) | I1: שיעור מנכסי אפיק ההשקעה (רגל 1) | J1: שיעור מסך נכסי ההשקעה (רגל 1) | K1: מספר עסקה (רגל 2) | L1: מטבע פעילות (רגל 2) | M1: שער חליפין | N1: ערך נקוב (רגל 2) | O1: שווי הוגן במטבע הנסחר (רגל 2) | P1: שיעור מנכסי ההשקעה (רגל 2) | Q1: שיעור מסך אפיק ההשקעה (רגל 2) | R1: שווי הוגן (נטו באלפי ש"ח) | S1: ישראל/חו"ל | T1: מדינה לפי חשיפה כלכלית | U1: סוג הנכס | V1: פקטור מוביל | W1: פקטור נוסף | X1: טיקר | Y1: בעל עניין/צד קשור | Z1: מועד ההתקשרות בעסקה | AA1: מועד סיום חוזי | AB1: תדירות Reset | AC1: סוג הסליקה | AD1: נספח התחשבנות בטחונות - CSA | AE1: גורם מצטט | AF1: ריבית עוגן | AG1: תקופת ריבית עוגן | AH1: שיעור ריבית עוגן | AI1: שער נכס הבסיס במועד ההתקשרות בעסקה | AJ1: שער הנגזר במועד ההתקשרות בעסקה | AK1: האם קיים קנס בגין יציאה מוקדמת | AL1: שיעור הקנס בגין יציאה מוקדמת | AM1: צד נגדי - Counterparty | AN1: שיעור מנכסי אפיק ההשקעה | AO1: שיעור מסך נכסי ההשקעה
A2: 382 | B2: 382 | C2: Funded Forward | D2: 90024359 | E2: USD | F2: 3.718 | G2: -4000000 | H2: -3998.4714 | I2: 0.022801 | J2: -1e-06 | K2: 90024359 | L2: ILS | M2: 1 | N2: 14424000 | O2: 14424 | P2: 5e-06 | Q2: 0.022166 | R2: -442.3165 | S2: ישראל | T2: ישראל | U2: מט"ח | V2: מדינה/איזור גאוגרפי | W2: מטח/ ₪ | X2: USD ILS | Y2: לא | Z2: 15/01/2025 | AA2: 09/04/2025 | AB2: ללא | AC2: Delivery | AD2: כן | AE2: הצד הנגדי | AF2: ללא | AG2: ללא | AH2: ללא | AI2: 3.606 | AJ2: 0 | AK2: לא | AL2: NA | AM2: LUMILIT | AN2: 0.049616 | AO2: 0
A3: 382 | B3: 382 | C3: Funded Forward | D3: 90023456 | E3: USD | F3: 3.718 | G3: -90515000 | H3: -90169.173 | I3: 0.514187 | J3: -3.1e-05 | K3: 90023456 | L3: ILS | M3: 1 | N3: 3.388429e+08 | O3: 338842.9 | P3: 0.000117 | Q3: 0.520726 | R3: 3593.9183 | S3: ישראל | T3: ישראל | U3: מט"ח | V3: מדינה/איזור גאוגרפי | W3: מטח/ ₪ | X3: USD ILS | Y3: לא | Z3: 17/09/2024 | AA3: 17/09/2025 | AB3: ללא | AC3: Delivery | AD3: כן | AE3: הצד הנגדי | AF3: ללא | AG3: ללא | AH3: ללא | AI3: 3.7435 | AJ3: 0 | AK3: לא | AL3: NA | AM3: LUMILIT | AN3: -0.403143 | AO3: 1e-06
A4: 382 | B4: 382 | C4: Funded Forward | D4: 90024704 | E4: USD | F4: 3.718 | G4: 6500000 | H4: 6497.4504 | I4: -0.037051 | J4: 2e-06 | K4: 90024704 | L4: ILS | M4: 1 | N4: -23101000 | O4: -23101 | P4: -8e-06 | Q4: -0.035501 | R4: 1056.5205 | S4: ישראל | T4: ישראל | U4: מט"ח | V4: מדינה/איזור גאוגרפי | W4: מטח/ ₪ | X4: USD ILS | Y4: לא | Z4: 18/02/2025 | AA4: 09/04/2025 | AB4: ללא | AC4: Delivery | AD4: כן | AE4: הצד הנגדי | AF4: ללא | AG4: ללא | AH4: ללא | AI4: 3.554 | AJ4: 0 | AK4: לא | AL4: NA | AM4: LUMILIT | AN4: -0.118514 | AO4: 0
A5: 382 | B5: 382 | C5: Funded Forward | D5: 90024786 | E5: USD | F5: 3.718 | G5: 4000000 | H5: 3998.4302 | I5: -0.022801 | J5: 1e-06 | K5: 90024786 | L5: ILS | M5: 1 | N5: -14212000 | O5: -14212 | P5: -5e-06 | Q5: -0.021841 | R5: 654.16358 | S5: ישראל | T5: ישראל | U5: מט"ח | V5: מדינה/איזור גאוגרפי | W5: מטח/ ₪ | X5: USD ILS | Y5: לא | Z5: 27/02/2025 | AA5: 09/04/2025 | AB5: ללא | AC5: Delivery | AD5: כן | AE5: הצד הנגדי | AF5: ללא | AG5: ללא | AH5: ללא | AI5: 3.553 | AJ5: 0 | AK5: לא | AL5: NA | AM5: LUMILIT | AN5: -0.07338 | AO5: 0
A6: 382 | B6: 382 | C6: Funded Forward | D6: 90024804 | E6: USD | F6: 3.718 | G6: -6500000 | H6: -6497.5021 | I6: 0.037052 | J6: -2e-06 | K6: 90024804 | L6: ILS | M6: 1 | N6: 23367500 | O6: 23367.5 | P6: 8e-06 | Q6: 0.035911 | R6: -790.2127 | S6: ישראל | T6: ישראל | U6: מט"ח | V6: מדינה/איזור גאוגרפי | W6: מטח/ ₪ | X6: USD ILS | Y6: לא | Z6: 03/03/2025 | AA6: 09/04/2025 | AB6: ללא | AC6: Delivery | AD6: כן | AE6: הצד הנגדי | AF6: ללא | AG6: ללא | AH6: ללא | AI6: 3.595 | AJ6: 0 | AK6: לא | AL6: NA | AM6: LUMILIT | AN6: 0.088641 | AO6: 0
A7: 382 | B7: 382 | C7: Funded Forward | D7: 90024342 | E7: USD | F7: 3.718 | G7: -60115000 | H7: -60092.225 | I7: 0.342674 | J7: -2.1e-05 | K7: 90024342 | L7: ILS | M7: 1 | N7: 217796645 | O7: 217796.64 | P7: 7.5e-05 | Q7: 0.334705 | R7: -5626.2471 | S7: ישראל | T7: ישראל | U7: מט"ח | V7: מדינה/איזור גאוגרפי | W7: מטח/ ₪ | X7: USD ILS | Y7: לא | Z7: 14/01/2025 | AA7: 09/04/2025 | AB7: ללא | AC7: Delivery | AD7: כן | AE7: הצד הנגדי | AF7: ללא | AG7: ללא | AH7: ללא | AI7: 3.623 | AJ7: 0 | AK7: לא | AL7: NA | AM7: LUMILIT | AN7: 0.631117 | AO7: -2e-06
A8: 382 | B8: 382 | C8: Funded Forward | D8: 90024340 | E8: EUR | F8: 4.0219 | G8: -21000000 | H8: -21001.008 | I8: 0.119758 | J8: -7e-06 | K8: 90024340 | L8: ILS | M8: 1 | N8: 78315300 | O8: 78315.3 | P8: 2.7e-05 | Q8: 0.120353 | R8: -6148.6529 | S8: ישראל | T8: ישראל | U8: מט"ח | V8: מדינה/איזור גאוגרפי | W8: מטח/ ₪ | X8: EUR ILS | Y8: לא | Z8: 14/01/2025 | AA8: 09/04/2025 | AB8: ללא | AC8: Delivery | AD8: כן | AE8: הצד הנגדי | AF8: ללא | AG8: ללא | AH8: ללא | AI8: 3.7293 | AJ8: 0 | AK8: לא | AL8: NA | AM8: LUMILIT | AN8: 0.689717 | AO8: -2e-06
A9: 382 | B9: 382 | C9: Funded Forward | D9: 90024681 | E9: EUR | F9: 4.0219 | G9: -4100000 | H9: -4100.1947 | I9: 0.023381 | J9: -1e-06 | K9: 90024681 | L9: ILS | M9: 1 | N9: 15278650 | O9: 15278.65 | P9: 5e-06 | Q9: 0.02348 | R9: -1211.923 | S9: ישראל | T9: ישראל | U9: מט"ח | V9: מדינה/איזור גאוגרפי | W9: מטח/ ₪ | X9: EUR ILS | Y9: לא | Z9: 13/02/2025 | AA9: 09/04/2025 | AB9: ללא | AC9: Delivery | AD9: כן | AE9: הצד הנגדי | AF9: ללא | AG9: ללא | AH9: ללא | AI9: 3.7265 | AJ9: 0 | AK9: לא | AL9: NA | AM9: LUMILIT | AN9: 0.135946 | AO9: 0
A10: 382 | B10: 7635 | C10: Funded Forward | D10: 90024342 | E10: USD | F10: 3.718 | G10: -47000 | H10: -46.982195 | I10: 0.813344 | J10: -3e-06 | K10: 90024342 | L10: ILS | M10: 1 | N10: 170281 | O10: 170.281 | P10: 9e-06 | Q10: 0.755663 | R10: -4.3988 | S10: ישראל | T10: ישראל | U10: מט"ח | V10: מדינה/איזור גאוגרפי | W10: מטח/ ₪ | X10: USD ILS | Y10: לא | Z10: 14/01/2025 | AA10: 09/04/2025 | AB10: ללא | AC10: Delivery | AD10: כן | AE10: הצד הנגדי | AF10: ללא | AG10: ללא | AH10: ללא | AI10: 3.623 | AJ10: 0 | AK10: לא | AL10: NA | AM10: LUMILIT | AN10: -1.049773 | AO10: 0
A11: 382 | B11: 7635 | C11: Funded Forward | D11: 90023456 | E11: USD | F11: 3.718 | G11: -65000 | H11: -64.751657 | I11: 1.120964 | J11: -3e-06 | K11: 90023456 | L11: ILS | M11: 1 | N11: 243327.5 | O11: 243.3275 | P11: 1.3e-05 | Q11: 1.079824 | R11: 2.58084 | S11: ישראל | T11: ישראל | U11: מט"ח | V11: מדינה/איזור גאוגרפי | W11: מטח/ ₪ | X11: USD ILS | Y11: לא | Z11: 17/09/2024 | AA11: 17/09/2025 | AB11: ללא | AC11: Delivery | AD11: כן | AE11: הצד הנגדי | AF11: ללא | AG11: ללא | AH11: ללא | AI11: 3.7435 | AJ11: 0 | AK11: לא | AL11: NA | AM11: LUMILIT | AN11: 0.615917 | AO11: 0
A12: 382 | B12: 7635 | C12: Funded Forward | D12: 90024704 | E12: USD | F12: 3.718 | G12: 50000 | H12: 49.980387 | I12: -0.865247 | J12: 3e-06 | K12: 90024704 | L12: ILS | M12: 1 | N12: -177700 | O12: -177.7 | P12: -1e-05 | Q12: -0.788586 | R12: 8.12708 | S12: ישראל | T12: ישראל | U12: מט"ח | V12: מדינה/איזור גאוגרפי | W12: מטח/ ₪ | X12: USD ILS | Y12: לא | Z12: 18/02/2025 | AA12: 09/04/2025 | AB12: ללא | AC12: Delivery | AD12: כן | AE12: הצד הנגדי | AF12: ללא | AG12: ללא | AH12: ללא | AI12: 3.554 | AJ12: 0 | AK12: לא | AL12: NA | AM12: LUMILIT | AN12: 1.939526 | AO12: 0
A13: 382 | B13: 7635 | C13: Funded Forward | D13: 90024786 | E13: USD | F13: 3.718 | G13: 25000 | H13: 24.990188 | I13: -0.432624 | J13: 1e-06 | K13: 90024786 | L13: ILS | M13: 1 | N13: -88825 | O13: -88.825 | P13: -5e-06 | Q13: -0.394182 | R13: 4.08852 | S13: ישראל | T13: ישראל | U13: מט"ח | V13: מדינה/איזור גאוגרפי | W13: מטח/ ₪ | X13: USD ILS | Y13: לא | Z13: 27/02/2025 | AA13: 09/04/2025 | AB13: ללא | AC13: Delivery | AD13: כן | AE13: הצד הנגדי | AF13: ללא | AG13: ללא | AH13: ללא | AI13: 3.553 | AJ13: 0 | AK13: לא | AL13: NA | AM13: LUMILIT | AN13: 0.975725 | AO13: 0
... A19: 382 | B19: 9479 | C19: Funded Forward | D19: 90024340 | E19: EUR | F19: 4.0219 | G19: -310000 | H19: -310.01487 | I19: 0.186085 | J19: -4e-06 | K19: 90024340 | L19: ILS | M19: 1 | N19: 1156083 | O19: 1156.083 | P19: 1.6e-05 | Q19: 0.18604 | R19: -90.7658 | S19: ישראל | T19: ישראל | U19: מט"ח | V19: מדינה/איזור גאוגרפי | W19: מטח/ ₪ | X19: EUR ILS | Y19: לא | Z19: 14/01/2025 | AA19: 09/04/2025 | AB19: ללא | AC19: Delivery | AD19: כן | AE19: הצד הנגדי | AF19: ללא | AG19: ללא | AH19: ללא | AI19: 3.7293 | AJ19: 0 | AK19: לא | AL19: NA | AM19: LUMILIT | AN19: 0.65762 | AO19: -1e-06

Sheet הלוואות
A1: מספר קופה/קרן/ח.פ. עבור חברת ביטוח | B1: מספר מסלול | C1: מספר מזהה לווה | D1: סוג מספר מזהה לווה | E1: שם הלוואה | F1: מספר הלוואה | G1: מאפיין עיקרי | H1: מאפיין הלוואות מתואמות עבור זכויות מקרקעין | I1: ישראל/חו"ל | J1: מדינה לפי חשיפה כלכלית | K1: ענף מסחר | L1: בעל עניין/צד קשור | M1: קונסורציום/ סינדיקציה | N1: מספר קונסורציום/ סינדיקציה | O1: תאריך העמדת הלוואה | P1: דירוג | Q1: שם מדרג | R1: דירוג הלוואה/המנפיק | S1: מטבע פעילות | T1: מח"מ | U1: סוג הריבית | V1: שיעור ריבית | W1: סוג הצמדה | X1: ריבית עוגן | Y1: שיעור תוספת/הפחתה לריבית העוגן | Z1: תשואה לפדיון | AA1: מועד פדיון | AB1: נחיתות חוזית | AC1: סוג בטוחה | AD1: שווי הבטוחות העומדות כנגד ההלוואה | AE1: שיעור הבטוחות מהחוב | AF1: מועד עדכון אחרון לשווי הבטוחות | AG1: זכות חזרה | AH1: מבנה לוח סילוקין | AI1: יעוד הלוואה | AJ1: זכות פירעון מוקדם | AK1: סוג גורם משערך | AL1: שם גורם משערך | AM1: תלות/אי-תלות המשערך | AN1: תאריך שערוך אחרון | AO1: תאריך אחרון בו נבחנה בפועל ירידת ערך | AP1: שיעור ריבית בגין אי-ניצול מסגרת האשראי | AQ1: ערך נקוב | AR1: שער הלוואה | AS1: שער חליפין | AT1: שווי הוגן (באלפי ש"ח) | AU1: שווי הוגן (במטבע הפעילות) | AV1: עלות מופחתת (באלפי ש"ח) | AW1: עלות מופחתת (במטבע הפעילות) | AX1: האם סווג כחוב בעייתי | AY1: השיטה שיושמה בדוח הכספי | AZ1: שיעור מנכסי אפיק ההשקעה | BA1: שיעור מסך נכסי ההשקעה
A2: 382 | B2: 382 | C2: 510960586 | D2: ח.פ | E2: הלוואות לחברים עובדי מדינה (ריבית צמוד פריים) | F2: 29994014 | G2: עמית/מבוטח | I2: ישראל | J2: ישראל | K2: שירותים פיננסיים | L2: לא | M2: לא | O2: 21/02/2017 | P2: NR | Q2: NR | R2: הלוואה | S2: ILS | T2: 2.52 | U2: משתנה | V2: 0.055632 | W2: צמוד למדד אחר | X2: ללא | Y2: 0 | Z2: 0.0513 | AA2: 30/12/2100 | AB2: החוב לא נחות | AE2: 0 | AG2: לא | AJ2: לא | AK2: חברת ציטוט | AL2: פריים | AM2: אי תלות | AN2: 31/03/2025 | AP2: 0 | AQ2: 86789822 | AR2: 102.371 | AS2: 1 | AT2: 88847.242 | AU2: 88847.242 | AX2: לא | AY2: שווי הוגן | AZ2: 1 | BA2: 0.030730448

Sheet לא סחיר מוצרים מובנים
A1: מספר קופה/קרן/ח.פ. עבור חברת ביטוח | B1: מספר מסלול | C1: שם מנפיק | D1: מספר מנפיק | E1: סוג מספר מזהה מנפיק | F1: שם נייר ערך | G1: מספר נייר ערך | H1: סוג מספר נייר ערך | I1: מאפיין עיקרי | J1: ישראל/חו"ל | K1: מדינה לפי חשיפה כלכלית | L1: בעל עניין/צד קשור | M1: נכס בסיס | N1: תאריך רכישה | O1: דירוג | P1: שם מדרג | Q1: דירוג נייר הערך/המנפיק | R1: מטבע פעילות | S1: מח"מ | T1: שיעור ריבית | U1: תשואה לפדיון | V1: סוג גורם משערך | W1: תלות/אי-תלות המשערך | X1: תאריך שערוך אחרון | Y1: ערך נקוב (יחידות) | Z1: שער חליפין | AA1: שער נייר הערך | AB1: שווי הוגן (באלפי ש"ח) | AC1: שיעור מנכסי אפיק ההשקעה | AD1: שיעור מסך נכסי ההשקעה
A2: 382 | B2: 382 | C2: ALESCO PREF FUNDING IX | D2: 549300FP1ZNOHOUNLV32 | E2: LEI | F2: ALESCO PFD VI | G2: KYG015912085 | H2: ISIN | J2: חו"ל | K2: ארה"ב | L2: לא | M2: אחר | N2: 06/08/2019 | O2: NR | P2: NR | Q2: NR | R2: USD | S2: 0 | T2: 0 | U2: 0 | V2: אחר | W2: אי-תלות | X2: 08/08/2019 | Y2: 82 | Z2: 3.718 | AA2: 0.027 | AB2: 0 | AC2: 1 | AD2: 2.8362127e-11

Sheet פיקדונות מעל 3 חודשים
A1: מספר קופה/קרן/ח.פ. עבור חברת ביטוח | B1: מספר מסלול | C1: שם הבנק | D1: מספר מזהה בנק | E1: סוג מספר מזהה בנק | F1: מאפיין עיקרי | G1: תאריך פקיעת פיקדון | H1: ישראל/חו"ל | I1: מדינה לפי חשיפה כלכלית | J1: בעל עניין/צד קשור | K1: דירוג הבנק | L1: שם מדרג | M1: מטבע פעילות | N1: מח"מ | O1: שיעור ריבית | P1: תשואה לפדיון | Q1: שווי מטבעי | R1: שער חליפין | S1: שער פיקדון | T1: שווי הוגן (באלפי ש"ח) | U1: שיעור מנכסי אפיק ההשקעה | V1: שיעור מסך נכסי ההשקעה

Sheet זכויות מקרקעין
A1: מספר קופה/קרן/ח.פ. עבור חברת ביטוח | B1: מספר מסלול | C1: שם הנכס | D1: מאפיין עיקרי | E1: מדינת מיקום נדל"ן | F1: בעל עניין/צד קשור | G1: תאריך רכישה | H1: שימוש עיקרי בנכס | I1: מחזור חיי הנכס | J1: כתובת הנכס | K1: שיעור תשואה בפועל במהלך הרבעון | L1: השיטה שבאמצעותה נקבע שווי הנכס | M1: סוג גורם משערך | N1: שם גורם משערך | O1: תלות/אי-תלות המשערך | P1: תאריך שערוך אחרון | Q1: מטבע פעילות | R1: שווי הוגן (במטבע הפעילות) | S1: שווי הוגן (באלפי ש"ח) | T1: עלות מופחתת (באלפי ש"ח) | U1: עלות מופחתת (במטבע הפעילות) | V1: השיטה שיושמה בדוח הכספי | W1: שיעור מנכסי אפיק ההשקעה | X1: שיעור מסך נכסי ההשקעה

Sheet השקעה בחברות מוחזקות
A1: מספר קופה/קרן/ח.פ. עבור חברת ביטוח | B1: מספר מסלול | C1: שם מנפיק | D1: מספר מנפיק | E1: סוג מספר מזהה מנפיק | F1: שם נייר ערך | G1: מספר נייר ערך | H1: סוג מספר נייר ערך | I1: מאפיין עיקרי | J1: ישראל/חו"ל | K1: מדינה לפי חשיפה כלכלית | L1: ענף מסחר | M1: בעל עניין/צד קשור | N1: מטבע פעילות | O1: סוג גורם משערך | P1: תלות/אי-תלות המשערך | Q1: תאריך שערוך אחרון | R1: תאריך אחרון בו נבחנה בפועל ירידת ערך | S1: שיעור אחזקה באמצעי שליטה | T1: שווי מאזני (באלפי ש"ח) | U1: שווי הוגן (באלפי ש"ח) | V1: שיעור מנכסי אפיק ההשקעה | W1: שיעור מסך נכסי ההשקעה

Sheet נכסים אחרים
A1: מספר קופה/קרן/ח.פ. עבור חברת ביטוח | B1: מספר מסלול | C1: שם הנכס האחר | D1: מספר הנכס האחר | E1: מאפיין עיקרי | F1: ישראל/חו"ל | G1: מדינה לפי חשיפה כלכלית | H1: בעל עניין/צד קשור | I1: תאריך עסקה | J1: מטבע פעילות | K1: תאריך שערוך אחרון | L1: שווי מטבעי | M1: שער חליפין | N1: שווי הוגן (באלפי ש"ח) | O1: עלות מופחתת (באלפי ש"ח) | P1: השיטה שיושמה בדוח הכספי | Q1: שיעור מנכסי אפיק ההשקעה | R1: שיעור מסך נכסי ההשקעה
A2: 382 | B2: 382 | C2: זכאים | D2: 28080000 | E2: חייבים וזכאים | F2: ישראל | G2: ישראל | H2: לא | J2: ILS | K2: 31/03/2025 | L2: -914.075 | M2: 1 | N2: -914.075 | P2: שווי הוגן | Q2: 0.93222306 | R2: -0.00031615989
A3: 382 | B3: 382 | C3: חייבים | D3: 27960000 | E3: חייבים וזכאים | F3: ישראל | G3: ישראל | H3: לא | J3: ILS | K3: 31/03/2025 | L3: 121.81 | M3: 1 | N3: 121.81 | P3: שווי הוגן | Q3: -0.1242283 | R3: 4.2131556e-05
A4: 382 | B4: 382 | C4: זכאים מס עמיתים | D4: 28200000 | E4: חייבים וזכאים מס | F4: ישראל | G4: ישראל | H4: לא | J4: ILS | K4: 31/03/2025 | L4: -188.267 | M4: 1 | N4: -188.267 | P4: שווי הוגן | Q4: 0.19200524 | R4: -6.5117845e-05
A5: 382 | B5: 1404 | C5: זכאים | D5: 28080000 | E5: חייבים וזכאים | F5: ישראל | G5: ישראל | H5: לא | J5: ILS | K5: 31/03/2025 | L5: -8.426 | M5: 1 | N5: -8.426 | P5: שווי הוגן | Q5: 0.88141357 | R5: -0.00031515811
A6: 382 | B6: 1404 | C6: חייבים | D6: 27960000 | E6: חייבים וזכאים | F6: ישראל | G6: ישראל | H6: לא | J6: ILS | K6: 31/03/2025 | L6: 0 | M6: 1 | N6: 0 | P6: שווי הוגן | Q6: -3.5566304e-05 | R6: 1.2717083e-08
A7: 382 | B7: 1404 | C7: זכאים מס עמיתים | D7: 28200000 | E7: חייבים וזכאים מס | F7: ישראל | G7: ישראל | H7: לא | J7: ILS | K7: 31/03/2025 | L7: -1.134 | M7: 1 | N7: -1.134 | P7: שווי הוגן | Q7: 0.11862199 | R7: -4.2414463e-05
A8: 382 | B8: 7635 | C8: זכאים | D8: 28080000 | E8: חייבים וזכאים | F8: ישראל | G8: ישראל | H8: לא | J8: ILS | K8: 31/03/2025 | L8: -5.882 | M8: 1 | N8: -5.882 | P8: שווי הוגן | Q8: 1.0468991 | R8: -0.00031672532
A9: 382 | B9: 7635 | C9: חייבים | D9: 27960000 | E9: חייבים וזכאים | F9: ישראל | G9: ישראל | H9: לא | J9: ILS | K9: 31/03/2025 | L9: 0.264 | M9: 1 | N9: 0.264 | P9: שווי הוגן | Q9: -0.047043245 | R9: 1.4232305e-05
A10: 382 | B10: 7635 | C10: זכאים מס עמיתים | D10: 28200000 | E10: חייבים וזכאים מס | F10: ישראל | G10: ישראל | H10: לא | J10: ILS | K10: 31/03/2025 | L10: -0.001 | M10: 1 | N10: -0.001 | P10: שווי הוגן | Q10: 0.00014416249 | R10: -4.3614433e-08
A11: 382 | B11: 9479 | C11: זכאים | D11: 28080000 | E11: חייבים וזכאים | F11: ישראל | G11: ישראל | H11: לא | J11: ILS | K11: 31/03/2025 | L11: -22.655 | M11: 1 | N11: -22.655 | P11: שווי הוגן | Q11: 0.98596149 | R11: -0.00031682287
A12: 382 | B12: 9479 | C12: חייבים | D12: 27960000 | E12: חייבים וזכאים | F12: ישראל | G12: ישראל | H12: לא | J12: ILS | K12: 31/03/2025 | L12: 1.019 | M12: 1 | N12: 1.019 | P12: שווי הוגן | Q12: -0.044328563 | R12: 1.4244271e-05
A13: 382 | B13: 9479 | C13: זכאים מס עמיתים | D13: 28200000 | E13: חייבים וזכאים מס | F13: ישראל | G13: ישראל | H13: לא | J13: ILS | K13: 31/03/2025 | L13: -1.341 | M13: 1 | N13: -1.341 | P13: שווי הוגן | Q13: 0.058367073 | R13: -1.875532e-05
... A16: 382 | B16: 15404 | C16: זכאים | D16: 28080000 | E16: חייבים וזכאים | F16: ישראל | G16: ישראל | H16: לא | J16: ILS | K16: 31/03/2025 | L16: -4.675 | M16: 1 | N16: -4.675 | P16: שווי הוגן | Q16: 1 | R16: -0.00028043981

Sheet מסגרות אשראי
A1: מספר קופה/קרן/ח.פ. עבור חברת ביטוח | B1: מספר מסלול | C1: מספר מזהה לווה | D1: סוג מספר מזהה לווה | E1: שם הלוואה | F1: מספר הלוואה | G1: תאריך העמדת מסגרת אשראי | H1: ישראל/חו"ל | I1: מדינה לפי חשיפה כלכלית | J1: בעל עניין/צד קשור | K1: דירוג | L1: שם מדרג | M1: דירוג הלוואה/המנפיק | N1: מטבע פעילות | O1: שער חליפין | P1: שיעור ריבית | Q1: סוג הריבית | R1: סכום מסגרת האשראי הראשוני (במטבע הפעילות) | S1: סכום מסגרת האשראי הראשוני (באלפי ש"ח) | T1: שיעור יתרת מסגרת אשראי

Sheet יתרות התחייבות להשקעה
A1: מספר קופה/קרן/ח.פ. עבור חברת ביטוח | B1: מספר מסלול | C1: מאפיין עיקרי | D1: שם שותף כללי קרן השקעות | E1: מספר מזהה שותף כללי קרן השקעות | F1: סוג מספר מזהה שותף כללי קרן השקעות | G1: שם קרן השקעה | H1: מספר מזהה קרן השקעה | I1: סוג מספר מזהה קרן השקעות | J1: מטבע פעילות | K1: תאריך העמדת התחייבות לקרן השקעה | L1: סכום המחויבות הראשוני (במטבע הדיווח של קרן ההשקעה) | M1: סכום המחויבות הראשוני (באלפי ש"ח) | N1: יתרת המחויבות לתקופת הדיווח (במטבע הדיווח של קרן ההשקעה) | O1: יתרת המחויבות לתקופת הדיווח (באלפי ש"ח) | P1: שיעור יתרת המחויבות | Q1: תאריך פקיעת מחויבות להשקעה
A2: 9479 | B2: 9479 | C2: גידור | D2: אלפא | E2: 530278803 | F2: ח.פ | G2: אלפא | H2: 27940035 | I2: פנימי | J2: ILS | K2: 45371 | L2: 300 | M2: 300 | N2: 0 | O2: 0 | P2: 0.00% | Q2: ניתן לצאת מהקרן בכל עת
E3: 1
A4: 382 | B4: 382 | C4: נדל"ן | D4: Alto II | E4: 27092 | F4: פנימי | G4: Alto II | H4: 603880223 | I4: פנימי | J4: USD | K4: 42156 | L4: 1500 | M4: 5577 | N4: 0 | O4: 0 | P4: 0.00% | Q4: 45544
A5: 382 | B5: 382 | C5: נדל"ן | D5: Alto | E5: 27092 | F5: פנימי | G5: Alto III | H5: 620000732 | I5: פנימי | J5: USD | K5: 42744 | L5: 1250 | M5: 4647.5 | N5: 0 | O5: 0 | P5: 0.00% | Q5: 46020
A6: 382 | B6: 382 | C6: Private Equity | D6: Ami Opportunities | E6: 550254411 | F6: שותפות | G6: Ami Opportunities | H6: 603978741 | I6: פנימי | J6: USD | K6: 42352 | L6: 2500 | M6: 9295 | N6: 605.37673 | O6: 2250.7907 | P6: 24.22% | Q6: 46351
A7: 382 | B7: 382 | C7: נדל"ן | D7: בראק קפיטל | E7: 34250659 | F7: LEI | G7: Brack Capital | H7: 9840572 | I7: פנימי | J7: USD | K7: 39335 | L7: 1500 | M7: 5577 | N7: 17.091 | O7: 63.544338 | P7: 1.14% | Q7: 45736
A8: 382 | B8: 382 | C8: Private Equity | D8: Coller International General Partner | E8: 4310 | F8: מספר שותפות | G8: Coller IX-B | H8: 27940040 | I8: פנימי | J8: USD | K8: 45716 | L8: 3200 | M8: 11897.6 | N8: 2377.139 | O8: 8838.2028 | P8: 74.29% | Q8: 49096
A9: 382 | B9: 382 | C9: Private Equity | D9: EQT | E9: 862034928 | F9: שותפות | G9: EQT X Buyout (יורו) | H9: 27940031 | I9: פנימי | J9: EUR | K9: 45173 | L9: 3000 | M9: 12065.7 | N9: 1973.1386 | O9: 7935.7661 | P9: 65.77% | Q9: 48700
A10: 382 | B10: 382 | C10: תשתיות | D10: EQT | E10: 862034928 | F10: שותפות | G10: EQT Infrastructure V (יורו) | H10: 27940014 | I10: פנימי | J10: EUR | K10: 44421 | L10: 2850 | M10: 11462.415 | N10: 559.11375 | O10: 2248.6996 | P10: 19.62% | Q10: 48061
