Workbook
Name Additional_Factor: 'אפשרויות בחירה'!$C$701:$C$850
Name Amoritization: 'אפשרויות בחירה'!$C$546:$C$550
Name Capsule: 'אפשרויות בחירה'!$C$926:$C$928
Name Company_Name: 'File Name Info'!$A$34:$A$120
Name Company_Name_ID: 'File Name Info'!$A$34:$B$120
Name Consortium: 'אפשרויות בחירה'!$C$514:$C$515
Name Country_list: 'אפשרויות בחירה'!$C$4:$C$85
Name Country_list_funds: 'אפשרויות בחירה'!$C$4:$C$103
Name CSA: 'אפשרויות בחירה'!$C$688:$C$689
Name Delivery: 'אפשרויות בחירה'!$C$666:$C$667
Name Dependence_Independence: 'אפשרויות בחירה'!$C$654:$C$655
Name Duration_Underlying_Interest_Rate: 'אפשרויות בחירה'!$C$680:$C$687
Name File_Type: 'File Name Info'!$A$10:$A$12
Name Full_File_Type: 'File Name Info'!$A$11:$B$13
Name Full_Type: 'File Name Info'!$A$2:$B$8
Name Full_Type_Nostro: 'File Name Info'!$A$3:$B$6
Name Full_Year: 'File Name Info'!$A$22:$B$31
Name Fund_Strategy: 'אפשרויות בחירה'!$C$597:$C$621
Name Fund_type: 'אפשרויות בחירה'!$C$328:$C$498
Name Holding_interest: 'אפשרויות בחירה'!$C$146:$C$147
Name In_the_books: 'אפשרויות בחירה'!$C$656:$C$657
Name Industry_Sector: 'אפשרויות בחירה'!$C$1129:$C$1245
Name Industry_sector_all: 'אפשרויות בחירה'!$C$202:$C$327
Name Industry_sectors: 'אפשרויות בחירה'!$C$202:$C$327
Name israel_abroad: 'אפשרויות בחירה'!$C$2:$C$3
Name Issuer_Number_Banks: 'אפשרויות בחירה'!$C$111:$C$113
Name Issuer_Number_Fund: 'אפשרויות בחירה'!$C$114:$C$117
Name issuer_number_loan: 'אפשרויות בחירה'!$C$118:$C$126
Name Issuer_Number_Type: 'אפשרויות בחירה'!$C$104:$C$110
Name Issuer_Number_Type_2: 'אפשרויות בחירה'!$C$1076:$C$1079
Name Issuer_Number_Type_3: 'אפשרויות בחירה'!$C$1081:$C$1085
Name Issuer_Number_Type_V2: 'אפשרויות בחירה'!$C$104:$C$110
Name Issuer_Type_TFunds: 'אפשרויות בחירה'!$C$1087:$C$1089
Name Leading_factor: 'אפשרויות בחירה'!$C$692:$C$700
Name Linked_Type: 'אפשרויות בחירה'!$C$516:$C$519
Name other_investments: 'אפשרויות בחירה'!$C$1000:$C$1033
Name Penalty: 'אפשרויות בחירה'!$C$851:$C$852
Name QTR: 'File Name Info'!$A$15:$A$19
Name Rating_Agency: 'אפשרויות בחירה'!$C$188:$C$201
Name real_estate_lifestage: 'אפשרויות בחירה'!$C$634:$C$642
Name real_estate_loans: 'אפשרויות בחירה'!$C$553:$C$591
Name Real_Estate_Main_Use: 'אפשרויות בחירה'!$C$622:$C$633
Name Recourse_Nonrecourse: 'אפשרויות בחירה'!$C$544:$C$545
Name Repayment_Rights: 'אפשרויות בחירה'!$C$551:$C$552
Name Reset_frequency: 'אפשרויות בחירה'!$C$658:$C$665
Name Security_ID_Number_Type: 'אפשרויות בחירה'!$C$1113:$C$1116
Name Security_Number_Loans: 'אפשרויות בחירה'!$C$131
Name Stock_Exchange: 'אפשרויות בחירה'!$C$1283:$C$1315
Name Stock_Exchange_Gov_Bonds: 'אפשרויות בחירה'!$C$148:$C$181
Name Subordination_Risk: 'אפשרויות בחירה'!$C$186:$C$187
Name Tradeable_Status: 'אפשרויות בחירה'!$C$1272:$C$1281
Name Tradeable_Status_All: 'אפשרויות בחירה'!$C$135:$C$145
Name tradeable_status_bonds: 'אפשרויות בחירה'!$C$1248:$C$1253
Name tradeable_status_funds: 'אפשרויות בחירה'!$C$1118:$C$1119
Name tradeable_status_stock: 'אפשרויות בחירה'!$C$1255:$C$1259
Name Tradeable_Status_v2: 'אפשרויות בחירה'!$C$1121:$C$1126
Name tradeable_status_warrants: 'אפשרויות בחירה'!$C$1261:$C$1265
Name tradeable_status_warrants_v2: 'אפשרויות בחירה'!$C$1267:$C$1269
Name Transaction: 'אפשרויות בחירה'!$C$643:$C$646
Name Type: 'File Name Info'!$A$2:$A$8

Sheet עמוד פתיחה
A1: קובץ דיווח עבור רשימת נכסים ברמת הנכס הבודד (חוזר גופים מוסדיים 2015-9-14)
A3: יש לבחור תחום: | D3: נכסי עמיתים - קופות גמל
A5: האם מדובר בקובץ לממומנה או לציבור: | D5: לציבור
A7: יש לבחור את רבעון הדיווח: | D7: 02
A9: יש לבחור את שנת הדיווח: | D9: 2025
A11: יש לבחור את הגוף המוסדי: | D11: חברה לניהול קופות גמל של העובדים בעיריית תל - אביב יפו בע"מ
A13: ח.פ. הגוף המוסדי: | D13: =IFERROR(VLOOKUP(D11,'File Name Info'!A35:B121,2,0),"תא מחושב") -> 513452003
A15: שם קובץ לשמירה | D15: =IF(D5="לממונה",CONCATENATE(D13, "_",VLOOKUP(D3,Full_Type,2,0),"_",D7,VLOOKUP(D9,Full_Year,2,0),".xlxs"),IF(D5="לציבור",CONCATENATE(D13,"_",VLOOKUP(D3,Full_Type_Nostro,2,0),"_",VLOOKUP(D5,Full_File_Type,2,0),"_",D7,VLOOKUP(D9,Full_Year,2,0),".xlsx"),"שם קובץ לשמירה")) -> 513452003_gm_p_0225.xlsx
A17: פרטי האחראי על הדיווח בגוף המוסדי | B17: שם: | D17: צביקה שמיר , מנכ"ל
B19: מספר טלפון: | D19: 03-5210603
B21: כתובת מייל: | D21: zvi-sha@ovdim-tlv.org.il

Sheet סכום נכסים
C1: ידווח בקבצי נכסי הנוסטרו בלבד
B2: שווי הוגן | C2: עלות מופחתת | D2: השיטה שיושמה בדוח הכספי | E2: שיעור מסך נכסי השקעה
A3: מזומנים ושווי מזומנים | B3: =SUM('מזומנים ושווי מזומנים'!O:O) -> 4743.67 | E3: =SUM('מזומנים ושווי מזומנים'!O:O)/B29 -> 0.030567204
A4: איגרות חוב ממשלתיות | B4: =SUM('איגרות חוב ממשלתיות'!U:U) -> 29527.347 | E4: =SUM('איגרות חוב ממשלתיות'!U:U)/B29 -> 0.19026796
A5: ניירות ערך מסחריים | B5: =SUM('ניירות ערך מסחריים'!AD:AD) -> 0 | E5: =SUM('ניירות ערך מסחריים'!AD:AD)/B29 -> 0
A6: איגרות חוב | B6: =SUM('איגרות חוב'!AD:AD) -> 27965.09 | E6: =SUM('איגרות חוב'!AD:AD)/B29 -> 0.18020111
A7: מניות, מניות בכורה ויחידות השתתפות | B7: =SUM('מניות מבכ ויהש'!U:U) -> 32927.007 | E7: =SUM('מניות מבכ ויהש'!U:U)/B29 -> 0.21217465
A8: קרנות סל | B8: =SUM('קרנות סל'!T:T) -> 31331.432 | E8: =SUM('קרנות סל'!T:T)/B29 -> 0.2018931
A9: קרנות נאמנות | B9: =SUM('קרנות נאמנות'!T:T) -> 1019.059 | E9: =SUM('קרנות נאמנות'!T:T)/B29 -> 0.0065666001
A10: כתבי אופציה | B10: =SUM('כתבי אופציה'!W:W) -> 37.714 | E10: =SUM('כתבי אופציה'!W:W)/B29 -> 0.00024302102
A11: חוזים עתידיים | B11: =SUM('חוזים עתידיים'!R:R) -> 477.517 | E11: =SUM('חוזים עתידיים'!R:R)/B29 -> 0.0030770183
A12: מוצרים מובנים | B12: =SUM('מוצרים מובנים'!Z:Z) -> 0 | E12: =SUM('מוצרים מובנים'!Z:Z)/B29 -> 0
A13: לא סחיר איגרות חוב ממשלתיות | B13: =SUM('לא סחיר איגרות חוב ממשלתיות'!U:U) -> 0 | E13: =SUM('לא סחיר איגרות חוב ממשלתיות'!U:U)/B29 -> 0
A14: לא סחיר איגרות חוב מיועדות | B14: =SUM('לא סחיר איגרות חוב מיועדות'!N:N) -> 0 | E14: =SUM('לא סחיר איגרות חוב מיועדות'!N:N)/B29 -> 0
A15: אפיק השקעה מובטח תשואה | B15: =SUM('אפיק השקעה מובטח תשואה'!F:F) -> 0 | E15: =SUM('אפיק השקעה מובטח תשואה'!F:F)/B29 -> 0
A16: לא סחיר ניירות ערך מסחריים | B16: =SUM('לא סחיר ניירות ערך מסחריים'!AI:AI) -> 0 | E16: =SUM('לא סחיר ניירות ערך מסחריים'!AI:AI)/B29 -> 0
A17: לא סחיר איגרות חוב | B17: =SUM('לא סחיר איגרות חוב'!AG:AG) -> 1748.616 | E17: =SUM('לא סחיר איגרות חוב'!AG:AG)/B29 -> 0.011267711
A18: לא סחיר מניות, מניות בכורה ויחידות השתתפות | B18: =SUM('לא סחיר מניות מבכ ויהש'!X:X) -> 1924.192 | E18: =SUM('לא סחיר מניות מבכ ויהש'!X:X)/B29 -> 0.012399085
A19: קרנות השקעה | B19: =SUM('קרנות השקעה'!W:W) -> 22490.382 | E19: =SUM('קרנות השקעה'!W:W)/B29 -> 0.14492325
A20: לא סחיר כתבי אופציה | B20: =SUM('לא סחיר כתבי אופציה'!Z:Z) -> 0 | E20: =SUM('לא סחיר כתבי אופציה'!Z:Z)/B29 -> 0
A21: לא סחיר אופציות | B21: =SUM('לא סחיר אופציות'!Z:Z) -> 0 | E21: =SUM('לא סחיר אופציות'!Z:Z)/B29 -> 0
A22: לא סחיר נגזרים אחרים | B22: =SUM('לא סחיר נגזרים אחרים'!R:R) -> 1146.421 | E22: =SUM('לא סחיר נגזרים אחרים'!R:R)/B29 -> 0.0073872939
A23: הלוואות | B23: =SUM(הלוואות!AT:AT) -> 0 | E23: =SUM(הלוואות!AT:AT)/B29 -> 0
A24: לא סחיר מוצרים מובנים | B24: =SUM('לא סחיר מוצרים מובנים'!AB:AB) -> 0 | E24: =SUM('לא סחיר מוצרים מובנים'!AB:AB)/B29 -> 0
A25: פיקדונות מעל 3 חודשים | B25: =SUM('פיקדונות מעל 3 חודשים'!T:T) -> 0 | E25: =SUM('פיקדונות מעל 3 חודשים'!T:T)/B29 -> 0
A26: זכויות מקרקעין | B26: =SUM('זכויות מקרקעין'!S:S) -> 0 | E26: =SUM('זכויות מקרקעין'!S:S)/B29 -> 0
A27: השקעה בחברות מוחזקות | B27: =SUM('השקעה בחברות מוחזקות'!U:U) -> 0 | E27: =SUM('השקעה בחברות מוחזקות'!U:U)/B29 -> 0
A28: נכסים אחרים | B28: =SUM('נכסים אחרים'!N:N) -> -150.22495 | E28: =SUM('נכסים אחרים'!N:N)/B29 -> -0.00096801773
A29: סך הכל נכסים | B29: =IF(SUM(B3:B28)=0,0.0001,SUM(B3:B28)) -> 155188.22 | C29: 0 | D29: 0 | E29: =SUM(E3:E28) -> 1
A30: מסגרות אשראי
A31: יתרות התחייבויות להשקעה | B31: =SUM('יתרות התחייבות להשקעה'!O:O) -> 6394.0616 | E31: =B31/B29 -> 0.041201978

Sheet מזומנים ושווי מזומנים
A1: מספר קופה/קרן/ח.פ. עבור חברת ביטוח | B1: מספר מסלול | C1: שם הבנק | D1: מספר מזהה בנק | E1: סוג מספר מזהה בנק | F1: מאפיין עיקרי | G1: ישראל/חו"ל | H1: בעל עניין/צד קשור | I1: דירוג הבנק | J1: שם מדרג | K1: מטבע פעילות | L1: שווי מטבעי | M1: שער חליפין | N1: שיעור ריבית | O1: שווי הוגן (באלפי ש"ח) | P1: שיעור מנכסי אפיק ההשקעה | Q1: שיעור מסך נכסי ההשקעה
A2: 891 | B2: 9956 | C2: בנק לאומי לישראל בע"מ | D2: 10-800 | E2: סימול בנק | F2: מזומן ועו"ש בש"ח | G2: ישראל | H2: לא | I2: AAA | J2: S&P מעלות | K2: ILS | L2: 0 | M2: 1 | N2: 0 | O2: 0 | P2: 1 | Q2: 1
A3: 891 | B3: 9957 | C3: בנק לאומי לישראל בע"מ | D3: 10-800 | E3: סימול בנק | F3: מזומן ועו"ש בש"ח | G3: ישראל | H3: לא | I3: AAA | J3: S&P מעלות | K3: ILS | L3: 236.673 | M3: 1 | N3: 0.0403 | O3: 236.673 | P3: 0.049892312 | Q3: 0.0015363917
A4: 891 | B4: 9957 | C4: פועלים | D4: 12-591 | E4: סימול בנק | F4: מזומן ועו"ש נקוב במט"ח | G4: ישראל | H4: לא | I4: AAA | J4: S&P מעלות | K4: USD | L4: 694.231 | M4: 3.372 | N4: SOFR-1.5% | O4: 2340.946 | P4: 0.49348854 | Q4: 0.015196564
A5: 891 | B5: 9957 | C5: פועלים | D5: 12-591 | E5: סימול בנק | F5: מזומן ועו"ש נקוב במט"ח | G5: ישראל | H5: לא | I5: AAA | J5: S&P מעלות | K5: HKD | L5: 0.001 | M5: 0.429 | N5: 0 | O5: 0.001 | P5: 1.1015147e-07 | Q5: 3.3920217e-09
A6: 891 | B6: 9957 | C6: פועלים | D6: 12-591 | E6: סימול בנק | F6: מזומן ועו"ש נקוב במט"ח | G6: ישראל | H6: לא | I6: AAA | J6: S&P מעלות | K6: EUR | L6: 262.551 | M6: 3.9552 | N6: 0 | O6: 1038.441 | P6: 0.21891091 | Q6: 0.0067411769
A7: 891 | B7: 9957 | C7: פועלים | D7: 12-591 | E7: סימול בנק | F7: מזומן ועו"ש נקוב במט"ח | G7: ישראל | H7: לא | I7: AAA | J7: S&P מעלות | K7: JPY | L7: 183.401 | M7: 0.023369 | N7: 0 | O7: 4.286 | P7: 0.00090350077 | Q7: 2.7822544e-05
A8: 891 | B8: 9957 | C8: פועלים | D8: 12-591 | E8: סימול בנק | F8: מזומן ועו"ש נקוב במט"ח | G8: ישראל | H8: לא | I8: AAA | J8: S&P מעלות | K8: DKK | L8: 0 | M8: 0.5301 | N8: 0 | O8: 0 | P8: -1.1174897e-09 | Q8: -3.4412153e-11
A9: 891 | B9: 9957 | C9: פועלים | D9: 12-591 | E9: סימול בנק | F9: מזומן ועו"ש נקוב במט"ח | G9: חו"ל | H9: לא | I9: AAA | J9: S&P מעלות | K9: sek | L9: 0 | M9: 0.355 | N9: 0 | O9: 0 | P9: -7.4836605e-10 | Q9: -2.3045302e-11
A10: 891 | B10: 9957 | C10: פועלים | D10: 12-591 | E10: סימול בנק | F10: מזומן ועו"ש נקוב במט"ח | G10: ישראל | H10: לא | I10: AAA | J10: S&P מעלות | K10: GBP | L10: 12.772 | M10: 4.6236 | N10: 0 | O10: 59.053 | P10: 0.012448774 | Q10: 0.00038334951
A11: 891 | B11: 9957 | C11: פועלים | D11: 12-591 | E11: סימול בנק | F11: מזומן ועו"ש בש"ח | G11: ישראל | H11: לא | I11: AAA | J11: S&P מעלות | K11: ILS | L11: 982.895 | M11: 1 | N11: 0 | O11: 982.895 | P11: 0.20720151 | Q11: 0.0063805957
A12: 891 | B12: 9957 | C12: פועלים | D12: 12-591 | E12: סימול בנק | F12: מזומן ועו"ש נקוב במט"ח | G12: ישראל | H12: לא | I12: AAA | J12: S&P מעלות | K12: CHF | L12: 19.231 | M12: 4.2314 | N12: 0 | O12: 81.375 | P12: 0.017154346 | Q12: 0.00052825361
A13: 891 | B13: 9958 | C13: בנק לאומי לישראל בע"מ | D13: 10-800 | E13: סימול בנק | F13: מזומן ועו"ש בש"ח | G13: ישראל | H13: לא | I13: AAA | J13: S&P מעלות | K13: ILS | L13: 0 | M13: 1 | N13: 0 | O13: 0 | P13: 1 | Q13: 1

Sheet איגרות חוב ממשלתיות
A1: מספר קופה/קרן/ח.פ. עבור חברת ביטוח | B1: מספר מסלול | C1: שם מנפיק | D1: שם נייר ערך | E1: מספר נייר ערך | F1: מאפיין עיקרי | G1: ישראל/חו"ל | H1: מדינה לפי חשיפה כלכלית | I1: זירת מסחר | J1: דירוג | K1: שם מדרג | L1: מטבע פעילות | M1: מח"מ | N1: מועד פדיון | O1: שיעור ריבית | P1: תשואה לפדיון | Q1: סכום לקבל (במטבע הפעילות) | R1: ערך נקוב (יחידות) | S1: שער חליפין | T1: שער נייר הערך | U1: שווי הוגן (באלפי ש"ח) | V1: עלות מופחתת (באלפי ש"ח) | W1: השיטה שיושמה בדוח הכספי | X1: שיעור מערך נקוב מונפק | Y1: שיעור מנכסי אפיק ההשקעה | Z1: שיעור מסך נכסי ההשקעה
A2: 891 | B2: 9957 | C2: גליל | D2: ממשל צמודה 0527 | E2: IL0011408478 | F2: צמוד למדד המחירים לצרכן בריבית קבועה | G2: ישראל | H2: ישראל | I2: TASE | J2: RF | K2: פנימי | L2: ILS | M2: 1.905 | N2: 31/05/2027 | O2: 0.0075 | P2: 0.02096 | R2: 2122291 | S2: 1 | T2: 115.45 | U2: 2450.185 | W2: שווי הוגן | X2: 8.7e-05 | Y2: 0.082980193 | Z2: 0.015905705
A3: 891 | B3: 9957 | C3: גליל | D3: ממשל צמודה 0545 | E3: IL0011348658 | F3: צמוד למדד המחירים לצרכן בריבית קבועה | G3: ישראל | H3: ישראל | I3: TASE | J3: RF | K3: פנימי | L3: ILS | M3: 17.932 | N3: 31/05/2045 | O3: 0.01 | P3: 0.02023 | R3: 1000000 | S3: 1 | T3: 98.54 | U3: 985.4 | W3: שווי הוגן | X3: 4.4e-05 | Y3: 0.033372453 | Z3: 0.0063968564
A4: 891 | B4: 9957 | C4: גליל | D4: ממשל צמודה 1025 | E4: IL0011359127 | F4: צמוד למדד המחירים לצרכן בריבית קבועה | G4: ישראל | H4: ישראל | I4: TASE | J4: RF | K4: פנימי | L4: ILS | M4: 0.332 | N4: 31/10/2025 | O4: 0.0075 | P4: 0.00599 | R4: 2029976 | S4: 1 | T4: 118.26 | U4: 2400.65 | W4: שווי הוגן | X4: 0.00016 | Y4: 0.081302584 | Z4: 0.015584139
A5: 891 | B5: 9957 | C5: שחר | D5: ממשל שיקלית 0928 | E5: IL0011508798 | F5: לא צמוד למדד המחירים לצרכן ריבית קבועה | G5: ישראל | H5: ישראל | I5: TASE | J5: RF | K5: פנימי | L5: ILS | M5: 3.109 | N5: 28/09/2028 | O5: 0.0225 | P5: 0.03952 | R5: 1521608 | S5: 1 | T5: 96.6 | U5: 1469.873 | W5: שווי הוגן | X5: 4.4e-05 | Y5: 0.049780067 | Z5: 0.00954188
A6: 891 | B6: 9957 | C6: שחר | D6: ממשל שקלית 0927 | E6: IL0012035791 | F6: לא צמוד למדד המחירים לצרכן ריבית קבועה | G6: ישראל | H6: ישראל | I6: TASE | J6: RF | K6: פנימי | L6: ILS | M6: 2.139 | N6: 30/09/2027 | O6: 0.0375 | P6: 0.03974 | R6: 2062192 | S6: 1 | T6: 102.34 | U6: 2110.447 | W6: שווי הוגן | X6: 5.8e-05 | Y6: 0.071474328 | Z6: 0.013700252
A7: 891 | B7: 9957 | C7: שחר | D7: ממשל שקלית 0229 | E7: IL0011948028 | F7: לא צמוד למדד המחירים לצרכן ריבית קבועה | G7: ישראל | H7: ישראל | I7: TASE | J7: RF | K7: פנימי | L7: ILS | M7: 3.45 | N7: 28/02/2029 | O7: 0.0375 | P7: 0.03943 | R7: 1975189 | S7: 1 | T7: 100.61 | U7: 1987.238 | W7: שווי הוגן | X7: 5.6e-05 | Y7: 0.067301598 | Z7: 0.01290042
A8: 891 | B8: 9957 | C8: שחר | D8: ממשל שקלית 0335 | E8: IL0012023326 | F8: לא צמוד למדד המחירים לצרכן ריבית קבועה | G8: ישראל | H8: ישראל | I8: TASE | J8: RF | K8: פנימי | L8: ILS | M8: 8.174 | N8: 30/03/2035 | O8: 0.04 | P8: 0.04114 | R8: 5725974 | S8: 1 | T8: 100.1 | U8: 5731.7 | W8: שווי הוגן | X8: 0.000172 | Y8: 0.19411497 | Z8: 0.0372081
A9: 891 | B9: 9957 | C9: שחר | D9: ממשל שקלית 0347 | E9: IL0011401937 | F9: לא צמוד למדד המחירים לצרכן ריבית קבועה | G9: ישראל | H9: ישראל | I9: TASE | J9: RF | K9: פנימי | L9: ILS | M9: 14.709 | N9: 31/03/2047 | O9: 0.0375 | P9: 0.0447 | R9: 595000 | S9: 1 | T9: 91.05 | U9: 541.747 | W9: שווי הוגן | X9: 2.3e-05 | Y9: 0.018347314 | Z9: 0.0035168266
A10: 891 | B10: 9957 | C10: שחר | D10: ממשלתי שקלית 0142 | E10: IL0011254005 | F10: לא צמוד למדד המחירים לצרכן ריבית קבועה | G10: ישראל | H10: ישראל | I10: TASE | J10: RF | K10: פנימי | L10: ILS | M10: 11.421 | N10: 31/01/2042 | O10: 0.055 | P10: 0.04352 | R10: 5814603 | S10: 1 | T10: 115.63 | U10: 6723.425 | W10: שווי הוגן | X10: 0.000202 | Y10: 0.22770164 | Z10: 0.043646019
A11: 891 | B11: 9957 | C11: גליל | D11: ממשלתית צמודה 0726 | E11: IL0011695645 | F11: צמוד למדד המחירים לצרכן בריבית קבועה | G11: ישראל | H11: ישראל | I11: TASE | J11: RF | K11: פנימי | L11: ILS | M11: 1.078 | N11: 31/07/2026 | O11: 0.001 | P11: 0.02338 | R11: 265000 | S11: 1 | T11: 114.5 | U11: 303.425 | W11: שווי הוגן | X11: 1.3e-05 | Y11: 0.010276067 | Z11: 0.0019697241
A12: 891 | B12: 9957 | C12: שחר | D12: ממשלתית שקלית 0537 | E12: IL0011661803 | F12: לא צמוד למדד המחירים לצרכן ריבית קבועה | G12: ישראל | H12: ישראל | I12: TASE | J12: RF | K12: פנימי | L12: ILS | M12: 10.803 | N12: 31/05/2037 | O12: 0.015 | P12: 0.04253 | R12: 560815 | S12: 1 | T12: 74.8 | U12: 419.49 | W12: שווי הוגן | X12: 1.5e-05 | Y12: 0.014206817 | Z12: 0.0027231732
A13: 891 | B13: 9957 | C13: שחר | D13: ממשלתית שקלית 1.00% 03/30 | E13: IL0011609851 | F13: לא צמוד למדד המחירים לצרכן ריבית קבועה | G13: ישראל | H13: ישראל | I13: TASE | J13: RF | K13: פנימי | L13: ILS | M13: 4.641 | N13: 31/03/2030 | O13: 0.01 | P13: 0.03969 | R13: 3037907 | S13: 1 | T13: 87.63 | U13: 2662.118 | W13: שווי הוגן | X13: 8e-05 | Y13: 0.090157707 | Z13: 0.017281496
A14: 891 | B14: 9957 | C14: שחר | D14: ממשלתית שקלית 1.3% 04/32 | E14: IL0011806606 | F14: לא צמוד למדד המחירים לצרכן ריבית קבועה | G14: ישראל | H14: ישראל | I14: TASE | J14: RF | K14: פנימי | L14: ILS | M14: 6.538 | N14: 30/04/2032 | O14: 0.013 | P14: 0.04048 | R14: 2070926 | S14: 1 | T14: 84.1 | U14: 1741.649 | W14: שווי הוגן | X14: 5.8e-05 | Y14: 0.058984262 | Z14: 0.011306147

Sheet ניירות ערך מסחריים
A1: מספר קופה/קרן/ח.פ. עבור חברת ביטוח | B1: מספר מסלול | C1: שם מנפיק | D1: מספר מנפיק | E1: סוג מספר מזהה מנפיק | F1: שם נייר ערך | G1: מספר נייר ערך | H1: סוג מספר נייר ערך | I1: מאפיין עיקרי | J1: ישראל/חו"ל | K1: מדינה לפי חשיפה כלכלית | L1: זירת מסחר | M1: ענף מסחר | N1: בעל עניין/צד קשור | O1: דירוג | P1: שם מדרג | Q1: דירוג נייר הערך/המנפיק | R1: מטבע פעילות | S1: מח"מ | T1: ריבית עוגן | U1: מועד פדיון | V1: שיעור ריבית | W1: תשואה לפדיון | X1: נחיתות חוזית | Y1: האם סווג כחוב בעייתי | Z1: ערך נקוב (יחידות) | AA1: שער חליפין | AB1: שער נייר הערך | AC1: סכום לקבל (במטבע הפעילות) | AD1: שווי הוגן (באלפי ש"ח) | AE1: עלות מופחתת (באלפי ש"ח) | AF1: עלות מופחתת (במטבע הפעילות) | AG1: השיטה שיושמה בדוח הכספי | AH1: שיעור מערך נקוב מונפק | AI1: שיעור מנכסי אפיק ההשקעה | AJ1: שיעור מסך נכסי ההשקעה
A2: 891 | B2: 9957

Sheet איגרות חוב
A1: מספר קופה/קרן/ח.פ. עבור חברת ביטוח | B1: מספר מסלול | C1: שם מנפיק | D1: מספר מנפיק | E1: סוג מספר מזהה מנפיק | F1: שם נייר ערך | G1: מספר נייר ערך | H1: סוג מספר נייר ערך | I1: מאפיין עיקרי | J1: ישראל/חו"ל | K1: מדינה לפי חשיפה כלכלית | L1: סטאטוס סחירות | M1: זירת מסחר | N1: ענף מסחר | O1: בעל עניין/צד קשור | P1: דירוג | Q1: שם מדרג | R1: דירוג נייר הערך/המנפיק | S1: מטבע פעילות | T1: מח"מ | U1: מועד פדיון | V1: שיעור ריבית | W1: תשואה לפדיון | X1: נחיתות חוזית | Y1: האם סווג כחוב בעייתי | Z1: ערך נקוב (יחידות) | AA1: שער חליפין | AB1: שער נייר הערך | AC1: סכום לקבל (במטבע הפעילות) | AD1: שווי הוגן (באלפי ש"ח) | AE1: עלות מופחתת (באלפי ש"ח) | AF1: עלות מופחתת (במטבע הפעילות) | AG1: השיטה שיושמה בדוח הכספי | AH1: שיעור מערך נקוב מונפק | AI1: שיעור מנכסי אפיק ההשקעה | AJ1: שיעור מסך נכסי ההשקעה
A2: 891 | B2: 9957 | C2: לוויתן בונד בע"מ | D2: 516223864 | E2: ח.פ | F2: LVIATH 6.125% 6/25 | G2: IL0011677742 | H2: ISIN | I2: צמוד למט"ח | J2: חו"ל | K2: ישראל | L2: סחיר | M2: אחר | N2: חיפושי נפט וגז | O2: לא | P2: BB- | Q2: S&P | R2: נייר ערך | S2: USD | T2: 0.133 | U2: 30/06/2025 | V2: 0.06125 | W2: 0.23773 | X2: החוב לא נחות | Y2: לא | Z2: 0 | AA2: 3.372 | AB2: 0 | AC2: 1.296 | AD2: 4.372 | AG2: שווי הוגן | AH2: 0 | AI2: 0.00015632453 | AJ2: 2.8379501e-05
A3: 891 | B3: 9957 | C3: אאורה השקעות בע"מ | D3: 520038274 | E3: ח.פ | F3: אאורה אגח טז | G3: IL0037305799 | H3: ISIN | I3: לא צמוד למדד המחירים לצרכן | J3: ישראל | K3: ישראל | L3: סחיר | M3: TASE | N3: בנייה | O3: לא | P3: A2 | Q3: מידרוג Moodys | R3: נייר ערך | S3: ILS | T3: 1.207 | U3: 30/09/2027 | V3: 0.035 | W3: 0.04885 | X3: החוב לא נחות | Y3: לא | Z3: 155124 | AA3: 1 | AB3: 99.31 | AD3: 154.054 | AG3: שווי הוגן | AH3: 0.001116 | AI3: 0.0055087845 | AJ3: 0.0010000769
A4: 891 | B4: 9957 | C4: אאורה השקעות בע"מ | D4: 520038274 | E4: ח.פ | F4: אאורה אגח יז %3.85 31/01/2029 | G4: IL0011935801 | H4: ISIN | I4: צמוד למדד המחירים לצרכן | J4: ישראל | K4: ישראל | L4: סחיר | M4: TASE | N4: בנייה | O4: לא | P4: A2 | Q4: מידרוג Moodys | R4: נייר ערך | S4: ILS | T4: 2.116 | U4: 31/01/2029 | V4: 0.0385 | W4: 0.03237 | X4: החוב לא נחות | Y4: לא | Z4: 245000 | AA4: 1 | AB4: 111.11 | AD4: 272.219 | AG4: שווי הוגן | AH4: 0.000817 | AI4: 0.0097342621 | AJ4: 0.0017671795
A5: 891 | B5: 9957 | C5: אדמה פתרונות לחקלאות בע"מ | D5: 520043605 | E5: ח.פ | F5: אדמה אגח ב | G5: IL0011109159 | H5: ISIN | I5: צמוד למדד המחירים לצרכן | J5: ישראל | K5: ישראל | L5: סחיר | M5: TASE | N5: כימיה, גומי ופלסטיק | O5: לא | P5: AA- | Q5: S&P מעלות | R5: נייר ערך | S5: ILS | T5: 5.037 | U5: 30/11/2036 | V5: 0.0515 | W5: 0.04176 | X5: החוב לא נחות | Y5: לא | Z5: 0.22 | AA5: 1 | AB5: 148.91 | AD5: 0 | AG5: שווי הוגן | AH5: 0 | AI5: 1.1714678e-08 | AJ5: 2.1267085e-09
A6: 891 | B6: 9957 | C6: או.פי.סי. אנרגיה בע"מ | D6: 514401702 | E6: ח.פ | F6: או פי סי אגח ב' | G6: IL0011660573 | H6: ISIN | I6: צמוד למדד המחירים לצרכן | J6: ישראל | K6: ישראל | L6: סחיר | M6: TASE | N6: אנרגיה | O6: לא | P6: A+ | Q6: S&P מעלות | R6: נייר ערך | S6: ILS | T6: 2.472 | U6: 01/10/2028 | V6: 0.0275 | W6: 0.03084 | X6: החוב לא נחות | Y6: לא | Z6: 337462.57 | AA6: 1 | AB6: 116.37 | AD6: 392.705 | AG6: שווי הוגן | AH6: 0.000453 | AI6: 0.014042695 | AJ6: 0.0025493418
A7: 891 | B7: 9957 | C7: איי.סי.אל גרופ בע"מ (דואלי) | D7: 520027830 | E7: ח.פ | F7: אייסיאל אגח ז | G7: IL0028103724 | H7: ISIN | I7: לא צמוד למדד המחירים לצרכן | J7: ישראל | K7: ישראל | L7: סחיר | M7: TASE | N7: כימיה, גומי ופלסטיק | O7: לא | P7: AA | Q7: S&P מעלות | R7: נייר ערך | S7: ILS | T7: 7.331 | U7: 30/12/2034 | V7: 0.024 | W7: 0.04694 | X7: החוב לא נחות | Y7: לא | Z7: 300000 | AA7: 1 | AB7: 84.92 | AD7: 254.76 | AG7: שווי הוגן | AH7: 0.000191 | AI7: 0.0091099301 | AJ7: 0.0016538368
A8: 891 | B8: 9957 | C8: איירפורט סיטי בע"מ | D8: 511659401 | E8: ח.פ | F8: איירפורט אגח ה | G8: IL0011334872 | H8: ISIN | I8: צמוד למדד המחירים לצרכן | J8: ישראל | K8: ישראל | L8: סחיר | M8: TASE | N8: נדל"ן מניב בישראל | O8: לא | P8: AA | Q8: S&P מעלות | R8: נייר ערך | S8: ILS | T8: 2.014 | U8: 28/02/2029 | V8: 0.0234 | W8: 0.02872 | X8: החוב לא נחות | Y8: לא | Z8: 251891.89 | AA8: 1 | AB8: 116.49 | AD8: 293.429 | AG8: שווי הוגן | AH8: 0.000155 | AI8: 0.010492685 | AJ8: 0.0019048652
A9: 891 | B9: 9957 | C9: אלבר שירותי מימונית בע"מ | D9: 512025891 | E9: ח.פ | F9: אלבר אגח יט | G9: IL0011918245 | H9: ISIN | I9: צמוד למדד המחירים לצרכן | J9: ישראל | K9: ישראל | L9: סחיר | M9: TASE | N9: שירותים | O9: לא | P9: A+ | Q9: S&P מעלות | R9: נייר ערך | S9: ILS | T9: 1.451 | U9: 15/05/2028 | V9: 0.032 | W9: 0.03223 | X9: החוב לא נחות | Y9: לא | Z9: 85200 | AA9: 1 | AB9: 109.13 | AD9: 92.979 | AG9: שווי הוגן | AH9: 0.000129 | AI9: 0.0033248155 | AJ9: 0.00060359436
A10: 891 | B10: 9957 | C10: אלבר שירותי מימונית בע"מ | D10: 512025891 | E10: ח.פ | F10: אלבר אגח כ | G10: IL0011918328 | H10: ISIN | I10: לא צמוד למדד המחירים לצרכן | J10: ישראל | K10: ישראל | L10: סחיר | M10: TASE | N10: שירותים | O10: לא | P10: A+ | Q10: S&P מעלות | R10: נייר ערך | S10: ILS | T10: 1.518 | U10: 20/06/2028 | V10: 0.057 | W10: 0.05189 | X10: החוב לא נחות | Y10: לא | Z10: 83400 | AA10: 1 | AB10: 101.09 | AD10: 84.309 | AG10: שווי הוגן | AH10: 0.000106 | AI10: 0.0030147968 | AJ10: 0.00054731288
A11: 891 | B11: 9957 | C11: אלדן תחבורה בע"מ | D11: 510454333 | E11: ח.פ | F11: אלדן תחבורה אגח ח | G11: IL0011924425 | H11: ISIN | I11: צמוד למדד המחירים לצרכן | J11: ישראל | K11: ישראל | L11: סחיר | M11: TASE | N11: שירותים | O11: לא | P11: A+ | Q11: S&P מעלות | R11: נייר ערך | S11: ILS | T11: 2.168 | U11: 30/09/2029 | V11: 0.0323 | W11: 0.02972 | X11: החוב לא נחות | Y11: לא | Z11: 117600 | AA11: 1 | AB11: 110.07 | AD11: 129.442 | AG11: שווי הוגן | AH11: 0.000228 | AI11: 0.0046287113 | AJ11: 0.00084030648
A12: 891 | B12: 9957 | C12: אלה ר. הנדסת בנין והשקעות בע"מ | D12: 520040015 | E12: ח.פ | F12: אלה ר השקע אגח א | G12: IL0011899502 | H12: ISIN | I12: צמוד למדד המחירים לצרכן | J12: ישראל | K12: ישראל | L12: סחיר | M12: TASE | N12: נדל"ן מניב בישראל | O12: לא | P12: A | Q12: S&P מעלות | R12: נייר ערך | S12: ILS | T12: 2.176 | U12: 01/07/2029 | V12: 0.0249 | W12: 0.03135 | X12: החוב לא נחות | Y12: לא | Z12: 232000 | AA12: 1 | AB12: 108.03 | AD12: 250.63 | AG12: שווי הוגן | AH12: 0.001244 | AI12: 0.0089622317 | AJ12: 0.0016270233
A13: 891 | B13: 9957 | C13: אלומיי קפיטל בע"מ | D13: 520039868 | E13: ח.פ | F13: אלומיי אגח ו | G13: IL0012030743 | H13: ISIN | I13: לא צמוד למדד המחירים לצרכן | J13: ישראל | K13: ישראל | L13: סחיר | M13: TASE | N13: אנרגיה מתחדשת | O13: לא | P13: NR | Q13: NR | R13: NR | S13: ILS | T13: 2.733 | U13: 31/03/2030 | V13: 0.055 | W13: 0.06331 | X13: החוב לא נחות | Y13: לא | Z13: 79000 | AA13: 1 | AB13: 99.42 | AD13: 78.542 | AG13: שווי הוגן | AH13: 0.000241 | AI13: 0.0028085661 | AJ13: 0.0005098733
A14: 891 | B14: 9957 | C14: אלקו בע"מ | D14: 520025370 | E14: ח.פ | F14: אלקו אגח יד 30/05/2032 5.98% | G14: IL0012077520 | H14: ISIN | I14: לא צמוד למדד המחירים לצרכן | J14: ישראל | K14: ישראל | L14: סחיר | M14: TASE | N14: השקעה ואחזקות | O14: לא | P14: AA- | Q14: S&P מעלות | R14: נייר ערך | S14: ILS | T14: 3.801 | U14: 30/05/2032 | V14: 0.0299 | W14: 0.04685 | X14: החוב לא נחות | Y14: לא | Z14: 300000 | AA14: 1 | AB14: 105.62 | AD14: 316.86 | AG14: שווי הוגן | AH14: 0.0015 | AI14: 0.011330556 | AJ14: 0.0020569742
... A52: 891 | B52: 9957 | C52: יו.אמ.איץ' פרופרטיס אינק. | D52: 221890929 | E52: מספר תאגיד או שותפות בחו"ל | F52: יו.אמ.איץ' אגח א | G52: IL0011841678 | H52: ISIN | I52: צמוד למט"ח | J52: ישראל | K52: ארה"ב | L52: סחיר | M52: TASE | N52: נדל"ן מניב בחו"ל | O52: לא | P52: AA- | Q52: S&P מעלות | R52: נייר ערך | S52: USD | T52: 1.592 | U52: 28/02/2027 | V52: 0.0472 | W52: 0.05895 | X52: החוב לא נחות | Y52: לא | Z52: 233000 | AA52: 3.372 | AB52: 31.234 | AD52: 245.396 | AG52: שווי הוגן | AH52: 0.000708 | AI52: 0.0087750697 | AJ52: 0.0015930456
A53: 891 | B53: 9957 | C53: קבוצת יובלים השקעות בע"מ | D53: 514625094 | E53: ח.פ | F53: יובלים אגח ב | G53: IL0011869075 | H53: ISIN | I53: לא צמוד למדד המחירים לצרכן | J53: ישראל | K53: ישראל | L53: סחיר | M53: TASE | N53: בנייה | O53: לא | P53: NR | Q53: NR | R53: NR | S53: ILS | T53: 0.995 | U53: 05/07/2026 | V53: 0.056 | W53: 0.05842 | X53: החוב לא נחות | Y53: לא | Z53: 155378.4 | AA53: 1 | AB53: 99.8 | AC53: 44.283 | AD53: 199.35 | AG53: שווי הוגן | AH53: 0.001142 | AI53: 0.0071285483 | AJ53: 0.0012941324
A54: 891 | B54: 9957 | C54: ירושלים מימון והנפקות (2005) בע"מ | D54: 513682146 | E54: ח.פ | F54: ירושלים הנפ אגח יט | G54: IL0012014333 | H54: ISIN | I54: צמוד למדד המחירים לצרכן | J54: ישראל | K54: ישראל | L54: סחיר | M54: TASE | N54: בנקים | O54: לא | P54: AA- | Q54: S&P מעלות | R54: נייר ערך | S54: ILS | T54: 3.874 | U54: 31/01/2031 | V54: 0.0259 | W54: 0.02747 | X54: החוב לא נחות | Y54: לא | Z54: 134000 | AA54: 1 | AB54: 105.24 | AD54: 141.022 | AG54: שווי הוגן | AH54: 0.000196 | AI54: 0.0050427733 | AJ54: 0.00091547621
A55: 891 | B55: 9957 | C55: ישפרו בע"מ | D55: 516291754 | E55: ח.פ | F55: ישפרו אגח א | G55: IL0012022906 | H55: ISIN | I55: צמוד למדד המחירים לצרכן | J55: ישראל | K55: ישראל | L55: סחיר | M55: TASE | N55: נדל"ן מניב בישראל | O55: לא | P55: NR | Q55: NR | R55: NR | S55: ILS | T55: 2.361 | U55: 31/12/2027 | V55: 0.045 | W55: 0.03339 | X55: החוב לא נחות | Y55: לא | Z55: 215000 | AA55: 1 | AB55: 108.49 | AD55: 233.254 | AG55: שווי הוגן | AH55: 0.000219 | AI55: 0.008340882 | AJ55: 0.0015142221
A56: 891 | B56: 9957 | C56: ישרס חברה להשקעות בע"מ | D56: 520017807 | E56: ח.פ | F56: ישרס אגח טו | G56: IL0061302076 | H56: ISIN | I56: צמוד למדד המחירים לצרכן | J56: ישראל | K56: ישראל | L56: סחיר | M56: TASE | N56: נדל"ן מניב בישראל | O56: לא | P56: AA | Q56: S&P מעלות | R56: נייר ערך | S56: ILS | T56: 1.757 | U56: 16/05/2027 | V56: 0.0158 | W56: 0.02779 | X56: החוב לא נחות | Y56: לא | Z56: 106953 | AA56: 1 | AB56: 116.04 | AD56: 124.108 | AG56: שווי הוגן | AH56: 0.000272 | AI56: 0.0044379714 | AJ56: 0.00080567913
A57: 891 | B57: 9957 | C57: ישרס חברה להשקעות בע"מ | D57: 520017807 | E57: ח.פ | F57: ישרס אגח יח | G57: IL0061302803 | H57: ISIN | I57: צמוד למדד המחירים לצרכן | J57: ישראל | K57: ישראל | L57: סחיר | M57: TASE | N57: נדל"ן מניב בישראל | O57: לא | P57: AA | Q57: S&P מעלות | R57: נייר ערך | S57: ILS | T57: 4.224 | U57: 10/04/2030 | V57: 0.0084 | W57: 0.02787 | X57: החוב לא נחות | Y57: לא | Z57: 272747.26 | AA57: 1 | AB57: 107.28 | AD57: 292.603 | AG57: שווי הוגן | AH57: 0.000356 | AI57: 0.010463162 | AJ57: 0.0018995056
A58: 891 | B58: 9957 | C58: כלל החזקות עסקי ביטוח בע"מ | D58: 520036120 | E58: ח.פ | F58: כלל ביטוח אגח ג | G58: IL0012013913 | H58: ISIN | I58: לא צמוד למדד המחירים לצרכן | J58: ישראל | K58: ישראל | L58: סחיר | M58: TASE | N58: ביטוח | O58: לא | P58: AA- | Q58: S&P מעלות | R58: נייר ערך | S58: ILS | T58: 4.694 | U58: 02/11/2031 | V58: 0.0525 | W58: 0.04653 | X58: החוב לא נחות | Y58: לא | Z58: 204000 | AA58: 1 | AB58: 103.89 | AD58: 211.936 | AG58: שווי הוגן | AH58: 0.000408 | AI58: 0.0075785779 | AJ58: 0.0013758318
A59: 891 | B59: 9957 | C59: כללביט מימון בע"מ | D59: 513754069 | E59: ח.פ | F59: כלל הון אגח יד | G59: IL0012205246 | H59: ISIN | I59: לא צמוד למדד המחירים לצרכן | J59: ישראל | K59: ישראל | L59: סחיר | M59: TASE | N59: ביטוח | O59: לא | P59: AA- | Q59: S&P מעלות | R59: נייר ערך | S59: ILS | T59: 8.511 | U59: 30/09/2039 | V59: 0.0551 | W59: 0.05145 | X59: החוב לא נחות | Y59: לא | Z59: 299000 | AA59: 1 | AB59: 104.59 | AD59: 312.724 | AG59: שווי הוגן | AH59: 0.000598 | AI59: 0.011182661 | AJ59: 0.002030125
A60: 891 | B60: 9957 | C60: בנק לאומי לישראל בע"מ | D60: 520018078 | E60: ח.פ | F60: לאומי אגח 185 | G60: IL0012018219 | H60: ISIN | I60: צמוד למדד המחירים לצרכן | J60: ישראל | K60: ישראל | L60: סחיר | M60: TASE | N60: בנקים | O60: לא | P60: AAA | Q60: S&P מעלות | R60: נייר ערך | S60: ILS | T60: 2.092 | U60: 31/08/2029 | V60: 0.0186 | W60: 0.02568 | X60: החוב לא נחות | Y60: לא | Z60: 193500 | AA60: 1 | AB60: 104.2 | AD60: 201.627 | AG60: שווי הוגן | AH60: 6.7e-05 | AI60: 0.007209954 | AJ60: 0.001308911
A61: 891 | B61: 9957 | C61: בנק לאומי לישראל בע"מ | D61: 520018078 | E61: ח.פ | F61: לאומי אגח 182 | G61: IL0060405391 | H61: ISIN | I61: צמוד למדד המחירים לצרכן | J61: ישראל | K61: ישראל | L61: סחיר | M61: TASE | N61: בנקים | O61: לא | P61: AAA | Q61: S&P מעלות | R61: נייר ערך | S61: ILS | T61: 2.397 | U61: 25/11/2027 | V61: 0.001 | W61: 0.02497 | X61: החוב לא נחות | Y61: לא | Z61: 229000 | AA61: 1 | AB61: 107.95 | AD61: 247.206 | AG61: שווי הוגן | AH61: 7.3e-05 | AI61: 0.0088397897 | AJ61: 0.001604795
A62: 891 | B62: 9957 | C62: בנק לאומי לישראל בע"מ | D62: 520018078 | E62: ח.פ | F62: לאומי אגח 186 | G62: IL0012018391 | H62: ISIN | I62: צמוד למדד המחירים לצרכן | J62: ישראל | K62: ישראל | L62: סחיר | M62: TASE | N62: בנקים | O62: לא | P62: AAA | Q62: S&P מעלות | R62: נייר ערך | S62: ILS | T62: 4.388 | U62: 30/11/2033 | V62: 0.0202 | W62: 0.02636 | X62: החוב לא נחות | Y62: לא | Z62: 656000 | AA62: 1 | AB62: 102.52 | AD62: 672.531 | AG62: שווי הוגן | AH62: 0.000184 | AI62: 0.024048957 | AJ62: 0.0043659008
A63: 891 | B63: 9957 | C63: בנק לאומי לישראל בע"מ | D63: 520018078 | E63: ח.פ | F63: לאומי התח נדח' סד' 405 | G63: IL0060406209 | H63: ISIN | I63: צמוד למדד המחירים לצרכן | J63: ישראל | K63: ישראל | L63: סחיר | M63: TASE | N63: בנקים | O63: לא | P63: AA- | Q63: S&P מעלות | R63: נייר ערך | S63: ILS | T63: 2.692 | U63: 27/03/2028 | V63: 0.015 | W63: 0.02954 | X63: החוב לא נחות | Y63: לא | Z63: 300000 | AA63: 1 | AB63: 109.15 | AD63: 327.45 | AG63: שווי הוגן | AH63: 0.000214 | AI63: 0.011709243 | AJ63: 0.0021257218
A64: 891 | B64: 9957 | C64: בנק לאומי לישראל בע"מ | D64: 520018078 | E64: ח.פ | F64: לאומי התח נדח' סד' 406 | G64: IL0012164237 | H64: ISIN | I64: צמוד למדד המחירים לצרכן | J64: ישראל | K64: ישראל | L64: סחיר | M64: TASE | N64: בנקים | O64: לא | P64: AA- | Q64: S&P מעלות | R64: נייר ערך | S64: ILS | T64: 5.232 | U64: 28/02/2036 | V64: 0.031 | W64: 0.02937 | X64: החוב לא נחות | Y64: לא | Z64: 294000 | AA64: 1 | AB64: 103.76 | AD64: 305.054 | AG64: שווי הוגן | AH64: 0.000192 | AI64: 0.010908401 | AJ64: 0.0019803352
A65: 891 | B65: 9957 | C65: לוזון רונסון | D65: 560040545 | E65: ח.פ | F65: לוזון רונסון אגח א 8.15% 25/09/2030 | G65: IL0012023409 | H65: ISIN | I65: לא צמוד למדד המחירים לצרכן | J65: ישראל | K65: ישראל | L65: סחיר | M65: TASE | N65: בנייה | O65: לא | P65: NR | Q65: NR | R65: NR | S65: ILS | T65: 2.842 | U65: 25/09/2030 | V65: 0.0815 | W65: 0.05673 | X65: החוב לא נחות | Y65: לא | Z65: 143000 | AA65: 1 | AB65: 109.5 | AD65: 156.585 | AG65: שווי הוגן | AH65: 0.000693 | AI65: 0.0055993029 | AJ65: 0.0010165098
... A69: 891 | B69: 9957 | C69: מגה אור החזקות בע"מ | D69: 513257873 | E69: ח.פ | F69: מגה אור אגח יא | G69: IL0011783755 | H69: ISIN | I69: צמוד למדד המחירים לצרכן | J69: ישראל | K69: ישראל | L69: סחיר | M69: TASE | N69: נדל"ן מניב בישראל | O69: לא | P69: A+ | Q69: S&P מעלות | R69: נייר ערך | S69: ILS | T69: 5.11 | U69: 31/03/2032 | V69: 0.0097 | W69: 0.03203 | X69: החוב לא נחות | Y69: לא | Z69: 213529.41 | AA69: 1 | AB69: 103.36 | AD69: 220.704 | AG69: שווי הוגן | AH69: 0.000355 | AI69: 0.0078921259 | AJ69: 0.001432754
A70: 891 | B70: 9957 | C70: מזרחי טפחות חברה להנפקות בע"מ | D70: 520032046 | E70: ח.פ | F70: מז טפ הנפק 52 | G70: IL0023103810 | H70: ISIN | I70: צמוד למדד המחירים לצרכן | J70: ישראל | K70: ישראל | L70: סחיר | M70: TASE | N70: בנקים | O70: לא | P70: AAA | Q70: S&P מעלות | R70: נייר ערך | S70: ILS | T70: 4.979 | U70: 01/07/2030 | V70: 0.002 | W70: 0.02616 | X70: החוב לא נחות | Y70: לא | Z70: 300000 | AA70: 1 | AB70: 104.05 | AC70: 0.703 | AD70: 312.853 | AG70: שווי הוגן | AH70: 8.7e-05 | AI70: 0.011187268 | AJ70: 0.0020309613
A71: 891 | B71: 9957 | C71: מזרחי טפחות חברה להנפקות בע"מ | D71: 520032046 | E71: ח.פ | F71: מזרחי טפ הנפק התח 69 | G71: IL0012021593 | H71: ISIN | I71: צמוד למדד המחירים לצרכן | J71: ישראל | K71: ישראל | L71: סחיר | M71: TASE | N71: בנקים | O71: לא | P71: AA- | Q71: S&P מעלות | R71: נייר ערך | S71: ILS | T71: 3.795 | U71: 25/06/2029 | V71: 0.0336 | W71: 0.02733 | X71: החוב לא נחות | Y71: לא | Z71: 42000 | AA71: 1 | AB71: 107.56 | AD71: 45.175 | AG71: שווי הוגן | AH71: 3.6e-05 | AI71: 0.0016154142 | AJ71: 0.00029326586
A72: 891 | B72: 9957 | C72: מזרחי טפחות חברה להנפקות בע"מ | D72: 520032046 | E72: ח.פ | F72: מזרחי טפחות הנפק 49 | G72: IL0023102820 | H72: ISIN | I72: צמוד למדד המחירים לצרכן | J72: ישראל | K72: ישראל | L72: סחיר | M72: TASE | N72: בנקים | O72: לא | P72: AAA | Q72: S&P מעלות | R72: נייר ערך | S72: ILS | T72: 0.975 | U72: 23/06/2026 | V72: 0.0038 | W72: 0.02561 | X72: החוב לא נחות | Y72: לא | Z72: 413357 | AA72: 1 | AB72: 112.93 | AD72: 466.804 | AG72: שווי הוגן | AH72: 0.000138 | AI72: 0.016692386 | AJ72: 0.0030303727
A73: 891 | B73: 9957 | C73: מימון ישיר מקבוצת ישיר 2006 בע"מ | D73: 513893123 | E73: ח.פ | F73: מימון ישיר אגח ה | G73: IL0011828311 | H73: ISIN | I73: צמוד למדד המחירים לצרכן | J73: ישראל | K73: ישראל | L73: סחיר | M73: TASE | N73: אשראי חוץ בנקאי | O73: לא | P73: A1 | Q73: מידרוג Moodys | R73: נייר ערך | S73: ILS | T73: 2.782 | U73: 31/07/2031 | V73: 0.01 | W73: 0.03107 | X73: החוב לא נחות | Y73: לא | Z73: 325402.5 | AA73: 1 | AB73: 108.19 | AD73: 352.053 | AG73: שווי הוגן | AH73: 0.000181 | AI73: 0.012589017 | AJ73: 0.0022854379
A74: 891 | B74: 9957 | C74: מימון ישיר מקבוצת ישיר 2006 בע"מ | D74: 513893123 | E74: ח.פ | F74: מימון ישיר אגח ו | G74: IL0011916595 | H74: ISIN | I74: צמוד למדד המחירים לצרכן | J74: ישראל | K74: ישראל | L74: סחיר | M74: TASE | N74: אשראי חוץ בנקאי | O74: לא | P74: A1 | Q74: מידרוג Moodys | R74: נייר ערך | S74: ILS | T74: 1.056 | U74: 31/03/2027 | V74: 0.0354 | W74: 0.03425 | X74: החוב לא נחות | Y74: לא | Z74: 226800 | AA74: 1 | AB74: 109.8 | AD74: 249.026 | AG74: שווי הוגן | AH74: 0.000226 | AI74: 0.0089049031 | AJ74: 0.0016166158
A75: 891 | B75: 9957 | C75: מימון ישיר מקבוצת ישיר 2006 בע"מ | D75: 513893123 | E75: ח.פ | F75: מימון ישיר ד | G75: IL0011756603 | H75: ISIN | I75: צמוד למדד המחירים לצרכן | J75: ישראל | K75: ישראל | L75: סחיר | M75: TASE | N75: אשראי חוץ בנקאי | O75: לא | P75: A1 | Q75: מידרוג Moodys | R75: נייר ערך | S75: ILS | T75: 0.179 | U75: 01/02/2026 | V75: 0.01 | W75: 0.03569 | X75: החוב לא נחות | Y75: לא | Z75: 121882.57 | AA75: 1 | AB75: 115.84 | AD75: 141.189 | AG75: שווי הוגן | AH75: 0.000721 | AI75: 0.0050487511 | AJ75: 0.00091656143
A76: 891 | B76: 9957 | C76: מליסרון בע"מ | D76: 520037789 | E76: ח.פ | F76: מליסרון אגח יט | G76: IL0032303989 | H76: ISIN | I76: צמוד למדד המחירים לצרכן | J76: ישראל | K76: ישראל | L76: סחיר | M76: TASE | N76: נדל"ן מניב בישראל | O76: לא | P76: AA | Q76: S&P מעלות | R76: נייר ערך | S76: ILS | T76: 3.744 | U76: 01/07/2029 | V76: 0.0143 | W76: 0.0281 | X76: החוב לא נחות | Y76: לא | Z76: 515317.27 | AA76: 1 | AB76: 111.28 | AC76: 11.062 | AD76: 584.507 | AG76: שווי הוגן | AH76: 0.000267 | AI76: 0.020901295 | AJ76: 0.0037944673
A77: 891 | B77: 9957 | C77: מליסרון בע"מ | D77: 520037789 | E77: ח.פ | F77: מליסרון אגח כא | G77: IL0011946386 | H77: ISIN | I77: צמוד למדד המחירים לצרכן | J77: ישראל | K77: ישראל | L77: סחיר | M77: TASE | N77: נדל"ן מניב בישראל | O77: לא | P77: AA | Q77: S&P מעלות | R77: נייר ערך | S77: ILS | T77: 5.598 | U77: 01/01/2037 | V77: 0.0361 | W77: 0.02928 | X77: החוב לא נחות | Y77: לא | Z77: 292500 | AA77: 1 | AB77: 111.6 | AC77: 6.49 | AD77: 332.92 | AG77: שווי הוגן | AH77: 0.000187 | AI77: 0.011904856 | AJ77: 0.0021612339
A78: 891 | B78: 9957 | C78: מליסרון בע"מ | D78: 520037789 | E78: ח.פ | F78: מליסרון אגח כ | G78: IL0032304227 | H78: ISIN | I78: צמוד למדד המחירים לצרכן | J78: ישראל | K78: ישראל | L78: סחיר | M78: TASE | N78: נדל"ן מניב בישראל | O78: לא | P78: AA | Q78: S&P מעלות | R78: נייר ערך | S78: ILS | T78: 4.692 | U78: 01/07/2030 | V78: 0.0025 | W78: 0.02702 | X78: החוב לא נחות | Y78: לא | Z78: 228593.93 | AA78: 1 | AB78: 102.52 | AC78: 3.385 | AD78: 237.739 | AG78: שווי הוגן | AH78: 0.000171 | AI78: 0.0085012929 | AJ78: 0.0015433435
A79: 891 | B79: 9957 | C79: מנורה מבטחים גיוס הון בע"מ | D79: 513937714 | E79: ח.פ | F79: מנורה הון התח סד' ט | G79: IL0012193699 | H79: ISIN | I79: לא צמוד למדד המחירים לצרכן | J79: ישראל | K79: ישראל | L79: סחיר | M79: TASE | N79: ביטוח | O79: לא | P79: Aa3 | Q79: מידרוג Moodys | R79: נייר ערך | S79: ILS | T79: 6.099 | U79: 30/09/2035 | V79: 0.0502 | W79: 0.04789 | X79: החוב לא נחות | Y79: לא | Z79: 220000 | AA79: 1 | AB79: 103.09 | AD79: 226.798 | AG79: שווי הוגן | AH79: 0.00055 | AI79: 0.0081100406 | AJ79: 0.0014723147
A80: 891 | B80: 9957 | C80: מניף - שירותים פיננסים בע"מ | D80: 512764408 | E80: ח.פ | F80: מניף אגח א | G80: IL0011858839 | H80: ISIN | I80: לא צמוד למדד המחירים לצרכן | J80: ישראל | K80: ישראל | L80: סחיר | M80: TASE | N80: אשראי חוץ בנקאי | O80: לא | P80: A3 | Q80: מידרוג Moodys | R80: נייר ערך | S80: ILS | T80: 0.731 | U80: 30/09/2026 | V80: 0.114 | W80: 0.0591 | X80: החוב לא נחות | Y80: לא | Z80: 196310 | AA80: 1 | AB80: 102.52 | AD80: 201.257 | AG80: שווי הוגן | AH80: 0.000812 | AI80: 0.0071967236 | AJ80: 0.0013065091
A81: 891 | B81: 9957 | C81: מניף - שירותים פיננסים בע"מ | D81: 512764408 | E81: ח.פ | F81: מניף אגח ג | G81: IL0012167206 | H81: ISIN | I81: לא צמוד למדד המחירים לצרכן | J81: ישראל | K81: ישראל | L81: סחיר | M81: TASE | N81: אשראי חוץ בנקאי | O81: לא | P81: A3 | Q81: מידרוג Moodys | R81: נייר ערך | S81: ILS | T81: 3.107 | U81: 30/11/2029 | V81: 0.064 | W81: 0.05565 | X81: החוב לא נחות | Y81: לא | Z81: 146000 | AA81: 1 | AB81: 103.33 | AD81: 150.862 | AG81: שווי הוגן | AH81: 0.000422 | AI81: 0.0053946477 | AJ81: 0.00097935627
A82: 891 | B82: 9957 | C82: קבוצת מנרב בע"מ | D82: 520034505 | E82: ח.פ | F82: מנרב אגח ד | G82: IL0015501690 | H82: ISIN | I82: צמוד למדד המחירים לצרכן | J82: ישראל | K82: ישראל | L82: סחיר | M82: TASE | N82: בנייה | O82: לא | P82: Baa1 | Q82: מידרוג Moodys | R82: נייר ערך | S82: ILS | T82: 3.546 | U82: 15/04/2032 | V82: 0.0207 | W82: 0.03721 | X82: החוב לא נחות | Y82: לא | Z82: 335231.8 | AA82: 1 | AB82: 107.9 | AD82: 361.715 | AG82: שווי הוגן | AH82: 0.000803 | AI82: 0.012934524 | AJ82: 0.0023481621
A83: 891 | B83: 9957 | C83: נאוויטס פטרוליום, שותפות מוגבלת | D83: 550263107 | E83: מספר שותפות | F83: נאוויטס פטרו אגח ג | G83: IL0011815938 | H83: ISIN | I83: לא צמוד למדד המחירים לצרכן | J83: ישראל | K83: ישראל | L83: סחיר | M83: TASE | N83: חיפושי נפט וגז | O83: לא | P83: A- | Q83: S&P מעלות | R83: נייר ערך | S83: ILS | T83: 1.709 | U83: 15/10/2028 | V83: 0.0525 | W83: 0.05182 | X83: החוב לא נחות | Y83: לא | Z83: 405000 | AA83: 1 | AB83: 102.65 | AD83: 415.733 | AG83: שווי הוגן | AH83: 0.001227 | AI83: 0.014866125 | AJ83: 0.0026988292
A84: 891 | B84: 9957 | C84: נאוויטס פטרוליום, שותפות מוגבלת | D84: 550263107 | E84: מספר שותפות | F84: נאוויטס פטרו אגח ה | G84: IL0011979122 | H84: ISIN | I84: לא צמוד למדד המחירים לצרכן | J84: ישראל | K84: ארה"ב | L84: סחיר | M84: TASE | N84: חיפושי נפט וגז | O84: לא | P84: A- | Q84: S&P מעלות | R84: נייר ערך | S84: ILS | T84: 2.554 | U84: 31/12/2028 | V84: 0.065 | W84: 0.05201 | X84: החוב לא נחות | Y84: לא | Z84: 287000 | AA84: 1 | AB84: 103.44 | AD84: 296.873 | AG84: שווי הוגן | AH84: 0.000574 | AI84: 0.010615836 | AJ84: 0.0019272224
A85: 891 | B85: 9957 | C85: נאוויטס פטרוליום, שותפות מוגבלת | D85: 550263107 | E85: מספר שותפות | F85: נאוויטס פטרו אגח ו | G85: IL0012048257 | H85: ISIN | I85: לא צמוד למדד המחירים לצרכן | J85: ישראל | K85: ישראל | L85: סחיר | M85: TASE | N85: חיפושי נפט וגז | O85: לא | P85: A- | Q85: S&P מעלות | R85: נייר ערך | S85: ILS | T85: 3.129 | U85: 30/09/2029 | V85: 0.067 | W85: 0.05114 | X85: החוב לא נחות | Y85: לא | Z85: 240000 | AA85: 1 | AB85: 106.88 | AD85: 256.512 | AG85: שווי הוגן | AH85: 0.000264 | AI85: 0.0091725797 | AJ85: 0.0016652104
A86: 891 | B86: 9957 | C86: ע.י נופר אנרגי' בע"מ | D86: 514599943 | E86: ח.פ | F86: נופר אנרג אגח א | G86: IL0011793408 | H86: ISIN | I86: צמוד למדד המחירים לצרכן | J86: ישראל | K86: ישראל | L86: סחיר | M86: TASE | N86: אנרגיה מתחדשת | O86: לא | P86: A3 | Q86: מידרוג Moodys | R86: נייר ערך | S86: ILS | T86: 2.159 | U86: 31/12/2027 | V86: 0.0148 | W86: 0.02986 | X86: החוב לא נחות | Y86: לא | Z86: 285780 | AA86: 1 | AB86: 111.27 | AD86: 317.987 | AG86: שווי הוגן | AH86: 0.000983 | AI86: 0.011370871 | AJ86: 0.002064293
A87: 891 | B87: 9957 | C87: חברה לנכסים ולבנין בע"מ | D87: 520025438 | E87: ח.פ | F87: נכסים ובנין אגח י | G87: IL0011936304 | H87: ISIN | I87: צמוד למדד המחירים לצרכן | J87: ישראל | K87: ישראל | L87: סחיר | M87: TASE | N87: נדל"ן מניב בישראל | O87: לא | P87: A | Q87: S&P מעלות | R87: נייר ערך | S87: ILS | T87: 3.557 | U87: 01/07/2029 | V87: 0.0362 | W87: 0.03002 | X87: החוב לא נחות | Y87: לא | Z87: 125800 | AA87: 1 | AB87: 110.37 | AD87: 138.845 | AG87: שווי הוגן | AH87: 6.9e-05 | AI87: 0.004964957 | AJ87: 0.00090134926
A88: 891 | B88: 9957 | C88: נמקו ריאליטי לטד | D88: 1905761 | E88: מספר תאגיד או שותפות בחו"ל | F88: נמקו אגח ב' 2020/2032 4.5% | G88: IL0011602583 | H88: ISIN | I88: לא צמוד למדד המחירים לצרכן | J88: ישראל | K88: ארה"ב | L88: סחיר | M88: TASE | N88: נדל"ן מניב בחו"ל | O88: לא | P88: AA- | Q88: S&P מעלות | R88: נייר ערך | S88: ILS | T88: 3.359 | U88: 15/10/2032 | V88: 0.045 | W88: 0.05524 | X88: החוב לא נחות | Y88: לא | Z88: 261941.61 | AA88: 1 | AB88: 97.83 | AD88: 256.257 | AG88: שווי הוגן | AH88: 0.000324 | AI88: 0.0091634782 | AJ88: 0.0016635581
A89: 891 | B89: 9957 | C89: נמקו ריאליטי לטד | D89: 1905761 | E89: מספר תאגיד או שותפות בחו"ל | F89: נמקו אגח ג | G89: IL0011987612 | H89: ISIN | I89: לא צמוד למדד המחירים לצרכן | J89: ישראל | K89: ישראל | L89: סחיר | M89: TASE | N89: נדל"ן מניב בחו"ל | O89: לא | P89: AA | Q89: S&P מעלות | R89: נייר ערך | S89: ILS | T89: 1.877 | U89: 30/06/2027 | V89: 0.0635 | W89: 0.0533 | X89: החוב לא נחות | Y89: לא | Z89: 139680 | AA89: 1 | AB89: 102.04 | AD89: 142.529 | AG89: שווי הוגן | AH89: 0.000351 | AI89: 0.0050966931 | AJ89: 0.00092526493
A90: 891 | B90: 9957 | C90: נמקו ריאליטי לטד | D90: 1905761 | E90: מספר תאגיד או שותפות בחו"ל | F90: נמקו אגח ד 15/04/2029 6.25% | G90: IL0012064734 | H90: ISIN | I90: לא צמוד למדד המחירים לצרכן | J90: ישראל | K90: ישראל | L90: סחיר | M90: TASE | N90: נדל"ן מניב בחו"ל | O90: לא | P90: AA | Q90: S&P מעלות | R90: נייר ערך | S90: ILS | T90: 3.398 | U90: 15/04/2029 | V90: 0.0625 | W90: 0.05285 | X90: החוב לא נחות | Y90: לא | Z90: 138000 | AA90: 1 | AB90: 104.82 | AD90: 144.652 | AG90: שווי הוגן | AH90: 0.000251 | AI90: 0.005172578 | AJ90: 0.00093904124
... A93: 891 | B93: 9957 | C93: SILVERSTEIN PROPERTIES LTD | D93: 1970336 | E93: מספר תאגיד או שותפות בחו"ל | F93: סילברסטין אגח ג | G93: IL0012116484 | H93: ISIN | I93: לא צמוד למדד המחירים לצרכן | J93: ישראל | K93: ארה"ב | L93: סחיר | M93: TASE | N93: נדל"ן מניב בחו"ל | O93: לא | P93: AA | Q93: S&P מעלות | R93: נייר ערך | S93: ILS | T93: 3.96 | U93: 31/12/2030 | V93: 0.0674 | W93: 0.05684 | X93: החוב לא נחות | Y93: לא | Z93: 277000 | AA93: 1 | AB93: 104.44 | AD93: 289.299 | AG93: שווי הוגן | AH93: 0.000972 | AI93: 0.010344999 | AJ93: 0.0018780539
A94: 891 | B94: 9957 | C94: קבוצת עזריאלי בע"מ (לשעבר קנית מימון) | D94: 510960719 | E94: ח.פ | F94: עזריאלי אגח ד | G94: IL0011386500 | H94: ISIN | I94: צמוד למדד המחירים לצרכן | J94: ישראל | K94: ישראל | L94: סחיר | M94: TASE | N94: נדל"ן מניב בישראל | O94: לא | P94: AA+ | Q94: S&P מעלות | R94: נייר ערך | S94: ILS | T94: 2.678 | U94: 05/07/2030 | V94: 0.0134 | W94: 0.02803 | X94: החוב לא נחות | Y94: לא | Z94: 294117.65 | AA94: 1 | AB94: 114.07 | AC94: 37.442 | AD94: 372.942 | AG94: שווי הוגן | AH94: 0.000133 | AI94: 0.013335986 | AJ94: 0.0024210443
A95: 891 | B95: 9957 | C95: קבוצת עזריאלי בע"מ (לשעבר קנית מימון) | D95: 510960719 | E95: ח.פ | F95: עזריאלי אגח ה | G95: IL0011566036 | H95: ISIN | I95: צמוד למדד המחירים לצרכן | J95: ישראל | K95: ישראל | L95: סחיר | M95: TASE | N95: נדל"ן מניב בישראל | O95: לא | P95: Aa1 | Q95: מידרוג Moodys | R95: נייר ערך | S95: ILS | T95: 1.957 | U95: 30/06/2028 | V95: 0.0177 | W95: 0.02822 | X95: החוב לא נחות | Y95: לא | Z95: 170780.3 | AA95: 1 | AB95: 114.73 | AD95: 195.936 | AG95: שווי הוגן | AH95: 7e-05 | AI95: 0.0070064588 | AJ95: 0.001271968
A96: 891 | B96: 9957 | C96: קבוצת עזריאלי בע"מ (לשעבר קנית מימון) | D96: 510960719 | E96: ח.פ | F96: עזריאלי אגח ז | G96: IL0011786725 | H96: ISIN | I96: צמוד למדד המחירים לצרכן | J96: ישראל | K96: ישראל | L96: סחיר | M96: TASE | N96: נדל"ן מניב בישראל | O96: לא | P96: AA+ | Q96: S&P מעלות | R96: נייר ערך | S96: ILS | T96: 6.416 | U96: 02/07/2036 | V96: 0.009 | W96: 0.02841 | X96: החוב לא נחות | Y96: לא | Z96: 361469.39 | AA96: 1 | AB96: 101.93 | AC96: 10.598 | AD96: 379.044 | AG96: שווי הוגן | AH96: 0.000134 | AI96: 0.013554176 | AJ96: 0.0024606551
A97: 891 | B97: 9957 | C97: קבוצת עזריאלי בע"מ (לשעבר קנית מימון) | D97: 510960719 | E97: ח.פ | F97: עזריאלי אגח ט | G97: IL0012092537 | H97: ISIN | I97: צמוד למדד המחירים לצרכן | J97: ישראל | K97: ישראל | L97: סחיר | M97: TASE | N97: נדל"ן מניב בישראל | O97: לא | P97: Aa1 | Q97: מידרוג Moodys | R97: נייר ערך | S97: ILS | T97: 11.936 | U97: 02/01/2046 | V97: 0.0367 | W97: 0.03162 | X97: החוב לא נחות | Y97: לא | Z97: 150000 | AA97: 1 | AB97: 109.54 | AC97: 2.835 | AD97: 167.145 | AG97: שווי הוגן | AH97: 4.6e-05 | AI97: 0.0059769112 | AJ97: 0.0010850617
A98: 891 | B98: 9957 | C98: עמרם אברהם חברה לבנין בע"מ | D98: 513201582 | E98: ח.פ | F98: עמרם אברהם אגח א | G98: IL0011880445 | H98: ISIN | I98: לא צמוד למדד המחירים לצרכן | J98: ישראל | K98: ישראל | L98: סחיר | M98: TASE | N98: בנייה | O98: לא | P98: A3 | Q98: מידרוג Moodys | R98: נייר ערך | S98: ILS | T98: 1.385 | U98: 31/05/2027 | V98: 0.06 | W98: 0.05236 | X98: החוב לא נחות | Y98: לא | Z98: 0.38 | AA98: 1 | AB98: 101.65 | AD98: 0 | AG98: שווי הוגן | AH98: 0 | AI98: 1.3812579e-08 | AJ98: 2.5075662e-09
A99: 891 | B99: 9957 | C99: בנק הפועלים בע"מ | D99: 520000118 | E99: ח.פ | F99: פועלים אגח 200 | G99: IL0066204962 | H99: ISIN | I99: צמוד למדד המחירים לצרכן | J99: ישראל | K99: ישראל | L99: סחיר | M99: TASE | N99: בנקים | O99: לא | P99: AAA | Q99: S&P מעלות | R99: נייר ערך | S99: ILS | T99: 3.335 | U99: 09/12/2031 | V99: 0.001 | W99: 0.02573 | X99: החוב לא נחות | Y99: לא | Z99: 86800 | AA99: 1 | AB99: 105.19 | AD99: 91.305 | AG99: שווי הוגן | AH99: 8.8e-05 | AI99: 0.0032649609 | AJ99: 0.00059272822
A100: 891 | B100: 9957 | C100: בנק הפועלים בע"מ | D100: 520000118 | E100: ח.פ | F100: פועלים אגח 201 | G100: IL0011913451 | H100: ISIN | I100: צמוד למדד המחירים לצרכן | J100: ישראל | K100: ישראל | L100: סחיר | M100: TASE | N100: בנקים | O100: לא | P100: AAA | Q100: S&P מעלות | R100: נייר ערך | S100: ILS | T100: 3.715 | U100: 29/11/2032 | V100: 0.0139 | W100: 0.02511 | X100: החוב לא נחות | Y100: לא | Z100: 229600 | AA100: 1 | AB100: 105.13 | AD100: 241.378 | AG100: שווי הוגן | AH100: 0.000143 | AI100: 0.0086314221 | AJ100: 0.0015669674
A101: 891 | B101: 9957 | C101: בנק הפועלים בע"מ | D101: 520000118 | E101: ח.פ | F101: פועלים אגח 203 | G101: IL0011998684 | H101: ISIN | I101: צמוד למדד המחירים לצרכן | J101: ישראל | K101: ישראל | L101: סחיר | M101: TASE | N101: בנקים | O101: לא | P101: AAA | Q101: S&P מעלות | R101: נייר ערך | S101: ILS | T101: 2.804 | U101: 02/12/2030 | V101: 0.0175 | W101: 0.02447 | X101: החוב לא נחות | Y101: לא | Z101: 265106 | AA101: 1 | AB101: 115.29 | AD101: 305.641 | AG101: שווי הוגן | AH101: 0.000119 | AI101: 0.010929367 | AJ101: 0.0019841414
A102: 891 | B102: 9957 | C102: בנק הפועלים בע"מ | D102: 520000118 | E102: ח.פ | F102: פועלים התח נד יב | G102: IL0012141219 | H102: ISIN | I102: צמוד למדד המחירים לצרכן | J102: ישראל | K102: ישראל | L102: סחיר | M102: TASE | N102: בנקים | O102: לא | P102: AA- | Q102: S&P מעלות | R102: נייר ערך | S102: ILS | T102: 6.56 | U102: 28/11/2032 | V102: 0.0345 | W102: 0.02903 | X102: החוב לא נחות | Y102: לא | Z102: 290000 | AA102: 1 | AB102: 106.85 | AD102: 309.865 | AG102: שווי הוגן | AH102: 0.000197 | AI102: 0.011080423 | AJ102: 0.0020115644
A103: 891 | B103: 9957 | C103: בנק הפועלים בע"מ | D103: 520000118 | E103: ח.פ | F103: פועלים התחייבות נדחים ו | G103: IL0066205530 | H103: ISIN | I103: צמוד למדד המחירים לצרכן | J103: ישראל | K103: ישראל | L103: סחיר | M103: TASE | N103: בנקים | O103: לא | P103: AA- | Q103: S&P מעלות | R103: נייר ערך | S103: ILS | T103: 2.673 | U103: 13/03/2028 | V103: 0.0084 | W103: 0.02973 | X103: החוב לא נחות | Y103: לא | Z103: 300000 | AA103: 1 | AB103: 107.82 | AD103: 323.46 | AG103: שווי הוגן | AH103: 0.000754 | AI103: 0.011566565 | AJ103: 0.0020998197
A104: 891 | B104: 9957 | C104: פורמולה מערכות (1985)בע"מ | D104: 520036690 | E104: ח.פ | F104: פורמולה אג"ח ג | G104: IL0025602090 | H104: ISIN | I104: לא צמוד למדד המחירים לצרכן | J104: ישראל | K104: ישראל | L104: סחיר | M104: TASE | N104: שירותי מידע | O104: לא | P104: AA- | Q104: S&P מעלות | R104: נייר ערך | S104: ILS | T104: 0.902 | U104: 01/12/2026 | V104: 0.0229 | W104: 0.04703 | X104: החוב לא נחות | Y104: לא | Z104: 140192.31 | AA104: 1 | AB104: 98.11 | AD104: 137.543 | AG104: שווי הוגן | AH104: 0.000423 | AI104: 0.0049183709 | AJ104: 0.00089289192
A105: 891 | B105: 9957 | C105: הפניקס גיוסי הון (2009) בע"מ | D105: 514290345 | E105: ח.פ | F105: פניקס הון אגח טז | G105: IL0012203340 | H105: ISIN | I105: לא צמוד למדד המחירים לצרכן | J105: ישראל | K105: ישראל | L105: סחיר | M105: TASE | N105: ביטוח | O105: לא | P105: AA | Q105: S&P מעלות | R105: נייר ערך | S105: ILS | T105: 5.445 | U105: 01/11/2034 | V105: 0.0515 | W105: 0.04768 | X105: החוב לא נחות | Y105: לא | Z105: 220000 | AA105: 1 | AB105: 103.43 | AD105: 227.546 | AG105: שווי הוגן | AH105: 0.000396 | AI105: 0.0081367882 | AJ105: 0.0014771705
A106: 891 | B106: 9957 | C106: הפניקס גיוסי הון (2009) בע"מ | D106: 514290345 | E106: ח.פ | F106: פניקס הון אגח יב | G106: IL0011955858 | H106: ISIN | I106: צמוד למדד המחירים לצרכן | J106: ישראל | K106: ישראל | L106: סחיר | M106: TASE | N106: ביטוח | O106: לא | P106: AA- | Q106: S&P מעלות | R106: נייר ערך | S106: ILS | T106: 6.133 | U106: 05/02/2032 | V106: 0.0209 | W106: 0.02916 | X106: החוב לא נחות | Y106: לא | Z106: 600000 | AA106: 1 | AB106: 110.73 | AD106: 664.38 | AG106: שווי הוגן | AH106: 0.000389 | AI106: 0.023757479 | AJ106: 0.0043129853
A107: 891 | B107: 9957 | C107: פסיפיק אוק אסאואר(בי וי איי) הולדינגס | D107: 1900288 | E107: מספר תאגיד או שותפות בחו"ל | F107: פסיפיק אגח ב | G107: IL0011630626 | H107: ISIN | I107: לא צמוד למדד המחירים לצרכן | J107: ישראל | K107: ארה"ב | L107: סחיר | M107: TASE | N107: נדל"ן מניב בחו"ל | O107: לא | P107: A | Q107: S&P מעלות | R107: נייר ערך | S107: ILS | T107: 0.574 | U107: 01/02/2026 | V107: 0.04045 | W107: 0.44588 | X107: החוב לא נחות | Y107: לא | Z107: 0.26 | AA107: 1 | AB107: 84.44 | AD107: 0 | AG107: שווי הוגן | AH107: 0 | AI107: 7.8506457e-09 | AJ107: 1.4252236e-09
A108: 891 | B108: 9957 | C108: פתאל נכסים(אירופה)בע"מ | D108: 515328250 | E108: ח.פ | F108: פתאל אירו אגח ו | G108: IL0012192865 | H108: ISIN | I108: לא צמוד למדד המחירים לצרכן | J108: ישראל | K108: ישראל | L108: סחיר | M108: TASE | N108: נדל"ן מניב בחו"ל | O108: לא | P108: A2 | Q108: מידרוג Moodys | R108: נייר ערך | S108: ILS | T108: 5.651 | U108: 01/10/2034 | V108: 0.0559 | W108: 0.05245 | X108: החוב לא נחות | Y108: לא | Z108: 191000 | AA108: 1 | AB108: 103.88 | AD108: 198.411 | AG108: שווי הוגן | AH108: 0.000854 | AI108: 0.0070949463 | AJ108: 0.0012880322
A109: 891 | B109: 9957 | C109: פתאל החזקות 1998 בע"מ | D109: 512607888 | E109: ח.פ | F109: פתאל החזקות אגח ד | G109: IL0011881922 | H109: ISIN | I109: צמוד למדד המחירים לצרכן | J109: ישראל | K109: ישראל | L109: סחיר | M109: TASE | N109: מלונאות ותיירות | O109: לא | P109: A2 | Q109: מידרוג Moodys | R109: נייר ערך | S109: ILS | T109: 3.407 | U109: 31/12/2032 | V109: 0.0325 | W109: 0.03083 | X109: החוב לא נחות | Y109: לא | Z109: 196710 | AA109: 1 | AB109: 111.12 | AD109: 218.584 | AG109: שווי הוגן | AH109: 0.000541 | AI109: 0.0078163226 | AJ109: 0.0014189925
... A125: 891 | B125: 9957 | C125: טבע תעשיות פרמצבטיות בע"מ | D125: 520013954 | E125: ח.פ | F125: TEVA 5.125% 09/05/29 | G125: US88167AAQ40 | H125: ISIN | I125: צמוד למט"ח | J125: חו"ל | K125: ארה"ב | L125: סחיר | M125: אחר | N125: פארמה | O125: לא | P125: BB- | Q125: S&P | R125: נייר ערך | S125: USD | T125: 3.315 | U125: 09/05/2029 | V125: 0.05125 | W125: 0.05051 | X125: החוב לא נחות | Y125: לא | Z125: 63000 | AA125: 3.372 | AB125: 102.147 | AD125: 216.998 | AG125: שווי הוגן | AH125: 6.3e-05 | AI125: 0.0077595939 | AJ125: 0.0014086938

Sheet מניות מבכ ויהש
A1: מספר קופה/קרן/ח.פ. עבור חברת ביטוח | B1: מספר מסלול | C1: שם מנפיק | D1: מספר מנפיק | E1: סוג מספר מזהה מנפיק | F1: שם נייר ערך | G1: מספר נייר ערך | H1: סוג מספר נייר ערך | I1: מאפיין עיקרי | J1: ישראל/חו"ל | K1: מדינה לפי חשיפה כלכלית | L1: סטאטוס סחירות | M1: זירת מסחר | N1: ענף מסחר | O1: בעל עניין/צד קשור | P1: מטבע פעילות | Q1: ערך נקוב (יחידות) | R1: שער חליפין | S1: שער נייר הערך | T1: סכום לקבל (במטבע הפעילות) | U1: שווי הוגן (באלפי ש"ח) | V1: שיעור מערך נקוב מונפק | W1: שיעור מנכסי אפיק ההשקעה | X1: שיעור מסך נכסי ההשקעה
A2: 891 | B2: 9957 | C2: או.פי.סי. אנרגיה בע"מ | D2: 514401702 | E2: ח.פ | F2: או פי סי אנרגיה | G2: IL0011415713 | H2: ISIN | I2: מניות | J2: ישראל | K2: ישראל | L2: סחיר | M2: TASE | N2: אנרגיה | O2: לא | P2: ILS | Q2: 9723 | R2: 1 | S2: 4100 | U2: 398.643 | V2: 3.5e-05 | W2: 0.01210687 | X2: 0.0025878445
A3: 891 | B3: 9957 | C3: אורמת טכנולגיות אינק | D3: 5493000TSHHWY24VHM09 | E3: LEI | F3: אורמת טכנולוגיות | G3: US6866881021 | H3: ISIN | I3: מניות | J3: ישראל | K3: ארה"ב | L3: סחיר | M3: TASE | N3: אנרגיה מתחדשת | O3: לא | P3: ILS | Q3: 1457 | R3: 1 | S3: 27780 | U3: 404.755 | V3: 2.6e-05 | W3: 0.01229248 | X3: 0.0026275188
A4: 891 | B4: 9957 | C4: איי.סי.אל גרופ בע"מ (דואלי) | D4: 520027830 | E4: ח.פ | F4: איי.סי.אל | G4: IL0002810146 | H4: ISIN | I4: מניות | J4: ישראל | K4: ישראל | L4: סחיר | M4: TASE | N4: כימיה, גומי ופלסטיק | O4: לא | P4: ILS | Q4: 25440 | R4: 1 | S4: 2309 | U4: 587.41 | V4: 1.9e-05 | W4: 0.01783975 | X4: 0.0038132483
A5: 891 | B5: 9957 | C5: אינרום תעשיות בנייה בע"מ | D5: 515001659 | E5: ח.פ | F5: אינרום | G5: IL0011323560 | H5: ISIN | I5: מניות | J5: ישראל | K5: ישראל | L5: סחיר | M5: TASE | N5: מתכת ומוצרי בניה | O5: לא | P5: ILS | Q5: 12000 | R5: 1 | S5: 2100 | U5: 252 | V5: 8.1e-05 | W5: 0.0076532917 | X5: 0.0016358918
A6: 891 | B6: 9957 | C6: אלביט מערכות בע"מ | D6: 520043027 | E6: ח.פ | F6: אלביט מערכות | G6: IL0010811243 | H6: ISIN | I6: מניות | J6: ישראל | K6: ישראל | L6: סחיר | M6: TASE | N6: ביטחוניות | O6: לא | P6: ILS | Q6: 806 | R6: 1 | S6: 149800 | T6: 1.705 | U6: 1209.093 | V6: 1.7e-05 | W6: 0.036720393 | X6: 0.0078489875
A7: 891 | B7: 9957 | C7: אלוני-חץ נכסים והשקעות בע"מ | D7: 520038506 | E7: ח.פ | F7: אלוני חץ | G7: IL0003900136 | H7: ISIN | I7: מניות | J7: ישראל | K7: ישראל | L7: סחיר | M7: TASE | N7: נדל"ן מניב בישראל | O7: לא | P7: ILS | Q7: 9180 | R7: 1 | S7: 3489 | U7: 320.29 | V7: 4.3e-05 | W7: 0.0097272791 | X7: 0.0020792068
A8: 891 | B8: 9957 | C8: אלקטרה נדל"ן בע"מ | D8: 510607328 | E8: ח.פ | F8: אלקטרה נדלן | G8: IL0010940448 | H8: ISIN | I8: מניות | J8: ישראל | K8: ישראל | L8: סחיר | M8: TASE | N8: נדל"ן מניב בחו"ל | O8: לא | P8: ILS | Q8: 2562 | R8: 1 | S8: 5007 | U8: 128.279 | V8: 3.9e-05 | W8: 0.0038958699 | X8: 0.00083274256
A9: 891 | B9: 9957 | C9: אמות השקעות בע"מ | D9: 520026683 | E9: ח.פ | F9: אמות | G9: IL0010972789 | H9: ISIN | I9: מניות | J9: ישראל | K9: ישראל | L9: סחיר | M9: TASE | N9: נדל"ן מניב בישראל | O9: לא | P9: ILS | Q9: 13336 | R9: 1 | S9: 2281 | U9: 304.194 | V9: 2.8e-05 | W9: 0.0092384391 | X9: 0.0019747172
A10: 891 | B10: 9957 | C10: אנלייט אנרגיה מתחדשת בע"מ | D10: 520041146 | E10: ח.פ | F10: אנלייט אנרגיה | G10: IL0007200111 | H10: ISIN | I10: מניות | J10: ישראל | K10: ארה"ב | L10: סחיר | M10: TASE | N10: אנרגיה מתחדשת | O10: לא | P10: ILS | Q10: 2775.4 | R10: 1 | S10: 7640 | U10: 212.041 | V10: 2.3e-05 | W10: 0.0064397153 | X10: 0.0013764898
A11: 891 | B11: 9957 | C11: Energean plc | D11: 98450044QACBL3F8EB03 | E11: LEI | F11: אנרג'יאן | G11: GB00BG12Y042 | H11: ISIN | I11: מניות | J11: ישראל | K11: בריטניה | L11: סחיר | M11: TASE | N11: חיפושי נפט וגז | O11: לא | P11: ILS | Q11: 8728 | R11: 1 | S11: 4272 | T11: 8.829 | U11: 381.689 | V11: 4.7e-05 | W11: 0.011591986 | X11: 0.002477788
A12: 891 | B12: 9957 | C12: אנרג'יקס אנרגיות מתחדשות בע"מ | D12: 513901371 | E12: ח.פ | F12: אנרג'יקס | G12: IL0011233553 | H12: ISIN | I12: מניות | J12: ישראל | K12: ישראל | L12: סחיר | M12: TASE | N12: אנרגיה מתחדשת | O12: לא | P12: ILS | Q12: 11984 | R12: 1 | S12: 1244 | U12: 149.081 | V12: 2.2e-05 | W12: 0.0045276193 | X12: 0.00096777906
A13: 891 | B13: 9957 | C13: אר פי אופטיקל לאב בעמ | D13: 514454701 | E13: ח.פ | F13: אר פי אופטיקל לאב | G13: IL0012224627 | H13: ISIN | I13: מניות | J13: ישראל | K13: ישראל | L13: סחיר | M13: TASE | N13: ביטחוניות | O13: לא | P13: ILS | Q13: 6000 | R13: 1 | S13: 1336 | U13: 80.16 | V13: 8.1e-05 | W13: 0.0024344756 | X13: 0.0005203694
A14: 891 | B14: 9957 | C14: ארגו פרופרטיז אן. וי | D14: 70252750 | E14: מספר תאגיד או שותפות בחו"ל | F14: ארגו פרופרטיז אן. וי | G14: NL0015000D84 | H14: ISIN | I14: מניות | J14: ישראל | K14: גרמניה | L14: סחיר | M14: TASE | N14: נדל"ן מניב בחו"ל | O14: לא | P14: ILS | Q14: 2139 | R14: 1 | S14: 12250 | U14: 262.027 | V14: 9.8e-05 | W14: 0.0079578289 | X14: 0.0017009867
A15: 891 | B15: 9957 | C15: קבוצת אשטרום | D15: 510381601 | E15: ח.פ | F15: אשטרום קבוצה | G15: IL0011323156 | H15: ISIN | I15: מניות | J15: ישראל | K15: ישראל | L15: סחיר | M15: TASE | N15: בנייה | O15: לא | P15: ILS | Q15: 3000 | R15: 1 | S15: 7670 | U15: 230.1 | V15: 2.7e-05 | W15: 0.0069881842 | X15: 0.001493725
A16: 891 | B16: 9957 | C16: בזק החברה הישראלית לתקשורת בע"מ | D16: 520031931 | E16: ח.פ | F16: בזק | G16: IL0002300114 | H16: ISIN | I16: מניות | J16: ישראל | K16: ישראל | L16: סחיר | M16: TASE | N16: תקשורת ומדיה | O16: לא | P16: ILS | Q16: 74329 | R16: 1 | S16: 575 | U16: 427.392 | V16: 2.7e-05 | W16: 0.012979975 | X16: 0.0027744709
A17: 891 | B17: 9957 | C17: ביג מרכזי קניות (2004) בע"מ | D17: 513623314 | E17: ח.פ | F17: ביג | G17: IL0010972607 | H17: ISIN | I17: מניות | J17: ישראל | K17: ישראל | L17: סחיר | M17: TASE | N17: נדל"ן מניב בישראל | O17: לא | P17: ILS | Q17: 1367 | R17: 1 | S17: 64490 | U17: 881.578 | V17: 5.5e-05 | W17: 0.026773714 | X17: 0.0057228839
A18: 891 | B18: 9957 | C18: הבנק הבינלאומי הראשון לישראל בע"מ | D18: 520029083 | E18: ח.פ | F18: בינלאומי 5 | G18: IL0005930388 | H18: ISIN | I18: מניות | J18: ישראל | K18: ישראל | L18: סחיר | M18: TASE | N18: בנקים | O18: לא | P18: ILS | Q18: 2503 | R18: 1 | S18: 24370 | U18: 609.981 | V18: 2.5e-05 | W18: 0.018525251 | X18: 0.0039597742
A19: 891 | B19: 9957 | C19: בית בכפר בע"מ | D19: 511605719 | E19: ח.פ | F19: בית בכפר | G19: IL0011836561 | H19: ISIN | I19: מניות | J19: ישראל | K19: ישראל | L19: סחיר | M19: TASE | N19: נדל"ן מניב בישראל | O19: לא | P19: ILS | Q19: 10069 | R19: 1 | S19: 1506 | U19: 151.639 | V19: 0.000144 | W19: 0.0046053118 | X19: 0.00098438583
A20: 891 | B20: 9957 | C20: מנועי בית שמש אחזקות (1997) בע"מ | D20: 520043480 | E20: ח.פ | F20: בית שמש | G20: IL0010815616 | H20: ISIN | I20: מניות | J20: ישראל | K20: ישראל | L20: סחיר | M20: TASE | N20: מתכת ומוצרי בניה | O20: לא | P20: ILS | Q20: 1344 | R20: 1 | S20: 56070 | U20: 753.581 | V20: 0.000148 | W20: 0.022886404 | X20: 0.0048919709
A21: 891 | B21: 9957 | C21: חברת גב-ים לקרקעות בע"מ | D21: 520001736 | E21: ח.פ | F21: גב ים | G21: IL0007590198 | H21: ISIN | I21: מניות | J21: ישראל | K21: ישראל | L21: סחיר | M21: TASE | N21: נדל"ן מניב בישראל | O21: לא | P21: ILS | Q21: 6272 | R21: 1 | S21: 3685 | U21: 231.123 | V21: 2.8e-05 | W21: 0.007019259 | X21: 0.0015003673
A22: 891 | B22: 9957 | C22: קבוצת דוראל משאבי אנרגיה מתחדשת בעמ | D22: 515364891 | E22: ח.פ | F22: דוראל אנרגיה | G22: IL0011667685 | H22: ISIN | I22: מניות | J22: ישראל | K22: ישראל | L22: סחיר | M22: TASE | N22: אנרגיה מתחדשת | O22: לא | P22: ILS | Q22: 10141 | R22: 1 | S22: 1532 | U22: 155.36 | V22: 5.7e-05 | W22: 0.0047183187 | X22: 0.0010085411
A23: 891 | B23: 9957 | C23: בנק דיסקונט לישראל בע"מ | D23: 520007030 | E23: ח.פ | F23: דיסקונט | G23: IL0006912120 | H23: ISIN | I23: מניות | J23: ישראל | K23: ישראל | L23: סחיר | M23: TASE | N23: בנקים | O23: לא | P23: ILS | Q23: 19618 | R23: 1 | S23: 3356 | U23: 658.38 | V23: 1.6e-05 | W23: 0.019995138 | X23: 0.0042739627
... A27: 891 | B27: 9957 | C27: הבורסה לניירות ערך בתל-אביב בע"מ | D27: 520020033 | E27: ח.פ | F27: הבורסה לניע בתא | G27: IL0011590291 | H27: ISIN | I27: מניות | J27: ישראל | K27: ישראל | L27: סחיר | M27: TASE | N27: שירותים פיננסיים | O27: לא | P27: ILS | Q27: 1778 | R27: 1 | S27: 6510 | U27: 115.748 | V27: 1.7e-05 | W27: 0.0035152844 | X27: 0.00075139238
A28: 891 | B28: 9957 | C28: הולמס פלייס אינטרנשיונל בע"מ | D28: 512466723 | E28: ח.פ | F28: הולמס פלייס | G28: IL0011425878 | H28: ISIN | I28: מניות | J28: ישראל | K28: ישראל | L28: סחיר | M28: TASE | N28: שירותים | O28: לא | P28: ILS | Q28: 44000 | R28: 1 | S28: 732.6 | T28: 5.273 | U28: 327.617 | V28: 0.000479 | W28: 0.0099497925 | X28: 0.0021267691
A29: 891 | B29: 9957 | C29: חברת הכשרת הישוב בישראל- אנרגיה בע"מ | D29: 514423474 | E29: ח.פ | F29: הכשרה התפתחות עירונית | G29: IL0011214744 | H29: ISIN | I29: מניות | J29: ישראל | K29: ישראל | L29: סחיר | M29: TASE | N29: בנייה | O29: לא | P29: ILS | Q29: 27000 | R29: 1 | S29: 711.9 | U29: 192.213 | V29: 0.000309 | W29: 0.0058375483 | X29: 0.0012477765
A30: 891 | B30: 9957 | C30: הפניקס אחזקות בע"מ | D30: 520017450 | E30: ח.פ | F30: הפניקס | G30: IL0007670123 | H30: ISIN | I30: מניות | J30: ישראל | K30: ישראל | L30: סחיר | M30: TASE | N30: ביטוח | O30: לא | P30: ILS | Q30: 6229 | R30: 1 | S30: 9745 | U30: 607.016 | V30: 2.4e-05 | W30: 0.018435202 | X30: 0.0039405262
A31: 891 | B31: 9957 | C31: הראל השקעות בביטוח ושרותים פיננסים בע"מ | D31: 520033986 | E31: ח.פ | F31: הראל השקעות | G31: IL0005850180 | H31: ISIN | I31: מניות | J31: ישראל | K31: ישראל | L31: סחיר | M31: TASE | N31: ביטוח | O31: לא | P31: ILS | Q31: 10085 | R31: 1 | S31: 9432 | U31: 951.217 | V31: 4.5e-05 | W31: 0.028888662 | X31: 0.0061749541
A32: 891 | B32: 9957 | C32: וואן טכנולוגיות תוכנה(או.אס.טי)בע"מ | D32: 520034695 | E32: ח.פ | F32: וואן טכנולוגיות תוכנה | G32: IL0001610182 | H32: ISIN | I32: מניות | J32: ישראל | K32: ישראל | L32: סחיר | M32: TASE | N32: שירותי מידע | O32: לא | P32: ILS | Q32: 1520 | R32: 1 | S32: 8680 | U32: 131.936 | V32: 2.1e-05 | W32: 0.0040069234 | X32: 0.00085648026
A33: 891 | B33: 9957 | C33: החברה לישראל בע"מ | D33: 520028010 | E33: ח.פ | F33: חברה לישראל | G33: IL0005760173 | H33: ISIN | I33: מניות | J33: ישראל | K33: ישראל | L33: סחיר | M33: TASE | N33: השקעה ואחזקות | O33: לא | P33: ILS | Q33: 175 | R33: 1 | S33: 112370 | U33: 196.648 | V33: 2.3e-05 | W33: 0.0059722249 | X33: 0.0012765636
A34: 891 | B34: 9957 | C34: חילן בע"מ | D34: 520039942 | E34: ח.פ | F34: חילן | G34: IL0010846983 | H34: ISIN | I34: מניות | J34: ישראל | K34: ישראל | L34: סחיר | M34: TASE | N34: שירותי מידע | O34: לא | P34: ILS | Q34: 761 | R34: 1 | S34: 28610 | U34: 217.722 | V34: 3.3e-05 | W34: 0.0066122649 | X34: 0.0014133722
A35: 891 | B35: 9957 | C35: קבוצת חמת בע"מ | D35: 520038530 | E35: ח.פ | F35: חמת | G35: IL0003840167 | H35: ISIN | I35: מניות | J35: ישראל | K35: ישראל | L35: סחיר | M35: TASE | N35: מתכת ומוצרי בניה | O35: לא | P35: ILS | Q35: 6747 | R35: 1 | S35: 1866 | T35: 2.762 | U35: 128.661 | V35: 0.000183 | W35: 0.0039074573 | X35: 0.00083521937
A36: 891 | B36: 9957 | C36: טאואר סמיקונדקטור בע"מ | D36: 520041997 | E36: ח.פ | F36: טאואר | G36: IL0010823792 | H36: ISIN | I36: מניות | J36: ישראל | K36: גלובלי | L36: סחיר | M36: TASE | N36: מוליכים למחצה | O36: לא | P36: ILS | Q36: 2003 | R36: 1 | S36: 14620 | U36: 292.839 | V36: 1.8e-05 | W36: 0.0088935684 | X36: 0.0019010011
A37: 891 | B37: 9957 | C37: טבע תעשיות פרמצבטיות בע"מ | D37: 520013954 | E37: ח.פ | F37: טבע | G37: IL0006290147 | H37: ISIN | I37: מניות | J37: ישראל | K37: ארה"ב | L37: סחיר | M37: TASE | N37: פארמה | O37: לא | P37: ILS | Q37: 27613 | R37: 1 | S37: 5699 | U37: 1573.665 | V37: 2.2e-05 | W37: 0.047792525 | X37: 0.010215657
A38: 891 | B38: 9957 | C38: טיב טעם הולדינגס 1 בע"מ | D38: 520041187 | E38: ח.פ | F38: טיב טעם | G38: IL0001030100 | H38: ISIN | I38: מניות | J38: ישראל | K38: ישראל | L38: סחיר | M38: TASE | N38: רשתות שיווק | O38: לא | P38: ILS | Q38: 25353 | R38: 1 | S38: 810 | U38: 205.359 | V38: 0.000233 | W38: 0.0062368041 | X38: 0.0013331175
A39: 891 | B39: 9957 | C39: ישראמקו נגב 2 שותפות מוגבלת | D39: 550010003 | E39: מספר שותפות | F39: ישראמקו יהש | G39: IL0002320179 | H39: ISIN | I39: מניות | J39: ישראל | K39: ישראל | L39: סחיר | M39: TASE | N39: חיפושי נפט וגז | O39: לא | P39: ILS | Q39: 111900 | R39: 1 | S39: 229.9 | U39: 257.258 | V39: 4.3e-05 | W39: 0.0078129813 | X39: 0.0016700255
A40: 891 | B40: 9957 | C40: כלל החזקות עסקי ביטוח בע"מ | D40: 520036120 | E40: ח.פ | F40: כלל ביטוח | G40: IL0002240146 | H40: ISIN | I40: מניות | J40: ישראל | K40: ישראל | L40: סחיר | M40: TASE | N40: ביטוח | O40: לא | P40: ILS | Q40: 4988 | R40: 1 | S40: 14880 | U40: 742.214 | V40: 6.3e-05 | W40: 0.022541204 | X40: 0.0048181844
A41: 891 | B41: 9957 | C41: בנק לאומי לישראל בע"מ | D41: 520018078 | E41: ח.פ | F41: לאומי | G41: IL0006046119 | H41: ISIN | I41: מניות | J41: ישראל | K41: ישראל | L41: סחיר | M41: TASE | N41: בנקים | O41: לא | P41: ILS | Q41: 30015 | R41: 1 | S41: 6262 | U41: 1879.539 | V41: 1.9e-05 | W41: 0.057081994 | X41: 0.012201282
A42: 891 | B42: 9957 | C42: יוחננוף | D42: 511344186 | E42: ח.פ | F42: מ. יוחננוף | G42: IL0011612640 | H42: ISIN | I42: מניות | J42: ישראל | K42: ישראל | L42: סחיר | M42: TASE | N42: רשתות שיווק | O42: לא | P42: ILS | Q42: 939 | R42: 1 | S42: 30850 | U42: 289.682 | V42: 6.5e-05 | W42: 0.0087976866 | X42: 0.0018805063
A43: 891 | B43: 9957 | C43: מבנה נדל"ן (כ.ד) בע"מ | D43: 520024126 | E43: ח.פ | F43: מבנה | G43: IL0002260193 | H43: ISIN | I43: מניות | J43: ישראל | K43: ישראל | L43: סחיר | M43: TASE | N43: נדל"ן מניב בישראל | O43: לא | P43: ILS | Q43: 13606.16 | R43: 1 | S43: 1262 | U43: 171.71 | V43: 1.9e-05 | W43: 0.00521486 | X43: 0.0011146768
A44: 891 | B44: 9957 | C44: בנק מזרחי טפחות בע"מ | D44: 520000522 | E44: ח.פ | F44: מזרחי טפחות | G44: IL0006954379 | H44: ISIN | I44: מניות | J44: ישראל | K44: ישראל | L44: סחיר | M44: TASE | N44: בנקים | O44: לא | P44: ILS | Q44: 5269.93 | R44: 1 | S44: 21950 | U44: 1156.75 | V44: 2e-05 | W44: 0.035130724 | X44: 0.0075091955
A45: 891 | B45: 9957 | C45: מטריקס אי.טי בע"מ | D45: 520039413 | E45: ח.פ | F45: מטריקס | G45: IL0004450156 | H45: ISIN | I45: מניות | J45: ישראל | K45: ישראל | L45: סחיר | M45: TASE | N45: שירותי מידע | O45: לא | P45: ILS | Q45: 2046 | R45: 1 | S45: 11720 | U45: 239.791 | V45: 3.2e-05 | W45: 0.0072825079 | X45: 0.0015566368
A46: 891 | B46: 9957 | C46: מליסרון בע"מ | D46: 520037789 | E46: ח.פ | F46: מליסרון | G46: IL0003230146 | H46: ISIN | I46: מניות | J46: ישראל | K46: ישראל | L46: סחיר | M46: TASE | N46: נדל"ן מניב בישראל | O46: לא | P46: ILS | Q46: 839 | R46: 1 | S46: 38400 | U46: 322.176 | V46: 1.8e-05 | W46: 0.0097845512 | X46: 0.0020914488
A47: 891 | B47: 9957 | C47: מנורה מבטחים החזקות בע"מ | D47: 520007469 | E47: ח.פ | F47: מנורה מבטחים החזקות | G47: IL0005660183 | H47: ISIN | I47: מניות | J47: ישראל | K47: ישראל | L47: סחיר | M47: TASE | N47: ביטוח | O47: לא | P47: ILS | Q47: 1337 | R47: 1 | S47: 26530 | U47: 354.706 | V47: 2.1e-05 | W47: 0.010772497 | X47: 0.0023026223
... A72: 891 | B72: 9957 | C72: AIRBUS GROUP | D72: MINO79WLOO247M1IL051 | E72: LEI | F72: AIRBNB INC | G72: US0090661010 | H72: ISIN | I72: מניות | J72: חו"ל | K72: ארה"ב | L72: סחיר | M72: NASDAQ | N72: DiversifiedTelecom Service | O72: לא | P72: USD | Q72: 501 | R72: 3.372 | S72: 13234 | U72: 223.571 | V72: 1e-06 | W72: 0.006789912 | X72: 0.0014513443
A73: 891 | B73: 9957 | C73: ALIBABA COM LTD | D73: 5493001NTNQJDH60PM02 | E73: LEI | F73: BABA US Alibaba Group Holding Ltd | G73: US01609W1027 | H73: ISIN | I73: מניות | J73: חו"ל | K73: סין | L73: סחיר | M73: NYSE | N73: Textiles, Apparel & Luxury Goods | O73: לא | P73: USD | Q73: 308 | R73: 3.372 | S73: 11341 | T73: 0.609 | U73: 119.839 | V73: 0 | W73: 0.0036395485 | X73: 0.00077795384
A74: 891 | B74: 9957 | C74: Deere&Company | D74: PWFTNG3EI0Y73OXWDH08 | E74: LEI | F74: DEERE & CO | G74: US2441991054 | H74: ISIN | I74: מניות | J74: חו"ל | K74: ארה"ב | L74: סחיר | M74: NYSE | N74: Food & Staples Retailing Consumer Staples Distribution & Retail | O74: לא | P74: USD | Q74: 134 | R74: 3.372 | S74: 50849 | T74: 0.163 | U74: 230.309 | V74: 0 | W74: 0.0069945225 | X74: 0.0014950798
A75: 891 | B75: 9957 | C75: ELI LILLY & CO | D75: FRDRIPF3EKNDJ2CQJL29 | E75: LEI | F75: Eli Lilly | G75: US5324571083 | H75: ISIN | I75: מניות | J75: חו"ל | K75: ארה"ב | L75: סחיר | M75: NYSE | N75: Pharmaceuticals | O75: לא | P75: USD | Q75: 62 | R75: 3.372 | S75: 77953 | U75: 162.972 | V75: 0 | W75: 0.0049494828 | X75: 0.0010579524
A76: 891 | B76: 9957 | C76: Meta Platforms Inc | D76: BQ4BKCS1HXDV9HN80Z93 | E76: LEI | F76: Facebook Inc | G76: US30303M1027 | H76: ISIN | I76: מניות | J76: חו"ל | K76: ארה"ב | L76: סחיר | M76: NASDAQ | N76: Diversified Telecommunication Services | O76: לא | P76: USD | Q76: 116 | R76: 3.372 | S76: 73809 | U76: 288.705 | V76: 0 | W76: 0.0087680416 | X76: 0.0018741697
A77: 891 | B77: 9957 | C77: INTEL CORP | D77: KNX4USFCNGPY45LOCE31 | E77: LEI | F77: Intel corp | G77: US4581401001 | H77: ISIN | I77: מניות | J77: חו"ל | K77: ארה"ב | L77: סחיר | M77: NASDAQ | N77: Semiconductors & Semiconductor | O77: לא | P77: USD | Q77: 4408 | R77: 3.372 | S77: 2240 | U77: 332.949 | V77: 1e-06 | W77: 0.010111717 | X77: 0.0021613804
A78: 891 | B78: 9957 | C78: JP MORGAN ASSET MANAGEMENT | D78: 8I5DZWZKVSZI1NUHU748 | E78: LEI | F78: JPMORGAN CHASE & CO | G78: US46625H1005 | H78: ISIN | I78: מניות | J78: חו"ל | K78: ארה"ב | L78: סחיר | M78: NYSE | N78: Banks | O78: לא | P78: USD | Q78: 271 | R78: 3.372 | S78: 28991 | U78: 264.923 | V78: 0 | W78: 0.0080457731 | X78: 0.0017197848
A79: 891 | B79: 9957 | C79: MARVELL TECH | D79: 8DF36O58U3QIHUCGZB18 | E79: LEI | F79: Marvell tech group | G79: BMG5876H1051 | H79: ISIN | I79: מניות | J79: חו"ל | K79: ארה"ב | L79: סחיר | M79: NASDAQ | N79: Semiconductors & Semiconductor | O79: לא | P79: USD | Q79: 1926 | R79: 3.372 | S79: 7740 | U79: 502.672 | V79: 3e-06 | W79: 0.015266256 | X79: 0.0032631636
A80: 891 | B80: 9957 | C80: נייס מערכות בע"מ | D80: 520036872 | E80: ח.פ | F80: NICE SYS ADR | G80: US6536561086 | H80: ISIN | I80: מניות | J80: חו"ל | K80: ישראל | L80: סחיר | M80: NASDAQ | N80: Wireless Telecommunication Services | O80: לא | P80: USD | Q80: 353 | R80: 3.372 | S80: 16891 | U80: 201.056 | V80: 6e-06 | W80: 0.0061061203 | X80: 0.0013051838
A81: 891 | B81: 9957 | C81: NIKE INC | D81: 787RXPR0UX0O0XUXPZ81 | E81: LEI | F81: NIKE INC | G81: US6541061031 | H81: ISIN | I81: מניות | J81: חו"ל | K81: ארה"ב | L81: סחיר | M81: NYSE | N81: Textiles, Apparel & Luxury Goods | O81: לא | P81: USD | Q81: 895 | R81: 3.372 | S81: 7104 | U81: 214.394 | V81: 1e-06 | W81: 0.0065112037 | X81: 0.0013917704
A82: 891 | B82: 9957 | C82: NVIDIA CORP | D82: 549300S4KLFTLO7GSQ80 | E82: LEI | F82: Nvidia corp | G82: US67066G1040 | H82: ISIN | I82: מניות | J82: חו"ל | K82: ארה"ב | L82: סחיר | M82: NASDAQ | N82: Semiconductors & Semiconductor Equipment | O82: לא | P82: USD | Q82: 1340 | R82: 3.372 | S82: 15799 | T82: 0.01 | U82: 713.909 | V82: 0 | W82: 0.021681548 | X82: 0.004634433
A83: 891 | B83: 9957 | C83: אורמת טכנולגיות אינק | D83: 5493000TSHHWY24VHM09 | E83: LEI | F83: Ormat Technologies | G83: US6866881021 | H83: ISIN | I83: מניות | J83: חו"ל | K83: ארה"ב | L83: סחיר | M83: NYSE | N83: Water Utilities | O83: לא | P83: USD | Q83: 451 | R83: 3.372 | S83: 8376 | U83: 127.38 | V83: 7e-06 | W83: 0.0038685526 | X83: 0.00082690348
A84: 891 | B84: 9957 | C84: Palo alto networks inc | D84: 549300QXR2YVZV231H43 | E84: LEI | F84: PALO ALTO NETWORKS INC | G84: US6974351057 | H84: ISIN | I84: מניות | J84: חו"ל | K84: ארה"ב | L84: סחיר | M84: NASDAQ | N84: Software | O84: לא | P84: USD | Q84: 436 | R84: 3.372 | S84: 20464 | U84: 300.86 | V84: 1e-06 | W84: 0.0091371827 | X84: 0.0019530737
A85: 891 | B85: 9957 | C85: PPHE HOTEL GROUP LTD | D85: 2138003H1BZGR6KM5823 | E85: LEI | F85: PP HOTEL GROUP LTD | G85: GG00B1Z5FH87 | H85: ISIN | I85: מניות | J85: חו"ל | K85: בריטניה | L85: סחיר | M85: LSE | N85: Diversified Consumer Services | O85: לא | P85: GBP | Q85: 3960 | R85: 4.6236 | S85: 1600 | U85: 292.951 | V85: 8.9e-05 | W85: 0.008896991 | X85: 0.0019017327
A86: 891 | B86: 9957 | C86: Saleforce.com Inc | D86: RCGZFPDMRW58VJ54VR07 | E86: LEI | F86: Saleforce | G86: US794466L3024 | H86: ISIN | I86: מניות | J86: חו"ל | K86: ארה"ב | L86: סחיר | M86: NASDAQ | N86: Software | O86: לא | P86: USD | Q86: 121 | R86: 3.372 | S86: 27269 | T86: 0.07 | U86: 111.496 | V86: 0 | W86: 0.0033861631 | X86: 0.00072379269
A87: 891 | B87: 9957 | C87: Selina Hospitality Plc | D87: 549300BAEIWO0QPTC061 | E87: LEI | F87: SELINA HOSPITALITY | G87: GB00BQ1MW662 | H87: ISIN | I87: מניות | J87: חו"ל | K87: ארה"ב | L87: סחיר | M87: NASDAQ | N87: Diversified Consumer Services | O87: לא | P87: USD | Q87: 17661 | R87: 3.372 | S87: 0.04 | U87: 0.024 | V87: 3.2e-05 | W87: 7.2345342e-07 | X87: 1.5463824e-07
A88: 891 | B88: 9957 | C88: TAIWAN Semiconductor | D88: 549300KB6NK5SBD14S87 | E88: LEI | F88: TAIWAN SEMICON ADR | G88: US8740391003 | H88: ISIN | I88: מניות | J88: חו"ל | K88: סין | L88: סחיר | M88: NYSE | N88: Semiconductors & Semiconductor Equipment | O88: לא | P88: USD | Q88: 375 | R88: 3.372 | S88: 22649 | T88: 0.223 | U88: 287.147 | V88: 0 | W88: 0.0087207168 | X88: 0.001864054

Sheet קרנות סל
A1: מספר קופה/קרן/ח.פ. עבור חברת ביטוח | B1: מספר מסלול | C1: שם מנפיק | D1: מספר מנפיק | E1: סוג מספר מזהה מנפיק | F1: שם נייר ערך | G1: מספר נייר ערך | H1: סוג מספר נייר ערך | I1: מאפיין עיקרי | J1: ישראל/חו"ל | K1: מדינה לפי חשיפה כלכלית | L1: זירת מסחר | M1: סיווג הקרן | N1: בעל עניין/צד קשור | O1: מטבע פעילות | P1: ערך נקוב (יחידות) | Q1: שער חליפין | R1: שער נייר הערך | S1: סכום לקבל (במטבע הפעילות) | T1: שווי הוגן (באלפי ש"ח) | U1: שיעור מערך נקוב מונפק | V1: שיעור מנכסי אפיק ההשקעה | W1: שיעור מסך נכסי ההשקעה
A2: 891 | B2: 9957 | C2: מגדל קרנות נאמנות בע"מ | D2: 511303661 | E2: ח.פ | F2: MTF סל (S&P 500 (4D | G2: IL0011503336 | H2: ISIN | I2: עוקב אחר מדדי מניות בחו"ל | J2: ישראל | K2: ארה"ב | L2: TASE | M2: מניות בחו"ל חשופות מט"ח | N2: לא | O2: ILS | P2: 1747 | Q2: 1 | R2: 8961 | T2: 156.549 | U2: 2e-05 | V2: 0.0049965371 | W2: 0.0010162567
A3: 891 | B3: 9957 | C3: מגדל קרנות נאמנות בע"מ | D3: 511303661 | E3: ח.פ | F3: MTF500SP ממ | G3: IL0011505729 | H3: ISIN | I3: עוקב אחר מדדי מניות בחו"ל | J3: ישראל | K3: ארה"ב | L3: TASE | M3: מניות בחו"ל משולבת | N3: לא | O3: ILS | P3: 31179 | Q3: 1 | R3: 7820 | T3: 2438.198 | U3: 0.001279 | V3: 0.077819542 | W3: 0.015827888
A4: 891 | B4: 9957 | C4: הראל קרנות נאמנות בע"מ | D4: 511776783 | E4: ח.פ | F4: הראל סל (4A) MSCI AC World מנ | G4: IL0011502007 | H4: ISIN | I4: עוקב אחר מדדי מניות בחו"ל | J4: ישראל | K4: גלובלי | L4: TASE | M4: מניות בחו"ל חשופות מט"ח | N4: לא | O4: ILS | P4: 222910 | Q4: 1 | R4: 864.7 | T4: 1927.503 | U4: 0.000443 | V4: 0.061519776 | W4: 0.012512643
A5: 891 | B5: 9957 | C5: הראל קרנות נאמנות בע"מ | D5: 511776783 | E5: ח.פ | F5: הראל סל תא 90 | G5: IL0011489312 | H5: ISIN | I5: עוקב אחר מדדי מניות בישראל | J5: ישראל | K5: ישראל | L5: TASE | M5: מניות בישראל | N5: לא | O5: ILS | P5: 23148 | Q5: 1 | R5: 3032 | T5: 701.847 | U5: 9.3e-05 | V5: 0.022400742 | W5: 0.0045561364
A6: 891 | B6: 9957 | C6: הראל קרנות נאמנות בע"מ | D6: 511776783 | E6: ח.פ | F6: הראל קרן סל 4AׂSTOXX EUROPE 600ממ | G6: IL0011498891 | H6: ISIN | I6: עוקב אחר מדדי מניות בחו"ל | J6: ישראל | K6: אירופה | L6: TASE | M6: מניות בחו"ל משולבת | N6: לא | O6: ILS | P6: 171631 | Q6: 1 | R6: 699.4 | T6: 1200.387 | U6: 0.000727 | V6: 0.038312553 | W6: 0.0077924747
A7: 891 | B7: 9957 | C7: הראל קרנות נאמנות בע"מ | D7: 511776783 | E7: ח.פ | F7: הראל.DAX 30 ממ | G7: IL0011491607 | H7: ISIN | I7: עוקב אחר מדדי מניות בחו"ל | J7: ישראל | K7: גרמניה | L7: TASE | M7: מניות בחו"ל משולבת | N7: לא | O7: ILS | P7: 2287 | Q7: 1 | R7: 20650 | T7: 472.265 | U7: 0.0002 | V7: 0.015073217 | W7: 0.0030657749
A8: 891 | B8: 9957 | C8: קסם קרנות נאמנות בע"מ | D8: 510938608 | E8: ח.פ | F8: ממEURO STOXX 50 (4A) ETF.קסם | G8: IL0011459521 | H8: ISIN | I8: עוקב אחר מדדי מניות בחו"ל | J8: ישראל | K8: אירופה | L8: TASE | M8: מניות בחו"ל משולבת | N8: לא | O8: ILS | P8: 22280 | Q8: 1 | R8: 7493 | T8: 1669.44 | U8: 0.0016 | V8: 0.053283243 | W8: 0.010837396
A9: 891 | B9: 9957 | C9: קסם קרנות נאמנות בע"מ | D9: 510938608 | E9: ח.פ | F9: קסם תל בונד שקלי | G9: IL0011464141 | H9: ISIN | I9: עוקב אחר מדדים אחרים בישראל | J9: ישראל | K9: ישראל | L9: TASE | M9: אג"ח בישראל - חברות והמרה | N9: לא | O9: ILS | P9: 99385 | Q9: 1 | R9: 4144.02 | T9: 4118.534 | U9: 0.00184 | V9: 0.13145055 | W9: 0.026736018
A10: 891 | B10: 9957 | C10: Amundi Asset Management | D10: 213800VZW861M5FHMD50 | E10: LEI | F10: AMUNDI MSCI EMERGING MARKETS I | G10: LU2573967036 | H10: ISIN | I10: עוקב אחר מדדי מניות בחו"ל | J10: חו"ל | K10: שווקים מתעוררים | L10: NASDAQ | M10: Equity Funds | N10: לא | O10: USD | P10: 13433 | Q10: 3.372 | R10: 6036 | T10: 2734.071 | U10: 0 | V10: 0.087262881 | W10: 0.01774859
A11: 891 | B11: 9957 | C11: BlackRock Asset Managment | D11: 254900UWHMJRRODS3Z64 | E11: LEI | F11: Cef Ishares Russell iwm | G11: US4642876555 | H11: ISIN | I11: עוקב אחר מדדי מניות בחו"ל | J11: חו"ל | K11: ארה"ב | L11: NYSE | M11: Equity Funds | N11: לא | O11: USD | P11: 1932 | Q11: 3.372 | R11: 21579 | T11: 1405.808 | U11: 7e-06 | V11: 0.044868932 | W11: 0.0091259912
A12: 891 | B12: 9957 | C12: BlackRock Asset Managment | D12: 254900UWHMJRRODS3Z64 | E12: LEI | F12: IGV US_ISHARES EXPANDED TECH | G12: US4642875151 | H12: ISIN | I12: עוקב אחר מדדי מניות בחו"ל | J12: חו"ל | K12: ארה"ב | L12: CBOE | M12: Equity Funds | N12: לא | O12: USD | P12: 775 | Q12: 3.372 | R12: 10950 | T12: 286.156 | U12: 7e-06 | V12: 0.0091332032 | W12: 0.0018576224
A13: 891 | B13: 9957 | C13: BlackRock Asset Managment | D13: 254900UWHMJRRODS3Z64 | E13: LEI | F13: Ishares iboxx h/y corp | G13: US4642885135 | H13: ISIN | I13: עוקב אחר מדדים אחרים בחו"ל | J13: חו"ל | K13: ארה"ב | L13: NYSE | M13: Bond/Fixed Income Funds | N13: לא | O13: USD | P13: 1580 | Q13: 3.372 | R13: 8065 | T13: 429.684 | U13: 5e-06 | V13: 0.013714146 | W13: 0.0027893504
... A15: 891 | B15: 9957 | C15: BlackRock Asset Managment | D15: 254900UWHMJRRODS3Z64 | E15: LEI | F15: MCHI_Ishares Msci Chaina Etf | G15: US46429B6719 | H15: ISIN | I15: עוקב אחר מדדי מניות בחו"ל | J15: חו"ל | K15: סין | L15: NASDAQ | M15: Equity Funds | N15: לא | O15: USD | P15: 2900 | Q15: 3.372 | R15: 5510 | T15: 538.812 | U15: 1.8e-05 | V15: 0.017197167 | W15: 0.0034977697
A16: 891 | B16: 9957 | C16: Invesco investment management limited | D16: ECPGFXU8A2SHKVVGJI15 | E16: LEI | F16: Powershares QQQ NAS1 | G16: US46090E1038 | H16: ISIN | I16: עוקב אחר מדדי מניות בחו"ל | J16: חו"ל | K16: ארה"ב | L16: NASDAQ | M16: Equity Funds | N16: לא | O16: USD | P16: 1072 | Q16: 3.372 | R16: 55164 | S16: 0.318 | T16: 1995.133 | U16: 2e-06 | V16: 0.063678329 | W16: 0.012951676
A17: 891 | B17: 9957 | C17: Invesco investment management limited | D17: ECPGFXU8A2SHKVVGJI15 | E17: LEI | F17: SOURCE S&P 500 UCITS EFT | G17: IE00B3YCGJ38 | H17: ISIN | I17: עוקב אחר מדדי מניות בחו"ל | J17: חו"ל | K17: ארה"ב | L17: LSE | M17: Equity Funds | N17: לא | O17: USD | P17: 988 | Q17: 3.372 | R17: 122758 | T17: 4089.727 | U17: 0.000195 | V17: 0.13053112 | W17: 0.026549012
A18: 891 | B18: 9957 | C18: State Street Corp | D18: 07F5H7W3ET8ZLWNMFP29 | E18: LEI | F18: SPDR BLOOMBERG SASB U.S. HIGH | G18: IE0004TYCC17 | H18: ISIN | I18: עוקב אחר מדדים אחרים בחו"ל | J18: חו"ל | K18: ארה"ב | L18: NYSE | M18: Bond/Fixed Income Funds | N18: לא | O18: USD | P18: 31999 | Q18: 3.372 | R18: 1125.9 | T18: 1214.853 | U18: 0 | V18: 0.038774261 | W18: 0.0078863824
A19: 891 | B19: 9957 | C19: State Street Corp | D19: 07F5H7W3ET8ZLWNMFP29 | E19: LEI | F19: SPDR S&P 500 ETF TRUST | G19: US78462F1030 | H19: ISIN | I19: עוקב אחר מדדי מניות בחו"ל | J19: חו"ל | K19: ארה"ב | L19: NYSE | M19: Equity Funds | N19: לא | O19: USD | P19: 338 | Q19: 3.372 | R19: 61785 | S19: 0.446 | T19: 705.69 | U19: 0 | V19: 0.022523385 | W19: 0.004581081
A20: 891 | B20: 9957 | C20: Van Eck ETF | D20: 549300ZLFKNTXC51ZN76 | E20: LEI | F20: VANECK VECTORS SEMICONDUCTOR | G20: US92189F6768 | H20: ISIN | I20: עוקב אחר מדדי מניות בחו"ל | J20: חו"ל | K20: ארה"ב | L20: NASDAQ | M20: Equity Funds | N20: לא | O20: USD | P20: 357 | Q20: 3.372 | R20: 27888 | T20: 335.717 | U20: 1.6e-05 | V20: 0.010715018 | W20: 0.0021793511
A21: 891 | B21: 9957 | C21: Vanguard Group | D21: 549300Y88GQ3VLJIBX57 | E21: LEI | F21: VANGUARD S&P 500 | G21: us9229083632 | H21: ISIN | I21: עוקב אחר מדדי מניות בחו"ל | J21: חו"ל | K21: ארה"ב | L21: NYSE | M21: Equity Funds | N21: לא | O21: USD | P21: 2400 | Q21: 3.372 | R21: 56803 | S21: 3.138 | T21: 4607.533 | U21: 3e-06 | V21: 0.14705785 | W21: 0.029910422

Sheet קרנות נאמנות
A1: מספר קופה/קרן/ח.פ. עבור חברת ביטוח | B1: מספר מסלול | C1: שם מנפיק | D1: מספר מנפיק | E1: סוג מספר מזהה מנפיק | F1: שם נייר ערך | G1: מספר נייר ערך | H1: סוג מספר נייר ערך | I1: מאפיין עיקרי | J1: ישראל/חו"ל | K1: מדינה לפי חשיפה כלכלית | L1: סטאטוס סחירות | M1: זירת מסחר | N1: סיווג הקרן | O1: בעל עניין/צד קשור | P1: מטבע פעילות | Q1: ערך נקוב (יחידות) | R1: שער חליפין | S1: שער נייר הערך | T1: שווי הוגן (באלפי ש"ח) | U1: שיעור מערך נקוב מונפק | V1: שיעור מנכסי אפיק ההשקעה | W1: שיעור מסך נכסי ההשקעה
A2: 891 | B2: 9957 | C2: אי בי אי ניהול קרנות נאמנות בע"מ | D2: 510791031 | E2: ח.פ | F2: איביאי טכנולגיית עילית | G2: IL0011425381 | H2: ISIN | I2: מניות | J2: ישראל | K2: ישראל | L2: סחיר | M2: TASE | N2: מניות בישראל | O2: לא | P2: ILS | Q2: 295799.52 | R2: 1 | S2: 74.8 | T2: 221.258 | U2: 0.000955 | V2: 0.21712003 | W2: 0.0014363263
A3: 891 | B3: 9957 | C3: Kotak | D3: 213800SJ3IH3EXMXSJ47 | E3: LEI | F3: KOTAK FDS-INDIA MIDCAP (S) USD A | G3: LU2126068639 | H3: ISIN | I3: מניות | J3: חו"ל | K3: הודו | L3: סחיר | M3: אחר | N3: Equity Funds | O3: לא | P3: USD | Q3: 15643.62 | R3: 3.372 | S3: 1512.41 | T3: 797.801 | U3: 0.000682 | V3: 0.78287997 | W3: 0.0051790298

Sheet כתבי אופציה
A1: מספר קופה/קרן/ח.פ. עבור חברת ביטוח | B1: מספר מסלול | C1: שם מנפיק | D1: מספר מנפיק | E1: סוג מספר מזהה מנפיק | F1: שם נייר ערך | G1: מספר נייר ערך | H1: סוג מספר נייר ערך | I1: ישראל/חו"ל | J1: מדינה לפי חשיפה כלכלית | K1: סטאטוס סחירות | L1: זירת מסחר | M1: נכס בסיס (כתב אופציה) | N1: ענף מסחר | O1: תאריך פקיעה | P1: בעל עניין/צד קשור | Q1: מטבע פעילות | R1: שער מימוש | S1: יחס המרה | T1: ערך נקוב (יחידות) | U1: שער חליפין | V1: שער נייר הערך | W1: שווי הוגן (באלפי ש"ח) | X1: שיעור מנכסי אפיק ההשקעה | Y1: שיעור מסך נכסי ההשקעה
A2: 891 | B2: 9957 | C2: אלומיי קפיטל בע"מ | D2: 520039868 | E2: ח.פ | F2: אלומיי אופ 2 | G2: IL0012030826 | H2: ISIN | I2: ישראל | J2: ישראל | K2: סחיר | L2: TASE | M2: IL0010826357 | N2: אנרגיה מתחדשת | O2: 05/01/2028 | P2: לא | Q2: ILS | R2: 8000 | S2: 0 | T2: 834 | U2: 1 | V2: 327.1 | W2: 2.728 | X2: 0.072334226 | Y2: 1.7709269e-05
A3: 891 | B3: 9957 | C3: ביג מרכזי קניות (2004) בע"מ | D3: 513623314 | E3: ח.פ | F3: ביג אפ 7 | G3: IL0012143454 | H3: ISIN | I3: ישראל | J3: ישראל | K3: סחיר | L3: TASE | M3: IL0010972607 | N3: נדל"ן מניב בישראל | O3: 01/06/2026 | P3: לא | Q3: ILS | R3: 58000 | S3: 1 | T3: 357 | U3: 1 | V3: 9800 | W3: 34.986 | X3: 0.92766577 | Y3: 0.00022711632

Sheet אופציות
A1: מספר קופה/קרן/ח.פ. עבור חברת ביטוח | B1: מספר מסלול | C1: שם מנפיק | D1: מספר מנפיק | E1: סוג מספר מזהה מנפיק | F1: שם נייר ערך | G1: מספר נייר ערך | H1: סוג מספר נייר ערך | I1: מאפיין עיקרי | J1: ישראל/חו"ל | K1: מדינה לפי חשיפה כלכלית | L1: זירת מסחר | M1: ענף מסחר | N1: נכס בסיס | O1: תאריך פקיעה | P1: בעל עניין/צד קשור | Q1: מטבע פעילות | R1: שער מימוש | S1: ערך נקוב (יחידות) | T1: שער חליפין | U1: שער נייר הערך | V1: שווי הוגן (באלפי ש"ח) | W1: שיעור מנכסי אפיק ההשקעה | X1: שיעור מסך נכסי ההשקעה
A2: 891 | B2: 9957

Sheet חוזים עתידיים
A1: מספר קופה/קרן/ח.פ. עבור חברת ביטוח | B1: מספר מסלול | C1: שם מנפיק | D1: מספר מנפיק | E1: סוג מספר מזהה מנפיק | F1: שם נייר ערך | G1: מספר נייר ערך | H1: סוג מספר נייר ערך | I1: ישראל/חו"ל | J1: מדינה לפי חשיפה כלכלית | K1: זירת מסחר | L1: נכס בסיס | M1: בעל עניין/צד קשור | N1: מטבע פעילות | O1: ערך נקוב (יחידות) | P1: שער חליפין | Q1: שער נייר הערך | R1: שווי הוגן (באלפי ש"ח) | S1: שיעור מנכסי אפיק ההשקעה | T1: שיעור מסך נכסי ההשקעה
A2: 891 | B2: 9957 | C2: חוזים עתידיים בחול | D2: 10527 | E2: פנימי | F2: ESU5_MINI S&P 500 FUT 09/2025 | G2: ESU5 | H2: אחר | I2: חו"ל | J2: ארה"ב | K2: CME | L2: מניות לרבות מדדי מניות | M2: לא | N2: USD | O2: 12 | P2: 3.372 | Q2: 6253.75 | R2: 448.645 | S2: 0.93953637 | T2: 0.0029124366
A3: 891 | B3: 9957 | C3: חוזים עתידיים בחול | D3: 10527 | E3: פנימי | F3: US 10YR ULTRA FUT SEP 25 | G3: UXYU5 | H3: אחר | I3: חו"ל | J3: ארה"ב | K3: CBOE | L3: ריבית ואג"ח | M3: לא | N3: USD | O3: 4 | P3: 3.372 | Q3: 114.266 | R3: 28.872 | S3: 0.060463632 | T3: 0.00018742914

Sheet מוצרים מובנים
A1: מספר קופה/קרן/ח.פ. עבור חברת ביטוח | B1: מספר מסלול | C1: שם מנפיק | D1: מספר מנפיק | E1: סוג מספר מזהה מנפיק | F1: שם נייר ערך | G1: מספר נייר ערך | H1: סוג מספר נייר ערך | I1: מאפיין עיקרי | J1: ישראל/חו"ל | K1: מדינה לפי חשיפה כלכלית | L1: סטאטוס סחירות | M1: זירת מסחר | N1: נכס בסיס | O1: בעל עניין/צד קשור | P1: מח"מ | Q1: שיעור ריבית | R1: תשואה לפדיון | S1: דירוג | T1: שם מדרג | U1: דירוג נייר הערך/המנפיק | V1: מטבע פעילות | W1: ערך נקוב (יחידות) | X1: שער חליפין | Y1: שער נייר הערך | Z1: שווי הוגן (באלפי ש"ח) | AA1: שיעור מנכסי אפיק ההשקעה | AB1: שיעור מסך נכסי ההשקעה
A2: 891 | B2: 9957

Sheet לא סחיר איגרות חוב ממשלתיות
A1: מספר קופה/קרן/ח.פ. עבור חברת ביטוח | B1: מספר מסלול | C1: שם מנפיק | D1: שם נייר ערך | E1: מספר נייר ערך | F1: סוג מספר נייר ערך | G1: מאפיין עיקרי | H1: ישראל/חו"ל | I1: מדינה לפי חשיפה כלכלית | J1: תאריך רכישה | K1: דירוג | L1: שם מדרג | M1: מטבע פעילות | N1: מח"מ | O1: מועד פדיון | P1: שיעור ריבית | Q1: תשואה לפדיון | R1: ערך נקוב (יחידות) | S1: שער חליפין | T1: שער נייר הערך | U1: שווי הוגן (באלפי ש"ח) | V1: עלות מופחתת (באלפי ש"ח) | W1: השיטה שיושמה בדוח הכספי | X1: שיעור מנכסי אפיק ההשקעה | Y1: שיעור מסך נכסי ההשקעה
A2: 891 | B2: 9957

Sheet לא סחיר איגרות חוב מיועדות
A1: מספר קופה/קרן/ח.פ. עבור חברת ביטוח | B1: מספר מסלול | C1: מאפיין עיקרי | D1: שם נייר ערך | E1: מספר נייר ערך | F1: תאריך רכישה | G1: מח"מ | H1: סוג הצמדה | I1: מועד פדיון | J1: שיעור ריבית | K1: תשואה לפדיון | L1: ערך נקוב (יחידות) | M1: שער נייר הערך | N1: שווי הוגן (באלפי ש"ח) | O1: עלות מופחתת (באלפי ש"ח) | P1: השיטה שיושמה בדוח הכספי | Q1: שיעור מנכסי אפיק ההשקעה | R1: שיעור מסך נכסי ההשקעה
A2: 891 | B2: 9957

Sheet אפיק השקעה מובטח תשואה
A1: מספר קרן | B1: מספר מסלול | C1: מאפיין עיקרי | D1: חודש הנפקת שכבה | E1: חודש הבדיקה | F1: שווי הנכסים באפיק (באלפי ש"ח) | G1: שיעור מסך נכסי ההשקעה

Sheet לא סחיר ניירות ערך מסחריים
A1: מספר קופה/קרן/ח.פ. עבור חברת ביטוח | B1: מספר מסלול | C1: שם מנפיק | D1: מספר מנפיק | E1: סוג מספר מזהה מנפיק | F1: שם נייר ערך | G1: מספר נייר ערך | H1: סוג מספר נייר ערך | I1: מאפיין עיקרי | J1: ישראל/חו"ל | K1: מדינה לפי חשיפה כלכלית | L1: ענף מסחר | M1: בעל עניין/צד קשור | N1: תאריך רכישה | O1: דירוג | P1: שם מדרג | Q1: דירוג נייר הערך/המנפיק | R1: מטבע פעילות | S1: מח"מ | T1: סוג הצמדה | U1: ריבית עוגן | V1: מועד פדיון | W1: שיעור ריבית | X1: תשואה לפדיון | Y1: נחיתות חוזית | Z1: האם סווג כחוב בעייתי | AA1: סוג גורם משערך | AB1: תלות/אי-תלות המשערך | AC1: שם גורם משערך | AD1: תאריך שערוך אחרון | AE1: תאריך אחרון בו נבחנה בפועל ירידת ערך | AF1: ערך נקוב (יחידות) | AG1: שער חליפין | AH1: שער נייר הערך | AI1: שווי הוגן (באלפי ש"ח) | AJ1: עלות מופחתת (באלפי ש"ח) | AK1: עלות מופחתת (במטבע הפעילות) | AL1: השיטה שיושמה בדוח הכספי | AM1: שיעור מנכסי אפיק ההשקעה | AN1: שיעור מסך נכסי ההשקעה
A2: 891 | B2: 9957

Sheet לא סחיר איגרות חוב
A1: מספר קופה/קרן/ח.פ. עבור חברת ביטוח | B1: מספר מסלול | C1: שם מנפיק | D1: מספר מנפיק | E1: סוג מספר מזהה מנפיק | F1: שם נייר ערך | G1: מספר נייר ערך | H1: סוג מספר נייר ערך | I1: מאפיין עיקרי | J1: ישראל/חו"ל | K1: מדינה לפי חשיפה כלכלית | L1: סטאטוס סחירות | M1: ענף מסחר | N1: בעל עניין/צד קשור | O1: תאריך רכישה | P1: דירוג | Q1: שם מדרג | R1: דירוג נייר הערך/המנפיק | S1: מטבע פעילות | T1: מח"מ | U1: מועד פדיון | V1: תשואה לפדיון | W1: שיעור ריבית | X1: נחיתות חוזית | Y1: האם סווג כחוב בעייתי | Z1: סוג גורם משערך | AA1: תלות/אי-תלות המשערך | AB1: תאריך שערוך אחרון | AC1: תאריך אחרון בו נבחנה בפועל ירידת ערך | AD1: ערך נקוב (יחידות) | AE1: שער חליפין | AF1: שער נייר הערך | AG1: שווי הוגן (באלפי ש"ח) | AH1: עלות מופחתת (באלפי ש"ח) | AI1: עלות מופחתת (במטבע הפעילות) | AJ1: השיטה שיושמה בדוח הכספי | AK1: שיעור מנכסי אפיק ההשקעה | AL1: שיעור מסך נכסי ההשקעה
A2: 891 | B2: 9957 | C2: אידיבי חברה לאחזקות בע"מ | D2: 520028283 | E2: ח.פ | F2: אידיבי אגח ב (מחוק) | G2: IL0073600350 | H2: ISIN | I2: צמוד למדד המחירים לצרכן | J2: ישראל | K2: ישראל | L2: אחר | M2: השקעה ואחזקות | N2: לא | O2: 15/12/2014 | P2: D | Q2: S&P מעלות | R2: נייר ערך | S2: ILS | T2: 0.01 | U2: 06/09/2013 | V2: 0.0001 | W2: 0.057 | X2: החוב נחות | Y2: כן | Z2: גורם תלוי/פנימי | AA2: קיימת תלות | AB2: 31/03/2020 | AD2: 16666.7 | AE2: 1 | AF2: 0 | AG2: 0 | AJ2: שווי הוגן | AK2: 9.5313671e-11 | AL2: 1.0819412e-12
A3: 891 | B3: 9957 | C3: י.ח.ק להשקעות שותפות מוגבלת | D3: 550016091 | E3: מספר שותפות | F3: י.ח.ק. אגח ב רמ | G3: IL0011817835 | H3: ISIN | I3: לא צמוד למדד המחירים לצרכן | J3: ישראל | K3: ישראל | L3: לא סחיר | M3: השקעה ואחזקות | N3: לא | O3: 19/11/2021 | P3: A+ | Q3: S&P מעלות | R3: נייר ערך | S3: ILS | T3: 1.91 | U3: 31/12/2028 | V3: 0.051 | W3: 0.0286 | X3: החוב לא נחות | Y3: לא | Z3: חברת ציטוט | AA3: אי-תלות | AB3: 30/06/2025 | AD3: 90285.74 | AE3: 1 | AF3: 97.29 | AG3: 87.839 | AJ3: שווי הוגן | AK3: 0.050233443 | AL3: 0.00057021864
A4: 891 | B4: 9957 | C4: כלל תעשיות בע"מ | D4: 520021874 | E4: ח.פ | F4: כלל תעש אגח טז-רמ | G4: IL0060802381 | H4: ISIN | I4: לא צמוד למדד המחירים לצרכן | J4: ישראל | K4: ישראל | L4: לא סחיר | M4: השקעה ואחזקות | N4: לא | O4: 27/10/2021 | P4: A | Q4: S&P | R4: נייר ערך | S4: ILS | T4: 1.72 | U4: 30/06/2027 | V4: 0.0521 | W4: 0.0447 | X4: החוב לא נחות | Y4: לא | Z4: חברת ציטוט | AA4: אי-תלות | AB4: 30/06/2025 | AD4: 398163.28 | AE4: 1 | AF4: 98.87 | AG4: 393.664 | AJ4: שווי הוגן | AK4: 0.22512893 | AL4: 0.0025555229
A5: 891 | B5: 9957 | C5: לידר החזקות והשקעות בע"מ | D5: 520037664 | E5: ח.פ | F5: לידר אגח ח - רמ | G5: IL0031803617 | H5: ISIN | I5: לא צמוד למדד המחירים לצרכן | J5: ישראל | K5: ישראל | L5: אחר | M5: השקעה ואחזקות | N5: לא | O5: 01/03/2021 | P5: A1 | Q5: מידרוג Moodys | R5: נייר ערך | S5: ILS | T5: 1.59 | U5: 15/02/2028 | V5: 0.0475 | W5: 0.021 | X5: החוב לא נחות | Y5: לא | Z5: חברת ציטוט | AA5: אי תלות | AB5: 30/06/2025 | AD5: 144857.33 | AE5: 1 | AF5: 96.74 | AG5: 140.135 | AJ5: שווי הוגן | AK5: 0.080140516 | AL5: 0.00090970504
A6: 891 | B6: 9957 | C6: מת"ם - מרכז תעשיות מדע חיפה בע"מ | D6: 510687403 | E6: ח.פ | F6: מתם מרכז תעשיות מדע חיפה אגח א ר.מ | G6: IL0011389991 | H6: ISIN | I6: לא צמוד למדד המחירים לצרכן | J6: ישראל | K6: ישראל | L6: אחר | M6: נדל"ן מניב בישראל | N6: לא | O6: 04/03/2024 | P6: Aa2 | Q6: מידרוג Moodys | R6: נייר ערך | S6: ILS | T6: 1.46 | U6: 30/06/2027 | V6: 0.0463 | W6: 0.031 | X6: החוב לא נחות | Y6: לא | Z6: חברת ציטוט | AA6: אי תלות | AB6: 30/06/2025 | AD6: 99016 | AE6: 1 | AF6: 97.91 | AG6: 96.947 | AJ6: שווי הוגן | AK6: 0.055441887 | AL6: 0.00062934164
A7: 891 | B7: 9957 | C7: עוגן-אג"ח חברתית 2 בע"מ | D7: 516556545 | E7: ח.פ | F7: עוגן חברתית 2 אגחא-רמ | G7: IL0011968315 | H7: ISIN | I7: לא צמוד למדד המחירים לצרכן | J7: ישראל | K7: ישראל | L7: אחר | M7: שירותים פיננסיים | N7: לא | O7: 19/06/2023 | P7: Aa2 | Q7: מידרוג Moodys | R7: נייר ערך | S7: ILS | T7: 0.46 | U7: 15/03/2026 | V7: 0.052 | W7: 0.065 | X7: החוב לא נחות | Y7: לא | Z7: חברת ציטוט | AA7: אי-תלות | AB7: 30/06/2025 | AD7: 47082.84 | AE7: 1 | AF7: 100.81 | AG7: 47.464 | AJ7: שווי הוגן | AK7: 0.027143875 | AL7: 0.0003081203
A8: 891 | B8: 9957 | C8: רפאל-רשות לפיתוח אמצעי לחימה בע"מ | D8: 520042185 | E8: ח.פ | F8: רפאל אגח ג ר.מ. | G8: IL0011402760 | H8: ISIN | I8: צמוד למדד המחירים לצרכן | J8: ישראל | K8: ישראל | L8: אחר | M8: ביטחוניות | N8: לא | O8: 05/05/2021 | P8: AAA | Q8: S&P מעלות | R8: נייר ערך | S8: ILS | T8: 4.38 | U8: 15/09/2034 | V8: 0.0249 | W8: 0.023218 | X8: החוב לא נחות | Y8: לא | Z8: חברת ציטוט | AA8: אי תלות | AB8: 30/06/2025 | AD8: 256538.47 | AE8: 1 | AF8: 117.69 | AG8: 301.92 | AJ8: שווי הוגן | AK8: 0.17266235 | AL8: 0.001959955
A9: 891 | B9: 9957 | C9: רפאל-רשות לפיתוח אמצעי לחימה בע"מ | D9: 520042185 | E9: ח.פ | F9: רפאל אגח סדרה ה 2020/2026 | G9: IL0011402927 | H9: ISIN | I9: לא צמוד למדד המחירים לצרכן | J9: ישראל | K9: ישראל | L9: לא סחיר | M9: ביטחוניות | N9: לא | O9: 05/05/2021 | P9: AAA | Q9: S&P מעלות | R9: נייר ערך | S9: ILS | T9: 0.7 | U9: 15/03/2026 | V9: 0.0472 | W9: 0.025 | X9: החוב לא נחות | Y9: לא | Z9: חברת ציטוט | AA9: אי תלות | AB9: 30/06/2025 | AD9: 151744.61 | AE9: 1 | AF9: 99.24 | AG9: 150.591 | AJ9: שווי הוגן | AK9: 0.086120314 | AL9: 0.00097758397
A10: 891 | B10: 9957 | C10: רפאל-רשות לפיתוח אמצעי לחימה בע"מ | D10: 520042185 | E10: ח.פ | F10: רפאל סד' ד 2020/2034 | G10: IL0011402844 | H10: ISIN | I10: לא צמוד למדד המחירים לצרכן | J10: ישראל | K10: ישראל | L10: לא סחיר | M10: ביטחוניות | N10: לא | O10: 05/05/2021 | P10: AAA | Q10: S&P מעלות | R10: נייר ערך | S10: ILS | T10: 4.13 | U10: 15/09/2034 | V10: 0.0465 | W10: 0.0374 | X10: החוב לא נחות | Y10: לא | Z10: חברת ציטוט | AA10: אי תלות | AB10: 30/06/2025 | AD10: 543089.79 | AE10: 1 | AF10: 97.6 | AG10: 530.056 | AJ10: שווי הוגן | AK10: 0.30312868 | AL10: 0.0034409273

Sheet לא סחיר מניות מבכ ויהש
A1: מספר קופה/קרן/ח.פ. עבור חברת ביטוח | B1: מספר מסלול | C1: שם מנפיק | D1: מספר מנפיק | E1: סוג מספר מזהה מנפיק | F1: שם נייר ערך | G1: מספר נייר ערך | H1: סוג מספר נייר ערך | I1: מאפיין עיקרי | J1: ישראל/חו"ל | K1: מדינה לפי חשיפה כלכלית | L1: סטאטוס סחירות | M1: ענף מסחר | N1: בעל עניין/צד קשור | O1: תאריך רכישה | P1: מטבע פעילות | Q1: סוג גורם משערך | R1: תלות/אי-תלות המשערך | S1: תאריך שערוך אחרון | T1: תאריך אחרון בו נבחנה בפועל ירידת ערך | U1: ערך נקוב (יחידות) | V1: שער חליפין | W1: שער נייר הערך | X1: שווי הוגן (באלפי ש"ח) | Y1: שיעור מנכסי אפיק ההשקעה | Z1: שיעור מסך נכסי ההשקעה
A2: 891 | B2: 9957 | C2: לוסיקס בע"מ | D2: 515374742 | E2: ח.פ | F2: Lusix | G2: 620201931 | H2: פנימי | I2: מניות לא סחירות | J2: ישראל | K2: ישראל | L2: אחר | M2: Utilities | N2: לא | O2: 02/12/2024 | P2: USD | Q2: דיווח מנהל הקרן | R2: אי תלות | S2: 28/11/2024 | U2: 36518 | V2: 3.372 | W2: 27.384 | X2: 33.72 | Y2: 0.01752439 | Z2: 0.00021889986
A3: 891 | B3: 9957 | C3: UVEYE LTD | D3: 514234202 | E3: ח.פ | F3: UVEYE LTD | G3: 62018263 | H3: פנימי | I3: מניות לא סחירות | J3: ישראל | K3: ישראל | L3: אחר | M3: השקעות בהייטק | N3: לא | O3: 01/04/2025 | P3: USD | Q3: דיווח מנהל הקרן | R3: אי תלות | S3: 31/03/2025 | U3: 25178 | V3: 3.372 | W3: 830.05 | X3: 704.714 | Y3: 0.36623895 | Z3: 0.0045747471
A4: 891 | B4: 9957 | C4: ג'נריישן ניהול בע"מ | D4: 515785012 | E4: ח.פ | F4: ג'נריישן ניהול בע"מ | G4: 56093 | H4: פנימי | I4: מניות לא סחירות | J4: ישראל | K4: ישראל | L4: אחר | M4: נדל"ן מניב בישראל | N4: לא | O4: 16/08/2018 | P4: ILS | Q4: דיווח מנהל הקרן | R4: אי-תלות | S4: 30/06/2025 | U4: 50.63 | V4: 1 | W4: 159065.18 | X4: 80.535 | Y4: 0.041853764 | Z4: 0.00052280181
A5: 891 | B5: 9957 | C5: מניבים קרן הריט החדשה בע"מ | D5: 515327120 | E5: ח.פ | F5: מניבים ניהול הר | G5: 36475 | H5: פנימי | I5: מניות לא סחירות | J5: ישראל | K5: ישראל | L5: אחר | M5: נדל"ן מניב בישראל | N5: לא | O5: 03/11/2015 | P5: ILS | Q5: דיווח מנהל הקרן | R5: אי תלות | S5: 30/06/2025 | U5: 5 | V5: 1 | W5: 680012.79 | X5: 34.001 | Y5: 0.017670082 | Z5: 0.00022071972
A6: 891 | B6: 9957 | C6: וויו (veev) גרופ | D6: 832652993 | E6: פנימי | F6: C וויו גרופ | G6: US9224741010 | H6: ISIN | I6: מניות לא סחירות | J6: ישראל | K6: ישראל | L6: אחר | M6: השקעות בהיי-טק | N6: לא | O6: 08/03/2021 | P6: ILS | Q6: גורם תלוי/פנימי | R6: קיימת תלות | S6: 30/04/2025 | U6: 316640 | V6: 1 | W6: 0 | X6: 0 | Y6: 1.6455734e-09 | Z6: 2.0555111e-11
A7: 891 | B7: 9957 | C7: Rapyd financial network 2016 ltd | D7: 28595 | E7: פנימי | F7: TARGET GLOBAL -FLUORINE (RAPYD | G7: 62018115 | H7: פנימי | I7: מניות לא סחירות | J7: חו"ל | K7: גרמניה | L7: אחר | M7: Technology Hardware, Storage & Peripherals | N7: לא | O7: 04/07/2022 | P7: USD | Q7: דיווח מנהל הקרן | R7: אי-תלות | S7: 24/06/2025 | U7: 45225 | V7: 3.372 | W7: 157.821 | X7: 240.675 | Y7: 0.12507866 | Z7: 0.0015623769
A8: 891 | B8: 9957 | C8: wefox | D8: 28503 | E8: פנימי | F8: TARGET GLOBAL-NICKEL (WEFOX) | G8: 62018396 | H8: פנימי | I8: מניות לא סחירות | J8: חו"ל | K8: גרמניה | L8: אחר | M8: Technology Hardware, Storage & Peripherals | N8: לא | O8: 04/07/2022 | P8: EUR | Q8: דיווח מנהל הקרן | R8: אי תלות | S8: 24/06/2025 | U8: 75375 | V8: 3.9552 | W8: 99.907 | X8: 297.847 | Y8: 0.15479072 | Z8: 0.0019335147
A9: 891 | B9: 9957 | C9: Verbit Inc | D9: 28460 | E9: פנימי | F9: Verbit Inc | G9: 620182700 | H9: פנימי | I9: מניות לא סחירות | J9: חו"ל | K9: גלובלי | L9: אחר | M9: Technology Hardware, Storage & Peripherals | N9: לא | O9: 20/03/2023 | P9: USD | Q9: דיווח מנהל הקרן | R9: אי תלות | S9: 29/06/2025 | U9: 9960 | V9: 3.372 | W9: 381.3 | X9: 128.06 | Y9: 0.066552625 | Z9: 0.00083131909
A10: 891 | B10: 9957 | C10: PROSPECT CAPITAL CORP | D10: 549300FSD8T39P5Q0O47 | E10: LEI | F10: מניות בכורה Prospect 5.5% 1025 | G10: US74348T5083 | H10: ISIN | I10: מניות לא סחירות | J10: חו"ל | K10: ארה"ב | L10: אחר | M10: שירותים פיננסיים | N10: לא | O10: 27/04/2021 | P10: USD | Q10: מומחה בלתי תלוי | R10: אי תלות | S10: 01/04/2025 | U10: 4800 | V10: 3.372 | W10: 2500 | X10: 404.64 | Y10: 0.21029081 | Z10: 0.0026267749

Sheet קרנות השקעה
A1: מספר קופה/קרן/ח.פ. עבור חברת ביטוח | B1: מספר מסלול | C1: שם שותף כללי קרן השקעות | D1: מספר מזהה שותף כללי קרן השקעות | E1: סוג מספר מזהה שותף כללי קרן השקעות | F1: שם קרן השקעה | G1: מספר מזהה קרן השקעה | H1: סוג מספר מזהה קרן השקעות | I1: מאפיין עיקרי | J1: אסטרטגיית קרן ההשקעה | K1: ישראל/חו"ל | L1: מדינת התאגדות קרן השקעה | M1: מיקום משרד השותף הכללי | N1: מדינה לפי חשיפה כלכלית | O1: בעל עניין/צד קשור | P1: תאריך רכישה | Q1: מטבע פעילות | R1: סוג גורם משערך | S1: תלות/אי-תלות המשערך | T1: תאריך שערוך אחרון | U1: שער חליפין | V1: NAV (במטבע הדיווח של קרן ההשקעה) | W1: שווי הוגן (באלפי ש"ח) | X1: שיעור החזקה בקרן השקעה | Y1: שיעור מנכסי אפיק ההשקעה | Z1: שיעור מסך נכסי ההשקעה
A2: 891 | B2: 9957 | C2: Forma european fund 2 | D2: 516190006 | E2: ח.פ | F2: Forma European Fund II LP | G2: 62018528 | H2: פנימי | I2: פרייבט אקוויטי | J2: Other | K2: ישראל | L2: ישראל | M2: ישראל | N2: אירופה | O2: לא | P2: 06/07/2021 | Q2: EUR | R2: דיווח מנהל הקרן | S2: אי-תלות | T2: 19/05/2025 | U2: 3.9552 | V2: 78.967 | W2: 312.33 | X2: 0 | Y2: 0.013887264 | Z2: 0.0020275312
A3: 891 | B3: 9957 | C3: Kedma Capital | D3: 540286333 | E3: ח.פ | F3: KEDMA CAPITAL PARTNERS III LTD | G3: 62018080 | H3: פנימי | I3: פרייבט אקוויטי | J3: Other | K3: ישראל | L3: ישראל | M3: ישראל | N3: ישראל | O3: לא | P3: 04/04/2021 | Q3: USD | R3: דיווח מנהל הקרן | S3: אי-תלות | T3: 31/03/2025 | U3: 3.372 | V3: 105.58 | W3: 356.017 | X3: 0 | Y3: 0.015829725 | Z3: 0.0023111292
A4: 891 | B4: 9957 | C4: Klirmark Opportunity Fund | D4: CO-101523 | E4: מספר תאגיד או שותפות בחו"ל | F4: klirmark IV | G4: 50007947 | H4: פנימי | I4: קרן חוב | J4: Other | K4: ישראל | L4: איי קיימן | M4: איי קיימן | N4: ישראל | O4: לא | P4: 23/04/2023 | Q4: ILS | R4: דיווח מנהל הקרן | S4: אי-תלות | T4: 30/06/2025 | U4: 1 | V4: 410.801 | W4: 410.801 | X4: 0 | Y4: 0.018265615 | Z4: 0.0026667675
A5: 891 | B5: 9957 | C5: Peregrine Ventures Growth General Partner LP | D5: 540297413 | E5: פנימי | F5: Peregrine Ventures Growth General Partner LP | G5: 62018569 | H5: פנימי | I5: פרייבט אקוויטי | J5: Other | K5: ישראל | L5: ישראל | M5: ישראל | N5: גלובלי | O5: לא | P5: 08/07/2021 | Q5: USD | R5: דיווח מנהל הקרן | S5: אי-תלות | T5: 12/05/2025 | U5: 3.372 | V5: 49.412 | W5: 166.618 | X5: 0 | Y5: 0.0074084178 | Z5: 0.001081624
A6: 891 | B6: 9957 | C6: 0 | D6: 540310885 | E6: מספר שותפות | F6: Qumra Opportunity fund | G6: 62018254 | H6: פנימי | I6: פרייבט אקוויטי | J6: Growth Venture Capital | K6: חו"ל | L6: איי קיימן | M6: איי קיימן | N6: ישראל | O6: לא | P6: 11/05/2021 | Q6: USD | R6: דיווח מנהל הקרן | S6: אי-תלות | T6: 30/06/2025 | U6: 3.372 | V6: 48.941 | W6: 165.03 | X6: 0 | Y6: 0.0073377954 | Z6: 0.0010713132
A7: 891 | B7: 9957 | C7: קרן השקעה אלפא ערך 1 | D7: 530225416 | E7: ח.פ | F7: אלפא ערך 1 ש.מ | G7: 50008341 | H7: פנימי | I7: קרן גידור (Hedge Fund) | J7: Other | K7: ישראל | L7: ישראל | M7: ישראל | N7: ישראל | O7: לא | P7: 26/12/2024 | Q7: ILS | R7: דיווח מנהל הקרן | S7: אי תלות | T7: 17/06/2025 | U7: 1 | V7: 434.18 | W7: 434.18 | X7: 0 | Y7: 0.019305125 | Z7: 0.0028185352
A8: 891 | B8: 9957 | C8: יסודות א נדלן שותפות מוגבלת | D8: 550257125 | E8: מספר שותפות | F8: יסודות נדל"ן ג' פיתוח ושותפות | G8: 50006691 | H8: פנימי | I8: קרן חוב | J8: Other | K8: ישראל | L8: ישראל | M8: ישראל | N8: ישראל | O8: לא | P8: 04/04/2021 | Q8: ILS | R8: דיווח מנהל הקרן | S8: אי-תלות | T8: 05/06/2025 | U8: 1 | V8: 484.283 | W8: 484.283 | X8: 0.000246 | Y8: 0.021532907 | Z8: 0.0031437899
A9: 891 | B9: 9957 | C9: קוגיטו קפיטל אל.אמ.אי שותף כללי, שותפות מוגבלת | D9: 550270912 | E9: פנימי | F9: קוגיטו קפיטל 2 | G9: 62020158 | H9: פנימי | I9: פרייבט אקוויטי | J9: Other | K9: ישראל | L9: ישראל | M9: ישראל | N9: ישראל | O9: לא | P9: 06/02/2022 | Q9: ILS | R9: דיווח מנהל הקרן | S9: אי-תלות | T9: 24/06/2025 | U9: 1 | V9: 411.989 | W9: 411.989 | X9: 0 | Y9: 0.018318458 | Z9: 0.0026744825
A10: 891 | B10: 9957 | C10: קרן ברוש 2234 | D10: 774636625 | E10: פנימי | F10: קרן ברוש | G10: 50005 | H10: פנימי | I10: קרן גידור (Hedge Fund) | J10: Other | K10: ישראל | L10: ישראל | M10: ישראל | N10: ישראל | O10: לא | P10: 29/05/2017 | Q10: ILS | R10: דיווח מנהל הקרן | S10: אי-תלות | T10: 17/06/2025 | U10: 1 | V10: 1386.001 | W10: 1386.001 | X10: 0 | Y10: 0.061626405 | Z10: 0.0089974136
A11: 891 | B11: 9957 | C11: תשתיות ישראל ג'י. פי. 4 שותפות מוגבלת | D11: 550243026 | E11: ח.פ | F11: תשתיות ישראל 4 -ע' ת"א | G11: 62017520 | H11: פנימי | I11: פרייבט אקוויטי | J11: Other | K11: ישראל | L11: ישראל | M11: ישראל | N11: ישראל | O11: לא | P11: 13/10/2020 | Q11: USD | R11: דיווח מנהל הקרן | S11: אי-תלות | T11: 29/05/2025 | U11: 3.372 | V11: 125.23 | W11: 422.275 | X11: 0 | Y11: 0.018775822 | Z11: 0.0027412574
A12: 891 | B12: 9957 | C12: ALTO FUND | D12: 27092 | E12: מספר תאגיד או שותפות בחו"ל | F12: ALTO 3 | G12: 62000073 | H12: פנימי | I12: קרן נדל"ן | J12: Other | K12: חו"ל | L12: איי קיימן | M12: ישראל | N12: ארה"ב | O12: לא | P12: 22/01/2017 | Q12: USD | R12: דיווח מנהל הקרן | S12: אי-תלות | T12: 24/06/2025 | U12: 3.372 | V12: 146.855 | W12: 495.196 | X12: 0 | Y12: 0.022018138 | Z12: 0.0032146333
A13: 891 | B13: 9957 | C13: ALTO FUND | D13: 27092 | E13: מספר תאגיד או שותפות בחו"ל | F13: ALTO FUND | G13: 60388022 | H13: פנימי | I13: קרן נדל"ן | J13: Other | K13: חו"ל | L13: איי קיימן | M13: ישראל | N13: ארה"ב | O13: לא | P13: 01/06/2015 | Q13: USD | R13: דיווח מנהל הקרן | S13: אי-תלות | T13: 29/05/2025 | U13: 3.372 | V13: 48.403 | W13: 163.213 | X13: 9.2e-05 | Y13: 0.0072570239 | Z13: 0.0010595206
... A54: 891 | B54: 9957 | C54: comrit | D54: 27344 | E54: פנימי | F54: קרן קומריט | G54: 60418969 | H54: פנימי | I54: קרן נדל"ן | J54: Other | K54: חו"ל | L54: איי קיימן | M54: ארה"ב | N54: ארה"ב | O54: לא | P54: 04/12/2016 | Q54: USD | R54: דיווח מנהל הקרן | S54: אי-תלות | T54: 10/02/2025 | U54: 3.372 | V54: 105.312 | W54: 355.112 | X54: 0 | Y54: 0.015789506 | Z54: 0.0023052572

Sheet לא סחיר כתבי אופציה
A1: מספר קופה/קרן/ח.פ. עבור חברת ביטוח | B1: מספר מסלול | C1: שם מנפיק | D1: מספר מנפיק | E1: סוג מספר מזהה מנפיק | F1: שם נייר ערך | G1: מספר נייר ערך | H1: סוג מספר נייר ערך | I1: ישראל/חו"ל | J1: מדינה לפי חשיפה כלכלית | K1: סטאטוס סחירות | L1: נכס בסיס (כתב אופציה) | M1: ענף מסחר | N1: תאריך פקיעה | O1: בעל עניין/צד קשור | P1: תאריך רכישה | Q1: מטבע פעילות | R1: סוג גורם משערך | S1: תלות/אי-תלות המשערך | T1: תאריך שערוך אחרון | U1: שער מימוש | V1: יחס המרה | W1: ערך נקוב (יחידות) | X1: שער נייר הערך | Y1: שער חליפין | Z1: שווי הוגן (באלפי ש"ח) | AA1: שיעור מנכסי אפיק ההשקעה | AB1: שיעור מסך נכסי ההשקעה

Sheet לא סחיר אופציות
A1: מספר קופה/קרן/ח.פ. עבור חברת ביטוח | B1: מספר מסלול | C1: שם מנפיק | D1: מספר מנפיק | E1: סוג מספר מזהה מנפיק | F1: שם נייר ערך | G1: מספר נייר ערך | H1: סוג מספר נייר ערך | I1: מאפיין עיקרי | J1: ישראל/חו"ל | K1: מדינה לפי חשיפה כלכלית | L1: ענף מסחר | M1: נכס בסיס | N1: תאריך פקיעה | O1: בעל עניין/צד קשור | P1: תאריך רכישה | Q1: מטבע פעילות | R1: סוג גורם משערך | S1: תלות/אי-תלות המשערך | T1: תאריך שערוך אחרון | U1: שער מימוש | V1: יחס המרה | W1: ערך נקוב (יחידות) | X1: שער נייר הערך | Y1: שער חליפין | Z1: שווי הוגן (בש"ח) | AA1: שיעור מנכסי אפיק ההשקעה | AB1: שיעור מסך נכסי ההשקעה

Sheet לא סחיר נגזרים אחרים
A1: מספר קופה/קרן/ח.פ. עבור חברת ביטוח | B1: מספר מסלול | C1: מאפיין עיקרי | D1: מספר עסקה (רגל 1) | E1: מטבע פעילות (רגל 1) | F1: שער חליפין | G1: ערך נקוב (רגל 1) | H1: שווי הוגן במטבע הנסחר (רגל 1) | I1: שיעור מנכסי אפיק ההשקעה (רגל 1) | J1: שיעור מסך נכסי ההשקעה (רגל 1) | K1: מספר עסקה (רגל 2) | L1: מטבע פעילות (רגל 2) | M1: שער חליפין | N1: ערך נקוב (רגל 2) | O1: שווי הוגן במטבע הנסחר (רגל 2) | P1: שיעור מנכסי ההשקעה (רגל 2) | Q1: שיעור מסך אפיק ההשקעה (רגל 2) | R1: שווי הוגן (נטו באלפי ש"ח) | S1: ישראל/חו"ל | T1: מדינה לפי חשיפה כלכלית | U1: סוג הנכס | V1: פקטור מוביל | W1: פקטור נוסף | X1: טיקר | Y1: בעל עניין/צד קשור | Z1: מועד ההתקשרות בעסקה | AA1: מועד סיום חוזי | AB1: תדירות Reset | AC1: סוג הסליקה | AD1: נספח התחשבנות בטחונות - CSA | AE1: גורם מצטט | AF1: ריבית עוגן | AG1: תקופת ריבית עוגן | AH1: שיעור ריבית עוגן | AI1: שער נכס הבסיס במועד ההתקשרות בעסקה | AJ1: שער הנגזר במועד ההתקשרות בעסקה | AK1: האם קיים קנס בגין יציאה מוקדמת | AL1: שיעור הקנס בגין יציאה מוקדמת | AM1: צד נגדי - Counterparty | AN1: שיעור מנכסי אפיק ההשקעה | AO1: שיעור מסך נכסי ההשקעה
A2: 891 | B2: 891 | C2: Funded Forward | D2: 9941677 | E2: USD | F2: 3.372 | G2: -5071000 | H2: -18052.28 | I2: 83.17 | J2: 11.72 | K2: 9941677 | L2: ILS | M2: 1 | N2: 18133896 | O2: 17018.37 | P2: 82.77 | Q2: 11.05 | R2: 1033.91 | S2: ישראל | T2: ישראל | U2: מט"ח | V2: מדינה/איזור גאוגרפי | W2: מט"ח/₪ | X2: USD ILS | Y2: לא | Z2: 45784 | AA2: 45876 | AB2: ללא | AC2: delivery | AD2: לא | AE2: הצד הנגדי | AF2: ללא | AG2: חודשי | AH2: ללא | AI2: 3.559 | AJ2: 3.356 | AK2: לא | AL2: NA | AM2: POALILIT | AN2: 0.9019 | AO2: 0.0067
A3: 891 | B3: 891 | C3: Funded Forward | D3: 9941678 | E3: EUR | F3: 3.9552 | G3: -897500 | H3: -3654.19 | I3: 16.83 | J3: 2.37 | K3: 9941678 | L3: ILS | M3: 1 | N3: 3670416 | O3: 3541.68 | P3: 17.23 | Q3: 2.3 | R3: 112.511 | S3: ישראל | T3: ישראל | U3: מט"ח | V3: מדינה/איזור גאוגרפי | W3: מט"ח/₪ | X3: EUR ILS | Y3: לא | Z3: 45784 | AA3: 45876 | AB3: ללא | AC3: delivery | AD3: לא | AE3: הצד הנגדי | AF3: ללא | AG3: חודשי | AH3: ללא | AI3: 4.071 | AJ3: 3.946 | AK3: לא | AL3: NA | AM3: POALILIT | AN3: 0.0981 | AO3: 0.0007

Sheet הלוואות
A1: מספר קופה/קרן/ח.פ. עבור חברת ביטוח | B1: מספר מסלול | C1: מספר מזהה לווה | D1: סוג מספר מזהה לווה | E1: שם הלוואה | F1: מספר הלוואה | G1: מאפיין עיקרי | H1: מאפיין הלוואות מתואמות עבור זכויות מקרקעין | I1: ישראל/חו"ל | J1: מדינה לפי חשיפה כלכלית | K1: ענף מסחר | L1: בעל עניין/צד קשור | M1: קונסורציום/ סינדיקציה | N1: מספר קונסורציום/ סינדיקציה | O1: תאריך העמדת הלוואה | P1: דירוג | Q1: שם מדרג | R1: דירוג הלוואה/המנפיק | S1: מטבע פעילות | T1: מח"מ | U1: סוג הריבית | V1: שיעור ריבית | W1: סוג הצמדה | X1: ריבית עוגן | Y1: שיעור תוספת/הפחתה לריבית העוגן | Z1: תשואה לפדיון | AA1: מועד פדיון | AB1: נחיתות חוזית | AC1: סוג בטוחה | AD1: שווי הבטוחות העומדות כנגד ההלוואה | AE1: שיעור הבטוחות מהחוב | AF1: מועד עדכון אחרון לשווי הבטוחות | AG1: זכות חזרה | AH1: מבנה לוח סילוקין | AI1: יעוד הלוואה | AJ1: זכות פירעון מוקדם | AK1: סוג גורם משערך | AL1: שם גורם משערך | AM1: תלות/אי-תלות המשערך | AN1: תאריך שערוך אחרון | AO1: תאריך אחרון בו נבחנה בפועל ירידת ערך | AP1: שיעור ריבית בגין אי-ניצול מסגרת האשראי | AQ1: ערך נקוב | AR1: שער הלוואה | AS1: שער חליפין | AT1: שווי הוגן (באלפי ש"ח) | AU1: שווי הוגן (במטבע הפעילות) | AV1: עלות מופחתת (באלפי ש"ח) | AW1: עלות מופחתת (במטבע הפעילות) | AX1: האם סווג כחוב בעייתי | AY1: השיטה שיושמה בדוח הכספי | AZ1: שיעור מנכסי אפיק ההשקעה | BA1: שיעור מסך נכסי ההשקעה
A2: 891 | B2: 9957

Sheet לא סחיר מוצרים מובנים
A1: מספר קופה/קרן/ח.פ. עבור חברת ביטוח | B1: מספר מסלול | C1: שם מנפיק | D1: מספר מנפיק | E1: סוג מספר מזהה מנפיק | F1: שם נייר ערך | G1: מספר נייר ערך | H1: סוג מספר נייר ערך | I1: מאפיין עיקרי | J1: ישראל/חו"ל | K1: מדינה לפי חשיפה כלכלית | L1: בעל עניין/צד קשור | M1: נכס בסיס | N1: תאריך רכישה | O1: דירוג | P1: שם מדרג | Q1: דירוג נייר הערך/המנפיק | R1: מטבע פעילות | S1: מח"מ | T1: שיעור ריבית | U1: תשואה לפדיון | V1: סוג גורם משערך | W1: תלות/אי-תלות המשערך | X1: תאריך שערוך אחרון | Y1: ערך נקוב (יחידות) | Z1: שער חליפין | AA1: שער נייר הערך | AB1: שווי הוגן (באלפי ש"ח) | AC1: שיעור מנכסי אפיק ההשקעה | AD1: שיעור מסך נכסי ההשקעה
A2: 891 | B2: 9957

Sheet פיקדונות מעל 3 חודשים
A1: מספר קופה/קרן/ח.פ. עבור חברת ביטוח | B1: מספר מסלול | C1: שם הבנק | D1: מספר מזהה בנק | E1: סוג מספר מזהה בנק | F1: מאפיין עיקרי | G1: תאריך פקיעת פיקדון | H1: ישראל/חו"ל | I1: מדינה לפי חשיפה כלכלית | J1: בעל עניין/צד קשור | K1: דירוג הבנק | L1: שם מדרג | M1: מטבע פעילות | N1: מח"מ | O1: שיעור ריבית | P1: תשואה לפדיון | Q1: שווי מטבעי | R1: שער חליפין | S1: שער פיקדון | T1: שווי הוגן (באלפי ש"ח) | U1: שיעור מנכסי אפיק ההשקעה | V1: שיעור מסך נכסי ההשקעה
A2: 891 | B2: 9957

Sheet זכויות מקרקעין
A1: מספר קופה/קרן/ח.פ. עבור חברת ביטוח | B1: מספר מסלול | C1: שם הנכס | D1: מאפיין עיקרי | E1: מדינת מיקום נדל"ן | F1: בעל עניין/צד קשור | G1: תאריך רכישה | H1: שימוש עיקרי בנכס | I1: מחזור חיי הנכס | J1: כתובת הנכס | K1: שיעור תשואה בפועל במהלך הרבעון | L1: השיטה שבאמצעותה נקבע שווי הנכס | M1: סוג גורם משערך | N1: שם גורם משערך | O1: תלות/אי-תלות המשערך | P1: תאריך שערוך אחרון | Q1: מטבע פעילות | R1: שווי הוגן (במטבע הפעילות) | S1: שווי הוגן (באלפי ש"ח) | T1: עלות מופחתת (באלפי ש"ח) | U1: עלות מופחתת (במטבע הפעילות) | V1: השיטה שיושמה בדוח הכספי | W1: שיעור מנכסי אפיק ההשקעה | X1: שיעור מסך נכסי ההשקעה
A2: 891 | B2: 9957

Sheet השקעה בחברות מוחזקות
A1: מספר קופה/קרן/ח.פ. עבור חברת ביטוח | B1: מספר מסלול | C1: שם מנפיק | D1: מספר מנפיק | E1: סוג מספר מזהה מנפיק | F1: שם נייר ערך | G1: מספר נייר ערך | H1: סוג מספר נייר ערך | I1: מאפיין עיקרי | J1: ישראל/חו"ל | K1: מדינה לפי חשיפה כלכלית | L1: ענף מסחר | M1: בעל עניין/צד קשור | N1: מטבע פעילות | O1: סוג גורם משערך | P1: תלות/אי-תלות המשערך | Q1: תאריך שערוך אחרון | R1: תאריך אחרון בו נבחנה בפועל ירידת ערך | S1: שיעור אחזקה באמצעי שליטה | T1: שווי מאזני (באלפי ש"ח) | U1: שווי הוגן (באלפי ש"ח) | V1: שיעור מנכסי אפיק ההשקעה | W1: שיעור מסך נכסי ההשקעה
A2: 891 | B2: 9957

Sheet נכסים אחרים
A1: מספר קופה/קרן/ח.פ. עבור חברת ביטוח | B1: מספר מסלול | C1: שם הנכס האחר | D1: מספר הנכס האחר | E1: מאפיין עיקרי | F1: ישראל/חו"ל | G1: מדינה לפי חשיפה כלכלית | H1: בעל עניין/צד קשור | I1: תאריך עסקה | J1: מטבע פעילות | K1: תאריך שערוך אחרון | L1: שווי מטבעי | M1: שער חליפין | N1: שווי הוגן (באלפי ש"ח) | O1: עלות מופחתת (באלפי ש"ח) | P1: השיטה שיושמה בדוח הכספי | Q1: שיעור מנכסי אפיק ההשקעה | R1: שיעור מסך נכסי ההשקעה
A2: 891 | B2: 9957 | C2: זכאים | D2: 28080000 | E2: חייבים וזכאים | F2: ישראל | G2: ישראל | H2: לא | I2: NA | J2: ILS | K2: 30/06/2025 | L2: -200.372 | M2: 1 | N2: -109.87195 | P2: שווי הוגן | Q2: 1.3337946 | R2: -0.0013007419
A3: 891 | B3: 9957 | C3: חייבים | D3: 27960000 | E3: חייבים וזכאים | F3: ישראל | G3: ישראל | H3: לא | I3: NA | J3: ILS | K3: 30/06/2025 | L3: 94.168 | M3: 1 | N3: 3.67 | P3: שווי הוגן | Q3: -0.62683729 | R3: 0.00061130363
A4: 891 | B4: 9957 | C4: זכאים מס עמיתים | D4: 28200000 | E4: חייבים וזכאים מס | F4: ישראל | G4: ישראל | H4: לא | I4: NA | J4: ILS | K4: 30/06/2025 | L4: -44.023 | M4: 1 | N4: -44.023 | P4: שווי הוגן | Q4: 0.29304265 | R4: -0.00028578076

Sheet מסגרות אשראי
A1: מספר קופה/קרן/ח.פ. עבור חברת ביטוח | B1: מספר מסלול | C1: מספר מזהה לווה | D1: סוג מספר מזהה לווה | E1: שם הלוואה | F1: מספר הלוואה | G1: תאריך העמדת מסגרת אשראי | H1: ישראל/חו"ל | I1: מדינה לפי חשיפה כלכלית | J1: בעל עניין/צד קשור | K1: דירוג | L1: שם מדרג | M1: דירוג הלוואה/המנפיק | N1: מטבע פעילות | O1: שער חליפין | P1: שיעור ריבית | Q1: סוג הריבית | R1: סכום מסגרת האשראי הראשוני (במטבע הפעילות) | S1: סכום מסגרת האשראי הראשוני (באלפי ש"ח) | T1: שיעור יתרת מסגרת אשראי
A2: 891 | B2: 9957

Sheet יתרות התחייבות להשקעה
A1: מספר קופה/קרן/ח.פ. עבור חברת ביטוח | B1: מספר מסלול | C1: מאפיין עיקרי | D1: שם שותף כללי קרן השקעות | E1: מספר מזהה שותף כללי קרן השקעות | F1: סוג מספר מזהה שותף כללי קרן השקעות | G1: שם קרן השקעה | H1: מספר מזהה קרן השקעה | I1: סוג מספר מזהה קרן השקעות | J1: מטבע פעילות | K1: תאריך העמדת התחייבות לקרן השקעה | L1: סכום המחויבות הראשוני (במטבע הדיווח של קרן ההשקעה) | M1: סכום המחויבות הראשוני (באלפי ש"ח) | N1: יתרת המחויבות לתקופת הדיווח (במטבע הדיווח של קרן ההשקעה) | O1: יתרת המחויבות לתקופת הדיווח (באלפי ש"ח) | P1: שיעור יתרת המחויבות | Q1: תאריך פקיעת מחויבות להשקעה
A2: 891 | B2: 9957 | C2: קרן השקעה אחרת | D2: Qumra Opportunity Fund GP, L.P. | E2: 111401 | F2: מספר תאגיד או שותפות בחו"ל | G2: Qumra Opportunity | H2: 62018254 | I2: פנימי | J2: USD | K2: 44327 | L2: 65000 | M2: 219.18 | N2: 9749 | O2: 32.873628 | P2: 0.14998462 | Q2: 45775
A3: 891 | B3: 9957 | C3: קרן השקעה אחרת | D3: PEREGRINE VENTURES GROWTH GENERAL PARTNER, LIMITED PARTNERSHIP | E3: 540297413 | F3: מספר שותפות | G3: Peregrin Growth | H3: 62018569 | I3: פנימי | J3: USD | K3: 44384 | L3: 90000 | M3: 303.48 | N3: 22876 | O3: 77.137872 | P3: 0.25417778 | Q3: 46022
A4: 891 | B4: 9957 | C4: קרן השקעה אחרת | D4: Hanaco II GP, L.P. | E4: 104909 | F4: מספר תאגיד או שותפות בחו"ל | G4: Hanaco II L.P | H4: 62018734 | I4: פנימי | J4: USD | K4: 44403 | L4: 100000 | M4: 337.2 | N4: 20000 | O4: 67.44 | P4: 0.2 | Q4: 46948
A5: 891 | B5: 9957 | C5: קרן השקעה אחרת | D5: Pagay Opportunity Manager Ltd. | E5: 324885 | F5: מספר תאגיד או שותפות בחו"ל | G5: PAGAYA OPPORTUNITY | H5: 62018866 | I5: פנימי | J5: USD | K5: 44406 | L5: 180000 | M5: 606.96 | N5: 40039.85 | O5: 135.01437 | P5: 0.22244361 | Q5: 46022
A6: 891 | B6: 9957 | C6: קרן השקעה אחרת | D6: Vertex Venturs Partners LTD | E6: 107746 | F6: מספר תאגיד או שותפות בחו"ל | G6: Vertex Israel Opportunity II Fund | H6: 62018965 | I6: פנימי | J6: USD | K6: 44431 | L6: 120000 | M6: 404.64 | N6: 18000 | O6: 60.696 | P6: 0.15 | Q6: 46023
A7: 891 | B7: 9957 | C7: פרייבט אקוויטי | D7: LLCP LMM III GP L.P | E7: 4352472 | F7: מספר תאגיד או שותפות בחו"ל | G7: LLCP Lower Middle Market (LLM) III | H7: 62019021 | I7: פנימי | J7: USD | K7: 44431 | L7: 275000 | M7: 927.3 | N7: 91558.61 | O7: 308.73563 | P7: 0.3329404 | Q7: 46727
A8: 891 | B8: 9957 | C8: קרן חוב | D8: Avenue Global Dislocation Opportunities GenPar, LLC, | E8: 362595 | F8: מספר תאגיד או שותפות בחו"ל | G8: Avenue B-1 | H8: 62019567 | I8: פנימי | J8: USD | K8: 44481 | L8: 67500 | M8: 227.61 | N8: 6244 | O8: 21.054768 | P8: 0.092503704 | Q8: 46022
A9: 891 | B9: 9957 | C9: קרן חוב | D9: Avenue Global Dislocation Opportunities GenPar, LLC, | E9: 362595 | F9: מספר תאגיד או שותפות בחו"ל | G9: Avenue B-2 | H9: 62019575 | I9: פנימי | J9: USD | K9: 44481 | L9: 67500 | M9: 227.61 | N9: 6244 | O9: 21.054768 | P9: 0.092503704 | Q9: 46022
A10: 891 | B10: 9957 | C10: פרייבט אקוויטי | D10: OEP VIII General Partner L.P | E10: 310223474 | F10: מספר תאגיד או שותפות בחו"ל | G10: One Equity Partners VIII, L.P. | H10: 62019740 | I10: פנימי | J10: USD | K10: 44518 | L10: 185000 | M10: 623.82 | N10: 8178 | O10: 27.576216 | P10: 0.044205405 | Q10: 49041
A11: 891 | B11: 9957 | C11: קרן השקעה אחרת | D11: ARKIN BIO CAPITAL, LIMITED PARTNERSHIP | E11: 540303633 | F11: מספר שותפות | G11: Arkin Bio Capital | H11: 62020128 | I11: פנימי | J11: USD | K11: 44581 | L11: 100000 | M11: 337.2 | N11: 65005 | O11: 219.19686 | P11: 0.65005 | Q11: 45572
A12: 891 | B12: 9957 | C12: קרן השקעה אחרת | D12: Viola Opportunity GP I, L.P., | E12: 382566 | F12: מספר תאגיד או שותפות בחו"ל | G12: VIOLA OPPORTUNITY I | H12: 62020284 | I12: פנימי | J12: USD | K12: 44620 | L12: 200000 | M12: 674.4 | N12: 103500 | O12: 349.002 | P12: 0.5175 | Q12: 46739
A13: 891 | B13: 9957 | C13: קרן נדל"ן | D13: Electra America Hospitality AKA LLC | E13: 86-3690594 | F13: מספר תאגיד או שותפות בחו"ל | G13: Electra America Principal Hospitality | H13: 62020359 | I13: פנימי | J13: USD | K13: 44635 | L13: 600000 | M13: 2023.2 | N13: 220457 | O13: 743.381 | P13: 0.36742833 | Q13: 47208
A14: 891 | B14: 9957 | C14: קרן חוב | D14: VIOLA CREDIT GL II, LIMITED PARTNERSHIP | E14: 540327830 | F14: מספר שותפות | G14: Viola Credit GL II, Limited Partnership | H14: 62020938 | I14: פנימי | J14: USD | K14: 44858 | L14: 78958 | M14: 266.24638 | N14: 41240 | O14: 139.06128 | P14: 0.522303 | Q14: 47026
A15: 891 | B15: 9957 | C15: קרן חוב | D15: Madison Realty Capital Debt Fund VI GP LLC | E15: 6589505 | F15: מספר תאגיד או שותפות בחו"ל | G15: Madison Realty Capital Debt Fund VI LP | H15: 62021001 | I15: פנימי | J15: USD | K15: 44887 | L15: 150000 | M15: 505.8 | N15: 59421.45 | O15: 200.36913 | P15: 0.396143 | Q15: 46608
A16: 891 | B16: 9957 | C16: קרן חוב | D16: HGI Multifamily Credit Fund GP LLC | E16: 6196719 | F16: מספר תאגיד או שותפות בחו"ל | G16: HGI Multifamily Credit Fund, LP | H16: 62021076 | I16: פנימי | J16: USD | K16: 44938 | L16: 165000 | M16: 556.38 | N16: 14850 | O16: 50.0742 | P16: 0.09 | Q16: 46203
A17: 891 | B17: 9957 | C17: קרן נדל"ן | D17: Alto Fund III GP, LLC | E17: 81-4386819 | F17: מספר תאגיד או שותפות בחו"ל | G17: ALTO III | H17: 62000073 | I17: פנימי | J17: USD | K17: 42758 | L17: 200100 | M17: 674.7372 | N17: 10100 | O17: 34.0572 | P17: 0.050474763 | Q17: 46022
A18: 891 | B18: 9957 | C18: קרן השקעה אחרת | D18: HarbourVest GP LLC | E18: 801-53287 | F18: מספר תאגיד או שותפות בחו"ל | G18: HARBOURVEST ACCESS DOVER X | H18: 62015433 | I18: פנימי | J18: USD | K18: 43865 | L18: 240000 | M18: 809.28 | N18: 48000 | O18: 161.856 | P18: 0.2 | Q18: 46422
A19: 891 | B19: 9957 | C19: קרן השקעה אחרת | D19: Vestar Capital Partners GP | E19: 549300WW8RO3OMLV4Z13 | F19: מספר תאגיד או שותפות בחו"ל | G19: VESTAR VII A | H19: 62018098 | I19: פנימי | J19: USD | K19: 44286 | L19: 125000 | M19: 421.5 | N19: 54284.261 | O19: 183.04653 | P19: 0.43427409 | Q19: 46843
A20: 891 | B20: 9957 | C20: קרן השקעה אחרת | D20: Bain Capital Distressed and Special Situations 2019 Investors, LLC | E20: 98-1467575 | F20: מספר תאגיד או שותפות בחו"ל | G20: BAIN CAPITAL DSS | H20: 62017934 | I20: פנימי | J20: USD | K20: 44262 | L20: 150000 | M20: 505.8 | N20: 29959.79 | O20: 101.02441 | P20: 0.19973193 | Q20: 46819
A21: 891 | B21: 9957 | C21: קרן גידור (Hedge Fund) | D21: AMI GP L.P. Inc | E21: 2030 | F21: מספר תאגיד או שותפות בחו"ל | G21: AMI OPPORTUNIT | H21: 60397874 | I21: פנימי | J21: USD | K21: 42354 | L21: 120000 | M21: 404.64 | N21: 59381.376 | O21: 200.234 | P21: 0.4948448 | Q21: 46007
A22: 891 | B22: 9957 | C22: קרן השקעה אחרת | D22: STATE OF MIND VENTURES GP LIMITED PARTNERSHIP | E22: 550256168 | F22: מספר שותפות | G22: SOMV FUND | H22: 60407392 | I22: פנימי | J22: USD | K22: 42516 | L22: 75000 | M22: 252.9 | N22: 562 | O22: 1.895064 | P22: 0.0074933333 | Q22: 46022
A23: 891 | B23: 9957 | C23: קרן השקעה אחרת | D23: ISFM GPLP LTD | E23: 515333862 | F23: ח.פ. | G23: ISF II | H23: 62000395 | I23: פנימי | J23: USD | K23: 42762 | L23: 160000 | M23: 539.52 | N23: 8800 | O23: 29.6736 | P23: 0.055 | Q23: 46006
A24: 891 | B24: 9957 | C24: קרן השקעה אחרת | D24: Gatewood Capital GP LLC | E24: 47-4190465 | F24: מספר תאגיד או שותפות בחו"ל | G24: [GATEWOOD FUND (IBI) | H24: 62000698 | I24: פנימי | J24: USD | K24: 42793 | L24: 170000 | M24: 573.24 | N24: 44276.34 | O24: 149.29982 | P24: 0.26044906 | Q24: 46424
A25: 891 | B25: 9957 | C25: קרן השקעה אחרת | D25: MACQUARIE INFRASTRUCTURE PARTNERS GP LLC | E25: 11744 | F25: מספר תאגיד או שותפות בחו"ל | G25: MACQUARIE | H25: 62010970 | I25: פנימי | J25: USD | K25: 43507 | L25: 190000 | M25: 640.68 | N25: 10883.61 | O25: 36.699533 | P25: 0.057282158 | Q25: 47119
A26: 891 | B26: 9957 | C26: פרייבט אקוויטי | D26: PGSF VI GP S.à r.l | E26: B 219908 | F26: מספר תאגיד או שותפות בחו"ל | G26: פנתאון PGSF VI | H26: 62014261 | I26: פנימי | J26: USD | K26: 43762 | L26: 300000 | M26: 1011.6 | N26: 87679 | O26: 295.65359 | P26: 0.29226333 | Q26: 47392
A27: 891 | B27: 9957 | C27: קרן השקעה אחרת | D27: HarbouVest Partners, LLC | E27: 801-53287 | F27: מספר תאגיד או שותפות בחו"ל | G27: HARBOURVEST ACCESS CO INVEST V | H27: 62014352 | I27: פנימי | J27: USD | K27: 43765 | L27: 160000 | M27: 539.52 | N27: 36000 | O27: 121.392 | P27: 0.225 | Q27: 47392
A28: 891 | B28: 9957 | C28: פרייבט אקוויטי | D28: PGCO IV GP S.à r.l. | E28: B B222234 | F28: מספר תאגיד או שותפות בחו"ל | G28: PGCO IV I פנתאון | H28: 62014592 | I28: פנימי | J28: USD | K28: 43787 | L28: 120000 | M28: 404.64 | N28: 10411 | O28: 35.105892 | P28: 0.086758333 | Q28: 46997
A29: 891 | B29: 9957 | C29: קרן השקעה אחרת | D29: ISRAEL INFRASTRUCTURE G.P. 4, LIMITED PARTNERSHIP | E29: 540294501 | F29: מספר שותפות | G29: תשתיות ישראל 4 | H29: 62017520 | I29: פנימי | J29: USD | K29: 44117 | L29: 170000 | M29: 573.24 | N29: 23800 | O29: 80.2536 | P29: 0.14 | Q29: 46996
A30: 891 | B30: 9957 | C30: קרן אנרגיה ותשתיות | D30: Pantheon PGIF IV GP (LUX) S.à r.l | E30: B 283012 | F30: מספר תאגיד או שותפות בחו"ל | G30: Pantheon Global Infrastructure Fund IV (Luxembourg | H30: 62021282 | I30: פנימי | J30: USD | K30: 45132 | L30: 100000 | M30: 337.2 | N30: 30452 | O30: 102.68414 | P30: 0.30452 | Q30: 46310
A31: 891 | B31: 9957 | C31: קרן נדל"ן | D31: Oak Street Real Estate Capital Fund VI, LP | E31: 6858778 | F31: מספר תאגיד או שותפות בחו"ל | G31: Oak Street Real Estate Capital Fund VI, LP | H31: 62021175 | I31: פנימי | J31: USD | K31: 45057 | L31: 100000 | M31: 337.2 | N31: 59047.21 | O31: 199.10719 | P31: 0.5904721 | Q31: 45747
A32: 891 | B32: 9957 | C32: קרן נדל"ן | D32: Starlight Bond FP I GP LIMITED | E32: RN157039 | F32: מספר תאגיד או שותפות בחו"ל | G32: Starlight Bond FP I LP | H32: 620211181 | I32: פנימי | J32: GBP | K32: 44950 | L32: 100000 | M32: 462.36 | N32: 80346.82 | O32: 371.49156 | P32: 0.8034682 | Q32: 45939
A33: 891 | B33: 9957 | C33: קרן נדל"ן | D33: FORMA FUND GENERAL PARTNER LTD | E33: 515527968 | F33: ח.פ. | G33: FORMA FUND | H33: 62017942 | I33: פנימי | J33: EUR | K33: 44262 | L33: 170000 | M33: 672.384 | N33: 1049 | O33: 4.1490048 | P33: 0.0061705882 | Q33: 45814
A34: 891 | B34: 9957 | C34: קרן נדל"ן | D34: FORMA EUROPEAN FUND II GENERAL PARTNER LTD | E34: 516190006 | F34: ח.פ. | G34: Forma European Fund II LP Forma European Fund II | H34: 62018528 | I34: פנימי | J34: EUR | K34: 44382 | L34: 125000 | M34: 494.4 | N34: 20517 | O34: 81.148838 | P34: 0.164136 | Q34: 46939
A35: 891 | B35: 9957 | C35: קרן אנרגיה ותשתיות | D35: EQT Infrastructure V (General Partner) S.à r.l. | E35: B243962 | F35: מספר תאגיד או שותפות בחו"ל | G35: Fund EQT Infrastructure V | H35: 62018891 | I35: פנימי | J35: EUR | K35: 44417 | L35: 170000 | M35: 672.384 | N35: 15898.24 | O35: 62.880719 | P35: 0.093519059 | Q35: 46688
A36: 891 | B36: 9957 | C36: קרן השקעה אחרת | D36: Target Global Growth II GP S.à r.l. | E36: B241115 | F36: מספר תאגיד או שותפות בחו"ל | G36: Target Global Growth Fund II | H36: 62019716 | I36: פנימי | J36: EUR | K36: 44508 | L36: 100000 | M36: 395.52 | N36: 12000 | O36: 47.4624 | P36: 0.12 | Q36: 47066
A37: 891 | B37: 9957 | C37: קרן נדל"ן | D37: יסודות מעטפת פיננסית ג'יפי שותפות מוגבלת | E37: 550257125 | F37: מספר שותפות | G37: יסודות נדל"ן ג' פיתוח ושותפות I | H37: 50006691 | I37: פנימי | J37: ILS | K37: 43801 | L37: 700000 | M37: 700 | N37: 207597 | O37: 207.597 | P37: 0.29656714 | Q37: 46721
A38: 891 | B38: 9957 | C38: קרן השקעה אחרת | D38: Kedma Capital III G.P.L.P Limited Partnership | E38: 540285145 | F38: מספר תאגיד או שותפות בחו"ל | G38: KEDMA CAPITAL PARTNERS III LTD | H38: 62018080 | I38: פנימי | J38: USD | K38: 43572 | L38: 125000 | M38: 421.5 | N38: 38421 | O38: 129.55561 | P38: 0.307368 | Q38: 46112
A39: 891 | B39: 9957 | C39: קרן השקעה אחרת | D39: COGITO CAPITAL FUND II GENERAL PARTNER LTD | E39: 516445962 | F39: ח.פ. | G39: קוגיטו קפיטל 2 | H39: 62020158 | I39: פנימי | J39: ILS | K39: 44598 | L39: 715584 | M39: 715.584 | N39: 257654 | O39: 257.654 | P39: 0.36006115 | Q39: 46284
A40: 891 | B40: 9957 | C40: קרן השקעה אחרת | D40: Klirmark Opportunity Fund | E40: CO – 121764 | F40: מספר תאגיד או שותפות בחו"ל | G40: Klirmark Opportunity Fund IV, L.P | H40: 50007947 | I40: פנימי | J40: ILS | K40: 45039 | L40: 1000000 | M40: 1000 | N40: 630000 | O40: 630 | P40: 0.63 | Q40: 47923
A41: 891 | B41: 9957 | C41: קרן אנרגיה ותשתיות | D41: Ares CIP Mangement II,L.P. | E41: 1987624 | F41: מספר תאגיד או שותפות בחו"ל | G41: Ares Climate Infrastructure Partners II-A, L.P | H41: 62022132 | I41: פנימי | J41: USD | K41: 45107 | L41: 125000 | M41: 421.5 | N41: 70363.13 | O41: 237.26447 | P41: 0.56290504 | Q41: 47299
A42: 891 | B42: 9957 | C42: קרן נדל"ן | D42: ARGIS Asset Management GP, LLC | E42: 37-2131827 | F42: מספר תאגיד או שותפות בחו"ל | G42: ARGIS LIVING FUND II | H42: 62022363 | I42: פנימי | J42: EUR | K42: 45777 | L42: 75000 | M42: 296.64 | N42: 45562.23 | O42: 180.20773 | P42: 0.6074964 | Q42: 48699

Sheet אפשרויות בחירה
A1: שם גיליון (רלוונטי לגיליונות עם עמודה "מאפיין עיקרי") | B1: שם עמודה | C1: אפשרות בחירה | D1: הערות והסברים
B2: ישראל/חו"ל | C2: ישראל
C3: חו"ל
B4: מדינה לפי חשיפה כלכלית; מדינת התאגדות קרן השקעה, מיקום משרד השותף הכללי, מדינת מיקום נדל"ן | C4: ישראל
C5: אוסטריה
C6: אוסטרליה
C7: אזור תעלת פנמה
C8: אזרביג'אן
C9: איחוד האמירויות הערביות
C10: איטליה
C11: איי הבתולה הבריטיים | E11: נוסף במסגרת עדכון הרשימה
C12: איי הבתולה של ארצות הברית | E12: נוסף במסגרת עדכון הרשימה
C13: איי סיישל
C14: איי קיימן
C15: איי שלמה הבריטיים
C16: איסלנד
C17: אירלנד
C18: אנדורה
C19: אסטוניה
C20: ארגנטינה
C21: ארה"ב
C22: אתיופיה
C23: בהמס
C24: בולגריה
... C35: גרמניה
C36: ג'רזי (Jersey) | E36: נוסף במסגרת עדכון הרשימה
C37: גרנזי (Guernsey) | E37: נוסף במסגרת עדכון הרשימה
C38: דנמרק
C39: דרום אפריקה
C40: דרום קוריאה | E40: נוסף במסגרת עדכון הרשימה
C41: הודו
C42: הולנד
C43: הונג קונג
C44: הונגריה
C45: הונדורס
C46: טייוואן | E46: נוסף במסגרת עדכון הרשימה
C47: יוון
C48: יפן
C49: ירדן
C50: לוכסמבורג
C51: לטביה
C52: ליטא
C53: ליכטנשטיין
C54: מאוריציוס
C55: מולדובה
C56: מונקו
C57: מלדיבים
C58: מלטה
... C62: מרוקו
C63: נורבגיה | E63: נוסף במסגרת עדכון הרשימה
C64: ניו זילנד
C65: סין
C66: סינגפור
C67: סלובניה
C68: סלובקיה
C69: ספרד
C70: סרביה
C71: ערב הסעודית
C72: פולין
C73: פורטוגל
C74: פינלנד
C75: פנמה
... C93: גלובלי
C94: Emerging Markets - Americas | D94: שווקים מתעוררים לפי הגדרת MSCI | E94: נוסף במסגרת עדכון הרשימה
C95: Emerging Markets - Euope, Middle East & Africa | D95: לפי הגדרת MSCI | E95: נוסף במסגרת עדכון הרשימה
C96: Emerging Markets - Asia | D96: לפי הגדרת MSCI | E96: נוסף במסגרת עדכון הרשימה
C97: Developed Markets - Americas | D97: לפי הגדרת MSCI | E97: נוסף במסגרת עדכון הרשימה
C98: Developed Markets - Europe | D98: לפי הגדרת MSCI | E98: נוסף במסגרת עדכון הרשימה
C99: Developed Markets - Pacific | D99: לפי הגדרת MSCI | E99: נוסף במסגרת עדכון הרשימה
C100: Frontier Markets - Euope | D100: לפי הגדרת MSCI | E100: נוסף במסגרת עדכון הרשימה
C101: Frontier Markets - Africa | D101: לפי הגדרת MSCI | E101: נוסף במסגרת עדכון הרשימה
C102: Frontier Markets - Middle East | D102: לפי הגדרת MSCI | E102: נוסף במסגרת עדכון הרשימה
C103: Frontier Markets - Asia | D103: לפי הגדרת MSCI | E103: נוסף במסגרת עדכון הרשימה
B104: סוג מספר מזהה מנפיק | C104: ח.פ.
C105: מספר מנפיק
C106: מספר שותפות
C107: מספר תאגיד או שותפות בחו"ל
C108: פנימי
C109: LEI
C110: אחר
B111: סוג מספר מזהה בנק | C111: ח.פ.
C112: סימול בנק
C113: SWIFT
B114: סוג מספר מזהה מנהל קרן השקעות | C114: ח.פ.
C115: מספר שותפות
C116: מספר תאגיד או שותפות בחו"ל
C117: LEI
B118: סוג מספר מזהה לווה | C118: ח.פ.
C119: מרשם
C120: מספר תאגיד או שותפות בחו"ל
C121: פנימי
C122: מספר שותפות
C123: ת"ז
C124: דרכון
C125: LEI
C126: אחר
B127: סוג מספר נייר ערך | C127: ISIN
C128: OCC
C129: FIGI
C130: טיקר
...

Sheet מיפוי סעיפים
A1: שם גיליון | B1: שם סעיף | C1: מספר סעיף | D1: מידע שניתן לדווח רק לרשות
A2: מזומנים ושווי מזומנים | B2: מספר קופה/קרן/ח.פ. עבור חברת ביטוח | C2: 5.1
A3: מזומנים ושווי מזומנים | B3: מספר מסלול | C3: 5.2
A4: מזומנים ושווי מזומנים | B4: שם הבנק | C4: 5.4
A5: מזומנים ושווי מזומנים | B5: מספר מזהה בנק | C5: 5.7
A6: מזומנים ושווי מזומנים | B6: סוג מספר מזהה בנק | C6: 5.11
A7: מזומנים ושווי מזומנים | B7: מאפיין עיקרי | C7: 5.26
A8: מזומנים ושווי מזומנים | B8: ישראל/חו"ל | C8: 5.27
A9: מזומנים ושווי מזומנים | B9: בעל עניין/צד קשור | C9: 5.36
A10: מזומנים ושווי מזומנים | B10: דירוג הבנק | C10: 5.5
A11: מזומנים ושווי מזומנים | B11: שם מדרג | C11: 5.51
A12: מזומנים ושווי מזומנים | B12: מטבע פעילות | C12: 5.53
A13: מזומנים ושווי מזומנים | B13: שווי מטבעי | C13: 5.59
A14: מזומנים ושווי מזומנים | B14: שער חליפין | C14: 5.54
A15: מזומנים ושווי מזומנים | B15: שיעור ריבית | C15: 5.7 | D15: ü
A16: מזומנים ושווי מזומנים | B16: שווי הוגן (באלפי ש"ח) | C16: 5.63
A17: מזומנים ושווי מזומנים | B17: שיעור מנכסי אפיק ההשקעה | C17: 5.47
A18: מזומנים ושווי מזומנים | B18: שיעור מסך נכסי ההשקעה | C18: 5.48
A19: מזומנים ושווי מזומנים
A20: איגרות חוב ממשלתיות | B20: מספר קופה/קרן/ח.פ. עבור חברת ביטוח | C20: 5.1
A21: איגרות חוב ממשלתיות | B21: מספר מסלול | C21: 5.2
A22: איגרות חוב ממשלתיות | B22: שם מנפיק | C22: 5.3
A23: איגרות חוב ממשלתיות | B23: שם נייר ערך | C23: 5.14
A24: איגרות חוב ממשלתיות | B24: מספר נייר ערך | C24: 5.19
A25: איגרות חוב ממשלתיות | B25: מאפיין עיקרי | C25: 5.26
A26: איגרות חוב ממשלתיות | B26: ישראל/חו"ל | C26: 5.27
A27: איגרות חוב ממשלתיות | B27: מדינה לפי חשיפה כלכלית | C27: 5.28
A28: איגרות חוב ממשלתיות | B28: זירת מסחר | C28: 5.3
A29: איגרות חוב ממשלתיות | B29: דירוג | C29: 5.49
A30: איגרות חוב ממשלתיות | B30: שם מדרג | C30: 5.51
A31: איגרות חוב ממשלתיות | B31: מטבע פעילות | C31: 5.53
... A45: איגרות חוב ממשלתיות | B45: שיעור מסך נכסי ההשקעה | C45: 5.48
A46: איגרות חוב ממשלתיות
A47: ניירות ערך מסחריים | B47: מספר קופה/קרן/ח.פ. עבור חברת ביטוח | C47: 5.1
A48: ניירות ערך מסחריים | B48: מספר מסלול | C48: 5.2
A49: ניירות ערך מסחריים | B49: שם מנפיק | C49: 5.3
A50: ניירות ערך מסחריים | B50: מספר מנפיק | C50: 5.6
A51: ניירות ערך מסחריים | B51: סוג מספר מזהה מנפיק | C51: 5.1
A52: ניירות ערך מסחריים | B52: שם נייר ערך | C52: 5.14
A53: ניירות ערך מסחריים | B53: מספר נייר ערך | C53: 5.19
A54: ניירות ערך מסחריים | B54: סוג מספר נייר ערך | C54: 5.24
A55: ניירות ערך מסחריים | B55: מאפיין עיקרי | C55: 5.26
A56: ניירות ערך מסחריים | B56: ישראל/חו"ל | C56: 5.27
A57: ניירות ערך מסחריים | B57: מדינה לפי חשיפה כלכלית | C57: 5.28
A58: ניירות ערך מסחריים | B58: זירת מסחר | C58: 5.3
... A70: ניירות ערך מסחריים | B70: נחיתות חוזית | C70: 5.76
A71: ניירות ערך מסחריים | B71: האם סווג כחוב בעייתי | C71: 5.89 | D71: ü
A72: ניירות ערך מסחריים | B72: ערך נקוב (יחידות) | C72: 5.58
A73: ניירות ערך מסחריים | B73: סכום לקבל (במטבע הפעילות) | C73: 5.62
A74: ניירות ערך מסחריים | B74: שער חליפין | C74: 5.54
A75: ניירות ערך מסחריים | B75: שער נייר הערך | C75: 5.55
A76: ניירות ערך מסחריים | B76: שווי הוגן (באלפי ש"ח) | C76: 5.63
A77: ניירות ערך מסחריים | B77: עלות מופחתת (באלפי ש"ח) | C77: 5.65
A78: ניירות ערך מסחריים | B78: עלות מופחתת (במטבע הפעילות) | C78: 5.66
A79: ניירות ערך מסחריים | B79: השיטה שיושמה בדוח הכספי | C79: 5.68
A80: ניירות ערך מסחריים | B80: שיעור מערך נקוב מונפק | C80: 5.45
A81: ניירות ערך מסחריים | B81: שיעור מנכסי אפיק ההשקעה | C81: 5.47
A82: ניירות ערך מסחריים | B82: שיעור מסך נכסי ההשקעה | C82: 5.48
A83: ניירות ערך מסחריים
A84: איגרות חוב | B84: מספר קופה/קרן/ח.פ. עבור חברת ביטוח | C84: 5.1
A85: איגרות חוב | B85: מספר מסלול | C85: 5.2
A86: איגרות חוב | B86: שם מנפיק | C86: 5.3
A87: איגרות חוב | B87: מספר מנפיק | C87: 5.6
A88: איגרות חוב | B88: סוג מספר מזהה מנפיק | C88: 5.1
A89: איגרות חוב | B89: שם נייר ערך | C89: 5.14
A90: איגרות חוב | B90: מספר נייר ערך | C90: 5.19
A91: איגרות חוב | B91: סוג מספר נייר ערך | C91: 5.24
A92: איגרות חוב | B92: מאפיין עיקרי | C92: 5.26
A93: איגרות חוב | B93: ישראל/חו"ל | C93: 5.27
A94: איגרות חוב | B94: מדינה לפי חשיפה כלכלית | C94: 5.28
A95: איגרות חוב | B95: סטאטוס סחירות | C95: 5.29
... A107: איגרות חוב | B107: נחיתות חוזית | C107: 5.76
A108: איגרות חוב | B108: האם סווג כחוב בעייתי | C108: 5.89 | D108: ü
A109: איגרות חוב | B109: ערך נקוב (יחידות) | C109: 5.58
A110: איגרות חוב | B110: סכום לקבל (במטבע הפעילות) | C110: 5.62
A111: איגרות חוב | B111: שער חליפין | C111: 5.54
A112: איגרות חוב | B112: שער נייר הערך | C112: 5.55
A113: איגרות חוב | B113: עלות מופחתת (באלפי ש"ח) | C113: 5.65
A114: איגרות חוב | B114: עלות מופחתת (במטבע הפעילות) | C114: 5.66
A115: איגרות חוב | B115: השיטה שיושמה בדוח הכספי | C115: 5.68
A116: איגרות חוב | B116: שיעור מערך נקוב מונפק | C116: 5.45
A117: איגרות חוב | B117: שיעור מנכסי אפיק ההשקעה | C117: 5.47
A118: איגרות חוב | B118: שיעור מסך נכסי ההשקעה | C118: 5.48
A119: איגרות חוב
A120: מניות, מב"כ ויה"ש | B120: מספר קופה/קרן/ח.פ. עבור חברת ביטוח | C120: 5.1
A121: מניות, מב"כ ויה"ש | B121: מספר מסלול | C121: 5.2
A122: מניות, מב"כ ויה"ש | B122: שם מנפיק | C122: 5.3
A123: מניות, מב"כ ויה"ש | B123: מספר מנפיק | C123: 5.6
A124: מניות, מב"כ ויה"ש | B124: סוג מספר מזהה מנפיק | C124: 5.1
A125: מניות, מב"כ ויה"ש | B125: שם נייר ערך | C125: 5.14
A126: מניות, מב"כ ויה"ש | B126: מספר נייר ערך | C126: 5.19
A127: מניות, מב"כ ויה"ש | B127: סוג מספר נייר ערך | C127: 5.24
A128: מניות, מב"כ ויה"ש | B128: מאפיין עיקרי | C128: 5.26
A129: מניות, מב"כ ויה"ש | B129: ישראל/חו"ל | C129: 5.27
A130: מניות, מב"כ ויה"ש | B130: מדינה לפי חשיפה כלכלית | C130: 5.28
A131: מניות, מב"כ ויה"ש | B131: סטאטוס סחירות | C131: 5.29
... A143: מניות, מב"כ ויה"ש | B143: שיעור מסך נכסי ההשקעה | C143: 5.48
A144: מניות, מב"כ ויה"ש
A145: קרנות סל | B145: מספר קופה/קרן/ח.פ. עבור חברת ביטוח | C145: 5.1
A146: קרנות סל | B146: מספר מסלול | C146: 5.2
...

Sheet File Name Info
A2: סוג קובץ
A3: נכסי מבוטחים - חברת ביטוח | B3: in
A4: נכסי עמיתים - קופות גמל | B4: gm
A5: נכסי עמיתים - קרנות פנסיה | B5: pn
A6: נכסי אפיק השקעה מובטח תשואה | B6: ca
A7: נכסי נוסטרו - חברת ביטוח | B7: ni
A8: נכסי נוסטרו - חברה מנהלת | B8: nf
A10: יעוד הקובץ
A11: לממונה
A12: לציבור | B12: p
A15: רבעון
A16: 01
A17: 02
A18: 03
A19: 04
A21: שנה
A22: 2022 | B22: 22
A23: 2023 | B23: 23
A24: 2024 | B24: 24
A25: 2025 | B25: 25
A26: 2026 | B26: 26
A27: 2027 | B27: 27
A28: 2028 | B28: 28
A29: 2029 | B29: 29
A30: 2030 | B30: 30
A31: 2031 | B31: 31
A34: שם גוף מוסדי | B34: ח.פ.
A35: אי. אם. איי - עזר חברה לביטוח משכנתאות בע"מ | B35: 512310509
A36: איי. די. איי. חברה לביטוח בע"מ | B36: 513910703
A37: איי.אי.ג'י חברה לביטוח בע"מ | B37: 512304882
A38: איילון חברה לביטוח בע"מ | B38: 520030677
A39: אינפיניטי השתלמות, גמל ופנסיה בע"מ | B39: 513621110
A40: אלטשולר שחם גמל ופנסיה בע"מ | B40: 513173393
A41: אנליסט קופות גמל בע"מ | B41: 511880460
A42: ארם גמולים - חברה לניהול קופות גמל בע''מ | B42: 510773922
A43: אשרא - החברה הישראלית לביטוח יצוא בע"מ | B43: 520021916
A44: ב.ס.ס.ח. - החברה הישראלית לביטוח אשראי בע"מ | B44: 520044025
A45: ביטוח חקלאי אגודה מרכזית בע"מ | B45: 570003152
A46: גילעד גימלאות לעובדים דתיים בע"מ | B46: 520023094
... A121: תגמולים של עובדים בעירית ת"א-יפו א.ש. בע"מ | B121: 570002618
