Workbook
Name Additional_Factor: 'אפשרויות בחירה'!$C$701:$C$850
Name Amoritization: 'אפשרויות בחירה'!$C$546:$C$550
Name Capsule: 'אפשרויות בחירה'!$C$926:$C$928
Name Company_Name: 'File Name Info'!$A$34:$A$130
Name Company_Name_ID: 'File Name Info'!$A$34:$B$130
Name Consortium: 'אפשרויות בחירה'!$C$514:$C$515
Name Country_list: 'אפשרויות בחירה'!$C$4:$C$85
Name Country_list_funds: 'אפשרויות בחירה'!$C$4:$C$103
Name CSA: 'אפשרויות בחירה'!$C$688:$C$689
Name Delivery: 'אפשרויות בחירה'!$C$666:$C$667
Name Dependence_Independence: 'אפשרויות בחירה'!$C$654:$C$655
Name Duration_Underlying_Interest_Rate: 'אפשרויות בחירה'!$C$680:$C$687
Name File_Type: 'File Name Info'!$A$10:$A$12
Name Full_File_Type: 'File Name Info'!$A$11:$B$13
Name Full_Type: 'File Name Info'!$A$2:$B$8
Name Full_Type_Nostro: 'File Name Info'!$A$3:$B$6
Name Full_Year: 'File Name Info'!$A$22:$B$31
Name Fund_Strategy: 'אפשרויות בחירה'!$C$597:$C$621
Name Fund_type: 'אפשרויות בחירה'!$C$328:$C$498
Name Holding_interest: 'אפשרויות בחירה'!$C$146:$C$147
Name In_the_books: 'אפשרויות בחירה'!$C$656:$C$657
Name Industry_Sector: 'אפשרויות בחירה'!$C$1129:$C$1245
Name Industry_sector_all: 'אפשרויות בחירה'!$C$202:$C$327
Name Industry_sectors: 'אפשרויות בחירה'!$C$202:$C$327
Name israel_abroad: 'אפשרויות בחירה'!$C$2:$C$3
Name Issuer_Number_Banks: 'אפשרויות בחירה'!$C$111:$C$113
Name Issuer_Number_Fund: 'אפשרויות בחירה'!$C$114:$C$117
Name issuer_number_loan: 'אפשרויות בחירה'!$C$118:$C$126
Name Issuer_Number_Type: 'אפשרויות בחירה'!$C$104:$C$110
Name Issuer_Number_Type_2: 'אפשרויות בחירה'!$C$1076:$C$1079
Name Issuer_Number_Type_3: 'אפשרויות בחירה'!$C$1081:$C$1085
Name Issuer_Number_Type_V2: 'אפשרויות בחירה'!$C$104:$C$110
Name Issuer_Type_TFunds: 'אפשרויות בחירה'!$C$1087:$C$1089
Name Leading_factor: 'אפשרויות בחירה'!$C$692:$C$700
Name Linked_Type: 'אפשרויות בחירה'!$C$516:$C$519
Name other_investments: 'אפשרויות בחירה'!$C$1000:$C$1033
Name Penalty: 'אפשרויות בחירה'!$C$851:$C$852
Name QTR: 'File Name Info'!$A$15:$A$19
Name Rating_Agency: 'אפשרויות בחירה'!$C$188:$C$201
Name real_estate_lifestage: 'אפשרויות בחירה'!$C$634:$C$642
Name real_estate_loans: 'אפשרויות בחירה'!$C$553:$C$591
Name Real_Estate_Main_Use: 'אפשרויות בחירה'!$C$622:$C$633
Name Recourse_Nonrecourse: 'אפשרויות בחירה'!$C$544:$C$545
Name Repayment_Rights: 'אפשרויות בחירה'!$C$551:$C$552
Name Reset_frequency: 'אפשרויות בחירה'!$C$658:$C$665
Name Security_ID_Number_Type: 'אפשרויות בחירה'!$C$1113:$C$1116
Name Security_Number_Loans: 'אפשרויות בחירה'!$C$131
Name Stock_Exchange: 'אפשרויות בחירה'!$C$1283:$C$1315
Name Stock_Exchange_Gov_Bonds: 'אפשרויות בחירה'!$C$148:$C$181
Name Subordination_Risk: 'אפשרויות בחירה'!$C$186:$C$187
Name Tradeable_Status: 'אפשרויות בחירה'!$C$1272:$C$1281
Name Tradeable_Status_All: 'אפשרויות בחירה'!$C$135:$C$145
Name tradeable_status_bonds: 'אפשרויות בחירה'!$C$1248:$C$1253
Name tradeable_status_funds: 'אפשרויות בחירה'!$C$1118:$C$1119
Name tradeable_status_stock: 'אפשרויות בחירה'!$C$1255:$C$1259
Name Tradeable_Status_v2: 'אפשרויות בחירה'!$C$1121:$C$1126
Name tradeable_status_warrants: 'אפשרויות בחירה'!$C$1261:$C$1265
Name tradeable_status_warrants_v2: 'אפשרויות בחירה'!$C$1267:$C$1269
Name Transaction: 'אפשרויות בחירה'!$C$643:$C$646
Name Type: 'File Name Info'!$A$2:$A$8

Sheet עמוד פתיחה
A1: קובץ דיווח עבור רשימת נכסים ברמת הנכס הבודד (חוזר גופים מוסדיים 2015-9-14)
A3: יש לבחור תחום: | D3: נכסי עמיתים - קרנות פנסיה
A5: האם מדובר בקובץ לממומנה או לציבור: | D5: לציבור
A7: יש לבחור את רבעון הדיווח: | D7: 2
A9: יש לבחור את שנת הדיווח: | D9: 2025
A11: יש לבחור את הגוף המוסדי: | D11: קופת הפנסיה לעובדי הדסה בעמ
A13: ח.פ. הגוף המוסדי: | D13: 520022963
A15: שם קובץ לשמירה | D15: 520022963_pn_p_0225.xlsx
A17: פרטי האחראי על הדיווח בגוף המוסדי | B17: שם: | D17: יגאל שלפר
B19: מספר טלפון: | D19: 054-5565745
B21: כתובת מייל: | D21: shlefer@amitim.com
A23: הוראות למילוי הדיווח: | D23: יש לדווח לפי ההנחיות בחלק ג' לנספח 5.4.3.2 שבפרק 3 שבחלק 4 לשער 5 בחוזר המאוחד - "רשימת נכסים ברמת הנכס הבודד".

Sheet סכום נכסים
C1: ידווח בקבצי נכסי הנוסטרו בלבד
B2: שווי הוגן | C2: עלות מופחתת | D2: השיטה שיושמה בדוח הכספי | E2: שיעור מסך נכסי השקעה
A3: מזומנים ושווי מזומנים | B3: =SUM('מזומנים ושווי מזומנים'!O:O) -> 87277.433 | E3: =IFERROR(B3/$B$30,0) -> 0.021204737
A4: איגרות חוב ממשלתיות | B4: =SUM('איגרות חוב ממשלתיות'!U:U) -> 508720.69 | E4: =IFERROR(B4/$B$30,0) -> 0.12359768
A5: ניירות ערך מסחריים | B5: =SUM('ניירות ערך מסחריים'!AD:AD) -> 0 | E5: =IFERROR(B5/$B$30,0) -> 0
A6: איגרות חוב | B6: =SUM('איגרות חוב'!AD:AD) -> 106156.44 | E6: =IFERROR(B6/$B$30,0) -> 0.02579154
A7: מניות, מניות בכורה ויחידות השתתפות | B7: =SUM('מניות מבכ ויהש'!U:U) -> 86195.319 | E7: =IFERROR(B7/$B$30,0) -> 0.020941829
A8: קרנות סל | B8: =SUM('קרנות סל'!T:T) -> 313738.07 | E8: =IFERROR(B8/$B$30,0) -> 0.076225126
A9: קרנות נאמנות | B9: =SUM('קרנות נאמנות'!T:T) -> 29971.416 | E9: =IFERROR(B9/$B$30,0) -> 0.0072817907
A10: כתבי אופציה | B10: =SUM('כתבי אופציה'!W:W) -> 23.9499 | E10: =IFERROR(B10/$B$30,0) -> 5.8188161e-06
A11: אופציות | B11: =SUM(אופציות!V:V) -> 0 | E11: =IFERROR(B11/$B$30,0) -> 0
A12: חוזים עתידיים | B12: =SUM('חוזים עתידיים'!R:R) -> 0 | E12: =IFERROR(B12/$B$30,0) -> 0
A13: מוצרים מובנים | B13: =SUM('מוצרים מובנים'!Z:Z) -> 0 | E13: =IFERROR(B13/$B$30,0) -> 0
A14: לא סחיר איגרות חוב ממשלתיות | B14: =SUM('לא סחיר איגרות חוב ממשלתיות'!U:U) -> 0 | E14: =IFERROR(B14/$B$30,0) -> 0
A15: לא סחיר איגרות חוב מיועדות | B15: =SUM('לא סחיר איגרות חוב מיועדות'!N:N) -> 815615.47 | E15: =IFERROR(B15/$B$30,0) -> 0.19816018
A16: אפיק השקעה מובטח תשואה | B16: =SUM('אפיק השקעה מובטח תשואה'!F:F) -> 0 | E16: =IFERROR(B16/$B$30,0) -> 0
A17: לא סחיר ניירות ערך מסחריים | B17: =SUM('לא סחיר ניירות ערך מסחריים'!AI:AI) -> 0 | E17: =IFERROR(B17/$B$30,0) -> 0
A18: לא סחיר איגרות חוב | B18: =SUM('לא סחיר איגרות חוב'!AG:AG) -> 14159.775 | E18: =IFERROR(B18/$B$30,0) -> 0.0034402284
A19: לא סחיר מניות, מניות בכורה ויחידות השתתפות | B19: =SUM('לא סחיר מניות מבכ ויהש'!X:X) -> 0 | E19: =IFERROR(B19/$B$30,0) -> 0
A20: קרנות השקעה | B20: =SUM('קרנות השקעה'!W:W) -> 2505.418 | E20: =IFERROR(B20/$B$30,0) -> 0.00060871095
A21: לא סחיר כתבי אופציה | B21: =SUM('לא סחיר כתבי אופציה'!Z:Z) -> 0 | E21: =IFERROR(B21/$B$30,0) -> 0
A22: לא סחיר אופציות | B22: =SUM('לא סחיר אופציות'!Z:Z) -> 0 | E22: =IFERROR(B22/$B$30,0) -> 0
A23: לא סחיר נגזרים אחרים | B23: =SUM('לא סחיר נגזרים אחרים'!R:R) -> 3782.4278 | E23: =IFERROR(B23/$B$30,0) -> 0.00091897051
A24: הלוואות | B24: =SUM(הלוואות!AT:AT) -> 18338.508 | E24: =IFERROR(B24/$B$30,0) -> 0.0044554844
A25: לא סחיר מוצרים מובנים | B25: =SUM('לא סחיר מוצרים מובנים'!AB:AB) -> 0 | E25: =IFERROR(B25/$B$30,0) -> 0
A26: פיקדונות מעל 3 חודשים | B26: =SUM('פיקדונות מעל 3 חודשים'!T:T) -> 27874.718 | E26: =IFERROR(B26/$B$30,0) -> 0.0067723815
A27: זכויות מקרקעין | B27: =SUM('זכויות מקרקעין'!S:S) -> 0 | E27: =IFERROR(B27/$B$30,0) -> 0
A28: השקעה בחברות מוחזקות | B28: =SUM('השקעה בחברות מוחזקות'!U:U) -> 0 | E28: =IFERROR(B28/$B$30,0) -> 0
A29: נכסים אחרים | B29: =SUM('נכסים אחרים'!N:N) -> 2101580.7 | E29: =IFERROR(B29/$B$30,0) -> 0.51059552
A30: סך הכל נכסים | B30: =SUM(B3:B29) -> 4115940.3 | E30: =SUM(E3:E29) -> 1
A31: מסגרות אשראי | B31: 65.318
A32: יתרות התחייבויות להשקעה

Sheet מזומנים ושווי מזומנים
A1: מספר קופה/קרן/ח.פ. עבור חברת ביטוח | B1: מספר מסלול | C1: שם הבנק | D1: מספר מזהה בנק | E1: סוג מספר מזהה בנק | F1: מאפיין עיקרי | G1: ישראל/חו"ל | H1: בעל עניין/צד קשור | I1: דירוג הבנק | J1: שם מדרג | K1: מטבע פעילות | L1: שווי מטבעי | M1: שער חליפין | N1: שיעור ריבית | O1: שווי הוגן (באלפי ש"ח) | P1: שיעור מנכסי אפיק ההשקעה | Q1: שיעור מסך נכסי ההשקעה
A2: 274 | B2: 274 | C2: בנק מזרחי | D2: 20-21 | E2: סימול בנק | F2: מזומן ועו"ש נקוב במט"ח | G2: ישראל | H2: לא | I2: ilAAA | J2: S&P מעלות | K2: USD | L2: 218.92736 | M2: 3.372 | O2: 738.22306 | P2: 0.008458 | Q2: 0.000179
A3: 274 | B3: 274 | C3: בנק הפועלים | D3: 12-600 | E3: סימול בנק | F3: מזומן ועו"ש נקוב במט"ח | G3: ישראל | H3: לא | I3: ilAAA | J3: S&P מעלות | K3: DKK | L3: 319.44623 | M3: 0.5301 | O3: 169.33845 | P3: 0.00194 | Q3: 4.1e-05
A4: 274 | B4: 274 | C4: בנק הפועלים | D4: 12-600 | E4: סימול בנק | F4: מזומן ועו"ש נקוב במט"ח | G4: ישראל | H4: לא | I4: ilAAA | J4: S&P מעלות | K4: USD | L4: 3729.4615 | M4: 3.372 | O4: 12575.744 | P4: 0.144089 | Q4: 0.003055
A5: 274 | B5: 274 | C5: בנק הפועלים | D5: 12-600 | E5: סימול בנק | F5: מזומן ועו"ש בש"ח | G5: ישראל | H5: לא | I5: ilAAA | J5: S&P מעלות | K5: ILS | L5: 27349.785 | M5: 1 | O5: 27349.785 | P5: 0.313365 | Q5: 0.006644
A6: 274 | B6: 274 | C6: יו-בנק | D6: 26-273 | E6: סימול בנק | F6: מזומן ועו"ש בש"ח | G6: ישראל | H6: לא | I6: ilAAA | J6: S&P מעלות | K6: ILS | L6: 128.85152 | M6: 1 | O6: 128.85152 | P6: 0.001476 | Q6: 3.1e-05
A7: 274 | B7: 274 | C7: בנק לאומי | D7: 10-800 | E7: סימול בנק | F7: מזומן ועו"ש נקוב במט"ח | G7: ישראל | H7: לא | I7: ilAAA | J7: S&P מעלות | K7: GBP | L7: 138.9235 | M7: 4.6236 | O7: 642.32669 | P7: 0.007359 | Q7: 0.000156
A8: 274 | B8: 274 | C8: בנק דיסקונט | D8: 11-10 | E8: סימול בנק | F8: מזומן ועו"ש נקוב במט"ח | G8: ישראל | H8: לא | I8: ilAAA | J8: S&P מעלות | K8: USD | L8: 23.56657 | M8: 3.372 | O8: 79.46647 | P8: 0.00091 | Q8: 1.9e-05
A9: 274 | B9: 274 | C9: בנק לאומי | D9: 10-800 | E9: סימול בנק | F9: מזומן ועו"ש נקוב במט"ח | G9: ישראל | H9: לא | I9: ilAAA | J9: S&P מעלות | K9: DKK | L9: 14.03109 | M9: 0.5301 | O9: 7.43788 | P9: 8.5e-05 | Q9: 1e-06
A10: 274 | B10: 274 | C10: בנק הפועלים | D10: 12-600 | E10: סימול בנק | F10: מזומן ועו"ש נקוב במט"ח | G10: ישראל | H10: לא | I10: ilAAA | J10: S&P מעלות | K10: CAD | L10: 18.88165 | M10: 2.4674 | O10: 46.58858 | P10: 0.000533 | Q10: 1.1e-05
A11: 274 | B11: 274 | C11: בנק הפועלים | D11: 12-600 | E11: סימול בנק | F11: מזומן ועו"ש נקוב במט"ח | G11: ישראל | H11: לא | I11: ilAAA | J11: S&P מעלות | K11: GBP | L11: 16.01492 | M11: 4.6236 | O11: 74.04658 | P11: 0.000848 | Q11: 1.7e-05
A12: 274 | B12: 274 | C12: יו-בנק | D12: 26-273 | E12: סימול בנק | F12: מזומן ועו"ש נקוב במט"ח | G12: ישראל | H12: לא | I12: ilAAA | J12: S&P מעלות | K12: USD | L12: 21.19476 | M12: 3.372 | O12: 71.46873 | P12: 0.000818 | Q12: 1.7e-05
A13: 274 | B13: 274 | C13: בנק מזרחי | D13: 20-21 | E13: סימול בנק | F13: פח"ק/פר"י | G13: ישראל | H13: לא | I13: ilAAA | J13: S&P מעלות | K13: ILS | L13: 8354.7344 | M13: 1 | O13: 8354.7344 | P13: 0.095726 | Q13: 0.002029
... A28: 274 | B28: 274 | C28: בנק לאומי | D28: 10-800 | E28: סימול בנק | F28: מזומן ועו"ש נקוב במט"ח | G28: ישראל | H28: לא | I28: ilAAA | J28: S&P מעלות | K28: EUR | L28: 22.92477 | M28: 3.9552 | O28: 90.67205 | P28: 0.001038 | Q28: 2.2e-05

Sheet איגרות חוב ממשלתיות
A1: מספר קופה/קרן/ח.פ. עבור חברת ביטוח | B1: מספר מסלול | C1: שם מנפיק | D1: שם נייר ערך | E1: מספר נייר ערך | F1: מאפיין עיקרי | G1: ישראל/חו"ל | H1: מדינה לפי חשיפה כלכלית | I1: זירת מסחר | J1: דירוג | K1: שם מדרג | L1: מטבע פעילות | M1: מח"מ | N1: מועד פדיון | O1: שיעור ריבית | P1: תשואה לפדיון | Q1: סכום לקבל (במטבע הפעילות) | R1: ערך נקוב (יחידות) | S1: שער חליפין | T1: שער נייר הערך | U1: שווי הוגן (באלפי ש"ח) | V1: עלות מופחתת (באלפי ש"ח) | W1: השיטה שיושמה בדוח הכספי | X1: שיעור מערך נקוב מונפק | Y1: שיעור מנכסי אפיק ההשקעה | Z1: שיעור מסך נכסי ההשקעה
A2: 274 | B2: 274 | C2: ממשלת ישראל | D2: ממשלתי שקלי 142 | E2: IL0011254005 | F2: לא צמוד למדד המחירים לצרכן ריבית קבועה | G2: ישראל | H2: ישראל | I2: TASE | J2: ilRF | K2: S&P מעלות | L2: ILS | M2: 11.43 | N2: 51897 | O2: 0.055 | P2: 0.0435 | R2: 1808829 | S2: 1 | T2: 115.63 | U2: 2091.549 | X2: 6.2e-05 | Y2: 0.004111 | Z2: 0.000508
A3: 274 | B3: 274 | C3: ממשלת ישראל | D3: ממשל צמודה 0726 | E3: IL0011695645 | F3: צמוד למדד המחירים לצרכן בריבית קבועה | G3: ישראל | H3: ישראל | I3: TASE | J3: ilRF | K3: S&P מעלות | L3: ILS | M3: 1.08 | N3: 46234 | O3: 0.001 | P3: 0.0233 | R3: 5313038 | S3: 1 | T3: 114.5 | U3: 6083.4285 | X3: 0.000262 | Y3: 0.011958 | Z3: 0.001478
A4: 274 | B4: 274 | C4: ממשלת ישראל | D4: ממשל צמודה 1033 | E4: IL0012043795 | F4: צמוד למדד המחירים לצרכן בריבית קבועה | G4: ישראל | H4: ישראל | I4: TASE | J4: ilRF | K4: S&P מעלות | L4: ILS | M4: 7.78 | N4: 48883 | O4: 0.016 | P4: 0.0197 | R4: 10973000 | S4: 1 | T4: 103.3 | U4: 11335.109 | X4: 0.000463 | Y4: 0.022281 | Z4: 0.002753
A5: 274 | B5: 274 | C5: ממשלת ישראל | D5: ממשל שקלית 0330 | E5: IL0011609851 | F5: לא צמוד למדד המחירים לצרכן ריבית קבועה | G5: ישראל | H5: ישראל | I5: TASE | J5: ilRF | K5: S&P מעלות | L5: ILS | M5: 4.64 | N5: 47573 | O5: 0.01 | P5: 0.0397 | R5: 756821 | S5: 1 | T5: 87.63 | U5: 663.20224 | X5: 2e-05 | Y5: 0.001303 | Z5: 0.000161
A6: 274 | B6: 274 | C6: ממשלת ישראל | D6: ממשלתי צמוד 0841 | E6: IL0011205833 | F6: צמוד למדד המחירים לצרכן בריבית קבועה | G6: ישראל | H6: ישראל | I6: TASE | J6: ilRF | K6: S&P מעלות | L6: ILS | M6: 13.17 | N6: 51744 | O6: 0.0275 | P6: 0.0196 | R6: 39630164 | S6: 1 | T6: 141.8 | U6: 56195.573 | X6: 0.001964 | Y6: 0.110464 | Z6: 0.013653
A7: 274 | B7: 274 | C7: ממשלת ישראל | D7: ממשלתי 0928 | E7: IL0011508798 | F7: לא צמוד למדד המחירים לצרכן ריבית קבועה | G7: ישראל | H7: ישראל | I7: TASE | J7: ilRF | K7: S&P מעלות | L7: ILS | M7: 3.11 | N7: 47024 | O7: 0.0225 | P7: 0.0395 | R7: 45103 | S7: 1 | T7: 96.6 | U7: 43.5695 | X7: 1e-06 | Y7: 8.5e-05 | Z7: 1e-05
A8: 274 | B8: 274 | C8: ממשלת ישראל | D8: ממשלתי משתנה 0526 | E8: IL0011417958 | F8: לא צמוד למדד המחירים לצרכן ריבית משתנה | G8: ישראל | H8: ישראל | I8: TASE | J8: ilRF | K8: S&P מעלות | L8: ILS | M8: 0.9 | N8: 46173 | O8: 0 | P8: 0.0432 | R8: 2118357 | S8: 1 | T8: 100.22 | U8: 2123.0174 | X8: 9.9e-05 | Y8: 0.004173 | Z8: 0.000515
A9: 274 | B9: 274 | C9: ממשלת ישראל | D9: ממשלתי שקלי 1152 | E9: IL0011840761 | F9: לא צמוד למדד המחירים לצרכן ריבית קבועה | G9: ישראל | H9: ישראל | I9: TASE | J9: ilRF | K9: S&P מעלות | L9: ILS | M9: 17.52 | N9: 55852 | O9: 0.028 | P9: 0.0459 | R9: 39981728 | S9: 1 | T9: 73.98 | U9: 29578.482 | X9: 0.001553 | Y9: 0.058142 | Z9: 0.007186
A10: 274 | B10: 274 | C10: ממשלת ישראל | D10: ממשלתי צמוד 0545 | E10: IL0011348658 | F10: צמוד למדד המחירים לצרכן בריבית קבועה | G10: ישראל | H10: ישראל | I10: TASE | J10: ilRF | K10: S&P מעלות | L10: ILS | M10: 17.94 | N10: 53113 | O10: 0.01 | P10: 0.0202 | R10: 53418839 | S10: 1 | T10: 98.54 | U10: 52638.924 | X10: 0.002339 | Y10: 0.103473 | Z10: 0.012789
A11: 274 | B11: 274 | C11: ממשלת ישראל | D11: ממשלתי 0327 | E11: IL0011393449 | F11: לא צמוד למדד המחירים לצרכן ריבית קבועה | G11: ישראל | H11: ישראל | I11: TASE | J11: ilRF | K11: S&P מעלות | L11: ILS | M11: 1.73 | N11: 46477 | O11: 0.02 | P11: 0.04 | R11: 13296396 | S11: 1 | T11: 97.19 | U11: 12922.767 | X11: 0.000471 | Y11: 0.025402 | Z11: 0.003139
A12: 274 | B12: 274 | C12: ממשלת ישראל | D12: ממשלתי צמוד 0536 | E12: IL0010977085 | F12: צמוד למדד המחירים לצרכן בריבית קבועה | G12: ישראל | H12: ישראל | I12: TASE | J12: ilRF | K12: S&P מעלות | L12: ILS | M12: 9.22 | N12: 49825 | O12: 0.04 | P12: 0.0194 | R12: 61925738 | S12: 1 | T12: 167.7 | U12: 103849.46 | X12: 0.003886 | Y12: 0.204138 | Z12: 0.025231
A13: 274 | B13: 274 | C13: ממשלת ישראל | D13: ממשלתי צמוד 1151 | E13: IL0011683013 | F13: צמוד למדד המחירים לצרכן בריבית קבועה | G13: ישראל | H13: ישראל | I13: TASE | J13: ilRF | K13: S&P מעלות | L13: ILS | M13: 24.26 | N13: 55487 | O13: 0.005 | P13: 0.021 | R13: 164086445 | S13: 1 | T13: 79.6 | U13: 130612.81 | X13: 0.005383 | Y13: 0.256747 | Z13: 0.031733
... A20: 274 | B20: 274 | C20: US Government | D20: B 0 08/21/25 (p) | E20: US912797PP64 | F20: מק"מ קצר משנים עשר חודשים | G20: חו"ל | H20: ארה"ב | I20: אחר | J20: Aa1 | K20: Moodys | L20: USD | M20: 0.14 | N20: 45890 | O20: 0 | P20: 0.0437 | R20: 52000 | S20: 3.372 | T20: 99.3927 | U20: 174.27914 | X20: 0 | Y20: 0.000342 | Z20: 4.2e-05

Sheet ניירות ערך מסחריים
A1: מספר קופה/קרן/ח.פ. עבור חברת ביטוח | B1: מספר מסלול | C1: שם מנפיק | D1: מספר מנפיק | E1: סוג מספר מזהה מנפיק | F1: שם נייר ערך | G1: מספר נייר ערך | H1: סוג מספר נייר ערך | I1: מאפיין עיקרי | J1: ישראל/חו"ל | K1: מדינה לפי חשיפה כלכלית | L1: זירת מסחר | M1: ענף מסחר | N1: בעל עניין/צד קשור | O1: דירוג | P1: שם מדרג | Q1: דירוג נייר הערך/המנפיק | R1: מטבע פעילות | S1: מח"מ | T1: ריבית עוגן | U1: מועד פדיון | V1: שיעור ריבית | W1: תשואה לפדיון | X1: נחיתות חוזית | Y1: האם סווג כחוב בעייתי | Z1: ערך נקוב (יחידות) | AA1: שער חליפין | AB1: שער נייר הערך | AC1: סכום לקבל (במטבע הפעילות) | AD1: שווי הוגן (באלפי ש"ח) | AE1: עלות מופחתת (באלפי ש"ח) | AF1: עלות מופחתת (במטבע הפעילות) | AG1: השיטה שיושמה בדוח הכספי | AH1: שיעור מערך נקוב מונפק | AI1: שיעור מנכסי אפיק ההשקעה | AJ1: שיעור מסך נכסי ההשקעה
A2: 274 | B2: 274

Sheet איגרות חוב
A1: מספר קופה/קרן/ח.פ. עבור חברת ביטוח | B1: מספר מסלול | C1: שם מנפיק | D1: מספר מנפיק | E1: סוג מספר מזהה מנפיק | F1: שם נייר ערך | G1: מספר נייר ערך | H1: סוג מספר נייר ערך | I1: מאפיין עיקרי | J1: ישראל/חו"ל | K1: מדינה לפי חשיפה כלכלית | L1: סטאטוס סחירות | M1: זירת מסחר | N1: ענף מסחר | O1: בעל עניין/צד קשור | P1: דירוג | Q1: שם מדרג | R1: דירוג נייר הערך/המנפיק | S1: מטבע פעילות | T1: מח"מ | U1: מועד פדיון | V1: שיעור ריבית | W1: תשואה לפדיון | X1: נחיתות חוזית | Y1: האם סווג כחוב בעייתי | Z1: ערך נקוב (יחידות) | AA1: שער חליפין | AB1: שער נייר הערך | AC1: סכום לקבל (במטבע הפעילות) | AD1: שווי הוגן (באלפי ש"ח) | AE1: עלות מופחתת (באלפי ש"ח) | AF1: עלות מופחתת (במטבע הפעילות) | AG1: השיטה שיושמה בדוח הכספי | AH1: שיעור מערך נקוב מונפק | AI1: שיעור מנכסי אפיק ההשקעה | AJ1: שיעור מסך נכסי ההשקעה
A2: 274 | B2: 274 | C2: מזרחי טפחות הנפקות | D2: 520032046 | E2: ח.פ. | F2: מזרחי טפחות הנפקות 49 | G2: IL0023102820 | H2: ISIN | I2: צמוד למדד המחירים לצרכן | J2: ישראל | K2: ישראל | L2: סחיר | M2: TASE | N2: בנקים | O2: לא | P2: ilAAA | Q2: S&P מעלות | R2: נייר ערך | S2: ILS | T2: 0.98 | U2: 46196 | V2: 0.0038 | W2: 0.0255 | X2: החוב לא נחות | Z2: 750000 | AA2: 1 | AB2: 112.93 | AD2: 846.975 | AH2: 0.00025 | AI2: 0.007978 | AJ2: 0.000205
A3: 274 | B3: 274 | C3: חברת החשמל לישראל בע"מ | D3: 520000472 | E3: ח.פ. | F3: חשמל 35 | G3: IL0011967994 | H3: ISIN | I3: צמוד למדד המחירים לצרכן | J3: ישראל | K3: ישראל | L3: סחיר | M3: TASE | N3: אנרגיה | O3: לא | P3: ilAAA | Q3: S&P מעלות | R3: נייר ערך | S3: ILS | T3: 10.06 | U3: 50203 | V3: 0.032 | W3: 0.0279 | X3: החוב לא נחות | Z3: 1287000 | AA3: 1 | AB3: 110.87 | AD3: 1426.8969 | AH3: 0.000261 | AI3: 0.013441 | AJ3: 0.000346
A4: 274 | B4: 274 | C4: בנק הפועלים | D4: 520000118 | E4: ח.פ. | F4: פועלים אגח 201 | G4: IL0011913451 | H4: ISIN | I4: צמוד למדד המחירים לצרכן | J4: ישראל | K4: ישראל | L4: סחיר | M4: TASE | N4: בנקים | O4: לא | P4: Aaa.il | Q4: מידרוג Moodys | R4: נייר ערך | S4: ILS | T4: 3.72 | U4: 48547 | V4: 0.0139 | W4: 0.0251 | X4: החוב לא נחות | Z4: 114400 | AA4: 1 | AB4: 105.13 | AD4: 120.26872 | AH4: 7.1e-05 | AI4: 0.001132 | AJ4: 2.9e-05
A5: 274 | B5: 274 | C5: בנק הפועלים | D5: 520000118 | E5: ח.פ. | F5: פועלים אגח 202 | G5: IL0011998502 | H5: ISIN | I5: צמוד למדד המחירים לצרכן | J5: ישראל | K5: ישראל | L5: סחיר | M5: TASE | N5: בנקים | O5: לא | P5: Aaa.il | Q5: מידרוג Moodys | R5: נייר ערך | S5: ILS | T5: 1.81 | U5: 46872 | V5: 0.006 | W5: 0.0247 | X5: החוב לא נחות | Z5: 386700 | AA5: 1 | AB5: 114.32 | AD5: 442.07544 | AH5: 0.000579 | AI5: 0.004164 | AJ5: 0.000107
A6: 274 | B6: 274 | C6: בנק הפועלים | D6: 520000118 | E6: ח.פ. | F6: פועלים התח נד ז | G6: IL0011913295 | H6: ISIN | I6: צמוד למדד המחירים לצרכן | J6: ישראל | K6: ישראל | L6: סחיר | M6: TASE | N6: בנקים | O6: לא | P6: ilAA- | Q6: S&P מעלות | R6: נייר ערך | S6: ILS | T6: 3.24 | U6: 47086 | V6: 0.0309 | W6: 0.0298 | X6: החוב לא נחות | Z6: 600000 | AA6: 1 | AB6: 110.98 | AD6: 665.88 | AH6: 0.000631 | AI6: 0.006272 | AJ6: 0.000161
A7: 274 | B7: 274 | C7: חברת החשמל לישראל בע"מ | D7: 520000472 | E7: ח.פ. | F7: חשמל אגח 33 | G7: IL0060003923 | H7: ISIN | I7: צמוד למדד המחירים לצרכן | J7: ישראל | K7: ישראל | L7: סחיר | M7: TASE | N7: אנרגיה | O7: לא | P7: ilAAA | Q7: S&P מעלות | R7: נייר ערך | S7: ILS | T7: 10.2 | U7: 49825 | V7: 0.0125 | W7: 0.0279 | X7: החוב לא נחות | Z7: 586000 | AA7: 1 | AB7: 98.88 | AD7: 579.4368 | AH7: 0.000136 | AI7: 0.005458 | AJ7: 0.00014
A8: 274 | B8: 274 | C8: קבוצת עזריאלי בע"מ | D8: 510960719 | E8: ח.פ. | F8: עזריאלי אגח ד | G8: IL0011386500 | H8: ISIN | I8: צמוד למדד המחירים לצרכן | J8: ישראל | K8: ישראל | L8: סחיר | M8: TASE | N8: נדל"ן מניב בישראל | O8: לא | P8: Aa1.il | Q8: מידרוג Moodys | R8: נייר ערך | S8: ILS | T8: 2.68 | U8: 47669 | V8: 0.0134 | W8: 0.028 | X8: החוב לא נחות | Z8: 41086.65 | AA8: 1 | AB8: 114.07 | AC8: 5.23046 | AD8: 52.098 | AH8: 1.8e-05 | AI8: 0.000489 | AJ8: 1.2e-05
A9: 274 | B9: 274 | C9: מזרחי טפחות הנפקות | D9: 520032046 | E9: ח.פ. | F9: מזרחי טפחות הנפקות 64 | G9: IL0023105559 | H9: ISIN | I9: צמוד למדד המחירים לצרכן | J9: ישראל | K9: ישראל | L9: סחיר | M9: TASE | N9: בנקים | O9: לא | P9: ilAAA | Q9: S&P מעלות | R9: נייר ערך | S9: ILS | T9: 3.21 | U9: 47950 | V9: 0.001 | W9: 0.0258 | X9: החוב לא נחות | Z9: 1473407 | AA9: 1 | AB9: 104.36 | AD9: 1537.6475 | AH9: 0.00066 | AI9: 0.014484 | AJ9: 0.000373
A10: 274 | B10: 274 | C10: לאומי | D10: 520018078 | E10: ח.פ. | F10: לאומי מימון 179 | G10: IL0060403727 | H10: ISIN | I10: צמוד למדד המחירים לצרכן | J10: ישראל | K10: ישראל | L10: סחיר | M10: TASE | N10: בנקים | O10: לא | P10: ilAAA | Q10: S&P מעלות | R10: נייר ערך | S10: ILS | T10: 1 | U10: 46203 | V10: 0.0083 | W10: 0.0248 | X10: החוב לא נחות | Z10: 377569 | AA10: 1 | AB10: 115.16 | AD10: 434.80846 | AH10: 0.000248 | AI10: 0.004095 | AJ10: 0.000105
A11: 274 | B11: 274 | C11: נתיבי הגז הטבעי לישראל בע"מ | D11: 513436394 | E11: ח.פ. | F11: נתיבי גז אגח ד | G11: IL0011475030 | H11: ISIN | I11: צמוד למדד המחירים לצרכן | J11: ישראל | K11: ישראל | L11: סחיר | M11: TASE | N11: שירותים | O11: לא | P11: Aa1.il | Q11: מידרוג Moodys | R11: נייר ערך | S11: ILS | T11: 5.05 | U11: 48760 | V11: 0.0295 | W11: 0.0252 | X11: החוב לא נחות | Z11: 3888057.3 | AA11: 1 | AB11: 118.55 | AD11: 4609.2919 | AH11: 0.002736 | AI11: 0.043419 | AJ11: 0.001119
A12: 274 | B12: 274 | C12: דיסקונט מנפיקים בע"מ | D12: 520029935 | E12: ח.פ. | F12: דיסקונט מנפיקים אגח טו | G12: IL0074803045 | H12: ISIN | I12: צמוד למדד המחירים לצרכן | J12: ישראל | K12: ישראל | L12: סחיר | M12: TASE | N12: בנקים | O12: לא | P12: ilAAA | Q12: S&P מעלות | R12: נייר ערך | S12: ILS | T12: 3.5 | U12: 48441 | V12: 0.002 | W12: 0.026 | X12: החוב לא נחות | Z12: 4495158.2 | AA12: 1 | AB12: 105.05 | AD12: 4722.1637 | AH12: 0.001318 | AI12: 0.044483 | AJ12: 0.001147
A13: 274 | B13: 274 | C13: בנק הפועלים | D13: 520000118 | E13: ח.פ. | F13: פועלים התח נד ה | G13: IL0066204624 | H13: ISIN | I13: צמוד למדד המחירים לצרכן | J13: ישראל | K13: ישראל | L13: סחיר | M13: TASE | N13: בנקים | O13: לא | P13: ilAA- | Q13: S&P מעלות | R13: נייר ערך | S13: ILS | T13: 1.1 | U13: 46251 | V13: 0.0297 | W13: 0.0303 | X13: החוב לא נחות | Z13: 300000 | AA13: 1 | AB13: 119.99 | AD13: 359.97 | AH13: 0.000428 | AI13: 0.00339 | AJ13: 8.7e-05
A14: 274 | B14: 274 | C14: בנק הפועלים | D14: 520000118 | E14: ח.פ. | F14: פועלים 200 | G14: IL0066204962 | H14: ISIN | I14: צמוד למדד המחירים לצרכן | J14: ישראל | K14: ישראל | L14: סחיר | M14: TASE | N14: בנקים | O14: לא | P14: Aaa.il | Q14: מידרוג Moodys | R14: נייר ערך | S14: ILS | T14: 3.34 | U14: 48191 | V14: 0.001 | W14: 0.0257 | X14: החוב לא נחות | Z14: 465458.7 | AA14: 1 | AB14: 105.19 | AD14: 489.61601 | AH14: 0.000472 | AI14: 0.004612 | AJ14: 0.000118
A15: 274 | B15: 274 | C15: בנק הפועלים | D15: 520000118 | E15: ח.פ. | F15: פועלים אגח 203 | G15: IL0011998684 | H15: ISIN | I15: צמוד למדד המחירים לצרכן | J15: ישראל | K15: ישראל | L15: סחיר | M15: TASE | N15: בנקים | O15: לא | P15: Aaa.il | Q15: מידרוג Moodys | R15: נייר ערך | S15: ILS | T15: 2.81 | U15: 47819 | V15: 0.0175 | W15: 0.0244 | X15: החוב לא נחות | Z15: 766449.9 | AA15: 1 | AB15: 115.29 | AD15: 883.64009 | AH15: 0.000343 | AI15: 0.008323 | AJ15: 0.000214
A16: 274 | B16: 274 | C16: בזק החברה הישראלית לתקשורת בע"מ | D16: 520031931 | E16: ח.פ. | F16: בזק 9 | G16: IL0023001766 | H16: ISIN | I16: לא צמוד למדד המחירים לצרכן | J16: ישראל | K16: ישראל | L16: סחיר | M16: TASE | N16: תקשורת ומדיה | O16: לא | P16: Aa2.il | Q16: מידרוג Moodys | R16: נייר ערך | S16: ILS | T16: 0.42 | U16: 45992 | V16: 0.0365 | W16: 0.0448 | X16: החוב לא נחות | Z16: 176220.85 | AA16: 1 | AB16: 99.97 | AD16: 176.16798 | AH16: 0.00033 | AI16: 0.001659 | AJ16: 4.2e-05
A17: 274 | B17: 274 | C17: לאומי | D17: 520018078 | E17: ח.פ. | F17: לאומי 183 | G17: IL0060405474 | H17: ISIN | I17: צמוד למדד המחירים לצרכן | J17: ישראל | K17: ישראל | L17: סחיר | M17: TASE | N17: בנקים | O17: לא | P17: ilAAA | Q17: S&P מעלות | R17: נייר ערך | S17: ILS | T17: 4.39 | U17: 47447 | V17: 0.001 | W17: 0.0258 | X17: החוב לא נחות | Z17: 2394730 | AA17: 1 | AB17: 102.6 | AD17: 2456.993 | AH17: 0.000558 | AI17: 0.023145 | AJ17: 0.000596
A18: 274 | B18: 274 | C18: חברת החשמל לישראל בע"מ | D18: 520000472 | E18: ח.פ. | F18: חשמל אגח 27 | G18: IL0060002107 | H18: ISIN | I18: צמוד למדד המחירים לצרכן | J18: ישראל | K18: ישראל | L18: סחיר | M18: TASE | N18: אנרגיה | O18: לא | P18: ilAAA | Q18: S&P מעלות | R18: נייר ערך | S18: ILS | T18: 2.77 | U18: 47220 | V18: 0.0385 | W18: 0.0246 | X18: החוב לא נחות | Z18: 11402090 | AA18: 1 | AB18: 123.46 | AD18: 14077.02 | AH18: 0.004511 | AI18: 0.132606 | AJ18: 0.00342
A19: 274 | B19: 274 | C19: הראל ביטוח מימון והנפקות בע"מ | D19: 513834200 | E19: ח.פ. | F19: הראל שטר הון נדחה יג 2029 3.95% | G19: IL0011381717 | H19: ISIN | I19: לא צמוד למדד המחירים לצרכן | J19: ישראל | K19: ישראל | L19: סחיר | M19: TASE | N19: ביטוח | O19: לא | P19: Aa3.il | Q19: מידרוג Moodys | R19: נייר ערך | S19: ILS | T19: 4.17 | U19: 47483 | V19: 0.0395 | W19: 0.0448 | X19: החוב לא נחות | Z19: 26066 | AA19: 1 | AB19: 98.06 | AD19: 25.56032 | AH19: 0.000108 | AI19: 0.00024 | AJ19: 6e-06
A20: 274 | B20: 274 | C20: מקורות חברת מים בע"מ | D20: 520010869 | E20: ח.פ. | F20: מקורות סדרה 10 | G20: IL0011584682 | H20: ISIN | I20: צמוד למדד המחירים לצרכן | J20: ישראל | K20: ישראל | L20: סחיר | M20: TASE | N20: שירותים | O20: לא | P20: ilAAA | Q20: S&P מעלות | R20: נייר ערך | S20: ILS | T20: 1.48 | U20: 46752 | V20: 0.001 | W20: 0.026 | X20: החוב לא נחות | Z20: 967200 | AA20: 1 | AB20: 111.15 | AD20: 1075.0428 | AH20: 0.001505 | AI20: 0.010126 | AJ20: 0.000261
... A26: 274 | B26: 274 | C26: מימון ישיר | D26: 513893123 | E26: ח.פ. | F26: מימון ישיר אגח ד | G26: IL0011756603 | H26: ISIN | I26: צמוד למדד המחירים לצרכן | J26: ישראל | K26: ישראל | L26: סחיר | M26: TASE | N26: אשראי חוץ בנקאי | O26: לא | P26: A1.il | Q26: מידרוג Moodys | R26: נייר ערך | S26: ILS | T26: 0.18 | U26: 46054 | V26: 0.01 | W26: 0.0353 | X26: החוב לא נחות | Z26: 138232.86 | AA26: 1 | AB26: 115.84 | AD26: 160.12895 | AH26: 0.000817 | AI26: 0.001508 | AJ26: 3.8e-05
A27: 274 | B27: 274 | C27: מזרחי טפחות הנפקות | D27: 520032046 | E27: ח.פ. | F27: מזרחי טפחות הנפקות 52 | G27: IL0023103810 | H27: ISIN | I27: צמוד למדד המחירים לצרכן | J27: ישראל | K27: ישראל | L27: סחיר | M27: TASE | N27: בנקים | O27: לא | P27: ilAAA | Q27: S&P מעלות | R27: נייר ערך | S27: ILS | T27: 4.98 | U27: 47665 | V27: 0.002 | W27: 0.0261 | X27: החוב לא נחות | Z27: 2913500 | AA27: 1 | AB27: 104.05 | AC27: 6.82661 | AD27: 3038.3234 | AH27: 0.000842 | AI27: 0.02862 | AJ27: 0.000737
A28: 274 | B28: 274 | C28: קבוצת עזריאלי בע"מ | D28: 510960719 | E28: ח.פ. | F28: עזריאלי אגח ט | G28: IL0012092537 | H28: ISIN | I28: צמוד למדד המחירים לצרכן | J28: ישראל | K28: ישראל | L28: סחיר | M28: TASE | N28: נדל"ן מניב בישראל | O28: לא | P28: Aa1.il | Q28: מידרוג Moodys | R28: נייר ערך | S28: ILS | T28: 11.94 | U28: 53329 | V28: 0.0367 | W28: 0.0316 | X28: החוב לא נחות | Z28: 1882000 | AA28: 1 | AB28: 109.54 | AC28: 35.56791 | AD28: 2097.1107 | AH28: 0.000573 | AI28: 0.019754 | AJ28: 0.000508
A29: 274 | B29: 274 | C29: חברת החשמל לישראל בע"מ | D29: 520000472 | E29: ח.פ. | F29: חשמל 34 | G29: IL0011967812 | H29: ISIN | I29: צמוד למדד המחירים לצרכן | J29: ישראל | K29: ישראל | L29: סחיר | M29: TASE | N29: אנרגיה | O29: לא | P29: ilAAA | Q29: S&P מעלות | R29: נייר ערך | S29: ILS | T29: 7.14 | U29: 48742 | V29: 0.03 | W29: 0.026 | X29: החוב לא נחות | Z29: 1976000 | AA29: 1 | AB29: 109.5 | AD29: 2163.72 | AH29: 0.000484 | AI29: 0.020382 | AJ29: 0.000525
A30: 274 | B30: 274 | C30: מזרחי טפחות הנפקות | D30: 520032046 | E30: ח.פ. | F30: מזרחי טפחות הנפקות 46 | G30: IL0023102259 | H30: ISIN | I30: צמוד למדד המחירים לצרכן | J30: ישראל | K30: ישראל | L30: סחיר | M30: TASE | N30: בנקים | O30: לא | P30: ilAAA | Q30: S&P מעלות | R30: נייר ערך | S30: ILS | T30: 2.21 | U30: 46658 | V30: 0.0122 | W30: 0.0251 | X30: החוב לא נחות | Z30: 7934990 | AA30: 1 | AB30: 116.02 | AD30: 9206.1754 | AH30: 0.002631 | AI30: 0.086722 | AJ30: 0.002236
A31: 274 | B31: 274 | C31: חברת החשמל לישראל בע"מ | D31: 520000472 | E31: ח.פ. | F31: חשמל 31 | G31: IL0060002859 | H31: ISIN | I31: צמוד למדד המחירים לצרכן | J31: ישראל | K31: ישראל | L31: סחיר | M31: TASE | N31: אנרגיה | O31: לא | P31: ilAAA | Q31: S&P מעלות | R31: נייר ערך | S31: ILS | T31: 5.12 | U31: 48112 | V31: 0.0239 | W31: 0.0262 | X31: החוב לא נחות | Z31: 3431000 | AA31: 1 | AB31: 116.21 | AD31: 3987.1651 | AH31: 0.000882 | AI31: 0.037559 | AJ31: 0.000968
A32: 274 | B32: 274 | C32: מימון ישיר | D32: 513893123 | E32: ח.פ. | F32: מימון ישיר קבוצה ו | G32: IL0011916595 | H32: ISIN | I32: צמוד למדד המחירים לצרכן | J32: ישראל | K32: ישראל | L32: סחיר | M32: TASE | N32: אשראי חוץ בנקאי | O32: לא | P32: A1.il | Q32: מידרוג Moodys | R32: נייר ערך | S32: ILS | T32: 1.06 | U32: 46477 | V32: 0.0354 | W32: 0.0342 | X32: החוב לא נחות | Z32: 271737.9 | AA32: 1 | AB32: 109.8 | AD32: 298.36821 | AH32: 0.00027 | AI32: 0.00281 | AJ32: 7.2e-05
A33: 274 | B33: 274 | C33: איידיאיי הנפקות | D33: 514486042 | E33: ח.פ. | F33: אידיאי הנפקות שטר הון נדחה ה 3.27% 15.11.25 רובד2 | G33: IL0011558785 | H33: ISIN | I33: לא צמוד למדד המחירים לצרכן | J33: ישראל | K33: ישראל | L33: סחיר | M33: TASE | N33: ביטוח | O33: לא | P33: A2.il | Q33: מידרוג Moodys | R33: נייר ערך | S33: ILS | T33: 0.4 | U33: 45976 | V33: 0.0327 | W33: 0.0507 | X33: החוב לא נחות | Z33: 516000 | AA33: 1 | AB33: 99.72 | AD33: 514.5552 | AH33: 0.001635 | AI33: 0.004847 | AJ33: 0.000125
A34: 274 | B34: 274 | C34: קבוצת עזריאלי בע"מ | D34: 510960719 | E34: ח.פ. | F34: עזריאלי אגח ה | G34: IL0011566036 | H34: ISIN | I34: צמוד למדד המחירים לצרכן | J34: ישראל | K34: ישראל | L34: סחיר | M34: TASE | N34: נדל"ן מניב בישראל | O34: לא | P34: Aa1.il | Q34: מידרוג Moodys | R34: נייר ערך | S34: ILS | T34: 1.96 | U34: 46934 | V34: 0.0177 | W34: 0.0282 | X34: החוב לא נחות | Z34: 1145250 | AA34: 1 | AB34: 114.73 | AD34: 1313.9453 | AH34: 0.00047 | AI34: 0.012377 | AJ34: 0.000319
A35: 274 | B35: 274 | C35: מזרחי טפחות הנפקות | D35: 520032046 | E35: ח.פ. | F35: מזרחי טפחות הנפקות אגח 62 | G35: IL0023104982 | H35: ISIN | I35: צמוד למדד המחירים לצרכן | J35: ישראל | K35: ישראל | L35: סחיר | M35: TASE | N35: בנקים | O35: לא | P35: ilAAA | Q35: S&P מעלות | R35: נייר ערך | S35: ILS | T35: 3.3 | U35: 47048 | V35: 0.001 | W35: 0.0258 | X35: החוב לא נחות | Z35: 8521952 | AA35: 1 | AB35: 105.48 | AD35: 8988.955 | AH35: 0.002523 | AI35: 0.084676 | AJ35: 0.002183
A36: 274 | B36: 274 | C36: מימון ישיר | D36: 513893123 | E36: ח.פ. | F36: הפחתה בגין קניה בהנפקה מימון ישיר ו 12.9.23 | G36: IL0011916595 | H36: ISIN | I36: צמוד למדד המחירים לצרכן | J36: ישראל | K36: ישראל | L36: סחיר | M36: TASE | N36: אשראי חוץ בנקאי | O36: לא | P36: A1.il | Q36: מידרוג Moodys | R36: נייר ערך | S36: ILS | T36: 1.04 | U36: 46477 | V36: 0.0354 | W36: 0.1305 | X36: החוב לא נחות | Z36: -264.67 | AA36: 1 | AB36: 100 | AD36: -0.26467 | AH36: 0 | AI36: -2e-06 | AJ36: 0
A37: 274 | B37: 274 | C37: מזרחי טפחות הנפקות | D37: 520032046 | E37: ח.פ. | F37: מזרחי טפ הנ אגח 68 | G37: IL0012021429 | H37: ISIN | I37: צמוד למדד המחירים לצרכן | J37: ישראל | K37: ישראל | L37: סחיר | M37: TASE | N37: בנקים | O37: לא | P37: ilAAA | Q37: S&P מעלות | R37: נייר ערך | S37: ILS | T37: 4.2 | U37: 48938 | V37: 0.0199 | W37: 0.0258 | X37: החוב לא נחות | Z37: 3780000 | AA37: 1 | AB37: 103.57 | AD37: 3914.946 | AH37: 0.001555 | AI37: 0.036879 | AJ37: 0.000951
A38: 274 | B38: 274 | C38: הראל ביטוח מימון והנפקות בע"מ | D38: 513834200 | E38: ח.פ. | F38: הראל הנפק אגח ט | G38: IL0011340309 | H38: ISIN | I38: צמוד למדד המחירים לצרכן | J38: ישראל | K38: ישראל | L38: סחיר | M38: TASE | N38: ביטוח | O38: לא | P38: Aa3.il | Q38: מידרוג Moodys | R38: נייר ערך | S38: ILS | T38: 0.5 | U38: 46022 | V38: 0.024 | W38: 0.0288 | X38: החוב לא נחות | Z38: 34548 | AA38: 1 | AB38: 116.76 | AD38: 40.33824 | AH38: 0.000117 | AI38: 0.000379 | AJ38: 9e-06
A39: 274 | B39: 274 | C39: HF SINCLAIR CORP | D39: 98840072S6T63E2V1291 | E39: LEI | F39: DINO 4 1/2 10/01/30 | G39: US403949AC48 | H39: ISIN | I39: צמוד למט"ח | J39: חו"ל | K39: ארה"ב | L39: סחיר | M39: אחר | N39: Energy Equipment & Services | O39: לא | P39: BBB- | Q39: S&P | R39: נייר ערך | S39: USD | T39: 4.68 | U39: 47757 | V39: 0.045 | W39: 0.0523 | X39: החוב לא נחות | Z39: 12000 | AA39: 3.372 | AB39: 98.0653 | AD39: 39.68114 | AH39: 3.6e-05 | AI39: 0.000373 | AJ39: 9e-06
A40: 274 | B40: 274 | C40: Micron Technology Inc | D40: B3DXGBC8GAIYWI2Z0172 | E40: LEI | F40: MU 5 7.8 09.15.33 | G40: US595112CB74 | H40: ISIN | I40: צמוד למט"ח | J40: חו"ל | K40: ארה"ב | L40: סחיר | M40: אחר | N40: Technology Hardware, Storage & Peripherals | O40: לא | P40: Baa3 | Q40: Moodys | R40: נייר ערך | S40: USD | T40: 6.57 | U40: 48837 | V40: 0.05875 | W40: 0.0524 | X40: החוב לא נחות | Z40: 18000 | AA40: 3.372 | AB40: 106.2952 | AD40: 64.51693 | AH40: 2e-05 | AI40: 0.000607 | AJ40: 1.5e-05
A41: 274 | B41: 274 | C41: Hong Kong Airport Authority | D41: 549300DSMAD69T7GGN13 | E41: LEI | F41: HKAA 2.4 PERP | G41: XS2264055182 | H41: ISIN | I41: צמוד למט"ח | J41: חו"ל | K41: הונג קונג | L41: סחיר | M41: HKSE | N41: Other | O41: לא | P41: AA | Q41: S&P | R41: נייר ערך | S41: USD | T41: 2.61 | U41: 46820 | V41: 0.024 | W41: 0.0477 | X41: החוב לא נחות | Z41: 45000 | AA41: 3.372 | AB41: 94.363 | AD41: 143.18642 | AH41: 6e-05 | AI41: 0.001348 | AJ41: 3.4e-05
A42: 274 | B42: 274 | C42: Tapestry | D42: 549300LJNVY5SW3VTN33 | E42: LEI | F42: TPR 4 1/8 07/15/27 | G42: US189754AC88 | H42: ISIN | I42: צמוד למט"ח | J42: חו"ל | K42: ארה"ב | L42: סחיר | M42: NYSE | N42: Personal Care Products | O42: לא | P42: BBB | Q42: S&P | R42: נייר ערך | S42: USD | T42: 1.94 | U42: 46583 | V42: 0.04125 | W42: 0.0456 | X42: החוב לא נחות | Z42: 5000 | AA42: 3.372 | AB42: 101.1551 | AD42: 17.05475 | AH42: 1.2e-05 | AI42: 0.00016 | AJ42: 4e-06
A43: 274 | B43: 274 | C43: POSCO | D43: 988400E5HRVX81AYLM04 | E43: LEI | F43: POHANG 5.75 01/17/28 | G43: USY7S272AG74 | H43: ISIN | I43: צמוד למט"ח | J43: חו"ל | K43: Developed Markets - Pacific | L43: סחיר | M43: FWB | N43: Metals & Mining | O43: לא | P43: Baa1 | Q43: Moodys | R43: נייר ערך | S43: USD | T43: 2.35 | U43: 46769 | V43: 0.0575 | W43: 0.0473 | X43: החוב לא נחות | Z43: 26000 | AA43: 3.372 | AB43: 105.141 | AD43: 92.17922 | AH43: 2.6e-05 | AI43: 0.000868 | AJ43: 2.2e-05
A44: 274 | B44: 274 | C44: valero energy corp | D44: 549300XTO5VR8SKV1V74 | E44: LEI | F44: VLO 5.15 02/15/30 | G44: US91913YBF60 | H44: ISIN | I44: צמוד למט"ח | J44: חו"ל | K44: ארה"ב | L44: סחיר | M44: אחר | N44: Energy Equipment & Services | O44: לא | P44: Baa2 | Q44: Moodys | R44: נייר ערך | S44: USD | T44: 4.1 | U44: 47529 | V44: 0.0515 | W44: 0.0467 | X44: החוב לא נחות | Z44: 24000 | AA44: 3.372 | AB44: 104.2507 | AD44: 84.36801 | AH44: 3.6e-05 | AI44: 0.000794 | AJ44: 2e-05
A45: 274 | B45: 274 | C45: Verisign | D45: LMPL4N8ZOJRMF0KOF759 | E45: LEI | F45: VRSN 2.7 06/15/31 | G45: US92343EAM49 | H45: ISIN | I45: צמוד למט"ח | J45: חו"ל | K45: ארה"ב | L45: סחיר | M45: אחר | N45: Software | O45: לא | P45: Baa3 | Q45: Moodys | R45: נייר ערך | S45: USD | T45: 5.51 | U45: 48014 | V45: 0.027 | W45: 0.0482 | X45: החוב לא נחות | Z45: 25000 | AA45: 3.372 | AB45: 89.4923 | AD45: 75.44201 | AH45: 3.3e-05 | AI45: 0.00071 | AJ45: 1.8e-05
A46: 274 | B46: 274 | C46: H&R Block | D46: 549300CE3KUCWLZBG404 | E46: LEI | F46: HRB 3.875 08/15/30 | G46: US093662AH70 | H46: ISIN | I46: צמוד למט"ח | J46: חו"ל | K46: ארה"ב | L46: סחיר | M46: NYSE | N46: Electric Utilities | O46: לא | P46: Baa3 | Q46: Moodys | R46: נייר ערך | S46: USD | T46: 4.62 | U46: 47710 | V46: 0.03875 | W46: 0.0505 | X46: החוב לא נחות | Z46: 45000 | AA46: 3.372 | AB46: 96.4703 | AD46: 146.38403 | AH46: 6.9e-05 | AI46: 0.001378 | AJ46: 3.5e-05
A47: 274 | B47: 274 | C47: Juniper Networks Inc. | D47: AUHIXNGG7U2U7JEHM527 | E47: LEI | F47: JNPR 2 12/10/30 COR | G47: US48203RAP91 | H47: ISIN | I47: צמוד למט"ח | J47: חו"ל | K47: ארה"ב | L47: סחיר | M47: NYSE | N47: Technology Hardware, Storage & Peripherals | O47: לא | P47: Baa2 | Q47: Moodys | R47: נייר ערך | S47: USD | T47: 5.16 | U47: 47827 | V47: 0.02 | W47: 0.0486 | X47: החוב לא נחות | Z47: 42000 | AA47: 3.372 | AB47: 86.8004 | AD47: 122.9302 | AH47: 0.000105 | AI47: 0.001158 | AJ47: 2.9e-05
A48: 274 | B48: 274 | C48: D.R. Horton Inc | D48: 529900ZIUEYVSB8QDD25 | E48: LEI | F48: DHI 5 10/15/34 | G48: US23331ABS78 | H48: ISIN | I48: צמוד למט"ח | J48: חו"ל | K48: ארה"ב | L48: סחיר | M48: אחר | N48: Personal Care Products | O48: לא | P48: Baa1 | Q48: Moodys | R48: נייר ערך | S48: USD | T48: 7.46 | U48: 49232 | V48: 0.05 | W48: 0.0521 | X48: החוב לא נחות | Z48: 26000 | AA48: 3.372 | AB48: 99.9804 | AD48: 87.65482 | AH48: 3.7e-05 | AI48: 0.000825 | AJ48: 2.1e-05
A49: 274 | B49: 274 | C49: Wipro IT Services | D49: 335800IFS1IJHESG8362 | E49: LEI | F49: WPROIN 1.5 06/23/26 | G49: USU9841MAA00 | H49: ISIN | I49: צמוד למט"ח | J49: חו"ל | K49: גלובלי | L49: סחיר | M49: SGX | N49: Software | O49: לא | P49: A- | Q49: S&P | R49: נייר ערך | S49: USD | T49: 0.98 | U49: 46196 | V49: 0.015 | W49: 0.0465 | X49: החוב לא נחות | Z49: 20000 | AA49: 3.372 | AB49: 97.089 | AD49: 65.47682 | AH49: 2.6e-05 | AI49: 0.000616 | AJ49: 1.5e-05
A50: 274 | B50: 274 | C50: HYUNDAI CAPITAL AMERICA | D50: 9884004RQX8PRBXQ8S60 | E50: LEI | F50: HYNMTR 5.35% 03/19/29 | G50: US44891CCY75 | H50: ISIN | I50: צמוד למט"ח | J50: חו"ל | K50: ארה"ב | L50: סחיר | M50: אחר | N50: Automobile Components | O50: לא | P50: A- | Q50: S&P | R50: נייר ערך | S50: USD | T50: 3.38 | U50: 47196 | V50: 0.0535 | W50: 0.0491 | X50: החוב לא נחות | Z50: 10000 | AA50: 3.372 | AB50: 103.1813 | AD50: 34.79273 | AH50: 2e-05 | AI50: 0.000327 | AJ50: 8e-06
A51: 274 | B51: 274 | C51: חברת החשמל לישראל בע"מ | D51: 520000472 | E51: ח.פ. | F51: ISRAEL ELECTRIC 8.1% 2096 | G51: USM60170AC79 | H51: ISIN | I51: צמוד למט"ח | J51: חו"ל | K51: ישראל | L51: סחיר | M51: אחר | N51: Electric Utilities | O51: לא | P51: Baa2 | Q51: Moodys | R51: נייר ערך | S51: USD | T51: 16.39 | U51: 71939 | V51: 0.081 | W51: 0.0622 | X51: החוב לא נחות | Z51: 200000 | AA51: 3.372 | AB51: 132.123 | AD51: 891.03751 | AH51: 0.0016 | AI51: 0.008393 | AJ51: 0.000216
A52: 274 | B52: 274 | C52: Tapestry | D52: 549300LJNVY5SW3VTN33 | E52: LEI | F52: TPR 3.05 03/15/32 | G52: US876030AA54 | H52: ISIN | I52: צמוד למט"ח | J52: חו"ל | K52: ארה"ב | L52: סחיר | M52: אחר | N52: Personal Care Products | O52: לא | P52: BBB | Q52: S&P | R52: נייר ערך | S52: USD | T52: 6.02 | U52: 48288 | V52: 0.0305 | W52: 0.0495 | X52: החוב לא נחות | Z52: 39000 | AA52: 3.372 | AB52: 90.4542 | AD52: 118.95451 | AH52: 7.8e-05 | AI52: 0.00112 | AJ52: 2.8e-05
A53: 274 | B53: 274 | C53: חברת החשמל לישראל בע"מ | D53: 520000472 | E53: ח.פ. | F53: 7.75% I.ELECTRIC 12/27 | G53: US46507WAB63 | H53: ISIN | I53: צמוד למט"ח | J53: חו"ל | K53: ישראל | L53: סחיר | M53: אחר | N53: Electric Utilities | O53: לא | P53: Baa2 | Q53: Moodys | R53: נייר ערך | S53: USD | T53: 2.29 | U53: 46736 | V53: 0.0775 | W53: 0.0524 | X53: החוב לא נחות | Z53: 1000000 | AA53: 3.372 | AB53: 106.1595 | AD53: 3579.6983 | AH53: 0.003333 | AI53: 0.03372 | AJ53: 0.000869
A54: 274 | B54: 274 | C54: Verisign | D54: LMPL4N8ZOJRMF0KOF759 | E54: LEI | F54: VRSN 5 ¼ 06/01/32 | G54: US92343EAQ52 | H54: ISIN | I54: צמוד למט"ח | J54: חו"ל | K54: ארה"ב | L54: סחיר | M54: אחר | N54: Diversified Telecommunication Services | O54: לא | P54: Baa3 | Q54: Moodys | R54: נייר ערך | S54: USD | T54: 5.88 | U54: 48366 | V54: 0.0525 | W54: 0.0498 | X54: החוב לא נחות | Z54: 15000 | AA54: 3.372 | AB54: 102.3201 | AD54: 51.75351 | AH54: 3e-05 | AI54: 0.000487 | AJ54: 1.2e-05
A55: 274 | B55: 274 | C55: Alibaba Group Holding | D55: 5493001NTNQJDH60PM02 | E55: LEI | F55: BABA 5 1/4 05/26/35 REGS | G55: USG01719AM89 | H55: ISIN | I55: צמוד למט"ח | J55: חו"ל | K55: סין | L55: סחיר | M55: SGX | N55: Media | O55: לא | P55: A+ | Q55: S&P | R55: נייר ערך | S55: USD | T55: 7.83 | U55: 49455 | V55: 0.0525 | W55: 0.0516 | X55: החוב לא נחות | Z55: 19000 | AA55: 3.372 | AB55: 101.6294 | AD55: 65.11192 | AH55: 1.6e-05 | AI55: 0.000613 | AJ55: 1.5e-05
A56: 274 | B56: 274 | C56: Kyndryl Holdings, Inc. | D56: 549300LQ4LWX2R8ZV130 | E56: LEI | F56: KD 6.35 02/20/34 | G56: US50155QAN07 | H56: ISIN | I56: צמוד למט"ח | J56: חו"ל | K56: ארה"ב | L56: סחיר | M56: NYSE | N56: Software | O56: לא | P56: BBB- | Q56: S&P | R56: נייר ערך | S56: USD | T56: 6.72 | U56: 48995 | V56: 0.0635 | W56: 0.0539 | X56: החוב לא נחות | Z56: 18000 | AA56: 3.372 | AB56: 109.2819 | AD56: 66.32974 | AH56: 3.6e-05 | AI56: 0.000624 | AJ56: 1.6e-05
A57: 274 | B57: 274 | C57: GENERAL MOTORS | D57: 54930070NSV60J38I987 | E57: LEI | F57: GM 4.2 01.10.27 | G57: US37045VAN01 | H57: ISIN | I57: צמוד למט"ח | J57: חו"ל | K57: ארה"ב | L57: סחיר | M57: NYSE | N57: Automobile Components | O57: לא | P57: Baa2 | Q57: Moodys | R57: נייר ערך | S57: USD | T57: 2.15 | U57: 46661 | V57: 0.042 | W57: 0.0471 | X57: החוב לא נחות | Z57: 27000 | AA57: 3.372 | AB57: 100.0643 | AD57: 91.10254 | AH57: 3.6e-05 | AI57: 0.000858 | AJ57: 2.2e-05
A58: 274 | B58: 274 | C58: Pershing Square Holdings | D58: G67KJ524WPCAX4V2X190 | E58: LEI | F58: PSHNA 3.25 10/01/31 | G58: XS2392997172 | H58: ISIN | I58: צמוד למט"ח | J58: חו"ל | K58: גרמניה | L58: סחיר | M58: FWB | N58: Diversified Telecommunication Services | O58: לא | P58: BBB+ | Q58: S&P | R58: נייר ערך | S58: USD | T58: 5.62 | U58: 48122 | V58: 0.0325 | W58: 0.0573 | X58: החוב לא נחות | Z58: 46000 | AA58: 3.372 | AB58: 88.2746 | AD58: 136.9245 | AH58: 6.5e-05 | AI58: 0.001289 | AJ58: 3.3e-05
A59: 274 | B59: 274 | C59: Expedia group | D59: 549300IMO4B4W5RWYH14 | E59: LEI | F59: EXPE 2.95 03/15/31 | G59: US30212PBH73 | H59: ISIN | I59: צמוד למט"ח | J59: חו"ל | K59: ארה"ב | L59: סחיר | M59: אחר | N59: Hotels, Restaurants & Leisure | O59: לא | P59: Baa2 | Q59: Moodys | R59: נייר ערך | S59: USD | T59: 5.22 | U59: 47922 | V59: 0.0295 | W59: 0.0475 | X59: החוב לא נחות | Z59: 27000 | AA59: 3.372 | AB59: 92.1828 | AD59: 83.92691 | AH59: 2.7e-05 | AI59: 0.00079 | AJ59: 2e-05
A60: 274 | B60: 274 | C60: Lenovo | D60: 254900VUZRGD5U73RE46 | E60: LEI | F60: Lenovo 3.421 11/02/30 | G60: USY5257YAJ65 | H60: ISIN | I60: צמוד למט"ח | J60: חו"ל | K60: סין | L60: סחיר | M60: HKSE | N60: Technology Hardware, Storage & Peripherals | O60: לא | P60: BBB | Q60: S&P | R60: נייר ערך | S60: USD | T60: 4.88 | U60: 47789 | V60: 0.03421 | W60: 0.0493 | X60: החוב לא נחות | Z60: 44000 | AA60: 3.372 | AB60: 93.7701 | AD60: 139.12482 | AH60: 4.4e-05 | AI60: 0.00131 | AJ60: 3.3e-05

Sheet מניות מבכ ויהש
A1: מספר קופה/קרן/ח.פ. עבור חברת ביטוח | B1: מספר מסלול | C1: שם מנפיק | D1: מספר מנפיק | E1: סוג מספר מזהה מנפיק | F1: שם נייר ערך | G1: מספר נייר ערך | H1: סוג מספר נייר ערך | I1: מאפיין עיקרי | J1: ישראל/חו"ל | K1: מדינה לפי חשיפה כלכלית | L1: סטאטוס סחירות | M1: זירת מסחר | N1: ענף מסחר | O1: בעל עניין/צד קשור | P1: מטבע פעילות | Q1: ערך נקוב (יחידות) | R1: שער חליפין | S1: שער נייר הערך | T1: סכום לקבל (במטבע הפעילות) | U1: שווי הוגן (באלפי ש"ח) | V1: שיעור מערך נקוב מונפק | W1: שיעור מנכסי אפיק ההשקעה | X1: שיעור מסך נכסי ההשקעה
A2: 274 | B2: 274 | C2: שפיר הנדסה ותעשיה בע"מ | D2: 514892801 | E2: ח.פ. | F2: שפיר הנדסה ותעשיה בע"מ | G2: IL0011338758 | H2: ISIN | I2: מניות | J2: ישראל | K2: ישראל | L2: סחיר | M2: TASE | N2: מתכת ומוצרי בניה | O2: לא | P2: ILS | Q2: 25075 | R2: 1 | S2: 3000 | U2: 752.25 | V2: 7e-05 | W2: 0.008727 | X2: 0.000182
A3: 274 | B3: 274 | C3: הפניקס אחזקות | D3: 520017450 | E3: ח.פ. | F3: הפניקס 1 | G3: IL0007670123 | H3: ISIN | I3: מניות | J3: ישראל | K3: ישראל | L3: סחיר | M3: TASE | N3: ביטוח | O3: לא | P3: ILS | Q3: 26458 | R3: 1 | S3: 9745 | U3: 2578.3321 | V3: 0.0001 | W3: 0.029912 | X3: 0.000626
A4: 274 | B4: 274 | C4: אר פי אופטיקל לאב בע"מ | D4: 514454701 | E4: ח.פ. | F4: אר פי אופטיקל | G4: IL0012224627 | H4: ISIN | I4: מניות | J4: ישראל | K4: ישראל | L4: סחיר | M4: TASE | N4: ביטחוניות | O4: לא | P4: ILS | Q4: 16000 | R4: 1 | S4: 1336 | U4: 213.76 | V4: 0.000215 | W4: 0.002479 | X4: 5.1e-05
A5: 274 | B5: 274 | C5: מליסרון | D5: 520037789 | E5: ח.פ. | F5: מליסרון | G5: IL0003230146 | H5: ISIN | I5: מניות | J5: ישראל | K5: ישראל | L5: סחיר | M5: TASE | N5: נדל"ן מניב בישראל | O5: לא | P5: ILS | Q5: 2485 | R5: 1 | S5: 38400 | U5: 954.24 | V5: 5.2e-05 | W5: 0.01107 | X5: 0.000231
A6: 274 | B6: 274 | C6: אנרג'יאן נפט וגז פי אל סי | D6: 560033185 | E6: ח.פ. | F6: אנרג'יאן | G6: GB00BG12Y042 | H6: ISIN | I6: מניות | J6: ישראל | K6: ישראל | L6: סחיר | M6: TASE | N6: חיפושי נפט וגז | O6: לא | P6: ILS | Q6: 9090 | R6: 1 | S6: 4272 | T6: 9.98955 | U6: 398.31435 | V6: 4.9e-05 | W6: 0.00462 | X6: 9.6e-05
A7: 274 | B7: 274 | C7: פתאל החזקות | D7: 512607888 | E7: ח.פ. | F7: פתאל החזקות | G7: IL0011434292 | H7: ISIN | I7: מניות | J7: ישראל | K7: ישראל | L7: סחיר | M7: TASE | N7: מלונאות ותיירות | O7: לא | P7: ILS | Q7: 1432 | R7: 1 | S7: 58480 | U7: 837.4336 | V7: 8.6e-05 | W7: 0.009715 | X7: 0.000203
A8: 274 | B8: 274 | C8: כלל חברה לביטוח | D8: 520036120 | E8: ח.פ. | F8: כלל עסקי ביטוח | G8: IL0002240146 | H8: ISIN | I8: מניות | J8: ישראל | K8: ישראל | L8: סחיר | M8: TASE | N8: ביטוח | O8: לא | P8: ILS | Q8: 9728 | R8: 1 | S8: 14880 | U8: 1447.5264 | V8: 0.000122 | W8: 0.016793 | X8: 0.000351
A9: 274 | B9: 274 | C9: נובה מכשירי מדידה | D9: 511812463 | E9: ח.פ. | F9: נובה | G9: IL0010845571 | H9: ISIN | I9: מניות | J9: ישראל | K9: ישראל | L9: סחיר | M9: TASE | N9: מוליכים למחצה | O9: לא | P9: ILS | Q9: 2728 | R9: 1 | S9: 95280 | U9: 2599.2384 | V9: 9.3e-05 | W9: 0.030155 | X9: 0.000631
A10: 274 | B10: 274 | C10: הראל השקעות | D10: 520033986 | E10: ח.פ. | F10: הראל השקעות | G10: IL0005850180 | H10: ISIN | I10: מניות | J10: ישראל | K10: ישראל | L10: סחיר | M10: TASE | N10: ביטוח | O10: לא | P10: ILS | Q10: 19904 | R10: 1 | S10: 9432 | U10: 1877.3453 | V10: 8.8e-05 | W10: 0.02178 | X10: 0.000456
A11: 274 | B11: 274 | C11: החברה לישראל | D11: 520028010 | E11: ח.פ. | F11: חברה לישראל | G11: IL0005760173 | H11: ISIN | I11: מניות | J11: ישראל | K11: ישראל | L11: סחיר | M11: TASE | N11: השקעה ואחזקות | O11: לא | P11: ILS | Q11: 693 | R11: 1 | S11: 112370 | U11: 778.7241 | V11: 8.9e-05 | W11: 0.009034 | X11: 0.000189
A12: 274 | B12: 274 | C12: אנלייט אנרגיה | D12: 520041146 | E12: ח.פ. | F12: אנלייט אנרגיה | G12: IL0007200111 | H12: ISIN | I12: מניות | J12: ישראל | K12: ישראל | L12: סחיר | M12: TASE | N12: אנרגיה מתחדשת | O12: לא | P12: ILS | Q12: 8738.4 | R12: 1 | S12: 7640 | U12: 667.61376 | V12: 7.3e-05 | W12: 0.007745 | X12: 0.000162
A13: 274 | B13: 274 | C13: טאואר | D13: 520041997 | E13: ח.פ. | F13: טאואר | G13: IL0010823792 | H13: ISIN | I13: מניות | J13: ישראל | K13: ישראל | L13: סחיר | M13: TASE | N13: מוליכים למחצה | O13: לא | P13: ILS | Q13: 9225.76 | R13: 1 | S13: 14620 | U13: 1348.8061 | V13: 8.2e-05 | W13: 0.015648 | X13: 0.000327
A14: 274 | B14: 274 | C14: ביג מרכזי קניות | D14: 513623314 | E14: ח.פ. | F14: ביג | G14: IL0010972607 | H14: ISIN | I14: מניות | J14: ישראל | K14: ישראל | L14: סחיר | M14: TASE | N14: נדל"ן מניב בישראל | O14: לא | P14: ILS | Q14: 1865 | R14: 1 | S14: 64490 | U14: 1202.7385 | V14: 7.4e-05 | W14: 0.013953 | X14: 0.000292
A15: 274 | B15: 274 | C15: טבע | D15: 520013954 | E15: ח.פ. | F15: טבע | G15: IL0006290147 | H15: ISIN | I15: מניות | J15: ישראל | K15: ישראל | L15: סחיר | M15: TASE | N15: פארמה | O15: לא | P15: ILS | Q15: 66101 | R15: 1 | S15: 5699 | U15: 3767.096 | V15: 5.2e-05 | W15: 0.043704 | X15: 0.000915
A16: 274 | B16: 274 | C16: בנק הפועלים | D16: 520000118 | E16: ח.פ. | F16: פועלים | G16: IL0006625771 | H16: ISIN | I16: מניות | J16: ישראל | K16: ישראל | L16: סחיר | M16: TASE | N16: בנקים | O16: לא | P16: ILS | Q16: 92545.18 | R16: 1 | S16: 6462 | U16: 5980.2695 | V16: 6.9e-05 | W16: 0.06938 | X16: 0.001452
A17: 274 | B17: 274 | C17: שיכון ובינוי | D17: 520036104 | E17: ח.פ. | F17: שיכון ובינוי | G17: IL0010819428 | H17: ISIN | I17: מניות | J17: ישראל | K17: ישראל | L17: סחיר | M17: TASE | N17: בנייה | O17: לא | P17: ILS | Q17: 19914.6 | R17: 1 | S17: 1690 | U17: 336.55674 | V17: 3.5e-05 | W17: 0.003904 | X17: 8.1e-05
A18: 274 | B18: 274 | C18: נאוויטס פטרוליום, שותפות מוגבלת | D18: 550263107 | E18: מספר שותפות | F18: נאוויטס פטר יהש | G18: IL0011419699 | H18: ISIN | I18: מניות | J18: ישראל | K18: ישראל | L18: סחיר | M18: TASE | N18: חיפושי נפט וגז | O18: לא | P18: ILS | Q18: 13908 | R18: 1 | S18: 9900 | U18: 1376.892 | V18: 0.000133 | W18: 0.015974 | X18: 0.000334
... A36: 274 | B36: 274 | C36: פרטנר | D36: 520044314 | E36: ח.פ. | F36: פרטנר | G36: IL0010834849 | H36: ISIN | I36: מניות | J36: ישראל | K36: ישראל | L36: סחיר | M36: TASE | N36: מסחר | O36: לא | P36: ILS | Q36: 20423 | R36: 1 | S36: 2555 | U36: 521.80765 | V36: 0.000106 | W36: 0.006053 | X36: 0.000126
A37: 274 | B37: 274 | C37: אלביט מערכות | D37: 520043027 | E37: ח.פ. | F37: אלביט מערכות | G37: IL0010811243 | H37: ISIN | I37: מניות | J37: ישראל | K37: ישראל | L37: סחיר | M37: TASE | N37: ביטחוניות | O37: לא | P37: ILS | Q37: 3354 | R37: 1 | S37: 149800 | T37: 6.85222 | U37: 5031.1442 | V37: 7.2e-05 | W37: 0.058368 | X37: 0.001221
A38: 274 | B38: 274 | C38: קבוצת דלק בע"מ | D38: 520044322 | E38: ח.פ. | F38: דלק קבוצה | G38: IL0010841281 | H38: ISIN | I38: מניות | J38: ישראל | K38: ישראל | L38: סחיר | M38: TASE | N38: חיפושי נפט וגז | O38: לא | P38: ILS | Q38: 809 | R38: 1 | S38: 69740 | U38: 564.1966 | V38: 4.3e-05 | W38: 0.006545 | X38: 0.000137
A39: 274 | B39: 274 | C39: שופרסל | D39: 520022732 | E39: ח.פ. | F39: שופרסל | G39: IL0007770378 | H39: ISIN | I39: מניות | J39: ישראל | K39: ישראל | L39: סחיר | M39: TASE | N39: רשתות שיווק | O39: לא | P39: ILS | Q39: 31033 | R39: 1 | S39: 3869 | U39: 1200.6668 | V39: 0.000112 | W39: 0.013929 | X39: 0.000291
A40: 274 | B40: 274 | C40: כיל | D40: 520027830 | E40: ח.פ. | F40: אי.סי. אל - כיל | G40: IL0002810146 | H40: ISIN | I40: מניות | J40: ישראל | K40: ישראל | L40: סחיר | M40: TASE | N40: כימיה, גומי ופלסטיק | O40: לא | P40: ILS | Q40: 132612 | R40: 1 | S40: 2309 | U40: 3062.0111 | V40: 0.0001 | W40: 0.035524 | X40: 0.000743
A41: 274 | B41: 274 | C41: קבוצת עזריאלי בע"מ | D41: 510960719 | E41: ח.פ. | F41: עזריאלי קבוצה | G41: IL0011194789 | H41: ISIN | I41: מניות | J41: ישראל | K41: ישראל | L41: סחיר | M41: TASE | N41: נדל"ן מניב בישראל | O41: לא | P41: ILS | Q41: 5978 | R41: 1 | S41: 30970 | U41: 1851.3866 | V41: 4.9e-05 | W41: 0.021478 | X41: 0.000449
A42: 274 | B42: 274 | C42: ריט 1 | D42: 513821488 | E42: ח.פ. | F42: ריט 1 | G42: IL0010989205 | H42: ISIN | I42: מניות | J42: ישראל | K42: ישראל | L42: סחיר | M42: TASE | N42: נדל"ן מניב בישראל | O42: לא | P42: ILS | Q42: 20598 | R42: 1 | S42: 2261 | U42: 465.72078 | V42: 0.000105 | W42: 0.005403 | X42: 0.000113
A43: 274 | B43: 274 | C43: לאומי | D43: 520018078 | E43: ח.פ. | F43: לאומי | G43: IL0006046119 | H43: ISIN | I43: מניות | J43: ישראל | K43: ישראל | L43: סחיר | M43: TASE | N43: בנקים | O43: לא | P43: ILS | Q43: 90757.21 | R43: 1 | S43: 6262 | U43: 5683.2165 | V43: 5.6e-05 | W43: 0.065934 | X43: 0.00138
A44: 274 | B44: 274 | C44: נייס | D44: 520036872 | E44: ח.פ. | F44: נייס | G44: IL0002730112 | H44: ISIN | I44: מניות | J44: ישראל | K44: ישראל | L44: סחיר | M44: TASE | N44: תוכנה ואינטרנט | O44: לא | P44: ILS | Q44: 8124 | R44: 1 | S44: 57150 | U44: 4642.866 | V44: 0.000108 | W44: 0.053864 | X44: 0.001128
A45: 274 | B45: 274 | C45: בנק דיסקונט | D45: 520007030 | E45: ח.פ. | F45: דיסקונט א | G45: IL0006912120 | H45: ISIN | I45: מניות | J45: ישראל | K45: ישראל | L45: סחיר | M45: TASE | N45: בנקים | O45: לא | P45: ILS | Q45: 200641.49 | R45: 1 | S45: 3356 | U45: 6733.5284 | V45: 0.000162 | W45: 0.078119 | X45: 0.001635
A46: 274 | B46: 274 | C46: נובה מכשירי מדידה | D46: 511812463 | E46: ח.פ. | F46: NVMI US (POALIM) | G46: IL0010845571 | H46: ISIN | I46: מניות | J46: חו"ל | K46: ישראל | L46: סחיר | M46: NASDAQ | N46: Semiconductors & Semiconductor Equipment | O46: לא | P46: USD | Q46: 1961 | R46: 3.372 | S46: 27520 | U46: 1819.7578 | V46: 6.6e-05 | W46: 0.021112 | X46: 0.000442
A47: 274 | B47: 274 | C47: נייס | D47: 520036872 | E47: ח.פ. | F47: NICE US ( poalim) | G47: US6536561086 | H47: ISIN | I47: מניות | J47: חו"ל | K47: ישראל | L47: סחיר | M47: NASDAQ | N47: Software | O47: לא | P47: USD | Q47: 928 | R47: 3.372 | S47: 16891 | U47: 528.55587 | V47: 1.4e-05 | W47: 0.006132 | X47: 0.000128
A48: 274 | B48: 274 | C48: טבע | D48: 520013954 | E48: ח.פ. | F48: Teva US(poalim) | G48: US8816242098 | H48: ISIN | I48: מניות | J48: חו"ל | K48: ישראל | L48: סחיר | M48: NYSE | N48: Pharmaceuticals | O48: לא | P48: USD | Q48: 24264 | R48: 3.372 | S48: 1676 | U48: 1371.2732 | V48: 2.1e-05 | W48: 0.015908 | X48: 0.000333
A49: 274 | B49: 274 | C49: Taiwan Semiconductor | D49: 549300KB6NK5SBD14S87 | E49: LEI | F49: TSM - Taiwan Semiconductor (P) | G49: US8740391003 | H49: ISIN | I49: מניות | J49: חו"ל | K49: גלובלי | L49: סחיר | M49: NYSE | N49: Semiconductors & Semiconductor Equipment | O49: לא | P49: USD | Q49: 552 | R49: 3.372 | S49: 22649 | T49: 0.41508 | U49: 422.97545 | V49: 0 | W49: 0.004906 | X49: 0.000102
A50: 274 | B50: 274 | C50: InMode | D50: 549300TTHIODYMGND828 | E50: LEI | F50: INMD - InMode (POALIM) | G50: IL0011595993 | H50: ISIN | I50: מניות | J50: חו"ל | K50: ארה"ב | L50: סחיר | M50: NASDAQ | N50: Health Care Providers & Services | O50: לא | P50: USD | Q50: 6133 | R50: 3.372 | S50: 1444 | U50: 298.62607 | V50: 9.7e-05 | W50: 0.003464 | X50: 7.2e-05
A51: 274 | B51: 274 | C51: GOLDMAN | D51: 784F5XWPLTWKTBV3E584 | E51: LEI | F51: GS - Goldman Sachs (P) | G51: US38141G1040 | H51: ISIN | I51: מניות | J51: חו"ל | K51: ארה"ב | L51: סחיר | M51: NYSE | N51: Banks | O51: לא | P51: USD | Q51: 182 | R51: 3.372 | S51: 70775 | U51: 434.34901 | V51: 0 | W51: 0.005039 | X51: 0.000105
A52: 274 | B52: 274 | C52: Lam Research Corp | D52: 549300I4GMO6D34U1T02 | E52: LEI | F52: LRCX - Lam Research (P) | G52: US5128071082 | H52: ISIN | I52: מניות | J52: חו"ל | K52: ארה"ב | L52: סחיר | M52: NASDAQ | N52: Semiconductors & Semiconductor Equipment | O52: לא | P52: USD | Q52: 624 | R52: 3.372 | S52: 9734 | T52: 0.14351 | U52: 205.29974 | V52: 0 | W52: 0.002381 | X52: 4.9e-05
A53: 274 | B53: 274 | C53: GOOGLE INC | D53: 5493006MHB84DD0ZWV18 | E53: LEI | F53: GOOG- Alphabet (p) | G53: US02079K1079 | H53: ISIN | I53: מניות | J53: חו"ל | K53: ארה"ב | L53: סחיר | M53: NASDAQ | N53: Diversified Telecommunication Services | O53: לא | P53: USD | Q53: 777 | R53: 3.372 | S53: 17739 | U53: 464.76961 | V53: 0 | W53: 0.005392 | X53: 0.000112
A54: 274 | B54: 274 | C54: ASML | D54: 724500Y6DUVHQD6OXN27 | E54: LEI | F54: ASML NA - ASML Holding (P) | G54: NL0010273215 | H54: ISIN | I54: מניות | J54: חו"ל | K54: אירופה | L54: סחיר | M54: אחר | N54: Technology Hardware, Storage & Peripherals | O54: לא | P54: EUR | Q54: 75 | R54: 3.9552 | S54: 67760 | U54: 201.00326 | V54: 0 | W54: 0.002331 | X54: 4.8e-05
A55: 274 | B55: 274 | C55: קמטק | D55: 511235434 | E55: ח.פ. | F55: camt-קמטק חול(poalim) | G55: IL0010952641 | H55: ISIN | I55: מניות | J55: חו"ל | K55: ישראל | L55: סחיר | M55: NYSE | N55: Semiconductors & Semiconductor Equipment | O55: לא | P55: USD | Q55: 462 | R55: 3.372 | S55: 8456 | U55: 131.73298 | V55: 1e-05 | W55: 0.001528 | X55: 3.2e-05
A56: 274 | B56: 274 | C56: אנלייט אנרגיה | D56: 520041146 | E56: ח.פ. | F56: ENLIGHT RENEWABLE ENERGY LTD(poalim) | G56: IL0007200111 | H56: ISIN | I56: מניות | J56: חו"ל | K56: ישראל | L56: סחיר | M56: NASDAQ | N56: Energy Equipment & Services | O56: לא | P56: USD | Q56: 3164 | R56: 3.372 | S56: 2273 | U56: 242.50655 | V56: 2.6e-05 | W56: 0.002813 | X56: 5.8e-05
A57: 274 | B57: 274 | C57: NVIDIA Corporation | D57: 549300S4KLFTLO7GSQ80 | E57: LEI | F57: NVDA - NVIDIA (P) | G57: US67066G1040 | H57: ISIN | I57: מניות | J57: חו"ל | K57: ארה"ב | L57: סחיר | M57: NASDAQ | N57: Semiconductors & Semiconductor Equipment | O57: לא | P57: USD | Q57: 1105 | R57: 3.372 | S57: 15799 | T57: 0.01105 | U57: 588.71748 | V57: 0 | W57: 0.006829 | X57: 0.000143
A58: 274 | B58: 274 | C58: אורמת טכנולוגיות, אינק (דואלי) | D58: 880326081 | E58: ח.פ. | F58: ORA US (POALIM) | G58: US6866881021 | H58: ISIN | I58: מניות | J58: חו"ל | K58: ארה"ב | L58: סחיר | M58: NYSE | N58: Energy Equipment & Services | O58: לא | P58: USD | Q58: 3469 | R58: 3.372 | S58: 8376 | U58: 979.77992 | V58: 5.7e-05 | W58: 0.011366 | X58: 0.000238
A59: 274 | B59: 274 | C59: TESLA INC | D59: 54930043XZGB27CTOV49 | E59: LEI | F59: TSLA Tesla Inc (P) | G59: US88160R1014 | H59: ISIN | I59: מניות | J59: חו"ל | K59: ארה"ב | L59: סחיר | M59: NASDAQ | N59: Automobile Components | O59: לא | P59: USD | Q59: 187 | R59: 3.372 | S59: 31766 | U59: 200.30496 | V59: 0 | W59: 0.002323 | X59: 4.8e-05
A60: 274 | B60: 274 | C60: Freeport Mcmoran | D60: 549300IRDTHJQ1PVET45 | E60: LEI | F60: FCX - Freeport Mcmoran (p) | G60: US35671D8570 | H60: ISIN | I60: מניות | J60: חו"ל | K60: ארה"ב | L60: סחיר | M60: NYSE | N60: Metals & Mining | O60: לא | P60: USD | Q60: 773 | R60: 3.372 | S60: 4335 | U60: 112.9942 | V60: 0 | W60: 0.00131 | X60: 2.7e-05
A61: 274 | B61: 274 | C61: Vertiv | D61: 549300KTTIRAOGXCRV69 | E61: LEI | F61: VRT - Vertiv Holding(P) | G61: US92537N1081 | H61: ISIN | I61: מניות | J61: חו"ל | K61: ארה"ב | L61: סחיר | M61: NYSE | N61: Industrial Conglomerates | O61: לא | P61: USD | Q61: 406 | R61: 3.372 | S61: 12841 | U61: 175.7974 | V61: 1e-06 | W61: 0.002039 | X61: 4.2e-05
A62: 274 | B62: 274 | C62: SOLAREDGE | D62: 5493000K6Y58XXPDF853 | E62: LEI | F62: SEDG US ( POALIM) | G62: US83417M1045 | H62: ISIN | I62: מניות | J62: חו"ל | K62: ארה"ב | L62: סחיר | M62: NASDAQ | N62: Technology Hardware, Storage & Peripherals | O62: לא | P62: USD | Q62: 6770 | R62: 3.372 | S62: 2040 | U62: 465.70018 | V62: 0.000114 | W62: 0.005402 | X62: 0.000113
A63: 274 | B63: 274 | C63: CHENIERE ENERGY INC | D63: MIHC87W9WTYSYZWV1J40 | E63: LEI | F63: LNG Cheniere Energy Inc (P) | G63: US16411R2085 | H63: ISIN | I63: מניות | J63: חו"ל | K63: ארה"ב | L63: סחיר | M63: NYSE | N63: Energy Equipment & Services | O63: לא | P63: USD | Q63: 323 | R63: 3.372 | S63: 24352 | U63: 265.23127 | V63: 1e-06 | W63: 0.003077 | X63: 6.4e-05
A64: 274 | B64: 274 | C64: טאואר | D64: 520041997 | E64: ח.פ. | F64: TOWER TSEM US( POALIM) | G64: IL0010823792 | H64: ISIN | I64: מניות | J64: חו"ל | K64: ישראל | L64: סחיר | M64: NASDAQ | N64: Semiconductors & Semiconductor Equipment | O64: לא | P64: USD | Q64: 10554 | R64: 3.372 | S64: 4335 | U64: 1542.7436 | V64: 9.4e-05 | W64: 0.017898 | X64: 0.000374
A65: 274 | B65: 274 | C65: META PLATFORMS INC | D65: BQ4BKCS1HXDV9HN80Z93 | E65: LEI | F65: META - Meta Platforms (P) | G65: US30303M1027 | H65: ISIN | I65: מניות | J65: חו"ל | K65: ארה"ב | L65: סחיר | M65: NASDAQ | N65: Media | O65: לא | P65: USD | Q65: 422 | R65: 3.372 | S65: 73809 | U65: 1050.2903 | V65: 0 | W65: 0.012185 | X65: 0.000255

Sheet קרנות סל
A1: מספר קופה/קרן/ח.פ. עבור חברת ביטוח | B1: מספר מסלול | C1: שם מנפיק | D1: מספר מנפיק | E1: סוג מספר מזהה מנפיק | F1: שם נייר ערך | G1: מספר נייר ערך | H1: סוג מספר נייר ערך | I1: מאפיין עיקרי | J1: ישראל/חו"ל | K1: מדינה לפי חשיפה כלכלית | L1: זירת מסחר | M1: סיווג הקרן | N1: בעל עניין/צד קשור | O1: מטבע פעילות | P1: ערך נקוב (יחידות) | Q1: שער חליפין | R1: שער נייר הערך | S1: סכום לקבל (במטבע הפעילות) | T1: שווי הוגן (באלפי ש"ח) | U1: שיעור מערך נקוב מונפק | V1: שיעור מנכסי אפיק ההשקעה | W1: שיעור מסך נכסי ההשקעה
A2: 274 | B2: 274 | C2: מגדל קרנות נאמנות בע"מ | D2: 511303661 | E2: ח.פ. | F2: MTF סל (00) תל בונד 20 | G2: IL0011499881 | H2: ISIN | I2: עוקב אחר מדדים אחרים בישראל | J2: ישראל | K2: ישראל | L2: TASE | M2: 20 אג"ח בארץ - חברות והמרה-תל בונד צמוד מדד-תל בונד | N2: לא | O2: ILS | P2: 33000 | Q2: 1 | R2: 486.63 | T2: 160.5879 | U2: 0.000138 | V2: 0.000511 | W2: 3.9e-05
A3: 274 | B3: 274 | C3: קסם קרנות נאמנות בע"מ | D3: 510938608 | E3: ח.פ. | F3: קסם ETF תלבונד 20 | G3: IL0011459604 | H3: ISIN | I3: עוקב אחר מדדים אחרים בישראל | J3: ישראל | K3: ישראל | L3: TASE | M3: 20 אג"ח בארץ - חברות והמרה-תל בונד צמוד מדד-תל בונד | N3: לא | O3: ILS | P3: 5930.5 | Q3: 1 | R3: 3896.38 | T3: 231.07482 | U3: 0.000113 | V3: 0.000736 | W3: 5.6e-05
A4: 274 | B4: 274 | C4: מיטב תכלית קרנות נאמנות בע"מ | D4: 513534974 | E4: ח.פ. | F4: תכלית סל (00) תל בונד 40 | G4: IL0011450934 | H4: ISIN | I4: עוקב אחר מדדים אחרים בישראל | J4: ישראל | K4: ישראל | L4: TASE | M4: 40 אג"ח בארץ - חברות והמרה-תל בונד צמוד מדד-תל בונד | N4: לא | O4: ILS | P4: 351755 | Q4: 1 | R4: 373.55 | T4: 1313.9808 | U4: 0.000612 | V4: 0.004188 | W4: 0.000319
A5: 274 | B5: 274 | C5: הראל קרנות נאמנות בע"מ | D5: 511776783 | E5: ח.פ. | F5: הראל סל תא 35 | G5: IL0011489072 | H5: ISIN | I5: עוקב אחר מדדי מניות בישראל | J5: ישראל | K5: ישראל | L5: TASE | M5: 35 מניות בארץ - מניות כללי-ת"א | N5: לא | O5: ILS | P5: 152802 | Q5: 1 | R5: 2915 | T5: 4454.1783 | U5: 0.001793 | V5: 0.014197 | W5: 0.001082
A6: 274 | B6: 274 | C6: מגדל קרנות נאמנות בע"מ | D6: 511303661 | E6: ח.פ. | F6: MTF סל תל בונד 60 | G6: IL0011499964 | H6: ISIN | I6: עוקב אחר מדדים אחרים בישראל | J6: ישראל | K6: ישראל | L6: TASE | M6: 60 אג"ח בארץ - חברות והמרה-תל בונד צמוד מדד-תל בונד | N6: לא | O6: ILS | P6: 1818503 | Q6: 1 | R6: 488.99 | T6: 8892.2978 | U6: 0.008659 | V6: 0.028343 | W6: 0.00216
A7: 274 | B7: 274 | C7: מיטב תכלית קרנות נאמנות בע"מ | D7: 513534974 | E7: ח.פ. | F7: תכלית סל תא 35 | G7: IL0011437006 | H7: ISIN | I7: עוקב אחר מדדי מניות בישראל | J7: ישראל | K7: ישראל | L7: TASE | M7: 35 מניות בארץ - מניות כללי-ת"א | N7: לא | O7: ILS | P7: 46030 | Q7: 1 | R7: 2913 | T7: 1340.8539 | U7: 0.000179 | V7: 0.004273 | W7: 0.000325
A8: 274 | B8: 274 | C8: מגדל קרנות נאמנות בע"מ | D8: 511303661 | E8: ח.פ. | F8: MTF סל (4A) ת"א 35 | G8: IL0011501843 | H8: ISIN | I8: עוקב אחר מדדי מניות בישראל | J8: ישראל | K8: ישראל | L8: TASE | M8: 35 מניות בארץ - מניות כללי-ת"א | N8: לא | O8: ILS | P8: 189694 | Q8: 1 | R8: 3968 | T8: 7527.0579 | U8: 0.002709 | V8: 0.023991 | W8: 0.001828
A9: 274 | B9: 274 | C9: קסם קרנות נאמנות בע"מ | D9: 510938608 | E9: ח.פ. | F9: קסם ETF תא 35 | G9: IL0011465700 | H9: ISIN | I9: עוקב אחר מדדי מניות בישראל | J9: ישראל | K9: ישראל | L9: TASE | M9: 35 מניות בארץ - מניות כללי-ת"א | N9: לא | O9: ILS | P9: 9711.81 | Q9: 1 | R9: 28980 | T9: 2814.4825 | U9: 0.000502 | V9: 0.00897 | W9: 0.000683
A10: 274 | B10: 274 | C10: הראל קרנות נאמנות בע"מ | D10: 511776783 | E10: ח.פ. | F10: הראל סל תלבונד 20 | G10: IL0011504409 | H10: ISIN | I10: עוקב אחר מדדים אחרים בישראל | J10: ישראל | K10: ישראל | L10: TASE | M10: 20 אג"ח בארץ - חברות והמרה-תל בונד צמוד מדד-תל בונד | N10: לא | O10: ILS | P10: 68800 | Q10: 1 | R10: 393.25 | T10: 270.556 | U10: 0.000282 | V10: 0.000862 | W10: 6.5e-05
A11: 274 | B11: 274 | C11: State Street | D11: 549300ZFEEJ2IP5VME73 | E11: LEI | F11: XLU US (p) | G11: US81369Y8865 | H11: ISIN | I11: עוקב אחר מדדי מניות בחו"ל | J11: חו"ל | K11: ארה"ב | L11: NYSE | M11: Equity Funds | N11: לא | O11: USD | P11: 698 | Q11: 3.372 | R11: 8166 | T11: 192.19955 | U11: 2e-06 | V11: 0.000612 | W11: 4.6e-05
A12: 274 | B12: 274 | C12: VanEck | D12: 549300MJTG2N9QRH7I02 | E12: LEI | F12: SMH- VanEck Semiconductor -POALIM | G12: US92189F6768 | H12: ISIN | I12: עוקב אחר מדדי מניות בחו"ל | J12: חו"ל | K12: ארה"ב | L12: NASDAQ | M12: Equity Funds | N12: לא | O12: USD | P12: 695 | Q12: 3.372 | R12: 27888 | T12: 653.56644 | U12: 7e-06 | V12: 0.002083 | W12: 0.000158
A13: 274 | B13: 274 | C13: AMUNDI INVT SOLUTIONS | D13: 549300FMBJ5S1PXQ2305 | E13: LEI | F13: U127 LN - MSCI Emerging Markets (P) | G13: LU2573966905 | H13: ISIN | I13: עוקב אחר מדדי מניות בחו"ל | J13: חו"ל | K13: גלובלי | L13: LSE | M13: Equity Funds | N13: לא | O13: USD | P13: 136677 | Q13: 3.372 | R13: 5416 | T13: 24960.982 | U13: 0.002289 | V13: 0.079559 | W13: 0.006064
A14: 274 | B14: 274 | C14: State Street | D14: 549300ZFEEJ2IP5VME73 | E14: LEI | F14: XLC US - Communication Services (P) | G14: US81369Y8527 | H14: ISIN | I14: עוקב אחר מדדי מניות בחו"ל | J14: חו"ל | K14: ארה"ב | L14: NYSE | M14: Equity Funds | N14: לא | O14: USD | P14: 3998 | Q14: 3.372 | R14: 10853 | T14: 1463.1207 | U14: 1.7e-05 | V14: 0.004663 | W14: 0.000355
A15: 274 | B15: 274 | C15: INVESCO | D15: ECPGFXU8A2SHKVVGJI15 | E15: LEI | F15: MUNI LN | G15: IE00BNG70R26 | H15: ISIN | I15: אחר | J15: חו"ל | K15: ארה"ב | L15: LSE | M15: אג"ח בחו"ל - אג"ח חשופת מט"ח | N15: לא | O15: USD | P15: 6600 | Q15: 3.372 | R15: 3180 | T15: 707.71536 | U15: 0.008816 | V15: 0.002255 | W15: 0.000171
A16: 274 | B16: 274 | C16: INVESCO | D16: ECPGFXU8A2SHKVVGJI15 | E16: LEI | F16: PPA - Invesco Aerospace & Defense (p) | G16: US46137V1008 | H16: ISIN | I16: עוקב אחר מדדי מניות בחו"ל | J16: חו"ל | K16: ארה"ב | L16: NYSE | M16: Equity Funds | N16: לא | O16: USD | P16: 819 | Q16: 3.372 | R16: 14169 | T16: 391.30074 | U16: 2e-05 | V16: 0.001247 | W16: 9.5e-05
A17: 274 | B17: 274 | C17: AMUNDI INVT SOLUTIONS | D17: 549300FMBJ5S1PXQ2305 | E17: LEI | F17: CEU FP - MSCI EUROPE ESG (P) | G17: LU1681042609 | H17: ISIN | I17: עוקב אחר מדדי מניות בחו"ל | J17: חו"ל | K17: Developed Markets - Europe | L17: NYSE | M17: Equity Funds | N17: לא | O17: EUR | P17: 3346 | Q17: 3.9552 | R17: 36108.52 | T17: 4778.6373 | U17: 0.000597 | V17: 0.015231 | W17: 0.001161
A18: 274 | B18: 274 | C18: Tabula | D18: 635400BK5J6GBMBFNG77 | E18: LEI | F18: TAHY LN - Asia USD HY | G18: IE000LZC9M0 | H18: ISIN | I18: אחר | J18: חו"ל | K18: אסיה | L18: LSE | M18: אג"ח בחו"ל - אג"ח חשופת מט"ח | N18: לא | O18: USD | P18: 10550 | Q18: 3.372 | R18: 775.1 | T18: 275.73872 | U18: 0.000546 | V18: 0.000878 | W18: 6.6e-05
A19: 274 | B19: 274 | C19: DWS | D19: 7LTWFZYICNSX8D621K86 | E19: LEI | F19: XDWD LN - MSCI World (P) | G19: IE00BJ0KDQ92 | H19: ISIN | I19: עוקב אחר מדדי מניות בחו"ל | J19: חו"ל | K19: אסיה | L19: LSE | M19: Equity Funds | N19: לא | O19: USD | P19: 51959 | Q19: 3.372 | R19: 12865.5 | T19: 22541.096 | U19: 0.000402 | V19: 0.071846 | W19: 0.005476
A20: 274 | B20: 274 | C20: INVESCO MARKETS PLC | D20: ECPGFXU8A2SHKVVGJI15 | E20: LEI | F20: MXWO LN - MSCI World (P) | G20: IE00B60SX394 | H20: ISIN | I20: עוקב אחר מדדי מניות בחו"ל | J20: חו"ל | K20: אסיה | L20: LSE | M20: Equity Funds | N20: לא | O20: USD | P20: 20140 | Q20: 3.372 | R20: 12626 | T20: 8574.5792 | U20: 0.000368 | V20: 0.02733 | W20: 0.002083
A21: 274 | B21: 274 | C21: DWS | D21: 7LTWFZYICNSX8D621K86 | E21: LEI | F21: XDJP GR - Nikkei 225 (P) | G21: LU0839027447 | H21: ISIN | I21: עוקב אחר מדדי מניות בחו"ל | J21: חו"ל | K21: יפן | L21: FWB | M21: Equity Funds | N21: לא | O21: EUR | P21: 18776 | Q21: 3.9552 | R21: 2459 | T21: 1826.1231 | U21: 0.000355 | V21: 0.00582 | W21: 0.000443
A22: 274 | B22: 274 | C22: AMUNDI INVT SOLUTIONS | D22: 549300FMBJ5S1PXQ2305 | E22: LEI | F22: SP5C LN - S&P 500 (P) | G22: LU1135865084 | H22: ISIN | I22: עוקב אחר מדדי מניות בחו"ל | J22: חו"ל | K22: ארה"ב | L22: LSE | M22: Equity Funds | N22: לא | O22: USD | P22: 14942 | Q22: 3.372 | R22: 44471 | T22: 22406.457 | U22: 0.000574 | V22: 0.071417 | W22: 0.005443
... A45: 274 | B45: 274 | C45: ISHARES | D45: 549300LRIF3NWCU26A80 | E45: LEI | F45: MUSD NA - MSCI USA (P) | G45: IE0002W8NB38 | H45: ISIN | I45: עוקב אחר מדדי מניות בחו"ל | J45: חו"ל | K45: ארה"ב | L45: אחר | M45: Equity Funds | N45: לא | O45: USD | P45: 675112 | Q45: 3.372 | R45: 842.93 | T45: 19189.113 | U45: 0.003747 | V45: 0.061162 | W45: 0.004662

Sheet קרנות נאמנות
A1: מספר קופה/קרן/ח.פ. עבור חברת ביטוח | B1: מספר מסלול | C1: שם מנפיק | D1: מספר מנפיק | E1: סוג מספר מזהה מנפיק | F1: שם נייר ערך | G1: מספר נייר ערך | H1: סוג מספר נייר ערך | I1: מאפיין עיקרי | J1: ישראל/חו"ל | K1: מדינה לפי חשיפה כלכלית | L1: סטאטוס סחירות | M1: זירת מסחר | N1: סיווג הקרן | O1: בעל עניין/צד קשור | P1: מטבע פעילות | Q1: ערך נקוב (יחידות) | R1: שער חליפין | S1: שער נייר הערך | T1: שווי הוגן (באלפי ש"ח) | U1: שיעור מערך נקוב מונפק | V1: שיעור מנכסי אפיק ההשקעה | W1: שיעור מסך נכסי ההשקעה
A2: 274 | B2: 274 | C2: Nomura Asset Management UK | D2: 549300B3CEAHYG7K8164 | E2: LEI | F2: Nomura US HY | G2: IE00B3RW8498 | H2: ISIN | I2: אג"ח קונצרני | J2: חו"ל | K2: ארה"ב | L2: סחיר | M2: אחר | N2: אג"ח בחו"ל - אג"ח חשופת מט"ח | O2: לא | P2: USD | Q2: 1180 | R2: 3.372 | S2: 41914.19 | T2: 1667.7488 | U2: 4.5e-05 | V2: 0.055644 | W2: 0.000405
A3: 274 | B3: 274 | C3: Liontrust | D3: 549300XVXU6S7PLCL855 | E3: LEI | F3: Liontrust European Dynamic | G3: GB00BKPQVT86 | H3: ISIN | I3: מניות | J3: חו"ל | K3: אירופה | L3: סחיר | M3: אחר | N3: Equity Funds | O3: לא | P3: GBP | Q3: 391485 | R3: 4.6236 | S3: 145.78 | T3: 2638.6905 | U3: 0.000756 | V3: 0.08804 | W3: 0.000641
A4: 274 | B4: 274 | C4: Pinebridge | D4: 549300KM5F6LSTMERC50 | E4: LEI | F4: PineBridge US IG | G4: IE00BD82R632 | H4: ISIN | I4: אג"ח קונצרני | J4: חו"ל | K4: ארה"ב | L4: סחיר | M4: ISE | N4: אג"ח בחו"ל - אג"ח חשופת מט"ח | O4: לא | P4: USD | Q4: 1346.3 | R4: 3.372 | S4: 12289 | T4: 557.88663 | U4: 1e-06 | V4: 0.018613 | W4: 0.000135
A5: 274 | B5: 274 | C5: Daiwa | D5: 2138008IOOVSKCGISQ06 | E5: LEI | F5: DAIWA SBI JAPAN SC | G5: LU1907539057 | H5: ISIN | I5: מניות | J5: חו"ל | K5: יפן | L5: סחיר | M5: אחר | N5: Equity Funds | O5: לא | P5: JPY | Q5: 2993 | R5: 0.023369 | S5: 2244699 | T5: 1570.0192 | U5: 0.010712 | V5: 0.052383 | W5: 0.000381
A6: 274 | B6: 274 | C6: Lazard Inc | D6: 254900RIBCDJSUFG1A11 | E6: LEI | F6: Lazard Japanese Strategic Equity | G6: IE000UTYHEP1 | H6: ISIN | I6: מניות | J6: חו"ל | K6: יפן | L6: סחיר | M6: אחר | N6: Equity Funds | O6: לא | P6: JPY | Q6: 3326 | R6: 0.023369 | S6: 1453342.8 | T6: 1129.6149 | U6: 0.003314 | V6: 0.037689 | W6: 0.000274
A7: 274 | B7: 274 | C7: Ninety One | D7: 549300G0TJCT3K15ZG14 | E7: LEI | F7: N91 EM IG | G7: LU1275256334 | H7: ISIN | I7: אג"ח קונצרני | J7: חו"ל | K7: גלובלי | L7: סחיר | M7: אחר | N7: אג"ח בחו"ל - אג"ח חשופת מט"ח | O7: לא | P7: USD | Q7: 4808.92 | R7: 3.372 | S7: 2925 | T7: 474.30859 | U7: 0.000928 | V7: 0.015825 | W7: 0.000115
A8: 274 | B8: 274 | C8: HSBC Global Investment Funds | D8: 2138009R2RHG7P8LL653 | E8: LEI | F8: HSBC IG Global Securitized Credit | G8: LU1194161839 | H8: ISIN | I8: אג"ח קונצרני | J8: חו"ל | K8: גלובלי | L8: סחיר | M8: אחר | N8: אג"ח בחו"ל - אג"ח חשופת מט"ח | O8: לא | P8: USD | Q8: 11200 | R8: 3.372 | S8: 1193.2 | T8: 450.62868 | U8: 0.008407 | V8: 0.015035 | W8: 0.000109
A9: 274 | B9: 274 | C9: India Acorn ICAV | D9: 213800MG9QHLSQHZYD08 | E9: LEI | F9: Ashoka Indian Opportunities | G9: IE00BH3N4915 | H9: ISIN | I9: מניות | J9: חו"ל | K9: גלובלי | L9: סחיר | M9: אחר | N9: Equity Funds | O9: לא | P9: USD | Q9: 1992 | R9: 3.372 | S9: 27787 | T9: 1866.4595 | U9: 1e-06 | V9: 0.062274 | W9: 0.000453
A10: 274 | B10: 274 | C10: RAM (Lux) Systematic funds | D10: 54930031J1R3XQN7ZR19 | E10: LEI | F10: RAM (Lux) Systematic EM | G10: LU1433244511 | H10: ISIN | I10: מניות | J10: חו"ל | K10: גלובלי | L10: סחיר | M10: אחר | N10: Equity Funds | O10: לא | P10: USD | Q10: 2258 | R10: 3.372 | S10: 12994 | T10: 989.36004 | U10: 0.002889 | V10: 0.03301 | W10: 0.00024
A11: 274 | B11: 274 | C11: Threadneedle | D11: 6ZLKQF7QB6JAEKQS5388 | E11: LEI | F11: Threadneedle US | G11: LU1859430891 | H11: ISIN | I11: אג"ח קונצרני | J11: חו"ל | K11: ארה"ב | L11: סחיר | M11: אחר | N11: אג"ח בחו"ל - אג"ח חשופת מט"ח | O11: לא | P11: USD | Q11: 39118.44 | R11: 3.372 | S11: 1409.78 | T11: 1859.6039 | U11: 0.000459 | V11: 0.062045 | W11: 0.000451
A12: 274 | B12: 274 | C12: Oaktree Capital Management LP | D12: 5493003O8J2P3YCBEH15 | E12: LEI | F12: Oaktree Global Credit | G12: LU1617688392 | H12: ISIN | I12: אג"ח קונצרני | J12: חו"ל | K12: גלובלי | L12: סחיר | M12: אחר | N12: אג"ח בחו"ל - אג"ח חשופת מט"ח | O12: לא | P12: USD | Q12: 5380 | R12: 3.372 | S12: 15062.3 | T12: 2732.5061 | U12: 1.6e-05 | V12: 0.09117 | W12: 0.000663
A13: 274 | B13: 274 | C13: HSBC Global Investment Funds | D13: 2138009R2RHG7P8LL653 | E13: LEI | F13: HSBC HY Global Securitized Credit | G13: LU1194162217 | H13: ISIN | I13: אג"ח קונצרני | J13: חו"ל | K13: גלובלי | L13: סחיר | M13: אחר | N13: אג"ח בחו"ל - אג"ח חשופת מט"ח | O13: לא | P13: USD | Q13: 5400 | R13: 3.372 | S13: 1668 | T13: 303.72278 | U13: 0.00241 | V13: 0.010133 | W13: 7.3e-05
... A21: 274 | B21: 274 | C21: ARTEMIS | D21: 549300CN3YT7REW82D41 | E21: LEI | F21: Artemis SmartGARP EM | G21: LU1846577242 | H21: ISIN | I21: מניות | J21: חו"ל | K21: גלובלי | L21: סחיר | M21: אחר | N21: Equity Funds | O21: לא | P21: USD | Q21: 179624 | R21: 3.372 | S21: 164.88 | T21: 998.66518 | U21: 0.002975 | V21: 0.03332 | W21: 0.000242

Sheet כתבי אופציה
A1: מספר קופה/קרן/ח.פ. עבור חברת ביטוח | B1: מספר מסלול | C1: שם מנפיק | D1: מספר מנפיק | E1: סוג מספר מזהה מנפיק | F1: שם נייר ערך | G1: מספר נייר ערך | H1: סוג מספר נייר ערך | I1: ישראל/חו"ל | J1: מדינה לפי חשיפה כלכלית | K1: סטאטוס סחירות | L1: זירת מסחר | M1: נכס בסיס (כתב אופציה) | N1: ענף מסחר | O1: תאריך פקיעה | P1: בעל עניין/צד קשור | Q1: מטבע פעילות | R1: שער מימוש | S1: יחס המרה | T1: ערך נקוב (יחידות) | U1: שער חליפין | V1: שער נייר הערך | W1: שווי הוגן (באלפי ש"ח) | X1: שיעור מנכסי אפיק ההשקעה | Y1: שיעור מסך נכסי ההשקעה
A2: 274 | B2: 274 | C2: זפירוס ווינג אנרג'יס בע"מ | D2: 516537560 | E2: ח.פ. | F2: זפירוס אפ1 | G2: IL0011947038 | H2: ISIN | I2: ישראל | J2: ישראל | K2: סחיר | L2: TASE | M2: IL0011946956 | N2: אנרגיה מתחדשת | O2: 46203 | P2: לא | Q2: ILS | R2: 1650 | S2: 1 | T2: 6900 | U2: 1 | V2: 347.1 | W2: 23.9499 | X2: 1 | Y2: 5e-06

Sheet אופציות
A1: מספר קופה/קרן/ח.פ. עבור חברת ביטוח | B1: מספר מסלול | C1: שם מנפיק | D1: מספר מנפיק | E1: סוג מספר מזהה מנפיק | F1: שם נייר ערך | G1: מספר נייר ערך | H1: סוג מספר נייר ערך | I1: מאפיין עיקרי | J1: ישראל/חו"ל | K1: מדינה לפי חשיפה כלכלית | L1: זירת מסחר | M1: ענף מסחר | N1: נכס בסיס | O1: תאריך פקיעה | P1: בעל עניין/צד קשור | Q1: מטבע פעילות | R1: שער מימוש | S1: ערך נקוב (יחידות) | T1: שער חליפין | U1: שער נייר הערך | V1: שווי הוגן (באלפי ש"ח) | W1: שיעור מנכסי אפיק ההשקעה | X1: שיעור מסך נכסי ההשקעה
A2: 274 | B2: 274

Sheet חוזים עתידיים
A1: מספר קופה/קרן/ח.פ. עבור חברת ביטוח | B1: מספר מסלול | C1: שם מנפיק | D1: מספר מנפיק | E1: סוג מספר מזהה מנפיק | F1: שם נייר ערך | G1: מספר נייר ערך | H1: סוג מספר נייר ערך | I1: ישראל/חו"ל | J1: מדינה לפי חשיפה כלכלית | K1: זירת מסחר | L1: נכס בסיס | M1: בעל עניין/צד קשור | N1: מטבע פעילות | O1: ערך נקוב (יחידות) | P1: שער חליפין | Q1: שער נייר הערך | R1: שווי הוגן (באלפי ש"ח) | S1: שיעור מנכסי אפיק ההשקעה | T1: שיעור מסך נכסי ההשקעה
A2: 274 | B2: 274

Sheet מוצרים מובנים
A1: מספר קופה/קרן/ח.פ. עבור חברת ביטוח | B1: מספר מסלול | C1: שם מנפיק | D1: מספר מנפיק | E1: סוג מספר מזהה מנפיק | F1: שם נייר ערך | G1: מספר נייר ערך | H1: סוג מספר נייר ערך | I1: מאפיין עיקרי | J1: ישראל/חו"ל | K1: מדינה לפי חשיפה כלכלית | L1: סטאטוס סחירות | M1: זירת מסחר | N1: נכס בסיס | O1: בעל עניין/צד קשור | P1: מח"מ | Q1: שיעור ריבית | R1: תשואה לפדיון | S1: דירוג | T1: שם מדרג | U1: דירוג נייר הערך/המנפיק | V1: מטבע פעילות | W1: ערך נקוב (יחידות) | X1: שער חליפין | Y1: שער נייר הערך | Z1: שווי הוגן (באלפי ש"ח) | AA1: שיעור מנכסי אפיק ההשקעה | AB1: שיעור מסך נכסי ההשקעה
A2: 274 | B2: 274

Sheet לא סחיר איגרות חוב ממשלתיות
A1: מספר קופה/קרן/ח.פ. עבור חברת ביטוח | B1: מספר מסלול | C1: שם מנפיק | D1: שם נייר ערך | E1: מספר נייר ערך | F1: סוג מספר נייר ערך | G1: מאפיין עיקרי | H1: ישראל/חו"ל | I1: מדינה לפי חשיפה כלכלית | J1: תאריך רכישה | K1: דירוג | L1: שם מדרג | M1: מטבע פעילות | N1: מח"מ | O1: מועד פדיון | P1: שיעור ריבית | Q1: תשואה לפדיון | R1: ערך נקוב (יחידות) | S1: שער חליפין | T1: שער נייר הערך | U1: שווי הוגן (באלפי ש"ח) | V1: עלות מופחתת (באלפי ש"ח) | W1: השיטה שיושמה בדוח הכספי | X1: שיעור מנכסי אפיק ההשקעה | Y1: שיעור מסך נכסי ההשקעה
A2: 274 | B2: 274

Sheet לא סחיר איגרות חוב מיועדות
A1: מספר קופה/קרן/ח.פ. עבור חברת ביטוח | B1: מספר מסלול | C1: מאפיין עיקרי | D1: שם נייר ערך | E1: מספר נייר ערך | F1: תאריך רכישה | G1: מח"מ | H1: סוג הצמדה | I1: מועד פדיון | J1: שיעור ריבית | K1: תשואה לפדיון | L1: ערך נקוב (יחידות) | M1: שער נייר הערך | N1: שווי הוגן (באלפי ש"ח) | O1: עלות מופחתת (באלפי ש"ח) | P1: השיטה שיושמה בדוח הכספי | Q1: שיעור מנכסי אפיק ההשקעה | R1: שיעור מסך נכסי ההשקעה
A2: 274 | B2: 274 | C2: ערד בקרן פנסיה ותיקה | D2: ערד 8808 01.11.28 4.8% | E2: 8288086 | F2: 41579 | G2: 3.12 | H2: צמוד למדד המחירים לצרכן | I2: 47058 | J2: 0.048 | K2: 0.0202 | L2: 17560000 | M2: 128.154 | N2: 22503.844 | Q2: 0.027591 | R2: 0.005467
A3: 274 | B3: 274 | C3: ערד בקרן פנסיה ותיקה | D3: ערד 8813 01.4.29 4.8% | E3: 8288136 | F3: 41730 | G3: 3.46 | H3: צמוד למדד המחירים לצרכן | I3: 47209 | J3: 0.048 | K3: 0.0201 | L3: 13232000 | M3: 130.954 | N3: 17327.834 | Q3: 0.021245 | R3: 0.004209
A4: 274 | B4: 274 | C4: ערד בקרן פנסיה ותיקה | D4: ערד 8815 01.6.29 4.8% | E4: 8288151 | F4: 41791 | G4: 3.63 | H4: צמוד למדד המחירים לצרכן | I4: 47270 | J4: 0.048 | K4: 0.02 | L4: 2205000 | M4: 130.0493 | N4: 2867.5867 | Q4: 0.003515 | R4: 0.000696
A5: 274 | B5: 274 | C5: ערד בקרן פנסיה ותיקה | D5: ערד 8810 01.1.29 4.8% | E5: 8288102 | F5: 41640 | G5: 3.21 | H5: צמוד למדד המחירים לצרכן | I5: 47119 | J5: 0.048 | K5: 0.0202 | L5: 9964000 | M5: 130.6875 | N5: 13021.701 | Q5: 0.015965 | R5: 0.003163
A6: 274 | B6: 274 | C6: ערד בקרן פנסיה ותיקה | D6: ערד 8802 01.05.28 4.8% | E6: 8288029 | F6: 41395 | G6: 2.68 | H6: צמוד למדד המחירים לצרכן | I6: 46874 | J6: 0.048 | K6: 0.0204 | L6: 7882000 | M6: 128.8464 | N6: 10155.676 | Q6: 0.012451 | R6: 0.002467
A7: 274 | B7: 274 | C7: ערד בקרן פנסיה ותיקה | D7: ערד 8822 1.1.30 4.8% | E7: 8288227 | F7: 42005 | G7: 4.05 | H7: צמוד למדד המחירים לצרכן | I7: 47484 | J7: 0.048 | K7: 0.0199 | L7: 10497000 | M7: 133.9332 | N7: 14058.967 | Q7: 0.017237 | R7: 0.003415
A8: 274 | B8: 274 | C8: ערד בקרן פנסיה ותיקה | D8: ערד 8847 1.2.32 4.8% | E8: 8288474 | F8: 42767 | G8: 5.72 | H8: צמוד למדד המחירים לצרכן | I8: 48245 | J8: 0.048 | K8: 0.0197 | L8: 19656000 | M8: 141.4681 | N8: 27806.967 | Q8: 0.034093 | R8: 0.006755
A9: 274 | B9: 274 | C9: ערד בקרן פנסיה ותיקה | D9: ערד 8798 01.01.28 4.8% | E9: 8287989 | F9: 41275 | G9: 2.35 | H9: צמוד למדד המחירים לצרכן | I9: 46754 | J9: 0.048 | K9: 0.0205 | L9: 8201000 | M9: 129.9651 | N9: 10658.438 | Q9: 0.013067 | R9: 0.002589
A10: 274 | B10: 274 | C10: ערד בקרן פנסיה ותיקה | D10: ערד 8809 01.12.28 4.8% | E10: 8288094 | F10: 41609 | G10: 3.2 | H10: צמוד למדד המחירים לצרכן | I10: 47088 | J10: 0.048 | K10: 0.0201 | L10: 6804000 | M10: 127.5992 | N10: 8681.8494 | Q10: 0.010644 | R10: 0.002109
A11: 274 | B11: 274 | C11: ערד בקרן פנסיה ותיקה | D11: ערד 8801 02.04.28 4.8% | E11: 8288011 | F11: 41366 | G11: 2.6 | H11: צמוד למדד המחירים לצרכן | I11: 46845 | J11: 0.048 | K11: 0.0204 | L11: 4900000 | M11: 129.3123 | N11: 6336.3034 | Q11: 0.007768 | R11: 0.001539
A12: 274 | B12: 274 | C12: ערד בקרן פנסיה ותיקה | D12: ערד 8897 02.05.36 4.8% | E12: 8288979 | F12: 44318 | G12: 8.84 | H12: צמוד למדד המחירים לצרכן | I12: 49797 | J12: 0.048 | K12: 0.0194 | L12: 18604000 | M12: 149.6031 | N12: 27832.165 | Q12: 0.034124 | R12: 0.006762
A13: 274 | B13: 274 | C13: ערד בקרן פנסיה ותיקה | D13: ערד 8894 01.02.36 4.8% | E13: 8288946 | F13: 44228 | G13: 8.59 | H13: צמוד למדד המחירים לצרכן | I13: 49706 | J13: 0.048 | K13: 0.0194 | L13: 9736000 | M13: 151.5105 | N13: 14751.064 | Q13: 0.018085 | R13: 0.003583
... A78: 274 | B78: 274 | C78: ערד בקרן פנסיה ותיקה | D78: ערד 8856 1.11.32 4.8% | E78: 8288565 | F78: 43040 | G78: 6.34 | H78: צמוד למדד המחירים לצרכן | I78: 48519 | J78: 0.048 | K78: 0.0196 | L78: 1162000 | M78: 141.873 | N78: 1648.5638 | Q78: 0.002021 | R78: 0.0004

Sheet אפיק השקעה מובטח תשואה
A1: מספר קרן | B1: מספר מסלול | C1: מאפיין עיקרי | D1: חודש הנפקת שכבה | E1: חודש הבדיקה | F1: שווי הנכסים באפיק (באלפי ש"ח) | G1: שיעור מסך נכסי ההשקעה
A2: 274 | B2: 274

Sheet לא סחיר ניירות ערך מסחריים
A1: מספר קופה/קרן/ח.פ. עבור חברת ביטוח | B1: מספר מסלול | C1: שם מנפיק | D1: מספר מנפיק | E1: סוג מספר מזהה מנפיק | F1: שם נייר ערך | G1: מספר נייר ערך | H1: סוג מספר נייר ערך | I1: מאפיין עיקרי | J1: ישראל/חו"ל | K1: מדינה לפי חשיפה כלכלית | L1: ענף מסחר | M1: בעל עניין/צד קשור | N1: תאריך רכישה | O1: דירוג | P1: שם מדרג | Q1: דירוג נייר הערך/המנפיק | R1: מטבע פעילות | S1: מח"מ | T1: סוג הצמדה | U1: ריבית עוגן | V1: מועד פדיון | W1: שיעור ריבית | X1: תשואה לפדיון | Y1: נחיתות חוזית | Z1: האם סווג כחוב בעייתי | AA1: סוג גורם משערך | AB1: תלות/אי-תלות המשערך | AC1: שם גורם משערך | AD1: תאריך שערוך אחרון | AE1: תאריך אחרון בו נבחנה בפועל ירידת ערך | AF1: ערך נקוב (יחידות) | AG1: שער חליפין | AH1: שער נייר הערך | AI1: שווי הוגן (באלפי ש"ח) | AJ1: עלות מופחתת (באלפי ש"ח) | AK1: עלות מופחתת (במטבע הפעילות) | AL1: השיטה שיושמה בדוח הכספי | AM1: שיעור מנכסי אפיק ההשקעה | AN1: שיעור מסך נכסי ההשקעה
A2: 274 | B2: 274

Sheet לא סחיר איגרות חוב
A1: מספר קופה/קרן/ח.פ. עבור חברת ביטוח | B1: מספר מסלול | C1: שם מנפיק | D1: מספר מנפיק | E1: סוג מספר מזהה מנפיק | F1: שם נייר ערך | G1: מספר נייר ערך | H1: סוג מספר נייר ערך | I1: מאפיין עיקרי | J1: ישראל/חו"ל | K1: מדינה לפי חשיפה כלכלית | L1: סטאטוס סחירות | M1: ענף מסחר | N1: בעל עניין/צד קשור | O1: תאריך רכישה | P1: דירוג | Q1: שם מדרג | R1: דירוג נייר הערך/המנפיק | S1: מטבע פעילות | T1: מח"מ | U1: מועד פדיון | V1: תשואה לפדיון | W1: שיעור ריבית | X1: נחיתות חוזית | Y1: האם סווג כחוב בעייתי | Z1: סוג גורם משערך | AA1: תלות/אי-תלות המשערך | AB1: תאריך שערוך אחרון | AC1: תאריך אחרון בו נבחנה בפועל ירידת ערך | AD1: ערך נקוב (יחידות) | AE1: שער חליפין | AF1: שער נייר הערך | AG1: שווי הוגן (באלפי ש"ח) | AH1: עלות מופחתת (באלפי ש"ח) | AI1: עלות מופחתת (במטבע הפעילות) | AJ1: השיטה שיושמה בדוח הכספי | AK1: שיעור מנכסי אפיק ההשקעה | AL1: שיעור מסך נכסי ההשקעה
A2: 274 | B2: 274 | C2: מקורות חברת מים בע"מ | D2: 520010869 | E2: ח.פ. | F2: מקורות סדרה ו | G2: IL0011009086 | H2: ISIN | I2: צמוד למדד המחירים לצרכן | J2: ישראל | K2: ישראל | L2: לא סחיר | M2: שירותים | N2: לא | O2: 39076 | P2: ilAAA | Q2: S&P מעלות | R2: נייר ערך | S2: ILS | T2: 5.24 | U2: 50034 | V2: 0.027 | W2: 0.049 | X2: החוב לא נחות | Z2: חברת ציטוט | AA2: אי-תלות | AB2: 45838 | AD2: 1100612.3 | AE2: 1 | AF2: 161.45 | AG2: 1776.9386 | AK2: 0.125492 | AL2: 0.000431
A3: 274 | B3: 274 | C3: נתיבי הגז הטבעי לישראל בע"מ | D3: 513436394 | E3: ח.פ. | F3: נתיבי גז א | G3: IL0011030843 | H3: ISIN | I3: צמוד למדד המחירים לצרכן | J3: ישראל | K3: ישראל | L3: לא סחיר | M3: שירותים | N3: לא | O3: 39084 | P3: Aa1.il | Q3: מידרוג Moodys | R3: נייר ערך | S3: ILS | T3: 0.83 | U3: 46385 | V3: 0.0289 | W3: 0.056 | X3: החוב לא נחות | Z3: חברת ציטוט | AA3: אי-תלות | AB3: 45838 | AD3: 269338.36 | AE3: 1 | AF3: 144.6 | AG3: 389.46327 | AK3: 0.027504 | AL3: 9.4e-05
A4: 274 | B4: 274 | C4: מקורות חברת מים בע"מ | D4: 520010869 | E4: ח.פ. | F4: מקורות 8 4.1% 2048 | G4: IL0011243461 | H4: ISIN | I4: צמוד למדד המחירים לצרכן | J4: ישראל | K4: ישראל | L4: לא סחיר | M4: שירותים | N4: לא | O4: 40738 | P4: ilAAA | Q4: S&P מעלות | R4: נייר ערך | S4: ILS | T4: 8.88 | U4: 54253 | V4: 0.0308 | W4: 0.041 | X4: החוב לא נחות | Z4: חברת ציטוט | AA4: אי-תלות | AB4: 45838 | AD4: 4647667.3 | AE4: 1 | AF4: 137.31 | AG4: 6381.7119 | AK4: 0.450693 | AL4: 0.00155
A5: 274 | B5: 274 | C5: נתיבי הגז הטבעי לישראל בע"מ | D5: 513436394 | E5: ח.פ. | F5: נתיבי גז ג | G5: IL0011255093 | H5: ISIN | I5: צמוד למדד המחירים לצרכן | J5: ישראל | K5: ישראל | L5: לא סחיר | M5: שירותים | N5: לא | O5: 40910 | P5: Aa1.il | Q5: מידרוג Moodys | R5: נייר ערך | S5: ILS | T5: 3.29 | U5: 48213 | V5: 0.0286 | W5: 0.048 | X5: החוב לא נחות | Z5: חברת ציטוט | AA5: אי-תלות | AB5: 45838 | AD5: 2541899.9 | AE5: 1 | AF5: 128.67 | AG5: 3270.6626 | AK5: 0.230982 | AL5: 0.000794
A6: 274 | B6: 274 | C6: מתם מרכז תעשיות מדע חיפה בע"מ | D6: 510687403 | E6: ח.פ. | F6: מת"ם אגח א -רמ | G6: IL0011389991 | H6: ISIN | I6: לא צמוד למדד המחירים לצרכן | J6: ישראל | K6: ישראל | L6: לא סחיר | M6: נדל"ן מניב בישראל | N6: לא | O6: 42598 | P6: ilAA | Q6: S&P מעלות | R6: נייר ערך | S6: ILS | T6: 1.46 | U6: 46568 | V6: 0.0463 | W6: 0.031 | X6: החוב לא נחות | Z6: חברת ציטוט | AA6: אי-תלות | AB6: 45838 | AD6: 448000.13 | AE6: 1 | AF6: 97.91 | AG6: 438.63693 | AK6: 0.030977 | AL6: 0.000106
A7: 274 | B7: 274 | C7: אורמת טכנולוגיות, אינק (דואלי) | D7: 880326081 | E7: ח.פ. | F7: אורמת 4 | G7: IL0011672123 | H7: ISIN | I7: לא צמוד למדד המחירים לצרכן | J7: ישראל | K7: ישראל | L7: לא סחיר | M7: אנרגיה מתחדשת | N7: לא | O7: 44014 | P7: ilAA- | Q7: S&P מעלות | R7: נייר ערך | S7: ILS | T7: 3.2 | U7: 48014 | V7: 0.0512 | W7: 0.0335 | X7: החוב לא נחות | Z7: חברת ציטוט | AA7: אי-תלות | AB7: 45838 | AD7: 213678.6 | AE7: 1 | AF7: 94.87 | AG7: 202.71689 | AK7: 0.014316 | AL7: 4.9e-05
A8: 274 | B8: 274 | C8: רשות שדות התעופה בישראל | D8: 500102868 | E8: ח.פ. | F8: רש"ת אגח א-רמ | G8: IL0011873358 | H8: ISIN | I8: צמוד למדד המחירים לצרכן | J8: ישראל | K8: ישראל | L8: לא סחיר | M8: שירותים | N8: לא | O8: 44740 | P8: Aaa.il | Q8: מידרוג Moodys | R8: נייר ערך | S8: ILS | T8: 3.51 | U8: 48213 | V8: 0.0283 | W8: 0.0155 | X8: החוב לא נחות | Z8: חברת ציטוט | AA8: אי-תלות | AB8: 45838 | AD8: 787500 | AE8: 1 | AF8: 106.05 | AG8: 835.14375 | AK8: 0.05898 | AL8: 0.000202
A9: 274 | B9: 274 | C9: רשות שדות התעופה בישראל | D9: 500102868 | E9: ח.פ. | F9: רש"ת אגח ב-רמ | G9: IL0011873432 | H9: ISIN | I9: צמוד למדד המחירים לצרכן | J9: ישראל | K9: ישראל | L9: לא סחיר | M9: שירותים | N9: לא | O9: 44740 | P9: Aaa.il | Q9: מידרוג Moodys | R9: נייר ערך | S9: ILS | T9: 6.42 | U9: 50040 | V9: 0.0281 | W9: 0.0175 | X9: החוב לא נחות | Z9: חברת ציטוט | AA9: אי-תלות | AB9: 45838 | AD9: 712800 | AE9: 1 | AF9: 103.68 | AG9: 739.03104 | AK9: 0.052192 | AL9: 0.000179
A10: 274 | B10: 274 | C10: בינלאומי | D10: 520029083 | E10: ח.פ. | F10: אוצר החייל כ.התח 03/26 3.95% | G10: 6014211 | H10: פנימי | I10: צמוד למדד המחירים לצרכן | J10: ישראל | K10: ישראל | L10: לא סחיר | M10: בנקים | N10: לא | O10: 40625 | P10: ilAA+ | Q10: S&P מעלות | R10: נייר ערך | S10: ILS | T10: 0.73 | U10: 46104 | V10: 0.0247 | W10: 0.0395 | X10: החוב לא נחות | Z10: חברת ציטוט | AA10: אי-תלות | AB10: 45838 | AD10: 100000 | AE10: 1 | AF10: 125.47 | AG10: 125.47 | AK10: 0.008861 | AL10: 3e-05

Sheet לא סחיר מניות מבכ ויהש
A1: מספר קופה/קרן/ח.פ. עבור חברת ביטוח | B1: מספר מסלול | C1: שם מנפיק | D1: מספר מנפיק | E1: סוג מספר מזהה מנפיק | F1: שם נייר ערך | G1: מספר נייר ערך | H1: סוג מספר נייר ערך | I1: מאפיין עיקרי | J1: ישראל/חו"ל | K1: מדינה לפי חשיפה כלכלית | L1: סטאטוס סחירות | M1: ענף מסחר | N1: בעל עניין/צד קשור | O1: תאריך רכישה | P1: מטבע פעילות | Q1: סוג גורם משערך | R1: תלות/אי-תלות המשערך | S1: תאריך שערוך אחרון | T1: תאריך אחרון בו נבחנה בפועל ירידת ערך | U1: ערך נקוב (יחידות) | V1: שער חליפין | W1: שער נייר הערך | X1: שווי הוגן (באלפי ש"ח) | Y1: שיעור מנכסי אפיק ההשקעה | Z1: שיעור מסך נכסי ההשקעה
A2: 274 | B2: 274

Sheet קרנות השקעה
A1: מספר קופה/קרן/ח.פ. עבור חברת ביטוח | B1: מספר מסלול | C1: שם שותף כללי קרן השקעות | D1: מספר מזהה שותף כללי קרן השקעות | E1: סוג מספר מזהה שותף כללי קרן השקעות | F1: שם קרן השקעה | G1: מספר מזהה קרן השקעה | H1: סוג מספר מזהה קרן השקעות | I1: מאפיין עיקרי | J1: אסטרטגיית קרן ההשקעה | K1: ישראל/חו"ל | L1: מדינת התאגדות קרן השקעה | M1: מיקום משרד השותף הכללי | N1: מדינה לפי חשיפה כלכלית | O1: בעל עניין/צד קשור | P1: תאריך רכישה | Q1: מטבע פעילות | R1: סוג גורם משערך | S1: תלות/אי-תלות המשערך | T1: תאריך שערוך אחרון | U1: שער חליפין | V1: NAV (במטבע הדיווח של קרן ההשקעה) | W1: שווי הוגן (באלפי ש"ח) | X1: שיעור החזקה בקרן השקעה | Y1: שיעור מנכסי אפיק ההשקעה | Z1: שיעור מסך נכסי ההשקעה
A2: 274 | B2: 274 | C2: IIF | F2: A ת.ש.י דרכים מר | G2: 6254 | H2: פנימי | I2: קרן אנרגיה ותשתיות | K2: ישראל | N2: ישראל | O2: לא | P2: 40542 | Q2: ILS | R2: דיווח מנהל הקרן | S2: אי-תלות | T2: 45838 | U2: 1 | V2: 2505.418 | W2: 2505.418 | X2: 1.8e-05 | Y2: 1 | Z2: 0.000608

Sheet לא סחיר כתבי אופציה
A1: מספר קופה/קרן/ח.פ. עבור חברת ביטוח | B1: מספר מסלול | C1: שם מנפיק | D1: מספר מנפיק | E1: סוג מספר מזהה מנפיק | F1: שם נייר ערך | G1: מספר נייר ערך | H1: סוג מספר נייר ערך | I1: ישראל/חו"ל | J1: מדינה לפי חשיפה כלכלית | K1: סטאטוס סחירות | L1: נכס בסיס (כתב אופציה) | M1: ענף מסחר | N1: תאריך פקיעה | O1: בעל עניין/צד קשור | P1: תאריך רכישה | Q1: מטבע פעילות | R1: סוג גורם משערך | S1: תלות/אי-תלות המשערך | T1: תאריך שערוך אחרון | U1: שער מימוש | V1: יחס המרה | W1: ערך נקוב (יחידות) | X1: שער נייר הערך | Y1: שער חליפין | Z1: שווי הוגן (באלפי ש"ח) | AA1: שיעור מנכסי אפיק ההשקעה | AB1: שיעור מסך נכסי ההשקעה
A2: 274 | B2: 274

Sheet לא סחיר אופציות
A1: מספר קופה/קרן/ח.פ. עבור חברת ביטוח | B1: מספר מסלול | C1: שם מנפיק | D1: מספר מנפיק | E1: סוג מספר מזהה מנפיק | F1: שם נייר ערך | G1: מספר נייר ערך | H1: סוג מספר נייר ערך | I1: מאפיין עיקרי | J1: ישראל/חו"ל | K1: מדינה לפי חשיפה כלכלית | L1: ענף מסחר | M1: נכס בסיס | N1: תאריך פקיעה | O1: בעל עניין/צד קשור | P1: תאריך רכישה | Q1: מטבע פעילות | R1: סוג גורם משערך | S1: תלות/אי-תלות המשערך | T1: תאריך שערוך אחרון | U1: שער מימוש | V1: יחס המרה | W1: ערך נקוב (יחידות) | X1: שער נייר הערך | Y1: שער חליפין | Z1: שווי הוגן (בש"ח) | AA1: שיעור מנכסי אפיק ההשקעה | AB1: שיעור מסך נכסי ההשקעה
A2: 274 | B2: 274

Sheet לא סחיר נגזרים אחרים
A1: מספר קופה/קרן/ח.פ. עבור חברת ביטוח | B1: מספר מסלול | C1: מאפיין עיקרי | D1: מספר עסקה (רגל 1) | E1: מטבע פעילות (רגל 1) | F1: שער חליפין | G1: ערך נקוב (רגל 1) | H1: שווי הוגן במטבע הנסחר (רגל 1) | I1: שיעור מנכסי אפיק ההשקעה (רגל 1) | J1: שיעור מסך נכסי ההשקעה (רגל 1) | K1: מספר עסקה (רגל 2) | L1: מטבע פעילות (רגל 2) | M1: שער חליפין | N1: ערך נקוב (רגל 2) | O1: שווי הוגן במטבע הנסחר (רגל 2) | P1: שיעור מנכסי ההשקעה (רגל 2) | Q1: שיעור מסך אפיק ההשקעה (רגל 2) | R1: שווי הוגן (נטו באלפי ש"ח) | S1: ישראל/חו"ל | T1: מדינה לפי חשיפה כלכלית | U1: סוג הנכס | V1: פקטור מוביל | W1: פקטור נוסף | X1: טיקר | Y1: בעל עניין/צד קשור | Z1: מועד ההתקשרות בעסקה | AA1: מועד סיום חוזי | AB1: תדירות Reset | AC1: סוג הסליקה | AD1: נספח התחשבנות בטחונות - CSA | AE1: גורם מצטט | AF1: ריבית עוגן | AG1: תקופת ריבית עוגן | AH1: שיעור ריבית עוגן | AI1: שער נכס הבסיס במועד ההתקשרות בעסקה | AJ1: שער הנגזר במועד ההתקשרות בעסקה | AK1: האם קיים קנס בגין יציאה מוקדמת | AL1: שיעור הקנס בגין יציאה מוקדמת | AM1: צד נגדי - Counterparty | AN1: שיעור מנכסי אפיק ההשקעה | AO1: שיעור מסך נכסי ההשקעה
A2: 274 | B2: 274 | C2: Funded Forward | D2: 76020372 | E2: USD | F2: 3.372 | G2: -700000 | H2: -700 | I2: -0.02605667 | J2: -0.0005734777 | K2: 760203720 | L2: ILS | M2: 1 | N2: 700000 | O2: 2527.62 | P2: 0.00061410512 | Q2: -0.43851716 | R2: 167.22003 | S2: ישראל | T2: ישראל | U2: מט"ח | V2: אחר | W2: מט"ח/₪ | X2: USDILS | Y2: לא | Z2: 45530 | AA2: 45909 | AB2: ללא | AC2: Delivery | AD2: לא קיים חוזה | AE2: הצד הנגדי | AF2: ללא | AG2: ללא | AI2: 3.666 | AM2: MIZBILIT | AN2: 0.044209708 | AO2: 4.0627418e-05
A3: 274 | B3: 274 | C3: Funded Swap | D3: 31011130 | E3: ILS | F3: 1 | G3: 1900000 | H3: 2441.087 | I3: 0.090866569 | J3: 0.00059308123 | K3: 310111300 | L3: ILS | M3: 1 | N3: -1900000 | O3: -2386.284 | P3: -0.00057976642 | Q3: 0.41399675 | R3: 54.80296 | S3: ישראל | T3: ישראל | U3: מדד המחירים לצרכן | V3: אחר | W3: מדדים | X3: ILSILS | Y3: לא | Z3: 44718 | AA3: 48219 | AB3: ללא | AC3: No-delivery | AD3: קיים חוזה | AE3: הצד הנגדי | AF3: ללא | AG3: ללא | AI3: 1 | AM3: LEUMIILILTXXX | AN3: 0.014488832 | AO3: 1.3314809e-05
A4: 274 | B4: 274 | C4: Funded Swap | D4: 31011191 | E4: ILS | F4: 1 | G4: 1600000 | H4: 2005.7769 | I4: 0.074662669 | J4: 0.00048731924 | K4: 310111910 | L4: ILS | M4: 1 | N4: -1600000 | O4: -2054.138 | P4: -0.00049906894 | Q4: 0.35637269 | R4: -48.36107 | S4: ישראל | T4: ישראל | U4: מדד המחירים לצרכן | V4: אחר | W4: מדדים | X4: ILSILS | Y4: לא | Z4: 44718 | AA4: 48715 | AB4: ללא | AC4: No-delivery | AD4: קיים חוזה | AE4: הצד הנגדי | AF4: ללא | AG4: ללא | AI4: 1 | AM4: IDBLILITXXX | AN4: -0.012785722 | AO4: -1.1749701e-05
A5: 274 | B5: 274 | C5: Funded Swap | D5: 31010411 | E5: ILS | F5: 1 | G5: 1082000 | H5: 1404.6142 | I5: 0.052285099 | J5: 0.00034126204 | K5: 310104110 | L5: ILS | M5: 1 | N5: -1082000 | O5: -1376.965 | P5: -0.00033454445 | Q5: 0.23888985 | R5: 27.64921 | S5: ישראל | T5: ישראל | U5: מדד המחירים לצרכן | V5: אחר | W5: מדדים | X5: ILSILS | Y5: לא | Z5: 45628 | AA5: 49023 | AB5: ללא | AC5: No-delivery | AD5: קיים חוזה | AE5: הצד הנגדי | AF5: ללא | AG5: ללא | AI5: 1 | AM5: LEUMIILILTXXX | AN5: 0.0073099108 | AO5: 6.7175925e-06
A6: 274 | B6: 274 | C6: Funded Swap | D6: 31011190 | E6: ILS | F6: 1 | G6: 900000 | H6: 1134.4779 | I6: 0.042229597 | J6: 0.00027563032 | K6: 310111900 | L6: ILS | M6: 1 | N6: -900000 | O6: -1165.635 | P6: -0.00028320017 | Q6: 0.20222618 | R6: -31.15706 | S6: ישראל | T6: ישראל | U6: מדד המחירים לצרכן | V6: אחר | W6: מדדים | X6: ILSILS | Y6: לא | Z6: 44648 | AA6: 48652 | AB6: ללא | AC6: No-delivery | AD6: קיים חוזה | AE6: הצד הנגדי | AF6: ללא | AG6: ללא | AI6: 1 | AM6: IDBLILITXXX | AN6: -0.0082373178 | AO6: -7.5698522e-06
A7: 274 | B7: 274 | C7: Funded Forward | D7: 76020204 | E7: USD | F7: 3.372 | G7: -1500000 | H7: -1500 | I7: -0.055835722 | J7: -0.0012288808 | K7: 760202040 | L7: ILS | M7: 1 | N7: 1500000 | O7: 5366.7739 | P7: 0.0013038998 | Q7: -0.93108238 | R7: 308.77394 | S7: ישראל | T7: ישראל | U7: מט"ח | V7: אחר | W7: מט"ח/₪ | X7: USDILS | Y7: לא | Z7: 45490 | AA7: 45855 | AB7: ללא | AC7: Delivery | AD7: קיים חוזה | AE7: הצד הנגדי | AF7: ללא | AG7: ללא | AI7: 3.627 | AM7: LEUMIILILTXXX | AN7: 0.081633796 | AO7: 7.5019051e-05
A8: 274 | B8: 274 | C8: Funded Forward | D8: 76020460 | E8: USD | F8: 3.372 | G8: -1100000 | H8: -1100 | I8: -0.040946196 | J8: -0.00090117924 | K8: 760204600 | L8: ILS | M8: 1 | N8: 1100000 | O8: 4111.0306 | P8: 0.00099880715 | Q8: -0.71322329 | R8: 401.83064 | S8: ישראל | T8: ישראל | U8: מט"ח | V8: אחר | W8: מט"ח/₪ | X8: USDILS | Y8: לא | Z8: 45553 | AA8: 45951 | AB8: ללא | AC8: Delivery | AD8: קיים חוזה | AE8: הצד הנגדי | AF8: ללא | AG8: ללא | AI8: 3.773 | AM8: POALIILIT | AN8: 0.10623617 | AO8: 9.7627907e-05
A9: 274 | B9: 274 | C9: Funded Forward | D9: 76021292 | E9: USD | F9: 3.372 | G9: -2000000 | H9: -2000 | I9: -0.07444763 | J9: -0.0016385077 | K9: 760212920 | L9: ILS | M9: 1 | N9: 2000000 | O9: 7237.1098 | P9: 0.0017583126 | Q9: -1.2555672 | R9: 493.10985 | S9: ישראל | T9: ישראל | U9: מט"ח | V9: אחר | W9: מט"ח/₪ | X9: USDILS | Y9: לא | Z9: 45775 | AA9: 45867 | AB9: ללא | AC9: Delivery | AD9: קיים חוזה | AE9: הצד הנגדי | AF9: ללא | AG9: ללא | AI9: 3.631 | AM9: POALIILIT | AN9: 0.13036861 | AO9: 0.00011980491
A10: 274 | B10: 274 | C10: Funded Swap | D10: 31011197 | E10: ILS | F10: 1 | G10: 1200000 | H10: -1472.2803 | I10: -0.05480389 | J10: -0.00035770205 | K10: 310111970 | L10: ILS | M10: 1 | N10: -1200000 | O10: 1491.7299 | P10: 0.00036242749 | Q10: -0.25880044 | R10: 19.44962 | S10: ישראל | T10: ישראל | U10: מדד המחירים לצרכן | V10: אחר | W10: מדדים | X10: ILSILS | Y10: לא | Z10: 45768 | AA10: 49420 | AB10: ללא | AC10: No-delivery | AD10: קיים חוזה | AE10: הצד הנגדי | AF10: ללא | AG10: ללא | AI10: 1 | AM10: LEUMIILILTXXX | AN10: 0.0051420995 | AO10: 4.7254378e-06
A11: 274 | B11: 274 | C11: Funded Forward | D11: 76020524 | E11: USD | F11: 3.372 | G11: -631010 | H11: -631.01 | I11: -0.023488599 | J11: -0.00051695738 | K11: 760205240 | L11: ILS | M11: 1 | N11: 631010 | O11: 2338.7882 | P11: 0.00056822695 | Q11: -0.40575671 | R11: 211.02252 | S11: ישראל | T11: ישראל | U11: מט"ח | V11: אחר | W11: מט"ח/₪ | X11: USDILS | Y11: לא | Z11: 45560 | AA11: 45973 | AB11: ללא | AC11: Delivery | AD11: קיים חוזה | AE11: הצד הנגדי | AF11: ללא | AG11: ללא | AI11: 3.758 | AM11: LEUMIILILTXXX | AN11: 0.055790231 | AO11: 5.1269577e-05
A12: 274 | B12: 274 | C12: Funded Forward | D12: 76021332 | E12: USD | F12: 3.372 | G12: 1000000 | H12: 1000 | I12: 0.037223815 | J12: 0.00081925386 | K12: 760213320 | L12: ILS | M12: 1 | N12: -1000000 | O12: -3569.6104 | P12: -0.00086726486 | Q12: 0.61929222 | R12: -197.61041 | S12: ישראל | T12: ישראל | U12: מט"ח | V12: אחר | W12: מט"ח/₪ | X12: USDILS | Y12: לא | Z12: 45790 | AA12: 45848 | AB12: ללא | AC12: Delivery | AD12: קיים חוזה | AE12: הצד הנגדי | AF12: ללא | AG12: ללא | AI12: 3.576 | AM12: POALIILIT | AN12: -0.052244331 | AO12: -4.8011e-05
A13: 274 | B13: 274 | C13: Funded Forward | D13: 76020356 | E13: USD | F13: 3.372 | G13: -1264000 | H13: -1264 | I13: -0.047050902 | J13: -0.0010355369 | K13: 760203560 | L13: ILS | M13: 1 | N13: 1264000 | O13: 4644.5417 | P13: 0.0011284279 | Q13: -0.80578221 | R13: 382.33375 | S13: ישראל | T13: ישראל | U13: מט"ח | V13: אחר | W13: מט"ח/₪ | X13: USDILS | Y13: לא | Z13: 45525 | AA13: 45894 | AB13: ללא | AC13: Delivery | AD13: קיים חוזה | AE13: הצד הנגדי | AF13: ללא | AG13: ללא | AI13: 3.722 | AM13: LEUMIILILTXXX | AN13: 0.10108157 | AO13: 9.2890984e-05
... A27: 274 | B27: 274 | C27: Funded Swap | D27: 31028202 | E27: USD | F27: 3.372 | G27: -359000 | H27: -348.78494 | I27: -0.012983106 | J27: -0.00028574341 | K27: 31028201 | L27: ILS | M27: 1 | N27: 1284502 | O27: 1261.4956 | P27: 0.00030649026 | Q27: -0.21885705 | R27: 85.39278 | S27: חו"ל | T27: ארה"ב | U27: מט"ח | V27: אחר | W27: מט"ח/₪ | X27: USDILS | Y27: לא | Z27: 43924 | AA27: 47667 | AB27: ללא | AC27: No-delivery | AD27: קיים חוזה | AE27: הצד הנגדי | AF27: ללא | AG27: ללא | AI27: 3.636 | AM27: POALIILIT | AN27: 0.022576182 | AO27: 2.0746846e-05

Sheet הלוואות
A1: מספר קופה/קרן/ח.פ. עבור חברת ביטוח | B1: מספר מסלול | C1: מספר מזהה לווה | D1: סוג מספר מזהה לווה | E1: שם הלוואה | F1: מספר הלוואה | G1: מאפיין עיקרי | H1: מאפיין הלוואות מתואמות עבור זכויות מקרקעין | I1: ישראל/חו"ל | J1: מדינה לפי חשיפה כלכלית | K1: ענף מסחר | L1: בעל עניין/צד קשור | M1: קונסורציום/ סינדיקציה | N1: מספר קונסורציום/ סינדיקציה | O1: תאריך העמדת הלוואה | P1: דירוג | Q1: שם מדרג | R1: דירוג הלוואה/המנפיק | S1: מטבע פעילות | T1: מח"מ | U1: סוג הריבית | V1: שיעור ריבית | W1: סוג הצמדה | X1: ריבית עוגן | Y1: שיעור תוספת/הפחתה לריבית העוגן | Z1: תשואה לפדיון | AA1: מועד פדיון | AB1: נחיתות חוזית | AC1: סוג בטוחה | AD1: שווי הבטוחות העומדות כנגד ההלוואה | AE1: שיעור הבטוחות מהחוב | AF1: מועד עדכון אחרון לשווי הבטוחות | AG1: זכות חזרה | AH1: מבנה לוח סילוקין | AI1: יעוד הלוואה | AJ1: זכות פירעון מוקדם | AK1: סוג גורם משערך | AL1: שם גורם משערך | AM1: תלות/אי-תלות המשערך | AN1: תאריך שערוך אחרון | AO1: תאריך אחרון בו נבחנה בפועל ירידת ערך | AP1: שיעור ריבית בגין אי-ניצול מסגרת האשראי | AQ1: ערך נקוב | AR1: שער הלוואה | AS1: שער חליפין | AT1: שווי הוגן (באלפי ש"ח) | AU1: שווי הוגן (במטבע הפעילות) | AV1: עלות מופחתת (באלפי ש"ח) | AW1: עלות מופחתת (במטבע הפעילות) | AX1: האם סווג כחוב בעייתי | AY1: השיטה שיושמה בדוח הכספי | AZ1: שיעור מנכסי אפיק ההשקעה | BA1: שיעור מסך נכסי ההשקעה
A2: 274 | B2: 274 | F2: 24554 | G2: תאגיד | H2: תשתיות - שלב הקמה | I2: ישראל | K2: תשתיות | L2: לא | M2: כן | O2: 40570 | P2: ilAA- | Q2: S&P מעלות | R2: הלוואה | S2: ILS | T2: 3.07 | U2: קבועה | V2: 0.055 | Z2: 0.0297 | AA2: 47986 | AB2: החוב לא נחות | AJ2: כן | AK2: חברת ציטוט | AM2: אי-תלות | AN2: 45838 | AQ2: 1084485.8 | AR2: 132.28 | AS2: 1 | AT2: 1434.5578 | AU2: 1434.5578 | AZ2: 0.078226 | BA2: 0.000348
A3: 274 | B3: 274 | F3: 8070146 | G3: תאגיד | H3: תשתיות - שלב הקמה | I3: ישראל | K3: תשתיות | L3: לא | M3: כן | O3: 38258 | P3: Aa1.il | Q3: מידרוג Moodys | R3: הלוואה | S3: ILS | T3: 1.23 | U3: קבועה | V3: 0.051695 | Z3: 0.026 | AA3: 46568 | AB3: החוב לא נחות | AJ3: כן | AK3: חברת ציטוט | AM3: אי-תלות | AN3: 45838 | AQ3: 99659.73 | AR3: 147.73 | AS3: 1 | AT3: 147.22732 | AU3: 147.22732 | AZ3: 0.008028 | BA3: 3.5e-05
A4: 274 | B4: 274 | F4: 63883 | G4: תאגיד | H4: תשתיות - שלב הקמה | I4: ישראל | K4: בנייה | L4: לא | M4: כן | O4: 42942 | P4: ilAA+ | Q4: S&P מעלות | R4: הלוואה | S4: ILS | T4: 5.47 | U4: קבועה | V4: 0.0341 | Z4: 0.0307 | AA4: 50040 | AB4: החוב לא נחות | AJ4: כן | AK4: חברת ציטוט | AM4: אי-תלות | AN4: 45838 | AQ4: 3271795.1 | AR4: 120.26 | AS4: 1 | AT4: 3934.6608 | AU4: 3934.6608 | AZ4: 0.214557 | BA4: 0.000955
A5: 274 | B5: 274 | F5: 8070153 | G5: תאגיד | H5: תשתיות - שלב הקמה | I5: ישראל | K5: תשתיות | L5: לא | M5: כן | O5: 38258 | P5: Aa1.il | Q5: מידרוג Moodys | R5: הלוואה | S5: ILS | T5: 1.23 | U5: קבועה | V5: 0.051695 | Z5: 0.026 | AA5: 46568 | AB5: החוב לא נחות | AJ5: כן | AK5: חברת ציטוט | AM5: אי-תלות | AN5: 45838 | AQ5: 87808.06 | AR5: 147.28 | AS5: 1 | AT5: 129.32371 | AU5: 129.32371 | AZ5: 0.007052 | BA5: 3.1e-05
A6: 274 | B6: 274 | F6: 63289 | G6: תאגיד | H6: תשתיות - שלב הקמה | I6: ישראל | K6: בנייה | L6: לא | M6: כן | O6: 43067 | P6: ilAA+ | Q6: S&P מעלות | R6: הלוואה | S6: ILS | T6: 5.44 | U6: קבועה | V6: 0.0331 | Z6: 0.0335 | AA6: 50040 | AB6: החוב לא נחות | AJ6: כן | AK6: חברת ציטוט | AM6: אי-תלות | AN6: 45838 | AQ6: 134064.6 | AR6: 117.75 | AS6: 1 | AT6: 157.86107 | AU6: 157.86107 | AZ6: 0.008608 | BA6: 3.8e-05
A7: 274 | B7: 274 | F7: 8070161 | G7: תאגיד | H7: תשתיות - שלב הקמה | I7: ישראל | K7: תשתיות | L7: לא | M7: כן | O7: 38258 | P7: Aa1.il | Q7: מידרוג Moodys | R7: הלוואה | S7: ILS | T7: 1.23 | U7: קבועה | V7: 0.051695 | Z7: 0.0261 | AA7: 46568 | AB7: החוב לא נחות | AJ7: כן | AK7: חברת ציטוט | AM7: אי-תלות | AN7: 45838 | AQ7: 91035.26 | AR7: 148 | AS7: 1 | AT7: 134.73218 | AU7: 134.73218 | AZ7: 0.007346 | BA7: 3.2e-05
A8: 274 | B8: 274 | F8: 6205 | G8: תאגיד | H8: תשתיות - שלב הקמה | I8: ישראל | K8: תשתיות | L8: לא | M8: כן | O8: 39922 | P8: ilAA | Q8: S&P מעלות | R8: הלוואה | S8: ILS | T8: 2.61 | U8: קבועה | V8: 0.0427 | Z8: 0.0433 | AA8: 47762 | AB8: החוב לא נחות | AJ8: כן | AK8: חברת ציטוט | AM8: אי-תלות | AN8: 45838 | AQ8: 2613946.4 | AR8: 135.8 | AS8: 1 | AT8: 3549.7392 | AU8: 3549.7392 | AZ8: 0.193567 | BA8: 0.000862
A9: 274 | B9: 274 | F9: 8070179 | G9: תאגיד | H9: תשתיות - שלב הקמה | I9: ישראל | K9: תשתיות | L9: לא | M9: כן | O9: 38258 | P9: Aa1.il | Q9: מידרוג Moodys | R9: הלוואה | S9: ILS | T9: 1.23 | U9: קבועה | V9: 0.051695 | Z9: 0.026 | AA9: 46568 | AB9: החוב לא נחות | AJ9: כן | AK9: חברת ציטוט | AM9: אי-תלות | AN9: 45838 | AQ9: 64576.72 | AR9: 149.63 | AS9: 1 | AT9: 96.62615 | AU9: 96.62615 | AZ9: 0.005269 | BA9: 2.3e-05
A10: 274 | B10: 274 | F10: 6189 | G10: תאגיד | H10: תשתיות - שלב הקמה | I10: ישראל | K10: תשתיות | L10: לא | M10: כן | O10: 39261 | P10: Aa2.il | Q10: מידרוג Moodys | R10: הלוואה | S10: ILS | T10: 1.24 | U10: קבועה | V10: 0.04704 | Z10: 0.0355 | AA10: 46568 | AB10: החוב לא נחות | AJ10: כן | AK10: חברת ציטוט | AM10: אי-תלות | AN10: 45838 | AQ10: 119490.2 | AR10: 143.05 | AS10: 1 | AT10: 170.93073 | AU10: 170.93073 | AZ10: 0.00932 | BA10: 4.1e-05
A11: 274 | B11: 274 | F11: 8070187 | G11: תאגיד | H11: תשתיות - שלב הקמה | I11: ישראל | K11: תשתיות | L11: לא | M11: כן | O11: 38258 | P11: Aa1.il | Q11: מידרוג Moodys | R11: הלוואה | S11: ILS | T11: 1.23 | U11: קבועה | V11: 0.051695 | Z11: 0.026 | AA11: 46568 | AB11: החוב לא נחות | AJ11: כן | AK11: חברת ציטוט | AM11: אי-תלות | AN11: 45838 | AQ11: 38917.86 | AR11: 150.68 | AS11: 1 | AT11: 58.64143 | AU11: 58.64143 | AZ11: 0.003197 | BA11: 1.4e-05
A12: 274 | B12: 274 | F12: 54130 | G12: תאגיד | H12: תשתיות - שלב הקמה | I12: ישראל | K12: תשתיות | L12: לא | M12: כן | O12: 42054 | P12: ilAA- | Q12: S&P מעלות | R12: הלוואה | S12: ILS | T12: 3.07 | U12: קבועה | V12: 0.055 | Z12: 0.0298 | AA12: 47986 | AB12: החוב לא נחות | AJ12: כן | AK12: חברת ציטוט | AM12: אי-תלות | AN12: 45838 | AQ12: 175216.08 | AR12: 126.46 | AS12: 1 | AT12: 221.57825 | AU12: 221.57825 | AZ12: 0.012082 | BA12: 5.3e-05
A13: 274 | B13: 274 | F13: 8070195 | G13: תאגיד | H13: תשתיות - שלב הקמה | I13: ישראל | K13: תשתיות | L13: לא | M13: כן | O13: 38258 | P13: Aa1.il | Q13: מידרוג Moodys | R13: הלוואה | S13: ILS | T13: 1.23 | U13: קבועה | V13: 0.051695 | Z13: 0.026 | AA13: 46568 | AB13: החוב לא נחות | AJ13: כן | AK13: חברת ציטוט | AM13: אי-תלות | AN13: 45838 | AQ13: 39133.79 | AR13: 151.14 | AS13: 1 | AT13: 59.14681 | AU13: 59.14681 | AZ13: 0.003225 | BA13: 1.4e-05
... A75: 274 | B75: 274 | F75: 8070138 | G75: תאגיד | H75: תשתיות - שלב הקמה | I75: ישראל | K75: תשתיות | L75: לא | M75: כן | O75: 38258 | P75: Aa1.il | Q75: מידרוג Moodys | R75: הלוואה | S75: ILS | T75: 1.23 | U75: קבועה | V75: 0.051695 | Z75: 0.026 | AA75: 46568 | AB75: החוב לא נחות | AJ75: כן | AK75: חברת ציטוט | AM75: אי-תלות | AN75: 45838 | AQ75: 103491.18 | AR75: 148 | AS75: 1 | AT75: 153.16695 | AU75: 153.16695 | AZ75: 0.008352 | BA75: 3.7e-05

Sheet לא סחיר מוצרים מובנים
A1: מספר קופה/קרן/ח.פ. עבור חברת ביטוח | B1: מספר מסלול | C1: שם מנפיק | D1: מספר מנפיק | E1: סוג מספר מזהה מנפיק | F1: שם נייר ערך | G1: מספר נייר ערך | H1: סוג מספר נייר ערך | I1: מאפיין עיקרי | J1: ישראל/חו"ל | K1: מדינה לפי חשיפה כלכלית | L1: בעל עניין/צד קשור | M1: נכס בסיס | N1: תאריך רכישה | O1: דירוג | P1: שם מדרג | Q1: דירוג נייר הערך/המנפיק | R1: מטבע פעילות | S1: מח"מ | T1: שיעור ריבית | U1: תשואה לפדיון | V1: סוג גורם משערך | W1: תלות/אי-תלות המשערך | X1: תאריך שערוך אחרון | Y1: ערך נקוב (יחידות) | Z1: שער חליפין | AA1: שער נייר הערך | AB1: שווי הוגן (באלפי ש"ח) | AC1: שיעור מנכסי אפיק ההשקעה | AD1: שיעור מסך נכסי ההשקעה
A2: 274 | B2: 274

Sheet פיקדונות מעל 3 חודשים
A1: מספר קופה/קרן/ח.פ. עבור חברת ביטוח | B1: מספר מסלול | C1: שם הבנק | D1: מספר מזהה בנק | E1: סוג מספר מזהה בנק | F1: מאפיין עיקרי | G1: תאריך פקיעת פיקדון | H1: ישראל/חו"ל | I1: מדינה לפי חשיפה כלכלית | J1: בעל עניין/צד קשור | K1: דירוג הבנק | L1: שם מדרג | M1: מטבע פעילות | N1: מח"מ | O1: שיעור ריבית | P1: תשואה לפדיון | Q1: שווי מטבעי | R1: שער חליפין | S1: שער פיקדון | T1: שווי הוגן (באלפי ש"ח) | U1: שיעור מנכסי אפיק ההשקעה | V1: שיעור מסך נכסי ההשקעה
A2: 274 | B2: 274 | C2: בנק הפועלים | D2: 12-600 | E2: סימול בנק | F2: בטחונות לא שוטפים | H2: ישראל | I2: בריטניה | J2: לא | K2: Baa1 | L2: Moodys | M2: USD | P2: 0 | Q2: -0.00302 | R2: 3.372 | S2: 100 | T2: -0.01018 | U2: 0 | V2: 0
A3: 274 | B3: 274 | C3: בנק הפועלים | D3: 12-600 | E3: סימול בנק | F3: בטחונות לא שוטפים | H3: ישראל | I3: בריטניה | J3: לא | K3: BBB+ | L3: S&P | M3: USD | P3: 0 | Q3: -270 | R3: 3.372 | S3: 100 | T3: -910.44 | U3: -0.032661 | V3: -0.000221
A4: 274 | B4: 274 | C4: בנק מזרחי | D4: 20-21 | E4: סימול בנק | F4: לא צמוד למדד המחירים לצרכן | G4: 45965 | H4: ישראל | I4: ישראל | J4: לא | K4: Aaa.il | L4: מידרוג Moodys | M4: ILS | N4: 0.35 | P4: 0.0459 | Q4: 12370.8 | R4: 1 | S4: 103.09 | T4: 12370.8 | U4: 0.4438 | V4: 0.003005
A5: 274 | B5: 274 | C5: בנק מזרחי | D5: 20-21 | E5: סימול בנק | F5: צמוד למדד המחירים לצרכן | G5: 50895 | H5: ישראל | I5: ישראל | J5: לא | K5: Aaa.il | L5: מידרוג Moodys | M5: ILS | N5: 13.86 | P5: 0.0284 | Q5: 2844.7684 | R5: 1 | S5: 106.26 | T5: 2844.7684 | U5: 0.102055 | V5: 0.000691
A6: 274 | B6: 274 | C6: בנק דיסקונט | D6: 11-10 | E6: סימול בנק | F6: לא צמוד למדד המחירים לצרכן | G6: 45991 | H6: ישראל | I6: ישראל | J6: לא | K6: Aaa.il | L6: מידרוג Moodys | M6: ILS | N6: 0.42 | P6: 0.0455 | Q6: 13569.6 | R6: 1 | S6: 102.8 | T6: 13569.6 | U6: 0.486806 | V6: 0.003296

Sheet זכויות מקרקעין
A1: מספר קופה/קרן/ח.פ. עבור חברת ביטוח | B1: מספר מסלול | C1: שם הנכס | D1: מאפיין עיקרי | E1: מדינת מיקום נדל"ן | F1: בעל עניין/צד קשור | G1: תאריך רכישה | H1: שימוש עיקרי בנכס | I1: מחזור חיי הנכס | J1: כתובת הנכס | K1: שיעור תשואה בפועל במהלך הרבעון | L1: השיטה שבאמצעותה נקבע שווי הנכס | M1: סוג גורם משערך | N1: שם גורם משערך | O1: תלות/אי-תלות המשערך | P1: תאריך שערוך אחרון | Q1: מטבע פעילות | R1: שווי הוגן (במטבע הפעילות) | S1: שווי הוגן (באלפי ש"ח) | T1: עלות מופחתת (באלפי ש"ח) | U1: עלות מופחתת (במטבע הפעילות) | V1: השיטה שיושמה בדוח הכספי | W1: שיעור מנכסי אפיק ההשקעה | X1: שיעור מסך נכסי ההשקעה
A2: 274 | B2: 274

Sheet השקעה בחברות מוחזקות
A1: מספר קופה/קרן/ח.פ. עבור חברת ביטוח | B1: מספר מסלול | C1: שם מנפיק | D1: מספר מנפיק | E1: סוג מספר מזהה מנפיק | F1: שם נייר ערך | G1: מספר נייר ערך | H1: סוג מספר נייר ערך | I1: מאפיין עיקרי | J1: ישראל/חו"ל | K1: מדינה לפי חשיפה כלכלית | L1: ענף מסחר | M1: בעל עניין/צד קשור | N1: מטבע פעילות | O1: סוג גורם משערך | P1: תלות/אי-תלות המשערך | Q1: תאריך שערוך אחרון | R1: תאריך אחרון בו נבחנה בפועל ירידת ערך | S1: שיעור אחזקה באמצעי שליטה | T1: שווי מאזני (באלפי ש"ח) | U1: שווי הוגן (באלפי ש"ח) | V1: שיעור מנכסי אפיק ההשקעה | W1: שיעור מסך נכסי ההשקעה
A2: 274 | B2: 274

Sheet נכסים אחרים
A1: מספר קופה/קרן/ח.פ. עבור חברת ביטוח | B1: מספר מסלול | C1: שם הנכס האחר | D1: מספר הנכס האחר | E1: מאפיין עיקרי | F1: ישראל/חו"ל | G1: מדינה לפי חשיפה כלכלית | H1: בעל עניין/צד קשור | I1: תאריך עסקה | J1: מטבע פעילות | K1: תאריך שערוך אחרון | L1: שווי מטבעי | M1: שער חליפין | N1: שווי הוגן (באלפי ש"ח) | O1: עלות מופחתת (באלפי ש"ח) | P1: השיטה שיושמה בדוח הכספי | Q1: שיעור מנכסי אפיק ההשקעה | R1: שיעור מסך נכסי ההשקעה
A2: 274 | B2: 274 | C2: הדסה ס.מ.ישיר 31.03.25 | D2: 7893866 | E2: סיוע ממשלתי | F2: ישראל | G2: ישראל | H2: לא | I2: 37668 | J2: ILS | K2: 45838 | L2: 2024580.7 | M2: 1 | N2: 2024580.7 | Q2: 0.96336 | R2: 0.491887
A3: 274 | B3: 274 | C3: התח.ממש.אי העלאת ג.פרישה נשים | D3: 7900000 | E3: התחייבות הממשלה בגין אי העלאת גיל הפרישה לנשים | F3: ישראל | G3: ישראל | H3: לא | I3: 39658 | J3: ILS | K3: 45838 | L3: 77000 | M3: 1 | N3: 77000 | Q3: 0.036639 | R3: 0.018707

Sheet מסגרות אשראי
A1: מספר קופה/קרן/ח.פ. עבור חברת ביטוח | B1: מספר מסלול | C1: מספר מזהה לווה | D1: סוג מספר מזהה לווה | E1: שם הלוואה | F1: מספר הלוואה | G1: תאריך העמדת מסגרת אשראי | H1: ישראל/חו"ל | I1: מדינה לפי חשיפה כלכלית | J1: בעל עניין/צד קשור | K1: דירוג | L1: שם מדרג | M1: דירוג הלוואה/המנפיק | N1: מטבע פעילות | O1: שער חליפין | P1: שיעור ריבית | Q1: סוג הריבית | R1: סכום מסגרת האשראי הראשוני (במטבע הפעילות) | S1: סכום מסגרת האשראי הראשוני (באלפי ש"ח) | T1: שיעור יתרת מסגרת אשראי
A2: 274 | B2: 274 | F2: 71000300 | G2: 44858 | H2: ישראל | J2: לא | K2: Aa3.il | L2: מידרוג Moodys | M2: מנפיק | N2: ILS | O2: 1 | P2: 0.009 | Q2: קבועה | R2: 9.419466 | S2: 9.419466 | T2: 1
A3: 274 | B3: 274 | F3: 71000301 | G3: 44858 | H3: ישראל | J3: לא | K3: Aa3.il | L3: מידרוג Moodys | M3: מנפיק | N3: ILS | O3: 1 | P3: 0.009 | Q3: קבועה | R3: 10.149398 | S3: 10.149398 | T3: 1
A4: 274 | B4: 274 | F4: 71000302 | G4: 44858 | H4: ישראל | J4: לא | K4: Aa3.il | L4: מידרוג Moodys | M4: מנפיק | N4: ILS | O4: 1 | P4: 0.009 | Q4: קבועה | R4: 11.740204 | S4: 11.740204 | T4: 1
A5: 274 | B5: 274 | F5: 71000303 | G5: 44858 | H5: ישראל | J5: לא | K5: Aa3.il | L5: מידרוג Moodys | M5: מנפיק | N5: ILS | O5: 1 | P5: 0.009 | Q5: קבועה | R5: 8.62267 | S5: 8.62267 | T5: 1
A6: 274 | B6: 274 | F6: 71000304 | G6: 44858 | H6: ישראל | J6: לא | K6: Aa3.il | L6: מידרוג Moodys | M6: מנפיק | N6: ILS | O6: 1 | P6: 0.009 | Q6: קבועה | R6: 8.631028 | S6: 8.631028 | T6: 1
A7: 274 | B7: 274 | F7: 71000200 | G7: 44858 | H7: ישראל | J7: לא | K7: Aa3.il | L7: מידרוג Moodys | M7: מנפיק | N7: ILS | O7: 1 | P7: 0.009 | Q7: קבועה | R7: 3.596726 | S7: 3.596726 | T7: 1
A8: 274 | B8: 274 | F8: 71000201 | G8: 44858 | H8: ישראל | J8: לא | K8: Aa3.il | L8: מידרוג Moodys | M8: מנפיק | N8: ILS | O8: 1 | P8: 0.009 | Q8: קבועה | R8: 3.290266 | S8: 3.290266 | T8: 1
A9: 274 | B9: 274 | F9: 71000202 | G9: 44858 | H9: ישראל | J9: לא | K9: Aa3.il | L9: מידרוג Moodys | M9: מנפיק | N9: ILS | O9: 1 | P9: 0.009 | Q9: קבועה | R9: 4.52725 | S9: 4.52725 | T9: 1
A10: 274 | B10: 274 | F10: 71000203 | G10: 44858 | H10: ישראל | J10: לא | K10: Aa3.il | L10: מידרוג Moodys | M10: מנפיק | N10: ILS | O10: 1 | P10: 0.009 | Q10: קבועה | R10: 2.518544 | S10: 2.518544 | T10: 1
A11: 274 | B11: 274 | F11: 71000204 | G11: 44858 | H11: ישראל | J11: לא | K11: Aa3.il | L11: מידרוג Moodys | M11: מנפיק | N11: ILS | O11: 1 | P11: 0.009 | Q11: קבועה | R11: 2.822218 | S11: 2.822218 | T11: 1

Sheet יתרות התחייבות להשקעה
A1: מספר קופה/קרן/ח.פ. עבור חברת ביטוח | B1: מספר מסלול | C1: מאפיין עיקרי | D1: שם שותף כללי קרן השקעות | E1: מספר מזהה שותף כללי קרן השקעות | F1: סוג מספר מזהה שותף כללי קרן השקעות | G1: שם קרן השקעה | H1: מספר מזהה קרן השקעה | I1: סוג מספר מזהה קרן השקעות | J1: מטבע פעילות | K1: תאריך העמדת התחייבות לקרן השקעה | L1: סכום המחויבות הראשוני (במטבע הדיווח של קרן ההשקעה) | M1: סכום המחויבות הראשוני (באלפי ש"ח) | N1: יתרת המחויבות לתקופת הדיווח (במטבע הדיווח של קרן ההשקעה) | O1: יתרת המחויבות לתקופת הדיווח (באלפי ש"ח) | P1: שיעור יתרת המחויבות | Q1: תאריך פקיעת מחויבות להשקעה
A2: 274 | B2: 274

Sheet אפשרויות בחירה
A1: שם גיליון (רלוונטי לגיליונות עם עמודה "מאפיין עיקרי") | B1: שם עמודה | C1: אפשרות בחירה | D1: הערות והסברים
B2: ישראל/חו"ל | C2: ישראל
C3: חו"ל
B4: מדינה לפי חשיפה כלכלית; מדינת התאגדות קרן השקעה, מיקום משרד השותף הכללי, מדינת מיקום נדל"ן | C4: ישראל
C5: אוסטריה
C6: אוסטרליה
C7: אזור תעלת פנמה
C8: אזרביג'אן
C9: איחוד האמירויות הערביות
C10: איטליה
C11: איי הבתולה הבריטיים | E11: נוסף במסגרת עדכון הרשימה
C12: איי הבתולה של ארצות הברית | E12: נוסף במסגרת עדכון הרשימה
C13: איי סיישל
C14: איי קיימן
C15: איי שלמה הבריטיים
C16: איסלנד
C17: אירלנד
C18: אנדורה
C19: אסטוניה
C20: ארגנטינה
C21: ארה"ב
C22: אתיופיה
C23: בהמס
C24: בולגריה
... C35: גרמניה
C36: ג'רזי (Jersey) | E36: נוסף במסגרת עדכון הרשימה
C37: גרנזי (Guernsey) | E37: נוסף במסגרת עדכון הרשימה
C38: דנמרק
C39: דרום אפריקה
C40: דרום קוריאה | E40: נוסף במסגרת עדכון הרשימה
C41: הודו
C42: הולנד
C43: הונג קונג
C44: הונגריה
C45: הונדורס
C46: טייוואן | E46: נוסף במסגרת עדכון הרשימה
C47: יוון
C48: יפן
C49: ירדן
C50: לוכסמבורג
C51: לטביה
C52: ליטא
C53: ליכטנשטיין
C54: מאוריציוס
C55: מולדובה
C56: מונקו
C57: מלדיבים
C58: מלטה
... C62: מרוקו
C63: נורבגיה | E63: נוסף במסגרת עדכון הרשימה
C64: ניו זילנד
C65: סין
C66: סינגפור
C67: סלובניה
C68: סלובקיה
C69: ספרד
C70: סרביה
C71: ערב הסעודית
C72: פולין
C73: פורטוגל
C74: פינלנד
C75: פנמה
... C93: גלובלי
C94: Emerging Markets - Americas | D94: שווקים מתעוררים לפי הגדרת MSCI | E94: נוסף במסגרת עדכון הרשימה
C95: Emerging Markets - Euope, Middle East & Africa | D95: לפי הגדרת MSCI | E95: נוסף במסגרת עדכון הרשימה
C96: Emerging Markets - Asia | D96: לפי הגדרת MSCI | E96: נוסף במסגרת עדכון הרשימה
C97: Developed Markets - Americas | D97: לפי הגדרת MSCI | E97: נוסף במסגרת עדכון הרשימה
C98: Developed Markets - Europe | D98: לפי הגדרת MSCI | E98: נוסף במסגרת עדכון הרשימה
C99: Developed Markets - Pacific | D99: לפי הגדרת MSCI | E99: נוסף במסגרת עדכון הרשימה
C100: Frontier Markets - Euope | D100: לפי הגדרת MSCI | E100: נוסף במסגרת עדכון הרשימה
C101: Frontier Markets - Africa | D101: לפי הגדרת MSCI | E101: נוסף במסגרת עדכון הרשימה
C102: Frontier Markets - Middle East | D102: לפי הגדרת MSCI | E102: נוסף במסגרת עדכון הרשימה
C103: Frontier Markets - Asia | D103: לפי הגדרת MSCI | E103: נוסף במסגרת עדכון הרשימה
B104: סוג מספר מזהה מנפיק | C104: ח.פ.
C105: מספר מנפיק
C106: מספר שותפות
C107: מספר תאגיד או שותפות בחו"ל
C108: פנימי
C109: LEI
C110: אחר
B111: סוג מספר מזהה בנק | C111: ח.פ.
C112: סימול בנק
C113: SWIFT
B114: סוג מספר מזהה מנהל קרן השקעות | C114: ח.פ.
C115: מספר שותפות
C116: מספר תאגיד או שותפות בחו"ל
C117: LEI
B118: סוג מספר מזהה לווה | C118: ח.פ.
C119: מרשם
C120: מספר תאגיד או שותפות בחו"ל
C121: פנימי
C122: מספר שותפות
C123: ת"ז
C124: דרכון
C125: LEI
C126: אחר
B127: סוג מספר נייר ערך | C127: ISIN
C128: OCC
C129: FIGI
C130: טיקר
...

Sheet מיפוי סעיפים
A1: שם גיליון | B1: שם סעיף | C1: מספר סעיף | D1: מידע שניתן לדווח רק לרשות
A2: מזומנים ושווי מזומנים | B2: מספר קופה/קרן/ח.פ. עבור חברת ביטוח | C2: 5.1
A3: מזומנים ושווי מזומנים | B3: מספר מסלול | C3: 5.2
A4: מזומנים ושווי מזומנים | B4: שם הבנק | C4: 5.4
A5: מזומנים ושווי מזומנים | B5: מספר מזהה בנק | C5: 5.7
A6: מזומנים ושווי מזומנים | B6: סוג מספר מזהה בנק | C6: 5.11
A7: מזומנים ושווי מזומנים | B7: מאפיין עיקרי | C7: 5.26
A8: מזומנים ושווי מזומנים | B8: ישראל/חו"ל | C8: 5.27
A9: מזומנים ושווי מזומנים | B9: בעל עניין/צד קשור | C9: 5.36
A10: מזומנים ושווי מזומנים | B10: דירוג הבנק | C10: 5.5
A11: מזומנים ושווי מזומנים | B11: שם מדרג | C11: 5.51
A12: מזומנים ושווי מזומנים | B12: מטבע פעילות | C12: 5.53
A13: מזומנים ושווי מזומנים | B13: שווי מטבעי | C13: 5.59
A14: מזומנים ושווי מזומנים | B14: שער חליפין | C14: 5.54
A15: מזומנים ושווי מזומנים | B15: שיעור ריבית | C15: 5.7 | D15: ü
A16: מזומנים ושווי מזומנים | B16: שווי הוגן (באלפי ש"ח) | C16: 5.63
A17: מזומנים ושווי מזומנים | B17: שיעור מנכסי אפיק ההשקעה | C17: 5.47
A18: מזומנים ושווי מזומנים | B18: שיעור מסך נכסי ההשקעה | C18: 5.48
A19: מזומנים ושווי מזומנים
A20: איגרות חוב ממשלתיות | B20: מספר קופה/קרן/ח.פ. עבור חברת ביטוח | C20: 5.1
A21: איגרות חוב ממשלתיות | B21: מספר מסלול | C21: 5.2
A22: איגרות חוב ממשלתיות | B22: שם מנפיק | C22: 5.3
A23: איגרות חוב ממשלתיות | B23: שם נייר ערך | C23: 5.14
A24: איגרות חוב ממשלתיות | B24: מספר נייר ערך | C24: 5.19
A25: איגרות חוב ממשלתיות | B25: מאפיין עיקרי | C25: 5.26
A26: איגרות חוב ממשלתיות | B26: ישראל/חו"ל | C26: 5.27
A27: איגרות חוב ממשלתיות | B27: מדינה לפי חשיפה כלכלית | C27: 5.28
A28: איגרות חוב ממשלתיות | B28: זירת מסחר | C28: 5.3
A29: איגרות חוב ממשלתיות | B29: דירוג | C29: 5.49
A30: איגרות חוב ממשלתיות | B30: שם מדרג | C30: 5.51
A31: איגרות חוב ממשלתיות | B31: מטבע פעילות | C31: 5.53
... A45: איגרות חוב ממשלתיות | B45: שיעור מסך נכסי ההשקעה | C45: 5.48
A46: איגרות חוב ממשלתיות
A47: ניירות ערך מסחריים | B47: מספר קופה/קרן/ח.פ. עבור חברת ביטוח | C47: 5.1
A48: ניירות ערך מסחריים | B48: מספר מסלול | C48: 5.2
A49: ניירות ערך מסחריים | B49: שם מנפיק | C49: 5.3
A50: ניירות ערך מסחריים | B50: מספר מנפיק | C50: 5.6
A51: ניירות ערך מסחריים | B51: סוג מספר מזהה מנפיק | C51: 5.1
A52: ניירות ערך מסחריים | B52: שם נייר ערך | C52: 5.14
A53: ניירות ערך מסחריים | B53: מספר נייר ערך | C53: 5.19
A54: ניירות ערך מסחריים | B54: סוג מספר נייר ערך | C54: 5.24
A55: ניירות ערך מסחריים | B55: מאפיין עיקרי | C55: 5.26
A56: ניירות ערך מסחריים | B56: ישראל/חו"ל | C56: 5.27
A57: ניירות ערך מסחריים | B57: מדינה לפי חשיפה כלכלית | C57: 5.28
A58: ניירות ערך מסחריים | B58: זירת מסחר | C58: 5.3
... A70: ניירות ערך מסחריים | B70: נחיתות חוזית | C70: 5.76
A71: ניירות ערך מסחריים | B71: האם סווג כחוב בעייתי | C71: 5.89 | D71: ü
A72: ניירות ערך מסחריים | B72: ערך נקוב (יחידות) | C72: 5.58
A73: ניירות ערך מסחריים | B73: סכום לקבל (במטבע הפעילות) | C73: 5.62
A74: ניירות ערך מסחריים | B74: שער חליפין | C74: 5.54
A75: ניירות ערך מסחריים | B75: שער נייר הערך | C75: 5.55
A76: ניירות ערך מסחריים | B76: שווי הוגן (באלפי ש"ח) | C76: 5.63
A77: ניירות ערך מסחריים | B77: עלות מופחתת (באלפי ש"ח) | C77: 5.65
A78: ניירות ערך מסחריים | B78: עלות מופחתת (במטבע הפעילות) | C78: 5.66
A79: ניירות ערך מסחריים | B79: השיטה שיושמה בדוח הכספי | C79: 5.68
A80: ניירות ערך מסחריים | B80: שיעור מערך נקוב מונפק | C80: 5.45
A81: ניירות ערך מסחריים | B81: שיעור מנכסי אפיק ההשקעה | C81: 5.47
A82: ניירות ערך מסחריים | B82: שיעור מסך נכסי ההשקעה | C82: 5.48
A83: ניירות ערך מסחריים
A84: איגרות חוב | B84: מספר קופה/קרן/ח.פ. עבור חברת ביטוח | C84: 5.1
A85: איגרות חוב | B85: מספר מסלול | C85: 5.2
A86: איגרות חוב | B86: שם מנפיק | C86: 5.3
A87: איגרות חוב | B87: מספר מנפיק | C87: 5.6
A88: איגרות חוב | B88: סוג מספר מזהה מנפיק | C88: 5.1
A89: איגרות חוב | B89: שם נייר ערך | C89: 5.14
A90: איגרות חוב | B90: מספר נייר ערך | C90: 5.19
A91: איגרות חוב | B91: סוג מספר נייר ערך | C91: 5.24
A92: איגרות חוב | B92: מאפיין עיקרי | C92: 5.26
A93: איגרות חוב | B93: ישראל/חו"ל | C93: 5.27
A94: איגרות חוב | B94: מדינה לפי חשיפה כלכלית | C94: 5.28
A95: איגרות חוב | B95: סטאטוס סחירות | C95: 5.29
... A107: איגרות חוב | B107: נחיתות חוזית | C107: 5.76
A108: איגרות חוב | B108: האם סווג כחוב בעייתי | C108: 5.89 | D108: ü
A109: איגרות חוב | B109: ערך נקוב (יחידות) | C109: 5.58
A110: איגרות חוב | B110: סכום לקבל (במטבע הפעילות) | C110: 5.62
A111: איגרות חוב | B111: שער חליפין | C111: 5.54
A112: איגרות חוב | B112: שער נייר הערך | C112: 5.55
A113: איגרות חוב | B113: עלות מופחתת (באלפי ש"ח) | C113: 5.65
A114: איגרות חוב | B114: עלות מופחתת (במטבע הפעילות) | C114: 5.66
A115: איגרות חוב | B115: השיטה שיושמה בדוח הכספי | C115: 5.68
A116: איגרות חוב | B116: שיעור מערך נקוב מונפק | C116: 5.45
A117: איגרות חוב | B117: שיעור מנכסי אפיק ההשקעה | C117: 5.47
A118: איגרות חוב | B118: שיעור מסך נכסי ההשקעה | C118: 5.48
A119: איגרות חוב
A120: מניות, מב"כ ויה"ש | B120: מספר קופה/קרן/ח.פ. עבור חברת ביטוח | C120: 5.1
A121: מניות, מב"כ ויה"ש | B121: מספר מסלול | C121: 5.2
A122: מניות, מב"כ ויה"ש | B122: שם מנפיק | C122: 5.3
A123: מניות, מב"כ ויה"ש | B123: מספר מנפיק | C123: 5.6
A124: מניות, מב"כ ויה"ש | B124: סוג מספר מזהה מנפיק | C124: 5.1
A125: מניות, מב"כ ויה"ש | B125: שם נייר ערך | C125: 5.14
A126: מניות, מב"כ ויה"ש | B126: מספר נייר ערך | C126: 5.19
A127: מניות, מב"כ ויה"ש | B127: סוג מספר נייר ערך | C127: 5.24
A128: מניות, מב"כ ויה"ש | B128: מאפיין עיקרי | C128: 5.26
A129: מניות, מב"כ ויה"ש | B129: ישראל/חו"ל | C129: 5.27
A130: מניות, מב"כ ויה"ש | B130: מדינה לפי חשיפה כלכלית | C130: 5.28
A131: מניות, מב"כ ויה"ש | B131: סטאטוס סחירות | C131: 5.29
... A143: מניות, מב"כ ויה"ש | B143: שיעור מסך נכסי ההשקעה | C143: 5.48
A144: מניות, מב"כ ויה"ש
A145: קרנות סל | B145: מספר קופה/קרן/ח.פ. עבור חברת ביטוח | C145: 5.1
A146: קרנות סל | B146: מספר מסלול | C146: 5.2
...

Sheet File Name Info
A2: סוג קובץ
A3: נכסי מבוטחים - חברת ביטוח | B3: in
A4: נכסי עמיתים - קופות גמל | B4: gm
A5: נכסי עמיתים - קרנות פנסיה | B5: pn
A6: נכסי אפיק השקעה מובטח תשואה | B6: ca
A7: נכסי נוסטרו - חברת ביטוח | B7: ni
A8: נכסי נוסטרו - חברה מנהלת | B8: nf
A10: יעוד הקובץ
A11: לממונה
A12: לציבור | B12: p
A15: רבעון
A16: 01
A17: 02
A18: 03
A19: 04
A21: שנה
A22: 2022 | B22: 22
A23: 2023 | B23: 23
A24: 2024 | B24: 24
A25: 2025 | B25: 25
A26: 2026 | B26: 26
A27: 2027 | B27: 27
A28: 2028 | B28: 28
A29: 2029 | B29: 29
A30: 2030 | B30: 30
A31: 2031 | B31: 31
A34: שם גוף מוסדי | B34: ח.פ.
A35: הפניקס חברה לביטוח בע"מ | B35: 520023185
A36: כלל חברה לביטוח בע"מ | B36: 520024647
A37: מגדל חברה לביטוח בע"מ | B37: 520004896
A38: מנורה מבטחים ביטוח בע"מ | B38: 520042540
A39: אשרא החברה הישראלית לביטוח סיכוני סחר חוץ בע"מ | B39: 520021916
A40: שומרה חברה לביטוח בע"מ | B40: 510015951
A41: כלל ביטוח אשראי בע"מ | B41: 510888985
A42: הכשרה חברה לביטוח בע"מ | B42: 520042177
A43: ענבל חברה לביטוח בע"מ | B43: 520031030
A44: איילון חברה לביטוח בע"מ | B44: 520030677
A45: ש. שלמה חברה לביטוח בע"מ | B45: 513879189
A46: קנט - קרן לביטוח נזקי טבע בחקלאות | B46: 520027848
... A130: אקטיון בע"מ | B130: 515977338
