Workbook
Name Additional_Factor: 'אפשרויות בחירה'!$C$701:$C$850
Name Amoritization: 'אפשרויות בחירה'!$C$546:$C$550
Name Capsule: 'אפשרויות בחירה'!$C$926:$C$928
Name Company_Name: 'File Name Info'!$A$34:$A$130
Name Company_Name_ID: 'File Name Info'!$A$34:$B$130
Name Consortium: 'אפשרויות בחירה'!$C$514:$C$515
Name Country_list: 'אפשרויות בחירה'!$C$4:$C$85
Name Country_list_funds: 'אפשרויות בחירה'!$C$4:$C$103
Name CSA: 'אפשרויות בחירה'!$C$688:$C$689
Name Delivery: 'אפשרויות בחירה'!$C$666:$C$667
Name Dependence_Independence: 'אפשרויות בחירה'!$C$654:$C$655
Name Duration_Underlying_Interest_Rate: 'אפשרויות בחירה'!$C$680:$C$687
Name File_Type: 'File Name Info'!$A$10:$A$12
Name Full_File_Type: 'File Name Info'!$A$11:$B$13
Name Full_Type: 'File Name Info'!$A$2:$B$8
Name Full_Type_Nostro: 'File Name Info'!$A$3:$B$6
Name Full_Year: 'File Name Info'!$A$22:$B$31
Name Fund_Strategy: 'אפשרויות בחירה'!$C$597:$C$621
Name Fund_type: 'אפשרויות בחירה'!$C$328:$C$498
Name Holding_interest: 'אפשרויות בחירה'!$C$146:$C$147
Name In_the_books: 'אפשרויות בחירה'!$C$656:$C$657
Name Industry_Sector: 'אפשרויות בחירה'!$C$1129:$C$1245
Name Industry_sector_all: 'אפשרויות בחירה'!$C$202:$C$327
Name Industry_sectors: 'אפשרויות בחירה'!$C$202:$C$327
Name israel_abroad: 'אפשרויות בחירה'!$C$2:$C$3
Name Issuer_Number_Banks: 'אפשרויות בחירה'!$C$111:$C$113
Name Issuer_Number_Fund: 'אפשרויות בחירה'!$C$114:$C$117
Name issuer_number_loan: 'אפשרויות בחירה'!$C$118:$C$126
Name Issuer_Number_Type: 'אפשרויות בחירה'!$C$104:$C$110
Name Issuer_Number_Type_2: 'אפשרויות בחירה'!$C$1076:$C$1079
Name Issuer_Number_Type_3: 'אפשרויות בחירה'!$C$1081:$C$1085
Name Issuer_Number_Type_V2: 'אפשרויות בחירה'!$C$104:$C$110
Name Issuer_Type_TFunds: 'אפשרויות בחירה'!$C$1087:$C$1089
Name Leading_factor: 'אפשרויות בחירה'!$C$692:$C$700
Name Linked_Type: 'אפשרויות בחירה'!$C$516:$C$519
Name other_investments: 'אפשרויות בחירה'!$C$1000:$C$1033
Name Penalty: 'אפשרויות בחירה'!$C$851:$C$852
Name QTR: 'File Name Info'!$A$15:$A$19
Name Rating_Agency: 'אפשרויות בחירה'!$C$188:$C$201
Name real_estate_lifestage: 'אפשרויות בחירה'!$C$634:$C$642
Name real_estate_loans: 'אפשרויות בחירה'!$C$553:$C$591
Name Real_Estate_Main_Use: 'אפשרויות בחירה'!$C$622:$C$633
Name Recourse_Nonrecourse: 'אפשרויות בחירה'!$C$544:$C$545
Name Repayment_Rights: 'אפשרויות בחירה'!$C$551:$C$552
Name Reset_frequency: 'אפשרויות בחירה'!$C$658:$C$665
Name Security_ID_Number_Type: 'אפשרויות בחירה'!$C$1113:$C$1116
Name Security_Number_Loans: 'אפשרויות בחירה'!$C$131
Name Stock_Exchange: 'אפשרויות בחירה'!$C$1283:$C$1315
Name Stock_Exchange_Gov_Bonds: 'אפשרויות בחירה'!$C$148:$C$181
Name Subordination_Risk: 'אפשרויות בחירה'!$C$186:$C$187
Name Tradeable_Status: 'אפשרויות בחירה'!$C$1272:$C$1281
Name Tradeable_Status_All: 'אפשרויות בחירה'!$C$135:$C$145
Name tradeable_status_bonds: 'אפשרויות בחירה'!$C$1248:$C$1253
Name tradeable_status_funds: 'אפשרויות בחירה'!$C$1118:$C$1119
Name tradeable_status_stock: 'אפשרויות בחירה'!$C$1255:$C$1259
Name Tradeable_Status_v2: 'אפשרויות בחירה'!$C$1121:$C$1126
Name tradeable_status_warrants: 'אפשרויות בחירה'!$C$1261:$C$1265
Name tradeable_status_warrants_v2: 'אפשרויות בחירה'!$C$1267:$C$1269
Name Transaction: 'אפשרויות בחירה'!$C$643:$C$646
Name Type: 'File Name Info'!$A$2:$A$8

Sheet עמוד פתיחה
A1: קובץ דיווח עבור רשימת נכסים ברמת הנכס הבודד (חוזר גופים מוסדיים 2015-9-14)
A3: יש לבחור תחום: | D3: נכסי עמיתים - קופות גמל
A5: האם מדובר בקובץ לממומנה או לציבור: | D5: לציבור
A7: יש לבחור את רבעון הדיווח: | D7: 02
A9: יש לבחור את שנת הדיווח: | D9: 2025
A11: יש לבחור את הגוף המוסדי: | D11: תגמולים של עובדים בעירית ת"א-יפו א.ש. בע"מ
A13: ח.פ. הגוף המוסדי: | D13: =IFERROR(VLOOKUP(D11,'[1]File Name Info'!A35:B121,2,0),"תא מחושב") -> 570002618
A15: שם קובץ לשמירה | D15: =IF(D5="לממונה",CONCATENATE(D13, "_",VLOOKUP(D3,Full_Type,2,0),"_",D7,VLOOKUP(D9,Full_Year,2,0),".xlxs"),IF(D5="לציבור",CONCATENATE(D13,"_",VLOOKUP(D3,Full_Type_Nostro,2,0),"_",VLOOKUP(D5,Full_File_Type,2,0),"_",D7,VLOOKUP(D9,Full_Year,2,0),".xlsx"),"שם קובץ לשמירה")) -> 570002618_gm_p_0225.xlsx
A17: פרטי האחראי על הדיווח בגוף המוסדי | B17: שם: | D17: צביקה שמיר , מנכ"ל
B19: מספר טלפון: | D19: 03-5210603
B21: כתובת מייל: | D21: zvi-sha@ovdim-tlv.org.il

Sheet סכום נכסים
C1: ידווח בקבצי נכסי הנוסטרו בלבד
B2: שווי הוגן | C2: עלות מופחתת | D2: השיטה שיושמה בדוח הכספי | E2: שיעור מסך נכסי השקעה
A3: מזומנים ושווי מזומנים | B3: =SUM('מזומנים ושווי מזומנים'!O:O) -> 43747.862 | E3: =SUM('[1]מזומנים ושווי מזומנים'!O:O)/B30 -> 0.03544885
A4: איגרות חוב ממשלתיות | B4: =SUM('איגרות חוב ממשלתיות'!U:U) -> 263457.41 | E4: =SUM('[1]איגרות חוב ממשלתיות'!U:U)/B30 -> 0.21347929
A5: ניירות ערך מסחריים | B5: =SUM('ניירות ערך מסחריים'!AD:AD) -> 0 | E5: =SUM('[1]ניירות ערך מסחריים'!AD:AD)/B30 -> 0
A6: איגרות חוב | B6: =SUM('איגרות חוב'!AD:AD) -> 206889.14 | E6: =SUM('[1]איגרות חוב'!AD:AD)/B30 -> 0.16764207
A7: מניות, מניות בכורה ויחידות השתתפות | B7: =SUM('מניות מבכ ויהש'!U:U) -> 250049.68 | E7: =SUM('[1]מניות מבכ ויהש'!U:U)/B30 -> 0.20261501
A8: קרנות סל | B8: =SUM('קרנות סל'!T:T) -> 228466.79 | E8: =SUM('[1]קרנות סל'!T:T)/B30 -> 0.18512642
A9: קרנות נאמנות | B9: =SUM('קרנות נאמנות'!T:T) -> 8363.206 | E9: =SUM('[1]קרנות נאמנות'!T:T)/B30 -> 0.0067766977
A10: כתבי אופציה | B10: =SUM('כתבי אופציה'!W:W) -> 508.51 | E10: =SUM('[1]כתבי אופציה'!W:W)/B30 -> 0.00041204516
A11: אופציות | B11: =SUM(אופציות!V:V) -> 0 | E11: =SUM([1]אופציות!V:V)/B30 -> 0
A12: חוזים עתידיים | B12: =SUM('חוזים עתידיים'!R:R) -> 4396.952 | E12: =SUM('[1]חוזים עתידיים'!R:R)/B30 -> 0.0035628459
A13: מוצרים מובנים | B13: =SUM('מוצרים מובנים'!Z:Z) -> 0 | E13: =SUM('[1]מוצרים מובנים'!Z:Z)/B30 -> 0
A14: לא סחיר איגרות חוב ממשלתיות | B14: =SUM('לא סחיר איגרות חוב ממשלתיות'!U:U) -> 0 | E14: =SUM('[1]לא סחיר איגרות חוב ממשלתיות'!U:U)/B30 -> 0
A15: לא סחיר איגרות חוב מיועדות | B15: =SUM('לא סחיר איגרות חוב מיועדות'!N:N) -> 0 | E15: =SUM('[1]לא סחיר איגרות חוב מיועדות'!N:N)/B30 -> 0
A16: אפיק השקעה מובטח תשואה | B16: =SUM('אפיק השקעה מובטח תשואה'!F:F) -> 0 | E16: =SUM('[1]אפיק השקעה מובטח תשואה'!F:F)/B30 -> 0
A17: לא סחיר ניירות ערך מסחריים | B17: =SUM('לא סחיר ניירות ערך מסחריים'!AI:AI) -> 0 | E17: =SUM('[1]לא סחיר ניירות ערך מסחריים'!AI:AI)/B30 -> 0
A18: לא סחיר איגרות חוב | B18: =SUM('לא סחיר איגרות חוב'!AG:AG) -> 13089.55 | E18: =SUM('[1]לא סחיר איגרות חוב'!AG:AG)/B30 -> 0.01060645
A19: לא סחיר מניות, מניות בכורה ויחידות השתתפות | B19: =SUM('לא סחיר מניות מבכ ויהש'!X:X) -> 14657.946 | E19: =SUM('[1]לא סחיר מניות מבכ ויהש'!X:X)/B30 -> 0.011877319
A20: קרנות השקעה | B20: =SUM('קרנות השקעה'!W:W) -> 147922.38 | E20: =SUM('[1]קרנות השקעה'!W:W)/B30 -> 0.11986136
A21: לא סחיר כתבי אופציה | B21: =SUM('לא סחיר כתבי אופציה'!Z:Z) -> 0 | E21: =SUM('[1]לא סחיר כתבי אופציה'!Z:Z)/B30 -> 0
A22: לא סחיר אופציות | B22: =SUM('לא סחיר אופציות'!Z:Z) -> 0 | E22: =SUM('[1]לא סחיר אופציות'!Z:Z)/B30 -> 0
A23: לא סחיר נגזרים אחרים | B23: =SUM('לא סחיר נגזרים אחרים'!R:R) -> 7090.775 | E23: =SUM('[1]לא סחיר נגזרים אחרים'!R:R)/B30 -> 0.0057456481
A24: הלוואות | B24: =SUM(הלוואות!AT:AT) -> 42244.724 | E24: =SUM([1]הלוואות!AT:AT)/B30 -> 0.034230859
A25: לא סחיר מוצרים מובנים | B25: =SUM('לא סחיר מוצרים מובנים'!AB:AB) -> 0 | E25: =SUM('[1]לא סחיר מוצרים מובנים'!AB:AB)/B30 -> 0
A26: פיקדונות מעל 3 חודשים | B26: =SUM('פיקדונות מעל 3 חודשים'!T:T) -> 0 | E26: =SUM('[1]פיקדונות מעל 3 חודשים'!T:T)/B30 -> 0
A27: זכויות מקרקעין | B27: =SUM('זכויות מקרקעין'!S:S) -> 5100 | E27: =SUM('[1]זכויות מקרקעין'!S:S)/B30 -> 0.004132525
A28: השקעה בחברות מוחזקות | B28: =SUM('השקעה בחברות מוחזקות'!U:U) -> 0 | E28: =SUM('[1]השקעה בחברות מוחזקות'!U:U)/B30 -> 0
A29: נכסים אחרים | B29: =SUM('נכסים אחרים'!N:N) -> -1872.62 | E29: =SUM('[1]נכסים אחרים'!N:N)/B30 -> -0.0015173822
A30: סך הכל נכסים | B30: =IF(SUM(B3:B29)=0,0.0001,SUM(B3:B29)) -> 1234112.3 | C30: =SUM(C3:C29) -> 0 | D30: =SUM(D3:D29) -> 0 | E30: =SUM(E3:E29) -> 1
A31: מסגרות אשראי
A32: יתרות התחייבויות להשקעה | B32: =SUM('[1]יתרות התחייבות להשקעה'!O:O) -> 41332.228 | E32: =B32/D30 -> #DIV/0!

Sheet מזומנים ושווי מזומנים
A1: מספר קופה/קרן/ח.פ. עבור חברת ביטוח | B1: מספר מסלול | C1: שם הבנק | D1: מספר מזהה בנק | E1: סוג מספר מזהה בנק | F1: מאפיין עיקרי | G1: ישראל/חו"ל | H1: בעל עניין/צד קשור | I1: דירוג הבנק | J1: שם מדרג | K1: מטבע פעילות | L1: שווי מטבעי | M1: שער חליפין | N1: שיעור ריבית | O1: שווי הוגן (באלפי ש"ח) | P1: שיעור מנכסי אפיק ההשקעה | Q1: שיעור מסך נכסי ההשקעה
A2: 337 | B2: 1405 | C2: בנק לאומי לישראל בע"מ | D2: 10-800 | E2: סימול בנק | F2: מזומן ועו"ש בש"ח | G2: ישראל | H2: לא | I2: AAA | J2: S&P מעלות | K2: ILS | L2: 128.862 | M2: 1 | N2: 0 | O2: 128.862 | P2: 0.17416081 | Q2: 0.014290384
A3: 337 | B3: 1405 | C3: פועלים | D3: 12-591 | E3: סימול בנק | F3: מזומן ועו"ש נקוב במט"ח | G3: ישראל | H3: לא | I3: AAA | J3: S&P מעלות | K3: USD | L3: 92.893 | M3: 3.372 | N3: SOFR-1.5% | O3: 313.234 | P3: 0.42334558 | Q3: 0.034736694
A4: 337 | B4: 1405 | C4: פועלים | D4: 12-591 | E4: סימול בנק | F4: מזומן ועו"ש נקוב במט"ח | G4: ישראל | H4: לא | I4: AAA | J4: S&P מעלות | K4: EUR | L4: 5.182 | M4: 3.9552 | N4: 0 | O4: 20.498 | P4: 0.027703314 | Q4: 0.0022731348
A5: 337 | B5: 1405 | C5: פועלים | D5: 12-591 | E5: סימול בנק | F5: מזומן ועו"ש בש"ח | G5: ישראל | H5: לא | I5: AAA | J5: S&P מעלות | K5: ILS | L5: 277.304 | M5: 1 | N5: 0.0403 | O5: 277.304 | P5: 0.37478427 | Q5: 0.030752103
A6: 337 | B6: 1405 | C6: בנק לאומי לישראל בע"מ | D6: 10-800 | E6: סימול בנק | F6: מזומן ועו"ש בש"ח | G6: ישראל | H6: לא | I6: AAA | J6: S&P מעלות | K6: ILS | L6: 0.004 | M6: 1 | N6: 0 | O6: 0.004 | P6: 6.0278231e-06 | Q6: 4.9459983e-07
A7: 337 | B7: 1477 | C7: בנק לאומי לישראל בע"מ | D7: 10-800 | E7: סימול בנק | F7: מזומן ועו"ש בש"ח | G7: ישראל | H7: לא | I7: AAA | J7: S&P מעלות | K7: ILS | L7: 603.083 | M7: 1 | N7: 0 | O7: 603.083 | P7: 0.37332678 | Q7: 0.034711146
A8: 337 | B8: 1477 | C8: פועלים | D8: 12-591 | E8: סימול בנק | F8: מזומן ועו"ש נקוב במט"ח | G8: ישראל | H8: לא | I8: AAA | J8: S&P מעלות | K8: USD | L8: 38.502 | M8: 3.372 | N8: SOFR-1.5% | O8: 129.829 | P8: 0.080367862 | Q8: 0.0074724363
A9: 337 | B9: 1477 | C9: פועלים | D9: 12-591 | E9: סימול בנק | F9: מזומן ועו"ש נקוב במט"ח | G9: ישראל | H9: לא | I9: AAA | J9: S&P מעלות | K9: HKD | L9: 2.916 | M9: 0.429 | N9: 0 | O9: 1.251 | P9: 0.00077425223 | Q9: 7.1988358e-05
A10: 337 | B10: 1477 | C10: פועלים | D10: 12-591 | E10: סימול בנק | F10: מזומן ועו"ש נקוב במט"ח | G10: ישראל | H10: לא | I10: AAA | J10: S&P מעלות | K10: EUR | L10: 106.806 | M10: 3.9552 | N10: 0 | O10: 422.44 | P10: 0.26150327 | Q10: 0.024314029
A11: 337 | B11: 1477 | C11: פועלים | D11: 12-591 | E11: סימול בנק | F11: מזומן ועו"ש נקוב במט"ח | G11: ישראל | H11: לא | I11: AAA | J11: S&P מעלות | K11: JPY | L11: 88.168 | M11: 0.023369 | N11: 0 | O11: 2.06 | P11: 0.0012754542 | Q11: 0.00011858908
A12: 337 | B12: 1477 | C12: פועלים | D12: 12-591 | E12: סימול בנק | F12: מזומן ועו"ש נקוב במט"ח | G12: ישראל | H12: לא | I12: AAA | J12: S&P מעלות | K12: GBP | L12: 0.521 | M12: 4.6236 | N12: 0 | O12: 2.409 | P12: 0.0014909511 | Q12: 0.00013862553
A13: 337 | B13: 1477 | C13: פועלים | D13: 12-591 | E13: סימול בנק | F13: מזומן ועו"ש בש"ח | G13: ישראל | H13: לא | I13: AAA | J13: S&P מעלות | K13: ILS | L13: 448.595 | M13: 1 | N13: 0.0403 | O13: 448.595 | P13: 0.27769394 | Q13: 0.025819404
A14: 337 | B14: 1477 | C14: פועלים | D14: 12-591 | E14: סימול בנק | F14: פח"ק/פר"י | G14: ישראל | H14: לא | I14: AAA | J14: S&P מעלות | K14: ILS | L14: 0.237 | M14: 1 | N14: 0.0403 | O14: 0.237 | P14: 0.00014678454 | Q14: 1.364772e-05
A15: 337 | B15: 1477 | C15: פועלים | D15: 12-591 | E15: סימול בנק | F15: מזומן ועו"ש נקוב במט"ח | G15: ישראל | H15: לא | I15: AAA | J15: S&P מעלות | K15: CHF | L15: 1.306 | M15: 4.2314 | N15: 0 | O15: 5.526 | P15: 0.0034207088 | Q15: 0.00031805038
A16: 337 | B16: 9962 | C16: בנק לאומי לישראל בע"מ | D16: 10-800 | E16: סימול בנק | F16: מזומן ועו"ש בש"ח | G16: ישראל | H16: לא | I16: AAA | J16: S&P מעלות | K16: ILS | L16: 283.855 | M16: 1 | N16: 0 | O16: 283.855 | P16: 0.14743132 | Q16: 0.0066718397
A17: 337 | B17: 9962 | C17: פועלים | D17: 12-591 | E17: סימול בנק | F17: מזומן ועו"ש נקוב במט"ח | G17: ישראל | H17: לא | I17: AAA | J17: S&P מעלות | K17: USD | L17: 49.248 | M17: 3.372 | N17: SOFR-1.5% | O17: 166.065 | P17: 0.086252547 | Q17: 0.0039032626
A18: 337 | B18: 9962 | C18: פועלים | D18: 12-591 | E18: סימול בנק | F18: מזומן ועו"ש נקוב במט"ח | G18: ישראל | H18: לא | I18: AAA | J18: S&P מעלות | K18: HKD | L18: 0.908 | M18: 0.429 | N18: 0 | O18: 0.389 | P18: 0.00020225877 | Q18: 9.1529946e-06
A19: 337 | B19: 9962 | C19: פועלים | D19: 12-591 | E19: סימול בנק | F19: מזומן ועו"ש נקוב במט"ח | G19: ישראל | H19: לא | I19: AAA | J19: S&P מעלות | K19: EUR | L19: 89.39 | M19: 3.9552 | N19: 0 | O19: 353.556 | P19: 0.18363316 | Q19: 0.0083101134
A20: 337 | B20: 9962 | C20: פועלים | D20: 12-591 | E20: סימול בנק | F20: מזומן ועו"ש נקוב במט"ח | G20: ישראל | H20: לא | I20: AAA | J20: S&P מעלות | K20: JPY | L20: 99.373 | M20: 0.023369 | N20: 0 | O20: 2.322 | P20: 0.001206157 | Q20: 5.4583285e-05
A21: 337 | B21: 9962 | C21: פועלים | D21: 12-591 | E21: סימול בנק | F21: מזומן ועו"ש נקוב במט"ח | G21: ישראל | H21: לא | I21: AAA | J21: S&P מעלות | K21: GBP | L21: 0.703 | M21: 4.6236 | N21: 0 | O21: 3.252 | P21: 0.0016889161 | Q21: 7.6430011e-05
A22: 337 | B22: 9962 | C22: פועלים | D22: 12-591 | E22: סימול בנק | F22: מזומן ועו"ש בש"ח | G22: ישראל | H22: לא | I22: AAA | J22: S&P מעלות | K22: ILS | L22: 1104.74 | M22: 1 | N22: 0.0403 | O22: 1104.74 | P22: 0.57379064 | Q22: 0.025966254
A23: 337 | B23: 9962 | C23: פועלים | D23: 12-591 | E23: סימול בנק | F23: מזומן ועו"ש נקוב במט"ח | G23: ישראל | H23: לא | I23: AAA | J23: S&P מעלות | K23: CHF | L23: 2.637 | M23: 4.2314 | N23: 0 | O23: 11.157 | P23: 0.0057949943 | Q23: 0.00026224599
A24: 337 | B24: 9963 | C24: בנק לאומי לישראל בע"מ | D24: 10-800 | E24: סימול בנק | F24: מזומן ועו"ש בש"ח | G24: ישראל | H24: לא | I24: AAA | J24: S&P מעלות | K24: ILS | L24: 1411.249 | M24: 1 | N24: 0 | O24: 1411.249 | P24: 0.03731159 | Q24: 0.0012683887
A25: 337 | B25: 9963 | C25: פועלים | D25: 12-591 | E25: סימול בנק | F25: מזומן ועו"ש נקוב במט"ח | G25: ישראל | H25: לא | I25: AAA | J25: S&P מעלות | K25: USD | L25: 3928.299 | M25: 3.372 | N25: SOFR-1.5% | O25: 13246.225 | P25: 0.3502129 | Q25: 0.011905311
A26: 337 | B26: 9963 | C26: פועלים | D26: 12-591 | E26: סימול בנק | F26: מזומן ועו"ש נקוב במט"ח | G26: ישראל | H26: לא | I26: AAA | J26: S&P מעלות | K26: HKD | L26: 87.459 | M26: 0.429 | N26: 0 | O26: 37.52 | P26: 0.00099198179 | Q26: 3.372192e-05
A27: 337 | B27: 9963 | C27: פועלים | D27: 12-591 | E27: סימול בנק | F27: מזומן ועו"ש נקוב במט"ח | G27: ישראל | H27: לא | I27: AAA | J27: S&P מעלות | K27: CAD | L27: 7.495 | M27: 2.4674 | N27: 0 | O27: 18.494 | P27: 0.00048895075 | Q27: 1.6621634e-05
A28: 337 | B28: 9963 | C28: פועלים | D28: 12-591 | E28: סימול בנק | F28: מזומן ועו"ש נקוב במט"ח | G28: ישראל | H28: לא | I28: AAA | J28: S&P מעלות | K28: EUR | L28: 1666.009 | M28: 3.9552 | N28: 0 | O28: 6589.398 | P28: 0.17421509 | Q28: 0.005922354
A29: 337 | B29: 9963 | C29: פועלים | D29: 12-591 | E29: סימול בנק | F29: מזומן ועו"ש נקוב במט"ח | G29: ישראל | H29: לא | I29: AAA | J29: S&P מעלות | K29: JPY | L29: 57.023 | M29: 0.023369 | N29: 0 | O29: 1.333 | P29: 3.5231307e-05 | Q29: 1.1976705e-06
A30: 337 | B30: 9963 | C30: פועלים | D30: 12-591 | E30: סימול בנק | F30: מזומן ועו"ש נקוב במט"ח | G30: ישראל | H30: לא | I30: AAA | J30: S&P מעלות | K30: GBP | L30: 10.005 | M30: 4.6236 | N30: 0 | O30: 46.261 | P30: 0.0012230723 | Q30: 4.1577724e-05
A31: 337 | B31: 9963 | C31: פועלים | D31: 12-591 | E31: סימול בנק | F31: מזומן ועו"ש בש"ח | G31: ישראל | H31: לא | I31: AAA | J31: S&P מעלות | K31: ILS | L31: 14210.135 | M31: 1 | N31: 0.0403 | O31: 14210.135 | P31: 0.37569742 | Q31: 0.012771644
A32: 337 | B32: 9963 | C32: פועלים | D32: 12-591 | E32: סימול בנק | F32: מזומן ועו"ש נקוב במט"ח | G32: ישראל | H32: לא | I32: AAA | J32: S&P מעלות | K32: CHF | L32: 9.414 | M32: 4.2314 | N32: 0 | O32: 39.833 | P32: 0.0010531382 | Q32: 3.5800902e-05
A33: 337 | B33: 9963 | C33: בנק לאומי לישראל בע"מ | D33: 10-800 | E33: סימול בנק | F33: מזומן ועו"ש בש"ח | G33: ישראל | H33: לא | I33: AAA | J33: S&P מעלות | K33: ILS | L33: 1906.459 | M33: 1 | N33: 0 | O33: 1906.459 | P33: 0.05040429 | Q33: 0.0017134684
A34: 337 | B34: 9963 | C34: בנק לאומי לישראל בע"מ | D34: 10-800 | E34: סימול בנק | F34: מזומן ועו"ש בש"ח | G34: ישראל | H34: לא | I34: AAA | J34: S&P מעלות | K34: ILS | L34: 309.109 | M34: 1 | N34: 0 | O34: 309.109 | P34: 0.0081724307 | Q34: 0.00027781765
A35: 337 | B35: 9963 | C35: פועלים | D35: 12-591 | E35: סימול בנק | F35: מזומן ועו"ש בש"ח | G35: ישראל | H35: לא | I35: AAA | J35: S&P מעלות | K35: ILS | L35: 0 | M35: 1 | N35: 0.0403 | O35: 0 | P35: 3.1726434e-09 | Q35: 1.0785241e-10
A36: 337 | B36: 9963 | C36: בנק לאומי לישראל בע"מ | D36: 10-800 | E36: סימול בנק | F36: מזומן ועו"ש בש"ח | G36: ישראל | H36: לא | I36: AAA | J36: S&P מעלות | K36: ILS | L36: 7.334 | M36: 1 | N36: 0 | O36: 7.334 | P36: 0.0001939006 | Q36: 6.5915528e-06
A37: 337 | B37: 9964 | C37: בנק לאומי לישראל בע"מ | D37: 10-800 | E37: סימול בנק | F37: מזומן ועו"ש בש"ח | G37: ישראל | H37: לא | I37: AAA | J37: S&P מעלות | K37: ILS | L37: 285.307 | M37: 1 | N37: 0 | O37: 285.307 | P37: 0.17866912 | Q37: 0.0073479158
A38: 337 | B38: 9964 | C38: פועלים | D38: 12-591 | E38: סימול בנק | F38: מזומן ועו"ש נקוב במט"ח | G38: ישראל | H38: לא | I38: AAA | J38: S&P מעלות | K38: USD | L38: 107.552 | M38: 3.372 | N38: SOFR-1.5% | O38: 362.665 | P38: 0.22711348 | Q38: 0.0093402304
A39: 337 | B39: 9964 | C39: פועלים | D39: 12-591 | E39: סימול בנק | F39: מזומן ועו"ש נקוב במט"ח | G39: ישראל | H39: לא | I39: AAA | J39: S&P מעלות | K39: HKD | L39: 3.056 | M39: 0.429 | N39: 0 | O39: 1.311 | P39: 0.0008210819 | Q39: 3.3767674e-05
A40: 337 | B40: 9964 | C40: פועלים | D40: 12-591 | E40: סימול בנק | F40: מזומן ועו"ש נקוב במט"ח | G40: ישראל | H40: לא | I40: AAA | J40: S&P מעלות | K40: EUR | L40: 75.393 | M40: 3.9552 | N40: 0 | O40: 298.195 | P40: 0.18674047 | Q40: 0.0076798566
A41: 337 | B41: 9964 | C41: פועלים | D41: 12-591 | E41: סימול בנק | F41: מזומן ועו"ש נקוב במט"ח | G41: ישראל | H41: לא | I41: AAA | J41: S&P מעלות | K41: JPY | L41: 15.502 | M41: 0.023369 | N41: 0 | O41: 0.362 | P41: 0.00022686943 | Q41: 9.3301934e-06
A42: 337 | B42: 9964 | C42: פועלים | D42: 12-591 | E42: סימול בנק | F42: מזומן ועו"ש נקוב במט"ח | G42: ישראל | H42: לא | I42: AAA | J42: S&P מעלות | K42: GBP | L42: 1.264 | M42: 4.6236 | N42: 0 | O42: 5.846 | P42: 0.0036608472 | Q42: 0.00015055538
A43: 337 | B43: 9964 | C43: פועלים | D43: 12-591 | E43: סימול בנק | F43: מזומן ועו"ש בש"ח | G43: ישראל | H43: לא | I43: AAA | J43: S&P מעלות | K43: ILS | L43: 622.253 | M43: 1 | N43: 0.0403 | O43: 622.253 | P43: 0.38967702 | Q43: 0.016025791
A44: 337 | B44: 9964 | C44: פועלים | D44: 12-591 | E44: סימול בנק | F44: מזומן ועו"ש נקוב במט"ח | G44: ישראל | H44: לא | I44: AAA | J44: S&P מעלות | K44: CHF | L44: 4.94 | M44: 4.2314 | N44: 0 | O44: 20.904 | P44: 0.013091115 | Q44: 0.00053838295
A45: 337 | B45: 15372 | C45: בנק לאומי לישראל בע"מ | D45: 10-800 | E45: סימול בנק | F45: מזומן ועו"ש בש"ח | G45: ישראל | H45: לא | I45: AAA | J45: S&P מעלות | K45: ILS | L45: 10.617 | M45: 1 | N45: 0 | O45: 10.617 | P45: 0.22588236 | Q45: 0.001604161
A46: 337 | B46: 15372 | C46: פועלים | D46: 12-591 | E46: סימול בנק | F46: מזומן ועו"ש נקוב במט"ח | G46: ישראל | H46: לא | I46: AAA | J46: S&P מעלות | K46: USD | L46: 3.607 | M46: 3.372 | N46: SOFR-1.5% | O46: 12.164 | P46: 0.2588012 | Q46: 0.0018379425
A47: 337 | B47: 15372 | C47: פועלים | D47: 12-591 | E47: סימול בנק | F47: מזומן ועו"ש בש"ח | G47: ישראל | H47: לא | I47: AAA | J47: S&P מעלות | K47: ILS | L47: 24.22 | M47: 1 | N47: 0.0403 | O47: 24.22 | P47: 0.51531644 | Q47: 0.0036596507

Sheet איגרות חוב ממשלתיות
A1: מספר קופה/קרן/ח.פ. עבור חברת ביטוח | B1: מספר מסלול | C1: שם מנפיק | D1: שם נייר ערך | E1: מספר נייר ערך | F1: מאפיין עיקרי | G1: ישראל/חו"ל | H1: מדינה לפי חשיפה כלכלית | I1: זירת מסחר | J1: דירוג | K1: שם מדרג | L1: מטבע פעילות | M1: מח"מ | N1: מועד פדיון | O1: שיעור ריבית | P1: תשואה לפדיון | Q1: סכום לקבל (במטבע הפעילות) | R1: ערך נקוב (יחידות) | S1: שער חליפין | T1: שער נייר הערך | U1: שווי הוגן (באלפי ש"ח) | V1: עלות מופחתת (באלפי ש"ח) | W1: השיטה שיושמה בדוח הכספי | X1: שיעור מערך נקוב מונפק | Y1: שיעור מנכסי אפיק ההשקעה | Z1: שיעור מסך נכסי ההשקעה
A2: 337 | B2: 1405 | C2: גליל | D2: ממשל צמודה 0527 | E2: IL0011408478 | F2: צמוד למדד המחירים לצרכן בריבית קבועה | G2: ישראל | H2: ישראל | I2: TASE | J2: RF | K2: פנימי | L2: ILS | M2: 1.905 | N2: 31/05/2027 | O2: 0.0075 | P2: 0.02096 | R2: 320378 | S2: 1 | T2: 115.45 | U2: 369.876 | W2: שווי הוגן | X2: 1.3e-05 | Y2: 0.096282126 | Z2: 0.041018118
A3: 337 | B3: 1405 | C3: שחר | D3: ממשל שיקלית 0928 | E3: IL0011508798 | F3: לא צמוד למדד המחירים לצרכן ריבית קבועה | G3: ישראל | H3: ישראל | I3: TASE | J3: RF | K3: פנימי | L3: ILS | M3: 3.109 | N3: 28/09/2028 | O3: 0.0225 | P3: 0.03952 | R3: 703616 | S3: 1 | T3: 96.6 | U3: 679.693 | W3: שווי הוגן | X3: 2e-05 | Y3: 0.17693016 | Z3: 0.0753758
A4: 337 | B4: 1405 | C4: שחר | D4: ממשל שקלית 0327 | E4: IL0011393449 | F4: לא צמוד למדד המחירים לצרכן ריבית קבועה | G4: ישראל | H4: ישראל | I4: TASE | J4: RF | K4: פנימי | L4: ILS | M4: 1.725 | N4: 31/03/2027 | O4: 0.02 | P4: 0.04003 | R4: 186178 | S4: 1 | T4: 97.19 | U4: 180.946 | W4: שווי הוגן | X4: 7e-06 | Y4: 0.047101961 | Z4: 0.020066381
A5: 337 | B5: 1405 | C5: שחר | D5: ממשל שקלית 0335 | E5: IL0012023326 | F5: לא צמוד למדד המחירים לצרכן ריבית קבועה | G5: ישראל | H5: ישראל | I5: TASE | J5: RF | K5: פנימי | L5: ILS | M5: 8.174 | N5: 30/03/2035 | O5: 0.04 | P5: 0.04114 | R5: 210941 | S5: 1 | T5: 100.1 | U5: 211.152 | W5: שווי הוגן | X5: 6e-06 | Y5: 0.054964734 | Z5: 0.023416079
A6: 337 | B6: 1405 | C6: שחר | D6: ממשל שקלית 4.60% 8/29 | E6: IL0012128935 | F6: לא צמוד למדד המחירים לצרכן ריבית קבועה | G6: ישראל | H6: ישראל | I6: TASE | J6: RF | K6: פנימי | L6: ILS | M6: 3.781 | N6: 31/08/2029 | O6: 0.046 | P6: 0.03939 | R6: 97599 | S6: 1 | T6: 105.5 | U6: 102.967 | W6: שווי הוגן | X6: 6e-06 | Y6: 0.026803214 | Z6: 0.011418707
A7: 337 | B7: 1405 | C7: שחר | D7: ממשלתי שקלית 0142 | E7: IL0011254005 | F7: לא צמוד למדד המחירים לצרכן ריבית קבועה | G7: ישראל | H7: ישראל | I7: TASE | J7: RF | K7: פנימי | L7: ILS | M7: 11.421 | N7: 31/01/2042 | O7: 0.055 | P7: 0.04352 | R7: 736311 | S7: 1 | T7: 115.63 | U7: 851.396 | W7: שווי הוגן | X7: 2.6e-05 | Y7: 0.22162608 | Z7: 0.094417157
A8: 337 | B8: 1405 | C8: גליל | D8: ממשלתית צמודה 0726 | E8: IL0011695645 | F8: צמוד למדד המחירים לצרכן בריבית קבועה | G8: ישראל | H8: ישראל | I8: TASE | J8: RF | K8: פנימי | L8: ILS | M8: 1.078 | N8: 31/07/2026 | O8: 0.001 | P8: 0.02338 | R8: 116422 | S8: 1 | T8: 114.5 | U8: 133.303 | W8: שווי הוגן | X8: 6e-06 | Y8: 0.034700009 | Z8: 0.0147829
A9: 337 | B9: 1405 | C9: גליל | D9: ממשלתית צמודה 1.10% 1028 | E9: IL0011973265 | F9: צמוד למדד המחירים לצרכן בריבית קבועה | G9: ישראל | H9: ישראל | I9: TASE | J9: RF | K9: פנימי | L9: ILS | M9: 3.268 | N9: 31/10/2028 | O9: 0.011 | P9: 0.02053 | R9: 176782 | S9: 1 | T9: 103.51 | U9: 182.987 | W9: שווי הוגן | X9: 6e-06 | Y9: 0.047633161 | Z9: 0.020292682
A10: 337 | B10: 1405 | C10: שחר | D10: ממשלתית שקלית 0537 | E10: IL0011661803 | F10: לא צמוד למדד המחירים לצרכן ריבית קבועה | G10: ישראל | H10: ישראל | I10: TASE | J10: RF | K10: פנימי | L10: ILS | M10: 10.803 | N10: 31/05/2037 | O10: 0.015 | P10: 0.04253 | R10: 109758 | S10: 1 | T10: 74.8 | U10: 82.099 | W10: שווי הוגן | X10: 3e-06 | Y10: 0.021371098 | Z10: 0.0091045165
A11: 337 | B11: 1405 | C11: שחר | D11: ממשלתית שקלית 1.00% 03/30 | E11: IL0011609851 | F11: לא צמוד למדד המחירים לצרכן ריבית קבועה | G11: ישראל | H11: ישראל | I11: TASE | J11: RF | K11: פנימי | L11: ILS | M11: 4.641 | N11: 31/03/2030 | O11: 0.01 | P11: 0.03969 | R11: 975818 | S11: 1 | T11: 87.63 | U11: 855.109 | W11: שווי הוגן | X11: 2.6e-05 | Y11: 0.22259258 | Z11: 0.094828906
A12: 337 | B12: 1405 | C12: US Govt | D12: T 3.875% 08/34 | E12: US91282CLF67 | F12: צמוד מט"ח בריבית קבועה | G12: חו"ל | H12: ארה"ב | I12: FOREIGN_GOV_SEC | J12: AA+ | K12: Fitch | L12: USD | M12: 7.638 | N12: 15/08/2034 | O12: 0.03875 | P12: 0.0424 | R12: 27500 | S12: 3.372 | T12: 99.135 | U12: 91.928 | W12: שווי הוגן | X12: 0 | Y12: 0.023929745 | Z12: 0.010194552
A13: 337 | B13: 1405 | C13: US Govt | D13: T-3 3/8 15/05/33 | E13: US91282CHC82 | F13: צמוד מט"ח בריבית קבועה | G13: חו"ל | H13: ארה"ב | I13: FOREIGN_GOV_SEC | J13: AA+ | K13: Fitch | L13: USD | M13: 6.921 | N13: 15/05/2033 | O13: 0.03375 | P13: 0.04125 | R13: 31000 | S13: 3.372 | T13: 95.79 | U13: 100.132 | W13: שווי הוגן | X13: 0 | Y13: 0.026065127 | Z13: 0.011104267
... A50: 337 | B50: 9964 | C50: US Govt | D50: T-3 3/8 15/05/33 | E50: US91282CHC82 | F50: צמוד מט"ח בריבית קבועה | G50: חו"ל | H50: ארה"ב | I50: FOREIGN_GOV_SEC | J50: AA+ | K50: Fitch | L50: USD | M50: 6.921 | N50: 15/05/2033 | O50: 0.03375 | P50: 0.04125 | R50: 282000 | S50: 3.372 | T50: 95.79 | U50: 910.874 | W50: שווי הוגן | X50: 3e-06 | Y50: 0.052587269 | Z50: 0.023459046

Sheet ניירות ערך מסחריים
A1: מספר קופה/קרן/ח.פ. עבור חברת ביטוח | B1: מספר מסלול | C1: שם מנפיק | D1: מספר מנפיק | E1: סוג מספר מזהה מנפיק | F1: שם נייר ערך | G1: מספר נייר ערך | H1: סוג מספר נייר ערך | I1: מאפיין עיקרי | J1: ישראל/חו"ל | K1: מדינה לפי חשיפה כלכלית | L1: זירת מסחר | M1: ענף מסחר | N1: בעל עניין/צד קשור | O1: דירוג | P1: שם מדרג | Q1: דירוג נייר הערך/המנפיק | R1: מטבע פעילות | S1: מח"מ | T1: ריבית עוגן | U1: מועד פדיון | V1: שיעור ריבית | W1: תשואה לפדיון | X1: נחיתות חוזית | Y1: האם סווג כחוב בעייתי | Z1: ערך נקוב (יחידות) | AA1: שער חליפין | AB1: שער נייר הערך | AC1: סכום לקבל (במטבע הפעילות) | AD1: שווי הוגן (באלפי ש"ח) | AE1: עלות מופחתת (באלפי ש"ח) | AF1: עלות מופחתת (במטבע הפעילות) | AG1: השיטה שיושמה בדוח הכספי | AH1: שיעור מערך נקוב מונפק | AI1: שיעור מנכסי אפיק ההשקעה | AJ1: שיעור מסך נכסי ההשקעה
A2: 337 | B2: 1405
A3: 337 | B3: 1477
A4: 337 | B4: 9962
A5: 337 | B5: 9963
A6: 337 | B6: 9964
A7: 337 | B7: 15372

Sheet איגרות חוב
A1: מספר קופה/קרן/ח.פ. עבור חברת ביטוח | B1: מספר מסלול | C1: שם מנפיק | D1: מספר מנפיק | E1: סוג מספר מזהה מנפיק | F1: שם נייר ערך | G1: מספר נייר ערך | H1: סוג מספר נייר ערך | I1: מאפיין עיקרי | J1: ישראל/חו"ל | K1: מדינה לפי חשיפה כלכלית | L1: סטאטוס סחירות | M1: זירת מסחר | N1: ענף מסחר | O1: בעל עניין/צד קשור | P1: דירוג | Q1: שם מדרג | R1: דירוג נייר הערך/המנפיק | S1: מטבע פעילות | T1: מח"מ | U1: מועד פדיון | V1: שיעור ריבית | W1: תשואה לפדיון | X1: נחיתות חוזית | Y1: האם סווג כחוב בעייתי | Z1: ערך נקוב (יחידות) | AA1: שער חליפין | AB1: שער נייר הערך | AC1: סכום לקבל (במטבע הפעילות) | AD1: שווי הוגן (באלפי ש"ח) | AE1: עלות מופחתת (באלפי ש"ח) | AF1: עלות מופחתת (במטבע הפעילות) | AG1: השיטה שיושמה בדוח הכספי | AH1: שיעור מערך נקוב מונפק | AI1: שיעור מנכסי אפיק ההשקעה | AJ1: שיעור מסך נכסי ההשקעה
A2: 337 | B2: 1405 | C2: לוויתן בונד בע"מ | D2: 516223864 | E2: ח.פ | F2: LVIATH 6.125% 6/25 | G2: IL0011677742 | H2: ISIN | I2: צמוד למט"ח | J2: חו"ל | K2: ישראל | L2: סחיר | M2: אחר | N2: חיפושי נפט וגז | O2: לא | P2: BB- | Q2: S&P | R2: נייר ערך | S2: USD | T2: 0.133 | U2: 30/06/2025 | V2: 0.06125 | W2: 0.23773 | X2: החוב לא נחות | Y2: לא | Z2: 0 | AA2: 3.372 | AB2: 0 | AC2: 0.061 | AD2: 0.207 | AG2: שווי הוגן | AH2: 0 | AI2: 5.6765712e-05 | AJ2: 2.2904631e-05
A3: 337 | B3: 1405 | C3: אאורה השקעות בע"מ | D3: 520038274 | E3: ח.פ | F3: אאורה אגח טז | G3: IL0037305799 | H3: ISIN | I3: לא צמוד למדד המחירים לצרכן | J3: ישראל | K3: ישראל | L3: סחיר | M3: TASE | N3: בנייה | O3: לא | P3: A2 | Q3: מידרוג Moodys | R3: נייר ערך | S3: ILS | T3: 1.207 | U3: 30/09/2027 | V3: 0.035 | W3: 0.04885 | X3: החוב לא נחות | Y3: לא | Z3: 28912 | AA3: 1 | AB3: 99.31 | AD3: 28.713 | AG3: שווי הוגן | AH3: 0.000208 | AI3: 0.0078915724 | AJ3: 0.003184203
A4: 337 | B4: 1405 | C4: אאורה השקעות בע"מ | D4: 520038274 | E4: ח.פ | F4: אאורה אגח יז %3.85 31/01/2029 | G4: IL0011935801 | H4: ISIN | I4: צמוד למדד המחירים לצרכן | J4: ישראל | K4: ישראל | L4: סחיר | M4: TASE | N4: בנייה | O4: לא | P4: A2 | Q4: מידרוג Moodys | R4: נייר ערך | S4: ILS | T4: 2.116 | U4: 31/01/2029 | V4: 0.0385 | W4: 0.03237 | X4: החוב לא נחות | Y4: לא | Z4: 19000 | AA4: 1 | AB4: 111.11 | AD4: 21.111 | AG4: שווי הוגן | AH4: 6.3e-05 | AI4: 0.0058022866 | AJ4: 0.0023411885
A5: 337 | B5: 1405 | C5: אדגר השקעות ופיתוח בע"מ | D5: 520035171 | E5: ח.פ | F5: אדגר אגח סד יא | G5: IL0018202817 | H5: ISIN | I5: צמוד למדד המחירים לצרכן | J5: ישראל | K5: גלובלי | L5: סחיר | M5: TASE | N5: נדל"ן מניב בחו"ל | O5: לא | P5: A2 | Q5: מידרוג Moodys | R5: נייר ערך | S5: ILS | T5: 2.624 | U5: 31/03/2030 | V5: 0.0245 | W5: 0.03057 | X5: החוב לא נחות | Y5: לא | Z5: 4565.22 | AA5: 1 | AB5: 115.76 | AD5: 5.285 | AG5: שווי הוגן | AH5: 1e-05 | AI5: 0.0014524883 | AJ5: 0.0005860705
A6: 337 | B6: 1405 | C6: אדמה פתרונות לחקלאות בע"מ | D6: 520043605 | E6: ח.פ | F6: אדמה אגח ב | G6: IL0011109159 | H6: ISIN | I6: צמוד למדד המחירים לצרכן | J6: ישראל | K6: ישראל | L6: סחיר | M6: TASE | N6: כימיה, גומי ופלסטיק | O6: לא | P6: AA- | Q6: S&P מעלות | R6: נייר ערך | S6: ILS | T6: 5.037 | U6: 30/11/2036 | V6: 0.0515 | W6: 0.04176 | X6: החוב לא נחות | Y6: לא | Z6: 0.77 | AA6: 1 | AB6: 148.91 | AD6: 0.001 | AG6: שווי הוגן | AH6: 0 | AI6: 3.1514253e-07 | AJ6: 1.2715816e-07
A7: 337 | B7: 1405 | C7: או.פי.סי. אנרגיה בע"מ | D7: 514401702 | E7: ח.פ | F7: או פי סי אגח ב' | G7: IL0011660573 | H7: ISIN | I7: צמוד למדד המחירים לצרכן | J7: ישראל | K7: ישראל | L7: סחיר | M7: TASE | N7: אנרגיה | O7: לא | P7: A+ | Q7: S&P מעלות | R7: נייר ערך | S7: ILS | T7: 2.472 | U7: 01/10/2028 | V7: 0.0275 | W7: 0.03084 | X7: החוב לא נחות | Y7: לא | Z7: 32076.49 | AA7: 1 | AB7: 116.37 | AD7: 37.327 | AG7: שווי הוגן | AH7: 4.3e-05 | AI7: 0.010259361 | AJ7: 0.0041395917
A8: 337 | B8: 1405 | C8: איי.סי.אל גרופ בע"מ (דואלי) | D8: 520027830 | E8: ח.פ | F8: אייסיאל אגח ז | G8: IL0028103724 | H8: ISIN | I8: לא צמוד למדד המחירים לצרכן | J8: ישראל | K8: ישראל | L8: סחיר | M8: TASE | N8: כימיה, גומי ופלסטיק | O8: לא | P8: AA | Q8: S&P מעלות | R8: נייר ערך | S8: ILS | T8: 7.331 | U8: 30/12/2034 | V8: 0.024 | W8: 0.04694 | X8: החוב לא נחות | Y8: לא | Z8: 57491 | AA8: 1 | AB8: 84.92 | AD8: 48.821 | AG8: שווי הוגן | AH8: 3.7e-05 | AI8: 0.013418448 | AJ8: 0.0054142646
A9: 337 | B9: 1405 | C9: איירפורט סיטי בע"מ | D9: 511659401 | E9: ח.פ | F9: איירפורט אגח ה | G9: IL0011334872 | H9: ISIN | I9: צמוד למדד המחירים לצרכן | J9: ישראל | K9: ישראל | L9: סחיר | M9: TASE | N9: נדל"ן מניב בישראל | O9: לא | P9: AA | Q9: S&P מעלות | R9: נייר ערך | S9: ILS | T9: 2.014 | U9: 28/02/2029 | V9: 0.0234 | W9: 0.02872 | X9: החוב לא נחות | Y9: לא | Z9: 44835.17 | AA9: 1 | AB9: 116.49 | AD9: 52.228 | AG9: שווי הוגן | AH9: 2.8e-05 | AI9: 0.014354891 | AJ9: 0.005792114
A10: 337 | B10: 1405 | C10: איסתא בע"מ | D10: 520042763 | E10: ח.פ | F10: איסתא אגח א להמרה | G10: IL0011971285 | H10: ISIN | I10: אג"ח להמרה לא צמוד למדד המחירים לצרכן | J10: ישראל | K10: ישראל | L10: סחיר | M10: TASE | N10: מלונאות ותיירות | O10: לא | P10: NR | Q10: NR | R10: NR | S10: ILS | T10: 2.839 | U10: 30/06/2028 | V10: 0.0485 | W10: 0.0001 | X10: החוב לא נחות | Y10: לא | Z10: 13000 | AA10: 1 | AB10: 115 | AD10: 14.95 | AG10: שווי הוגן | AH10: 4.3e-05 | AI10: 0.0041089761 | AJ10: 0.0016579477
A11: 337 | B11: 1405 | C11: אלבר שירותי מימונית בע"מ | D11: 512025891 | E11: ח.פ | F11: אלבר אגח יט | G11: IL0011918245 | H11: ISIN | I11: צמוד למדד המחירים לצרכן | J11: ישראל | K11: ישראל | L11: סחיר | M11: TASE | N11: שירותים | O11: לא | P11: A+ | Q11: S&P מעלות | R11: נייר ערך | S11: ILS | T11: 1.451 | U11: 15/05/2028 | V11: 0.032 | W11: 0.03223 | X11: החוב לא נחות | Y11: לא | Z11: 6000 | AA11: 1 | AB11: 109.13 | AD11: 6.548 | AG11: שווי הוגן | AH11: 9e-06 | AI11: 0.0017996491 | AJ11: 0.00072614782
A12: 337 | B12: 1405 | C12: אלבר שירותי מימונית בע"מ | D12: 512025891 | E12: ח.פ | F12: אלבר אגח כ | G12: IL0011918328 | H12: ISIN | I12: לא צמוד למדד המחירים לצרכן | J12: ישראל | K12: ישראל | L12: סחיר | M12: TASE | N12: שירותים | O12: לא | P12: A+ | Q12: S&P מעלות | R12: נייר ערך | S12: ILS | T12: 1.518 | U12: 20/06/2028 | V12: 0.057 | W12: 0.05189 | X12: החוב לא נחות | Y12: לא | Z12: 7200 | AA12: 1 | AB12: 101.09 | AD12: 7.278 | AG12: שווי הוגן | AH12: 9e-06 | AI12: 0.002000475 | AJ12: 0.00080717987
A13: 337 | B13: 1405 | C13: אלדן תחבורה בע"מ | D13: 510454333 | E13: ח.פ | F13: אלדן תחבורה אגח ח | G13: IL0011924425 | H13: ISIN | I13: צמוד למדד המחירים לצרכן | J13: ישראל | K13: ישראל | L13: סחיר | M13: TASE | N13: שירותים | O13: לא | P13: A+ | Q13: S&P מעלות | R13: נייר ערך | S13: ILS | T13: 2.168 | U13: 30/09/2029 | V13: 0.0323 | W13: 0.02972 | X13: החוב לא נחות | Y13: לא | Z13: 10080 | AA13: 1 | AB13: 110.07 | AD13: 11.095 | AG13: שווי הוגן | AH13: 2e-05 | AI13: 0.0030494529 | AJ13: 0.0012304363
A14: 337 | B14: 1405 | C14: אלה ר. הנדסת בנין והשקעות בע"מ | D14: 520040015 | E14: ח.פ | F14: אלה ר השקע אגח א | G14: IL0011899502 | H14: ISIN | I14: צמוד למדד המחירים לצרכן | J14: ישראל | K14: ישראל | L14: סחיר | M14: TASE | N14: נדל"ן מניב בישראל | O14: לא | P14: A | Q14: S&P מעלות | R14: נייר ערך | S14: ILS | T14: 2.176 | U14: 01/07/2029 | V14: 0.0249 | W14: 0.03135 | X14: החוב לא נחות | Y14: לא | Z14: 18400 | AA14: 1 | AB14: 108.03 | AD14: 19.878 | AG14: שווי הוגן | AH14: 9.9e-05 | AI14: 0.0054632947 | AJ14: 0.0022044073
... A61: 337 | B61: 1405 | C61: יו.אמ.איץ' פרופרטיס אינק. | D61: 221890929 | E61: מספר תאגיד או שותפות בחו"ל | F61: יו.אמ.איץ' אגח א | G61: IL0011841678 | H61: ISIN | I61: צמוד למט"ח | J61: ישראל | K61: ארה"ב | L61: סחיר | M61: TASE | N61: נדל"ן מניב בחו"ל | O61: לא | P61: AA- | Q61: S&P מעלות | R61: נייר ערך | S61: USD | T61: 1.592 | U61: 28/02/2027 | V61: 0.0472 | W61: 0.05895 | X61: החוב לא נחות | Y61: לא | Z61: 18000 | AA61: 3.372 | AB61: 31.234 | AD61: 18.958 | AG61: שווי הוגן | AH61: 5.5e-05 | AI61: 0.0052104566 | AJ61: 0.0021023886
A62: 337 | B62: 1405 | C62: קבוצת יובלים השקעות בע"מ | D62: 514625094 | E62: ח.פ | F62: יובלים אגח ב | G62: IL0011869075 | H62: ISIN | I62: לא צמוד למדד המחירים לצרכן | J62: ישראל | K62: ישראל | L62: סחיר | M62: TASE | N62: בנייה | O62: לא | P62: NR | Q62: NR | R62: NR | S62: ILS | T62: 0.995 | U62: 05/07/2026 | V62: 0.056 | W62: 0.05842 | X62: החוב לא נחות | Y62: לא | Z62: 13600 | AA62: 1 | AB62: 99.8 | AC62: 3.876 | AD62: 17.449 | AG62: שווי הוגן | AH62: 0.0001 | AI62: 0.0047957661 | AJ62: 0.0019350634
A63: 337 | B63: 1405 | C63: יוחננוף | D63: 511344186 | E63: ח.פ | F63: יוחננוף אגח א | G63: IL0011874182 | H63: ISIN | I63: לא צמוד למדד המחירים לצרכן | J63: ישראל | K63: ישראל | L63: סחיר | M63: TASE | N63: רשתות שיווק | O63: לא | P63: A1 | Q63: מידרוג Moodys | R63: נייר ערך | S63: ILS | T63: 3.431 | U63: 01/07/2032 | V63: 0.0394 | W63: 0.04604 | X63: החוב לא נחות | Y63: לא | Z63: 1264.2 | AA63: 1 | AB63: 97.95 | AC63: 0.117 | AD63: 1.355 | AG63: שווי הוגן | AH63: 9e-06 | AI63: 0.00037249144 | AJ63: 0.0001502981
A64: 337 | B64: 1405 | C64: ירושלים מימון והנפקות (2005) בע"מ | D64: 513682146 | E64: ח.פ | F64: ירושלים הנפ אגח יט | G64: IL0012014333 | H64: ISIN | I64: צמוד למדד המחירים לצרכן | J64: ישראל | K64: ישראל | L64: סחיר | M64: TASE | N64: בנקים | O64: לא | P64: AA- | Q64: S&P מעלות | R64: נייר ערך | S64: ILS | T64: 3.874 | U64: 31/01/2031 | V64: 0.0259 | W64: 0.02747 | X64: החוב לא נחות | Y64: לא | Z64: 10000 | AA64: 1 | AB64: 105.24 | AD64: 10.524 | AG64: שווי הוגן | AH64: 1.5e-05 | AI64: 0.0028924993 | AJ64: 0.0011671065
A65: 337 | B65: 1405 | C65: ישפרו בע"מ | D65: 516291754 | E65: ח.פ | F65: ישפרו אגח א | G65: IL0012022906 | H65: ISIN | I65: צמוד למדד המחירים לצרכן | J65: ישראל | K65: ישראל | L65: סחיר | M65: TASE | N65: נדל"ן מניב בישראל | O65: לא | P65: NR | Q65: NR | R65: NR | S65: ILS | T65: 2.361 | U65: 31/12/2027 | V65: 0.045 | W65: 0.03339 | X65: החוב לא נחות | Y65: לא | Z65: 16000 | AA65: 1 | AB65: 108.49 | AD65: 17.358 | AG65: שווי הוגן | AH65: 1.6e-05 | AI65: 0.0047709198 | AJ65: 0.0019250381
A66: 337 | B66: 1405 | C66: ישראל קנדה (ט.ר) בעמ | D66: 520039298 | E66: ח.פ | F66: ישראל קנדה אגח ז | G66: IL0043402127 | H66: ISIN | I66: לא צמוד למדד המחירים לצרכן | J66: ישראל | K66: ישראל | L66: סחיר | M66: TASE | N66: בנייה | O66: לא | P66: A- | Q66: S&P מעלות | R66: נייר ערך | S66: ILS | T66: 1.457 | U66: 30/06/2027 | V66: 0.0395 | W66: 0.05565 | X66: החוב לא נחות | Y66: לא | Z66: 20300 | AA66: 1 | AB66: 97.85 | AD66: 19.864 | AG66: שווי הוגן | AH66: 3.5e-05 | AI66: 0.0054594551 | AJ66: 0.002202858
A67: 337 | B67: 1405 | C67: ישראמקו נגב 2 שותפות מוגבלת | D67: 550010003 | E67: מספר שותפות | F67: ישראמקו אגח ג | G67: IL0023202323 | H67: ISIN | I67: לא צמוד למדד המחירים לצרכן | J67: ישראל | K67: ישראל | L67: סחיר | M67: TASE | N67: חיפושי נפט וגז | O67: לא | P67: AA | Q67: S&P מעלות | R67: נייר ערך | S67: ILS | T67: 2.93 | U67: 10/10/2030 | V67: 0.0224 | W67: 0.04589 | X67: החוב לא נחות | Y67: לא | Z67: 47133.71 | AA67: 1 | AB67: 94.01 | AD67: 44.31 | AG67: שווי הוגן | AH67: 8.8e-05 | AI67: 0.012178621 | AJ67: 0.0049140018
A68: 337 | B68: 1405 | C68: ישרס חברה להשקעות בע"מ | D68: 520017807 | E68: ח.פ | F68: ישרס אגח טו | G68: IL0061302076 | H68: ISIN | I68: צמוד למדד המחירים לצרכן | J68: ישראל | K68: ישראל | L68: סחיר | M68: TASE | N68: נדל"ן מניב בישראל | O68: לא | P68: AA | Q68: S&P מעלות | R68: נייר ערך | S68: ILS | T68: 1.757 | U68: 16/05/2027 | V68: 0.0158 | W68: 0.02779 | X68: החוב לא נחות | Y68: לא | Z68: 0.26 | AA68: 1 | AB68: 116.04 | AD68: 0 | AG68: שווי הוגן | AH68: 0 | AI68: 8.2922712e-08 | AJ68: 3.3458826e-08
A69: 337 | B69: 1405 | C69: ישרס חברה להשקעות בע"מ | D69: 520017807 | E69: ח.פ | F69: ישרס אגח טז | G69: IL0061302233 | H69: ISIN | I69: צמוד למדד המחירים לצרכן | J69: ישראל | K69: ישראל | L69: סחיר | M69: TASE | N69: נדל"ן מניב בישראל | O69: לא | P69: AA- | Q69: S&P מעלות | R69: נייר ערך | S69: ILS | T69: 2.975 | U69: 30/07/2031 | V69: 0.024 | W69: 0.02959 | X69: החוב לא נחות | Y69: לא | Z69: 26447.37 | AA69: 1 | AB69: 117.41 | AD69: 31.052 | AG69: שווי הוגן | AH69: 2.2e-05 | AI69: 0.0085345378 | AJ69: 0.0034436358
A70: 337 | B70: 1405 | C70: ישרס חברה להשקעות בע"מ | D70: 520017807 | E70: ח.פ | F70: ישרס אגח יח | G70: IL0061302803 | H70: ISIN | I70: צמוד למדד המחירים לצרכן | J70: ישראל | K70: ישראל | L70: סחיר | M70: TASE | N70: נדל"ן מניב בישראל | O70: לא | P70: AA | Q70: S&P מעלות | R70: נייר ערך | S70: ILS | T70: 4.224 | U70: 10/04/2030 | V70: 0.0084 | W70: 0.02787 | X70: החוב לא נחות | Y70: לא | Z70: 20549.46 | AA70: 1 | AB70: 107.28 | AD70: 22.045 | AG70: שווי הוגן | AH70: 2.7e-05 | AI70: 0.0060591486 | AJ70: 0.0024448308
A71: 337 | B71: 1405 | C71: כלל החזקות עסקי ביטוח בע"מ | D71: 520036120 | E71: ח.פ | F71: כלל ביטוח אגח ג | G71: IL0012013913 | H71: ISIN | I71: לא צמוד למדד המחירים לצרכן | J71: ישראל | K71: ישראל | L71: סחיר | M71: TASE | N71: ביטוח | O71: לא | P71: AA- | Q71: S&P מעלות | R71: נייר ערך | S71: ILS | T71: 4.694 | U71: 02/11/2031 | V71: 0.0525 | W71: 0.04653 | X71: החוב לא נחות | Y71: לא | Z71: 15000 | AA71: 1 | AB71: 103.89 | AD71: 15.584 | AG71: שווי הוגן | AH71: 3e-05 | AI71: 0.0042830923 | AJ71: 0.0017282025
A72: 337 | B72: 1405 | C72: כללביט מימון בע"מ | D72: 513754069 | E72: ח.פ | F72: כלל הון אגח יד | G72: IL0012205246 | H72: ISIN | I72: לא צמוד למדד המחירים לצרכן | J72: ישראל | K72: ישראל | L72: סחיר | M72: TASE | N72: ביטוח | O72: לא | P72: AA- | Q72: S&P מעלות | R72: נייר ערך | S72: ILS | T72: 8.511 | U72: 30/09/2039 | V72: 0.0551 | W72: 0.05145 | X72: החוב לא נחות | Y72: לא | Z72: 17000 | AA72: 1 | AB72: 104.59 | AD72: 17.78 | AG72: שווי הוגן | AH72: 3.4e-05 | AI72: 0.0048868782 | AJ72: 0.0019718266
A73: 337 | B73: 1405 | C73: בנק לאומי לישראל בע"מ | D73: 520018078 | E73: ח.פ | F73: לאומי אגח 185 | G73: IL0012018219 | H73: ISIN | I73: צמוד למדד המחירים לצרכן | J73: ישראל | K73: ישראל | L73: סחיר | M73: TASE | N73: בנקים | O73: לא | P73: AAA | Q73: S&P מעלות | R73: נייר ערך | S73: ILS | T73: 2.092 | U73: 31/08/2029 | V73: 0.0186 | W73: 0.02568 | X73: החוב לא נחות | Y73: לא | Z73: 14400 | AA73: 1 | AB73: 104.2 | AD73: 15.005 | AG73: שווי הוגן | AH73: 5e-06 | AI73: 0.0041240378 | AJ73: 0.001664025
A74: 337 | B74: 1405 | C74: בנק לאומי לישראל בע"מ | D74: 520018078 | E74: ח.פ | F74: לאומי אגח 186 | G74: IL0012018391 | H74: ISIN | I74: צמוד למדד המחירים לצרכן | J74: ישראל | K74: ישראל | L74: סחיר | M74: TASE | N74: בנקים | O74: לא | P74: AAA | Q74: S&P מעלות | R74: נייר ערך | S74: ILS | T74: 4.388 | U74: 30/11/2033 | V74: 0.0202 | W74: 0.02636 | X74: החוב לא נחות | Y74: לא | Z74: 66000 | AA74: 1 | AB74: 102.52 | AD74: 67.663 | AG74: שווי הוגן | AH74: 1.8e-05 | AI74: 0.018597089 | AJ74: 0.0075038158
A75: 337 | B75: 1405 | C75: בנק לאומי לישראל בע"מ | D75: 520018078 | E75: ח.פ | F75: לאומי אגח סד 183 | G75: IL0060405474 | H75: ISIN | I75: צמוד למדד המחירים לצרכן | J75: ישראל | K75: ישראל | L75: סחיר | M75: TASE | N75: בנקים | O75: לא | P75: AAA | Q75: S&P מעלות | R75: נייר ערך | S75: ILS | T75: 4.392 | U75: 25/11/2029 | V75: 0.001 | W75: 0.02581 | X75: החוב לא נחות | Y75: לא | Z75: 79000 | AA75: 1 | AB75: 102.6 | AD75: 81.054 | AG75: שווי הוגן | AH75: 1.8e-05 | AI75: 0.022277522 | AJ75: 0.008988849
... A89: 337 | B89: 1405 | C89: מזרחי טפחות חברה להנפקות בע"מ | D89: 520032046 | E89: ח.פ | F89: מז טפ הנ אגח 67 | G89: IL0011968075 | H89: ISIN | I89: צמוד למדד המחירים לצרכן | J89: ישראל | K89: ישראל | L89: סחיר | M89: TASE | N89: בנקים | O89: לא | P89: AAA | Q89: S&P מעלות | R89: נייר ערך | S89: ILS | T89: 4.216 | U89: 12/06/2033 | V89: 0.0206 | W89: 0.0259 | X89: החוב לא נחות | Y89: לא | Z89: 80000 | AA89: 1 | AB89: 103.97 | AD89: 83.176 | AG89: שווי הוגן | AH89: 5e-05 | AI89: 0.022860749 | AJ89: 0.0092241777
A90: 337 | B90: 1405 | C90: מזרחי טפחות חברה להנפקות בע"מ | D90: 520032046 | E90: ח.פ | F90: מז טפ הנפק 52 | G90: IL0023103810 | H90: ISIN | I90: צמוד למדד המחירים לצרכן | J90: ישראל | K90: ישראל | L90: סחיר | M90: TASE | N90: בנקים | O90: לא | P90: AAA | Q90: S&P מעלות | R90: נייר ערך | S90: ILS | T90: 4.979 | U90: 01/07/2030 | V90: 0.002 | W90: 0.02616 | X90: החוב לא נחות | Y90: לא | Z90: 21000 | AA90: 1 | AB90: 104.05 | AC90: 0.049 | AD90: 21.9 | AG90: שווי הוגן | AH90: 6e-06 | AI90: 0.0060190894 | AJ90: 0.0024286671
A91: 337 | B91: 1405 | C91: מזרחי טפחות חברה להנפקות בע"מ | D91: 520032046 | E91: ח.פ | F91: מזרחי טפחות הנפק אגח 64 | G91: IL0023105559 | H91: ISIN | I91: צמוד למדד המחירים לצרכן | J91: ישראל | K91: ישראל | L91: סחיר | M91: TASE | N91: בנקים | O91: לא | P91: AAA | Q91: S&P מעלות | R91: נייר ערך | S91: ILS | T91: 3.203 | U91: 13/04/2031 | V91: 0.001 | W91: 0.02586 | X91: החוב לא נחות | Y91: לא | Z91: 42858.06 | AA91: 1 | AB91: 104.36 | AD91: 44.727 | AG91: שווי הוגן | AH91: 1.9e-05 | AI91: 0.012293032 | AJ91: 0.004960166
A92: 337 | B92: 1405 | C92: מימון ישיר מקבוצת ישיר 2006 בע"מ | D92: 513893123 | E92: ח.פ | F92: מימון ישיר אגח ה | G92: IL0011828311 | H92: ISIN | I92: צמוד למדד המחירים לצרכן | J92: ישראל | K92: ישראל | L92: סחיר | M92: TASE | N92: אשראי חוץ בנקאי | O92: לא | P92: A1 | Q92: מידרוג Moodys | R92: נייר ערך | S92: ILS | T92: 2.782 | U92: 31/07/2031 | V92: 0.01 | W92: 0.03107 | X92: החוב לא נחות | Y92: לא | Z92: 23828.88 | AA92: 1 | AB92: 108.19 | AD92: 25.78 | AG92: שווי הוגן | AH92: 1.3e-05 | AI92: 0.0070857068 | AJ92: 0.002859041
A93: 337 | B93: 1405 | C93: מימון ישיר מקבוצת ישיר 2006 בע"מ | D93: 513893123 | E93: ח.פ | F93: מימון ישיר אגח ו | G93: IL0011916595 | H93: ISIN | I93: צמוד למדד המחירים לצרכן | J93: ישראל | K93: ישראל | L93: סחיר | M93: TASE | N93: אשראי חוץ בנקאי | O93: לא | P93: A1 | Q93: מידרוג Moodys | R93: נייר ערך | S93: ILS | T93: 1.056 | U93: 31/03/2027 | V93: 0.0354 | W93: 0.03425 | X93: החוב לא נחות | Y93: לא | Z93: 20700 | AA93: 1 | AB93: 109.8 | AD93: 22.729 | AG93: שווי הוגן | AH93: 2.1e-05 | AI93: 0.006246908 | AJ93: 0.0025205906
A94: 337 | B94: 1405 | C94: מימון ישיר מקבוצת ישיר 2006 בע"מ | D94: 513893123 | E94: ח.פ | F94: מימון ישיר ד | G94: IL0011756603 | H94: ISIN | I94: צמוד למדד המחירים לצרכן | J94: ישראל | K94: ישראל | L94: סחיר | M94: TASE | N94: אשראי חוץ בנקאי | O94: לא | P94: A1 | Q94: מידרוג Moodys | R94: נייר ערך | S94: ILS | T94: 0.179 | U94: 01/02/2026 | V94: 0.01 | W94: 0.03569 | X94: החוב לא נחות | Y94: לא | Z94: 16800 | AA94: 1 | AB94: 115.84 | AD94: 19.461 | AG94: שווי הוגן | AH94: 9.9e-05 | AI94: 0.005348848 | AJ94: 0.0021582287
A95: 337 | B95: 1405 | C95: מליסרון בע"מ | D95: 520037789 | E95: ח.פ | F95: מליסרון אגח יט | G95: IL0032303989 | H95: ISIN | I95: צמוד למדד המחירים לצרכן | J95: ישראל | K95: ישראל | L95: סחיר | M95: TASE | N95: נדל"ן מניב בישראל | O95: לא | P95: AA | Q95: S&P מעלות | R95: נייר ערך | S95: ILS | T95: 3.744 | U95: 01/07/2029 | V95: 0.0143 | W95: 0.0281 | X95: החוב לא נחות | Y95: לא | Z95: 66172 | AA95: 1 | AB95: 111.28 | AC95: 1.42 | AD95: 75.057 | AG95: שווי הוגן | AH95: 3.4e-05 | AI95: 0.020629152 | AJ95: 0.0083237415
A96: 337 | B96: 1405 | C96: מליסרון בע"מ | D96: 520037789 | E96: ח.פ | F96: מליסרון אגח כא | G96: IL0011946386 | H96: ISIN | I96: צמוד למדד המחירים לצרכן | J96: ישראל | K96: ישראל | L96: סחיר | M96: TASE | N96: נדל"ן מניב בישראל | O96: לא | P96: AA | Q96: S&P מעלות | R96: נייר ערך | S96: ILS | T96: 5.598 | U96: 01/01/2037 | V96: 0.0361 | W96: 0.02928 | X96: החוב לא נחות | Y96: לא | Z96: 20892.86 | AA96: 1 | AB96: 111.6 | AC96: 0.464 | AD96: 23.78 | AG96: שווי הוגן | AH96: 1.3e-05 | AI96: 0.0065358891 | AJ96: 0.0026371928
A97: 337 | B97: 1405 | C97: מליסרון בע"מ | D97: 520037789 | E97: ח.פ | F97: מליסרון אגח יז | G97: IL0032302734 | H97: ISIN | I97: צמוד למדד המחירים לצרכן | J97: ישראל | K97: ישראל | L97: סחיר | M97: TASE | N97: נדל"ן מניב בישראל | O97: לא | P97: AA | Q97: S&P מעלות | R97: נייר ערך | S97: ILS | T97: 3.33 | U97: 01/01/2032 | V97: 0.0225 | W97: 0.02861 | X97: החוב לא נחות | Y97: לא | Z97: 18870.72 | AA97: 1 | AB97: 116.27 | AC97: 0.6 | AD97: 22.541 | AG97: שווי הוגן | AH97: 1.1e-05 | AI97: 0.0061952823 | AJ97: 0.0024997599
A98: 337 | B98: 1405 | C98: מליסרון בע"מ | D98: 520037789 | E98: ח.פ | F98: מליסרון אגח כ | G98: IL0032304227 | H98: ISIN | I98: צמוד למדד המחירים לצרכן | J98: ישראל | K98: ישראל | L98: סחיר | M98: TASE | N98: נדל"ן מניב בישראל | O98: לא | P98: AA | Q98: S&P מעלות | R98: נייר ערך | S98: ILS | T98: 4.692 | U98: 01/07/2030 | V98: 0.0025 | W98: 0.02702 | X98: החוב לא נחות | Y98: לא | Z98: 42140 | AA98: 1 | AB98: 102.52 | AC98: 0.624 | AD98: 43.826 | AG98: שווי הוגן | AH98: 3.2e-05 | AI98: 0.012045462 | AJ98: 0.0048602729
A99: 337 | B99: 1405 | C99: מנורה מבטחים גיוס הון בע"מ | D99: 513937714 | E99: ח.פ | F99: מנורה הון התח סד' ט | G99: IL0012193699 | H99: ISIN | I99: לא צמוד למדד המחירים לצרכן | J99: ישראל | K99: ישראל | L99: סחיר | M99: TASE | N99: ביטוח | O99: לא | P99: Aa3 | Q99: מידרוג Moodys | R99: נייר ערך | S99: ILS | T99: 6.099 | U99: 30/09/2035 | V99: 0.0502 | W99: 0.04789 | X99: החוב לא נחות | Y99: לא | Z99: 16000 | AA99: 1 | AB99: 103.09 | AD99: 16.494 | AG99: שווי הוגן | AH99: 4e-05 | AI99: 0.0045334512 | AJ99: 0.0018292209
A100: 337 | B100: 1405 | C100: מניף - שירותים פיננסים בע"מ | D100: 512764408 | E100: ח.פ | F100: מניף אגח א | G100: IL0011858839 | H100: ISIN | I100: לא צמוד למדד המחירים לצרכן | J100: ישראל | K100: ישראל | L100: סחיר | M100: TASE | N100: אשראי חוץ בנקאי | O100: לא | P100: A3 | Q100: מידרוג Moodys | R100: נייר ערך | S100: ILS | T100: 0.731 | U100: 30/09/2026 | V100: 0.114 | W100: 0.0591 | X100: החוב לא נחות | Y100: לא | Z100: 15410 | AA100: 1 | AB100: 102.52 | AD100: 15.798 | AG100: שווי הוגן | AH100: 6.4e-05 | AI100: 0.0043421384 | AJ100: 0.0017520273
A101: 337 | B101: 1405 | C101: מניף - שירותים פיננסים בע"מ | D101: 512764408 | E101: ח.פ | F101: מניף אגח ג | G101: IL0012167206 | H101: ISIN | I101: לא צמוד למדד המחירים לצרכן | J101: ישראל | K101: ישראל | L101: סחיר | M101: TASE | N101: אשראי חוץ בנקאי | O101: לא | P101: A3 | Q101: מידרוג Moodys | R101: נייר ערך | S101: ILS | T101: 3.107 | U101: 30/11/2029 | V101: 0.064 | W101: 0.05565 | X101: החוב לא נחות | Y101: לא | Z101: 10000 | AA101: 1 | AB101: 103.33 | AD101: 10.333 | AG101: שווי הוגן | AH101: 2.9e-05 | AI101: 0.0028400034 | AJ101: 0.0011459246
A102: 337 | B102: 1405 | C102: קבוצת מנרב בע"מ | D102: 520034505 | E102: ח.פ | F102: מנרב אגח ד | G102: IL0015501690 | H102: ISIN | I102: צמוד למדד המחירים לצרכן | J102: ישראל | K102: ישראל | L102: סחיר | M102: TASE | N102: בנייה | O102: לא | P102: Baa1 | Q102: מידרוג Moodys | R102: נייר ערך | S102: ILS | T102: 3.546 | U102: 15/04/2032 | V102: 0.0207 | W102: 0.03721 | X102: החוב לא נחות | Y102: לא | Z102: 24889.6 | AA102: 1 | AB102: 107.9 | AD102: 26.856 | AG102: שווי הוגן | AH102: 6e-05 | AI102: 0.0073812819 | AJ102: 0.0029783038
A103: 337 | B103: 1405 | C103: נאוויטס פטרוליום, שותפות מוגבלת | D103: 550263107 | E103: מספר שותפות | F103: נאוויטס פטרו אגח ג | G103: IL0011815938 | H103: ISIN | I103: לא צמוד למדד המחירים לצרכן | J103: ישראל | K103: ישראל | L103: סחיר | M103: TASE | N103: חיפושי נפט וגז | O103: לא | P103: A- | Q103: S&P מעלות | R103: נייר ערך | S103: ILS | T103: 1.709 | U103: 15/10/2028 | V103: 0.0525 | W103: 0.05182 | X103: החוב לא נחות | Y103: לא | Z103: 34000 | AA103: 1 | AB103: 102.65 | AD103: 34.901 | AG103: שווי הוגן | AH103: 0.000103 | AI103: 0.0095924667 | AJ103: 0.0038705038
A104: 337 | B104: 1405 | C104: נאוויטס פטרוליום, שותפות מוגבלת | D104: 550263107 | E104: מספר שותפות | F104: נאוויטס פטרו אגח ה | G104: IL0011979122 | H104: ISIN | I104: לא צמוד למדד המחירים לצרכן | J104: ישראל | K104: ארה"ב | L104: סחיר | M104: TASE | N104: חיפושי נפט וגז | O104: לא | P104: A- | Q104: S&P מעלות | R104: נייר ערך | S104: ILS | T104: 2.554 | U104: 31/12/2028 | V104: 0.065 | W104: 0.05201 | X104: החוב לא נחות | Y104: לא | Z104: 21000 | AA104: 1 | AB104: 103.44 | AD104: 21.722 | AG104: שווי הוגן | AH104: 4.2e-05 | AI104: 0.0059703561 | AJ104: 0.0024090035
A105: 337 | B105: 1405 | C105: נאוויטס פטרוליום, שותפות מוגבלת | D105: 550263107 | E105: מספר שותפות | F105: נאוויטס פטרו אגח ו | G105: IL0012048257 | H105: ISIN | I105: לא צמוד למדד המחירים לצרכן | J105: ישראל | K105: ישראל | L105: סחיר | M105: TASE | N105: חיפושי נפט וגז | O105: לא | P105: A- | Q105: S&P מעלות | R105: נייר ערך | S105: ILS | T105: 3.129 | U105: 30/09/2029 | V105: 0.067 | W105: 0.05114 | X105: החוב לא נחות | Y105: לא | Z105: 17000 | AA105: 1 | AB105: 106.88 | AD105: 18.17 | AG105: שווי הוגן | AH105: 1.9e-05 | AI105: 0.0049938765 | AJ105: 0.0020149998
A106: 337 | B106: 1405 | C106: ע.י נופר אנרגי' בע"מ | D106: 514599943 | E106: ח.פ | F106: נופר אנרג אגח א | G106: IL0011793408 | H106: ISIN | I106: צמוד למדד המחירים לצרכן | J106: ישראל | K106: ישראל | L106: סחיר | M106: TASE | N106: אנרגיה מתחדשת | O106: לא | P106: A3 | Q106: מידרוג Moodys | R106: נייר ערך | S106: ILS | T106: 2.159 | U106: 31/12/2027 | V106: 0.0148 | W106: 0.02986 | X106: החוב לא נחות | Y106: לא | Z106: 21780 | AA106: 1 | AB106: 111.27 | AD106: 24.235 | AG106: שווי הוגן | AH106: 7.5e-05 | AI106: 0.0066608306 | AJ106: 0.002687606
A107: 337 | B107: 1405 | C107: חברה לנכסים ולבנין בע"מ | D107: 520025438 | E107: ח.פ | F107: נכסים ובניין אגח ט | G107: IL0069902125 | H107: ISIN | I107: לא צמוד למדד המחירים לצרכן | J107: ישראל | K107: ישראל | L107: סחיר | M107: TASE | N107: נדל"ן מניב בישראל | O107: לא | P107: A | Q107: S&P מעלות | R107: נייר ערך | S107: ILS | T107: 2.363 | U107: 01/07/2029 | V107: 0.0395 | W107: 0.05326 | X107: החוב לא נחות | Y107: לא | Z107: 24729.24 | AA107: 1 | AB107: 97.03 | AD107: 23.995 | AG107: שווי הוגן | AH107: 2.1e-05 | AI107: 0.0065949154 | AJ107: 0.0026610095
A108: 337 | B108: 1405 | C108: חברה לנכסים ולבנין בע"מ | D108: 520025438 | E108: ח.פ | F108: נכסים ובנין אגח י | G108: IL0011936304 | H108: ISIN | I108: צמוד למדד המחירים לצרכן | J108: ישראל | K108: ישראל | L108: סחיר | M108: TASE | N108: נדל"ן מניב בישראל | O108: לא | P108: A | Q108: S&P מעלות | R108: נייר ערך | S108: ILS | T108: 3.557 | U108: 01/07/2029 | V108: 0.0362 | W108: 0.03002 | X108: החוב לא נחות | Y108: לא | Z108: 11100 | AA108: 1 | AB108: 110.37 | AD108: 12.251 | AG108: שווי הוגן | AH108: 6e-06 | AI108: 0.0033671809 | AJ108: 0.0013586377
A109: 337 | B109: 1405 | C109: נמקו ריאליטי לטד | D109: 1905761 | E109: מספר תאגיד או שותפות בחו"ל | F109: נמקו אגח ב' 2020/2032 4.5% | G109: IL0011602583 | H109: ISIN | I109: לא צמוד למדד המחירים לצרכן | J109: ישראל | K109: ארה"ב | L109: סחיר | M109: TASE | N109: נדל"ן מניב בחו"ל | O109: לא | P109: AA- | Q109: S&P מעלות | R109: נייר ערך | S109: ILS | T109: 3.359 | U109: 15/10/2032 | V109: 0.045 | W109: 0.05524 | X109: החוב לא נחות | Y109: לא | Z109: 18855.84 | AA109: 1 | AB109: 97.83 | AD109: 18.447 | AG109: שווי הוגן | AH109: 2.3e-05 | AI109: 0.0050700281 | AJ109: 0.0020457265
A110: 337 | B110: 1405 | C110: נמקו ריאליטי לטד | D110: 1905761 | E110: מספר תאגיד או שותפות בחו"ל | F110: נמקו אגח ג | G110: IL0011987612 | H110: ISIN | I110: לא צמוד למדד המחירים לצרכן | J110: ישראל | K110: ישראל | L110: סחיר | M110: TASE | N110: נדל"ן מניב בחו"ל | O110: לא | P110: AA | Q110: S&P מעלות | R110: נייר ערך | S110: ILS | T110: 1.877 | U110: 30/06/2027 | V110: 0.0635 | W110: 0.0533 | X110: החוב לא נחות | Y110: לא | Z110: 9700 | AA110: 1 | AB110: 102.04 | AD110: 9.898 | AG110: שווי הוגן | AH110: 2.4e-05 | AI110: 0.0027204116 | AJ110: 0.0010976701
... A116: 337 | B116: 1405 | C116: ספנסר אקוויטי גרופ לימיטד | D116: 1838863 | E116: מספר תאגיד או שותפות בחו"ל | F116: ספנסר אגח ב | G116: IL0011398984 | H116: ISIN | I116: לא צמוד למדד המחירים לצרכן | J116: ישראל | K116: ארה"ב | L116: סחיר | M116: TASE | N116: נדל"ן מניב בחו"ל | O116: לא | P116: A | Q116: S&P מעלות | R116: נייר ערך | S116: ILS | T116: 1.638 | U116: 31/03/2028 | V116: 0.0515 | W116: 0.06041 | X116: החוב לא נחות | Y116: לא | Z116: 0.49 | AA116: 1 | AB116: 101.87 | AD116: 0 | AG116: שווי הוגן | AH116: 0 | AI116: 1.371939e-07 | AJ116: 5.5356933e-08
A117: 337 | B117: 1405 | C117: קבוצת עזריאלי בע"מ (לשעבר קנית מימון) | D117: 510960719 | E117: ח.פ | F117: עזריאלי אגח ד | G117: IL0011386500 | H117: ISIN | I117: צמוד למדד המחירים לצרכן | J117: ישראל | K117: ישראל | L117: סחיר | M117: TASE | N117: נדל"ן מניב בישראל | O117: לא | P117: AA+ | Q117: S&P מעלות | R117: נייר ערך | S117: ILS | T117: 2.678 | U117: 05/07/2030 | V117: 0.0134 | W117: 0.02803 | X117: החוב לא נחות | Y117: לא | Z117: 35000 | AA117: 1 | AB117: 114.07 | AC117: 4.456 | AD117: 44.38 | AG117: שווי הוגן | AH117: 1.6e-05 | AI117: 0.012197777 | AJ117: 0.0049217314
A118: 337 | B118: 1405 | C118: קבוצת עזריאלי בע"מ (לשעבר קנית מימון) | D118: 510960719 | E118: ח.פ | F118: עזריאלי אגח ה | G118: IL0011566036 | H118: ISIN | I118: צמוד למדד המחירים לצרכן | J118: ישראל | K118: ישראל | L118: סחיר | M118: TASE | N118: נדל"ן מניב בישראל | O118: לא | P118: Aa1 | Q118: מידרוג Moodys | R118: נייר ערך | S118: ILS | T118: 1.957 | U118: 30/06/2028 | V118: 0.0177 | W118: 0.02822 | X118: החוב לא נחות | Y118: לא | Z118: 59952.31 | AA118: 1 | AB118: 114.73 | AD118: 68.783 | AG118: שווי הוגן | AH118: 2.5e-05 | AI118: 0.018904942 | AJ118: 0.0076280327
A119: 337 | B119: 1405 | C119: קבוצת עזריאלי בע"מ (לשעבר קנית מימון) | D119: 510960719 | E119: ח.פ | F119: עזריאלי אגח ז | G119: IL0011786725 | H119: ISIN | I119: צמוד למדד המחירים לצרכן | J119: ישראל | K119: ישראל | L119: סחיר | M119: TASE | N119: נדל"ן מניב בישראל | O119: לא | P119: AA+ | Q119: S&P מעלות | R119: נייר ערך | S119: ILS | T119: 6.416 | U119: 02/07/2036 | V119: 0.009 | W119: 0.02841 | X119: החוב לא נחות | Y119: לא | Z119: 26233.47 | AA119: 1 | AB119: 101.93 | AC119: 0.769 | AD119: 27.509 | AG119: שווי הוגן | AH119: 1e-05 | AI119: 0.0075607706 | AJ119: 0.0030507264
A120: 337 | B120: 1405 | C120: קבוצת עזריאלי בע"מ (לשעבר קנית מימון) | D120: 510960719 | E120: ח.פ | F120: עזריאלי אגח ח | G120: IL0011786808 | H120: ISIN | I120: צמוד למדד המחירים לצרכן | J120: ישראל | K120: ישראל | L120: סחיר | M120: TASE | N120: נדל"ן מניב בישראל | O120: לא | P120: AA+ | Q120: S&P מעלות | R120: נייר ערך | S120: ILS | T120: 9.88 | U120: 02/01/2041 | V120: 0.0169 | W120: 0.0295 | X120: החוב לא נחות | Y120: לא | Z120: 30000 | AA120: 1 | AB120: 102.05 | AC120: 0.292 | AD120: 30.907 | AG120: שווי הוגן | AH120: 7e-06 | AI120: 0.0084948066 | AJ120: 0.0034276045
A121: 337 | B121: 1405 | C121: עמרם אברהם חברה לבנין בע"מ | D121: 513201582 | E121: ח.פ | F121: עמרם אברהם אגח א | G121: IL0011880445 | H121: ISIN | I121: לא צמוד למדד המחירים לצרכן | J121: ישראל | K121: ישראל | L121: סחיר | M121: TASE | N121: בנייה | O121: לא | P121: A3 | Q121: מידרוג Moodys | R121: נייר ערך | S121: ILS | T121: 1.385 | U121: 31/05/2027 | V121: 0.06 | W121: 0.05236 | X121: החוב לא נחות | Y121: לא | Z121: 9200 | AA121: 1 | AB121: 101.65 | AD121: 9.352 | AG121: שווי הוגן | AH121: 5.4e-05 | AI121: 0.0025703226 | AJ121: 0.00103711
A122: 337 | B122: 1405 | C122: בנק הפועלים בע"מ | D122: 520000118 | E122: ח.פ | F122: פועלים אגח 200 | G122: IL0066204962 | H122: ISIN | I122: צמוד למדד המחירים לצרכן | J122: ישראל | K122: ישראל | L122: סחיר | M122: TASE | N122: בנקים | O122: לא | P122: AAA | Q122: S&P מעלות | R122: נייר ערך | S122: ILS | T122: 3.335 | U122: 09/12/2031 | V122: 0.001 | W122: 0.02573 | X122: החוב לא נחות | Y122: לא | Z122: 11988.2 | AA122: 1 | AB122: 105.19 | AD122: 12.61 | AG122: שווי הוגן | AH122: 1.2e-05 | AI122: 0.0034659386 | AJ122: 0.0013984858
A123: 337 | B123: 1405 | C123: בנק הפועלים בע"מ | D123: 520000118 | E123: ח.פ | F123: פועלים אגח 201 | G123: IL0011913451 | H123: ISIN | I123: צמוד למדד המחירים לצרכן | J123: ישראל | K123: ישראל | L123: סחיר | M123: TASE | N123: בנקים | O123: לא | P123: AAA | Q123: S&P מעלות | R123: נייר ערך | S123: ILS | T123: 3.715 | U123: 29/11/2032 | V123: 0.0139 | W123: 0.02511 | X123: החוב לא נחות | Y123: לא | Z123: 18400 | AA123: 1 | AB123: 105.13 | AD123: 19.344 | AG123: שווי הוגן | AH123: 1.2e-05 | AI123: 0.0053166358 | AJ123: 0.0021452313
A124: 337 | B124: 1405 | C124: בנק הפועלים בע"מ | D124: 520000118 | E124: ח.פ | F124: פועלים אגח 203 | G124: IL0011998684 | H124: ISIN | I124: צמוד למדד המחירים לצרכן | J124: ישראל | K124: ישראל | L124: סחיר | M124: TASE | N124: בנקים | O124: לא | P124: AAA | Q124: S&P מעלות | R124: נייר ערך | S124: ILS | T124: 2.804 | U124: 02/12/2030 | V124: 0.0175 | W124: 0.02447 | X124: החוב לא נחות | Y124: לא | Z124: 33342.23 | AA124: 1 | AB124: 115.29 | AD124: 38.44 | AG124: שווי הוגן | AH124: 1.5e-05 | AI124: 0.010565224 | AJ124: 0.0042630057
A125: 337 | B125: 1405 | C125: בנק הפועלים בע"מ | D125: 520000118 | E125: ח.פ | F125: פועלים התח נד יב | G125: IL0012141219 | H125: ISIN | I125: צמוד למדד המחירים לצרכן | J125: ישראל | K125: ישראל | L125: סחיר | M125: TASE | N125: בנקים | O125: לא | P125: AA- | Q125: S&P מעלות | R125: נייר ערך | S125: ILS | T125: 6.56 | U125: 28/11/2032 | V125: 0.0345 | W125: 0.02903 | X125: החוב לא נחות | Y125: לא | Z125: 21000 | AA125: 1 | AB125: 106.85 | AD125: 22.439 | AG125: שווי הוגן | AH125: 1.4e-05 | AI125: 0.0061671747 | AJ125: 0.0024884187
A126: 337 | B126: 1405 | C126: פורמולה מערכות (1985)בע"מ | D126: 520036690 | E126: ח.פ | F126: פורמולה אג"ח ג | G126: IL0025602090 | H126: ISIN | I126: לא צמוד למדד המחירים לצרכן | J126: ישראל | K126: ישראל | L126: סחיר | M126: TASE | N126: שירותי מידע | O126: לא | P126: AA- | Q126: S&P מעלות | R126: נייר ערך | S126: ILS | T126: 0.902 | U126: 01/12/2026 | V126: 0.0229 | W126: 0.04703 | X126: החוב לא נחות | Y126: לא | Z126: 10961.53 | AA126: 1 | AB126: 98.11 | AD126: 10.754 | AG126: שווי הוגן | AH126: 3.3e-05 | AI126: 0.0029558125 | AJ126: 0.0011926529
A127: 337 | B127: 1405 | C127: הפניקס גיוסי הון (2009) בע"מ | D127: 514290345 | E127: ח.פ | F127: פניקס הון אגח טז | G127: IL0012203340 | H127: ISIN | I127: לא צמוד למדד המחירים לצרכן | J127: ישראל | K127: ישראל | L127: סחיר | M127: TASE | N127: ביטוח | O127: לא | P127: AA | Q127: S&P מעלות | R127: נייר ערך | S127: ILS | T127: 5.445 | U127: 01/11/2034 | V127: 0.0515 | W127: 0.04768 | X127: החוב לא נחות | Y127: לא | Z127: 15000 | AA127: 1 | AB127: 103.43 | AD127: 15.515 | AG127: שווי הוגן | AH127: 2.7e-05 | AI127: 0.0042641278 | AJ127: 0.0017205505
A128: 337 | B128: 1405 | C128: הפניקס גיוסי הון (2009) בע"מ | D128: 514290345 | E128: ח.פ | F128: פניקס הון אגח יב | G128: IL0011955858 | H128: ISIN | I128: צמוד למדד המחירים לצרכן | J128: ישראל | K128: ישראל | L128: סחיר | M128: TASE | N128: ביטוח | O128: לא | P128: AA- | Q128: S&P מעלות | R128: נייר ערך | S128: ILS | T128: 6.133 | U128: 05/02/2032 | V128: 0.0209 | W128: 0.02916 | X128: החוב לא נחות | Y128: לא | Z128: 50000 | AA128: 1 | AB128: 110.73 | AD128: 55.365 | AG128: שווי הוגן | AH128: 3.2e-05 | AI128: 0.015216954 | AJ128: 0.0061399514
A129: 337 | B129: 1405 | C129: פסיפיק אוק אסאואר(בי וי איי) הולדינגס | D129: 1900288 | E129: מספר תאגיד או שותפות בחו"ל | F129: פסיפיק אגח ב | G129: IL0011630626 | H129: ISIN | I129: לא צמוד למדד המחירים לצרכן | J129: ישראל | K129: ארה"ב | L129: סחיר | M129: TASE | N129: נדל"ן מניב בחו"ל | O129: לא | P129: A | Q129: S&P מעלות | R129: נייר ערך | S129: ILS | T129: 0.574 | U129: 01/02/2026 | V129: 0.04045 | W129: 0.44588 | X129: החוב לא נחות | Y129: לא | Z129: 0.18 | AA129: 1 | AB129: 84.44 | AD129: 0 | AG129: שווי הוגן | AH129: 0 | AI129: 4.1774682e-08 | AJ129: 1.6855838e-08
A130: 337 | B130: 1405 | C130: פתאל נכסים(אירופה)בע"מ | D130: 515328250 | E130: ח.פ | F130: פתאל אירו אגח ו | G130: IL0012192865 | H130: ISIN | I130: לא צמוד למדד המחירים לצרכן | J130: ישראל | K130: ישראל | L130: סחיר | M130: TASE | N130: נדל"ן מניב בחו"ל | O130: לא | P130: A2 | Q130: מידרוג Moodys | R130: נייר ערך | S130: ILS | T130: 5.651 | U130: 01/10/2034 | V130: 0.0559 | W130: 0.05245 | X130: החוב לא נחות | Y130: לא | Z130: 13000 | AA130: 1 | AB130: 103.88 | AD130: 13.504 | AG130: שווי הוגן | AH130: 5.8e-05 | AI130: 0.003711656 | AJ130: 0.0014976314
A131: 337 | B131: 1405 | C131: פתאל נכסים(אירופה)בע"מ | D131: 515328250 | E131: ח.פ | F131: פתאל אירופה אגח ג | G131: IL0011418527 | H131: ISIN | I131: לא צמוד למדד המחירים לצרכן | J131: ישראל | K131: ישראל | L131: סחיר | M131: TASE | N131: נדל"ן מניב בחו"ל | O131: לא | P131: A2 | Q131: מידרוג Moodys | R131: נייר ערך | S131: ILS | T131: 1.316 | U131: 30/08/2027 | V131: 0.0265 | W131: 0.04976 | X131: החוב לא נחות | Y131: לא | Z131: 31010 | AA131: 1 | AB131: 97.97 | AD131: 30.38 | AG131: שווי הוגן | AH131: 6.1e-05 | AI131: 0.0083500159 | AJ131: 0.0033691823
A132: 337 | B132: 1405 | C132: פתאל החזקות 1998 בע"מ | D132: 512607888 | E132: ח.פ | F132: פתאל החזקות אגח ד | G132: IL0011881922 | H132: ISIN | I132: צמוד למדד המחירים לצרכן | J132: ישראל | K132: ישראל | L132: סחיר | M132: TASE | N132: מלונאות ותיירות | O132: לא | P132: A2 | Q132: מידרוג Moodys | R132: נייר ערך | S132: ILS | T132: 3.407 | U132: 31/12/2032 | V132: 0.0325 | W132: 0.03083 | X132: החוב לא נחות | Y132: לא | Z132: 15010 | AA132: 1 | AB132: 111.12 | AD132: 16.679 | AG132: שווי הוגן | AH132: 4.1e-05 | AI132: 0.004584219 | AJ132: 0.0018497054
... A141: 337 | B141: 1405 | C141: ש.י.ר שלמה נדל"ן בע"מ | D141: 513957472 | E141: ח.פ | F141: שלמה נדלן אגח ד | G141: IL0011576688 | H141: ISIN | I141: לא צמוד למדד המחירים לצרכן | J141: ישראל | K141: ישראל | L141: סחיר | M141: TASE | N141: נדל"ן מניב בישראל | O141: לא | P141: A3 | Q141: מידרוג Moodys | R141: נייר ערך | S141: ILS | T141: 2.608 | U141: 31/10/2030 | V141: 0.041 | W141: 0.05068 | X141: החוב לא נחות | Y141: לא | Z141: 65238.1 | AA141: 1 | AB141: 98.37 | AD141: 64.175 | AG141: שווי הוגן | AH141: 0.000143 | AI141: 0.017638287 | AJ141: 0.007116945
A142: 337 | B142: 1405 | C142: שפיר הנדסה ותעשיה בע"מ | D142: 514892801 | E142: ח.פ | F142: שפיר הנדסה אגח ב | G142: IL0011419517 | H142: ISIN | I142: לא צמוד למדד המחירים לצרכן | J142: ישראל | K142: ישראל | L142: סחיר | M142: TASE | N142: מתכת ומוצרי בניה | O142: לא | P142: A+ | Q142: S&P מעלות | R142: נייר ערך | S142: ILS | T142: 2.864 | U142: 05/07/2030 | V142: 0.0262 | W142: 0.04875 | X142: החוב לא נחות | Y142: לא | Z142: 13948.08 | AA142: 1 | AB142: 93.94 | AC142: 2.982 | AD142: 16.085 | AG142: שווי הוגן | AH142: 3.9e-05 | AI142: 0.0044208506 | AJ142: 0.0017837872
A143: 337 | B143: 1405 | C143: תנופורט (1990) בע"מ | D143: 511519829 | E143: ח.פ | F143: תנופורט אגח ב | G143: IL0011899197 | H143: ISIN | I143: צמוד למדד המחירים לצרכן | J143: ישראל | K143: ישראל | L143: סחיר | M143: TASE | N143: נדל"ן מניב בישראל | O143: לא | P143: NR | Q143: NR | R143: NR | S143: ILS | T143: 1.448 | U143: 31/12/2026 | V143: 0.03518 | W143: 0.03911 | X143: החוב לא נחות | Y143: לא | Z143: 10000 | AA143: 1 | AB143: 108.93 | AD143: 10.893 | AG143: שווי הוגן | AH143: 1.4e-05 | AI143: 0.0029939182 | AJ143: 0.0012080284
A144: 337 | B144: 1405 | C144: Energean plc | D144: 98450044QACBL3F8EB03 | E144: LEI | F144: ENOIGA 5 3/8 30/03/28 | G144: IL0011736738 | H144: ISIN | I144: צמוד למט"ח | J144: חו"ל | K144: גלובלי | L144: סחיר | M144: אחר | N144: חיפושי נפט וגז | O144: לא | P144: BB- | Q144: S&P | R144: נייר ערך | S144: USD | T144: 2.549 | U144: 30/03/2028 | V144: 0.05375 | W144: 0.07415 | X144: החוב לא נחות | Y144: לא | Z144: 4000 | AA144: 3.372 | AB144: 96.94 | AD144: 13.075 | AG144: שווי הוגן | AH144: 6e-06 | AI144: 0.0035936986 | AJ144: 0.0014500363
A145: 337 | B145: 1405 | C145: Energean plc | D145: 98450044QACBL3F8EB03 | E145: LEI | F145: ENOIGA 5 7/8 30/03/31 | G145: IL0011736811 | H145: ISIN | I145: צמוד למט"ח | J145: חו"ל | K145: גלובלי | L145: סחיר | M145: אחר | N145: חיפושי נפט וגז | O145: לא | P145: BB- | Q145: S&P | R145: נייר ערך | S145: USD | T145: 4.844 | U145: 30/03/2031 | V145: 0.05875 | W145: 0.07617 | X145: החוב לא נחות | Y145: לא | Z145: 4000 | AA145: 3.372 | AB145: 94.051 | AD145: 12.686 | AG145: שווי הוגן | AH145: 6e-06 | AI145: 0.003486614 | AJ145: 0.0014068282
A146: 337 | B146: 1405 | C146: בנק לאומי לישראל בע"מ | D146: 520018078 | E146: ח.פ | F146: LUMIIT 3.275 01/29/31 | G146: IL0060404899 | H146: ISIN | I146: צמוד למט"ח | J146: חו"ל | K146: ישראל | L146: סחיר | M146: אחר | N146: בנקים | O146: לא | P146: BBB- | Q146: S&P | R146: נייר ערך | S146: USD | T146: 4.848 | U146: 29/01/2031 | V146: 0.03275 | W146: 0.05843 | X146: החוב לא נחות | Y146: לא | Z146: 3000 | AA146: 3.372 | AB146: 99.753 | AD146: 10.091 | AG146: שווי הוגן | AH146: 4e-06 | AI146: 0.0027734911 | AJ146: 0.0011190873
A147: 337 | B147: 1405 | C147: לוויתן בונד בע"מ | D147: 516223864 | E147: ח.פ | F147: LVIATH 6.5 30/06/27 | G147: IL0011677825 | H147: ISIN | I147: צמוד למט"ח | J147: חו"ל | K147: ישראל | L147: סחיר | M147: אחר | N147: חיפושי נפט וגז | O147: לא | P147: BB- | Q147: S&P | R147: נייר ערך | S147: USD | T147: 1.902 | U147: 30/06/2027 | V147: 0.065 | W147: 0.07045 | X147: החוב לא נחות | Y147: לא | Z147: 2000 | AA147: 3.372 | AB147: 99.573 | AD147: 6.715 | AG147: שווי הוגן | AH147: 3e-06 | AI147: 0.0018456613 | AJ147: 0.00074471349
A148: 337 | B148: 1405 | C148: בנק מזרחי טפחות בע"מ | D148: 520000522 | E148: ח.פ | F148: MZRHIT 3.077 04/07/31 | G148: IL0069508369 | H148: ISIN | I148: צמוד למט"ח | J148: חו"ל | K148: ישראל | L148: סחיר | M148: אחר | N148: בנקים | O148: לא | P148: BBB- | Q148: S&P | R148: נייר ערך | S148: USD | T148: 5.006 | U148: 07/04/2031 | V148: 0.03077 | W148: 0.06297 | X148: החוב לא נחות | Y148: לא | Z148: 3000 | AA148: 3.372 | AB148: 98.425 | AD148: 9.957 | AG148: שווי הוגן | AH148: 5e-06 | AI148: 0.0027365707 | AJ148: 0.0011041902
A149: 337 | B149: 1405 | C149: טבע תעשיות פרמצבטיות בע"מ | D149: 520013954 | E149: ח.פ | F149: TEVA 4.375% 09/05/30 | G149: XS2406607171 | H149: ISIN | I149: צמוד למט"ח | J149: חו"ל | K149: ארה"ב | L149: סחיר | M149: אחר | N149: פארמה | O149: לא | P149: BB- | Q149: S&P | R149: נייר ערך | S149: EUR | T149: 4.201 | U149: 09/05/2030 | V149: 0.04375 | W149: 0.04082 | X149: החוב לא נחות | Y149: לא | Z149: 15000 | AA149: 3.9552 | AB149: 102.464 | AD149: 60.79 | AG149: שווי הוגן | AH149: 1e-05 | AI149: 0.016707977 | AJ149: 0.0067415703
A150: 337 | B150: 1405 | C150: טבע תעשיות פרמצבטיות בע"מ | D150: 520013954 | E150: ח.פ | F150: TEVA 5.125% 09/05/29 | G150: US88167AAQ40 | H150: ISIN | I150: צמוד למט"ח | J150: חו"ל | K150: ארה"ב | L150: סחיר | M150: אחר | N150: פארמה | O150: לא | P150: BB- | Q150: S&P | R150: נייר ערך | S150: USD | T150: 3.315 | U150: 09/05/2029 | V150: 0.05125 | W150: 0.05051 | X150: החוב לא נחות | Y150: לא | Z150: 13000 | AA150: 3.372 | AB150: 102.147 | AD150: 44.777 | AG150: שווי הוגן | AH150: 1.3e-05 | AI150: 0.012306949 | AJ150: 0.0049657816
A151: 337 | B151: 1477 | C151: לוויתן בונד בע"מ | D151: 516223864 | E151: ח.פ | F151: LVIATH 6.125% 6/25 | G151: IL0011677742 | H151: ISIN | I151: צמוד למט"ח | J151: חו"ל | K151: ישראל | L151: סחיר | M151: אחר | N151: חיפושי נפט וגז | O151: לא | P151: BB- | Q151: S&P | R151: נייר ערך | S151: USD | T151: 0.133 | U151: 30/06/2025 | V151: 0.06125 | W151: 0.23773 | X151: החוב לא נחות | Y151: לא | Z151: 0 | AA151: 3.372 | AB151: 0 | AC151: 0.01 | AD151: 0.034 | AG151: שווי הוגן | AH151: 0 | AI151: 0.00031972243 | AJ151: 1.9796226e-06
A152: 337 | B152: 1477 | C152: או.פי.סי. אנרגיה בע"מ | D152: 514401702 | E152: ח.פ | F152: או פי סי אגח ב' | G152: IL0011660573 | H152: ISIN | I152: צמוד למדד המחירים לצרכן | J152: ישראל | K152: ישראל | L152: סחיר | M152: TASE | N152: אנרגיה | O152: לא | P152: A+ | Q152: S&P מעלות | R152: נייר ערך | S152: ILS | T152: 2.472 | U152: 01/10/2028 | V152: 0.0275 | W152: 0.03084 | X152: החוב לא נחות | Y152: לא | Z152: 0.59 | AA152: 1 | AB152: 116.37 | AD152: 0.001 | AG152: שווי הוגן | AH152: 0 | AI152: 6.3823177e-06 | AJ152: 3.9517341e-08
A153: 337 | B153: 1477 | C153: אלומיי קפיטל בע"מ | D153: 520039868 | E153: ח.פ | F153: אלומיי אגח ו | G153: IL0012030743 | H153: ISIN | I153: לא צמוד למדד המחירים לצרכן | J153: ישראל | K153: ישראל | L153: סחיר | M153: TASE | N153: אנרגיה מתחדשת | O153: לא | P153: NR | Q153: NR | R153: NR | S153: ILS | T153: 2.733 | U153: 31/03/2030 | V153: 0.055 | W153: 0.06331 | X153: החוב לא נחות | Y153: לא | Z153: 17000 | AA153: 1 | AB153: 99.42 | AD153: 16.901 | AG153: שווי הוגן | AH153: 5.2e-05 | AI153: 0.15711153 | AJ153: 0.00097278608
A154: 337 | B154: 1477 | C154: אמפא יובלים דיור להשכרה בע"מ | D154: 516286432 | E154: ח.פ | F154: אמפא יובלים אגח א | G154: IL0011935157 | H154: ISIN | I154: לא צמוד למדד המחירים לצרכן | J154: ישראל | K154: ישראל | L154: סחיר | M154: TASE | N154: נדל"ן מניב בישראל | O154: לא | P154: NR | Q154: NR | R154: NR | S154: ILS | T154: 0.455 | U154: 15/12/2025 | V154: 0.065 | W154: 0.07286 | X154: החוב לא נחות | Y154: לא | Z154: 9589 | AA154: 1 | AB154: 100 | AD154: 9.589 | AG154: שווי הוגן | AH154: 0.000175 | AI154: 0.089137139 | AJ154: 0.00055190965
A155: 337 | B155: 1477 | C155: אנרג'יקס אנרגיות מתחדשות בע"מ | D155: 513901371 | E155: ח.פ | F155: אנרג'יקס ב 0.25% | G155: IL0011684839 | H155: ISIN | I155: אג"ח להמרה לא צמוד למדד המחירים לצרכן | J155: ישראל | K155: ישראל | L155: סחיר | M155: TASE | N155: אנרגיה מתחדשת | O155: לא | P155: A | Q155: S&P מעלות | R155: נייר ערך | S155: ILS | T155: 2.076 | U155: 01/08/2027 | V155: 0.00125 | W155: 0.04852 | X155: החוב לא נחות | Y155: לא | Z155: 4000 | AA155: 1 | AB155: 91.2 | AD155: 3.648 | AG155: שווי הוגן | AH155: 7e-06 | AI155: 0.033910969 | AJ155: 0.00020996625
A156: 337 | B156: 1477 | C156: אס.אר.אקורד בע"מ | D156: 520038670 | E156: ח.פ | F156: אסאר אקורד אגח ב | G156: IL0042203724 | H156: ISIN | I156: צמוד למדד המחירים לצרכן | J156: ישראל | K156: ישראל | L156: סחיר | M156: TASE | N156: אשראי חוץ בנקאי | O156: לא | P156: A3 | Q156: מידרוג Moodys | R156: נייר ערך | S156: ILS | T156: 1.231 | U156: 30/06/2027 | V156: 0.0125 | W156: 0.03802 | X156: החוב לא נחות | Y156: לא | Z156: 0.22 | AA156: 1 | AB156: 107.48 | AD156: 0 | AG156: שווי הוגן | AH156: 0 | AI156: 2.1980406e-06 | AJ156: 1.3609589e-08
A157: 337 | B157: 1477 | C157: אקסטל לימיטד | D157: 1811308 | E157: מספר תאגיד או שותפות בחו"ל | F157: אקסטל אג"ח ג | G157: IL0011750416 | H157: ISIN | I157: לא צמוד למדד המחירים לצרכן | J157: ישראל | K157: ישראל | L157: סחיר | M157: TASE | N157: נדל"ן מניב בחו"ל | O157: לא | P157: A3 | Q157: מידרוג Moodys | R157: נייר ערך | S157: ILS | T157: 0.728 | U157: 31/03/2026 | V157: 0.07 | W157: 0.05975 | X157: החוב לא נחות | Y157: לא | Z157: 0.37 | AA157: 1 | AB157: 102.57 | AD157: 0 | AG157: שווי הוגן | AH157: 0 | AI157: 3.5278284e-06 | AJ157: 2.1843224e-08
A158: 337 | B158: 1477 | C158: גפן מגורים והתחדשות בע"מ | D158: 512781386 | E158: ח.פ | F158: גפן מגורים אג א | G158: IL0011996860 | H158: ISIN | I158: אג"ח להמרה לא צמוד למדד המחירים לצרכן | J158: ישראל | K158: ישראל | L158: סחיר | M158: TASE | N158: בנייה | O158: לא | P158: NR | Q158: NR | R158: NR | S158: ILS | T158: 2.978 | U158: 01/10/2028 | V158: 0.07 | W158: -0.04108 | X158: החוב לא נחות | Y158: לא | Z158: 18000 | AA158: 1 | AB158: 141 | AD158: 25.38 | AG158: שווי הוגן | AH158: 0.00036 | AI158: 0.23592664 | AJ158: 0.001460785
A159: 337 | B159: 1477 | C159: חברה לנכסים ולבנין בע"מ | D159: 520025438 | E159: ח.פ | F159: נכסים ובנין ד | G159: IL0069901549 | H159: ISIN | I159: צמוד למדד המחירים לצרכן | J159: ישראל | K159: ישראל | L159: סחיר | M159: TASE | N159: נדל"ן מניב בישראל | O159: לא | P159: A | Q159: S&P מעלות | R159: נייר ערך | S159: ILS | T159: 0.499 | U159: 31/12/2025 | V159: 0.0495 | W159: 0.03091 | X159: החוב לא נחות | Y159: לא | Z159: 0.17 | AA159: 1 | AB159: 142.71 | AD159: 0 | AG159: שווי הוגן | AH159: 0 | AI159: 2.2552189e-06 | AJ159: 1.3963619e-08
A160: 337 | B160: 1477 | C160: סטרוברי פילדס ריט לימיטד | D160: 1863501 | E160: מספר תאגיד או שותפות בחו"ל | F160: סטרוברי אגח ג | G160: IL0011790198 | H160: ISIN | I160: לא צמוד למדד המחירים לצרכן | J160: ישראל | K160: גלובלי | L160: סחיר | M160: TASE | N160: נדל"ן מניב בחו"ל | O160: לא | P160: AA- | Q160: S&P מעלות | R160: נייר ערך | S160: ILS | T160: 0.968 | U160: 31/07/2026 | V160: 0.057 | W160: 0.05803 | X160: החוב לא נחות | Y160: לא | Z160: 0.1 | AA160: 1 | AB160: 102.37 | AD160: 0 | AG160: שווי הוגן | AH160: 0 | AI160: 9.5160798e-07 | AJ160: 5.8920629e-09
A161: 337 | B161: 1477 | C161: עמרם אברהם חברה לבנין בע"מ | D161: 513201582 | E161: ח.פ | F161: עמרם אברהם אגח א | G161: IL0011880445 | H161: ISIN | I161: לא צמוד למדד המחירים לצרכן | J161: ישראל | K161: ישראל | L161: סחיר | M161: TASE | N161: בנייה | O161: לא | P161: A3 | Q161: מידרוג Moodys | R161: נייר ערך | S161: ILS | T161: 1.385 | U161: 31/05/2027 | V161: 0.06 | W161: 0.05236 | X161: החוב לא נחות | Y161: לא | Z161: 0.6 | AA161: 1 | AB161: 101.65 | AD161: 0.001 | AG161: שווי הוגן | AH161: 0 | AI161: 5.6694902e-06 | AJ161: 3.5103733e-08
A162: 337 | B162: 1477 | C162: א.נ שוהם בידנס בע"מ | D162: 520043860 | E162: ח.פ | F162: שוהם ביזנס אגח ד | G162: IL0011820474 | H162: ISIN | I162: לא צמוד למדד המחירים לצרכן | J162: ישראל | K162: ישראל | L162: סחיר | M162: TASE | N162: אשראי חוץ בנקאי | O162: לא | P162: Baa2 | Q162: מידרוג Moodys | R162: נייר ערך | S162: ILS | T162: 0.499 | U162: 31/12/2025 | V162: 0.0315 | W162: 0.05327 | X162: החוב לא נחות | Y162: לא | Z162: 4749.96 | AA162: 1 | AB162: 98.98 | AD162: 4.702 | AG162: שווי הוגן | AH162: 0.00011 | AI162: 0.04370416 | AJ162: 0.00027060267
A163: 337 | B163: 1477 | C163: בנק לאומי לישראל בע"מ | D163: 520018078 | E163: ח.פ | F163: LUMIIT 3.275 01/29/31 | G163: IL0060404899 | H163: ISIN | I163: צמוד למט"ח | J163: חו"ל | K163: ישראל | L163: סחיר | M163: אחר | N163: בנקים | O163: לא | P163: BBB- | Q163: S&P | R163: נייר ערך | S163: USD | T163: 4.848 | U163: 29/01/2031 | V163: 0.03275 | W163: 0.05843 | X163: החוב לא נחות | Y163: לא | Z163: 2000 | AA163: 3.372 | AB163: 99.753 | AD163: 6.727 | AG163: שווי הוגן | AH163: 3e-06 | AI163: 0.062535765 | AJ163: 0.00038720215
... A167: 337 | B167: 1477 | C167: טבע תעשיות פרמצבטיות בע"מ | D167: 520013954 | E167: ח.פ | F167: TEVA 5.125% 09/05/29 | G167: US88167AAQ40 | H167: ISIN | I167: צמוד למט"ח | J167: חו"ל | K167: ארה"ב | L167: סחיר | M167: אחר | N167: פארמה | O167: לא | P167: BB- | Q167: S&P | R167: נייר ערך | S167: USD | T167: 3.315 | U167: 09/05/2029 | V167: 0.05125 | W167: 0.05051 | X167: החוב לא נחות | Y167: לא | Z167: 3000 | AA167: 3.372 | AB167: 102.147 | AD167: 10.333 | AG167: שווי הוגן | AH167: 3e-06 | AI167: 0.096055286 | AJ167: 0.00059474468
A168: 337 | B168: 9962 | C168: לוויתן בונד בע"מ | D168: 516223864 | E168: ח.פ | F168: LVIATH 6.125% 6/25 | G168: IL0011677742 | H168: ISIN | I168: צמוד למט"ח | J168: חו"ל | K168: ישראל | L168: סחיר | M168: אחר | N168: חיפושי נפט וגז | O168: לא | P168: BB- | Q168: S&P | R168: נייר ערך | S168: USD | T168: 0.133 | U168: 30/06/2025 | V168: 0.06125 | W168: 0.23773 | X168: החוב לא נחות | Y168: לא | Z168: 0 | AA168: 3.372 | AB168: 0 | AC168: 0.112 | AD168: 0.379 | AG168: שווי הוגן | AH168: 0 | AI168: 5.6071382e-05 | AJ168: 8.8982577e-06
A169: 337 | B169: 9962 | C169: אאורה השקעות בע"מ | D169: 520038274 | E169: ח.פ | F169: אאורה אגח טז | G169: IL0037305799 | H169: ISIN | I169: לא צמוד למדד המחירים לצרכן | J169: ישראל | K169: ישראל | L169: סחיר | M169: TASE | N169: בנייה | O169: לא | P169: A2 | Q169: מידרוג Moodys | R169: נייר ערך | S169: ILS | T169: 1.207 | U169: 30/09/2027 | V169: 0.035 | W169: 0.04885 | X169: החוב לא נחות | Y169: לא | Z169: 21128 | AA169: 1 | AB169: 99.31 | AD169: 20.982 | AG169: שווי הוגן | AH169: 0.000152 | AI169: 0.0031077161 | AJ169: 0.00049317955
A170: 337 | B170: 9962 | C170: אאורה השקעות בע"מ | D170: 520038274 | E170: ח.פ | F170: אאורה אגח יז %3.85 31/01/2029 | G170: IL0011935801 | H170: ISIN | I170: צמוד למדד המחירים לצרכן | J170: ישראל | K170: ישראל | L170: סחיר | M170: TASE | N170: בנייה | O170: לא | P170: A2 | Q170: מידרוג Moodys | R170: נייר ערך | S170: ILS | T170: 2.116 | U170: 31/01/2029 | V170: 0.0385 | W170: 0.03237 | X170: החוב לא נחות | Y170: לא | Z170: 43000 | AA170: 1 | AB170: 111.11 | AD170: 47.777 | AG170: שווי הוגן | AH170: 0.000143 | AI170: 0.007076387 | AJ170: 0.0011229885
A171: 337 | B171: 9962 | C171: אדגר השקעות ופיתוח בע"מ | D171: 520035171 | E171: ח.פ | F171: אדגר אגח סד יא | G171: IL0018202817 | H171: ISIN | I171: צמוד למדד המחירים לצרכן | J171: ישראל | K171: גלובלי | L171: סחיר | M171: TASE | N171: נדל"ן מניב בחו"ל | O171: לא | P171: A2 | Q171: מידרוג Moodys | R171: נייר ערך | S171: ILS | T171: 2.624 | U171: 31/03/2030 | V171: 0.0245 | W171: 0.03057 | X171: החוב לא נחות | Y171: לא | Z171: 10956.52 | AA171: 1 | AB171: 115.76 | AD171: 12.683 | AG171: שווי הוגן | AH171: 2.3e-05 | AI171: 0.0018785429 | AJ171: 0.0002981157
A172: 337 | B172: 9962 | C172: או.פי.סי. אנרגיה בע"מ | D172: 514401702 | E172: ח.פ | F172: או פי סי אגח ב' | G172: IL0011660573 | H172: ISIN | I172: צמוד למדד המחירים לצרכן | J172: ישראל | K172: ישראל | L172: סחיר | M172: TASE | N172: אנרגיה | O172: לא | P172: A+ | Q172: S&P מעלות | R172: נייר ערך | S172: ILS | T172: 2.472 | U172: 01/10/2028 | V172: 0.0275 | W172: 0.03084 | X172: החוב לא נחות | Y172: לא | Z172: 62007.58 | AA172: 1 | AB172: 116.37 | AD172: 72.158 | AG172: שווי הוגן | AH172: 8.3e-05 | AI172: 0.010687492 | AJ172: 0.0016960533
A173: 337 | B173: 9962 | C173: איי.סי.אל גרופ בע"מ (דואלי) | D173: 520027830 | E173: ח.פ | F173: אייסיאל אגח ז | G173: IL0028103724 | H173: ISIN | I173: לא צמוד למדד המחירים לצרכן | J173: ישראל | K173: ישראל | L173: סחיר | M173: TASE | N173: כימיה, גומי ופלסטיק | O173: לא | P173: AA | Q173: S&P מעלות | R173: נייר ערך | S173: ILS | T173: 7.331 | U173: 30/12/2034 | V173: 0.024 | W173: 0.04694 | X173: החוב לא נחות | Y173: לא | Z173: 76000 | AA173: 1 | AB173: 84.92 | AD173: 64.539 | AG173: שווי הוגן | AH173: 4.8e-05 | AI173: 0.009559024 | AJ173: 0.001516971
A174: 337 | B174: 9962 | C174: איירפורט סיטי בע"מ | D174: 511659401 | E174: ח.פ | F174: איירפורט אגח ה | G174: IL0011334872 | H174: ISIN | I174: צמוד למדד המחירים לצרכן | J174: ישראל | K174: ישראל | L174: סחיר | M174: TASE | N174: נדל"ן מניב בישראל | O174: לא | P174: AA | Q174: S&P מעלות | R174: נייר ערך | S174: ILS | T174: 2.014 | U174: 28/02/2029 | V174: 0.0234 | W174: 0.02872 | X174: החוב לא נחות | Y174: לא | Z174: 28481.48 | AA174: 1 | AB174: 116.49 | AD174: 33.178 | AG174: שווי הוגן | AH174: 1.7e-05 | AI174: 0.0049140681 | AJ174: 0.00077983889
A175: 337 | B175: 9962 | C175: איסתא בע"מ | D175: 520042763 | E175: ח.פ | F175: איסתא אגח א להמרה | G175: IL0011971285 | H175: ISIN | I175: אג"ח להמרה לא צמוד למדד המחירים לצרכן | J175: ישראל | K175: ישראל | L175: סחיר | M175: TASE | N175: מלונאות ותיירות | O175: לא | P175: NR | Q175: NR | R175: NR | S175: ILS | T175: 2.839 | U175: 30/06/2028 | V175: 0.0485 | W175: 0.0001 | X175: החוב לא נחות | Y175: לא | Z175: 33000 | AA175: 1 | AB175: 115 | AD175: 37.95 | AG175: שווי הוגן | AH175: 0.00011 | AI175: 0.0056208469 | AJ175: 0.00089200126
...

Sheet מניות מבכ ויהש
A1: מספר קופה/קרן/ח.פ. עבור חברת ביטוח | B1: מספר מסלול | C1: שם מנפיק | D1: מספר מנפיק | E1: סוג מספר מזהה מנפיק | F1: שם נייר ערך | G1: מספר נייר ערך | H1: סוג מספר נייר ערך | I1: מאפיין עיקרי | J1: ישראל/חו"ל | K1: מדינה לפי חשיפה כלכלית | L1: סטאטוס סחירות | M1: זירת מסחר | N1: ענף מסחר | O1: בעל עניין/צד קשור | P1: מטבע פעילות | Q1: ערך נקוב (יחידות) | R1: שער חליפין | S1: שער נייר הערך | T1: סכום לקבל (במטבע הפעילות) | U1: שווי הוגן (באלפי ש"ח) | V1: שיעור מערך נקוב מונפק | W1: שיעור מנכסי אפיק ההשקעה | X1: שיעור מסך נכסי ההשקעה
A2: 337 | B2: 1477 | C2: או.פי.סי. אנרגיה בע"מ | D2: 514401702 | E2: ח.פ | F2: או פי סי אנרגיה | G2: IL0011415713 | H2: ISIN | I2: מניות | J2: ישראל | K2: ישראל | L2: סחיר | M2: TASE | N2: אנרגיה | O2: לא | P2: ILS | Q2: 2712 | R2: 1 | S2: 4100 | U2: 111.192 | V2: 1e-05 | W2: 0.01466742 | X2: 0.0063998267
A3: 337 | B3: 1477 | C3: אורמת טכנולגיות אינק | D3: 5493000TSHHWY24VHM09 | E3: LEI | F3: אורמת טכנולוגיות | G3: US6866881021 | H3: ISIN | I3: מניות | J3: ישראל | K3: ארה"ב | L3: סחיר | M3: TASE | N3: אנרגיה מתחדשת | O3: לא | P3: ILS | Q3: 425 | R3: 1 | S3: 27780 | U3: 118.065 | V3: 7e-06 | W3: 0.015574043 | X3: 0.0067954127
A4: 337 | B4: 1477 | C4: אזורים-חברה להשקעות בפתוח ובבנין בע"מ | D4: 520025990 | E4: ח.פ | F4: אזורים | G4: IL0007150118 | H4: ISIN | I4: מניות | J4: ישראל | K4: ישראל | L4: סחיר | M4: TASE | N4: בנייה | O4: לא | P4: ILS | Q4: 366 | R4: 1 | S4: 2366 | U4: 8.66 | V4: 2e-06 | W4: 0.0011422891 | X4: 0.0004984143
A5: 337 | B5: 1477 | C5: איי.סי.אל גרופ בע"מ (דואלי) | D5: 520027830 | E5: ח.פ | F5: איי.סי.אל | G5: IL0002810146 | H5: ISIN | I5: מניות | J5: ישראל | K5: ישראל | L5: סחיר | M5: TASE | N5: כימיה, גומי ופלסטיק | O5: לא | P5: ILS | Q5: 6841 | R5: 1 | S5: 2309 | U5: 157.959 | V5: 5e-06 | W5: 0.02083645 | X5: 0.0090915555
A6: 337 | B6: 1477 | C6: אינרום תעשיות בנייה בע"מ | D6: 515001659 | E6: ח.פ | F6: אינרום | G6: IL0011323560 | H6: ISIN | I6: מניות | J6: ישראל | K6: ישראל | L6: סחיר | M6: TASE | N6: מתכת ומוצרי בניה | O6: לא | P6: ILS | Q6: 1000 | R6: 1 | S6: 2100 | U6: 21 | V6: 7e-06 | W6: 0.0027701258 | X6: 0.0012086873
A7: 337 | B7: 1477 | C7: איסתא בע"מ | D7: 520042763 | E7: ח.פ | F7: איסתא | G7: IL0010810740 | H7: ISIN | I7: מניות | J7: ישראל | K7: ישראל | L7: סחיר | M7: TASE | N7: מלונאות ותיירות | O7: לא | P7: ILS | Q7: 113 | R7: 1 | S7: 10930 | U7: 12.351 | V7: 6e-06 | W7: 0.0016292165 | X7: 0.00071087505
A8: 337 | B8: 1477 | C8: אלביט מערכות בע"מ | D8: 520043027 | E8: ח.פ | F8: אלביט מערכות | G8: IL0010811243 | H8: ISIN | I8: מניות | J8: ישראל | K8: ישראל | L8: סחיר | M8: TASE | N8: ביטחוניות | O8: לא | P8: ILS | Q8: 194 | R8: 1 | S8: 149800 | T8: 0.41 | U8: 291.022 | V8: 4e-06 | W8: 0.038388972 | X8: 0.016750237
A9: 337 | B9: 1477 | C9: אלוני-חץ נכסים והשקעות בע"מ | D9: 520038506 | E9: ח.פ | F9: אלוני חץ | G9: IL0003900136 | H9: ISIN | I9: מניות | J9: ישראל | K9: ישראל | L9: סחיר | M9: TASE | N9: נדל"ן מניב בישראל | O9: לא | P9: ILS | Q9: 1419 | R9: 1 | S9: 3489 | U9: 49.509 | V9: 7e-06 | W9: 0.0065307576 | X9: 0.0028495615
A10: 337 | B10: 1477 | C10: אלקטרה נדל"ן בע"מ | D10: 510607328 | E10: ח.פ | F10: אלקטרה נדלן | G10: IL0010940448 | H10: ISIN | I10: מניות | J10: ישראל | K10: ישראל | L10: סחיר | M10: TASE | N10: נדל"ן מניב בחו"ל | O10: לא | P10: ILS | Q10: 830 | R10: 1 | S10: 5007 | U10: 41.558 | V10: 1.3e-05 | W10: 0.0054819603 | X10: 0.0023919404
A11: 337 | B11: 1477 | C11: אמות השקעות בע"מ | D11: 520026683 | E11: ח.פ | F11: אמות | G11: IL0010972789 | H11: ISIN | I11: מניות | J11: ישראל | K11: ישראל | L11: סחיר | M11: TASE | N11: נדל"ן מניב בישראל | O11: לא | P11: ILS | Q11: 1801 | R11: 1 | S11: 2281 | U11: 41.081 | V11: 4e-06 | W11: 0.0054190006 | X11: 0.0023644692
A12: 337 | B12: 1477 | C12: אנלייט אנרגיה מתחדשת בע"מ | D12: 520041146 | E12: ח.פ | F12: אנלייט אנרגיה | G12: IL0007200111 | H12: ISIN | I12: מניות | J12: ישראל | K12: ארה"ב | L12: סחיר | M12: TASE | N12: אנרגיה מתחדשת | O12: לא | P12: ILS | Q12: 1959.3 | R12: 1 | S12: 7640 | U12: 149.691 | V12: 1.6e-05 | W12: 0.019745789 | X12: 0.0086156682
A13: 337 | B13: 1477 | C13: Energean plc | D13: 98450044QACBL3F8EB03 | E13: LEI | F13: אנרג'יאן | G13: GB00BG12Y042 | H13: ISIN | I13: מניות | J13: ישראל | K13: בריטניה | L13: סחיר | M13: TASE | N13: חיפושי נפט וגז | O13: לא | P13: ILS | Q13: 2500 | R13: 1 | S13: 4272 | T13: 2.529 | U13: 109.329 | V13: 1.4e-05 | W13: 0.014421671 | X13: 0.0062925988
A14: 337 | B14: 1477 | C14: אנרג'יקס אנרגיות מתחדשות בע"מ | D14: 513901371 | E14: ח.פ | F14: אנרג'יקס | G14: IL0011233553 | H14: ISIN | I14: מניות | J14: ישראל | K14: ישראל | L14: סחיר | M14: TASE | N14: אנרגיה מתחדשת | O14: לא | P14: ILS | Q14: 1846 | R14: 1 | S14: 1244 | U14: 22.964 | V14: 3e-06 | W14: 0.0030292302 | X14: 0.0013217422
A15: 337 | B15: 1477 | C15: אפריקה ישראל מגורים בע"מ | D15: 520034760 | E15: ח.פ | F15: אפריקה מגורים | G15: IL0010979487 | H15: ISIN | I15: מניות | J15: ישראל | K15: ישראל | L15: סחיר | M15: TASE | N15: בנייה | O15: לא | P15: ILS | Q15: 43 | R15: 1 | S15: 30100 | U15: 12.943 | V15: 3e-06 | W15: 0.0017073209 | X15: 0.00074495428
A16: 337 | B16: 1477 | C16: ארגו פרופרטיז אן. וי | D16: 70252750 | E16: מספר תאגיד או שותפות בחו"ל | F16: ארגו פרופרטיז אן. וי | G16: NL0015000D84 | H16: ISIN | I16: מניות | J16: ישראל | K16: גרמניה | L16: סחיר | M16: TASE | N16: נדל"ן מניב בחו"ל | O16: לא | P16: ILS | Q16: 695 | R16: 1 | S16: 12250 | U16: 85.138 | V16: 3.2e-05 | W16: 0.011230552 | X16: 0.0049002198
A17: 337 | B17: 1477 | C17: קבוצת אשטרום | D17: 510381601 | E17: ח.פ | F17: אשטרום קבוצה | G17: IL0011323156 | H17: ISIN | I17: מניות | J17: ישראל | K17: ישראל | L17: סחיר | M17: TASE | N17: בנייה | O17: לא | P17: ILS | Q17: 1600 | R17: 1 | S17: 7670 | U17: 122.72 | V17: 1.4e-05 | W17: 0.016188088 | X17: 0.0070633384
A18: 337 | B18: 1477 | C18: בזק החברה הישראלית לתקשורת בע"מ | D18: 520031931 | E18: ח.פ | F18: בזק | G18: IL0002300114 | H18: ISIN | I18: מניות | J18: ישראל | K18: ישראל | L18: סחיר | M18: TASE | N18: תקשורת ומדיה | O18: לא | P18: ILS | Q18: 25108 | R18: 1 | S18: 575 | U18: 144.371 | V18: 9e-06 | W18: 0.019044087 | X18: 0.0083094951
A19: 337 | B19: 1477 | C19: ביג מרכזי קניות (2004) בע"מ | D19: 513623314 | E19: ח.פ | F19: ביג | G19: IL0010972607 | H19: ISIN | I19: מניות | J19: ישראל | K19: ישראל | L19: סחיר | M19: TASE | N19: נדל"ן מניב בישראל | O19: לא | P19: ILS | Q19: 307 | R19: 1 | S19: 64490 | U19: 197.984 | V19: 1.2e-05 | W19: 0.026116258 | X19: 0.011395291
A20: 337 | B20: 1477 | C20: הבנק הבינלאומי הראשון לישראל בע"מ | D20: 520029083 | E20: ח.פ | F20: בינלאומי 5 | G20: IL0005930388 | H20: ISIN | I20: מניות | J20: ישראל | K20: ישראל | L20: סחיר | M20: TASE | N20: בנקים | O20: לא | P20: ILS | Q20: 545 | R20: 1 | S20: 24370 | U20: 132.816 | V20: 5e-06 | W20: 0.017519924 | X20: 0.007644458
A21: 337 | B21: 1477 | C21: בית בכפר בע"מ | D21: 511605719 | E21: ח.פ | F21: בית בכפר | G21: IL0011836561 | H21: ISIN | I21: מניות | J21: ישראל | K21: ישראל | L21: סחיר | M21: TASE | N21: נדל"ן מניב בישראל | O21: לא | P21: ILS | Q21: 542 | R21: 1 | S21: 1506 | U21: 8.163 | V21: 8e-06 | W21: 0.0010767242 | X21: 0.0004698064
A22: 337 | B22: 1477 | C22: מנועי בית שמש אחזקות (1997) בע"מ | D22: 520043480 | E22: ח.פ | F22: בית שמש | G22: IL0010815616 | H22: ISIN | I22: מניות | J22: ישראל | K22: ישראל | L22: סחיר | M22: TASE | N22: מתכת ומוצרי בניה | O22: לא | P22: ILS | Q22: 206 | R22: 1 | S22: 56070 | U22: 115.504 | V22: 2.3e-05 | W22: 0.015236246 | X22: 0.006648022
A23: 337 | B23: 1477 | C23: חברת גב-ים לקרקעות בע"מ | D23: 520001736 | E23: ח.פ | F23: גב ים | G23: IL0007590198 | H23: ISIN | I23: מניות | J23: ישראל | K23: ישראל | L23: סחיר | M23: TASE | N23: נדל"ן מניב בישראל | O23: לא | P23: ILS | Q23: 348 | R23: 1 | S23: 3685 | U23: 12.824 | V23: 2e-06 | W23: 0.0016915971 | X23: 0.00073809354
A24: 337 | B24: 1477 | C24: קבוצת דוראל משאבי אנרגיה מתחדשת בעמ | D24: 515364891 | E24: ח.פ | F24: דוראל אנרגיה | G24: IL0011667685 | H24: ISIN | I24: מניות | J24: ישראל | K24: ישראל | L24: סחיר | M24: TASE | N24: אנרגיה מתחדשת | O24: לא | P24: ILS | Q24: 1391 | R24: 1 | S24: 1532 | U24: 21.31 | V24: 8e-06 | W24: 0.002811034 | X24: 0.0012265367
A25: 337 | B25: 1477 | C25: בנק דיסקונט לישראל בע"מ | D25: 520007030 | E25: ח.פ | F25: דיסקונט | G25: IL0006912120 | H25: ISIN | I25: מניות | J25: ישראל | K25: ישראל | L25: סחיר | M25: TASE | N25: בנקים | O25: לא | P25: ILS | Q25: 4067 | R25: 1 | S25: 3356 | U25: 136.489 | V25: 3e-06 | W25: 0.018004303 | X25: 0.0078558068
... A29: 337 | B29: 1477 | C29: הבורסה לניירות ערך בתל-אביב בע"מ | D29: 520020033 | E29: ח.פ | F29: הבורסה לניע בתא | G29: IL0011590291 | H29: ISIN | I29: מניות | J29: ישראל | K29: ישראל | L29: סחיר | M29: TASE | N29: שירותים פיננסיים | O29: לא | P29: ILS | Q29: 485 | R29: 1 | S29: 6510 | U29: 31.573 | V29: 5e-06 | W29: 0.0041648842 | X29: 0.0018172614
A30: 337 | B30: 1477 | C30: הולמס פלייס אינטרנשיונל בע"מ | D30: 512466723 | E30: ח.פ | F30: הולמס פלייס | G30: IL0011425878 | H30: ISIN | I30: מניות | J30: ישראל | K30: ישראל | L30: סחיר | M30: TASE | N30: שירותים | O30: לא | P30: ILS | Q30: 15506 | R30: 1 | S30: 732.6 | T30: 1.858 | U30: 115.455 | V30: 0.000169 | W30: 0.015229779 | X30: 0.0066452003
A31: 337 | B31: 1477 | C31: חברת הכשרת הישוב בישראל- אנרגיה בע"מ | D31: 514423474 | E31: ח.פ | F31: הכשרה התפתחות עירונית | G31: IL0011214744 | H31: ISIN | I31: מניות | J31: ישראל | K31: ישראל | L31: סחיר | M31: TASE | N31: בנייה | O31: לא | P31: ILS | Q31: 5000 | R31: 1 | S31: 711.9 | U31: 35.595 | V31: 5.7e-05 | W31: 0.0046953632 | X31: 0.002048725
A32: 337 | B32: 1477 | C32: הפניקס אחזקות בע"מ | D32: 520017450 | E32: ח.פ | F32: הפניקס | G32: IL0007670123 | H32: ISIN | I32: מניות | J32: ישראל | K32: ישראל | L32: סחיר | M32: TASE | N32: ביטוח | O32: לא | P32: ILS | Q32: 2057 | R32: 1 | S32: 9745 | U32: 200.455 | V32: 8e-06 | W32: 0.026442124 | X32: 0.011537476
A33: 337 | B33: 1477 | C33: הראל השקעות בביטוח ושרותים פיננסים בע"מ | D33: 520033986 | E33: ח.פ | F33: הראל השקעות | G33: IL0005850180 | H33: ISIN | I33: מניות | J33: ישראל | K33: ישראל | L33: סחיר | M33: TASE | N33: ביטוח | O33: לא | P33: ILS | Q33: 2376 | R33: 1 | S33: 9432 | U33: 224.104 | V33: 1.1e-05 | W33: 0.02956177 | X33: 0.012898669
A34: 337 | B34: 1477 | C34: וואן טכנולוגיות תוכנה(או.אס.טי)בע"מ | D34: 520034695 | E34: ח.פ | F34: וואן טכנולוגיות תוכנה | G34: IL0001610182 | H34: ISIN | I34: מניות | J34: ישראל | K34: ישראל | L34: סחיר | M34: TASE | N34: שירותי מידע | O34: לא | P34: ILS | Q34: 794 | R34: 1 | S34: 8680 | U34: 68.919 | V34: 1.1e-05 | W34: 0.0090911836 | X34: 0.0039667506
A35: 337 | B35: 1477 | C35: קבוצת חג'ג' ייזום נדל"ן בע"מ | D35: 520033309 | E35: ח.פ | F35: חג'ג' נדלן | G35: IL0008230133 | H35: ISIN | I35: מניות | J35: ישראל | K35: ישראל | L35: סחיר | M35: TASE | N35: בנייה | O35: לא | P35: ILS | Q35: 1589 | R35: 1 | S35: 2063 | U35: 32.781 | V35: 2.6e-05 | W35: 0.0043241756 | X35: 0.0018867649
A36: 337 | B36: 1477 | C36: חילן בע"מ | D36: 520039942 | E36: ח.פ | F36: חילן | G36: IL0010846983 | H36: ISIN | I36: מניות | J36: ישראל | K36: ישראל | L36: סחיר | M36: TASE | N36: שירותי מידע | O36: לא | P36: ILS | Q36: 87 | R36: 1 | S36: 28610 | U36: 24.891 | V36: 4e-06 | W36: 0.003283351 | X36: 0.0014326225
A37: 337 | B37: 1477 | C37: קבוצת חמת בע"מ | D37: 520038530 | E37: ח.פ | F37: חמת | G37: IL0003840167 | H37: ISIN | I37: מניות | J37: ישראל | K37: ישראל | L37: סחיר | M37: TASE | N37: מתכת ומוצרי בניה | O37: לא | P37: ILS | Q37: 462 | R37: 1 | S37: 1866 | T37: 0.189 | U37: 8.81 | V37: 1.3e-05 | W37: 0.001162139 | X37: 0.00050707541
A38: 337 | B38: 1477 | C38: טאואר סמיקונדקטור בע"מ | D38: 520041997 | E38: ח.פ | F38: טאואר | G38: IL0010823792 | H38: ISIN | I38: מניות | J38: ישראל | K38: גלובלי | L38: סחיר | M38: TASE | N38: מוליכים למחצה | O38: לא | P38: ILS | Q38: 292 | R38: 1 | S38: 14620 | U38: 42.69 | V38: 3e-06 | W38: 0.0056313228 | X38: 0.0024571117
A39: 337 | B39: 1477 | C39: טבע תעשיות פרמצבטיות בע"מ | D39: 520013954 | E39: ח.פ | F39: טבע | G39: IL0006290147 | H39: ISIN | I39: מניות | J39: ישראל | K39: ארה"ב | L39: סחיר | M39: TASE | N39: פארמה | O39: לא | P39: ILS | Q39: 7385 | R39: 1 | S39: 5699 | U39: 420.871 | V39: 6e-06 | W39: 0.05551743 | X39: 0.024223887
A40: 337 | B40: 1477 | C40: טיב טעם הולדינגס 1 בע"מ | D40: 520041187 | E40: ח.פ | F40: טיב טעם | G40: IL0001030100 | H40: ISIN | I40: מניות | J40: ישראל | K40: ישראל | L40: סחיר | M40: TASE | N40: רשתות שיווק | O40: לא | P40: ILS | Q40: 4200 | R40: 1 | S40: 810 | U40: 34.02 | V40: 3.9e-05 | W40: 0.0044876038 | X40: 0.0019580734
A41: 337 | B41: 1477 | C41: ישראמקו נגב 2 שותפות מוגבלת | D41: 550010003 | E41: מספר שותפות | F41: ישראמקו יהש | G41: IL0002320179 | H41: ISIN | I41: מניות | J41: ישראל | K41: ישראל | L41: סחיר | M41: TASE | N41: חיפושי נפט וגז | O41: לא | P41: ILS | Q41: 6100 | R41: 1 | S41: 229.9 | U41: 14.024 | V41: 2e-06 | W41: 0.0018499032 | X41: 0.00080716714
A42: 337 | B42: 1477 | C42: ישרוטל בע"מ | D42: 520042482 | E42: ח.פ | F42: ישרוטל | G42: IL0010809858 | H42: ISIN | I42: מניות | J42: ישראל | K42: ישראל | L42: סחיר | M42: TASE | N42: מלונאות ותיירות | O42: לא | P42: ILS | Q42: 65 | R42: 1 | S42: 9500 | U42: 6.175 | V42: 1e-06 | W42: 0.0008145489 | X42: 0.00035541163
A43: 337 | B43: 1477 | C43: כלל החזקות עסקי ביטוח בע"מ | D43: 520036120 | E43: ח.פ | F43: כלל ביטוח | G43: IL0002240146 | H43: ISIN | I43: מניות | J43: ישראל | K43: ישראל | L43: סחיר | M43: TASE | N43: ביטוח | O43: לא | P43: ILS | Q43: 2074 | R43: 1 | S43: 14880 | U43: 308.611 | V43: 2.6e-05 | W43: 0.040709136 | X43: 0.017762592
A44: 337 | B44: 1477 | C44: בנק לאומי לישראל בע"מ | D44: 520018078 | E44: ח.פ | F44: לאומי | G44: IL0006046119 | H44: ISIN | I44: מניות | J44: ישראל | K44: ישראל | L44: סחיר | M44: TASE | N44: בנקים | O44: לא | P44: ILS | Q44: 3440 | R44: 1 | S44: 6262 | U44: 215.413 | V44: 2e-06 | W44: 0.028415265 | X44: 0.012398415
A45: 337 | B45: 1477 | C45: יוחננוף | D45: 511344186 | E45: ח.פ | F45: מ. יוחננוף | G45: IL0011612640 | H45: ISIN | I45: מניות | J45: ישראל | K45: ישראל | L45: סחיר | M45: TASE | N45: רשתות שיווק | O45: לא | P45: ILS | Q45: 320 | R45: 1 | S45: 30850 | U45: 98.72 | V45: 2.2e-05 | W45: 0.01302223 | X45: 0.0056819815
A46: 337 | B46: 1477 | C46: מבנה נדל"ן (כ.ד) בע"מ | D46: 520024126 | E46: ח.פ | F46: מבנה | G46: IL0002260193 | H46: ISIN | I46: מניות | J46: ישראל | K46: ישראל | L46: סחיר | M46: TASE | N46: נדל"ן מניב בישראל | O46: לא | P46: ILS | Q46: 5129 | R46: 1 | S46: 1262 | U46: 64.728 | V46: 7e-06 | W46: 0.0085383166 | X46: 0.0037255185
A47: 337 | B47: 1477 | C47: בנק מזרחי טפחות בע"מ | D47: 520000522 | E47: ח.פ | F47: מזרחי טפחות | G47: IL0006954379 | H47: ISIN | I47: מניות | J47: ישראל | K47: ישראל | L47: סחיר | M47: TASE | N47: בנקים | O47: לא | P47: ILS | Q47: 499 | R47: 1 | S47: 21950 | U47: 109.531 | V47: 2e-06 | W47: 0.014448251 | X47: 0.0063041965
A48: 337 | B48: 1477 | C48: מטריקס אי.טי בע"מ | D48: 520039413 | E48: ח.פ | F48: מטריקס | G48: IL0004450156 | H48: ISIN | I48: מניות | J48: ישראל | K48: ישראל | L48: סחיר | M48: TASE | N48: שירותי מידע | O48: לא | P48: ILS | Q48: 235 | R48: 1 | S48: 11720 | U48: 27.542 | V48: 4e-06 | W48: 0.003633086 | X48: 0.0015852222
A49: 337 | B49: 1477 | C49: מליסרון בע"מ | D49: 520037789 | E49: ח.פ | F49: מליסרון | G49: IL0003230146 | H49: ISIN | I49: מניות | J49: ישראל | K49: ישראל | L49: סחיר | M49: TASE | N49: נדל"ן מניב בישראל | O49: לא | P49: ILS | Q49: 245 | R49: 1 | S49: 38400 | U49: 94.08 | V49: 5e-06 | W49: 0.012410164 | X49: 0.0054149192
... A80: 337 | B80: 1477 | C80: amazon.com | D80: ZXTILKJKG63JELOEG630 | E80: LEI | F80: AMAZON.COM INC | G80: US0231351067 | H80: ISIN | I80: מניות | J80: חו"ל | K80: ארה"ב | L80: סחיר | M80: NASDAQ | N80: Textiles, Apparel & Luxury Goods | O80: לא | P80: USD | Q80: 29 | R80: 3.372 | S80: 21939 | U80: 21.454 | V80: 0 | W80: 0.0028299749 | X80: 0.0012348013
A81: 337 | B81: 1477 | C81: ALIBABA COM LTD | D81: 5493001NTNQJDH60PM02 | E81: LEI | F81: BABA US Alibaba Group Holding Ltd | G81: US01609W1027 | H81: ISIN | I81: מניות | J81: חו"ל | K81: סין | L81: סחיר | M81: NYSE | N81: Textiles, Apparel & Luxury Goods | O81: לא | P81: USD | Q81: 72 | R81: 3.372 | S81: 11341 | T81: 0.0684 | U81: 27.76 | V81: 0 | W81: 0.003695401 | X81: 0.0016124121
A82: 337 | B82: 1477 | C82: Deere&Company | D82: PWFTNG3EI0Y73OXWDH08 | E82: LEI | F82: DEERE & CO | G82: US2441991054 | H82: ISIN | I82: מניות | J82: חו"ל | K82: ארה"ב | L82: סחיר | M82: NYSE | N82: Food & Staples Retailing Consumer Staples Distribution & Retail | O82: לא | P82: USD | Q82: 27 | R82: 3.372 | S82: 50849 | T82: 0.033 | U82: 46.405 | V82: 0 | W82: 0.0061213796 | X82: 0.0026709379
A83: 337 | B83: 1477 | C83: ELI LILLY & CO | D83: FRDRIPF3EKNDJ2CQJL29 | E83: LEI | F83: Eli Lilly | G83: US5324571083 | H83: ISIN | I83: מניות | J83: חו"ל | K83: ארה"ב | L83: סחיר | M83: NYSE | N83: Pharmaceuticals | O83: לא | P83: USD | Q83: 15 | R83: 3.372 | S83: 77953 | U83: 39.429 | V83: 0 | W83: 0.0052010599 | X83: 0.0022693753
A84: 337 | B84: 1477 | C84: Meta Platforms Inc | D84: BQ4BKCS1HXDV9HN80Z93 | E84: LEI | F84: Facebook Inc | G84: US30303M1027 | H84: ISIN | I84: מניות | J84: חו"ל | K84: ארה"ב | L84: סחיר | M84: NASDAQ | N84: Diversified Telecommunication Services | O84: לא | P84: USD | Q84: 17 | R84: 3.372 | S84: 73809 | U84: 42.31 | V84: 0 | W84: 0.0055811797 | X84: 0.0024352328
A85: 337 | B85: 1477 | C85: INTEL CORP | D85: KNX4USFCNGPY45LOCE31 | E85: LEI | F85: Intel corp | G85: US4581401001 | H85: ISIN | I85: מניות | J85: חו"ל | K85: ארה"ב | L85: סחיר | M85: NASDAQ | N85: Semiconductors & Semiconductor | O85: לא | P85: USD | Q85: 451 | R85: 3.372 | S85: 2240 | U85: 34.065 | V85: 0 | W85: 0.0044935784 | X85: 0.0019606803
A86: 337 | B86: 1477 | C86: JP MORGAN ASSET MANAGEMENT | D86: 8I5DZWZKVSZI1NUHU748 | E86: LEI | F86: JPMORGAN CHASE & CO | G86: US46625H1005 | H86: ISIN | I86: מניות | J86: חו"ל | K86: ארה"ב | L86: סחיר | M86: NYSE | N86: Banks | O86: לא | P86: USD | Q86: 14 | R86: 3.372 | S86: 28991 | U86: 13.686 | V86: 0 | W86: 0.00180534 | X86: 0.00078772289
A87: 337 | B87: 1477 | C87: MARVELL TECH | D87: 8DF36O58U3QIHUCGZB18 | E87: LEI | F87: Marvell tech group | G87: BMG5876H1051 | H87: ISIN | I87: מניות | J87: חו"ל | K87: ארה"ב | L87: סחיר | M87: NASDAQ | N87: Semiconductors & Semiconductor | O87: לא | P87: USD | Q87: 615 | R87: 3.372 | S87: 7740 | U87: 160.511 | V87: 1e-06 | W87: 0.02117307 | X87: 0.009238433
A88: 337 | B88: 1477 | C88: MONDELEZ INTERNATIONAL | D88: 549300DV9GIB88LZ5P30 | E88: LEI | F88: MONDELEZ INTERNATIONAL INC | G88: US6092071058 | H88: ISIN | I88: מניות | J88: חו"ל | K88: ארה"ב | L88: סחיר | M88: NASDAQ | N88: Food Products | O88: לא | P88: USD | Q88: 60 | R88: 3.372 | S88: 6744 | T88: 0.021 | U88: 13.716 | V88: 0 | W88: 0.0018092497 | X88: 0.00078942884
A89: 337 | B89: 1477 | C89: נייס מערכות בע"מ | D89: 520036872 | E89: ח.פ | F89: NICE SYS ADR | G89: US6536561086 | H89: ISIN | I89: מניות | J89: חו"ל | K89: ישראל | L89: סחיר | M89: NASDAQ | N89: Wireless Telecommunication Services | O89: לא | P89: USD | Q89: 18 | R89: 3.372 | S89: 16891 | U89: 10.252 | V89: 0 | W89: 0.0013523703 | X89: 0.00059007892
A90: 337 | B90: 1477 | C90: NIKE INC | D90: 787RXPR0UX0O0XUXPZ81 | E90: LEI | F90: NIKE INC | G90: US6541061031 | H90: ISIN | I90: מניות | J90: חו"ל | K90: ארה"ב | L90: סחיר | M90: NYSE | N90: Textiles, Apparel & Luxury Goods | O90: לא | P90: USD | Q90: 304 | R90: 3.372 | S90: 7104 | U90: 72.822 | V90: 0 | W90: 0.009606038 | X90: 0.0041913967
A91: 337 | B91: 1477 | C91: NVIDIA CORP | D91: 549300S4KLFTLO7GSQ80 | E91: LEI | F91: Nvidia corp | G91: US67066G1040 | H91: ISIN | I91: מניות | J91: חו"ל | K91: ארה"ב | L91: סחיר | M91: NASDAQ | N91: Semiconductors & Semiconductor Equipment | O91: לא | P91: USD | Q91: 357 | R91: 3.372 | S91: 15799 | T91: 0.003 | U91: 190.198 | V91: 0 | W91: 0.025089165 | X91: 0.01094714
A92: 337 | B92: 1477 | C92: אורמת טכנולגיות אינק | D92: 5493000TSHHWY24VHM09 | E92: LEI | F92: Ormat Technologies | G92: US6866881021 | H92: ISIN | I92: מניות | J92: חו"ל | K92: ארה"ב | L92: סחיר | M92: NYSE | N92: Water Utilities | O92: לא | P92: USD | Q92: 23 | R92: 3.372 | S92: 8376 | U92: 6.496 | V92: 0 | W92: 0.0008569042 | X92: 0.00037389249
A93: 337 | B93: 1477 | C93: Palo alto networks inc | D93: 549300QXR2YVZV231H43 | E93: LEI | F93: PALO ALTO NETWORKS INC | G93: US6974351057 | H93: ISIN | I93: מניות | J93: חו"ל | K93: ארה"ב | L93: סחיר | M93: NASDAQ | N93: Software | O93: לא | P93: USD | Q93: 56 | R93: 3.372 | S93: 20464 | U93: 38.643 | V93: 0 | W93: 0.0050973719 | X93: 0.0022241332
A94: 337 | B94: 1477 | C94: PPHE HOTEL GROUP LTD | D94: 2138003H1BZGR6KM5823 | E94: LEI | F94: PP HOTEL GROUP LTD | G94: GG00B1Z5FH87 | H94: ISIN | I94: מניות | J94: חו"ל | K94: בריטניה | L94: סחיר | M94: LSE | N94: Diversified Consumer Services | O94: לא | P94: GBP | Q94: 310 | R94: 4.6236 | S94: 1600 | U94: 22.933 | V94: 7e-06 | W94: 0.0030251167 | X94: 0.0013199473
A95: 337 | B95: 1477 | C95: Saleforce.com Inc | D95: RCGZFPDMRW58VJ54VR07 | E95: LEI | F95: Saleforce | G95: US794466L3024 | H95: ISIN | I95: מניות | J95: חו"ל | K95: ארה"ב | L95: סחיר | M95: NASDAQ | N95: Software | O95: לא | P95: USD | Q95: 0 | R95: 3.372 | S95: 0 | T95: 0.024 | U95: 0.08 | V95: 0 | W95: 1.0537031e-05 | X95: 4.5976163e-06
A96: 337 | B96: 1477 | C96: TAIWAN Semiconductor | D96: 549300KB6NK5SBD14S87 | E96: LEI | F96: TAIWAN SEMICON ADR | G96: US8740391003 | H96: ISIN | I96: מניות | J96: חו"ל | K96: סין | L96: סחיר | M96: NYSE | N96: Semiconductors & Semiconductor Equipment | O96: לא | P96: USD | Q96: 50 | R96: 3.372 | S96: 22649 | T96: 0.03 | U96: 38.286 | V96: 0 | W96: 0.0050503712 | X96: 0.0022036254
A97: 337 | B97: 9962 | C97: או.פי.סי. אנרגיה בע"מ | D97: 514401702 | E97: ח.פ | F97: או פי סי אנרגיה | G97: IL0011415713 | H97: ISIN | I97: מניות | J97: ישראל | K97: ישראל | L97: סחיר | M97: TASE | N97: אנרגיה | O97: לא | P97: ILS | Q97: 3856 | R97: 1 | S97: 4100 | U97: 158.096 | V97: 1.4e-05 | W97: 0.016414395 | X97: 0.0037159903
A98: 337 | B98: 9962 | C98: אורמת טכנולגיות אינק | D98: 5493000TSHHWY24VHM09 | E98: LEI | F98: אורמת טכנולוגיות | G98: US6866881021 | H98: ISIN | I98: מניות | J98: ישראל | K98: ארה"ב | L98: סחיר | M98: TASE | N98: אנרגיה מתחדשת | O98: לא | P98: ILS | Q98: 530 | R98: 1 | S98: 27780 | U98: 147.234 | V98: 9e-06 | W98: 0.015286643 | X98: 0.0034606829
A99: 337 | B99: 9962 | C99: איי.סי.אל גרופ בע"מ (דואלי) | D99: 520027830 | E99: ח.פ | F99: איי.סי.אל | G99: IL0002810146 | H99: ISIN | I99: מניות | J99: ישראל | K99: ישראל | L99: סחיר | M99: TASE | N99: כימיה, גומי ופלסטיק | O99: לא | P99: ILS | Q99: 9074 | R99: 1 | S99: 2309 | U99: 209.519 | V99: 7e-06 | W99: 0.021753378 | X99: 0.0049246617
A100: 337 | B100: 9962 | C100: אינרום תעשיות בנייה בע"מ | D100: 515001659 | E100: ח.פ | F100: אינרום | G100: IL0011323560 | H100: ISIN | I100: מניות | J100: ישראל | K100: ישראל | L100: סחיר | M100: TASE | N100: מתכת ומוצרי בניה | O100: לא | P100: ILS | Q100: 2000 | R100: 1 | S100: 2100 | U100: 42 | V100: 1.3e-05 | W100: 0.0043606708 | X100: 0.00098719508
A101: 337 | B101: 9962 | C101: אלביט מערכות בע"מ | D101: 520043027 | E101: ח.פ | F101: אלביט מערכות | G101: IL0010811243 | H101: ISIN | I101: מניות | J101: ישראל | K101: ישראל | L101: סחיר | M101: TASE | N101: ביטחוניות | O101: לא | P101: ILS | Q101: 224 | R101: 1 | S101: 149800 | T101: 0.474 | U101: 336.026 | V101: 5e-06 | W101: 0.034888041 | X101: 0.0078981661
A102: 337 | B102: 9962 | C102: אלוני-חץ נכסים והשקעות בע"מ | D102: 520038506 | E102: ח.פ | F102: אלוני חץ | G102: IL0003900136 | H102: ISIN | I102: מניות | J102: ישראל | K102: ישראל | L102: סחיר | M102: TASE | N102: נדל"ן מניב בישראל | O102: לא | P102: ILS | Q102: 1836 | R102: 1 | S102: 3489 | U102: 64.058 | V102: 9e-06 | W102: 0.0066508577 | X102: 0.0015056615
A103: 337 | B103: 9962 | C103: אלקטרה נדל"ן בע"מ | D103: 510607328 | E103: ח.פ | F103: אלקטרה נדלן | G103: IL0010940448 | H103: ISIN | I103: מניות | J103: ישראל | K103: ישראל | L103: סחיר | M103: TASE | N103: נדל"ן מניב בחו"ל | O103: לא | P103: ILS | Q103: 1314 | R103: 1 | S103: 5007 | U103: 65.792 | V103: 2e-05 | W103: 0.0068308848 | X103: 0.0015464171
A104: 337 | B104: 9962 | C104: אמות השקעות בע"מ | D104: 520026683 | E104: ח.פ | F104: אמות | G104: IL0010972789 | H104: ISIN | I104: מניות | J104: ישראל | K104: ישראל | L104: סחיר | M104: TASE | N104: נדל"ן מניב בישראל | O104: לא | P104: ILS | Q104: 3221 | R104: 1 | S104: 2281 | U104: 73.471 | V104: 7e-06 | W104: 0.0076281639 | X104: 0.00172691
A105: 337 | B105: 9962 | C105: אנלייט אנרגיה מתחדשת בע"מ | D105: 520041146 | E105: ח.פ | F105: אנלייט אנרגיה | G105: IL0007200111 | H105: ISIN | I105: מניות | J105: ישראל | K105: ארה"ב | L105: סחיר | M105: TASE | N105: אנרגיה מתחדשת | O105: לא | P105: ILS | Q105: 1287.7 | R105: 1 | S105: 7640 | U105: 98.38 | V105: 1.1e-05 | W105: 0.010214381 | X105: 0.0023123935
A106: 337 | B106: 9962 | C106: Energean plc | D106: 98450044QACBL3F8EB03 | E106: LEI | F106: אנרג'יאן | G106: GB00BG12Y042 | H106: ISIN | I106: מניות | J106: ישראל | K106: בריטניה | L106: סחיר | M106: TASE | N106: חיפושי נפט וגז | O106: לא | P106: ILS | Q106: 2020 | R106: 1 | S106: 4272 | T106: 2.043 | U106: 88.338 | V106: 1.1e-05 | W106: 0.0091717191 | X106: 0.0020763494
A107: 337 | B107: 9962 | C107: אנרג'יקס אנרגיות מתחדשות בע"מ | D107: 513901371 | E107: ח.פ | F107: אנרג'יקס | G107: IL0011233553 | H107: ISIN | I107: מניות | J107: ישראל | K107: ישראל | L107: סחיר | M107: TASE | N107: אנרגיה מתחדשת | O107: לא | P107: ILS | Q107: 2349 | R107: 1 | S107: 1244 | U107: 29.222 | V107: 4e-06 | W107: 0.0030339429 | X107: 0.00068684238
A108: 337 | B108: 9962 | C108: אפריקה ישראל מגורים בע"מ | D108: 520034760 | E108: ח.פ | F108: אפריקה מגורים | G108: IL0010979487 | H108: ISIN | I108: מניות | J108: ישראל | K108: ישראל | L108: סחיר | M108: TASE | N108: בנייה | O108: לא | P108: ILS | Q108: 66 | R108: 1 | S108: 30100 | U108: 19.866 | V108: 5e-06 | W108: 0.0020625973 | X108: 0.00046694327
A109: 337 | B109: 9962 | C109: ארגו פרופרטיז אן. וי | D109: 70252750 | E109: מספר תאגיד או שותפות בחו"ל | F109: ארגו פרופרטיז אן. וי | G109: NL0015000D84 | H109: ISIN | I109: מניות | J109: ישראל | K109: גרמניה | L109: סחיר | M109: TASE | N109: נדל"ן מניב בחו"ל | O109: לא | P109: ILS | Q109: 720 | R109: 1 | S109: 12250 | U109: 88.2 | V109: 3.3e-05 | W109: 0.0091574086 | X109: 0.0020731097
A110: 337 | B110: 9962 | C110: קבוצת אשטרום | D110: 510381601 | E110: ח.פ | F110: אשטרום קבוצה | G110: IL0011323156 | H110: ISIN | I110: מניות | J110: ישראל | K110: ישראל | L110: סחיר | M110: TASE | N110: בנייה | O110: לא | P110: ILS | Q110: 800 | R110: 1 | S110: 7670 | U110: 61.36 | V110: 7e-06 | W110: 0.0063707323 | X110: 0.001442245
A111: 337 | B111: 9962 | C111: בזק החברה הישראלית לתקשורת בע"מ | D111: 520031931 | E111: ח.פ | F111: בזק | G111: IL0002300114 | H111: ISIN | I111: מניות | J111: ישראל | K111: ישראל | L111: סחיר | M111: TASE | N111: תקשורת ומדיה | O111: לא | P111: ILS | Q111: 12834 | R111: 1 | S111: 575 | U111: 73.796 | V111: 5e-06 | W111: 0.0076618543 | X111: 0.001734537
A112: 337 | B112: 9962 | C112: ביג מרכזי קניות (2004) בע"מ | D112: 513623314 | E112: ח.פ | F112: ביג | G112: IL0010972607 | H112: ISIN | I112: מניות | J112: ישראל | K112: ישראל | L112: סחיר | M112: TASE | N112: נדל"ן מניב בישראל | O112: לא | P112: ILS | Q112: 395 | R112: 1 | S112: 64490 | U112: 254.736 | V112: 1.6e-05 | W112: 0.026448039 | X112: 0.0059874674
A113: 337 | B113: 9962 | C113: הבנק הבינלאומי הראשון לישראל בע"מ | D113: 520029083 | E113: ח.פ | F113: בינלאומי 5 | G113: IL0005930388 | H113: ISIN | I113: מניות | J113: ישראל | K113: ישראל | L113: סחיר | M113: TASE | N113: בנקים | O113: לא | P113: ILS | Q113: 661 | R113: 1 | S113: 24370 | U113: 161.086 | V113: 7e-06 | W113: 0.016724802 | X113: 0.0037862621
A114: 337 | B114: 9962 | C114: בית בכפר בע"מ | D114: 511605719 | E114: ח.פ | F114: בית בכפר | G114: IL0011836561 | H114: ISIN | I114: מניות | J114: ישראל | K114: ישראל | L114: סחיר | M114: TASE | N114: נדל"ן מניב בישראל | O114: לא | P114: ILS | Q114: 1499 | R114: 1 | S114: 1506 | U114: 22.575 | V114: 2.1e-05 | W114: 0.0023438543 | X114: 0.00053061594
A115: 337 | B115: 9962 | C115: מנועי בית שמש אחזקות (1997) בע"מ | D115: 520043480 | E115: ח.פ | F115: בית שמש | G115: IL0010815616 | H115: ISIN | I115: מניות | J115: ישראל | K115: ישראל | L115: סחיר | M115: TASE | N115: מתכת ומוצרי בניה | O115: לא | P115: ILS | Q115: 315 | R115: 1 | S115: 56070 | U115: 176.62 | V115: 3.5e-05 | W115: 0.018337711 | X115: 0.0041514021
A116: 337 | B116: 9962 | C116: חברת גב-ים לקרקעות בע"מ | D116: 520001736 | E116: ח.פ | F116: גב ים | G116: IL0007590198 | H116: ISIN | I116: מניות | J116: ישראל | K116: ישראל | L116: סחיר | M116: TASE | N116: נדל"ן מניב בישראל | O116: לא | P116: ILS | Q116: 1101 | R116: 1 | S116: 3685 | U116: 40.572 | V116: 5e-06 | W116: 0.0042123924 | X116: 0.00095362692
A117: 337 | B117: 9962 | C117: קבוצת דוראל משאבי אנרגיה מתחדשת בעמ | D117: 515364891 | E117: ח.פ | F117: דוראל אנרגיה | G117: IL0011667685 | H117: ISIN | I117: מניות | J117: ישראל | K117: ישראל | L117: סחיר | M117: TASE | N117: אנרגיה מתחדשת | O117: לא | P117: ILS | Q117: 2221 | R117: 1 | S117: 1532 | U117: 34.026 | V117: 1.2e-05 | W117: 0.0035327372 | X117: 0.00079976246
A118: 337 | B118: 9962 | C118: בנק דיסקונט לישראל בע"מ | D118: 520007030 | E118: ח.פ | F118: דיסקונט | G118: IL0006912120 | H118: ISIN | I118: מניות | J118: ישראל | K118: ישראל | L118: סחיר | M118: TASE | N118: בנקים | O118: לא | P118: ILS | Q118: 6526 | R118: 1 | S118: 3356 | U118: 219.013 | V118: 5e-06 | W118: 0.022739087 | X118: 0.0051478124
... A121: 337 | B121: 9962 | C121: הבורסה לניירות ערך בתל-אביב בע"מ | D121: 520020033 | E121: ח.פ | F121: הבורסה לניע בתא | G121: IL0011590291 | H121: ISIN | I121: מניות | J121: ישראל | K121: ישראל | L121: סחיר | M121: TASE | N121: שירותים פיננסיים | O121: לא | P121: ILS | Q121: 748 | R121: 1 | S121: 6510 | U121: 48.695 | V121: 7e-06 | W121: 0.0050557617 | X121: 0.001144554
A122: 337 | B122: 9962 | C122: הולמס פלייס אינטרנשיונל בע"מ | D122: 512466723 | E122: ח.פ | F122: הולמס פלייס | G122: IL0011425878 | H122: ISIN | I122: מניות | J122: ישראל | K122: ישראל | L122: סחיר | M122: TASE | N122: שירותים | O122: לא | P122: ILS | Q122: 12000 | R122: 1 | S122: 732.6 | T122: 1.438 | U122: 89.35 | V122: 0.000131 | W122: 0.0092768141 | X122: 0.0021001414
A123: 337 | B123: 9962 | C123: חברת הכשרת הישוב בישראל- אנרגיה בע"מ | D123: 514423474 | E123: ח.פ | F123: הכשרה התפתחות עירונית | G123: IL0011214744 | H123: ISIN | I123: מניות | J123: ישראל | K123: ישראל | L123: סחיר | M123: TASE | N123: בנייה | O123: לא | P123: ILS | Q123: 7000 | R123: 1 | S123: 711.9 | U123: 49.833 | V123: 8e-05 | W123: 0.0051739359 | X123: 0.001171307
A124: 337 | B124: 9962 | C124: הפניקס אחזקות בע"מ | D124: 520017450 | E124: ח.פ | F124: הפניקס | G124: IL0007670123 | H124: ISIN | I124: מניות | J124: ישראל | K124: ישראל | L124: סחיר | M124: TASE | N124: ביטוח | O124: לא | P124: ILS | Q124: 3120 | R124: 1 | S124: 9745 | U124: 304.044 | V124: 1.2e-05 | W124: 0.031567519 | X124: 0.0071464462
A125: 337 | B125: 9962 | C125: הראל השקעות בביטוח ושרותים פיננסים בע"מ | D125: 520033986 | E125: ח.פ | F125: הראל השקעות | G125: IL0005850180 | H125: ISIN | I125: מניות | J125: ישראל | K125: ישראל | L125: סחיר | M125: TASE | N125: ביטוח | O125: לא | P125: ILS | Q125: 4174 | R125: 1 | S125: 9432 | U125: 393.692 | V125: 1.9e-05 | W125: 0.040875233 | X125: 0.009253583
A126: 337 | B126: 9962 | C126: וואן טכנולוגיות תוכנה(או.אס.טי)בע"מ | D126: 520034695 | E126: ח.פ | F126: וואן טכנולוגיות תוכנה | G126: IL0001610182 | H126: ISIN | I126: מניות | J126: ישראל | K126: ישראל | L126: סחיר | M126: TASE | N126: שירותי מידע | O126: לא | P126: ILS | Q126: 485 | R126: 1 | S126: 8680 | U126: 42.098 | V126: 7e-06 | W126: 0.0043708457 | X126: 0.00098949853
A127: 337 | B127: 9962 | C127: החברה לישראל בע"מ | D127: 520028010 | E127: ח.פ | F127: חברה לישראל | G127: IL0005760173 | H127: ISIN | I127: מניות | J127: ישראל | K127: ישראל | L127: סחיר | M127: TASE | N127: השקעה ואחזקות | O127: לא | P127: ILS | Q127: 82 | R127: 1 | S127: 112370 | U127: 92.143 | V127: 1.1e-05 | W127: 0.0095668341 | X127: 0.0021657979
A128: 337 | B128: 9962 | C128: קבוצת חג'ג' ייזום נדל"ן בע"מ | D128: 520033309 | E128: ח.פ | F128: חג'ג' נדלן | G128: IL0008230133 | H128: ISIN | I128: מניות | J128: ישראל | K128: ישראל | L128: סחיר | M128: TASE | N128: בנייה | O128: לא | P128: ILS | Q128: 2503 | R128: 1 | S128: 2063 | U128: 51.637 | V128: 4e-05 | W128: 0.0053612256 | X128: 0.0012137068
A129: 337 | B129: 9962 | C129: חילן בע"מ | D129: 520039942 | E129: ח.פ | F129: חילן | G129: IL0010846983 | H129: ISIN | I129: מניות | J129: ישראל | K129: ישראל | L129: סחיר | M129: TASE | N129: שירותי מידע | O129: לא | P129: ILS | Q129: 144 | R129: 1 | S129: 28610 | U129: 41.198 | V129: 6e-06 | W129: 0.0042774442 | X129: 0.00096835375
A130: 337 | B130: 9962 | C130: קבוצת חמת בע"מ | D130: 520038530 | E130: ח.פ | F130: חמת | G130: IL0003840167 | H130: ISIN | I130: מניות | J130: ישראל | K130: ישראל | L130: סחיר | M130: TASE | N130: מתכת ומוצרי בניה | O130: לא | P130: ILS | Q130: 1370 | R130: 1 | S130: 1866 | T130: 0.561 | U130: 26.125 | V130: 3.7e-05 | W130: 0.002712441 | X130: 0.00061405884
A131: 337 | B131: 9962 | C131: טאואר סמיקונדקטור בע"מ | D131: 520041997 | E131: ח.פ | F131: טאואר | G131: IL0010823792 | H131: ISIN | I131: מניות | J131: ישראל | K131: גלובלי | L131: סחיר | M131: TASE | N131: מוליכים למחצה | O131: לא | P131: ILS | Q131: 500 | R131: 1 | S131: 14620 | U131: 73.1 | V131: 4e-06 | W131: 0.0075896436 | X131: 0.0017181895
A132: 337 | B132: 9962 | C132: טבע תעשיות פרמצבטיות בע"מ | D132: 520013954 | E132: ח.פ | F132: טבע | G132: IL0006290147 | H132: ISIN | I132: מניות | J132: ישראל | K132: ארה"ב | L132: סחיר | M132: TASE | N132: פארמה | O132: לא | P132: ILS | Q132: 8180 | R132: 1 | S132: 5699 | U132: 466.178 | V132: 7e-06 | W132: 0.048401182 | X132: 0.010957353
A133: 337 | B133: 9962 | C133: טיב טעם הולדינגס 1 בע"מ | D133: 520041187 | E133: ח.פ | F133: טיב טעם | G133: IL0001030100 | H133: ISIN | I133: מניות | J133: ישראל | K133: ישראל | L133: סחיר | M133: TASE | N133: רשתות שיווק | O133: לא | P133: ILS | Q133: 4467 | R133: 1 | S133: 810 | U133: 36.183 | V133: 4.1e-05 | W133: 0.0037566867 | X133: 0.00085046151
A134: 337 | B134: 9962 | C134: ישראמקו נגב 2 שותפות מוגבלת | D134: 550010003 | E134: מספר שותפות | F134: ישראמקו יהש | G134: IL0002320179 | H134: ISIN | I134: מניות | J134: ישראל | K134: ישראל | L134: סחיר | M134: TASE | N134: חיפושי נפט וגז | O134: לא | P134: ILS | Q134: 40000 | R134: 1 | S134: 229.9 | U134: 91.96 | V134: 1.5e-05 | W134: 0.0095477925 | X134: 0.0021614871
A135: 337 | B135: 9962 | C135: כלל החזקות עסקי ביטוח בע"מ | D135: 520036120 | E135: ח.פ | F135: כלל ביטוח | G135: IL0002240146 | H135: ISIN | I135: מניות | J135: ישראל | K135: ישראל | L135: סחיר | M135: TASE | N135: ביטוח | O135: לא | P135: ILS | Q135: 2699 | R135: 1 | S135: 14880 | U135: 401.611 | V135: 3.4e-05 | W135: 0.041697481 | X135: 0.0094397285
...

Sheet קרנות סל
A1: מספר קופה/קרן/ח.פ. עבור חברת ביטוח | B1: מספר מסלול | C1: שם מנפיק | D1: מספר מנפיק | E1: סוג מספר מזהה מנפיק | F1: שם נייר ערך | G1: מספר נייר ערך | H1: סוג מספר נייר ערך | I1: מאפיין עיקרי | J1: ישראל/חו"ל | K1: מדינה לפי חשיפה כלכלית | L1: זירת מסחר | M1: סיווג הקרן | N1: בעל עניין/צד קשור | O1: מטבע פעילות | P1: ערך נקוב (יחידות) | Q1: שער חליפין | R1: שער נייר הערך | S1: סכום לקבל (במטבע הפעילות) | T1: שווי הוגן (באלפי ש"ח) | U1: שיעור מערך נקוב מונפק | V1: שיעור מנכסי אפיק ההשקעה | W1: שיעור מסך נכסי ההשקעה
A2: 337 | B2: 1405 | C2: מגדל קרנות נאמנות בע"מ | D2: 511303661 | E2: ח.פ | F2: MTF.תלבונדשקלי | G2: IL0011500027 | H2: ISIN | I2: עוקב אחר מדדים אחרים בישראל | J2: ישראל | K2: ישראל | L2: TASE | M2: אג"ח בישראל - חברות והמרה | N2: לא | O2: ILS | P2: 12757 | Q2: 1 | R2: 482.69 | T2: 61.577 | U2: 5.2e-05 | V2: 0.10101415 | W2: 0.0068286674
A3: 337 | B3: 1405 | C3: קסם קרנות נאמנות בע"מ | D3: 510938608 | E3: ח.פ | F3: קסם תל בונד שקלי | G3: IL0011464141 | H3: ISIN | I3: עוקב אחר מדדים אחרים בישראל | J3: ישראל | K3: ישראל | L3: TASE | M3: אג"ח בישראל - חברות והמרה | N3: לא | O3: ILS | P3: 10345 | Q3: 1 | R3: 4144.02 | T3: 428.699 | U3: 0.000192 | V3: 0.70326286 | W3: 0.047541342
A4: 337 | B4: 1405 | C4: BlackRock Asset Managment | D4: 254900UWHMJRRODS3Z64 | E4: LEI | F4: Ishares iboxx h/y corp | G4: US4642885135 | H4: ISIN | I4: עוקב אחר מדדים אחרים בחו"ל | J4: חו"ל | K4: ארה"ב | L4: NYSE | M4: Bond/Fixed Income Funds | N4: לא | O4: USD | P4: 114 | Q4: 3.372 | R4: 8065 | T4: 31.003 | U4: 0 | V4: 0.050858335 | W4: 0.0034380793
A5: 337 | B5: 1405 | C5: State Street Corp | D5: 07F5H7W3ET8ZLWNMFP29 | E5: LEI | F5: SPDR BLOOMBERG SASB U.S. HIGH | G5: IE0004TYCC17 | H5: ISIN | I5: עוקב אחר מדדים אחרים בחו"ל | J5: חו"ל | K5: ארה"ב | L5: NYSE | M5: Bond/Fixed Income Funds | N5: לא | O5: USD | P5: 2326 | Q5: 3.372 | R5: 1125.9 | T5: 88.307 | U5: 0 | V5: 0.14486466 | W5: 0.00979301
A6: 337 | B6: 1477 | C6: מגדל קרנות נאמנות בע"מ | D6: 511303661 | E6: ח.פ | F6: MTF500SP ממ | G6: IL0011505729 | H6: ISIN | I6: עוקב אחר מדדי מניות בחו"ל | J6: ישראל | K6: ארה"ב | L6: TASE | M6: מניות בחו"ל משולבת | N6: לא | O6: ILS | P6: 1649 | Q6: 1 | R6: 7820 | T6: 128.952 | U6: 6.8e-05 | V6: 0.016309503 | W6: 0.0074219725
A7: 337 | B7: 1477 | C7: אי.בי.אי קרנות נאמנות בע"מ | D7: 513765339 | E7: ח.פ | F7: אי.בי.אי. סל (4D)י S&P 500 | G7: IL0011481624 | H7: ISIN | I7: עוקב אחר מדדי מניות בחו"ל | J7: ישראל | K7: ארה"ב | L7: TASE | M7: מניות בחו"ל חשופות מט"ח | N7: לא | O7: ILS | P7: 2943 | Q7: 1 | R7: 20650 | T7: 607.73 | U7: 3e-05 | V7: 0.076864117 | W7: 0.034978586
A8: 337 | B8: 1477 | C8: הראל קרנות נאמנות בע"מ | D8: 511776783 | E8: ח.פ | F8: הראל סל (4A) MSCI AC World מנ | G8: IL0011502007 | H8: ISIN | I8: עוקב אחר מדדי מניות בחו"ל | J8: ישראל | K8: גלובלי | L8: TASE | M8: מניות בחו"ל חשופות מט"ח | N8: לא | O8: ILS | P8: 37152 | Q8: 1 | R8: 864.7 | T8: 321.253 | U8: 7.4e-05 | V8: 0.040631325 | W8: 0.018490114
A9: 337 | B9: 1477 | C9: הראל קרנות נאמנות בע"מ | D9: 511776783 | E9: ח.פ | F9: הראל סל תא 90 | G9: IL0011489312 | H9: ISIN | I9: עוקב אחר מדדי מניות בישראל | J9: ישראל | K9: ישראל | L9: TASE | M9: מניות בישראל | N9: לא | O9: ILS | P9: 3637 | Q9: 1 | R9: 3032 | T9: 110.274 | U9: 1.5e-05 | V9: 0.013947161 | W9: 0.0063469405
A10: 337 | B10: 1477 | C10: הראל קרנות נאמנות בע"מ | D10: 511776783 | E10: ח.פ | F10: הראל קרן סל 4AׂSTOXX EUROPE 600ממ | G10: IL0011498891 | H10: ISIN | I10: עוקב אחר מדדי מניות בחו"ל | J10: ישראל | K10: אירופה | L10: TASE | M10: מניות בחו"ל משולבת | N10: לא | O10: ILS | P10: 47386 | Q10: 1 | R10: 699.4 | T10: 331.418 | U10: 0.000201 | V10: 0.041916885 | W10: 0.019075135
A11: 337 | B11: 1477 | C11: הראל קרנות נאמנות בע"מ | D11: 511776783 | E11: ח.פ | F11: הראל.DAX 30 ממ | G11: IL0011491607 | H11: ISIN | I11: עוקב אחר מדדי מניות בחו"ל | J11: ישראל | K11: גרמניה | L11: TASE | M11: מניות בחו"ל משולבת | N11: לא | O11: ILS | P11: 467 | Q11: 1 | R11: 20650 | T11: 96.436 | U11: 4.1e-05 | V11: 0.012196922 | W11: 0.0055504586
A12: 337 | B12: 1477 | C12: מור ניהול קרנות נאמנות בע"מ | D12: 514884485 | E12: ח.פ | F12: מור סל S&P 500 ממ | G12: IL0011658288 | H12: ISIN | I12: עוקב אחר מדדי מניות בחו"ל | J12: ישראל | K12: ארה"ב | L12: TASE | M12: מניות בחו"ל משולבת | N12: לא | O12: ILS | P12: 667 | Q12: 1 | R12: 9600 | T12: 64.032 | U12: 4.9e-05 | V12: 0.0080986082 | W12: 0.0036854371
A13: 337 | B13: 1477 | C13: קסם קרנות נאמנות בע"מ | D13: 510938608 | E13: ח.פ | F13: ממEURO STOXX 50 (4A) ETF.קסם | G13: IL0011459521 | H13: ISIN | I13: עוקב אחר מדדי מניות בחו"ל | J13: ישראל | K13: אירופה | L13: TASE | M13: מניות בחו"ל משולבת | N13: לא | O13: ILS | P13: 4609 | Q13: 1 | R13: 7493 | T13: 345.352 | U13: 0.000331 | V13: 0.04367931 | W13: 0.019877162
... A22: 337 | B22: 1477 | C22: BlackRock Asset Managment | D22: 254900UWHMJRRODS3Z64 | E22: LEI | F22: MCHI_Ishares Msci Chaina Etf | G22: US46429B6719 | H22: ISIN | I22: עוקב אחר מדדי מניות בחו"ל | J22: חו"ל | K22: סין | L22: NASDAQ | M22: Equity Funds | N22: לא | O22: USD | P22: 420 | Q22: 3.372 | R22: 5510 | T22: 78.035 | U22: 3e-06 | V22: 0.0098696506 | W22: 0.0044913861
A23: 337 | B23: 1477 | C23: Invesco investment management limited | D23: ECPGFXU8A2SHKVVGJI15 | E23: LEI | F23: Powershares QQQ NAS1 | G23: US46090E1038 | H23: ISIN | I23: עוקב אחר מדדי מניות בחו"ל | J23: חו"ל | K23: ארה"ב | L23: NASDAQ | M23: Equity Funds | N23: לא | O23: USD | P23: 353 | Q23: 3.372 | R23: 55164 | S23: 0.123 | T23: 657.041 | U23: 1e-06 | V23: 0.083100932 | W23: 0.037816776
A24: 337 | B24: 1477 | C24: Invesco investment management limited | D24: ECPGFXU8A2SHKVVGJI15 | E24: LEI | F24: SOURCE S&P 500 UCITS EFT | G24: IE00B3YCGJ38 | H24: ISIN | I24: עוקב אחר מדדי מניות בחו"ל | J24: חו"ל | K24: ארה"ב | L24: LSE | M24: Equity Funds | N24: לא | O24: USD | P24: 27 | Q24: 3.372 | R24: 122758 | T24: 111.764 | U24: 5e-06 | V24: 0.014135607 | W24: 0.0064326966
A25: 337 | B25: 1477 | C25: State Street Corp | D25: 07F5H7W3ET8ZLWNMFP29 | E25: LEI | F25: SPDR S&P 500 ETF TRUST | G25: US78462F1030 | H25: ISIN | I25: עוקב אחר מדדי מניות בחו"ל | J25: חו"ל | K25: ארה"ב | L25: NYSE | M25: Equity Funds | N25: לא | O25: USD | P25: 623 | Q25: 3.372 | R25: 61785 | S25: 0.822 | T25: 1300.724 | U25: 1e-06 | V25: 0.16451239 | W25: 0.074864721
A26: 337 | B26: 1477 | C26: Van Eck ETF | D26: 549300ZLFKNTXC51ZN76 | E26: LEI | F26: VANECK VECTORS SEMICONDUCTOR | G26: US92189F6768 | H26: ISIN | I26: עוקב אחר מדדי מניות בחו"ל | J26: חו"ל | K26: ארה"ב | L26: NASDAQ | M26: Equity Funds | N26: לא | O26: USD | P26: 99 | Q26: 3.372 | R26: 27888 | T26: 93.098 | U26: 4e-06 | V26: 0.011774798 | W26: 0.0053583622
A27: 337 | B27: 1477 | C27: Vanguard Group | D27: 549300Y88GQ3VLJIBX57 | E27: LEI | F27: VANGUARD S&P 500 | G27: us9229083632 | H27: ISIN | I27: עוקב אחר מדדי מניות בחו"ל | J27: חו"ל | K27: ארה"ב | L27: NYSE | M27: Equity Funds | N27: לא | O27: USD | P27: 637 | Q27: 3.372 | R27: 56803 | S27: 0.833 | T27: 1222.916 | U27: 1e-06 | V27: 0.1546714 | W27: 0.070386377
A28: 337 | B28: 9962 | C28: מגדל קרנות נאמנות בע"מ | D28: 511303661 | E28: ח.פ | F28: MTF סל (S&P 500 (4D | G28: IL0011503336 | H28: ISIN | I28: עוקב אחר מדדי מניות בחו"ל | J28: ישראל | K28: ארה"ב | L28: TASE | M28: מניות בחו"ל חשופות מט"ח | N28: לא | O28: ILS | P28: 872 | Q28: 1 | R28: 8961 | T28: 78.14 | U28: 1e-05 | V28: 0.0070524494 | W28: 0.0018366322
A29: 337 | B29: 9962 | C29: מגדל קרנות נאמנות בע"מ | D29: 511303661 | E29: ח.פ | F29: MTF סל תא 125 | G29: IL0011502833 | H29: ISIN | I29: עוקב אחר מדדי מניות בישראל | J29: ישראל | K29: ישראל | L29: TASE | M29: מניות בישראל | N29: לא | O29: ILS | P29: 2056 | Q29: 1 | R29: 4659 | T29: 95.789 | U29: 2.4e-05 | V29: 0.0086453551 | W29: 0.0022514642
A30: 337 | B30: 9962 | C30: מגדל קרנות נאמנות בע"מ | D30: 511303661 | E30: ח.פ | F30: MTF סל תלבונד 60 | G30: IL0011499964 | H30: ISIN | I30: עוקב אחר מדדים אחרים בישראל | J30: ישראל | K30: ישראל | L30: TASE | M30: אג"ח בישראל - חברות והמרה | N30: לא | O30: ILS | P30: 303768 | Q30: 1 | R30: 488.99 | T30: 1485.395 | U30: 0.001447 | V30: 0.13406303 | W30: 0.034913326
A31: 337 | B31: 9962 | C31: הראל קרנות נאמנות בע"מ | D31: 511776783 | E31: ח.פ | F31: הראל סל (4A) MSCI AC World מנ | G31: IL0011502007 | H31: ISIN | I31: עוקב אחר מדדי מניות בחו"ל | J31: ישראל | K31: גלובלי | L31: TASE | M31: מניות בחו"ל חשופות מט"ח | N31: לא | O31: ILS | P31: 49536 | Q31: 1 | R31: 864.7 | T31: 428.338 | U31: 9.9e-05 | V31: 0.038659249 | W31: 0.010067824
A32: 337 | B32: 9962 | C32: הראל קרנות נאמנות בע"מ | D32: 511776783 | E32: ח.פ | F32: הראל סל תא 90 | G32: IL0011489312 | H32: ISIN | I32: עוקב אחר מדדי מניות בישראל | J32: ישראל | K32: ישראל | L32: TASE | M32: מניות בישראל | N32: לא | O32: ILS | P32: 15621 | Q32: 1 | R32: 3032 | T32: 473.629 | U32: 6.2e-05 | V32: 0.042746942 | W32: 0.01113236
A33: 337 | B33: 9962 | C33: הראל קרנות נאמנות בע"מ | D33: 511776783 | E33: ח.פ | F33: הראל סל תל בונד שקלי | G33: IL0011505232 | H33: ISIN | I33: עוקב אחר מדדים אחרים בישראל | J33: ישראל | K33: ישראל | L33: TASE | M33: אג"ח בישראל - חברות והמרה | N33: לא | O33: ILS | P33: 62014 | Q33: 1 | R33: 415.44 | T33: 257.631 | U33: 0.000227 | V33: 0.023252255 | W33: 0.006055462
A34: 337 | B34: 9962 | C34: הראל קרנות נאמנות בע"מ | D34: 511776783 | E34: ח.פ | F34: הראל קרן סל 4AׂSTOXX EUROPE 600ממ | G34: IL0011498891 | H34: ISIN | I34: עוקב אחר מדדי מניות בחו"ל | J34: ישראל | K34: אירופה | L34: TASE | M34: מניות בחו"ל משולבת | N34: לא | O34: ILS | P34: 13763 | Q34: 1 | R34: 699.4 | T34: 96.258 | U34: 5.8e-05 | V34: 0.0086877188 | W34: 0.0022624967
A35: 337 | B35: 9962 | C35: הראל קרנות נאמנות בע"מ | D35: 511776783 | E35: ח.פ | F35: הראל.DAX 30 ממ | G35: IL0011491607 | H35: ISIN | I35: עוקב אחר מדדי מניות בחו"ל | J35: ישראל | K35: גרמניה | L35: TASE | M35: מניות בחו"ל משולבת | N35: לא | O35: ILS | P35: 673 | Q35: 1 | R35: 20650 | T35: 138.975 | U35: 5.9e-05 | V35: 0.012543021 | W35: 0.0032665127
A36: 337 | B36: 9962 | C36: קסם קרנות נאמנות בע"מ | D36: 510938608 | E36: ח.פ | F36: ממEURO STOXX 50 (4A) ETF.קסם | G36: IL0011459521 | H36: ISIN | I36: עוקב אחר מדדי מניות בחו"ל | J36: ישראל | K36: אירופה | L36: TASE | M36: מניות בחו"ל משולבת | N36: לא | O36: ILS | P36: 5531 | Q36: 1 | R36: 7493 | T36: 414.438 | U36: 0.000397 | V36: 0.03740472 | W36: 0.0097411138
A37: 337 | B37: 9962 | C37: קסם קרנות נאמנות בע"מ | D37: 510938608 | E37: ח.פ | F37: קסם קרן סל תא 125 | G37: IL0011463564 | H37: ISIN | I37: עוקב אחר מדדי מניות בישראל | J37: ישראל | K37: ישראל | L37: TASE | M37: מניות בישראל | N37: לא | O37: ILS | P37: 329 | Q37: 1 | R37: 29540 | T37: 97.187 | U37: 9e-06 | V37: 0.0087714907 | W37: 0.002284313
A38: 337 | B38: 9962 | C38: קסם קרנות נאמנות בע"מ | D38: 510938608 | E38: ח.פ | F38: קסם קרן סל תל בונד 60 | G38: IL0011462327 | H38: ISIN | I38: עוקב אחר מדדים אחרים בישראל | J38: ישראל | K38: ישראל | L38: TASE | M38: אג"ח בישראל - חברות והמרה | N38: לא | O38: ILS | P38: 13000 | Q38: 1 | R38: 3822.55 | T38: 496.932 | U38: 0.000181 | V38: 0.044850113 | W38: 0.011680078
A39: 337 | B39: 9962 | C39: Amundi Asset Management | D39: 213800VZW861M5FHMD50 | E39: LEI | F39: AMUNDI MSCI EMERGING MARKETS I | G39: LU2573967036 | H39: ISIN | I39: עוקב אחר מדדי מניות בחו"ל | J39: חו"ל | K39: שווקים מתעוררים | L39: NASDAQ | M39: Equity Funds | N39: לא | O39: USD | P39: 4210 | Q39: 3.372 | R39: 6036 | T39: 856.878 | U39: 0 | V39: 0.077336749 | W39: 0.020140401
... A44: 337 | B44: 9962 | C44: BlackRock Asset Managment | D44: 254900UWHMJRRODS3Z64 | E44: LEI | F44: MCHI_Ishares Msci Chaina Etf | G44: US46429B6719 | H44: ISIN | I44: עוקב אחר מדדי מניות בחו"ל | J44: חו"ל | K44: סין | L44: NASDAQ | M44: Equity Funds | N44: לא | O44: USD | P44: 710 | Q44: 3.372 | R44: 5510 | T44: 131.916 | U44: 4e-06 | V44: 0.011905963 | W44: 0.0031006071
A45: 337 | B45: 9962 | C45: Invesco investment management limited | D45: ECPGFXU8A2SHKVVGJI15 | E45: LEI | F45: Powershares QQQ NAS1 | G45: US46090E1038 | H45: ISIN | I45: עוקב אחר מדדי מניות בחו"ל | J45: חו"ל | K45: ארה"ב | L45: NASDAQ | M45: Equity Funds | N45: לא | O45: USD | P45: 710 | Q45: 3.372 | R45: 55164 | S45: 0.237 | T45: 1321.491 | U45: 1e-06 | V45: 0.11927004 | W45: 0.031060867
A46: 337 | B46: 9962 | C46: Invesco investment management limited | D46: ECPGFXU8A2SHKVVGJI15 | E46: LEI | F46: SOURCE S&P 500 UCITS EFT | G46: IE00B3YCGJ38 | H46: ISIN | I46: עוקב אחר מדדי מניות בחו"ל | J46: חו"ל | K46: ארה"ב | L46: LSE | M46: Equity Funds | N46: לא | O46: USD | P46: 513 | Q46: 3.372 | R46: 122758 | T46: 2123.512 | U46: 0.000101 | V46: 0.19165571 | W46: 0.049911884
A47: 337 | B47: 9962 | C47: State Street Corp | D47: 07F5H7W3ET8ZLWNMFP29 | E47: LEI | F47: SPDR BLOOMBERG SASB U.S. HIGH | G47: IE0004TYCC17 | H47: ISIN | I47: עוקב אחר מדדים אחרים בחו"ל | J47: חו"ל | K47: ארה"ב | L47: NYSE | M47: Bond/Fixed Income Funds | N47: לא | O47: USD | P47: 2754 | Q47: 3.372 | R47: 1125.9 | T47: 104.557 | U47: 0 | V47: 0.0094366607 | W47: 0.0024575397
A48: 337 | B48: 9962 | C48: Van Eck ETF | D48: 549300ZLFKNTXC51ZN76 | E48: LEI | F48: VANECK VECTORS SEMICONDUCTOR | G48: US92189F6768 | H48: ISIN | I48: עוקב אחר מדדי מניות בחו"ל | J48: חו"ל | K48: ארה"ב | L48: NASDAQ | M48: Equity Funds | N48: לא | O48: USD | P48: 102 | Q48: 3.372 | R48: 27888 | T48: 95.919 | U48: 4e-06 | V48: 0.0086570938 | W48: 0.0022545213
A49: 337 | B49: 9962 | C49: Vanguard Group | D49: 549300Y88GQ3VLJIBX57 | E49: LEI | F49: VANGUARD S&P 500 | G49: us9229083632 | H49: ISIN | I49: עוקב אחר מדדי מניות בחו"ל | J49: חו"ל | K49: ארה"ב | L49: NYSE | M49: Equity Funds | N49: לא | O49: USD | P49: 789 | Q49: 3.372 | R49: 56803 | S49: 1.032 | T49: 1514.727 | U49: 1e-06 | V49: 0.13671031 | W49: 0.035602745
A50: 337 | B50: 9963 | C50: מגדל קרנות נאמנות בע"מ | D50: 511303661 | E50: ח.פ | F50: MTF סל (S&P 500 (4D | G50: IL0011503336 | H50: ISIN | I50: עוקב אחר מדדי מניות בחו"ל | J50: ישראל | K50: ארה"ב | L50: TASE | M50: מניות בחו"ל חשופות מט"ח | N50: לא | O50: ILS | P50: 40700 | Q50: 1 | R50: 8961 | T50: 3647.127 | U50: 0.000466 | V50: 0.018627011 | W50: 0.0032779286
A51: 337 | B51: 9963 | C51: מגדל קרנות נאמנות בע"מ | D51: 511303661 | E51: ח.פ | F51: MTF.תלבונדשקלי | G51: IL0011500027 | H51: ISIN | I51: עוקב אחר מדדים אחרים בישראל | J51: ישראל | K51: ישראל | L51: TASE | M51: אג"ח בישראל - חברות והמרה | N51: לא | O51: ILS | P51: 1077354 | Q51: 1 | R51: 482.69 | T51: 5200.28 | U51: 0.004375 | V51: 0.026559446 | W51: 0.0046738561
A52: 337 | B52: 9963 | C52: מגדל קרנות נאמנות בע"מ | D52: 511303661 | E52: ח.פ | F52: MTF500SP ממ | G52: IL0011505729 | H52: ISIN | I52: עוקב אחר מדדי מניות בחו"ל | J52: ישראל | K52: ארה"ב | L52: TASE | M52: מניות בחו"ל משולבת | N52: לא | O52: ILS | P52: 340258 | Q52: 1 | R52: 7820 | T52: 26608.176 | U52: 0.01396 | V52: 0.13589622 | W52: 0.023914632
A53: 337 | B53: 9963 | C53: מגדל קרנות נאמנות בע"מ | D53: 511303661 | E53: ח.פ | F53: MTF600STX ממ | G53: IL0011506149 | H53: ISIN | I53: עוקב אחר מדדי מניות בחו"ל | J53: ישראל | K53: אירופה | L53: TASE | M53: מניות בחו"ל משולבת | N53: לא | O53: ILS | P53: 51170 | Q53: 1 | R53: 8095 | T53: 4142.212 | U53: 0.012521 | V53: 0.021155561 | W53: 0.0037228958
A54: 337 | B54: 9963 | C54: הראל קרנות נאמנות בע"מ | D54: 511776783 | E54: ח.פ | F54: הראל סל (4A) MSCI AC World מנ | G54: IL0011502007 | H54: ISIN | I54: עוקב אחר מדדי מניות בחו"ל | J54: ישראל | K54: גלובלי | L54: TASE | M54: מניות בחו"ל חשופות מט"ח | N54: לא | O54: ILS | P54: 573613 | Q54: 1 | R54: 864.7 | T54: 4960.032 | U54: 0.001141 | V54: 0.025332423 | W54: 0.004457928
A55: 337 | B55: 9963 | C55: הראל קרנות נאמנות בע"מ | D55: 511776783 | E55: ח.פ | F55: הראל סל בונד שק- בנקוביט | G55: IL0011507477 | H55: ISIN | I55: עוקב אחר מדדים אחרים בישראל | J55: ישראל | K55: ישראל | L55: TASE | M55: אג"ח בישראל - חברות והמרה | N55: לא | O55: ILS | P55: 1202935 | Q55: 1 | R55: 431.75 | T55: 5193.672 | U55: 0.01114 | V55: 0.026525696 | W55: 0.0046679169
A56: 337 | B56: 9963 | C56: הראל קרנות נאמנות בע"מ | D56: 511776783 | E56: ח.פ | F56: הראל סל תא 90 | G56: IL0011489312 | H56: ISIN | I56: עוקב אחר מדדי מניות בישראל | J56: ישראל | K56: ישראל | L56: TASE | M56: מניות בישראל | N56: לא | O56: ILS | P56: 115740 | Q56: 1 | R56: 3032 | T56: 3509.237 | U56: 0.000463 | V56: 0.017922763 | W56: 0.003153997
A57: 337 | B57: 9963 | C57: הראל קרנות נאמנות בע"מ | D57: 511776783 | E57: ח.פ | F57: הראל קרן סל 4AׂSTOXX EUROPE 600ממ | G57: IL0011498891 | H57: ISIN | I57: עוקב אחר מדדי מניות בחו"ל | J57: ישראל | K57: אירופה | L57: TASE | M57: מניות בחו"ל משולבת | N57: לא | O57: ILS | P57: 1137800 | Q57: 1 | R57: 699.4 | T57: 7957.773 | U57: 0.004819 | V57: 0.04064282 | W57: 0.0071522085
A58: 337 | B58: 9963 | C58: הראל קרנות נאמנות בע"מ | D58: 511776783 | E58: ח.פ | F58: הראל.DAX 30 ממ | G58: IL0011491607 | H58: ISIN | I58: עוקב אחר מדדי מניות בחו"ל | J58: ישראל | K58: גרמניה | L58: TASE | M58: מניות בחו"ל משולבת | N58: לא | O58: ILS | P58: 16336 | Q58: 1 | R58: 20650 | T58: 3373.384 | U58: 0.001431 | V58: 0.01722892 | W58: 0.0030318966
A59: 337 | B59: 9963 | C59: מור ניהול קרנות נאמנות בע"מ | D59: 514884485 | E59: ח.פ | F59: מור סל )00( תל בונד 60 | G59: IL0011953044 | H59: ISIN | I59: עוקב אחר מדדים אחרים בישראל | J59: ישראל | K59: ישראל | L59: TASE | M59: אג"ח בישראל - חברות והמרה | N59: לא | O59: ILS | P59: 2832 | Q59: 1 | R59: 5603.55 | T59: 158.693 | U59: 0.000472 | V59: 0.00081049209 | W59: 0.0001426281
A60: 337 | B60: 9963 | C60: קסם קרנות נאמנות בע"מ | D60: 510938608 | E60: ח.פ | F60: ממEURO STOXX 50 (4A) ETF.קסם | G60: IL0011459521 | H60: ISIN | I60: עוקב אחר מדדי מניות בחו"ל | J60: ישראל | K60: אירופה | L60: TASE | M60: מניות בחו"ל משולבת | N60: לא | O60: ILS | P60: 110633 | Q60: 1 | R60: 7493 | T60: 8289.731 | U60: 0.007945 | V60: 0.04233823 | W60: 0.0074505619
A61: 337 | B61: 9963 | C61: קסם קרנות נאמנות בע"מ | D61: 510938608 | E61: ח.פ | F61: קסם תל בונד שקלי | G61: IL0011464141 | H61: ISIN | I61: עוקב אחר מדדים אחרים בישראל | J61: ישראל | K61: ישראל | L61: TASE | M61: אג"ח בישראל - חברות והמרה | N61: לא | O61: ILS | P61: 73572 | Q61: 1 | R61: 4144.02 | T61: 3048.838 | U61: 0.001362 | V61: 0.015571365 | W61: 0.0027402047
... A69: 337 | B69: 9963 | C69: BlackRock Asset Managment | D69: 254900UWHMJRRODS3Z64 | E69: LEI | F69: MCHI_Ishares Msci Chaina Etf | G69: US46429B6719 | H69: ISIN | I69: עוקב אחר מדדי מניות בחו"ל | J69: חו"ל | K69: סין | L69: NASDAQ | M69: Equity Funds | N69: לא | O69: USD | P69: 20000 | Q69: 3.372 | R69: 5510 | T69: 3715.944 | U69: 0.000126 | V69: 0.018978481 | W69: 0.0033397793
A70: 337 | B70: 9963 | C70: Invesco investment management limited | D70: ECPGFXU8A2SHKVVGJI15 | E70: LEI | F70: Powershares QQQ NAS1 | G70: US46090E1038 | H70: ISIN | I70: עוקב אחר מדדי מניות בחו"ל | J70: חו"ל | K70: ארה"ב | L70: NASDAQ | M70: Equity Funds | N70: לא | O70: USD | P70: 7373 | Q70: 3.372 | R70: 55164 | S70: 2.005 | T70: 13721.499 | U70: 1.3e-05 | V70: 0.070079957 | W70: 0.012332472
A71: 337 | B71: 9963 | C71: Invesco investment management limited | D71: ECPGFXU8A2SHKVVGJI15 | E71: LEI | F71: SOURCE S&P 500 UCITS EFT | G71: IE00B3YCGJ38 | H71: ISIN | I71: עוקב אחר מדדי מניות בחו"ל | J71: חו"ל | K71: ארה"ב | L71: LSE | M71: Equity Funds | N71: לא | O71: USD | P71: 1809 | Q71: 3.372 | R71: 122758 | T71: 7488.174 | U71: 0.000356 | V71: 0.038244432 | W71: 0.0067301469
A72: 337 | B72: 9963 | C72: State Street Corp | D72: 07F5H7W3ET8ZLWNMFP29 | E72: LEI | F72: SPDR BLOOMBERG SASB U.S. HIGH | G72: IE0004TYCC17 | H72: ISIN | I72: עוקב אחר מדדים אחרים בחו"ל | J72: חו"ל | K72: ארה"ב | L72: NYSE | M72: Bond/Fixed Income Funds | N72: לא | O72: USD | P72: 323004 | Q72: 3.372 | R72: 1125.9 | T72: 12262.959 | U72: 0 | V72: 0.062630743 | W72: 0.011021581
A73: 337 | B73: 9963 | C73: State Street Corp | D73: 07F5H7W3ET8ZLWNMFP29 | E73: LEI | F73: SPDR S&P 500 ETF TRUST | G73: US78462F1030 | H73: ISIN | I73: עוקב אחר מדדי מניות בחו"ל | J73: חו"ל | K73: ארה"ב | L73: NYSE | M73: Equity Funds | N73: לא | O73: USD | P73: 3750 | Q73: 3.372 | R73: 61785 | S73: 4.619 | T73: 7828.288 | U73: 4e-06 | V73: 0.039981499 | W73: 0.007035831
A74: 337 | B74: 9963 | C74: Van Eck ETF | D74: 549300ZLFKNTXC51ZN76 | E74: LEI | F74: VANECK VECTORS SEMICONDUCTOR | G74: US92189F6768 | H74: ISIN | I74: עוקב אחר מדדי מניות בחו"ל | J74: חו"ל | K74: ארה"ב | L74: NASDAQ | M74: Equity Funds | N74: לא | O74: USD | P74: 2548 | Q74: 3.372 | R74: 27888 | T74: 2396.097 | U74: 0.000111 | V74: 0.012237611 | W74: 0.0021535401
A75: 337 | B75: 9963 | C75: Vanguard Group | D75: 549300Y88GQ3VLJIBX57 | E75: LEI | F75: VANGUARD S&P 500 | G75: us9229083632 | H75: ISIN | I75: עוקב אחר מדדי מניות בחו"ל | J75: חו"ל | K75: ארה"ב | L75: NYSE | M75: Equity Funds | N75: לא | O75: USD | P75: 823 | Q75: 3.372 | R75: 56803 | S75: 1.004 | T75: 1579.758 | U75: 1e-06 | V75: 0.0080683155 | W75: 0.0014198393
A76: 337 | B76: 9964 | C76: מגדל קרנות נאמנות בע"מ | D76: 511303661 | E76: ח.פ | F76: MTF סל (S&P 500 (4D | G76: IL0011503336 | H76: ISIN | I76: עוקב אחר מדדי מניות בחו"ל | J76: ישראל | K76: ארה"ב | L76: TASE | M76: מניות בחו"ל חשופות מט"ח | N76: לא | O76: ILS | P76: 466 | Q76: 1 | R76: 8961 | T76: 41.758 | U76: 5e-06 | V76: 0.0064407232 | W76: 0.0010754607
A77: 337 | B77: 9964 | C77: מגדל קרנות נאמנות בע"מ | D77: 511303661 | E77: ח.פ | F77: MTF סל )00( תל בונד - שקלי A | G77: IL0011728248 | H77: ISIN | I77: עוקב אחר מדדים אחרים בישראל | J77: ישראל | K77: ישראל | L77: TASE | M77: אג"ח בישראל - חברות והמרה | N77: לא | O77: ILS | P77: 30970 | Q77: 1 | R77: 433.1 | T77: 134.131 | U77: 0.000584 | V77: 0.020688149 | W77: 0.0034544708
A78: 337 | B78: 9964 | C78: מגדל קרנות נאמנות בע"מ | D78: 511303661 | E78: ח.פ | F78: MTF סל תלבונד 60 | G78: IL0011499964 | H78: ISIN | I78: עוקב אחר מדדים אחרים בישראל | J78: ישראל | K78: ישראל | L78: TASE | M78: אג"ח בישראל - חברות והמרה | N78: לא | O78: ILS | P78: 12861 | Q78: 1 | R78: 488.99 | T78: 62.889 | U78: 6.1e-05 | V78: 0.0096998934 | W78: 0.0016196712
A79: 337 | B79: 9964 | C79: מגדל קרנות נאמנות בע"מ | D79: 511303661 | E79: ח.פ | F79: MTF.תלבונדשקלי | G79: IL0011500027 | H79: ISIN | I79: עוקב אחר מדדים אחרים בישראל | J79: ישראל | K79: ישראל | L79: TASE | M79: אג"ח בישראל - חברות והמרה | N79: לא | O79: ILS | P79: 100000 | Q79: 1 | R79: 482.69 | T79: 482.69 | U79: 0.000406 | V79: 0.074449288 | W79: 0.012431411
A80: 337 | B80: 9964 | C80: מגדל קרנות נאמנות בע"מ | D80: 511303661 | E80: ח.פ | F80: MTF500SP ממ | G80: IL0011505729 | H80: ISIN | I80: עוקב אחר מדדי מניות בחו"ל | J80: ישראל | K80: ארה"ב | L80: TASE | M80: מניות בחו"ל משולבת | N80: לא | O80: ILS | P80: 5754 | Q80: 1 | R80: 7820 | T80: 449.963 | U80: 0.000236 | V80: 0.0694015 | W80: 0.011588541
A81: 337 | B81: 9964 | C81: מגדל קרנות נאמנות בע"מ | D81: 511303661 | E81: ח.פ | F81: MTF600STX ממ | G81: IL0011506149 | H81: ISIN | I81: עוקב אחר מדדי מניות בחו"ל | J81: ישראל | K81: אירופה | L81: TASE | M81: מניות בחו"ל משולבת | N81: לא | O81: ILS | P81: 1057 | Q81: 1 | R81: 8095 | T81: 85.564 | U81: 0.000259 | V81: 0.013197269 | W81: 0.0022036569
A82: 337 | B82: 9964 | C82: הראל קרנות נאמנות בע"מ | D82: 511776783 | E82: ח.פ | F82: הראל סל (4A) MSCI AC World מנ | G82: IL0011502007 | H82: ISIN | I82: עוקב אחר מדדי מניות בחו"ל | J82: ישראל | K82: גלובלי | L82: TASE | M82: מניות בחו"ל חשופות מט"ח | N82: לא | O82: ILS | P82: 46837 | Q82: 1 | R82: 864.7 | T82: 405 | U82: 9.3e-05 | V82: 0.062466442 | W82: 0.010430537
A83: 337 | B83: 9964 | C83: הראל קרנות נאמנות בע"מ | D83: 511776783 | E83: ח.פ | F83: הראל סל תא 90 | G83: IL0011489312 | H83: ISIN | I83: עוקב אחר מדדי מניות בישראל | J83: ישראל | K83: ישראל | L83: TASE | M83: מניות בישראל | N83: לא | O83: ILS | P83: 2513 | Q83: 1 | R83: 3032 | T83: 76.194 | U83: 1e-05 | V83: 0.011752058 | W83: 0.001962338
A84: 337 | B84: 9964 | C84: הראל קרנות נאמנות בע"מ | D84: 511776783 | E84: ח.פ | F84: הראל סל תל בונד שקלי | G84: IL0011505232 | H84: ISIN | I84: עוקב אחר מדדים אחרים בישראל | J84: ישראל | K84: ישראל | L84: TASE | M84: אג"ח בישראל - חברות והמרה | N84: לא | O84: ILS | P84: 62014 | Q84: 1 | R84: 415.44 | T84: 257.631 | U84: 0.000227 | V84: 0.039736563 | W84: 0.0066351416
A85: 337 | B85: 9964 | C85: הראל קרנות נאמנות בע"מ | D85: 511776783 | E85: ח.פ | F85: הראל קרן סל 4AׂSTOXX EUROPE 600ממ | G85: IL0011498891 | H85: ISIN | I85: עוקב אחר מדדי מניות בחו"ל | J85: ישראל | K85: אירופה | L85: TASE | M85: מניות בחו"ל משולבת | N85: לא | O85: ILS | P85: 7898 | Q85: 1 | R85: 699.4 | T85: 55.239 | U85: 3.3e-05 | V85: 0.0085199099 | W85: 0.0014226396
A86: 337 | B86: 9964 | C86: הראל קרנות נאמנות בע"מ | D86: 511776783 | E86: ח.פ | F86: הראל.DAX 30 ממ | G86: IL0011491607 | H86: ISIN | I86: עוקב אחר מדדי מניות בחו"ל | J86: ישראל | K86: גרמניה | L86: TASE | M86: מניות בחו"ל משולבת | N86: לא | O86: ILS | P86: 462 | Q86: 1 | R86: 20650 | T86: 95.403 | U86: 4e-05 | V86: 0.014714797 | W86: 0.002457051
A87: 337 | B87: 9964 | C87: קסם קרנות נאמנות בע"מ | D87: 510938608 | E87: ח.פ | F87: ממEURO STOXX 50 (4A) ETF.קסם | G87: IL0011459521 | H87: ISIN | I87: עוקב אחר מדדי מניות בחו"ל | J87: ישראל | K87: אירופה | L87: TASE | M87: מניות בחו"ל משולבת | N87: לא | O87: ILS | P87: 769 | Q87: 1 | R87: 7493 | T87: 57.621 | U87: 5.5e-05 | V87: 0.0088873916 | W87: 0.0014840011
... A95: 337 | B95: 9964 | C95: BlackRock Asset Managment | D95: 254900UWHMJRRODS3Z64 | E95: LEI | F95: MCHI_Ishares Msci Chaina Etf | G95: US46429B6719 | H95: ISIN | I95: עוקב אחר מדדי מניות בחו"ל | J95: חו"ל | K95: סין | L95: NASDAQ | M95: Equity Funds | N95: לא | O95: USD | P95: 360 | Q95: 3.372 | R95: 5510 | T95: 66.887 | U95: 2e-06 | V95: 0.010316536 | W95: 0.0017226371
A96: 337 | B96: 9964 | C96: Invesco investment management limited | D96: ECPGFXU8A2SHKVVGJI15 | E96: LEI | F96: Powershares QQQ NAS1 | G96: US46090E1038 | H96: ISIN | I96: עוקב אחר מדדי מניות בחו"ל | J96: חו"ל | K96: ארה"ב | L96: NASDAQ | M96: Equity Funds | N96: לא | O96: USD | P96: 306 | Q96: 3.372 | R96: 55164 | S96: 0.108 | T96: 569.564 | U96: 1e-06 | V96: 0.087848621 | W96: 0.014668809
A97: 337 | B97: 9964 | C97: Invesco investment management limited | D97: ECPGFXU8A2SHKVVGJI15 | E97: LEI | F97: SOURCE S&P 500 UCITS EFT | G97: IE00B3YCGJ38 | H97: ISIN | I97: עוקב אחר מדדי מניות בחו"ל | J97: חו"ל | K97: ארה"ב | L97: LSE | M97: Equity Funds | N97: לא | O97: USD | P97: 177 | Q97: 3.372 | R97: 122758 | T97: 732.674 | U97: 3.5e-05 | V97: 0.11300636 | W97: 0.018869604
A98: 337 | B98: 9964 | C98: State Street Corp | D98: 07F5H7W3ET8ZLWNMFP29 | E98: LEI | F98: SPDR BLOOMBERG SASB U.S. HIGH | G98: IE0004TYCC17 | H98: ISIN | I98: עוקב אחר מדדים אחרים בחו"ל | J98: חו"ל | K98: ארה"ב | L98: NYSE | M98: Bond/Fixed Income Funds | N98: לא | O98: USD | P98: 3009 | Q98: 3.372 | R98: 1125.9 | T98: 114.238 | U98: 0 | V98: 0.017619834 | W98: 0.002942129
A99: 337 | B99: 9964 | C99: Van Eck ETF | D99: 549300ZLFKNTXC51ZN76 | E99: LEI | F99: VANECK VECTORS SEMICONDUCTOR | G99: US92189F6768 | H99: ISIN | I99: עוקב אחר מדדי מניות בחו"ל | J99: חו"ל | K99: ארה"ב | L99: NASDAQ | M99: Equity Funds | N99: לא | O99: USD | P99: 79 | Q99: 3.372 | R99: 27888 | T99: 74.29 | U99: 3e-06 | V99: 0.011458408 | W99: 0.0019133048
A100: 337 | B100: 9964 | C100: Vanguard Group | D100: 549300Y88GQ3VLJIBX57 | E100: LEI | F100: VANGUARD S&P 500 | G100: us9229083632 | H100: ISIN | I100: עוקב אחר מדדי מניות בחו"ל | J100: חו"ל | K100: ארה"ב | L100: NYSE | M100: Equity Funds | N100: לא | O100: USD | P100: 313 | Q100: 3.372 | R100: 56803 | S100: 0.409 | T100: 600.899 | U100: 0 | V100: 0.092681667 | W100: 0.015475822
A101: 337 | B101: 15372 | C101: מגדל קרנות נאמנות בע"מ | D101: 511303661 | E101: ח.פ | F101: MTF סל (S&P 500 (4D | G101: IL0011503336 | H101: ISIN | I101: עוקב אחר מדדי מניות בחו"ל | J101: ישראל | K101: ארה"ב | L101: TASE | M101: מניות בחו"ל חשופות מט"ח | N101: לא | O101: ILS | P101: 8550 | Q101: 1 | R101: 8961 | T101: 766.165 | U101: 9.8e-05 | V101: 0.11626905 | W101: 0.11576697
A102: 337 | B102: 15372 | C102: אי.בי.אי קרנות נאמנות בע"מ | D102: 513765339 | E102: ח.פ | F102: אי.בי.אי. סל (4D)י S&P 500 | G102: IL0011481624 | H102: ISIN | I102: עוקב אחר מדדי מניות בחו"ל | J102: ישראל | K102: ארה"ב | L102: TASE | M102: מניות בחו"ל חשופות מט"ח | N102: לא | O102: ILS | P102: 3467 | Q102: 1 | R102: 20650 | T102: 715.936 | U102: 3.5e-05 | V102: 0.10864642 | W102: 0.10817726
A103: 337 | B103: 15372 | C103: הראל קרנות נאמנות בע"מ | D103: 511776783 | E103: ח.פ | F103: הראל סל SP500 | G103: IL0011490203 | H103: ISIN | I103: עוקב אחר מדדי מניות בחו"ל | J103: ישראל | K103: ארה"ב | L103: TASE | M103: מניות בחו"ל חשופות מט"ח | N103: לא | O103: ILS | P103: 29016 | Q103: 1 | R103: 2432 | T103: 705.669 | U103: 7.7e-05 | V103: 0.10708845 | W103: 0.10662602
A104: 337 | B104: 15372 | C104: מור ניהול קרנות נאמנות בע"מ | D104: 514884485 | E104: ח.פ | F104: מור סל )4D(י S&P 500 | G104: IL0011658106 | H104: ISIN | I104: עוקב אחר מדדי מניות בחו"ל | J104: ישראל | K104: ארה"ב | L104: TASE | M104: מניות בחו"ל חשופות מט"ח | N104: לא | O104: ILS | P104: 7300 | Q104: 1 | R104: 10390 | T104: 758.47 | U104: 0.000107 | V104: 0.11510122 | W104: 0.11460419
A105: 337 | B105: 15372 | C105: קסם קרנות נאמנות בע"מ | D105: 510938608 | E105: ח.פ | F105: קסם S&P 500 (4D) ETF | G105: IL0011464711 | H105: ISIN | I105: עוקב אחר מדדי מניות בחו"ל | J105: ישראל | K105: ארה"ב | L105: TASE | M105: מניות בחו"ל חשופות מט"ח | N105: לא | O105: ILS | P105: 3187 | Q105: 1 | R105: 22980 | T105: 732.373 | U105: 0.000109 | V105: 0.11114083 | W105: 0.11066089
A106: 337 | B106: 15372 | C106: BlackRock Asset Managment | D106: 254900UWHMJRRODS3Z64 | E106: LEI | F106: IVV US iShares S&P 500 Index F | G106: US4642872000 | H106: ISIN | I106: עוקב אחר מדדי מניות בחו"ל | J106: חו"ל | K106: ארה"ב | L106: NYSE | M106: Equity Funds | N106: לא | O106: USD | P106: 417 | Q106: 3.372 | R106: 62090 | T106: 873.062 | U106: 1e-06 | V106: 0.13249113 | W106: 0.13191901
A107: 337 | B107: 15372 | C107: Invesco investment management limited | D107: ECPGFXU8A2SHKVVGJI15 | E107: LEI | F107: SOURCE S&P 500 UCITS EFT | G107: IE00B3YCGJ38 | H107: ISIN | I107: עוקב אחר מדדי מניות בחו"ל | J107: חו"ל | K107: ארה"ב | L107: LSE | M107: Equity Funds | N107: לא | O107: USD | P107: 167 | Q107: 3.372 | R107: 122758 | T107: 691.28 | U107: 3.3e-05 | V107: 0.1049048 | W107: 0.1044518
A108: 337 | B108: 15372 | C108: State Street Corp | D108: 07F5H7W3ET8ZLWNMFP29 | E108: LEI | F108: SPDR S&P 500 ETF TRUST | G108: US78462F1030 | H108: ISIN | I108: עוקב אחר מדדי מניות בחו"ל | J108: חו"ל | K108: ארה"ב | L108: NYSE | M108: Equity Funds | N108: לא | O108: USD | P108: 245 | Q108: 3.372 | R108: 61785 | S108: 0.323 | T108: 511.521 | U108: 0 | V108: 0.077625577 | W108: 0.077290371
A109: 337 | B109: 15372 | C109: Vanguard Group | D109: 549300Y88GQ3VLJIBX57 | E109: LEI | F109: VANGUARD S&P 500 | G109: us9229083632 | H109: ISIN | I109: עוקב אחר מדדי מניות בחו"ל | J109: חו"ל | K109: ארה"ב | L109: NYSE | M109: Equity Funds | N109: לא | O109: USD | P109: 435 | Q109: 3.372 | R109: 56803 | S109: 0.569 | T109: 835.115 | U109: 1e-06 | V109: 0.12673251 | W109: 0.12618525

Sheet קרנות נאמנות
A1: מספר קופה/קרן/ח.פ. עבור חברת ביטוח | B1: מספר מסלול | C1: שם מנפיק | D1: מספר מנפיק | E1: סוג מספר מזהה מנפיק | F1: שם נייר ערך | G1: מספר נייר ערך | H1: סוג מספר נייר ערך | I1: מאפיין עיקרי | J1: ישראל/חו"ל | K1: מדינה לפי חשיפה כלכלית | L1: סטאטוס סחירות | M1: זירת מסחר | N1: סיווג הקרן | O1: בעל עניין/צד קשור | P1: מטבע פעילות | Q1: ערך נקוב (יחידות) | R1: שער חליפין | S1: שער נייר הערך | T1: שווי הוגן (באלפי ש"ח) | U1: שיעור מערך נקוב מונפק | V1: שיעור מנכסי אפיק ההשקעה | W1: שיעור מסך נכסי ההשקעה
A2: 337 | B2: 1477 | C2: Kotak | D2: 213800SJ3IH3EXMXSJ47 | E2: LEI | F2: KOTAK FDS-INDIA MIDCAP (S) USD A | G2: LU2126068639 | H2: ISIN | I2: מניות | J2: חו"ל | K2: הודו | L2: סחיר | M2: אחר | N2: Equity Funds | O2: לא | P2: USD | Q2: 2695.22 | R2: 3.372 | S2: 1512.41 | T2: 137.452 | U2: 0.000117 | V2: 1 | W2: 0.0079112163
A3: 337 | B3: 9962 | C3: Kotak | D3: 213800SJ3IH3EXMXSJ47 | E3: LEI | F3: KOTAK FDS-INDIA MIDCAP (S) USD A | G3: LU2126068639 | H3: ISIN | I3: מניות | J3: חו"ל | K3: הודו | L3: סחיר | M3: אחר | N3: Equity Funds | O3: לא | P3: USD | Q3: 4716.63 | R3: 3.372 | S3: 1512.41 | T3: 240.541 | U3: 0.000205 | V3: 1 | W3: 0.0056537701
A4: 337 | B4: 9963 | C4: אי בי אי ניהול קרנות נאמנות בע"מ | D4: 510791031 | E4: ח.פ | F4: איביאי טכנולגיית עילית | G4: IL0011425381 | H4: ISIN | I4: מניות | J4: ישראל | K4: ישראל | L4: סחיר | M4: TASE | N4: מניות בישראל | O4: לא | P4: ILS | Q4: 3697494.1 | R4: 1 | S4: 74.8 | T4: 2765.726 | U4: 0.011941 | V4: 0.35195994 | W4: 0.0024857514
A5: 337 | B5: 9963 | C5: Kotak | D5: 213800SJ3IH3EXMXSJ47 | E5: LEI | F5: KOTAK FDS-INDIA MIDCAP (S) USD A | G5: LU2126068639 | H5: ISIN | I5: מניות | J5: חו"ל | K5: הודו | L5: סחיר | M5: אחר | N5: Equity Funds | O5: לא | P5: USD | Q5: 99852.88 | R5: 3.372 | S5: 1512.41 | T5: 5092.344 | U5: 0.00435 | V5: 0.64804006 | W5: 0.0045768461
A6: 337 | B6: 9964 | C6: Kotak | D6: 213800SJ3IH3EXMXSJ47 | E6: LEI | F6: KOTAK FDS-INDIA MIDCAP (S) USD A | G6: LU2126068639 | H6: ISIN | I6: מניות | J6: חו"ל | K6: הודו | L6: סחיר | M6: אחר | N6: Equity Funds | O6: לא | P6: USD | Q6: 2493.08 | R6: 3.372 | S6: 1512.41 | T6: 127.143 | U6: 0.000109 | V6: 1 | W6: 0.0032745035

Sheet כתבי אופציה
A1: מספר קופה/קרן/ח.פ. עבור חברת ביטוח | B1: מספר מסלול | C1: שם מנפיק | D1: מספר מנפיק | E1: סוג מספר מזהה מנפיק | F1: שם נייר ערך | G1: מספר נייר ערך | H1: סוג מספר נייר ערך | I1: ישראל/חו"ל | J1: מדינה לפי חשיפה כלכלית | K1: סטאטוס סחירות | L1: זירת מסחר | M1: נכס בסיס (כתב אופציה) | N1: ענף מסחר | O1: תאריך פקיעה | P1: בעל עניין/צד קשור | Q1: מטבע פעילות | R1: שער מימוש | S1: יחס המרה | T1: ערך נקוב (יחידות) | U1: שער חליפין | V1: שער נייר הערך | W1: שווי הוגן (באלפי ש"ח) | X1: שיעור מנכסי אפיק ההשקעה | Y1: שיעור מסך נכסי ההשקעה
A2: 337 | B2: 1405 | C2: ביג מרכזי קניות (2004) בע"מ | D2: 513623314 | E2: ח.פ | F2: ביג אפ 7 | G2: IL0012143454 | H2: ISIN | I2: ישראל | J2: ישראל | K2: סחיר | L2: TASE | M2: IL0010972607 | N2: נדל"ן מניב בישראל | O2: 01/06/2026 | P2: לא | Q2: ILS | R2: 58000 | S2: 1 | T2: 34 | U2: 1 | V2: 9800 | W2: 3.332 | X2: 1 | Y2: 0.00036950821
A3: 337 | B3: 1477 | C3: אלומיי קפיטל בע"מ | D3: 520039868 | E3: ח.פ | F3: אלומיי אופ 2 | G3: IL0012030826 | H3: ISIN | I3: ישראל | J3: ישראל | K3: סחיר | L3: TASE | M3: IL0010826357 | N3: אנרגיה מתחדשת | O3: 05/01/2028 | P3: לא | Q3: ILS | R3: 8000 | S3: 0 | T3: 102 | U3: 1 | V3: 327.1 | W3: 0.334 | X3: 1 | Y3: 1.9203158e-05
A4: 337 | B4: 9962 | C4: אלומיי קפיטל בע"מ | D4: 520039868 | E4: ח.פ | F4: אלומיי אופ 2 | G4: IL0012030826 | H4: ISIN | I4: ישראל | J4: ישראל | K4: סחיר | L4: TASE | M4: IL0010826357 | N4: אנרגיה מתחדשת | O4: 05/01/2028 | P4: לא | Q4: ILS | R4: 8000 | S4: 0 | T4: 156 | U4: 1 | V4: 327.1 | W4: 0.51 | X4: 0.048568684 | Y4: 1.1993733e-05
A5: 337 | B5: 9962 | C5: ביג מרכזי קניות (2004) בע"מ | D5: 513623314 | E5: ח.פ | F5: ביג אפ 7 | G5: IL0012143454 | H5: ISIN | I5: ישראל | J5: ישראל | K5: סחיר | L5: TASE | M5: IL0010972607 | N5: נדל"ן מניב בישראל | O5: 01/06/2026 | P5: לא | Q5: ILS | R5: 58000 | S5: 1 | T5: 102 | U5: 1 | V5: 9800 | W5: 9.996 | X5: 0.95143132 | Y5: 0.00023495001
A6: 337 | B6: 9963 | C6: אלומיי קפיטל בע"מ | D6: 520039868 | E6: ח.פ | F6: אלומיי אופ 2 | G6: IL0012030826 | H6: ISIN | I6: ישראל | J6: ישראל | K6: סחיר | L6: TASE | M6: IL0010826357 | N6: אנרגיה מתחדשת | O6: 05/01/2028 | P6: לא | Q6: ILS | R6: 8000 | S6: 0 | T6: 5766 | U6: 1 | V6: 327.1 | W6: 18.861 | X6: 0.03899437 | Y6: 1.695133e-05
A7: 337 | B7: 9963 | C7: ביג מרכזי קניות (2004) בע"מ | D7: 513623314 | E7: ח.פ | F7: ביג אפ 7 | G7: IL0012143454 | H7: ISIN | I7: ישראל | J7: ישראל | K7: סחיר | L7: TASE | M7: IL0010972607 | N7: נדל"ן מניב בישראל | O7: 01/06/2026 | P7: לא | Q7: ILS | R7: 58000 | S7: 1 | T7: 4743 | U7: 1 | V7: 9800 | W7: 464.814 | X7: 0.96100563 | Y7: 0.00041776092
A8: 337 | B8: 9964 | C8: אלומיי קפיטל בע"מ | D8: 520039868 | E8: ח.פ | F8: אלומיי אופ 2 | G8: IL0012030826 | H8: ISIN | I8: ישראל | J8: ישראל | K8: סחיר | L8: TASE | M8: IL0010826357 | N8: אנרגיה מתחדשת | O8: 05/01/2028 | P8: לא | Q8: ILS | R8: 8000 | S8: 0 | T8: 204 | U8: 1 | V8: 327.1 | W8: 0.667 | X8: 0.06257772 | Y8: 1.7185527e-05
A9: 337 | B9: 9964 | C9: ביג מרכזי קניות (2004) בע"מ | D9: 513623314 | E9: ח.פ | F9: ביג אפ 7 | G9: IL0012143454 | H9: ISIN | I9: ישראל | J9: ישראל | K9: סחיר | L9: TASE | M9: IL0010972607 | N9: נדל"ן מניב בישראל | O9: 01/06/2026 | P9: לא | Q9: ILS | R9: 58000 | S9: 1 | T9: 102 | U9: 1 | V9: 9800 | W9: 9.996 | X9: 0.93742228 | Y9: 0.0002574414

Sheet אופציות
A1: מספר קופה/קרן/ח.פ. עבור חברת ביטוח | B1: מספר מסלול | C1: שם מנפיק | D1: מספר מנפיק | E1: סוג מספר מזהה מנפיק | F1: שם נייר ערך | G1: מספר נייר ערך | H1: סוג מספר נייר ערך | I1: מאפיין עיקרי | J1: ישראל/חו"ל | K1: מדינה לפי חשיפה כלכלית | L1: זירת מסחר | M1: ענף מסחר | N1: נכס בסיס | O1: תאריך פקיעה | P1: בעל עניין/צד קשור | Q1: מטבע פעילות | R1: שער מימוש | S1: ערך נקוב (יחידות) | T1: שער חליפין | U1: שער נייר הערך | V1: שווי הוגן (באלפי ש"ח) | W1: שיעור מנכסי אפיק ההשקעה | X1: שיעור מסך נכסי ההשקעה
A2: 337 | B2: 1405
A3: 337 | B3: 1477
A4: 337 | B4: 9962
A5: 337 | B5: 9963
A6: 337 | B6: 9964
A7: 337 | B7: 15372

Sheet חוזים עתידיים
A1: מספר קופה/קרן/ח.פ. עבור חברת ביטוח | B1: מספר מסלול | C1: שם מנפיק | D1: מספר מנפיק | E1: סוג מספר מזהה מנפיק | F1: שם נייר ערך | G1: מספר נייר ערך | H1: סוג מספר נייר ערך | I1: ישראל/חו"ל | J1: מדינה לפי חשיפה כלכלית | K1: זירת מסחר | L1: נכס בסיס | M1: בעל עניין/צד קשור | N1: מטבע פעילות | O1: ערך נקוב (יחידות) | P1: שער חליפין | Q1: שער נייר הערך | R1: שווי הוגן (באלפי ש"ח) | S1: שיעור מנכסי אפיק ההשקעה | T1: שיעור מסך נכסי ההשקעה
A2: 337 | B2: 1477 | C2: חוזים עתידיים בחול | D2: 10527 | E2: פנימי | F2: HWAU5_SP500 MIC EMIN FUTSEP25 | G2: HWAU5 | H2: אחר | I2: חו"ל | J2: ארה"ב | K2: CME | L2: מניות לרבות מדדי מניות | M2: לא | N2: USD | O2: 15 | P2: 3.372 | Q2: 6253.75 | R2: 56.06 | S2: 1 | T2: 0.0032265768
A3: 337 | B3: 9962 | C3: חוזים עתידיים בחול | D3: 10527 | E3: פנימי | F3: HWAU5_SP500 MIC EMIN FUTSEP25 | G3: HWAU5 | H3: אחר | I3: חו"ל | J3: ארה"ב | K3: CME | L3: מניות לרבות מדדי מניות | M3: לא | N3: USD | O3: 36 | P3: 3.372 | Q3: 6253.75 | R3: 134.543 | S3: 0.86448236 | T3: 0.0031623544
A4: 337 | B4: 9962 | C4: חוזים עתידיים בחול | D4: 10527 | E4: פנימי | F4: HWBU5_NASDAQ 100 MICRO EMIN SEP25 | G4: HWBU5 | H4: אחר | I4: חו"ל | J4: ארה"ב | K4: CME | L4: מניות לרבות מדדי מניות | M4: לא | N4: USD | O4: 2 | P4: 3.372 | Q4: 22893.25 | R4: 13.873 | S4: 0.089139007 | T4: 0.00032607852
A5: 337 | B5: 9962 | C5: חוזים עתידיים בחול | D5: 10527 | E5: פנימי | F5: US 10YR ULTRA FUT SEP 25 | G5: UXYU5 | H5: אחר | I5: חו"ל | J5: ארה"ב | K5: CBOE | L5: ריבית ואג"ח | M5: לא | N5: USD | O5: 1 | P5: 3.372 | Q5: 114.266 | R5: 7.218 | S5: 0.04637863 | T5: 0.00016965721
A6: 337 | B6: 9963 | C6: חוזים עתידיים בחול | D6: 10527 | E6: פנימי | F6: ESU5_MINI S&P 500 FUT 09/2025 | G6: ESU5 | H6: אחר | I6: חו"ל | J6: ארה"ב | K6: CME | L6: מניות לרבות מדדי מניות | M6: לא | N6: USD | O6: 87 | P6: 3.372 | Q6: 6253.75 | R6: 3252.673 | S6: 0.78271746 | T6: 0.0029234055
A7: 337 | B7: 9963 | C7: חוזים עתידיים בחול | D7: 10527 | E7: פנימי | F7: NQU5 _MINI NASDAQ 100 09/2025 | G7: NQU5 | H7: אחר | I7: חו"ל | J7: ארה"ב | K7: CME | L7: מניות לרבות מדדי מניות | M7: לא | N7: USD | O7: 10 | P7: 3.372 | Q7: 22893.25 | R7: 693.618 | S7: 0.16691095 | T7: 0.00062340296
A8: 337 | B8: 9963 | C8: חוזים עתידיים בחול | D8: 10527 | E8: פנימי | F8: US 10YR ULTRA FUT SEP 25 | G8: UXYU5 | H8: אחר | I8: חו"ל | J8: ארה"ב | K8: CBOE | L8: ריבית ואג"ח | M8: לא | N8: USD | O8: 29 | P8: 3.372 | Q8: 114.266 | R8: 209.325 | S8: 0.05037159 | T8: 0.00018813504
A9: 337 | B9: 9964 | C9: חוזים עתידיים בחול | D9: 10527 | E9: פנימי | F9: HWAU5_SP500 MIC EMIN FUTSEP25 | G9: HWAU5 | H9: אחר | I9: חו"ל | J9: ארה"ב | K9: CME | L9: מניות לרבות מדדי מניות | M9: לא | N9: USD | O9: 6 | P9: 3.372 | Q9: 6253.75 | R9: 22.424 | S9: 0.75649025 | T9: 0.00057751358
A10: 337 | B10: 9964 | C10: חוזים עתידיים בחול | D10: 10527 | E10: פנימי | F10: US 10YR ULTRA FUT SEP 25 | G10: UXYU5 | H10: אחר | I10: חו"ל | J10: ארה"ב | K10: CBOE | L10: ריבית ואג"ח | M10: לא | N10: USD | O10: 1 | P10: 3.372 | Q10: 114.266 | R10: 7.218 | S10: 0.24350975 | T10: 0.00018589822

Sheet מוצרים מובנים
A1: מספר קופה/קרן/ח.פ. עבור חברת ביטוח | B1: מספר מסלול | C1: שם מנפיק | D1: מספר מנפיק | E1: סוג מספר מזהה מנפיק | F1: שם נייר ערך | G1: מספר נייר ערך | H1: סוג מספר נייר ערך | I1: מאפיין עיקרי | J1: ישראל/חו"ל | K1: מדינה לפי חשיפה כלכלית | L1: סטאטוס סחירות | M1: זירת מסחר | N1: נכס בסיס | O1: בעל עניין/צד קשור | P1: מח"מ | Q1: שיעור ריבית | R1: תשואה לפדיון | S1: דירוג | T1: שם מדרג | U1: דירוג נייר הערך/המנפיק | V1: מטבע פעילות | W1: ערך נקוב (יחידות) | X1: שער חליפין | Y1: שער נייר הערך | Z1: שווי הוגן (באלפי ש"ח) | AA1: שיעור מנכסי אפיק ההשקעה | AB1: שיעור מסך נכסי ההשקעה
A2: 337 | B2: 1405
A3: 337 | B3: 1477
A4: 337 | B4: 9962
A5: 337 | B5: 9963
A6: 337 | B6: 9964
A7: 337 | B7: 15372

Sheet לא סחיר איגרות חוב ממשלתיות
A1: מספר קופה/קרן/ח.פ. עבור חברת ביטוח | B1: מספר מסלול | C1: שם מנפיק | D1: שם נייר ערך | E1: מספר נייר ערך | F1: סוג מספר נייר ערך | G1: מאפיין עיקרי | H1: ישראל/חו"ל | I1: מדינה לפי חשיפה כלכלית | J1: תאריך רכישה | K1: דירוג | L1: שם מדרג | M1: מטבע פעילות | N1: מח"מ | O1: מועד פדיון | P1: שיעור ריבית | Q1: תשואה לפדיון | R1: ערך נקוב (יחידות) | S1: שער חליפין | T1: שער נייר הערך | U1: שווי הוגן (באלפי ש"ח) | V1: עלות מופחתת (באלפי ש"ח) | W1: השיטה שיושמה בדוח הכספי | X1: שיעור מנכסי אפיק ההשקעה | Y1: שיעור מסך נכסי ההשקעה
A2: 337 | B2: 1405
A3: 337 | B3: 1477
A4: 337 | B4: 9962
A5: 337 | B5: 9963
A6: 337 | B6: 9964
A7: 337 | B7: 15372

Sheet לא סחיר איגרות חוב מיועדות
A1: מספר קופה/קרן/ח.פ. עבור חברת ביטוח | B1: מספר מסלול | C1: מאפיין עיקרי | D1: שם נייר ערך | E1: מספר נייר ערך | F1: תאריך רכישה | G1: מח"מ | H1: סוג הצמדה | I1: מועד פדיון | J1: שיעור ריבית | K1: תשואה לפדיון | L1: ערך נקוב (יחידות) | M1: שער נייר הערך | N1: שווי הוגן (באלפי ש"ח) | O1: עלות מופחתת (באלפי ש"ח) | P1: השיטה שיושמה בדוח הכספי | Q1: שיעור מנכסי אפיק ההשקעה | R1: שיעור מסך נכסי ההשקעה
A2: 337 | B2: 1405
A3: 337 | B3: 1477
A4: 337 | B4: 9962
A5: 337 | B5: 9963
A6: 337 | B6: 9964
A7: 337 | B7: 15372

Sheet אפיק השקעה מובטח תשואה
A1: מספר קרן | B1: מספר מסלול | C1: מאפיין עיקרי | D1: חודש הנפקת שכבה | E1: חודש הבדיקה | F1: שווי הנכסים באפיק (באלפי ש"ח) | G1: שיעור מסך נכסי ההשקעה

Sheet לא סחיר ניירות ערך מסחריים
A1: מספר קופה/קרן/ח.פ. עבור חברת ביטוח | B1: מספר מסלול | C1: שם מנפיק | D1: מספר מנפיק | E1: סוג מספר מזהה מנפיק | F1: שם נייר ערך | G1: מספר נייר ערך | H1: סוג מספר נייר ערך | I1: מאפיין עיקרי | J1: ישראל/חו"ל | K1: מדינה לפי חשיפה כלכלית | L1: ענף מסחר | M1: בעל עניין/צד קשור | N1: תאריך רכישה | O1: דירוג | P1: שם מדרג | Q1: דירוג נייר הערך/המנפיק | R1: מטבע פעילות | S1: מח"מ | T1: סוג הצמדה | U1: ריבית עוגן | V1: מועד פדיון | W1: שיעור ריבית | X1: תשואה לפדיון | Y1: נחיתות חוזית | Z1: האם סווג כחוב בעייתי | AA1: סוג גורם משערך | AB1: תלות/אי-תלות המשערך | AC1: שם גורם משערך | AD1: תאריך שערוך אחרון | AE1: תאריך אחרון בו נבחנה בפועל ירידת ערך | AF1: ערך נקוב (יחידות) | AG1: שער חליפין | AH1: שער נייר הערך | AI1: שווי הוגן (באלפי ש"ח) | AJ1: עלות מופחתת (באלפי ש"ח) | AK1: עלות מופחתת (במטבע הפעילות) | AL1: השיטה שיושמה בדוח הכספי | AM1: שיעור מנכסי אפיק ההשקעה | AN1: שיעור מסך נכסי ההשקעה
A2: 337 | B2: 1405
A3: 337 | B3: 1477
A4: 337 | B4: 9962
A5: 337 | B5: 9963
A6: 337 | B6: 9964
A7: 337 | B7: 15372

Sheet לא סחיר איגרות חוב
A1: מספר קופה/קרן/ח.פ. עבור חברת ביטוח | B1: מספר מסלול | C1: שם מנפיק | D1: מספר מנפיק | E1: סוג מספר מזהה מנפיק | F1: שם נייר ערך | G1: מספר נייר ערך | H1: סוג מספר נייר ערך | I1: מאפיין עיקרי | J1: ישראל/חו"ל | K1: מדינה לפי חשיפה כלכלית | L1: סטאטוס סחירות | M1: ענף מסחר | N1: בעל עניין/צד קשור | O1: תאריך רכישה | P1: דירוג | Q1: שם מדרג | R1: דירוג נייר הערך/המנפיק | S1: מטבע פעילות | T1: מח"מ | U1: מועד פדיון | V1: תשואה לפדיון | W1: שיעור ריבית | X1: נחיתות חוזית | Y1: האם סווג כחוב בעייתי | Z1: סוג גורם משערך | AA1: תלות/אי-תלות המשערך | AB1: תאריך שערוך אחרון | AC1: תאריך אחרון בו נבחנה בפועל ירידת ערך | AD1: ערך נקוב (יחידות) | AE1: שער חליפין | AF1: שער נייר הערך | AG1: שווי הוגן (באלפי ש"ח) | AH1: עלות מופחתת (באלפי ש"ח) | AI1: עלות מופחתת (במטבע הפעילות) | AJ1: השיטה שיושמה בדוח הכספי | AK1: שיעור מנכסי אפיק ההשקעה | AL1: שיעור מסך נכסי ההשקעה
A2: 337 | B2: 1405 | C2: י.ח.ק להשקעות שותפות מוגבלת | D2: 550016091 | E2: מספר שותפות | F2: י.ח.ק. אגח ב רמ | G2: IL0011817835 | H2: ISIN | I2: לא צמוד למדד המחירים לצרכן | J2: ישראל | K2: ישראל | L2: לא סחיר | M2: השקעה ואחזקות | N2: לא | O2: 19/11/2021 | P2: A+ | Q2: S&P מעלות | R2: נייר ערך | S2: ILS | T2: 1.91 | U2: 31/12/2028 | V2: 0.051 | W2: 0.0286 | X2: החוב לא נחות | Y2: לא | Z2: חברת ציטוט | AA2: אי-תלות | AB2: 30/06/2025 | AD2: 7428.58 | AE2: 1 | AF2: 97.29 | AG2: 7.227 | AJ2: שווי הוגן | AK2: 0.041593674 | AL2: 0.00080148078
A3: 337 | B3: 1405 | C3: כלל תעשיות בע"מ | D3: 520021874 | E3: ח.פ | F3: כלל תעש אגח טז-רמ | G3: IL0060802381 | H3: ISIN | I3: לא צמוד למדד המחירים לצרכן | J3: ישראל | K3: ישראל | L3: לא סחיר | M3: השקעה ואחזקות | N3: לא | O3: 27/10/2021 | P3: A | Q3: S&P | R3: נייר ערך | S3: ILS | T3: 1.72 | U3: 30/06/2027 | V3: 0.0521 | W3: 0.0447 | X3: החוב לא נחות | Y3: לא | Z3: חברת ציטוט | AA3: אי תלות | AB3: 30/06/2025 | AD3: 30377.74 | AE3: 1 | AF3: 98.87 | AG3: 30.034 | AJ3: שווי הוגן | AK3: 0.17285155 | AL3: 0.0033307275
A4: 337 | B4: 1405 | C4: לידר החזקות והשקעות בע"מ | D4: 520037664 | E4: ח.פ | F4: לידר אגח ח - רמ | G4: IL0031803617 | H4: ISIN | I4: לא צמוד למדד המחירים לצרכן | J4: ישראל | K4: ישראל | L4: אחר | M4: השקעה ואחזקות | N4: לא | O4: 01/03/2021 | P4: A1 | Q4: מידרוג Moodys | R4: נייר ערך | S4: ILS | T4: 1.59 | U4: 15/02/2028 | V4: 0.0475 | W4: 0.021 | X4: החוב לא נחות | Y4: לא | Z4: חברת ציטוט | AA4: אי תלות | AB4: 30/06/2025 | AD4: 22714.32 | AE4: 1 | AF4: 96.74 | AG4: 21.974 | AJ4: שווי הוגן | AK4: 0.12646172 | AL4: 0.0024368283
A5: 337 | B5: 1405 | C5: מת"ם - מרכז תעשיות מדע חיפה בע"מ | D5: 510687403 | E5: ח.פ | F5: מתם מרכז תעשיות מדע חיפה אגח א ר.מ | G5: IL0011389991 | H5: ISIN | I5: לא צמוד למדד המחירים לצרכן | J5: ישראל | K5: ישראל | L5: אחר | M5: נדל"ן מניב בישראל | N5: לא | O5: 04/03/2024 | P5: Aa2 | Q5: מידרוג Moodys | R5: נייר ערך | S5: ILS | T5: 1.46 | U5: 20/07/2040 | V5: 0.0463 | W5: 0.031 | X5: החוב לא נחות | Y5: לא | Z5: חברת ציטוט | AA5: אי תלות | AB5: 30/06/2025 | AD5: 7260.92 | AE5: 1 | AF5: 97.91 | AG5: 7.109 | AJ5: שווי הוגן | AK5: 0.040914004 | AL5: 0.00078838401
A6: 337 | B6: 1405 | C6: עוגן-אג"ח חברתית 2 בע"מ | D6: 516556545 | E6: ח.פ | F6: עוגן חברתית 2 אגחא-רמ | G6: IL0011968315 | H6: ISIN | I6: לא צמוד למדד המחירים לצרכן | J6: ישראל | K6: ישראל | L6: אחר | M6: שירותים פיננסיים | N6: לא | O6: 19/06/2023 | P6: Aa2 | Q6: מידרוג Moodys | R6: נייר ערך | S6: ILS | T6: 0.46 | U6: 15/03/2026 | V6: 0.052 | W6: 0.065 | X6: החוב לא נחות | Y6: לא | Z6: חברת ציטוט | AA6: אי-תלות | AB6: 30/06/2025 | AD6: 3778.25 | AE6: 1 | AF6: 100.81 | AG6: 3.809 | AJ6: שווי הוגן | AK6: 0.021920355 | AL6: 0.00042238979
A7: 337 | B7: 1405 | C7: רפאל-רשות לפיתוח אמצעי לחימה בע"מ | D7: 520042185 | E7: ח.פ | F7: רפאל אגח ג ר.מ. | G7: IL0011402760 | H7: ISIN | I7: צמוד למדד המחירים לצרכן | J7: ישראל | K7: ישראל | L7: אחר | M7: ביטחוניות | N7: לא | O7: 05/05/2021 | P7: AAA | Q7: S&P מעלות | R7: נייר ערך | S7: ILS | T7: 4.38 | U7: 15/09/2034 | V7: 0.0249 | W7: 0.023218 | X7: החוב לא נחות | Y7: לא | Z7: חברת ציטוט | AA7: אי תלות | AB7: 30/06/2025 | AD7: 27154.48 | AE7: 1 | AF7: 117.69 | AG7: 31.958 | AJ7: שווי הוגן | AK7: 0.18392227 | AL7: 0.0035440526
A8: 337 | B8: 1405 | C8: רפאל-רשות לפיתוח אמצעי לחימה בע"מ | D8: 520042185 | E8: ח.פ | F8: רפאל אגח סדרה ה 2020/2026 | G8: IL0011402927 | H8: ISIN | I8: לא צמוד למדד המחירים לצרכן | J8: ישראל | K8: ישראל | L8: לא סחיר | M8: ביטחוניות | N8: לא | O8: 05/05/2021 | P8: AAA | Q8: S&P מעלות | R8: נייר ערך | S8: ILS | T8: 0.7 | U8: 15/03/2026 | V8: 0.0472 | W8: 0.025 | X8: החוב לא נחות | Y8: לא | Z8: חברת ציטוט | AA8: אי תלות | AB8: 30/06/2025 | AD8: 15973.12 | AE8: 1 | AF8: 99.24 | AG8: 15.852 | AJ8: שווי הוגן | AK8: 0.091228343 | AL8: 0.0017579059
A9: 337 | B9: 1405 | C9: רפאל-רשות לפיתוח אמצעי לחימה בע"מ | D9: 520042185 | E9: ח.פ | F9: רפאל סד' ד 2020/2034 | G9: IL0011402844 | H9: ISIN | I9: לא צמוד למדד המחירים לצרכן | J9: ישראל | K9: ישראל | L9: לא סחיר | M9: ביטחוניות | N9: לא | O9: 05/05/2021 | P9: AAA | Q9: S&P מעלות | R9: נייר ערך | S9: ILS | T9: 4.13 | U9: 15/09/2034 | V9: 0.0465 | W9: 0.0374 | X9: החוב לא נחות | Y9: לא | Z9: חברת ציטוט | AA9: אי תלות | AB9: 30/06/2025 | AD9: 57167.36 | AE9: 1 | AF9: 97.6 | AG9: 55.795 | AJ9: שווי הוגן | AK9: 0.32110808 | AL9: 0.0061875263
A10: 337 | B10: 1477 | C10: י.ח.ק להשקעות שותפות מוגבלת | D10: 550016091 | E10: מספר שותפות | F10: י.ח.ק. אגח ב רמ | G10: IL0011817835 | H10: ISIN | I10: לא צמוד למדד המחירים לצרכן | J10: ישראל | K10: ישראל | L10: לא סחיר | M10: השקעה ואחזקות | N10: לא | O10: 19/11/2021 | P10: A+ | Q10: S&P מעלות | R10: נייר ערך | S10: ILS | T10: 1.91 | U10: 31/12/2028 | V10: 0.051 | W10: 0.0286 | X10: החוב לא נחות | Y10: לא | Z10: חברת ציטוט | AA10: אי-תלות | AB10: 30/06/2025 | AD10: 4571.42 | AE10: 1 | AF10: 97.29 | AG10: 4.448 | AJ10: שווי הוגן | AK10: 0.52880955 | AL10: 0.00025598308
A11: 337 | B11: 1477 | C11: רפאל-רשות לפיתוח אמצעי לחימה בע"מ | D11: 520042185 | E11: ח.פ | F11: רפאל אגח סדרה ה 2020/2026 | G11: IL0011402927 | H11: ISIN | I11: לא צמוד למדד המחירים לצרכן | J11: ישראל | K11: ישראל | L11: לא סחיר | M11: ביטחוניות | N11: לא | O11: 05/05/2021 | P11: AAA | Q11: S&P מעלות | R11: נייר ערך | S11: ILS | T11: 0.7 | U11: 15/03/2026 | V11: 0.0472 | W11: 0.025 | X11: החוב לא נחות | Y11: לא | Z11: חברת ציטוט | AA11: אי תלות | AB11: 30/06/2025 | AD11: 3993.28 | AE11: 1 | AF11: 99.24 | AG11: 3.963 | AJ11: שווי הוגן | AK11: 0.47119045 | AL11: 0.00022809116
A12: 337 | B12: 9962 | C12: י.ח.ק להשקעות שותפות מוגבלת | D12: 550016091 | E12: מספר שותפות | F12: י.ח.ק. אגח ב רמ | G12: IL0011817835 | H12: ISIN | I12: לא צמוד למדד המחירים לצרכן | J12: ישראל | K12: ישראל | L12: לא סחיר | M12: השקעה ואחזקות | N12: לא | O12: 19/11/2021 | P12: A+ | Q12: S&P מעלות | R12: נייר ערך | S12: ILS | T12: 1.91 | U12: 31/12/2028 | V12: 0.051 | W12: 0.0286 | X12: החוב לא נחות | Y12: לא | Z12: חברת ציטוט | AA12: אי-תלות | AB12: 30/06/2025 | AD12: 10857.15 | AE12: 1 | AF12: 97.29 | AG12: 10.563 | AJ12: שווי הוגן | AK12: 0.048521717 | AL12: 0.00024827516
A13: 337 | B13: 9962 | C13: כלל תעשיות בע"מ | D13: 520021874 | E13: ח.פ | F13: כלל תעש אגח טז-רמ | G13: IL0060802381 | H13: ISIN | I13: לא צמוד למדד המחירים לצרכן | J13: ישראל | K13: ישראל | L13: לא סחיר | M13: השקעה ואחזקות | N13: לא | O13: 27/10/2021 | P13: A | Q13: S&P | R13: נייר ערך | S13: ILS | T13: 1.72 | U13: 30/06/2027 | V13: 0.0521 | W13: 0.0447 | X13: החוב לא נחות | Y13: לא | Z13: חברת ציטוט | AA13: אי תלות | AB13: 30/06/2025 | AD13: 68383.89 | AE13: 1 | AF13: 98.87 | AG13: 67.611 | AJ13: שווי הוגן | AK13: 0.31057784 | AL13: 0.0015891598
... A40: 337 | B40: 9964 | C40: רפאל-רשות לפיתוח אמצעי לחימה בע"מ | D40: 520042185 | E40: ח.פ | F40: רפאל סד' ד 2020/2034 | G40: IL0011402844 | H40: ISIN | I40: לא צמוד למדד המחירים לצרכן | J40: ישראל | K40: ישראל | L40: לא סחיר | M40: ביטחוניות | N40: לא | O40: 05/05/2021 | P40: AAA | Q40: S&P מעלות | R40: נייר ערך | S40: ILS | T40: 4.13 | U40: 15/09/2034 | V40: 0.0465 | W40: 0.0374 | X40: החוב לא נחות | Y40: לא | Z40: חברת ציטוט | AA40: אי תלות | AB40: 30/06/2025 | AD40: 107188.76 | AE40: 1 | AF40: 97.6 | AG40: 104.616 | AJ40: שווי הוגן | AK40: 0.28658266 | AL40: 0.0026943326

Sheet לא סחיר מניות מבכ ויהש
A1: מספר קופה/קרן/ח.פ. עבור חברת ביטוח | B1: מספר מסלול | C1: שם מנפיק | D1: מספר מנפיק | E1: סוג מספר מזהה מנפיק | F1: שם נייר ערך | G1: מספר נייר ערך | H1: סוג מספר נייר ערך | I1: מאפיין עיקרי | J1: ישראל/חו"ל | K1: מדינה לפי חשיפה כלכלית | L1: סטאטוס סחירות | M1: ענף מסחר | N1: בעל עניין/צד קשור | O1: תאריך רכישה | P1: מטבע פעילות | Q1: סוג גורם משערך | R1: תלות/אי-תלות המשערך | S1: תאריך שערוך אחרון | T1: תאריך אחרון בו נבחנה בפועל ירידת ערך | U1: ערך נקוב (יחידות) | V1: שער חליפין | W1: שער נייר הערך | X1: שווי הוגן (באלפי ש"ח) | Y1: שיעור מנכסי אפיק ההשקעה | Z1: שיעור מסך נכסי ההשקעה
A2: 337 | B2: 1405 | C2: PROSPECT CAPITAL CORP | D2: 549300FSD8T39P5Q0O47 | E2: LEI | F2: מניות בכורה Prospect 5.5% 1025 | G2: US74348T5083 | H2: ISIN | I2: מניות לא סחירות | J2: חו"ל | K2: ארה"ב | L2: אחר | M2: שירותים פיננסיים | N2: לא | O2: 27/04/2021 | P2: USD | Q2: אחר | R2: אי תלות | S2: 45700 | U2: 570 | V2: 3.372 | W2: 2500 | X2: 48.051 | Y2: 1 | Z2: 0.0053287032
A3: 337 | B3: 1477 | C3: וויו (veev) גרופ | D3: 832652993 | E3: פנימי | F3: C וויו גרופ | G3: US9224741010 | H3: ISIN | I3: מניות לא סחירות | J3: ישראל | K3: ישראל | L3: אחר | M3: השקעות בהיי-טק | N3: לא | O3: 08/03/2021 | P3: ILS | Q3: אחר | R3: אי-תלות | S3: 45657 | U3: 9693 | V3: 1 | W3: 0 | X3: 0 | Y3: 9.5818504e-09 | Z3: 5.5789201e-12
A4: 337 | B4: 1477 | C4: PROSPECT CAPITAL CORP | D4: 549300FSD8T39P5Q0O47 | E4: LEI | F4: מניות בכורה Prospect 5.5% 1025 | G4: US74348T5083 | H4: ISIN | I4: מניות לא סחירות | J4: חו"ל | K4: ארה"ב | L4: אחר | M4: שירותים פיננסיים | N4: לא | O4: 27/04/2021 | P4: USD | Q4: אחר | R4: אי תלות | S4: 45700 | U4: 120 | V4: 3.372 | W4: 2500 | X4: 10.116 | Y4: 0.99999999 | Z4: 0.00058223828
A5: 337 | B5: 9962 | C5: וויו (veev) גרופ | D5: 832652993 | E5: פנימי | F5: C וויו גרופ | G5: US9224741010 | H5: ISIN | I5: מניות לא סחירות | J5: ישראל | K5: ישראל | L5: אחר | M5: השקעות בהיי-טק | N5: לא | O5: 08/03/2021 | P5: ILS | Q5: אחר | R5: אי-תלות | S5: 45657 | U5: 30695 | V5: 1 | W5: 0 | X5: 0 | Y5: 8.0914722e-09 | Z5: 7.2146765e-12
A6: 337 | B6: 9962 | C6: PROSPECT CAPITAL CORP | D6: 549300FSD8T39P5Q0O47 | E6: LEI | F6: מניות בכורה Prospect 5.5% 1025 | G6: US74348T5083 | H6: ISIN | I6: מניות לא סחירות | J6: חו"ל | K6: ארה"ב | L6: אחר | M6: שירותים פיננסיים | N6: לא | O6: 27/04/2021 | P6: USD | Q6: אחר | R6: אי תלות | S6: 45700 | U6: 450 | V6: 3.372 | W6: 2500 | X6: 37.935 | Y6: 0.99999999 | Z6: 0.00089163953
A7: 337 | B7: 9963 | C7: לוסיקס בע"מ | D7: 515374742 | E7: ח.פ | F7: Lusix | G7: 620201931 | H7: פנימי | I7: מניות לא סחירות | J7: ישראל | K7: ישראל | L7: אחר | M7: Utilities | N7: לא | O7: 02/12/2024 | P7: USD | Q7: דיווח מנהל הקרן | R7: אי תלות | S7: 28/11/2024 | U7: 237368 | V7: 3.372 | W7: 27.384 | X7: 219.183 | Y7: 0.015126297 | Z7: 0.00019699501
A8: 337 | B8: 9963 | C8: UVEYE LTD | D8: 514234202 | E8: ח.פ | F8: UVEYE LTD | G8: 62018263 | H8: פנימי | I8: מניות לא סחירות | J8: ישראל | K8: ישראל | L8: אחר | M8: השקעות בהייטק | N8: לא | O8: 01/04/2025 | P8: USD | Q8: דיווח מנהל הקרן | R8: אי תלות | S8: 45544 | U8: 167852 | V8: 3.372 | W8: 830.05 | X8: 4698.058 | Y8: 0.32422339 | Z8: 0.0042224736
A9: 337 | B9: 9963 | C9: אדאקום טכנולוגיות בע"מ | D9: 520036419 | E9: ח.פ | F9: אדאקום | G9: IL0002390123 | H9: ISIN | I9: מניות לא סחירות | J9: ישראל | K9: ישראל | L9: אחר | M9: ביוטכנולוגיה | N9: לא | O9: 15/12/2014 | P9: ILS | Q9: גורם תלוי/פנימי | R9: אי-תלות | S9: 45657 | U9: 20165 | V9: 1 | W9: 0 | X9: 0 | Y9: 1.3916314e-11 | Z9: 1.8123699e-13
A10: 337 | B10: 9963 | C10: ג'נריישן ניהול בע"מ | D10: 515785012 | E10: ח.פ | F10: ג'נריישן ניהול בע"מ | G10: 56093 | H10: פנימי | I10: מניות לא סחירות | J10: ישראל | K10: ישראל | L10: אחר | M10: נדל"ן מניב בישראל | N10: לא | O10: 16/08/2018 | P10: ILS | Q10: דיווח מנהל הקרן | R10: אי-תלות | S10: 30/06/2025 | U10: 396.62 | V10: 1 | W10: 159065.18 | X10: 630.884 | Y10: 0.043538726 | Z10: 0.00056701993
A11: 337 | B11: 9963 | C11: מניבים קרן הריט החדשה בע"מ | D11: 515327120 | E11: ח.פ | F11: מניבים ניהול הר | G11: 36475 | H11: פנימי | I11: מניות לא סחירות | J11: ישראל | K11: ישראל | L11: אחר | M11: נדל"ן מניב בישראל | N11: לא | O11: 03/11/2015 | P11: ILS | Q11: דיווח מנהל הקרן | R11: אי תלות | S11: 30/06/2025 | U11: 38 | V11: 1 | W11: 680012.79 | X11: 258.405 | Y11: 0.017833093 | Z11: 0.00023224656
A12: 337 | B12: 9963 | C12: וויו (veev) גרופ | D12: 832652993 | E12: פנימי | F12: C וויו גרופ | G12: US9224741010 | H12: ISIN | I12: מניות לא סחירות | J12: ישראל | K12: ישראל | L12: אחר | M12: השקעות בהיי-טק | N12: לא | O12: 08/03/2021 | P12: ILS | Q12: גורם תלוי/פנימי | R12: קיימת תלות | S12: 45657 | U12: 2116317 | V12: 1 | W12: 0 | X12: 0 | Y12: 1.4605173e-09 | Z12: 1.9020824e-11
A13: 337 | B13: 9963 | C13: Sunbit Inc | D13: 89324 | E13: פנימי | F13: SUNBIT | G13: 62018403 | H13: פנימי | I13: מניות לא סחירות | J13: חו"ל | K13: גלובלי | L13: אחר | M13: השקעה ואחזקות | N13: לא | O13: 03/06/2021 | P13: USD | Q13: דיווח מנהל הקרן | R13: אי-תלות | S13: 30/06/2025 | U13: 8941 | V13: 3.372 | W13: 5228.9 | X13: 1576.464 | Y13: 0.10879526 | Z13: 0.0014168785
A14: 337 | B14: 9963 | C14: Rapyd financial network 2016 ltd | D14: 28595 | E14: פנימי | F14: TARGET GLOBAL -FLUORINE (RAPYD | G14: 62018115 | H14: פנימי | I14: מניות לא סחירות | J14: חו"ל | K14: גרמניה | L14: אחר | M14: Technology Hardware, Storage & Peripherals | N14: לא | O14: 03/07/2022 | P14: USD | Q14: דיווח מנהל הקרן | R14: אי-תלות | S14: 24/06/2025 | U14: 301500 | V14: 3.372 | W14: 157.821 | X14: 1604.503 | Y14: 0.1107303 | Z14: 0.0014420792
A15: 337 | B15: 9963 | C15: wefox | D15: 28503 | E15: פנימי | F15: TARGET GLOBAL-NICKEL (WEFOX) | G15: 62018396 | H15: פנימי | I15: מניות לא סחירות | J15: חו"ל | K15: גרמניה | L15: אחר | M15: Technology Hardware, Storage & Peripherals | N15: לא | O15: 03/07/2022 | P15: EUR | Q15: דיווח מנהל הקרן | R15: אי תלות | S15: 24/06/2025 | U15: 502500 | V15: 3.9552 | W15: 99.907 | X15: 1985.648 | Y15: 0.13703395 | Z15: 0.0017846406
A16: 337 | B16: 9963 | C16: Verbit Inc | D16: 28460 | E16: פנימי | F16: Verbit Inc | G16: 620182700 | H16: פנימי | I16: מניות לא סחירות | J16: חו"ל | K16: גלובלי | L16: אחר | M16: Technology Hardware, Storage & Peripherals | N16: לא | O16: 20/03/2023 | P16: USD | Q16: דיווח מנהל הקרן | R16: אי תלות | S16: 45838 | U16: 65700 | V16: 3.372 | W16: 381.3 | X16: 844.734 | Y16: 0.058296937 | Z16: 0.00075922124
A17: 337 | B17: 9963 | C17: PROSPECT CAPITAL CORP | D17: 549300FSD8T39P5Q0O47 | E17: LEI | F17: מניות בכורה Prospect 5.5% 1025 | G17: US74348T5083 | H17: ISIN | I17: מניות לא סחירות | J17: חו"ל | K17: ארה"ב | L17: אחר | M17: שירותים פיננסיים | N17: לא | O17: 27/04/2021 | P17: USD | Q17: מומחה בלתי תלוי | R17: אי תלות | S17: 45700 | U17: 31700 | V17: 3.372 | W17: 2500 | X17: 2672.31 | Y17: 0.18442204 | Z17: 0.0024017923
A18: 337 | B18: 9964 | C18: וויו (veev) גרופ | D18: 832652993 | E18: פנימי | F18: C וויו גרופ | G18: US9224741010 | H18: ISIN | I18: מניות לא סחירות | J18: ישראל | K18: ישראל | L18: אחר | M18: השקעות בהיי-טק | N18: לא | O18: 08/03/2021 | P18: ILS | Q18: גורם תלוי/פנימי | R18: קיימת תלות | S18: 45657 | U18: 24232 | V18: 1 | W18: 0 | X18: 0 | Y18: 3.3817598e-09 | Z18: 6.2408163e-12
A19: 337 | B19: 9964 | C19: PROSPECT CAPITAL CORP | D19: 549300FSD8T39P5Q0O47 | E19: LEI | F19: מניות בכורה Prospect 5.5% 1025 | G19: US74348T5083 | H19: ISIN | I19: מניות לא סחירות | J19: חו"ל | K19: ארה"ב | L19: אחר | M19: שירותים פיננסיים | N19: לא | O19: 27/04/2021 | P19: USD | Q19: מומחה בלתי תלוי | R19: אי תלות | S19: 45700 | U19: 850 | V19: 3.372 | W19: 2500 | X19: 71.655 | Y19: 1 | Z19: 0.0018454345

Sheet קרנות השקעה
A1: מספר קופה/קרן/ח.פ. עבור חברת ביטוח | B1: מספר מסלול | C1: שם שותף כללי קרן השקעות | D1: מספר מזהה שותף כללי קרן השקעות | E1: סוג מספר מזהה שותף כללי קרן השקעות | F1: שם קרן השקעה | G1: מספר מזהה קרן השקעה | H1: סוג מספר מזהה קרן השקעות | I1: מאפיין עיקרי | J1: אסטרטגיית קרן ההשקעה | K1: ישראל/חו"ל | L1: מדינת התאגדות קרן השקעה | M1: מיקום משרד השותף הכללי | N1: מדינה לפי חשיפה כלכלית | O1: בעל עניין/צד קשור | P1: תאריך רכישה | Q1: מטבע פעילות | R1: סוג גורם משערך | S1: תלות/אי-תלות המשערך | T1: תאריך שערוך אחרון | U1: שער חליפין | V1: NAV (במטבע הדיווח של קרן ההשקעה) | W1: שווי הוגן (באלפי ש"ח) | X1: שיעור החזקה בקרן השקעה | Y1: שיעור מנכסי אפיק ההשקעה | Z1: שיעור מסך נכסי ההשקעה
A2: 337 | B2: 9962 | C2: Coller Credit Opportunities | D2: 89525 | E2: פנימי | F2: Coller Credit Opportunities | G2: 62019286 | H2: פנימי | I2: קרן חוב | J2: Other | K2: חו"ל | L2: ג'רנסי | M2: אירופה | N2: אירופה | O2: לא | P2: 02/09/2021 | Q2: USD | R2: דיווח מנהל הקרן | S2: אי-תלות | T2: 30/04/2025 | U2: 3.372 | V2: 16.315 | W2: 55.014 | X2: 0 | Y2: 1 | Z2: 0.0012930786
A3: 337 | B3: 9963 | C3: Forma european fund 2 | D3: 516190006 | E3: ח.פ | F3: Forma European Fund II LP | G3: 62018528 | H3: פנימי | I3: פרייבט אקוויטי | J3: Other | K3: ישראל | L3: ישראל | M3: ישראל | N3: אירופה | O3: לא | P3: 06/07/2021 | Q3: EUR | R3: דיווח מנהל הקרן | S3: אי-תלות | T3: 19/05/2025 | U3: 3.9552 | V3: 366.407 | W3: 1449.213 | X3: 0 | Y3: 0.0098062368 | Z3: 0.0013025094
A4: 337 | B4: 9963 | C4: Kedma Capital | D4: 540286333 | E4: ח.פ | F4: KEDMA CAPITAL PARTNERS III LTD | G4: 62018080 | H4: פנימי | I4: פרייבט אקוויטי | J4: Other | K4: ישראל | L4: ישראל | M4: ישראל | N4: ישראל | O4: לא | P4: 04/04/2021 | Q4: USD | R4: דיווח מנהל הקרן | S4: אי-תלות | T4: 31/03/2025 | U4: 3.372 | V4: 739.064 | W4: 2492.124 | X4: 0 | Y4: 0.016863191 | Z4: 0.0022398465
A5: 337 | B5: 9963 | C5: Klirmark Opportunity Fund | D5: CO-101523 | E5: מספר תאגיד או שותפות בחו"ל | F5: KLIRMARK FUND III | G5: 50000967 | H5: פנימי | I5: קרן חוב | J5: Other | K5: ישראל | L5: איי קיימן | M5: איי קיימן | N5: ישראל | O5: לא | P5: 13/11/2019 | Q5: ILS | R5: דיווח מנהל הקרן | S5: אי-תלות | T5: 30/06/2025 | U5: 1 | V5: 1039.5 | W5: 1039.5 | X5: 0 | Y5: 0.0070338743 | Z5: 0.0009342715
A6: 337 | B6: 9963 | C6: Klirmark Opportunity Fund | D6: CO-101523 | E6: מספר תאגיד או שותפות בחו"ל | F6: klirmark IV | G6: 50007947 | H6: פנימי | I6: קרן חוב | J6: Other | K6: ישראל | L6: איי קיימן | M6: איי קיימן | N6: ישראל | O6: לא | P6: 23/04/2023 | Q6: ILS | R6: דיווח מנהל הקרן | S6: אי-תלות | T6: 30/06/2025 | U6: 1 | V6: 2054.003 | W6: 2054.003 | X6: 0 | Y6: 0.013898605 | Z6: 0.0018460766
A7: 337 | B7: 9963 | C7: Peregrine Ventures Growth General Partner LP | D7: 540297413 | E7: פנימי | F7: Peregrine Ventures Growth General Partner LP | G7: 62018569 | H7: פנימי | I7: פרייבט אקוויטי | J7: Other | K7: ישראל | L7: ישראל | M7: ישראל | N7: גלובלי | O7: לא | P7: 07/07/2021 | Q7: USD | R7: דיווח מנהל הקרן | S7: אי-תלות | T7: 12/05/2025 | U7: 3.372 | V7: 329.342 | W7: 1110.541 | X7: 0 | Y7: 0.0075145799 | Z7: 0.00099812103
A8: 337 | B8: 9963 | C8: 0 | D8: 540310885 | E8: מספר שותפות | F8: Qumra Opportunity fund | G8: 62018254 | H8: פנימי | I8: פרייבט אקוויטי | J8: Growth Venture Capital | K8: חו"ל | L8: איי קיימן | M8: איי קיימן | N8: ישראל | O8: לא | P8: 11/05/2021 | Q8: USD | R8: דיווח מנהל הקרן | S8: אי-תלות | T8: 30/06/2025 | U8: 3.372 | V8: 338.818 | W8: 1142.493 | X8: 0 | Y8: 0.0077307888 | Z8: 0.0010268389
A9: 337 | B9: 9963 | C9: קרן השקעה אלפא ערך 1 | D9: 530225416 | E9: ח.פ | F9: אלפא ערך 1 ש.מ | G9: 50008341 | H9: פנימי | I9: קרן גידור (Hedge Fund) | J9: Other | K9: ישראל | L9: ישראל | M9: ישראל | N9: ישראל | O9: לא | P9: 26/12/2024 | Q9: ILS | R9: דיווח מנהל הקרן | S9: אי תלות | T9: 17/06/2025 | U9: 1 | V9: 2822.167 | W9: 2822.167 | X9: 0 | Y9: 0.019096461 | Z9: 0.0025364796
A10: 337 | B10: 9963 | C10: יסודות א נדלן שותפות מוגבלת | D10: 550257125 | E10: מספר שותפות | F10: יסודות נדל"ן ג' פיתוח ושותפות | G10: 50006691 | H10: פנימי | I10: קרן חוב | J10: Other | K10: ישראל | L10: ישראל | M10: ישראל | N10: ישראל | O10: לא | P10: 04/04/2021 | Q10: ILS | R10: דיווח מנהל הקרן | S10: אי-תלות | T10: 05/06/2025 | U10: 1 | V10: 3320.81 | W10: 3320.81 | X10: 0.001688 | Y10: 0.022470571 | Z10: 0.0029846444
A11: 337 | B11: 9963 | C11: קוגיטו קפיטל אל.אמ.אי שותף כללי, שותפות מוגבלת | D11: 550270912 | E11: פנימי | F11: קוגיטו קפיטל 2 | G11: 62020158 | H11: פנימי | I11: פרייבט אקוויטי | J11: Other | K11: ישראל | L11: ישראל | M11: ישראל | N11: ישראל | O11: לא | P11: 06/02/2022 | Q11: ILS | R11: דיווח מנהל הקרן | S11: אי-תלות | T11: 24/06/2025 | U11: 1 | V11: 2746.575 | W11: 2746.575 | X11: 0 | Y11: 0.01858496 | Z11: 0.0024685397
A12: 337 | B12: 9963 | C12: קרן ברוש 2234 | D12: 774636625 | E12: פנימי | F12: קרן ברוש | G12: 50005 | H12: פנימי | I12: קרן גידור (Hedge Fund) | J12: Other | K12: ישראל | L12: ישראל | M12: ישראל | N12: ישראל | O12: לא | P12: 29/05/2017 | Q12: ILS | R12: דיווח מנהל הקרן | S12: אי-תלות | T12: 17/06/2025 | U12: 1 | V12: 9808.628 | W12: 9808.628 | X12: 0 | Y12: 0.066371 | Z12: 0.0088157011
A13: 337 | B13: 9963 | C13: תשתיות ישראל ג'י. פי. 4 שותפות מוגבלת | D13: 550243026 | E13: ח.פ | F13: תשתיות ישראל 4 -ע' ת"א | G13: 62017520 | H13: פנימי | I13: פרייבט אקוויטי | J13: Other | K13: ישראל | L13: ישראל | M13: ישראל | N13: ישראל | O13: לא | P13: 13/10/2020 | Q13: USD | R13: דיווח מנהל הקרן | S13: אי-תלות | T13: 29/05/2025 | U13: 3.372 | V13: 883.976 | W13: 2980.767 | X13: 0 | Y13: 0.020169643 | Z13: 0.0026790246
... A58: 337 | B58: 9963 | C58: Gatewood Capital Opportunity Fund | D58: 13011 | E58: פנימי | F58: WOOD FUND - IBI | G58: 62000698 | H58: פנימי | I58: פרייבט אקוויטי | J58: Other | K58: חו"ל | L58: איי קיימן | M58: ארה"ב | N58: גלובלי | O58: לא | P58: 27/02/2017 | Q58: USD | R58: דיווח מנהל הקרן | S58: אי-תלות | T58: 29/05/2025 | U58: 3.372 | V58: 946.662 | W58: 3192.143 | X58: 0 | Y58: 0.021599937 | Z58: 0.0028690028
A59: 337 | B59: 9963 | C59: גרופ 11 קרן 5 | D59: 1992 | E59: פנימי | F59: גרופ 11 רצף מוסדיים משוערך בדולר | G59: 11811062 | H59: פנימי | I59: פרייבט אקוויטי | J59: Other | K59: חו"ל | L59: איי קיימן | N59: ארה"ב | O59: לא | P59: 31/03/2025 | Q59: USD | R59: דיווח מנהל הקרן | S59: אי-תלות | T59: 26/06/2025 | U59: 3.372 | V59: 523.943 | W59: 1766.737 | X59: 0.007299 | Y59: 0.011954791 | Z59: 0.0015878902
A60: 337 | B60: 9963 | C60: פונטיפקס 5 ג'י.פי ש.מ | D60: 232962336 | E60: פנימי | F60: פנתאון PGSF VI | G60: 62014261 | H60: פנימי | I60: פרייבט אקוויטי | J60: Other | K60: חו"ל | L60: לוכסמבורג | M60: בריטניה | N60: גלובלי | O60: לא | P60: 24/10/2019 | Q60: USD | R60: דיווח מנהל הקרן | S60: אי-תלות | T60: 30/06/2025 | U60: 3.372 | V60: 1428.731 | W60: 4817.682 | X60: 0 | Y60: 0.0325993 | Z60: 0.0043299888
A61: 337 | B61: 9963 | C61: א. רוטשילד ת ניהול נכסים בע"מ | D61: 513872440 | E61: ח.פ | F61: רוטשילד קרן נדלן | G61: 9840688 | H61: פנימי | I61: קרן נדל"ן | J61: Other | K61: חו"ל | L61: ישראל | M61: ישראל | N61: אירופה | O61: לא | P61: 15/12/2014 | Q61: EUR | R61: דיווח מנהל הקרן | S61: אי-תלות | T61: 19/05/2025 | U61: 3.9552 | V61: 53.862 | W61: 213.035 | X61: 0.0455 | Y61: 0.0014415209 | Z61: 0.00019146943
A62: 337 | B62: 9964 | C62: Coller Credit Opportunities | D62: 89525 | E62: פנימי | F62: Coller Credit Opportunities | G62: 62019286 | H62: פנימי | I62: קרן חוב | J62: Other | K62: חו"ל | L62: ג'רנסי | M62: אירופה | N62: אירופה | O62: לא | P62: 02/09/2021 | Q62: USD | R62: דיווח מנהל הקרן | S62: אי-תלות | T62: 30/04/2025 | U62: 3.372 | V62: 24.474 | W62: 82.525 | X62: 0 | Y62: 1 | Z62: 0.0021253897

Sheet לא סחיר כתבי אופציה
A1: מספר קופה/קרן/ח.פ. עבור חברת ביטוח | B1: מספר מסלול | C1: שם מנפיק | D1: מספר מנפיק | E1: סוג מספר מזהה מנפיק | F1: שם נייר ערך | G1: מספר נייר ערך | H1: סוג מספר נייר ערך | I1: ישראל/חו"ל | J1: מדינה לפי חשיפה כלכלית | K1: סטאטוס סחירות | L1: נכס בסיס (כתב אופציה) | M1: ענף מסחר | N1: תאריך פקיעה | O1: בעל עניין/צד קשור | P1: תאריך רכישה | Q1: מטבע פעילות | R1: סוג גורם משערך | S1: תלות/אי-תלות המשערך | T1: תאריך שערוך אחרון | U1: שער מימוש | V1: יחס המרה | W1: ערך נקוב (יחידות) | X1: שער נייר הערך | Y1: שער חליפין | Z1: שווי הוגן (באלפי ש"ח) | AA1: שיעור מנכסי אפיק ההשקעה | AB1: שיעור מסך נכסי ההשקעה
A2: 337 | B2: 1405
A3: 337 | B3: 1477
A4: 337 | B4: 9962
A5: 337 | B5: 9963
A6: 337 | B6: 9964
A7: 337 | B7: 15372

Sheet לא סחיר אופציות
A1: מספר קופה/קרן/ח.פ. עבור חברת ביטוח | B1: מספר מסלול | C1: שם מנפיק | D1: מספר מנפיק | E1: סוג מספר מזהה מנפיק | F1: שם נייר ערך | G1: מספר נייר ערך | H1: סוג מספר נייר ערך | I1: מאפיין עיקרי | J1: ישראל/חו"ל | K1: מדינה לפי חשיפה כלכלית | L1: ענף מסחר | M1: נכס בסיס | N1: תאריך פקיעה | O1: בעל עניין/צד קשור | P1: תאריך רכישה | Q1: מטבע פעילות | R1: סוג גורם משערך | S1: תלות/אי-תלות המשערך | T1: תאריך שערוך אחרון | U1: שער מימוש | V1: יחס המרה | W1: ערך נקוב (יחידות) | X1: שער נייר הערך | Y1: שער חליפין | Z1: שווי הוגן (בש"ח) | AA1: שיעור מנכסי אפיק ההשקעה | AB1: שיעור מסך נכסי ההשקעה
A2: 337 | B2: 1405
A3: 337 | B3: 1477
A4: 337 | B4: 9962
A5: 337 | B5: 9963
A6: 337 | B6: 9964
A7: 337 | B7: 15372

Sheet לא סחיר נגזרים אחרים
A1: מספר קופה/קרן/ח.פ. עבור חברת ביטוח | B1: מספר מסלול | C1: מאפיין עיקרי | D1: מספר עסקה (רגל 1) | E1: מטבע פעילות (רגל 1) | F1: שער חליפין | G1: ערך נקוב (רגל 1) | H1: שווי הוגן במטבע הנסחר (רגל 1) | I1: שיעור מנכסי אפיק ההשקעה (רגל 1) | J1: שיעור מסך נכסי ההשקעה (רגל 1) | K1: מספר עסקה (רגל 2) | L1: מטבע פעילות (רגל 2) | M1: שער חליפין | N1: ערך נקוב (רגל 2) | O1: שווי הוגן במטבע הנסחר (רגל 2) | P1: שיעור מנכסי ההשקעה (רגל 2) | Q1: שיעור מסך אפיק ההשקעה (רגל 2) | R1: שווי הוגן (נטו באלפי ש"ח) | S1: ישראל/חו"ל | T1: מדינה לפי חשיפה כלכלית | U1: סוג הנכס | V1: פקטור מוביל | W1: פקטור נוסף | X1: טיקר | Y1: בעל עניין/צד קשור | Z1: מועד ההתקשרות בעסקה | AA1: מועד סיום חוזי | AB1: תדירות Reset | AC1: סוג הסליקה | AD1: נספח התחשבנות בטחונות - CSA | AE1: גורם מצטט | AF1: ריבית עוגן | AG1: תקופת ריבית עוגן | AH1: שיעור ריבית עוגן | AI1: שער נכס הבסיס במועד ההתקשרות בעסקה | AJ1: שער הנגזר במועד ההתקשרות בעסקה | AK1: האם קיים קנס בגין יציאה מוקדמת | AL1: שיעור הקנס בגין יציאה מוקדמת | AM1: צד נגדי - Counterparty | AN1: שיעור מנכסי אפיק ההשקעה | AO1: שיעור מסך נכסי ההשקעה
A2: 337 | B2: 1405 | C2: Funded Forward | D2: 9941677 | E2: USD | F2: 3.372 | G2: -1000 | H2: -3.559 | I2: 5.72 | J2: 0.04 | K2: 9941677 | L2: ILS | M2: 1 | N2: 3576 | O2: 3.356 | P2: 5.58 | Q2: 0.04 | R2: 0.204 | S2: ישראל | T2: ישראל | U2: מט"ח | V2: מדינה/איזור גאוגרפי | W2: מט"ח/₪ | X2: USD ILS | Y2: לא | Z2: 45784 | AA2: 45876 | AB2: ללא | AC2: delivery | AD2: לא | AE2: הצד הנגדי | AF2: ללא | AG2: חודשי | AH2: ללא | AI2: 3.559 | AJ2: 3.356 | AK2: לא | AL2: NA | AM2: POALILIT | AN2: 2.8769775e-05 | AO2: 1.65301e-07
A3: 337 | B3: 1405 | C3: Funded Forward | D3: 9941678 | E3: EUR | F3: 3.9552 | G3: -14400 | H3: -58.629 | I3: 94.28 | J3: 0.66 | K3: 9941678 | L3: ILS | M3: 1 | N3: 58890.24 | O3: 56.824 | P3: 94.42 | Q3: 0.64 | R3: 1.805 | S3: ישראל | T3: ישראל | U3: מט"ח | V3: מדינה/איזור גאוגרפי | W3: מט"ח/₪ | X3: EUR ILS | Y3: לא | Z3: 45784 | AA3: 45876 | AB3: ללא | AC3: delivery | AD3: לא | AE3: הצד הנגדי | AF3: ללא | AG3: חודשי | AH3: ללא | AI3: 4.071 | AJ3: 3.946 | AK3: לא | AL3: NA | AM3: POALILIT | AN3: 0.0002545561 | AO3: 1.4625897e-06
A4: 337 | B4: 9963 | C4: Funded Forward | D4: 9941677 | E4: USD | F4: 3.372 | G4: -28744000 | H4: -102325.91 | I4: 80.25 | J4: 9.58 | K4: 9941677 | L4: ILS | M4: 1 | N4: 102788544 | O4: 96465.41 | P4: 79.81 | Q4: 9.03 | R4: 5860.51 | S4: ישראל | T4: ישראל | U4: מט"ח | V4: מדינה/איזור גאוגרפי | W4: מט"ח/₪ | X4: USD ILS | Y4: לא | Z4: 45784 | AA4: 45876 | AB4: ללא | AC4: delivery | AD4: לא | AE4: הצד הנגדי | AF4: ללא | AG4: חודשי | AH4: ללא | AI4: 3.559 | AJ4: 3.356 | AK4: לא | AL4: NA | AM4: POALILIT | AN4: 0.82649781 | AO4: 0.0047487656
A5: 337 | B5: 9963 | C5: Funded Forward | D5: 9941678 | E5: EUR | F5: 3.9552 | G5: -6185000 | H5: -25182.36 | I5: 19.75 | J5: 2.36 | K5: 9941678 | L5: ILS | M5: 1 | N5: 25294176 | O5: 24407.01 | P5: 20.19 | Q5: 2.29 | R5: 775.354 | S5: ישראל | T5: ישראל | U5: מט"ח | V5: מדינה/איזור גאוגרפי | W5: מט"ח/₪ | X5: EUR ILS | Y5: לא | Z5: 45784 | AA5: 45876 | AB5: ללא | AC5: delivery | AD5: לא | AE5: הצד הנגדי | AF5: ללא | AG5: חודשי | AH5: ללא | AI5: 4.071 | AJ5: 3.946 | AK5: לא | AL5: NA | AM5: POALILIT | AN5: 0.10934686 | AO5: 0.00062826859
A6: 337 | B6: 1477 | C6: Funded Forward | D6: 9941677 | E6: USD | F6: 3.372 | G6: -1094000 | H6: -3894.54 | I6: 98.986809 | J6: 22.86 | K6: 9941677 | L6: ILS | M6: 1 | N6: 3912144 | O6: 3671.48 | P6: 98.94 | Q6: 21.55 | R6: 223.052 | S6: ישראל | T6: ישראל | U6: מט"ח | V6: מדינה/איזור גאוגרפי | W6: מט"ח/₪ | X6: USD ILS | Y6: לא | Z6: 45784 | AA6: 45876 | AB6: ללא | AC6: delivery | AD6: לא | AE6: הצד הנגדי | AF6: ללא | AG6: חודשי | AH6: ללא | AI6: 3.559 | AJ6: 3.356 | AK6: לא | AL6: NA | AM6: POALILIT | AN6: 0.031456646 | AO6: 0.00018073882
A7: 337 | B7: 1477 | C7: Funded Forward | D7: 9941678 | E7: EUR | F7: 3.9552 | G7: -95000 | H7: -386.794 | I7: 9.8310722 | J7: 2.27 | K7: 9941678 | L7: ILS | M7: 1 | N7: 388512 | O7: 374.885 | P7: 10.1 | Q7: 2.2 | R7: 11.909 | S7: ישראל | T7: ישראל | U7: מט"ח | V7: מדינה/איזור גאוגרפי | W7: מט"ח/₪ | X7: EUR ILS | Y7: לא | Z7: 45784 | AA7: 45876 | AB7: ללא | AC7: delivery | AD7: לא | AE7: הצד הנגדי | AF7: ללא | AG7: חודשי | AH7: ללא | AI7: 4.071 | AJ7: 3.946 | AK7: לא | AL7: NA | AM7: POALILIT | AN7: 0.0016795061 | AO7: 9.6498511e-06
A8: 337 | B8: 1477 | C8: Funded Forward | D8: 9942531 | E8: USD | F8: 3.372 | G8: 100000 | H8: 346.931 | I8: -8.8178816 | J8: 2.04 | K8: 9942531 | L8: ILS | M8: 1 | N8: -348500 | O8: -335.603 | P8: -9.04 | Q8: 1.97 | R8: -11.329 | S8: ישראל | T8: ישראל | U8: מט"ח | V8: מדינה/איזור גאוגרפי | W8: מט"ח/₪ | X8: USD ILS | Y8: לא | Z8: 45818 | AA8: 45876 | AB8: ללא | AC8: delivery | AD8: לא | AE8: הצד הנגדי | AF8: ללא | AG8: חודשי | AH8: ללא | AI8: 3.469 | AJ8: 3.356 | AK8: לא | AL8: NA | AM8: POALILIT | AN8: -0.0015977097 | AO8: -9.1798777e-06
A9: 337 | B9: 9962 | C9: Funded Forward | D9: 9941677 | E9: USD | F9: 3.372 | G9: -637000 | H9: -2267.66 | I9: 85.3 | J9: 5.33 | K9: 9941677 | L9: ILS | M9: 1 | N9: 2277912 | O9: 2137.78 | P9: 84.95 | Q9: 5.02 | R9: 129.876 | S9: ישראל | T9: ישראל | U9: מט"ח | V9: מדינה/איזור גאוגרפי | W9: מט"ח/₪ | X9: USD ILS | Y9: לא | Z9: 45784 | AA9: 45876 | AB9: ללא | AC9: delivery | AD9: לא | AE9: הצד הנגדי | AF9: ללא | AG9: חודשי | AH9: ללא | AI9: 3.559 | AJ9: 3.356 | AK9: לא | AL9: NA | AM9: POALILIT | AN9: 0.018316193 | AO9: 0.0001052384
A10: 337 | B10: 9962 | C10: Funded Forward | D10: 9941678 | E10: EUR | F10: 3.9552 | G10: -96000 | H10: -390.866 | I10: 14.7 | J10: 0.92 | K10: 9941678 | L10: ILS | M10: 1 | N10: 392601.6 | O10: 378.831 | P10: 15.05 | Q10: 0.89 | R10: 12.035 | S10: ישראל | T10: ישראל | U10: מט"ח | V10: מדינה/איזור גאוגרפי | W10: מט"ח/₪ | X10: EUR ILS | Y10: לא | Z10: 45784 | AA10: 45876 | AB10: ללא | AC10: delivery | AD10: לא | AE10: הצד הנגדי | AF10: ללא | AG10: חודשי | AH10: ללא | AI10: 4.071 | AJ10: 3.946 | AK10: לא | AL10: NA | AM10: POALILIT | AN10: 0.0016972757 | AO10: 9.7519488e-06
A11: 337 | B11: 9964 | C11: Funded Forward | D11: 9941677 | E11: USD | F11: 3.372 | G11: -351000 | H11: -1249.53 | I11: 70.9 | J11: 3.23 | K11: 9941677 | L11: ILS | M11: 1 | N11: 1255176 | O11: 1177.96 | P11: 70.32 | Q11: 3.04 | R11: 71.564 | S11: ישראל | T11: ישראל | U11: מט"ח | V11: מדינה/איזור גאוגרפי | W11: מט"ח/₪ | X11: USD ILS | Y11: לא | Z11: 45784 | AA11: 45876 | AB11: ללא | AC11: delivery | AD11: לא | AE11: הצד הנגדי | AF11: ללא | AG11: חודשי | AH11: ללא | AI11: 3.559 | AJ11: 3.356 | AK11: לא | AL11: NA | AM11: POALILIT | AN11: 0.01009255 | AO11: 5.798824e-05
A12: 337 | B12: 9964 | C12: Funded Forward | D12: 9941678 | E12: EUR | F12: 3.9552 | G12: -126000 | H12: -513.011 | I12: 29.1 | J12: 1.32 | K12: 9941678 | L12: ILS | M12: 1 | N12: 515289.6 | O12: 497.216 | P12: 29.68 | Q12: 1.28 | R12: 15.795 | S12: ישראל | T12: ישראל | U12: מט"ח | V12: מדינה/איזור גאוגרפי | W12: מט"ח/₪ | X12: EUR ILS | Y12: לא | Z12: 45784 | AA12: 45876 | AB12: ללא | AC12: delivery | AD12: לא | AE12: הצד הנגדי | AF12: ללא | AG12: חודשי | AH12: ללא | AI12: 4.071 | AJ12: 3.946 | AK12: לא | AL12: NA | AM12: POALILIT | AN12: 0.0022275421 | AO12: 1.2798673e-05

Sheet הלוואות
A1: מספר קופה/קרן/ח.פ. עבור חברת ביטוח | B1: מספר מסלול | C1: מספר מזהה לווה | D1: סוג מספר מזהה לווה | E1: שם הלוואה | F1: מספר הלוואה | G1: מאפיין עיקרי | H1: מאפיין הלוואות מתואמות עבור זכויות מקרקעין | I1: ישראל/חו"ל | J1: מדינה לפי חשיפה כלכלית | K1: ענף מסחר | L1: בעל עניין/צד קשור | M1: קונסורציום/ סינדיקציה | N1: מספר קונסורציום/ סינדיקציה | O1: תאריך העמדת הלוואה | P1: דירוג | Q1: שם מדרג | R1: דירוג הלוואה/המנפיק | S1: מטבע פעילות | T1: מח"מ | U1: סוג הריבית | V1: שיעור ריבית | W1: סוג הצמדה | X1: ריבית עוגן | Y1: שיעור תוספת/הפחתה לריבית העוגן | Z1: תשואה לפדיון | AA1: מועד פדיון | AB1: נחיתות חוזית | AC1: סוג בטוחה | AD1: שווי הבטוחות העומדות כנגד ההלוואה | AE1: שיעור הבטוחות מהחוב | AF1: מועד עדכון אחרון לשווי הבטוחות | AG1: זכות חזרה | AH1: מבנה לוח סילוקין | AI1: יעוד הלוואה | AJ1: זכות פירעון מוקדם | AK1: סוג גורם משערך | AL1: שם גורם משערך | AM1: תלות/אי-תלות המשערך | AN1: תאריך שערוך אחרון | AO1: תאריך אחרון בו נבחנה בפועל ירידת ערך | AP1: שיעור ריבית בגין אי-ניצול מסגרת האשראי | AQ1: ערך נקוב | AR1: שער הלוואה | AS1: שער חליפין | AT1: שווי הוגן (באלפי ש"ח) | AU1: שווי הוגן (במטבע הפעילות) | AV1: עלות מופחתת (באלפי ש"ח) | AW1: עלות מופחתת (במטבע הפעילות) | AX1: האם סווג כחוב בעייתי | AY1: השיטה שיושמה בדוח הכספי | AZ1: שיעור מנכסי אפיק ההשקעה | BA1: שיעור מסך נכסי ההשקעה
A2: 337 | B2: 9963 | C2: 510960586 | D2: פנימי | E2: הלוואות לעמיתים | F2: 1000090 | G2: עמית/מבוטח | I2: ישראל | J2: ישראל | K2: שירותים פיננסיים | L2: לא | M2: לא | O2: 15/12/2014 | P2: AA+ | Q2: פנימי | R2: הלוואה | S2: ILS | T2: 2 | U2: קבועה | V2: 0.055 | W2: לא צמוד | X2: ריבית פריים | Y2: -0.005 | Z2: 0.0508 | AA2: 01/01/2100 | AB2: החוב לא נחות | AC2: חסכון עמיתים/מבוטחים | AE2: 0 | AG2: כן | AH2: שפיצר | AI2: לכל מטרה | AJ2: לא | AK2: חברת ציטוט | AL2: מרווח הוגן | AM2: אי-תלות | AN2: 30/06/2025 | AP2: 0 | AQ2: 42203733 | AR2: 100.097 | AS2: 1 | AT2: 42244.724 | AU2: 42244.724 | AX2: לא | AY2: שווי הוגן | AZ2: 1 | BA2: 0.037968294
A3: 337 | B3: 1405
A4: 337 | B4: 1477
A5: 337 | B5: 9962
A6: 337 | B6: 9964
A7: 337 | B7: 15372

Sheet לא סחיר מוצרים מובנים
A1: מספר קופה/קרן/ח.פ. עבור חברת ביטוח | B1: מספר מסלול | C1: שם מנפיק | D1: מספר מנפיק | E1: סוג מספר מזהה מנפיק | F1: שם נייר ערך | G1: מספר נייר ערך | H1: סוג מספר נייר ערך | I1: מאפיין עיקרי | J1: ישראל/חו"ל | K1: מדינה לפי חשיפה כלכלית | L1: בעל עניין/צד קשור | M1: נכס בסיס | N1: תאריך רכישה | O1: דירוג | P1: שם מדרג | Q1: דירוג נייר הערך/המנפיק | R1: מטבע פעילות | S1: מח"מ | T1: שיעור ריבית | U1: תשואה לפדיון | V1: סוג גורם משערך | W1: תלות/אי-תלות המשערך | X1: תאריך שערוך אחרון | Y1: ערך נקוב (יחידות) | Z1: שער חליפין | AA1: שער נייר הערך | AB1: שווי הוגן (באלפי ש"ח) | AC1: שיעור מנכסי אפיק ההשקעה | AD1: שיעור מסך נכסי ההשקעה
A2: 337 | B2: 1405
A3: 337 | B3: 1477
A4: 337 | B4: 9962
A5: 337 | B5: 9963
A6: 337 | B6: 9964
A7: 337 | B7: 15372

Sheet פיקדונות מעל 3 חודשים
A1: מספר קופה/קרן/ח.פ. עבור חברת ביטוח | B1: מספר מסלול | C1: שם הבנק | D1: מספר מזהה בנק | E1: סוג מספר מזהה בנק | F1: מאפיין עיקרי | G1: תאריך פקיעת פיקדון | H1: ישראל/חו"ל | I1: מדינה לפי חשיפה כלכלית | J1: בעל עניין/צד קשור | K1: דירוג הבנק | L1: שם מדרג | M1: מטבע פעילות | N1: מח"מ | O1: שיעור ריבית | P1: תשואה לפדיון | Q1: שווי מטבעי | R1: שער חליפין | S1: שער פיקדון | T1: שווי הוגן (באלפי ש"ח) | U1: שיעור מנכסי אפיק ההשקעה | V1: שיעור מסך נכסי ההשקעה
A2: 337 | B2: 1405
A3: 337 | B3: 1477
A4: 337 | B4: 9962
A5: 337 | B5: 9963
A6: 337 | B6: 9964
A7: 337 | B7: 15372

Sheet זכויות מקרקעין
A1: מספר קופה/קרן/ח.פ. עבור חברת ביטוח | B1: מספר מסלול | C1: שם הנכס | D1: מאפיין עיקרי | E1: מדינת מיקום נדל"ן | F1: בעל עניין/צד קשור | G1: תאריך רכישה | H1: שימוש עיקרי בנכס | I1: מחזור חיי הנכס | J1: כתובת הנכס | K1: שיעור תשואה בפועל במהלך הרבעון | L1: השיטה שבאמצעותה נקבע שווי הנכס | M1: סוג גורם משערך | N1: שם גורם משערך | O1: תלות/אי-תלות המשערך | P1: תאריך שערוך אחרון | Q1: מטבע פעילות | R1: שווי הוגן (במטבע הפעילות) | S1: שווי הוגן (באלפי ש"ח) | T1: עלות מופחתת (באלפי ש"ח) | U1: עלות מופחתת (במטבע הפעילות) | V1: השיטה שיושמה בדוח הכספי | W1: שיעור מנכסי אפיק ההשקעה | X1: שיעור מסך נכסי ההשקעה
A2: 337 | B2: 9963 | C2: זכויות בנכסי מקרקעין נדל"ן | D2: נדל"ן לא מניב | E2: ישראל | F2: לא | G2: 15/12/2014 | H2: משרדים | I2: אחר | J2: פומבדיתא 4 תל אביב | L2: אחר | M2: מומחה בלתי תלוי | N2: יצחק בן נוב, שמאי מקרקעין | O2: אי-תלות | P2: 46022 | Q2: ILS | R2: 5100 | S2: 5100 | V2: שווי הוגן | W2: 1 | X2: 0.0045837274
A3: 337 | B3: 1405
A4: 337 | B4: 1477
A5: 337 | B5: 9962
A6: 337 | B6: 9964
A7: 337 | B7: 15372

Sheet השקעה בחברות מוחזקות
A1: מספר קופה/קרן/ח.פ. עבור חברת ביטוח | B1: מספר מסלול | C1: שם מנפיק | D1: מספר מנפיק | E1: סוג מספר מזהה מנפיק | F1: שם נייר ערך | G1: מספר נייר ערך | H1: סוג מספר נייר ערך | I1: מאפיין עיקרי | J1: ישראל/חו"ל | K1: מדינה לפי חשיפה כלכלית | L1: ענף מסחר | M1: בעל עניין/צד קשור | N1: מטבע פעילות | O1: סוג גורם משערך | P1: תלות/אי-תלות המשערך | Q1: תאריך שערוך אחרון | R1: תאריך אחרון בו נבחנה בפועל ירידת ערך | S1: שיעור אחזקה באמצעי שליטה | T1: שווי מאזני (באלפי ש"ח) | U1: שווי הוגן (באלפי ש"ח) | V1: שיעור מנכסי אפיק ההשקעה | W1: שיעור מסך נכסי ההשקעה
A2: 337 | B2: 1405
A3: 337 | B3: 1477
A4: 337 | B4: 9962
A5: 337 | B5: 9963
A6: 337 | B6: 9964
A7: 337 | B7: 15372

Sheet נכסים אחרים
A1: מספר קופה/קרן/ח.פ. עבור חברת ביטוח | B1: מספר מסלול | C1: שם הנכס האחר | D1: מספר הנכס האחר | E1: מאפיין עיקרי | F1: ישראל/חו"ל | G1: מדינה לפי חשיפה כלכלית | H1: בעל עניין/צד קשור | I1: תאריך עסקה | J1: מטבע פעילות | K1: תאריך שערוך אחרון | L1: שווי מטבעי | M1: שער חליפין | N1: שווי הוגן (באלפי ש"ח) | O1: עלות מופחתת (באלפי ש"ח) | P1: השיטה שיושמה בדוח הכספי | Q1: שיעור מנכסי אפיק ההשקעה | R1: שיעור מסך נכסי ההשקעה
A2: 337 | B2: 1405 | C2: חוז שונים | D2: 27960000 | E2: חייבים וזכאים | F2: ישראל | G2: ישראל | H2: לא | I2: NA | J2: ILS | K2: 30/06/2025 | L2: -28.328 | M2: 1 | N2: -28.328 | P2: שווי הוגן | Q2: 0.015127468 | R2: -2.2954151e-05
A3: 337 | B3: 1405 | C3: זכאים מס עמיתים | D3: 28200000 | E3: חייבים וזכאים מס | F3: ישראל | G3: ישראל | H3: לא | I3: NA | J3: ILS | K3: 30/06/2025 | L3: -5.762 | M3: 1 | N3: -5.762 | P3: שווי הוגן | Q3: 0.0030769724 | R3: -4.668943e-06
A4: 999 | B4: 1477 | C4: חוז שונים | D4: 27960000 | E4: חייבים וזכאים | F4: ישראל | G4: ישראל | H4: לא | I4: NA | J4: ILS | K4: 30/06/2025 | L4: -48.583 | M4: 1 | N4: -48.583 | P4: שווי הוגן | Q4: 0.025943865 | R4: -3.9366758e-05
A5: 337 | B5: 9962 | C5: חוז שונים | D5: 27960000 | E5: חייבים וזכאים | F5: ישראל | G5: ישראל | H5: לא | I5: NA | J5: ILS | K5: 30/06/2025 | L5: -149.356 | M5: 1 | N5: -149.356 | P5: שווי הוגן | Q5: 0.079757773 | R5: -0.00012102302
A6: 337 | B6: 9962 | C6: זכאים מס עמיתים | D6: 28200000 | E6: חייבים וזכאים מס | F6: ישראל | G6: ישראל | H6: לא | I6: NA | J6: ILS | K6: 30/06/2025 | L6: -17.856 | M6: 1 | N6: -17.856 | P6: שווי הוגן | Q6: 0.0095353035 | R6: -1.4468699e-05
A7: 337 | B7: 9963 | C7: זכאים | D7: 28080000 | E7: חייבים וזכאים | F7: ישראל | G7: ישראל | H7: לא | I7: NA | J7: ILS | K7: 30/06/2025 | L7: -1457.715 | M7: 1 | N7: -1457.715 | P7: שווי הוגן | Q7: 0.77843609 | R7: -0.001181185
A8: 337 | B8: 9963 | C8: חוז שונים | D8: 27960000 | E8: חייבים וזכאים | F8: ישראל | G8: ישראל | H8: לא | I8: NA | J8: ILS | K8: 30/06/2025 | L8: 21.17 | M8: 1 | N8: 21.17 | P8: שווי הוגן | Q8: -0.011305017 | R8: 1.715403e-05
A9: 337 | B9: 9963 | C9: זכאים מס עמיתים | D9: 28200000 | E9: חייבים וזכאים מס | F9: ישראל | G9: ישראל | H9: לא | I9: NA | J9: ILS | K9: 30/06/2025 | L9: -67.582 | M9: 1 | N9: -67.582 | P9: שווי הוגן | Q9: 0.036089543 | R9: -5.4761629e-05
A10: 337 | B10: 9964 | C10: חוז שונים | D10: 27960000 | E10: חייבים וזכאים | F10: ישראל | G10: ישראל | H10: לא | I10: NA | J10: ILS | K10: 30/06/2025 | L10: -101.547 | M10: 1 | N10: -101.547 | P10: שווי הוגן | Q10: 0.054227232 | R10: -8.2283435e-05
A11: 337 | B11: 9964 | C11: זכאים מס עמיתים | D11: 28200000 | E11: חייבים וזכאים מס | F11: ישראל | G11: ישראל | H11: לא | I11: NA | J11: ILS | K11: 30/06/2025 | L11: -1.161 | M11: 1 | N11: -1.161 | P11: שווי הוגן | Q11: 0.00061998697 | R11: -9.4075717e-07
A12: 337 | B12: 15372 | C12: חוז שונים | D12: 27960000 | E12: חייבים וזכאים | F12: ישראל | G12: ישראל | H12: לא | I12: NA | J12: ILS | K12: 30/06/2025 | L12: -15.9 | M12: 1 | N12: -15.9 | P12: שווי הוגן | Q12: 0.0084907776 | R12: -1.2883755e-05

Sheet מסגרות אשראי
A1: מספר קופה/קרן/ח.פ. עבור חברת ביטוח | B1: מספר מסלול | C1: מספר מזהה לווה | D1: סוג מספר מזהה לווה | E1: שם הלוואה | F1: מספר הלוואה | G1: תאריך העמדת מסגרת אשראי | H1: ישראל/חו"ל | I1: מדינה לפי חשיפה כלכלית | J1: בעל עניין/צד קשור | K1: דירוג | L1: שם מדרג | M1: דירוג הלוואה/המנפיק | N1: מטבע פעילות | O1: שער חליפין | P1: שיעור ריבית | Q1: סוג הריבית | R1: סכום מסגרת האשראי הראשוני (במטבע הפעילות) | S1: סכום מסגרת האשראי הראשוני (באלפי ש"ח) | T1: שיעור יתרת מסגרת אשראי
A2: 337 | B2: 1405
A3: 337 | B3: 1477
A4: 337 | B4: 9962
A5: 337 | B5: 9963
A6: 337 | B6: 9964
A7: 337 | B7: 15372

Sheet יתרות התחייבות להשקעה
A1: מספר קופה/קרן/ח.פ. עבור חברת ביטוח | B1: מספר מסלול | C1: מאפיין עיקרי | D1: שם שותף כללי קרן השקעות | E1: מספר מזהה שותף כללי קרן השקעות | F1: סוג מספר מזהה שותף כללי קרן השקעות | G1: שם קרן השקעה | H1: מספר מזהה קרן השקעה | I1: סוג מספר מזהה קרן השקעות | J1: מטבע פעילות | K1: תאריך העמדת התחייבות לקרן השקעה | L1: סכום המחויבות הראשוני (במטבע הדיווח של קרן ההשקעה) | M1: סכום המחויבות הראשוני (באלפי ש"ח) | N1: יתרת המחויבות לתקופת הדיווח (במטבע הדיווח של קרן ההשקעה) | O1: יתרת המחויבות לתקופת הדיווח (באלפי ש"ח) | P1: שיעור יתרת המחויבות | Q1: תאריך פקיעת מחויבות להשקעה
A2: 337 | B2: 9963 | C2: קרן השקעה אחרת | D2: Gatewood Capital GP LLC | E2: 47-4190465 | F2: מספר תאגיד או שותפות בחו"ל | G2: [GATEWOOD FUND (IBI) | H2: 62000698 | I2: פנימי | J2: USD | K2: 42793 | L2: 1200000 | M2: 4046.4 | N2: 312537.39 | O2: 1053.8761 | P2: 0.26044782 | Q2: 46424
A3: 337 | B3: 9963 | C3: קרן נדל"ן | D3: Alto Fund III GP, LLC | E3: 81-4386819 | F3: מספר תאגיד או שותפות בחו"ל | G3: ALTO III | H3: 62000073 | I3: פנימי | J3: USD | K3: 42758 | L3: 1327000 | M3: 4474.644 | N3: 67000 | O3: 225.924 | P3: 0.050489827 | Q3: 46022
