Workbook
Name Additional_Factor: 'אפשרויות בחירה'!$C$701:$C$850
Name Amoritization: 'אפשרויות בחירה'!$C$546:$C$550
Name Capsule: 'אפשרויות בחירה'!$C$926:$C$928
Name Company_Name: 'File Name Info'!$A$34:$A$120
Name Company_Name_ID: 'File Name Info'!$A$34:$B$120
Name Consortium: 'אפשרויות בחירה'!$C$514:$C$515
Name Country_list: 'אפשרויות בחירה'!$C$4:$C$85
Name Country_list_funds: 'אפשרויות בחירה'!$C$4:$C$103
Name CSA: 'אפשרויות בחירה'!$C$688:$C$689
Name Delivery: 'אפשרויות בחירה'!$C$666:$C$667
Name Dependence_Independence: 'אפשרויות בחירה'!$C$654:$C$655
Name Duration_Underlying_Interest_Rate: 'אפשרויות בחירה'!$C$680:$C$687
Name File_Type: 'File Name Info'!$A$10:$A$12
Name Full_File_Type: 'File Name Info'!$A$11:$B$13
Name Full_Type: 'File Name Info'!$A$2:$B$8
Name Full_Type_Nostro: 'File Name Info'!$A$3:$B$6
Name Full_Year: 'File Name Info'!$A$22:$B$31
Name Fund_Strategy: 'אפשרויות בחירה'!$C$597:$C$621
Name Fund_type: 'אפשרויות בחירה'!$C$328:$C$498
Name Holding_interest: 'אפשרויות בחירה'!$C$146:$C$147
Name In_the_books: 'אפשרויות בחירה'!$C$656:$C$657
Name Industry_Sector: 'אפשרויות בחירה'!$C$1129:$C$1245
Name Industry_sector_all: 'אפשרויות בחירה'!$C$202:$C$327
Name Industry_sectors: 'אפשרויות בחירה'!$C$202:$C$327
Name israel_abroad: 'אפשרויות בחירה'!$C$2:$C$3
Name Issuer_Number_Banks: 'אפשרויות בחירה'!$C$111:$C$113
Name Issuer_Number_Fund: 'אפשרויות בחירה'!$C$114:$C$117
Name issuer_number_loan: 'אפשרויות בחירה'!$C$118:$C$126
Name Issuer_Number_Type: 'אפשרויות בחירה'!$C$104:$C$110
Name Issuer_Number_Type_2: 'אפשרויות בחירה'!$C$1076:$C$1079
Name Issuer_Number_Type_3: 'אפשרויות בחירה'!$C$1081:$C$1085
Name Issuer_Number_Type_V2: 'אפשרויות בחירה'!$C$104:$C$110
Name Issuer_Type_TFunds: 'אפשרויות בחירה'!$C$1087:$C$1089
Name Leading_factor: 'אפשרויות בחירה'!$C$692:$C$700
Name Linked_Type: 'אפשרויות בחירה'!$C$516:$C$519
Name other_investments: 'אפשרויות בחירה'!$C$1000:$C$1033
Name Penalty: 'אפשרויות בחירה'!$C$851:$C$852
Name QTR: 'File Name Info'!$A$15:$A$19
Name Rating_Agency: 'אפשרויות בחירה'!$C$188:$C$201
Name real_estate_lifestage: 'אפשרויות בחירה'!$C$634:$C$642
Name real_estate_loans: 'אפשרויות בחירה'!$C$553:$C$591
Name Real_Estate_Main_Use: 'אפשרויות בחירה'!$C$622:$C$633
Name Recourse_Nonrecourse: 'אפשרויות בחירה'!$C$544:$C$545
Name Repayment_Rights: 'אפשרויות בחירה'!$C$551:$C$552
Name Reset_frequency: 'אפשרויות בחירה'!$C$658:$C$665
Name Security_ID_Number_Type: 'אפשרויות בחירה'!$C$1113:$C$1116
Name Security_Number_Loans: 'אפשרויות בחירה'!$C$131
Name Stock_Exchange: 'אפשרויות בחירה'!$C$1283:$C$1315
Name Stock_Exchange_Gov_Bonds: 'אפשרויות בחירה'!$C$148:$C$181
Name Subordination_Risk: 'אפשרויות בחירה'!$C$186:$C$187
Name Tradeable_Status: 'אפשרויות בחירה'!$C$1272:$C$1281
Name Tradeable_Status_All: 'אפשרויות בחירה'!$C$135:$C$145
Name tradeable_status_bonds: 'אפשרויות בחירה'!$C$1248:$C$1253
Name tradeable_status_funds: 'אפשרויות בחירה'!$C$1118:$C$1119
Name tradeable_status_stock: 'אפשרויות בחירה'!$C$1255:$C$1259
Name Tradeable_Status_v2: 'אפשרויות בחירה'!$C$1121:$C$1126
Name tradeable_status_warrants: 'אפשרויות בחירה'!$C$1261:$C$1265
Name tradeable_status_warrants_v2: 'אפשרויות בחירה'!$C$1267:$C$1269
Name Transaction: 'אפשרויות בחירה'!$C$643:$C$646
Name Type: 'File Name Info'!$A$2:$A$8

Sheet עמוד פתיחה
A1: קובץ דיווח עבור רשימת נכסים ברמת הנכס הבודד (חוזר גופים מוסדיים 2015-9-14)
A3: יש לבחור תחום: | D3: נכסי עמיתים - קופות גמל
A5: האם מדובר בקובץ לממומנה או לציבור:
A7: יש לבחור את רבעון הדיווח:
A9: יש לבחור את שנת הדיווח:
A11: יש לבחור את הגוף המוסדי:
A13: ח.פ. הגוף המוסדי: | D13: =IFERROR(VLOOKUP(D11,'File Name Info'!A35:B121,2,0),"תא מחושב") -> תא מחושב
A15: שם קובץ לשמירה | D15: =IF(D5="לממונה",CONCATENATE(D13, "_",VLOOKUP(D3,Full_Type,2,0),"_",D7,VLOOKUP(D9,Full_Year,2,0),".xlxs"),IF(D5="לציבור",CONCATENATE(D13,"_",VLOOKUP(D3,Full_Type_Nostro,2,0),"_",VLOOKUP(D5,Full_File_Type,2,0),"_",D7,VLOOKUP(D9,Full_Year,2,0),".xlsx"),"שם קובץ לשמירה")) -> שם קובץ לשמירה
A17: פרטי האחראי על הדיווח בגוף המוסדי | B17: שם:
B19: מספר טלפון:
B21: כתובת מייל:
A23: הוראות למילוי הדיווח: | D23: יש לדווח לפי ההנחיות בחלק ג' לנספח 5.4.3.2 שבפרק 3 שבחלק 4 לשער 5 בחוזר המאוחד - "רשימת נכסים ברמת הנכס הבודד".

Sheet סכום נכסים
C1: ידווח בקבצי נכסי הנוסטרו בלבד
B2: שווי הוגן | C2: עלות מופחתת | D2: השיטה שיושמה בדוח הכספי | E2: שיעור מסך נכסי השקעה
A3: מזומנים ושווי מזומנים | B3: =SUM('מזומנים ושווי מזומנים'!O:O) -> 56141.256 | D3: =B3+C3 -> 56141.256 | E3: =SUM('מזומנים ושווי מזומנים'!O:O)/B30 -> 0.018831201
A4: איגרות חוב ממשלתיות | B4: =SUM('איגרות חוב ממשלתיות'!U:U) -> 377040.49 | D4: =B4+C4 -> 377040.49 | E4: =SUM('איגרות חוב ממשלתיות'!U:U)/B30 -> 0.12646894
A5: ניירות ערך מסחריים | B5: =SUM('ניירות ערך מסחריים'!AD:AD) -> 0 | D5: =B5+C5 -> 0 | E5: =SUM('ניירות ערך מסחריים'!AD:AD)/B30 -> 0
A6: איגרות חוב | B6: =SUM('איגרות חוב'!AD:AD) -> 184393.96 | D6: =B6+C6 -> 184393.96 | E6: =SUM('איגרות חוב'!AD:AD)/B30 -> 0.061850412
A7: מניות, מניות בכורה ויחידות השתתפות | B7: =SUM('מניות מבכ ויהש'!U:U) -> 353483.04 | D7: =B7+C7 -> 353483.04 | E7: =SUM('מניות מבכ ויהש'!U:U)/B30 -> 0.11856718
A8: קרנות סל | B8: =SUM('קרנות סל'!T:T) -> 717037.29 | D8: =B8+C8 -> 717037.29 | E8: =SUM('קרנות סל'!T:T)/B30 -> 0.24051249
A9: קרנות נאמנות | B9: =SUM('קרנות נאמנות'!T:T) -> 121588.34 | D9: =B9+C9 -> 121588.34 | E9: =SUM('קרנות נאמנות'!T:T)/B30 -> 0.040783813
A10: כתבי אופציה | B10: =SUM('כתבי אופציה'!W:W) -> 36.54 | D10: =B10+C10 -> 36.54 | E10: =SUM('כתבי אופציה'!W:W)/B30 -> 1.2256443e-05
A11: אופציות | B11: =SUM(אופציות!V:V) -> 0 | D11: =B11+C11 -> 0 | E11: =SUM(אופציות!V:V)/B30 -> 0
A12: חוזים עתידיים | B12: =SUM('חוזים עתידיים'!R:R) -> 6828.044 | D12: =B12+C12 -> 6828.044 | E12: =SUM('חוזים עתידיים'!R:R)/B30 -> 0.0022902991
A13: מוצרים מובנים | B13: =SUM('מוצרים מובנים'!Z:Z) -> 0 | D13: =B13+C13 -> 0 | E13: =SUM('מוצרים מובנים'!Z:Z)/B30 -> 0
A14: לא סחיר איגרות חוב ממשלתיות | B14: =SUM('לא סחיר איגרות חוב ממשלתיות'!U:U) -> 0 | D14: =B14+C14 -> 0 | E14: =SUM('לא סחיר איגרות חוב ממשלתיות'!U:U)/B30 -> 0
A15: לא סחיר איגרות חוב מיועדות | B15: =SUM('לא סחיר איגרות חוב מיועדות'!N:N) -> 0 | D15: =B15+C15 -> 0 | E15: =SUM('לא סחיר איגרות חוב מיועדות'!N:N)/B30 -> 0
A16: אפיק השקעה מובטח תשואה | B16: =SUM('אפיק השקעה מובטח תשואה'!F:F) -> 0 | D16: =B16+C16 -> 0 | E16: =SUM('אפיק השקעה מובטח תשואה'!F:F)/B30 -> 0
A17: לא סחיר ניירות ערך מסחריים | B17: =SUM('לא סחיר ניירות ערך מסחריים'!AI:AI) -> 0 | D17: =B17+C17 -> 0 | E17: =SUM('לא סחיר ניירות ערך מסחריים'!AI:AI)/B30 -> 0
A18: לא סחיר איגרות חוב | B18: =SUM('לא סחיר איגרות חוב'!AG:AG) -> 8513.34 | D18: =B18+C18 -> 8513.34 | E18: =SUM('לא סחיר איגרות חוב'!AG:AG)/B30 -> 0.0028555901
A19: לא סחיר מניות, מניות בכורה ויחידות השתתפות | B19: =SUM('לא סחיר מניות מבכ ויהש'!X:X) -> 88966.841 | D19: =B19+C19 -> 88966.841 | E19: =SUM('לא סחיר מניות מבכ ויהש'!X:X)/B30 -> 0.029841735
A20: קרנות השקעה | B20: =SUM('קרנות השקעה'!W:W) -> 523732.14 | D20: =B20+C20 -> 523732.14 | E20: =SUM('קרנות השקעה'!W:W)/B30 -> 0.17567304
A21: לא סחיר כתבי אופציה | B21: =SUM('לא סחיר כתבי אופציה'!Z:Z) -> 0.268 | D21: =B21+C21 -> 0.268 | E21: =SUM('לא סחיר כתבי אופציה'!Z:Z)/B30 -> 8.9893997e-08
A22: לא סחיר אופציות | B22: =SUM('לא סחיר אופציות'!Z:Z) -> 0 | D22: =B22+C22 -> 0 | E22: =SUM('לא סחיר אופציות'!Z:Z)/B30 -> 0
A23: לא סחיר נגזרים אחרים | B23: =SUM('לא סחיר נגזרים אחרים'!R:R) -> -285.985 | D23: =B23+C23 -> -285.985 | E23: =SUM('לא סחיר נגזרים אחרים'!R:R)/B30 -> -9.5926622e-05
A24: הלוואות | B24: =SUM(הלוואות!AT:AT) -> 65265.22 | D24: =B24+C24 -> 65265.22 | E24: =SUM(הלוואות!AT:AT)/B30 -> 0.02189161
A25: לא סחיר מוצרים מובנים | B25: =SUM('לא סחיר מוצרים מובנים'!AB:AB) -> 0 | D25: =B25+C25 -> 0 | E25: =SUM('לא סחיר מוצרים מובנים'!AB:AB)/B30 -> 0
A26: פיקדונות מעל 3 חודשים | B26: =SUM('פיקדונות מעל 3 חודשים'!T:T) -> 58489.992 | D26: =B26+C26 -> 58489.992 | E26: =SUM('פיקדונות מעל 3 חודשים'!T:T)/B30 -> 0.019619027
A27: זכויות מקרקעין | B27: =SUM('זכויות מקרקעין'!S:S) -> 419529.71 | D27: =B27+C27 -> 419529.71 | E27: =SUM('זכויות מקרקעין'!S:S)/$B$30 -> 0.14072091
A28: השקעה בחברות מוחזקות | B28: =SUM('השקעה בחברות מוחזקות'!U:U) -> 0 | D28: =B28+C28 -> 0 | E28: =SUM('השקעה בחברות מוחזקות'!U:U)/B30 -> 0
A29: נכסים אחרים | B29: =SUM('נכסים אחרים'!N:N) -> 528.687 | D29: =B29+C29 -> 528.687 | E29: =SUM('נכסים אחרים'!N:N)/B30 -> 0.00017733503
A30: סך הכל נכסים | B30: =IF(SUM(B3:B29)=0,0.0001,SUM(B3:B29)) -> 2981289.2 | C30: =SUM(C3:C29) -> 0 | D30: =SUM(D3:D29) -> 2981289.2 | E30: =SUM(E3:E29) -> 1
A31: מסגרות אשראי
A32: יתרות התחייבויות להשקעה | B32: =SUM('יתרות התחייבות להשקעה'!O:O) -> 210392.99

Sheet מזומנים ושווי מזומנים
A1: מספר קופה/קרן/ח.פ. עבור חברת ביטוח | B1: מספר מסלול | C1: שם הבנק | D1: מספר מזהה בנק | E1: סוג מספר מזהה בנק | F1: מאפיין עיקרי | G1: ישראל/חו"ל | H1: בעל עניין/צד קשור | I1: דירוג הבנק | J1: שם מדרג | K1: מטבע פעילות | L1: שווי מטבעי | M1: שער חליפין | N1: שיעור ריבית | O1: שווי הוגן (באלפי ש"ח) | P1: שיעור מנכסי אפיק ההשקעה | Q1: שיעור מסך נכסי ההשקעה
A2: 1182 | B2: 1182 | C2: בנק לאומי לישראל בע"מ | D2: 10-800 | E2: סימול בנק | F2: מזומן ועו"ש בש"ח | G2: ישראל | H2: לא | I2: AAA | J2: S&P מעלות | K2: ILS | L2: 0 | M2: 1 | N2: 0.0403 | O2: 341.663 | P2: 0.023583541 | Q2: 0.00089948588
A3: 1182 | B3: 1182 | C3: בנק לאומי לישראל בע"מ | D3: 10-800 | E3: סימול בנק | F3: מזומן ועו"ש בש"ח | G3: ישראל | H3: לא | I3: AAA | J3: S&P מעלות | K3: ILS | L3: 0 | M3: 1 | N3: 0.0403 | O3: 1993.559 | P3: 0.13760698 | Q3: 0.0052483863
A4: 1182 | B4: 1182 | C4: בנק לאומי לישראל בע"מ | D4: 10-800 | E4: סימול בנק | F4: מזומן ועו"ש בש"ח | G4: ישראל | H4: לא | I4: AAA | J4: S&P מעלות | K4: ILS | L4: 0 | M4: 1 | N4: 0.0403 | O4: 0.01 | P4: 6.9025798e-07 | Q4: 2.6326722e-08
A5: 1182 | B5: 1182 | C5: גמול פועלים סהר | D5: 33-414 | E5: סימול בנק | F5: מזומן ועו"ש נקוב במט"ח | G5: חו"ל | H5: לא | I5: AAA | J5: S&P מעלות | K5: USD | L5: 47.03 | M5: 3.681 | N5: 0.0384 | O5: 173.117 | P5: 0.01194951 | Q5: 0.00045575921
A6: 1182 | B6: 1182 | C6: גמול פועלים סהר | D6: 33-414 | E6: סימול בנק | F6: מזומן ועו"ש נקוב במט"ח | G6: חו"ל | H6: לא | I6: AAA | J6: S&P מעלות | K6: CAD | L6: 849.473 | M6: 2.712 | N6: 0 | O6: 2303.941 | P6: 0.15903135 | Q6: 0.0060655207
A7: 1182 | B7: 1182 | C7: גמול פועלים סהר | D7: 33-414 | E7: סימול בנק | F7: מזומן ועו"ש נקוב במט"ח | G7: חו"ל | H7: לא | I7: AAA | J7: S&P מעלות | K7: JPY | L7: 2544.117 | M7: 2.433 | N7: 0 | O7: 61.909 | P7: 0.0042732873 | Q7: 0.00016298492
A8: 1182 | B8: 1182 | C8: גמול פועלים סהר | D8: 33-414 | E8: סימול בנק | F8: מזומן ועו"ש נקוב במט"ח | G8: חו"ל | H8: לא | I8: AAA | J8: S&P מעלות | K8: GBP | L8: 6.71 | M8: 4.654 | N8: 0 | O8: 31.223 | P8: 0.0021552043 | Q8: 8.2200371e-05
A9: 1182 | B9: 1182 | C9: גמול פועלים סהר | D9: 33-414 | E9: סימול בנק | F9: מזומן ועו"ש בש"ח | G9: ישראל | H9: לא | I9: AAA | J9: S&P מעלות | K9: ILS | L9: 0 | M9: 1 | N9: 0.0403 | O9: 9581.917 | P9: 0.66139944 | Q9: 0.025226045
A10: 1182 | B10: 14769 | C10: בנק לאומי לישראל בע"מ | D10: 10-800 | E10: סימול בנק | F10: מזומן ועו"ש בש"ח | G10: ישראל | H10: לא | I10: AAA | J10: S&P מעלות | K10: ILS | L10: 0 | M10: 1 | N10: 0.0403 | O10: 96.614 | P10: 0.13536992 | Q10: 0.01238455
A11: 1182 | B11: 14769 | C11: גמול פועלים סהר | D11: 33-414 | E11: סימול בנק | F11: מזומן ועו"ש נקוב במט"ח | G11: חו"ל | H11: לא | I11: AAA | J11: S&P מעלות | K11: USD | L11: 34.435 | M11: 3.681 | N11: 0.0384 | O11: 126.756 | P11: 0.17760182 | Q11: 0.016248208
A12: 1182 | B12: 14769 | C12: גמול פועלים סהר | D12: 33-414 | E12: סימול בנק | F12: מזומן ועו"ש נקוב במט"ח | G12: חו"ל | H12: לא | I12: AAA | J12: S&P מעלות | K12: CAD | L12: -0.9 | M12: 2.712 | N12: 0 | O12: -2.44 | P12: -0.0034188546 | Q12: -0.00031277979
A13: 1182 | B13: 14769 | C13: גמול פועלים סהר | D13: 33-414 | E13: סימול בנק | F13: מזומן ועו"ש נקוב במט"ח | G13: חו"ל | H13: לא | I13: AAA | J13: S&P מעלות | K13: EUR | L13: 2.322 | M13: 3.979 | N13: 0 | O13: 9.239 | P13: 0.012945538 | Q13: 0.0011843448
... A65: 969 | B65: 969 | C65: גמול פועלים סהר | D65: 33-414 | E65: סימול בנק | F65: מזומן ועו"ש בש"ח | G65: ישראל | H65: לא | I65: AAA | J65: S&P מעלות | K65: ILS | L65: 0 | M65: 1 | N65: 0.0403 | O65: 710.241 | P65: 0.31332323 | Q65: 0.0096700746

Sheet איגרות חוב ממשלתיות
A1: מספר קופה/קרן/ח.פ. עבור חברת ביטוח | B1: מספר מסלול | C1: שם מנפיק | D1: שם נייר ערך | E1: מספר נייר ערך | F1: מאפיין עיקרי | G1: ישראל/חו"ל | H1: מדינה לפי חשיפה כלכלית | I1: זירת מסחר | J1: דירוג | K1: שם מדרג | L1: מטבע פעילות | M1: מח"מ | N1: מועד פדיון | O1: שיעור ריבית | P1: תשואה לפדיון | Q1: סכום לקבל (במטבע הפעילות) | R1: ערך נקוב (יחידות) | S1: שער חליפין | T1: שער נייר הערך | U1: שווי הוגן (באלפי ש"ח) | V1: עלות מופחתת (באלפי ש"ח) | W1: השיטה שיושמה בדוח הכספי | X1: שיעור מערך נקוב מונפק | Y1: שיעור מנכסי אפיק ההשקעה | Z1: שיעור מסך נכסי ההשקעה
A2: 1182 | B2: 1182 | C2: בנק ישראל- מק"מ | D2: מ.ק.מ. 414 | E2: IL0082404182 | F2: מק"מ קצר משנים עשר חודשים | G2: ישראל | H2: ישראל | I2: TASE | J2: RF | K2: פנימי | L2: ILS | M2: 0.005 | N2: 03/04/2024 | O2: 0 | P2: 0.05629 | R2: 3718013 | S2: 1 | T2: 99.97 | U2: 3716.898 | W2: שווי הוגן | X2: 0.000186 | Y2: 0.059153818 | Z2: 0.0097853728
A3: 1182 | B3: 1182 | C3: בנק ישראל- מק"מ | D3: מלווה קצר מועד 1014 | E3: IL0082410106 | F3: מק"מ קצר משנים עשר חודשים | G3: ישראל | H3: ישראל | I3: TASE | J3: RF | K3: פנימי | L3: ILS | M3: 0.504 | N3: 02/10/2024 | O3: 0 | P3: 0.04258 | R3: 307125 | S3: 1 | T3: 97.93 | U3: 300.768 | W3: שווי הוגן | X3: 0 | Y3: 0.0047866658 | Z3: 0.00079182225
A4: 1182 | B4: 1182 | C4: בנק ישראל- מק"מ | D4: מלווה קצר מועד 1214 | E4: IL0082412185 | F4: מק"מ קצר משנים עשר חודשים | G4: ישראל | H4: ישראל | I4: TASE | J4: RF | K4: פנימי | L4: ILS | M4: 0.677 | N4: 04/12/2024 | O4: 0 | P4: 0.04238 | R4: 5000000 | S4: 1 | T4: 97.22 | U4: 4861 | W4: שווי הוגן | X4: 0.000357 | Y4: 0.077362021 | Z4: 0.012797419
A5: 1182 | B5: 1182 | C5: גליל | D5: ממשל צמודה 0527 | E5: IL0011408478 | F5: צמוד למדד המחירים לצרכן בריבית קבועה | G5: ישראל | H5: ישראל | I5: TASE | J5: RF | K5: פנימי | L5: ILS | M5: 3.119 | N5: 31/05/2027 | O5: 0.0075 | P5: 0.01152 | R5: 1171463 | S5: 1 | T5: 111.88 | U5: 1310.633 | W5: שווי הוגן | X5: 5.6e-05 | Y5: 0.020858507 | Z5: 0.0034504665
A6: 1182 | B6: 1182 | C6: גליל | D6: ממשל צמודה 0545 | E6: IL0011348658 | F6: צמוד למדד המחירים לצרכן בריבית קבועה | G6: ישראל | H6: ישראל | I6: TASE | J6: RF | K6: פנימי | L6: ILS | M6: 18.8 | N6: 31/05/2045 | O6: 0.01 | P6: 0.01853 | R6: 1670758 | S6: 1 | T6: 96.44 | U6: 1611.279 | W6: שווי הוגן | X6: 9.2e-05 | Y6: 0.025643242 | Z6: 0.0042419694
A7: 1182 | B7: 1182 | C7: גליל | D7: ממשל צמודה 1025 | E7: IL0011359127 | F7: צמוד למדד המחירים לצרכן בריבית קבועה | G7: ישראל | H7: ישראל | I7: TASE | J7: RF | K7: פנימי | L7: ILS | M7: 1.576 | N7: 31/10/2025 | O7: 0.0075 | P7: 0.00797 | R7: 1346811 | S7: 1 | T7: 112.14 | U7: 1510.314 | W7: שווי הוגן | X7: 6.2e-05 | Y7: 0.024036398 | Z7: 0.0039761612
A8: 1182 | B8: 1182 | C8: גליל | D8: ממשל צמודה 1131 | E8: IL0011722209 | F8: צמוד למדד המחירים לצרכן בריבית קבועה | G8: ישראל | H8: ישראל | I8: TASE | J8: RF | K8: פנימי | L8: ILS | M8: 7.638 | N8: 30/11/2031 | O8: 0.001 | P8: 0.01556 | R8: 202224 | S8: 1 | T8: 99.81 | U8: 201.84 | W8: שווי הוגן | X8: 8e-06 | Y8: 0.003212247 | Z8: 0.00053137795
A9: 1182 | B9: 1182 | C9: שחר | D9: ממשל שיקלית 0928 | E9: IL0011508798 | F9: לא צמוד למדד המחירים לצרכן ריבית קבועה | G9: ישראל | H9: ישראל | I9: TASE | J9: RF | K9: פנימי | L9: ILS | M9: 4.269 | N9: 28/09/2028 | O9: 0.0225 | P9: 0.04072 | R9: 266042 | S9: 1 | T9: 93.79 | U9: 249.521 | W9: שווי הוגן | X9: 1e-05 | Y9: 0.0039710826 | Z9: 0.00065690644
A10: 1182 | B10: 1182 | C10: שחר | D10: ממשל שקלית 0229 | E10: IL0011948028 | F10: לא צמוד למדד המחירים לצרכן ריבית קבועה | G10: ישראל | H10: ישראל | I10: TASE | J10: RF | K10: פנימי | L10: ILS | M10: 4.563 | N10: 28/02/2029 | O10: 0.0375 | P10: 0.04094 | R10: 1799925 | S10: 1 | T10: 98.83 | U10: 1778.866 | W10: שווי הוגן | X10: 0.000141 | Y10: 0.02831036 | Z10: 0.0046831707
A11: 1182 | B11: 1182 | C11: שחר | D11: ממשל שקלית 0327 | E11: IL0011393449 | F11: לא צמוד למדד המחירים לצרכן ריבית קבועה | G11: ישראל | H11: ישראל | I11: TASE | J11: RF | K11: פנימי | L11: ILS | M11: 2.937 | N11: 31/03/2027 | O11: 0.02 | P11: 0.04015 | R11: 528276 | S11: 1 | T11: 94.43 | U11: 498.851 | W11: שווי הוגן | X11: 2.4e-05 | Y11: 0.0079391326 | Z11: 0.0013133112
A12: 1182 | B12: 1182 | C12: שחר | D12: ממשל שקלית 0347 | E12: IL0011401937 | F12: לא צמוד למדד המחירים לצרכן ריבית קבועה | G12: ישראל | H12: ישראל | I12: TASE | J12: RF | K12: פנימי | L12: ILS | M12: 15.141 | N12: 31/03/2047 | O12: 0.0375 | P12: 0.04826 | R12: 1302268 | S12: 1 | T12: 85.26 | U12: 1110.314 | W12: שווי הוגן | X12: 5.2e-05 | Y12: 0.017670461 | Z12: 0.002923092
A13: 1182 | B13: 1182 | C13: גליל | D13: ממשלתי צמוד 841 | E13: IL0011205833 | F13: צמוד למדד המחירים לצרכן בריבית קבועה | G13: ישראל | H13: ישראל | I13: TASE | J13: RF | K13: פנימי | L13: ILS | M13: 14.135 | N13: 30/08/2041 | O13: 0.0275 | P13: 0.01782 | R13: 68189 | S13: 1 | T13: 138.12 | U13: 94.183 | W13: שווי הוגן | X13: 4e-06 | Y13: 0.0014989014 | Z13: 0.00024795203
... A99: 969 | B99: 969 | C99: US TREASURY N/B | D99: T-3 3/8 15/05/33 | E99: US91282CHC82 | F99: צמוד מט"ח בריבית קבועה | G99: חו"ל | H99: ארה"ב | I99: NYSE | J99: Aaa | K99: Moodys | L99: USD | M99: 7.57 | N99: 15/05/2033 | O99: 0.03375 | P99: 0.04409 | R99: 765000 | S99: 3.681 | T99: 95.014 | U99: 2675.555 | W99: שווי הוגן | X99: 7e-06 | Y99: 0.16364508 | Z99: 0.036428227

Sheet ניירות ערך מסחריים
A1: מספר קופה/קרן/ח.פ. עבור חברת ביטוח | B1: מספר מסלול | C1: שם מנפיק | D1: מספר מנפיק | E1: סוג מספר מזהה מנפיק | F1: שם נייר ערך | G1: מספר נייר ערך | H1: סוג מספר נייר ערך | I1: מאפיין עיקרי | J1: ישראל/חו"ל | K1: מדינה לפי חשיפה כלכלית | L1: זירת מסחר | M1: ענף מסחר | N1: בעל עניין/צד קשור | O1: דירוג | P1: שם מדרג | Q1: דירוג נייר הערך/המנפיק | R1: מטבע פעילות | S1: מח"מ | T1: ריבית עוגן | U1: מועד פדיון | V1: שיעור ריבית | W1: תשואה לפדיון | X1: נחיתות חוזית | Y1: האם סווג כחוב בעייתי | Z1: ערך נקוב (יחידות) | AA1: שער חליפין | AB1: שער נייר הערך | AC1: סכום לקבל (במטבע הפעילות) | AD1: שווי הוגן (באלפי ש"ח) | AE1: עלות מופחתת (באלפי ש"ח) | AF1: עלות מופחתת (במטבע הפעילות) | AG1: השיטה שיושמה בדוח הכספי | AH1: שיעור מערך נקוב מונפק | AI1: שיעור מנכסי אפיק ההשקעה | AJ1: שיעור מסך נכסי ההשקעה

Sheet איגרות חוב
A1: מספר קופה/קרן/ח.פ. עבור חברת ביטוח | B1: מספר מסלול | C1: שם מנפיק | D1: מספר מנפיק | E1: סוג מספר מזהה מנפיק | F1: שם נייר ערך | G1: מספר נייר ערך | H1: סוג מספר נייר ערך | I1: מאפיין עיקרי | J1: ישראל/חו"ל | K1: מדינה לפי חשיפה כלכלית | L1: סטאטוס סחירות | M1: זירת מסחר | N1: ענף מסחר | O1: בעל עניין/צד קשור | P1: דירוג | Q1: שם מדרג | R1: דירוג נייר הערך/המנפיק | S1: מטבע פעילות | T1: מח"מ | U1: מועד פדיון | V1: שיעור ריבית | W1: תשואה לפדיון | X1: נחיתות חוזית | Y1: האם סווג כחוב בעייתי | Z1: ערך נקוב (יחידות) | AA1: שער חליפין | AB1: שער נייר הערך | AC1: סכום לקבל (במטבע הפעילות) | AD1: שווי הוגן (באלפי ש"ח) | AE1: עלות מופחתת (באלפי ש"ח) | AF1: עלות מופחתת (במטבע הפעילות) | AG1: השיטה שיושמה בדוח הכספי | AH1: שיעור מערך נקוב מונפק | AI1: שיעור מנכסי אפיק ההשקעה | AJ1: שיעור מסך נכסי ההשקעה
A2: 1182 | B2: 1182 | C2: אדגר השקעות ופיתוח בע"מ | D2: 520035171 | E2: ח.פ | F2: אדגר אגח ט | G2: IL0018201900 | H2: ISIN | I2: צמוד למדד המחירים לצרכן | J2: ישראל | K2: גלובלי | L2: סחיר | M2: TASE | N2: נדל"ן מניב בחו"ל | O2: לא | P2: A2 | Q2: מידרוג Moodys | R2: נייר ערך | S2: ILS | T2: 0.739 | U2: 01/07/2025 | V2: 0.0465 | W2: 0.02557 | X2: החוב לא נחות | Y2: לא | Z2: 97638.4 | AA2: 1 | AB2: 115.33 | AD2: 112.606 | AG2: שווי הוגן | AH2: 0.000227 | AI2: 0.0050809308 | AJ2: 0.00029645565
A3: 1182 | B3: 1182 | C3: אדמה פתרונות לחקלאות בע"מ | D3: 520043605 | E3: ח.פ | F3: אדמה אגח ב | G3: IL0011109159 | H3: ISIN | I3: צמוד למדד המחירים לצרכן | J3: ישראל | K3: ישראל | L3: סחיר | M3: TASE | N3: כימיה, גומי ופלסטיק | O3: לא | P3: AA- | Q3: S&P מעלות | R3: נייר ערך | S3: ILS | T3: 5.674 | U3: 30/11/2036 | V3: 0.0515 | W3: 0.02931 | X3: החוב לא נחות | Y3: לא | Z3: 86702.36 | AA3: 1 | AB3: 154.27 | AD3: 133.756 | AG3: שווי הוגן | AH3: 2.8e-05 | AI3: 0.0060352148 | AJ3: 0.00035213499
A4: 1182 | B4: 1182 | C4: או.פי.סי. אנרגיה בע"מ | D4: 514401702 | E4: ח.פ | F4: או פי סי אגח ב' | G4: IL0011660573 | H4: ISIN | I4: צמוד למדד המחירים לצרכן | J4: ישראל | K4: ישראל | L4: סחיר | M4: TASE | N4: אנרגיה | O4: לא | P4: A- | Q4: S&P מעלות | R4: נייר ערך | S4: ILS | T4: 3.318 | U4: 01/10/2028 | V4: 0.0275 | W4: 0.02769 | X4: החוב לא נחות | Y4: לא | Z4: 195942.09 | AA4: 1 | AB4: 110.77 | AD4: 217.045 | AG4: שווי הוגן | AH4: 0.000217 | AI4: 0.0097933263 | AJ4: 0.00057140847
A5: 1182 | B5: 1182 | C5: או.פי.סי. אנרגיה בע"מ | D5: 514401702 | E5: ח.פ | F5: או.פי.סי אגח ג | G5: IL0011803553 | H5: ISIN | I5: לא צמוד למדד המחירים לצרכן | J5: ישראל | K5: ישראל | L5: סחיר | M5: TASE | N5: אנרגיה | O5: לא | P5: A- | Q5: S&P מעלות | R5: נייר ערך | S5: ILS | T5: 3.532 | U5: 31/08/2030 | V5: 0.025 | W5: 0.05517 | X5: החוב לא נחות | Y5: לא | Z5: 304000 | AA5: 1 | AB5: 90.36 | AD5: 274.694 | AG5: שווי הוגן | AH5: 0.000357 | AI5: 0.012394532 | AJ5: 0.0007231803
A6: 1182 | B6: 1182 | C6: אזורים-חברה להשקעות בפתוח ובבנין בע"מ | D6: 520025990 | E6: ח.פ | F6: אזורים סדרה 14 | G6: IL0071504448 | H6: ISIN | I6: לא צמוד למדד המחירים לצרכן | J6: ישראל | K6: ישראל | L6: סחיר | M6: TASE | N6: בנייה | O6: לא | P6: A2 | Q6: מידרוג Moodys | R6: נייר ערך | S6: ILS | T6: 2.725 | U6: 31/12/2028 | V6: 0.0255 | W6: 0.05373 | X6: החוב לא נחות | Y6: לא | Z6: 393125 | AA6: 1 | AB6: 93.65 | AD6: 368.162 | AG6: שווי הוגן | AH6: 0.000675 | AI6: 0.01661188 | AJ6: 0.00096924869
A7: 1182 | B7: 1182 | C7: איי.די.איי. הנפקות (2010) בע"מ | D7: 514486042 | E7: ח.פ | F7: איידיאיי הנפקות אגח ו | G7: IL0011830374 | H7: ISIN | I7: לא צמוד למדד המחירים לצרכן | J7: ישראל | K7: ישראל | L7: סחיר | M7: TASE | N7: ביטוח | O7: לא | P7: A2 | Q7: מידרוג Moodys | R7: נייר ערך | S7: ILS | T7: 4.451 | U7: 15/12/2028 | V7: 0.0218 | W7: 0.05413 | X7: החוב לא נחות | Y7: לא | Z7: 965867 | AA7: 1 | AB7: 87.63 | AD7: 846.389 | AG7: שווי הוגן | AH7: 0.005875 | AI7: 0.038190072 | AJ7: 0.0022282654
A8: 1182 | B8: 1182 | C8: איירפורט סיטי בע"מ | D8: 511659401 | E8: ח.פ | F8: איירפורט אגח ה | G8: IL0011334872 | H8: ISIN | I8: צמוד למדד המחירים לצרכן | J8: ישראל | K8: ישראל | L8: סחיר | M8: TASE | N8: נדל"ן מניב בישראל | O8: לא | P8: AA | Q8: S&P מעלות | R8: נייר ערך | S8: ILS | T8: 2.698 | U8: 28/02/2029 | V8: 0.0234 | W8: 0.02157 | X8: החוב לא נחות | Y8: לא | Z8: 132000.02 | AA8: 1 | AB8: 111.84 | AD8: 147.629 | AG8: שווי הוגן | AH8: 5.1e-05 | AI8: 0.0066611849 | AJ8: 0.00038865829
A9: 1182 | B9: 1182 | C9: אלוני-חץ נכסים והשקעות בע"מ | D9: 520038506 | E9: ח.פ | F9: אלוני חץ אגח יב | G9: IL0039004952 | H9: ISIN | I9: לא צמוד למדד המחירים לצרכן | J9: ישראל | K9: ישראל | L9: סחיר | M9: TASE | N9: נדל"ן מניב בישראל | O9: לא | P9: AA- | Q9: S&P מעלות | R9: נייר ערך | S9: ILS | T9: 4.837 | U9: 28/02/2031 | V9: 0.0241 | W9: 0.05745 | X9: החוב לא נחות | Y9: לא | Z9: 204444.44 | AA9: 1 | AB9: 85.75 | AD9: 175.311 | AG9: שווי הוגן | AH9: 0.000132 | AI9: 0.0079102419 | AJ9: 0.00046153667
A10: 1182 | B10: 1182 | C10: אלוני-חץ נכסים והשקעות בע"מ | D10: 520038506 | E10: ח.פ | F10: אלוני חץ אגח יג | G10: IL0011894065 | H10: ISIN | I10: לא צמוד למדד המחירים לצרכן | J10: ישראל | K10: ישראל | L10: סחיר | M10: TASE | N10: נדל"ן מניב בישראל | O10: לא | P10: Aa3 | Q10: מידרוג Moodys | R10: נייר ערך | S10: ILS | T10: 6.789 | U10: 01/03/2037 | V10: 0.0494 | W10: 0.06222 | X10: החוב לא נחות | Y10: לא | Z10: 235951 | AA10: 1 | AB10: 92.4 | AD10: 218.019 | AG10: שווי הוגן | AH10: 0.000445 | AI10: 0.0098372595 | AJ10: 0.00057397182
A11: 1182 | B11: 1182 | C11: אלקטרה בע"מ | D11: 520028911 | E11: ח.פ | F11: אלקטרה אגח ה | G11: IL0073902228 | H11: ISIN | I11: לא צמוד למדד המחירים לצרכן | J11: ישראל | K11: ישראל | L11: סחיר | M11: TASE | N11: השקעה ואחזקות | O11: לא | P11: A+ | Q11: S&P מעלות | R11: נייר ערך | S11: ILS | T11: 3.41 | U11: 10/01/2031 | V11: 0.04 | W11: 0.0502 | X11: החוב לא נחות | Y11: לא | Z11: 218750.04 | AA11: 1 | AB11: 97.7 | AD11: 213.719 | AG11: שווי הוגן | AH11: 0.000283 | AI11: 0.0096432414 | AJ11: 0.0005626515
A12: 1182 | B12: 1182 | C12: אפי נכסים בע"מ | D12: 510560188 | E12: ח.פ | F12: אפי נכסים אגח 8 | G12: IL0011422313 | H12: ISIN | I12: צמוד למדד המחירים לצרכן | J12: ישראל | K12: ישראל | L12: סחיר | M12: TASE | N12: נדל"ן מניב בחו"ל | O12: לא | P12: A2 | Q12: מידרוג Moodys | R12: נייר ערך | S12: ILS | T12: 1.943 | U12: 15/10/2026 | V12: 0.0257 | W12: 0.02477 | X12: החוב לא נחות | Y12: לא | Z12: 910740 | AA12: 1 | AB12: 113.66 | AD12: 1035.147 | AG12: שווי הוגן | AH12: 0.00071 | AI12: 0.046707046 | AJ12: 0.0027252029
A13: 1182 | B13: 1182 | C13: אפי נכסים בע"מ | D13: 510560188 | E13: ח.פ | F13: אפי נכסים אגח יד | G13: IL0011845307 | H13: ISIN | I13: צמוד למדד המחירים לצרכן | J13: ישראל | K13: ישראל | L13: סחיר | M13: TASE | N13: נדל"ן מניב בחו"ל | O13: לא | P13: A2 | Q13: מידרוג Moodys | R13: נייר ערך | S13: ILS | T13: 5.621 | U13: 30/03/2031 | V13: 0.0154 | W13: 0.03297 | X13: החוב לא נחות | Y13: לא | Z13: 317000 | AA13: 1 | AB13: 98.44 | AD13: 312.055 | AG13: שווי הוגן | AH13: 0.000906 | AI13: 0.014080277 | AJ13: 0.00082153798
... A371: 969 | B371: 969 | C371: Chamoss International Limited | D371: 633896 | E371: מספר תאגיד או שותפות בחו"ל | F371: שמוס אגח א | G371: IL0011559510 | H371: ISIN | I371: צמוד למט"ח | J371: חו"ל | K371: בריטניה | L371: סחיר | M371: TASE | N371: נדל"ן מניב בחו"ל | O371: לא | P371: Aa3 | Q371: מידרוג Moodys | R371: נייר ערך | S371: ILS | T371: 3.25 | U371: 10/07/2028 | V371: 0.043 | W371: 0.08436 | X371: החוב לא נחות | Y371: לא | Z371: 85751.85 | AA371: 1 | AB371: 86.78 | AD371: 74.415 | AG371: שווי הוגן | AH371: 7.4e-05 | AI371: 0.012149967 | AJ371: 0.0010131815

Sheet מניות מבכ ויהש
A1: מספר קופה/קרן/ח.פ. עבור חברת ביטוח | B1: מספר מסלול | C1: שם מנפיק | D1: מספר מנפיק | E1: סוג מספר מזהה מנפיק | F1: שם נייר ערך | G1: מספר נייר ערך | H1: סוג מספר נייר ערך | I1: מאפיין עיקרי | J1: ישראל/חו"ל | K1: מדינה לפי חשיפה כלכלית | L1: סטאטוס סחירות | M1: זירת מסחר | N1: ענף מסחר | O1: בעל עניין/צד קשור | P1: מטבע פעילות | Q1: ערך נקוב (יחידות) | R1: שער חליפין | S1: שער נייר הערך | T1: סכום לקבל (במטבע הפעילות) | U1: שווי הוגן (באלפי ש"ח) | V1: שיעור מערך נקוב מונפק | W1: שיעור מנכסי אפיק ההשקעה | X1: שיעור מסך נכסי ההשקעה
A2: 1182 | B2: 1182 | C2: אורמת טכנולגיות אינק | D2: 5493000TSHHWY24VHM09 | E2: LEI | F2: אורמת טכנולוגיות | G2: US6866881021 | H2: ISIN | I2: מניות | J2: חו"ל | K2: ארה"ב | L2: סחיר | M2: TASE | N2: אנרגיה מתחדשת | O2: לא | P2: ILS | Q2: 2795.5 | R2: 1 | S2: 24060 | U2: 672.597 | V2: 5e-05 | W2: 0.016620469 | X2: 0.0017707282
A3: 1182 | B3: 1182 | C3: איי.סי.אל גרופ בע"מ (דואלי) | D3: 520027830 | E3: ח.פ | F3: איי.סי.אל | G3: IL0002810146 | H3: ISIN | I3: מניות | J3: ישראל | K3: ישראל | L3: סחיר | M3: TASE | N3: כימיה, גומי ופלסטיק | O3: לא | P3: ILS | Q3: 36441 | R3: 1 | S3: 1951 | U3: 710.964 | V3: 2.8e-05 | W3: 0.017568542 | X3: 0.0018717349
A4: 1182 | B4: 1182 | C4: איי.די.איי. חברה לביטוח בע"מ | D4: 513910703 | E4: ח.פ | F4: איידיאיי ביטוח | G4: IL0011295016 | H4: ISIN | I4: מניות | J4: ישראל | K4: ישראל | L4: סחיר | M4: TASE | N4: ביטוח | O4: לא | P4: ILS | Q4: 2680 | R4: 1 | S4: 10700 | U4: 286.76 | V4: 0.000183 | W4: 0.0070860912 | X4: 0.00075494507
A5: 1182 | B5: 1182 | C5: אינרום תעשיות בנייה בע"מ | D5: 515001659 | E5: ח.פ | F5: אינרום | G5: IL0011323560 | H5: ISIN | I5: מניות | J5: ישראל | K5: ישראל | L5: סחיר | M5: TASE | N5: מתכת ומוצרי בניה | O5: לא | P5: ILS | Q5: 15773 | R5: 1 | S5: 1180 | U5: 186.121 | V5: 0.000126 | W5: 0.0045992231 | X5: 0.00048999663
A6: 1182 | B6: 1182 | C6: אל על נתיבי אויר לישראל בע"מ | D6: 520017146 | E6: פנימי | F6: אל על | G6: IL0010878242 | H6: ISIN | I6: מניות | J6: ישראל | K6: ישראל | L6: סחיר | M6: TASE | N6: שירותים | O6: לא | P6: ILS | Q6: 0 | R6: 1 | S6: 499.9 | T6: 0.001 | U6: 0.001 | W6: 1.2849656e-08 | X6: 1.3689895e-09
A7: 1182 | B7: 1182 | C7: אלביט מערכות בע"מ | D7: 520043027 | E7: ח.פ | F7: אלביט מערכות | G7: IL0010811243 | H7: ISIN | I7: מניות | J7: ישראל | K7: ישראל | L7: סחיר | M7: TASE | N7: ביטחוניות | O7: לא | P7: ILS | Q7: 1175 | R7: 1 | S7: 77500 | U7: 910.625 | V7: 2.6e-05 | W7: 0.022502343 | X7: 0.0023973771
A8: 1182 | B8: 1182 | C8: אלקטרה בע"מ | D8: 520028911 | E8: ח.פ | F8: אלקטרה | G8: IL0007390375 | H8: ISIN | I8: מניות | J8: ישראל | K8: ישראל | L8: סחיר | M8: TASE | N8: השקעה ואחזקות | O8: לא | P8: ILS | Q8: 283 | R8: 1 | S8: 158340 | U8: 448.102 | V8: 7.4e-05 | W8: 0.011072998 | X8: 0.0011797062
A9: 1182 | B9: 1182 | C9: אנלייט אנרגיה מתחדשת בע"מ | D9: 520041146 | E9: ח.פ | F9: אנלייט אנרגיה | G9: IL0007200111 | H9: ISIN | I9: מניות | J9: ישראל | K9: ארה"ב | L9: סחיר | M9: TASE | N9: אנרגיה מתחדשת | O9: לא | P9: ILS | Q9: 6025.5 | R9: 1 | S9: 6299 | U9: 379.546 | V9: 5.1e-05 | W9: 0.0093789207 | X9: 0.00099922083
A10: 1182 | B10: 1182 | C10: Energean plc | D10: 549300RVMKU0CYUZBB05 | E10: LEI | F10: אנרג'יאן | G10: GB00BG12Y042 | H10: ISIN | I10: מניות | J10: חו"ל | K10: בריטניה | L10: סחיר | M10: TASE | N10: חיפושי נפט וגז | O10: לא | P10: ILS | Q10: 5585 | R10: 1 | S10: 5008 | T10: 6.132 | U10: 285.829 | V10: 3.2e-05 | W10: 0.0070630885 | X10: 0.00075249439
A11: 1182 | B11: 1182 | C11: אפריקה ישראל תעשיות בע"מ | D11: 520026618 | E11: ח.פ | F11: אפריקה תעשיות | G11: IL0008000114 | H11: ISIN | I11: מניות | J11: ישראל | K11: ישראל | L11: סחיר | M11: TASE | N11: מתכת ומוצרי בניה | O11: לא | P11: ILS | Q11: 250 | R11: 1 | S11: 0 | U11: 0 | V11: 0 | W11: 6.1777193e-12 | X11: 6.5816804e-13
A12: 1182 | B12: 1182 | C12: קבוצת אשטרום | D12: 510381601 | E12: ח.פ | F12: אשטרום קבוצה | G12: IL0011323156 | H12: ISIN | I12: מניות | J12: ישראל | K12: ישראל | L12: סחיר | M12: TASE | N12: בנייה | O12: לא | P12: ILS | Q12: 12160 | R12: 1 | S12: 5478 | U12: 666.125 | V12: 0.00012 | W12: 0.016460528 | X12: 0.0017536882
A13: 1182 | B13: 1182 | C13: בוליגו קפיטל בע"מ | D13: 514766195 | E13: ח.פ | F13: בוליגו | G13: IL0011805954 | H13: ISIN | I13: מניות | J13: ישראל | K13: ארה"ב | L13: סחיר | M13: TASE | N13: נדל"ן מניב בחו"ל | O13: לא | P13: ILS | Q13: 9400 | R13: 1 | S13: 755 | U13: 70.97 | V13: 0.00017 | W13: 0.001753731 | X13: 0.00018684074
A14: 1182 | B14: 1182 | C14: בתי זקוק לנפט בע"מ | D14: 520036658 | E14: ח.פ | F14: בזן | G14: IL0025902482 | H14: ISIN | I14: מניות | J14: ישראל | K14: ישראל | L14: סחיר | M14: TASE | N14: אנרגיה | O14: לא | P14: ILS | Q14: 136064 | R14: 1 | S14: 122 | T14: 22.649 | U14: 188.647 | V14: 4.3e-05 | W14: 0.00466164 | X14: 0.00049664647
A15: 1182 | B15: 1182 | C15: בזק החברה הישראלית לתקשורת בע"מ | D15: 520031931 | E15: ח.פ | F15: בזק | G15: IL0002300114 | H15: ISIN | I15: מניות | J15: ישראל | K15: ישראל | L15: סחיר | M15: TASE | N15: תקשורת ומדיה | O15: לא | P15: ILS | Q15: 145858 | R15: 1 | S15: 473 | U15: 689.908 | V15: 5.3e-05 | W15: 0.01704824 | X15: 0.0018163025
A16: 1182 | B16: 1182 | C16: ביג מרכזי קניות (2004) בע"מ | D16: 513623314 | E16: ח.פ | F16: ביג | G16: IL0010972607 | H16: ISIN | I16: מניות | J16: ישראל | K16: ישראל | L16: סחיר | M16: TASE | N16: נדל"ן מניב בישראל | O16: לא | P16: ILS | Q16: 1178.76 | R16: 1 | S16: 41030 | U16: 483.645 | V16: 4.8e-05 | W16: 0.011951298 | X16: 0.0012732793
A17: 1182 | B17: 1182 | C17: הבנק הבינלאומי הראשון לישראל בע"מ | D17: 520029083 | E17: ח.פ | F17: בינלאומי 5 | G17: IL0005930388 | H17: ISIN | I17: מניות | J17: ישראל | K17: ישראל | L17: סחיר | M17: TASE | N17: בנקים | O17: לא | P17: ILS | Q17: 501 | R17: 1 | S17: 15440 | U17: 77.354 | V17: 5e-06 | W17: 0.0019114951 | X17: 0.00020364877
A18: 1182 | B18: 1182 | C18: בית-הזהב בע"מ | D18: 520034562 | E18: ח.פ | F18: בית הזהב | G18: IL0002350101 | H18: ISIN | I18: מניות | J18: ישראל | K18: ישראל | L18: סחיר | M18: TASE | N18: נדל"ן מניב בישראל | O18: לא | P18: ILS | Q18: 6000 | R18: 1 | S18: 2015 | U18: 120.9 | V18: 0.000334 | W18: 0.0029875451 | X18: 0.00031829006
A19: 1182 | B19: 1182 | C19: בנק דיסקונט לישראל בע"מ | D19: 520007030 | E19: ח.פ | F19: דיסקונט | G19: IL0006912120 | H19: ISIN | I19: מניות | J19: ישראל | K19: ישראל | L19: סחיר | M19: TASE | N19: בנקים | O19: לא | P19: ILS | Q19: 19245 | R19: 1 | S19: 1946 | T19: 2.86 | U19: 377.367 | V19: 1.6e-05 | W19: 0.0093250745 | X19: 0.00099348412
A20: 1182 | B20: 1182 | C20: דלתא-גליל תעשיות בע"מ | D20: 520025602 | E20: ח.פ | F20: דלתא גליל | G20: IL0006270347 | H20: ISIN | I20: מניות | J20: ישראל | K20: ישראל | L20: סחיר | M20: TASE | N20: אופנה והלבשה | O20: לא | P20: ILS | Q20: 4338 | R20: 1 | S20: 16390 | U20: 710.998 | V20: 0.000169 | W20: 0.017569389 | X20: 0.0018718252
A21: 1182 | B21: 1182 | C21: הפניקס אחזקות בע"מ | D21: 520017450 | E21: ח.פ | F21: הפניקס | G21: IL0007670123 | H21: ISIN | I21: מניות | J21: ישראל | K21: ישראל | L21: סחיר | M21: TASE | N21: ביטוח | O21: לא | P21: ILS | Q21: 11560 | R21: 1 | S21: 3810 | U21: 440.436 | V21: 4.5e-05 | W21: 0.01088356 | X21: 0.0011595236
A22: 1182 | B22: 1182 | C22: הראל השקעות בביטוח ושרותים פיננסים בע"מ | D22: 520033986 | E22: ח.פ | F22: הראל השקעות | G22: IL0005850180 | H22: ISIN | I22: מניות | J22: ישראל | K22: ישראל | L22: סחיר | M22: TASE | N22: ביטוח | O22: לא | P22: ILS | Q22: 14508 | R22: 1 | S22: 3510 | U22: 509.231 | V22: 7e-05 | W22: 0.01258354 | X22: 0.0013406377
A23: 1182 | B23: 1182 | C23: החברה לישראל בע"מ | D23: 520028010 | E23: ח.פ | F23: חברה לישראל | G23: IL0005760173 | H23: ISIN | I23: מניות | J23: ישראל | K23: ישראל | L23: סחיר | M23: TASE | N23: השקעה ואחזקות | O23: לא | P23: ILS | Q23: 190 | R23: 1 | S23: 100120 | U23: 190.228 | V23: 2.5e-05 | W23: 0.0047007008 | X23: 0.00050080796
A24: 1182 | B24: 1182 | C24: חילן בע"מ | D24: 520039942 | E24: ח.פ | F24: חילן | G24: IL0010846983 | H24: ISIN | I24: מניות | J24: ישראל | K24: ישראל | L24: סחיר | M24: TASE | N24: שירותי מידע | O24: לא | P24: ILS | Q24: 1406 | R24: 1 | S24: 23460 | U24: 329.848 | V24: 6e-05 | W24: 0.0081508235 | X24: 0.00086838059
A25: 1182 | B25: 1182 | C25: חלל-תקשורת בע"מ | D25: 511396046 | E25: ח.פ | F25: חלל תקשורת | G25: IL0010923451 | H25: ISIN | I25: מניות | J25: ישראל | K25: ישראל | L25: סחיר | M25: TASE | N25: תקשורת ומדיה | O25: לא | P25: ILS | Q25: 15254 | R25: 1 | S25: 58.7 | U25: 8.954 | V25: 0.000481 | W25: 0.00022126362 | X25: 2.3573204e-05
A26: 1182 | B26: 1182 | C26: טאואר סמיקונדקטור בע"מ | D26: 520041997 | E26: ח.פ | F26: טאואר | G26: IL0010823792 | H26: ISIN | I26: מניות | J26: ישראל | K26: גלובלי | L26: סחיר | M26: TASE | N26: מוליכים למחצה | O26: לא | P26: ILS | Q26: 2951 | R26: 1 | S26: 12310 | U26: 363.268 | V26: 2.7e-05 | W26: 0.0089766734 | X26: 0.00095636581
A27: 1182 | B27: 1182 | C27: טבע תעשיות פרמצבטיות בע"מ | D27: 520013954 | E27: ח.פ | F27: טבע | G27: IL0006290147 | H27: ISIN | I27: מניות | J27: ישראל | K27: ארה"ב | L27: סחיר | M27: TASE | N27: פארמה | O27: לא | P27: ILS | Q27: 29888 | R27: 1 | S27: 5173 | U27: 1546.106 | V27: 2.7e-05 | W27: 0.038205641 | X27: 0.0040703908
A28: 1182 | B28: 1182 | C28: טיב טעם הולדינגס 1 בע"מ | D28: 520041187 | E28: ח.פ | F28: טיב טעם | G28: IL0001030100 | H28: ISIN | I28: מניות | J28: ישראל | K28: ישראל | L28: סחיר | M28: TASE | N28: רשתות שיווק | O28: לא | P28: ILS | Q28: 47850 | R28: 1 | S28: 511 | U28: 244.513 | V28: 0.000449 | W28: 0.0060421431 | X28: 0.00064372388
A29: 1182 | B29: 1182 | C29: ישראכרט בע"מ | D29: 510706153 | E29: ח.פ | F29: ישראכרט | G29: IL0011574030 | H29: ISIN | I29: מניות | J29: ישראל | K29: ישראל | L29: סחיר | M29: TASE | N29: שירותים פיננסיים | O29: לא | P29: ILS | Q29: 29655 | R29: 1 | S29: 1476 | T29: 6.794 | U29: 444.502 | V29: 0.000148 | W29: 0.010984036 | X29: 0.0011702282
A30: 1182 | B30: 1182 | C30: כלל החזקות עסקי ביטוח בע"מ | D30: 520036120 | E30: ח.פ | F30: כלל ביטוח | G30: IL0002240146 | H30: ISIN | I30: מניות | J30: ישראל | K30: ישראל | L30: סחיר | M30: TASE | N30: ביטוח | O30: לא | P30: ILS | Q30: 11533 | R30: 1 | S30: 6569 | U30: 757.603 | V30: 0.000146 | W30: 0.018721029 | X30: 0.0019945197
A31: 1182 | B31: 1182 | C31: בנק לאומי לישראל בע"מ | D31: 520018078 | E31: ח.פ | F31: לאומי | G31: IL0006046119 | H31: ISIN | I31: מניות | J31: ישראל | K31: ישראל | L31: סחיר | M31: TASE | N31: בנקים | O31: לא | P31: ILS | Q31: 44013 | R31: 1 | S31: 3100 | T31: 10.55 | U31: 1374.953 | V31: 2.7e-05 | W31: 0.033976301 | X31: 0.0036198011
A32: 1182 | B32: 1182 | C32: מגדלי הים התיכון | D32: 512719485 | E32: ח.פ | F32: מגדלי תיכון | G32: IL0011315236 | H32: ISIN | I32: מניות | J32: ישראל | K32: ישראל | L32: סחיר | M32: TASE | N32: נדל"ן מניב בישראל | O32: לא | P32: ILS | Q32: 12893 | R32: 1 | S32: 962.6 | U32: 124.108 | V32: 8.6e-05 | W32: 0.003066818 | X32: 0.00032673572
A33: 1182 | B33: 1182 | C33: מהדרין בע"מ | D33: 520018482 | E33: ח.פ | F33: מהדרין | G33: IL0006860147 | H33: ISIN | I33: מניות | J33: ישראל | K33: ישראל | L33: סחיר | M33: TASE | N33: מזון | O33: לא | P33: ILS | Q33: 1860 | R33: 1 | S33: 15760 | U33: 293.136 | V33: 0.000559 | W33: 0.0072436477 | X33: 0.00077173098
A34: 1182 | B34: 1182 | C34: מטריקס אי.טי בע"מ | D34: 520039413 | E34: ח.פ | F34: מטריקס | G34: IL0004450156 | H34: ISIN | I34: מניות | J34: ישראל | K34: ישראל | L34: סחיר | M34: TASE | N34: שירותי מידע | O34: לא | P34: ILS | Q34: 3508 | R34: 1 | S34: 8160 | T34: 4.455 | U34: 290.708 | V34: 5.5e-05 | W34: 0.0071836487 | X34: 0.00076533875
A35: 1182 | B35: 1182 | C35: מליסרון בע"מ | D35: 520037789 | E35: ח.פ | F35: מליסרון | G35: IL0003230146 | H35: ISIN | I35: מניות | J35: ישראל | K35: ישראל | L35: סחיר | M35: TASE | N35: נדל"ן מניב בישראל | O35: לא | P35: ILS | Q35: 777.75 | R35: 1 | S35: 26900 | T35: 1.964 | U35: 211.179 | V35: 1.6e-05 | W35: 0.0052184114 | X35: 0.00055596434
A36: 1182 | B36: 1182 | C36: מנורה מבטחים החזקות בע"מ | D36: 520007469 | E36: ח.פ | F36: מנורה מבטחים החזקות | G36: IL0005660183 | H36: ISIN | I36: מניות | J36: ישראל | K36: ישראל | L36: סחיר | M36: TASE | N36: ביטוח | O36: לא | P36: ILS | Q36: 7832 | R36: 1 | S36: 9800 | U36: 767.536 | V36: 0.000127 | W36: 0.018966488 | X36: 0.0020206707
A37: 1182 | B37: 1182 | C37: מניף - שירותים פיננסים בע"מ | D37: 512764408 | E37: ח.פ | F37: מניף | G37: IL0011708935 | H37: ISIN | I37: מניות | J37: ישראל | K37: ישראל | L37: סחיר | M37: TASE | N37: אשראי חוץ בנקאי | O37: לא | P37: ILS | Q37: 60804 | R37: 1 | S37: 1207 | U37: 733.904 | V37: 0.001005 | W37: 0.018135419 | X37: 0.0019321294
A38: 1182 | B38: 1182 | C38: מקס סטוק בע"מ | D38: 513618967 | E38: ח.פ | F38: מקס סטוק | G38: IL0011685588 | H38: ISIN | I38: מניות | J38: ישראל | K38: ישראל | L38: סחיר | M38: TASE | N38: רשתות שיווק | O38: לא | P38: ILS | Q38: 47143 | R38: 1 | S38: 841.6 | U38: 396.755 | V38: 0.000339 | W38: 0.0098041762 | X38: 0.0010445271
A39: 1182 | B39: 1182 | C39: ניו-מד אנרג'י- שותפות מוגבלת | D39: 550013098 | E39: ח.פ | F39: ניו-מד אנרג'י יהש | G39: IL0004750209 | H39: ISIN | I39: מניות | J39: ישראל | K39: ישראל | L39: סחיר | M39: TASE | N39: חיפושי נפט וגז | O39: לא | P39: ILS | Q39: 21816.21 | R39: 1 | S39: 935.3 | T39: 4.162 | U39: 208.209 | V39: 1.9e-05 | W39: 0.0051450293 | X39: 0.00054814628
A40: 1182 | B40: 1182 | C40: נייס מערכות בע"מ | D40: 520036872 | E40: ח.פ | F40: נייס | G40: IL0002730112 | H40: ISIN | I40: מניות | J40: ישראל | K40: ארה"ב | L40: סחיר | M40: TASE | N40: תוכנה ואינטרנט | O40: לא | P40: ILS | Q40: 1388 | R40: 1 | S40: 95150 | U40: 1320.682 | V40: 2.2e-05 | W40: 0.032635211 | X40: 0.0034769227
A41: 1182 | B41: 1182 | C41: סיפיה ווז'ן בע"מ | D41: 513476010 | E41: ח.פ | F41: סיפיה וויזן | G41: IL0011819328 | H41: ISIN | I41: מניות | J41: ישראל | K41: ישראל | L41: סחיר | M41: TASE | N41: תוכנה ואינטרנט | O41: לא | P41: ILS | Q41: 5600 | R41: 1 | S41: 53.4 | U41: 2.99 | V41: 4.1e-05 | W41: 7.3895407e-05 | X41: 7.8727428e-06
A42: 1182 | B42: 1182 | C42: סלקום ישראל בע"מ | D42: 511930125 | E42: ח.פ | F42: סלקום | G42: IL0011015349 | H42: ISIN | I42: מניות | J42: ישראל | K42: ישראל | L42: סחיר | M42: TASE | N42: תקשורת ומדיה | O42: לא | P42: ILS | Q42: 17338 | R42: 1 | S42: 1560 | U42: 270.473 | V42: 0.000105 | W42: 0.0066836202 | X42: 0.00071206621
A43: 1182 | B43: 1182 | C43: קבוצת עזריאלי בע"מ (לשעבר קנית מימון) | D43: 510960719 | E43: ח.פ | F43: עזריאלי קבוצה | G43: IL0011194789 | H43: ISIN | I43: מניות | J43: ישראל | K43: ישראל | L43: סחיר | M43: TASE | N43: נדל"ן מניב בישראל | O43: לא | P43: ILS | Q43: 684 | R43: 1 | S43: 26610 | U43: 182.012 | V43: 6e-06 | W43: 0.0044976861 | X43: 0.00047917898
A44: 1182 | B44: 1182 | C44: בנק הפועלים בע"מ | D44: 520000118 | E44: ח.פ | F44: פועלים | G44: IL0006625771 | H44: ISIN | I44: מניות | J44: ישראל | K44: ישראל | L44: סחיר | M44: TASE | N44: בנקים | O44: לא | P44: ILS | Q44: 20998 | R44: 1 | S44: 3500 | T44: 5.527 | U44: 740.457 | V44: 1.6e-05 | W44: 0.018297344 | X44: 0.0019493808
A45: 1182 | B45: 1182 | C45: פלסאנמור בע"מ | D45: 515139129 | E45: ח.פ | F45: פלסאנמור | G45: IL0011767006 | H45: ISIN | I45: מניות | J45: ישראל | K45: ישראל | L45: סחיר | M45: TASE | N45: מכשור רפואי | O45: לא | P45: ILS | Q45: 5600 | R45: 1 | S45: 451 | U45: 25.256 | V45: 0.000112 | W45: 0.00062409792 | X45: 6.6490768e-05
A46: 1182 | B46: 1182 | C46: חברת פרטנר תקשורת בע"מ | D46: 520044314 | E46: ח.פ | F46: פרטנר | G46: IL0010834849 | H46: ISIN | I46: מניות | J46: ישראל | K46: ישראל | L46: סחיר | M46: TASE | N46: תקשורת ומדיה | O46: לא | P46: ILS | Q46: 34260 | R46: 1 | S46: 1597 | U46: 547.132 | V46: 0.000184 | W46: 0.013520117 | X46: 0.0014404197
A47: 1182 | B47: 1182 | C47: פרידנזון שירותים לוגיסטיים בע"מ | D47: 510712466 | E47: ח.פ | F47: פרידנזון | G47: IL0011022196 | H47: ISIN | I47: מניות | J47: ישראל | K47: ישראל | L47: סחיר | M47: TASE | N47: שירותים | O47: לא | P47: ILS | Q47: 1068 | R47: 1 | S47: 5830 | T47: 1.309 | U47: 63.573 | V47: 0.000654 | W47: 0.0015709537 | X47: 0.00016736784
A48: 1182 | B48: 1182 | C48: פריון נטוורק בע"מ לשעבר אינקרדימייל | D48: 512849498 | E48: ח.פ | F48: פריון נטוורק | G48: IL0010958192 | H48: ISIN | I48: מניות | J48: ישראל | K48: גלובלי | L48: סחיר | M48: TASE | N48: תוכנה ואינטרנט | O48: לא | P48: ILS | Q48: 4087 | R48: 1 | S48: 8289 | U48: 338.771 | V48: 8.9e-05 | W48: 0.0083713392 | X48: 0.00089187411
A49: 1182 | B49: 1182 | C49: קבוצת אקרשטיין בע"מ | D49: 512714494 | E49: ח.פ | F49: קבוצת אקרשטיין | G49: IL0011762056 | H49: ISIN | I49: מניות | J49: ישראל | K49: ישראל | L49: סחיר | M49: TASE | N49: מתכת ומוצרי בניה | O49: לא | P49: ILS | Q49: 102313 | R49: 1 | S49: 510 | T49: 17.793 | U49: 539.589 | V49: 0.000356 | W49: 0.013333724 | X49: 0.0014205616
A50: 1182 | B50: 1182 | C50: ריט אזורים - ה.פ ליווינג בע"מ | D50: 516117181 | E50: ח.פ | F50: ריט אזורים ליווינג | G50: IL0011627754 | H50: ISIN | I50: מניות | J50: ישראל | K50: ישראל | L50: סחיר | M50: TASE | N50: נדל"ן מניב בישראל | O50: לא | P50: ILS | Q50: 23731 | R50: 1 | S50: 434.7 | U50: 103.159 | V50: 0.000334 | W50: 0.0025491409 | X50: 0.00027158292
A51: 1182 | B51: 1182 | C51: שטראוס גרופ בע"מ | D51: 520003781 | E51: ח.פ | F51: שטראוס | G51: IL0007460160 | H51: ISIN | I51: מניות | J51: ישראל | K51: ישראל | L51: סחיר | M51: TASE | N51: מזון | O51: לא | P51: ILS | Q51: 10024 | R51: 1 | S51: 6910 | U51: 692.658 | V51: 8.6e-05 | W51: 0.017116197 | X51: 0.0018235425
A52: 1182 | B52: 1182 | C52: שפיר הנדסה ותעשיה בע"מ | D52: 514892801 | E52: ח.פ | F52: שפיר הנדסה | G52: IL0011338758 | H52: ISIN | I52: מניות | J52: ישראל | K52: ישראל | L52: סחיר | M52: TASE | N52: מתכת ומוצרי בניה | O52: לא | P52: ILS | Q52: 23723 | R52: 1 | S52: 2100 | U52: 498.183 | V52: 6.6e-05 | W52: 0.012310539 | X52: 0.0013115525
A53: 1182 | B53: 1182 | C53: amazon.com | D53: 549300LQHH5G4WPME241 | E53: LEI | F53: AMAZON.COM INC | G53: US0231351067 | H53: ISIN | I53: מניות | J53: חו"ל | K53: ארה"ב | L53: סחיר | M53: NASDAQ | N53: Textiles, Apparel & Luxury Goods | O53: לא | P53: USD | Q53: 902 | R53: 3.681 | S53: 180.38 | U53: 598.909 | V53: 0 | W53: 0.014799563 | X53: 0.0015767307
A54: 1182 | B54: 1182 | C54: AMERICAN EXPRESS | D54: SV60HQBVB2DXO09D8H53 | E54: LEI | F54: American Express co | G54: US0258161092 | H54: ISIN | I54: מניות | J54: חו"ל | K54: ארה"ב | L54: סחיר | M54: NYSE | N54: Diversified Financial Services Financial Services | O54: לא | P54: USD | Q54: 870 | R54: 3.681 | S54: 22769 | U54: 729.17 | V54: 2e-06 | W54: 0.01801844 | X54: 0.0019196666
A55: 1182 | B55: 1182 | C55: ALIBABA COM LTD | D55: 549300561UZND4C7B569 | E55: LEI | F55: BABA US Alibaba Group Holding Ltd | G55: US01609W1027 | H55: ISIN | I55: מניות | J55: חו"ל | K55: סין | L55: סחיר | M55: NYSE | N55: Textiles, Apparel & Luxury Goods | O55: לא | P55: USD | Q55: 1923 | R55: 3.681 | S55: 7236 | U55: 512.205 | V55: 1e-06 | W55: 0.01265703 | X55: 0.0013484674
A56: 1182 | B56: 1182 | C56: BIOGEN IDEC INC | D56: W8J5WZB5IY3K0NDQT671 | E56: LEI | F56: Biogen Inc | G56: US09062X1037 | H56: ISIN | I56: מניות | J56: חו"ל | K56: ארה"ב | L56: סחיר | M56: NASDAQ | N56: Pharmaceuticals | O56: לא | P56: USD | Q56: 592 | R56: 3.681 | S56: 21563 | U56: 469.891 | V56: 4e-06 | W56: 0.011611408 | X56: 0.0012370678
A57: 1182 | B57: 1182 | C57: BOEING CO | D57: 549300U5Y5EL6PHYLF13 | E57: LEI | F57: Boeing Co | G57: US0970231058 | H57: ISIN | I57: מניות | J57: חו"ל | K57: ארה"ב | L57: סחיר | M57: NYSE | N57: Food & Staples Retailing Consumer Staples Distribution & Retail | O57: לא | P57: USD | Q57: 430 | R57: 3.681 | S57: 19299 | U57: 305.47 | V57: 1e-06 | W57: 0.0075484406 | X57: 0.00080420332
A58: 1182 | B58: 1182 | D58: GZYUYYBVN9JCLNYWZ615 | E58: LEI | F58: CIFC SEN.SEC.COR.LOAN ISRLPE | G58: XD1338857968 | H58: ISIN | I58: מניות | J58: חו"ל | L58: סחיר | M58: אחר | N58: other | O58: לא | P58: USD | Q58: 387.13 | R58: 3.681 | S58: 129156 | U58: 1840.506 | V58: 0 | W58: 0.045480517 | X58: 0.0048454488
A59: 1182 | B59: 1182 | C59: Deere&Company | D59: PWFTNG3EI0Y73OXWDH08 | E59: LEI | F59: DEERE & CO | G59: US2441991054 | H59: ISIN | I59: מניות | J59: חו"ל | K59: ארה"ב | L59: סחיר | M59: NYSE | N59: Food & Staples Retailing Consumer Staples Distribution & Retail | O59: לא | P59: USD | Q59: 306 | R59: 3.681 | S59: 41074 | U59: 462.652 | V59: 1e-06 | W59: 0.011432531 | X59: 0.0012180105
A60: 1182 | B60: 1182 | C60: FLEX LTD | D60: 549300EAQH74YHD07T53 | E60: LEI | F60: FLEX LTD | G60: SG9999000020 | H60: ISIN | I60: מניות | J60: חו"ל | K60: ארה"ב | L60: סחיר | M60: NASDAQ | N60: Technology Hardware, Storage & Peripherals | O60: לא | P60: USD | Q60: 5000 | R60: 3.681 | S60: 2861 | U60: 526.567 | V60: 1.2e-05 | W60: 0.013011934 | X60: 0.0013862784
A61: 1182 | B61: 1182 | C61: גאמידה סל בע"מ | D61: 512601204 | E61: ח.פ | F61: GAMIDA CELL LTD | G61: IL0011552663 | H61: ISIN | I61: מניות | J61: ישראל | K61: ישראל | L61: סחיר | M61: NASDAQ | N61: Pharmaceuticals | O61: לא | P61: USD | Q61: 10747 | R61: 3.681 | S61: 3.61 | U61: 1.428 | V61: 0.000179 | W61: 3.5289738e-05 | X61: 3.7597334e-06
A62: 1182 | B62: 1182 | C62: ALPHABET INC | D62: 7ZW8QJWVPR4P1J1KQY45 | E62: LEI | F62: Google Us Class c | G62: US02079K1079 | H62: ISIN | I62: מניות | J62: חו"ל | K62: ארה"ב | L62: סחיר | M62: NASDAQ | N62: Diversified Telecommunication Services | O62: לא | P62: USD | Q62: 805 | R62: 3.681 | S62: 15226 | U62: 451.178 | V62: 0 | W62: 0.011148994 | X62: 0.0011878027
A63: 1182 | B63: 1182 | C63: Lvmh Moet Hennessy Louis Vui | D63: IOG4E947OATN0KJYSD45 | E63: LEI | F63: LVMH MOET HENNESSY LOUIS VUITT | G63: FR0000121014 | H63: ISIN | I63: מניות | J63: חו"ל | L63: סחיר | M63: אחר | N63: ConsumerStaplesDistrib&Retai | O63: לא | P63: EUR | Q63: 225 | R63: 3.979 | S63: 83370 | U63: 746.41 | V63: 0 | W63: 0.018444434 | X63: 0.0019650516
A64: 1182 | B64: 1182 | C64: MASTERCARD INC | D64: AR5L2ODV9HN37376R084 | E64: LEI | F64: MASTERCARD UNC | G64: US57636Q1040 | H64: ISIN | I64: מניות | J64: חו"ל | K64: ארה"ב | L64: סחיר | M64: NYSE | N64: Diversified Financial Services Financial Services | O64: לא | P64: USD | Q64: 380 | R64: 3.681 | S64: 481.57 | U64: 673.61 | V64: 0 | W64: 0.016645506 | X64: 0.0017733956
A65: 1182 | B65: 1182 | C65: MERCK &CO INC | D65: 4YV9Y5M8S0BRK1RP0397 | E65: LEI | F65: MERCK & CO INC | G65: US58933Y1055 | H65: ISIN | I65: מניות | J65: חו"ל | K65: ארה"ב | L65: סחיר | M65: NYSE | N65: Pharmaceuticals | O65: לא | P65: USD | Q65: 418 | R65: 3.681 | S65: 13195 | T65: 0.228 | U65: 203.867 | V65: 0 | W65: 0.0050377261 | X65: 0.0005367143
A66: 1182 | B66: 1182 | C66: MICROSOFT CORP | D66: INR2EJN1ERAN0W5ZP974 | E66: LEI | F66: Microsoft crop | G66: US5949181045 | H66: ISIN | I66: מניות | J66: חו"ל | K66: ארה"ב | L66: סחיר | M66: NASDAQ | N66: Software | O66: לא | P66: USD | Q66: 1167 | R66: 3.681 | S66: 420.72 | U66: 1807.298 | V66: 0 | W66: 0.044659925 | X66: 0.0047580238
A67: 1182 | B67: 1182 | C67: MODERNA INC | D67: 549300EI6OKH5K5Q2G38 | E67: LEI | F67: MODERNA INC | G67: US60770K1079 | H67: ISIN | I67: מניות | J67: חו"ל | K67: ארה"ב | L67: סחיר | M67: NASDAQ | N67: Pharmaceuticals | O67: לא | P67: USD | Q67: 1607 | R67: 3.681 | S67: 10656 | U67: 630.342 | V67: 5e-06 | W67: 0.015576292 | X67: 0.0016594825
A68: 1182 | B68: 1182 | C68: NASDAQ INC | D68: 13300 | E68: פנימי | F68: NASDAQ INC | G68: US6311031061 | H68: ISIN | I68: מניות | J68: חו"ל | K68: ארה"ב | L68: סחיר | M68: NASDAQ | N68: Diversified Financial Services Financial Services | O68: לא | P68: USD | Q68: 1924 | R68: 3.681 | S68: 6310 | U68: 446.89 | V68: 0 | W68: 0.011043034 | X68: 0.0011765138
A69: 1182 | B69: 1182 | C69: Netflix Inc | D69: 549300Y7VHGU0I7CE873 | E69: LEI | F69: NETFLIX INC | G69: US64110L1061 | H69: ISIN | I69: מניות | J69: חו"ל | K69: ארה"ב | L69: סחיר | M69: NASDAQ | N69: Diversified Telecommunication Services | O69: לא | P69: USD | Q69: 365 | R69: 3.681 | S69: 60733 | U69: 815.987 | V69: 1e-06 | W69: 0.020163763 | X69: 0.0021482271
A70: 1182 | B70: 1182 | C70: Northrop Grumman Corp | D70: RIMU48P07456QXSO0R61 | E70: LEI | F70: NORTHROP GRUMMAN CORP | G70: US6668071029 | H70: ISIN | I70: מניות | J70: חו"ל | K70: ארה"ב | L70: סחיר | M70: NYSE | N70: Food & Staples Retailing Consumer Staples Distribution & Retail | O70: לא | P70: USD | Q70: 126 | R70: 3.681 | S70: 47866 | U70: 222.005 | V70: 1e-06 | W70: 0.0054859477 | X70: 0.00058446738
A71: 1182 | B71: 1182 | C71: Novo Nordsik | D71: 549300DAQ1CVT6CXN342 | E71: LEI | F71: NOVO NORDISK A/S | G71: US6701002056 | H71: ISIN | I71: מניות | J71: חו"ל | L71: סחיר | M71: אחר | N71: Pharmaceuticals | O71: לא | P71: USD | Q71: 1147 | R71: 3.681 | S71: 12840 | T71: 1.066 | U71: 546.042 | V71: 0 | W71: 0.013493184 | X71: 0.0014375504
A72: 1182 | B72: 1182 | C72: NVIDIA CORP | D72: 549300S4KLFTLO7GSQ80 | E72: LEI | F72: Nvidia corp | G72: US67066G1040 | H72: ISIN | I72: מניות | J72: חו"ל | K72: ארה"ב | L72: סחיר | M72: NASDAQ | N72: Semiconductors & Semiconductor Equipment | O72: לא | P72: USD | Q72: 459 | R72: 3.681 | S72: 90356 | U72: 1526.636 | V72: 0 | W72: 0.037724515 | X72: 0.0040191321
A73: 1182 | B73: 1182 | C73: Pluristem Therapeutics Inc | D73: 529900OZKMF7JGZMYM81 | E73: LEI | F73: PLURISTEM THERAPEUTICS INC | G73: US72942G1040 | H73: ISIN | I73: מניות | J73: חו"ל | K73: ארה"ב | L73: סחיר | M73: NASDAQ | N73: Pharmaceuticals | O73: לא | P73: USD | Q73: 8011 | R73: 3.681 | S73: 80.6 | U73: 23.768 | V73: 0.000254 | W73: 0.0005873213 | X73: 6.2572624e-05
A74: 1182 | B74: 1182 | C74: Prologis Inc | D74: 529900DFH19P073LZ636 | E74: LEI | F74: PROLOGIS INC | G74: US74340W1036 | H74: ISIN | I74: מניות | J74: חו"ל | K74: ארה"ב | L74: סחיר | M74: NYSE | N74: Real Estate Management & Development | O74: לא | P74: USD | Q74: 1240 | R74: 3.681 | S74: 13022 | U74: 594.381 | V74: 1e-06 | W74: 0.014687685 | X74: 0.0015648113
A75: 1182 | B75: 1182 | C75: SCHLUMBERGER LIMITED | D75: 529900IKZG65COT1D505 | E75: LEI | F75: Schlumberger Ltd | G75: AN8068571086 | H75: ISIN | I75: מניות | J75: חו"ל | K75: ארה"ב | L75: סחיר | M75: NYSE | N75: Energy Equipment & Services | O75: לא | P75: USD | Q75: 2617 | R75: 3.681 | S75: 54.81 | T75: 0.73 | U75: 530.68 | V75: 2e-06 | W75: 0.013113575 | X75: 0.0013971072
A76: 1182 | B76: 1182 | C76: SONOS INC | D76: 549300WEPU6075I77M08 | E76: LEI | F76: SONOS INC | G76: US83570H1086 | H76: ISIN | I76: מניות | J76: חו"ל | K76: ארה"ב | L76: סחיר | M76: NASDAQ | N76: Textiles, Apparel & Luxury Goods | O76: לא | P76: USD | Q76: 6720 | R76: 3.681 | S76: 1906 | U76: 471.474 | V76: 5.5e-05 | W76: 0.011650543 | X76: 0.0012412372
A77: 1182 | B77: 1182 | C77: TAIWAN Semiconductor | D77: 549300KB6NK5SBD14S87 | E77: LEI | F77: TAIWAN SEMICON ADR | G77: US8740391003 | H77: ISIN | I77: מניות | J77: חו"ל | K77: סין | L77: סחיר | M77: NYSE | N77: Semiconductors & Semiconductor Equipment | O77: לא | P77: USD | Q77: 2904 | R77: 3.681 | S77: 13605 | T77: 1.288 | U77: 1459.063 | V77: 1e-06 | W77: 0.036054721 | X77: 0.0038412339
A78: 1182 | B78: 1182 | C78: TESLA MOTORS INC | D78: 54930043XZGB27CTOV49 | E78: LEI | F78: TESLA MOTORS INC | G78: US88160R1014 | H78: ISIN | I78: מניות | J78: חו"ל | K78: ארה"ב | L78: סחיר | M78: NASDAQ | N78: Automobiles | O78: לא | P78: USD | Q78: 1084 | R78: 3.681 | S78: 17579 | U78: 701.438 | V78: 0 | W78: 0.017333147 | X78: 0.0018466562
A79: 1182 | B79: 1182 | C79: Vbare Iberian Properties SOCIM | D79: 959800X1MGWGZZW5ZS47 | E79: LEI | F79: VBARE IBERIAN PROPERTIES SOCIM | G79: ES0105196002 | H79: ISIN | I79: מניות | J79: חו"ל | K79: ספרד | L79: סחיר | M79: BME | N79: Real Estate Management & Development | O79: לא | P79: EUR | Q79: 2205 | R79: 3.979 | S79: 600 | U79: 52.643 | V79: 0.001248 | W79: 0.0013008669 | X79: 0.00013859306
A80: 1182 | B80: 1182 | C80: VISA Inc - CLASS A | D80: 549300JZ4OKEHW3DPJ59 | E80: LEI | F80: VISA inc-class a | G80: US92826C8394 | H80: ISIN | I80: מניות | J80: חו"ל | K80: ארה"ב | L80: סחיר | M80: NYSE | N80: Diversified Financial Services Financial Services | O80: לא | P80: USD | Q80: 645 | R80: 3.681 | S80: 27908 | U80: 662.604 | V80: 0 | W80: 0.016373533 | X80: 0.0017444199
A81: 1182 | B81: 1182 | C81: Walt Disney Company | D81: 549300GZKULIZ0WOW665 | E81: LEI | F81: WALT DISNEY CO | G81: US2546871060 | H81: ISIN | I81: מניות | J81: חו"ל | K81: ארה"ב | L81: סחיר | M81: NYSE | N81: Diversified Telecommunication Services | O81: לא | P81: USD | Q81: 1395 | R81: 3.681 | S81: 12236 | U81: 628.318 | V81: 1e-06 | W81: 0.015526289 | X81: 0.0016541553
A82: 1182 | B82: 14769 | C82: DANAHER CORP | D82: S4BKK9OTCEWQ3YHPFM11 | E82: LEI | F82: DANAHER CORP | G82: US2358511028 | H82: ISIN | I82: מניות | J82: ישראל | K82: ארה"ב | L82: סחיר | M82: TASE | N82: Health Care Equipment & Supplies | O82: לא | P82: USD | Q82: 16 | R82: 3.681 | S82: 24972 | T82: 0.003 | U82: 14.72 | V82: 0 | W82: 0.011985334 | X82: 0.0018868377
A83: 1182 | B83: 14769 | C83: אורמת טכנולגיות אינק | D83: 5493000TSHHWY24VHM09 | E83: LEI | F83: אורמת טכנולוגיות | G83: US6866881021 | H83: ISIN | I83: מניות | J83: חו"ל | K83: ארה"ב | L83: סחיר | M83: TASE | N83: אנרגיה מתחדשת | O83: לא | P83: ILS | Q83: 102 | R83: 1 | S83: 24060 | U83: 24.541 | V83: 2e-06 | W83: 0.019982506 | X83: 0.0031458235
A84: 1182 | B84: 14769 | C84: איי.סי.אל גרופ בע"מ (דואלי) | D84: 520027830 | E84: ח.פ | F84: איי.סי.אל | G84: IL0002810146 | H84: ISIN | I84: מניות | J84: ישראל | K84: ישראל | L84: סחיר | M84: TASE | N84: כימיה, גומי ופלסטיק | O84: לא | P84: ILS | Q84: 1061 | R84: 1 | S84: 1951 | U84: 20.7 | V84: 1e-06 | W84: 0.016854925 | X84: 0.0026534518
A85: 1182 | B85: 14769 | C85: איי.די.איי. חברה לביטוח בע"מ | D85: 513910703 | E85: ח.פ | F85: איידיאיי ביטוח | G85: IL0011295016 | H85: ISIN | I85: מניות | J85: ישראל | K85: ישראל | L85: סחיר | M85: TASE | N85: ביטוח | O85: לא | P85: ILS | Q85: 82 | R85: 1 | S85: 10700 | U85: 8.774 | V85: 6e-06 | W85: 0.0071441703 | X85: 0.0011246987
A86: 1182 | B86: 14769 | C86: אינרום תעשיות בנייה בע"מ | D86: 515001659 | E86: ח.פ | F86: אינרום | G86: IL0011323560 | H86: ISIN | I86: מניות | J86: ישראל | K86: ישראל | L86: סחיר | M86: TASE | N86: מתכת ומוצרי בניה | O86: לא | P86: ILS | Q86: 111 | R86: 1 | S86: 1180 | U86: 1.31 | V86: 1e-06 | W86: 0.0010664958 | X86: 0.00016789723
A87: 1182 | B87: 14769 | C87: אלביט מערכות בע"מ | D87: 520043027 | E87: ח.פ | F87: אלביט מערכות | G87: IL0010811243 | H87: ISIN | I87: מניות | J87: ישראל | K87: ישראל | L87: סחיר | M87: TASE | N87: ביטחוניות | O87: לא | P87: ILS | Q87: 28 | R87: 1 | S87: 77500 | U87: 21.7 | V87: 1e-06 | W87: 0.017669078 | X87: 0.0027816231
A88: 1182 | B88: 14769 | C88: אלקטרה בע"מ | D88: 520028911 | E88: ח.פ | F88: אלקטרה | G88: IL0007390375 | H88: ISIN | I88: מניות | J88: ישראל | K88: ישראל | L88: סחיר | M88: TASE | N88: השקעה ואחזקות | O88: לא | P88: ILS | Q88: 10 | R88: 1 | S88: 158340 | U88: 15.834 | V88: 3e-06 | W88: 0.012892728 | X88: 0.0020296876
A89: 1182 | B89: 14769 | C89: אנלייט אנרגיה מתחדשת בע"מ | D89: 520041146 | E89: ח.פ | F89: אנלייט אנרגיה | G89: IL0007200111 | H89: ISIN | I89: מניות | J89: ישראל | K89: ארה"ב | L89: סחיר | M89: TASE | N89: אנרגיה מתחדשת | O89: לא | P89: ILS | Q89: 240 | R89: 1 | S89: 6299 | U89: 15.118 | V89: 2e-06 | W89: 0.012309404 | X89: 0.0019378556
A90: 1182 | B90: 14769 | C90: Energean plc | D90: 549300RVMKU0CYUZBB05 | E90: LEI | F90: אנרג'יאן | G90: GB00BG12Y042 | H90: ISIN | I90: מניות | J90: חו"ל | K90: בריטניה | L90: סחיר | M90: TASE | N90: חיפושי נפט וגז | O90: לא | P90: ILS | Q90: 214 | R90: 1 | S90: 5008 | T90: 0.235 | U90: 10.952 | V90: 1e-06 | W90: 0.0089176653 | X90: 0.001403898
A91: 1182 | B91: 14769 | C91: קבוצת אשטרום | D91: 510381601 | E91: ח.פ | F91: אשטרום קבוצה | G91: IL0011323156 | H91: ISIN | I91: מניות | J91: ישראל | K91: ישראל | L91: סחיר | M91: TASE | N91: בנייה | O91: לא | P91: ILS | Q91: 168 | R91: 1 | S91: 5478 | U91: 9.203 | V91: 2e-06 | W91: 0.0074935132 | X91: 0.0011796953
A92: 1182 | B92: 14769 | C92: בתי זקוק לנפט בע"מ | D92: 520036658 | E92: ח.פ | F92: בזן | G92: IL0025902482 | H92: ISIN | I92: מניות | J92: ישראל | K92: ישראל | L92: סחיר | M92: TASE | N92: אנרגיה | O92: לא | P92: ILS | Q92: 973 | R92: 1 | S92: 122 | T92: 0.162 | U92: 1.349 | V92: 0 | W92: 0.0010984386 | X92: 0.00017292595
A93: 1182 | B93: 14769 | C93: בזק החברה הישראלית לתקשורת בע"מ | D93: 520031931 | E93: ח.פ | F93: בזק | G93: IL0002300114 | H93: ISIN | I93: מניות | J93: ישראל | K93: ישראל | L93: סחיר | M93: TASE | N93: תקשורת ומדיה | O93: לא | P93: ILS | Q93: 8045 | R93: 1 | S93: 473 | U93: 38.053 | V93: 3e-06 | W93: 0.030984276 | X93: 0.0048778197
A94: 1182 | B94: 14769 | C94: ביג מרכזי קניות (2004) בע"מ | D94: 513623314 | E94: ח.פ | F94: ביג | G94: IL0010972607 | H94: ISIN | I94: מניות | J94: ישראל | K94: ישראל | L94: סחיר | M94: TASE | N94: נדל"ן מניב בישראל | O94: לא | P94: ILS | Q94: 26 | R94: 1 | S94: 41030 | U94: 10.668 | V94: 1e-06 | W94: 0.0086861841 | X94: 0.0013674562
A95: 1182 | B95: 14769 | C95: הבנק הבינלאומי הראשון לישראל בע"מ | D95: 520029083 | E95: ח.פ | F95: בינלאומי 5 | G95: IL0005930388 | H95: ISIN | I95: מניות | J95: ישראל | K95: ישראל | L95: סחיר | M95: TASE | N95: בנקים | O95: לא | P95: ILS | Q95: 9 | R95: 1 | S95: 15440 | U95: 1.39 | V95: 0 | W95: 0.0011314724 | X95: 0.00017812643
A96: 1182 | B96: 14769 | C96: בנק דיסקונט לישראל בע"מ | D96: 520007030 | E96: ח.פ | F96: דיסקונט | G96: IL0006912120 | H96: ISIN | I96: מניות | J96: ישראל | K96: ישראל | L96: סחיר | M96: TASE | N96: בנקים | O96: לא | P96: ILS | Q96: 2194 | R96: 1 | S96: 1946 | T96: 0.326 | U96: 43.021 | V96: 2e-06 | W96: 0.035029746 | X96: 0.0055146935
A97: 1182 | B97: 14769 | C97: קבוצת דלק בע"מ | D97: 520044322 | E97: ח.פ | F97: דלק קבוצה | G97: IL0010841281 | H97: ISIN | I97: מניות | J97: ישראל | K97: ישראל | L97: סחיר | M97: TASE | N97: חיפושי נפט וגז | O97: לא | P97: ILS | Q97: 69 | R97: 1 | S97: 48400 | U97: 33.396 | V97: 4e-06 | W97: 0.027192468 | X97: 0.0042808796
A98: 1182 | B98: 14769 | C98: דלתא-גליל תעשיות בע"מ | D98: 520025602 | E98: ח.פ | F98: דלתא גליל | G98: IL0006270347 | H98: ISIN | I98: מניות | J98: ישראל | K98: ישראל | L98: סחיר | M98: TASE | N98: אופנה והלבשה | O98: לא | P98: ILS | Q98: 78 | R98: 1 | S98: 16390 | U98: 12.784 | V98: 3e-06 | W98: 0.010409449 | X98: 0.0016387478
A99: 1182 | B99: 14769 | C99: הפניקס אחזקות בע"מ | D99: 520017450 | E99: ח.פ | F99: הפניקס | G99: IL0007670123 | H99: ISIN | I99: מניות | J99: ישראל | K99: ישראל | L99: סחיר | M99: TASE | N99: ביטוח | O99: לא | P99: ILS | Q99: 102 | R99: 1 | S99: 3810 | U99: 3.886 | V99: 0 | W99: 0.0031643121 | X99: 0.00049815409
A100: 1182 | B100: 14769 | C100: הראל השקעות בביטוח ושרותים פיננסים בע"מ | D100: 520033986 | E100: ח.פ | F100: הראל השקעות | G100: IL0005850180 | H100: ISIN | I100: מניות | J100: ישראל | K100: ישראל | L100: סחיר | M100: TASE | N100: ביטוח | O100: לא | P100: ILS | Q100: 1167 | R100: 1 | S100: 3510 | U100: 40.962 | V100: 6e-06 | W100: 0.033352788 | X100: 0.0052506918
...

Sheet קרנות סל
A1: מספר קופה/קרן/ח.פ. עבור חברת ביטוח | B1: מספר מסלול | C1: שם מנפיק | D1: מספר מנפיק | E1: סוג מספר מזהה מנפיק | F1: שם נייר ערך | G1: מספר נייר ערך | H1: סוג מספר נייר ערך | I1: מאפיין עיקרי | J1: ישראל/חו"ל | K1: מדינה לפי חשיפה כלכלית | L1: זירת מסחר | M1: סיווג הקרן | N1: בעל עניין/צד קשור | O1: מטבע פעילות | P1: ערך נקוב (יחידות) | Q1: שער חליפין | R1: שער נייר הערך | S1: סכום לקבל (במטבע הפעילות) | T1: שווי הוגן (באלפי ש"ח) | U1: שיעור מערך נקוב מונפק | V1: שיעור מנכסי אפיק ההשקעה | W1: שיעור מסך נכסי ההשקעה
A2: 1182 | B2: 1182 | C2: מגדל קרנות נאמנות בע"מ | D2: 511303661 | E2: ח.פ | F2: MTF סל Nasdaq 100 (4D) | G2: IL0011813875 | H2: ISIN | I2: עוקב אחר מדדי מניות בחו"ל | J2: ישראל | K2: ארה"ב | L2: TASE | M2: מניות בחו"ל חשופות מט"ח | N2: לא | O2: ILS | P2: 5380 | Q2: 1 | R2: 9356 | T2: 503.353 | U2: 0.000849 | V2: 0.0054690331 | W2: 0.0013251629
A3: 1182 | B3: 1182 | C3: מגדל קרנות נאמנות בע"מ | D3: 511303661 | E3: ח.פ | F3: MTF סל תא 125 | G3: IL0011502833 | H3: ISIN | I3: עוקב אחר מדדי מניות בישראל | J3: ישראל | K3: ישראל | L3: TASE | M3: מניות בישראל | N3: לא | O3: ILS | P3: 15305 | Q3: 1 | R3: 3157 | T3: 483.179 | U3: 0.000382 | V3: 0.005249839 | W3: 0.0012720515
A4: 1182 | B4: 1182 | C4: מגדל קרנות נאמנות בע"מ | D4: 511303661 | E4: ח.פ | F4: MTF סל תא 35 | G4: IL0011501843 | H4: ISIN | I4: עוקב אחר מדדי מניות בישראל | J4: ישראל | K4: ישראל | L4: TASE | M4: מניות בישראל | N4: לא | O4: ILS | P4: 18700 | Q4: 1 | R4: 2713 | T4: 507.331 | U4: 0.000369 | V4: 0.0055122571 | W4: 0.0013356362
A5: 1182 | B5: 1182 | C5: מגדל קרנות נאמנות בע"מ | D5: 511303661 | E5: ח.פ | F5: MTF סל תא 90 | G5: IL0011502593 | H5: ISIN | I5: עוקב אחר מדדי מניות בישראל | J5: ישראל | K5: ישראל | L5: TASE | M5: מניות בישראל | N5: לא | O5: ILS | P5: 21395 | Q5: 1 | R5: 3091 | T5: 661.319 | U5: 0.000594 | V5: 0.0071853737 | W5: 0.0017410373
A6: 1182 | B6: 1182 | C6: מגדל קרנות נאמנות בע"מ | D6: 511303661 | E6: ח.פ | F6: SpUSA&D.MTF | G6: IL0011503419 | H6: ISIN | I6: עוקב אחר מדדי מניות בחו"ל | J6: ישראל | K6: ארה"ב | L6: TASE | M6: מניות בחו"ל חשופות מט"ח | N6: לא | O6: ILS | P6: 7580 | Q6: 1 | R6: 8701 | T6: 659.536 | U6: 0.002013 | V6: 0.007165994 | W6: 0.0017363415
A7: 1182 | B7: 1182 | C7: הראל קרנות נאמנות בע"מ | D7: 511776783 | E7: ח.פ | F7: הראל סל תא 90 | G7: IL0011489312 | H7: ISIN | I7: עוקב אחר מדדי מניות בישראל | J7: ישראל | K7: ישראל | L7: TASE | M7: מניות בישראל | N7: לא | O7: ILS | P7: 20973 | Q7: 1 | R7: 2053 | T7: 430.576 | U7: 0.00043 | V7: 0.0046782947 | W7: 0.0011335646
A8: 1182 | B8: 1182 | C8: הראל קרנות נאמנות בע"מ | D8: 511776783 | E8: ח.פ | F8: הראל קרן סל תא 125 | G8: IL0011488991 | H8: ISIN | I8: עוקב אחר מדדי מניות בישראל | J8: ישראל | K8: ישראל | L8: TASE | M8: מניות בישראל | N8: לא | O8: ILS | P8: 12121 | Q8: 1 | R8: 2014 | T8: 244.117 | U8: 0.000213 | V8: 0.0026523815 | W8: 0.00064267987
A9: 1182 | B9: 1182 | C9: מור ניהול קרנות נאמנות בע"מ | D9: 514884485 | E9: ח.פ | F9: מור סל )4D(י NASDAQ 100 | G9: IL0011658361 | H9: ISIN | I9: עוקב אחר מדדי מניות בחו"ל | J9: ישראל | K9: ארה"ב | L9: TASE | M9: מניות בחו"ל חשופות מט"ח | N9: לא | O9: ILS | P9: 9311 | Q9: 1 | R9: 10160 | T9: 945.998 | U9: 0.00098 | V9: 0.010278461 | W9: 0.0024905015
A10: 1182 | B10: 1182 | C10: מגדל קרנות נאמנות בע"מ | D10: 511303661 | E10: ח.פ | F10: סל mtf Trave l& Vacation | G10: IL0011675845 | H10: ISIN | I10: עוקב אחר מדדי מניות בחו"ל | J10: ישראל | K10: ארה"ב | L10: TASE | M10: מניות בחו"ל חשופות מט"ח | N10: לא | O10: ILS | P10: 4108 | Q10: 1 | R10: 3141 | T10: 129.032 | U10: 0.000205 | V10: 0.0014019626 | W10: 0.00033969969
A11: 1182 | B11: 1182 | C11: State Street Corp | D11: 549300E2D1JKWI3P9D54 | E11: LEI | F11: .UTILITIES SELECT S | G11: US81369Y8865 | H11: ISIN | I11: עוקב אחר מדדי מניות בחו"ל | J11: חו"ל | K11: ארה"ב | L11: NYSE | M11: Equity Funds | N11: לא | O11: USD | P11: 3240 | Q11: 3.681 | R11: 65.65 | T11: 782.971 | U11: 1.4e-05 | V11: 0.0085071409 | W11: 0.0020613054
A12: 1182 | B12: 1182 | C12: Invesco investment management limited | D12: 635400KFAN415FMIGG54 | E12: LEI | F12: AINVESCO AEROSPACE & DEFENSE ET | G12: US46137V1008 | H12: ISIN | I12: עוקב אחר מדדי מניות בחו"ל | J12: חו"ל | K12: ארה"ב | L12: NYSE | M12: Equity Funds | N12: לא | O12: USD | P12: 1706 | Q12: 3.681 | R12: 10157 | T12: 637.838 | U12: 8.8e-05 | V12: 0.0069302414 | W12: 0.001679218
A13: 1182 | B13: 1182 | C13: CREDIT AGRICOLE SA | D13: 969500TJ5KRTCJQWXH05 | E13: LEI | F13: AMUNDI ETF ICAV - AMUNDI MSCI | G13: 79279501 | H13: פנימי | I13: עוקב אחר מדדי מניות בחו"ל | J13: חו"ל | K13: צרפת | L13: NASDAQ | M13: Equity Funds | N13: לא | O13: USD | P13: 3184 | Q13: 3.681 | R13: 12389 | T13: 1452.028 | U13: 0 | V13: 0.015776592 | W13: 0.0038227149
... A42: 1182 | B42: 1182 | C42: State Street Corp | D42: 549300E2D1JKWI3P9D54 | E42: LEI | F42: NERGY S.SECTOR SPDR | G42: US81369Y5069 | H42: ISIN | I42: עוקב אחר מדדי מניות בחו"ל | J42: חו"ל | K42: ארה"ב | L42: NYSE | M42: Equity Funds | N42: לא | O42: USD | P42: 3507 | Q42: 3.681 | R42: 94.41 | T42: 1218.764 | U42: 8e-06 | V42: 0.013242124 | W42: 0.0032086058
A43: 1182 | B43: 1182 | C43: Invesco investment management limited | D43: 635400KFAN415FMIGG54 | E43: LEI | F43: Powershares QQQ NAS1 | G43: US46090E1038 | H43: ISIN | I43: עוקב אחר מדדי מניות בחו"ל | J43: חו"ל | K43: ארה"ב | L43: NASDAQ | M43: Equity Funds | N43: לא | O43: USD | P43: 1115 | Q43: 3.681 | R43: 444.01 | S43: 0.454 | T43: 1824.027 | U43: 2e-06 | V43: 0.019818437 | W43: 0.0048020658
A44: 1182 | B44: 1182 | C44: State Street Corp | D44: 549300E2D1JKWI3P9D54 | E44: LEI | F44: Real Estate Select Sector SPDR | G44: US81369Y8600 | H44: ISIN | I44: עוקב אחר מדדי מניות בחו"ל | J44: חו"ל | K44: ארה"ב | L44: NYSE | M44: Equity Funds | N44: לא | O44: USD | P44: 4858 | Q44: 3.681 | R44: 39.53 | T44: 706.887 | U44: 7.9e-05 | V44: 0.0076804773 | W44: 0.0018610024
A45: 1182 | B45: 1182 | C45: State Street Corp | D45: 549300E2D1JKWI3P9D54 | E45: LEI | F45: spdr Amex tech sel indx | G45: US81369Y8030 | H45: ISIN | I45: עוקב אחר מדדי מניות בחו"ל | J45: חו"ל | K45: ארה"ב | L45: NYSE | M45: Equity Funds | N45: לא | O45: USD | P45: 4896 | Q45: 3.681 | R45: 208.27 | T45: 3753.479 | U45: 1.6e-05 | V45: 0.040782328 | W45: 0.0098816786
A46: 1182 | B46: 1182 | C46: State Street Corp | D46: 549300E2D1JKWI3P9D54 | E46: LEI | F46: SPDR BL00MBERG SASB U.S HIGH | G46: IE00B99FL386 | H46: ISIN | I46: עוקב אחר מדדים אחרים בחו"ל | J46: חו"ל | K46: ארה"ב | L46: NASDAQ | M46: Bond/Fixed Income Funds | N46: לא | O46: USD | P46: 18000 | Q46: 3.681 | R46: 4007.5 | T46: 2655.289 | U46: 0 | V46: 0.028850272 | W46: 0.0069905063
A47: 1182 | B47: 1182 | C47: Real Estate Credit Investments Pcc ltd | D47: 549300D9O5F5P2DTYB19 | E47: LEI | F47: SPDR BLOOMBERG BAR | G47: US78488R4083 | H47: ISIN | I47: עוקב אחר מדדים אחרים בחו"ל | J47: חו"ל | K47: ארה"ב | L47: אחר | M47: Bond/Fixed Income Funds | N47: לא | O47: USD | P47: 16000 | Q47: 3.681 | R47: 2522 | T47: 1485.357 | U47: 0.000101 | V47: 0.016138715 | W47: 0.0039104583
A48: 1182 | B48: 1182 | C48: Real Estate Credit Investments Pcc ltd | D48: 549300D9O5F5P2DTYB19 | E48: LEI | F48: SPDR MSCI EUROPE CONSUMER DISC | G48: IE00BKWQ0C77 | H48: ISIN | I48: עוקב אחר מדדי מניות בחו"ל | J48: חו"ל | K48: אירופה | L48: EURONEXT | M48: Equity Funds | N48: לא | O48: EUR | P48: 900 | Q48: 3.979 | R48: 18642 | T48: 667.605 | U48: 0.001029 | V48: 0.0072536723 | W48: 0.0017575863
A49: 1182 | B49: 1182 | C49: Van Eck ETF | D49: 549300WSDUDKDJCJOV22 | E49: LEI | F49: VANECK VECTORS SEMICONDUCTOR | G49: US92189F6768 | H49: ISIN | I49: עוקב אחר מדדי מניות בחו"ל | J49: חו"ל | K49: ארה"ב | L49: NASDAQ | M49: Equity Funds | N49: לא | O49: USD | P49: 1043 | Q49: 3.681 | R49: 22499 | T49: 863.8 | U49: 4.6e-05 | V49: 0.0093853702 | W49: 0.0022741029
A50: 1182 | B50: 1182 | C50: Vanguard Group | D50: QS6WHLCJOJSYY4PYNF72 | E50: LEI | F50: VANGUARD S&P MID-CAP 400 ETF | G50: US9219328856 | H50: ISIN | I50: עוקב אחר מדדי מניות בחו"ל | J50: חו"ל | K50: ארה"ב | L50: NYSE | M50: Equity Funds | N50: לא | O50: USD | P50: 8340 | Q50: 3.681 | R50: 10301 | T50: 3162.36 | U50: 0.001046 | V50: 0.034359697 | W50: 0.0083254561
A51: 1182 | B51: 1182 | C51: WisdomTree Europe ltd | D51: 549300R6SLTQ0LZOHH17 | E51: LEI | F51: Wisdomtree em ex-state-owned D E | G51: US97717X5784 | H51: ISIN | I51: עוקב אחר מדדי מניות בחו"ל | J51: חו"ל | K51: גלובלי | L51: NYSE | M51: Equity Funds | N51: לא | O51: USD | P51: 12340 | Q51: 3.681 | R51: 2946 | T51: 1338.177 | U51: 0.000141 | V51: 0.014539577 | W51: 0.0035229826
A52: 1182 | B52: 1182 | C52: WisdomTree Europe ltd | D52: 549300R6SLTQ0LZOHH17 | E52: LEI | F52: WISDOMTREE INDI | G52: US97717W4226 | H52: ISIN | I52: עוקב אחר מדדי מניות בחו"ל | J52: חו"ל | K52: הודו | L52: NYSE | M52: Equity Funds | N52: לא | O52: USD | P52: 17508 | Q52: 3.681 | R52: 43.56 | T52: 2807.309 | U52: 0.000796 | V52: 0.030501998 | W52: 0.0073907244
A53: 1182 | B53: 1182 | C53: DB x TRACKERS | D53: 549300GFAB28PI25Z431 | E53: LEI | F53: XTRXCKERS NIKKEI 225 UCITS ETF | G53: LU0839027447 | H53: ISIN | I53: עוקב אחר מדדי מניות בחו"ל | J53: חו"ל | K53: יפן | L53: FWB | M53: Equity Funds | N53: לא | O53: EUR | P53: 56629 | Q53: 3.979 | R53: 2551.5 | T53: 5749.358 | U53: 0.00095 | V53: 0.062467969 | W53: 0.015136174
A54: 1182 | B54: 14769 | C54: קסם קרנות נאמנות בע"מ | D54: 510938608 | E54: ח.פ | F54: FTSE 100 (4D) ETF קסם | G54: IL0011464976 | H54: ISIN | I54: עוקב אחר מדדי מניות בחו"ל | J54: ישראל | K54: בריטניה | L54: TASE | M54: מניות בחו"ל חשופות מט"ח | N54: לא | O54: ILS | P54: 1098 | Q54: 1 | R54: 4148 | T54: 45.545 | U54: 7e-05 | V54: 0.0088512996 | W54: 0.0058382091
A55: 1182 | B55: 14769 | C55: מגדל קרנות נאמנות בע"מ | D55: 511303661 | E55: ח.פ | F55: MTF סל תא 90 | G55: IL0011502593 | H55: ISIN | I55: עוקב אחר מדדי מניות בישראל | J55: ישראל | K55: ישראל | L55: TASE | M55: מניות בישראל | N55: לא | O55: ILS | P55: 6930 | Q55: 1 | R55: 3091 | T55: 214.206 | U55: 0.000192 | V55: 0.041629212 | W55: 0.02745812
... A63: 1182 | B63: 14769 | C63: קסם קרנות נאמנות בע"מ | D63: 510938608 | E63: ח.פ | F63: קסם S&P 500 (4D) ETF | G63: IL0011464711 | H63: ISIN | I63: עוקב אחר מדדי מניות בחו"ל | J63: ישראל | K63: ארה"ב | L63: TASE | M63: מניות בחו"ל חשופות מט"ח | N63: לא | O63: ILS | P63: 157 | Q63: 1 | R63: 21080 | T63: 33.096 | U63: 1e-05 | V63: 0.0064318545 | W63: 0.0042423727
A64: 1182 | B64: 14769 | C64: קסם קרנות נאמנות בע"מ | D64: 510938608 | E64: ח.פ | F64: קסםXOTS006. | G64: IL0011462087 | H64: ISIN | I64: עוקב אחר מדדי מניות בחו"ל | J64: ישראל | L64: אחר | M64: מניות בחו"ל חשופות מט"ח | N64: לא | O64: ILS | P64: 68 | Q64: 1 | R64: 46860 | T64: 31.865 | U64: 3.5e-05 | V64: 0.0061926587 | W64: 0.0040846021
A65: 1182 | B65: 14769 | C65: State Street Corp | D65: 549300E2D1JKWI3P9D54 | E65: LEI | F65: .UTILITIES SELECT S | G65: US81369Y8865 | H65: ISIN | I65: עוקב אחר מדדי מניות בחו"ל | J65: חו"ל | K65: ארה"ב | L65: NYSE | M65: Equity Funds | N65: לא | O65: USD | P65: 141 | Q65: 3.681 | R65: 65.65 | T65: 34.074 | U65: 1e-06 | V65: 0.0066219456 | W65: 0.0043677545
A66: 1182 | B66: 14769 | C66: Invesco investment management limited | D66: 635400KFAN415FMIGG54 | E66: LEI | F66: AINVESCO AEROSPACE & DEFENSE ET | G66: US46137V1008 | H66: ISIN | I66: עוקב אחר מדדי מניות בחו"ל | J66: חו"ל | K66: ארה"ב | L66: NYSE | M66: Equity Funds | N66: לא | O66: USD | P66: 66 | Q66: 3.681 | R66: 10157 | T66: 24.676 | U66: 3e-06 | V66: 0.0047955802 | W66: 0.0031631061
A67: 1182 | B67: 14769 | C67: CREDIT AGRICOLE SA | D67: 969500TJ5KRTCJQWXH05 | E67: LEI | F67: AMUNDI ETF ICAV - AMUNDI MSCI | G67: 79279501 | H67: פנימי | I67: עוקב אחר מדדי מניות בחו"ל | J67: חו"ל | K67: צרפת | L67: NASDAQ | M67: Equity Funds | N67: לא | O67: USD | P67: 602 | Q67: 3.681 | R67: 12389 | T67: 274.536 | U67: 0 | V67: 0.053353696 | W67: 0.035191446
A68: 1182 | B68: 14769 | C68: Amundi Asset Management | D68: 549300W6M26WPJCWRV83 | E68: LEI | F68: AMUNDI MSCI EMERGING MARKETS I | G68: LU2573967036 | H68: ISIN | I68: עוקב אחר מדדי מניות בחו"ל | J68: חו"ל | K68: שווקים מתעוררים | L68: NASDAQ | M68: Equity Funds | N68: לא | O68: USD | P68: 403 | Q68: 3.681 | R68: 4968.5 | T68: 73.705 | U68: 0 | V68: 0.014323927 | W68: 0.0094478875
A69: 1182 | B69: 14769 | C69: Amundi Asset Management | D69: 549300W6M26WPJCWRV83 | E69: LEI | F69: AMUNDI MSCI EUROPE QUALITY FAC | G69: LU1681041890 | H69: ISIN | I69: עוקב אחר מדדי מניות בחו"ל | J69: חו"ל | K69: צרפת | L69: EURONEXT | M69: Equity Funds | N69: לא | O69: EUR | P69: 132 | Q69: 3.979 | R69: 11016 | T69: 57.861 | U69: 2.6e-05 | V69: 0.01124472 | W69: 0.0074168803
A70: 1182 | B70: 14769 | C70: Amundi Asset Management | D70: 549300W6M26WPJCWRV83 | E70: LEI | F70: AMUNDI US CURVE STEEPENING 2-1 | G70: LU2018762653 | H70: ISIN | I70: עוקב אחר מדדי מניות בחו"ל | J70: חו"ל | K70: ארה"ב | L70: LSE | M70: Equity Funds | N70: לא | O70: USD | P70: 101 | Q70: 3.681 | R70: 9308 | T70: 34.605 | U70: 0 | V70: 0.0067252668 | W70: 0.0044359038
A71: 1182 | B71: 14769 | C71: State Street Corp | D71: 549300E2D1JKWI3P9D54 | E71: LEI | F71: COMMUNICATION SERVICES SELECT | G71: US81369Y8527 | H71: ISIN | I71: עוקב אחר מדדי מניות בחו"ל | J71: חו"ל | K71: ארה"ב | L71: NYSE | M71: Equity Funds | N71: לא | O71: USD | P71: 33 | Q71: 3.681 | R71: 81.66 | T71: 9.919 | U71: 0 | V71: 0.0019277694 | W71: 0.0012715332
A72: 1182 | B72: 14769 | C72: State Street Corp | D72: 549300E2D1JKWI3P9D54 | E72: LEI | F72: Consumer discretionary etf | G72: us81369y4070 | H72: ISIN | I72: עוקב אחר מדדי מניות בחו"ל | J72: חו"ל | K72: ארה"ב | L72: NYSE | M72: Equity Funds | N72: לא | O72: USD | P72: 46 | Q72: 3.681 | R72: 183.89 | T72: 31.137 | U72: 0 | V72: 0.0060512865 | W72: 0.0039913546
A73: 1182 | B73: 14769 | C73: BlackRock Asset Managment | D73: 549300IJBBIPXKWNXJ28 | E73: LEI | F73: DIVORP ERACHTLAEH .S | G73: US4642888287 | H73: ISIN | I73: עוקב אחר מדדי מניות בחו"ל | J73: חו"ל | K73: ארה"ב | L73: NYSE | M73: Equity Funds | N73: לא | O73: USD | P73: 25 | Q73: 3.681 | R73: 5454 | T73: 5.019 | U73: 4e-06 | V73: 0.00097540934 | W73: 0.00064336809
A74: 1182 | B74: 14769 | C74: State Street Corp | D74: 549300E2D1JKWI3P9D54 | E74: LEI | F74: Financial sel sector spdr | G74: US81369Y6059 | H74: ISIN | I74: עוקב אחר מדדי מניות בחו"ל | J74: חו"ל | K74: ארה"ב | L74: NYSE | M74: Equity Funds | N74: לא | O74: USD | P74: 590 | Q74: 3.681 | R74: 42.12 | T74: 91.476 | U74: 1e-06 | V74: 0.01777756 | W74: 0.011725861
A75: 1182 | B75: 14769 | C75: First trust | D75: 549300QT3GGKQPIIB521 | E75: LEI | F75: First Trust Nas | G75: US3373451026 | H75: ISIN | I75: עוקב אחר מדדי מניות בחו"ל | J75: חו"ל | K75: ארה"ב | L75: NASDAQ | M75: Equity Funds | N75: לא | O75: USD | P75: 40 | Q75: 3.681 | R75: 19068 | T75: 28.076 | U75: 3e-06 | V75: 0.0054562832 | W75: 0.0035988978
A76: 1182 | B76: 14769 | C76: First trust | D76: 549300QT3GGKQPIIB521 | E76: LEI | F76: FIRSTTRUST RTUST NASDAQ CLEAN EDGE | G76: US33737A1088 | H76: ISIN | I76: עוקב אחר מדדי מניות בחו"ל | J76: חו"ל | K76: גלובלי | L76: NASDAQ | M76: Equity Funds | N76: לא | O76: USD | P76: 19 | Q76: 3.681 | R76: 11461 | T76: 8.016 | U76: 3e-06 | V76: 0.0015577863 | W76: 0.0010274968
... A99: 1182 | B99: 14769 | C99: State Street Corp | D99: 549300E2D1JKWI3P9D54 | E99: LEI | F99: NERGY S.SECTOR SPDR | G99: US81369Y5069 | H99: ISIN | I99: עוקב אחר מדדי מניות בחו"ל | J99: חו"ל | K99: ארה"ב | L99: NYSE | M99: Equity Funds | N99: לא | O99: USD | P99: 80 | Q99: 3.681 | R99: 94.41 | T99: 27.802 | U99: 0 | V99: 0.0054030595 | W99: 0.0035637921
A100: 1182 | B100: 14769 | C100: Invesco investment management limited | D100: 635400KFAN415FMIGG54 | E100: LEI | F100: Powershares QQQ NAS1 | G100: US46090E1038 | H100: ISIN | I100: עוקב אחר מדדי מניות בחו"ל | J100: חו"ל | K100: ארה"ב | L100: NASDAQ | M100: Equity Funds | N100: לא | O100: USD | P100: 100 | Q100: 3.681 | R100: 444.01 | S100: 0.044 | T100: 163.601 | U100: 0 | V100: 0.031794414 | W100: 0.020971207
A101: 1182 | B101: 14769 | C101: State Street Corp | D101: 549300E2D1JKWI3P9D54 | E101: LEI | F101: Real Estate Select Sector SPDR | G101: US81369Y8600 | H101: ISIN | I101: עוקב אחר מדדי מניות בחו"ל | J101: חו"ל | K101: ארה"ב | L101: NYSE | M101: Equity Funds | N101: לא | O101: USD | P101: 78 | Q101: 3.681 | R101: 39.53 | T101: 11.35 | U101: 1e-06 | V101: 0.0022057342 | W101: 0.0014548754
A102: 1182 | B102: 14769 | C102: Guggenheim Capital LLC | D102: 549300BDOTSNHM6LG979 | E102: LEI | F102: RSP US | G102: US46137V3574 | H102: ISIN | I102: עוקב אחר מדדי מניות בחו"ל | J102: חו"ל | K102: ארה"ב | L102: NYSE | M102: Equity Funds | N102: לא | O102: USD | P102: 77 | Q102: 3.681 | R102: 16937 | T102: 48.006 | U102: 0 | V102: 0.0093295132 | W102: 0.0061536329
A103: 1182 | B103: 14769 | C103: Source Markets plc | D103: 12119 | E103: פנימי | F103: SDJE50 GR Equity | G103: IE00B60SWX25 | H103: ISIN | I103: עוקב אחר מדדי מניות בחו"ל | J103: חו"ל | L103: אחר | M103: Equity Funds | N103: לא | O103: EUR | P103: 311 | Q103: 3.979 | R103: 12328 | T103: 152.559 | U103: 0.000122 | V103: 0.029648575 | W103: 0.019555838
A104: 1182 | B104: 14769 | C104: Invesco investment management limited | D104: 635400KFAN415FMIGG54 | E104: LEI | F104: SOURCE S&P 500 UCITS EFT | G104: IE00B3YCGJ38 | H104: ISIN | I104: עוקב אחר מדדי מניות בחו"ל | J104: חו"ל | K104: ארה"ב | L104: LSE | M104: Equity Funds | N104: לא | O104: USD | P104: 30 | Q104: 3.681 | R104: 102524 | T104: 113.217 | U104: 6e-06 | V104: 0.022002831 | W104: 0.014512799
A105: 1182 | B105: 14769 | C105: State Street Corp | D105: 549300E2D1JKWI3P9D54 | E105: LEI | F105: spdr Amex tech sel indx | G105: US81369Y8030 | H105: ISIN | I105: עוקב אחר מדדי מניות בחו"ל | J105: חו"ל | K105: ארה"ב | L105: NYSE | M105: Equity Funds | N105: לא | O105: USD | P105: 89 | Q105: 3.681 | R105: 208.27 | T105: 68.231 | U105: 0 | V105: 0.013260152 | W105: 0.0087462341
A106: 1182 | B106: 14769 | C106: State Street Corp | D106: 549300E2D1JKWI3P9D54 | E106: LEI | F106: SPDR BL00MBERG SASB U.S HIGH | G106: IE00B99FL386 | H106: ISIN | I106: עוקב אחר מדדים אחרים בחו"ל | J106: חו"ל | K106: ארה"ב | L106: NASDAQ | M106: Bond/Fixed Income Funds | N106: לא | O106: USD | P106: 200 | Q106: 3.681 | R106: 4007.5 | T106: 29.503 | U106: 0 | V106: 0.0057337043 | W106: 0.0037818814
A107: 1182 | B107: 14769 | C107: Real Estate Credit Investments Pcc ltd | D107: 549300D9O5F5P2DTYB19 | E107: LEI | F107: SPDR BLOOMBERG BAR | G107: US78488R4083 | H107: ISIN | I107: עוקב אחר מדדים אחרים בחו"ל | J107: חו"ל | K107: ארה"ב | L107: אחר | M107: Bond/Fixed Income Funds | N107: לא | O107: USD | P107: 240 | Q107: 3.681 | R107: 2522 | T107: 22.28 | U107: 2e-06 | V107: 0.004330002 | W107: 0.0028560164
A108: 1182 | B108: 14769 | C108: Van Eck ETF | D108: 549300WSDUDKDJCJOV22 | E108: LEI | F108: VANECK VECTORS SEMICONDUCTOR | G108: US92189F6768 | H108: ISIN | I108: עוקב אחר מדדי מניות בחו"ל | J108: חו"ל | K108: ארה"ב | L108: NASDAQ | M108: Equity Funds | N108: לא | O108: USD | P108: 12 | Q108: 3.681 | R108: 22499 | T108: 9.938 | U108: 1e-06 | V108: 0.0019314178 | W108: 0.0012739396
A109: 1182 | B109: 14769 | C109: Vanguard Group | D109: QS6WHLCJOJSYY4PYNF72 | E109: LEI | F109: VANGUARD S&P 50 | G109: us9229083632 | H109: ISIN | I109: עוקב אחר מדדי מניות בחו"ל | J109: חו"ל | K109: ארה"ב | L109: NYSE | M109: Equity Funds | N109: לא | O109: USD | P109: 65 | Q109: 3.681 | R109: 480.7 | T109: 115.015 | U109: 0 | V109: 0.022352147 | W109: 0.014743203
A110: 1182 | B110: 14769 | C110: Vanguard Group | D110: QS6WHLCJOJSYY4PYNF72 | E110: LEI | F110: VANGUARD S&P 500 VALUE ETF | G110: US9219327031 | H110: ISIN | I110: עוקב אחר מדדי מניות בחו"ל | J110: חו"ל | K110: ארה"ב | L110: NASDAQ | M110: Equity Funds | N110: לא | O110: USD | P110: 38 | Q110: 3.681 | R110: 18047 | T110: 25.244 | U110: 0 | V110: 0.0049059191 | W110: 0.0032358843
A111: 1182 | B111: 14769 | C111: Vanguard Group | D111: QS6WHLCJOJSYY4PYNF72 | E111: LEI | F111: VANGUARD S&P MID-CAP 400 ETF | G111: US9219328856 | H111: ISIN | I111: עוקב אחר מדדי מניות בחו"ל | J111: חו"ל | K111: ארה"ב | L111: NYSE | M111: Equity Funds | N111: לא | O111: USD | P111: 340 | Q111: 3.681 | R111: 10301 | T111: 128.921 | U111: 4.3e-05 | V111: 0.02505475 | W111: 0.016525807
A112: 1182 | B112: 14769 | C112: Vanguard Group | D112: QS6WHLCJOJSYY4PYNF72 | E112: LEI | F112: VANGUARD TOTAL WORLD STOCK ETF | G112: US9220427424 | H112: ISIN | I112: עוקב אחר מדדי מניות בחו"ל | J112: חו"ל | K112: גלובלי | L112: NYSE | M112: Equity Funds | N112: לא | O112: USD | P112: 637 | Q112: 3.681 | R112: 11050 | T112: 259.1 | U112: 2e-06 | V112: 0.050353942 | W112: 0.033212845
A113: 1182 | B113: 14769 | C113: WisdomTree Europe ltd | D113: 549300R6SLTQ0LZOHH17 | E113: LEI | F113: Wisdomtree em ex-state-owned D E | G113: US97717X5784 | H113: ISIN | I113: עוקב אחר מדדי מניות בחו"ל | J113: חו"ל | K113: גלובלי | L113: NYSE | M113: Equity Funds | N113: לא | O113: USD | P113: 2168 | Q113: 3.681 | R113: 2946 | T113: 235.103 | U113: 2.5e-05 | V113: 0.045690277 | W113: 0.030136749
A114: 1182 | B114: 14769 | C114: WisdomTree Europe ltd | D114: 549300R6SLTQ0LZOHH17 | E114: LEI | F114: WISDOMTREE INDI | G114: US97717W4226 | H114: ISIN | I114: עוקב אחר מדדי מניות בחו"ל | J114: חו"ל | K114: הודו | L114: NYSE | M114: Equity Funds | N114: לא | O114: USD | P114: 764 | Q114: 3.681 | R114: 43.56 | T114: 122.503 | U114: 3.5e-05 | V114: 0.023807456 | W114: 0.015703107
A115: 1182 | B115: 14769 | C115: DB x TRACKERS | D115: 549300GFAB28PI25Z431 | E115: LEI | F115: XTRXCKERS NIKKEI 225 UCITS ETF | G115: LU0839027447 | H115: ISIN | I115: עוקב אחר מדדי מניות בחו"ל | J115: חו"ל | K115: יפן | L115: FWB | M115: Equity Funds | N115: לא | O115: EUR | P115: 1300 | Q115: 3.979 | R115: 2551.5 | T115: 131.985 | U115: 2.2e-05 | V115: 0.025650139 | W115: 0.016918519
... A159: 12904 | B159: 12905 | C159: State Street Corp | D159: 549300E2D1JKWI3P9D54 | E159: LEI | F159: NERGY S.SECTOR SPDR | G159: US81369Y5069 | H159: ISIN | I159: עוקב אחר מדדי מניות בחו"ל | J159: חו"ל | K159: ארה"ב | L159: NYSE | M159: Equity Funds | N159: לא | O159: USD | P159: 194 | Q159: 3.681 | R159: 94.41 | T159: 67.42 | U159: 0 | V159: 0.0054929026 | W159: 0.0023286673
A160: 12904 | B160: 12905 | C160: Invesco investment management limited | D160: 635400KFAN415FMIGG54 | E160: LEI | F160: Powershares QQQ NAS1 | G160: US46090E1038 | H160: ISIN | I160: עוקב אחר מדדי מניות בחו"ל | J160: חו"ל | K160: ארה"ב | L160: NASDAQ | M160: Equity Funds | N160: לא | O160: USD | P160: 262 | Q160: 3.681 | R160: 444.01 | S160: 0.114 | T160: 428.634 | U160: 0 | V160: 0.034922272 | W160: 0.014804987
A161: 12904 | B161: 12905 | C161: State Street Corp | D161: 549300E2D1JKWI3P9D54 | E161: LEI | F161: Real Estate Select Sector SPDR | G161: US81369Y8600 | H161: ISIN | I161: עוקב אחר מדדי מניות בחו"ל | J161: חו"ל | K161: ארה"ב | L161: NYSE | M161: Equity Funds | N161: לא | O161: USD | P161: 324 | Q161: 3.681 | R161: 39.53 | T161: 47.145 | U161: 5e-06 | V161: 0.0038410857 | W161: 0.0016283942
A162: 12904 | B162: 12905 | C162: Source Markets plc | D162: 12119 | E162: פנימי | F162: SDJE50 GR Equity | G162: IE00B60SWX25 | H162: ISIN | I162: עוקב אחר מדדי מניות בחו"ל | J162: חו"ל | L162: אחר | M162: Equity Funds | N162: לא | O162: EUR | P162: 230 | Q162: 3.979 | R162: 12328 | T162: 112.825 | U162: 9e-05 | V162: 0.0091922466 | W162: 0.0038969713
A163: 12904 | B163: 12905 | C163: State Street Corp | D163: 549300E2D1JKWI3P9D54 | E163: LEI | F163: spdr Amex tech sel indx | G163: US81369Y8030 | H163: ISIN | I163: עוקב אחר מדדי מניות בחו"ל | J163: חו"ל | K163: ארה"ב | L163: NYSE | M163: Equity Funds | N163: לא | O163: USD | P163: 152 | Q163: 3.681 | R163: 208.27 | T163: 116.53 | U163: 1e-06 | V163: 0.0094940709 | W163: 0.0040249271
A164: 12904 | B164: 12905 | C164: State Street Corp | D164: 549300E2D1JKWI3P9D54 | E164: LEI | F164: SPDR BL00MBERG SASB U.S HIGH | G164: IE00B99FL386 | H164: ISIN | I164: עוקב אחר מדדים אחרים בחו"ל | J164: חו"ל | K164: ארה"ב | L164: NASDAQ | M164: Bond/Fixed Income Funds | N164: לא | O164: USD | P164: 1320 | Q164: 3.681 | R164: 4007.5 | T164: 194.721 | U164: 0 | V164: 0.015864618 | W164: 0.0067256641
A165: 12904 | B165: 12905 | C165: Real Estate Credit Investments Pcc ltd | D165: 549300D9O5F5P2DTYB19 | E165: LEI | F165: SPDR BLOOMBERG BAR | G165: US78488R4083 | H165: ISIN | I165: עוקב אחר מדדים אחרים בחו"ל | J165: חו"ל | K165: ארה"ב | L165: אחר | M165: Bond/Fixed Income Funds | N165: לא | O165: USD | P165: 1480 | Q165: 3.681 | R165: 2522 | T165: 137.396 | U165: 9e-06 | V165: 0.011194094 | W165: 0.0047456369
A166: 12904 | B166: 12905 | C166: Van Eck ETF | D166: 549300WSDUDKDJCJOV22 | E166: LEI | F166: VANECK VECTORS SEMICONDUCTOR | G166: US92189F6768 | H166: ISIN | I166: עוקב אחר מדדי מניות בחו"ל | J166: חו"ל | K166: ארה"ב | L166: NASDAQ | M166: Equity Funds | N166: לא | O166: USD | P166: 87 | Q166: 3.681 | R166: 22499 | T166: 72.052 | U166: 4e-06 | V166: 0.0058703587 | W166: 0.0024886864
A167: 12904 | B167: 12905 | C167: Vanguard Group | D167: QS6WHLCJOJSYY4PYNF72 | E167: LEI | F167: VANGUARD S&P 50 | G167: us9229083632 | H167: ISIN | I167: עוקב אחר מדדי מניות בחו"ל | J167: חו"ל | K167: ארה"ב | L167: NYSE | M167: Equity Funds | N167: לא | O167: USD | P167: 288 | Q167: 3.681 | R167: 480.7 | T167: 509.604 | U167: 0 | V167: 0.041519181 | W167: 0.017601688
A168: 12904 | B168: 12905 | C168: Vanguard Group | D168: QS6WHLCJOJSYY4PYNF72 | E168: LEI | F168: VANGUARD S&P MID-CAP 400 ETF | G168: US9219328856 | H168: ISIN | I168: עוקב אחר מדדי מניות בחו"ל | J168: חו"ל | K168: ארה"ב | L168: NYSE | M168: Equity Funds | N168: לא | O168: USD | P168: 660 | Q168: 3.681 | R168: 10301 | T168: 250.259 | U168: 8.3e-05 | V168: 0.020389449 | W168: 0.0086439259
A169: 12904 | B169: 12905 | C169: WisdomTree Europe ltd | D169: 549300R6SLTQ0LZOHH17 | E169: LEI | F169: Wisdomtree em ex-state-owned D E | G169: US97717X5784 | H169: ISIN | I169: עוקב אחר מדדי מניות בחו"ל | J169: חו"ל | K169: גלובלי | L169: NYSE | M169: Equity Funds | N169: לא | O169: USD | P169: 3922 | Q169: 3.681 | R169: 2946 | T169: 425.311 | U169: 4.5e-05 | V169: 0.034651537 | W169: 0.014690211
A170: 12904 | B170: 12905 | C170: WisdomTree Europe ltd | D170: 549300R6SLTQ0LZOHH17 | E170: LEI | F170: WISDOMTREE INDI | G170: US97717W4226 | H170: ISIN | I170: עוקב אחר מדדי מניות בחו"ל | J170: חו"ל | K170: הודו | L170: NYSE | M170: Equity Funds | N170: לא | O170: USD | P170: 2090 | Q170: 3.681 | R170: 43.56 | T170: 335.12 | U170: 9.5e-05 | V170: 0.027303374 | W170: 0.011575023
A171: 12904 | B171: 12905 | C171: DB x TRACKERS | D171: 549300GFAB28PI25Z431 | E171: LEI | F171: XTRXCKERS NIKKEI 225 UCITS ETF | G171: LU0839027447 | H171: ISIN | I171: עוקב אחר מדדי מניות בחו"ל | J171: חו"ל | K171: יפן | L171: FWB | M171: Equity Funds | N171: לא | O171: EUR | P171: 3740 | Q171: 3.979 | R171: 2551.5 | T171: 379.71 | U171: 6.3e-05 | V171: 0.030936301 | W171: 0.01311517
A172: 12904 | B172: 13680 | C172: קסם קרנות נאמנות בע"מ | D172: 510938608 | E172: ח.פ | F172: FTSE 100 (4D) ETF קסם | G172: IL0011464976 | H172: ISIN | I172: עוקב אחר מדדי מניות בחו"ל | J172: ישראל | K172: בריטניה | L172: TASE | M172: מניות בחו"ל חשופות מט"ח | N172: לא | O172: ILS | P172: 10150 | Q172: 1 | R172: 4148 | T172: 421.022 | U172: 0.000649 | V172: 0.021414896 | W172: 0.014393821
A173: 12904 | B173: 13680 | C173: מגדל קרנות נאמנות בע"מ | D173: 511303661 | E173: ח.פ | F173: MTF סל Nasdaq 100 (4D) | G173: IL0011813875 | H173: ISIN | I173: עוקב אחר מדדי מניות בחו"ל | J173: ישראל | K173: ארה"ב | L173: TASE | M173: מניות בחו"ל חשופות מט"ח | N173: לא | O173: ILS | P173: 2984 | Q173: 1 | R173: 9356 | T173: 279.183 | U173: 0.000471 | V173: 0.014200388 | W173: 0.0095446572
A174: 12904 | B174: 13680 | C174: מגדל קרנות נאמנות בע"מ | D174: 511303661 | E174: ח.פ | F174: MTF סל תא 90 | G174: IL0011502593 | H174: ISIN | I174: עוקב אחר מדדי מניות בישראל | J174: ישראל | K174: ישראל | L174: TASE | M174: מניות בישראל | N174: לא | O174: ILS | P174: 19231 | Q174: 1 | R174: 3091 | T174: 594.43 | U174: 0.000534 | V174: 0.030235145 | W174: 0.020322268
... A220: 12904 | B220: 13680 | C220: State Street Corp | D220: 549300E2D1JKWI3P9D54 | E220: LEI | F220: NERGY S.SECTOR SPDR | G220: US81369Y5069 | H220: ISIN | I220: עוקב אחר מדדי מניות בחו"ל | J220: חו"ל | K220: ארה"ב | L220: NYSE | M220: Equity Funds | N220: לא | O220: USD | P220: 655 | Q220: 3.681 | R220: 94.41 | T220: 227.628 | U220: 1e-06 | V220: 0.011578073 | W220: 0.0077820931
A221: 12904 | B221: 13680 | C221: Invesco investment management limited | D221: 635400KFAN415FMIGG54 | E221: LEI | F221: Powershares QQQ NAS1 | G221: US46090E1038 | H221: ISIN | I221: עוקב אחר מדדי מניות בחו"ל | J221: חו"ל | K221: ארה"ב | L221: NASDAQ | M221: Equity Funds | N221: לא | O221: USD | P221: 252 | Q221: 3.681 | R221: 444.01 | S221: 0.11 | T221: 412.273 | U221: 0 | V221: 0.02096991 | W221: 0.014094728
A222: 12904 | B222: 13680 | C222: State Street Corp | D222: 549300E2D1JKWI3P9D54 | E222: LEI | F222: Real Estate Select Sector SPDR | G222: US81369Y8600 | H222: ISIN | I222: עוקב אחר מדדי מניות בחו"ל | J222: חו"ל | K222: ארה"ב | L222: NYSE | M222: Equity Funds | N222: לא | O222: USD | P222: 432 | Q222: 3.681 | R222: 39.53 | T222: 62.86 | U222: 7e-06 | V222: 0.0031973307 | W222: 0.0021490558
A223: 12904 | B223: 13680 | C223: Guggenheim Capital LLC | D223: 549300BDOTSNHM6LG979 | E223: LEI | F223: RSP US | G223: US46137V3574 | H223: ISIN | I223: עוקב אחר מדדי מניות בחו"ל | J223: חו"ל | K223: ארה"ב | L223: NYSE | M223: Equity Funds | N223: לא | O223: USD | P223: 639 | Q223: 3.681 | R223: 16937 | T223: 398.385 | U223: 3e-06 | V223: 0.020263495 | W223: 0.013619917
A224: 12904 | B224: 13680 | C224: Source Markets plc | D224: 12119 | E224: פנימי | F224: SDJE50 GR Equity | G224: IE00B60SWX25 | H224: ISIN | I224: עוקב אחר מדדי מניות בחו"ל | J224: חו"ל | L224: אחר | M224: Equity Funds | N224: לא | O224: EUR | P224: 885 | Q224: 3.979 | R224: 12328 | T224: 434.131 | U224: 0.000348 | V224: 0.022081671 | W224: 0.014841987
A225: 12904 | B225: 13680 | C225: State Street Corp | D225: 549300E2D1JKWI3P9D54 | E225: LEI | F225: spdr Amex tech sel indx | G225: US81369Y8030 | H225: ISIN | I225: עוקב אחר מדדי מניות בחו"ל | J225: חו"ל | K225: ארה"ב | L225: NYSE | M225: Equity Funds | N225: לא | O225: USD | P225: 241 | Q225: 3.681 | R225: 208.27 | T225: 184.761 | U225: 1e-06 | V225: 0.0093976823 | W225: 0.0063165637
A226: 12904 | B226: 13680 | C226: State Street Corp | D226: 549300E2D1JKWI3P9D54 | E226: LEI | F226: SPDR BL00MBERG SASB U.S HIGH | G226: IE00B99FL386 | H226: ISIN | I226: עוקב אחר מדדים אחרים בחו"ל | J226: חו"ל | K226: ארה"ב | L226: NASDAQ | M226: Bond/Fixed Income Funds | N226: לא | O226: USD | P226: 1200 | Q226: 3.681 | R226: 4007.5 | T226: 177.019 | U226: 0 | V226: 0.0090039231 | W226: 0.0060519022
A227: 12904 | B227: 13680 | C227: Real Estate Credit Investments Pcc ltd | D227: 549300D9O5F5P2DTYB19 | E227: LEI | F227: SPDR BLOOMBERG BAR | G227: US78488R4083 | H227: ISIN | I227: עוקב אחר מדדים אחרים בחו"ל | J227: חו"ל | K227: ארה"ב | L227: אחר | M227: Bond/Fixed Income Funds | N227: לא | O227: USD | P227: 1840 | Q227: 3.681 | R227: 2522 | T227: 170.816 | U227: 1.2e-05 | V227: 0.008688402 | W227: 0.0058398276
A228: 12904 | B228: 13680 | C228: Van Eck ETF | D228: 549300WSDUDKDJCJOV22 | E228: LEI | F228: VANECK VECTORS SEMICONDUCTOR | G228: US92189F6768 | H228: ISIN | I228: עוקב אחר מדדי מניות בחו"ל | J228: חו"ל | K228: ארה"ב | L228: NASDAQ | M228: Equity Funds | N228: לא | O228: USD | P228: 122 | Q228: 3.681 | R228: 22499 | T228: 101.039 | U228: 5e-06 | V228: 0.0051392536 | W228: 0.0034543009
A229: 12904 | B229: 13680 | C229: Vanguard Group | D229: QS6WHLCJOJSYY4PYNF72 | E229: LEI | F229: VANGUARD S&P 50 | G229: us9229083632 | H229: ISIN | I229: עוקב אחר מדדי מניות בחו"ל | J229: חו"ל | K229: ארה"ב | L229: NYSE | M229: Equity Funds | N229: לא | O229: USD | P229: 610 | Q229: 3.681 | R229: 480.7 | T229: 1079.369 | U229: 1e-06 | V229: 0.054901089 | W229: 0.03690125
A230: 12904 | B230: 13680 | C230: Vanguard Group | D230: QS6WHLCJOJSYY4PYNF72 | E230: LEI | F230: VANGUARD S&P 500 VALUE ETF | G230: US9219327031 | H230: ISIN | I230: עוקב אחר מדדי מניות בחו"ל | J230: חו"ל | K230: ארה"ב | L230: NASDAQ | M230: Equity Funds | N230: לא | O230: USD | P230: 205 | Q230: 3.681 | R230: 18047 | T230: 136.184 | U230: 0 | V230: 0.0069268515 | W230: 0.0046558181
A231: 12904 | B231: 13680 | C231: Vanguard Group | D231: QS6WHLCJOJSYY4PYNF72 | E231: LEI | F231: VANGUARD S&P MID-CAP 400 ETF | G231: US9219328856 | H231: ISIN | I231: עוקב אחר מדדי מניות בחו"ל | J231: חו"ל | K231: ארה"ב | L231: NYSE | M231: Equity Funds | N231: לא | O231: USD | P231: 1330 | Q231: 3.681 | R231: 10301 | T231: 504.309 | U231: 0.000167 | V231: 0.02565122 | W231: 0.017241226
A232: 12904 | B232: 13680 | C232: Vanguard Group | D232: QS6WHLCJOJSYY4PYNF72 | E232: LEI | F232: VANGUARD TOTAL WORLD STOCK ETF | G232: US9220427424 | H232: ISIN | I232: עוקב אחר מדדי מניות בחו"ל | J232: חו"ל | K232: גלובלי | L232: NYSE | M232: Equity Funds | N232: לא | O232: USD | P232: 2230 | Q232: 3.681 | R232: 11050 | T232: 907.054 | U232: 9e-06 | V232: 0.046136447 | W232: 0.031010178
A233: 12904 | B233: 13680 | C233: WisdomTree Europe ltd | D233: 549300R6SLTQ0LZOHH17 | E233: LEI | F233: Wisdomtree em ex-state-owned D E | G233: US97717X5784 | H233: ISIN | I233: עוקב אחר מדדי מניות בחו"ל | J233: חו"ל | K233: גלובלי | L233: NYSE | M233: Equity Funds | N233: לא | O233: USD | P233: 5910 | Q233: 3.681 | R233: 2946 | T233: 640.894 | U233: 6.8e-05 | V233: 0.032598471 | W233: 0.021910755
A234: 12904 | B234: 13680 | C234: WisdomTree Europe ltd | D234: 549300R6SLTQ0LZOHH17 | E234: LEI | F234: WISDOMTREE INDI | G234: US97717W4226 | H234: ISIN | I234: עוקב אחר מדדי מניות בחו"ל | J234: חו"ל | K234: הודו | L234: NYSE | M234: Equity Funds | N234: לא | O234: USD | P234: 2355 | Q234: 3.681 | R234: 43.56 | T234: 377.611 | U234: 0.000107 | V234: 0.019206834 | W234: 0.012909693
A235: 12904 | B235: 13680 | C235: DB x TRACKERS | D235: 549300GFAB28PI25Z431 | E235: LEI | F235: XTRXCKERS NIKKEI 225 UCITS ETF | G235: LU0839027447 | H235: ISIN | I235: עוקב אחר מדדי מניות בחו"ל | J235: חו"ל | K235: יפן | L235: FWB | M235: Equity Funds | N235: לא | O235: EUR | P235: 9029 | Q235: 3.979 | R235: 2551.5 | T235: 916.685 | U235: 0.000152 | V235: 0.046626333 | W235: 0.031339451
A236: 424 | B236: 7228 | C236: מגדל קרנות נאמנות בע"מ | D236: 511303661 | E236: ח.פ | F236: סל mtf Trave l& Vacation | G236: IL0011675845 | H236: ISIN | I236: עוקב אחר מדדי מניות בחו"ל | J236: ישראל | K236: ארה"ב | L236: TASE | M236: מניות בחו"ל חשופות מט"ח | N236: לא | O236: ILS | P236: 125683 | Q236: 1 | R236: 3141 | T236: 3947.703 | U236: 0.006284 | V236: 0.0073462517 | W236: 0.0017034482
... A266: 424 | B266: 7228 | C266: State Street Corp | D266: 549300E2D1JKWI3P9D54 | E266: LEI | F266: NERGY S.SECTOR SPDR | G266: US81369Y5069 | H266: ISIN | I266: עוקב אחר מדדי מניות בחו"ל | J266: חו"ל | K266: ארה"ב | L266: NYSE | M266: Equity Funds | N266: לא | O266: USD | P266: 31272 | Q266: 3.681 | R266: 94.41 | T266: 10867.746 | U266: 6.7e-05 | V266: 0.020223709 | W266: 0.0046894719
A267: 424 | B267: 7228 | C267: Invesco investment management limited | D267: 635400KFAN415FMIGG54 | E267: LEI | F267: Powershares QQQ NAS1 | G267: US46090E1038 | H267: ISIN | I267: עוקב אחר מדדי מניות בחו"ל | J267: חו"ל | K267: ארה"ב | L267: NASDAQ | M267: Equity Funds | N267: לא | O267: USD | P267: 6346 | Q267: 3.681 | R267: 444.01 | S267: 2.583 | T267: 10381.414 | U267: 1.1e-05 | V267: 0.019318698 | W267: 0.0044796181
A268: 424 | B268: 7228 | C268: State Street Corp | D268: 549300E2D1JKWI3P9D54 | E268: LEI | F268: Real Estate Select Sector SPDR | G268: US81369Y8600 | H268: ISIN | I268: עוקב אחר מדדי מניות בחו"ל | J268: חו"ל | K268: ארה"ב | L268: NYSE | M268: Equity Funds | N268: לא | O268: USD | P268: 36972 | Q268: 3.681 | R268: 39.53 | T268: 5379.793 | U268: 0.000602 | V268: 0.010011218 | W268: 0.0023214003
A269: 424 | B269: 7228 | C269: State Street Corp | D269: 549300E2D1JKWI3P9D54 | E269: LEI | F269: spdr Amex tech sel indx | G269: US81369Y8030 | H269: ISIN | I269: עוקב אחר מדדי מניות בחו"ל | J269: חו"ל | K269: ארה"ב | L269: NYSE | M269: Equity Funds | N269: לא | O269: USD | P269: 50663 | Q269: 3.681 | R269: 208.27 | T269: 38840.377 | U269: 0.000168 | V269: 0.072277773 | W269: 0.016759764
A270: 424 | B270: 7228 | C270: State Street Corp | D270: 549300E2D1JKWI3P9D54 | E270: LEI | F270: SPDR BL00MBERG SASB U.S HIGH | G270: IE00B99FL386 | H270: ISIN | I270: עוקב אחר מדדים אחרים בחו"ל | J270: חו"ל | K270: ארה"ב | L270: NASDAQ | M270: Bond/Fixed Income Funds | N270: לא | O270: USD | P270: 109000 | Q270: 3.681 | R270: 4007.5 | T270: 16079.252 | U270: 0 | V270: 0.029921763 | W270: 0.0069382558
A271: 424 | B271: 7228 | C271: Real Estate Credit Investments Pcc ltd | D271: 549300D9O5F5P2DTYB19 | E271: LEI | F271: SPDR MSCI EUROPE CONSUMER DISC | G271: IE00BKWQ0C77 | H271: ISIN | I271: עוקב אחר מדדי מניות בחו"ל | J271: חו"ל | K271: אירופה | L271: EURONEXT | M271: Equity Funds | N271: לא | O271: EUR | P271: 8000 | Q271: 3.979 | R271: 18642 | T271: 5934.271 | U271: 0.009143 | V271: 0.011043041 | W271: 0.0025606593
A272: 424 | B272: 7228 | C272: Van Eck ETF | D272: 549300WSDUDKDJCJOV22 | E272: LEI | F272: VANECK VECTORS SEMICONDUCTOR | G272: US92189F6768 | H272: ISIN | I272: עוקב אחר מדדי מניות בחו"ל | J272: חו"ל | K272: ארה"ב | L272: NASDAQ | M272: Equity Funds | N272: לא | O272: USD | P272: 7617 | Q272: 3.681 | R272: 22499 | T272: 6308.309 | U272: 0.000333 | V272: 0.011739087 | W272: 0.0027220585
A273: 424 | B273: 7228 | C273: Vanguard Group | D273: QS6WHLCJOJSYY4PYNF72 | E273: LEI | F273: VANGUARD S&P MID-CAP 400 ETF | G273: US9219328856 | H273: ISIN | I273: עוקב אחר מדדי מניות בחו"ל | J273: חו"ל | K273: ארה"ב | L273: NYSE | M273: Equity Funds | N273: לא | O273: USD | P273: 4400 | Q273: 3.681 | R273: 10301 | T273: 1668.391 | U273: 0.000552 | V273: 0.0031046969 | W273: 0.00071991686
A274: 424 | B274: 7228 | C274: WisdomTree Europe ltd | D274: 549300R6SLTQ0LZOHH17 | E274: LEI | F274: Wisdomtree em ex-state-owned D E | G274: US97717X5784 | H274: ISIN | I274: עוקב אחר מדדי מניות בחו"ל | J274: חו"ל | K274: גלובלי | L274: NYSE | M274: Equity Funds | N274: לא | O274: USD | P274: 89970 | Q274: 3.681 | R274: 2946 | T274: 9756.55 | U274: 0.001028 | V274: 0.018155893 | W274: 0.0042099869
...

Sheet קרנות נאמנות
A1: מספר קופה/קרן/ח.פ. עבור חברת ביטוח | B1: מספר מסלול | C1: שם מנפיק | D1: מספר מנפיק | E1: סוג מספר מזהה מנפיק | F1: שם נייר ערך | G1: מספר נייר ערך | H1: סוג מספר נייר ערך | I1: מאפיין עיקרי | J1: ישראל/חו"ל | K1: מדינה לפי חשיפה כלכלית | L1: סטאטוס סחירות | M1: זירת מסחר | N1: סיווג הקרן | O1: בעל עניין/צד קשור | P1: מטבע פעילות | Q1: ערך נקוב (יחידות) | R1: שער חליפין | S1: שער נייר הערך | T1: שווי הוגן (באלפי ש"ח) | U1: שיעור מערך נקוב מונפק | V1: שיעור מנכסי אפיק ההשקעה | W1: שיעור מסך נכסי ההשקעה
A2: 1182 | B2: 1182 | C2: Comgest | D2: 635400JYB1RHBTRDH390 | E2: LEI | F2: COMGEST GROWTH PLC - EURO | G2: IE0004766675 | H2: ISIN | I2: מניות | J2: חו"ל | K2: אירופה | L2: סחיר | M2: ISE | N2: Equity Funds | O2: לא | P2: EUR | Q2: 5997.08 | R2: 3.979 | S2: 5063 | T2: 1208.183 | U2: 0.00022 | V2: 0.076617475 | W2: 0.003180749
A3: 1182 | B3: 1182 | C3: Investec | D3: 549300X3ENFKGMH04N42 | E3: LEI | F3: IGS-EMERG MKT CORP DEBT-IUSD | G3: LU0611395327 | H3: ISIN | I3: אג"ח קונצרני | J3: חו"ל | K3: לוכסמבורג | L3: סחיר | M3: אחר | N3: Bond/Fixed Income Funds | O3: לא | P3: USD | Q3: 6970.12 | R3: 3.681 | S3: 3303 | T3: 847.451 | U3: 0.000161 | V3: 0.053741509 | W3: 0.0022310609
A4: 1182 | B4: 1182 | C4: Invesco investment management limited | D4: 635400KFAN415FMIGG54 | E4: LEI | F4: IUSSENG LX Equity | G4: LU0564079282 | H4: ISIN | I4: אג"ח קונצרני | J4: חו"ל | K4: גלובלי | L4: סחיר | M4: ISE | N4: Bond/Fixed Income Funds | O4: לא | P4: USD | Q4: 2848.35 | R4: 3.681 | S4: 17736 | T4: 1859.58 | U4: 0.000313 | V4: 0.11792613 | W4: 0.0048956643
A5: 1182 | B5: 1182 | C5: KBI Global Investors | D5: 635400UCQYVGO94KDT51 | E5: LEI | F5: KBI FUND ICAV -KBI ENERGY SOL | G5: IE00BNGJJ156 | H5: ISIN | I5: מניות | J5: חו"ל | K5: גלובלי | L5: סחיר | M5: ISE | N5: Equity Funds | O5: לא | P5: USD | Q5: 40605.74 | R5: 3.681 | S5: 978.2 | T5: 1462.113 | U5: 0.003214 | V5: 0.092720575 | W5: 0.0038492639
A6: 1182 | B6: 1182 | C6: Kotak | D6: 549300P1V22EKK1UCL34 | E6: LEI | F6: KOTAK FDS-INDIA MIDCAP (S) USD A | G6: LU2126068639 | H6: ISIN | I6: מניות | J6: חו"ל | K6: לוכסמבורג | L6: סחיר | M6: אחר | N6: Equity Funds | O6: לא | P6: USD | Q6: 28772.31 | R6: 3.681 | S6: 1294.89 | T6: 1371.429 | U6: 0 | V6: 0.086969833 | W6: 0.0036105237
A7: 1182 | B7: 1182 | C7: Lombard Odier Funds-Asia Value | D7: 5493001DJ8NYPLGGID75 | E7: LEI | F7: LOMBARD ODIER-ASIA INV.GR.BD(I | G7: LU2083909536 | H7: ISIN | I7: מניות | J7: חו"ל | K7: אסיה | L7: סחיר | M7: אחר | N7: Equity Funds | O7: לא | P7: USD | Q7: 29128.48 | R7: 3.681 | S7: 1045.75 | T7: 1121.273 | U7: 0 | V7: 0.071106078 | W7: 0.0029519452
A8: 1182 | B8: 1182 | C8: LUXEMBOURG LIFE | D8: 89900 | E8: פנימי | F8: LUXEMBOURG LIFE | G8: lu24283023721 | H8: ISIN | I8: מניות | J8: חו"ל | K8: ארה"ב | L8: סחיר | M8: אחר | N8: Equity Funds | O8: לא | P8: USD | Q8: 4000 | R8: 3.681 | S8: 11473 | T8: 1689.285 | U8: 0 | V8: 0.10712677 | W8: 0.0044473323
A9: 1182 | B9: 1182 | D9: GZYUYYBVN9JCLNYWZ615 | E9: LEI | F9: MGLEUCA LX Equity | G9: LU1670632501 | H9: ISIN | I9: אחר | J9: חו"ל | K9: גלובלי | L9: סחיר | M9: אחר | N9: Other | O9: לא | P9: USD | Q9: 59547.05 | R9: 3.681 | S9: 1199.66 | T9: 2629.567 | U9: 0 | V9: 0.16675523 | W9: 0.0069227879
A10: 1182 | B10: 1182 | C10: PRINCIPAL FINANCIAL | D10: 549300MS0GBEZOTILG43 | E10: LEI | F10: PRINCIPAL GLOBAL INVEST | G10: IE00BKDW9G15 | H10: ISIN | I10: אג"ח קונצרני | J10: חו"ל | K10: אירלנד | L10: סחיר | M10: ISE | N10: Bond/Fixed Income Funds | O10: לא | P10: USD | Q10: 85932.43 | R10: 3.681 | S10: 1131.82 | T10: 3580.142 | U10: 0.00348 | V10: 0.2270364 | W10: 0.0094253406
A11: 1182 | B11: 14769 | C11: Invesco investment management limited | D11: 635400KFAN415FMIGG54 | E11: LEI | F11: IUSSENG LX Equity | G11: LU0564079282 | H11: ISIN | I11: אג"ח קונצרני | J11: חו"ל | K11: גלובלי | L11: סחיר | M11: ISE | N11: Bond/Fixed Income Funds | O11: לא | P11: USD | Q11: 17.09 | R11: 3.681 | S11: 17736 | T11: 11.157 | U11: 2e-06 | V11: 0.11335188 | W11: 0.0014302176
A12: 1182 | B12: 14769 | C12: KBI Global Investors | D12: 635400UCQYVGO94KDT51 | E12: LEI | F12: KBI FUND ICAV -KBI ENERGY SOL | G12: IE00BNGJJ156 | H12: ISIN | I12: מניות | J12: חו"ל | K12: גלובלי | L12: סחיר | M12: ISE | N12: Equity Funds | O12: לא | P12: USD | Q12: 999.43 | R12: 3.681 | S12: 978.2 | T12: 35.987 | U12: 7.9e-05 | V12: 0.36560406 | W12: 0.0046130102
A13: 1182 | B13: 14769 | C13: Kotak | D13: 549300P1V22EKK1UCL34 | E13: LEI | F13: KOTAK FDS-INDIA MIDCAP (S) USD A | G13: LU2126068639 | H13: ISIN | I13: מניות | J13: חו"ל | K13: לוכסמבורג | L13: סחיר | M13: אחר | N13: Equity Funds | O13: לא | P13: USD | Q13: 801.55 | R13: 3.681 | S13: 1294.89 | T13: 38.206 | U13: 0 | V13: 0.38814542 | W13: 0.0048974258
A14: 1182 | B14: 14769 | C14: Lombard Odier Funds-Asia Value | D14: 5493001DJ8NYPLGGID75 | E14: LEI | F14: LOMBARD ODIER-ASIA INV.GR.BD(I | G14: LU2083909536 | H14: ISIN | I14: מניות | J14: חו"ל | K14: אסיה | L14: סחיר | M14: אחר | N14: Equity Funds | O14: לא | P14: USD | Q14: 339.83 | R14: 3.681 | S14: 1045.75 | T14: 13.081 | U14: 0 | V14: 0.13289865 | W14: 0.001676849
A15: 12904 | B15: 12905 | C15: Invesco investment management limited | D15: 635400KFAN415FMIGG54 | E15: LEI | F15: INVESCO GLOBAL INVESTMENT GRAD | G15: LU1218206339 | H15: ISIN | I15: אג"ח קונצרני | J15: חו"ל | K15: גלובלי | L15: סחיר | M15: אחר | N15: Bond/Fixed Income Funds | O15: לא | P15: USD | Q15: 2821.86 | R15: 3.681 | S15: 1242.53 | T15: 129.065 | U15: 0 | V15: 0.14267373 | W15: 0.0044578973
A16: 12904 | B16: 12905 | C16: Invesco investment management limited | D16: 635400KFAN415FMIGG54 | E16: LEI | F16: IUSSENG LX Equity | G16: LU0564079282 | H16: ISIN | I16: אג"ח קונצרני | J16: חו"ל | K16: גלובלי | L16: סחיר | M16: ISE | N16: Bond/Fixed Income Funds | O16: לא | P16: USD | Q16: 210.78 | R16: 3.681 | S16: 17736 | T16: 137.61 | U16: 2.3e-05 | V16: 0.15212015 | W16: 0.0047530545
A17: 12904 | B17: 12905 | C17: KBI Global Investors | D17: 635400UCQYVGO94KDT51 | E17: LEI | F17: KBI FUND ICAV -KBI ENERGY SOL | G17: IE00BNGJJ156 | H17: ISIN | I17: מניות | J17: חו"ל | K17: גלובלי | L17: סחיר | M17: ISE | N17: Equity Funds | O17: לא | P17: USD | Q17: 3284.78 | R17: 3.681 | S17: 978.2 | T17: 118.277 | U17: 0.00026 | V17: 0.13074817 | W17: 0.0040852784
A18: 12904 | B18: 12905 | C18: Kotak | D18: 549300P1V22EKK1UCL34 | E18: LEI | F18: KOTAK FDS-INDIA MIDCAP (S) USD A | G18: LU2126068639 | H18: ISIN | I18: מניות | J18: חו"ל | K18: לוכסמבורג | L18: סחיר | M18: אחר | N18: Equity Funds | O18: לא | P18: USD | Q18: 837.01 | R18: 3.681 | S18: 1294.89 | T18: 39.896 | U18: 0 | V18: 0.044102702 | W18: 0.0013780064
A19: 12904 | B19: 12905 | C19: Lombard Odier Funds-Asia Value | D19: 5493001DJ8NYPLGGID75 | E19: LEI | F19: LOMBARD ODIER-ASIA INV.GR.BD(I | G19: LU2083909536 | H19: ISIN | I19: מניות | J19: חו"ל | K19: אסיה | L19: סחיר | M19: אחר | N19: Equity Funds | O19: לא | P19: USD | Q19: 2233.18 | R19: 3.681 | S19: 1045.75 | T19: 85.964 | U19: 0 | V19: 0.09502837 | W19: 0.0029691991
A20: 12904 | B20: 12905 | D20: GZYUYYBVN9JCLNYWZ615 | E20: LEI | F20: MGLEUCA LX Equity | G20: LU1670632501 | H20: ISIN | I20: אחר | J20: חו"ל | K20: גלובלי | L20: סחיר | M20: אחר | N20: Other | O20: לא | P20: USD | Q20: 4425.79 | R20: 3.681 | S20: 1199.66 | T20: 195.441 | U20: 0 | V20: 0.2160482 | W20: 0.0067505117
A21: 12904 | B21: 12905 | C21: PRINCIPAL FINANCIAL | D21: 549300MS0GBEZOTILG43 | E21: LEI | F21: PRINCIPAL GLOBAL INVEST | G21: IE00BKDW9G15 | H21: ISIN | I21: אג"ח קונצרני | J21: חו"ל | K21: אירלנד | L21: סחיר | M21: ISE | N21: Bond/Fixed Income Funds | O21: לא | P21: USD | Q21: 4761.21 | R21: 3.681 | S21: 1131.82 | T21: 198.363 | U21: 0.000193 | V21: 0.21927867 | W21: 0.0068514487
A22: 12904 | B22: 13680 | C22: Invesco investment management limited | D22: 635400KFAN415FMIGG54 | E22: LEI | F22: IUSSENG LX Equity | G22: LU0564079282 | H22: ISIN | I22: אג"ח קונצרני | J22: חו"ל | K22: גלובלי | L22: סחיר | M22: ISE | N22: Bond/Fixed Income Funds | O22: לא | P22: USD | Q22: 96.84 | R22: 3.681 | S22: 17736 | T22: 63.223 | U22: 1.1e-05 | V22: 0.14942309 | W22: 0.0021614619
A23: 12904 | B23: 13680 | C23: KBI Global Investors | D23: 635400UCQYVGO94KDT51 | E23: LEI | F23: KBI FUND ICAV -KBI ENERGY SOL | G23: IE00BNGJJ156 | H23: ISIN | I23: מניות | J23: חו"ל | K23: גלובלי | L23: סחיר | M23: ISE | N23: Equity Funds | O23: לא | P23: USD | Q23: 4112.51 | R23: 3.681 | S23: 978.2 | T23: 148.081 | U23: 0.000326 | V23: 0.3499789 | W23: 0.0050625782
A24: 12904 | B24: 13680 | C24: Kotak | D24: 549300P1V22EKK1UCL34 | E24: LEI | F24: KOTAK FDS-INDIA MIDCAP (S) USD A | G24: LU2126068639 | H24: ISIN | I24: מניות | J24: חו"ל | K24: לוכסמבורג | L24: סחיר | M24: אחר | N24: Equity Funds | O24: לא | P24: USD | Q24: 2875.47 | R24: 3.681 | S24: 1294.89 | T24: 137.059 | U24: 0 | V24: 0.32392835 | W24: 0.004685747
A25: 12904 | B25: 13680 | C25: Lombard Odier Funds-Asia Value | D25: 5493001DJ8NYPLGGID75 | E25: LEI | F25: LOMBARD ODIER-ASIA INV.GR.BD(I | G25: LU2083909536 | H25: ISIN | I25: מניות | J25: חו"ל | K25: אסיה | L25: סחיר | M25: אחר | N25: Equity Funds | O25: לא | P25: USD | Q25: 1941.9 | R25: 3.681 | S25: 1045.75 | T25: 74.752 | U25: 0 | V25: 0.17666966 | W25: 0.002555594
A26: 424 | B26: 7228 | C26: Comgest | D26: 635400JYB1RHBTRDH390 | E26: LEI | F26: COMGEST GROWTH PLC - EURO | G26: IE0004766675 | H26: ISIN | I26: מניות | J26: חו"ל | K26: אירופה | L26: סחיר | M26: ISE | N26: Equity Funds | O26: לא | P26: EUR | Q26: 54973.29 | R26: 3.979 | S26: 5063 | T26: 11075.02 | U26: 0.002012 | V26: 0.11644732 | W26: 0.0047789113
A27: 424 | B27: 7228 | C27: Investec | D27: 549300X3ENFKGMH04N42 | E27: LEI | F27: IGS-EMERG MKT CORP DEBT-IUSD | G27: LU0611395327 | H27: ISIN | I27: אג"ח קונצרני | J27: חו"ל | K27: לוכסמבורג | L27: סחיר | M27: אחר | N27: Bond/Fixed Income Funds | O27: לא | P27: USD | Q27: 71123.75 | R27: 3.681 | S27: 3303 | T27: 8647.469 | U27: 0.001641 | V27: 0.090923055 | W27: 0.0037314145
A28: 424 | B28: 7228 | C28: Invesco investment management limited | D28: 635400KFAN415FMIGG54 | E28: LEI | F28: IUSSENG LX Equity | G28: LU0564079282 | H28: ISIN | I28: אג"ח קונצרני | J28: חו"ל | K28: גלובלי | L28: סחיר | M28: ISE | N28: Bond/Fixed Income Funds | O28: לא | P28: USD | Q28: 17090.12 | R28: 3.681 | S28: 17736 | T28: 11157.493 | U28: 0.001875 | V28: 0.11731447 | W28: 0.0048144987
A29: 424 | B29: 7228 | C29: KBI Global Investors | D29: 635400UCQYVGO94KDT51 | E29: LEI | F29: KBI FUND ICAV -KBI ENERGY SOL | G29: IE00BNGJJ156 | H29: ISIN | I29: מניות | J29: חו"ל | K29: גלובלי | L29: סחיר | M29: ISE | N29: Equity Funds | O29: לא | P29: USD | Q29: 349645.04 | R29: 3.681 | S29: 978.2 | T29: 12589.858 | U29: 0.027677 | V29: 0.13237496 | W29: 0.0054325697
A30: 424 | B30: 7228 | C30: Kotak | D30: 549300P1V22EKK1UCL34 | E30: LEI | F30: KOTAK FDS-INDIA MIDCAP (S) USD A | G30: LU2126068639 | H30: ISIN | I30: מניות | J30: חו"ל | K30: לוכסמבורג | L30: סחיר | M30: אחר | N30: Equity Funds | O30: לא | P30: USD | Q30: 262821.98 | R30: 3.681 | S30: 1294.89 | T30: 12527.384 | U30: 0 | V30: 0.13171807 | W30: 0.0054056116
A31: 424 | B31: 7228 | C31: Lombard Odier Funds-Asia Value | D31: 5493001DJ8NYPLGGID75 | E31: LEI | F31: LOMBARD ODIER-ASIA INV.GR.BD(I | G31: LU2083909536 | H31: ISIN | I31: מניות | J31: חו"ל | K31: אסיה | L31: סחיר | M31: אחר | N31: Equity Funds | O31: לא | P31: USD | Q31: 174770.86 | R31: 3.681 | S31: 1045.75 | T31: 6727.64 | U31: 0 | V31: 0.070737172 | W31: 0.0029030009
A32: 424 | B32: 7228 | C32: LUXEMBOURG LIFE | D32: 89900 | E32: פנימי | F32: LUXEMBOURG LIFE | G32: lu24283023721 | H32: ISIN | I32: מניות | J32: חו"ל | K32: ארה"ב | L32: סחיר | M32: אחר | N32: Equity Funds | O32: לא | P32: USD | Q32: 10000 | R32: 3.681 | S32: 11473 | T32: 4223.211 | U32: 0 | V32: 0.044404582 | W32: 0.001822331
A33: 424 | B33: 7228 | D33: GZYUYYBVN9JCLNYWZ615 | E33: LEI | F33: MGLEUCA LX Equity | G33: LU1670632501 | H33: ISIN | I33: אחר | J33: חו"ל | K33: גלובלי | L33: סחיר | M33: אחר | N33: Other | O33: לא | P33: USD | Q33: 211763.91 | R33: 3.681 | S33: 1199.66 | T33: 9351.385 | U33: 0 | V33: 0.098324314 | W33: 0.0040351567
A34: 424 | B34: 7228 | C34: PRINCIPAL FINANCIAL | D34: 549300MS0GBEZOTILG43 | E34: LEI | F34: PRINCIPAL GLOBAL INVEST | G34: IE00BKDW9G15 | H34: ISIN | I34: אג"ח קונצרני | J34: חו"ל | K34: אירלנד | L34: סחיר | M34: ISE | N34: Bond/Fixed Income Funds | O34: לא | P34: USD | Q34: 451441.67 | R34: 3.681 | S34: 1131.82 | T34: 18808.096 | U34: 0.018281 | V34: 0.19775606 | W34: 0.0081157617
A35: 424 | B35: 7229 | C35: Investec | D35: 549300X3ENFKGMH04N42 | E35: LEI | F35: IGS-EMERG MKT CORP DEBT-IUSD | G35: LU0611395327 | H35: ISIN | I35: אג"ח קונצרני | J35: חו"ל | K35: לוכסמבורג | L35: סחיר | M35: אחר | N35: Bond/Fixed Income Funds | O35: לא | P35: USD | Q35: 6543.38 | R35: 3.681 | S35: 3303 | T35: 795.567 | U35: 0.000151 | V35: 0.13539962 | W35: 0.005549661
A36: 424 | B36: 7229 | C36: Invesco investment management limited | D36: 635400KFAN415FMIGG54 | E36: LEI | F36: IUSSENG LX Equity | G36: LU0564079282 | H36: ISIN | I36: אג"ח קונצרני | J36: חו"ל | K36: גלובלי | L36: סחיר | M36: ISE | N36: Bond/Fixed Income Funds | O36: לא | P36: USD | Q36: 541.19 | R36: 3.681 | S36: 17736 | T36: 353.322 | U36: 5.9e-05 | V36: 0.060132905 | W36: 0.0024646836
A37: 424 | B37: 7229 | C37: KBI Global Investors | D37: 635400UCQYVGO94KDT51 | E37: LEI | F37: KBI FUND ICAV -KBI ENERGY SOL | G37: IE00BNGJJ156 | H37: ISIN | I37: מניות | J37: חו"ל | K37: גלובלי | L37: סחיר | M37: ISE | N37: Equity Funds | O37: לא | P37: USD | Q37: 28821.46 | R37: 3.681 | S37: 978.2 | T37: 1037.79 | U37: 0.002281 | V37: 0.17662427 | W37: 0.0072393467
A38: 424 | B38: 7229 | C38: Kotak | D38: 549300P1V22EKK1UCL34 | E38: LEI | F38: KOTAK FDS-INDIA MIDCAP (S) USD A | G38: LU2126068639 | H38: ISIN | I38: מניות | J38: חו"ל | K38: לוכסמבורג | L38: סחיר | M38: אחר | N38: Equity Funds | O38: לא | P38: USD | Q38: 1177.04 | R38: 3.681 | S38: 1294.89 | T38: 56.103 | U38: 0 | V38: 0.0095484051 | W38: 0.00039136307
A39: 424 | B39: 7229 | C39: Lombard Odier Funds-Asia Value | D39: 5493001DJ8NYPLGGID75 | E39: LEI | F39: LOMBARD ODIER-ASIA INV.GR.BD(I | G39: LU2083909536 | H39: ISIN | I39: מניות | J39: חו"ל | K39: אסיה | L39: סחיר | M39: אחר | N39: Equity Funds | O39: לא | P39: USD | Q39: 11165.92 | R39: 3.681 | S39: 1045.75 | T39: 429.822 | U39: 0 | V39: 0.073152492 | W39: 0.002998321
A40: 424 | B40: 7229 | D40: GZYUYYBVN9JCLNYWZ615 | E40: LEI | F40: MGLEUCA LX Equity | G40: LU1670632501 | H40: ISIN | I40: אחר | J40: חו"ל | K40: גלובלי | L40: סחיר | M40: אחר | N40: Other | O40: לא | P40: USD | Q40: 26395.85 | R40: 3.681 | S40: 1199.66 | T40: 1165.627 | U40: 0 | V40: 0.19838123 | W40: 0.008131105
A41: 424 | B41: 7229 | C41: PRINCIPAL FINANCIAL | D41: 549300MS0GBEZOTILG43 | E41: LEI | F41: PRINCIPAL GLOBAL INVEST | G41: IE00BKDW9G15 | H41: ISIN | I41: אג"ח קונצרני | J41: חו"ל | K41: אירלנד | L41: סחיר | M41: ISE | N41: Bond/Fixed Income Funds | O41: לא | P41: USD | Q41: 48904.21 | R41: 3.681 | S41: 1131.82 | T41: 2037.462 | U41: 0.00198 | V41: 0.34676108 | W41: 0.01421279
A42: 424 | B42: 9817 | C42: מגדל קרנות נאמנות בע"מ | D42: 511303661 | E42: ח.פ | F42: מחקה תל-דיב FTM | G42: IL0051370133 | H42: ISIN | I42: מניות | J42: ישראל | K42: ישראל | L42: סחיר | M42: TASE | N42: מניות בישראל | O42: לא | P42: ILS | Q42: 590 | R42: 1 | S42: 2914.49 | T42: 17.195 | U42: 0 | V42: 1 | W42: 0.011853978
A43: 969 | B43: 969 | C43: Investec | D43: 549300X3ENFKGMH04N42 | E43: LEI | F43: IGS-EMERG MKT CORP DEBT-IUSD | G43: LU0611395327 | H43: ISIN | I43: אג"ח קונצרני | J43: חו"ל | K43: לוכסמבורג | L43: סחיר | M43: אחר | N43: Bond/Fixed Income Funds | O43: לא | P43: USD | Q43: 3129.44 | R43: 3.681 | S43: 3303 | T43: 380.488 | U43: 7.2e-05 | V43: 0.11214871 | W43: 0.0051804217
A44: 969 | B44: 969 | C44: Invesco investment management limited | D44: 635400KFAN415FMIGG54 | E44: LEI | F44: IUSSENG LX Equity | G44: LU0564079282 | H44: ISIN | I44: אג"ח קונצרני | J44: חו"ל | K44: גלובלי | L44: סחיר | M44: ISE | N44: Bond/Fixed Income Funds | O44: לא | P44: USD | Q44: 552.58 | R44: 3.681 | S44: 17736 | T44: 360.759 | U44: 6.1e-05 | V44: 0.10633345 | W44: 0.0049118009
A45: 969 | B45: 969 | C45: KBI Global Investors | D45: 635400UCQYVGO94KDT51 | E45: LEI | F45: KBI FUND ICAV -KBI ENERGY SOL | G45: IE00BNGJJ156 | H45: ISIN | I45: מניות | J45: חו"ל | K45: גלובלי | L45: סחיר | M45: ISE | N45: Equity Funds | O45: לא | P45: USD | Q45: 13191.1 | R45: 3.681 | S45: 978.2 | T45: 474.979 | U45: 0.001044 | V45: 0.1399999 | W45: 0.0064669362
A46: 969 | B46: 969 | C46: Kotak | D46: 549300P1V22EKK1UCL34 | E46: LEI | F46: KOTAK FDS-INDIA MIDCAP (S) USD A | G46: LU2126068639 | H46: ISIN | I46: מניות | J46: חו"ל | K46: לוכסמבורג | L46: סחיר | M46: אחר | N46: Equity Funds | O46: לא | P46: USD | Q46: 10462.65 | R46: 3.681 | S46: 1294.89 | T46: 498.701 | U46: 0 | V46: 0.14699198 | W46: 0.0067899173
A47: 969 | B47: 969 | C47: Lombard Odier Funds-Asia Value | D47: 5493001DJ8NYPLGGID75 | E47: LEI | F47: LOMBARD ODIER-ASIA INV.GR.BD(I | G47: LU2083909536 | H47: ISIN | I47: מניות | J47: חו"ל | K47: אסיה | L47: סחיר | M47: אחר | N47: Equity Funds | O47: לא | P47: USD | Q47: 5825.7 | R47: 3.681 | S47: 1045.75 | T47: 224.255 | U47: 0 | V47: 0.066099025 | W47: 0.0030532748
A48: 969 | B48: 969 | D48: GZYUYYBVN9JCLNYWZ615 | E48: LEI | F48: MGLEUCA LX Equity | G48: LU1670632501 | H48: ISIN | I48: אחר | J48: חו"ל | K48: גלובלי | L48: סחיר | M48: אחר | N48: Other | O48: לא | P48: USD | Q48: 11740 | R48: 3.681 | S48: 1199.66 | T48: 518.432 | U48: 0 | V48: 0.15280774 | W48: 0.0070585612
A49: 969 | B49: 969 | C49: PRINCIPAL FINANCIAL | D49: 549300MS0GBEZOTILG43 | E49: LEI | F49: PRINCIPAL GLOBAL INVEST | G49: IE00BKDW9G15 | H49: ISIN | I49: אג"ח קונצרני | J49: חו"ל | K49: אירלנד | L49: סחיר | M49: ISE | N49: Bond/Fixed Income Funds | O49: לא | P49: USD | Q49: 22444.66 | R49: 3.681 | S49: 1131.82 | T49: 935.096 | U49: 0.000909 | V49: 0.2756192 | W49: 0.012731521

Sheet כתבי אופציה
A1: מספר קופה/קרן/ח.פ. עבור חברת ביטוח | B1: מספר מסלול | C1: שם מנפיק | D1: מספר מנפיק | E1: סוג מספר מזהה מנפיק | F1: שם נייר ערך | G1: מספר נייר ערך | H1: סוג מספר נייר ערך | I1: ישראל/חו"ל | J1: מדינה לפי חשיפה כלכלית | K1: סטאטוס סחירות | L1: זירת מסחר | M1: נכס בסיס (כתב אופציה) | N1: ענף מסחר | O1: תאריך פקיעה | P1: בעל עניין/צד קשור | Q1: מטבע פעילות | R1: שער מימוש | S1: יחס המרה | T1: ערך נקוב (יחידות) | U1: שער חליפין | V1: שער נייר הערך | W1: שווי הוגן (באלפי ש"ח) | X1: שיעור מנכסי אפיק ההשקעה | Y1: שיעור מסך נכסי ההשקעה
A2: 1182 | B2: 1182 | C2: סיפיה ווז'ן בע"מ | D2: 513476010 | E2: ח.פ | F2: סיפיה אופציה 1 | G2: IL0011820052 | H2: ISIN | I2: ישראל | J2: ישראל | K2: סחיר | L2: TASE | M2: אחר | N2: תוכנה ואינטרנט | O2: 18/11/2024 | P2: לא | Q2: ILS | R2: 0 | S2: 0 | T2: 18000 | U2: 1 | V2: 12.5 | W2: 2.25 | X2: 0.66276601 | Y2: 5.9235123e-06
A3: 1182 | B3: 1182 | C3: ריט אזורים - ה.פ ליווינג בע"מ | D3: 516117181 | E3: ח.פ | F3: ריט אזורים אפ 1 | G3: IL0012010117 | H3: ISIN | I3: ישראל | J3: ישראל | K3: סחיר | L3: TASE | M3: מניות לרבות מדדי מניות | N3: נדל"ן מניב בישראל | O3: 31/12/2024 | P3: לא | Q3: ILS | R3: 550 | S3: 0 | T3: 4489.66 | U3: 1 | V3: 25.5 | W3: 1.145 | X3: 0.33723399 | Y3: 3.0140497e-06
A4: 424 | B4: 7228 | C4: סיפיה ווז'ן בע"מ | D4: 513476010 | E4: ח.פ | F4: סיפיה אופציה 1 | G4: IL0011820052 | H4: ISIN | I4: ישראל | J4: ישראל | K4: סחיר | L4: TASE | M4: אחר | N4: תוכנה ואינטרנט | O4: 18/11/2024 | P4: לא | Q4: ILS | R4: 0 | S4: 0 | T4: 162225 | U4: 1 | V4: 12.5 | W4: 20.278 | X4: 0.66003845 | Y4: 8.7500847e-06
A5: 424 | B5: 7228 | C5: ריט אזורים - ה.פ ליווינג בע"מ | D5: 516117181 | E5: ח.פ | F5: ריט אזורים אפ 1 | G5: IL0012010117 | H5: ISIN | I5: ישראל | J5: ישראל | K5: סחיר | L5: TASE | M5: מניות לרבות מדדי מניות | N5: נדל"ן מניב בישראל | O5: 31/12/2024 | P5: לא | Q5: ILS | R5: 550 | S5: 0 | T5: 40958.89 | U5: 1 | V5: 25.5 | W5: 10.445 | X5: 0.33996155 | Y5: 4.5068471e-06
A6: 424 | B6: 7229 | C6: סיפיה ווז'ן בע"מ | D6: 513476010 | E6: ח.פ | F6: סיפיה אופציה 1 | G6: IL0011820052 | H6: ISIN | I6: ישראל | J6: ישראל | K6: סחיר | L6: TASE | M6: אחר | N6: תוכנה ואינטרנט | O6: 18/11/2024 | P6: לא | Q6: ILS | R6: 0 | S6: 0 | T6: 7200 | U6: 1 | V6: 12.5 | W6: 0.9 | X6: 1 | Y6: 6.2781607e-06
A7: 424 | B7: 9817 | C7: ריט אזורים - ה.פ ליווינג בע"מ | D7: 516117181 | E7: ח.פ | F7: ריט אזורים אפ 1 | G7: IL0012010117 | H7: ISIN | I7: ישראל | J7: ישראל | K7: סחיר | L7: TASE | M7: מניות לרבות מדדי מניות | N7: נדל"ן מניב בישראל | O7: 31/12/2024 | P7: לא | Q7: ILS | R7: 550 | S7: 0 | T7: 40.81 | U7: 1 | V7: 25.5 | W7: 0.01 | X7: 1 | Y7: 7.1739162e-06
A8: 969 | B8: 969 | C8: סיפיה ווז'ן בע"מ | D8: 513476010 | E8: ח.פ | F8: סיפיה אופציה 1 | G8: IL0011820052 | H8: ISIN | I8: ישראל | J8: ישראל | K8: סחיר | L8: TASE | M8: אחר | N8: תוכנה ואינטרנט | O8: 18/11/2024 | P8: לא | Q8: ILS | R8: 0 | S8: 0 | T8: 7200 | U8: 1 | V8: 12.5 | W8: 0.9 | X8: 0.59530637 | Y8: 1.2253682e-05
A9: 969 | B9: 969 | C9: ריט אזורים - ה.פ ליווינג בע"מ | D9: 516117181 | E9: ח.פ | F9: ריט אזורים אפ 1 | G9: IL0012010117 | H9: ISIN | I9: ישראל | J9: ישראל | K9: סחיר | L9: TASE | M9: מניות לרבות מדדי מניות | N9: נדל"ן מניב בישראל | O9: 31/12/2024 | P9: לא | Q9: ILS | R9: 550 | S9: 0 | T9: 2399.32 | U9: 1 | V9: 25.5 | W9: 0.612 | X9: 0.40469363 | Y9: 8.3301428e-06

Sheet אופציות
A1: מספר קופה/קרן/ח.פ. עבור חברת ביטוח | B1: מספר מסלול | C1: שם מנפיק | D1: מספר מנפיק | E1: סוג מספר מזהה מנפיק | F1: שם נייר ערך | G1: מספר נייר ערך | H1: סוג מספר נייר ערך | I1: מאפיין עיקרי | J1: ישראל/חו"ל | K1: מדינה לפי חשיפה כלכלית | L1: זירת מסחר | M1: ענף מסחר | N1: נכס בסיס | O1: תאריך פקיעה | P1: בעל עניין/צד קשור | Q1: מטבע פעילות | R1: שער מימוש | S1: ערך נקוב (יחידות) | T1: שער חליפין | U1: שער נייר הערך | V1: שווי הוגן (באלפי ש"ח) | W1: שיעור מנכסי אפיק ההשקעה | X1: שיעור מסך נכסי ההשקעה

Sheet חוזים עתידיים
A1: מספר קופה/קרן/ח.פ. עבור חברת ביטוח | B1: מספר מסלול | C1: שם מנפיק | D1: מספר מנפיק | E1: סוג מספר מזהה מנפיק | F1: שם נייר ערך | G1: מספר נייר ערך | H1: סוג מספר נייר ערך | I1: ישראל/חו"ל | J1: מדינה לפי חשיפה כלכלית | K1: זירת מסחר | L1: נכס בסיס | M1: בעל עניין/צד קשור | N1: מטבע פעילות | O1: ערך נקוב (יחידות) | P1: שער חליפין | Q1: שער נייר הערך | R1: שווי הוגן (באלפי ש"ח) | S1: שיעור מנכסי אפיק ההשקעה | T1: שיעור מסך נכסי ההשקעה
A2: 1182 | B2: 1182 | C2: חוזים עתידיים בחול | D2: 10527 | E2: פנימי | F2: ESM4_S&P 500 EMINI FUT JUN24 | G2: ESM4 | H2: אחר | I2: חו"ל | J2: ארה"ב | K2: NASDAQD | L2: מניות לרבות מדדי מניות | M2: לא | N2: USD | O2: 35 | P2: 3.681 | Q2: 5308.5 | R2: 744.666 | S2: 0.96666483 | T2: 0.0019604622
A3: 1182 | B3: 1182 | C3: חוזים עתידיים בחול | D3: 10527 | E3: פנימי | F3: NQM4_NASDAQ 100 E-MINI JUN24 | G3: NQM4 | H3: אחר | I3: חו"ל | J3: ארה"ב | K3: NASDAQD | L3: מניות לרבות מדדי מניות | M3: לא | N3: USD | O3: 2 | P3: 3.681 | Q3: 18475 | R3: 25.68 | S3: 0.033335171 | T3: 6.7606002e-05
A4: 1182 | B4: 14769 | C4: חוזים עתידיים בחול | D4: 10527 | E4: פנימי | F4: ESM4_S&P 500 EMINI FUT JUN24 | G4: ESM4 | H4: אחר | I4: חו"ל | J4: ארה"ב | K4: NASDAQD | L4: מניות לרבות מדדי מניות | M4: לא | N4: USD | O4: 1 | P4: 3.681 | Q4: 5308.5 | R4: 21.276 | S4: 1 | T4: 0.0027272956
A5: 12904 | B5: 12905 | C5: חוזים עתידיים בחול | D5: 10527 | E5: פנימי | F5: ESM4_S&P 500 EMINI FUT JUN24 | G5: ESM4 | H5: אחר | I5: חו"ל | J5: ארה"ב | K5: NASDAQD | L5: מניות לרבות מדדי מניות | M5: לא | N5: USD | O5: 1 | P5: 3.681 | Q5: 5308.5 | R5: 21.276 | S5: 1 | T5: 0.00073487851
A6: 12904 | B6: 13680 | C6: חוזים עתידיים בחול | D6: 10527 | E6: פנימי | F6: ESM4_S&P 500 EMINI FUT JUN24 | G6: ESM4 | H6: אחר | I6: חו"ל | J6: ארה"ב | K6: NASDAQD | L6: מניות לרבות מדדי מניות | M6: לא | N6: USD | O6: 2 | P6: 3.681 | Q6: 5308.5 | R6: 42.552 | S6: 0.76820176 | T6: 0.0014547721
A7: 12904 | B7: 13680 | C7: חוזים עתידיים בחול | D7: 10527 | E7: פנימי | F7: NQM4_NASDAQ 100 E-MINI JUN24 | G7: NQM4 | H7: אחר | I7: חו"ל | J7: ארה"ב | K7: NASDAQD | L7: מניות לרבות מדדי מניות | M7: לא | N7: USD | O7: 1 | P7: 3.681 | Q7: 18475 | R7: 12.84 | S7: 0.23179824 | T7: 0.00043896489
A8: 424 | B8: 7228 | C8: חוזים עתידיים בחול | D8: 10527 | E8: פנימי | F8: ESM4_S&P 500 EMINI FUT JUN24 | G8: ESM4 | H8: אחר | I8: חו"ל | J8: ארה"ב | K8: NASDAQD | L8: מניות לרבות מדדי מניות | M8: לא | N8: USD | O8: 257 | P8: 3.681 | Q8: 5308.5 | R8: 5467.978 | S8: 0.96213617 | T8: 0.0023594525
A9: 424 | B9: 7228 | C9: חוזים עתידיים בחול | D9: 10527 | E9: פנימי | F9: NQM4_NASDAQ 100 E-MINI JUN24 | G9: NQM4 | H9: אחר | I9: חו"ל | J9: ארה"ב | K9: NASDAQD | L9: מניות לרבות מדדי מניות | M9: לא | N9: USD | O9: 9 | P9: 3.681 | Q9: 18475 | R9: 115.558 | S9: 0.020333435 | T9: 4.9863809e-05
A10: 424 | B10: 7228 | C10: חוזים עתידיים בחול | D10: 10527 | E10: פנימי | F10: US 10 YR ULTRA FUT JUN24 | G10: UXYM4 | H10: אחר | I10: חו"ל | J10: ארה"ב | K10: אחר | L10: מניות לרבות מדדי מניות | M10: לא | N10: USD | O10: 55 | P10: 3.681 | Q10: 114.609 | R10: 99.628 | S10: 0.017530392 | T10: 4.298989e-05
A11: 424 | B11: 7229 | C11: חוזים עתידיים בחול | D11: 10527 | E11: פנימי | F11: ESM4_S&P 500 EMINI FUT JUN24 | G11: ESM4 | H11: אחר | I11: חו"ל | J11: ארה"ב | K11: NASDAQD | L11: מניות לרבות מדדי מניות | M11: לא | N11: USD | O11: 6 | P11: 3.681 | Q11: 5308.5 | R11: 127.657 | S11: 1 | T11: 0.00089050185
A12: 969 | B12: 969 | C12: חוזים עתידיים בחול | D12: 10527 | E12: פנימי | F12: ESM4_S&P 500 EMINI FUT JUN24 | G12: ESM4 | H12: אחר | I12: חו"ל | J12: ארה"ב | K12: NASDAQD | L12: מניות לרבות מדדי מניות | M12: לא | N12: USD | O12: 7 | P12: 3.681 | Q12: 5308.5 | R12: 148.933 | S12: 1 | T12: 0.0020277564

Sheet מוצרים מובנים
A1: מספר קופה/קרן/ח.פ. עבור חברת ביטוח | B1: מספר מסלול | C1: שם מנפיק | D1: מספר מנפיק | E1: סוג מספר מזהה מנפיק | F1: שם נייר ערך | G1: מספר נייר ערך | H1: סוג מספר נייר ערך | I1: מאפיין עיקרי | J1: ישראל/חו"ל | K1: מדינה לפי חשיפה כלכלית | L1: סטאטוס סחירות | M1: זירת מסחר | N1: נכס בסיס | O1: בעל עניין/צד קשור | P1: מח"מ | Q1: שיעור ריבית | R1: תשואה לפדיון | S1: דירוג | T1: שם מדרג | U1: דירוג נייר הערך/המנפיק | V1: מטבע פעילות | W1: ערך נקוב (יחידות) | X1: שער חליפין | Y1: שער נייר הערך | Z1: שווי הוגן (באלפי ש"ח) | AA1: שיעור מנכסי אפיק ההשקעה | AB1: שיעור מסך נכסי ההשקעה

Sheet לא סחיר איגרות חוב ממשלתיות
A1: מספר קופה/קרן/ח.פ. עבור חברת ביטוח | B1: מספר מסלול | C1: שם מנפיק | D1: שם נייר ערך | E1: מספר נייר ערך | F1: סוג מספר נייר ערך | G1: מאפיין עיקרי | H1: ישראל/חו"ל | I1: מדינה לפי חשיפה כלכלית | J1: תאריך רכישה | K1: דירוג | L1: שם מדרג | M1: מטבע פעילות | N1: מח"מ | O1: מועד פדיון | P1: שיעור ריבית | Q1: תשואה לפדיון | R1: ערך נקוב (יחידות) | S1: שער חליפין | T1: שער נייר הערך | U1: שווי הוגן (באלפי ש"ח) | V1: עלות מופחתת (באלפי ש"ח) | W1: השיטה שיושמה בדוח הכספי | X1: שיעור מנכסי אפיק ההשקעה | Y1: שיעור מסך נכסי ההשקעה

Sheet לא סחיר איגרות חוב מיועדות
A1: מספר קופה/קרן/ח.פ. עבור חברת ביטוח | B1: מספר מסלול | C1: מאפיין עיקרי | D1: שם נייר ערך | E1: מספר נייר ערך | F1: תאריך רכישה | G1: מח"מ | H1: סוג הצמדה | I1: מועד פדיון | J1: שיעור ריבית | K1: תשואה לפדיון | L1: ערך נקוב (יחידות) | M1: שער נייר הערך | N1: שווי הוגן (באלפי ש"ח) | O1: עלות מופחתת (באלפי ש"ח) | P1: השיטה שיושמה בדוח הכספי | Q1: שיעור מנכסי אפיק ההשקעה | R1: שיעור מסך נכסי ההשקעה

Sheet אפיק השקעה מובטח תשואה
A1: מספר קרן | B1: מספר מסלול | C1: מאפיין עיקרי | D1: חודש הנפקת שכבה | E1: חודש הבדיקה | F1: שווי הנכסים באפיק (באלפי ש"ח) | G1: שיעור מסך נכסי ההשקעה

Sheet לא סחיר ניירות ערך מסחריים
A1: מספר קופה/קרן/ח.פ. עבור חברת ביטוח | B1: מספר מסלול | C1: שם מנפיק | D1: מספר מנפיק | E1: סוג מספר מזהה מנפיק | F1: שם נייר ערך | G1: מספר נייר ערך | H1: סוג מספר נייר ערך | I1: מאפיין עיקרי | J1: ישראל/חו"ל | K1: מדינה לפי חשיפה כלכלית | L1: ענף מסחר | M1: בעל עניין/צד קשור | N1: תאריך רכישה | O1: דירוג | P1: שם מדרג | Q1: דירוג נייר הערך/המנפיק | R1: מטבע פעילות | S1: מח"מ | T1: סוג הצמדה | U1: ריבית עוגן | V1: מועד פדיון | W1: שיעור ריבית | X1: תשואה לפדיון | Y1: נחיתות חוזית | Z1: האם סווג כחוב בעייתי | AA1: סוג גורם משערך | AB1: תלות/אי-תלות המשערך | AC1: שם גורם משערך | AD1: תאריך שערוך אחרון | AE1: תאריך אחרון בו נבחנה בפועל ירידת ערך | AF1: ערך נקוב (יחידות) | AG1: שער חליפין | AH1: שער נייר הערך | AI1: שווי הוגן (באלפי ש"ח) | AJ1: עלות מופחתת (באלפי ש"ח) | AK1: עלות מופחתת (במטבע הפעילות) | AL1: השיטה שיושמה בדוח הכספי | AM1: שיעור מנכסי אפיק ההשקעה | AN1: שיעור מסך נכסי ההשקעה

Sheet לא סחיר איגרות חוב
A1: מספר קופה/קרן/ח.פ. עבור חברת ביטוח | B1: מספר מסלול | C1: שם מנפיק | D1: מספר מנפיק | E1: סוג מספר מזהה מנפיק | F1: שם נייר ערך | G1: מספר נייר ערך | H1: סוג מספר נייר ערך | I1: מאפיין עיקרי | J1: ישראל/חו"ל | K1: מדינה לפי חשיפה כלכלית | L1: סטאטוס סחירות | M1: ענף מסחר | N1: בעל עניין/צד קשור | O1: תאריך רכישה | P1: דירוג | Q1: שם מדרג | R1: דירוג נייר הערך/המנפיק | S1: מטבע פעילות | T1: מח"מ | U1: מועד פדיון | V1: תשואה לפדיון | W1: שיעור ריבית | X1: נחיתות חוזית | Y1: האם סווג כחוב בעייתי | Z1: סוג גורם משערך | AA1: תלות/אי-תלות המשערך | AB1: תאריך שערוך אחרון | AC1: תאריך אחרון בו נבחנה בפועל ירידת ערך | AD1: ערך נקוב (יחידות) | AE1: שער חליפין | AF1: שער נייר הערך | AG1: שווי הוגן (באלפי ש"ח) | AH1: עלות מופחתת (באלפי ש"ח) | AI1: עלות מופחתת (במטבע הפעילות) | AJ1: השיטה שיושמה בדוח הכספי | AK1: שיעור מנכסי אפיק ההשקעה | AL1: שיעור מסך נכסי ההשקעה
A2: 1182 | B2: 1182 | C2: דוראה השקעות ופיתוח בע"מ | D2: 520038282 | E2: ח.פ | F2: 5.15% 2015 'דוראה סדרה ד | G2: IL0037201170 | H2: ISIN | I2: צמוד למדד המחירים לצרכן | J2: ישראל | K2: ישראל | L2: אחר | M2: בנייה | N2: לא | P2: N/R | Q2: אחר | R2: מנפיק | S2: ILS | T2: 0.01 | U2: 28/02/2015 | V2: 0 | W2: 0.0515 | X2: החוב לא נחות | Y2: לא | Z2: אחר | AB2: 31/03/2020 | AD2: 13377 | AE2: 1 | AF2: 0 | AG2: 0 | AJ2: שווי הוגן | AK2: 1.9232378e-08 | AL2: 3.5217255e-11
A3: 1182 | B3: 1182 | C3: אאורה השקעות בע"מ | D3: 520038274 | E3: ח.פ | F3: אאורה סדרה 1 21/12 %6 (החלפת א-ד)חש | G3: IL0037302986 | H3: ISIN | I3: צמוד למדד המחירים לצרכן | J3: ישראל | K3: ישראל | L3: אחר | M3: בנייה | N3: לא | O3: 29/06/2023 | P3: D | Q3: S&P מעלות | R3: נייר ערך | S3: ILS | T3: 0.01 | U3: 24/09/2015 | V3: 0.0019 | W3: 0.02 | X3: החוב לא נחות | Y3: לא | Z3: אחר | AB3: 31/03/2024 | AD3: 3767.71 | AE3: 1 | AF3: 13 | AG3: 0.49 | AJ3: שווי הוגן | AK3: 0.00070419848 | AL3: 1.2894889e-06
A4: 1182 | B4: 1182 | C4: אולימפיה החזקות נדל"ן בע"מ | D4: 520035155 | E4: ח.פ | F4: אולימפיה אג"ח ב' | G4: IL0017900544 | H4: ISIN | I4: אג"ח להמרה צמוד למדד המחירים לצרכן | J4: ישראל | K4: ישראל | L4: אחר | M4: בנייה | N4: לא | O4: 30/12/2014 | P4: N/R | Q4: אחר | R4: מנפיק | S4: ILS | T4: 0.01 | U4: 31/12/2021 | V4: 0 | W4: 0.057 | X4: החוב נחות | Y4: כן | Z4: גורם תלוי/פנימי | AB4: 30/06/2021 | AD4: 1380.01 | AE4: 1 | AF4: 0.01 | AG4: 0 | AJ4: שווי הוגן | AK4: 1.9840678e-07 | AL4: 3.6331139e-10
A5: 1182 | B5: 1182 | C5: ב.ס.ר אירופה בע"מ | D5: 520033838 | E5: ח.פ | F5: בסר אירופה אגח ח | G5: IL0011701419 | H5: ISIN | I5: אג"ח להמרה צמוד למדד המחירים לצרכן | J5: ישראל | K5: ישראל | L5: אחר | M5: בנייה | N5: לא | O5: 30/12/2014 | P5: N/R | Q5: אחר | R5: נייר ערך | S5: ILS | T5: 2.92 | U5: 30/11/2023 | V5: 0.0001 | W5: 0.065 | X5: החוב נחות | Y5: כן | Z5: גורם תלוי/פנימי | AB5: 30/12/2021 | AD5: 39.99 | AE5: 1 | AF5: 73 | AG5: 0.029 | AJ5: שווי הוגן | AK5: 4.1970924e-05 | AL5: 7.6854808e-08
A6: 1182 | B6: 1182 | C6: גב-ים נגב בע"מ | D6: 514189596 | E6: ח.פ | F6: גב-ים נגב אגח א רמ | G6: IL0011511412 | H6: ISIN | I6: לא צמוד למדד המחירים לצרכן | J6: ישראל | K6: ישראל | L6: אחר | M6: נדל"ן מניב בישראל | N6: לא | O6: 29/07/2018 | P6: A+ | Q6: S&P מעלות | R6: נייר ערך | S6: ILS | T6: 0.74 | U6: 20/10/2027 | V6: 0.053 | W6: 0.0355 | X6: החוב לא נחות | Y6: לא | Z6: חברת ציטוט | AA6: אי תלות | AB6: 31/03/2024 | AD6: 240000 | AE6: 1 | AF6: 99.64 | AG6: 239.136 | AJ6: שווי הוגן | AK6: 0.34381057 | AL6: 0.00062956669
A7: 1182 | B7: 1182 | C7: דוראה השקעות ופיתוח בע"מ | D7: 520038282 | E7: ח.פ | F7: דוראה אגח ב | G7: IL0037200750 | H7: ISIN | I7: צמוד למדד המחירים לצרכן | J7: ישראל | K7: ישראל | L7: אחר | M7: בנייה | N7: לא | O7: 03/12/2012 | P7: N/R | Q7: אחר | R7: מנפיק | S7: ILS | T7: 0.01 | U7: 30/04/2014 | V7: 0 | W7: 0.049 | X7: החוב לא נחות | Y7: לא | Z7: אחר | AB7: 28/06/2018 | AD7: 3992.61 | AE7: 1 | AF7: 6.4 | AG7: 0.256 | AJ7: שווי הוגן | AK7: 0.0003673763 | AL7: 6.7271892e-07
A8: 1182 | B8: 1182 | C8: חבס השקעות (1960) בע"מ | D8: 520039017 | E8: ח.פ | F8: חבס אגח 12 | G8: IL0041500906 | H8: ISIN | I8: אג"ח להמרה צמוד למדד המחירים לצרכן | J8: ישראל | K8: ישראל | L8: אחר | M8: בנייה | N8: לא | O8: 25/05/2015 | P8: N/R | Q8: אחר | R8: נייר ערך | S8: ILS | T8: 0.01 | U8: 29/05/2014 | V8: 0.0001 | W8: 0.055 | X8: החוב נחות | Y8: כן | Z8: גורם תלוי/פנימי | AB8: 31/01/2022 | AD8: 1000 | AE8: 1 | AF8: 1 | AG8: 0.01 | AJ8: שווי הוגן | AK8: 1.4377198e-05 | AL8: 2.6326722e-08
A9: 1182 | B9: 1182 | C9: עוגן- אגח חברתיות 1 בעמ | D9: 516432044 | E9: ח.פ | F9: עוגן חלצ אגחב-רמ | G9: IL0011968497 | H9: ISIN | I9: לא צמוד למדד המחירים לצרכן | J9: ישראל | K9: ישראל | L9: אחר | M9: שירותים פיננסיים | N9: לא | O9: 19/06/2023 | P9: N/R | Q9: אחר | R9: מנפיק | S9: ILS | T9: 2.46 | U9: 15/06/2027 | V9: 0.0774 | W9: 0 | X9: החוב לא נחות | Y9: לא | Z9: חברת ציטוט | AB9: 31/03/2024 | AD9: 450000 | AE9: 1 | AF9: 101.25 | AG9: 455.625 | AJ9: שווי הוגן | AK9: 0.6550611 | AL9: 0.0011995113
A10: 1182 | B10: 1182 | C10: קמור בע"מ | D10: 520034117 | E10: ח.פ | F10: קמור אגח ו | G10: IL0013201186 | H10: ISIN | I10: צמוד למדד המחירים לצרכן | J10: ישראל | K10: ישראל | L10: אחר | M10: השקעה ואחזקות | N10: לא | P10: C | Q10: S&P | R10: נייר ערך | S10: ILS | T10: 0.01 | U10: 27/09/2026 | V10: 0 | W10: 0.055 | X10: החוב לא נחות | Y10: לא | Z10: אחר | AB10: 09/01/2024 | AD10: 1285.8 | AE10: 1 | AF10: 0.01 | AG10: 0 | AJ10: שווי הוגן | AK10: 1.8486202e-07 | AL10: 3.3850899e-10
A11: 12904 | B11: 12905 | C11: עוגן- אגח חברתיות 1 בעמ | D11: 516432044 | E11: ח.פ | F11: עוגן חלצ אגחב-רמ | G11: IL0011968497 | H11: ISIN | I11: לא צמוד למדד המחירים לצרכן | J11: ישראל | K11: ישראל | L11: אחר | M11: שירותים פיננסיים | N11: לא | O11: 19/06/2023 | P11: N/R | Q11: אחר | R11: מנפיק | S11: ILS | T11: 2.46 | U11: 15/06/2027 | V11: 0.0774 | W11: 0 | X11: החוב לא נחות | Y11: לא | Z11: חברת ציטוט | AB11: 31/03/2024 | AD11: 25000 | AE11: 1 | AF11: 101.25 | AG11: 25.313 | AJ11: שווי הוגן | AK11: 1 | AL11: 0.00087429287
A12: 424 | B12: 7228 | C12: דוראה השקעות ופיתוח בע"מ | D12: 520038282 | E12: ח.פ | F12: 5.15% 2015 'דוראה סדרה ד | G12: IL0037201170 | H12: ISIN | I12: צמוד למדד המחירים לצרכן | J12: ישראל | K12: ישראל | L12: אחר | M12: בנייה | N12: לא | O12: 03/12/2012 | P12: N/R | Q12: אחר | R12: מנפיק | S12: ILS | T12: 0.01 | U12: 28/02/2015 | V12: 0 | W12: 0.0515 | X12: החוב לא נחות | Y12: לא | Z12: אחר | AB12: 31/03/2020 | AD12: 70023.45 | AE12: 1 | AF12: 0 | AG12: 0 | AJ12: שווי הוגן | AK12: 1.0268182e-08 | AL12: 3.0215373e-11
A13: 424 | B13: 7228 | C13: א.פ.ס.ק. תעשיות בע"מ(פירוק) | D13: 520042441 | E13: ח.פ | F13: אפסק אגח א | G13: IL0010910326 | H13: ISIN | I13: אג"ח להמרה צמוד למדד המחירים לצרכן | J13: ישראל | K13: ישראל | L13: אחר | M13: השקעה ואחזקות | N13: לא | O13: 29/12/2013 | P13: N/R | Q13: אחר | R13: מנפיק | S13: ILS | T13: 0.01 | U13: 05/08/2012 | V13: 0.0068 | W13: 0.079 | X13: החוב נחות | Y13: כן | Z13: גורם תלוי/פנימי | AB13: 29/06/2021 | AD13: 10168.47 | AE13: 1 | AF13: 0 | AG13: 0 | AJ13: שווי הוגן | AK13: 1.4910963e-09 | AL13: 4.3877318e-12
A14: 424 | B14: 7228 | C14: ב.ס.ר אירופה בע"מ | D14: 520033838 | E14: ח.פ | F14: בסר אירופה אגח ח | G14: IL0011701419 | H14: ISIN | I14: אג"ח להמרה צמוד למדד המחירים לצרכן | J14: ישראל | K14: ישראל | L14: אחר | M14: בנייה | N14: לא | O14: 30/12/2014 | P14: N/R | Q14: אחר | R14: נייר ערך | S14: ILS | T14: 2.92 | U14: 30/11/2023 | V14: 0.0001 | W14: 0.065 | X14: החוב נחות | Y14: כן | Z14: גורם תלוי/פנימי | AB14: 30/12/2021 | AD14: 363.29 | AE14: 1 | AF14: 73 | AG14: 0.265 | AJ14: שווי הוגן | AK14: 3.8888964e-05 | AL14: 1.144355e-07
A15: 424 | B15: 7228 | C15: גב-ים נגב בע"מ | D15: 514189596 | E15: ח.פ | F15: גב-ים נגב אגח א רמ | G15: IL0011511412 | H15: ISIN | I15: לא צמוד למדד המחירים לצרכן | J15: ישראל | K15: ישראל | L15: אחר | M15: נדל"ן מניב בישראל | N15: לא | O15: 29/07/2018 | P15: A+ | Q15: S&P מעלות | R15: נייר ערך | S15: ILS | T15: 0.74 | U15: 20/10/2027 | V15: 0.053 | W15: 0.0355 | X15: החוב לא נחות | Y15: לא | Z15: חברת ציטוט | AA15: אי תלות | AB15: 31/03/2024 | AD15: 2200000 | AE15: 1 | AF15: 99.64 | AG15: 2192.08 | AJ15: שווי הוגן | AK15: 0.32144485 | AL15: 0.00094589049
A16: 424 | B16: 7228 | C16: גמול חברה להשקעות בע"מ | D16: 520018136 | E16: ח.פ | F16: גמול השקע ב | G16: IL0011167553 | H16: ISIN | I16: אג"ח להמרה צמוד למדד המחירים לצרכן | J16: ישראל | K16: ישראל | L16: אחר | M16: השקעה ואחזקות | N16: לא | O16: 07/09/2017 | P16: N/R | Q16: אחר | R16: מנפיק | S16: ILS | T16: 0.01 | U16: 30/09/2021 | V16: 0.009 | W16: 0.045 | X16: החוב לא נחות | Y16: לא | Z16: אחר | AB16: 09/01/2024 | AD16: 1792.17 | AE16: 1 | AF16: 0.82 | AG16: 0.015 | AJ16: שווי הוגן | AK16: 2.1549794e-06 | AL16: 6.3412886e-09
A17: 424 | B17: 7228 | C17: וי.אי.די. התפלת מי אשקלון | D17: 513102384 | E17: ח.פ | F17: התפלת מי אשקלון VID | G17: IL0010876832 | H17: ISIN | I17: צמוד למדד המחירים לצרכן | J17: ישראל | K17: ישראל | L17: אחר | M17: שירותים פיננסיים | N17: לא | O17: 30/12/2014 | P17: AA | Q17: S&P מעלות | R17: נייר ערך | S17: ILS | T17: 0.79 | U17: 22/10/2025 | V17: 0.0202 | W17: 0.0775 | X17: החוב לא נחות | Y17: לא | Z17: חברת ציטוט | AA17: אי תלות | AB17: 31/03/2024 | AD17: 287576.66 | AE17: 1 | AF17: 145.41 | AG17: 418.165 | AJ17: שווי הוגן | AK17: 0.061319412 | AL17: 0.00018043981
A18: 424 | B18: 7228 | C18: וורלד גרופ קפיטל בע"מ | D18: 520033614 | E18: ח.פ | F18: וורלד קפיטל אגח ב | G18: IL0013501072 | H18: ISIN | I18: צמוד למדד המחירים לצרכן | J18: ישראל | K18: ישראל | L18: אחר | M18: השקעה ואחזקות | N18: לא | O18: 25/05/2015 | P18: N/R | Q18: אחר | R18: נייר ערך | S18: ILS | T18: 0.01 | U18: 30/09/2011 | V18: 0.0001 | W18: 0.08 | X18: החוב לא נחות | Y18: כן | Z18: גורם תלוי/פנימי | AB18: 03/11/2021 | AD18: 0.01 | AE18: 1 | AF18: 352.5 | AG18: 0 | AJ18: שווי הוגן | AK18: 5.1690316e-09 | AL18: 1.5210503e-11
A19: 424 | B19: 7228 | C19: חבס השקעות (1960) בע"מ | D19: 520039017 | E19: ח.פ | F19: חבס אגח 12 | G19: IL0041500906 | H19: ISIN | I19: אג"ח להמרה צמוד למדד המחירים לצרכן | J19: ישראל | K19: ישראל | L19: אחר | M19: בנייה | N19: לא | O19: 25/05/2015 | P19: N/R | Q19: אחר | R19: נייר ערך | S19: ILS | T19: 0.01 | U19: 29/05/2014 | V19: 0.0001 | W19: 0.055 | X19: החוב נחות | Y19: כן | Z19: גורם תלוי/פנימי | AB19: 31/01/2022 | AD19: 22175.01 | AE19: 1 | AF19: 1 | AG19: 0.222 | AJ19: שווי הוגן | AK19: 3.2517256e-05 | AL19: 9.5685975e-08
A20: 424 | B20: 7228 | C20: חפציבה ג'רוזלם גולד בע"מ | D20: 510404460 | E20: ח.פ | F20: חפציבה גרוזלם אגח 1 | G20: IL0010999444 | H20: ISIN | I20: צמוד למדד המחירים לצרכן | J20: ישראל | K20: ישראל | L20: אחר | M20: בנייה | N20: לא | O20: 25/05/2015 | P20: N/R | Q20: אחר | R20: מנפיק | S20: ILS | T20: 0.01 | U20: 26/08/2009 | V20: 0.0001 | W20: 0.0575 | X20: החוב נחות | Y20: כן | Z20: גורם תלוי/פנימי | AB20: 23/01/2023 | AD20: 683.67 | AE20: 1 | AF20: 43.1 | AG20: 0.295 | AJ20: שווי הוגן | AK20: 4.3208965e-05 | AL20: 1.2714763e-07
A21: 424 | B21: 7228 | C21: חפציבה ג'רוזלם גולד בע"מ | D21: 510404460 | E21: ח.פ | F21: חפציבה גרוזלם אגח 2 | G21: IL0010999519 | H21: ISIN | I21: אג"ח להמרה צמוד למדד המחירים לצרכן | J21: ישראל | K21: ישראל | L21: אחר | M21: בנייה | N21: לא | O21: 25/05/2015 | P21: N/R | Q21: אחר | R21: מנפיק | S21: ILS | T21: 0.01 | U21: 30/11/2016 | V21: 0.0001 | W21: 0.075 | X21: החוב נחות | Y21: כן | Z21: גורם תלוי/פנימי | AB21: 23/01/2023 | AD21: 6593.35 | AE21: 1 | AF21: 31.9 | AG21: 2.103 | AJ21: שווי הוגן | AK21: 0.00030842309 | AL21: 9.0757239e-07
A22: 424 | B22: 7228 | C22: חפציבה ג'רוזלם גולד בע"מ | D22: 510404460 | E22: ח.פ | F22: חפציבה גרוזלם אגח 3 | G22: IL0010999691 | H22: ISIN | I22: צמוד למדד המחירים לצרכן | J22: ישראל | K22: ישראל | L22: אחר | M22: בנייה | N22: לא | O22: 25/05/2015 | P22: N/R | Q22: אחר | R22: מנפיק | S22: ILS | T22: 0.01 | U22: 25/02/2019 | V22: 0.0001 | W22: 0.075 | X22: החוב נחות | Y22: כן | Z22: גורם תלוי/פנימי | AB22: 23/01/2023 | AD22: 6692.34 | AE22: 1 | AF22: 33.6 | AG22: 2.249 | AJ22: שווי הוגן | AK22: 0.00032973674 | AL22: 9.702904e-07
A23: 424 | B23: 7228 | C23: חפציבה חופים בע"מ | D23: 513718734 | E23: ח.פ | F23: חפציבה חופים אג"ח א' חש 2/09 | G23: 11113562 | H23: פנימי | I23: צמוד למדד המחירים לצרכן | J23: ישראל | K23: ישראל | L23: אחר | M23: בנייה | N23: לא | O23: 18/05/2020 | P23: N/R | Q23: אחר | R23: מנפיק | S23: ILS | T23: 0.01 | U23: 28/02/2012 | V23: 0 | W23: 0.06 | X23: החוב לא נחות | Y23: לא | Z23: אחר | AB23: 20/05/2020 | AD23: 2301.19 | AE23: 1 | AF23: 0 | AG23: 0 | AJ23: שווי הוגן | AK23: 3.3744465e-10 | AL23: 9.9297186e-13
A24: 424 | B24: 7228 | C24: חפציבה חופים בע"מ | D24: 513718734 | E24: ח.פ | F24: חפציבה חופים אגח 1 | G24: IL0010959422 | H24: ISIN | I24: צמוד למדד המחירים לצרכן | J24: ישראל | K24: ישראל | L24: אחר | M24: בנייה | N24: לא | O24: 31/08/2006 | P24: N/R | Q24: אחר | R24: מנפיק | S24: ILS | T24: 0.01 | U24: 28/02/2012 | V24: 0 | W24: 0.06 | X24: החוב לא נחות | Y24: לא | Z24: אחר | AB24: 20/05/2020 | AD24: 13807.08 | AE24: 1 | AF24: 0 | AG24: 0 | AJ24: שווי הוגן | AK24: 2.0246591e-09 | AL24: 5.9578053e-12
A25: 424 | B25: 7228 | C25: נתיבים אגרות חוב בע"מ | D25: 513502229 | E25: ח.פ | F25: נתיבים אגח א רמ | G25: IL0010902810 | H25: ISIN | I25: צמוד למט"ח | J25: ישראל | K25: ישראל | L25: אחר | M25: אג"ח מובנות | N25: לא | O25: 30/12/2014 | P25: Aa1 | Q25: מידרוג Moodys | R25: נייר ערך | S25: USD | T25: 1.7 | U25: 02/07/2027 | V25: 0.0619 | W25: 0.0797 | X25: החוב לא נחות | Y25: לא | Z25: חברת ציטוט | AA25: אי תלות | AB25: 31/03/2024 | AD25: 72563.4 | AE25: 3.681 | AF25: 105.06 | AG25: 280.621 | AJ25: שווי הוגן | AK25: 0.041150101 | AL25: 0.00012108917
A26: 424 | B26: 7228 | C26: SYBIL EUROPE LIMITED | D26: 513948265 | E26: ח.פ | F26: סיביל יורופ אגח א (חברה מחוקה) | G26: IL0011052466 | H26: ISIN | I26: צמוד למדד המחירים לצרכן | J26: ישראל | K26: ישראל | L26: אחר | M26: נדל"ן מניב בישראל | N26: לא | O26: 25/05/2015 | P26: N/R | Q26: אחר | R26: נייר ערך | S26: ILS | T26: 7.36 | U26: 31/12/2014 | V26: 0.0001 | W26: 0.07 | X26: החוב נחות | Y26: כן | Z26: גורם תלוי/פנימי | AB26: 31/01/2022 | AD26: 120350 | AE26: 1 | AF26: 0 | AG26: 0 | AJ26: שווי הוגן | AK26: 1.7648027e-10 | AL26: 5.1931463e-13
A27: 424 | B27: 7228 | C27: סינרג'י כבלים בע"מ | D27: 520025271 | E27: ח.פ | F27: סינרג'יכב אגח ג | G27: IL0077802812 | H27: ISIN | I27: צמוד למדד המחירים לצרכן | J27: ישראל | K27: ישראל | L27: אחר | M27: מתכת ומוצרי בניה | N27: לא | O27: 24/09/2015 | P27: N/R | Q27: אחר | R27: מנפיק | S27: ILS | T27: 1.06 | U27: 05/01/2025 | V27: 0.2252 | W27: 0.06 | X27: החוב נחות | Y27: כן | Z27: גורם תלוי/פנימי | AB27: 31/03/2024 | AD27: 56725.01 | AE27: 1 | AF27: 0.01 | AG27: 0.006 | AJ27: שווי הוגן | AK27: 8.3181098e-07 | AL27: 2.4477048e-09
A28: 424 | B28: 7228 | C28: עוגן- אגח חברתיות 1 בעמ | D28: 516432044 | E28: ח.פ | F28: עוגן חלצ אגחב-רמ | G28: IL0011968497 | H28: ISIN | I28: לא צמוד למדד המחירים לצרכן | J28: ישראל | K28: ישראל | L28: אחר | M28: שירותים פיננסיים | N28: לא | O28: 19/06/2023 | P28: N/R | Q28: אחר | R28: מנפיק | S28: ILS | T28: 2.46 | U28: 15/06/2027 | V28: 0.0774 | W28: 0 | X28: החוב לא נחות | Y28: לא | Z28: חברת ציטוט | AB28: 31/03/2024 | AD28: 3875000 | AE28: 1 | AF28: 101.25 | AG28: 3923.438 | AJ28: שווי הוגן | AK28: 0.57532972 | AL28: 0.0016929776
A29: 424 | B29: 7228 | C29: קמור בע"מ | D29: 520034117 | E29: ח.פ | F29: קמור אגח ו | G29: IL0013201186 | H29: ISIN | I29: צמוד למדד המחירים לצרכן | J29: ישראל | K29: ישראל | L29: אחר | M29: השקעה ואחזקות | N29: לא | O29: 01/06/2015 | P29: C | Q29: S&P | R29: נייר ערך | S29: ILS | T29: 0.01 | U29: 27/09/2026 | V29: 0 | W29: 0.055 | X29: החוב לא נחות | Y29: לא | Z29: אחר | AB29: 09/01/2024 | AD29: 9612.14 | AE29: 1 | AF29: 0.01 | AG29: 0.001 | AJ29: שווי הוגן | AK29: 1.4095165e-07 | AL29: 4.1476734e-10
A30: 424 | B30: 7229 | C30: אמפל-אמריקן ישראל קורפוריישן | D30: 130435685 | E30: מספר תאגיד או שותפות בחו"ל | F30: אמפל אמריקן ישראל ב'12/16 %6.6(חש) | G30: 11256240 | H30: פנימי | I30: צמוד למדד המחירים לצרכן | J30: ישראל | K30: ישראל | L30: אחר | M30: השקעה ואחזקות | N30: לא | O30: 29/06/2023 | P30: N/R | Q30: אחר | R30: נייר ערך | S30: ILS | T30: 0.01 | U30: 31/12/2012 | V30: 0.0001 | W30: 0.066 | X30: החוב לא נחות | Y30: לא | Z30: אחר | AB30: 31/05/2021 | AD30: 750 | AE30: 1 | AF30: 0 | AG30: 0 | AJ30: שווי הוגן | AK30: 8.7473248e-11 | AL30: 5.2318006e-13
A31: 424 | B31: 7229 | C31: גב-ים נגב בע"מ | D31: 514189596 | E31: ח.פ | F31: גב-ים נגב אגח א רמ | G31: IL0011511412 | H31: ISIN | I31: לא צמוד למדד המחירים לצרכן | J31: ישראל | K31: ישראל | L31: אחר | M31: נדל"ן מניב בישראל | N31: לא | O31: 29/07/2018 | P31: A+ | Q31: S&P מעלות | R31: נייר ערך | S31: ILS | T31: 0.74 | U31: 20/10/2027 | V31: 0.053 | W31: 0.0355 | X31: החוב לא נחות | Y31: לא | Z31: חברת ציטוט | AA31: אי תלות | AB31: 31/03/2024 | AD31: 200000 | AE31: 1 | AF31: 99.64 | AG31: 199.28 | AJ31: שווי הוגן | AK31: 0.23242225 | AL31: 0.0013901243
A32: 424 | B32: 7229 | C32: עוגן- אגח חברתיות 1 בעמ | D32: 516432044 | E32: ח.פ | F32: עוגן חלצ אגחב-רמ | G32: IL0011968497 | H32: ISIN | I32: לא צמוד למדד המחירים לצרכן | J32: ישראל | K32: ישראל | L32: אחר | M32: שירותים פיננסיים | N32: לא | O32: 19/06/2023 | P32: N/R | Q32: אחר | R32: מנפיק | S32: ILS | T32: 2.46 | U32: 15/06/2027 | V32: 0.0774 | W32: 0 | X32: החוב לא נחות | Y32: לא | Z32: חברת ציטוט | AB32: 31/03/2024 | AD32: 650000 | AE32: 1 | AF32: 101.25 | AG32: 658.125 | AJ32: שווי הוגן | AK32: 0.76757775 | AL32: 0.004590905
A33: 424 | B33: 9817 | C33: גב-ים נגב בע"מ | D33: 514189596 | E33: ח.פ | F33: גב-ים נגב אגח א רמ | G33: IL0011511412 | H33: ISIN | I33: לא צמוד למדד המחירים לצרכן | J33: ישראל | K33: ישראל | L33: אחר | M33: נדל"ן מניב בישראל | N33: לא | O33: 29/07/2018 | P33: A+ | Q33: S&P מעלות | R33: נייר ערך | S33: ILS | T33: 0.74 | U33: 20/10/2027 | V33: 0.053 | W33: 0.0355 | X33: החוב לא נחות | Y33: לא | Z33: חברת ציטוט | AA33: אי תלות | AB33: 31/03/2024 | AD33: 4000 | AE33: 1 | AF33: 99.64 | AG33: 3.986 | AJ33: שווי הוגן | AK33: 1 | AL33: 0.002747535
A34: 969 | B34: 969 | C34: דוראה השקעות ופיתוח בע"מ | D34: 520038282 | E34: ח.פ | F34: 5.15% 2015 'דוראה סדרה ד | G34: IL0037201170 | H34: ISIN | I34: צמוד למדד המחירים לצרכן | J34: ישראל | K34: ישראל | L34: אחר | M34: בנייה | N34: לא | O34: 03/12/2012 | P34: N/R | Q34: אחר | R34: מנפיק | S34: ILS | T34: 0.01 | U34: 28/02/2015 | V34: 0 | W34: 0.0515 | X34: החוב לא נחות | Y34: לא | Z34: אחר | AB34: 31/03/2020 | AD34: 5145 | AE34: 1 | AF34: 0 | AG34: 0 | AJ34: שווי הוגן | AK34: 4.6089918e-08 | AL34: 7.0050215e-11
A35: 969 | B35: 969 | C35: אולימפיה החזקות נדל"ן בע"מ | D35: 520035155 | E35: ח.פ | F35: אולימפיה אג"ח ב' | G35: IL0017900544 | H35: ISIN | I35: אג"ח להמרה צמוד למדד המחירים לצרכן | J35: ישראל | K35: ישראל | L35: אחר | M35: בנייה | N35: לא | O35: 30/12/2014 | P35: N/R | Q35: אחר | R35: מנפיק | S35: ILS | T35: 0.01 | U35: 31/12/2021 | V35: 0 | W35: 0.057 | X35: החוב נחות | Y35: כן | Z35: גורם תלוי/פנימי | AB35: 30/06/2021 | AD35: 1200.01 | AE35: 1 | AF35: 0.01 | AG35: 0 | AJ35: שווי הוגן | AK35: 1.0749925e-06 | AL35: 1.6338379e-09
A36: 969 | B36: 969 | C36: אולימפיה החזקות נדל"ן בע"מ | D36: 520035155 | E36: ח.פ | F36: אולימפיה אגח ג (מחוקה) | G36: IL0017900627 | H36: ISIN | I36: צמוד למדד המחירים לצרכן | J36: ישראל | K36: ישראל | L36: אחר | M36: בנייה | N36: לא | O36: 01/01/2018 | P36: N/R | Q36: אחר | R36: נייר ערך | S36: ILS | T36: 0.01 | U36: 31/08/2015 | V36: 0.0045 | W36: 0.059 | X36: החוב נחות | Y36: כן | Z36: גורם תלוי/פנימי | AB36: 10/11/2021 | AD36: 1300 | AE36: 1 | AF36: 0.01 | AG36: 0 | AJ36: שווי הוגן | AK36: 1.1645655e-06 | AL36: 1.7699763e-09
A37: 969 | B37: 969 | C37: אמפל-אמריקן ישראל קורפוריישן | D37: 130435685 | E37: מספר תאגיד או שותפות בחו"ל | F37: אמפל אמריקן ישראל ב'12/16 %6.6(חש) | G37: 11256240 | H37: פנימי | I37: צמוד למדד המחירים לצרכן | J37: ישראל | K37: ישראל | L37: אחר | M37: השקעה ואחזקות | N37: לא | O37: 29/06/2023 | P37: N/R | Q37: אחר | R37: נייר ערך | S37: ILS | T37: 0.01 | U37: 31/12/2012 | V37: 0.0001 | W37: 0.066 | X37: החוב לא נחות | Y37: לא | Z37: אחר | AB37: 31/05/2021 | AD37: 4500 | AE37: 1 | AF37: 0 | AG37: 0 | AJ37: שווי הוגן | AK37: 4.0311881e-09 | AL37: 6.1268409e-12
A38: 969 | B38: 969 | C38: גב-ים נגב בע"מ | D38: 514189596 | E38: ח.פ | F38: גב-ים נגב אגח א רמ | G38: IL0011511412 | H38: ISIN | I38: לא צמוד למדד המחירים לצרכן | J38: ישראל | K38: ישראל | L38: אחר | M38: נדל"ן מניב בישראל | N38: לא | O38: 29/07/2018 | P38: A+ | Q38: S&P מעלות | R38: נייר ערך | S38: ILS | T38: 0.74 | U38: 20/10/2027 | V38: 0.053 | W38: 0.0355 | X38: החוב לא נחות | Y38: לא | Z38: חברת ציטוט | AA38: אי תלות | AB38: 31/03/2024 | AD38: 112000 | AE38: 1 | AF38: 99.64 | AG38: 111.597 | AJ38: שווי הוגן | AK38: 0.99970599 | AL38: 0.001519413
A39: 969 | B39: 969 | C39: דוראה השקעות ופיתוח בע"מ | D39: 520038282 | E39: ח.פ | F39: דוראה אגח א | G39: IL0037200347 | H39: ISIN | I39: צמוד למדד המחירים לצרכן | J39: ישראל | K39: ישראל | L39: אחר | M39: נדל"ן מניב בישראל | N39: לא | O39: 01/05/2019 | P39: N/R | Q39: אחר | R39: מנפיק | S39: ILS | T39: 2.27 | U39: 31/05/2012 | V39: 0.2474 | W39: 0.04 | X39: החוב לא נחות | Y39: לא | Z39: אחר | AB39: 31/08/2020 | AD39: 1401.95 | AE39: 1 | AF39: 0 | AG39: 0 | AJ39: שווי הוגן | AK39: 1.2558943e-10 | AL39: 1.9087833e-13
A40: 969 | B40: 969 | C40: חבס השקעות (1960) בע"מ | D40: 520039017 | E40: ח.פ | F40: חבס אגח 12 | G40: IL0041500906 | H40: ISIN | I40: אג"ח להמרה צמוד למדד המחירים לצרכן | J40: ישראל | K40: ישראל | L40: אחר | M40: בנייה | N40: לא | O40: 25/05/2015 | P40: N/R | Q40: אחר | R40: נייר ערך | S40: ILS | T40: 0.01 | U40: 29/05/2014 | V40: 0.0001 | W40: 0.055 | X40: החוב נחות | Y40: כן | Z40: גורם תלוי/פנימי | AB40: 31/01/2022 | AD40: 3250 | AE40: 1 | AF40: 1 | AG40: 0.033 | AJ40: שווי הוגן | AK40: 0.00029114137 | AL40: 4.4249407e-07
A41: 969 | B41: 969 | C41: קמור בע"מ | D41: 520034117 | E41: ח.פ | F41: קמור אגח ו | G41: IL0013201186 | H41: ISIN | I41: צמוד למדד המחירים לצרכן | J41: ישראל | K41: ישראל | L41: אחר | M41: השקעה ואחזקות | N41: לא | P41: C | Q41: S&P | R41: נייר ערך | S41: ILS | T41: 0.01 | U41: 27/09/2026 | V41: 0 | W41: 0.055 | X41: החוב לא נחות | Y41: לא | Z41: אחר | AB41: 09/01/2024 | AD41: 642.9 | AE41: 1 | AF41: 0.01 | AG41: 0 | AJ41: שווי הוגן | AK41: 5.7592241e-07 | AL41: 8.7532134e-10

Sheet לא סחיר מניות מבכ ויהש
A1: מספר קופה/קרן/ח.פ. עבור חברת ביטוח | B1: מספר מסלול | C1: שם מנפיק | D1: מספר מנפיק | E1: סוג מספר מזהה מנפיק | F1: שם נייר ערך | G1: מספר נייר ערך | H1: סוג מספר נייר ערך | I1: מאפיין עיקרי | J1: ישראל/חו"ל | K1: מדינה לפי חשיפה כלכלית | L1: סטאטוס סחירות | M1: ענף מסחר | N1: בעל עניין/צד קשור | O1: תאריך רכישה | P1: מטבע פעילות | Q1: סוג גורם משערך | R1: תלות/אי-תלות המשערך | S1: תאריך שערוך אחרון | T1: תאריך אחרון בו נבחנה בפועל ירידת ערך | U1: ערך נקוב (יחידות) | V1: שער חליפין | W1: שער נייר הערך | X1: שווי הוגן (באלפי ש"ח) | Y1: שיעור מנכסי אפיק ההשקעה | Z1: שיעור מסך נכסי ההשקעה
A2: 1182 | B2: 1182 | C2: ATERA NETWORKS LTD | D2: 27702 | E2: פנימי | F2: ATERA NETWORKS LTD | G2: 60353513 | H2: פנימי | I2: מניות לא סחירות | J2: ישראל | K2: ישראל | L2: אחר | M2: Software | N2: לא | O2: 24/12/2019 | P2: USD | Q2: אחר | S2: 31/03/2024 | U2: 5306 | V2: 3.681 | W2: 6792 | X2: 1326.572 | Y2: 0.14496003 | Z2: 0.0034924285
A3: 1182 | B3: 1182 | C3: CIVAN ADVANCED TECHNOGIES | E3: אחר | F3: CIVAN ADVANCED TECHNOGIES | G3: 62021290 | H3: פנימי | I3: מניות לא סחירות | J3: ישראל | K3: גלובלי | L3: אחר | M3: Technology Hardware, Storage & Peripherals | N3: לא | O3: 07/08/2023 | P3: USD | Q3: אחר | S3: 31/03/2024 | U3: 332.99 | V3: 3.681 | W3: 90093.3 | X3: 1104.306 | Y3: 0.12067215 | Z3: 0.0029072761
A4: 1182 | B4: 1182 | C4: GEMMACERT LTD | D4: 27994 | E4: פנימי | F4: GEMMACERT LTD | G4: 62013677 | H4: פנימי | I4: מניות לא סחירות | J4: ישראל | K4: ישראל | L4: אחר | M4: Health Care Equipment & Supplies | N4: לא | O4: 24/07/2019 | P4: USD | Q4: אחר | S4: 31/03/2024 | U4: 26572 | V4: 3.681 | W4: 0 | X4: 0 | Y4: 1.0688275e-08 | Z4: 2.575057e-10
A5: 1182 | B5: 1182 | C5: IMM- VX L.P. (Velox | D5: 89500 | E5: פנימי | F5: IMM- VX L.P. (Velox | G5: 62018924 | H5: פנימי | I5: מניות לא סחירות | J5: ישראל | K5: ארה"ב | L5: אחר | M5: Software | N5: לא | O5: 12/08/2021 | P5: USD | Q5: דיווח מנהל הקרן | S5: 31/03/2024 | U5: 50000 | V5: 3.681 | W5: 75 | X5: 138.037 | Y5: 0.015083934 | Z5: 0.00036340748
A6: 1182 | B6: 1182 | C6: וואן זירו הבנק הדיגיטלי בעמ | D6: 515981728 | E6: ח.פ | F6: ONE ZERO DIGITAL BANK LTD | G6: 62020045 | H6: פנימי | I6: מניות לא סחירות | J6: ישראל | K6: ארה"ב | L6: אחר | M6: בנקים | N6: לא | O6: 03/01/2022 | P6: USD | Q6: אחר | S6: 31/03/2024 | U6: 244820 | V6: 3.681 | W6: 374.808 | X6: 3377.705 | Y6: 0.3690959 | Z6: 0.0088923891
A7: 1182 | B7: 1182 | C7: ONE ZERO DIGITAL BANK LTD | D7: 89735 | E7: פנימי | F7: ONE ZERO SAFE | G7: 62021506 | H7: פנימי | I7: מניות לא סחירות | J7: ישראל | K7: ארה"ב | L7: אחר | M7: בנקים | N7: לא | O7: 05/12/2023 | P7: USD | Q7: אחר | S7: 31/03/2024 | U7: 400000 | V7: 3.681 | W7: 100 | X7: 1472.4 | Y7: 0.1608953 | Z7: 0.0038763465
A8: 1182 | B8: 1182 | C8: QUANTUM | D8: 28588 | E8: פנימי | F8: Quantum Machines | G8: 62020714 | H8: פנימי | I8: מניות לא סחירות | J8: חו"ל | K8: ארה"ב | L8: אחר | M8: השקעות בהיי-טק | N8: לא | O8: 01/08/2022 | P8: USD | Q8: מומחה בלתי תלוי | S8: 31/03/2024 | U8: 9829 | V8: 3.681 | W8: 610.438 | X8: 220.86 | Y8: 0.024134294 | Z8: 0.00058145197
A9: 1182 | B9: 1182 | C9: RESONAI | D9: 89849 | E9: פנימי | F9: RESONAI | G9: 62020383 | H9: פנימי | I9: מניות לא סחירות | J9: ישראל | K9: ארה"ב | L9: אחר | M9: Technology Hardware, Storage & Peripherals | N9: לא | O9: 03/04/2022 | P9: USD | Q9: מומחה בלתי תלוי | S9: 31/03/2024 | U9: 60000 | V9: 3.681 | W9: 67 | X9: 147.976 | Y9: 0.016169977 | Z9: 0.00038957282
A10: 1182 | B10: 1182 | C10: Rewire | D10: 89738 | E10: פנימי | F10: Rewire | G10: 62020060 | H10: פנימי | I10: מניות לא סחירות | J10: ישראל | K10: ארה"ב | L10: אחר | M10: שירותים פיננסיים | N10: לא | O10: 03/01/2022 | P10: USD | Q10: אחר | S10: 31/03/2024 | U10: 3735.95 | V10: 3.681 | W10: 1272.98 | X10: 175.061 | Y10: 0.019129605 | Z10: 0.00046087721
A11: 1182 | B11: 1182 | C11: silentium | D11: 89338 | E11: פנימי | F11: Silentium LTD | G11: 62018429 | H11: פנימי | I11: מניות לא סחירות | J11: ישראל | K11: ארה"ב | L11: אחר | M11: השקעות בהיי-טק | N11: לא | O11: 08/06/2021 | P11: USD | Q11: מומחה בלתי תלוי | S11: 31/03/2024 | U11: 562517 | V11: 3.681 | W11: 6.114 | X11: 126.6 | Y11: 0.01383412 | Z11: 0.00033329653
A12: 1182 | B12: 1182 | C12: TIPA CORP LTD | D12: 514420660 | E12: ח.פ | F12: TIPA CORP LTD | G12: 62020102 | H12: פנימי | I12: מניות לא סחירות | J12: ישראל | K12: ארה"ב | L12: אחר | M12: Technology Hardware, Storage & Peripherals | N12: לא | O12: 12/01/2022 | P12: USD | Q12: מומחה בלתי תלוי | S12: 31/03/2024 | U12: 3605 | V12: 3.681 | W12: 1387.07 | X12: 184.064 | Y12: 0.02011347 | Z12: 0.00048458085
A13: 1182 | B13: 1182 | C13: TWINE | D13: 13286 | E13: פנימי | F13: TWINE SOLUTIONS LTD | G13: 62018296 | H13: פנימי | I13: מניות לא סחירות | J13: ישראל | K13: ארה"ב | L13: אחר | M13: Software | N13: לא | O13: 19/05/2021 | P13: USD | Q13: מומחה בלתי תלוי | S13: 31/03/2024 | U13: 8020 | V13: 3.681 | W13: 0 | X13: 0 | Y13: 3.2259507e-09 | Z13: 7.7720747e-11
A14: 1182 | B14: 1182 | C14: UVEYE LTD | D14: 514234202 | E14: ח.פ | F14: UVEYE LTD | G14: 62018304 | H14: פנימי | I14: מניות לא סחירות | J14: ישראל | K14: ארה"ב | L14: אחר | M14: Software | N14: לא | O14: 19/05/2021 | P14: USD | Q14: מומחה בלתי תלוי | S14: 31/03/2024 | U14: 13988 | V14: 3.681 | W14: 830.053 | X14: 427.393 | Y14: 0.046702991 | Z14: 0.001125185
A15: 1182 | B15: 1182 | C15: ג'נריישן קפיטל בע"מ | D15: 515846558 | E15: ח.פ | F15: ויולה ג'נריישן ניהול בע"מ(אוניברסי | G15: 56200 | H15: פנימי | I15: מניות לא סחירות | J15: ישראל | K15: ישראל | L15: אחר | M15: שירותים פיננסיים | N15: לא | O15: 30/08/2018 | P15: ILS | Q15: אחר | S15: 31/03/2024 | U15: 127 | V15: 1 | W15: 195840.64 | X15: 248.718 | Y15: 0.027178412 | Z15: 0.00065479194
A16: 1182 | B16: 1182 | C16: קרופס גארד בע"מ | D16: 516186301 | E16: ח.פ | F16: קרופס גארד בע"מ | G16: 62016738 | H16: פנימי | I16: מניות לא סחירות | J16: ישראל | K16: ישראל | L16: אחר | M16: ביוטכנולוגיה | N16: לא | O16: 15/06/2020 | P16: USD | Q16: אחר | S16: 31/03/2024 | U16: 41131.24 | V16: 3.681 | W16: 0 | X16: 0 | Y16: 1.6544558e-08 | Z16: 3.9859734e-10
A17: 1182 | B17: 1182 | C17: Straffan Asset Management Ltd | D17: 28068 | E17: פנימי | F17: BRIGHTON SPC - KIJANI COMMODIT | G17: KYG1367R1083 | H17: ISIN | I17: מניות לא סחירות | J17: חו"ל | K17: גלובלי | L17: אחר | M17: Diversified Financial Services Financial Services | N17: לא | P17: USD | Q17: אחר | S17: 27/09/2018 | U17: 14.84 | V17: 3.681 | W17: 0 | X17: 0 | Y17: 5.9692155e-12 | Z17: 1.4381245e-13
A18: 1182 | B18: 1182 | C18: EMERALD SIDEPOC | D18: 27703 | E18: פנימי | F18: EMERALD SIDEPOC | G18: XXX133661328 | H18: ISIN | I18: מניות לא סחירות | J18: חו"ל | K18: ארה"ב | L18: אחר | M18: Food & Staples Retailing Consumer Staples Distribution & Retail | N18: לא | P18: USD | Q18: אחר | S18: 27/09/2018 | U18: 43.79 | V18: 3.681 | W18: 0 | X18: 0 | Y18: 1.7614013e-11 | Z18: 4.2436303e-13
A19: 1182 | B19: 1182 | C19: Silk Technologies INC | D19: 28307 | E19: פנימי | F19: SILK | G19: 62018056 | H19: פנימי | I19: מניות לא סחירות | J19: חו"ל | K19: ארה"ב | L19: אחר | M19: Technology Hardware, Storage & Peripherals | N19: לא | O19: 25/03/2021 | P19: USD | Q19: מומחה בלתי תלוי | S19: 31/03/2024 | U19: 12316 | V19: 3.681 | W19: 444.69 | X19: 201.601 | Y19: 0.022029792 | Z19: 0.00053074956
A20: 12904 | B20: 12905 | C20: CIVAN ADVANCED TECHNOGIES | E20: אחר | F20: CIVAN ADVANCED TECHNOGIES | G20: 62021290 | H20: פנימי | I20: מניות לא סחירות | J20: ישראל | K20: גלובלי | L20: אחר | M20: Technology Hardware, Storage & Peripherals | N20: לא | O20: 07/08/2023 | P20: USD | Q20: אחר | S20: 31/03/2024 | U20: 16.65 | V20: 3.681 | W20: 90093.3 | X20: 55.217 | Y20: 0.15789947 | Z20: 0.0019071921
A21: 12904 | B21: 12905 | C21: ONE ZERO DIGITAL BANK LTD | D21: 89735 | E21: פנימי | F21: ONE ZERO SAFE | G21: 62021506 | H21: פנימי | I21: מניות לא סחירות | J21: ישראל | K21: ארה"ב | L21: אחר | M21: בנקים | N21: לא | O21: 05/12/2023 | P21: USD | Q21: אחר | S21: 31/03/2024 | U21: 80000 | V21: 3.681 | W21: 100 | X21: 294.48 | Y21: 0.84210053 | Z21: 0.010171329
A22: 12904 | B22: 13680 | C22: CIVAN ADVANCED TECHNOGIES | E22: אחר | F22: CIVAN ADVANCED TECHNOGIES | G22: 62021290 | H22: פנימי | I22: מניות לא סחירות | J22: ישראל | K22: גלובלי | L22: אחר | M22: Technology Hardware, Storage & Peripherals | N22: לא | O22: 07/08/2023 | P22: USD | Q22: אחר | S22: 31/03/2024 | U22: 11.1 | V22: 3.681 | W22: 90093.3 | X22: 36.811 | Y22: 0.1250039 | Z22: 0.0012584982
A23: 12904 | B23: 13680 | C23: ONE ZERO DIGITAL BANK LTD | D23: 89735 | E23: פנימי | F23: ONE ZERO SAFE | G23: 62021506 | H23: פנימי | I23: מניות לא סחירות | J23: ישראל | K23: ארה"ב | L23: אחר | M23: בנקים | N23: לא | O23: 05/12/2023 | P23: USD | Q23: אחר | S23: 31/03/2024 | U23: 70000 | V23: 3.681 | W23: 100 | X23: 257.67 | Y23: 0.8749961 | Z23: 0.0088091735
A24: 424 | B24: 7228 | C24: ATERA NETWORKS LTD | D24: 27702 | E24: פנימי | F24: ATERA NETWORKS LTD | G24: 60353513 | H24: פנימי | I24: מניות לא סחירות | J24: ישראל | K24: ישראל | L24: אחר | M24: Software | N24: לא | O24: 24/12/2019 | P24: USD | Q24: אחר | S24: 31/03/2024 | U24: 82545 | V24: 3.681 | W24: 6792 | X24: 20637.366 | Y24: 0.27736751 | Z24: 0.0089050985
A25: 424 | B25: 7228 | C25: CIVAN ADVANCED TECHNOGIES | E25: אחר | F25: CIVAN ADVANCED TECHNOGIES | G25: 62021290 | H25: פנימי | I25: מניות לא סחירות | J25: ישראל | K25: גלובלי | L25: אחר | M25: Technology Hardware, Storage & Peripherals | N25: לא | O25: 07/08/2023 | P25: USD | Q25: אחר | S25: 31/03/2024 | U25: 2219.02 | V25: 3.681 | W25: 90093.3 | X25: 7359.012 | Y25: 0.098905593 | Z25: 0.0031754406
A26: 424 | B26: 7228 | C26: GEMMACERT LTD | D26: 27994 | E26: פנימי | F26: GEMMACERT LTD | G26: 62013677 | H26: פנימי | I26: מניות לא סחירות | J26: ישראל | K26: ישראל | L26: אחר | M26: Health Care Equipment & Supplies | N26: לא | O26: 24/07/2019 | P26: USD | Q26: אחר | S26: 31/03/2024 | U26: 239148 | V26: 3.681 | W26: 0 | X26: 0.001 | Y26: 1.1831339e-08 | Z26: 3.7985429e-10
A27: 424 | B27: 7228 | C27: IMM- VX L.P. (Velox | D27: 89500 | E27: פנימי | F27: IMM- VX L.P. (Velox | G27: 62018924 | H27: פנימי | I27: מניות לא סחירות | J27: ישראל | K27: ארה"ב | L27: אחר | M27: Software | N27: לא | O27: 12/08/2021 | P27: USD | Q27: דיווח מנהל הקרן | S27: 31/03/2024 | U27: 260000 | V27: 3.681 | W27: 75 | X27: 717.795 | Y27: 0.0096472104 | Z27: 0.00030973115
A28: 424 | B28: 7228 | C28: INTEGRA HOLDING | D28: 27771 | E28: פנימי | F28: INTEGRA HOLDING | G28: 60314101 | H28: פנימי | I28: מניות לא סחירות | J28: ישראל | K28: ישראל | L28: אחר | M28: Health Care Equipment & Supplies | N28: לא | P28: USD | Q28: אחר | S28: 31/03/2024 | U28: 2939 | V28: 3.681 | W28: 31340.456 | X28: 3390.554 | Y28: 0.045569266 | Z28: 0.0014630365
A29: 424 | B29: 7228 | C29: וואן זירו הבנק הדיגיטלי בעמ | D29: 515981728 | E29: ח.פ | F29: ONE ZERO DIGITAL BANK LTD | G29: 62020045 | H29: פנימי | I29: מניות לא סחירות | J29: ישראל | K29: ארה"ב | L29: אחר | M29: בנקים | N29: לא | O29: 03/01/2022 | P29: USD | Q29: אחר | S29: 31/03/2024 | U29: 2325794 | V29: 3.681 | W29: 374.808 | X29: 32088.25 | Y29: 0.43126812 | Z29: 0.013846197
A30: 424 | B30: 7228 | C30: ONE ZERO DIGITAL BANK LTD | D30: 89735 | E30: פנימי | F30: ONE ZERO SAFE | G30: 62021506 | H30: פנימי | I30: מניות לא סחירות | J30: ישראל | K30: ארה"ב | L30: אחר | M30: בנקים | N30: לא | O30: 05/12/2023 | P30: USD | Q30: אחר | S30: 31/03/2024 | U30: 150000 | V30: 3.681 | W30: 100 | X30: 552.15 | Y30: 0.0074209311 | Z30: 0.00023825473
A31: 424 | B31: 7228 | C31: QUANTUM | D31: 28588 | E31: פנימי | F31: Quantum Machines | G31: 62020714 | H31: פנימי | I31: מניות לא סחירות | J31: חו"ל | K31: ארה"ב | L31: אחר | M31: השקעות בהיי-טק | N31: לא | O31: 01/08/2022 | P31: USD | Q31: מומחה בלתי תלוי | S31: 31/03/2024 | U31: 47505 | V31: 3.681 | W31: 610.438 | X31: 1067.449 | Y31: 0.01434658 | Z31: 0.00046060804
A32: 424 | B32: 7228 | C32: RESONAI | D32: 89849 | E32: פנימי | F32: RESONAI | G32: 62020383 | H32: פנימי | I32: מניות לא סחירות | J32: ישראל | K32: ארה"ב | L32: אחר | M32: Technology Hardware, Storage & Peripherals | N32: לא | O32: 03/04/2022 | P32: USD | Q32: מומחה בלתי תלוי | S32: 31/03/2024 | U32: 290000 | V32: 3.681 | W32: 67 | X32: 715.218 | Y32: 0.0096125794 | Z32: 0.0003086193
A33: 424 | B33: 7228 | C33: Rewire | D33: 89738 | E33: פנימי | F33: Rewire | G33: 62020060 | H33: פנימי | I33: מניות לא סחירות | J33: ישראל | K33: ארה"ב | L33: אחר | M33: שירותים פיננסיים | N33: לא | O33: 03/01/2022 | P33: USD | Q33: אחר | S33: 31/03/2024 | U33: 14943.8 | V33: 3.681 | W33: 1272.98 | X33: 700.242 | Y33: 0.0094113032 | Z33: 0.00030215717
A34: 424 | B34: 7228 | C34: silentium | D34: 89338 | E34: פנימי | F34: Silentium LTD | G34: 62018429 | H34: פנימי | I34: מניות לא סחירות | J34: ישראל | K34: ארה"ב | L34: אחר | M34: השקעות בהיי-טק | N34: לא | O34: 08/06/2021 | P34: USD | Q34: מומחה בלתי תלוי | S34: 31/03/2024 | U34: 2925086 | V34: 3.681 | W34: 6.114 | X34: 658.32 | Y34: 0.0088478615 | Z34: 0.00028406744
A35: 424 | B35: 7228 | C35: TIPA CORP LTD | D35: 514420660 | E35: ח.פ | F35: TIPA CORP LTD | G35: 62020102 | H35: פנימי | I35: מניות לא סחירות | J35: ישראל | K35: ארה"ב | L35: אחר | M35: Technology Hardware, Storage & Peripherals | N35: לא | O35: 12/01/2022 | P35: USD | Q35: מומחה בלתי תלוי | S35: 31/03/2024 | U35: 21628 | V35: 3.681 | W35: 1387.07 | X35: 1104.283 | Y35: 0.01484164 | Z35: 0.00047650232
A36: 424 | B36: 7228 | C36: TWINE | D36: 13286 | E36: פנימי | F36: TWINE SOLUTIONS LTD | G36: 62018296 | H36: פנימי | I36: מניות לא סחירות | J36: ישראל | K36: ארה"ב | L36: אחר | M36: Software | N36: לא | O36: 19/05/2021 | P36: USD | Q36: מומחה בלתי תלוי | S36: 31/03/2024 | U36: 41703 | V36: 3.681 | W36: 0 | X36: 0 | Y36: 2.0631673e-09 | Z36: 6.6239581e-11
A37: 424 | B37: 7228 | C37: UVEYE LTD | D37: 514234202 | E37: ח.פ | F37: UVEYE LTD | G37: 62018304 | H37: פנימי | I37: מניות לא סחירות | J37: ישראל | K37: ארה"ב | L37: אחר | M37: Software | N37: לא | O37: 19/05/2021 | P37: USD | Q37: מומחה בלתי תלוי | S37: 31/03/2024 | U37: 72735 | V37: 3.681 | W37: 830.053 | X37: 2222.363 | Y37: 0.029868699 | Z37: 0.00095895768
A38: 424 | B38: 7228 | C38: אספרו | D38: 513868380 | E38: ח.פ | F38: אספרו מ"ר | G38: 62406 | H38: פנימי | I38: מניות לא סחירות | J38: ישראל | K38: ישראל | L38: אחר | M38: תשתיות | N38: לא | P38: USD | Q38: אחר | S38: 15/03/2018 | U38: 198592 | V38: 3.681 | W38: 0 | X38: 0.001 | Y38: 8.4494286e-09 | Z38: 2.7127544e-10
A39: 424 | B39: 7228 | C39: גת אנרגיה בע"מ | D39: 514293380 | E39: ח.פ | F39: גת אנרגיה ג' | G39: 50000298 | H39: פנימי | I39: מניות לא סחירות | J39: ישראל | K39: ישראל | L39: אחר | M39: קרנות סל | N39: לא | O39: 31/12/2018 | P39: ILS | Q39: אחר | S39: 31/03/2024 | U39: 200000 | V39: 1 | W39: 30 | X39: 60 | Y39: 0.00080640381 | Z39: 2.5890218e-05
A40: 424 | B40: 7228 | C40: גת אנרגיה בע"מ | D40: 514293380 | E40: ח.פ | F40: גת אנרגיה מניה לא סחירה | G40: 26211 | H40: פנימי | I40: מניות לא סחירות | J40: ישראל | K40: ישראל | L40: אחר | M40: קרנות סל | N40: לא | P40: USD | Q40: אחר | S40: 31/03/2024 | U40: 68145 | V40: 3.681 | W40: 225.989 | X40: 566.874 | Y40: 0.0076188226 | Z40: 0.00024460819
A41: 424 | B41: 7228 | C41: ג'נריישן קפיטל בע"מ | D41: 515846558 | E41: ח.פ | F41: ויולה ג'נריישן ניהול בע"מ(אוניברסי | G41: 56200 | H41: פנימי | I41: מניות לא סחירות | J41: ישראל | K41: ישראל | L41: אחר | M41: שירותים פיננסיים | N41: לא | O41: 30/08/2018 | P41: ILS | Q41: אחר | S41: 31/03/2024 | U41: 688 | V41: 1 | W41: 195840.64 | X41: 1347.384 | Y41: 0.018108921 | Z41: 0.00058140093
A42: 424 | B42: 7228 | C42: חפציבה גלובל בע"מ | D42: 511963183 | E42: ח.פ | F42: חפציבה גלובל | G42: 1085489 | H42: פנימי | I42: מניות לא סחירות | J42: ישראל | K42: ישראל | L42: אחר | M42: בנייה | N42: לא | P42: ILS | Q42: אחר | S42: 15/03/2018 | U42: 90000 | V42: 1 | W42: 0 | X42: 0 | Y42: 1.2096057e-09 | Z42: 3.8835327e-11
A43: 424 | B43: 7228 | C43: קרופס גארד בע"מ | D43: 516186301 | E43: ח.פ | F43: קרופס גארד בע"מ | G43: 62016738 | H43: פנימי | I43: מניות לא סחירות | J43: ישראל | K43: ישראל | L43: אחר | M43: ביוטכנולוגיה | N43: לא | O43: 15/06/2020 | P43: USD | Q43: אחר | S43: 31/03/2024 | U43: 256208.76 | V43: 3.681 | W43: 0 | X43: 0.001 | Y43: 1.2675384e-08 | Z43: 4.06953e-10
A44: 424 | B44: 7228 | C44: Straffan Asset Management Ltd | D44: 28068 | E44: פנימי | F44: BRIGHTON SPC - KIJANI COMMODIT | G44: KYG1367R1083 | H44: ISIN | I44: מניות לא סחירות | J44: חו"ל | K44: גלובלי | L44: אחר | M44: Diversified Financial Services Financial Services | N44: לא | P44: USD | Q44: אחר | S44: 27/09/2018 | U44: 118.77 | V44: 3.681 | W44: 0 | X44: 0 | Y44: 5.8758932e-12 | Z44: 1.886501e-13
A45: 424 | B45: 7228 | C45: EMERALD SIDEPOC | D45: 27703 | E45: פנימי | F45: EMERALD SIDEPOC | G45: XXX133661328 | H45: ISIN | I45: מניות לא סחירות | J45: חו"ל | K45: ארה"ב | L45: אחר | M45: Food & Staples Retailing Consumer Staples Distribution & Retail | N45: לא | P45: USD | Q45: אחר | S45: 27/09/2018 | U45: 403.95 | V45: 3.681 | W45: 0 | X45: 0 | Y45: 1.9984567e-11 | Z45: 6.4162e-13
A46: 424 | B46: 7228 | C46: ENLIVEX THERAPEUTICS LTD | D46: 28078 | E46: פנימי | F46: ENLIVEX THERAPEUTICS LTD | G46: IL009A4Z4OU8 | H46: ISIN | I46: מניות לא סחירות | J46: חו"ל | K46: ארה"ב | L46: אחר | M46: Pharmaceuticals | N46: לא | O46: 07/07/2020 | P46: USD | Q46: אחר | S46: 31/03/2024 | U46: 475 | V46: 3.681 | W46: 0 | X46: 0 | Y46: 2.3499615e-11 | Z46: 7.5447332e-13
A47: 424 | B47: 7228 | C47: מור תעשיות פלסטיק בע"מ | D47: 520042284 | E47: ח.פ | F47: MOR KEREN B | G47: XS0025555XXX | H47: ISIN | I47: מניות לא סחירות | J47: חו"ל | K47: אירלנד | L47: אחר | M47: Real Estate Management & Development | N47: לא | O47: 08/12/2019 | P47: EUR | Q47: אחר | S47: 31/03/2024 | U47: 30775.59 | V47: 3.979 | W47: 0 | X47: 0 | Y47: 1.6458588e-09 | Z47: 5.2841569e-11
A48: 424 | B48: 7228 | C48: Silk Technologies INC | D48: 28307 | E48: פנימי | F48: SILK | G48: 62018056 | H48: פנימי | I48: מניות לא סחירות | J48: חו"ל | K48: ארה"ב | L48: אחר | M48: Technology Hardware, Storage & Peripherals | N48: לא | O48: 25/03/2021 | P48: USD | Q48: מומחה בלתי תלוי | S48: 31/03/2024 | U48: 64043 | V48: 3.681 | W48: 444.69 | X48: 1048.322 | Y48: 0.014089519 | Z48: 0.00045235491
A49: 424 | B49: 7228 | C49: Supercom Ltd | D49: 520044074 | E49: ח.פ | F49: מ.אופנהימר אס.פי.סי.בי | G49: IL0010830961 | H49: ISIN | I49: מניות לא סחירות | J49: חו"ל | K49: ישראל | L49: אחר | M49: שירותים פיננסיים | N49: לא | O49: 24/11/2022 | P49: USD | Q49: אחר | S49: 31/03/2024 | U49: 236 | V49: 3.681 | W49: 16.6 | X49: 0.144 | Y49: 1.9381493e-06 | Z49: 6.2225783e-08
A50: 424 | B50: 7228 | C50: תאת טכנולוגיות בע"מ | D50: 520035791 | E50: ח.פ | F50: מ.אופנהימר תאת | G50: IL0010827264 | H50: ISIN | I50: מניות לא סחירות | J50: חו"ל | K50: גלובלי | L50: אחר | M50: תוכנה ואינטרנט | N50: לא | P50: USD | Q50: אחר | S50: 31/03/2024 | U50: 3784 | V50: 3.681 | W50: 1211 | X50: 168.679 | Y50: 0.0022670568 | Z50: 7.2785614e-05
A51: 424 | B51: 7228 | C51: מור תעשיות פלסטיק בע"מ | D51: 520042284 | E51: ח.פ | F51: מור קרן נדל"ן בינלאומי מניה A | G51: 10000495 | H51: פנימי | I51: מניות לא סחירות | J51: חו"ל | K51: ישראל | L51: אחר | M51: בנייה | N51: לא | O51: 08/12/2019 | P51: EUR | Q51: אחר | S51: 31/03/2024 | U51: 44698.99 | V51: 3.979 | W51: 0 | X51: 0 | Y51: 2.3904732e-09 | Z51: 7.6747993e-11
A52: 424 | B52: 7228 | C52: מור תעשיות פלסטיק בע"מ | D52: 520042284 | E52: ח.פ | F52: מור קרן נדל"ן בינלאומי מניה רגילה | G52: 9840879 | H52: פנימי | I52: מניות לא סחירות | J52: חו"ל | K52: ישראל | L52: אחר | M52: בנייה | N52: לא | P52: EUR | Q52: אחר | S52: 31/03/2024 | U52: 150000 | V52: 3.979 | W52: 0 | X52: 0.001 | Y52: 8.0219035e-09 | Z52: 2.5754942e-10
A53: 424 | B53: 7229 | C53: CIVAN ADVANCED TECHNOGIES | E53: אחר | F53: CIVAN ADVANCED TECHNOGIES | G53: 62021290 | H53: פנימי | I53: מניות לא סחירות | J53: ישראל | K53: גלובלי | L53: אחר | M53: Technology Hardware, Storage & Peripherals | N53: לא | O53: 07/08/2023 | P53: USD | Q53: אחר | S53: 31/03/2024 | U53: 194.24 | V53: 3.681 | W53: 90093.3 | X53: 644.165 | Y53: 0.18060852 | Z53: 0.0044935223
A54: 424 | B54: 7229 | C54: וואן זירו הבנק הדיגיטלי בעמ | D54: 515981728 | E54: ח.פ | F54: ONE ZERO DIGITAL BANK LTD | G54: 62020045 | H54: פנימי | I54: מניות לא סחירות | J54: ישראל | K54: ארה"ב | L54: אחר | M54: בנקים | N54: לא | O54: 03/01/2022 | P54: USD | Q54: אחר | S54: 31/03/2024 | U54: 204017 | V54: 3.681 | W54: 374.808 | X54: 2814.759 | Y54: 0.78919149 | Z54: 0.019635007
A55: 424 | B55: 7229 | C55: ג'נריישן קפיטל בע"מ | D55: 515846558 | E55: ח.פ | F55: ויולה ג'נריישן ניהול בע"מ(אוניברסי | G55: 56200 | H55: פנימי | I55: מניות לא סחירות | J55: ישראל | K55: ישראל | L55: אחר | M55: שירותים פיננסיים | N55: לא | O55: 30/08/2018 | P55: ILS | Q55: אחר | S55: 31/03/2024 | U55: 55 | V55: 1 | W55: 195840.64 | X55: 107.712 | Y55: 0.030199988 | Z55: 0.00075137274
A56: 969 | B56: 969 | C56: וואן זירו הבנק הדיגיטלי בעמ | D56: 515981728 | E56: ח.פ | F56: ONE ZERO DIGITAL BANK LTD | G56: 62020045 | H56: פנימי | I56: מניות לא סחירות | J56: ישראל | K56: ארה"ב | L56: אחר | M56: בנקים | N56: לא | O56: 03/01/2022 | P56: USD | Q56: אחר | S56: 31/03/2024 | U56: 81607 | V56: 3.681 | W56: 374.808 | X56: 1125.906 | Y56: 0.93800062 | Z56: 0.01532944
A57: 969 | B57: 969 | C57: ג'נריישן קפיטל בע"מ | D57: 515846558 | E57: ח.פ | F57: ויולה ג'נריישן ניהול בע"מ(אוניברסי | G57: 56200 | H57: פנימי | I57: מניות לא סחירות | J57: ישראל | K57: ישראל | L57: אחר | M57: שירותים פיננסיים | N57: לא | O57: 30/08/2018 | P57: ILS | Q57: אחר | S57: 31/03/2024 | U57: 38 | V57: 1 | W57: 195840.64 | X57: 74.419 | Y57: 0.06199938 | Z57: 0.0010132358

Sheet קרנות השקעה
A1: מספר קופה/קרן/ח.פ. עבור חברת ביטוח | B1: מספר מסלול | C1: שם שותף כללי קרן השקעות | D1: מספר מזהה שותף כללי קרן השקעות | E1: סוג מספר מזהה שותף כללי קרן השקעות | F1: שם קרן השקעה | G1: מספר מזהה קרן השקעה | H1: סוג מספר מזהה קרן השקעות | I1: מאפיין עיקרי | J1: אסטרטגיית קרן ההשקעה | K1: ישראל/חו"ל | L1: מדינת התאגדות קרן השקעה | M1: מיקום משרד השותף הכללי | N1: מדינה לפי חשיפה כלכלית | O1: בעל עניין/צד קשור | P1: תאריך רכישה | Q1: מטבע פעילות | R1: סוג גורם משערך | S1: תלות/אי-תלות המשערך | T1: תאריך שערוך אחרון | U1: שער חליפין | V1: NAV (במטבע הדיווח של קרן ההשקעה) | W1: שווי הוגן (באלפי ש"ח) | X1: שיעור החזקה בקרן השקעה | Y1: שיעור מנכסי אפיק ההשקעה | Z1: שיעור מסך נכסי ההשקעה
A2: 1182 | B2: 1182 | C2: JTLV III FUND, LIMITED PARTNERSHIP | D2: 540316908 | E2: אחר | F2: 3 JTLV | G2: 50007566 | H2: פנימי | I2: פרייבט אקוויטי | J2: Direct Real Estate | K2: ישראל | L2: ישראל | M2: ישראל | N2: ישראל | O2: לא | P2: 06/06/2022 | Q2: ILS | R2: דיווח מנהל הקרן | S2: אי-תלות | T2: 31/03/2024 | U2: 1 | V2: 1165.02 | W2: 1165.02 | Y2: 0.01689926 | Z2: 0.0030671152
A3: 1182 | B3: 1182 | C3: FIMI OPPORTUNITY FUND , L.P | D3: 530278548 | E3: מספר שותפות | F3: FIMI ISRAEL OPPORTUNITY FOUND 7 | G3: 62018312 | H3: פנימי | I3: פרייבט אקוויטי | J3: Other | K3: ישראל | L3: ישראל | M3: ישראל | N3: ישראל | O3: לא | P3: 24/05/2021 | Q3: USD | R3: דיווח מנהל הקרן | S3: אי-תלות | T3: 31/03/2024 | U3: 3.681 | V3: 201.36 | W3: 741.206 | Y3: 0.010751604 | Z3: 0.0019513522
A4: 1182 | B4: 1182 | C4: Firstime Ventures General Partner L.P. | D4: 27986 | E4: פנימי | F4: FIRST TIME | G4: 60390093 | H4: פנימי | I4: פרייבט אקוויטי | J4: Co-Investment/Direct | K4: חו"ל | L4: איי קיימן | M4: ישראל | N4: ישראל | O4: לא | P4: 02/07/2015 | Q4: USD | R4: דיווח מנהל הקרן | S4: אי-תלות | T4: 31/03/2024 | U4: 3.681 | V4: 68.302 | W4: 251.418 | Y4: 0.0036469606 | Z4: 0.00066190167
A5: 1182 | B5: 1182 | C5: Firstime Ventures General Partner L.P. | D5: 27986 | E5: פנימי | F5: FIRSTIME III | G5: 62019724 | H5: פנימי | I5: פרייבט אקוויטי | J5: Co-Investment/Direct | K5: חו"ל | L5: איי קיימן | M5: ישראל | N5: ישראל | O5: לא | P5: 18/11/2021 | Q5: USD | R5: דיווח מנהל הקרן | S5: אי-תלות | T5: 31/03/2024 | U5: 3.681 | V5: 58.51 | W5: 215.376 | Y5: 0.0031241515 | Z5: 0.00056701493
A6: 1182 | B6: 1182 | C6: Firstime Ventures General Partner L.P. | D6: 27986 | E6: פנימי | F6: FIRSTIME VENTURES II L.P | G6: 62000563 | H6: פנימי | I6: פרייבט אקוויטי | J6: Co-Investment/Direct | K6: חו"ל | L6: איי קיימן | M6: ישראל | N6: ישראל | O6: לא | P6: 12/02/2017 | Q6: USD | R6: דיווח מנהל הקרן | S6: אי-תלות | T6: 31/03/2024 | U6: 3.681 | V6: 67.789 | W6: 249.533 | Y6: 0.0036196094 | Z6: 0.00065693758
A7: 1182 | B7: 1182 | C7: ION ISRAEL FEEDER FUND LTD | D7: 27177 | E7: פנימי | F7: ION ISR. FEEDER 2013( USA ) 07 ׁ | G7: 77419109 | H7: פנימי | I7: קרן גידור (Hedge Fund) | J7: Other | K7: ישראל | L7: איי קיימן | M7: ישראל | N7: ישראל | O7: לא | P7: 18/02/2021 | Q7: USD | R7: אחר | S7: אי-תלות | T7: 31/03/2024 | U7: 3.681 | V7: 401.58 | W7: 1478.217 | Y7: 0.02144236 | Z7: 0.0038916608
A8: 1182 | B8: 1182 | C8: ISRAEL INFRASTRUCTURE FUND III, L.P. | D8: 530274141 | E8: מספר תאגיד או שותפות בחו"ל | F8: ISRAEL INFR III | G8: 60415775 | H8: פנימי | I8: פרייבט אקוויטי | J8: Value Added Infrastructure | K8: חו"ל | L8: איי קיימן | M8: ישראל | N8: ישראל | O8: לא | P8: 13/10/2016 | Q8: USD | R8: דיווח מנהל הקרן | S8: אי-תלות | T8: 31/03/2024 | U8: 3.681 | V8: 107.755 | W8: 396.645 | Y8: 0.0057535569 | Z8: 0.0010442364
A9: 1182 | B9: 1182 | C9: ISRAEL INFRASTRUCTURE FUND IV, LP | D9: 540294725 | E9: פנימי | F9: Israel Infrastructure Fund IV | G9: 62017538 | H9: פנימי | I9: פרייבט אקוויטי | J9: Value Added Infrastructure | K9: ישראל | L9: ישראל | M9: ישראל | N9: ישראל | O9: לא | P9: 13/10/2020 | Q9: USD | R9: אחר | S9: אי-תלות | T9: 31/03/2024 | U9: 3.681 | V9: 415.859 | W9: 1530.777 | Y9: 0.022204773 | Z9: 0.0040300343
A10: 1182 | B10: 1182 | C10: Israel secondary fund | D10: 12962 | E10: פנימי | F10: ISRAEL SECONDARY FUND II L.P | G10: 62001189 | H10: פנימי | I10: פרייבט אקוויטי | J10: Secondaries | K10: ישראל | L10: איי קיימן | M10: ישראל | N10: ישראל | O10: לא | P10: 06/04/2017 | Q10: USD | R10: דיווח מנהל הקרן | S10: אי-תלות | T10: 31/03/2024 | U10: 3.681 | V10: 132.922 | W10: 489.286 | Y10: 0.0070973645 | Z10: 0.0012881295
A11: 1182 | B11: 1182 | C11: JVP VII OPPORTUNITY LP | D11: 500452859 | E11: פנימי | F11: JVP VII OPPORTUNITY LP | G11: 60401809 | H11: פנימי | I11: פרייבט אקוויטי | J11: Growth Venture Capital | K11: חו"ל | L11: איי קיימן | M11: ישראל | N11: ארה"ב | O11: לא | P11: 28/02/2016 | Q11: USD | R11: דיווח מנהל הקרן | S11: אי-תלות | T11: 31/03/2024 | U11: 3.681 | V11: 198.638 | W11: 731.186 | Y11: 0.010606259 | Z11: 0.0019249729
A12: 1182 | B12: 1182 | C12: Klirmark Opportunity Fund | D12: CO-101523 | E12: מספר תאגיד או שותפות בחו"ל | F12: KLIRMARK III | G12: 50000983 | H12: פנימי | I12: פרייבט אקוויטי | J12: Special Situations Debt | K12: חו"ל | L12: איי קיימן | M12: ישראל | N12: גלובלי | O12: לא | P12: 06/11/2019 | Q12: ILS | R12: דיווח מנהל הקרן | S12: אי-תלות | T12: 31/03/2024 | U12: 1 | V12: 768.204 | W12: 768.204 | Y12: 0.011143231 | Z12: 0.0020224302
A13: 1182 | B13: 1182 | C13: Klirmark Opportunity Fund | D13: CO-101523 | E13: מספר תאגיד או שותפות בחו"ל | F13: Klirmark IV | G13: 50007897 | H13: פנימי | I13: פרייבט אקוויטי | J13: Special Situations Debt | K13: חו"ל | L13: איי קיימן | M13: ישראל | N13: גלובלי | O13: לא | P13: 17/04/2023 | Q13: ILS | R13: אחר | S13: אי-תלות | T13: 31/03/2024 | U13: 1 | V13: 391.665 | W13: 391.665 | Y13: 0.0056813168 | Z13: 0.0010311252
... A28: 1182 | B28: 1182 | C28: Vintage Fund of Funds VII (Access) L.P. | D28: 500472543 | E28: אחר | F28: Vintage FOF VII Access | G28: 62020748 | H28: פנימי | I28: פרייבט אקוויטי | J28: FOF/Managed Account | K28: חו"ל | L28: ארה"ב | M28: ישראל | N28: ארה"ב | O28: לא | P28: 15/08/2022 | Q28: USD | R28: אחר | S28: אי-תלות | T28: 31/03/2024 | U28: 3.681 | V28: 27.472 | W28: 101.125 | Y28: 0.001466876 | Z28: 0.00026622927
A29: 1182 | B29: 1182 | C29: וינטג' | E29: אחר | F29: Vintage Growth Fund III, L.P | G29: 62015151 | H29: פנימי | I29: פרייבט אקוויטי | J29: Growth Venture Capital | K29: חו"ל | L29: ארה"ב | M29: ישראל | N29: ישראל | O29: לא | P29: 06/01/2020 | Q29: USD | R29: דיווח מנהל הקרן | S29: אי-תלות | T29: 31/03/2024 | U29: 3.681 | V29: 205.874 | W29: 757.824 | Y29: 0.010992654 | Z29: 0.0019951014
A30: 1182 | B30: 1182 | C30: וינטג' | E30: אחר | F30: Vintage Secondary Fund IV | G30: 62007349 | H30: פנימי | I30: פרייבט אקוויטי | J30: Secondaries | K30: חו"ל | L30: איי קיימן | M30: ישראל | N30: ישראל | O30: לא | P30: 29/05/2018 | Q30: USD | R30: דיווח מנהל הקרן | S30: אי-תלות | T30: 31/03/2024 | U30: 3.681 | V30: 131.702 | W30: 484.795 | Y30: 0.0070322252 | Z30: 0.0012763071
A31: 1182 | B31: 1182 | C31: Vintage Secondary Fund V L.P. | D31: 500471925 | E31: אחר | F31: Vintage Secondary Fund V | G31: 62020755 | H31: פנימי | I31: פרייבט אקוויטי | J31: Secondaries | K31: חו"ל | L31: ארה"ב | M31: ישראל | N31: ישראל | O31: לא | P31: 15/08/2022 | Q31: USD | R31: אחר | S31: אי-תלות | T31: 31/03/2024 | U31: 3.681 | V31: 100.787 | W31: 370.999 | Y31: 0.0053815427 | Z31: 0.000976718
A32: 1182 | B32: 1182 | C32: אלפא לונג ביאס ג'י פי בע"מ | D32: 514517267 | E32: ח.פ | F32: אלפא קרן השקעות 1 - השתלמות | G32: 50006410 | H32: פנימי | I32: קרן גידור (Hedge Fund) | J32: Other | K32: ישראל | L32: איי קיימן | M32: ישראל | N32: ישראל | O32: לא | P32: 03/09/2020 | Q32: ILS | R32: אחר | S32: אי-תלות | T32: 31/03/2024 | U32: 1 | V32: 920.717 | W32: 920.717 | Y32: 0.013355508 | Z32: 0.0024239453
A33: 1182 | B33: 1182 | C33: קרן ארבל פאנד בע"מ | D33: 540307832 | E33: ח.פ | F33: ארבל פאנד 2 | G33: 50007004 | H33: פנימי | I33: פרייבט אקוויטי | J33: Debt Infrastructure | K33: ישראל | L33: ישראל | M33: ישראל | N33: ישראל | O33: לא | P33: 20/09/2021 | Q33: ILS | R33: דיווח מנהל הקרן | S33: אי-תלות | T33: 31/03/2024 | U33: 1 | V33: 866.24 | W33: 866.24 | Y33: 0.012565295 | Z33: 0.0022805263
A34: 1182 | B34: 1182 | C34: גיזה חוב | D34: 513540757 | E34: ח.פ | F34: גיזה חוב | G34: 50007350 | H34: פנימי | I34: פרייבט אקוויטי | J34: Mezzanine Debt | K34: ישראל | L34: ישראל | M34: ישראל | N34: ישראל | O34: לא | P34: 14/02/2022 | Q34: ILS | R34: אחר | S34: אי-תלות | T34: 31/03/2024 | U34: 1 | V34: 1491.012 | W34: 1491.012 | Y34: 0.021627962 | Z34: 0.0039253466
A35: 1182 | B35: 1182 | C35: FIMI OPPORTUNITY FUND , L.P | D35: 530278548 | E35: מספר שותפות | F35: פימי 6 | G35: 60400892 | H35: פנימי | I35: פרייבט אקוויטי | J35: Other | K35: ישראל | L35: ישראל | M35: ישראל | N35: ישראל | O35: לא | P35: 12/07/2016 | Q35: USD | R35: דיווח מנהל הקרן | S35: אי-תלות | T35: 31/03/2024 | U35: 3.681 | V35: 567.915 | W35: 2090.495 | Y35: 0.030323786 | Z35: 0.0055035869
A36: 1182 | B36: 1182 | C36: קרן ארבל פאנד בע"מ | D36: 540307832 | E36: ח.פ | F36: קרן ארבל פאנד בע"מ | G36: 18952 | H36: פנימי | I36: פרייבט אקוויטי | J36: Debt Infrastructure | K36: ישראל | L36: ישראל | M36: ישראל | N36: ישראל | O36: לא | P36: 12/12/2017 | Q36: ILS | R36: דיווח מנהל הקרן | S36: אי-תלות | T36: 31/03/2024 | U36: 1 | V36: 133.95 | W36: 133.95 | Y36: 0.0019430235 | Z36: 0.00035264722
A37: 1182 | B37: 1182 | C37: רגנאר 1 השקעות שותפות מוגבלת | D37: 540304573 | E37: אחר | F37: קרן רגנאר 1 | G37: 50007160 | H37: פנימי | I37: פרייבט אקוויטי | J37: Other | K37: ישראל | L37: ישראל | M37: ישראל | N37: ישראל | O37: לא | P37: 08/12/2021 | Q37: ILS | R37: אחר | S37: אי-תלות | T37: 31/03/2024 | U37: 1 | V37: 421.606 | W37: 421.606 | Y37: 0.0061156335 | Z37: 0.0011099511
A38: 1182 | B38: 1182 | C38: ARCLIGHT | D38: 89940 | E38: פנימי | F38: ARCLIGHT 3C SPV | G38: 62020672 | H38: פנימי | I38: פרייבט אקוויטי | J38: Other | K38: חו"ל | L38: ארה"ב | M38: ארה"ב | N38: ארה"ב | O38: לא | P38: 25/07/2022 | Q38: USD | R38: אחר | S38: אי-תלות | T38: 31/03/2024 | U38: 3.681 | V38: 84.827 | W38: 312.25 | Y38: 0.0045293564 | Z38: 0.00082205126
A39: 1182 | B39: 1182 | C39: ARDIAN Infrastructure Fund VI | D39: 98450046FF9E70CFBA37 | E39: LEI | F39: ARDIAN Infrastructure Fund VI | G39: 62021365 | H39: פנימי | I39: פרייבט אקוויטי | J39: Core-Plus | K39: חו"ל | L39: לוכסמבורג | M39: לוכסמבורג | N39: אירופה | O39: לא | P39: 04/09/2023 | Q39: USD | R39: דיווח מנהל הקרן | S39: אי-תלות | T39: 31/03/2024 | U39: 3.681 | V39: 41.856 | W39: 154.072 | Y39: 0.0022348989 | Z39: 0.00040562087
A40: 1182 | B40: 1182 | C40: ASF IX | D40: SL35491 | E40: מספר תאגיד או שותפות בחו"ל | F40: ASF IX | G40: 62020896 | H40: פנימי | I40: פרייבט אקוויטי | J40: Secondaries | K40: חו"ל | L40: בריטניה | M40: האי ג'רזי | N40: גלובלי | O40: לא | P40: 06/10/2022 | Q40: USD | R40: דיווח מנהל הקרן | S40: אי-תלות | T40: 31/03/2024 | U40: 3.681 | V40: 39.147 | W40: 144.101 | Y40: 0.0020902633 | Z40: 0.00037937037
A41: 1182 | B41: 1182 | C41: ASF VIII INFRASTRUCTURE L.P | D41: 984500641D7574IF1B24 | E41: LEI | F41: ASF VIII INFRASTRUCTURE L.P | G41: 62019815 | H41: פנימי | I41: פרייבט אקוויטי | J41: Secondaries | K41: חו"ל | L41: בריטניה | M41: האי ג'רזי | N41: גלובלי | O41: לא | P41: 07/12/2021 | Q41: USD | R41: דיווח מנהל הקרן | S41: אי-תלות | T41: 31/03/2024 | U41: 3.681 | V41: 200.636 | W41: 738.54 | Y41: 0.010712934 | Z41: 0.0019443338
A42: 1182 | B42: 1182 | C42: Axiom Asia Co-investment Fund II, L.P. | D42: 1840974 | E42: מספר תאגיד או שותפות בחו"ל | F42: Axiom Asia Co-investment II | G42: 62019757 | H42: פנימי | I42: פרייבט אקוויטי | J42: Co-Investment/Direct | K42: חו"ל | L42: איי קיימן | M42: איי קיימן | N42: אסיה | O42: לא | P42: 22/11/2021 | Q42: USD | R42: דיווח מנהל הקרן | S42: אי-תלות | T42: 31/03/2024 | U42: 3.681 | V42: 82.821 | W42: 304.863 | Y42: 0.0044222135 | Z42: 0.00080260545
... A121: 424 | B121: 7228 | C121: Vintage Growth Fund I (Israel), L.P. | D121: 500442751 | E121: אחר | F121: Vintage Growth Fund I (Israel), L.P. | G121: 60297512 | H121: פנימי | I121: פרייבט אקוויטי | J121: Growth Venture Capital | K121: ישראל | L121: ישראל | M121: ישראל | N121: ישראל | O121: לא | P121: 30/12/2014 | Q121: USD | R121: דיווח מנהל הקרן | S121: אי-תלות | T121: 31/03/2024 | U121: 3.681 | V121: 206.819 | W121: 761.3 | Y121: 0.0017720863 | Z121: 0.00032850372
A122: 424 | B122: 7228 | C122: וינטג' | E122: אחר | F122: Vintage Growth Fund III, L.P | G122: 62015151 | H122: פנימי | I122: פרייבט אקוויטי | J122: Growth Venture Capital | K122: חו"ל | L122: ארה"ב | M122: ישראל | N122: ישראל | O122: לא | P122: 06/01/2020 | Q122: USD | R122: דיווח מנהל הקרן | S122: אי-תלות | T122: 31/03/2024 | U122: 3.681 | V122: 686.251 | W122: 2526.091 | Y122: 0.0058800098 | Z122: 0.0010900175
A123: 424 | B123: 7228 | C123: Vintage Secondary Fund III (Israel), L.P. | D123: 500442769 | E123: אחר | F123: Vintage Secondary Fund III | G123: 60335908 | H123: פנימי | I123: פרייבט אקוויטי | J123: Secondaries | K123: ישראל | L123: ישראל | M123: ישראל | N123: ישראל | O123: לא | P123: 30/12/2014 | Q123: USD | R123: דיווח מנהל הקרן | S123: אי-תלות | T123: 31/03/2024 | U123: 3.681 | V123: 230.915 | W123: 849.998 | Y123: 0.0019785499 | Z123: 0.0003667773
A124: 424 | B124: 7228 | C124: וינטג' | E124: אחר | F124: Vintage Secondary Fund IV | G124: 62007349 | H124: פנימי | I124: פרייבט אקוויטי | J124: Secondaries | K124: חו"ל | L124: איי קיימן | M124: ישראל | N124: ישראל | O124: לא | P124: 28/05/2018 | Q124: USD | R124: דיווח מנהל הקרן | S124: אי-תלות | T124: 31/03/2024 | U124: 3.681 | V124: 1053.606 | W124: 3878.325 | Y124: 0.0090276183 | Z124: 0.0016735112
A125: 424 | B125: 7228 | C125: Vintage Secondary Fund V L.P. | D125: 500471925 | E125: אחר | F125: Vintage Secondary Fund V | G125: 62020755 | H125: פנימי | I125: פרייבט אקוויטי | J125: Secondaries | K125: חו"ל | L125: ארה"ב | M125: ישראל | N125: ישראל | O125: לא | P125: 15/08/2022 | Q125: USD | R125: אחר | S125: אי-תלות | T125: 31/03/2024 | U125: 3.681 | V125: 403.15 | W125: 1483.995 | Y125: 0.003454311 | Z125: 0.00064034919
A126: 424 | B126: 7228 | C126: אורגרין | D126: 530223684 | E126: פנימי | F126: אוורגרין 5 קרן הון ס | G126: 9840809 | H126: פנימי | I126: פרייבט אקוויטי | J126: Other | K126: חו"ל | L126: איי קיימן | M126: ישראל | N126: ישראל | O126: לא | P126: 30/12/2014 | Q126: USD | R126: דיווח מנהל הקרן | S126: אי-תלות | T126: 31/03/2024 | U126: 3.681 | V126: 360.523 | W126: 1327.085 | Y126: 0.0030890693 | Z126: 0.00057264186
A127: 424 | B127: 7228 | C127: אלפא לונג ביאס ג'י פי בע"מ | D127: 514517267 | E127: ח.פ | F127: אלפא קרן השקעות 1 | G127: 50007376 | H127: פנימי | I127: קרן גידור (Hedge Fund) | J127: Other | K127: ישראל | L127: איי קיימן | M127: ישראל | N127: ישראל | O127: לא | P127: 27/02/2022 | Q127: ILS | R127: דיווח מנהל הקרן | S127: אי-תלות | T127: 31/03/2024 | U127: 1 | V127: 11141.34 | W127: 11141.34 | Y127: 0.025933817 | Z127: 0.0048075286
A128: 424 | B128: 7228 | C128: קרן ארבל פאנד בע"מ | D128: 540307832 | E128: ח.פ | F128: ארבל פאנד 2 | G128: 50007004 | H128: פנימי | I128: פרייבט אקוויטי | J128: Debt Infrastructure | K128: ישראל | L128: ישראל | M128: ישראל | N128: ישראל | O128: לא | P128: 20/09/2021 | Q128: ILS | R128: דיווח מנהל הקרן | S128: אי-תלות | T128: 31/03/2024 | U128: 1 | V128: 4949.95 | W128: 4949.95 | Y128: 0.011522053 | Z128: 0.0021359215
A129: 424 | B129: 7228 | C129: גיזה חוב | D129: 513540757 | E129: ח.פ | F129: גיזה חוב | G129: 50007350 | H129: פנימי | I129: פרייבט אקוויטי | J129: Mezzanine Debt | K129: ישראל | L129: ישראל | M129: ישראל | N129: ישראל | O129: לא | P129: 14/02/2022 | Q129: ILS | R129: אחר | S129: אי-תלות | T129: 31/03/2024 | U129: 1 | V129: 5964.058 | W129: 5964.058 | Y129: 0.013882602 | Z129: 0.0025735127
A130: 424 | B130: 7228 | C130: מנוף אוריגו 2 שותפות מוגבלת | D130: 550234843 | E130: ח.פ | F130: מנוף אוריגו 1 בע"מ | G130: 26427 | H130: פנימי | I130: פרייבט אקוויטי | J130: Special Situations Debt | K130: ישראל | L130: ישראל | M130: ישראל | N130: ישראל | O130: לא | P130: 30/12/2014 | Q130: ILS | R130: דיווח מנהל הקרן | S130: אי-תלות | T130: 31/03/2024 | U130: 1 | V130: 8.613 | W130: 8.613 | Y130: 2.0049679e-05 | Z130: 3.7167459e-06
A131: 424 | B131: 7228 | C131: FIMI OPPORTUNITY FUND , L.P | D131: 530278548 | E131: מספר שותפות | F131: פימי 2 קרן הון סיכון | G131: 9840906 | H131: פנימי | I131: פרייבט אקוויטי | J131: Other | K131: ישראל | L131: ישראל | M131: ישראל | N131: ישראל | O131: לא | P131: 30/12/2014 | Q131: USD | R131: דיווח מנהל הקרן | S131: אי-תלות | T131: 31/03/2024 | U131: 3.681 | V131: 20.735 | W131: 76.326 | Y131: 0.00017766429 | Z131: 3.2934842e-05
A132: 424 | B132: 7228 | C132: FIMI OPPORTUNITY FUND , L.P | D132: 530278548 | E132: מספר שותפות | F132: פימי 4 | G132: 9840909 | H132: פנימי | I132: פרייבט אקוויטי | J132: Other | K132: ישראל | L132: ישראל | M132: ישראל | N132: ישראל | O132: לא | P132: 30/12/2014 | Q132: USD | R132: דיווח מנהל הקרן | S132: אי-תלות | T132: 31/03/2024 | U132: 3.681 | V132: 35.96 | W132: 132.368 | Y132: 0.00030811391 | Z132: 5.7117177e-05
A133: 424 | B133: 7228 | C133: FIMI OPPORTUNITY FUND , L.P | D133: 530278548 | E133: מספר שותפות | F133: פימי 6 | G133: 60400892 | H133: פנימי | I133: פרייבט אקוויטי | J133: Other | K133: ישראל | L133: ישראל | M133: ישראל | N133: ישראל | O133: לא | P133: 12/07/2016 | Q133: USD | R133: דיווח מנהל הקרן | S133: אי-תלות | T133: 31/03/2024 | U133: 3.681 | V133: 2271.666 | W133: 8362.002 | Y133: 0.019464322 | Z133: 0.0036082342
A134: 424 | B134: 7228 | C134: פלנוס טכנולוגיות בע"מ | D134: 512912775 | E134: ח.פ | F134: פלאנוס 2 L.P קרן השקעה | G134: 9840913 | H134: פנימי | I134: פרייבט אקוויטי | J134: Value Added Infrastructure | K134: ישראל | L134: ישראל | M134: ישראל | N134: ישראל | O134: לא | P134: 30/12/2014 | Q134: USD | R134: דיווח מנהל הקרן | S134: אי-תלות | T134: 31/03/2024 | U134: 3.681 | V134: 8.226 | W134: 30.281 | Y134: 7.0485077e-05 | Z134: 1.30663e-05
A135: 424 | B135: 7228 | C135: פלנוס | E135: אחר | F135: פלנוס מזנין קרן השקעה | G135: 9840922 | H135: פנימי | I135: פרייבט אקוויטי | J135: Value Added Real Estate | K135: ישראל | L135: ישראל | M135: ישראל | N135: ישראל | O135: לא | P135: 30/12/2014 | Q135: USD | R135: דיווח מנהל הקרן | S135: אי-תלות | T135: 31/03/2024 | U135: 3.681 | V135: 4.767 | W135: 17.547 | Y135: 4.0844106e-05 | Z135: 7.5715506e-06
A136: 424 | B136: 7228 | C136: AVIV VENTURES I PARTNERS , L.P | D136: 550205660 | E136: ח.פ | F136: קרן אביב 2 קרן הון סיכון | G136: 9840936 | H136: פנימי | I136: פרייבט אקוויטי | J136: Growth Venture Capital | K136: ישראל | L136: ישראל | M136: ישראל | N136: ישראל | O136: לא | P136: 30/12/2014 | Q136: USD | R136: דיווח מנהל הקרן | S136: אי-תלות | T136: 31/03/2024 | U136: 3.681 | V136: 333.01 | W136: 1225.81 | Y136: 0.0028533314 | Z136: 0.00052894151
A137: 424 | B137: 7228 | C137: קרן ארבל פאנד בע"מ | D137: 540307832 | E137: ח.פ | F137: קרן ארבל פאנד בע"מ | G137: 18952 | H137: פנימי | I137: פרייבט אקוויטי | J137: Debt Infrastructure | K137: ישראל | L137: ישראל | M137: ישראל | N137: ישראל | O137: לא | P137: 12/12/2017 | Q137: ILS | R137: דיווח מנהל הקרן | S137: אי-תלות | T137: 31/03/2024 | U137: 1 | V137: 1404.301 | W137: 1404.301 | Y137: 0.0032688067 | Z137: 0.00060596099
A138: 424 | B138: 7228 | C138: JVP V LP | D138: 500438023 | E138: פנימי | F138: קרן הון סיכון PVJ 5 | G138: 9840777 | H138: פנימי | I138: פרייבט אקוויטי | J138: Seed/Early Stage Venture Capital | K138: חו"ל | L138: איי קיימן | M138: ישראל | N138: ישראל | O138: לא | P138: 30/12/2014 | Q138: USD | R138: דיווח מנהל הקרן | S138: אי-תלות | T138: 31/03/2024 | U138: 3.681 | V138: 103.876 | W138: 382.368 | Y138: 0.0008900411 | Z138: 0.00016499299
A139: 424 | B139: 7228 | C139: רגנאר 1 השקעות שותפות מוגבלת | D139: 540304573 | E139: אחר | F139: קרן רגנאר 1 | G139: 50007160 | H139: פנימי | I139: פרייבט אקוויטי | J139: Other | K139: ישראל | L139: ישראל | M139: ישראל | N139: ישראל | O139: לא | P139: 08/12/2021 | Q139: ILS | R139: אחר | S139: אי-תלות | T139: 31/03/2024 | U139: 1 | V139: 2108.034 | W139: 2108.034 | Y139: 0.0049068939 | Z139: 0.00090962439
A140: 424 | B140: 7228 | C140: קרן תשתיות ישראל I | D140: 550224729 | E140: ח.פ | F140: קרן תשתיות ישראל | G140: 9840947 | H140: פנימי | I140: פרייבט אקוויטי | J140: Value Added Infrastructure | K140: חו"ל | L140: איי קיימן | M140: ישראל | N140: ארה"ב | O140: לא | P140: 30/12/2014 | Q140: USD | R140: דיווח מנהל הקרן | S140: אי-תלות | T140: 31/03/2024 | U140: 3.681 | V140: 11.948 | W140: 43.979 | Y140: 0.00010237151 | Z140: 1.8977305e-05
A141: 424 | B141: 7228 | C141: ARCLIGHT | D141: 89940 | E141: פנימי | F141: ARCLIGHT 3C SPV | G141: 62020672 | H141: פנימי | I141: פרייבט אקוויטי | J141: Other | K141: חו"ל | L141: ארה"ב | M141: ארה"ב | N141: ארה"ב | O141: לא | P141: 25/07/2022 | Q141: USD | R141: אחר | S141: אי-תלות | T141: 31/03/2024 | U141: 3.681 | V141: 988.221 | W141: 3637.642 | Y141: 0.0084673782 | Z141: 0.0015696557
A142: 424 | B142: 7228 | C142: ARDIAN Infrastructure Fund VI | D142: 98450046FF9E70CFBA37 | E142: LEI | F142: ARDIAN Infrastructure Fund VI | G142: 62021365 | H142: פנימי | I142: פרייבט אקוויטי | J142: Core-Plus | K142: חו"ל | L142: לוכסמבורג | M142: לוכסמבורג | N142: אירופה | O142: לא | P142: 04/09/2023 | Q142: USD | R142: דיווח מנהל הקרן | S142: אי-תלות | T142: 31/03/2024 | U142: 3.681 | V142: 313.92 | W142: 1155.539 | Y142: 0.0026897618 | Z142: 0.00049861949
A143: 424 | B143: 7228 | C143: ASF IX | D143: SL35491 | E143: מספר תאגיד או שותפות בחו"ל | F143: ASF IX | G143: 62020896 | H143: פנימי | I143: פרייבט אקוויטי | J143: Secondaries | K143: חו"ל | L143: בריטניה | M143: האי ג'רזי | N143: גלובלי | O143: לא | P143: 06/10/2022 | Q143: USD | R143: דיווח מנהל הקרן | S143: אי-תלות | T143: 31/03/2024 | U143: 3.681 | V143: 352.307 | W143: 1296.842 | Y143: 0.0030186731 | Z143: 0.00055959202
A144: 424 | B144: 7228 | C144: ASF VIII INFRASTRUCTURE L.P | D144: 984500641D7574IF1B24 | E144: LEI | F144: ASF VIII INFRASTRUCTURE L.P | G144: 62019815 | H144: פנימי | I144: פרייבט אקוויטי | J144: Secondaries | K144: חו"ל | L144: בריטניה | M144: האי ג'רזי | N144: גלובלי | O144: לא | P144: 07/12/2021 | Q144: USD | R144: דיווח מנהל הקרן | S144: אי-תלות | T144: 31/03/2024 | U144: 3.681 | V144: 1070.054 | W144: 3938.87 | Y144: 0.0091685495 | Z144: 0.0016996366
A145: 424 | B145: 7228 | C145: Axiom Asia Co-investment Fund II, L.P. | D145: 1840974 | E145: מספר תאגיד או שותפות בחו"ל | F145: Axiom Asia Co-investment II | G145: 62019757 | H145: פנימי | I145: פרייבט אקוויטי | J145: Co-Investment/Direct | K145: חו"ל | L145: איי קיימן | M145: איי קיימן | N145: אסיה | O145: לא | P145: 22/11/2021 | Q145: USD | R145: דיווח מנהל הקרן | S145: אי-תלות | T145: 31/03/2024 | U145: 3.681 | V145: 828.103 | W145: 3048.246 | Y145: 0.0070954357 | Z145: 0.0013153293
A146: 424 | B146: 7228 | C146: Blue Atlantic Partners III Cayman Feeder I, LP | D146: 1683231 | E146: מספר תאגיד או שותפות בחו"ל | F146: BLUE ATLANTIC PARTNERS 3 | G146: 62013909 | H146: פנימי | I146: פרייבט אקוויטי | J146: Value Added Real Estate | K146: חו"ל | L146: איי קיימן | M146: ארה"ב | N146: ארה"ב | O146: לא | P146: 03/12/2019 | Q146: USD | R146: דיווח מנהל הקרן | S146: אי-תלות | T146: 31/03/2024 | U146: 3.681 | V146: 1277.21 | W146: 4701.41 | Y146: 0.010943523 | Z146: 0.0020286755
A147: 424 | B147: 7228 | C147: COLCHIS INCOME FUND, LTD. | D147: 618052 | E147: מספר תאגיד או שותפות בחו"ל | F147: COLCHIS INCOME FUND | G147: 62011226 | H147: פנימי | I147: פרייבט אקוויטי | J147: Direct Lending Debt | K147: חו"ל | L147: איי קיימן | M147: ארה"ב | N147: ארה"ב | O147: לא | P147: 18/07/2019 | Q147: USD | R147: דיווח מנהל הקרן | S147: אי-תלות | T147: 31/03/2024 | U147: 3.681 | V147: 127.766 | W147: 470.307 | Y147: 0.0010947394 | Z147: 0.00020293931
... A229: 969 | B229: 969 | C229: Vintage Fund of Funds IV (Israel), L.P. | D229: 500450531 | E229: אחר | F229: Vintage FOF IV | G229: 60406600 | H229: פנימי | I229: פרייבט אקוויטי | J229: FOF/Managed Account | K229: חו"ל | L229: איי קיימן | M229: ישראל | N229: ישראל | O229: לא | P229: 05/04/2019 | Q229: USD | R229: דיווח מנהל הקרן | S229: אי-תלות | T229: 31/03/2024 | U229: 3.681 | V229: 228.344 | W229: 840.535 | Y229: 0.080628282 | Z229: 0.011444048
A230: 969 | B230: 969 | C230: וינטג' | E230: אחר | F230: Vintage Secondary Fund IV | G230: 62007349 | H230: פנימי | I230: פרייבט אקוויטי | J230: Secondaries | K230: חו"ל | L230: איי קיימן | M230: ישראל | N230: ישראל | O230: לא | P230: 29/05/2018 | Q230: USD | R230: דיווח מנהל הקרן | S230: אי-תלות | T230: 31/03/2024 | U230: 3.681 | V230: 131.702 | W230: 484.795 | Y230: 0.04650399 | Z230: 0.0066005859
A231: 969 | B231: 969 | C231: FIMI OPPORTUNITY FUND , L.P | D231: 530278548 | E231: מספר שותפות | F231: פימי 6 | G231: 60400892 | H231: פנימי | I231: פרייבט אקוויטי | J231: Other | K231: ישראל | L231: ישראל | M231: ישראל | N231: ישראל | O231: לא | P231: 16/04/2019 | Q231: USD | R231: דיווח מנהל הקרן | S231: אי-תלות | T231: 31/03/2024 | U231: 3.681 | V231: 397.54 | W231: 1463.344 | Y231: 0.14037131 | Z231: 0.019923729
A232: 969 | B232: 969 | C232: קרן ארבל פאנד בע"מ | D232: 540307832 | E232: ח.פ | F232: קרן ארבל פאנד בע"מ | G232: 18952 | H232: פנימי | I232: פרייבט אקוויטי | J232: Debt Infrastructure | K232: ישראל | L232: ישראל | M232: ישראל | N232: ישראל | O232: לא | P232: 12/12/2017 | Q232: ILS | R232: דיווח מנהל הקרן | S232: אי-תלות | T232: 31/03/2024 | U232: 1 | V232: 77.775 | W232: 77.775 | Y232: 0.0074605414 | Z232: 0.0010589187
A233: 969 | B233: 969 | C233: Blue Atlantic Partners III Cayman Feeder I, LP | D233: 1683231 | E233: מספר תאגיד או שותפות בחו"ל | F233: BLUE ATLANTIC PARTNERS 3 | G233: 62013909 | H233: פנימי | I233: פרייבט אקוויטי | J233: Value Added Real Estate | K233: חו"ל | L233: איי קיימן | M233: ארה"ב | N233: ארה"ב | O233: לא | P233: 03/12/2019 | Q233: USD | R233: דיווח מנהל הקרן | S233: אי-תלות | T233: 31/03/2024 | U233: 3.681 | V233: 63.861 | W233: 235.071 | Y233: 0.022549138 | Z233: 0.0032005324
A234: 969 | B234: 969 | C234: DOVER STREET IX CAYMAN FUND L.P. | D234: 1665355 | E234: מספר תאגיד או שותפות בחו"ל | F234: DOVER IX (9) | G234: 60419041 | H234: פנימי | I234: פרייבט אקוויטי | J234: Secondaries | K234: חו"ל | L234: איי קיימן | M234: ארה"ב | N234: גלובלי | O234: לא | P234: 19/07/2018 | Q234: USD | R234: דיווח מנהל הקרן | S234: אי-תלות | T234: 31/03/2024 | U234: 3.681 | V234: 59.681 | W234: 219.687 | Y234: 0.02107345 | Z234: 0.0029910793
A235: 969 | B235: 969 | C235: Dover Street X Feeder Fund L.P. | D235: 1661612 | E235: מספר תאגיד או שותפות בחו"ל | F235: DOVER STREET X LP | G235: 62016654 | H235: פנימי | I235: פרייבט אקוויטי | J235: Secondaries | K235: חו"ל | L235: איי קיימן | M235: ארה"ב | N235: גלובלי | O235: לא | P235: 03/06/2020 | Q235: USD | R235: דיווח מנהל הקרן | S235: אי-תלות | T235: 31/03/2024 | U235: 3.681 | V235: 102.542 | W235: 377.457 | Y235: 0.036207534 | Z235: 0.0051391492
A236: 969 | B236: 969 | C236: ECP CAPITAL LP | D236: 254900IUTAAOKV09RE87 | E236: LEI | F236: ECP Terra Gen Growth Fund | G236: 62018064 | H236: פנימי | I236: פרייבט אקוויטי | J236: Value Added Infrastructure | K236: חו"ל | L236: איי קיימן | M236: ארה"ב | N236: אמריקה הצפונית | O236: לא | P236: 25/03/2021 | Q236: USD | R236: אחר | S236: אי-תלות | T236: 31/03/2024 | U236: 3.681 | V236: 135.184 | W236: 497.612 | Y236: 0.047733446 | Z236: 0.0067750899
A237: 969 | B237: 969 | C237: HARBOURVEST PARTNERS, LLC | D237: 5493001MCDH7I6NIXC24 | E237: LEI | F237: HARBOURVEST 2017 GLOBAL FUND | G237: 62003800 | H237: פנימי | I237: פרייבט אקוויטי | J237: Leveraged Buyout | K237: חו"ל | L237: איי קיימן | M237: ארה"ב | N237: גלובלי | O237: לא | P237: 12/12/2018 | Q237: USD | R237: אחר | S237: אי-תלות | T237: 31/03/2024 | U237: 3.681 | V237: 135.235 | W237: 497.8 | Y237: 0.047751461 | Z237: 0.0067776469
A238: 969 | B238: 969 | C238: HARBOURVEST PARTNERS, LLC | D238: 5493001MCDH7I6NIXC24 | E238: LEI | F238: Harbourvest 2018 Global Fund L.P | G238: 620101031 | H238: פנימי | I238: פרייבט אקוויטי | J238: Other | K238: חו"ל | L238: איי קיימן | M238: ארה"ב | N238: ארה"ב | O238: לא | P238: 09/07/2019 | Q238: USD | R238: אחר | S238: אי-תלות | T238: 31/12/2023 | U238: 3.681 | V238: 85.076 | W238: 313.166 | Y238: 0.030040416 | Z238: 0.0042638137
A239: 969 | B239: 969 | C239: HARBOURVEST PARTNERS, LLC | D239: 5493001MCDH7I6NIXC24 | E239: LEI | F239: Harbourvest 2019 Global Fund L.P | G239: 62014857 | H239: פנימי | I239: פרייבט אקוויטי | J239: Leveraged Buyout | K239: חו"ל | L239: איי קיימן | M239: ארה"ב | N239: גלובלי | O239: לא | P239: 09/12/2019 | Q239: USD | R239: דיווח מנהל הקרן | S239: אי-תלות | T239: 31/03/2024 | U239: 3.681 | V239: 76.943 | W239: 283.228 | Y239: 0.027168613 | Z239: 0.0038562017
A240: 969 | B240: 969 | C240: HARBOURVEST PARTNERS, LLC | D240: 5493001MCDH7I6NIXC24 | E240: LEI | F240: HARBOURVEST COF II | G240: 62017678 | H240: פנימי | I240: פרייבט אקוויטי | J240: Mezzanine Debt | K240: חו"ל | L240: איי קיימן | M240: ארה"ב | N240: גלובלי | O240: לא | P240: 02/12/2020 | Q240: USD | R240: אחר | S240: אי-תלות | T240: 31/03/2024 | U240: 3.681 | V240: 152.432 | W240: 561.101 | Y240: 0.053823622 | Z240: 0.0076395046
A241: 969 | B241: 969 | C241: Carlisle Management Company S.C.A. | D241: 213800BMFRCLOWO3JI85 | E241: LEI | F241: LUXEMBOURG LIFE FUND II - ABSO | G241: 77847846 | H241: פנימי | I241: פרייבט אקוויטי | J241: Other | K241: חו"ל | L241: לוכסמבורג | M241: לוכסמבורג | N241: ארה"ב | O241: לא | P241: 18/05/2021 | Q241: USD | R241: דיווח מנהל הקרן | S241: אי-תלות | T241: 31/03/2024 | U241: 3.681 | V241: 397.755 | W241: 1464.134 | Y241: 0.14044709 | Z241: 0.019934485
