Workbook
Name Additional_Factor: 'אפשרויות בחירה'!$C$701:$C$850
Name Amoritization: 'אפשרויות בחירה'!$C$546:$C$550
Name Capsule: 'אפשרויות בחירה'!$C$926:$C$928
Name Company_Name: 'File Name Info'!$A$34:$A$120
Name Company_Name_ID: 'File Name Info'!$A$34:$B$120
Name Consortium: 'אפשרויות בחירה'!$C$514:$C$515
Name Country_list: 'אפשרויות בחירה'!$C$4:$C$85
Name Country_list_funds: 'אפשרויות בחירה'!$C$4:$C$103
Name CSA: 'אפשרויות בחירה'!$C$688:$C$689
Name Delivery: 'אפשרויות בחירה'!$C$666:$C$667
Name Dependence_Independence: 'אפשרויות בחירה'!$C$654:$C$655
Name Duration_Underlying_Interest_Rate: 'אפשרויות בחירה'!$C$680:$C$687
Name File_Type: 'File Name Info'!$A$10:$A$12
Name Full_File_Type: 'File Name Info'!$A$11:$B$13
Name Full_Type: 'File Name Info'!$A$2:$B$8
Name Full_Type_Nostro: 'File Name Info'!$A$3:$B$6
Name Full_Year: 'File Name Info'!$A$22:$B$31
Name Fund_Strategy: 'אפשרויות בחירה'!$C$597:$C$621
Name Fund_type: 'אפשרויות בחירה'!$C$328:$C$498
Name Holding_interest: 'אפשרויות בחירה'!$C$146:$C$147
Name In_the_books: 'אפשרויות בחירה'!$C$656:$C$657
Name Industry_Sector: 'אפשרויות בחירה'!$C$1129:$C$1245
Name Industry_sector_all: 'אפשרויות בחירה'!$C$202:$C$327
Name Industry_sectors: 'אפשרויות בחירה'!$C$202:$C$327
Name israel_abroad: 'אפשרויות בחירה'!$C$2:$C$3
Name Issuer_Number_Banks: 'אפשרויות בחירה'!$C$111:$C$113
Name Issuer_Number_Fund: 'אפשרויות בחירה'!$C$114:$C$117
Name issuer_number_loan: 'אפשרויות בחירה'!$C$118:$C$126
Name Issuer_Number_Type: 'אפשרויות בחירה'!$C$104:$C$110
Name Issuer_Number_Type_2: 'אפשרויות בחירה'!$C$1076:$C$1079
Name Issuer_Number_Type_3: 'אפשרויות בחירה'!$C$1081:$C$1085
Name Issuer_Number_Type_V2: 'אפשרויות בחירה'!$C$104:$C$110
Name Issuer_Type_TFunds: 'אפשרויות בחירה'!$C$1087:$C$1089
Name Leading_factor: 'אפשרויות בחירה'!$C$692:$C$700
Name Linked_Type: 'אפשרויות בחירה'!$C$516:$C$519
Name other_investments: 'אפשרויות בחירה'!$C$1000:$C$1033
Name Penalty: 'אפשרויות בחירה'!$C$851:$C$852
Name QTR: 'File Name Info'!$A$15:$A$19
Name Rating_Agency: 'אפשרויות בחירה'!$C$188:$C$201
Name real_estate_lifestage: 'אפשרויות בחירה'!$C$634:$C$642
Name real_estate_loans: 'אפשרויות בחירה'!$C$553:$C$591
Name Real_Estate_Main_Use: 'אפשרויות בחירה'!$C$622:$C$633
Name Recourse_Nonrecourse: 'אפשרויות בחירה'!$C$544:$C$545
Name Repayment_Rights: 'אפשרויות בחירה'!$C$551:$C$552
Name Reset_frequency: 'אפשרויות בחירה'!$C$658:$C$665
Name Security_ID_Number_Type: 'אפשרויות בחירה'!$C$1113:$C$1116
Name Security_Number_Loans: 'אפשרויות בחירה'!$C$131
Name Stock_Exchange: 'אפשרויות בחירה'!$C$1283:$C$1315
Name Stock_Exchange_Gov_Bonds: 'אפשרויות בחירה'!$C$148:$C$181
Name Subordination_Risk: 'אפשרויות בחירה'!$C$186:$C$187
Name Tradeable_Status: 'אפשרויות בחירה'!$C$1272:$C$1281
Name Tradeable_Status_All: 'אפשרויות בחירה'!$C$135:$C$145
Name tradeable_status_bonds: 'אפשרויות בחירה'!$C$1248:$C$1253
Name tradeable_status_funds: 'אפשרויות בחירה'!$C$1118:$C$1119
Name tradeable_status_stock: 'אפשרויות בחירה'!$C$1255:$C$1259
Name Tradeable_Status_v2: 'אפשרויות בחירה'!$C$1121:$C$1126
Name tradeable_status_warrants: 'אפשרויות בחירה'!$C$1261:$C$1265
Name tradeable_status_warrants_v2: 'אפשרויות בחירה'!$C$1267:$C$1269
Name Transaction: 'אפשרויות בחירה'!$C$643:$C$646
Name Type: 'File Name Info'!$A$2:$A$8

Sheet עמוד פתיחה
A1: קובץ דיווח עבור רשימת נכסים ברמת הנכס הבודד (חוזר גופים מוסדיים 2015-9-14)
A3: יש לבחור תחום: | D3: נכסי עמיתים - קופות גמל
A5: האם מדובר בקובץ לממומנה או לציבור:
A7: יש לבחור את רבעון הדיווח:
A9: יש לבחור את שנת הדיווח:
A11: יש לבחור את הגוף המוסדי:
A13: ח.פ. הגוף המוסדי: | D13: =IFERROR(VLOOKUP(D11,'File Name Info'!A35:B121,2,0),"תא מחושב") -> תא מחושב
A15: שם קובץ לשמירה | D15: =IF(D5="לממונה",CONCATENATE(D13, "_",VLOOKUP(D3,Full_Type,2,0),"_",D7,VLOOKUP(D9,Full_Year,2,0),".xlxs"),IF(D5="לציבור",CONCATENATE(D13,"_",VLOOKUP(D3,Full_Type_Nostro,2,0),"_",VLOOKUP(D5,Full_File_Type,2,0),"_",D7,VLOOKUP(D9,Full_Year,2,0),".xlsx"),"שם קובץ לשמירה")) -> שם קובץ לשמירה
A17: פרטי האחראי על הדיווח בגוף המוסדי | B17: שם:
B19: מספר טלפון:
B21: כתובת מייל:
A23: הוראות למילוי הדיווח: | D23: יש לדווח לפי ההנחיות בחלק ג' לנספח 5.4.3.2 שבפרק 3 שבחלק 4 לשער 5 בחוזר המאוחד - "רשימת נכסים ברמת הנכס הבודד".

Sheet סכום נכסים
C1: ידווח בקבצי נכסי הנוסטרו בלבד
B2: שווי הוגן | C2: עלות מופחתת | D2: השיטה שיושמה בדוח הכספי | E2: שיעור מסך נכסי השקעה
A3: מזומנים ושווי מזומנים | B3: =SUM('מזומנים ושווי מזומנים'!O:O) -> 57099.609 | D3: =B3+C3 -> 57099.609 | E3: =SUM('מזומנים ושווי מזומנים'!O:O)/B30 -> 0.049061827
A4: איגרות חוב ממשלתיות | B4: =SUM('איגרות חוב ממשלתיות'!U:U) -> 252168.13 | D4: =B4+C4 -> 252168.13 | E4: =SUM('איגרות חוב ממשלתיות'!U:U)/B30 -> 0.216671
A5: ניירות ערך מסחריים | B5: =SUM('ניירות ערך מסחריים'!AD:AD) -> 931.542 | D5: =B5+C5 -> 931.542 | E5: =SUM('ניירות ערך מסחריים'!AD:AD)/B30 -> 0.00080041095
A6: איגרות חוב | B6: =SUM('איגרות חוב'!AD:AD) -> 179439.1 | D6: =B6+C6 -> 179439.1 | E6: =SUM('איגרות חוב'!AD:AD)/B30 -> 0.15417987
A7: מניות, מניות בכורה ויחידות השתתפות | B7: =SUM('מניות מבכ ויהש'!U:U) -> 168001.35 | D7: =B7+C7 -> 168001.35 | E7: =SUM('מניות מבכ ויהש'!U:U)/B30 -> 0.14435218
A8: קרנות סל | B8: =SUM('קרנות סל'!T:T) -> 250540.48 | D8: =B8+C8 -> 250540.48 | E8: =SUM('קרנות סל'!T:T)/B30 -> 0.21527247
A9: קרנות נאמנות | B9: =SUM('קרנות נאמנות'!T:T) -> 8024.993 | D9: =B9+C9 -> 8024.993 | E9: =SUM('קרנות נאמנות'!T:T)/B30 -> 0.006895333
A10: כתבי אופציה | B10: =SUM('כתבי אופציה'!W:W) -> 281.904 | D10: =B10+C10 -> 281.904 | E10: =SUM('כתבי אופציה'!W:W)/B30 -> 0.00024222102
A11: אופציות | B11: =SUM(אופציות!V:V) -> 0 | D11: =B11+C11 -> 0 | E11: =SUM(אופציות!V:V)/B30 -> 0
A12: חוזים עתידיים | B12: =SUM('חוזים עתידיים'!R:R) -> 4693.77 | D12: =B12+C12 -> 4693.77 | E12: =SUM('חוזים עתידיים'!R:R)/B30 -> 0.0040330387
A13: מוצרים מובנים | B13: =SUM('מוצרים מובנים'!Z:Z) -> 977.187 | D13: =B13+C13 -> 977.187 | E13: =SUM('מוצרים מובנים'!Z:Z)/B30 -> 0.00083963061
A14: לא סחיר איגרות חוב ממשלתיות | B14: =SUM('לא סחיר איגרות חוב ממשלתיות'!U:U) -> 0 | D14: =B14+C14 -> 0 | E14: =SUM('לא סחיר איגרות חוב ממשלתיות'!U:U)/B30 -> 0
A15: לא סחיר איגרות חוב מיועדות | B15: =SUM('לא סחיר איגרות חוב מיועדות'!N:N) -> 0 | D15: =B15+C15 -> 0 | E15: =SUM('לא סחיר איגרות חוב מיועדות'!N:N)/B30 -> 0
A16: אפיק השקעה מובטח תשואה | B16: =SUM('אפיק השקעה מובטח תשואה'!F:F) -> 0 | D16: =B16+C16 -> 0 | E16: =SUM('אפיק השקעה מובטח תשואה'!F:F)/B30 -> 0
A17: לא סחיר ניירות ערך מסחריים | B17: =SUM('לא סחיר ניירות ערך מסחריים'!AI:AI) -> 2240.2 | D17: =B17+C17 -> 2240.2 | E17: =SUM('לא סחיר ניירות ערך מסחריים'!AI:AI)/B30 -> 0.0019248521
A18: לא סחיר איגרות חוב | B18: =SUM('לא סחיר איגרות חוב'!AG:AG) -> 11848.375 | D18: =B18+C18 -> 11848.375 | E18: =SUM('לא סחיר איגרות חוב'!AG:AG)/B30 -> 0.010180506
A19: לא סחיר מניות, מניות בכורה ויחידות השתתפות | B19: =SUM('לא סחיר מניות מבכ ויהש'!X:X) -> 13229.949 | D19: =B19+C19 -> 13229.949 | E19: =SUM('לא סחיר מניות מבכ ויהש'!X:X)/B30 -> 0.011367599
A20: קרנות השקעה | B20: =SUM('קרנות השקעה'!W:W) -> 213737.88 | D20: =B20+C20 -> 213737.88 | E20: =SUM('קרנות השקעה'!W:W)/B30 -> 0.18365049
A21: לא סחיר כתבי אופציה | B21: =SUM('לא סחיר כתבי אופציה'!Z:Z) -> 10.381 | D21: =B21+C21 -> 10.381 | E21: =SUM('לא סחיר כתבי אופציה'!Z:Z)/B30 -> 8.9196903e-06
A22: לא סחיר אופציות | B22: =SUM('לא סחיר אופציות'!Z:Z) -> 0 | D22: =B22+C22 -> 0 | E22: =SUM('לא סחיר אופציות'!Z:Z)/B30 -> 0
A23: לא סחיר נגזרים אחרים | B23: =SUM('לא סחיר נגזרים אחרים'!R:R) -> -766.731 | D23: =B23+C23 -> -766.731 | E23: =SUM('לא סחיר נגזרים אחרים'!R:R)/B30 -> -0.00065880002
A24: הלוואות | B24: =SUM(הלוואות!AT:AT) -> 654.806 | D24: =B24+C24 -> 654.806 | E24: =SUM(הלוואות!AT:AT)/B30 -> 0.00056263045
A25: לא סחיר מוצרים מובנים | B25: =SUM('לא סחיר מוצרים מובנים'!AB:AB) -> 0 | D25: =B25+C25 -> 0 | E25: =SUM('לא סחיר מוצרים מובנים'!AB:AB)/B30 -> 0
A26: פיקדונות מעל 3 חודשים | B26: =SUM('פיקדונות מעל 3 חודשים'!T:T) -> 0 | D26: =B26+C26 -> 0 | E26: =SUM('פיקדונות מעל 3 חודשים'!T:T)/B30 -> 0
A27: זכויות מקרקעין | B27: =SUM('זכויות מקרקעין'!S:S) -> 0 | D27: =B27+C27 -> 0 | E27: =SUM('זכויות מקרקעין'!S:S)/B30 -> 0
A28: השקעה בחברות מוחזקות | B28: =SUM('השקעה בחברות מוחזקות'!U:U) -> 0 | D28: =B28+C28 -> 0 | E28: =SUM('השקעה בחברות מוחזקות'!U:U)/B30 -> 0
A29: נכסים אחרים | B29: =SUM('נכסים אחרים'!N:N) -> 716.716 | D29: =B29+C29 -> 716.716 | E29: =SUM('נכסים אחרים'!N:N)/B30 -> 0.00061582552
A30: סך הכל נכסים | B30: =IF(SUM(B3:B29)=0,0.0001,SUM(B3:B29)) -> 1163829.6 | C30: =SUM(C3:C29) -> 0 | D30: =SUM(D3:D29) -> 1163829.6 | E30: =SUM(E3:E29) -> 1
A31: מסגרות אשראי
A32: יתרות התחייבויות להשקעה | B32: =SUM('יתרות התחייבות להשקעה'!O:O) -> 53859.235

Sheet מזומנים ושווי מזומנים
A1: מספר קופה/קרן/ח.פ. עבור חברת ביטוח | B1: מספר מסלול | C1: שם הבנק | D1: מספר מזהה בנק | E1: סוג מספר מזהה בנק | F1: מאפיין עיקרי | G1: ישראל/חו"ל | H1: בעל עניין/צד קשור | I1: דירוג הבנק | J1: שם מדרג | K1: מטבע פעילות | L1: שווי מטבעי | M1: שער חליפין | N1: שיעור ריבית | O1: שווי הוגן (באלפי ש"ח) | P1: שיעור מנכסי אפיק ההשקעה | Q1: שיעור מסך נכסי ההשקעה
A2: 158 | B2: 1441 | C2: גמול פועלים סהר | D2: 33-414 | E2: סימול בנק | F2: פח"ק/פר"י | G2: ישראל | H2: לא | I2: AAA | J2: S&P מעלות | K2: ILS | L2: 0 | M2: 1 | N2: 0 | O2: 247.038 | P2: 0.88361113 | Q2: 0.022524115
A3: 158 | B3: 1441 | C3: גמול פועלים סהר | D3: 33-414 | E3: סימול בנק | F3: מזומן ועו"ש נקוב במט"ח | G3: חו"ל | H3: לא | I3: AAA | J3: S&P מעלות | K3: USD | L3: 4.321 | M3: 3.681 | N3: 0 | O3: 15.904 | P3: 0.056886521 | Q3: 0.0014500933
A4: 158 | B4: 1441 | C4: גמול פועלים סהר | D4: 33-414 | E4: סימול בנק | F4: מזומן ועו"ש בש"ח | G4: ישראל | H4: לא | I4: AAA | J4: S&P מעלות | K4: ILS | L4: 0 | M4: 1 | N4: 0 | O4: -0.001 | P4: -2.611081e-06 | Q4: -6.6559018e-08
A5: 158 | B5: 1441 | C5: בנק לאומי לישראל בע"מ | D5: 10-800 | E5: סימול בנק | F5: מזומן ועו"ש בש"ח | G5: ישראל | H5: לא | I5: AAA | J5: S&P מעלות | K5: ILS | L5: 0 | M5: 1 | N5: 0 | O5: 16.636 | P5: 0.059504962 | Q5: 0.0015168399
A6: 158 | B6: 1522 | C6: גמול פועלים סהר | D6: 33-414 | E6: סימול בנק | F6: פח"ק/פר"י | G6: ישראל | H6: לא | I6: AAA | J6: S&P מעלות | K6: ILS | L6: 0 | M6: 1 | N6: 0 | O6: 385.696 | P6: 0.85272291 | Q6: 0.038234412
A7: 158 | B7: 1522 | C7: גמול פועלים סהר | D7: 33-414 | E7: סימול בנק | F7: מזומן ועו"ש נקוב במט"ח | G7: ישראל | H7: לא | I7: AAA | J7: S&P מעלות | K7: CHF | L7: 5.046 | M7: 4.074 | N7: 0 | O7: 20.558 | P7: 0.045451821 | Q7: 0.0020379699
A8: 158 | B8: 1522 | C8: גמול פועלים סהר | D8: 33-414 | E8: סימול בנק | F8: מזומן ועו"ש נקוב במט"ח | G8: חו"ל | H8: לא | I8: AAA | J8: S&P מעלות | K8: USD | L8: -3.136 | M8: 3.681 | N8: 0 | O8: -11.544 | P8: -0.025521924 | Q8: -0.0011443527
A9: 158 | B9: 1522 | C9: גמול פועלים סהר | D9: 33-414 | E9: סימול בנק | F9: מזומן ועו"ש נקוב במט"ח | G9: חו"ל | H9: לא | I9: AAA | J9: S&P מעלות | K9: HKD | L9: 2.66 | M9: 0.47 | N9: 0 | O9: 1.251 | P9: 0.0027665278 | Q9: 0.00012404564
A10: 158 | B10: 1522 | C10: גמול פועלים סהר | D10: 33-414 | E10: סימול בנק | F10: מזומן ועו"ש נקוב במט"ח | G10: חו"ל | H10: לא | I10: AAA | J10: S&P מעלות | K10: EUR | L10: 7.205 | M10: 3.979 | N10: 0 | O10: 28.671 | P10: 0.063388048 | Q10: 0.0028421949
A11: 158 | B11: 1522 | C11: גמול פועלים סהר | D11: 33-414 | E11: סימול בנק | F11: מזומן ועו"ש נקוב במט"ח | G11: חו"ל | H11: לא | I11: AAA | J11: S&P מעלות | K11: JPY | L11: 0.67 | M11: 2.433 | N11: 0 | O11: 0.016 | P11: 3.605899e-05 | Q11: 1.6168139e-06
A12: 158 | B12: 1522 | C12: גמול פועלים סהר | D12: 33-414 | E12: סימול בנק | F12: מזומן ועו"ש נקוב במט"ח | G12: חו"ל | H12: לא | I12: AAA | J12: S&P מעלות | K12: GBP | L12: 0.496 | M12: 4.654 | N12: 0 | O12: 2.31 | P12: 0.0051067955 | Q12: 0.00022897863
A13: 158 | B13: 1522 | C13: בנק לאומי לישראל בע"מ | D13: 10-800 | E13: סימול בנק | F13: מזומן ועו"ש בש"ח | G13: ישראל | H13: לא | I13: AAA | J13: S&P מעלות | K13: ILS | L13: 0 | M13: 1 | N13: 0 | O13: 25.352 | P13: 0.056050576 | Q13: 0.0025131972
... A50: 158 | B50: 9937 | C50: בנק לאומי לישראל בע"מ | D50: 10-800 | E50: סימול בנק | F50: מזומן ועו"ש בש"ח | G50: ישראל | H50: לא | I50: AAA | J50: S&P מעלות | K50: ILS | L50: 0 | M50: 1 | N50: 0 | O50: -362.403 | P50: -0.32948435 | Q50: -0.011527074

Sheet איגרות חוב ממשלתיות
A1: מספר קופה/קרן/ח.פ. עבור חברת ביטוח | B1: מספר מסלול | C1: שם מנפיק | D1: שם נייר ערך | E1: מספר נייר ערך | F1: מאפיין עיקרי | G1: ישראל/חו"ל | H1: מדינה לפי חשיפה כלכלית | I1: זירת מסחר | J1: דירוג | K1: שם מדרג | L1: מטבע פעילות | M1: מח"מ | N1: מועד פדיון | O1: שיעור ריבית | P1: תשואה לפדיון | Q1: סכום לקבל (במטבע הפעילות) | R1: ערך נקוב (יחידות) | S1: שער חליפין | T1: שער נייר הערך | U1: שווי הוגן (באלפי ש"ח) | V1: עלות מופחתת (באלפי ש"ח) | W1: השיטה שיושמה בדוח הכספי | X1: שיעור מערך נקוב מונפק | Y1: שיעור מנכסי אפיק ההשקעה | Z1: שיעור מסך נכסי ההשקעה
A2: 158 | B2: 1441 | C2: מדינת ישראל | D2: ISRAEL 2 7/8 03/16/26 | E2: US46513CXR23 | F2: צמוד מט"ח בריבית קבועה | G2: ישראל | H2: ישראל | I2: LSE | J2: A1 | K2: Moodys | L2: USD | M2: 3.22 | N2: 16/03/2026 | O2: 0.02875 | P2: 0.0451 | R2: 100000 | S2: 3.681 | T2: 95.365 | U2: 351.04 | W2: שווי הוגן | X2: 0.1 | Y2: 0.041204084 | Z2: 0.032006651
A3: 158 | B3: 1441 | C3: בנק ישראל- מק"מ | D3: מ.ק.מ. 315 | E3: IL0082503181 | F3: מק"מ קצר משנים עשר חודשים | G3: ישראל | H3: ישראל | I3: TASE | J3: RF | K3: פנימי | L3: ILS | M3: 0.94 | N3: 05/03/2025 | O3: 0 | P3: 0.04096 | R3: 860000 | S3: 1 | T3: 96.38 | U3: 828.868 | W3: שווי הוגן | X3: 0 | Y3: 0.097290276 | Z3: 0.075573479
A4: 158 | B4: 1441 | C4: בנק ישראל- מק"מ | D4: מלווה קצר מועד 1114 | E4: IL0082411195 | F4: מק"מ קצר משנים עשר חודשים | G4: ישראל | H4: ישראל | I4: TASE | J4: RF | K4: פנימי | L4: ILS | M4: 0.6 | N4: 06/11/2024 | O4: 0 | P4: 0.04274 | R4: 30000 | S4: 1 | T4: 97.52 | U4: 29.256 | W4: שווי הוגן | X4: 0 | Y4: 0.0034339899 | Z4: 0.0026674666
A5: 158 | B5: 1441 | C5: בנק ישראל- מק"מ | D5: מלווה קצר מועד 714 | E5: IL0082407151 | F5: מק"מ קצר משנים עשר חודשים | G5: ישראל | H5: ישראל | I5: TASE | J5: RF | K5: פנימי | L5: ILS | M5: 0.255 | N5: 03/07/2024 | O5: 0 | P5: 0.04312 | R5: 60000 | S5: 1 | T5: 98.95 | U5: 59.37 | W5: שווי הוגן | X5: 3e-06 | Y5: 0.0069686895 | Z5: 0.0054131628
A6: 158 | B6: 1441 | C6: בנק ישראל- מק"מ | D6: מלווה קצר מועד 914 | E6: IL0082409132 | F6: מק"מ קצר משנים עשר חודשים | G6: ישראל | H6: ישראל | I6: TASE | J6: RF | K6: פנימי | L6: ILS | M6: 0.427 | N6: 04/09/2024 | O6: 0 | P6: 0.04317 | R6: 125000 | S6: 1 | T6: 98.21 | U6: 122.762 | W6: שווי הוגן | X6: 7e-06 | Y6: 0.014409529 | Z6: 0.011193084
A7: 158 | B7: 1441 | C7: גליל | D7: ממשל צמודה 0527 | E7: IL0011408478 | F7: צמוד למדד המחירים לצרכן בריבית קבועה | G7: ישראל | H7: ישראל | I7: TASE | J7: RF | K7: פנימי | L7: ILS | M7: 3.119 | N7: 31/05/2027 | O7: 0.0075 | P7: 0.01152 | R7: 888842 | S7: 1 | T7: 111.88 | U7: 994.436 | W7: שווי הוגן | X7: 4.2e-05 | Y7: 0.11672425 | Z7: 0.090669468
A8: 158 | B8: 1441 | C8: גליל | D8: ממשל צמודה 1025 | E8: IL0011359127 | F8: צמוד למדד המחירים לצרכן בריבית קבועה | G8: ישראל | H8: ישראל | I8: TASE | J8: RF | K8: פנימי | L8: ILS | M8: 1.576 | N8: 31/10/2025 | O8: 0.0075 | P8: 0.00797 | R8: 1277299 | S8: 1 | T8: 112.14 | U8: 1432.363 | W8: שווי הוגן | X8: 5.9e-05 | Y8: 0.16812689 | Z8: 0.13059819
A9: 158 | B9: 1441 | C9: גליל | D9: ממשל צמודה 1131 | E9: IL0011722209 | F9: צמוד למדד המחירים לצרכן בריבית קבועה | G9: ישראל | H9: ישראל | I9: TASE | J9: RF | K9: פנימי | L9: ILS | M9: 7.638 | N9: 30/11/2031 | O9: 0.001 | P9: 0.01556 | R9: 54000 | S9: 1 | T9: 99.81 | U9: 53.897 | W9: שווי הוגן | X9: 2e-06 | Y9: 0.0063263305 | Z9: 0.004914189
A10: 158 | B10: 1441 | C10: שחר | D10: ממשל שיקלית 0928 | E10: IL0011508798 | F10: לא צמוד למדד המחירים לצרכן ריבית קבועה | G10: ישראל | H10: ישראל | I10: TASE | J10: RF | K10: פנימי | L10: ILS | M10: 4.269 | N10: 28/09/2028 | O10: 0.0225 | P10: 0.04072 | R10: 70000 | S10: 1 | T10: 93.79 | U10: 65.653 | W10: שווי הוגן | X10: 3e-06 | Y10: 0.0077061709 | Z10: 0.0059860263
A11: 158 | B11: 1441 | C11: שחר | D11: ממשל שקלית 0226 | E11: IL0011746976 | F11: לא צמוד למדד המחירים לצרכן ריבית קבועה | G11: ישראל | H11: ישראל | I11: TASE | J11: RF | K11: פנימי | L11: ILS | M11: 1.904 | N11: 27/02/2026 | O11: 0.005 | P11: 0.04029 | R11: 808000 | S11: 1 | T11: 93.69 | U11: 757.015 | W11: שווי הוגן | X11: 3.8e-05 | Y11: 0.088856389 | Z11: 0.069022175
A12: 158 | B12: 1441 | C12: שחר | D12: ממשל שקלית 0825 | E12: IL0011355570 | F12: לא צמוד למדד המחירים לצרכן ריבית קבועה | G12: ישראל | H12: ישראל | I12: TASE | J12: RF | K12: פנימי | L12: ILS | M12: 1.399 | N12: 31/08/2025 | O12: 0.0175 | P12: 0.04022 | R12: 344000 | S12: 1 | T12: 97.96 | U12: 336.982 | W12: שווי הוגן | X12: 1.4e-05 | Y12: 0.039554079 | Z12: 0.030724955
A13: 158 | B13: 1441 | C13: שחר | D13: ממשלתי שקלית 0142 | E13: IL0011254005 | F13: לא צמוד למדד המחירים לצרכן ריבית קבועה | G13: ישראל | H13: ישראל | I13: TASE | J13: RF | K13: פנימי | L13: ILS | M13: 11.998 | N13: 31/01/2042 | O13: 0.055 | P13: 0.04715 | R13: 148322 | S13: 1 | T13: 110.25 | U13: 163.525 | W13: שווי הוגן | X13: 8e-06 | Y13: 0.019194121 | Z13: 0.014909676
... A89: 158 | B89: 9937 | C89: בנק ישראל- מק"מ | D89: מקמ 614 | E89: IL0082406161 | F89: מק"מ קצר משנים עשר חודשים | G89: ישראל | H89: ישראל | I89: TASE | J89: RF | K89: פנימי | L89: ILS | M89: 0.178 | N89: 05/06/2024 | O89: 0 | P89: 0.04318 | R89: 62000 | S89: 1 | T89: 99.26 | U89: 61.541 | W89: שווי הוגן | X89: 3e-06 | Y89: 0.0060200688 | Z89: 0.001957461

Sheet ניירות ערך מסחריים
A1: מספר קופה/קרן/ח.פ. עבור חברת ביטוח | B1: מספר מסלול | C1: שם מנפיק | D1: מספר מנפיק | E1: סוג מספר מזהה מנפיק | F1: שם נייר ערך | G1: מספר נייר ערך | H1: סוג מספר נייר ערך | I1: מאפיין עיקרי | J1: ישראל/חו"ל | K1: מדינה לפי חשיפה כלכלית | L1: זירת מסחר | M1: ענף מסחר | N1: בעל עניין/צד קשור | O1: דירוג | P1: שם מדרג | Q1: דירוג נייר הערך/המנפיק | R1: מטבע פעילות | S1: מח"מ | T1: ריבית עוגן | U1: מועד פדיון | V1: שיעור ריבית | W1: תשואה לפדיון | X1: נחיתות חוזית | Y1: האם סווג כחוב בעייתי | Z1: ערך נקוב (יחידות) | AA1: שער חליפין | AB1: שער נייר הערך | AC1: סכום לקבל (במטבע הפעילות) | AD1: שווי הוגן (באלפי ש"ח) | AE1: עלות מופחתת (באלפי ש"ח) | AF1: עלות מופחתת (במטבע הפעילות) | AG1: השיטה שיושמה בדוח הכספי | AH1: שיעור מערך נקוב מונפק | AI1: שיעור מנכסי אפיק ההשקעה | AJ1: שיעור מסך נכסי ההשקעה
A2: 158 | B2: 9935 | C2: מגה אור החזקות בע"מ | D2: 513257873 | E2: ח.פ | F2: מגה אור נעמ 3 18062024 | G2: IL0011969552 | H2: ISIN | I2: לא צמוד למדד המחירים לצרכן ריבית קבועה | J2: ישראל | K2: ישראל | L2: TASE | M2: נדל"ן מניב בישראל | N2: לא | O2: A+ | P2: S&P מעלות | Q2: נייר ערך | R2: ILS | S2: 0.214 | T2: ריבית בנק ישראל | U2: 18/06/2024 | V2: 0.102 | W2: 0.06684 | X2: החוב לא נחות | Y2: לא | Z2: 86500 | AA2: 1 | AB2: 1044.33 | AD2: 903.345 | AG2: שווי הוגן | AH2: 0.005767 | AI2: 1 | AJ2: 0.00082407088
A3: 158 | B3: 9936 | C3: מגה אור החזקות בע"מ | D3: 513257873 | E3: ח.פ | F3: מגה אור נעמ 3 18062024 | G3: IL0011969552 | H3: ISIN | I3: לא צמוד למדד המחירים לצרכן ריבית קבועה | J3: ישראל | K3: ישראל | L3: TASE | M3: נדל"ן מניב בישראל | N3: לא | O3: A+ | P3: S&P מעלות | Q3: נייר ערך | R3: ILS | S3: 0.214 | T3: ריבית בנק ישראל | U3: 18/06/2024 | V3: 0.102 | W3: 0.06684 | X3: החוב לא נחות | Y3: לא | Z3: 2700 | AA3: 1 | AB3: 1044.33 | AD3: 28.197 | AG3: שווי הוגן | AH3: 0.00018 | AI3: 1 | AJ3: 0.0018522991

Sheet איגרות חוב
A1: מספר קופה/קרן/ח.פ. עבור חברת ביטוח | B1: מספר מסלול | C1: שם מנפיק | D1: מספר מנפיק | E1: סוג מספר מזהה מנפיק | F1: שם נייר ערך | G1: מספר נייר ערך | H1: סוג מספר נייר ערך | I1: מאפיין עיקרי | J1: ישראל/חו"ל | K1: מדינה לפי חשיפה כלכלית | L1: סטאטוס סחירות | M1: זירת מסחר | N1: ענף מסחר | O1: בעל עניין/צד קשור | P1: דירוג | Q1: שם מדרג | R1: דירוג נייר הערך/המנפיק | S1: מטבע פעילות | T1: מח"מ | U1: מועד פדיון | V1: שיעור ריבית | W1: תשואה לפדיון | X1: נחיתות חוזית | Y1: האם סווג כחוב בעייתי | Z1: ערך נקוב (יחידות) | AA1: שער חליפין | AB1: שער נייר הערך | AC1: סכום לקבל (במטבע הפעילות) | AD1: שווי הוגן (באלפי ש"ח) | AE1: עלות מופחתת (באלפי ש"ח) | AF1: עלות מופחתת (במטבע הפעילות) | AG1: השיטה שיושמה בדוח הכספי | AH1: שיעור מערך נקוב מונפק | AI1: שיעור מנכסי אפיק ההשקעה | AJ1: שיעור מסך נכסי ההשקעה
A2: 158 | B2: 1441 | C2: איירפורט סיטי בע"מ | D2: 511659401 | E2: ח.פ | F2: איירפורט אגח ה | G2: IL0011334872 | H2: ISIN | I2: צמוד למדד המחירים לצרכן | J2: ישראל | K2: ישראל | L2: סחיר | M2: TASE | N2: נדל"ן מניב בישראל | O2: לא | P2: AA | Q2: S&P מעלות | R2: נייר ערך | S2: ILS | T2: 2.698 | U2: 28/02/2029 | V2: 0.0234 | W2: 0.02157 | X2: החוב לא נחות | Y2: לא | Z2: 40362.48 | AA2: 1 | AB2: 111.84 | AD2: 45.141 | AG2: שווי הוגן | AH2: 1.6e-05 | AI2: 0.027522624 | AJ2: 0.0041158453
A3: 158 | B3: 1441 | C3: אלביט מערכות בע"מ | D3: 520043027 | E3: ח.פ | F3: אלביט מערכות ב' 1.08% | G3: IL0011782351 | H3: ISIN | I3: לא צמוד למדד המחירים לצרכן | J3: ישראל | K3: ישראל | L3: סחיר | M3: TASE | N3: ביטחוניות | O3: לא | P3: AA | Q3: S&P מעלות | R3: נייר ערך | S3: ILS | T3: 2.597 | U3: 01/07/2029 | V3: 0.0108 | W3: 0.04475 | X3: החוב לא נחות | Y3: לא | Z3: 25950.75 | AA3: 1 | AB3: 92.04 | AD3: 23.885 | AG3: שווי הוגן | AH3: 2e-05 | AI3: 0.014562682 | AJ3: 0.0021777628
A4: 158 | B4: 1441 | C4: אלוני-חץ נכסים והשקעות בע"מ | D4: 520038506 | E4: ח.פ | F4: אלוני חץ אגח ט | G4: IL0039003541 | H4: ISIN | I4: לא צמוד למדד המחירים לצרכן | J4: ישראל | K4: ישראל | L4: סחיר | M4: TASE | N4: נדל"ן מניב בישראל | O4: לא | P4: AA- | Q4: S&P מעלות | R4: נייר ערך | S4: ILS | T4: 1.858 | U4: 28/02/2027 | V4: 0.0385 | W4: 0.04768 | X4: החוב לא נחות | Y4: לא | Z4: 40500 | AA4: 1 | AB4: 98.71 | AD4: 39.978 | AG4: שווי הוגן | AH4: 4.2e-05 | AI4: 0.024374236 | AJ4: 0.0036450225
A5: 158 | B5: 1441 | C5: אלוני-חץ נכסים והשקעות בע"מ | D5: 520038506 | E5: ח.פ | F5: אלוני חץ אגח טו | G5: IL0011894149 | H5: ISIN | I5: צמוד למדד המחירים לצרכן | J5: ישראל | K5: ישראל | L5: סחיר | M5: TASE | N5: נדל"ן מניב בישראל | O5: לא | P5: Aa3 | Q5: מידרוג Moodys | R5: נייר ערך | S5: ILS | T5: 7.443 | U5: 28/02/2037 | V5: 0.0256 | W5: 0.03962 | X5: החוב לא נחות | Y5: לא | Z5: 10000 | AA5: 1 | AB5: 94.33 | AD5: 9.433 | AG5: שווי הוגן | AH5: 1.5e-05 | AI5: 0.0057512821 | AJ5: 0.00086007015
A6: 158 | B6: 1441 | C6: אלקטרה בע"מ | D6: 520028911 | E6: ח.פ | F6: אלקטרה אגח ה | G6: IL0073902228 | H6: ISIN | I6: לא צמוד למדד המחירים לצרכן | J6: ישראל | K6: ישראל | L6: סחיר | M6: TASE | N6: השקעה ואחזקות | O6: לא | P6: A+ | Q6: S&P מעלות | R6: נייר ערך | S6: ILS | T6: 3.41 | U6: 10/01/2031 | V6: 0.04 | W6: 0.0502 | X6: החוב לא נחות | Y6: לא | Z6: 31750 | AA6: 1 | AB6: 97.7 | AD6: 31.02 | AG6: שווי הוגן | AH6: 4.1e-05 | AI6: 0.018912682 | AJ6: 0.0028282796
A7: 158 | B7: 1441 | C7: אמות השקעות בע"מ | D7: 520026683 | E7: ח.פ | F7: אמות אגח ד | G7: IL0011331498 | H7: ISIN | I7: צמוד למדד המחירים לצרכן | J7: ישראל | K7: ישראל | L7: סחיר | M7: TASE | N7: נדל"ן מניב בישראל | O7: לא | P7: Aa2 | Q7: מידרוג Moodys | R7: נייר ערך | S7: ILS | T7: 2.036 | U7: 02/07/2028 | V7: 0.032 | W7: 0.021 | X7: החוב לא נחות | Y7: לא | Z7: 36000 | AA7: 1 | AB7: 116.39 | AD7: 41.9 | AG7: שווי הוגן | AH7: 2.6e-05 | AI7: 0.025546594 | AJ7: 0.0038203417
A8: 158 | B8: 1441 | C8: ביג מרכזי קניות (2004) בע"מ | D8: 513623314 | E8: ח.פ | F8: ביג אגח ז | G8: IL0011360844 | H8: ISIN | I8: צמוד למדד המחירים לצרכן | J8: ישראל | K8: ישראל | L8: סחיר | M8: TASE | N8: נדל"ן מניב בישראל | O8: לא | P8: Aa3 | Q8: מידרוג Moodys | R8: נייר ערך | S8: ILS | T8: 0.601 | U8: 11/05/2025 | V8: 0.025 | W8: 0.02022 | X8: החוב לא נחות | Y8: לא | Z8: 20001.27 | AA8: 1 | AB8: 113.37 | AD8: 22.675 | AG8: שווי הוגן | AH8: 4.2e-05 | AI8: 0.013825172 | AJ8: 0.0020674726
A9: 158 | B9: 1441 | C9: פז בית זיקוק לנפט-אשדוד בע"מ | D9: 513775163 | E9: ח.פ | F9: בית זיקוק אשדוד אגח 2 | G9: IL0011994881 | H9: ISIN | I9: לא צמוד למדד המחירים לצרכן | J9: ישראל | K9: ישראל | L9: סחיר | M9: TASE | N9: אנרגיה | O9: לא | P9: A3 | Q9: מידרוג Moodys | R9: נייר ערך | S9: ILS | T9: 3.07 | U9: 30/04/2029 | V9: 0.0725 | W9: 0.06232 | X9: החוב לא נחות | Y9: לא | Z9: 9954 | AA9: 1 | AB9: 108.29 | AD9: 10.779 | AG9: שווי הוגן | AH9: 1.7e-05 | AI9: 0.0065720495 | AJ9: 0.00098281105
A10: 158 | B10: 1441 | C10: דיסקונט מנפיקים בע"מ | D10: 520029935 | E10: ח.פ | F10: דיסק מנ אגח טו | G10: IL0074803045 | H10: ISIN | I10: צמוד למדד המחירים לצרכן | J10: ישראל | K10: ישראל | L10: סחיר | M10: TASE | N10: בנקים | O10: לא | P10: Aaa | Q10: מידרוג Moodys | R10: נייר ערך | S10: ILS | T10: 4.255 | U10: 15/08/2032 | V10: 0.002 | W10: 0.01936 | X10: החוב לא נחות | Y10: לא | Z10: 26842.1 | AA10: 1 | AB10: 101.27 | AD10: 27.183 | AG10: שווי הוגן | AH10: 6e-06 | AI10: 0.01657342 | AJ10: 0.0024784567
A11: 158 | B11: 1441 | C11: דיסקונט מנפיקים בע"מ | D11: 520029935 | E11: ח.פ | F11: דיסק מנ אגח טז | G11: IL0012031576 | H11: ISIN | I11: צמוד למדד המחירים לצרכן | J11: ישראל | K11: ישראל | L11: סחיר | M11: TASE | N11: בנקים | O11: לא | P11: Aaa | Q11: מידרוג Moodys | R11: נייר ערך | S11: ILS | T11: 5.62 | U11: 20/03/2035 | V11: 0.0247 | W11: 0.02011 | X11: החוב לא נחות | Y11: לא | Z11: 30000 | AA11: 1 | AB11: 101.35 | AD11: 30.405 | AG11: שווי הוגן | AH11: 1.9e-05 | AI11: 0.018537871 | AJ11: 0.0027722287
A12: 158 | B12: 1441 | C12: הראל ביטוח מימון והנפקות בע"מ | D12: 513834200 | E12: ח.פ | F12: הראל הנפ אגח טז | G12: IL0011576019 | H12: ISIN | I12: לא צמוד למדד המחירים לצרכן | J12: ישראל | K12: ישראל | L12: סחיר | M12: TASE | N12: ביטוח | O12: לא | P12: Aa3 | Q12: מידרוג Moodys | R12: נייר ערך | S12: ILS | T12: 2.174 | U12: 30/06/2026 | V12: 0.0291 | W12: 0.04602 | X12: החוב לא נחות | Y12: לא | Z12: 10000 | AA12: 1 | AB12: 97.28 | AD12: 9.728 | AG12: שווי הוגן | AH12: 1.7e-05 | AI12: 0.0059311431 | AJ12: 0.00088696729
A13: 158 | B13: 1441 | C13: הראל ביטוח מימון והנפקות בע"מ | D13: 513834200 | E13: ח.פ | F13: הראל הנפק אגח ז | G13: IL0011260770 | H13: ISIN | I13: צמוד למדד המחירים לצרכן | J13: ישראל | K13: ישראל | L13: סחיר | M13: TASE | N13: ביטוח | O13: לא | P13: AA- | Q13: מידרוג Moodys | R13: נייר ערך | S13: ILS | T13: 0.164 | U13: 31/05/2024 | V13: 0.0385 | W13: 0.0001 | X13: החוב לא נחות | Y13: לא | Z13: 27341 | AA13: 1 | AB13: 117.54 | AD13: 32.137 | AG13: שווי הוגן | AH13: 0.000109 | AI13: 0.019593631 | AJ13: 0.0029301113
... A15: 158 | B15: 1441 | C15: הראל השקעות בביטוח ושרותים פיננסים בע"מ | D15: 520033986 | E15: ח.פ | F15: הראל השקעות אגח א | G15: IL0058501102 | H15: ISIN | I15: לא צמוד למדד המחירים לצרכן | J15: ישראל | K15: ישראל | L15: סחיר | M15: TASE | N15: ביטוח | O15: לא | P15: Aa2 | Q15: מידרוג Moodys | R15: נייר ערך | S15: ILS | T15: 5.221 | U15: 31/12/2035 | V15: 0.0195 | W15: 0.05008 | X15: החוב לא נחות | Y15: לא | Z15: 37923.54 | AA15: 1 | AB15: 85.74 | AD15: 32.516 | AG15: שווי הוגן | AH15: 3.3e-05 | AI15: 0.019824726 | AJ15: 0.0029646702
A16: 158 | B16: 1441 | C16: חברת החשמל לישראל בע"מ | D16: 520000472 | E16: ח.פ | F16: חשמל אגח 27 | G16: IL0060002107 | H16: ISIN | I16: צמוד למדד המחירים לצרכן | J16: ישראל | K16: ישראל | L16: סחיר | M16: TASE | N16: אנרגיה | O16: לא | P16: Aa1 | Q16: מידרוג Moodys | R16: נייר ערך | S16: ILS | T16: 3.883 | U16: 12/04/2029 | V16: 0.0385 | W16: 0.0195 | X16: החוב לא נחות | Y16: לא | Z16: 95833.32 | AA16: 1 | AB16: 120.49 | AC16: 3.27 | AD16: 118.74 | AG16: שווי הוגן | AH16: 3.7e-05 | AI16: 0.072395251 | AJ16: 0.010826281
A17: 158 | B17: 1441 | C17: חברת החשמל לישראל בע"מ | D17: 520000472 | E17: ח.פ | F17: חשמל אגח 31 | G17: IL0060002859 | H17: ISIN | I17: צמוד למדד המחירים לצרכן | J17: ישראל | K17: ישראל | L17: סחיר | M17: TASE | N17: אנרגיה | O17: לא | P17: Aa1 | Q17: מידרוג Moodys | R17: נייר ערך | S17: ILS | T17: 6.24 | U17: 21/09/2031 | V17: 0.0239 | W17: 0.02476 | X17: החוב לא נחות | Y17: לא | Z17: 45000 | AA17: 1 | AB17: 110.76 | AD17: 49.842 | AG17: שווי הוגן | AH17: 1.2e-05 | AI17: 0.030388572 | AJ17: 0.0045444309
A18: 158 | B18: 1441 | C18: ישרס חברה להשקעות בע"מ | D18: 520017807 | E18: ח.פ | F18: ישרס אגח יד | G18: IL0061301995 | H18: ISIN | I18: לא צמוד למדד המחירים לצרכן | J18: ישראל | K18: ישראל | L18: סחיר | M18: TASE | N18: נדל"ן מניב בישראל | O18: לא | P18: Aa3 | Q18: מידרוג Moodys | R18: נייר ערך | S18: ILS | T18: 1.83 | U18: 01/03/2027 | V18: 0.0505 | W18: 0.0487 | X18: החוב לא נחות | Y18: לא | Z18: 35142.85 | AA18: 1 | AB18: 100.86 | AD18: 35.445 | AG18: שווי הוגן | AH18: 9.5e-05 | AI18: 0.021610797 | AJ18: 0.0032317666
A19: 158 | B19: 1441 | C19: כללביט מימון בע"מ | D19: 513754069 | E19: ח.פ | F19: כלל אגח יא | G19: IL0011606477 | H19: ISIN | I19: לא צמוד למדד המחירים לצרכן | J19: ישראל | K19: ישראל | L19: סחיר | M19: TASE | N19: ביטוח | O19: לא | P19: Aa3 | Q19: מידרוג Moodys | R19: נייר ערך | S19: ILS | T19: 5.554 | U19: 31/03/2030 | V19: 0.0264 | W19: 0.05041 | X19: החוב לא נחות | Y19: לא | Z19: 135500 | AA19: 1 | AB19: 88.01 | AD19: 119.254 | AG19: שווי הוגן | AH19: 8.3e-05 | AI19: 0.072708662 | AJ19: 0.010873149
A20: 158 | B20: 1441 | C20: בנק לאומי לישראל בע"מ | D20: 520018078 | E20: ח.פ | F20: לאומי אגח 179 | G20: IL0060403727 | H20: ISIN | I20: צמוד למדד המחירים לצרכן | J20: ישראל | K20: ישראל | L20: סחיר | M20: TASE | N20: בנקים | O20: לא | P20: Aaa | Q20: מידרוג Moodys | R20: נייר ערך | S20: ILS | T20: 1.23 | U20: 30/06/2026 | V20: 0.0083 | W20: 0.01398 | X20: החוב לא נחות | Y20: לא | Z20: 30000 | AA20: 1 | AB20: 111.66 | AD20: 33.498 | AG20: שווי הוגן | AH20: 1e-05 | AI20: 0.020423667 | AJ20: 0.0030542383
A21: 158 | B21: 1441 | C21: בנק לאומי לישראל בע"מ | D21: 520018078 | E21: ח.פ | F21: לאומי אגח 186 | G21: IL0012018391 | H21: ISIN | I21: צמוד למדד המחירים לצרכן | J21: ישראל | K21: ישראל | L21: סחיר | M21: TASE | N21: בנקים | O21: לא | P21: AAA | Q21: S&P מעלות | R21: נייר ערך | S21: ILS | T21: 5.54 | U21: 30/11/2033 | V21: 0.0202 | W21: 0.02037 | X21: החוב לא נחות | Y21: לא | Z21: 40000 | AA21: 1 | AB21: 100.75 | AD21: 40.3 | AG21: שווי הוגן | AH21: 1.9e-05 | AI21: 0.024570833 | AJ21: 0.0036744225
A22: 158 | B22: 1441 | C22: מבנה נדל"ן (כ.ד) בע"מ | D22: 520024126 | E22: ח.פ | F22: מבני תעשיה אגח טז | G22: IL0022604388 | H22: ISIN | I22: לא צמוד למדד המחירים לצרכן | J22: ישראל | K22: ישראל | L22: סחיר | M22: TASE | N22: נדל"ן מניב בישראל | O22: לא | P22: AA | Q22: S&P מעלות | R22: נייר ערך | S22: ILS | T22: 2.084 | U22: 30/06/2028 | V22: 0.0565 | W22: 0.04633 | X22: החוב לא נחות | Y22: לא | Z22: 32500 | AA22: 1 | AB22: 103.65 | AD22: 33.686 | AG22: שווי הוגן | AH22: 0.000139 | AI22: 0.020538442 | AJ22: 0.0030714023
A23: 158 | B23: 1441 | C23: מבנה נדל"ן (כ.ד) בע"מ | D23: 520024126 | E23: ח.פ | F23: מבני תעשיה אגח יז | G23: IL0022604461 | H23: ISIN | I23: צמוד למדד המחירים לצרכן | J23: ישראל | K23: ישראל | L23: סחיר | M23: TASE | N23: נדל"ן מניב בישראל | O23: לא | P23: Aa2 | Q23: מידרוג Moodys | R23: נייר ערך | S23: ILS | T23: 2.154 | U23: 30/06/2028 | V23: 0.037 | W23: 0.02189 | X23: החוב לא נחות | Y23: לא | Z23: 33125 | AA23: 1 | AB23: 116.15 | AD23: 38.475 | AG23: שווי הוגן | AH23: 8.8e-05 | AI23: 0.023457944 | AJ23: 0.0035079964
A24: 158 | B24: 1441 | C24: מגה אור החזקות בע"מ | D24: 513257873 | E24: ח.פ | F24: מגה אור אגח ז | G24: IL0011416968 | H24: ISIN | I24: צמוד למדד המחירים לצרכן | J24: ישראל | K24: ישראל | L24: סחיר | M24: TASE | N24: נדל"ן מניב בישראל | O24: לא | P24: A+ | Q24: S&P מעלות | R24: נייר ערך | S24: ILS | T24: 2.077 | U24: 30/08/2027 | V24: 0.0205 | W24: 0.02328 | X24: החוב לא נחות | Y24: לא | Z24: 21000 | AA24: 1 | AB24: 112.41 | AD24: 23.606 | AG24: שווי הוגן | AH24: 2.7e-05 | AI24: 0.014392594 | AJ24: 0.0021523272
A25: 158 | B25: 1441 | C25: מזרחי טפחות חברה להנפקות בע"מ | D25: 520032046 | E25: ח.פ | F25: מז הנפק 46 1.22% 9/2027 | G25: IL0023102259 | H25: ISIN | I25: צמוד למדד המחירים לצרכן | J25: ישראל | K25: ישראל | L25: סחיר | M25: TASE | N25: בנקים | O25: לא | P25: Aaa | Q25: מידרוג Moodys | R25: נייר ערך | S25: ILS | T25: 3.421 | U25: 28/09/2027 | V25: 0.0122 | W25: 0.018 | X25: החוב לא נחות | Y25: לא | Z25: 60000 | AA25: 1 | AB25: 111.35 | AD25: 66.81 | AG25: שווי הוגן | AH25: 2e-05 | AI25: 0.04073393 | AJ25: 0.0060915178
A26: 158 | B26: 1441 | C26: מזרחי טפחות חברה להנפקות בע"מ | D26: 520032046 | E26: ח.פ | F26: מז טפ הנ אגח 67 | G26: IL0011968075 | H26: ISIN | I26: צמוד למדד המחירים לצרכן | J26: ישראל | K26: ישראל | L26: סחיר | M26: TASE | N26: בנקים | O26: לא | P26: Aaa | Q26: מידרוג Moodys | R26: נייר ערך | S26: ILS | T26: 4.395 | U26: 12/06/2033 | V26: 0.0206 | W26: 0.01973 | X26: החוב לא נחות | Y26: לא | Z26: 30000 | AA26: 1 | AB26: 103.41 | AD26: 31.023 | AG26: שווי הוגן | AH26: 1.5e-05 | AI26: 0.018914664 | AJ26: 0.0028285759
A27: 158 | B27: 1441 | C27: מזרחי טפחות חברה להנפקות בע"מ | D27: 520032046 | E27: ח.פ | F27: מז טפ הנ אגח 68 | G27: IL0012021429 | H27: ISIN | I27: צמוד למדד המחירים לצרכן | J27: ישראל | K27: ישראל | L27: סחיר | M27: TASE | N27: בנקים | O27: לא | P27: AAA | Q27: S&P מעלות | R27: נייר ערך | S27: ILS | T27: 4.93 | U27: 25/12/2033 | V27: 0.0199 | W27: 0.01946 | X27: החוב לא נחות | Y27: לא | Z27: 30000 | AA27: 1 | AB27: 100.72 | AD27: 30.216 | AG27: שווי הוגן | AH27: 1.1e-05 | AI27: 0.018422638 | AJ27: 0.0027549963
A28: 158 | B28: 1441 | C28: מימון ישיר מקבוצת ישיר 2006 בע"מ | D28: 513893123 | E28: ח.פ | F28: מימון ישיר אגח ו | G28: IL0011916595 | H28: ISIN | I28: צמוד למדד המחירים לצרכן | J28: ישראל | K28: ישראל | L28: סחיר | M28: TASE | N28: אשראי חוץ בנקאי | O28: לא | P28: A1 | Q28: מידרוג Moodys | R28: נייר ערך | S28: ILS | T28: 2.129 | U28: 31/03/2027 | V28: 0.0354 | W28: 0.0321 | X28: החוב לא נחות | Y28: לא | Z28: 22000 | AA28: 1 | AB28: 104.17 | AD28: 22.917 | AG28: שווי הוגן | AH28: 3.2e-05 | AI28: 0.013972695 | AJ28: 0.0020895337
... A59: 158 | B59: 1522 | C59: קבוצת עזריאלי בע"מ (לשעבר קנית מימון) | D59: 510960719 | E59: ח.פ | F59: עזריאלי אגח ה | G59: IL0011566036 | H59: ISIN | I59: צמוד למדד המחירים לצרכן | J59: ישראל | K59: ישראל | L59: סחיר | M59: TASE | N59: נדל"ן מניב בישראל | O59: לא | P59: Aa1 | Q59: מידרוג Moodys | R59: נייר ערך | S59: ILS | T59: 2.864 | U59: 30/06/2028 | V59: 0.0177 | W59: 0.02054 | X59: החוב לא נחות | Y59: לא | Z59: 0.57 | AA59: 1 | AB59: 111.11 | AD59: 0.001 | AG59: שווי הוגן | AH59: 0 | AI59: 1.5582675e-06 | AJ59: 6.2782371e-08
A60: 158 | B60: 1522 | C60: קבוצת עזריאלי בע"מ (לשעבר קנית מימון) | D60: 510960719 | E60: ח.פ | F60: עזריאלי קבוצה אגח ב סחיר | G60: IL0011344368 | H60: ISIN | I60: צמוד למדד המחירים לצרכן | J60: ישראל | K60: ישראל | L60: סחיר | M60: TASE | N60: נדל"ן מניב בישראל | O60: לא | P60: AA+ | Q60: S&P מעלות | R60: נייר ערך | S60: ILS | T60: 0.998 | U60: 01/04/2025 | V60: 0.0065 | W60: 0.01649 | X60: החוב לא נחות | Y60: לא | Z60: 0 | AA60: 1 | AB60: 110.63 | AC60: 5.622 | AD60: 5.622 | AG60: שווי הוגן | AI60: 0.013833346 | AJ60: 0.00055734351
A61: 158 | B61: 1522 | C61: עמרם אברהם חברה לבנין בע"מ | D61: 513201582 | E61: ח.פ | F61: עמרם אברהם אגח א | G61: IL0011880445 | H61: ISIN | I61: לא צמוד למדד המחירים לצרכן | J61: ישראל | K61: ישראל | L61: סחיר | M61: TASE | N61: בנייה | O61: לא | P61: N/R | Q61: אחר | R61: מנפיק | S61: ILS | T61: 1.568 | U61: 31/05/2027 | V61: 0.06 | W61: 0.0618 | X61: החוב לא נחות | Y61: לא | Z61: 16100 | AA61: 1 | AB61: 101.88 | AD61: 16.403 | AG61: שווי הוגן | AH61: 6.4e-05 | AI61: 0.040357923 | AJ61: 0.0016260149
A62: 158 | B62: 1522 | C62: פסיפיק אוק אסאואר(בי וי איי) הולדינגס | D62: 1900288 | E62: ח.פ | F62: פסיפיק אגח ג | G62: IL0011976805 | H62: ISIN | I62: לא צמוד למדד המחירים לצרכן | J62: ישראל | K62: ארה"ב | L62: סחיר | M62: TASE | N62: נדל"ן מניב בחו"ל | O62: לא | P62: AA | Q62: S&P מעלות | R62: נייר ערך | S62: ILS | T62: 2.048 | U62: 30/06/2026 | V62: 0.09 | W62: 0.06228 | X62: החוב לא נחות | Y62: לא | Z62: 10000 | AA62: 1 | AB62: 108.21 | AD62: 10.821 | AG62: שווי הוגן | AH62: 3.1e-05 | AI62: 0.026624496 | AJ62: 0.0010726971
A63: 158 | B63: 1522 | C63: בנק לאומי לישראל בע"מ | D63: 520018078 | E63: ח.פ | F63: LUMIIT 3.275 01/29/31 | G63: IL0060404899 | H63: ISIN | I63: צמוד למט"ח | J63: ישראל | K63: ישראל | L63: סחיר | M63: אחר | N63: Banks | O63: לא | P63: BBB | Q63: S&P | R63: נייר ערך | S63: USD | T63: 1.69 | U63: 29/01/2031 | V63: 0.03275 | W63: 0.06581 | X63: החוב לא נחות | Y63: לא | Z63: 2000 | AA63: 3.681 | AB63: 92.834 | AD63: 6.875 | AG63: שווי הוגן | AH63: 3e-06 | AI63: 0.016916266 | AJ63: 0.00068155393
A64: 158 | B64: 1522 | C64: לוויתן בונד בע"מ | D64: 516223864 | E64: ח.פ | F64: LVIATH 6.5 30/06/27 | G64: IL0011677825 | H64: ISIN | I64: צמוד למט"ח | J64: ישראל | K64: ישראל | L64: סחיר | M64: אחר | N64: Energy Equipment & Services | O64: לא | P64: BB- | Q64: S&P | R64: נייר ערך | S64: USD | T64: 2.79 | U64: 30/06/2027 | V64: 0.065 | W64: 0.07799 | X64: החוב לא נחות | Y64: לא | Z64: 1000 | AA64: 3.681 | AB64: 96.843 | AD64: 3.625 | AG64: שווי הוגן | AH64: 2e-06 | AI64: 0.0089181533 | AJ64: 0.00035931111
A65: 158 | B65: 1522 | C65: בנק מזרחי טפחות בע"מ | D65: 520000522 | E65: ח.פ | F65: MZRHIT 3.077 04/07/31 | G65: IL0069508369 | H65: ISIN | I65: צמוד למט"ח | J65: ישראל | K65: ישראל | L65: סחיר | M65: אחר | N65: Banks | O65: לא | P65: BBB- | Q65: S&P | R65: נייר ערך | S65: USD | T65: 1.87 | U65: 07/04/2031 | V65: 0.03077 | W65: 0.07118 | X65: החוב לא נחות | Y65: לא | Z65: 2000 | AA65: 3.681 | AB65: 91.664 | AD65: 6.857 | AG65: שווי הוגן | AH65: 3e-06 | AI65: 0.016871686 | AJ65: 0.00067975781
A66: 158 | B66: 1522 | C66: Summit Properties Limited | D66: 213800KLWIACHRBYR158 | E66: LEI | F66: SMTPLN 2 01/31/25 | G66: XS1757821688 | H66: ISIN | I66: צמוד למט"ח | J66: חו"ל | K66: גרמניה | L66: סחיר | M66: אחר | N66: Real Estate Management & Development | O66: לא | P66: Ba1 | Q66: S&P | R66: נייר ערך | S66: EUR | T66: 0.77 | U66: 31/01/2025 | V66: 0.02 | W66: 0.0763 | X66: החוב לא נחות | Y66: לא | Z66: 1000 | AA66: 3.979 | AB66: 95.576 | AD66: 3.816 | AG66: שווי הוגן | AH66: 3e-06 | AI66: 0.0093898728 | AJ66: 0.00037831662
A67: 158 | B67: 9935 | C67: DELL INC | D67: 3E70L4WYANTIWWIPHC81 | E67: LEI | F67: DELL 5 1/4 02/01/28 | G67: US24703DBJ90 | H67: ISIN | I67: צמוד למט"ח | J67: חו"ל | K67: ארה"ב | L67: סחיר | M67: NYSE | N67: תוכנה ואינטרנט | O67: לא | P67: BBB | Q67: S&P | R67: נייר ערך | S67: USD | T67: 3.32 | U67: 01/02/2028 | V67: 0.0525 | W67: 0.05032 | X67: החוב לא נחות | Y67: לא | Z67: 260000 | AA67: 3.681 | AB67: 101.288 | AD67: 977.622 | AG67: שווי הוגן | AH67: 0.00026 | AI67: 0.0058497028 | AJ67: 0.00089182883
A68: 158 | B68: 9935 | C68: איירפורט סיטי בע"מ | D68: 511659401 | E68: ח.פ | F68: איירפורט אגח ה | G68: IL0011334872 | H68: ISIN | I68: צמוד למדד המחירים לצרכן | J68: ישראל | K68: ישראל | L68: סחיר | M68: TASE | N68: נדל"ן מניב בישראל | O68: לא | P68: AA | Q68: S&P מעלות | R68: נייר ערך | S68: ILS | T68: 2.698 | U68: 28/02/2029 | V68: 0.0234 | W68: 0.02157 | X68: החוב לא נחות | Y68: לא | Z68: 1031250 | AA68: 1 | AB68: 111.84 | AD68: 1153.35 | AG68: שווי הוגן | AH68: 0.000398 | AI68: 0.0069011921 | AJ68: 0.0010521359
A69: 158 | B69: 9935 | C69: אלביט מערכות בע"מ | D69: 520043027 | E69: ח.פ | F69: אלביט מערכות ב' 1.08% | G69: IL0011782351 | H69: ISIN | I69: לא צמוד למדד המחירים לצרכן | J69: ישראל | K69: ישראל | L69: סחיר | M69: TASE | N69: ביטחוניות | O69: לא | P69: AA | Q69: S&P מעלות | R69: נייר ערך | S69: ILS | T69: 2.597 | U69: 01/07/2029 | V69: 0.0108 | W69: 0.04475 | X69: החוב לא נחות | Y69: לא | Z69: 1482900 | AA69: 1 | AB69: 92.04 | AD69: 1364.861 | AG69: שווי הוגן | AH69: 0.00113 | AI69: 0.0081667916 | AJ69: 0.0012450855
A70: 158 | B70: 9935 | C70: אלוני-חץ נכסים והשקעות בע"מ | D70: 520038506 | E70: ח.פ | F70: אלוני חץ אגח ט | G70: IL0039003541 | H70: ISIN | I70: לא צמוד למדד המחירים לצרכן | J70: ישראל | K70: ישראל | L70: סחיר | M70: TASE | N70: נדל"ן מניב בישראל | O70: לא | P70: AA- | Q70: S&P מעלות | R70: נייר ערך | S70: ILS | T70: 1.858 | U70: 28/02/2027 | V70: 0.0385 | W70: 0.04768 | X70: החוב לא נחות | Y70: לא | Z70: 1506453.3 | AA70: 1 | AB70: 98.71 | AD70: 1487.02 | AG70: שווי הוגן | AH70: 0.001572 | AI70: 0.0088977423 | AJ70: 0.0013565242
A71: 158 | B71: 9935 | C71: אלוני-חץ נכסים והשקעות בע"מ | D71: 520038506 | E71: ח.פ | F71: אלוני חץ אגח טו | G71: IL0011894149 | H71: ISIN | I71: צמוד למדד המחירים לצרכן | J71: ישראל | K71: ישראל | L71: סחיר | M71: TASE | N71: נדל"ן מניב בישראל | O71: לא | P71: Aa3 | Q71: מידרוג Moodys | R71: נייר ערך | S71: ILS | T71: 7.443 | U71: 28/02/2037 | V71: 0.0256 | W71: 0.03962 | X71: החוב לא נחות | Y71: לא | Z71: 520000 | AA71: 1 | AB71: 94.33 | AD71: 490.516 | AG71: שווי הוגן | AH71: 0.000778 | AI71: 0.0029350545 | AJ71: 0.00044746996
A72: 158 | B72: 9935 | C72: אלקטרה בע"מ | D72: 520028911 | E72: ח.פ | F72: אלקטרה אגח ד | G72: IL0073901493 | H72: ISIN | I72: לא צמוד למדד המחירים לצרכן | J72: ישראל | K72: ישראל | L72: סחיר | M72: TASE | N72: השקעה ואחזקות | O72: לא | P72: A1 | Q72: מידרוג Moodys | R72: נייר ערך | S72: ILS | T72: 1.2 | U72: 30/06/2026 | V72: 0.04 | W72: 0.04906 | X72: החוב לא נחות | Y72: לא | Z72: 1613845.7 | AA72: 1 | AB72: 100.02 | AD72: 1614.168 | AG72: שווי הוגן | AH72: 0.008166 | AI72: 0.0096585484 | AJ72: 0.0014725144
... A105: 158 | B105: 9935 | C105: מליסרון בע"מ | D105: 520037789 | E105: ח.פ | F105: מליסרון אגח כא | G105: IL0011946386 | H105: ISIN | I105: צמוד למדד המחירים לצרכן | J105: ישראל | K105: ישראל | L105: סחיר | M105: TASE | N105: נדל"ן מניב בישראל | O105: לא | P105: AA | Q105: S&P מעלות | R105: נייר ערך | S105: ILS | T105: 6.45 | U105: 01/01/2037 | V105: 0.0361 | W105: 0.02996 | X105: החוב לא נחות | Y105: לא | Z105: 482130 | AA105: 1 | AB105: 107.22 | AD105: 516.94 | AG105: שווי הוגן | AH105: 0.001049 | AI105: 0.0030931641 | AJ105: 0.00047157488
A106: 158 | B106: 9935 | C106: מליסרון בע"מ | D106: 520037789 | E106: ח.פ | F106: מליסרון אגח י' | G106: IL0032301900 | H106: ISIN | I106: צמוד למדד המחירים לצרכן | J106: ישראל | K106: ישראל | L106: סחיר | M106: TASE | N106: נדל"ן מניב בישראל | O106: לא | P106: AA | Q106: S&P מעלות | R106: נייר ערך | S106: ILS | T106: 1.243 | U106: 10/07/2025 | V106: 0.0176 | W106: 0.01394 | X106: החוב לא נחות | Y106: לא | Z106: 1165547.9 | AA106: 1 | AB106: 114.03 | AC106: 930.821 | AD106: 2259.895 | AG106: שווי הוגן | AH106: 0.000873 | AI106: 0.01352232 | AJ106: 0.0020615739
A107: 158 | B107: 9935 | C107: מליסרון בע"מ | D107: 520037789 | E107: ח.פ | F107: מליסרון אגח כ | G107: IL0032304227 | H107: ISIN | I107: צמוד למדד המחירים לצרכן | J107: ישראל | K107: ישראל | L107: סחיר | M107: TASE | N107: נדל"ן מניב בישראל | O107: לא | P107: AA | Q107: S&P מעלות | R107: נייר ערך | S107: ILS | T107: 5.657 | U107: 01/07/2030 | V107: 0.0025 | W107: 0.02648 | X107: החוב לא נחות | Y107: לא | Z107: 1097038.8 | AA107: 1 | AB107: 95.66 | AD107: 1049.427 | AG107: שווי הוגן | AH107: 0.000845 | AI107: 0.0062793597 | AJ107: 0.00095733309
A108: 158 | B108: 9935 | C108: סלקום ישראל בע"מ | D108: 511930125 | E108: ח.פ | F108: סלקום אגח ט | G108: IL0011328361 | H108: ISIN | I108: לא צמוד למדד המחירים לצרכן | J108: ישראל | K108: ישראל | L108: סחיר | M108: TASE | N108: תקשורת ומדיה | O108: לא | P108: A+ | Q108: S&P מעלות | R108: נייר ערך | S108: ILS | T108: 0.745 | U108: 06/07/2025 | V108: 0.0414 | W108: 0.05097 | X108: החוב לא נחות | Y108: לא | Z108: 1359598.8 | AA108: 1 | AB108: 100.34 | AD108: 1364.221 | AG108: שווי הוגן | AH108: 0.006039 | AI108: 0.0081629638 | AJ108: 0.0012445019
A109: 158 | B109: 9935 | C109: קבוצת עזריאלי בע"מ (לשעבר קנית מימון) | D109: 510960719 | E109: ח.פ | F109: עזריאלי אגח ז | G109: IL0011786725 | H109: ISIN | I109: צמוד למדד המחירים לצרכן | J109: ישראל | K109: ישראל | L109: סחיר | M109: TASE | N109: נדל"ן מניב בישראל | O109: לא | P109: AA+ | Q109: S&P מעלות | R109: נייר ערך | S109: ILS | T109: 7.249 | U109: 02/07/2036 | V109: 0.009 | W109: 0.02898 | X109: החוב לא נחות | Y109: לא | Z109: 1000000 | AA109: 1 | AB109: 95.37 | AD109: 953.7 | AG109: שווי הוגן | AH109: 0.000525 | AI109: 0.0057065652 | AJ109: 0.00087000648
A110: 158 | B110: 9935 | C110: בנק הפועלים בע"מ | D110: 520000118 | E110: ח.פ | F110: פועלים אגח 100 | G110: IL0066204889 | H110: ISIN | I110: לא צמוד למדד המחירים לצרכן | J110: ישראל | K110: ישראל | L110: סחיר | M110: TASE | N110: בנקים | O110: לא | P110: Aaa | Q110: מידרוג Moodys | R110: נייר ערך | S110: ILS | T110: 3.845 | U110: 09/12/2031 | V110: 0.025 | W110: 0.04514 | X110: החוב לא נחות | Y110: לא | Z110: 1600000 | AA110: 1 | AB110: 93.42 | AD110: 1494.72 | AG110: שווי הוגן | AH110: 0.000539 | AI110: 0.0089438158 | AJ110: 0.0013635484
A111: 158 | B111: 9935 | C111: בנק הפועלים בע"מ | D111: 520000118 | E111: ח.פ | F111: פועלים אגח 203 | G111: IL0011998684 | H111: ISIN | I111: צמוד למדד המחירים לצרכן | J111: ישראל | K111: ישראל | L111: סחיר | M111: TASE | N111: בנקים | O111: לא | P111: Aaa | Q111: מידרוג Moodys | R111: נייר ערך | S111: ILS | T111: 3.54 | U111: 02/12/2030 | V111: 0.0175 | W111: 0.01893 | X111: החוב לא נחות | Y111: לא | Z111: 525044.99 | AA111: 1 | AB111: 111.16 | AD111: 583.64 | AG111: שווי הוגן | AH111: 0.000182 | AI111: 0.003492272 | AJ111: 0.00053242172
A112: 158 | B112: 9935 | C112: פז חברת הנפט בע"מ | D112: 510216054 | E112: ח.פ | F112: פז נפט אגח ז | G112: IL0011425951 | H112: ISIN | I112: צמוד למדד המחירים לצרכן | J112: ישראל | K112: ישראל | L112: סחיר | M112: TASE | N112: אנרגיה | O112: לא | P112: AA- | Q112: S&P מעלות | R112: נייר ערך | S112: ILS | T112: 3.565 | U112: 01/12/2030 | V112: 0.0123 | W112: 0.02209 | X112: החוב לא נחות | Y112: לא | Z112: 2869066.9 | AA112: 1 | AB112: 108.66 | AD112: 3117.528 | AG112: שווי הוגן | AH112: 0.002256 | AI112: 0.01865406 | AJ112: 0.0028439442
A113: 158 | B113: 9935 | C113: חברת פרטנר תקשורת בע"מ | D113: 520044314 | E113: ח.פ | F113: פרטנר אגח ו | G113: IL0011414153 | H113: ISIN | I113: לא צמוד למדד המחירים לצרכן | J113: ישראל | K113: ישראל | L113: סחיר | M113: TASE | N113: תקשורת ומדיה | O113: לא | P113: A+ | Q113: S&P מעלות | R113: נייר ערך | S113: ILS | T113: 0.233 | U113: 25/06/2024 | V113: 0.0216 | W113: 0.05556 | X113: החוב לא נחות | Y113: לא | Z113: 990664.64 | AA113: 1 | AB113: 99.83 | AD113: 988.981 | AG113: שווי הוגן | AH113: 0.007746 | AI113: 0.0059176699 | AJ113: 0.00090219089
A114: 158 | B114: 9935 | C114: חברת פרטנר תקשורת בע"מ | D114: 520044314 | E114: ח.פ | F114: פרטנר אגח ז | G114: IL0011563975 | H114: ISIN | I114: לא צמוד למדד המחירים לצרכן | J114: ישראל | K114: ישראל | L114: סחיר | M114: TASE | N114: תקשורת ומדיה | O114: לא | P114: A+ | Q114: S&P מעלות | R114: נייר ערך | S114: ILS | T114: 2.203 | U114: 25/06/2027 | V114: 0.04 | W114: 0.04798 | X114: החוב לא נחות | Y114: לא | Z114: 1220372.8 | AA114: 1 | AB114: 101.47 | AD114: 1238.312 | AG114: שווי הוגן | AH114: 0.001793 | AI114: 0.007409573 | AJ114: 0.0011296421
A115: 158 | B115: 9935 | C115: קרסו מוטורס בע"מ | D115: 514065283 | E115: ח.פ | F115: קרסו מוטורס אגח ג | G115: IL0011418295 | H115: ISIN | I115: לא צמוד למדד המחירים לצרכן | J115: ישראל | K115: ישראל | L115: סחיר | M115: TASE | N115: מסחר | O115: לא | P115: AA- | Q115: S&P מעלות | R115: נייר ערך | S115: ILS | T115: 2.063 | U115: 01/09/2027 | V115: 0.023 | W115: 0.04895 | X115: החוב לא נחות | Y115: לא | Z115: 1761290.3 | AA115: 1 | AB115: 95.14 | AD115: 1675.692 | AG115: שווי הוגן | AH115: 0.002157 | AI115: 0.010026679 | AJ115: 0.0015286385
A116: 158 | B116: 9935 | C116: שופר-סל בע"מ | D116: 520022732 | E116: ח.פ | F116: שופרסל אגח ד | G116: IL0077701915 | H116: ISIN | I116: צמוד למדד המחירים לצרכן | J116: ישראל | K116: ישראל | L116: סחיר | M116: TASE | N116: רשתות שיווק | O116: לא | P116: AA | Q116: S&P מעלות | R116: נייר ערך | S116: ILS | T116: 2.892 | U116: 08/10/2029 | V116: 0.0299 | W116: 0.01876 | X116: החוב לא נחות | Y116: לא | Z116: 1305116 | AA116: 1 | AB116: 116.68 | AD116: 1522.809 | AG116: שווי הוגן | AH116: 0.006315 | AI116: 0.0091118914 | AJ116: 0.0013891727
A117: 158 | B117: 9935 | C117: שופר-סל בע"מ | D117: 520022732 | E117: ח.פ | F117: שופרסל אגח ה | G117: IL0077702095 | H117: ISIN | I117: לא צמוד למדד המחירים לצרכן | J117: ישראל | K117: ישראל | L117: סחיר | M117: TASE | N117: רשתות שיווק | O117: לא | P117: AA | Q117: S&P מעלות | R117: נייר ערך | S117: ILS | T117: 2.764 | U117: 08/10/2029 | V117: 0.0509 | W117: 0.04639 | X117: החוב לא נחות | Y117: לא | Z117: 2039991.2 | AA117: 1 | AB117: 103.64 | AD117: 2114.247 | AG117: שווי הוגן | AH117: 0.002823 | AI117: 0.012650821 | AJ117: 0.0019287077
A118: 158 | B118: 9935 | C118: שיכון ובינוי בע"מ | D118: 520036104 | E118: ח.פ | F118: שיכון ובינוי אגח 7 | G118: IL0011297418 | H118: ISIN | I118: לא צמוד למדד המחירים לצרכן | J118: ישראל | K118: ישראל | L118: סחיר | M118: TASE | N118: בנייה | O118: לא | P118: A | Q118: מידרוג Moodys | R118: נייר ערך | S118: ILS | T118: 0.985 | U118: 01/04/2025 | V118: 0.0623 | W118: 0.04935 | X118: החוב לא נחות | Y118: לא | Z118: 592006.5 | AA118: 1 | AB118: 101.32 | AC118: 628.889 | AD118: 1228.71 | AG118: שווי הוגן | AH118: 0.001861 | AI118: 0.0073521137 | AJ118: 0.0011208821
A119: 158 | B119: 9935 | C119: שיכון ובינוי אנרגיה בע"מ | D119: 510459928 | E119: ח.פ | F119: שיכון ובינוי אנרגיה אגח א' | G119: IL0011985715 | H119: ISIN | I119: לא צמוד למדד המחירים לצרכן | J119: ישראל | K119: ישראל | L119: סחיר | M119: TASE | N119: אנרגיה | O119: לא | P119: A3 | Q119: מידרוג Moodys | R119: נייר ערך | S119: ILS | T119: 4.556 | U119: 30/06/2034 | V119: 0.0677 | W119: 0.05884 | X119: החוב לא נחות | Y119: לא | Z119: 900000 | AA119: 1 | AB119: 108.96 | AD119: 980.64 | AG119: שווי הוגן | AH119: 0 | AI119: 0.0058677635 | AJ119: 0.00089458232
A120: 158 | B120: 9935 | C120: תמר פטרוליום בעמ | D120: 515334662 | E120: ח.פ | F120: תמר פטרוליום אגח א | G120: IL0011413320 | H120: ISIN | I120: צמוד למט"ח | J120: ישראל | K120: ישראל | L120: סחיר | M120: TASE | N120: חיפושי נפט וגז | O120: לא | P120: A1 | Q120: מידרוג Moodys | R120: נייר ערך | S120: ILS | T120: 3.3 | U120: 30/08/2028 | V120: 0.0469 | W120: 0.06903 | X120: החוב לא נחות | Y120: לא | Z120: 2063314.8 | AA120: 1 | AB120: 98.27 | AD120: 2027.619 | AG120: שווי הוגן | AH120: 0.001408 | AI120: 0.012132476 | AJ120: 0.0018496824
A121: 158 | B121: 9935 | C121: לוויתן בונד בע"מ | D121: 516223864 | E121: ח.פ | F121: LVIA 6.125% 6/25 | G121: IL0011677742 | H121: ISIN | I121: צמוד למט"ח | J121: ישראל | K121: ישראל | L121: סחיר | M121: אחר | N121: Energy Equipment & Services | O121: לא | P121: Ba3 | Q121: Moodys | R121: נייר ערך | S121: USD | T121: 1.14 | U121: 30/06/2025 | V121: 0.06125 | W121: 0.07568 | X121: החוב לא נחות | Y121: לא | Z121: 350000 | AA121: 3.681 | AB121: 98.581 | AD121: 1289.796 | AG121: שווי הוגן | AH121: 0.000583 | AI121: 0.0077176323 | AJ121: 0.001176608
A122: 158 | B122: 9935 | C122: אאורה השקעות בע"מ | D122: 520038274 | E122: ח.פ | F122: אאורה אגח טז | G122: IL0037305799 | H122: ISIN | I122: לא צמוד למדד המחירים לצרכן | J122: ישראל | K122: ישראל | L122: סחיר | M122: TASE | N122: בנייה | O122: לא | P122: A3 | Q122: מידרוג Moodys | R122: נייר ערך | S122: ILS | T122: 1.912 | U122: 30/09/2027 | V122: 0.035 | W122: 0.05656 | X122: החוב לא נחות | Y122: לא | Z122: 728208 | AA122: 1 | AB122: 96.19 | AD122: 700.463 | AG122: שווי הוגן | AH122: 0.002913 | AI122: 0.0041912964 | AJ122: 0.00063899296
A123: 158 | B123: 9935 | C123: אאורה השקעות בע"מ | D123: 520038274 | E123: ח.פ | F123: אאורה אגח יז %3.85 31/01/2029 | G123: IL0011935801 | H123: ISIN | I123: צמוד למדד המחירים לצרכן | J123: ישראל | K123: ישראל | L123: סחיר | M123: TASE | N123: בנייה | O123: לא | P123: A- | Q123: S&P מעלות | R123: נייר ערך | S123: ILS | T123: 3.269 | U123: 31/01/2029 | V123: 0.0385 | W123: 0.03176 | X123: החוב לא נחות | Y123: לא | Z123: 330000 | AA123: 1 | AB123: 106.03 | AD123: 349.899 | AG123: שווי הוגן | AH123: 0.001864 | AI123: 0.0020936578 | AJ123: 0.00031919304
A124: 158 | B124: 9935 | C124: אאורה השקעות בע"מ | D124: 520038274 | E124: ח.פ | F124: אאורה אגח יז חסום עד 14.05.24 | G124: IL0011935801 | H124: ISIN | I124: צמוד למדד המחירים לצרכן | J124: ישראל | K124: ישראל | L124: חסום | M124: TASE | N124: בנייה | O124: לא | P124: A- | Q124: S&P מעלות | R124: נייר ערך | S124: ILS | T124: 3.45 | U124: 31/01/2029 | V124: 0.0385 | W124: 0.0297 | X124: החוב לא נחות | Y124: לא | Z124: 416000 | AA124: 1 | AB124: 105.578 | AD124: 439.204 | AG124: שווי הוגן | AH124: 0.00235 | AI124: 0.0026280241 | AJ124: 0.00040066099
A125: 158 | B125: 9935 | C125: אדמה פתרונות לחקלאות בע"מ | D125: 520043605 | E125: ח.פ | F125: אדמה אגח ב | G125: IL0011109159 | H125: ISIN | I125: צמוד למדד המחירים לצרכן | J125: ישראל | K125: ישראל | L125: סחיר | M125: TASE | N125: כימיה, גומי ופלסטיק | O125: לא | P125: AA- | Q125: S&P מעלות | R125: נייר ערך | S125: ILS | T125: 5.674 | U125: 30/11/2036 | V125: 0.0515 | W125: 0.02931 | X125: החוב לא נחות | Y125: לא | Z125: 1229896.1 | AA125: 1 | AB125: 154.27 | AD125: 1897.361 | AG125: שווי הוגן | AH125: 0.000393 | AI125: 0.011353059 | AJ125: 0.0017308547
A126: 158 | B126: 9935 | C126: איירפורט סיטי בע"מ | D126: 511659401 | E126: ח.פ | F126: איירפורט אגח ה | G126: IL0011334872 | H126: ISIN | I126: צמוד למדד המחירים לצרכן | J126: ישראל | K126: ישראל | L126: סחיר | M126: TASE | N126: נדל"ן מניב בישראל | O126: לא | P126: AA | Q126: S&P מעלות | R126: נייר ערך | S126: ILS | T126: 2.698 | U126: 28/02/2029 | V126: 0.0234 | W126: 0.02157 | X126: החוב לא נחות | Y126: לא | Z126: 639019.09 | AA126: 1 | AB126: 111.84 | AD126: 714.679 | AG126: שווי הוגן | AH126: 0.000247 | AI126: 0.0042763574 | AJ126: 0.00065196112
A127: 158 | B127: 9935 | C127: אלבר שירותי מימונית בע"מ | D127: 512025891 | E127: ח.פ | F127: אלבר אגח יט | G127: IL0011918245 | H127: ISIN | I127: צמוד למדד המחירים לצרכן | J127: ישראל | K127: ישראל | L127: סחיר | M127: TASE | N127: שירותים | O127: לא | P127: A+ | Q127: S&P מעלות | R127: נייר ערך | S127: ILS | T127: 2.036 | U127: 15/05/2028 | V127: 0.032 | W127: 0.02974 | X127: החוב לא נחות | Y127: לא | Z127: 0.89 | AA127: 1 | AB127: 104.3 | AD127: 0.001 | AG127: שווי הוגן | AH127: 0 | AI127: 5.5544021e-09 | AJ127: 8.4680813e-10
A128: 158 | B128: 9935 | C128: אלבר שירותי מימונית בע"מ | D128: 512025891 | E128: ח.פ | F128: אלבר אגח כ | G128: IL0011918328 | H128: ISIN | I128: לא צמוד למדד המחירים לצרכן | J128: ישראל | K128: ישראל | L128: סחיר | M128: TASE | N128: שירותים | O128: לא | P128: A+ | Q128: S&P מעלות | R128: נייר ערך | S128: ILS | T128: 2.059 | U128: 20/06/2028 | V128: 0.057 | W128: 0.05913 | X128: החוב לא נחות | Y128: לא | Z128: 367200 | AA128: 1 | AB128: 100.07 | AD128: 367.457 | AG128: שווי הוגן | AH128: 0.000926 | AI128: 0.0021987182 | AJ128: 0.00033521024
A129: 158 | B129: 9935 | C129: אלדן תחבורה בע"מ | D129: 510454333 | E129: ח.פ | F129: אלדן תחבורה אגח ח | G129: IL0011924425 | H129: ISIN | I129: צמוד למדד המחירים לצרכן | J129: ישראל | K129: ישראל | L129: סחיר | M129: TASE | N129: שירותים | O129: לא | P129: A+ | Q129: S&P מעלות | R129: נייר ערך | S129: ILS | T129: 2.987 | U129: 30/09/2029 | V129: 0.0323 | W129: 0.02875 | X129: החוב לא נחות | Y129: לא | Z129: 428160 | AA129: 1 | AB129: 104.51 | AD129: 447.47 | AG129: שווי הוגן | AH129: 0.000911 | AI129: 0.0026774843 | AJ129: 0.00040820155
A130: 158 | B130: 9935 | C130: אלומיי קפיטל בע"מ | D130: 520039868 | E130: ח.פ | F130: אלומיי אגח ו | G130: IL0012030743 | H130: ISIN | I130: לא צמוד למדד המחירים לצרכן | J130: ישראל | K130: ישראל | L130: סחיר | M130: TASE | N130: אנרגיה מתחדשת | O130: לא | P130: Baa1 | Q130: מידרוג Moodys | R130: מנפיק | S130: ILS | T130: 3.82 | U130: 31/03/2030 | V130: 0.055 | W130: 0.06694 | X130: החוב לא נחות | Y130: לא | Z130: 418000 | AA130: 1 | AB130: 96.08 | AD130: 401.614 | AG130: שווי הוגן | AH130: 0 | AI130: 0.0024031024 | AJ130: 0.00036637006
... A201: 158 | B201: 9935 | C201: קבוצת עזריאלי בע"מ (לשעבר קנית מימון) | D201: 510960719 | E201: ח.פ | F201: עזריאלי אגח ז | G201: IL0011786725 | H201: ISIN | I201: צמוד למדד המחירים לצרכן | J201: ישראל | K201: ישראל | L201: סחיר | M201: TASE | N201: נדל"ן מניב בישראל | O201: לא | P201: AA+ | Q201: S&P מעלות | R201: נייר ערך | S201: ILS | T201: 7.249 | U201: 02/07/2036 | V201: 0.009 | W201: 0.02898 | X201: החוב לא נחות | Y201: לא | Z201: 453000 | AA201: 1 | AB201: 95.37 | AD201: 432.026 | AG201: שווי הוגן | AH201: 0.000238 | AI201: 0.002585074 | AJ201: 0.00039411294
A202: 158 | B202: 9935 | C202: קבוצת עזריאלי בע"מ (לשעבר קנית מימון) | D202: 510960719 | E202: ח.פ | F202: עזריאלי קבוצה אגח ב סחיר | G202: IL0011344368 | H202: ISIN | I202: צמוד למדד המחירים לצרכן | J202: ישראל | K202: ישראל | L202: סחיר | M202: TASE | N202: נדל"ן מניב בישראל | O202: לא | P202: AA+ | Q202: S&P מעלות | R202: נייר ערך | S202: ILS | T202: 0.998 | U202: 01/04/2025 | V202: 0.0065 | W202: 0.01649 | X202: החוב לא נחות | Y202: לא | Z202: 397101 | AA202: 1 | AB202: 110.63 | AC202: 446.524 | AD202: 885.836 | AG202: שווי הוגן | AH202: 0.001315 | AI202: 0.005300496 | AJ202: 0.00080809835
A203: 158 | B203: 9935 | C203: עמרם אברהם חברה לבנין בע"מ | D203: 513201582 | E203: ח.פ | F203: עמרם אברהם אגח א | G203: IL0011880445 | H203: ISIN | I203: לא צמוד למדד המחירים לצרכן | J203: ישראל | K203: ישראל | L203: סחיר | M203: TASE | N203: בנייה | O203: לא | P203: N/R | Q203: אחר | R203: מנפיק | S203: ILS | T203: 1.568 | U203: 31/05/2027 | V203: 0.06 | W203: 0.0618 | X203: החוב לא נחות | Y203: לא | Z203: 778700 | AA203: 1 | AB203: 101.88 | AD203: 793.34 | AG203: שווי הוגן | AH203: 0.003115 | AI203: 0.0047470315 | AJ203: 0.00072371874
A204: 158 | B204: 9935 | C204: בנק הפועלים בע"מ | D204: 520000118 | E204: ח.פ | F204: פועלים אגח 100 | G204: IL0066204889 | H204: ISIN | I204: לא צמוד למדד המחירים לצרכן | J204: ישראל | K204: ישראל | L204: סחיר | M204: TASE | N204: בנקים | O204: לא | P204: Aaa | Q204: מידרוג Moodys | R204: נייר ערך | S204: ILS | T204: 3.845 | U204: 09/12/2031 | V204: 0.025 | W204: 0.04514 | X204: החוב לא נחות | Y204: לא | Z204: 1900000 | AA204: 1 | AB204: 93.42 | AD204: 1774.98 | AG204: שווי הוגן | AH204: 0.00064 | AI204: 0.010620781 | AJ204: 0.0016192137
A205: 158 | B205: 9935 | C205: בנק הפועלים בע"מ | D205: 520000118 | E205: ח.פ | F205: פועלים אגח 200 | G205: IL0066204962 | H205: ISIN | I205: צמוד למדד המחירים לצרכן | J205: ישראל | K205: ישראל | L205: סחיר | M205: TASE | N205: בנקים | O205: לא | P205: Aaa | Q205: מידרוג Moodys | R205: נייר ערך | S205: ILS | T205: 4.089 | U205: 09/12/2031 | V205: 0.001 | W205: 0.01965 | X205: החוב לא נחות | Y205: לא | Z205: 1239535.6 | AA205: 1 | AB205: 101.03 | AD205: 1252.303 | AG205: שווי הוגן | AH205: 0.00047 | AI205: 0.0074932866 | AJ205: 0.0011424049
A206: 158 | B206: 9935 | C206: בנק הפועלים בע"מ | D206: 520000118 | E206: ח.פ | F206: פועלים אגח 201 | G206: IL0011913451 | H206: ISIN | I206: צמוד למדד המחירים לצרכן | J206: ישראל | K206: ישראל | L206: סחיר | M206: TASE | N206: בנקים | O206: לא | P206: Aaa | Q206: מידרוג Moodys | R206: נייר ערך | S206: ILS | T206: 4.453 | U206: 29/11/2032 | V206: 0.0139 | W206: 0.01992 | X206: החוב לא נחות | Y206: לא | Z206: 1935200 | AA206: 1 | AB206: 101.5 | AD206: 1964.228 | AG206: שווי הוגן | AH206: 0.001075 | AI206: 0.011753167 | AJ206: 0.0017918539
A207: 158 | B207: 9935 | C207: בנק הפועלים בע"מ | D207: 520000118 | E207: ח.פ | F207: פועלים אגח 203 | G207: IL0011998684 | H207: ISIN | I207: צמוד למדד המחירים לצרכן | J207: ישראל | K207: ישראל | L207: סחיר | M207: TASE | N207: בנקים | O207: לא | P207: Aaa | Q207: מידרוג Moodys | R207: נייר ערך | S207: ILS | T207: 3.54 | U207: 02/12/2030 | V207: 0.0175 | W207: 0.01893 | X207: החוב לא נחות | Y207: לא | Z207: 1012372.5 | AA207: 1 | AB207: 111.16 | AD207: 1125.353 | AG207: שווי הוגן | AH207: 0.00035 | AI207: 0.0067336707 | AJ207: 0.001026596
A208: 158 | B208: 9935 | C208: הפועלים הנפקות בע"מ | D208: 520032640 | E208: ח.פ | F208: פועלים הנפקות סדרה 34 | G208: IL0019405765 | H208: ISIN | I208: צמוד למדד המחירים לצרכן | J208: ישראל | K208: ישראל | L208: סחיר | M208: TASE | N208: בנקים | O208: לא | P208: AAA | Q208: S&P מעלות | R208: נייר ערך | S208: ILS | T208: 0.01 | U208: 26/03/2023 | V208: 0.007 | W208: 0.2438 | X208: החוב לא נחות | Y208: לא | Z208: -0.13 | AA208: 1 | AB208: 111.44 | AD208: 0 | AG208: שווי הוגן | AH208: 0 | AI208: -8.6685699e-10 | AJ208: -1.3215852e-10
A209: 158 | B209: 9935 | C209: בנק הפועלים בע"מ | D209: 520000118 | E209: ח.פ | F209: פועלים התחייבות נדחים ו | G209: IL0066205530 | H209: ISIN | I209: צמוד למדד המחירים לצרכן | J209: ישראל | K209: ישראל | L209: סחיר | M209: TASE | N209: בנקים | O209: לא | P209: Aa2 | Q209: מידרוג Moodys | R209: נייר ערך | S209: ILS | T209: 3.899 | U209: 13/03/2028 | V209: 0.0084 | W209: 0.026 | X209: החוב לא נחות | Y209: לא | Z209: 1050000 | AA209: 1 | AB209: 101.18 | AD209: 1062.39 | AG209: שווי הוגן | AH209: 0.002641 | AI209: 0.0063569233 | AJ209: 0.00096915821
A210: 158 | B210: 9935 | C210: פורמולה מערכות (1985)בע"מ | D210: 520036690 | E210: ח.פ | F210: פורמולה אגח א | G210: IL0025601423 | H210: ISIN | I210: לא צמוד למדד המחירים לצרכן | J210: ישראל | K210: ישראל | L210: סחיר | M210: TASE | N210: שירותי מידע | O210: לא | P210: Aa3 | Q210: מידרוג Moodys | R210: נייר ערך | S210: ILS | T210: 0.252 | U210: 02/07/2024 | V210: 0.028 | W210: 0.04891 | X210: החוב לא נחות | Y210: לא | Z210: 0.31 | AA210: 1 | AB210: 100.2 | AD210: 0 | AG210: שווי הוגן | AH210: 0 | AI210: 1.8586277e-09 | AJ210: 2.8336103e-10
A211: 158 | B211: 9935 | C211: פז חברת הנפט בע"מ | D211: 510216054 | E211: ח.פ | F211: פז נפט ו | G211: IL0011395428 | H211: ISIN | I211: צמוד למדד המחירים לצרכן | J211: ישראל | K211: ישראל | L211: סחיר | M211: TASE | N211: אנרגיה | O211: לא | P211: AA- | Q211: S&P מעלות | R211: נייר ערך | S211: ILS | T211: 2.581 | U211: 30/11/2028 | V211: 0.0194 | W211: 0.01863 | X211: החוב לא נחות | Y211: לא | Z211: 0.36 | AA211: 1 | AB211: 113.16 | AD211: 0 | AG211: שווי הוגן | AH211: 0 | AI211: 2.4375775e-09 | AJ211: 3.7162605e-10
A212: 158 | B212: 9935 | C212: פסיפיק אוק אסאואר(בי וי איי) הולדינגס | D212: 1900288 | E212: ח.פ | F212: פסיפיק אגח ג | G212: IL0011976805 | H212: ISIN | I212: לא צמוד למדד המחירים לצרכן | J212: ישראל | K212: ארה"ב | L212: סחיר | M212: TASE | N212: נדל"ן מניב בחו"ל | O212: לא | P212: AA | Q212: S&P מעלות | R212: נייר ערך | S212: ILS | T212: 2.048 | U212: 30/06/2026 | V212: 0.09 | W212: 0.06228 | X212: החוב לא נחות | Y212: לא | Z212: 527000 | AA212: 1 | AB212: 108.21 | AD212: 570.267 | AG212: שווי הוגן | AH212: 0.001649 | AI212: 0.0034122513 | AJ212: 0.000520222
A213: 158 | B213: 9935 | C213: פתאל נכסים(אירופה)בע"מ | D213: 515328250 | E213: ח.פ | F213: פתאל אירופה אגח ג | G213: IL0011418527 | H213: ISIN | I213: לא צמוד למדד המחירים לצרכן | J213: ישראל | K213: ישראל | L213: סחיר | M213: TASE | N213: נדל"ן מניב בחו"ל | O213: לא | P213: A2 | Q213: מידרוג Moodys | R213: נייר ערך | S213: ILS | T213: 2.15 | U213: 30/08/2027 | V213: 0.0265 | W213: 0.05427 | X213: החוב לא נחות | Y213: לא | Z213: 650201.06 | AA213: 1 | AB213: 94.87 | AD213: 616.846 | AG213: שווי הוגן | AH213: 0.000907 | AI213: 0.003690962 | AJ213: 0.00056271343
A214: 158 | B214: 9935 | C214: פתאל החזקות 1998 בע"מ | D214: 512607888 | E214: ח.פ | F214: פתאל החזקות אגח ג | G214: IL0011617854 | H214: ISIN | I214: לא צמוד למדד המחירים לצרכן | J214: ישראל | K214: ישראל | L214: סחיר | M214: TASE | N214: מלונאות ותיירות | O214: לא | P214: A2 | Q214: מידרוג Moodys | R214: נייר ערך | S214: ILS | T214: 3.607 | U214: 31/08/2031 | V214: 0.0216 | W214: 0.05686 | X214: החוב לא נחות | Y214: לא | Z214: 683057.96 | AA214: 1 | AB214: 88.45 | AD214: 604.165 | AG214: שווי הוגן | AH214: 0.00083 | AI214: 0.003615084 | AJ214: 0.00055114529
... A223: 158 | B223: 9935 | C223: CITIGROUP INC | D223: 6SHGI4ZSSLCXXQSBB395 | E223: LEI | F223: C 4.14 05/24/25 | G223: US172967NQ03 | H223: ISIN | I223: צמוד למט"ח | J223: חו"ל | K223: ארה"ב | L223: סחיר | M223: אחר | N223: Banks | O223: לא | P223: BBB+ | Q223: Moodys | R223: נייר ערך | S223: USD | T223: 0.12 | U223: 24/05/2025 | V223: 0.0414 | W223: 0.06583 | X223: החוב לא נחות | Y223: לא | Z223: 525000 | AA223: 3.681 | AB223: 99.724 | AD223: 1954.757 | AG223: שווי הוגן | AH223: 0.00035 | AI223: 0.011696493 | AJ223: 0.0017832137
A224: 158 | B224: 9935 | C224: GENERAL MOTORS CORP | D224: 2YD5STGSJNMUB7H76907 | E224: LEI | F224: GM 4.35 04/09/25 | G224: US37045XCK00 | H224: ISIN | I224: צמוד למט"ח | J224: חו"ל | K224: ארה"ב | L224: סחיר | M224: אחר | N224: Automobiles | O224: לא | P224: BBB | Q224: S&P | R224: נייר ערך | S224: USD | T224: 0.96 | U224: 09/04/2025 | V224: 0.0435 | W224: 0.05635 | X224: החוב לא נחות | Y224: לא | Z224: 270000 | AA224: 3.681 | AB224: 98.779 | AC224: 5.844 | AD224: 1003.251 | AG224: שווי הוגן | AH224: 0.00027 | AI224: 0.0060030576 | AJ224: 0.00091520886
A225: 158 | B225: 9935 | C225: Energean plc | D225: 549300RVMKU0CYUZBB05 | E225: LEI | F225: ENOIGA 5 3/8 30/03/28 | G225: IL0011736738 | H225: ISIN | I225: צמוד למט"ח | J225: חו"ל | K225: גלובלי | L225: סחיר | M225: אחר | N225: חיפושי נפט וגז | O225: לא | P225: Ba3 | Q225: Moodys | R225: נייר ערך | S225: USD | T225: 3.63 | U225: 30/03/2028 | V225: 0.05375 | W225: 0.0892 | X225: החוב לא נחות | Y225: לא | Z225: 530000 | AA225: 3.681 | AB225: 91.602 | AD225: 1838.648 | AG225: שווי הוגן | AH225: 0.000848 | AI225: 0.011001747 | AJ225: 0.0016772947
A226: 158 | B226: 9935 | C226: Energean plc | D226: 549300RVMKU0CYUZBB05 | E226: LEI | F226: ENOIGA 5 7/8 30/03/31 | G226: IL0011736811 | H226: ISIN | I226: צמוד למט"ח | J226: חו"ל | K226: גלובלי | L226: סחיר | M226: אחר | N226: חיפושי נפט וגז | O226: לא | P226: Ba3 | Q226: Moodys | R226: נייר ערך | S226: USD | T226: 5.72 | U226: 30/03/2031 | V226: 0.05875 | W226: 0.0907 | X226: החוב לא נחות | Y226: לא | Z226: 670000 | AA226: 3.681 | AB226: 87.729 | AD226: 2234.873 | AG226: שווי הוגן | AH226: 0.001072 | AI226: 0.013372601 | AJ226: 0.0020387483
A227: 158 | B227: 9935 | C227: JPMORGAN CHASE | D227: 8I5DZWZKVSZI1NUHU748 | E227: LEI | F227: JPM 4.912 07/25/33 | G227: US46647PDH64 | H227: ISIN | I227: צמוד למט"ח | J227: חו"ל | K227: ארה"ב | L227: סחיר | M227: אחר | N227: Banks | O227: לא | P227: A- | Q227: Moodys | R227: נייר ערך | S227: USD | T227: 6.63 | U227: 25/07/2033 | V227: 0.04912 | W227: 0.05599 | X227: החוב לא נחות | Y227: לא | Z227: 131000 | AA227: 3.681 | AB227: 97.836 | AD227: 476.053 | AG227: שווי הוגן | AH227: 3.7e-05 | AI227: 0.0028485114 | AJ227: 0.00043427584
A228: 158 | B228: 9935 | C228: בנק לאומי לישראל בע"מ | D228: 520018078 | E228: ח.פ | F228: LUMIIT 3.275 01/29/31 | G228: IL0060404899 | H228: ISIN | I228: צמוד למט"ח | J228: ישראל | K228: ישראל | L228: סחיר | M228: אחר | N228: Banks | O228: לא | P228: BBB | Q228: S&P | R228: נייר ערך | S228: USD | T228: 1.69 | U228: 29/01/2031 | V228: 0.03275 | W228: 0.06581 | X228: החוב לא נחות | Y228: לא | Z228: 104000 | AA228: 3.681 | AB228: 92.834 | AD228: 357.515 | AG228: שווי הוגן | AH228: 0.000139 | AI228: 0.002139227 | AJ228: 0.00032614038
A229: 158 | B229: 9935 | C229: לוויתן בונד בע"מ | D229: 516223864 | E229: ח.פ | F229: LVIATH 6.5 30/06/27 | G229: IL0011677825 | H229: ISIN | I229: צמוד למט"ח | J229: ישראל | K229: ישראל | L229: סחיר | M229: אחר | N229: Energy Equipment & Services | O229: לא | P229: BB- | Q229: S&P | R229: נייר ערך | S229: USD | T229: 2.79 | U229: 30/06/2027 | V229: 0.065 | W229: 0.07799 | X229: החוב לא נחות | Y229: לא | Z229: 70000 | AA229: 3.681 | AB229: 96.843 | AD229: 253.722 | AG229: שווי הוגן | AH229: 0.000117 | AI229: 0.0015181755 | AJ229: 0.00023145666
A230: 158 | B230: 9935 | C230: בנק מזרחי טפחות בע"מ | D230: 520000522 | E230: ח.פ | F230: MZRHIT 3.077 04/07/31 | G230: IL0069508369 | H230: ISIN | I230: צמוד למט"ח | J230: ישראל | K230: ישראל | L230: סחיר | M230: אחר | N230: Banks | O230: לא | P230: BBB- | Q230: S&P | R230: נייר ערך | S230: USD | T230: 1.87 | U230: 07/04/2031 | V230: 0.03077 | W230: 0.07118 | X230: החוב לא נחות | Y230: לא | Z230: 104000 | AA230: 3.681 | AB230: 91.664 | AD230: 356.572 | AG230: שווי הוגן | AH230: 0.000173 | AI230: 0.0021335894 | AJ230: 0.00032528088
A231: 158 | B231: 9935 | C231: UNITEDHEALTH GROUP | D231: 549300GHBMY8T5GXDE41 | E231: LEI | F231: UHN 5.3 02/15/30 | G231: US91324PEQ19 | H231: ISIN | I231: צמוד למט"ח | J231: חו"ל | K231: ארה"ב | L231: סחיר | M231: אחר | N231: Health Care Equipment & Supplies | O231: לא | P231: A2 | Q231: Moodys | R231: נייר ערך | S231: USD | T231: 4.83 | U231: 15/02/2030 | V231: 0.053 | W231: 0.04986 | X231: החוב לא נחות | Y231: לא | Z231: 116000 | AA231: 3.681 | AB231: 102.421 | AD231: 440.162 | AG231: שווי הוגן | AH231: 9.3e-05 | AI231: 0.0026337586 | AJ231: 0.00040153524
A232: 158 | B232: 9935 | C232: נאוויטס פטרוליום, שותפות מוגבלת | D232: 550263107 | E232: ח.פ | F232: נאוויטס פטרו אגח ה חסום עד 11/07/24 | G232: IL0011979122 | H232: ISIN | I232: לא צמוד למדד המחירים לצרכן | J232: חו"ל | K232: ארה"ב | L232: חסום | M232: TASE | N232: חיפושי נפט וגז | O232: לא | P232: A- | Q232: S&P מעלות | R232: נייר ערך | S232: ILS | T232: 0 | U232: 31/12/2028 | V232: 0.065 | W232: 0 | X232: החוב לא נחות | Y232: לא | Z232: 867000 | AA232: 1 | AB232: 101.78 | AD232: 882.433 | AG232: שווי הוגן | AH232: 0 | AI232: 0.0052801343 | AJ232: 0.00080499406
A233: 158 | B233: 9935 | C233: נמקו ריאליטי לטד | D233: 1905761 | E233: מספר תאגיד או שותפות בחו"ל | F233: נמקו אגח ב' 2020/2032 4.5% | G233: IL0011602583 | H233: ISIN | I233: לא צמוד למדד המחירים לצרכן | J233: חו"ל | K233: ארה"ב | L233: סחיר | M233: TASE | N233: נדל"ן מניב בחו"ל | O233: לא | P233: AA- | Q233: S&P מעלות | R233: נייר ערך | S233: ILS | T233: 3.626 | U233: 15/10/2032 | V233: 0.045 | W233: 0.06389 | X233: החוב לא נחות | Y233: לא | Z233: -0.14 | AA233: 1 | AB233: 95.73 | AD233: 0 | AG233: שווי הוגן | AH233: 0 | AI233: -8.0193486e-10 | AJ233: -1.2226068e-10
A234: 158 | B234: 9935 | C234: סאפיינס אינטרנשיונל קורפוריישן N.V | D234: 53368 | E234: מספר תאגיד או שותפות בחו"ל | F234: סאפיינס אגח ב | G234: IL0011419368 | H234: ISIN | I234: צמוד למט"ח | J234: ישראל | K234: ישראל | L234: סחיר | M234: TASE | N234: תוכנה ואינטרנט | O234: לא | P234: AA- | Q234: S&P מעלות | R234: נייר ערך | S234: ILS | T234: 1.23 | U234: 01/01/2026 | V234: 0.0337 | W234: 0.06408 | X234: החוב לא נחות | Y234: לא | Z234: 0.21 | AA234: 1 | AB234: 101.54 | AD234: 0 | AG234: שווי הוגן | AH234: 0 | AI234: 1.2759083e-09 | AJ234: 1.945213e-10
A235: 158 | B235: 9935 | C235: פסיפיק אוק אסאואר(בי וי איי) הולדינגס | D235: 1900288 | E235: ח.פ | F235: פסיפיק אגח ב | G235: IL0011630626 | H235: ISIN | I235: לא צמוד למדד המחירים לצרכן | J235: חו"ל | K235: ארה"ב | L235: סחיר | M235: TASE | N235: נדל"ן מניב בחו"ל | O235: לא | P235: AA- | Q235: S&P מעלות | R235: נייר ערך | S235: ILS | T235: 1.295 | U235: 01/02/2026 | V235: 0.0393 | W235: 0.07365 | X235: החוב לא נחות | Y235: לא | Z235: 1330733.2 | AA235: 1 | AB235: 96.54 | AD235: 1284.69 | AG235: שווי הוגן | AH235: 0.001143 | AI235: 0.007687078 | AJ235: 0.0011719498
A236: 158 | B236: 9936 | C236: לוויתן בונד בע"מ | D236: 516223864 | E236: ח.פ | F236: LVIA 6.125% 6/25 | G236: IL0011677742 | H236: ISIN | I236: צמוד למט"ח | J236: ישראל | K236: ישראל | L236: סחיר | M236: אחר | N236: Energy Equipment & Services | O236: לא | P236: Ba3 | Q236: Moodys | R236: נייר ערך | S236: USD | T236: 1.14 | U236: 30/06/2025 | V236: 0.06125 | W236: 0.07568 | X236: החוב לא נחות | Y236: לא | Z236: 6000 | AA236: 3.681 | AB236: 98.581 | AD236: 22.111 | AG236: שווי הוגן | AH236: 1e-05 | AI236: 0.0074578186 | AJ236: 0.0014524925
... A306: 158 | B306: 9936 | C306: מליסרון בע"מ | D306: 520037789 | E306: ח.פ | F306: מליסרון אגח כא | G306: IL0011946386 | H306: ISIN | I306: צמוד למדד המחירים לצרכן | J306: ישראל | K306: ישראל | L306: סחיר | M306: TASE | N306: נדל"ן מניב בישראל | O306: לא | P306: AA | Q306: S&P מעלות | R306: נייר ערך | S306: ILS | T306: 6.45 | U306: 01/01/2037 | V306: 0.0361 | W306: 0.02996 | X306: החוב לא נחות | Y306: לא | Z306: 35000 | AA306: 1 | AB306: 107.22 | AD306: 37.527 | AG306: שווי הוגן | AH306: 7.6e-05 | AI306: 0.0126576 | AJ306: 0.0024652073
A307: 158 | B307: 9936 | C307: מליסרון בע"מ | D307: 520037789 | E307: ח.פ | F307: מליסרון אגח י' | G307: IL0032301900 | H307: ISIN | I307: צמוד למדד המחירים לצרכן | J307: ישראל | K307: ישראל | L307: סחיר | M307: TASE | N307: נדל"ן מניב בישראל | O307: לא | P307: AA | Q307: S&P מעלות | R307: נייר ערך | S307: ILS | T307: 1.243 | U307: 10/07/2025 | V307: 0.0176 | W307: 0.01394 | X307: החוב לא נחות | Y307: לא | Z307: 8367.71 | AA307: 1 | AB307: 114.03 | AC307: 6.683 | AD307: 16.224 | AG307: שווי הוגן | AH307: 6e-06 | AI307: 0.0054723317 | AJ307: 0.001065797
A308: 158 | B308: 9936 | C308: מליסרון בע"מ | D308: 520037789 | E308: ח.פ | F308: מליסרון אגח כ | G308: IL0032304227 | H308: ISIN | I308: צמוד למדד המחירים לצרכן | J308: ישראל | K308: ישראל | L308: סחיר | M308: TASE | N308: נדל"ן מניב בישראל | O308: לא | P308: AA | Q308: S&P מעלות | R308: נייר ערך | S308: ILS | T308: 5.657 | U308: 01/07/2030 | V308: 0.0025 | W308: 0.02648 | X308: החוב לא נחות | Y308: לא | Z308: 18900 | AA308: 1 | AB308: 95.66 | AD308: 18.08 | AG308: שווי הוגן | AH308: 1.5e-05 | AI308: 0.0060981725 | AJ308: 0.0011876864
A309: 158 | B309: 9936 | C309: ע.י נופר אנרגי' בע"מ | D309: 514599943 | E309: ח.פ | F309: נופר אנרג אגח א | G309: IL0011793408 | H309: ISIN | I309: צמוד למדד המחירים לצרכן | J309: ישראל | K309: ישראל | L309: סחיר | M309: TASE | N309: אנרגיה מתחדשת | O309: לא | P309: N/R | Q309: אחר | R309: מנפיק | S309: ILS | T309: 2.765 | U309: 31/12/2027 | V309: 0.0148 | W309: 0.03608 | X309: החוב לא נחות | Y309: לא | Z309: 25200 | AA309: 1 | AB309: 103.65 | AD309: 26.12 | AG309: שווי הוגן | AH309: 2.9e-05 | AI309: 0.0088100297 | AJ309: 0.0017158505
A310: 158 | B310: 9936 | C310: חברה לנכסים ולבנין בע"מ | D310: 520025438 | E310: ח.פ | F310: נכסים ובנין אגח י | G310: IL0011936304 | H310: ISIN | I310: צמוד למדד המחירים לצרכן | J310: ישראל | K310: ישראל | L310: סחיר | M310: TASE | N310: נדל"ן מניב בישראל | O310: לא | P310: A | Q310: S&P מעלות | R310: נייר ערך | S310: ILS | T310: 4.414 | U310: 01/07/2029 | V310: 0.0362 | W310: 0.03562 | X310: החוב לא נחות | Y310: לא | Z310: 11640 | AA310: 1 | AB310: 103.98 | AD310: 12.103 | AG310: שווי הוגן | AH310: 7e-06 | AI310: 0.0040823508 | AJ310: 0.00079508286
...

Sheet מניות מבכ ויהש
A1: מספר קופה/קרן/ח.פ. עבור חברת ביטוח | B1: מספר מסלול | C1: שם מנפיק | D1: מספר מנפיק | E1: סוג מספר מזהה מנפיק | F1: שם נייר ערך | G1: מספר נייר ערך | H1: סוג מספר נייר ערך | I1: מאפיין עיקרי | J1: ישראל/חו"ל | K1: מדינה לפי חשיפה כלכלית | L1: סטאטוס סחירות | M1: זירת מסחר | N1: ענף מסחר | O1: בעל עניין/צד קשור | P1: מטבע פעילות | Q1: ערך נקוב (יחידות) | R1: שער חליפין | S1: שער נייר הערך | T1: סכום לקבל (במטבע הפעילות) | U1: שווי הוגן (באלפי ש"ח) | V1: שיעור מערך נקוב מונפק | W1: שיעור מנכסי אפיק ההשקעה | X1: שיעור מסך נכסי ההשקעה
A2: 158 | B2: 1522 | C2: נובה מכשירי מדידה בע"מ | D2: 511812463 | E2: ח.פ | F2: Nova measuring inst | G2: IL0010845571 | H2: ISIN | I2: מניות | J2: ישראל | K2: אסיה | L2: סחיר | M2: NASDAQ | N2: מוליכים למחצה | O2: לא | P2: USD | Q2: 60 | R2: 3.681 | S2: 177.38 | U2: 39.176 | V2: 2e-06 | W2: 0.017755242 | X2: 0.0038835726
A3: 158 | B3: 1522 | C3: איידנטי הלת'קייר בע"מ | D3: 515679405 | E3: ח.פ | F3: איידנטי הלת'קייר | G3: IL0011774507 | H3: ISIN | I3: מניות | J3: ישראל | K3: ישראל | L3: סחיר | M3: TASE | N3: תוכנה ואינטרנט | O3: לא | P3: ILS | Q3: 5100 | R3: 1 | S3: 312.3 | U3: 15.927 | V3: 0.000405 | W3: 0.0072185014 | X3: 0.00157889
A4: 158 | B4: 1522 | C4: אלביט מערכות בע"מ | D4: 520043027 | E4: ח.פ | F4: אלביט מערכות | G4: IL0010811243 | H4: ISIN | I4: מניות | J4: ישראל | K4: ישראל | L4: סחיר | M4: TASE | N4: ביטחוניות | O4: לא | P4: ILS | Q4: 22 | R4: 1 | S4: 77500 | U4: 17.05 | V4: 0 | W4: 0.0077273266 | X4: 0.0016901844
A5: 158 | B5: 1522 | C5: אלוני-חץ נכסים והשקעות בע"מ | D5: 520038506 | E5: ח.פ | F5: אלוני חץ | G5: IL0003900136 | H5: ISIN | I5: מניות | J5: ישראל | K5: ישראל | L5: סחיר | M5: TASE | N5: נדל"ן מניב בישראל | O5: לא | P5: ILS | Q5: 1400 | R5: 1 | S5: 2653 | T5: 0.252 | U5: 37.394 | V5: 8e-06 | W5: 0.016947546 | X5: 0.0037069065
A6: 158 | B6: 1522 | C6: אמות השקעות בע"מ | D6: 520026683 | E6: ח.פ | F6: אמות | G6: IL0010972789 | H6: ISIN | I6: מניות | J6: ישראל | K6: ישראל | L6: סחיר | M6: TASE | N6: נדל"ן מניב בישראל | O6: לא | P6: ILS | Q6: 3039 | R6: 1 | S6: 1749 | U6: 53.152 | V6: 6e-06 | W6: 0.024089367 | X6: 0.0052690245
A7: 158 | B7: 1522 | C7: אנלייט אנרגיה מתחדשת בע"מ | D7: 520041146 | E7: ח.פ | F7: אנלייט אנרגיה | G7: IL0007200111 | H7: ISIN | I7: מניות | J7: ישראל | K7: ישראל | L7: סחיר | M7: TASE | N7: אנרגיה מתחדשת | O7: לא | P7: ILS | Q7: 918.8 | R7: 1 | S7: 6299 | U7: 57.875 | V7: 8e-06 | W7: 0.026229951 | X7: 0.0057372306
A8: 158 | B8: 1522 | C8: אנרג'יקס אנרגיות מתחדשות בע"מ | D8: 513901371 | E8: ח.פ | F8: אנרג'יקס | G8: IL0011233553 | H8: ISIN | I8: מניות | J8: ישראל | K8: ישראל | L8: סחיר | M8: TASE | N8: אנרגיה מתחדשת | O8: לא | P8: ILS | Q8: 6766 | R8: 1 | S8: 1352 | U8: 91.476 | V8: 1.2e-05 | W8: 0.041458499 | X8: 0.0090681437
A9: 158 | B9: 1522 | C9: בזק החברה הישראלית לתקשורת בע"מ | D9: 520031931 | E9: ח.פ | F9: בזק | G9: IL0002300114 | H9: ISIN | I9: מניות | J9: ישראל | K9: ישראל | L9: סחיר | M9: TASE | N9: תקשורת ומדיה | O9: לא | P9: ILS | Q9: 16485 | R9: 1 | S9: 473 | U9: 77.974 | V9: 6e-06 | W9: 0.035339059 | X9: 0.0077296495
A10: 158 | B10: 1522 | C10: בליץ טכנולוגיות בעמ | D10: 520038779 | E10: ח.פ | F10: בליץ | G10: IL0004240102 | H10: ISIN | I10: מניות | J10: ישראל | K10: ישראל | L10: סחיר | M10: TASE | N10: אלקטרוניקה ואופטיקה | O10: לא | P10: ILS | Q10: 0.12 | R10: 1 | S10: 439.6 | U10: 0.001 | V10: 0 | W10: 2.3908031e-07 | X10: 5.2293612e-08
A11: 158 | B11: 1522 | C11: בנק דיסקונט לישראל בע"מ | D11: 520007030 | E11: ח.פ | F11: דיסקונט | G11: IL0006912120 | H11: ISIN | I11: מניות | J11: ישראל | K11: ישראל | L11: סחיר | M11: TASE | N11: בנקים | O11: לא | P11: ILS | Q11: 8539 | R11: 1 | S11: 1946 | T11: 1.269 | U11: 167.438 | V11: 7e-06 | W11: 0.075885384 | X11: 0.016598275
A12: 158 | B12: 1522 | C12: י.ח.דמרי בניה ופיתוח בע"מ | D12: 511399388 | E12: ח.פ | F12: דמרי | G12: IL0010903156 | H12: ISIN | I12: מניות | J12: ישראל | K12: ישראל | L12: סחיר | M12: TASE | N12: בנייה | O12: לא | P12: ILS | Q12: 230 | R12: 1 | S12: 28600 | U12: 65.78 | V12: 1.2e-05 | W12: 0.029812525 | X12: 0.0065208405
A13: 158 | B13: 1522 | C13: הפניקס אחזקות בע"מ | D13: 520017450 | E13: ח.פ | F13: הפניקס | G13: IL0007670123 | H13: ISIN | I13: מניות | J13: ישראל | K13: ישראל | L13: סחיר | M13: TASE | N13: ביטוח | O13: לא | P13: ILS | Q13: 1261 | R13: 1 | S13: 3810 | U13: 48.044 | V13: 5e-06 | W13: 0.021774337 | X13: 0.0047626621
A14: 158 | B14: 1522 | C14: ישראל קנדה (ט.ר) בעמ | D14: 520039298 | E14: ח.פ | F14: ישראל קנדה | G14: IL0004340191 | H14: ISIN | I14: מניות | J14: ישראל | K14: ישראל | L14: סחיר | M14: TASE | N14: בנייה | O14: לא | P14: ILS | Q14: 3300 | R14: 1 | S14: 1475 | U14: 48.675 | V14: 1.1e-05 | W14: 0.022060271 | X14: 0.0048252039
A15: 158 | B15: 1522 | C15: כלל החזקות עסקי ביטוח בע"מ | D15: 520036120 | E15: ח.פ | F15: כלל ביטוח | G15: IL0002240146 | H15: ISIN | I15: מניות | J15: ישראל | K15: ישראל | L15: סחיר | M15: TASE | N15: ביטוח | O15: לא | P15: ILS | Q15: 540 | R15: 1 | S15: 6569 | U15: 35.473 | V15: 7e-06 | W15: 0.016076737 | X15: 0.0035164361
A16: 158 | B16: 1522 | C16: בנק לאומי לישראל בע"מ | D16: 520018078 | E16: ח.פ | F16: לאומי | G16: IL0006046119 | H16: ISIN | I16: מניות | J16: ישראל | K16: ישראל | L16: סחיר | M16: TASE | N16: בנקים | O16: לא | P16: ILS | Q16: 6909 | R16: 1 | S16: 3100 | T16: 1.656 | U16: 215.835 | V16: 4e-06 | W16: 0.09781986 | X16: 0.021395964
A17: 158 | B17: 1522 | C17: בנק מזרחי טפחות בע"מ | D17: 520000522 | E17: ח.פ | F17: מזרחי טפחות | G17: IL0006954379 | H17: ISIN | I17: מניות | J17: ישראל | K17: ישראל | L17: סחיר | M17: TASE | N17: בנקים | O17: לא | P17: ILS | Q17: 737 | R17: 1 | S17: 14000 | U17: 103.18 | V17: 3e-06 | W17: 0.046762789 | X17: 0.010228342
A18: 158 | B18: 1522 | C18: מטריקס אי.טי בע"מ | D18: 520039413 | E18: ח.פ | F18: מטריקס | G18: IL0004450156 | H18: ISIN | I18: מניות | J18: ישראל | K18: ישראל | L18: סחיר | M18: TASE | N18: שירותי מידע | O18: לא | P18: ILS | Q18: 618 | R18: 1 | S18: 8160 | T18: 0.785 | U18: 51.214 | V18: 1e-05 | W18: 0.023210832 | X18: 0.0050768639
A19: 158 | B19: 1522 | C19: מיטרוניקס בע"מ | D19: 511527202 | E19: ח.פ | F19: מיטרוניקס | G19: IL0010910656 | H19: ISIN | I19: מניות | J19: ישראל | K19: ישראל | L19: סחיר | M19: TASE | N19: רובוטיקה ותלת מימד | O19: לא | P19: ILS | Q19: 890 | R19: 1 | S19: 3622 | U19: 32.236 | V19: 8e-06 | W19: 0.014609769 | X19: 0.0031955687
A20: 158 | B20: 1522 | C20: מליסרון בע"מ | D20: 520037789 | E20: ח.פ | F20: מליסרון | G20: IL0003230146 | H20: ISIN | I20: מניות | J20: ישראל | K20: ישראל | L20: סחיר | M20: TASE | N20: נדל"ן מניב בישראל | O20: לא | P20: ILS | Q20: 257 | R20: 1 | S20: 26900 | T20: 0.649 | U20: 69.782 | V20: 5e-06 | W20: 0.03162628 | X20: 0.00691756
A21: 158 | B21: 1522 | C21: נאוויטס פטרוליום, שותפות מוגבלת | D21: 550263107 | E21: ח.פ | F21: נאוויטס פט יהש | G21: IL0011419699 | H21: ISIN | I21: מניות | J21: חו"ל | K21: ארה"ב | L21: סחיר | M21: TASE | N21: חיפושי נפט וגז | O21: לא | P21: ILS | Q21: 481 | R21: 1 | S21: 4170 | U21: 20.058 | V21: 5e-06 | W21: 0.0090904633 | X21: 0.0019883409
A22: 158 | B22: 1522 | C22: נובה מכשירי מדידה בע"מ | D22: 511812463 | E22: ח.פ | F22: נובה | G22: IL0010845571 | H22: ISIN | I22: מניות | J22: ישראל | K22: ישראל | L22: סחיר | M22: TASE | N22: מוליכים למחצה | O22: לא | P22: ILS | Q22: 21 | R22: 1 | S22: 64720 | U22: 13.591 | V22: 1e-06 | W22: 0.0061597444 | X22: 0.0013473099
A23: 158 | B23: 1522 | C23: ניו-מד אנרג'י- שותפות מוגבלת | D23: 550013098 | E23: ח.פ | F23: ניו-מד אנרג'י יהש | G23: IL0004750209 | H23: ISIN | I23: מניות | J23: ישראל | K23: ישראל | L23: סחיר | M23: TASE | N23: חיפושי נפט וגז | O23: לא | P23: ILS | Q23: 2366 | R23: 1 | S23: 935.3 | T23: 0.453 | U23: 22.583 | V23: 2e-06 | W23: 0.01023475 | X23: 0.0022386287
A24: 158 | B24: 1522 | C24: נייס מערכות בע"מ | D24: 520036872 | E24: ח.פ | F24: נייס | G24: IL0002730112 | H24: ISIN | I24: מניות | J24: ישראל | K24: ישראל | L24: סחיר | M24: TASE | N24: תוכנה ואינטרנט | O24: לא | P24: ILS | Q24: 60 | R24: 1 | S24: 95150 | U24: 57.09 | V24: 1e-06 | W24: 0.025874081 | X24: 0.0056593917
A25: 158 | B25: 1522 | C25: קבוצת עזריאלי בע"מ (לשעבר קנית מימון) | D25: 510960719 | E25: ח.פ | F25: עזריאלי קבוצה | G25: IL0011194789 | H25: ISIN | I25: מניות | J25: ישראל | K25: ישראל | L25: סחיר | M25: TASE | N25: נדל"ן מניב בישראל | O25: לא | P25: ILS | Q25: 364 | R25: 1 | S25: 26610 | U25: 96.86 | V25: 3e-06 | W25: 0.043898648 | X25: 0.0096018732
A26: 158 | B26: 1522 | C26: בנק הפועלים בע"מ | D26: 520000118 | E26: ח.פ | F26: פועלים | G26: IL0006625771 | H26: ISIN | I26: מניות | J26: ישראל | K26: ישראל | L26: סחיר | M26: TASE | N26: בנקים | O26: לא | P26: ILS | Q26: 3948 | R26: 1 | S26: 3500 | T26: 1.039 | U26: 139.219 | V26: 3e-06 | W26: 0.063096314 | X26: 0.013800945
A27: 158 | B27: 1522 | C27: פוקס-ויזל בע"מ | D27: 512157603 | E27: ח.פ | F27: פוקס- ויזל | G27: IL0010870223 | H27: ISIN | I27: מניות | J27: ישראל | K27: ישראל | L27: סחיר | M27: TASE | N27: רשתות שיווק | O27: לא | P27: ILS | Q27: 160 | R27: 1 | S27: 34140 | U27: 54.624 | V27: 1.2e-05 | W27: 0.024756451 | X27: 0.0054149345
A28: 158 | B28: 1522 | C28: פורמולה מערכות (1985)בע"מ | D28: 520036690 | E28: ח.פ | F28: פורמולה מערכות | G28: IL0002560162 | H28: ISIN | I28: מניות | J28: ישראל | K28: ישראל | L28: סחיר | M28: TASE | N28: שירותי מידע | O28: לא | P28: ILS | Q28: 99 | R28: 1 | S28: 30030 | U28: 29.73 | V28: 6e-06 | W28: 0.013473965 | X28: 0.0029471364
A29: 158 | B29: 1522 | C29: קמטק בע"מ | D29: 511235434 | E29: ח.פ | F29: קמטק | G29: IL0010952641 | H29: ISIN | I29: מניות | J29: ישראל | K29: ישראל | L29: סחיר | M29: TASE | N29: מוליכים למחצה | O29: לא | P29: ILS | Q29: 270 | R29: 1 | S29: 30800 | U29: 83.16 | V29: 6e-06 | W29: 0.037689412 | X29: 0.0082437382
A30: 158 | B30: 1522 | C30: ריט 1 בע"מ | D30: 513821488 | E30: ח.פ | F30: ריט 1 | G30: IL0010989205 | H30: ISIN | I30: מניות | J30: ישראל | K30: ישראל | L30: סחיר | M30: TASE | N30: נדל"ן מניב בישראל | O30: לא | P30: ILS | Q30: 1543 | R30: 1 | S30: 1566 | U30: 24.163 | V30: 8e-06 | W30: 0.010951222 | X30: 0.0023953412
A31: 158 | B31: 1522 | C31: תדיראן גרופ בע"מ | D31: 520036732 | E31: ח.פ | F31: תדיראן גרופ | G31: IL0002580129 | H31: ISIN | I31: מניות | J31: ישראל | K31: ישראל | L31: סחיר | M31: TASE | N31: מסחר | O31: לא | P31: ILS | Q31: 52 | R31: 1 | S31: 30040 | T31: 0.137 | U31: 15.758 | V31: 6e-06 | W31: 0.0071418989 | X31: 0.0015621349
A32: 158 | B32: 1522 | C32: amazon.com | D32: 549300LQHH5G4WPME241 | E32: LEI | F32: AMAZON.COM INC | G32: US0231351067 | H32: ISIN | I32: מניות | J32: חו"ל | K32: ארה"ב | L32: סחיר | M32: NASDAQ | N32: Textiles, Apparel & Luxury Goods | O32: לא | P32: USD | Q32: 65 | R32: 3.681 | S32: 180.38 | U32: 43.159 | V32: 0 | W32: 0.019560162 | X32: 0.0042783594
A33: 158 | B33: 1522 | C33: ASML HOLDING NV-NY | D33: 724500Y6DUVHQD6OXN27 | E33: LEI | F33: Asml Holding NV | G33: USN070592100 | H33: ISIN | I33: מניות | J33: חו"ל | K33: ארה"ב | L33: סחיר | M33: NASDAQ | N33: Semiconductors & Semiconductor Equipment | O33: לא | P33: USD | Q33: 25 | R33: 3.681 | S33: 97047 | U33: 89.308 | V33: 0 | W33: 0.040475556 | X33: 0.0088531465
A34: 158 | B34: 1522 | C34: Broadcom Inc | D34: 549300GR48KUO03W2V88 | E34: LEI | F34: BROADCOM LTD | G34: US11135F1012 | H34: ISIN | I34: מניות | J34: חו"ל | K34: ארה"ב | L34: סחיר | M34: NASDAQ | N34: Semiconductors & Semiconductor Equipment | O34: לא | P34: USD | Q34: 6 | R34: 3.681 | S34: 132541 | U34: 29.273 | V34: 0 | W34: 0.013266984 | X34: 0.0029018638
A35: 158 | B35: 1522 | C35: COSTCO WHOLESAL | D35: 29DX7H14B9S6O3FD6V18 | E35: LEI | F35: COSTCO WHOLESAL | G35: US22160K1051 | H35: ISIN | I35: מניות | J35: חו"ל | K35: גלובלי | L35: סחיר | M35: NASDAQ | N35: Food & Staples Retailing Consumer Staples Distribution & Retail | O35: לא | P35: USD | Q35: 15 | R35: 3.681 | S35: 73263 | U35: 40.452 | V35: 0 | W35: 0.018333554 | X35: 0.0040100657
A36: 158 | B36: 1522 | C36: ALPHABET INC | D36: 7ZW8QJWVPR4P1J1KQY45 | E36: LEI | F36: Google Us Class c | G36: US02079K1079 | H36: ISIN | I36: מניות | J36: חו"ל | K36: ארה"ב | L36: סחיר | M36: NASDAQ | N36: Diversified Telecommunication Services | O36: לא | P36: USD | Q36: 162 | R36: 3.681 | S36: 15226 | U36: 90.796 | V36: 0 | W36: 0.041150161 | X36: 0.0090007017
A37: 158 | B37: 1522 | C37: MASTERCARD INC | D37: AR5L2ODV9HN37376R084 | E37: LEI | F37: MASTERCARD UNC | G37: US57636Q1040 | H37: ISIN | I37: מניות | J37: חו"ל | K37: ארה"ב | L37: סחיר | M37: NYSE | N37: Diversified Financial Services Financial Services | O37: לא | P37: USD | Q37: 50 | R37: 3.681 | S37: 481.57 | U37: 88.633 | V37: 0 | W37: 0.040169843 | X37: 0.0087862783
A38: 158 | B38: 1522 | C38: MICROSOFT CORP | D38: INR2EJN1ERAN0W5ZP974 | E38: LEI | F38: Microsoft crop | G38: US5949181045 | H38: ISIN | I38: מניות | J38: חו"ל | K38: ארה"ב | L38: סחיר | M38: NASDAQ | N38: Software | O38: לא | P38: USD | Q38: 8 | R38: 3.681 | S38: 420.72 | U38: 12.389 | V38: 0 | W38: 0.0056150528 | X38: 0.0012281705
A39: 158 | B39: 1522 | C39: NICE LTD | D39: 254900YTY4EF5Z4W0A51 | E39: LEI | F39: NICE SYS ADR | G39: US6536561086 | H39: ISIN | I39: מניות | J39: חו"ל | K39: ישראל | L39: סחיר | M39: NASDAQ | N39: Wireless Telecommunication Services | O39: לא | P39: USD | Q39: 22 | R39: 3.681 | S39: 26062 | U39: 21.106 | V39: 0 | W39: 0.0095653557 | X39: 0.0020922132
A40: 158 | B40: 1522 | C40: אורמת טכנולגיות אינק | D40: 5493000TSHHWY24VHM09 | E40: LEI | F40: Ormat Technologies | G40: US6866881021 | H40: ISIN | I40: מניות | J40: חו"ל | K40: ארה"ב | L40: סחיר | M40: NYSE | N40: Water Utilities | O40: לא | P40: USD | Q40: 28 | R40: 3.681 | S40: 66.19 | U40: 6.822 | V40: 1e-06 | W40: 0.0030918692 | X40: 0.00067627906
A41: 158 | B41: 9935 | C41: נובה מכשירי מדידה בע"מ | D41: 511812463 | E41: ח.פ | F41: Nova measuring inst | G41: IL0010845571 | H41: ISIN | I41: מניות | J41: ישראל | K41: אסיה | L41: סחיר | M41: NASDAQ | N41: מוליכים למחצה | O41: לא | P41: USD | Q41: 2955 | R41: 3.681 | S41: 177.38 | U41: 1929.425 | V41: 0.000105 | W41: 0.011931137 | X41: 0.0017601053
A42: 158 | B42: 9935 | C42: אדגר השקעות ופיתוח בע"מ | D42: 520035171 | E42: ח.פ | F42: אדגר | G42: IL0018200837 | H42: ISIN | I42: מניות | J42: ישראל | K42: ישראל | L42: סחיר | M42: TASE | N42: נדל"ן מניב בחו"ל | O42: לא | P42: ILS | Q42: 108600 | R42: 1 | S42: 492.9 | U42: 535.289 | V42: 0.000659 | W42: 0.0033101107 | X42: 0.00048831419
A43: 158 | B43: 9935 | C43: אלביט מערכות בע"מ | D43: 520043027 | E43: ח.פ | F43: אלביט מערכות | G43: IL0010811243 | H43: ISIN | I43: מניות | J43: ישראל | K43: ישראל | L43: סחיר | M43: TASE | N43: ביטחוניות | O43: לא | P43: ILS | Q43: 2328 | R43: 1 | S43: 77500 | U43: 1804.2 | V43: 5.2e-05 | W43: 0.011156772 | X43: 0.0016458694
A44: 158 | B44: 9935 | C44: אלוני-חץ נכסים והשקעות בע"מ | D44: 520038506 | E44: ח.פ | F44: אלוני חץ | G44: IL0003900136 | H44: ISIN | I44: מניות | J44: ישראל | K44: ישראל | L44: סחיר | M44: TASE | N44: נדל"ן מניב בישראל | O44: לא | P44: ILS | Q44: 45276 | R44: 1 | S44: 2653 | T44: 8.15 | U44: 1209.322 | V44: 0.000252 | W44: 0.0074781782 | X44: 0.0011031959
A45: 158 | B45: 9935 | C45: אמות השקעות בע"מ | D45: 520026683 | E45: ח.פ | F45: אמות | G45: IL0010972789 | H45: ISIN | I45: מניות | J45: ישראל | K45: ישראל | L45: סחיר | M45: TASE | N45: נדל"ן מניב בישראל | O45: לא | P45: ILS | Q45: 109000 | R45: 1 | S45: 1749 | U45: 1906.41 | V45: 0.000232 | W45: 0.011788816 | X45: 0.0017391098
A46: 158 | B46: 9935 | C46: אנלייט אנרגיה מתחדשת בע"מ | D46: 520041146 | E46: ח.פ | F46: אנלייט אנרגיה | G46: IL0007200111 | H46: ISIN | I46: מניות | J46: ישראל | K46: ישראל | L46: סחיר | M46: TASE | N46: אנרגיה מתחדשת | O46: לא | P46: ILS | Q46: 24655.5 | R46: 1 | S46: 6299 | U46: 1553.05 | V46: 0.000209 | W46: 0.0096037157 | X46: 0.0014167595
A47: 158 | B47: 9935 | C47: אנרג'יקס אנרגיות מתחדשות בע"מ | D47: 513901371 | E47: ח.פ | F47: אנרג'יקס | G47: IL0011233553 | H47: ISIN | I47: מניות | J47: ישראל | K47: ישראל | L47: סחיר | M47: TASE | N47: אנרגיה מתחדשת | O47: לא | P47: ILS | Q47: 145280 | R47: 1 | S47: 1352 | U47: 1964.186 | V47: 0.000265 | W47: 0.012146087 | X47: 0.0017918152
A48: 158 | B48: 9935 | C48: בזק החברה הישראלית לתקשורת בע"מ | D48: 520031931 | E48: ח.פ | F48: בזק | G48: IL0002300114 | H48: ISIN | I48: מניות | J48: ישראל | K48: ישראל | L48: סחיר | M48: TASE | N48: תקשורת ומדיה | O48: לא | P48: ILS | Q48: 563000 | R48: 1 | S48: 473 | U48: 2662.99 | V48: 0.000203 | W48: 0.016467338 | X48: 0.0024292949
A49: 158 | B49: 9935 | C49: בנק דיסקונט לישראל בע"מ | D49: 520007030 | E49: ח.פ | F49: דיסקונט | G49: IL0006912120 | H49: ISIN | I49: מניות | J49: ישראל | K49: ישראל | L49: סחיר | M49: TASE | N49: בנקים | O49: לא | P49: ILS | Q49: 292256.48 | R49: 1 | S49: 1946 | T49: 43.425 | U49: 5730.736 | V49: 0.000236 | W49: 0.035437596 | X49: 0.0052278255
A50: 158 | B50: 9935 | C50: קבוצת דלק בע"מ | D50: 520044322 | E50: ח.פ | F50: דלק קבוצה | G50: IL0010841281 | H50: ISIN | I50: מניות | J50: ישראל | K50: ישראל | L50: סחיר | M50: TASE | N50: חיפושי נפט וגז | O50: לא | P50: ILS | Q50: 1 | R50: 1 | S50: 48400 | U50: 0.484 | V50: 0 | W50: 2.9929484e-06 | X50: 4.4152578e-07
A51: 158 | B51: 9935 | C51: י.ח.דמרי בניה ופיתוח בע"מ | D51: 511399388 | E51: ח.פ | F51: דמרי | G51: IL0010903156 | H51: ISIN | I51: מניות | J51: ישראל | K51: ישראל | L51: סחיר | M51: TASE | N51: בנייה | O51: לא | P51: ILS | Q51: 12050 | R51: 1 | S51: 28600 | U51: 3446.3 | V51: 0.000644 | W51: 0.021311153 | X51: 0.0031438643
A52: 158 | B52: 9935 | C52: הפניקס אחזקות בע"מ | D52: 520017450 | E52: ח.פ | F52: הפניקס | G52: IL0007670123 | H52: ISIN | I52: מניות | J52: ישראל | K52: ישראל | L52: סחיר | M52: TASE | N52: ביטוח | O52: לא | P52: ILS | Q52: 55515 | R52: 1 | S52: 3810 | U52: 2115.122 | V52: 0.000214 | W52: 0.013079441 | X52: 0.0019295055
A53: 158 | B53: 9935 | C53: טרמינל איקס אונליין בע"מ | D53: 515722536 | E53: ח.פ | F53: טרמינל איקס אונליין בעמ | G53: IL0011787145 | H53: ISIN | I53: מניות | J53: ישראל | K53: ישראל | L53: סחיר | M53: TASE | N53: רשתות שיווק | O53: לא | P53: ILS | Q53: 82750 | R53: 1 | S53: 283.8 | U53: 234.845 | V53: 0.000663 | W53: 0.0014522262 | X53: 0.00021423533
A54: 158 | B54: 9935 | C54: ישראל קנדה (ט.ר) בעמ | D54: 520039298 | E54: ח.פ | F54: ישראל קנדה | G54: IL0004340191 | H54: ISIN | I54: מניות | J54: ישראל | K54: ישראל | L54: סחיר | M54: TASE | N54: בנייה | O54: לא | P54: ILS | Q54: 140000 | R54: 1 | S54: 1475 | U54: 2065 | V54: 0.000463 | W54: 0.012769501 | X54: 0.0018837825
A55: 158 | B55: 9935 | C55: כלל החזקות עסקי ביטוח בע"מ | D55: 520036120 | E55: ח.פ | F55: כלל ביטוח | G55: IL0002240146 | H55: ISIN | I55: מניות | J55: ישראל | K55: ישראל | L55: סחיר | M55: TASE | N55: ביטוח | O55: לא | P55: ILS | Q55: 25000 | R55: 1 | S55: 6569 | U55: 1642.25 | V55: 0.000316 | W55: 0.010155309 | X55: 0.0014981316
A56: 158 | B56: 9935 | C56: בנק לאומי לישראל בע"מ | D56: 520018078 | E56: ח.פ | F56: לאומי | G56: IL0006046119 | H56: ISIN | I56: מניות | J56: ישראל | K56: ישראל | L56: סחיר | M56: TASE | N56: בנקים | O56: לא | P56: ILS | Q56: 187821 | R56: 1 | S56: 3100 | T56: 45.022 | U56: 5867.473 | V56: 0.000116 | W56: 0.03628315 | X56: 0.0053525633
A57: 158 | B57: 9935 | C57: מגדל אחזקות ביטוח ופיננסים בע"מ | D57: 520029984 | E57: ח.פ | F57: מגדל ביטוח | G57: IL0010811656 | H57: ISIN | I57: מניות | J57: ישראל | K57: ישראל | L57: סחיר | M57: TASE | N57: ביטוח | O57: לא | P57: ILS | Q57: 46125 | R57: 1 | S57: 508.1 | U57: 234.361 | V57: 4.4e-05 | W57: 0.0014492371 | X57: 0.00021379438
A58: 158 | B58: 9935 | C58: י.ד. מור השקעות בע"מ | D58: 513834606 | E58: ח.פ | F58: מור השקעות | G58: IL0011414641 | H58: ISIN | I58: מניות | J58: ישראל | K58: ישראל | L58: סחיר | M58: TASE | N58: שירותים פיננסיים | O58: כן | P58: ILS | Q58: 129600 | R58: 1 | S58: 848.3 | U58: 1099.397 | V58: 0.001826 | W58: 0.0067984255 | X58: 0.0010029174
A59: 158 | B59: 9935 | C59: בנק מזרחי טפחות בע"מ | D59: 520000522 | E59: ח.פ | F59: מזרחי טפחות | G59: IL0006954379 | H59: ISIN | I59: מניות | J59: ישראל | K59: ישראל | L59: סחיר | M59: TASE | N59: בנקים | O59: לא | P59: ILS | Q59: 20750 | R59: 1 | S59: 14000 | U59: 2905 | V59: 8e-05 | W59: 0.017963874 | X59: 0.0026500669
A60: 158 | B60: 9935 | C60: מטריקס אי.טי בע"מ | D60: 520039413 | E60: ח.פ | F60: מטריקס | G60: IL0004450156 | H60: ISIN | I60: מניות | J60: ישראל | K60: ישראל | L60: סחיר | M60: TASE | N60: שירותי מידע | O60: לא | P60: ILS | Q60: 25448 | R60: 1 | S60: 8160 | T60: 32.319 | U60: 2108.876 | V60: 0.000401 | W60: 0.013040819 | X60: 0.0019238079
A61: 158 | B61: 9935 | C61: מיטרוניקס בע"מ | D61: 511527202 | E61: ח.פ | F61: מיטרוניקס | G61: IL0010910656 | H61: ISIN | I61: מניות | J61: ישראל | K61: ישראל | L61: סחיר | M61: TASE | N61: רובוטיקה ותלת מימד | O61: לא | P61: ILS | Q61: 25999 | R61: 1 | S61: 3622 | U61: 941.684 | V61: 0.000237 | W61: 0.0058231632 | X61: 0.00085904476
A62: 158 | B62: 9935 | C62: מליסרון בע"מ | D62: 520037789 | E62: ח.פ | F62: מליסרון | G62: IL0003230146 | H62: ISIN | I62: מניות | J62: ישראל | K62: ישראל | L62: סחיר | M62: TASE | N62: נדל"ן מניב בישראל | O62: לא | P62: ILS | Q62: 5631 | R62: 1 | S62: 26900 | T62: 14.219 | U62: 1528.958 | V62: 0.000119 | W62: 0.0094547385 | X62: 0.0013947821
A63: 158 | B63: 9935 | C63: מניבים קרן הריט החדשה בע"מ | D63: 515327120 | E63: ח.פ | F63: מניבים ריט | G63: IL0011405730 | H63: ISIN | I63: מניות | J63: ישראל | K63: ישראל | L63: סחיר | M63: TASE | N63: נדל"ן מניב בישראל | O63: לא | P63: ILS | Q63: 543909 | R63: 1 | S63: 176.3 | U63: 958.912 | V63: 0.000788 | W63: 0.005929696 | X63: 0.0008747607
A64: 158 | B64: 9935 | C64: ניו-מד אנרג'י- שותפות מוגבלת | D64: 550013098 | E64: ח.פ | F64: ניו-מד אנרג'י יהש | G64: IL0004750209 | H64: ISIN | I64: מניות | J64: ישראל | K64: ישראל | L64: סחיר | M64: TASE | N64: חיפושי נפט וגז | O64: לא | P64: ILS | Q64: 87000 | R64: 1 | S64: 935.3 | T64: 16.669 | U64: 830.38 | V64: 7.4e-05 | W64: 0.0051348854 | X64: 0.00075750864
A65: 158 | B65: 9935 | C65: נייס מערכות בע"מ | D65: 520036872 | E65: ח.פ | F65: נייס | G65: IL0002730112 | H65: ISIN | I65: מניות | J65: ישראל | K65: ישראל | L65: סחיר | M65: TASE | N65: תוכנה ואינטרנט | O65: לא | P65: ILS | Q65: 1956.5 | R65: 1 | S65: 95150 | U65: 1861.61 | V65: 3.1e-05 | W65: 0.011511781 | X65: 0.0016982411
A66: 158 | B66: 9935 | C66: קבוצת עזריאלי בע"מ (לשעבר קנית מימון) | D66: 510960719 | E66: ח.פ | F66: עזריאלי קבוצה | G66: IL0011194789 | H66: ISIN | I66: מניות | J66: ישראל | K66: ישראל | L66: סחיר | M66: TASE | N66: נדל"ן מניב בישראל | O66: לא | P66: ILS | Q66: 9481 | R66: 1 | S66: 26610 | U66: 2522.894 | V66: 7.8e-05 | W66: 0.015601016 | X66: 0.0023014934
A67: 158 | B67: 9935 | C67: בנק הפועלים בע"מ | D67: 520000118 | E67: ח.פ | F67: פועלים | G67: IL0006625771 | H67: ISIN | I67: מניות | J67: ישראל | K67: ישראל | L67: סחיר | M67: TASE | N67: בנקים | O67: לא | P67: ILS | Q67: 191714 | R67: 1 | S67: 3500 | T67: 50.463 | U67: 6760.453 | V67: 0.000143 | W67: 0.041805139 | X67: 0.0061671783
A68: 158 | B68: 9935 | C68: פוקס-ויזל בע"מ | D68: 512157603 | E68: ח.פ | F68: פוקס- ויזל | G68: IL0010870223 | H68: ISIN | I68: מניות | J68: ישראל | K68: ישראל | L68: סחיר | M68: TASE | N68: רשתות שיווק | O68: לא | P68: ILS | Q68: 5029 | R68: 1 | S68: 34140 | U68: 1716.901 | V68: 0.000365 | W68: 0.010616932 | X68: 0.0015662312
A69: 158 | B69: 9935 | C69: פורמולה מערכות (1985)בע"מ | D69: 520036690 | E69: ח.פ | F69: פורמולה מערכות | G69: IL0002560162 | H69: ISIN | I69: מניות | J69: ישראל | K69: ישראל | L69: סחיר | M69: TASE | N69: שירותי מידע | O69: לא | P69: ILS | Q69: 6641 | R69: 1 | S69: 30030 | U69: 1994.292 | V69: 0.000433 | W69: 0.01233226 | X69: 0.0018192799
A70: 158 | B70: 9935 | C70: ריט 1 בע"מ | D70: 513821488 | E70: ח.פ | F70: ריט 1 | G70: IL0010989205 | H70: ISIN | I70: מניות | J70: ישראל | K70: ישראל | L70: סחיר | M70: TASE | N70: נדל"ן מניב בישראל | O70: לא | P70: ILS | Q70: 55958.5 | R70: 1 | S70: 1566 | U70: 876.31 | V70: 0.000288 | W70: 0.005418907 | X70: 0.00079940807
A71: 158 | B71: 9935 | C71: תדיראן גרופ בע"מ | D71: 520036732 | E71: ח.פ | F71: תדיראן גרופ | G71: IL0002580129 | H71: ISIN | I71: מניות | J71: ישראל | K71: ישראל | L71: סחיר | M71: TASE | N71: מסחר | O71: לא | P71: ILS | Q71: 2000 | R71: 1 | S71: 30040 | T71: 5.288 | U71: 606.088 | V71: 0.000233 | W71: 0.0037479115 | X71: 0.00055289945
A72: 158 | B72: 9935 | C72: אי.טי.גי. איי גרופ בע"מ | D72: 513764399 | E72: ח.פ | F72: אי. טי. ג'י. איי | G72: IL0011761140 | H72: ISIN | I72: מניות | J72: ישראל | K72: ישראל | L72: סחיר | M72: TASE | N72: שירותים | O72: לא | P72: ILS | Q72: 16883 | R72: 1 | S72: 1050 | T72: 2.668 | U72: 179.94 | V72: 0.000754 | W72: 0.0011127075 | X72: 0.00016414885
A73: 158 | B73: 9935 | C73: איי.סי.אל גרופ בע"מ (דואלי) | D73: 520027830 | E73: ח.פ | F73: איי.סי.אל | G73: IL0002810146 | H73: ISIN | I73: מניות | J73: ישראל | K73: ישראל | L73: סחיר | M73: TASE | N73: כימיה, גומי ופלסטיק | O73: לא | P73: ILS | Q73: -0.4 | R73: 1 | S73: 1951 | U73: -0.008 | V73: 0 | W73: -4.8258202e-08 | X73: -7.1191471e-09
A74: 158 | B74: 9935 | C74: אלביט מערכות בע"מ | D74: 520043027 | E74: ח.פ | F74: אלביט מערכות | G74: IL0010811243 | H74: ISIN | I74: מניות | J74: ישראל | K74: ישראל | L74: סחיר | M74: TASE | N74: ביטחוניות | O74: לא | P74: ILS | Q74: 862 | R74: 1 | S74: 77500 | U74: 668.05 | V74: 1.9e-05 | W74: 0.0041310727 | X74: 0.00060942417
A75: 158 | B75: 9935 | C75: אלוני-חץ נכסים והשקעות בע"מ | D75: 520038506 | E75: ח.פ | F75: אלוני חץ | G75: IL0003900136 | H75: ISIN | I75: מניות | J75: ישראל | K75: ישראל | L75: סחיר | M75: TASE | N75: נדל"ן מניב בישראל | O75: לא | P75: ILS | Q75: 45500.2 | R75: 1 | S75: 2653 | T75: 8.19 | U75: 1215.31 | V75: 0.000253 | W75: 0.0075152088 | X75: 0.0011086587
A76: 158 | B76: 9935 | C76: אמות השקעות בע"מ | D76: 520026683 | E76: ח.פ | F76: אמות | G76: IL0010972789 | H76: ISIN | I76: מניות | J76: ישראל | K76: ישראל | L76: סחיר | M76: TASE | N76: נדל"ן מניב בישראל | O76: לא | P76: ILS | Q76: 48927 | R76: 1 | S76: 1749 | U76: 855.733 | V76: 0.000104 | W76: 0.0052916641 | X76: 0.00078063695
A77: 158 | B77: 9935 | C77: אנלייט אנרגיה מתחדשת בע"מ | D77: 520041146 | E77: ח.פ | F77: אנלייט אנרגיה | G77: IL0007200111 | H77: ISIN | I77: מניות | J77: ישראל | K77: ישראל | L77: סחיר | M77: TASE | N77: אנרגיה מתחדשת | O77: לא | P77: ILS | Q77: 35385.2 | R77: 1 | S77: 6299 | U77: 2228.914 | V77: 0.0003 | W77: 0.013783107 | X77: 0.0020333117
A78: 158 | B78: 9935 | C78: אנרג'יקס אנרגיות מתחדשות בע"מ | D78: 513901371 | E78: ח.פ | F78: אנרג'יקס | G78: IL0011233553 | H78: ISIN | I78: מניות | J78: ישראל | K78: ישראל | L78: סחיר | M78: TASE | N78: אנרגיה מתחדשת | O78: לא | P78: ILS | Q78: 197401 | R78: 1 | S78: 1352 | U78: 2668.862 | V78: 0.00036 | W78: 0.016503647 | X78: 0.0024346512
A79: 158 | B79: 9935 | C79: בזק החברה הישראלית לתקשורת בע"מ | D79: 520031931 | E79: ח.פ | F79: בזק | G79: IL0002300114 | H79: ISIN | I79: מניות | J79: ישראל | K79: ישראל | L79: סחיר | M79: TASE | N79: תקשורת ומדיה | O79: לא | P79: ILS | Q79: 485119 | R79: 1 | S79: 473 | U79: 2294.613 | V79: 0.000175 | W79: 0.014189376 | X79: 0.0020932453
A80: 158 | B80: 9935 | C80: בליץ טכנולוגיות בעמ | D80: 520038779 | E80: ח.פ | F80: בליץ | G80: IL0004240102 | H80: ISIN | I80: מניות | J80: ישראל | K80: ישראל | L80: סחיר | M80: TASE | N80: אלקטרוניקה ואופטיקה | O80: לא | P80: ILS | Q80: 0.38 | R80: 1 | S80: 439.6 | U80: 0.002 | V80: 0 | W80: 1.0329877e-08 | X80: 1.5238843e-09
A81: 158 | B81: 9935 | C81: בנק דיסקונט לישראל בע"מ | D81: 520007030 | E81: ח.פ | F81: דיסקונט | G81: IL0006912120 | H81: ISIN | I81: מניות | J81: ישראל | K81: ישראל | L81: סחיר | M81: TASE | N81: בנקים | O81: לא | P81: ILS | Q81: 199048 | R81: 1 | S81: 1946 | T81: 29.575 | U81: 3903.049 | V81: 0.000161 | W81: 0.02413559 | X81: 0.0035605309
A82: 158 | B82: 9935 | C82: י.ח.דמרי בניה ופיתוח בע"מ | D82: 511399388 | E82: ח.פ | F82: דמרי | G82: IL0010903156 | H82: ISIN | I82: מניות | J82: ישראל | K82: ישראל | L82: סחיר | M82: TASE | N82: בנייה | O82: לא | P82: ILS | Q82: 4500 | R82: 1 | S82: 28600 | U82: 1287 | V82: 0.000241 | W82: 0.007958522 | X82: 0.0011740572
A83: 158 | B83: 9935 | C83: הפניקס אחזקות בע"מ | D83: 520017450 | E83: ח.פ | F83: הפניקס | G83: IL0007670123 | H83: ISIN | I83: מניות | J83: ישראל | K83: ישראל | L83: סחיר | M83: TASE | N83: ביטוח | O83: לא | P83: ILS | Q83: 29531 | R83: 1 | S83: 3810 | U83: 1125.131 | V83: 0.000114 | W83: 0.0069575607 | X83: 0.0010263934
A84: 158 | B84: 9935 | C84: יוטרון בע"מ | D84: 515883809 | E84: ח.פ | F84: יוטרון | G84: IL0011571143 | H84: ISIN | I84: מניות | J84: ישראל | K84: ישראל | L84: סחיר | M84: TASE | N84: רובוטיקה ותלת מימד | O84: לא | P84: ILS | Q84: 0.27 | R84: 1 | S84: 350.9 | U84: 0.001 | V84: 0 | W84: 5.8586966e-09 | X84: 8.6428672e-10
A85: 158 | B85: 9935 | C85: ישראל קנדה (ט.ר) בעמ | D85: 520039298 | E85: ח.פ | F85: ישראל קנדה | G85: IL0004340191 | H85: ISIN | I85: מניות | J85: ישראל | K85: ישראל | L85: סחיר | M85: TASE | N85: בנייה | O85: לא | P85: ILS | Q85: 42000 | R85: 1 | S85: 1475 | U85: 619.5 | V85: 0.000139 | W85: 0.0038308503 | X85: 0.00056513475
A86: 158 | B86: 9935 | C86: כלל החזקות עסקי ביטוח בע"מ | D86: 520036120 | E86: ח.פ | F86: כלל ביטוח | G86: IL0002240146 | H86: ISIN | I86: מניות | J86: ישראל | K86: ישראל | L86: סחיר | M86: TASE | N86: ביטוח | O86: לא | P86: ILS | Q86: 7100 | R86: 1 | S86: 6569 | U86: 466.399 | V86: 9e-05 | W86: 0.0028841078 | X86: 0.00042546939
A87: 158 | B87: 9935 | C87: בנק לאומי לישראל בע"מ | D87: 520018078 | E87: ח.פ | F87: לאומי | G87: IL0006046119 | H87: ISIN | I87: מניות | J87: ישראל | K87: ישראל | L87: סחיר | M87: TASE | N87: בנקים | O87: לא | P87: ILS | Q87: 200025 | R87: 1 | S87: 3100 | T87: 47.948 | U87: 6248.723 | V87: 0.000124 | W87: 0.038640711 | X87: 0.0057003555
A88: 158 | B88: 9935 | C88: מבנה נדל"ן (כ.ד) בע"מ | D88: 520024126 | E88: ח.פ | F88: מבנה | G88: IL0002260193 | H88: ISIN | I88: מניות | J88: ישראל | K88: ישראל | L88: סחיר | M88: TASE | N88: נדל"ן מניב בישראל | O88: לא | P88: ILS | Q88: 0.07 | R88: 1 | S88: 907.1 | U88: 0.001 | V88: 0 | W88: 3.9265134e-09 | X88: 5.7924716e-10
A89: 158 | B89: 9935 | C89: מגוריט ישראל בעמ | D89: 515434074 | E89: ח.פ | F89: מגוריט | G89: IL0011391955 | H89: ISIN | I89: מניות | J89: ישראל | K89: ישראל | L89: סחיר | M89: TASE | N89: נדל"ן מניב בישראל | O89: לא | P89: ILS | Q89: 0.4 | R89: 1 | S89: 451.6 | U89: 0.002 | V89: 0 | W89: 1.1170376e-08 | X89: 1.6478764e-09
A90: 158 | B90: 9935 | C90: בנק מזרחי טפחות בע"מ | D90: 520000522 | E90: ח.פ | F90: מזרחי טפחות | G90: IL0006954379 | H90: ISIN | I90: מניות | J90: ישראל | K90: ישראל | L90: סחיר | M90: TASE | N90: בנקים | O90: לא | P90: ILS | Q90: 24737 | R90: 1 | S90: 14000 | U90: 3463.18 | V90: 9.6e-05 | W90: 0.021415535 | X90: 0.0031592629
A91: 158 | B91: 9935 | C91: מטריקס אי.טי בע"מ | D91: 520039413 | E91: ח.פ | F91: מטריקס | G91: IL0004450156 | H91: ISIN | I91: מניות | J91: ישראל | K91: ישראל | L91: סחיר | M91: TASE | N91: שירותי מידע | O91: לא | P91: ILS | Q91: 13243 | R91: 1 | S91: 8160 | T91: 16.819 | U91: 1097.447 | V91: 0.000208 | W91: 0.0067863709 | X91: 0.0010011391
A92: 158 | B92: 9935 | C92: מיטרוניקס בע"מ | D92: 511527202 | E92: ח.פ | F92: מיטרוניקס | G92: IL0010910656 | H92: ISIN | I92: מניות | J92: ישראל | K92: ישראל | L92: סחיר | M92: TASE | N92: רובוטיקה ותלת מימד | O92: לא | P92: ILS | Q92: 25200 | R92: 1 | S92: 3622 | U92: 912.744 | V92: 0.00023 | W92: 0.005644206 | X92: 0.00083264464
A93: 158 | B93: 9935 | C93: מליסרון בע"מ | D93: 520037789 | E93: ח.פ | F93: מליסרון | G93: IL0003230146 | H93: ISIN | I93: מניות | J93: ישראל | K93: ישראל | L93: סחיר | M93: TASE | N93: נדל"ן מניב בישראל | O93: לא | P93: ILS | Q93: 3327 | R93: 1 | S93: 26900 | T93: 8.401 | U93: 903.364 | V93: 7e-05 | W93: 0.0055862041 | X93: 0.00082408807
A94: 158 | B94: 9935 | C94: נאוויטס פטרוליום, שותפות מוגבלת | D94: 550263107 | E94: ח.פ | F94: נאוויטס פט יהש | G94: IL0011419699 | H94: ISIN | I94: מניות | J94: חו"ל | K94: ארה"ב | L94: סחיר | M94: TASE | N94: חיפושי נפט וגז | O94: לא | P94: ILS | Q94: 22953 | R94: 1 | S94: 4170 | U94: 957.14 | V94: 0.000245 | W94: 0.0059187417 | X94: 0.00087314469
A95: 158 | B95: 9935 | C95: ניו-מד אנרג'י- שותפות מוגבלת | D95: 550013098 | E95: ח.פ | F95: ניו-מד אנרג'י יהש | G95: IL0004750209 | H95: ISIN | I95: מניות | J95: ישראל | K95: ישראל | L95: סחיר | M95: TASE | N95: חיפושי נפט וגז | O95: לא | P95: ILS | Q95: 115222 | R95: 1 | S95: 935.3 | T95: 22.076 | U95: 1099.748 | V95: 9.8e-05 | W95: 0.006800595 | X95: 0.0010032375
A96: 158 | B96: 9935 | C96: נייס מערכות בע"מ | D96: 520036872 | E96: ח.פ | F96: נייס | G96: IL0002730112 | H96: ISIN | I96: מניות | J96: ישראל | K96: ישראל | L96: סחיר | M96: TASE | N96: תוכנה ואינטרנט | O96: לא | P96: ILS | Q96: 1260 | R96: 1 | S96: 95150 | U96: 1198.89 | V96: 2e-05 | W96: 0.0074136693 | X96: 0.0010936794
A97: 158 | B97: 9935 | C97: קבוצת עזריאלי בע"מ (לשעבר קנית מימון) | D97: 510960719 | E97: ח.פ | F97: עזריאלי קבוצה | G97: IL0011194789 | H97: ISIN | I97: מניות | J97: ישראל | K97: ישראל | L97: סחיר | M97: TASE | N97: נדל"ן מניב בישראל | O97: לא | P97: ILS | Q97: 7339 | R97: 1 | S97: 26610 | U97: 1952.908 | V97: 6.1e-05 | W97: 0.012076348 | X97: 0.0017815272
A98: 158 | B98: 9935 | C98: בנק הפועלים בע"מ | D98: 520000118 | E98: ח.פ | F98: פועלים | G98: IL0006625771 | H98: ISIN | I98: מניות | J98: ישראל | K98: ישראל | L98: סחיר | M98: TASE | N98: בנקים | O98: לא | P98: ILS | Q98: 121431 | R98: 1 | S98: 3500 | T98: 31.963 | U98: 4282.048 | V98: 9.1e-05 | W98: 0.026479234 | X98: 0.0039062699
A99: 158 | B99: 9935 | C99: פוקס-ויזל בע"מ | D99: 512157603 | E99: ח.פ | F99: פוקס- ויזל | G99: IL0010870223 | H99: ISIN | I99: מניות | J99: ישראל | K99: ישראל | L99: סחיר | M99: TASE | N99: רשתות שיווק | O99: לא | P99: ILS | Q99: 3559 | R99: 1 | S99: 34140 | U99: 1215.043 | V99: 0.000258 | W99: 0.0075135534 | X99: 0.0011084145
A100: 158 | B100: 9935 | C100: פורמולה מערכות (1985)בע"מ | D100: 520036690 | E100: ח.פ | F100: פורמולה מערכות | G100: IL0002560162 | H100: ISIN | I100: מניות | J100: ישראל | K100: ישראל | L100: סחיר | M100: TASE | N100: שירותי מידע | O100: לא | P100: ILS | Q100: 2567 | R100: 1 | S100: 30030 | U100: 770.87 | V100: 0.000167 | W100: 0.0047668894 | X100: 0.00070322112
...

Sheet קרנות סל
A1: מספר קופה/קרן/ח.פ. עבור חברת ביטוח | B1: מספר מסלול | C1: שם מנפיק | D1: מספר מנפיק | E1: סוג מספר מזהה מנפיק | F1: שם נייר ערך | G1: מספר נייר ערך | H1: סוג מספר נייר ערך | I1: מאפיין עיקרי | J1: ישראל/חו"ל | K1: מדינה לפי חשיפה כלכלית | L1: זירת מסחר | M1: סיווג הקרן | N1: בעל עניין/צד קשור | O1: מטבע פעילות | P1: ערך נקוב (יחידות) | Q1: שער חליפין | R1: שער נייר הערך | S1: סכום לקבל (במטבע הפעילות) | T1: שווי הוגן (באלפי ש"ח) | U1: שיעור מערך נקוב מונפק | V1: שיעור מנכסי אפיק ההשקעה | W1: שיעור מסך נכסי ההשקעה
A2: 158 | B2: 1441 | C2: קסם קרנות נאמנות בע"מ | D2: 510938608 | E2: ח.פ | F2: קסם תל בונד שקלי | G2: IL0011464141 | H2: ISIN | I2: עוקב אחר מדדים אחרים בישראל | J2: ישראל | K2: ישראל | L2: TASE | M2: אג"ח בישראל - חברות והמרה | N2: לא | O2: ILS | P2: 10100 | Q2: 1 | R2: 3844.3 | T2: 388.274 | U2: 0.000289 | V2: 0.72978207 | W2: 0.035401583
A3: 158 | B3: 1441 | C3: קסם קרנות נאמנות בע"מ | D3: 510938608 | E3: ח.פ | F3: קסם.תלבונד ש 50 | G3: IL0011507626 | H3: ISIN | I3: עוקב אחר מדדים אחרים בישראל | J3: ישראל | K3: ישראל | L3: TASE | M3: אג"ח בישראל - חברות והמרה | N3: לא | O3: ILS | P3: 300 | Q3: 1 | R3: 3874.92 | T3: 11.625 | U3: 1.3e-05 | V3: 0.021849351 | W3: 0.0010599077
A4: 158 | B4: 1441 | C4: Real Estate Credit Investments Pcc ltd | D4: 549300D9O5F5P2DTYB19 | E4: LEI | F4: SPDR BLOOMBERG SASB US CORPORA | G4: IE00BLF7VX27 | H4: ISIN | I4: עוקב אחר מדדים אחרים בחו"ל | J4: חו"ל | K4: ארה"ב | L4: LSE | M4: Bond/Fixed Income Funds | N4: לא | O4: USD | P4: 700 | Q4: 3.681 | R4: 27.605 | T4: 71.13 | U4: 0 | V4: 0.13369222 | W4: 0.0064853833
A5: 158 | B5: 1441 | C5: Vanguard Group | D5: QS6WHLCJOJSYY4PYNF72 | E5: LEI | F5: VANGUARD USD CORPORATE BOND UC | G5: IE00BGYWFK87 | H5: ISIN | I5: עוקב אחר מדדים אחרים בחו"ל | J5: חו"ל | K5: ארה"ב | L5: LSE | M5: Bond/Fixed Income Funds | N5: לא | O5: USD | P5: 300 | Q5: 3.681 | R5: 5525 | T5: 61.013 | U5: 0 | V5: 0.11467636 | W5: 0.0055629275
A6: 158 | B6: 1522 | C6: ISHARES USD CROP BOND UCITS ET | D6: 549300QQR5SNTQVNFC45 | E6: LEI | F6: ITB US | G6: US4642887529 | H6: ISIN | I6: עוקב אחר מדדי מניות בחו"ל | J6: חו"ל | K6: ארה"ב | L6: NYSE | M6: מניות בחו"ל חשופות מט"ח | N6: לא | O6: USD | P6: 270 | Q6: 3.681 | R6: 115.77 | T6: 115.06 | U6: 7e-06 | V6: 0.029247139 | W6: 0.011406051
A7: 158 | B7: 1522 | C7: מגדל קרנות נאמנות בע"מ | D7: 511303661 | E7: ח.פ | F7: MTF סל תא 90 | G7: IL0011502593 | H7: ISIN | I7: עוקב אחר מדדי מניות בישראל | J7: ישראל | K7: ישראל | L7: TASE | M7: מניות בישראל | N7: לא | O7: ILS | P7: 8600 | Q7: 1 | R7: 3091 | T7: 265.826 | U7: 0.000239 | V7: 0.067570203 | W7: 0.026351611
A8: 158 | B8: 1522 | C8: קסם קרנות נאמנות בע"מ | D8: 510938608 | E8: ח.פ | F8: קסם קרן סל תא 125 | G8: IL0011463564 | H8: ISIN | I8: עוקב אחר מדדי מניות בישראל | J8: ישראל | K8: ישראל | L8: TASE | M8: מניות בישראל | N8: לא | O8: ILS | P8: 550 | Q8: 1 | R8: 20050 | T8: 110.275 | U8: 1.6e-05 | V8: 0.028030758 | W8: 0.010931677
A9: 158 | B9: 1522 | C9: קסם קרנות נאמנות בע"מ | D9: 510938608 | E9: ח.פ | F9: קסם תא נדלן | G9: IL0011465478 | H9: ISIN | I9: עוקב אחר מדדי מניות בישראל | J9: ישראל | K9: ישראל | L9: TASE | M9: מניות בישראל | N9: לא | O9: ILS | P9: 1900 | Q9: 1 | R9: 8947 | T9: 169.993 | U9: 0.001796 | V9: 0.043210452 | W9: 0.016851585
A10: 158 | B10: 1522 | C10: BlackRock Asset Managment | D10: 549300IJBBIPXKWNXJ28 | E10: LEI | F10: ISHARES EURO STOXX 50 DE | G10: DE0005933956 | H10: ISIN | I10: עוקב אחר מדדי מניות בחו"ל | J10: חו"ל | K10: אירופה | L10: FWB | M10: Equity Funds | N10: לא | O10: EUR | P10: 410 | Q10: 3.979 | R10: 5115 | T10: 83.448 | U10: 4e-06 | V10: 0.021211536 | W10: 0.0082722577
A11: 158 | B11: 1522 | C11: BlackRock Asset Managment | D11: 549300IJBBIPXKWNXJ28 | E11: LEI | F11: Ishares Phlx Se | G11: US4642875235 | H11: ISIN | I11: עוקב אחר מדדי מניות בחו"ל | J11: חו"ל | K11: ארה"ב | L11: NASDAQ | M11: Equity Funds | N11: לא | O11: USD | P11: 60 | Q11: 3.681 | R11: 22592 | T11: 49.897 | U11: 3e-06 | V11: 0.01268322 | W11: 0.0049463114
A12: 158 | B12: 1522 | C12: Invesco investment management limited | D12: 635400KFAN415FMIGG54 | E12: LEI | F12: Powershares QQQ NAS1 | G12: US46090E1038 | H12: ISIN | I12: עוקב אחר מדדי מניות בחו"ל | J12: חו"ל | K12: ארה"ב | L12: NASDAQ | M12: Equity Funds | N12: לא | O12: USD | P12: 410 | Q12: 3.681 | R12: 444.01 | S12: 0.18 | T12: 670.765 | U12: 1e-06 | V12: 0.17050154 | W12: 0.06649366
A13: 158 | B13: 1522 | C13: Invesco investment management limited | D13: 635400KFAN415FMIGG54 | E13: LEI | F13: SOURCE S&P 500 UCITS EFT | G13: IE00B3YCGJ38 | H13: ISIN | I13: עוקב אחר מדדי מניות בחו"ל | J13: חו"ל | K13: ארה"ב | L13: LSE | M13: Equity Funds | N13: לא | O13: USD | P13: 74 | Q13: 3.681 | R13: 102524 | T13: 279.269 | U13: 1.5e-05 | V13: 0.070987331 | W13: 0.027684252
A14: 158 | B14: 1522 | C14: State Street Corp | D14: 549300E2D1JKWI3P9D54 | E14: LEI | F14: SPDR S&P 500 ETF TRUST | G14: US78462F1030 | H14: ISIN | I14: עוקב אחר מדדי מניות בחו"ל | J14: חו"ל | K14: ארה"ב | L14: NYSE | M14: Equity Funds | N14: לא | O14: USD | P14: 350 | Q14: 3.681 | R14: 523.07 | S14: 0.426 | T14: 675.466 | U14: 0 | V14: 0.17169653 | W14: 0.066959695
A15: 158 | B15: 1522 | C15: S&P 500 | D15: Y6X4K52KMJMZE7I7MY94 | E15: LEI | F15: SPDR S&P 500 UCITS EFT | G15: IE000XZSV718 | H15: ISIN | I15: עוקב אחר מדדי מניות בחו"ל | J15: חו"ל | K15: ארה"ב | L15: LSE | M15: Equity Funds | N15: לא | O15: USD | P15: 8700 | Q15: 3.681 | R15: 1267.6 | T15: 405.945 | U15: 0 | V15: 0.10318702 | W15: 0.040241764
A16: 158 | B16: 1522 | C16: Van Eck ETF | D16: 549300WSDUDKDJCJOV22 | E16: LEI | F16: VANECK VECTORS SEMICONDUCTOR | G16: US92189F6768 | H16: ISIN | I16: עוקב אחר מדדי מניות בחו"ל | J16: חו"ל | K16: ארה"ב | L16: NASDAQ | M16: Equity Funds | N16: לא | O16: USD | P16: 55 | Q16: 3.681 | R16: 22499 | T16: 45.55 | U16: 2e-06 | V16: 0.011578425 | W16: 0.0045154541
A17: 158 | B17: 1522 | C17: Vanguard Group | D17: QS6WHLCJOJSYY4PYNF72 | E17: LEI | F17: VANGUARD FTSE BMERGING MARKETS | G17: IE00B3VVMM84 | H17: ISIN | I17: עוקב אחר מדדי מניות בחו"ל | J17: חו"ל | K17: שווקים מתעוררים | L17: LSE | M17: Equity Funds | N17: לא | O17: USD | P17: 500 | Q17: 3.681 | R17: 5682.5 | T17: 104.586 | U17: 0 | V17: 0.026584778 | W17: 0.010367761
A18: 158 | B18: 1522 | C18: Vanguard Group | D18: QS6WHLCJOJSYY4PYNF72 | E18: LEI | F18: VANGUARD S&P 50 | G18: us9229083632 | H18: ISIN | I18: עוקב אחר מדדי מניות בחו"ל | J18: חו"ל | K18: ארה"ב | L18: NYSE | M18: Equity Funds | N18: לא | O18: USD | P18: 439 | Q18: 3.681 | R18: 480.7 | T18: 776.791 | U18: 1e-06 | V18: 0.19745231 | W18: 0.077004157
A19: 158 | B19: 1522 | C19: WisdomTree Europe ltd | D19: 549300R6SLTQ0LZOHH17 | E19: LEI | F19: WisdomTree Japan Hedged | G19: US97717W8516 | H19: ISIN | I19: עוקב אחר מדדי מניות בחו"ל | J19: חו"ל | K19: יפן | L19: NYSE | M19: Equity Funds | N19: לא | O19: USD | P19: 260 | Q19: 3.681 | R19: 108.5 | T19: 103.841 | U19: 9e-06 | V19: 0.026395304 | W19: 0.010293868
A20: 158 | B20: 1522 | C20: מור ניהול קרנות נאמנות בע"מ | D20: 514884485 | E20: ח.פ | F20: מור סל S&P 500 ממ | G20: IL0011658288 | H20: ISIN | I20: עוקב אחר מדדי מניות בחו"ל | J20: חו"ל | K20: ארה"ב | L20: TASE | M20: מניות בחו"ל משולבת | N20: כן | O20: ILS | P20: 930 | Q20: 1 | R20: 8318 | T20: 77.357 | U20: 6.9e-05 | V20: 0.019663446 | W20: 0.0076685203
A21: 158 | B21: 9935 | C21: ISHARES USD CROP BOND UCITS ET | D21: 549300QQR5SNTQVNFC45 | E21: LEI | F21: ITB US | G21: US4642887529 | H21: ISIN | I21: עוקב אחר מדדי מניות בחו"ל | J21: חו"ל | K21: ארה"ב | L21: NYSE | M21: מניות בחו"ל חשופות מט"ח | N21: לא | O21: USD | P21: 8900 | Q21: 3.681 | R21: 115.77 | T21: 3792.729 | U21: 0.000242 | V21: 0.016318182 | W21: 0.0034598922
A22: 158 | B22: 9935 | C22: מגדל קרנות נאמנות בע"מ | D22: 511303661 | E22: ח.פ | F22: MTF סל תא 90 | G22: IL0011502593 | H22: ISIN | I22: עוקב אחר מדדי מניות בישראל | J22: ישראל | K22: ישראל | L22: TASE | M22: מניות בישראל | N22: לא | O22: ILS | P22: 144297 | Q22: 1 | R22: 3091 | T22: 4460.22 | U22: 0.004006 | V22: 0.019190055 | W22: 0.0040688063
A23: 158 | B23: 9935 | C23: הראל קרנות נאמנות בע"מ | D23: 511776783 | E23: ח.פ | F23: הראל סל תא 90 | G23: IL0011489312 | H23: ISIN | I23: עוקב אחר מדדי מניות בישראל | J23: ישראל | K23: ישראל | L23: TASE | M23: מניות בישראל | N23: לא | O23: ILS | P23: 155000 | Q23: 1 | R23: 2053 | T23: 3182.15 | U23: 0.003177 | V23: 0.01369117 | W23: 0.0029028952
A24: 158 | B24: 9935 | C24: הראל קרנות נאמנות בע"מ | D24: 511776783 | E24: ח.פ | F24: הראל סל תא נדלן | G24: IL0011489643 | H24: ISIN | I24: עוקב אחר מדדי מניות בישראל | J24: ישראל | K24: ישראל | L24: TASE | M24: מניות בישראל | N24: לא | O24: ILS | P24: 165000 | Q24: 1 | R24: 907.2 | T24: 1496.88 | U24: 0.009335 | V24: 0.0064403118 | W24: 0.0013655188
A25: 158 | B25: 9935 | C25: הראל קרנות נאמנות בע"מ | D25: 511776783 | E25: ח.פ | F25: הראל סל תל בונד שקלי | G25: IL0011505232 | H25: ISIN | I25: עוקב אחר מדדים אחרים בישראל | J25: ישראל | K25: ישראל | L25: TASE | M25: אג"ח בישראל - חברות והמרה | N25: לא | O25: ILS | P25: 1753000 | Q25: 1 | R25: 385.54 | T25: 6758.516 | U25: 0.007691 | V25: 0.029078451 | W25: 0.0061654114
A26: 158 | B26: 9935 | C26: הראל קרנות נאמנות בע"מ | D26: 511776783 | E26: ח.פ | F26: הראל קרן סל תא 125 | G26: IL0011488991 | H26: ISIN | I26: עוקב אחר מדדי מניות בישראל | J26: ישראל | K26: ישראל | L26: TASE | M26: מניות בישראל | N26: לא | O26: ILS | P26: 72000 | Q26: 1 | R26: 2014 | T26: 1450.08 | U26: 0.001263 | V26: 0.0062389553 | W26: 0.0013228258
... A57: 158 | B57: 9935 | C57: ISHARES USD CROP BOND UCITS ET | D57: 549300QQR5SNTQVNFC45 | E57: LEI | F57: ISHARES USD CROP BOND UCITS ET | G57: IE00BYXYYJ35 | H57: ISIN | I57: עוקב אחר מדדי מניות בחו"ל | J57: חו"ל | K57: ארה"ב | L57: LSE | M57: Equity Funds | N57: לא | O57: USD | P57: 210000 | Q57: 3.681 | R57: 574.3 | T57: 4439.396 | U57: 0 | V57: 0.019100461 | W57: 0.0040498099
A58: 158 | B58: 9935 | C58: Invesco investment management limited | D58: 635400KFAN415FMIGG54 | E58: LEI | F58: Powershares QQQ NAS1 | G58: US46090E1038 | H58: ISIN | I58: עוקב אחר מדדי מניות בחו"ל | J58: חו"ל | K58: ארה"ב | L58: NASDAQ | M58: Equity Funds | N58: לא | O58: USD | P58: 3630 | Q58: 3.681 | R58: 444.01 | S58: 1.59 | T58: 5938.726 | U58: 7e-06 | V58: 0.025551313 | W58: 0.0054175636
A59: 158 | B59: 9935 | C59: Invesco investment management limited | D59: 635400KFAN415FMIGG54 | E59: LEI | F59: SOURCE S&P 500 UCITS EFT | G59: IE00B3YCGJ38 | H59: ISIN | I59: עוקב אחר מדדי מניות בחו"ל | J59: חו"ל | K59: ארה"ב | L59: LSE | M59: Equity Funds | N59: לא | O59: USD | P59: 214 | Q59: 3.681 | R59: 102524 | T59: 807.616 | U59: 4.2e-05 | V59: 0.0034747618 | W59: 0.00073674269
A60: 158 | B60: 9935 | C60: S&P 500 | D60: Y6X4K52KMJMZE7I7MY94 | E60: LEI | F60: SPDR S&P 500 UCITS EFT | G60: IE000XZSV718 | H60: ISIN | I60: עוקב אחר מדדי מניות בחו"ל | J60: חו"ל | K60: ארה"ב | L60: LSE | M60: Equity Funds | N60: לא | O60: USD | P60: 280000 | Q60: 3.681 | R60: 1267.6 | T60: 13064.9 | U60: 0 | V60: 0.056211605 | W60: 0.011918368
A61: 158 | B61: 9935 | C61: Vanguard Group | D61: QS6WHLCJOJSYY4PYNF72 | E61: LEI | F61: VANGUARD FTSE BMERGING MARKETS | G61: IE00B3VVMM84 | H61: ISIN | I61: עוקב אחר מדדי מניות בחו"ל | J61: חו"ל | K61: שווקים מתעוררים | L61: LSE | M61: Equity Funds | N61: לא | O61: USD | P61: 11000 | Q61: 3.681 | R61: 5682.5 | T61: 2300.901 | U61: 0 | V61: 0.0098996048 | W61: 0.0020989817
A62: 158 | B62: 9935 | C62: WisdomTree Europe ltd | D62: 549300R6SLTQ0LZOHH17 | E62: LEI | F62: WisdomTree Japan Hedged | G62: US97717W8516 | H62: ISIN | I62: עוקב אחר מדדי מניות בחו"ל | J62: חו"ל | K62: יפן | L62: NYSE | M62: Equity Funds | N62: לא | O62: USD | P62: 6000 | Q62: 3.681 | R62: 108.5 | T62: 2396.331 | U62: 0.000199 | V62: 0.010310191 | W62: 0.002186037
A63: 158 | B63: 9935 | C63: מור ניהול קרנות נאמנות בע"מ | D63: 514884485 | E63: ח.פ | F63: מור סל S&P 500 ממ | G63: IL0011658288 | H63: ISIN | I63: עוקב אחר מדדי מניות בחו"ל | J63: חו"ל | K63: ארה"ב | L63: TASE | M63: מניות בחו"ל משולבת | N63: כן | O63: ILS | P63: 61000 | Q63: 1 | R63: 8318 | T63: 5073.98 | U63: 0.004519 | V63: 0.02183075 | W63: 0.0046287045
A64: 158 | B64: 9936 | C64: ISHARES USD CROP BOND UCITS ET | D64: 549300QQR5SNTQVNFC45 | E64: LEI | F64: ITB US | G64: US4642887529 | H64: ISIN | I64: עוקב אחר מדדי מניות בחו"ל | J64: חו"ל | K64: ארה"ב | L64: NYSE | M64: מניות בחו"ל חשופות מט"ח | N64: לא | O64: USD | P64: 240 | Q64: 3.681 | R64: 115.77 | T64: 102.276 | U64: 7e-06 | V64: 0.024763071 | W64: 0.0067186604
A65: 158 | B65: 9936 | C65: מגדל קרנות נאמנות בע"מ | D65: 511303661 | E65: ח.פ | F65: MTF סל תא 90 | G65: IL0011502593 | H65: ISIN | I65: עוקב אחר מדדי מניות בישראל | J65: ישראל | K65: ישראל | L65: TASE | M65: מניות בישראל | N65: לא | O65: ILS | P65: 8400 | Q65: 1 | R65: 3091 | T65: 259.644 | U65: 0.000233 | V65: 0.062865114 | W65: 0.01705642
A66: 158 | B66: 9936 | C66: הראל קרנות נאמנות בע"מ | D66: 511776783 | E66: ח.פ | F66: הראל סל תא 90 | G66: IL0011489312 | H66: ISIN | I66: עוקב אחר מדדי מניות בישראל | J66: ישראל | K66: ישראל | L66: TASE | M66: מניות בישראל | N66: לא | O66: ILS | P66: 3500 | Q66: 1 | R66: 2053 | T66: 71.855 | U66: 7.2e-05 | V66: 0.017397563 | W66: 0.0047202673
A67: 158 | B67: 9936 | C67: קסם קרנות נאמנות בע"מ | D67: 510938608 | E67: ח.פ | F67: קסם קרן סל תא 125 | G67: IL0011463564 | H67: ISIN | I67: עוקב אחר מדדי מניות בישראל | J67: ישראל | K67: ישראל | L67: TASE | M67: מניות בישראל | N67: לא | O67: ILS | P67: 390 | Q67: 1 | R67: 20050 | T67: 78.195 | U67: 1.1e-05 | V67: 0.018932606 | W67: 0.0051367518
A68: 158 | B68: 9936 | C68: קסם קרנות נאמנות בע"מ | D68: 510938608 | E68: ח.פ | F68: קסם תא נדלן | G68: IL0011465478 | H68: ISIN | I68: עוקב אחר מדדי מניות בישראל | J68: ישראל | K68: ישראל | L68: TASE | M68: מניות בישראל | N68: לא | O68: ILS | P68: 360 | Q68: 1 | R68: 8947 | T68: 32.209 | U68: 0.00034 | V68: 0.007798505 | W68: 0.0021158727
A69: 158 | B69: 9936 | C69: BlackRock Asset Managment | D69: 549300IJBBIPXKWNXJ28 | E69: LEI | F69: ISHARES EURO STOXX 50 DE | G69: DE0005933956 | H69: ISIN | I69: עוקב אחר מדדי מניות בחו"ל | J69: חו"ל | K69: אירופה | L69: FWB | M69: Equity Funds | N69: לא | O69: EUR | P69: 1000 | Q69: 3.979 | R69: 5115 | T69: 203.531 | U69: 1e-05 | V69: 0.049279003 | W69: 0.013370267
A70: 158 | B70: 9936 | C70: ISHARES USD CROP BOND UCITS ET | D70: 549300QQR5SNTQVNFC45 | E70: LEI | F70: ISHARES USD CROP BOND UCITS ET | G70: IE00BYXYYJ35 | H70: ISIN | I70: עוקב אחר מדדי מניות בחו"ל | J70: חו"ל | K70: ארה"ב | L70: LSE | M70: Equity Funds | N70: לא | O70: USD | P70: 7000 | Q70: 3.681 | R70: 574.3 | T70: 147.98 | U70: 0 | V70: 0.035828951 | W70: 0.0097210298
A71: 158 | B71: 9936 | C71: LYXOR ETF | D71: 549300D36R80ZKQLJ385 | E71: LEI | F71: Lyxor S&P 500 Ucits Etf - c-eu | G71: LU1135865084 | H71: ISIN | I71: עוקב אחר מדדי מניות בחו"ל | J71: חו"ל | K71: ארה"ב | L71: LSE | M71: Equity Funds | N71: לא | O71: USD | P71: 25 | Q71: 3.681 | R71: 37152.5 | T71: 34.19 | U71: 3e-06 | V71: 0.0082779974 | W71: 0.0022459675
A72: 158 | B72: 9936 | C72: Invesco investment management limited | D72: 635400KFAN415FMIGG54 | E72: LEI | F72: Powershares QQQ NAS1 | G72: US46090E1038 | H72: ISIN | I72: עוקב אחר מדדי מניות בחו"ל | J72: חו"ל | K72: ארה"ב | L72: NASDAQ | M72: Equity Funds | N72: לא | O72: USD | P72: 55 | Q72: 3.681 | R72: 444.01 | S72: 0.024 | T72: 89.981 | U72: 0 | V72: 0.021786161 | W72: 0.0059109719
A73: 158 | B73: 9936 | C73: Invesco investment management limited | D73: 635400KFAN415FMIGG54 | E73: LEI | F73: SOURCE S&P 500 UCITS EFT | G73: IE00B3YCGJ38 | H73: ISIN | I73: עוקב אחר מדדי מניות בחו"ל | J73: חו"ל | K73: ארה"ב | L73: LSE | M73: Equity Funds | N73: לא | O73: USD | P73: 109 | Q73: 3.681 | R73: 102524 | T73: 411.356 | U73: 2.1e-05 | V73: 0.099597692 | W73: 0.02702262
A74: 158 | B74: 9936 | C74: State Street Corp | D74: 549300E2D1JKWI3P9D54 | E74: LEI | F74: SPDR S&P 500 ETF TRUST | G74: US78462F1030 | H74: ISIN | I74: עוקב אחר מדדי מניות בחו"ל | J74: חו"ל | K74: ארה"ב | L74: NYSE | M74: Equity Funds | N74: לא | O74: USD | P74: 85 | Q74: 3.681 | R74: 523.07 | S74: 0.104 | T74: 164.042 | U74: 0 | V74: 0.039717883 | W74: 0.010776166
A75: 158 | B75: 9936 | C75: S&P 500 | D75: Y6X4K52KMJMZE7I7MY94 | E75: LEI | F75: SPDR S&P 500 UCITS EFT | G75: IE000XZSV718 | H75: ISIN | I75: עוקב אחר מדדי מניות בחו"ל | J75: חו"ל | K75: ארה"ב | L75: LSE | M75: Equity Funds | N75: לא | O75: USD | P75: 11000 | Q75: 3.681 | R75: 1267.6 | T75: 513.264 | U75: 0 | V75: 0.12427167 | W75: 0.033717109
A76: 158 | B76: 9936 | C76: Van Eck ETF | D76: 549300WSDUDKDJCJOV22 | E76: LEI | F76: VANECK VECTORS SEMICONDUCTOR | G76: US92189F6768 | H76: ISIN | I76: עוקב אחר מדדי מניות בחו"ל | J76: חו"ל | K76: ארה"ב | L76: NASDAQ | M76: Equity Funds | N76: לא | O76: USD | P76: 40 | Q76: 3.681 | R76: 22499 | T76: 33.128 | U76: 2e-06 | V76: 0.0080208509 | W76: 0.0021761991
A77: 158 | B77: 9936 | C77: Vanguard Group | D77: QS6WHLCJOJSYY4PYNF72 | E77: LEI | F77: VANGUARD FTSE BMERGING MARKETS | G77: IE00B3VVMM84 | H77: ISIN | I77: עוקב אחר מדדי מניות בחו"ל | J77: חו"ל | K77: שווקים מתעוררים | L77: LSE | M77: Equity Funds | N77: לא | O77: USD | P77: 370 | Q77: 3.681 | R77: 5682.5 | T77: 77.394 | U77: 0 | V77: 0.018738654 | W77: 0.0050841293
A78: 158 | B78: 9936 | C78: Vanguard Group | D78: QS6WHLCJOJSYY4PYNF72 | E78: LEI | F78: VANGUARD S&P 50 | G78: us9229083632 | H78: ISIN | I78: עוקב אחר מדדי מניות בחו"ל | J78: חו"ל | K78: ארה"ב | L78: NYSE | M78: Equity Funds | N78: לא | O78: USD | P78: 633 | Q78: 3.681 | R78: 480.7 | T78: 1120.066 | U78: 1e-06 | V78: 0.27119087 | W78: 0.073578893
A79: 158 | B79: 9936 | C79: WisdomTree Europe ltd | D79: 549300R6SLTQ0LZOHH17 | E79: LEI | F79: WisdomTree Japan Hedged | G79: US97717W8516 | H79: ISIN | I79: עוקב אחר מדדי מניות בחו"ל | J79: חו"ל | K79: יפן | L79: NYSE | M79: Equity Funds | N79: לא | O79: USD | P79: 200 | Q79: 3.681 | R79: 108.5 | T79: 79.878 | U79: 7e-06 | V79: 0.019340022 | W79: 0.005247291
A80: 158 | B80: 9936 | C80: מור ניהול קרנות נאמנות בע"מ | D80: 514884485 | E80: ח.פ | F80: מור סל S&P 500 ממ | G80: IL0011658288 | H80: ISIN | I80: עוקב אחר מדדי מניות בחו"ל | J80: חו"ל | K80: ארה"ב | L80: TASE | M80: מניות בחו"ל משולבת | N80: כן | O80: ILS | P80: 8550 | Q80: 1 | R80: 8318 | T80: 711.189 | U80: 0.000633 | V80: 0.17219338 | W80: 0.046719117
A81: 158 | B81: 9937 | C81: ISHARES USD CROP BOND UCITS ET | D81: 549300QQR5SNTQVNFC45 | E81: LEI | F81: ITB US | G81: US4642887529 | H81: ISIN | I81: עוקב אחר מדדי מניות בחו"ל | J81: חו"ל | K81: ארה"ב | L81: NYSE | M81: מניות בחו"ל חשופות מט"ח | N81: לא | O81: USD | P81: 265 | Q81: 3.681 | R81: 115.77 | T81: 112.93 | U81: 7e-06 | V81: 0.011861521 | W81: 0.003591988
A82: 158 | B82: 9937 | C82: מגדל קרנות נאמנות בע"מ | D82: 511303661 | E82: ח.פ | F82: MTF סל תא 90 | G82: IL0011502593 | H82: ISIN | I82: עוקב אחר מדדי מניות בישראל | J82: ישראל | K82: ישראל | L82: TASE | M82: מניות בישראל | N82: לא | O82: ILS | P82: 11059 | Q82: 1 | R82: 3091 | T82: 341.834 | U82: 0.000307 | V82: 0.035904388 | W82: 0.010872816
A83: 158 | B83: 9937 | C83: מגדל קרנות נאמנות בע"מ | D83: 511303661 | E83: ח.פ | F83: MTF סל תלבונד 60 | G83: IL0011499964 | H83: ISIN | I83: עוקב אחר מדדים אחרים בישראל | J83: ישראל | K83: ישראל | L83: TASE | M83: אג"ח בישראל - חברות והמרה | N83: לא | O83: ILS | P83: 54466 | Q83: 1 | R83: 457.01 | T83: 248.915 | U83: 0.000376 | V83: 0.026144711 | W83: 0.0079173226
A84: 158 | B84: 9937 | C84: מגדל קרנות נאמנות בע"מ | D84: 511303661 | E84: ח.פ | F84: MTF500SP ממ | G84: IL0011505729 | H84: ISIN | I84: עוקב אחר מדדי מניות בחו"ל | J84: ישראל | K84: ארה"ב | L84: TASE | M84: מניות בחו"ל משולבת | N84: לא | O84: ILS | P84: 4900 | Q84: 1 | R84: 6781 | T84: 332.269 | U84: 0.000201 | V84: 0.034899763 | W84: 0.010568588
A85: 158 | B85: 9937 | C85: הראל קרנות נאמנות בע"מ | D85: 511776783 | E85: ח.פ | F85: הראל סל תא נדלן | G85: IL0011489643 | H85: ISIN | I85: עוקב אחר מדדי מניות בישראל | J85: ישראל | K85: ישראל | L85: TASE | M85: מניות בישראל | N85: לא | O85: ILS | P85: 3700 | Q85: 1 | R85: 907.2 | T85: 33.566 | U85: 0.000209 | V85: 0.0035256356 | W85: 0.0010676574
A86: 158 | B86: 9937 | C86: הראל קרנות נאמנות בע"מ | D86: 511776783 | E86: ח.פ | F86: הראל קרן סל תא 125 | G86: IL0011488991 | H86: ISIN | I86: עוקב אחר מדדי מניות בישראל | J86: ישראל | K86: ישראל | L86: TASE | M86: מניות בישראל | N86: לא | O86: ILS | P86: 15600 | Q86: 1 | R86: 2014 | T86: 314.184 | U86: 0.000274 | V86: 0.033000212 | W86: 0.0099933529
... A97: 158 | B97: 9937 | C97: LYXOR ETF | D97: 549300D36R80ZKQLJ385 | E97: LEI | F97: Lyxor S&P 500 Ucits Etf - c-eu | G97: LU1135865084 | H97: ISIN | I97: עוקב אחר מדדי מניות בחו"ל | J97: חו"ל | K97: ארה"ב | L97: LSE | M97: Equity Funds | N97: לא | O97: USD | P97: 332 | Q97: 3.681 | R97: 37152.5 | T97: 454.038 | U97: 3.7e-05 | V97: 0.047689701 | W97: 0.014441726
A98: 158 | B98: 9937 | C98: Invesco investment management limited | D98: 635400KFAN415FMIGG54 | E98: LEI | F98: Powershares QQQ NAS1 | G98: US46090E1038 | H98: ISIN | I98: עוקב אחר מדדי מניות בחו"ל | J98: חו"ל | K98: ארה"ב | L98: NASDAQ | M98: Equity Funds | N98: לא | O98: USD | P98: 141 | Q98: 3.681 | R98: 444.01 | S98: 0.062 | T98: 230.678 | U98: 0 | V98: 0.024229165 | W98: 0.0073372438
A99: 158 | B99: 9937 | C99: Invesco investment management limited | D99: 635400KFAN415FMIGG54 | E99: LEI | F99: SOURCE S&P 500 UCITS EFT | G99: IE00B3YCGJ38 | H99: ISIN | I99: עוקב אחר מדדי מניות בחו"ל | J99: חו"ל | K99: ארה"ב | L99: LSE | M99: Equity Funds | N99: לא | O99: USD | P99: 35 | Q99: 3.681 | R99: 102524 | T99: 132.087 | U99: 7e-06 | V99: 0.013873692 | W99: 0.0042013277
A100: 158 | B100: 9937 | C100: Real Estate Credit Investments Pcc ltd | D100: 549300D9O5F5P2DTYB19 | E100: LEI | F100: SPDR BLOOMBERG SASB US CORPORA | G100: IE00BLF7VX27 | H100: ISIN | I100: עוקב אחר מדדים אחרים בחו"ל | J100: חו"ל | K100: ארה"ב | L100: LSE | M100: Bond/Fixed Income Funds | N100: לא | O100: USD | P100: 2400 | Q100: 3.681 | R100: 27.605 | T100: 243.874 | U100: 0 | V100: 0.025615183 | W100: 0.0077569674
A101: 158 | B101: 9937 | C101: State Street Corp | D101: 549300E2D1JKWI3P9D54 | E101: LEI | F101: SPDR PORTFOLIO S&P 500 ETF | G101: US78464A8541 | H101: ISIN | I101: עוקב אחר מדדי מניות בחו"ל | J101: חו"ל | K101: ארה"ב | L101: NYSE | M101: Equity Funds | N101: לא | O101: USD | P101: 4610 | Q101: 3.681 | R101: 6153 | T101: 1044.128 | U101: 1.5e-05 | V101: 0.10966961 | W101: 0.033210913
A102: 158 | B102: 9937 | C102: State Street Corp | D102: 549300E2D1JKWI3P9D54 | E102: LEI | F102: SPDR S&P 500 ETF TRUST | G102: US78462F1030 | H102: ISIN | I102: עוקב אחר מדדי מניות בחו"ל | J102: חו"ל | K102: ארה"ב | L102: NYSE | M102: Equity Funds | N102: לא | O102: USD | P102: 103 | Q102: 3.681 | R102: 523.07 | S102: 0.125 | T102: 198.78 | U102: 0 | V102: 0.020878803 | W102: 0.006322664
A103: 158 | B103: 9937 | C103: S&P 500 | D103: Y6X4K52KMJMZE7I7MY94 | E103: LEI | F103: SPDR S&P 500 UCITS EFT | G103: IE000XZSV718 | H103: ISIN | I103: עוקב אחר מדדי מניות בחו"ל | J103: חו"ל | K103: ארה"ב | L103: LSE | M103: Equity Funds | N103: לא | O103: USD | P103: 4000 | Q103: 3.681 | R103: 1267.6 | T103: 186.641 | U103: 0 | V103: 0.01960382 | W103: 0.0059365646
A104: 158 | B104: 9937 | C104: SXLE LN | D104: 549300M0AUGU3NFNF319 | E104: LEI | F104: SPDR S&P U.S. ENERGY SELECT SE | G104: IE00BWBXM492 | H104: ISIN | I104: עוקב אחר מדדי מניות בחו"ל | J104: חו"ל | K104: ארה"ב | L104: LSE | M104: Equity Funds | N104: לא | O104: USD | P104: 670 | Q104: 3.681 | R104: 3552.75 | T104: 87.62 | U104: 0 | V104: 0.0092031802 | W104: 0.0027869708
A105: 158 | B105: 9937 | C105: State Street Corp | D105: 549300E2D1JKWI3P9D54 | E105: LEI | F105: SPDR S&P U.S. FINANCIALS SELEC | G105: IE00BWBXM500 | H105: ISIN | I105: עוקב אחר מדדי מניות בחו"ל | J105: חו"ל | K105: ארה"ב | L105: LSE | M105: Equity Funds | N105: לא | O105: USD | P105: 240 | Q105: 3.681 | R105: 4855.875 | T105: 42.899 | U105: 0 | V105: 0.0045058551 | W105: 0.0013644943
A106: 158 | B106: 9937 | C106: Real Estate Credit Investments Pcc ltd | D106: 549300D9O5F5P2DTYB19 | E106: LEI | F106: SPDR S&P US TECHNOLOGY SELECT | G106: IE00BWBXM948 | H106: ISIN | I106: עוקב אחר מדדי מניות בחו"ל | J106: חו"ל | K106: ארה"ב | L106: LSE | M106: Equity Funds | N106: לא | O106: USD | P106: 200 | Q106: 3.681 | R106: 10869.5 | T106: 80.021 | U106: 0 | V106: 0.0084050062 | W106: 0.0025452623
A107: 158 | B107: 9937 | C107: Van Eck ETF | D107: 549300WSDUDKDJCJOV22 | E107: LEI | F107: VANECK VECTORS SEMICONDUCTOR | G107: US92189F6768 | H107: ISIN | I107: עוקב אחר מדדי מניות בחו"ל | J107: חו"ל | K107: ארה"ב | L107: NASDAQ | M107: Equity Funds | N107: לא | O107: USD | P107: 45 | Q107: 3.681 | R107: 22499 | T107: 37.268 | U107: 2e-06 | V107: 0.0039144812 | W107: 0.0011854103
A108: 158 | B108: 9937 | C108: Vanguard Group | D108: QS6WHLCJOJSYY4PYNF72 | E108: LEI | F108: VANGUARD FTSE BMERGING MARKETS | G108: IE00B3VVMM84 | H108: ISIN | I108: עוקב אחר מדדי מניות בחו"ל | J108: חו"ל | K108: שווקים מתעוררים | L108: LSE | M108: Equity Funds | N108: לא | O108: USD | P108: 1020 | Q108: 3.681 | R108: 5682.5 | T108: 213.356 | U108: 0 | V108: 0.022409806 | W108: 0.0067862928
A109: 158 | B109: 9937 | C109: Vanguard Group | D109: QS6WHLCJOJSYY4PYNF72 | E109: LEI | F109: VANGUARD S&P 50 | G109: us9229083632 | H109: ISIN | I109: עוקב אחר מדדי מניות בחו"ל | J109: חו"ל | K109: ארה"ב | L109: NYSE | M109: Equity Funds | N109: לא | O109: USD | P109: 438 | Q109: 3.681 | R109: 480.7 | T109: 775.022 | U109: 1e-06 | V109: 0.081404181 | W109: 0.024651378
A110: 158 | B110: 9937 | C110: Vanguard Group | D110: QS6WHLCJOJSYY4PYNF72 | E110: LEI | F110: VANGUARD USD CORPORATE BOND UC | G110: IE00BGYWFK87 | H110: ISIN | I110: עוקב אחר מדדים אחרים בחו"ל | J110: חו"ל | K110: ארה"ב | L110: LSE | M110: Bond/Fixed Income Funds | N110: לא | O110: USD | P110: 1500 | Q110: 3.681 | R110: 5525 | T110: 305.063 | U110: 0 | V110: 0.032042177 | W110: 0.0097032343
A111: 158 | B111: 9937 | C111: WisdomTree Europe ltd | D111: 549300R6SLTQ0LZOHH17 | E111: LEI | F111: WISDOMTREE JAPAN EQUITY UCITS | G111: IE00BYQCZD50 | H111: ISIN | I111: עוקב אחר מדדי מניות בחו"ל | J111: חו"ל | K111: ארה"ב | L111: LSE | M111: Equity Funds | N111: לא | O111: USD | P111: 320 | Q111: 3.681 | R111: 4107 | T111: 48.377 | U111: 0 | V111: 0.0050812804 | W111: 0.0015387485
A112: 158 | B112: 9937 | C112: WisdomTree Europe ltd | D112: 549300R6SLTQ0LZOHH17 | E112: LEI | F112: WisdomTree Japan Hedged | G112: US97717W8516 | H112: ISIN | I112: עוקב אחר מדדי מניות בחו"ל | J112: חו"ל | K112: יפן | L112: NYSE | M112: Equity Funds | N112: לא | O112: USD | P112: 970 | Q112: 3.681 | R112: 108.5 | T112: 387.407 | U112: 3.2e-05 | V112: 0.040691149 | W112: 0.012322376

Sheet קרנות נאמנות
A1: מספר קופה/קרן/ח.פ. עבור חברת ביטוח | B1: מספר מסלול | C1: שם מנפיק | D1: מספר מנפיק | E1: סוג מספר מזהה מנפיק | F1: שם נייר ערך | G1: מספר נייר ערך | H1: סוג מספר נייר ערך | I1: מאפיין עיקרי | J1: ישראל/חו"ל | K1: מדינה לפי חשיפה כלכלית | L1: סטאטוס סחירות | M1: זירת מסחר | N1: סיווג הקרן | O1: בעל עניין/צד קשור | P1: מטבע פעילות | Q1: ערך נקוב (יחידות) | R1: שער חליפין | S1: שער נייר הערך | T1: שווי הוגן (באלפי ש"ח) | U1: שיעור מערך נקוב מונפק | V1: שיעור מנכסי אפיק ההשקעה | W1: שיעור מסך נכסי ההשקעה
A2: 158 | B2: 1522 | C2: מגדל קרנות נאמנות בע"מ | D2: 511303661 | E2: ח.פ | F2: MTF מח SP500 ממ | G2: IL0051258692 | H2: ISIN | I2: מניות | J2: חו"ל | K2: ארה"ב | L2: סחיר | M2: TASE | N2: מניות בחו"ל משולבת | O2: לא | P2: ILS | Q2: 350000 | R2: 1 | S2: 183.98 | T2: 643.93 | U2: 0 | V2: 0.46837404 | W2: 0.063833457
A3: 158 | B3: 1522 | C3: קסם קרנות נאמנות בע"מ | D3: 510938608 | E3: ח.פ | F3: קסם 500נאףמנטרל | G3: IL0051229578 | H3: ISIN | I3: מניות | J3: חו"ל | K3: ארה"ב | L3: סחיר | M3: TASE | N3: מניות בחו"ל חשופות מט"ח | O3: לא | P3: ILS | Q3: 300000 | R3: 1 | S3: 243.63 | T3: 730.89 | U3: 0 | V3: 0.53162596 | W3: 0.072453894
A4: 158 | B4: 9935 | C4: אי בי אי ניהול קרנות נאמנות בע"מ | D4: 510791031 | E4: ח.פ | F4: איביאי טכנולגיית עילית | G4: IL0011425381 | H4: ISIN | I4: מניות | J4: ישראל | K4: ישראל | L4: סחיר | M4: TASE | N4: מניות בישראל | O4: לא | P4: ILS | Q4: 8209517.2 | R4: 1 | S4: 62.3 | T4: 5114.529 | U4: 0.022416 | V4: 0.77734407 | W4: 0.0046656953
A5: 158 | B5: 9935 | C5: קסם קרנות נאמנות בע"מ | D5: 510938608 | E5: ח.פ | F5: קסם KTF ת"א 100 | G5: IL0051133457 | H5: ISIN | I5: מניות | J5: ישראל | L5: סחיר | M5: TASE | N5: מניות בישראל | O5: לא | P5: ILS | Q5: 721550 | R5: 1 | S5: 203.03 | T5: 1464.963 | U5: 0.00619 | V5: 0.22265593 | W5: 0.0013364027
A6: 158 | B6: 9936 | C6: קסם קרנות נאמנות בע"מ | D6: 510938608 | E6: ח.פ | F6: קסם KTF ת"א 100 | G6: IL0051133457 | H6: ISIN | I6: מניות | J6: ישראל | L6: סחיר | M6: TASE | N6: מניות בישראל | O6: לא | P6: ILS | Q6: 34813 | R6: 1 | S6: 203.03 | T6: 70.681 | U6: 0.000299 | V6: 1 | W6: 0.0046431345

Sheet כתבי אופציה
A1: מספר קופה/קרן/ח.פ. עבור חברת ביטוח | B1: מספר מסלול | C1: שם מנפיק | D1: מספר מנפיק | E1: סוג מספר מזהה מנפיק | F1: שם נייר ערך | G1: מספר נייר ערך | H1: סוג מספר נייר ערך | I1: ישראל/חו"ל | J1: מדינה לפי חשיפה כלכלית | K1: סטאטוס סחירות | L1: זירת מסחר | M1: נכס בסיס (כתב אופציה) | N1: ענף מסחר | O1: תאריך פקיעה | P1: בעל עניין/צד קשור | Q1: מטבע פעילות | R1: שער מימוש | S1: יחס המרה | T1: ערך נקוב (יחידות) | U1: שער חליפין | V1: שער נייר הערך | W1: שווי הוגן (באלפי ש"ח) | X1: שיעור מנכסי אפיק ההשקעה | Y1: שיעור מסך נכסי ההשקעה
A2: 158 | B2: 1522 | C2: אלומיי קפיטל בע"מ | D2: 520039868 | E2: ח.פ | F2: אלומיי אופ 2 | G2: IL0012030826 | H2: ISIN | I2: ישראל | J2: ישראל | K2: סחיר | L2: TASE | M2: אחר | N2: אנרגיה מתחדשת | O2: 05/01/2028 | P2: לא | Q2: ILS | R2: 8000 | S2: 0 | T2: 108 | U2: 1 | V2: 827.5 | W2: 0.894 | X2: 0.083991868 | Y2: 8.859342e-05
A3: 158 | B3: 1522 | C3: בית בכפר בע"מ | D3: 511605719 | E3: ח.פ | F3: בית בכפר אר 1 | G3: IL0011836645 | H3: ISIN | I3: ישראל | J3: ישראל | K3: סחיר | L3: TASE | M3: אחר | N3: נדל"ן מניב בישראל | O3: 30/01/2025 | P3: לא | Q3: ILS | R3: 20 | S3: 0 | T3: 975 | U3: 1 | V3: 21.9 | W3: 0.214 | X3: 0.020067543 | Y3: 2.1166958e-05
A4: 158 | B4: 1522 | C4: גרופ 107 בע"מ | D4: 516199445 | E4: ח.פ | F4: גרופ 107 אפ 1 | G4: IL0011801995 | H4: ISIN | I4: ישראל | J4: ישראל | K4: סחיר | L4: TASE | M4: אחר | N4: תוכנה ואינטרנט | O4: 01/09/2024 | P4: לא | Q4: ILS | R4: 514 | S4: 1 | T4: 5570 | U4: 1 | V4: 1.1 | W4: 0.061 | X4: 0.0057582877 | Y4: 6.0737595e-06
A5: 158 | B5: 1522 | C5: זוז פאוור בע"מ | D5: 514881564 | E5: ח.פ | F5: זוז פאוור אופ 3 | G5: IL0011853210 | H5: ISIN | I5: ישראל | J5: ישראל | K5: סחיר | L5: TASE | M5: אחר | N5: קלינטק | O5: 20/03/2025 | P5: לא | Q5: ILS | R5: 4117.394 | S5: 1 | T5: 1057.08 | U5: 1 | V5: 226 | W5: 2.389 | X5: 0.22452349 | Y5: 0.00023682416
A6: 158 | B6: 1522 | C6: טראקנט אנטרפרייז בע"מ | D6: 515446474 | E6: ח.פ | F6: טרקנט אופ 1 | G6: IL0011741019 | H6: ISIN | I6: ישראל | J6: ישראל | K6: סחיר | L6: TASE | M6: אחר | N6: תוכנה ואינטרנט | O6: 02/03/2025 | P6: לא | Q6: ILS | R6: 0 | S6: 0 | T6: 4450 | U6: 1 | V6: 47.9 | W6: 2.132 | X6: 0.2003277 | Y6: 0.00021130279
A7: 158 | B7: 1522 | C7: פיימנט טכנולוגיות | D7: 515166544 | E7: ח.פ | F7: פיימנט אפ 1 | G7: IL0011808842 | H7: ISIN | I7: ישראל | J7: ישראל | K7: סחיר | L7: TASE | M7: אחר | N7: תוכנה ואינטרנט | O7: 15/10/2024 | P7: לא | Q7: ILS | R7: 0 | S7: 0 | T7: 3900 | U7: 1 | V7: 49.8 | W7: 1.942 | X7: 0.18253218 | Y7: 0.00019253233
A8: 158 | B8: 1522 | C8: קונטיניואל בע"מ | D8: 514949973 | E8: ח.פ | F8: קונטיניואל אופ | G8: IL0011822785 | H8: ISIN | I8: ישראל | J8: ישראל | K8: סחיר | L8: TASE | M8: אחר | N8: תוכנה ואינטרנט | O8: 12/12/2024 | P8: לא | Q8: ILS | R8: 1656 | S8: 1 | T8: 3727 | U8: 1 | V8: 1 | W8: 0.037 | X8: 0.0035027156 | Y8: 3.6946143e-06
A9: 158 | B9: 1522 | C9: איידנטי הלת'קייר בע"מ | D9: 515679405 | E9: ח.פ | F9: איידנטי אופ' 2 | G9: IL0011774762 | H9: ISIN | I9: חו"ל | J9: ישראל | K9: סחיר | L9: TASE | M9: מניות לרבות מדדי מניות | N9: תוכנה ואינטרנט | O9: 16/06/2024 | P9: לא | Q9: ILS | R9: 1125 | S9: 0 | T9: 3060 | U9: 1 | V9: 95.4 | W9: 2.919 | X9: 0.27435652 | Y9: 0.00028938733
A10: 158 | B10: 1522 | C10: שמיים אימפרוב בע"מ | D10: 515181014 | E10: ח.פ | F10: שמיים אופ 1 | G10: IL0011762478 | H10: ISIN | I10: חו"ל | J10: ישראל | K10: סחיר | L10: TASE | M10: מניות לרבות מדדי מניות | N10: תוכנה ואינטרנט | O10: 01/06/2025 | P10: לא | Q10: ILS | R10: 1415 | S10: 0 | T10: 146 | U10: 1 | V10: 36 | W10: 0.053 | X10: 0.004939703 | Y10: 5.210328e-06
A11: 158 | B11: 9935 | C11: י.ח.דמרי בניה ופיתוח בע"מ | D11: 511399388 | E11: ח.פ | F11: דמרי אופ 3 | G11: IL0012028374 | H11: ISIN | I11: ישראל | J11: ישראל | K11: סחיר | L11: TASE | M11: מניות לרבות מדדי מניות | N11: בנייה | O11: 04/08/2024 | P11: לא | Q11: ILS | R11: 28320 | S11: 0 | T11: 1800 | U11: 1 | V11: 1407 | W11: 25.326 | X11: 0.095403351 | Y11: 2.3103475e-05
A12: 158 | B12: 9935 | C12: אלומיי קפיטל בע"מ | D12: 520039868 | E12: ח.פ | F12: אלומיי אופ 2 | G12: IL0012030826 | H12: ISIN | I12: ישראל | J12: ישראל | K12: סחיר | L12: TASE | M12: אחר | N12: אנרגיה מתחדשת | O12: 05/01/2028 | P12: לא | Q12: ILS | R12: 8000 | S12: 0 | T12: 2508 | U12: 1 | V12: 827.5 | W12: 20.754 | X12: 0.078179441 | Y12: 1.8932425e-05
A13: 158 | B13: 9935 | C13: בית בכפר בע"מ | D13: 511605719 | E13: ח.פ | F13: בית בכפר אר 1 | G13: IL0011836645 | H13: ISIN | I13: ישראל | J13: ישראל | K13: סחיר | L13: TASE | M13: אחר | N13: נדל"ן מניב בישראל | O13: 30/01/2025 | P13: לא | Q13: ILS | R13: 20 | S13: 0 | T13: 44550 | U13: 1 | V13: 21.9 | W13: 9.756 | X13: 0.036752666 | Y13: 8.9002566e-06
... A26: 158 | B26: 9937 | C26: י.ח.דמרי בניה ופיתוח בע"מ | D26: 511399388 | E26: ח.פ | F26: דמרי אופ 3 | G26: IL0012028374 | H26: ISIN | I26: ישראל | J26: ישראל | K26: סחיר | L26: TASE | M26: מניות לרבות מדדי מניות | N26: בנייה | O26: 04/08/2024 | P26: לא | Q26: ILS | R26: 28320 | S26: 0 | T26: 100 | U26: 1 | V26: 1407 | W26: 1.407 | X26: 1 | Y26: 4.4752907e-05

Sheet אופציות
A1: מספר קופה/קרן/ח.פ. עבור חברת ביטוח | B1: מספר מסלול | C1: שם מנפיק | D1: מספר מנפיק | E1: סוג מספר מזהה מנפיק | F1: שם נייר ערך | G1: מספר נייר ערך | H1: סוג מספר נייר ערך | I1: מאפיין עיקרי | J1: ישראל/חו"ל | K1: מדינה לפי חשיפה כלכלית | L1: זירת מסחר | M1: ענף מסחר | N1: נכס בסיס | O1: תאריך פקיעה | P1: בעל עניין/צד קשור | Q1: מטבע פעילות | R1: שער מימוש | S1: ערך נקוב (יחידות) | T1: שער חליפין | U1: שער נייר הערך | V1: שווי הוגן (באלפי ש"ח) | W1: שיעור מנכסי אפיק ההשקעה | X1: שיעור מסך נכסי ההשקעה

Sheet חוזים עתידיים
A1: מספר קופה/קרן/ח.פ. עבור חברת ביטוח | B1: מספר מסלול | C1: שם מנפיק | D1: מספר מנפיק | E1: סוג מספר מזהה מנפיק | F1: שם נייר ערך | G1: מספר נייר ערך | H1: סוג מספר נייר ערך | I1: ישראל/חו"ל | J1: מדינה לפי חשיפה כלכלית | K1: זירת מסחר | L1: נכס בסיס | M1: בעל עניין/צד קשור | N1: מטבע פעילות | O1: ערך נקוב (יחידות) | P1: שער חליפין | Q1: שער נייר הערך | R1: שווי הוגן (באלפי ש"ח) | S1: שיעור מנכסי אפיק ההשקעה | T1: שיעור מסך נכסי ההשקעה
A2: 158 | B2: 1522 | C2: חוזים עתידיים בחול | D2: 10527 | E2: פנימי | F2: HWAM4_SP500 MIC EMIN FUTJUN24 | G2: HWAM4 INDEX | H2: אחר | I2: חו"ל | K2: אחר | L2: אחר | M2: לא | N2: USD | O2: 16 | P2: 3.681 | Q2: 5308.5 | R2: 36.177 | S2: 0.82859754 | T2: 0.0035862509
A3: 158 | B3: 1522 | C3: חוזים עתידיים בחול | D3: 10527 | E3: פנימי | F3: SXOM4_STOX EURP 600 JUN24 | G3: SXOM4 INDEX | H3: אחר | I3: חו"ל | K3: אחר | L3: אחר | M3: לא | N3: EUR | O3: 4 | P3: 3.979 | Q3: 510.8 | R3: 7.483 | S3: 0.17140246 | T3: 0.00074184656
A4: 158 | B4: 9935 | C4: חוזים עתידיים בחול | D4: 10527 | E4: פנימי | F4: ESM4_S&P 500 EMINI FUT JUN24 | G4: ESM4 | H4: אחר | I4: חו"ל | J4: ארה"ב | K4: NASDAQD | L4: מניות לרבות מדדי מניות | M4: לא | N4: USD | O4: 54 | P4: 3.681 | Q4: 5308.5 | R4: 1219.478 | S4: 0.26318632 | T4: 0.0011124611
A5: 158 | B5: 9935 | C5: חוזים עתידיים בחול | D5: 10527 | E5: פנימי | F5: NQM4_NASDAQ 100 E-MINI JUN24 | G5: NQM4 | H5: אחר | I5: חו"ל | J5: ארה"ב | K5: NASDAQD | L5: מניות לרבות מדדי מניות | M5: לא | N5: USD | O5: 21 | P5: 3.681 | Q5: 18475 | R5: 395.353 | S5: 0.085324528 | T5: 0.00036065789
A6: 158 | B6: 9935 | C6: חוזים עתידיים בחול | D6: 10527 | E6: פנימי | F6: ESM4_S&P 500 EMINI FUT JUN24 | G6: ESM4 | H6: אחר | I6: חו"ל | J6: ארה"ב | K6: NASDAQD | L6: מניות לרבות מדדי מניות | M6: לא | N6: USD | O6: 122 | P6: 3.681 | Q6: 5308.5 | R6: 2755.118 | S6: 0.59460613 | T6: 0.0025133381
A7: 158 | B7: 9935 | C7: חוזים עתידיים בחול | D7: 10527 | E7: פנימי | F7: NQM4_NASDAQ 100 E-MINI JUN24 | G7: NQM4 | H7: אחר | I7: חו"ל | J7: ארה"ב | K7: NASDAQD | L7: מניות לרבות מדדי מניות | M7: לא | N7: USD | O7: 14 | P7: 3.681 | Q7: 18475 | R7: 263.568 | S7: 0.056883019 | T7: 0.00024043859
A8: 158 | B8: 9936 | C8: חוזים עתידיים בחול | D8: 10527 | E8: פנימי | F8: HWAM4_SP500 MIC EMIN FUTJUN24 | G8: HWAM4 INDEX | H8: אחר | I8: חו"ל | K8: אחר | L8: אחר | M8: לא | N8: USD | O8: 4 | P8: 3.681 | Q8: 5308.5 | R8: 9.044 | S8: 0.54505524 | T8: 0.00059412876
A9: 158 | B9: 9936 | C9: חוזים עתידיים בחול | D9: 10527 | E9: פנימי | F9: HWBM4_NASDAQ 100 MICRO EMINJUN24 | G9: HWBM4 | H9: אחר | I9: חו"ל | K9: אחר | L9: אחר | M9: לא | N9: USD | O9: 4 | P9: 3.681 | Q9: 18475 | R9: 7.549 | S9: 0.45494476 | T9: 0.00049590527

Sheet מוצרים מובנים
A1: מספר קופה/קרן/ח.פ. עבור חברת ביטוח | B1: מספר מסלול | C1: שם מנפיק | D1: מספר מנפיק | E1: סוג מספר מזהה מנפיק | F1: שם נייר ערך | G1: מספר נייר ערך | H1: סוג מספר נייר ערך | I1: מאפיין עיקרי | J1: ישראל/חו"ל | K1: מדינה לפי חשיפה כלכלית | L1: סטאטוס סחירות | M1: זירת מסחר | N1: נכס בסיס | O1: בעל עניין/צד קשור | P1: מח"מ | Q1: שיעור ריבית | R1: תשואה לפדיון | S1: דירוג | T1: שם מדרג | U1: דירוג נייר הערך/המנפיק | V1: מטבע פעילות | W1: ערך נקוב (יחידות) | X1: שער חליפין | Y1: שער נייר הערך | Z1: שווי הוגן (באלפי ש"ח) | AA1: שיעור מנכסי אפיק ההשקעה | AB1: שיעור מסך נכסי ההשקעה
A2: 158 | B2: 1522 | C2: הראל פיקדון סחיר בע"מ | D2: 515989440 | E2: ח.פ | F2: הראל פיקדון אגח ב' | G2: IL0011625022 | H2: ISIN | I2: קרן מובטחת | J2: ישראל | K2: ישראל | L2: סחיר | M2: TASE | N2: ריבית ואג"ח | O2: לא | P2: 2.816 | Q2: 0.012 | R2: 0.04565 | S2: Aaa | T2: מידרוג Moodys | U2: נייר ערך | V2: ILS | W2: 30000 | X2: 1 | Y2: 95.88 | Z2: 28.764 | AA2: 1 | AB2: 0.0028514055
A3: 158 | B3: 9935 | C3: אלה פקדונות בע"מ | D3: 515666881 | E3: ח.פ | F3: אלה פקדון אגח ה | G3: IL0011625774 | H3: ISIN | I3: קרן מובטחת | J3: ישראל | K3: ישראל | L3: סחיר | M3: TASE | N3: מדד המחירים לצרכן | O3: לא | P3: 3.783 | Q3: 0.0005 | R3: 0.02112 | S3: AAA | T3: S&P מעלות | U3: נייר ערך | V3: ILS | W3: 859090.99 | X3: 1 | Y3: 102.75 | Z3: 882.716 | AA3: 1 | AB3: 0.00080525179
A4: 158 | B4: 9937 | C4: אלה פקדונות בע"מ | D4: 515666881 | E4: ח.פ | F4: אלה פקדון אגח ד | G4: IL0011623043 | H4: ISIN | I4: קרן מובטחת | J4: ישראל | K4: ישראל | L4: סחיר | M4: TASE | N4: מט"ח | O4: לא | P4: 1.907 | Q4: 0.117754 | R4: 0.05674 | S4: AAA | T4: S&P מעלות | U4: נייר ערך | V4: ILS | W4: 32000 | X4: 1 | Y4: 109.3 | Z4: 34.976 | AA4: 0.53230129 | AB4: 0.001112493
A5: 158 | B5: 9937 | C5: אלה פקדונות בע"מ | D5: 515666881 | E5: ח.פ | F5: אלה פקדון אגח ה | G5: IL0011625774 | H5: ISIN | I5: קרן מובטחת | J5: ישראל | K5: ישראל | L5: סחיר | M5: TASE | N5: מדד המחירים לצרכן | O5: לא | P5: 3.783 | Q5: 0.0005 | R5: 0.02112 | S5: AAA | T5: S&P מעלות | U5: נייר ערך | V5: ILS | W5: 29908.66 | X5: 1 | Y5: 102.75 | Z5: 30.731 | AA5: 0.46769871 | AB5: 0.00097747564

Sheet לא סחיר איגרות חוב ממשלתיות
A1: מספר קופה/קרן/ח.פ. עבור חברת ביטוח | B1: מספר מסלול | C1: שם מנפיק | D1: שם נייר ערך | E1: מספר נייר ערך | F1: סוג מספר נייר ערך | G1: מאפיין עיקרי | H1: ישראל/חו"ל | I1: מדינה לפי חשיפה כלכלית | J1: תאריך רכישה | K1: דירוג | L1: שם מדרג | M1: מטבע פעילות | N1: מח"מ | O1: מועד פדיון | P1: שיעור ריבית | Q1: תשואה לפדיון | R1: ערך נקוב (יחידות) | S1: שער חליפין | T1: שער נייר הערך | U1: שווי הוגן (באלפי ש"ח) | V1: עלות מופחתת (באלפי ש"ח) | W1: השיטה שיושמה בדוח הכספי | X1: שיעור מנכסי אפיק ההשקעה | Y1: שיעור מסך נכסי ההשקעה

Sheet לא סחיר איגרות חוב מיועדות
A1: מספר קופה/קרן/ח.פ. עבור חברת ביטוח | B1: מספר מסלול | C1: מאפיין עיקרי | D1: שם נייר ערך | E1: מספר נייר ערך | F1: תאריך רכישה | G1: מח"מ | H1: סוג הצמדה | I1: מועד פדיון | J1: שיעור ריבית | K1: תשואה לפדיון | L1: ערך נקוב (יחידות) | M1: שער נייר הערך | N1: שווי הוגן (באלפי ש"ח) | O1: עלות מופחתת (באלפי ש"ח) | P1: השיטה שיושמה בדוח הכספי | Q1: שיעור מנכסי אפיק ההשקעה | R1: שיעור מסך נכסי ההשקעה

Sheet אפיק השקעה מובטח תשואה
A1: מספר קרן | B1: מספר מסלול | C1: מאפיין עיקרי | D1: חודש הנפקת שכבה | E1: חודש הבדיקה | F1: שווי הנכסים באפיק (באלפי ש"ח) | G1: שיעור מסך נכסי ההשקעה

Sheet לא סחיר ניירות ערך מסחריים
A1: מספר קופה/קרן/ח.פ. עבור חברת ביטוח | B1: מספר מסלול | C1: שם מנפיק | D1: מספר מנפיק | E1: סוג מספר מזהה מנפיק | F1: שם נייר ערך | G1: מספר נייר ערך | H1: סוג מספר נייר ערך | I1: מאפיין עיקרי | J1: ישראל/חו"ל | K1: מדינה לפי חשיפה כלכלית | L1: ענף מסחר | M1: בעל עניין/צד קשור | N1: תאריך רכישה | O1: דירוג | P1: שם מדרג | Q1: דירוג נייר הערך/המנפיק | R1: מטבע פעילות | S1: מח"מ | T1: סוג הצמדה | U1: ריבית עוגן | V1: מועד פדיון | W1: שיעור ריבית | X1: תשואה לפדיון | Y1: נחיתות חוזית | Z1: האם סווג כחוב בעייתי | AA1: סוג גורם משערך | AB1: תלות/אי-תלות המשערך | AC1: שם גורם משערך | AD1: תאריך שערוך אחרון | AE1: תאריך אחרון בו נבחנה בפועל ירידת ערך | AF1: ערך נקוב (יחידות) | AG1: שער חליפין | AH1: שער נייר הערך | AI1: שווי הוגן (באלפי ש"ח) | AJ1: עלות מופחתת (באלפי ש"ח) | AK1: עלות מופחתת (במטבע הפעילות) | AL1: השיטה שיושמה בדוח הכספי | AM1: שיעור מנכסי אפיק ההשקעה | AN1: שיעור מסך נכסי ההשקעה
A2: 158 | B2: 9935 | C2: אדמה פתרונות לחקלאות בע"מ | D2: 520043605 | E2: ח.פ | F2: אדמה נעמ סדרה 2 | G2: IL0011619835 | H2: ISIN | I2: צמוד למט"ח | J2: ישראל | K2: ישראל | L2: כימיה, גומי ופלסטיק | M2: לא | N2: 15/06/2023 | O2: AA- | P2: S&P מעלות | Q2: נייר ערך | R2: USD | S2: 0.04 | T2: צמוד למדד אחר | U2: Libor | V2: 15/11/2024 | W2: 0.063598 | X2: 0.0674 | Y2: החוב לא נחות | Z2: לא | AA2: חברת ציטוט | AB2: אי תלות | AC2: מרווח הוגן | AD2: 31/03/2024 | AF2: 249000 | AG2: 3.681 | AH2: 362.86 | AI2: 923.26 | AL2: שווי הוגן | AM2: 0.42624849 | AN2: 0.00084223775
A3: 158 | B3: 9935 | C3: אורמת טכנולגיות אינק | D3: 5493000TSHHWY24VHM09 | E3: LEI | F3: אורמת נעמ 2 לא סחיר | G3: IL0012004680 | H3: ISIN | I3: צמוד למט"ח | J3: חו"ל | K3: ארה"ב | L3: אנרגיה מתחדשת | M3: לא | N3: 01/11/2023 | O3: AA- | P3: S&P מעלות | Q3: נייר ערך | R3: USD | S3: 0.02 | T3: צמוד למדד אחר | U3: SOFR | V3: 25/09/2028 | W3: 0.063982 | X3: 0.0572 | Y3: החוב לא נחות | Z3: לא | AA3: חברת ציטוט | AB3: אי תלות | AC3: מרווח הוגן | AD3: 31/03/2024 | AF3: 105000 | AG3: 3.681 | AH3: 101.228 | AI3: 391.298 | AL3: שווי הוגן | AM3: 0.18065339 | AN3: 0.00035695869
A4: 158 | B4: 9935 | C4: אלביט מערכות בע"מ | D4: 520043027 | E4: ח.פ | F4: אלביט מערכות נעמ1-ל | G4: IL0011991572 | H4: ISIN | I4: צמוד למט"ח | J4: ישראל | K4: ישראל | L4: ביטחוניות | M4: לא | N4: 31/08/2023 | O4: AA | P4: S&P מעלות | Q4: נייר ערך | R4: USD | S4: 0.05 | T4: צמוד למדד אחר | U4: SOFR | V4: 04/08/2028 | W4: 0.119823 | X4: 0.0562 | Y4: החוב לא נחות | Z4: לא | AA4: חברת ציטוט | AB4: אי תלות | AC4: מרווח הוגן | AD4: 31/03/2024 | AF4: 230000 | AG4: 3.681 | AH4: 380.84 | AI4: 851.456 | AL4: שווי הוגן | AM4: 0.39309812 | AN4: 0.00077673488
A5: 158 | B5: 9936 | C5: אדמה פתרונות לחקלאות בע"מ | D5: 520043605 | E5: ח.פ | F5: אדמה נעמ סדרה 2 | G5: IL0011619835 | H5: ISIN | I5: צמוד למט"ח | J5: ישראל | K5: ישראל | L5: כימיה, גומי ופלסטיק | M5: לא | N5: 15/06/2023 | O5: AA- | P5: S&P מעלות | Q5: נייר ערך | R5: USD | S5: 0.04 | T5: צמוד למדד אחר | U5: Libor | V5: 15/11/2024 | W5: 0.063598 | X5: 0.0674 | Y5: החוב לא נחות | Z5: לא | AA5: חברת ציטוט | AB5: אי תלות | AC5: מרווח הוגן | AD5: 31/03/2024 | AF5: 8000 | AG5: 3.681 | AH5: 362.86 | AI5: 29.663 | AL5: שווי הוגן | AM5: 0.39984916 | AN5: 0.0019486069
A6: 158 | B6: 9936 | C6: אורמת טכנולגיות אינק | D6: 5493000TSHHWY24VHM09 | E6: LEI | F6: אורמת נעמ 2 לא סחיר | G6: IL0012004680 | H6: ISIN | I6: צמוד למט"ח | J6: חו"ל | K6: ארה"ב | L6: אנרגיה מתחדשת | M6: לא | N6: 01/11/2023 | O6: AA- | P6: S&P מעלות | Q6: נייר ערך | R6: USD | S6: 0.02 | T6: צמוד למדד אחר | U6: SOFR | V6: 25/09/2028 | W6: 0.063982 | X6: 0.0572 | Y6: החוב לא נחות | Z6: לא | AA6: חברת ציטוט | AB6: אי תלות | AC6: מרווח הוגן | AD6: 31/03/2024 | AF6: 4000 | AG6: 3.681 | AH6: 101.228 | AI6: 14.907 | AL6: שווי הוגן | AM6: 0.20093681 | AN6: 0.00097923639
A7: 158 | B7: 9936 | C7: אלביט מערכות בע"מ | D7: 520043027 | E7: ח.פ | F7: אלביט מערכות נעמ1-ל | G7: IL0011991572 | H7: ISIN | I7: צמוד למט"ח | J7: ישראל | K7: ישראל | L7: ביטחוניות | M7: לא | N7: 31/08/2023 | O7: AA | P7: S&P מעלות | Q7: נייר ערך | R7: USD | S7: 0.05 | T7: צמוד למדד אחר | U7: SOFR | V7: 04/08/2028 | W7: 0.119823 | X7: 0.0562 | Y7: החוב לא נחות | Z7: לא | AA7: חברת ציטוט | AB7: אי תלות | AC7: מרווח הוגן | AD7: 31/03/2024 | AF7: 8000 | AG7: 3.681 | AH7: 380.84 | AI7: 29.616 | AL7: שווי הוגן | AM7: 0.39921404 | AN7: 0.0019455117

Sheet לא סחיר איגרות חוב
A1: מספר קופה/קרן/ח.פ. עבור חברת ביטוח | B1: מספר מסלול | C1: שם מנפיק | D1: מספר מנפיק | E1: סוג מספר מזהה מנפיק | F1: שם נייר ערך | G1: מספר נייר ערך | H1: סוג מספר נייר ערך | I1: מאפיין עיקרי | J1: ישראל/חו"ל | K1: מדינה לפי חשיפה כלכלית | L1: סטאטוס סחירות | M1: ענף מסחר | N1: בעל עניין/צד קשור | O1: תאריך רכישה | P1: דירוג | Q1: שם מדרג | R1: דירוג נייר הערך/המנפיק | S1: מטבע פעילות | T1: מח"מ | U1: מועד פדיון | V1: תשואה לפדיון | W1: שיעור ריבית | X1: נחיתות חוזית | Y1: האם סווג כחוב בעייתי | Z1: סוג גורם משערך | AA1: תלות/אי-תלות המשערך | AB1: תאריך שערוך אחרון | AC1: תאריך אחרון בו נבחנה בפועל ירידת ערך | AD1: ערך נקוב (יחידות) | AE1: שער חליפין | AF1: שער נייר הערך | AG1: שווי הוגן (באלפי ש"ח) | AH1: עלות מופחתת (באלפי ש"ח) | AI1: עלות מופחתת (במטבע הפעילות) | AJ1: השיטה שיושמה בדוח הכספי | AK1: שיעור מנכסי אפיק ההשקעה | AL1: שיעור מסך נכסי ההשקעה
A2: 158 | B2: 1522 | C2: י.ח.ק להשקעות שותפות מוגבלת | D2: 550016091 | E2: ח.פ | F2: י.ח.ק. אגח ב רמ | G2: IL0011817835 | H2: ISIN | I2: לא צמוד למדד המחירים לצרכן | J2: ישראל | K2: ישראל | L2: אחר | M2: השקעה ואחזקות | N2: לא | O2: 17/11/2021 | P2: A+ | Q2: S&P | R2: נייר ערך | S2: ILS | T2: 2.59 | U2: 31/12/2028 | V2: 0.058 | W2: 0.0286 | X2: החוב לא נחות | Y2: לא | Z2: חברת ציטוט | AB2: 31/03/2024 | AD2: 8571.43 | AE2: 1 | AF2: 92.56 | AG2: 8.018 | AJ2: שווי הוגן | AK2: 0.29172892 | AL2: 0.00079480457
A3: 158 | B3: 1522 | C3: רפאל-רשות לפיתוח אמצעי לחימה בע"מ | D3: 520042185 | E3: ח.פ | F3: רפאל אגח סדרה ה 2020/2026 | G3: IL0011402927 | H3: ISIN | I3: לא צמוד למדד המחירים לצרכן | J3: ישראל | K3: ישראל | L3: אחר | M3: ביטחוניות | N3: לא | O3: 04/05/2021 | P3: Aaa | Q3: מידרוג Moodys | R3: נייר ערך | S3: ILS | T3: 1.43 | U3: 15/03/2026 | V3: 0.0451 | W3: 0.025 | X3: החוב לא נחות | Y3: כן | Z3: חברת ציטוט | AA3: אי תלות | AB3: 31/03/2024 | AD3: 19987.4 | AE3: 1 | AF3: 95.5 | AG3: 19.466 | AJ3: שווי הוגן | AK3: 0.70827108 | AL3: 0.0019296582
A4: 158 | B4: 9935 | C4: אגרקסקו חברה ליצוא חקלאי בע"מ | D4: 510155625 | E4: ח.פ | F4: אגרקסקו אגח א לס 2017 | G4: IL0011091803 | H4: ISIN | I4: צמוד למדד המחירים לצרכן | J4: ישראל | K4: ישראל | L4: אחר | M4: אחר | N4: לא | O4: 31/12/2013 | P4: C | Q4: מידרוג Moodys | R4: נייר ערך | S4: ILS | T4: 0.01 | U4: 30/04/2017 | V4: 0.0001 | W4: 0.099 | X4: החוב לא נחות | Y4: לא | Z4: אחר | AB4: 31/03/2024 | AD4: 875000.04 | AE4: 1 | AF4: 0 | AG4: 0.001 | AJ4: שווי הוגן | AK4: 7.4852816e-08 | AL4: 7.9821297e-10
A5: 158 | B5: 9935 | C5: אורמת טכנולגיות אינק | D5: 5493000TSHHWY24VHM09 | E5: LEI | F5: אורמת אגח 4 רמ | G5: IL0011672123 | H5: ISIN | I5: לא צמוד למדד המחירים לצרכן | J5: ישראל | K5: ארה"ב | L5: אחר | M5: אנרגיה מתחדשת | N5: לא | O5: 01/07/2020 | P5: AA- | Q5: S&P מעלות | R5: נייר ערך | S5: ILS | T5: 3.28 | U5: 20/06/2041 | V5: 0.0594 | W5: 0.0335 | X5: החוב לא נחות | Y5: לא | Z5: חברת ציטוט | AA5: אי תלות | AB5: 31/03/2024 | AD5: 1082090.4 | AE5: 1 | AF5: 91 | AG5: 1006.777 | AJ5: שווי הוגן | AK5: 0.08612581 | AL5: 0.00091842554
A6: 158 | B6: 9935 | C6: אידיבי חברה לאחזקות בע"מ | D6: 520028283 | E6: ח.פ | F6: אי די בי הסדר ח | G6: 7360225 | H6: פנימי | I6: צמוד למדד המחירים לצרכן | J6: ישראל | K6: ישראל | L6: אחר | M6: השקעה ואחזקות | N6: לא | O6: 17/08/2014 | P6: D | Q6: S&P מעלות | R6: מנפיק | S6: ILS | T6: 0.01 | V6: 0.0001 | W6: 0 | X6: החוב לא נחות | Y6: לא | Z6: אחר | AB6: 31/03/2024 | AD6: 75000.16 | AE6: 1 | AF6: 0 | AG6: 0 | AJ6: שווי הוגן | AK6: 6.4159691e-09 | AL6: 6.8418397e-11
A7: 158 | B7: 9935 | C7: אלון חברת הדלק לישראל בע"מ | D7: 520041690 | E7: ח.פ | F7: אלון דלק אגח א` לס (Guy Fund) | G7: IL0011015679 | H7: ISIN | I7: צמוד למדד המחירים לצרכן | J7: ישראל | K7: ישראל | L7: אחר | M7: חיפושי נפט וגז | N7: לא | O7: 30/08/2018 | P7: N/R | Q7: אחר | R7: נייר ערך | S7: ILS | T7: 0.25 | U7: 31/08/2023 | V7: 0.00062 | W7: 0.0535 | X7: החוב לא נחות | Y7: לא | Z7: אחר | AB7: 31/03/2024 | AD7: 1184072.3 | AE7: 1 | AF7: 83.11 | AG7: 984.083 | AJ7: שווי הוגן | AK7: 0.084184393 | AL7: 0.00089772272
A8: 158 | B8: 9935 | C8: אלון חברת הדלק לישראל בע"מ | D8: 520041690 | E8: ח.פ | F8: אלון דלק אגח א` לס (Guy Fund)- נייר הפחתה | G8: IL0011015679 | H8: ISIN | I8: צמוד למדד המחירים לצרכן | J8: ישראל | L8: אחר | M8: חיפושי נפט וגז | N8: לא | O8: 20/03/2024 | P8: N/R | Q8: אחר | R8: נייר ערך | S8: ILS | T8: 0 | U8: 31/08/2023 | V8: 0 | W8: 0.0535 | X8: החוב לא נחות | Y8: לא | Z8: אחר | AB8: 31/03/2024 | AD8: -1184072.3 | AE8: 1 | AF8: 83.11 | AG8: -984.083 | AJ8: שווי הוגן | AK8: -0.084184393 | AL8: -0.00089772272
A9: 158 | B9: 9935 | C9: אלון חברת הדלק לישראל בע"מ | D9: 520041690 | E9: ח.פ | F9: אלון דלק אגח א` לס (Guy Fund)- ציטוט פרטני | G9: IL0011015679 | H9: ISIN | I9: צמוד למדד המחירים לצרכן | J9: ישראל | L9: אחר | M9: חיפושי נפט וגז | N9: לא | O9: 20/03/2024 | P9: N/R | Q9: אחר | R9: נייר ערך | S9: ILS | T9: 0 | U9: 31/08/2023 | V9: 0 | W9: 0.0535 | X9: החוב לא נחות | Y9: לא | Z9: אחר | AB9: 31/03/2024 | AD9: 1184072.3 | AE9: 1 | AF9: 15.43 | AG9: 182.702 | AJ9: שווי הוגן | AK9: 0.015629469 | AL9: 0.00016666901
A10: 158 | B10: 9935 | C10: אליהו הנפקות בע"מ | D10: 515703528 | E10: ח.פ | F10: אליהו הנפ אגח א לס | G10: IL0011420093 | H10: ISIN | I10: לא צמוד למדד המחירים לצרכן | J10: ישראל | K10: ישראל | L10: אחר | M10: ביטוח | N10: לא | O10: 19/09/2017 | P10: A3 | Q10: מידרוג Moodys | R10: נייר ערך | S10: ILS | T10: 1.14 | U10: 18/09/2025 | V10: 0.0606 | W10: 0.0384 | X10: החוב לא נחות | Y10: לא | Z10: חברת ציטוט | AA10: אי תלות | AB10: 31/03/2024 | AD10: 829053.03 | AE10: 1 | AF10: 99.96 | AG10: 815.291 | AJ10: שווי הוגן | AK10: 0.069744921 | AL10: 0.00074374356
A11: 158 | B11: 9935 | C11: ביטוח ישיר - השקעות פיננסיות בע"מ | D11: 520044439 | E11: ח.פ | F11: ביטוח ישיר אגח יא רמ | G11: IL0011388258 | H11: ISIN | I11: לא צמוד למדד המחירים לצרכן | J11: ישראל | K11: ישראל | L11: אחר | M11: השקעה ואחזקות | N11: לא | O11: 28/07/2016 | P11: A | Q11: S&P | R11: נייר ערך | S11: ILS | T11: 2.53 | U11: 30/06/2028 | V11: 0.0602 | W11: 0.046 | X11: החוב לא נחות | Y11: לא | Z11: חברת ציטוט | AA11: אי תלות | AB11: 31/03/2024 | AD11: 540000.03 | AE11: 1 | AF11: 98.35 | AG11: 528.444 | AJ11: שווי הוגן | AK11: 0.045206311 | AL11: 0.00048206955
A12: 158 | B12: 9935 | C12: וי.אי.די. התפלת מי אשקלון | D12: 513102384 | E12: ח.פ | F12: וי.אי.די. אג"ח מאוחד 0706 | G12: IL0010979974 | H12: ISIN | I12: צמוד למדד המחירים לצרכן | J12: ישראל | K12: ישראל | L12: אחר | M12: שירותים פיננסיים | N12: לא | O12: 31/12/2013 | P12: AA | Q12: S&P מעלות | R12: נייר ערך | S12: ILS | T12: 0.79 | U12: 22/10/2025 | V12: 0.0203 | W12: 0.0775 | X12: החוב לא נחות | Y12: לא | Z12: חברת ציטוט | AA12: אי תלות | AB12: 31/03/2024 | AD12: 87214.1 | AE12: 1 | AF12: 134.861 | AG12: 127.673 | AJ12: שווי הוגן | AK12: 0.0109219 | AL12: 0.00011646859
A13: 158 | B13: 9935 | C13: מת"ם - מרכז תעשיות מדע חיפה בע"מ | D13: 510687403 | E13: ח.פ | F13: מתם מרכז תעשיות מדע חיפה אגח א ר.מ | G13: IL0011389991 | H13: ISIN | I13: לא צמוד למדד המחירים לצרכן | J13: ישראל | K13: ישראל | L13: אחר | M13: נדל"ן מניב בישראל | N13: לא | O13: 24/08/2016 | P13: Aa2 | Q13: מידרוג Moodys | R13: נייר ערך | S13: ILS | T13: 2.01 | U13: 20/07/2040 | V13: 0.0481 | W13: 0.031 | X13: החוב לא נחות | Y13: לא | Z13: חברת ציטוט | AA13: אי תלות | AB13: 31/03/2024 | AD13: 1040000.2 | AE13: 1 | AF13: 93.5 | AG13: 1006.72 | AJ13: שווי הוגן | AK13: 0.086120958 | AL13: 0.0009183738
A14: 158 | B14: 9935 | C14: נתיבי הגז הטבעי לישראל בע"מ | D14: 513436394 | E14: ח.פ | F14: נתיבי גז אג"ח א - רמ | G14: IL0011030843 | H14: ISIN | I14: צמוד למדד המחירים לצרכן | J14: ישראל | K14: ישראל | L14: אחר | M14: שירותים | N14: לא | O14: 31/12/2013 | P14: Aa1 | Q14: S&P מעלות | R14: נייר ערך | S14: ILS | T14: 1.4 | U14: 29/12/2026 | V14: 0.0209 | W14: 0.056 | X14: החוב לא נחות | Y14: לא | Z14: חברת ציטוט | AA14: אי תלות | AB14: 31/03/2024 | AD14: 661207.02 | AE14: 1 | AF14: 142.19 | AG14: 949.626 | AJ14: שווי הוגן | AK14: 0.081236733 | AL14: 0.00086628957
A15: 158 | B15: 9935 | C15: קאר אנד גו 4.95% 2009 | D15: 1088210 | E15: פנימי | F15: קאר אנד גו 4.95% 2009 | G15: 1088210 | H15: פנימי | I15: צמוד למדד המחירים לצרכן | J15: ישראל | K15: ישראל | L15: אחר | M15: שירותים פיננסיים | N15: לא | O15: 31/12/2013 | P15: D | Q15: S&P מעלות | R15: נייר ערך | S15: ILS | T15: 0.01 | U15: 01/11/2011 | V15: 0.0495 | W15: 0.0495 | X15: החוב נחות | Y15: כן | Z15: אחר | AA15: אי-תלות | AB15: 31/03/2024 | AD15: 118452 | AE15: 1 | AF15: 0 | AG15: 0 | AJ15: שווי הוגן | AK15: 1.0133103e-08 | AL15: 1.0805705e-10
A16: 158 | B16: 9935 | C16: אמפל-אמריקן ישראל קורפוריישן | D16: 130435685 | E16: מספר תאגיד או שותפות בחו"ל | F16: אמפל אמריקן אגח א | G16: IL0011008336 | H16: ISIN | I16: צמוד למדד המחירים לצרכן | J16: ישראל | K16: ישראל | L16: אחר | M16: השקעה ואחזקות | N16: לא | O16: 30/03/2014 | P16: N/R | Q16: אחר | R16: נייר ערך | S16: ILS | T16: 8.67 | U16: 20/11/2020 | V16: 0.2085 | W16: 0.0575 | X16: החוב לא נחות | Y16: לא | Z16: אחר | AB16: 20/05/2021 | AD16: 94999.08 | AE16: 1 | AF16: 0 | AG16: 0 | AJ16: שווי הוגן | AK16: 8.1267981e-11 | AL16: 8.6662279e-13
A17: 158 | B17: 9935 | C17: ביטוח ישיר - השקעות פיננסיות בע"מ | D17: 520044439 | E17: ח.פ | F17: ביטוח ישיר אגח יא רמ | G17: IL0011388258 | H17: ISIN | I17: לא צמוד למדד המחירים לצרכן | J17: ישראל | K17: ישראל | L17: אחר | M17: השקעה ואחזקות | N17: לא | O17: 28/07/2016 | P17: A | Q17: S&P | R17: נייר ערך | S17: ILS | T17: 2.53 | U17: 30/06/2028 | V17: 0.0602 | W17: 0.046 | X17: החוב לא נחות | Y17: לא | Z17: חברת ציטוט | AA17: אי תלות | AB17: 31/03/2024 | AD17: 540000.03 | AE17: 1 | AF17: 98.35 | AG17: 528.444 | AJ17: שווי הוגן | AK17: 0.045206311 | AL17: 0.00048206955
A18: 158 | B18: 9935 | C18: י.ח.ק להשקעות שותפות מוגבלת | D18: 550016091 | E18: ח.פ | F18: י.ח.ק. אגח ב רמ | G18: IL0011817835 | H18: ISIN | I18: לא צמוד למדד המחירים לצרכן | J18: ישראל | K18: ישראל | L18: אחר | M18: השקעה ואחזקות | N18: לא | O18: 17/11/2021 | P18: A+ | Q18: S&P | R18: נייר ערך | S18: ILS | T18: 2.59 | U18: 31/12/2028 | V18: 0.058 | W18: 0.0286 | X18: החוב לא נחות | Y18: לא | Z18: חברת ציטוט | AB18: 31/03/2024 | AD18: 402142.9 | AE18: 1 | AF18: 92.56 | AG18: 376.164 | AJ18: שווי הוגן | AK18: 0.032179393 | AL18: 0.00034315353
A19: 158 | B19: 9935 | C19: כלל תעשיות בע"מ | D19: 520021874 | E19: ח.פ | F19: כלל תעש אגח טז-רמ | G19: IL0060802381 | H19: ISIN | I19: לא צמוד למדד המחירים לצרכן | J19: ישראל | K19: ישראל | L19: אחר | M19: השקעה ואחזקות | N19: לא | O19: 27/10/2021 | P19: A | Q19: S&P | R19: נייר ערך | S19: ILS | T19: 2.42 | U19: 30/06/2027 | V19: 0.0603 | W19: 0.0447 | X19: החוב לא נחות | Y19: לא | Z19: חברת ציטוט | AA19: קיימת תלות | AB19: 31/03/2024 | AD19: 662600.48 | AE19: 1 | AF19: 98.5 | AG19: 647.096 | AJ19: שווי הוגן | AK19: 0.055356489 | AL19: 0.00059030868
A20: 158 | B20: 9935 | C20: לידר החזקות והשקעות בע"מ | D20: 520037664 | E20: ח.פ | F20: לידר אגח ח - רמ | G20: IL0031803617 | H20: ISIN | I20: לא צמוד למדד המחירים לצרכן | J20: ישראל | K20: ישראל | L20: אחר | M20: השקעה ואחזקות | N20: לא | O20: 01/03/2021 | P20: A1 | Q20: מידרוג Moodys | R20: נייר ערך | S20: ILS | T20: 2.29 | U20: 15/02/2028 | V20: 0.0508 | W20: 0.021 | X20: החוב לא נחות | Y20: לא | Z20: אחר | AA20: אי תלות | AB20: 31/03/2024 | AD20: 151428.69 | AE20: 1 | AF20: 92 | AG20: 142.04 | AJ20: שווי הוגן | AK20: 0.012150974 | AL20: 0.00012957515
A21: 158 | B21: 9935 | C21: מפעלי פלדה מאוחדים בע"מ | D21: 520022492 | E21: ח.פ | F21: מ.פלדה אג-1 מפ1/00 | G21: 3980042 | H21: פנימי | I21: לא צמוד למדד המחירים לצרכן | J21: ישראל | K21: ישראל | L21: אחר | M21: מתכת ומוצרי בניה | N21: לא | O21: 31/12/2013 | P21: N/R | Q21: אחר | R21: מנפיק | S21: ILS | T21: 0 | U21: 31/01/2001 | V21: 0 | W21: 0 | X21: החוב נחות | Y21: כן | Z21: אחר | AA21: אי-תלות | AB21: 10/12/2018 | AD21: 1071.41 | AE21: 1 | AF21: 0 | AG21: 0 | AJ21: שווי הוגן | AK21: 9.1654917e-13 | AL21: 9.7738665e-15
A22: 158 | B22: 9935 | C22: מפעלי פלדה מאוחדים בע"מ | D22: 520022492 | E22: ח.פ | F22: מפעלי פלדה אג1 | G22: IL0039800185 | H22: ISIN | I22: צמוד למדד המחירים לצרכן | J22: ישראל | K22: ישראל | L22: אחר | M22: מתכת ומוצרי בניה | N22: לא | O22: 31/12/2013 | P22: N/R | Q22: אחר | R22: מנפיק | S22: ILS | T22: 0 | U22: 31/01/2001 | V22: 0 | W22: 0 | X22: החוב נחות | Y22: כן | Z22: אחר | AA22: אי-תלות | AB22: 10/12/2018 | AD22: 676.32 | AE22: 1 | AF22: 0 | AG22: 0 | AJ22: שווי הוגן | AK22: 5.7856519e-13 | AL22: 6.1696842e-15
A23: 158 | B23: 9935 | C23: מת"ם - מרכז תעשיות מדע חיפה בע"מ | D23: 510687403 | E23: ח.פ | F23: מתם מרכז תעשיות מדע חיפה אגח א ר.מ | G23: IL0011389991 | H23: ISIN | I23: לא צמוד למדד המחירים לצרכן | J23: ישראל | K23: ישראל | L23: אחר | M23: נדל"ן מניב בישראל | N23: לא | O23: 24/08/2016 | P23: Aa2 | Q23: מידרוג Moodys | R23: נייר ערך | S23: ILS | T23: 2.01 | U23: 20/07/2040 | V23: 0.0481 | W23: 0.031 | X23: החוב לא נחות | Y23: לא | Z23: חברת ציטוט | AA23: אי תלות | AB23: 31/03/2024 | AD23: 599954.39 | AE23: 1 | AF23: 93.5 | AG23: 580.756 | AJ23: שווי הוגן | AK23: 0.049681382 | AL23: 0.00052979066
A24: 158 | B24: 9935 | C24: עוגן-אג"ח חברתית 2 בע"מ | D24: 516556545 | E24: ח.פ | F24: עוגן חברתית 2 אגחא-רמ | G24: IL0011968315 | H24: ISIN | I24: לא צמוד למדד המחירים לצרכן | J24: ישראל | K24: ישראל | L24: אחר | M24: שירותים פיננסיים | N24: לא | O24: 19/06/2023 | P24: Aa3 | Q24: מידרוג Moodys | R24: נייר ערך | S24: ILS | T24: 1.06 | U24: 15/03/2026 | V24: 0.067 | W24: 0.065 | X24: החוב לא נחות | Y24: לא | Z24: אחר | AB24: 31/03/2024 | AD24: 369449.62 | AE24: 1 | AF24: 100 | AG24: 368.674 | AJ24: שווי הוגן | AK24: 0.031538593 | AL24: 0.0003363202
A25: 158 | B25: 9935 | C25: רפאל-רשות לפיתוח אמצעי לחימה בע"מ | D25: 520042185 | E25: ח.פ | F25: רפאל אגח ג | G25: IL0011402760 | H25: ISIN | I25: צמוד למדד המחירים לצרכן | J25: ישראל | K25: ישראל | L25: אחר | M25: ביטחוניות | N25: לא | O25: 04/05/2021 | P25: Aaa | Q25: מידרוג Moodys | R25: נייר ערך | S25: ILS | T25: 5.09 | U25: 20/12/2037 | V25: 0.0216 | W25: 0.0214 | X25: החוב לא נחות | Y25: לא | Z25: חברת ציטוט | AA25: אי תלות | AB25: 31/03/2024 | AD25: 1058666.4 | AE25: 1 | AF25: 118.3 | AG25: 1199.998 | AJ25: שווי הוגן | AK25: 0.10265514 | AL25: 0.0010946905
A26: 158 | B26: 9935 | C26: רפאל-רשות לפיתוח אמצעי לחימה בע"מ | D26: 520042185 | E26: ח.פ | F26: רפאל אגח סדרה ה 2020/2026 | G26: IL0011402927 | H26: ISIN | I26: לא צמוד למדד המחירים לצרכן | J26: ישראל | K26: ישראל | L26: אחר | M26: ביטחוניות | N26: לא | O26: 04/05/2021 | P26: Aaa | Q26: מידרוג Moodys | R26: נייר ערך | S26: ILS | T26: 1.43 | U26: 15/03/2026 | V26: 0.0451 | W26: 0.025 | X26: החוב לא נחות | Y26: כן | Z26: חברת ציטוט | AA26: אי תלות | AB26: 31/03/2024 | AD26: 1139281.7 | AE26: 1 | AF26: 95.5 | AG26: 1109.546 | AJ26: שווי הוגן | AK26: 0.094917341 | AL26: 0.0010121764
A27: 158 | B27: 9935 | C27: רפאל-רשות לפיתוח אמצעי לחימה בע"מ | D27: 520042185 | E27: ח.פ | F27: רפאל סד' ד 2020/2034 | G27: IL0011402844 | H27: ISIN | I27: לא צמוד למדד המחירים לצרכן | J27: ישראל | K27: ישראל | L27: אחר | M27: ביטחוניות | N27: לא | O27: 04/05/2021 | P27: Aaa | Q27: מידרוג Moodys | R27: נייר ערך | S27: ILS | T27: 4.72 | U27: 20/09/2026 | V27: 0.0501 | W27: 0.0374 | X27: החוב לא נחות | Y27: לא | Z27: חברת ציטוט | AA27: אי תלות | AB27: 31/03/2024 | AD27: 2239940 | AE27: 1 | AF27: 96 | AG27: 2119.655 | AJ27: שווי הוגן | AK27: 0.18132818 | AL27: 0.0019336414
A28: 158 | B28: 9936 | C28: אורמת טכנולגיות אינק | D28: 5493000TSHHWY24VHM09 | E28: LEI | F28: אורמת אגח 4 רמ | G28: IL0011672123 | H28: ISIN | I28: לא צמוד למדד המחירים לצרכן | J28: ישראל | K28: ארה"ב | L28: אחר | M28: אנרגיה מתחדשת | N28: לא | O28: 01/07/2020 | P28: AA- | Q28: S&P מעלות | R28: נייר ערך | S28: ILS | T28: 3.28 | U28: 20/06/2041 | V28: 0.0594 | W28: 0.0335 | X28: החוב לא נחות | Y28: לא | Z28: חברת ציטוט | AA28: אי תלות | AB28: 31/03/2024 | AD28: 17532.8 | AE28: 1 | AF28: 91 | AG28: 16.313 | AJ28: שווי הוגן | AK28: 0.12425448 | AL28: 0.0010715948
A29: 158 | B29: 9936 | C29: י.ח.ק להשקעות שותפות מוגבלת | D29: 550016091 | E29: ח.פ | F29: י.ח.ק. אגח ב רמ | G29: IL0011817835 | H29: ISIN | I29: לא צמוד למדד המחירים לצרכן | J29: ישראל | K29: ישראל | L29: אחר | M29: השקעה ואחזקות | N29: לא | O29: 17/11/2021 | P29: A+ | Q29: S&P | R29: נייר ערך | S29: ILS | T29: 2.59 | U29: 31/12/2028 | V29: 0.058 | W29: 0.0286 | X29: החוב לא נחות | Y29: לא | Z29: חברת ציטוט | AB29: 31/03/2024 | AD29: 8571.43 | AE29: 1 | AF29: 92.56 | AG29: 8.018 | AJ29: שווי הוגן | AK29: 0.061071941 | AL29: 0.00052669627
A30: 158 | B30: 9936 | C30: כלל תעשיות בע"מ | D30: 520021874 | E30: ח.פ | F30: כלל תעש אגח טז-רמ | G30: IL0060802381 | H30: ISIN | I30: לא צמוד למדד המחירים לצרכן | J30: ישראל | K30: ישראל | L30: אחר | M30: השקעה ואחזקות | N30: לא | O30: 27/10/2021 | P30: A | Q30: S&P | R30: נייר ערך | S30: ILS | T30: 2.42 | U30: 30/06/2027 | V30: 0.0603 | W30: 0.0447 | X30: החוב לא נחות | Y30: לא | Z30: חברת ציטוט | AA30: קיימת תלות | AB30: 31/03/2024 | AD30: 13804.79 | AE30: 1 | AF30: 98.5 | AG30: 13.482 | AJ30: שווי הוגן | AK30: 0.10269223 | AL30: 0.00088563776
A31: 158 | B31: 9936 | C31: לידר החזקות והשקעות בע"מ | D31: 520037664 | E31: ח.פ | F31: לידר אגח ח - רמ | G31: IL0031803617 | H31: ISIN | I31: לא צמוד למדד המחירים לצרכן | J31: ישראל | K31: ישראל | L31: אחר | M31: השקעה ואחזקות | N31: לא | O31: 01/03/2021 | P31: A1 | Q31: מידרוג Moodys | R31: נייר ערך | S31: ILS | T31: 2.29 | U31: 15/02/2028 | V31: 0.0508 | W31: 0.021 | X31: החוב לא נחות | Y31: לא | Z31: אחר | AA31: אי תלות | AB31: 31/03/2024 | AD31: 4571.43 | AE31: 1 | AF31: 92 | AG31: 4.288 | AJ31: שווי הוגן | AK31: 0.032662242 | AL31: 0.00028168551
A32: 158 | B32: 9936 | C32: מימון ישיר סידרה 4 רמ | D32: 515631026 | E32: ח.פ | F32: מימון ישיר אגח 4 רמ | G32: IL0011426371 | H32: ISIN | I32: צמוד למדד המחירים לצרכן | J32: ישראל | K32: ישראל | L32: אחר | M32: אשראי חוץ בנקאי | N32: לא | O32: 20/12/2017 | P32: Aa2 | Q32: מידרוג Moodys | R32: נייר ערך | S32: ILS | T32: 0.78 | U32: 12/03/2026 | V32: 0.01585 | W32: 0.019001 | X32: החוב לא נחות | Y32: לא | Z32: אחר | AB32: 31/03/2024 | AD32: 0.22 | AE32: 1 | AF32: 109.7 | AG32: 0 | AJ32: שווי הוגן | AK32: 1.8900981e-06 | AL32: 1.6300573e-08
A33: 158 | B33: 9936 | C33: עוגן-אג"ח חברתית 2 בע"מ | D33: 516556545 | E33: ח.פ | F33: עוגן חברתית 2 אגחא-רמ | G33: IL0011968315 | H33: ISIN | I33: לא צמוד למדד המחירים לצרכן | J33: ישראל | K33: ישראל | L33: אחר | M33: שירותים פיננסיים | N33: לא | O33: 19/06/2023 | P33: Aa3 | Q33: מידרוג Moodys | R33: נייר ערך | S33: ILS | T33: 1.06 | U33: 15/03/2026 | V33: 0.067 | W33: 0.065 | X33: החוב לא נחות | Y33: לא | Z33: אחר | AB33: 31/03/2024 | AD33: 11172.87 | AE33: 1 | AF33: 100 | AG33: 11.149 | AJ33: שווי הוגן | AK33: 0.084926426 | AL33: 0.00073242198
A34: 158 | B34: 9936 | C34: רפאל-רשות לפיתוח אמצעי לחימה בע"מ | D34: 520042185 | E34: ח.פ | F34: רפאל אגח ג | G34: IL0011402760 | H34: ISIN | I34: צמוד למדד המחירים לצרכן | J34: ישראל | K34: ישראל | L34: אחר | M34: ביטחוניות | N34: לא | O34: 04/05/2021 | P34: Aaa | Q34: מידרוג Moodys | R34: נייר ערך | S34: ILS | T34: 5.09 | U34: 20/12/2037 | V34: 0.0216 | W34: 0.0214 | X34: החוב לא נחות | Y34: לא | Z34: חברת ציטוט | AA34: אי תלות | AB34: 31/03/2024 | AD34: 18862.65 | AE34: 1 | AF34: 118.3 | AG34: 21.381 | AJ34: שווי הוגן | AK34: 0.16286033 | AL34: 0.0014045391
A35: 158 | B35: 9936 | C35: רפאל-רשות לפיתוח אמצעי לחימה בע"מ | D35: 520042185 | E35: ח.פ | F35: רפאל אגח סדרה ה 2020/2026 | G35: IL0011402927 | H35: ISIN | I35: לא צמוד למדד המחירים לצרכן | J35: ישראל | K35: ישראל | L35: אחר | M35: ביטחוניות | N35: לא | O35: 04/05/2021 | P35: Aaa | Q35: מידרוג Moodys | R35: נייר ערך | S35: ILS | T35: 1.43 | U35: 15/03/2026 | V35: 0.0451 | W35: 0.025 | X35: החוב לא נחות | Y35: כן | Z35: חברת ציטוט | AA35: אי תלות | AB35: 31/03/2024 | AD35: 19987.4 | AE35: 1 | AF35: 95.5 | AG35: 19.466 | AJ35: שווי הוגן | AK35: 0.14827289 | AL35: 0.0012787342
A36: 158 | B36: 9936 | C36: רפאל-רשות לפיתוח אמצעי לחימה בע"מ | D36: 520042185 | E36: ח.פ | F36: רפאל סד' ד 2020/2034 | G36: IL0011402844 | H36: ISIN | I36: לא צמוד למדד המחירים לצרכן | J36: ישראל | K36: ישראל | L36: אחר | M36: ביטחוניות | N36: לא | O36: 04/05/2021 | P36: Aaa | Q36: מידרוג Moodys | R36: נייר ערך | S36: ILS | T36: 4.72 | U36: 20/09/2026 | V36: 0.0501 | W36: 0.0374 | X36: החוב לא נחות | Y36: לא | Z36: חברת ציטוט | AA36: אי תלות | AB36: 31/03/2024 | AD36: 39297.2 | AE36: 1 | AF36: 96 | AG36: 37.187 | AJ36: שווי הוגן | AK36: 0.28325757 | AL36: 0.0024428683

Sheet לא סחיר מניות מבכ ויהש
A1: מספר קופה/קרן/ח.פ. עבור חברת ביטוח | B1: מספר מסלול | C1: שם מנפיק | D1: מספר מנפיק | E1: סוג מספר מזהה מנפיק | F1: שם נייר ערך | G1: מספר נייר ערך | H1: סוג מספר נייר ערך | I1: מאפיין עיקרי | J1: ישראל/חו"ל | K1: מדינה לפי חשיפה כלכלית | L1: סטאטוס סחירות | M1: ענף מסחר | N1: בעל עניין/צד קשור | O1: תאריך רכישה | P1: מטבע פעילות | Q1: סוג גורם משערך | R1: תלות/אי-תלות המשערך | S1: תאריך שערוך אחרון | T1: תאריך אחרון בו נבחנה בפועל ירידת ערך | U1: ערך נקוב (יחידות) | V1: שער חליפין | W1: שער נייר הערך | X1: שווי הוגן (באלפי ש"ח) | Y1: שיעור מנכסי אפיק ההשקעה | Z1: שיעור מסך נכסי ההשקעה
A2: 158 | B2: 1522 | C2: וויו (veev) גרופ | D2: 832652993 | E2: פנימי | F2: C וויו גרופ | G2: US9224741010 | H2: ISIN | I2: מניות לא סחירות | J2: ישראל | K2: ישראל | L2: אחר | M2: השקעות בהיי-טק | N2: לא | O2: 08/03/2021 | P2: ILS | Q2: אחר | R2: אי-תלות | S2: 28/11/2023 | U2: 25848 | V2: 1 | W2: 0 | X2: 0 | Y2: 9.3626731e-09 | Z2: 2.5623394e-11
A3: 158 | B3: 1522 | C3: PROSPECT CAPITAL CORP | D3: 549300FSD8T39P5Q0O47 | E3: LEI | F3: מניות בכורה Prospect 5.5% 1025 | G3: US74348T5083 | H3: ISIN | I3: מניות לא סחירות | J3: חו"ל | K3: ארה"ב | L3: אחר | M3: שירותים פיננסיים | N3: לא | O3: 27/04/2021 | P3: USD | Q3: אחר | S3: 27/04/2021 | U3: 300 | V3: 3.681 | W3: 25 | X3: 27.608 | Y3: 0.99999999 | Z3: 0.0027367605
A4: 158 | B4: 9935 | C4: ג'נריישן ניהול בע"מ | D4: 515785012 | E4: ח.פ | F4: ג'נריישן ניהול בע"מ (מחר השתלמות) | G4: 560930 | H4: פנימי | I4: מניות לא סחירות | J4: ישראל | K4: ישראל | L4: אחר | M4: נדל"ן מניב בישראל | N4: לא | O4: 18/04/2021 | P4: ILS | Q4: אחר | S4: 29/11/2023 | U4: 329 | V4: 1 | W4: 170152.62 | X4: 559.802 | Y4: 0.042508399 | Z4: 0.00051067577
A5: 158 | B5: 9935 | C5: לוסיקס בע"מ | D5: 515374742 | E5: ח.פ | F5: Lusix | G5: 62020193 | H5: פנימי | I5: מניות לא סחירות | J5: ישראל | K5: ארה"ב | L5: אחר | M5: Water Utilities | N5: לא | O5: 10/02/2022 | P5: USD | Q5: אחר | S5: 11/10/2023 | U5: 127813 | V5: 3.681 | W5: 273.836 | X5: 1288.342 | Y5: 0.097829814 | Z5: 0.0011752811
A6: 158 | B6: 9935 | C6: UVEYE LTD | D6: 514234202 | E6: ח.פ | F6: UVEYE LTD | G6: 62018262 | H6: פנימי | I6: מניות לא סחירות | J6: ישראל | K6: ישראל | L6: אחר | M6: השקעות בהיי-טק | N6: לא | O6: 18/05/2021 | P6: USD | Q6: אחר | S6: 26/12/2022 | U6: 139876 | V6: 3.681 | W6: 830.053 | X6: 4273.805 | Y6: 0.32453006 | Z6: 0.0038987505
A7: 158 | B7: 9935 | C7: וויו (veev) גרופ | D7: 832652993 | E7: פנימי | F7: C וויו גרופ | G7: US9224741010 | H7: ISIN | I7: מניות לא סחירות | J7: ישראל | K7: ישראל | L7: אחר | M7: השקעות בהיי-טק | N7: לא | O7: 08/03/2021 | P7: ILS | Q7: אחר | R7: אי-תלות | S7: 28/11/2023 | U7: 840064 | V7: 1 | W7: 0 | X7: 0 | Y7: 6.3789995e-10 | Z7: 7.663428e-12
A8: 158 | B8: 9935 | C8: wefox | D8: 28503 | E8: פנימי | F8: TARGET GLOBAL-NICKEL (WEFOX) | G8: 62018396 | H8: פנימי | I8: מניות לא סחירות | J8: חו"ל | K8: גרמניה | L8: אחר | M8: Technology Hardware, Storage & Peripherals | N8: לא | O8: 03/07/2022 | P8: EUR | Q8: אחר | S8: 31/03/2024 | U8: 361800 | V8: 3.979 | W8: 150.571 | X8: 2167.682 | Y8: 0.16460227 | Z8: 0.0019774537
A9: 158 | B9: 9935 | C9: Verbit Inc | D9: 28460 | E9: פנימי | F9: Verbit Inc | G9: 0 | H9: FIGI | I9: מניות לא סחירות | J9: חו"ל | K9: ארה"ב | L9: אחר | M9: Technology Hardware, Storage & Peripherals | N9: לא | O9: 18/05/2021 | P9: USD | Q9: אחר | S9: 20/03/2023 | U9: 4300 | V9: 3.681 | W9: 20229.37 | X9: 3201.965 | Y9: 0.24314023 | Z9: 0.0029209716
A10: 158 | B10: 9935 | C10: PROSPECT CAPITAL CORP | D10: 549300FSD8T39P5Q0O47 | E10: LEI | F10: מניות בכורה Prospect 5.5% 1025 | G10: US74348T5083 | H10: ISIN | I10: מניות לא סחירות | J10: חו"ל | K10: ארה"ב | L10: אחר | M10: שירותים פיננסיים | N10: לא | O10: 27/04/2021 | P10: USD | Q10: אחר | S10: 27/04/2021 | U10: 18230 | V10: 3.681 | W10: 25 | X10: 1677.616 | Y10: 0.12738922 | Z10: 0.0015303938
A11: 158 | B11: 9936 | C11: וויו (veev) גרופ | D11: 832652993 | E11: פנימי | F11: C וויו גרופ | G11: US9224741010 | H11: ISIN | I11: מניות לא סחירות | J11: ישראל | K11: ישראל | L11: אחר | M11: השקעות בהיי-טק | N11: לא | O11: 08/03/2021 | P11: ILS | Q11: אחר | R11: אי-תלות | S11: 28/11/2023 | U11: 16963 | V11: 1 | W11: 0 | X11: 0 | Y11: 5.1202873e-09 | Z11: 1.114326e-11
A12: 158 | B12: 9936 | C12: PROSPECT CAPITAL CORP | D12: 549300FSD8T39P5Q0O47 | E12: LEI | F12: מניות בכורה Prospect 5.5% 1025 | G12: US74348T5083 | H12: ISIN | I12: מניות לא סחירות | J12: חו"ל | K12: ארה"ב | L12: אחר | M12: שירותים פיננסיים | N12: לא | O12: 27/04/2021 | P12: USD | Q12: אחר | S12: 27/04/2021 | U12: 360 | V12: 3.681 | W12: 25 | X12: 33.129 | Y12: 0.99999999 | Z12: 0.0021762958

Sheet קרנות השקעה
A1: מספר קופה/קרן/ח.פ. עבור חברת ביטוח | B1: מספר מסלול | C1: שם שותף כללי קרן השקעות | D1: מספר מזהה שותף כללי קרן השקעות | E1: סוג מספר מזהה שותף כללי קרן השקעות | F1: שם קרן השקעה | G1: מספר מזהה קרן השקעה | H1: סוג מספר מזהה קרן השקעות | I1: מאפיין עיקרי | J1: אסטרטגיית קרן ההשקעה | K1: ישראל/חו"ל | L1: מדינת התאגדות קרן השקעה | M1: מיקום משרד השותף הכללי | N1: מדינה לפי חשיפה כלכלית | O1: בעל עניין/צד קשור | P1: תאריך רכישה | Q1: מטבע פעילות | R1: סוג גורם משערך | S1: תלות/אי-תלות המשערך | T1: תאריך שערוך אחרון | U1: שער חליפין | V1: NAV (במטבע הדיווח של קרן ההשקעה) | W1: שווי הוגן (באלפי ש"ח) | X1: שיעור החזקה בקרן השקעה | Y1: שיעור מנכסי אפיק ההשקעה | Z1: שיעור מסך נכסי ההשקעה
A2: 158 | B2: 9935 | C2: HAREL FINANCE ALTERNATIVE HAMA | E2: אחר | F2: Harel Alternative Cedit Co-invest | G2: 50007954 | H2: פנימי | I2: פרייבט אקוויטי | J2: Other | K2: ישראל | N2: ישראל | O2: לא | P2: 24/04/2023 | Q2: ILS | R2: אחר | T2: 31/03/2024 | U2: 1 | V2: 2026.895 | W2: 2026.895 | Y2: 0.0095269999 | Z2: 0.0018490219
A3: 158 | B3: 9935 | C3: Klirmark | D3: CO-101523 | E3: מספר תאגיד או שותפות בחו"ל | F3: Klirmark Fund IV | G3: 50007921 | H3: פנימי | I3: פרייבט אקוויטי | J3: Special Situations Debt | K3: ישראל | L3: איי קיימן | M3: כתובת: ז'בוטינסקי 2 , רמת גן , ישראל | N3: ישראל | O3: לא | P3: 19/04/2023 | Q3: ILS | R3: דיווח מנהל הקרן | S3: קיימת תלות | T3: 28/03/2024 | U3: 1 | V3: 977.859 | W3: 977.859 | Y3: 0.0045962225 | Z3: 0.00089204537
A4: 158 | B4: 9935 | C4: SPHERA | D4: 540305869 | E4: ח.פ | F4: קרן ספרה פארקינג | G4: 50007145 | H4: פנימי | I4: פרייבט אקוויטי | J4: Other | K4: ישראל | O4: לא | P4: 06/12/2021 | Q4: ILS | R4: אחר | T4: 31/03/2024 | U4: 1 | V4: 1692.497 | W4: 1692.497 | Y4: 0.0079552284 | Z4: 0.0015439689
A5: 158 | B5: 9935 | C5: BRIDGES ISRAEL GP GROWTH FUND 1 LIMITED PARTNERSHI | D5: 540279460 | E5: מספר שותפות | F5: BRIDGES ISRAEL GROWTH INVESTMENTS 1 | G5: 62014386 | H5: פנימי | I5: פרייבט אקוויטי | J5: Other | K5: ישראל | N5: ישראל | O5: לא | P5: 28/10/2019 | Q5: USD | R5: אחר | T5: 28/03/2024 | U5: 3.681 | V5: 550.394 | W5: 2025.999 | Y5: 0.0095227866 | Z5: 0.0018482042
A6: 158 | B6: 9935 | C6: Kedma Capital | D6: 540286333 | E6: ח.פ | F6: KEDMA CAPITAL PARTNERS III LTD | G6: 62012059 | H6: פנימי | I6: פרייבט אקוויטי | J6: Other | K6: ישראל | N6: ישראל | O6: לא | P6: 17/04/2019 | Q6: USD | R6: אחר | T6: 12/12/2023 | U6: 3.681 | V6: 840.076 | W6: 3092.319 | Y6: 0.014534801 | Z6: 0.0028209474
A7: 158 | B7: 9935 | C7: מרקסטון - קרן הון סיכון | D7: 513473264 | E7: ח.פ | F7: MARKSTONE CAPITAL | G7: 9840796 | H7: פנימי | I7: פרייבט אקוויטי | J7: Other | K7: ישראל | N7: ישראל | O7: לא | P7: 31/12/2013 | Q7: USD | R7: אחר | T7: 31/03/2024 | U7: 3.681 | V7: 0 | W7: 0.002 | Y7: 8.3991114e-09 | Z7: 1.6301187e-09
A8: 158 | B8: 9935 | C8: ג'נריישן ניהול בע"מ | D8: 515785012 | E8: ח.פ | F8: ויולה ג'נריישן ניהול | G8: 56184 | H8: פנימי | I8: פרייבט אקוויטי | J8: Other | K8: ישראל | N8: ישראל | O8: לא | P8: 23/08/2018 | Q8: ILS | R8: מומחה בלתי תלוי | S8: אי-תלות | T8: 29/11/2023 | U8: 1 | V8: 216.183 | W8: 216.183 | Y8: 0.0010161229 | Z8: 0.00019721145
A9: 158 | B9: 9935 | C9: יסודות א נדלן שותפות מוגבלת | D9: 550257125 | E9: מספר שותפות | F9: יסודות נדל"ן ג' פיתוח ושותפות P | G9: 50006782 | H9: פנימי | I9: פרייבט אקוויטי | J9: Other | K9: ישראל | N9: ישראל | O9: לא | P9: 15/06/2021 | Q9: ILS | R9: אחר | T9: 31/03/2024 | U9: 1 | V9: 4939.081 | W9: 4939.081 | Y9: 0.023215122 | Z9: 0.0045056439
A10: 158 | B10: 9935 | C10: קרן ברוש 2234 | D10: 774636625 | E10: פנימי | F10: קרן ברוש | G10: 500051 | H10: פנימי | I10: קרן גידור (Hedge Fund) | J10: Other | K10: ישראל | N10: ישראל | O10: לא | P10: 23/12/2020 | Q10: ILS | R10: אחר | T10: 14/03/2024 | U10: 1 | V10: 3551.914 | W10: 3551.914 | Y10: 0.016695032 | Z10: 0.00324021
A11: 158 | B11: 9935 | C11: נוקד אקוויטי השקעות בע"מ | D11: 515419356 | E11: ח.פ | F11: קרן גידור נוקד במרס | G11: 50006121 | H11: פנימי | I11: קרן גידור (Hedge Fund) | J11: Other | K11: ישראל | N11: ישראל | O11: לא | P11: 04/05/2020 | Q11: ILS | R11: אחר | T11: 14/03/2024 | U11: 1 | V11: 2454.392 | W11: 2454.392 | Y11: 0.011536357 | Z11: 0.0022390025
A12: 158 | B12: 9935 | C12: נוקד אקוויטי השקעות בע"מ | D12: 515419356 | E12: ח.פ | F12: קרן גידור-נוקד | G12: 99630 | H12: פנימי | I12: קרן גידור (Hedge Fund) | J12: Other | K12: ישראל | N12: ישראל | O12: לא | P12: 28/09/2017 | Q12: ILS | R12: אחר | T12: 14/03/2024 | U12: 1 | V12: 2715.537 | W12: 2715.537 | Y12: 0.012763817 | Z12: 0.0024772307
A13: 158 | B13: 9935 | C13: תשתיות ישראל ג'י. פי. 4 שותפות מוגבלת | D13: 550243026 | E13: ח.פ | F13: תשתיות ישראל 4 - קופות המחר | G13: 62017521 | H13: פנימי | I13: פרייבט אקוויטי | J13: Other | K13: ישראל | N13: ישראל | O13: לא | P13: 25/08/2021 | Q13: USD | R13: אחר | T13: 31/03/2024 | U13: 3.681 | V13: 1400.096 | W13: 5153.753 | Y13: 0.024224144 | Z13: 0.0047014772
A14: 158 | B14: 9935 | C14: Qumra Capital GP II, L.P. | D14: 12840 | E14: פנימי | F14: Qumra Opportunity fund | G14: 620182540 | H14: פנימי | I14: פרייבט אקוויטי | J14: Other | K14: ישראל | N14: ישראל | O14: לא | P14: 18/02/2024 | Q14: USD | R14: אחר | T14: 21/12/2023 | U14: 3.681 | V14: 223.009 | W14: 820.894 | Y14: 0.0038584434 | Z14: 0.00074885552
A15: 158 | B15: 9935 | C15: איבו קרן מלונאות ש.מ. | E15: אחר | F15: איבו קרן מלונאות ש.מ. | G15: 50007822 | H15: פנימי | I15: פרייבט אקוויטי | J15: Other | K15: ישראל | O15: לא | P15: 31/01/2023 | Q15: ILS | R15: אחר | T15: 31/03/2024 | U15: 1 | V15: 3500 | W15: 3500 | Y15: 0.016451021 | Z15: 0.0031928517
A16: 158 | B16: 9935 | C16: קוגיטו קפיטל אל.אמ.אי שותף כללי, שותפות מוגבלת | D16: 550270912 | E16: פנימי | F16: קוגיטו קפיטל 2 | G16: 620201580 | H16: פנימי | I16: פרייבט אקוויטי | J16: Other | K16: ישראל | N16: ישראל | O16: לא | P16: 18/02/2024 | Q16: ILS | R16: אחר | T16: 05/02/2024 | U16: 1 | V16: 1450.597 | W16: 1450.597 | Y16: 0.0068182297 | Z16: 0.0013232976
A17: 158 | B17: 9935 | C17: AGILITI INC | D17: 89987 | E17: פנימי | F17: קרן גידור אג'יליטי | G17: 50007889 | H17: פנימי | I17: פרייבט אקוויטי | J17: Other | K17: ישראל | N17: ישראל | O17: לא | P17: 03/04/2023 | Q17: ILS | R17: אחר | T17: 14/03/2024 | U17: 1 | V17: 4947.866 | W17: 4947.866 | Y17: 0.023256412 | Z17: 0.0045136577
A18: 158 | B18: 9935 | C18: LCN חו"לrth American Fund GP III, L.P. | D18: 540300902 | E18: פנימי | F18: CIP VII Cerberus | G18: 62020771 | H18: פנימי | I18: פרייבט אקוויטי | J18: Other | K18: חו"ל | N18: ארה"ב | O18: לא | P18: 25/08/2022 | Q18: USD | R18: אחר | T18: 31/01/2024 | U18: 3.681 | V18: 670.158 | W18: 2466.853 | Y18: 0.011594929 | Z18: 0.0022503703
A19: 158 | B19: 9935 | C19: Hamilton Lane Advisors, LLC | D19: 23-2962336 | E19: מספר תאגיד או שותפות בחו"ל | F19: HAMILTON STRATEGIC OPP 2020 VI - קופות המחר | G19: 620180311 | H19: פנימי | I19: פרייבט אקוויטי | J19: Other | K19: חו"ל | N19: ארה"ב | O19: לא | P19: 22/11/2021 | Q19: USD | R19: אחר | T19: 31/03/2024 | U19: 3.681 | V19: 1114.506 | W19: 4102.496 | Y19: 0.019282927 | Z19: 0.0037424745
A20: 158 | B20: 9935 | C20: המילטון ליין (ישראל) | E20: אחר | F20: Hamilton Strategic Opp VII | G20: 62020599 | H20: פנימי | I20: פרייבט אקוויטי | J20: Other | K20: חו"ל | N20: ארה"ב | O20: לא | P20: 14/06/2022 | Q20: USD | R20: אחר | T20: 31/03/2024 | U20: 3.681 | V20: 1161.053 | W20: 4273.834 | Y20: 0.020088268 | Z20: 0.0038987771
A21: 158 | B21: 9935 | C21: INSIGHT VENTURE PARTNERS IX | D21: 89445 | E21: פנימי | F21: Insight Partners XII | G21: 62018577 | H21: פנימי | I21: פרייבט אקוויטי | J21: Other | K21: חו"ל | N21: ארה"ב | O21: לא | P21: 12/07/2021 | Q21: USD | R21: אחר | T21: 19/03/2024 | U21: 3.681 | V21: 562.515 | W21: 2070.618 | Y21: 0.0097325078 | Z21: 0.0018889074
A22: 158 | B22: 9935 | C22: LCN חו"לrth American Fund GP III, L.P. | D22: 540300902 | E22: פנימי | F22: Invesco Credit Partners II | G22: 62020649 | H22: פנימי | I22: פרייבט אקוויטי | J22: Other | K22: חו"ל | N22: ארה"ב | O22: לא | P22: 13/07/2022 | Q22: USD | R22: אחר | T22: 15/02/2024 | U22: 3.681 | V22: 1034.954 | W22: 3809.667 | Y22: 0.017906546 | Z22: 0.0034753435
A23: 158 | B23: 9935 | C23: LCN חו"לrth American Fund GP III, L.P. | D23: 540300902 | E23: פנימי | F23: viola credit vi | G23: 62019633 | H23: פנימי | I23: פרייבט אקוויטי | J23: Other | K23: חו"ל | N23: ארה"ב | O23: לא | P23: 25/10/2021 | Q23: USD | R23: אחר | T23: 21/02/2024 | U23: 3.681 | V23: 890.028 | W23: 3276.193 | Y23: 0.015399063 | Z23: 0.0029886853
A24: 158 | B24: 9935 | C24: FORTISSIMO CAPITA FUND | D24: 530278498 | E24: מספר שותפות | F24: פורטיסימו 4 | G24: 62021399 | H24: פנימי | I24: פרייבט אקוויטי | J24: Other | K24: חו"ל | N24: ארה"ב | O24: לא | P24: 23/10/2023 | Q24: USD | R24: אחר | T24: 31/03/2024 | U24: 3.681 | V24: 114.696 | W24: 422.196 | Y24: 0.0019844442 | Z24: 0.00038514547
A25: 158 | B25: 9935 | C25: ALTO FUND | D25: 27092 | E25: פנימי | F25: ALTO FUND 2 | G25: 60399003 | H25: פנימי | I25: פרייבט אקוויטי | J25: Other | K25: חו"ל | N25: ארה"ב | O25: לא | P25: 28/12/2015 | Q25: USD | R25: אחר | T25: 22/02/2024 | U25: 3.681 | V25: 302.951 | W25: 1115.163 | Y25: 0.0052415933 | Z25: 0.0010173004
A26: 158 | B26: 9935 | C26: ALTO FUND | D26: 27092 | E26: פנימי | F26: ALTO III | G26: 62006697 | H26: פנימי | I26: פרייבט אקוויטי | J26: Other | K26: חו"ל | N26: ארה"ב | O26: לא | P26: 23/04/2018 | Q26: USD | R26: אחר | T26: 28/12/2023 | U26: 3.681 | V26: 275.97 | W26: 1015.846 | Y26: 0.0047747703 | Z26: 0.00092669834
A27: 158 | B27: 9935 | C27: bain capital senior loan fund | D27: 27725 | E27: פנימי | F27: BAIN CAPITAL DSS | G27: 62016845 | H27: פנימי | I27: פרייבט אקוויטי | J27: Other | K27: חו"ל | N27: ארה"ב | O27: לא | P27: 17/06/2020 | Q27: USD | R27: אחר | T27: 14/03/2024 | U27: 3.681 | V27: 1887.156 | W27: 6946.621 | Y27: 0.032651146 | Z27: 0.006337009
A28: 158 | B28: 9935 | C28: AP Fund III GP, LLC | D28: 84-2057868 | E28: מספר תאגיד או שותפות בחו"ל | F28: BLUE ATLANTIC PARTNERS | G28: 62002044 | H28: פנימי | I28: פרייבט אקוויטי | J28: Other | K28: חו"ל | N28: ארה"ב | O28: לא | P28: 22/06/2017 | Q28: USD | R28: אחר | T28: 27/03/2024 | U28: 3.681 | V28: 440.546 | W28: 1621.648 | Y28: 0.0076222185 | Z28: 0.0014793376
A29: 158 | B29: 9935 | C29: Direct Lending Fund III General Partner | D29: 540298221 | E29: פנימי | F29: COLCHIS INCOME FUND NEW | G29: 62013818 | H29: פנימי | I29: פרייבט אקוויטי | J29: Other | K29: חו"ל | N29: ארה"ב | O29: לא | P29: 31/07/2019 | Q29: USD | R29: אחר | T29: 07/03/2024 | U29: 3.681 | V29: 104.825 | W29: 385.86 | Y29: 0.0018136524 | Z29: 0.00035199781
A30: 158 | B30: 9935 | C30: Direct Lending Fund III General Partner | D30: B216569 | E30: LEI | F30: Direct Lending Fund III | G30: 62017611 | H30: פנימי | I30: פרייבט אקוויטי | J30: Other | K30: חו"ל | N30: גלובלי | O30: לא | P30: 08/11/2020 | Q30: EUR | R30: אחר | T30: 21/02/2024 | U30: 3.979 | V30: 830.474 | W30: 3304.537 | Y30: 0.015532289 | Z30: 0.0030145422
A31: 158 | B31: 9935 | C31: אלקטרה מוצרי צריכה בע"מ | D31: 520039967 | E31: ח.פ | F31: ELELCTRA MULTI FAMILY NADLAN II | G31: 62010558 | H31: פנימי | I31: פרייבט אקוויטי | J31: Other | K31: חו"ל | N31: ארה"ב | O31: לא | P31: 15/01/2019 | Q31: USD | R31: אחר | T31: 31/03/2024 | U31: 3.681 | V31: 1439.91 | W31: 5300.309 | Y31: 0.024912997 | Z31: 0.0048351714
A32: 158 | B32: 9935 | C32: EQT Infrastructure V | D32: 2020 2423 842 | E32: ח.פ | F32: EQT Infrastructure V | G32: 62018890 | H32: פנימי | I32: פרייבט אקוויטי | J32: Value Added Infrastructure | K32: ישראל | L32: לוכסמבורג | M32: לוכסמבורג | N32: גלובלי | O32: לא | P32: 30/08/2021 | Q32: EUR | R32: דיווח מנהל הקרן | T32: 25/02/2024 | U32: 3.979 | V32: 1242.374 | W32: 4943.532 | Y32: 0.02323604 | Z32: 0.0045097038
A33: 158 | B33: 9935 | C33: ני"ע זרים בחו"ל | D33: 549300W384M3RI3VXU42 | E33: LEI | F33: Forma Fund I | G33: 62019294 | H33: פנימי | I33: פרייבט אקוויטי | J33: Other | K33: חו"ל | N33: אירופה | O33: לא | P33: 09/09/2021 | Q33: EUR | R33: אחר | T33: 22/02/2024 | U33: 3.979 | V33: 614.352 | W33: 2444.57 | Y33: 0.011490191 | Z33: 0.0022300425
A34: 158 | B34: 9935 | C34: FORTISSIMO CAPITA FUND | D34: 530278498 | E34: מספר שותפות | F34: FORTTISSMO V - קופות המחר | G34: 620160840 | H34: פנימי | I34: פרייבט אקוויטי | J34: Other | K34: חו"ל | N34: ישראל | O34: לא | P34: 31/08/2021 | Q34: USD | R34: אחר | T34: 31/03/2024 | U34: 3.681 | V34: 1647.467 | W34: 6064.327 | Y34: 0.028504104 | Z34: 0.0055321418
A35: 158 | B35: 9935 | C35: Hamilton Lane Advisors, LLC | D35: 23-2962336 | E35: מספר תאגיד או שותפות בחו"ל | F35: HAMILTON LANE 4 | G35: 620127781 | H35: פנימי | I35: פרייבט אקוויטי | J35: Other | K35: חו"ל | N35: ארה"ב | O35: לא | P35: 15/06/2021 | Q35: USD | R35: אחר | T35: 14/03/2024 | U35: 3.681 | V35: 2253.282 | W35: 8294.332 | Y35: 0.03898578 | Z35: 0.0075664493
A36: 158 | B36: 9935 | C36: ECP V, LLC | D36: 27330 | E36: פנימי | F36: Harbourvest 2018 Global Fund L.P | G36: 62010103 | H36: פנימי | I36: פרייבט אקוויטי | J36: Other | K36: חו"ל | N36: ישראל | O36: לא | P36: 13/12/2018 | Q36: USD | R36: אחר | T36: 26/12/2023 | U36: 3.681 | V36: 2115.104 | W36: 7785.699 | Y36: 0.036595057 | Z36: 0.0071024524
A37: 158 | B37: 9935 | C37: Insight Associates XI, L.P. | D37: 981502442 | E37: מספר תאגיד או שותפות בחו"ל | F37: INSIGHT PARTNERS XI | G37: 62015862 | H37: פנימי | I37: פרייבט אקוויטי | J37: Other | K37: חו"ל | N37: ארה"ב | O37: לא | P37: 16/03/2020 | Q37: USD | R37: אחר | T37: 29/02/2024 | U37: 3.681 | V37: 1025.945 | W37: 3776.503 | Y37: 0.017750663 | Z37: 0.0034450893
A38: 158 | B38: 9935 | C38: Klirmark Opportunity Fund | D38: CO-101523 | E38: מספר תאגיד או שותפות בחו"ל | F38: KLIRMARK III | G38: 50001015 | H38: פנימי | I38: פרייבט אקוויטי | J38: Other | K38: חו"ל | N38: ישראל | O38: לא | P38: 13/11/2019 | Q38: ILS | R38: אחר | T38: 31/03/2024 | U38: 1 | V38: 3449.741 | W38: 3449.741 | Y38: 0.016214791 | Z38: 0.0031470036
A39: 158 | B39: 9935 | C39: Liquidity | D39: 28352 | E39: פנימי | F39: Liquidity Capital II | G39: 62017819 | H39: פנימי | I39: פרייבט אקוויטי | J39: Other | K39: חו"ל | N39: ארה"ב | O39: לא | P39: 17/02/2021 | Q39: USD | R39: אחר | T39: 31/03/2024 | U39: 3.681 | V39: 465.609 | W39: 1713.908 | Y39: 0.0080558693 | Z39: 0.0015635015
A40: 158 | B40: 9935 | C40: LLCP VI FUNF | D40: 27822 | E40: פנימי | F40: LLCP VI FUND | G40: 62009311 | H40: פנימי | I40: פרייבט אקוויטי | J40: Other | K40: חו"ל | N40: ארה"ב | O40: לא | P40: 14/10/2018 | Q40: USD | R40: אחר | T40: 31/03/2024 | U40: 3.681 | V40: 3081.204 | W40: 11341.91 | Y40: 0.053310287 | Z40: 0.010346582
A41: 158 | B41: 9935 | C41: Moneta Capital | D41: 540296522 | E41: ח.פ | F41: MONETA CAPITAL | G41: 62010434 | H41: פנימי | I41: פרייבט אקוויטי | J41: Other | K41: חו"ל | N41: ארה"ב | O41: לא | P41: 24/01/2019 | Q41: USD | R41: אחר | T41: 27/11/2023 | U41: 3.681 | V41: 990.4 | W41: 3645.663 | Y41: 0.017135681 | Z41: 0.0033257322
A42: 158 | B42: 9935 | C42: MV Senior GP S.à r.l | D42: 2016 2429 508 | E42: ח.פ | F42: MV SENIOR II DEEDER II UL SCSP | G42: 62017140 | H42: פנימי | I42: פרייבט אקוויטי | J42: Other | K42: חו"ל | N42: אירופה | O42: לא | P42: 20/07/2020 | Q42: EUR | R42: אחר | T42: 07/03/2024 | U42: 3.979 | V42: 1000.775 | W42: 3982.185 | Y42: 0.018717429 | Z42: 0.0036327214
A43: 158 | B43: 9935 | C43: Pantheon Access Feeder LP | D43: B 201.101 | E43: מספר תאגיד או שותפות בחו"ל | F43: PANTHEON ACCESS | G43: 620070831 | H43: פנימי | I43: פרייבט אקוויטי | J43: Other | K43: חו"ל | N43: ארה"ב | O43: לא | P43: 29/06/2021 | Q43: USD | R43: אחר | T43: 31/01/2024 | U43: 3.681 | V43: 1083.66 | W43: 3988.951 | Y43: 0.018749234 | Z43: 0.0036388942
A44: 158 | B44: 9935 | C44: PHOENIX CO INVEST | D44: 13139 | E44: פנימי | F44: PHOENIX CO INVEST | G44: 62013958 | H44: פנימי | I44: פרייבט אקוויטי | J44: Other | K44: חו"ל | N44: ארה"ב | O44: לא | P44: 19/08/2019 | Q44: USD | R44: אחר | T44: 06/03/2024 | U44: 3.681 | V44: 1003.987 | W44: 3695.678 | Y44: 0.017370763 | Z44: 0.0033713573
... A47: 158 | B47: 9935 | C47: Apexus Logisitcs RE Fund L.P | D47: 89867 | E47: פנימי | F47: Apexus | G47: 620204090 | H47: פנימי | I47: פרייבט אקוויטי | J47: Other | K47: חו"ל | N47: ארה"ב | O47: לא | P47: 18/02/2024 | Q47: USD | R47: אחר | T47: 29/01/2024 | U47: 3.681 | V47: 1158.9 | W47: 4265.911 | Y47: 0.020051025 | Z47: 0.0038915488
A48: 158 | B48: 9935 | D48: GZYUYYBVN9JCLNYWZ615 | E48: LEI | F48: Arkin Bio Capital | G48: 620201280 | H48: פנימי | I48: פרייבט אקוויטי | J48: Other | K48: חו"ל | N48: ארה"ב | O48: לא | P48: 18/02/2024 | Q48: USD | R48: אחר | T48: 26/03/2024 | U48: 3.681 | V48: 73.483 | W48: 270.492 | Y48: 0.0012713892 | Z48: 0.00024675412
A49: 158 | B49: 9935 | C49: Oak Street Real Estate Capital Fund | D49: 9492 | E49: פנימי | F49: Blue Owl Real Estate Fund VI | G49: 620211750 | H49: פנימי | I49: קרן נדל"ן | J49: Other | K49: חו"ל | N49: ארה"ב | O49: לא | P49: 18/02/2024 | Q49: USD | R49: אחר | T49: 31/03/2024 | U49: 3.681 | V49: 53.707 | W49: 197.695 | Y49: 0.00092922458 | Z49: 0.00018034603
A50: 158 | B50: 9935 | C50: Coller Credit Opportunities | D50: 89525 | E50: פנימי | F50: Coller Credit Opportunities | G50: 620192860 | H50: פנימי | I50: קרן חוב | J50: Other | K50: חו"ל | N50: אירופה | O50: לא | P50: 18/02/2024 | Q50: USD | R50: אחר | T50: 28/02/2024 | U50: 3.681 | V50: 607.589 | W50: 2236.534 | Y50: 0.010512364 | Z50: 0.0020402636
A51: 158 | B51: 9935 | C51: Crossroads European Real Estate Fund II | D51: 3333 | E51: פנימי | F51: Crossroads European Real Estate Fund II | G51: 62019765 | H51: פנימי | I51: פרייבט אקוויטי | J51: Other | K51: חו"ל | N51: אירופה | O51: לא | P51: 25/11/2021 | Q51: EUR | R51: אחר | T51: 14/03/2024 | U51: 3.979 | V51: 300.919 | W51: 1197.388 | Y51: 0.0056280728 | Z51: 0.0010923092
A52: 158 | B52: 9935 | C52: ELECTRA AMERICA PRINCIPAL HOSPITALITY LP | D52: 28654 | E52: פנימי | F52: Electra America Principal Hospitality | G52: 620203590 | H52: פנימי | I52: קרן נדל"ן | J52: Other | K52: חו"ל | N52: ארה"ב | O52: לא | P52: 18/02/2024 | Q52: USD | R52: אחר | T52: 28/03/2024 | U52: 3.681 | V52: 926.996 | W52: 3412.274 | Y52: 0.016038683 | Z52: 0.0031128242
A53: 158 | B53: 9935 | C53: אלקטרה בע"מ | D53: 520028911 | E53: ח.פ | F53: Electra capital Pm fund Lp | G53: 62018411 | H53: פנימי | I53: פרייבט אקוויטי | J53: Other | K53: חו"ל | N53: ארה"ב | O53: לא | P53: 08/06/2021 | Q53: USD | R53: אחר | T53: 28/03/2024 | U53: 3.681 | V53: 735.99 | W53: 2709.179 | Y53: 0.012733932 | Z53: 0.0024714307
A54: 158 | B54: 9935 | C54: hanaco growth venturres | D54: 28364 | E54: פנימי | F54: Hanaco growth venturres | G54: 620178760 | H54: פנימי | I54: פרייבט אקוויטי | J54: Other | K54: חו"ל | N54: ארה"ב | O54: לא | P54: 18/02/2024 | Q54: USD | R54: אחר | T54: 28/03/2024 | U54: 3.681 | V54: 435.883 | W54: 1604.485 | Y54: 0.007541549 | Z54: 0.0014636811
A55: 158 | B55: 9935 | C55: HANACO II L.P | D55: 89459 | E55: פנימי | F55: hanaco II L.P | G55: 620187340 | H55: פנימי | I55: פרייבט אקוויטי | J55: Other | K55: חו"ל | N55: ארה"ב | O55: לא | P55: 18/02/2024 | Q55: USD | R55: אחר | T55: 28/03/2024 | U55: 3.681 | V55: 367.139 | W55: 1351.439 | Y55: 0.0063521593 | Z55: 0.0012328416
A56: 158 | B56: 9935 | C56: אי.בי.אי IBI | D56: 550270045 | E56: ח.פ | F56: I.B.I PILLAR GOTTINGEN ASSETS | G56: 62019328 | H56: פנימי | I56: פרייבט אקוויטי | J56: Other | K56: חו"ל | N56: גרמניה | O56: לא | P56: 14/09/2021 | Q56: EUR | R56: אחר | T56: 31/03/2024 | U56: 3.979 | V56: 885.661 | W56: 3524.134 | Y56: 0.016564458 | Z56: 0.003214868
A57: 158 | B57: 9935 | C57: אי.בי.אי IBI | D57: 550270045 | E57: ח.פ | F57: IBI CCF | G57: 62018585 | H57: פנימי | I57: קרן גידור (Hedge Fund) | J57: Other | K57: חו"ל | N57: ארה"ב | O57: לא | P57: 12/07/2021 | Q57: USD | R57: אחר | T57: 13/03/2024 | U57: 3.681 | V57: 674.445 | W57: 2482.631 | Y57: 0.011669091 | Z57: 0.0022647638
A58: 158 | B58: 9935 | C58: אי.בי.אי IBI | D58: 550270045 | E58: ח.פ | F58: IBI CONSUMER | G58: 60400009 | H58: פנימי | I58: פרייבט אקוויטי | J58: Other | K58: חו"ל | N58: גלובלי | O58: לא | P58: 21/01/2016 | Q58: USD | R58: אחר | T58: 13/03/2024 | U58: 3.681 | V58: 112.314 | W58: 413.427 | Y58: 0.001943228 | Z58: 0.00037714613
A59: 158 | B59: 9935 | C59: LCN חו"לrth American Fund GP III, L.P. | D59: 540300902 | E59: פנימי | F59: LCN EUROPEAN FUND III SLP | G59: 62018072 | H59: פנימי | I59: פרייבט אקוויטי | J59: Other | K59: חו"ל | N59: אירופה | O59: לא | P59: 31/03/2021 | Q59: EUR | R59: אחר | T59: 29/02/2024 | U59: 3.979 | V59: 560.007 | W59: 2228.324 | Y59: 0.010473773 | Z59: 0.0020327738
A60: 158 | B60: 9935 | C60: LCCP | D60: 28600 | E60: פנימי | F60: LLCP Lower Middle Market (LLM) III | G60: 620190210 | H60: פנימי | I60: פרייבט אקוויטי | J60: Other | K60: חו"ל | N60: ארה"ב | O60: לא | P60: 18/02/2024 | Q60: USD | R60: אחר | T60: 11/03/2024 | U60: 3.681 | V60: 356.122 | W60: 1310.885 | Y60: 0.0061615401 | Z60: 0.0011958458
... A64: 158 | B64: 9935 | C64: VERTEX ISRAEL FUND II LP | D64: 89453 | E64: פנימי | F64: PARTNERSHIP VERTEX VENTURES | G64: 620186680 | H64: פנימי | I64: פרייבט אקוויטי | J64: Other | K64: חו"ל | N64: גלובלי | O64: לא | P64: 18/02/2024 | Q64: USD | R64: אחר | T64: 15/02/2024 | U64: 3.681 | V64: 260.635 | W64: 959.397 | Y64: 0.0045094479 | Z64: 0.00087520397
A65: 158 | B65: 9935 | C65: פרגרין ניהול קרנות (ישראל) בע"מ | E65: אחר | F65: Peregrine Ventures Growth General Partner LP | G65: 62018619 | H65: פנימי | I65: פרייבט אקוויטי | J65: Other | K65: חו"ל | N65: גלובלי | O65: לא | P65: 13/07/2021 | Q65: USD | R65: אחר | T65: 17/12/2023 | U65: 3.681 | V65: 232.614 | W65: 856.251 | Y65: 0.0040246293 | Z65: 0.00078110926
A66: 158 | B66: 9935 | C66: Rapyd financial network 2016 ltd | D66: 28595 | E66: פנימי | F66: TARGET GLOBAL -FLUORINE (RAPYD | G66: 620181150 | H66: פנימי | I66: פרייבט אקוויטי | J66: Other | K66: חו"ל | N66: ארה"ב | O66: לא | P66: 18/02/2024 | Q66: USD | R66: אחר | T66: 18/02/2024 | U66: 3.681 | V66: 902.942 | W66: 3323.73 | Y66: 0.015622502 | Z66: 0.003032051
A67: 158 | B67: 9935 | C67: Target Global | D67: 89655 | E67: פנימי | F67: Target Global Growth Fund II | G67: 620197160 | H67: פנימי | I67: פרייבט אקוויטי | J67: Other | K67: חו"ל | N67: אירופה | O67: לא | P67: 18/02/2024 | Q67: EUR | R67: אחר | T67: 17/03/2024 | U67: 3.979 | V67: 300.895 | W67: 1197.29 | Y67: 0.0056276114 | Z67: 0.0010922197
A68: 158 | B68: 9935 | C68: VERTEX ISRAEL FUND II LP | D68: 89453 | E68: פנימי | F68: Vertex Israel Opportunity II Fund | G68: 620189650 | H68: פנימי | I68: פרייבט אקוויטי | J68: Other | K68: חו"ל | N68: ארה"ב | O68: לא | P68: 18/02/2024 | Q68: USD | R68: אחר | T68: 01/02/2024 | U68: 3.681 | V68: 527.083 | W68: 1940.193 | Y68: 0.0091194742 | Z68: 0.0017699284
A69: 158 | B69: 9935 | C69: Viola Credit GL II, Limited Partnership | D69: 89968 | E69: פנימי | F69: Viola Credit GL II, Limited Partnership | G69: 620209380 | H69: פנימי | I69: פרייבט אקוויטי | J69: Other | K69: חו"ל | N69: ארה"ב | O69: לא | P69: 18/02/2024 | Q69: USD | R69: אחר | T69: 21/02/2024 | U69: 3.681 | V69: 99.48 | W69: 366.186 | Y69: 0.0017211828 | Z69: 0.00033405109
A70: 158 | B70: 9935 | C70: אי.בי.אי IBI | D70: 550270045 | E70: ח.פ | F70: קרן גידור איביאי SBL | G70: 62018445 | H70: פנימי | I70: קרן גידור (Hedge Fund) | J70: Other | K70: חו"ל | N70: ארה"ב | O70: כן | P70: 20/06/2021 | Q70: USD | R70: אחר | T70: 31/03/2024 | U70: 3.681 | V70: 2337.493 | W70: 8604.31 | Y70: 0.040442767 | Z70: 0.0078492247
