Workbook
Name Additional_Factor: 'אפשרויות בחירה'!$C$701:$C$850
Name Amoritization: 'אפשרויות בחירה'!$C$546:$C$550
Name Capsule: 'אפשרויות בחירה'!$C$926:$C$928
Name Company_Name: 'File Name Info'!$A$34:$A$120
Name Company_Name_ID: 'File Name Info'!$A$34:$B$120
Name Consortium: 'אפשרויות בחירה'!$C$514:$C$515
Name Country_list: 'אפשרויות בחירה'!$C$4:$C$85
Name Country_list_funds: 'אפשרויות בחירה'!$C$4:$C$103
Name CSA: 'אפשרויות בחירה'!$C$688:$C$689
Name Delivery: 'אפשרויות בחירה'!$C$666:$C$667
Name Dependence_Independence: 'אפשרויות בחירה'!$C$654:$C$655
Name Duration_Underlying_Interest_Rate: 'אפשרויות בחירה'!$C$680:$C$687
Name File_Type: 'File Name Info'!$A$10:$A$12
Name Full_File_Type: 'File Name Info'!$A$11:$B$13
Name Full_Type: 'File Name Info'!$A$2:$B$8
Name Full_Type_Nostro: 'File Name Info'!$A$3:$B$6
Name Full_Year: 'File Name Info'!$A$22:$B$31
Name Fund_Strategy: 'אפשרויות בחירה'!$C$597:$C$621
Name Fund_type: 'אפשרויות בחירה'!$C$328:$C$498
Name Holding_interest: 'אפשרויות בחירה'!$C$146:$C$147
Name In_the_books: 'אפשרויות בחירה'!$C$656:$C$657
Name Industry_Sector: 'אפשרויות בחירה'!$C$1129:$C$1245
Name Industry_sector_all: 'אפשרויות בחירה'!$C$202:$C$327
Name Industry_sectors: 'אפשרויות בחירה'!$C$202:$C$327
Name israel_abroad: 'אפשרויות בחירה'!$C$2:$C$3
Name Issuer_Number_Banks: 'אפשרויות בחירה'!$C$111:$C$113
Name Issuer_Number_Fund: 'אפשרויות בחירה'!$C$114:$C$117
Name issuer_number_loan: 'אפשרויות בחירה'!$C$118:$C$126
Name Issuer_Number_Type: 'אפשרויות בחירה'!$C$104:$C$110
Name Issuer_Number_Type_2: 'אפשרויות בחירה'!$C$1076:$C$1079
Name Issuer_Number_Type_3: 'אפשרויות בחירה'!$C$1081:$C$1085
Name Issuer_Number_Type_V2: 'אפשרויות בחירה'!$C$104:$C$110
Name Issuer_Type_TFunds: 'אפשרויות בחירה'!$C$1087:$C$1089
Name Leading_factor: 'אפשרויות בחירה'!$C$692:$C$700
Name Linked_Type: 'אפשרויות בחירה'!$C$516:$C$519
Name other_investments: 'אפשרויות בחירה'!$C$1000:$C$1033
Name Penalty: 'אפשרויות בחירה'!$C$851:$C$852
Name QTR: 'File Name Info'!$A$15:$A$19
Name Rating_Agency: 'אפשרויות בחירה'!$C$188:$C$201
Name real_estate_lifestage: 'אפשרויות בחירה'!$C$634:$C$642
Name real_estate_loans: 'אפשרויות בחירה'!$C$553:$C$591
Name Real_Estate_Main_Use: 'אפשרויות בחירה'!$C$622:$C$633
Name Recourse_Nonrecourse: 'אפשרויות בחירה'!$C$544:$C$545
Name Repayment_Rights: 'אפשרויות בחירה'!$C$551:$C$552
Name Reset_frequency: 'אפשרויות בחירה'!$C$658:$C$665
Name Security_ID_Number_Type: 'אפשרויות בחירה'!$C$1113:$C$1116
Name Security_Number_Loans: 'אפשרויות בחירה'!$C$131
Name Stock_Exchange: 'אפשרויות בחירה'!$C$1283:$C$1315
Name Stock_Exchange_Gov_Bonds: 'אפשרויות בחירה'!$C$148:$C$181
Name Subordination_Risk: 'אפשרויות בחירה'!$C$186:$C$187
Name Tradeable_Status: 'אפשרויות בחירה'!$C$1272:$C$1281
Name Tradeable_Status_All: 'אפשרויות בחירה'!$C$135:$C$145
Name tradeable_status_bonds: 'אפשרויות בחירה'!$C$1248:$C$1253
Name tradeable_status_funds: 'אפשרויות בחירה'!$C$1118:$C$1119
Name tradeable_status_stock: 'אפשרויות בחירה'!$C$1255:$C$1259
Name Tradeable_Status_v2: 'אפשרויות בחירה'!$C$1121:$C$1126
Name tradeable_status_warrants: 'אפשרויות בחירה'!$C$1261:$C$1265
Name tradeable_status_warrants_v2: 'אפשרויות בחירה'!$C$1267:$C$1269
Name Transaction: 'אפשרויות בחירה'!$C$643:$C$646
Name Type: 'File Name Info'!$A$2:$A$8

Sheet עמוד פתיחה
A1: קובץ דיווח עבור רשימת נכסים ברמת הנכס הבודד (חוזר גופים מוסדיים 2015-9-14)
A3: יש לבחור תחום: | D3: נכסי עמיתים - קופות גמל
A5: האם מדובר בקובץ לממומנה או לציבור: | D5: לציבור
A7: יש לבחור את רבעון הדיווח: | D7: 01
A9: יש לבחור את שנת הדיווח: | D9: 2024
A11: יש לבחור את הגוף המוסדי: | D11: תגמולים של עובדים בעירית ת"א יפו א.ש בע"מ
A13: ח.פ. הגוף המוסדי: | D13: 570002618
A15: שם קובץ לשמירה | D15: =IF(D5="לממונה",CONCATENATE(D13, "_",VLOOKUP(D3,Full_Type,2,0),"_",D7,VLOOKUP(D9,Full_Year,2,0),".xlxs"),IF(D5="לציבור",CONCATENATE(D13,"_",VLOOKUP(D3,Full_Type_Nostro,2,0),"_",VLOOKUP(D5,Full_File_Type,2,0),"_",D7,VLOOKUP(D9,Full_Year,2,0),".xlsx"),"שם קובץ לשמירה")) -> 570002618_gm_p_0124.xlsx
A17: פרטי האחראי על הדיווח בגוף המוסדי | B17: שם: | D17: צביקה שמיר , מנכ"ל
B19: מספר טלפון: | D19: 03-5210603
B21: כתובת מייל: | D21: zvi-sha@ovdim-tlv.org.il
A23: הוראות למילוי הדיווח: | D23: יש לדווח לפי ההנחיות בחלק ג' לנספח 5.4.3.2 שבפרק 3 שבחלק 4 לשער 5 בחוזר המאוחד - "רשימת נכסים ברמת הנכס הבודד".

Sheet סכום נכסים
C1: ידווח בקבצי נכסי הנוסטרו בלבד
B2: שווי הוגן | C2: עלות מופחתת | D2: השיטה שיושמה בדוח הכספי | E2: שיעור מסך נכסי השקעה
A3: מזומנים ושווי מזומנים | B3: =SUM('מזומנים ושווי מזומנים'!O:O) -> 140248.74 | D3: =B3+C3 -> 140248.74 | E3: =SUM('מזומנים ושווי מזומנים'!O:O)/B30 -> 0.12589573
A4: איגרות חוב ממשלתיות | B4: =SUM('איגרות חוב ממשלתיות'!U:U) -> 278744.77 | D4: =B4+C4 -> 278744.77 | E4: =SUM('איגרות חוב ממשלתיות'!U:U)/B30 -> 0.25021813
A5: ניירות ערך מסחריים | B5: =SUM('ניירות ערך מסחריים'!AD:AD) -> 2162.809 | D5: =B5+C5 -> 2162.809 | E5: =SUM('ניירות ערך מסחריים'!AD:AD)/B30 -> 0.0019414679
A6: איגרות חוב | B6: =SUM('איגרות חוב'!AD:AD) -> 260026.1 | D6: =B6+C6 -> 260026.1 | E6: =SUM('איגרות חוב'!AD:AD)/B30 -> 0.23341512
A7: מניות, מניות בכורה ויחידות השתתפות | B7: =SUM('מניות מבכ ויהש'!U:U) -> 171789.5 | D7: =B7+C7 -> 171789.5 | E7: =SUM('מניות מבכ ויהש'!U:U)/B30 -> 0.15420862
A8: קרנות סל | B8: =SUM('קרנות סל'!T:T) -> 6173.405 | D8: =B8+C8 -> 6173.405 | E8: =SUM('קרנות סל'!T:T)/B30 -> 0.0055416209
A9: קרנות נאמנות | B9: =SUM('קרנות נאמנות'!T:T) -> 2579.399 | D9: =B9+C9 -> 2579.399 | E9: =SUM('קרנות נאמנות'!T:T)/B30 -> 0.0023154242
A10: כתבי אופציה | B10: =SUM('כתבי אופציה'!W:W) -> 112.229 | D10: =B10+C10 -> 112.229 | E10: =SUM('כתבי אופציה'!W:W)/B30 -> 0.00010074352
A11: אופציות | B11: =SUM(אופציות!V:V) -> 0 | D11: =B11+C11 -> 0 | E11: =SUM(אופציות!V:V)/B30 -> 0
A12: חוזים עתידיים | B12: =SUM('חוזים עתידיים'!R:R) -> 6484.23 | D12: =B12+C12 -> 6484.23 | E12: =SUM('חוזים עתידיים'!R:R)/B30 -> 0.0058206362
A13: מוצרים מובנים | B13: =SUM('מוצרים מובנים'!Z:Z) -> 0 | D13: =B13+C13 -> 0 | E13: =SUM('מוצרים מובנים'!Z:Z)/B30 -> 0
A14: לא סחיר איגרות חוב ממשלתיות | B14: =SUM('לא סחיר איגרות חוב ממשלתיות'!U:U) -> 0 | D14: =B14+C14 -> 0 | E14: =SUM('לא סחיר איגרות חוב ממשלתיות'!U:U)/B30 -> 0
A15: לא סחיר איגרות חוב מיועדות | B15: =SUM('לא סחיר איגרות חוב מיועדות'!N:N) -> 0 | D15: =B15+C15 -> 0 | E15: =SUM('לא סחיר איגרות חוב מיועדות'!N:N)/B30 -> 0
A16: אפיק השקעה מובטח תשואה | B16: =SUM('אפיק השקעה מובטח תשואה'!F:F) -> 0 | D16: =B16+C16 -> 0 | E16: =SUM('אפיק השקעה מובטח תשואה'!F:F)/B30 -> 0
A17: לא סחיר ניירות ערך מסחריים | B17: =SUM('לא סחיר ניירות ערך מסחריים'!AI:AI) -> 5251.985 | D17: =B17+C17 -> 5251.985 | E17: =SUM('לא סחיר ניירות ערך מסחריים'!AI:AI)/B30 -> 0.0047144987
A18: לא סחיר איגרות חוב | B18: =SUM('לא סחיר איגרות חוב'!AG:AG) -> 16970.532 | D18: =B18+C18 -> 16970.532 | E18: =SUM('לא סחיר איגרות חוב'!AG:AG)/B30 -> 0.015233774
A19: לא סחיר מניות, מניות בכורה ויחידות השתתפות | B19: =SUM('לא סחיר מניות מבכ ויהש'!X:X) -> 16868.453 | D19: =B19+C19 -> 16868.453 | E19: =SUM('לא סחיר מניות מבכ ויהש'!X:X)/B30 -> 0.015142141
A20: קרנות השקעה | B20: =SUM('קרנות השקעה'!W:W) -> 156841.86 | D20: =B20+C20 -> 156841.86 | E20: =SUM('קרנות השקעה'!W:W)/B30 -> 0.14079072
A21: לא סחיר כתבי אופציה | B21: =SUM('לא סחיר כתבי אופציה'!Z:Z) -> 20.467 | D21: =B21+C21 -> 20.467 | E21: =SUM('לא סחיר כתבי אופציה'!Z:Z)/B30 -> 1.8372414e-05
A22: לא סחיר אופציות | B22: =SUM('לא סחיר אופציות'!Z:Z) -> 0 | D22: =B22+C22 -> 0 | E22: =SUM('לא סחיר אופציות'!Z:Z)/B30 -> 0
A23: לא סחיר נגזרים אחרים | B23: =SUM('לא סחיר נגזרים אחרים'!R:R) -> 8.08 | D23: =B23+C23 -> 8.08 | E23: =SUM('לא סחיר נגזרים אחרים'!R:R)/B30 -> 7.2530956e-06
A24: הלוואות | B24: =SUM(הלוואות!AT:AT) -> 47806.043 | D24: =B24+C24 -> 47806.043 | E24: =SUM(הלוואות!AT:AT)/B30 -> 0.042913589
A25: לא סחיר מוצרים מובנים | B25: =SUM('לא סחיר מוצרים מובנים'!AB:AB) -> 0 | D25: =B25+C25 -> 0 | E25: =SUM('לא סחיר מוצרים מובנים'!AB:AB)/B30 -> 0
A26: פיקדונות מעל 3 חודשים | B26: =SUM('פיקדונות מעל 3 חודשים'!T:T) -> 0 | D26: =B26+C26 -> 0 | E26: =SUM('פיקדונות מעל 3 חודשים'!T:T)/B30 -> 0
A27: זכויות מקרקעין | B27: =SUM('זכויות מקרקעין'!S:S) -> 5150 | D27: =B27+C27 -> 5150 | E27: =SUM('זכויות מקרקעין'!S:S)/B30 -> 0.0046229508
A28: השקעה בחברות מוחזקות | B28: =SUM('השקעה בחברות מוחזקות'!U:U) -> 0 | D28: =B28+C28 -> 0 | E28: =SUM('השקעה בחברות מוחזקות'!U:U)/B30 -> 0
A29: נכסים אחרים | B29: =SUM('נכסים אחרים'!N:N) -> -3231.508 | D29: =B29+C29 -> -3231.508 | E29: =SUM('נכסים אחרים'!N:N)/B30 -> -0.0029007966
A30: סך הכל נכסים | B30: =IF(SUM(B3:B29)=0,0.0001,SUM(B3:B29)) -> 1114007.1 | C30: =SUM(C3:C29) -> 0 | D30: =SUM(D3:D29) -> 1114007.1 | E30: =SUM(E3:E29) -> 1
A31: מסגרות אשראי
A32: יתרות התחייבויות להשקעה | B32: 55248.74 | E32: =B32/B30 -> 0.049594603

Sheet מזומנים ושווי מזומנים
A1: מספר קופה/קרן/ח.פ. עבור חברת ביטוח | B1: מספר מסלול | C1: שם הבנק | D1: מספר מזהה בנק | E1: סוג מספר מזהה בנק | F1: מאפיין עיקרי | G1: ישראל/חו"ל | H1: בעל עניין/צד קשור | I1: דירוג הבנק | J1: שם מדרג | K1: מטבע פעילות | L1: שווי מטבעי | M1: שער חליפין | N1: שיעור ריבית | O1: שווי הוגן (באלפי ש"ח) | P1: שיעור מנכסי אפיק ההשקעה | Q1: שיעור מסך נכסי ההשקעה
A2: 337 | B2: 1405 | C2: פועלים | D2: 12-600 | E2: סימול בנק | F2: פח"ק/פר"י | G2: ישראל | H2: לא | I2: AAA | J2: S&P מעלות | K2: ILS | L2: 497.749 | M2: 1 | O2: 497.749 | P2: 0.56409121 | Q2: 0.047076096
A3: 337 | B3: 1405 | C3: בנק לאומי לישראל בע"מ | D3: 10-800 | E3: סימול בנק | F3: מזומן ועו"ש בש"ח | G3: ישראל | H3: לא | I3: AAA | J3: S&P מעלות | K3: ILS | L3: 133.918 | M3: 1 | N3: 0.0405 | O3: 133.918 | P3: 0.15176758 | Q3: 0.012665727
A4: 337 | B4: 1405 | C4: פועלים | D4: 12-600 | E4: סימול בנק | F4: מזומן ועו"ש נקוב במט"ח | G4: חו"ל | H4: לא | I4: AAA | J4: S&P מעלות | K4: USD | L4: 65.885 | M4: 3.681 | O4: 242.522 | P4: 0.27484618 | Q4: 0.022937222
A5: 337 | B5: 1405 | C5: פועלים | D5: 12-600 | E5: סימול בנק | F5: מזומן ועו"ש נקוב במט"ח | G5: חו"ל | H5: לא | I5: AAA | J5: S&P מעלות | K5: EUR | L5: 2.06 | M5: 3.979 | O5: 8.197 | P5: 0.0092899716 | Q5: 0.00077529234
A6: 337 | B6: 1405 | C6: בנק לאומי לישראל בע"מ | D6: 10-800 | E6: סימול בנק | F6: מזומן ועו"ש בש"ח | G6: ישראל | H6: לא | I6: AAA | J6: S&P מעלות | K6: ILS | L6: 0.004 | M6: 1 | N6: 0.0405 | O6: 0.004 | P6: 5.0544509e-06 | Q6: 4.2181798e-07
A7: 337 | B7: 1477 | C7: פועלים | D7: 12-600 | E7: סימול בנק | F7: פח"ק/פר"י | G7: ישראל | H7: לא | I7: AAA | J7: S&P מעלות | K7: ILS | L7: 100.567 | M7: 1 | O7: 100.567 | P7: 0.061529878 | Q7: 0.010082965
A8: 337 | B8: 1477 | C8: פועלים | D8: 12-600 | E8: סימול בנק | F8: מזומן ועו"ש נקוב במט"ח | G8: ישראל | H8: לא | I8: AAA | J8: S&P מעלות | K8: CHF | L8: 0.648 | M8: 4.074 | O8: 2.639 | P8: 0.0016147016 | Q8: 0.00026460282
A9: 337 | B9: 1477 | C9: בנק לאומי לישראל בע"מ | D9: 10-800 | E9: סימול בנק | F9: מזומן ועו"ש בש"ח | G9: ישראל | H9: לא | I9: AAA | J9: S&P מעלות | K9: ILS | L9: 441.262 | M9: 1 | N9: 0.0405 | O9: 441.262 | P9: 0.26997726 | Q9: 0.044241454
A10: 337 | B10: 1477 | C10: פועלים | D10: 12-600 | E10: סימול בנק | F10: מזומן ועו"ש נקוב במט"ח | G10: חו"ל | H10: לא | I10: AAA | J10: S&P מעלות | K10: USD | L10: 250.048 | M10: 3.681 | O10: 920.426 | P10: 0.56314351 | Q10: 0.092282911
A11: 337 | B11: 1477 | C11: פועלים | D11: 12-600 | E11: סימול בנק | F11: מזומן ועו"ש נקוב במט"ח | G11: חו"ל | H11: לא | I11: AAA | J11: S&P מעלות | K11: HKD | L11: 2.916 | M11: 0.47 | O11: 1.371 | P11: 0.00083909408 | Q11: 0.00013750322
A12: 337 | B12: 1477 | C12: פועלים | D12: 12-600 | E12: סימול בנק | F12: מזומן ועו"ש נקוב במט"ח | G12: חו"ל | H12: לא | I12: AAA | J12: S&P מעלות | K12: EUR | L12: 40.699 | M12: 3.979 | O12: 161.946 | P12: 0.09908338 | Q12: 0.016236896
A13: 337 | B13: 1477 | C13: פועלים | D13: 12-600 | E13: סימול בנק | F13: מזומן ועו"ש נקוב במט"ח | G13: חו"ל | H13: לא | I13: AAA | J13: S&P מעלות | K13: JPY | L13: 88.168 | M13: 2.433 | O13: 2.145 | P13: 0.0013126726 | Q13: 0.00021510903
A14: 337 | B14: 1477 | C14: פועלים | D14: 12-600 | E14: סימול בנק | F14: מזומן ועו"ש נקוב במט"ח | G14: חו"ל | H14: לא | I14: AAA | J14: S&P מעלות | K14: GBP | L14: 0.341 | M14: 4.654 | O14: 1.587 | P14: 0.00097121907 | Q14: 0.00015915468
A15: 337 | B15: 1477 | C15: פועלים | D15: 12-600 | E15: סימול בנק | F15: מזומן ועו"ש בש"ח | G15: ישראל | H15: לא | I15: AAA | J15: S&P מעלות | K15: ILS | L15: 2.498 | M15: 1 | O15: 2.498 | P15: 0.0015282763 | Q15: 0.00025044022
A16: 337 | B16: 9962 | C16: פועלים | D16: 12-600 | E16: סימול בנק | F16: פח"ק/פר"י | G16: ישראל | H16: לא | I16: AAA | J16: S&P מעלות | K16: ILS | L16: 3729.594 | M16: 1 | O16: 3729.594 | P16: 0.69582212 | Q16: 0.1208265
A17: 337 | B17: 9962 | C17: פועלים | D17: 12-600 | E17: סימול בנק | F17: מזומן ועו"ש נקוב במט"ח | G17: ישראל | H17: לא | I17: AAA | J17: S&P מעלות | K17: CHF | L17: 1.057 | M17: 4.074 | O17: 4.306 | P17: 0.00080344727 | Q17: 0.00013951514
A18: 337 | B18: 9962 | C18: בנק לאומי לישראל בע"מ | D18: 10-800 | E18: סימול בנק | F18: מזומן ועו"ש בש"ח | G18: ישראל | H18: לא | I18: AAA | J18: S&P מעלות | K18: ILS | L18: 340.596 | M18: 1 | N18: 0.0405 | O18: 340.596 | P18: 0.06354428 | Q18: 0.011034189
A19: 337 | B19: 9962 | C19: פועלים | D19: 12-600 | E19: סימול בנק | F19: מזומן ועו"ש נקוב במט"ח | G19: חו"ל | H19: לא | I19: AAA | J19: S&P מעלות | K19: USD | L19: 164.928 | M19: 3.681 | O19: 607.1 | P19: 0.11326528 | Q19: 0.019668026
A20: 337 | B20: 9962 | C20: פועלים | D20: 12-600 | E20: סימול בנק | F20: מזומן ועו"ש נקוב במט"ח | G20: חו"ל | H20: לא | I20: AAA | J20: S&P מעלות | K20: HKD | L20: 0.908 | M20: 0.47 | O20: 0.427 | P20: 7.9663745e-05 | Q20: 1.3833264e-05
A21: 337 | B21: 9962 | C21: פועלים | D21: 12-600 | E21: סימול בנק | F21: מזומן ועו"ש נקוב במט"ח | G21: חו"ל | H21: לא | I21: AAA | J21: S&P מעלות | K21: EUR | L21: 168.797 | M21: 3.979 | O21: 671.659 | P21: 0.12530992 | Q21: 0.021759525
A22: 337 | B22: 9962 | C22: פועלים | D22: 12-600 | E22: סימול בנק | F22: מזומן ועו"ש נקוב במט"ח | G22: חו"ל | H22: לא | I22: AAA | J22: S&P מעלות | K22: JPY | L22: 99.373 | M22: 2.433 | O22: 2.418 | P22: 0.00045114956 | Q22: 7.8340165e-05
A23: 337 | B23: 9962 | C23: פועלים | D23: 12-600 | E23: סימול בנק | F23: מזומן ועו"ש נקוב במט"ח | G23: חו"ל | H23: לא | I23: AAA | J23: S&P מעלות | K23: GBP | L23: 0.297 | M23: 4.654 | O23: 1.383 | P23: 0.00025810519 | Q23: 4.4818847e-05
A24: 337 | B24: 9962 | C24: פועלים | D24: 12-600 | E24: סימול בנק | F24: מזומן ועו"ש בש"ח | G24: ישראל | H24: לא | I24: AAA | J24: S&P מעלות | K24: ILS | L24: 2.498 | M24: 1 | O24: 2.498 | P24: 0.000466024 | Q24: 8.0923048e-05
A25: 337 | B25: 9963 | C25: פועלים | D25: 12-600 | E25: סימול בנק | F25: פח"ק/פר"י | G25: ישראל | H25: לא | I25: AAA | J25: S&P מעלות | K25: ILS | L25: 119657.33 | M25: 1 | O25: 119657.33 | P25: 0.94008607 | Q25: 0.11645938
A26: 337 | B26: 9963 | C26: פועלים | D26: 12-600 | E26: סימול בנק | F26: מזומן ועו"ש נקוב במט"ח | G26: ישראל | H26: לא | I26: AAA | J26: S&P מעלות | K26: CHF | L26: 6.708 | M26: 4.074 | O26: 27.33 | P26: 0.00021471407 | Q26: 2.6599126e-05
A27: 337 | B27: 9963 | C27: בנק לאומי לישראל בע"מ | D27: 10-800 | E27: סימול בנק | F27: מזומן ועו"ש בש"ח | G27: ישראל | H27: לא | I27: AAA | J27: S&P מעלות | K27: ILS | L27: 2233.06 | M27: 1 | N27: 0.0405 | O27: 2233.06 | P27: 0.017544005 | Q27: 0.0021733796
A28: 337 | B28: 9963 | C28: פועלים | D28: 12-600 | E28: סימול בנק | F28: מזומן ועו"ש נקוב במט"ח | G28: חו"ל | H28: לא | I28: AAA | J28: S&P מעלות | K28: USD | L28: 219.166 | M28: 3.681 | O28: 806.751 | P28: 0.0063382262 | Q28: 0.0007851897
A29: 337 | B29: 9963 | C29: פועלים | D29: 12-600 | E29: סימול בנק | F29: מזומן ועו"ש נקוב במט"ח | G29: חו"ל | H29: לא | I29: AAA | J29: S&P מעלות | K29: HKD | L29: 87.459 | M29: 0.47 | O29: 41.141 | P29: 0.00032322281 | Q29: 4.0041364e-05
A30: 337 | B30: 9963 | C30: פועלים | D30: 12-600 | E30: סימול בנק | F30: מזומן ועו"ש נקוב במט"ח | G30: חו"ל | H30: לא | I30: AAA | J30: S&P מעלות | K30: CAD | L30: 1.121 | M30: 2.712 | O30: 3.04 | P30: 2.3880065e-05 | Q30: 2.9583011e-06
A31: 337 | B31: 9963 | C31: פועלים | D31: 12-600 | E31: סימול בנק | F31: מזומן ועו"ש נקוב במט"ח | G31: חו"ל | H31: לא | I31: AAA | J31: S&P מעלות | K31: EUR | L31: 77.805 | M31: 3.979 | O31: 309.593 | P31: 0.0024323153 | Q31: 0.00030131915
A32: 337 | B32: 9963 | C32: פועלים | D32: 12-600 | E32: סימול בנק | F32: מזומן ועו"ש נקוב במט"ח | G32: חו"ל | H32: לא | I32: AAA | J32: S&P מעלות | K32: JPY | L32: 57.023 | M32: 2.433 | O32: 1.388 | P32: 1.0901604e-05 | Q32: 1.3505084e-06
A33: 337 | B33: 9963 | C33: פועלים | D33: 12-600 | E33: סימול בנק | F33: מזומן ועו"ש נקוב במט"ח | G33: חו"ל | H33: לא | I33: AAA | J33: S&P מעלות | K33: GBP | L33: 20.777 | M33: 4.654 | O33: 96.686 | P33: 0.00075961398 | Q33: 9.4102207e-05
A34: 337 | B34: 9963 | C34: פועלים | D34: 12-600 | E34: סימול בנק | F34: מזומן ועו"ש בש"ח | G34: ישראל | H34: לא | I34: AAA | J34: S&P מעלות | K34: ILS | L34: 703.631 | M34: 1 | O34: 703.631 | P34: 0.0055280659 | Q34: 0.00068482574
A35: 337 | B35: 9963 | C35: בנק לאומי לישראל בע"מ | D35: 10-800 | E35: סימול בנק | F35: מזומן ועו"ש בש"ח | G35: ישראל | H35: לא | I35: AAA | J35: S&P מעלות | K35: ILS | L35: 3115.47 | M35: 1 | N35: 0.0405 | O35: 3115.47 | P35: 0.024476646 | Q35: 0.0030322065
A36: 337 | B36: 9963 | C36: בנק לאומי לישראל בע"מ | D36: 10-800 | E36: סימול בנק | F36: מזומן ועו"ש בש"ח | G36: ישראל | H36: לא | I36: AAA | J36: S&P מעלות | K36: ILS | L36: 279.842 | M36: 1 | N36: 0.0405 | O36: 279.842 | P36: 0.002198573 | Q36: 0.00027236277
A37: 337 | B37: 9963 | C37: בנק לאומי לישראל בע"מ | D37: 10-800 | E37: סימול בנק | F37: מזומן ועו"ש בש"ח | G37: ישראל | H37: לא | I37: AAA | J37: S&P מעלות | K37: ILS | L37: 8.117 | M37: 1 | N37: 0.0405 | O37: 8.117 | P37: 6.3770855e-05 | Q37: 7.9000365e-06
A38: 337 | B38: 9964 | C38: פועלים | D38: 12-600 | E38: סימול בנק | F38: פח"ק/פר"י | G38: ישראל | H38: לא | I38: AAA | J38: S&P מעלות | K38: ILS | L38: 3773.486 | M38: 1 | O38: 3773.486 | P38: 0.74156471 | Q38: 0.10877848
A39: 337 | B39: 9964 | C39: פועלים | D39: 12-600 | E39: סימול בנק | F39: מזומן ועו"ש נקוב במט"ח | G39: ישראל | H39: לא | I39: AAA | J39: S&P מעלות | K39: CHF | L39: 2.355 | M39: 4.074 | O39: 9.595 | P39: 0.0018855118 | Q39: 0.00027658153
A40: 337 | B40: 9964 | C40: בנק לאומי לישראל בע"מ | D40: 10-800 | E40: סימול בנק | F40: מזומן ועו"ש בש"ח | G40: ישראל | H40: לא | I40: AAA | J40: S&P מעלות | K40: ILS | L40: 380.639 | M40: 1 | N40: 0.0405 | O40: 380.639 | P40: 0.074803002 | Q40: 0.010972686
A41: 337 | B41: 9964 | C41: פועלים | D41: 12-600 | E41: סימול בנק | F41: מזומן ועו"ש נקוב במט"ח | G41: חו"ל | H41: לא | I41: AAA | J41: S&P מעלות | K41: USD | L41: 174.187 | M41: 3.681 | O41: 641.183 | P41: 0.12600509 | Q41: 0.018483406
A42: 337 | B42: 9964 | C42: פועלים | D42: 12-600 | E42: סימול בנק | F42: מזומן ועו"ש נקוב במט"ח | G42: חו"ל | H42: לא | I42: AAA | J42: S&P מעלות | K42: HKD | L42: 3.056 | M42: 0.47 | O42: 1.438 | P42: 0.00028253047 | Q42: 4.1443766e-05
A43: 337 | B43: 9964 | C43: פועלים | D43: 12-600 | E43: סימול בנק | F43: מזומן ועו"ש נקוב במט"ח | G43: חו"ל | H43: לא | I43: AAA | J43: S&P מעלות | K43: EUR | L43: 69.095 | M43: 3.979 | O43: 274.935 | P43: 0.054030218 | Q43: 0.0079255725
A44: 337 | B44: 9964 | C44: פועלים | D44: 12-600 | E44: סימול בנק | F44: מזומן ועו"ש נקוב במט"ח | G44: חו"ל | H44: לא | I44: AAA | J44: S&P מעלות | K44: JPY | L44: 15.502 | M44: 2.433 | O44: 0.377 | P44: 7.413412e-05 | Q44: 1.0874569e-05
A45: 337 | B45: 9964 | C45: פועלים | D45: 12-600 | E45: סימול בנק | F45: מזומן ועו"ש נקוב במט"ח | G45: חו"ל | H45: לא | I45: AAA | J45: S&P מעלות | K45: GBP | L45: 0.934 | M45: 4.654 | O45: 4.345 | P45: 0.00085390968 | Q45: 0.00012525811
A46: 337 | B46: 9964 | C46: פועלים | D46: 12-600 | E46: סימול בנק | F46: מזומן ועו"ש בש"ח | G46: ישראל | H46: לא | I46: AAA | J46: S&P מעלות | K46: ILS | L46: 2.549 | M46: 1 | O46: 2.549 | P46: 0.00050089942 | Q46: 7.3475823e-05

Sheet איגרות חוב ממשלתיות
A1: מספר קופה/קרן/ח.פ. עבור חברת ביטוח | B1: מספר מסלול | C1: שם מנפיק | D1: שם נייר ערך | E1: מספר נייר ערך | F1: מאפיין עיקרי | G1: ישראל/חו"ל | H1: מדינה לפי חשיפה כלכלית | I1: זירת מסחר | J1: דירוג | K1: שם מדרג | L1: מטבע פעילות | M1: מח"מ | N1: מועד פדיון | O1: שיעור ריבית | P1: תשואה לפדיון | Q1: סכום לקבל (במטבע הפעילות) | R1: ערך נקוב (יחידות) | S1: שער חליפין | T1: שער נייר הערך | U1: שווי הוגן (באלפי ש"ח) | V1: עלות מופחתת (באלפי ש"ח) | W1: השיטה שיושמה בדוח הכספי | X1: שיעור מערך נקוב מונפק | Y1: שיעור מנכסי אפיק ההשקעה | Z1: שיעור מסך נכסי ההשקעה
A2: 337 | B2: 1405 | C2: בנק ישראל- מק"מ | D2: מ.ק.מ. 315 | E2: IL0082503181 | F2: מק"מ קצר משנים עשר חודשים | G2: ישראל | H2: ישראל | I2: TASE | J2: RF | K2: פנימי | L2: ILS | M2: 0.94 | N2: 05/03/2025 | O2: 0 | P2: 0.04096 | R2: 238762 | S2: 1 | T2: 96.38 | U2: 230.119 | W2: שווי הוגן | X2: 0 | Y2: 0.044967376 | Z2: 0.021764182
A3: 337 | B3: 1405 | C3: בנק ישראל- מק"מ | D3: מלווה קצר מועד 1214 | E3: IL0082412185 | F3: מק"מ קצר משנים עשר חודשים | G3: ישראל | H3: ישראל | I3: TASE | J3: RF | K3: פנימי | L3: ILS | M3: 0.677 | N3: 04/12/2024 | O3: 0 | P3: 0.04238 | R3: 1064000 | S3: 1 | T3: 97.22 | U3: 1034.421 | W3: שווי הוגן | X3: 7.6e-05 | Y3: 0.20213553 | Z3: 0.097833473
A4: 337 | B4: 1405 | C4: גליל | D4: ממשלתי צמוד 841 | E4: IL0011205833 | F4: צמוד למדד המחירים לצרכן בריבית קבועה | G4: ישראל | H4: ישראל | I4: TASE | J4: RF | K4: פנימי | L4: ILS | M4: 14.135 | N4: 30/08/2041 | O4: 0.0275 | P4: 0.01782 | R4: 230000 | S4: 1 | T4: 138.12 | U4: 317.676 | W4: שווי הוגן | X4: 1.3e-05 | Y4: 0.062076872 | Z4: 0.030045168
A5: 337 | B5: 1405 | C5: שחר | D5: ממשלתי שקלית 0142 | E5: IL0011254005 | F5: לא צמוד למדד המחירים לצרכן ריבית קבועה | G5: ישראל | H5: ישראל | I5: TASE | J5: RF | K5: פנימי | L5: ILS | M5: 11.998 | N5: 31/01/2042 | O5: 0.055 | P5: 0.04715 | R5: 531206 | S5: 1 | T5: 110.25 | U5: 585.655 | W5: שווי הוגן | X5: 2.8e-05 | Y5: 0.11444241 | Z5: 0.055390055
A6: 337 | B6: 1405 | C6: גילון חדש | D6: ממשלתית משתנה 05/26 0.0866% | E6: IL0011417958 | F6: לא צמוד למדד המחירים לצרכן ריבית משתנה | G6: ישראל | H6: ישראל | I6: TASE | J6: RF | K6: פנימי | L6: ILS | M6: 2.072 | N6: 31/05/2026 | O6: 0.0394 | P6: 0.04743 | R6: 31000 | S6: 1 | T6: 99.22 | U6: 30.758 | W6: שווי הוגן | X6: 1e-06 | Y6: 0.0060104409 | Z6: 0.0029090497
A7: 337 | B7: 1405 | C7: גליל | D7: ממשלתית צמודה 0726 | E7: IL0011695645 | F7: צמוד למדד המחירים לצרכן בריבית קבועה | G7: ישראל | H7: ישראל | I7: TASE | J7: RF | K7: פנימי | L7: ILS | M7: 2.328 | N7: 31/07/2026 | O7: 0.001 | P7: 0.01041 | R7: 1593000 | S7: 1 | T7: 109.23 | U7: 1740.034 | W7: שווי הוגן | X7: 7.9e-05 | Y7: 0.34001895 | Z7: 0.16456896
A8: 337 | B8: 1405 | C8: שחר | D8: ממשלתית שקלית 1.00% 03/30 | E8: IL0011609851 | F8: לא צמוד למדד המחירים לצרכן ריבית קבועה | G8: ישראל | H8: ישראל | I8: TASE | J8: RF | K8: פנימי | L8: ILS | M8: 5.836 | N8: 31/03/2030 | O8: 0.01 | P8: 0.04173 | R8: 450000 | S8: 1 | T8: 83.47 | U8: 375.615 | W8: שווי הוגן | X8: 1.2e-05 | Y8: 0.073398696 | Z8: 0.035524924
A9: 337 | B9: 1405 | C9: בנק ישראל- מק"מ | D9: מקמ 524 | E9: IL0082405254 | F9: מק"מ קצר משנים עשר חודשים | G9: ישראל | H9: ישראל | I9: TASE | J9: RF | K9: פנימי | L9: ILS | M9: 0.101 | N9: 08/05/2024 | O9: 0 | P9: 0.04343 | R9: 400000 | S9: 1 | T9: 99.58 | U9: 398.32 | W9: שווי הוגן | X9: 2.2e-05 | Y9: 0.077835466 | Z9: 0.037672318
A10: 337 | B10: 1405 | C10: בנק ישראל- מק"מ | D10: מקמ 614 | E10: IL0082406161 | F10: מק"מ קצר משנים עשר חודשים | G10: ישראל | H10: ישראל | I10: TASE | J10: RF | K10: פנימי | L10: ILS | M10: 0.178 | N10: 05/06/2024 | O10: 0 | P10: 0.04318 | R10: 245800 | S10: 1 | T10: 99.26 | U10: 243.981 | W10: שווי הוגן | X10: 1.4e-05 | Y10: 0.047676193 | Z10: 0.023075248
A11: 337 | B11: 1405 | C11: US TREASURY N/B | D11: T-3 3/8 15/05/33 | E11: US91282CHC82 | F11: צמוד מט"ח בריבית קבועה | G11: חו"ל | H11: ארה"ב | I11: NYSE | J11: Aaa | K11: Moodys | L11: USD | M11: 7.57 | N11: 15/05/2033 | O11: 0.03375 | P11: 0.04409 | R11: 46000 | S11: 3.681 | T11: 95.014 | U11: 160.883 | W11: שווי הוגן | X11: 0 | Y11: 0.031438061 | Z11: 0.015216002
A12: 337 | B12: 1477 | C12: בנק ישראל- מק"מ | D12: מ.ק.מ. 315 | E12: IL0082503181 | F12: מק"מ קצר משנים עשר חודשים | G12: ישראל | H12: ישראל | I12: TASE | J12: RF | K12: פנימי | L12: ILS | M12: 0.94 | N12: 05/03/2025 | O12: 0 | P12: 0.04096 | R12: 376476 | S12: 1 | T12: 96.38 | U12: 362.848 | W12: שווי הוגן | X12: 0 | Y12: 0.098787297 | Z12: 0.036379499
A13: 337 | B13: 1477 | C13: בנק ישראל- מק"מ | D13: מלווה קצר מועד 1214 | E13: IL0082412185 | F13: מק"מ קצר משנים עשר חודשים | G13: ישראל | H13: ישראל | I13: TASE | J13: RF | K13: פנימי | L13: ILS | M13: 0.677 | N13: 04/12/2024 | O13: 0 | P13: 0.04238 | R13: 2606000 | S13: 1 | T13: 97.22 | U13: 2533.553 | W13: שווי הוגן | X13: 0.000186 | Y13: 0.68977415 | Z13: 0.25401685
... A59: 337 | B59: 9964 | C59: US TREASURY N/B | D59: T-3 3/8 15/05/33 | E59: US91282CHC82 | F59: צמוד מט"ח בריבית קבועה | G59: חו"ל | H59: ארה"ב | I59: NYSE | J59: Aaa | K59: Moodys | L59: USD | M59: 7.57 | N59: 15/05/2033 | O59: 0.03375 | P59: 0.04409 | R59: 235000 | S59: 3.681 | T59: 95.014 | U59: 821.903 | W59: שווי הוגן | X59: 2e-06 | Y59: 0.059035758 | Z59: 0.023693027

Sheet ניירות ערך מסחריים
A1: מספר קופה/קרן/ח.פ. עבור חברת ביטוח | B1: מספר מסלול | C1: שם מנפיק | D1: מספר מנפיק | E1: סוג מספר מזהה מנפיק | F1: שם נייר ערך | G1: מספר נייר ערך | H1: סוג מספר נייר ערך | I1: מאפיין עיקרי | J1: ישראל/חו"ל | K1: מדינה לפי חשיפה כלכלית | L1: זירת מסחר | M1: ענף מסחר | N1: בעל עניין/צד קשור | O1: דירוג | P1: שם מדרג | Q1: דירוג נייר הערך/המנפיק | R1: מטבע פעילות | S1: מח"מ | T1: ריבית עוגן | U1: מועד פדיון | V1: שיעור ריבית | W1: תשואה לפדיון | X1: נחיתות חוזית | Y1: האם סווג כחוב בעייתי | Z1: ערך נקוב (יחידות) | AA1: שער חליפין | AB1: שער נייר הערך | AC1: סכום לקבל (במטבע הפעילות) | AD1: שווי הוגן (באלפי ש"ח) | AE1: עלות מופחתת (באלפי ש"ח) | AF1: עלות מופחתת (במטבע הפעילות) | AG1: השיטה שיושמה בדוח הכספי | AH1: שיעור מערך נקוב מונפק | AI1: שיעור מנכסי אפיק ההשקעה | AJ1: שיעור מסך נכסי ההשקעה
A2: 337 | B2: 1405 | C2: מגה אור החזקות בע"מ | D2: 513257873 | E2: ח.פ | F2: מגה אור נעמ 3 18062024 | G2: IL0011969552 | H2: ISIN | I2: לא צמוד למדד המחירים לצרכן ריבית קבועה | J2: ישראל | K2: ישראל | L2: TASE | M2: נדל"ן מניב בישראל | N2: לא | O2: A+ | P2: S&P מעלות | Q2: נייר ערך | R2: ILS | S2: 0.214 | T2: ריבית בנק ישראל | U2: 18/06/2024 | V2: 0.102 | W2: 0.06684 | X2: החוב לא נחות | Y2: לא | Z2: 2300 | AA2: 1 | AB2: 1044.33 | AD2: 24.02 | AG2: שווי הוגן | AH2: 0.000153 | AI2: 1 | AJ2: 0.0022717253
A3: 337 | B3: 9962 | C3: מגה אור החזקות בע"מ | D3: 513257873 | E3: ח.פ | F3: מגה אור נעמ 3 18062024 | G3: IL0011969552 | H3: ISIN | I3: לא צמוד למדד המחירים לצרכן ריבית קבועה | J3: ישראל | K3: ישראל | L3: TASE | M3: נדל"ן מניב בישראל | N3: לא | O3: A+ | P3: S&P מעלות | Q3: נייר ערך | R3: ILS | S3: 0.214 | T3: ריבית בנק ישראל | U3: 18/06/2024 | V3: 0.102 | W3: 0.06684 | X3: החוב לא נחות | Y3: לא | Z3: 4700 | AA3: 1 | AB3: 1044.33 | AD3: 49.084 | AG3: שווי הוגן | AH3: 0.000313 | AI3: 1 | AJ3: 0.0015901433
A4: 337 | B4: 9963 | C4: מגה אור החזקות בע"מ | D4: 513257873 | E4: ח.פ | F4: מגה אור נעמ 3 18062024 | G4: IL0011969552 | H4: ISIN | I4: לא צמוד למדד המחירים לצרכן ריבית קבועה | J4: ישראל | K4: ישראל | L4: TASE | M4: נדל"ן מניב בישראל | N4: לא | O4: A+ | P4: S&P מעלות | Q4: נייר ערך | R4: ILS | S4: 0.214 | T4: ריבית בנק ישראל | U4: 18/06/2024 | V4: 0.102 | W4: 0.06684 | X4: החוב לא נחות | Y4: לא | Z4: 194100 | AA4: 1 | AB4: 1044.33 | AD4: 2027.045 | AG4: שווי הוגן | AH4: 0.01294 | AI4: 1 | AJ4: 0.0019728699
A5: 337 | B5: 9964 | C5: מגה אור החזקות בע"מ | D5: 513257873 | E5: ח.פ | F5: מגה אור נעמ 3 18062024 | G5: IL0011969552 | H5: ISIN | I5: לא צמוד למדד המחירים לצרכן ריבית קבועה | J5: ישראל | K5: ישראל | L5: TASE | M5: נדל"ן מניב בישראל | N5: לא | O5: A+ | P5: S&P מעלות | Q5: נייר ערך | R5: ILS | S5: 0.214 | T5: ריבית בנק ישראל | U5: 18/06/2024 | V5: 0.102 | W5: 0.06684 | X5: החוב לא נחות | Y5: לא | Z5: 6000 | AA5: 1 | AB5: 1044.33 | AD5: 62.66 | AG5: שווי הוגן | AH5: 0.0004 | AI5: 1 | AJ5: 0.0018062971

Sheet איגרות חוב
A1: מספר קופה/קרן/ח.פ. עבור חברת ביטוח | B1: מספר מסלול | C1: שם מנפיק | D1: מספר מנפיק | E1: סוג מספר מזהה מנפיק | F1: שם נייר ערך | G1: מספר נייר ערך | H1: סוג מספר נייר ערך | I1: מאפיין עיקרי | J1: ישראל/חו"ל | K1: מדינה לפי חשיפה כלכלית | L1: סטאטוס סחירות | M1: זירת מסחר | N1: ענף מסחר | O1: בעל עניין/צד קשור | P1: דירוג | Q1: שם מדרג | R1: דירוג נייר הערך/המנפיק | S1: מטבע פעילות | T1: מח"מ | U1: מועד פדיון | V1: שיעור ריבית | W1: תשואה לפדיון | X1: נחיתות חוזית | Y1: האם סווג כחוב בעייתי | Z1: ערך נקוב (יחידות) | AA1: שער חליפין | AB1: שער נייר הערך | AC1: סכום לקבל (במטבע הפעילות) | AD1: שווי הוגן (באלפי ש"ח) | AE1: עלות מופחתת (באלפי ש"ח) | AF1: עלות מופחתת (במטבע הפעילות) | AG1: השיטה שיושמה בדוח הכספי | AH1: שיעור מערך נקוב מונפק | AI1: שיעור מנכסי אפיק ההשקעה | AJ1: שיעור מסך נכסי ההשקעה
A2: 337 | B2: 1405 | C2: לוויתן בונד בע"מ | D2: 516223864 | E2: ח.פ | F2: LVIA 6.125% 6/25 | G2: IL0011677742 | H2: ISIN | I2: צמוד למט"ח | J2: ישראל | K2: ישראל | L2: סחיר | M2: אחר | N2: Energy Equipment & Services | O2: לא | P2: Ba3 | Q2: Moodys | R2: נייר ערך | S2: USD | T2: 1.14 | U2: 30/06/2025 | V2: 0.06125 | W2: 0.07568 | X2: החוב לא נחות | Y2: לא | Z2: 6000 | AA2: 3.681 | AB2: 98.581 | AD2: 22.111 | AG2: שווי הוגן | AH2: 1e-05 | AI2: 0.0053760933 | AJ2: 0.0020911949
A3: 337 | B3: 1405 | C3: אאורה השקעות בע"מ | D3: 520038274 | E3: ח.פ | F3: אאורה אגח טז | G3: IL0037305799 | H3: ISIN | I3: לא צמוד למדד המחירים לצרכן | J3: ישראל | K3: ישראל | L3: סחיר | M3: TASE | N3: בנייה | O3: לא | P3: A3 | Q3: מידרוג Moodys | R3: נייר ערך | S3: ILS | T3: 1.912 | U3: 30/09/2027 | V3: 0.035 | W3: 0.05656 | X3: החוב לא נחות | Y3: לא | Z3: 40456 | AA3: 1 | AB3: 96.19 | AD3: 38.915 | AG3: שווי הוגן | AH3: 0.000162 | AI3: 0.009461835 | AJ3: 0.0036804684
A4: 337 | B4: 1405 | C4: אאורה השקעות בע"מ | D4: 520038274 | E4: ח.פ | F4: אאורה אגח יז %3.85 31/01/2029 | G4: IL0011935801 | H4: ISIN | I4: צמוד למדד המחירים לצרכן | J4: ישראל | K4: ישראל | L4: סחיר | M4: TASE | N4: בנייה | O4: לא | P4: A- | Q4: S&P מעלות | R4: נייר ערך | S4: ILS | T4: 3.269 | U4: 31/01/2029 | V4: 0.0385 | W4: 0.03176 | X4: החוב לא נחות | Y4: לא | Z4: 9000 | AA4: 1 | AB4: 106.03 | AD4: 9.543 | AG4: שווי הוגן | AH4: 5.1e-05 | AI4: 0.0023202446 | AJ4: 0.00090252969
A5: 337 | B5: 1405 | C5: אאורה השקעות בע"מ | D5: 520038274 | E5: ח.פ | F5: אאורה אגח יז חסום עד 14.05.24 | G5: IL0011935801 | H5: ISIN | I5: צמוד למדד המחירים לצרכן | J5: ישראל | K5: ישראל | L5: חסום | M5: TASE | N5: בנייה | O5: לא | P5: A- | Q5: S&P מעלות | R5: נייר ערך | S5: ILS | T5: 3.45 | U5: 31/01/2029 | V5: 0.0385 | W5: 0.0297 | X5: החוב לא נחות | Y5: לא | Z5: 10000 | AA5: 1 | AB5: 105.578 | AD5: 10.558 | AG5: שווי הוגן | AH5: 5.6e-05 | AI5: 0.0025670571 | AJ5: 0.0009985349
A6: 337 | B6: 1405 | C6: אדגר השקעות ופיתוח בע"מ | D6: 520035171 | E6: ח.פ | F6: אדגר אגח י | G6: IL0018202080 | H6: ISIN | I6: צמוד למדד המחירים לצרכן | J6: ישראל | K6: ישראל | L6: סחיר | M6: TASE | N6: נדל"ן מניב בחו"ל | O6: לא | P6: A2 | Q6: מידרוג Moodys | R6: נייר ערך | S6: ILS | T6: 1.863 | U6: 01/09/2027 | V6: 0.0285 | W6: 0.02861 | X6: החוב לא נחות | Y6: לא | Z6: 24000 | AA6: 1 | AB6: 113.36 | AD6: 27.206 | AG6: שווי הוגן | AH6: 3.5e-05 | AI6: 0.0066150569 | AJ6: 0.0025731275
A7: 337 | B7: 1405 | C7: אדגר השקעות ופיתוח בע"מ | D7: 520035171 | E7: ח.פ | F7: אדגר אגח סד יא | G7: IL0018202817 | H7: ISIN | I7: צמוד למדד המחירים לצרכן | J7: ישראל | K7: ישראל | L7: סחיר | M7: TASE | N7: נדל"ן מניב בחו"ל | O7: לא | P7: A2 | Q7: מידרוג Moodys | R7: נייר ערך | S7: ILS | T7: 3.66 | U7: 31/03/2030 | V7: 0.0245 | W7: 0.03526 | X7: החוב לא נחות | Y7: לא | Z7: 4782.61 | AA7: 1 | AB7: 107.38 | AD7: 5.136 | AG7: שווי הוגן | AH7: 9e-06 | AI7: 0.0012486792 | AJ7: 0.00048571173
A8: 337 | B8: 1405 | C8: אדמה פתרונות לחקלאות בע"מ | D8: 520043605 | E8: ח.פ | F8: אדמה אגח ב | G8: IL0011109159 | H8: ISIN | I8: צמוד למדד המחירים לצרכן | J8: ישראל | K8: ישראל | L8: סחיר | M8: TASE | N8: כימיה, גומי ופלסטיק | O8: לא | P8: AA- | Q8: S&P מעלות | R8: נייר ערך | S8: ILS | T8: 5.674 | U8: 30/11/2036 | V8: 0.0515 | W8: 0.02931 | X8: החוב לא נחות | Y8: לא | Z8: 20312.5 | AA8: 1 | AB8: 154.27 | AD8: 31.336 | AG8: שווי הוגן | AH8: 6e-06 | AI8: 0.0076191647 | AJ8: 0.0029637058
A9: 337 | B9: 1405 | C9: או.פי.סי. אנרגיה בע"מ | D9: 514401702 | E9: ח.פ | F9: או פי סי אגח ב' | G9: IL0011660573 | H9: ISIN | I9: צמוד למדד המחירים לצרכן | J9: ישראל | K9: ישראל | L9: סחיר | M9: TASE | N9: אנרגיה | O9: לא | P9: A- | Q9: S&P מעלות | R9: מנפיק | S9: ILS | T9: 3.318 | U9: 01/10/2028 | V9: 0.0275 | W9: 0.02769 | X9: החוב לא נחות | Y9: לא | Z9: 36188.86 | AA9: 1 | AB9: 110.77 | AD9: 40.086 | AG9: שווי הוגן | AH9: 4e-05 | AI9: 0.0097467441 | AJ9: 0.0037912924
A10: 337 | B10: 1405 | C10: איירפורט סיטי בע"מ | D10: 511659401 | E10: ח.פ | F10: איירפורט אגח ה | G10: IL0011334872 | H10: ISIN | I10: צמוד למדד המחירים לצרכן | J10: ישראל | K10: ישראל | L10: סחיר | M10: TASE | N10: נדל"ן מניב בישראל | O10: לא | P10: AA | Q10: S&P מעלות | R10: נייר ערך | S10: ILS | T10: 2.698 | U10: 28/02/2029 | V10: 0.0234 | W10: 0.02157 | X10: החוב לא נחות | Y10: לא | Z10: 58021.99 | AA10: 1 | AB10: 111.84 | AD10: 64.892 | AG10: שווי הוגן | AH10: 2.2e-05 | AI10: 0.015778012 | AJ10: 0.0061373375
A11: 337 | B11: 1405 | C11: איסתא בע"מ | D11: 520042763 | E11: ח.פ | F11: איסתא אגח א להמרה | G11: IL0011971285 | H11: ISIN | I11: אג"ח להמרה לא צמוד למדד המחירים לצרכן | J11: ישראל | K11: ישראל | L11: סחיר | M11: TASE | N11: מלונאות ותיירות | O11: לא | P11: N/R | Q11: N/R | R11: N/R | S11: ILS | T11: 3.847 | U11: 30/06/2028 | V11: 0.0485 | W11: 0.04807 | X11: החוב לא נחות | Y11: לא | Z11: 13000 | AA11: 1 | AB11: 101.6 | AD11: 13.208 | AG11: שווי הוגן | AH11: 5.3e-05 | AI11: 0.0032114382 | AJ11: 0.0012491865
A12: 337 | B12: 1405 | C12: אלבר שירותי מימונית בע"מ | D12: 512025891 | E12: ח.פ | F12: אלבר אגח יט | G12: IL0011918245 | H12: ISIN | I12: צמוד למדד המחירים לצרכן | J12: ישראל | K12: ישראל | L12: סחיר | M12: TASE | N12: שירותים | O12: לא | P12: A+ | Q12: S&P מעלות | R12: נייר ערך | S12: ILS | T12: 2.036 | U12: 15/05/2028 | V12: 0.032 | W12: 0.02974 | X12: החוב לא נחות | Y12: לא | Z12: 8500 | AA12: 1 | AB12: 104.3 | AD12: 8.866 | AG12: שווי הוגן | AH12: 2.3e-05 | AI12: 0.0021555879 | AJ12: 0.00083848145
A13: 337 | B13: 1405 | C13: אלבר שירותי מימונית בע"מ | D13: 512025891 | E13: ח.פ | F13: אלבר אגח כ | G13: IL0011918328 | H13: ISIN | I13: לא צמוד למדד המחירים לצרכן | J13: ישראל | K13: ישראל | L13: סחיר | M13: TASE | N13: שירותים | O13: לא | P13: A+ | Q13: S&P מעלות | R13: נייר ערך | S13: ILS | T13: 2.059 | U13: 20/06/2028 | V13: 0.057 | W13: 0.05913 | X13: החוב לא נחות | Y13: לא | Z13: 10200 | AA13: 1 | AB13: 100.07 | AD13: 10.207 | AG13: שווי הוגן | AH13: 2.6e-05 | AI13: 0.0024817988 | AJ13: 0.00096537111
... A98: 337 | B98: 1405 | C98: קבוצת מנרב בע"מ | D98: 520034505 | E98: ח.פ | F98: מנרב אגח ד | G98: IL0015501690 | H98: ISIN | I98: צמוד למדד המחירים לצרכן | J98: ישראל | K98: ישראל | L98: סחיר | M98: TASE | N98: בנייה | O98: לא | P98: Baa1 | Q98: מידרוג Moodys | R98: נייר ערך | S98: ILS | T98: 3.667 | U98: 15/04/2032 | V98: 0.0207 | W98: 0.04213 | X98: החוב לא נחות | Y98: לא | Z98: 12000 | AA98: 1 | AB98: 101.49 | AD98: 12.179 | AG98: שווי הוגן | AH98: 2.6e-05 | AI98: 0.002961195 | AJ98: 0.0011518468
A99: 337 | B99: 1405 | C99: קבוצת מנרב בע"מ | D99: 520034505 | E99: ח.פ | F99: מנרב אגח ד חסום עד 07.09.24 | G99: IL0015501690 | H99: ISIN | I99: צמוד למדד המחירים לצרכן | J99: ישראל | K99: ישראל | L99: חסום | M99: TASE | N99: בנייה | O99: לא | P99: Baa1 | Q99: מידרוג Moodys | R99: נייר ערך | S99: ILS | T99: 3,67 | U99: 15/04/2032 | V99: 0.0182 | W99: 0.0421 | X99: החוב לא נחות | Y99: לא | Z99: 20000 | AA99: 1 | AB99: 100.203 | AD99: 20.041 | AG99: שווי הוגן | AH99: 0 | AI99: 0.0048727398 | AJ99: 0.0018954003
A100: 337 | B100: 1405 | C100: נאוויטס פטרוליום, שותפות מוגבלת | D100: 550263107 | E100: ח.פ | F100: נאוויטס פטרו אגח ה חסום עד 11.07.24 | G100: IL0011979122 | H100: ISIN | I100: לא צמוד למדד המחירים לצרכן | J100: ישראל | K100: ארה"ב | L100: חסום | M100: TASE | N100: חיפושי נפט וגז | O100: לא | P100: A- | Q100: S&P מעלות | R100: נייר ערך | S100: ILS | T100: 3.52 | U100: 31/12/2028 | V100: 0.065 | W100: 0.0615 | X100: החוב לא נחות | Y100: לא | Z100: 21000 | AA100: 1 | AB100: 101.78 | AD100: 21.374 | AG100: שווי הוגן | AH100: 0 | AI100: 0.0051969037 | AJ100: 0.0020214937
A101: 337 | B101: 1405 | C101: נאוויטס פטרוליום, שותפות מוגבלת | D101: 550263107 | E101: ח.פ | F101: נאוויטס פטרו אגח ו | G101: IL0012048257 | H101: ISIN | I101: לא צמוד למדד המחירים לצרכן | J101: ישראל | K101: ישראל | L101: סחיר | M101: TASE | N101: חיפושי נפט וגז | O101: לא | P101: A- | Q101: S&P מעלות | R101: נייר ערך | S101: ILS | T101: 4.14 | U101: 30/09/2029 | V101: 0.067 | W101: 0.06089 | X101: החוב לא נחות | Y101: לא | Z101: 17000 | AA101: 1 | AB101: 103.21 | AD101: 17.546 | AG101: שווי הוגן | AH101: 0 | AI101: 0.0042661213 | AJ101: 0.0016594376
A102: 337 | B102: 1405 | C102: ע.י נופר אנרגי' בע"מ | D102: 514599943 | E102: ח.פ | F102: נופר אנרג אגח א | G102: IL0011793408 | H102: ISIN | I102: צמוד למדד המחירים לצרכן | J102: ישראל | K102: ישראל | L102: סחיר | M102: TASE | N102: אנרגיה מתחדשת | O102: לא | P102: N/R | Q102: N/R | R102: N/R | S102: ILS | T102: 2.765 | U102: 31/12/2027 | V102: 0.0148 | W102: 0.03608 | X102: החוב לא נחות | Y102: לא | Z102: 27720 | AA102: 1 | AB102: 103.65 | AD102: 28.732 | AG102: שווי הוגן | AH102: 3.2e-05 | AI102: 0.006985943 | AJ102: 0.0027173949
A103: 337 | B103: 1405 | C103: חברה לנכסים ולבנין בע"מ | D103: 520025438 | E103: ח.פ | F103: נכסים ובניין אגח ט | G103: IL0069902125 | H103: ISIN | I103: לא צמוד למדד המחירים לצרכן | J103: ישראל | K103: ישראל | L103: סחיר | M103: TASE | N103: נדל"ן מניב בישראל | O103: לא | P103: A2 | Q103: מידרוג Moodys | R103: נייר ערך | S103: ILS | T103: 3.208 | U103: 01/07/2029 | V103: 0.0395 | W103: 0.07855 | X103: החוב לא נחות | Y103: לא | Z103: 26495.62 | AA103: 1 | AB103: 89.72 | AD103: 23.772 | AG103: שווי הוגן | AH103: 1.6e-05 | AI103: 0.0057799736 | AJ103: 0.0022482965
A104: 337 | B104: 1405 | C104: חברה לנכסים ולבנין בע"מ | D104: 520025438 | E104: ח.פ | F104: נכסים ובנין אגח י | G104: IL0011936304 | H104: ISIN | I104: צמוד למדד המחירים לצרכן | J104: ישראל | K104: ישראל | L104: סחיר | M104: TASE | N104: נדל"ן מניב בישראל | O104: לא | P104: A | Q104: S&P מעלות | R104: נייר ערך | S104: ILS | T104: 4.414 | U104: 01/07/2029 | V104: 0.0362 | W104: 0.03562 | X104: החוב לא נחות | Y104: לא | Z104: 11640 | AA104: 1 | AB104: 103.98 | AD104: 12.103 | AG104: שווי הוגן | AH104: 7e-06 | AI104: 0.0029428308 | AJ104: 0.0011447035
A105: 337 | B105: 1405 | C105: נמקו ריאליטי לטד | D105: 1905761 | E105: מספר תאגיד או שותפות בחו"ל | F105: נמקו אגח ג | G105: IL0011987612 | H105: ISIN | I105: לא צמוד למדד המחירים לצרכן | J105: ישראל | K105: ישראל | L105: סחיר | M105: TASE | N105: נדל"ן מניב בחו"ל | O105: לא | P105: AA | Q105: S&P מעלות | R105: נייר ערך | S105: ILS | T105: 2.865 | U105: 30/06/2027 | V105: 0.0635 | W105: 0.05893 | X105: החוב לא נחות | Y105: לא | Z105: 10000 | AA105: 1 | AB105: 103.15 | AD105: 10.315 | AG105: שווי הוגן | AH105: 2.4e-05 | AI105: 0.0025080243 | AJ105: 0.0009755723
A106: 337 | B106: 1405 | C106: סולאיר אנרגיות מתחדשות בע"מ | D106: 516046307 | E106: ח.פ | F106: סולאיר אגח א | G106: IL0011837304 | H106: ISIN | I106: צמוד למדד המחירים לצרכן | J106: ישראל | K106: ישראל | L106: סחיר | M106: TASE | N106: אנרגיה מתחדשת | O106: לא | P106: N/R | Q106: N/R | R106: N/R | S106: ILS | T106: 2.57 | U106: 31/12/2027 | V106: 0.023 | W106: 0.04785 | X106: החוב לא נחות | Y106: לא | Z106: 22386.6 | AA106: 1 | AB106: 102.88 | AD106: 23.031 | AG106: שווי הוגן | AH106: 9.3e-05 | AI106: 0.0055999171 | AJ106: 0.002178258
A107: 337 | B107: 1405 | C107: סולגרין בע"מ | D107: 512882747 | E107: ח.פ | F107: סולגרין אגח ב | G107: IL0011862468 | H107: ISIN | I107: צמוד למדד המחירים לצרכן | J107: ישראל | K107: ישראל | L107: סחיר | M107: TASE | N107: אנרגיה מתחדשת | O107: לא | P107: N/R | Q107: N/R | R107: N/R | S107: ILS | T107: 2.57 | U107: 31/12/2027 | V107: 0.0295 | W107: 0.03944 | X107: החוב לא נחות | Y107: לא | Z107: 11400 | AA107: 1 | AB107: 105.44 | AD107: 12.02 | AG107: שווי הוגן | AH107: 6.3e-05 | AI107: 0.0029226227 | AJ107: 0.001136843
A108: 337 | B108: 1405 | C108: סטרוברי פילדס ריט לימיטד | D108: 1863501 | E108: פנימי | F108: סטרוברי אגח ג | G108: IL0011790198 | H108: ISIN | I108: לא צמוד למדד המחירים לצרכן | J108: ישראל | K108: גלובלי | L108: סחיר | M108: TASE | N108: נדל"ן מניב בחו"ל | O108: לא | P108: A+ | Q108: S&P מעלות | R108: נייר ערך | S108: ILS | T108: 2.006 | U108: 31/07/2026 | V108: 0.057 | W108: 0.06157 | X108: החוב לא נחות | Y108: לא | Z108: 22316.43 | AA108: 1 | AB108: 100.25 | AD108: 22.372 | AG108: שווי הוגן | AH108: 9.5e-05 | AI108: 0.0054396581 | AJ108: 0.0021159204
A109: 337 | B109: 1405 | C109: סטרוברי פילדס ריט לימיטד | D109: 1863501 | E109: פנימי | F109: סטרוברי אגח ד | G109: IL0011970295 | H109: ISIN | I109: לא צמוד למדד המחירים לצרכן | J109: ישראל | K109: ארה"ב | L109: סחיר | M109: TASE | N109: נדל"ן מניב בחו"ל | O109: לא | P109: A | Q109: S&P מעלות | R109: נייר ערך | S109: ILS | T109: 2.15 | U109: 30/09/2026 | V109: 0.091 | W109: 0.06969 | X109: החוב לא נחות | Y109: לא | Z109: 18000 | AA109: 1 | AB109: 104.76 | AD109: 18.857 | AG109: שווי הוגן | AH109: 0.000118 | AI109: 0.0045849067 | AJ109: 0.0017834388
A110: 337 | B110: 1405 | C110: סיאון אינווסטמנט קורפוריישן | D110: 14242259 | E110: פנימי | F110: סיאון אגח א - חסום עד 05/04/24 | G110: IL0011940181 | H110: ISIN | I110: צמוד למט"ח | J110: ישראל | K110: ארה"ב | L110: חסום | M110: TASE | N110: אשראי חוץ בנקאי | O110: לא | P110: A1 | Q110: מידרוג Moodys | R110: נייר ערך | S110: ILS | T110: 2.4 | U110: 31/08/2026 | V110: 0.089127 | W110: 0.0655 | X110: החוב לא נחות | Y110: לא | Z110: 18000 | AA110: 1 | AB110: 104.923 | AD110: 18.886 | AG110: שווי הוגן | AH110: 0 | AI110: 0.0045920405 | AJ110: 0.0017862138
A111: 337 | B111: 1405 | C111: ספיר קורפ בע"מ | D111: 520038340 | E111: ח.פ | F111: ספיר קור אגח יט | G111: IL0011886483 | H111: ISIN | I111: לא צמוד למדד המחירים לצרכן | J111: ישראל | K111: ישראל | L111: סחיר | M111: TASE | N111: נדל"ן מניב בחו"ל | O111: לא | P111: N/R | Q111: N/R | R111: N/R | S111: ILS | T111: 2.087 | U111: 30/06/2026 | V111: 0.0675 | W111: 0.07486 | X111: החוב לא נחות | Y111: לא | Z111: 58000 | AA111: 1 | AB111: 100.49 | AD111: 58.284 | AG111: שווי הוגן | AH111: 0.000199 | AI111: 0.014171419 | AJ111: 0.0055124044
... A142: 337 | B142: 1405 | C142: G City Europe Ltd | D142: 213800OJ67K27RCO2J56 | E142: LEI | F142: ATRSAV 4 1/4 09/11/25 | G142: XS1829325239 | H142: ISIN | I142: צמוד למט"ח | J142: חו"ל | K142: אירופה | L142: סחיר | M142: אחר | N142: Real Estate Management & Development | O142: לא | P142: B2 | Q142: Moodys | R142: נייר ערך | S142: EUR | T142: 1.28 | U142: 11/09/2025 | V142: 0.0425 | W142: 0.07885 | X142: החוב לא נחות | Y142: לא | Z142: 3000 | AA142: 3.979 | AB142: 94.738 | AD142: 11.59 | AG142: שווי הוגן | AH142: 6e-06 | AI142: 0.0028179356 | AJ142: 0.0010961217
A143: 337 | B143: 1405 | C143: Energean plc | D143: 549300RVMKU0CYUZBB05 | E143: LEI | F143: ENOIGA 5 3/8 30/03/28 | G143: IL0011736738 | H143: ISIN | I143: צמוד למט"ח | J143: חו"ל | K143: גלובלי | L143: סחיר | M143: אחר | N143: חיפושי נפט וגז | O143: לא | P143: Ba3 | Q143: Moodys | R143: נייר ערך | S143: USD | T143: 3.63 | U143: 30/03/2028 | V143: 0.05375 | W143: 0.0892 | X143: החוב לא נחות | Y143: לא | Z143: 4000 | AA143: 3.681 | AB143: 91.602 | AC143: 0.107 | AD143: 13.883 | AG143: שווי הוגן | AH143: 6e-06 | AI143: 0.0033756052 | AJ143: 0.0013130443
A144: 337 | B144: 1405 | C144: Energean plc | D144: 549300RVMKU0CYUZBB05 | E144: LEI | F144: ENOIGA 5 7/8 30/03/31 | G144: IL0011736811 | H144: ISIN | I144: צמוד למט"ח | J144: חו"ל | K144: גלובלי | L144: סחיר | M144: אחר | N144: חיפושי נפט וגז | O144: לא | P144: Ba3 | Q144: Moodys | R144: נייר ערך | S144: USD | T144: 5.72 | U144: 30/03/2031 | V144: 0.05875 | W144: 0.0907 | X144: החוב לא נחות | Y144: לא | Z144: 4000 | AA144: 3.681 | AB144: 87.729 | AC144: 0.117 | AD144: 13.35 | AG144: שווי הוגן | AH144: 6e-06 | AI144: 0.0032459002 | AJ144: 0.0012625916
A145: 337 | B145: 1405 | C145: Hyundai Capital America | D145: 549300RIPPWJB5Z0FK07 | E145: LEI | F145: HYNMTR 5.6 03/30/28 | G145: US44891CCD39 | H145: ISIN | I145: צמוד למט"ח | J145: חו"ל | K145: ארה"ב | L145: סחיר | M145: אחר | N145: Textiles, Apparel & Luxury Goods | O145: לא | P145: BBB+ | Q145: Moodys | R145: נייר ערך | S145: USD | T145: 3.45 | U145: 30/03/2028 | V145: 0.056 | W145: 0.0543 | X145: החוב לא נחות | Y145: לא | Z145: 6000 | AA145: 3.681 | AB145: 101.197 | AD145: 22.35 | AG145: שווי הוגן | AH145: 8e-06 | AI145: 0.005434345 | AJ145: 0.0021138537
A146: 337 | B146: 1405 | C146: ITHACA ENERGY NORTH | D146: 21380057TNFLXPXBIP34 | E146: LEI | F146: IAECN 9% 07/26 | G146: USG49774AB18 | H146: ISIN | I146: צמוד למט"ח | J146: חו"ל | K146: בריטניה | L146: סחיר | M146: אחר | N146: Energy Equipment & Services | O146: לא | P146: B3 | Q146: Moodys | R146: נייר ערך | S146: USD | T146: 1.16 | U146: 15/07/2026 | V146: 0.09 | W146: 0.08178 | X146: החוב לא נחות | Y146: לא | Z146: 19000 | AA146: 3.681 | AB146: 100.85 | AD146: 71.845 | AG146: שווי הוגן | AH146: 3e-05 | AI146: 0.017468599 | AJ146: 0.0067949426
A147: 337 | B147: 1405 | C147: JPMORGAN CHASE | D147: 8I5DZWZKVSZI1NUHU748 | E147: LEI | F147: JPM 4.912 07/25/33 | G147: US46647PDH64 | H147: ISIN | I147: צמוד למט"ח | J147: חו"ל | K147: ארה"ב | L147: סחיר | M147: אחר | N147: Banks | O147: לא | P147: A- | Q147: Moodys | R147: נייר ערך | S147: USD | T147: 6.63 | U147: 25/07/2033 | V147: 0.04912 | W147: 0.05599 | X147: החוב לא נחות | Y147: לא | Z147: 3000 | AA147: 3.681 | AB147: 97.836 | AD147: 10.902 | AG147: שווי הוגן | AH147: 1e-06 | AI147: 0.0026507419 | AJ147: 0.0010310866
A148: 337 | B148: 1405 | C148: בנק לאומי לישראל בע"מ | D148: 520018078 | E148: ח.פ | F148: LUMIIT 3.275 01/29/31 | G148: IL0060404899 | H148: ISIN | I148: צמוד למט"ח | J148: ישראל | K148: ישראל | L148: סחיר | M148: אחר | N148: Banks | O148: לא | P148: BBB | Q148: S&P | R148: נייר ערך | S148: USD | T148: 1.69 | U148: 29/01/2031 | V148: 0.03275 | W148: 0.06581 | X148: החוב לא נחות | Y148: לא | Z148: 3000 | AA148: 3.681 | AB148: 92.834 | AD148: 10.313 | AG148: שווי הוגן | AH148: 4e-06 | AI148: 0.0025075193 | AJ148: 0.00097537586
A149: 337 | B149: 1405 | C149: לוויתן בונד בע"מ | D149: 516223864 | E149: ח.פ | F149: LVIATH 6.5 30/06/27 | G149: IL0011677825 | H149: ISIN | I149: צמוד למט"ח | J149: ישראל | K149: ישראל | L149: סחיר | M149: אחר | N149: Energy Equipment & Services | O149: לא | P149: BB- | Q149: אחר | R149: מנפיק | S149: USD | T149: 2.79 | U149: 30/06/2027 | V149: 0.065 | W149: 0.07799 | X149: החוב לא נחות | Y149: לא | Z149: 2000 | AA149: 3.681 | AB149: 96.843 | AD149: 7.249 | AG149: שווי הוגן | AH149: 3e-06 | AI149: 0.0017625987 | AJ149: 0.00068561634
A150: 337 | B150: 1405 | C150: AP MOLLER- MAERSK A/S | D150: 549300D2K6PKKKXVNN73 | E150: LEI | F150: MAERSK 5 7/8 14/09/33 | G150: USK0479SAG32 | H150: ISIN | I150: צמוד למט"ח | J150: חו"ל | K150: דנמרק | L150: סחיר | M150: אחר | N150: Transportation Infrastructure | O150: לא | P150: Baa1 | Q150: Moodys | R150: נייר ערך | S150: USD | T150: 7.02 | U150: 14/09/2033 | V150: 0.05875 | W150: 0.05588 | X150: החוב לא נחות | Y150: לא | Z150: 6000 | AA150: 3.681 | AB150: 102.749 | AD150: 22.751 | AG150: שווי הוגן | AH150: 8e-06 | AI150: 0.0055317103 | AJ150: 0.0021517269
A151: 337 | B151: 1405 | C151: Macquarie Group TLD | D151: ACMHD8HWFMFUIQQ8Y590 | E151: LEI | F151: MQGAU 5.887 06/15/34 | G151: US55608KBN46 | H151: ISIN | I151: צמוד למט"ח | J151: חו"ל | K151: ארה"ב | L151: סחיר | M151: אחר | N151: Diversified Financial Services Financial Services | O151: לא | P151: BBB+ | Q151: Moodys | R151: נייר ערך | S151: USD | T151: 6.92 | U151: 15/06/2034 | V151: 0.05887 | W151: 0.05811 | X151: החוב לא נחות | Y151: לא | Z151: 6000 | AA151: 3.681 | AB151: 102.133 | AD151: 22.936 | AG151: שווי הוגן | AH151: 8e-06 | AI151: 0.0055768151 | AJ151: 0.0021692718
A152: 337 | B152: 1405 | C152: בנק מזרחי טפחות בע"מ | D152: 520000522 | E152: ח.פ | F152: MZRHIT 3.077 04/07/31 | G152: IL0069508369 | H152: ISIN | I152: צמוד למט"ח | J152: ישראל | K152: ישראל | L152: סחיר | M152: אחר | N152: Banks | O152: לא | P152: BBB- | Q152: S&P מעלות | R152: מנפיק | S152: USD | T152: 1.87 | U152: 07/04/2031 | V152: 0.03077 | W152: 0.07118 | X152: החוב לא נחות | Y152: לא | Z152: 3000 | AA152: 3.681 | AB152: 91.664 | AD152: 10.286 | AG152: שווי הוגן | AH152: 5e-06 | AI152: 0.0025009111 | AJ152: 0.00097280542
A153: 337 | B153: 1405 | C153: OMEGA HEALTHCARE IN | D153: 549300OJ7ENK42CZ8E73 | E153: LEI | F153: OHI 3 3/8 01/02/31 | G153: US681936BM17 | H153: ISIN | I153: צמוד למט"ח | J153: חו"ל | K153: ארה"ב | L153: סחיר | M153: אחר | N153: Real Estate Management & Development | O153: לא | P153: BBB- | Q153: אחר | R153: מנפיק | S153: USD | T153: 5.85 | U153: 01/02/2031 | V153: 0.03375 | W153: 0.06157 | X153: החוב לא נחות | Y153: לא | Z153: 7000 | AA153: 3.681 | AB153: 85.454 | AD153: 22.161 | AG153: שווי הוגן | AH153: 1e-05 | AI153: 0.005388412 | AJ153: 0.0020959867
A154: 337 | B154: 1405 | C154: PROSPECT CAPITAL CORP | D154: 549300FSD8T39P5Q0O47 | E154: LEI | F154: PSEC 3.364% 11/26 | G154: US74348TAV44 | H154: ISIN | I154: צמוד למט"ח | J154: חו"ל | K154: ארה"ב | L154: סחיר | M154: אחר | N154: Diversified Financial Services Financial Services | O154: לא | P154: Baa3 | Q154: Moodys | R154: נייר ערך | S154: USD | T154: 2.39 | U154: 15/11/2026 | V154: 0.03364 | W154: 0.06959 | X154: החוב לא נחות | Y154: לא | Z154: 5000 | AA154: 3.681 | AB154: 91.462 | AD154: 17.066 | AG154: שווי הוגן | AH154: 1.7e-05 | AI154: 0.0041494271 | AJ154: 0.0016140458
A155: 337 | B155: 1405 | C155: SANTANDER HOLDINGS USA | D155: 549300SMVCQN2P0O6I58 | E155: LEI | F155: SANUSA 6.565 06/12/29 | G155: US80282KBG04 | H155: ISIN | I155: צמוד למט"ח | J155: חו"ל | K155: ארה"ב | L155: סחיר | M155: אחר | N155: Banks | O155: לא | P155: Baa2 | Q155: Moodys | R155: נייר ערך | S155: USD | T155: 3.55 | U155: 12/06/2029 | V155: 0.06565 | W155: 0.06211 | X155: החוב לא נחות | Y155: לא | Z155: 3000 | AA155: 3.681 | AB155: 103.237 | AD155: 11.618 | AG155: שווי הוגן | AH155: 6e-06 | AI155: 0.0028248289 | AJ155: 0.0010988031
A156: 337 | B156: 1405 | C156: Summit Properties Limited | D156: 213800KLWIACHRBYR158 | E156: LEI | F156: SMTPLN 2 01/31/25 | G156: XS1757821688 | H156: ISIN | I156: צמוד למט"ח | J156: חו"ל | K156: גרמניה | L156: סחיר | M156: אחר | N156: Real Estate Management & Development | O156: לא | P156: Ba1 | Q156: אחר | R156: מנפיק | S156: EUR | T156: 0.77 | U156: 31/01/2025 | V156: 0.02 | W156: 0.0763 | X156: החוב לא נחות | Y156: לא | Z156: 2000 | AA156: 3.979 | AB156: 95.576 | AD156: 7.633 | AG156: שווי הוגן | AH156: 7e-06 | AI156: 0.0018558302 | AJ156: 0.00072188157
... A309: 337 | B309: 9962 | C309: קבוצת מנרב בע"מ | D309: 520034505 | E309: ח.פ | F309: מנרב אגח ד | G309: IL0015501690 | H309: ISIN | I309: צמוד למדד המחירים לצרכן | J309: ישראל | K309: ישראל | L309: סחיר | M309: TASE | N309: בנייה | O309: לא | P309: Baa1 | Q309: מידרוג Moodys | R309: נייר ערך | S309: ILS | T309: 3.667 | U309: 15/04/2032 | V309: 0.0207 | W309: 0.04213 | X309: החוב לא נחות | Y309: לא | Z309: 20000 | AA309: 1 | AB309: 101.49 | AD309: 20.298 | AG309: שווי הוגן | AH309: 4.3e-05 | AI309: 0.0031871589 | AJ309: 0.00065758805
A310: 337 | B310: 9962 | C310: קבוצת מנרב בע"מ | D310: 520034505 | E310: ח.פ | F310: מנרב אגח ד חסום עד 07.09.24 | G310: IL0015501690 | H310: ISIN | I310: צמוד למדד המחירים לצרכן | J310: ישראל | K310: ישראל | L310: חסום | M310: TASE | N310: בנייה | O310: לא | P310: Baa1 | Q310: מידרוג Moodys | R310: נייר ערך | S310: ILS | T310: 3,67 | U310: 15/04/2032 | V310: 0.0182 | W310: 0.0421 | X310: החוב לא נחות | Y310: לא | Z310: 68000 | AA310: 1 | AB310: 100.203 | AD310: 68.138 | AG310: שווי הוגן | AH310: 0 | AI310: 0.010698924 | AJ310: 0.0022074471
A311: 337 | B311: 9962 | C311: נאוויטס פטרוליום, שותפות מוגבלת | D311: 550263107 | E311: ח.פ | F311: נאוויטס פטרו אגח ה חסום עד 11.07.24 | G311: IL0011979122 | H311: ISIN | I311: לא צמוד למדד המחירים לצרכן | J311: ישראל | K311: ארה"ב | L311: חסום | M311: TASE | N311: חיפושי נפט וגז | O311: לא | P311: A- | Q311: S&P מעלות | R311: נייר ערך | S311: ILS | T311: 3.52 | U311: 31/12/2028 | V311: 0.065 | W311: 0.0615 | X311: החוב לא נחות | Y311: לא | Z311: 56000 | AA311: 1 | AB311: 101.78 | AD311: 56.997 | AG311: שווי הוגן | AH311: 0 | AI311: 0.0089495535 | AJ311: 0.0018465096
A312: 337 | B312: 9962 | C312: נאוויטס פטרוליום, שותפות מוגבלת | D312: 550263107 | E312: ח.פ | F312: נאוויטס פטרו אגח ו | G312: IL0012048257 | H312: ISIN | I312: לא צמוד למדד המחירים לצרכן | J312: ישראל | K312: ישראל | L312: סחיר | M312: TASE | N312: חיפושי נפט וגז | O312: לא | P312: A- | Q312: S&P מעלות | R312: נייר ערך | S312: ILS | T312: 4.14 | U312: 30/09/2029 | V312: 0.067 | W312: 0.06089 | X312: החוב לא נחות | Y312: לא | Z312: 48000 | AA312: 1 | AB312: 103.21 | AD312: 49.541 | AG312: שווי הוגן | AH312: 0 | AI312: 0.0077788157 | AJ312: 0.001604958
A313: 337 | B313: 9962 | C313: ע.י נופר אנרגי' בע"מ | D313: 514599943 | E313: ח.פ | F313: נופר אנרג אגח א | G313: IL0011793408 | H313: ISIN | I313: צמוד למדד המחירים לצרכן | J313: ישראל | K313: ישראל | L313: סחיר | M313: TASE | N313: אנרגיה מתחדשת | O313: לא | P313: N/R | Q313: N/R | R313: N/R | S313: ILS | T313: 2.765 | U313: 31/12/2027 | V313: 0.0148 | W313: 0.03608 | X313: החוב לא נחות | Y313: לא | Z313: 47040 | AA313: 1 | AB313: 103.65 | AD313: 48.757 | AG313: שווי הוגן | AH313: 5.4e-05 | AI313: 0.0076557385 | AJ313: 0.0015795642
A314: 337 | B314: 9962 | C314: חברה לנכסים ולבנין בע"מ | D314: 520025438 | E314: ח.פ | F314: נכסים ובנין אגח י | G314: IL0011936304 | H314: ISIN | I314: צמוד למדד המחירים לצרכן | J314: ישראל | K314: ישראל | L314: סחיר | M314: TASE | N314: נדל"ן מניב בישראל | O314: לא | P314: A | Q314: S&P מעלות | R314: נייר ערך | S314: ILS | T314: 4.414 | U314: 01/07/2029 | V314: 0.0362 | W314: 0.03562 | X314: החוב לא נחות | Y314: לא | Z314: 20370 | AA314: 1 | AB314: 103.98 | AD314: 21.181 | AG314: שווי הוגן | AH314: 1.1e-05 | AI314: 0.0033257631 | AJ314: 0.00068618545
A315: 337 | B315: 9962 | C315: נמקו ריאליטי לטד | D315: 1905761 | E315: מספר תאגיד או שותפות בחו"ל | F315: נמקו אגח ג | G315: IL0011987612 | H315: ISIN | I315: לא צמוד למדד המחירים לצרכן | J315: ישראל | K315: ישראל | L315: סחיר | M315: TASE | N315: נדל"ן מניב בחו"ל | O315: לא | P315: AA | Q315: S&P מעלות | R315: נייר ערך | S315: ILS | T315: 2.865 | U315: 30/06/2027 | V315: 0.0635 | W315: 0.05893 | X315: החוב לא נחות | Y315: לא | Z315: 25000 | AA315: 1 | AB315: 103.15 | AD315: 25.788 | AG315: שווי הוגן | AH315: 6.1e-05 | AI315: 0.0040491113 | AJ315: 0.00083542969
A316: 337 | B316: 9962 | C316: סולאיר אנרגיות מתחדשות בע"מ | D316: 516046307 | E316: ח.פ | F316: סולאיר אגח א | G316: IL0011837304 | H316: ISIN | I316: צמוד למדד המחירים לצרכן | J316: ישראל | K316: ישראל | L316: סחיר | M316: TASE | N316: אנרגיה מתחדשת | O316: לא | P316: N/R | Q316: N/R | R316: N/R | S316: ILS | T316: 2.57 | U316: 31/12/2027 | V316: 0.023 | W316: 0.04785 | X316: החוב לא נחות | Y316: לא | Z316: 35100 | AA316: 1 | AB316: 102.88 | AD316: 36.111 | AG316: שווי הוגן | AH316: 0.000145 | AI316: 0.0056700716 | AJ316: 0.001169873
A317: 337 | B317: 9962 | C317: סולגרין בע"מ | D317: 512882747 | E317: ח.פ | F317: סולגרין אגח ב | G317: IL0011862468 | H317: ISIN | I317: צמוד למדד המחירים לצרכן | J317: ישראל | K317: ישראל | L317: סחיר | M317: TASE | N317: אנרגיה מתחדשת | O317: לא | P317: N/R | Q317: N/R | R317: N/R | S317: ILS | T317: 2.57 | U317: 31/12/2027 | V317: 0.0295 | W317: 0.03944 | X317: החוב לא נחות | Y317: לא | Z317: 19000 | AA317: 1 | AB317: 105.44 | AD317: 20.034 | AG317: שווי הוגן | AH317: 0.000104 | AI317: 0.0031456432 | AJ317: 0.00064902236
A318: 337 | B318: 9962 | C318: סטרוברי פילדס ריט לימיטד | D318: 1863501 | E318: פנימי | F318: סטרוברי אגח ד | G318: IL0011970295 | H318: ISIN | I318: לא צמוד למדד המחירים לצרכן | J318: ישראל | K318: ארה"ב | L318: סחיר | M318: TASE | N318: נדל"ן מניב בחו"ל | O318: לא | P318: A | Q318: S&P מעלות | R318: נייר ערך | S318: ILS | T318: 2.15 | U318: 30/09/2026 | V318: 0.091 | W318: 0.06969 | X318: החוב לא נחות | Y318: לא | Z318: 50000 | AA318: 1 | AB318: 104.76 | AD318: 52.38 | AG318: שווי הוגן | AH318: 0.000327 | AI318: 0.0082246223 | AJ318: 0.0016969387
A319: 337 | B319: 9962 | C319: סיאון אינווסטמנט קורפוריישן | D319: 14242259 | E319: פנימי | F319: סיאון אגח א - חסום עד 05/04/24 | G319: IL0011940181 | H319: ISIN | I319: צמוד למט"ח | J319: ישראל | K319: ארה"ב | L319: חסום | M319: TASE | N319: אשראי חוץ בנקאי | O319: לא | P319: A1 | Q319: מידרוג Moodys | R319: נייר ערך | S319: ILS | T319: 2.4 | U319: 31/08/2026 | V319: 0.089127 | W319: 0.0655 | X319: החוב לא נחות | Y319: לא | Z319: 33000 | AA319: 1 | AB319: 104.923 | AD319: 34.625 | AG319: שווי הוגן | AH319: 0 | AI319: 0.0054366967 | AJ319: 0.0011217222
A320: 337 | B320: 9962 | C320: ספיר קורפ בע"מ | D320: 520038340 | E320: ח.פ | F320: ספיר קור אגח יט | G320: IL0011886483 | H320: ISIN | I320: לא צמוד למדד המחירים לצרכן | J320: ישראל | K320: ישראל | L320: סחיר | M320: TASE | N320: נדל"ן מניב בחו"ל | O320: לא | P320: N/R | Q320: N/R | R320: N/R | S320: ILS | T320: 2.087 | U320: 30/06/2026 | V320: 0.0675 | W320: 0.07486 | X320: החוב לא נחות | Y320: לא | Z320: 61000 | AA320: 1 | AB320: 100.49 | AD320: 61.299 | AG320: שווי הוגן | AH320: 0.00021 | AI320: 0.0096250534 | AJ320: 0.0019858816
A321: 337 | B321: 9962 | C321: ספיר קורפ בע"מ | D321: 520038340 | E321: ח.פ | F321: ספיר קורפ אגח יח | G321: IL0036501406 | H321: ISIN | I321: לא צמוד למדד המחירים לצרכן | J321: ישראל | K321: ישראל | L321: סחיר | M321: TASE | N321: נדל"ן מניב בחו"ל | O321: לא | P321: N/R | Q321: N/R | R321: N/R | S321: ILS | T321: 0.748 | U321: 15/07/2025 | V321: 0.06 | W321: 0.14593 | X321: החוב לא נחות | Y321: לא | Z321: 5530.73 | AA321: 1 | AB321: 95.56 | AD321: 5.285 | AG321: שווי הוגן | AH321: 3.1e-05 | AI321: 0.00082986809 | AJ321: 0.00017122188
A322: 337 | B322: 9962 | C322: ספנסר אקוויטי גרופ לימיטד | D322: 1838863 | E322: מספר תאגיד או שותפות בחו"ל | F322: ספנסר אגח ד | G322: IL0011887887 | H322: ISIN | I322: לא צמוד למדד המחירים לצרכן | J322: ישראל | K322: ישראל | L322: סחיר | M322: TASE | N322: נדל"ן מניב בחו"ל | O322: לא | P322: A | Q322: S&P מעלות | R322: מנפיק | S322: ILS | T322: 2.614 | U322: 31/08/2029 | V322: 0.0724 | W322: 0.06965 | X322: החוב לא נחות | Y322: לא | Z322: 20370 | AA322: 1 | AB322: 101.61 | AD322: 20.698 | AG322: שווי הוגן | AH322: 7.8e-05 | AI322: 0.0032499595 | AJ322: 0.00067054533
... A349: 337 | B349: 9962 | C349: G City Europe Ltd | D349: 213800OJ67K27RCO2J56 | E349: LEI | F349: ATRSAV 4 1/4 09/11/25 | G349: XS1829325239 | H349: ISIN | I349: צמוד למט"ח | J349: חו"ל | K349: אירופה | L349: סחיר | M349: אחר | N349: Real Estate Management & Development | O349: לא | P349: B2 | Q349: Moodys | R349: נייר ערך | S349: EUR | T349: 1.28 | U349: 11/09/2025 | V349: 0.0425 | W349: 0.07885 | X349: החוב לא נחות | Y349: לא | Z349: 8000 | AA349: 3.979 | AB349: 94.738 | AD349: 30.906 | AG349: שווי הוגן | AH349: 1.6e-05 | AI349: 0.0048527482 | AJ349: 0.0010012394
A350: 337 | B350: 9962 | C350: Energean plc | D350: 549300RVMKU0CYUZBB05 | E350: LEI | F350: ENOIGA 5 3/8 30/03/28 | G350: IL0011736738 | H350: ISIN | I350: צמוד למט"ח | J350: חו"ל | K350: גלובלי | L350: סחיר | M350: אחר | N350: חיפושי נפט וגז | O350: לא | P350: Ba3 | Q350: Moodys | R350: נייר ערך | S350: USD | T350: 3.63 | U350: 30/03/2028 | V350: 0.05375 | W350: 0.0892 | X350: החוב לא נחות | Y350: לא | Z350: 7000 | AA350: 3.681 | AB350: 91.602 | AC350: 0.188 | AD350: 24.296 | AG350: שווי הוגן | AH350: 1.1e-05 | AI350: 0.0038148546 | AJ350: 0.00078709687
A351: 337 | B351: 9962 | C351: Energean plc | D351: 549300RVMKU0CYUZBB05 | E351: LEI | F351: ENOIGA 5 7/8 30/03/31 | G351: IL0011736811 | H351: ISIN | I351: צמוד למט"ח | J351: חו"ל | K351: גלובלי | L351: סחיר | M351: אחר | N351: חיפושי נפט וגז | O351: לא | P351: Ba3 | Q351: Moodys | R351: נייר ערך | S351: USD | T351: 5.72 | U351: 30/03/2031 | V351: 0.05875 | W351: 0.0907 | X351: החוב לא נחות | Y351: לא | Z351: 5000 | AA351: 3.681 | AB351: 87.729 | AC351: 0.147 | AD351: 16.687 | AG351: שווי הוגן | AH351: 8e-06 | AI351: 0.002620195 | AJ351: 0.00054060968
A352: 337 | B352: 9962 | C352: Hyundai Capital America | D352: 549300RIPPWJB5Z0FK07 | E352: LEI | F352: HYNMTR 5.6 03/30/28 | G352: US44891CCD39 | H352: ISIN | I352: צמוד למט"ח | J352: חו"ל | K352: ארה"ב | L352: סחיר | M352: אחר | N352: Textiles, Apparel & Luxury Goods | O352: לא | P352: BBB+ | Q352: Moodys | R352: נייר ערך | S352: USD | T352: 3.45 | U352: 30/03/2028 | V352: 0.056 | W352: 0.0543 | X352: החוב לא נחות | Y352: לא | Z352: 14000 | AA352: 3.681 | AB352: 101.197 | AD352: 52.151 | AG352: שווי הוגן | AH352: 1.7e-05 | AI352: 0.0081886434 | AJ352: 0.0016895154
A353: 337 | B353: 9962 | C353: ITHACA ENERGY NORTH | D353: 21380057TNFLXPXBIP34 | E353: LEI | F353: IAECN 9% 07/26 | G353: USG49774AB18 | H353: ISIN | I353: צמוד למט"ח | J353: חו"ל | K353: בריטניה | L353: סחיר | M353: אחר | N353: Energy Equipment & Services | O353: לא | P353: B3 | Q353: Moodys | R353: נייר ערך | S353: USD | T353: 1.16 | U353: 15/07/2026 | V353: 0.09 | W353: 0.08178 | X353: החוב לא נחות | Y353: לא | Z353: 21000 | AA353: 3.681 | AB353: 100.85 | AD353: 79.407 | AG353: שווי הוגן | AH353: 3.4e-05 | AI353: 0.012468429 | AJ353: 0.0025725388
A354: 337 | B354: 9962 | C354: JPMORGAN CHASE | D354: 8I5DZWZKVSZI1NUHU748 | E354: LEI | F354: JPM 4.912 07/25/33 | G354: US46647PDH64 | H354: ISIN | I354: צמוד למט"ח | J354: חו"ל | K354: ארה"ב | L354: סחיר | M354: אחר | N354: Banks | O354: לא | P354: A- | Q354: Moodys | R354: נייר ערך | S354: USD | T354: 6.63 | U354: 25/07/2033 | V354: 0.04912 | W354: 0.05599 | X354: החוב לא נחות | Y354: לא | Z354: 6000 | AA354: 3.681 | AB354: 97.836 | AD354: 21.804 | AG354: שווי הוגן | AH354: 2e-06 | AI354: 0.0034236187 | AJ354: 0.00070637543
A355: 337 | B355: 9962 | C355: בנק לאומי לישראל בע"מ | D355: 520018078 | E355: ח.פ | F355: LUMIIT 3.275 01/29/31 | G355: IL0060404899 | H355: ISIN | I355: צמוד למט"ח | J355: ישראל | K355: ישראל | L355: סחיר | M355: אחר | N355: Banks | O355: לא | P355: BBB | Q355: S&P | R355: נייר ערך | S355: USD | T355: 1.69 | U355: 29/01/2031 | V355: 0.03275 | W355: 0.06581 | X355: החוב לא נחות | Y355: לא | Z355: 7000 | AA355: 3.681 | AB355: 92.834 | AD355: 24.063 | AG355: שווי הוגן | AH355: 9e-06 | AI355: 0.0037784096 | AJ355: 0.00077957738
A356: 337 | B356: 9962 | C356: לוויתן בונד בע"מ | D356: 516223864 | E356: ח.פ | F356: LVIATH 6.5 30/06/27 | G356: IL0011677825 | H356: ISIN | I356: צמוד למט"ח | J356: ישראל | K356: ישראל | L356: סחיר | M356: אחר | N356: Energy Equipment & Services | O356: לא | P356: BB- | Q356: אחר | R356: מנפיק | S356: USD | T356: 2.79 | U356: 30/06/2027 | V356: 0.065 | W356: 0.07799 | X356: החוב לא נחות | Y356: לא | Z356: 4000 | AA356: 3.681 | AB356: 96.843 | AD356: 14.498 | AG356: שווי הוגן | AH356: 7e-06 | AI356: 0.0022765196 | AJ356: 0.00046970111
A357: 337 | B357: 9962 | C357: AP MOLLER- MAERSK A/S | D357: 549300D2K6PKKKXVNN73 | E357: LEI | F357: MAERSK 5 7/8 14/09/33 | G357: USK0479SAG32 | H357: ISIN | I357: צמוד למט"ח | J357: חו"ל | K357: דנמרק | L357: סחיר | M357: אחר | N357: Transportation Infrastructure | O357: לא | P357: Baa1 | Q357: Moodys | R357: נייר ערך | S357: USD | T357: 7.02 | U357: 14/09/2033 | V357: 0.05875 | W357: 0.05588 | X357: החוב לא נחות | Y357: לא | Z357: 14000 | AA357: 3.681 | AB357: 102.749 | AD357: 53.085 | AG357: שווי הוגן | AH357: 1.9e-05 | AI357: 0.0083353565 | AJ357: 0.0017197859
A358: 337 | B358: 9962 | C358: Macquarie Group TLD | D358: ACMHD8HWFMFUIQQ8Y590 | E358: LEI | F358: MQGAU 5.887 06/15/34 | G358: US55608KBN46 | H358: ISIN | I358: צמוד למט"ח | J358: חו"ל | K358: ארה"ב | L358: סחיר | M358: אחר | N358: Diversified Financial Services Financial Services | O358: לא | P358: BBB+ | Q358: Moodys | R358: נייר ערך | S358: USD | T358: 6.92 | U358: 15/06/2034 | V358: 0.05887 | W358: 0.05811 | X358: החוב לא נחות | Y358: לא | Z358: 14000 | AA358: 3.681 | AB358: 102.133 | AD358: 53.518 | AG358: שווי הוגן | AH358: 1.9e-05 | AI358: 0.0084033218 | AJ358: 0.0017338088
A359: 337 | B359: 9962 | C359: בנק מזרחי טפחות בע"מ | D359: 520000522 | E359: ח.פ | F359: MZRHIT 3.077 04/07/31 | G359: IL0069508369 | H359: ISIN | I359: צמוד למט"ח | J359: ישראל | K359: ישראל | L359: סחיר | M359: אחר | N359: Banks | O359: לא | P359: BBB- | Q359: S&P מעלות | R359: מנפיק | S359: USD | T359: 1.87 | U359: 07/04/2031 | V359: 0.03077 | W359: 0.07118 | X359: החוב לא נחות | Y359: לא | Z359: 7000 | AA359: 3.681 | AB359: 91.664 | AD359: 24 | AG359: שווי הוגן | AH359: 1.2e-05 | AI359: 0.0037684522 | AJ359: 0.00077752293
A360: 337 | B360: 9962 | C360: OMEGA HEALTHCARE IN | D360: 549300OJ7ENK42CZ8E73 | E360: LEI | F360: OHI 3 3/8 01/02/31 | G360: US681936BM17 | H360: ISIN | I360: צמוד למט"ח | J360: חו"ל | K360: ארה"ב | L360: סחיר | M360: אחר | N360: Real Estate Management & Development | O360: לא | P360: BBB- | Q360: אחר | R360: מנפיק | S360: USD | T360: 5.85 | U360: 01/02/2031 | V360: 0.03375 | W360: 0.06157 | X360: החוב לא נחות | Y360: לא | Z360: 17000 | AA360: 3.681 | AB360: 85.454 | AD360: 53.821 | AG360: שווי הוגן | AH360: 2.4e-05 | AI360: 0.0084508353 | AJ360: 0.0017436119
A361: 337 | B361: 9962 | C361: PROSPECT CAPITAL CORP | D361: 549300FSD8T39P5Q0O47 | E361: LEI | F361: PSEC 3.364% 11/26 | G361: US74348TAV44 | H361: ISIN | I361: צמוד למט"ח | J361: חו"ל | K361: ארה"ב | L361: סחיר | M361: אחר | N361: Diversified Financial Services Financial Services | O361: לא | P361: Baa3 | Q361: Moodys | R361: נייר ערך | S361: USD | T361: 2.39 | U361: 15/11/2026 | V361: 0.03364 | W361: 0.06959 | X361: החוב לא נחות | Y361: לא | Z361: 5000 | AA361: 3.681 | AB361: 91.462 | AD361: 17.066 | AG361: שווי הוגן | AH361: 1.7e-05 | AI361: 0.0026796379 | AJ361: 0.00055287417
A362: 337 | B362: 9962 | C362: SANTANDER HOLDINGS USA | D362: 549300SMVCQN2P0O6I58 | E362: LEI | F362: SANUSA 6.565 06/12/29 | G362: US80282KBG04 | H362: ISIN | I362: צמוד למט"ח | J362: חו"ל | K362: ארה"ב | L362: סחיר | M362: אחר | N362: Banks | O362: לא | P362: Baa2 | Q362: Moodys | R362: נייר ערך | S362: USD | T362: 3.55 | U362: 12/06/2029 | V362: 0.06565 | W362: 0.06211 | X362: החוב לא נחות | Y362: לא | Z362: 8000 | AA362: 3.681 | AB362: 103.237 | AD362: 30.981 | AG362: שווי הוגן | AH362: 1.6e-05 | AI362: 0.0048646192 | AJ362: 0.0010036887
A363: 337 | B363: 9962 | C363: Summit Properties Limited | D363: 213800KLWIACHRBYR158 | E363: LEI | F363: SMTPLN 2 01/31/25 | G363: XS1757821688 | H363: ISIN | I363: צמוד למט"ח | J363: חו"ל | K363: גרמניה | L363: סחיר | M363: אחר | N363: Real Estate Management & Development | O363: לא | P363: Ba1 | Q363: אחר | R363: מנפיק | S363: EUR | T363: 0.77 | U363: 31/01/2025 | V363: 0.02 | W363: 0.0763 | X363: החוב לא נחות | Y363: לא | Z363: 3000 | AA363: 3.979 | AB363: 95.576 | AD363: 11.449 | AG363: שווי הוגן | AH363: 1e-05 | AI363: 0.001797701 | AJ363: 0.00037090923
... A458: 337 | B458: 9963 | C458: קבוצת מנרב בע"מ | D458: 520034505 | E458: ח.פ | F458: מנרב אגח ד | G458: IL0015501690 | H458: ISIN | I458: צמוד למדד המחירים לצרכן | J458: ישראל | K458: ישראל | L458: סחיר | M458: TASE | N458: בנייה | O458: לא | P458: Baa1 | Q458: מידרוג Moodys | R458: נייר ערך | S458: ILS | T458: 3.667 | U458: 15/04/2032 | V458: 0.0207 | W458: 0.04213 | X458: החוב לא נחות | Y458: לא | Z458: 900000 | AA458: 1 | AB458: 101.49 | AD458: 913.41 | AG458: שווי הוגן | AH458: 0.001942 | AI458: 0.0038082643 | AJ458: 0.00088899828
A459: 337 | B459: 9963 | C459: קבוצת מנרב בע"מ | D459: 520034505 | E459: ח.פ | F459: מנרב אגח ד חסום עד 07.09.24 | G459: IL0015501690 | H459: ISIN | I459: צמוד למדד המחירים לצרכן | J459: ישראל | K459: ישראל | L459: חסום | M459: TASE | N459: בנייה | O459: לא | P459: Baa1 | Q459: מידרוג Moodys | R459: נייר ערך | S459: ILS | T459: 3,67 | U459: 15/04/2032 | V459: 0.0182 | W459: 0.0421 | X459: החוב לא נחות | Y459: לא | Z459: 2123000 | AA459: 1 | AB459: 100.203 | AD459: 2127.31 | AG459: שווי הוגן | AH459: 0 | AI459: 0.008869355 | AJ459: 0.0020704554
A460: 337 | B460: 9963 | C460: קבוצת האחים נאוי בע"מ | D460: 520036070 | E460: ח.פ | F460: נאווי אגח 6 | G460: IL0020802737 | H460: ISIN | I460: לא צמוד למדד המחירים לצרכן | J460: ישראל | K460: ישראל | L460: סחיר | M460: TASE | N460: אשראי חוץ בנקאי | O460: לא | P460: A | Q460: S&P מעלות | R460: נייר ערך | S460: ILS | T460: 6.6 | U460: 01/03/2026 | V460: 0.0155 | W460: 0.0635 | X460: החוב לא נחות | Y460: לא | Z460: 654545.46 | AA460: 1 | AB460: 95.72 | AD460: 626.531 | AG460: שווי הוגן | AH460: 0.005781 | AI460: 0.0026121843 | AJ460: 0.0006097863
A461: 337 | B461: 9963 | C461: נאוויטס פטרוליום, שותפות מוגבלת | D461: 550263107 | E461: ח.פ | F461: נאוויטס פטרו אגח ה חסום עד 11.07.24 | G461: IL0011979122 | H461: ISIN | I461: לא צמוד למדד המחירים לצרכן | J461: ישראל | K461: ארה"ב | L461: חסום | M461: TASE | N461: חיפושי נפט וגז | O461: לא | P461: A- | Q461: S&P מעלות | R461: נייר ערך | S461: ILS | T461: 3.52 | U461: 31/12/2028 | V461: 0.065 | W461: 0.0615 | X461: החוב לא נחות | Y461: לא | Z461: 2000000 | AA461: 1 | AB461: 101.78 | AD461: 2035.602 | AG461: שווי הוגן | AH461: 0 | AI461: 0.0084869997 | AJ461: 0.0019811987
A462: 337 | B462: 9963 | C462: נאוויטס פטרוליום, שותפות מוגבלת | D462: 550263107 | E462: ח.פ | F462: נאוויטס פטרו אגח ו | G462: IL0012048257 | H462: ISIN | I462: לא צמוד למדד המחירים לצרכן | J462: ישראל | K462: ישראל | L462: סחיר | M462: TASE | N462: חיפושי נפט וגז | O462: לא | P462: A- | Q462: S&P מעלות | R462: נייר ערך | S462: ILS | T462: 4.14 | U462: 30/09/2029 | V462: 0.067 | W462: 0.06089 | X462: החוב לא נחות | Y462: לא | Z462: 1668000 | AA462: 1 | AB462: 103.21 | AD462: 1721.543 | AG462: שווי הוגן | AH462: 0 | AI462: 0.0071775982 | AJ462: 0.001675533
A463: 337 | B463: 9963 | C463: ע.י נופר אנרגי' בע"מ | D463: 514599943 | E463: ח.פ | F463: נופר אנרג אגח א | G463: IL0011793408 | H463: ISIN | I463: צמוד למדד המחירים לצרכן | J463: ישראל | K463: ישראל | L463: סחיר | M463: TASE | N463: אנרגיה מתחדשת | O463: לא | P463: N/R | Q463: N/R | R463: N/R | S463: ILS | T463: 2.765 | U463: 31/12/2027 | V463: 0.0148 | W463: 0.03608 | X463: החוב לא נחות | Y463: לא | Z463: 1671600 | AA463: 1 | AB463: 103.65 | AD463: 1732.613 | AG463: שווי הוגן | AH463: 0.001921 | AI463: 0.0072237546 | AJ463: 0.0016863077
A464: 337 | B464: 9963 | C464: חברה לנכסים ולבנין בע"מ | D464: 520025438 | E464: ח.פ | F464: נכסים ובנין אגח י | G464: IL0011936304 | H464: ISIN | I464: צמוד למדד המחירים לצרכן | J464: ישראל | K464: ישראל | L464: סחיר | M464: TASE | N464: נדל"ן מניב בישראל | O464: לא | P464: A | Q464: S&P מעלות | R464: נייר ערך | S464: ILS | T464: 4.414 | U464: 01/07/2029 | V464: 0.0362 | W464: 0.03562 | X464: החוב לא נחות | Y464: לא | Z464: 914710 | AA464: 1 | AB464: 103.98 | AD464: 951.115 | AG464: שווי הוגן | AH464: 0.000515 | AI464: 0.003965469 | AJ464: 0.00092569603
A465: 337 | B465: 9963 | C465: נמקו ריאליטי לטד | D465: 1905761 | E465: מספר תאגיד או שותפות בחו"ל | F465: נמקו אגח ג | G465: IL0011987612 | H465: ISIN | I465: לא צמוד למדד המחירים לצרכן | J465: ישראל | K465: ישראל | L465: סחיר | M465: TASE | N465: נדל"ן מניב בחו"ל | O465: לא | P465: AA | Q465: S&P מעלות | R465: נייר ערך | S465: ILS | T465: 2.865 | U465: 30/06/2027 | V465: 0.0635 | W465: 0.05893 | X465: החוב לא נחות | Y465: לא | Z465: 991000 | AA465: 1 | AB465: 103.15 | AD465: 1022.216 | AG465: שווי הוגן | AH465: 0.002417 | AI465: 0.0042619093 | AJ465: 0.00099489683
A466: 337 | B466: 9963 | C466: סולאיר אנרגיות מתחדשות בע"מ | D466: 516046307 | E466: ח.פ | F466: סולאיר אגח א | G466: IL0011837304 | H466: ISIN | I466: צמוד למדד המחירים לצרכן | J466: ישראל | K466: ישראל | L466: סחיר | M466: TASE | N466: אנרגיה מתחדשת | O466: לא | P466: N/R | Q466: N/R | R466: N/R | S466: ILS | T466: 2.57 | U466: 31/12/2027 | V466: 0.023 | W466: 0.04785 | X466: החוב לא נחות | Y466: לא | Z466: 1719648 | AA466: 1 | AB466: 102.88 | AD466: 1769.174 | AG466: שווי הוגן | AH466: 0.007106 | AI466: 0.0073761855 | AJ466: 0.0017218911
A467: 337 | B467: 9963 | C467: סולגרין בע"מ | D467: 512882747 | E467: ח.פ | F467: סולגרין אגח ב | G467: IL0011862468 | H467: ISIN | I467: צמוד למדד המחירים לצרכן | J467: ישראל | K467: ישראל | L467: סחיר | M467: TASE | N467: אנרגיה מתחדשת | O467: לא | P467: N/R | Q467: N/R | R467: N/R | S467: ILS | T467: 2.57 | U467: 31/12/2027 | V467: 0.0295 | W467: 0.03944 | X467: החוב לא נחות | Y467: לא | Z467: 982009.3 | AA467: 1 | AB467: 105.44 | AD467: 1035.431 | AG467: שווי הוגן | AH467: 0.005396 | AI467: 0.0043170027 | AJ467: 0.0010077578
A468: 337 | B468: 9963 | C468: סטרוברי פילדס ריט לימיטד | D468: 1863501 | E468: פנימי | F468: סטרוברי אגח ד | G468: IL0011970295 | H468: ISIN | I468: לא צמוד למדד המחירים לצרכן | J468: ישראל | K468: ארה"ב | L468: סחיר | M468: TASE | N468: נדל"ן מניב בחו"ל | O468: לא | P468: A | Q468: S&P מעלות | R468: נייר ערך | S468: ILS | T468: 2.15 | U468: 30/09/2026 | V468: 0.091 | W468: 0.06969 | X468: החוב לא נחות | Y468: לא | Z468: 1745000 | AA468: 1 | AB468: 104.76 | AD468: 1828.062 | AG468: שווי הוגן | AH468: 0.011411 | AI468: 0.0076217068 | AJ468: 0.0017792054
A469: 337 | B469: 9963 | C469: סיאון אינווסטמנט קורפוריישן | D469: 14242259 | E469: פנימי | F469: סיאון אגח א - חסום עד 05/04/24 | G469: IL0011940181 | H469: ISIN | I469: צמוד למט"ח | J469: ישראל | K469: ארה"ב | L469: חסום | M469: TASE | N469: אשראי חוץ בנקאי | O469: לא | P469: A1 | Q469: מידרוג Moodys | R469: נייר ערך | S469: ILS | T469: 2.4 | U469: 31/08/2026 | V469: 0.089127 | W469: 0.0655 | X469: החוב לא נחות | Y469: לא | Z469: 1463000 | AA469: 1 | AB469: 104.923 | AD469: 1535.023 | AG469: שווי הוגן | AH469: 0 | AI469: 0.0063999465 | AJ469: 0.0014939986
A470: 337 | B470: 9963 | C470: ספיר קורפ בע"מ | D470: 520038340 | E470: ח.פ | F470: ספיר קור אגח יט | G470: IL0011886483 | H470: ISIN | I470: לא צמוד למדד המחירים לצרכן | J470: ישראל | K470: ישראל | L470: סחיר | M470: TASE | N470: נדל"ן מניב בחו"ל | O470: לא | P470: N/R | Q470: N/R | R470: N/R | S470: ILS | T470: 2.087 | U470: 30/06/2026 | V470: 0.0675 | W470: 0.07486 | X470: החוב לא נחות | Y470: לא | Z470: 3058000 | AA470: 1 | AB470: 100.49 | AD470: 3072.984 | AG470: שווי הוגן | AH470: 0.010518 | AI470: 0.012812139 | AJ470: 0.0029908559
A471: 337 | B471: 9963 | C471: ספיר קורפ בע"מ | D471: 520038340 | E471: ח.פ | F471: ספיר קורפ אגח יח | G471: IL0036501406 | H471: ISIN | I471: לא צמוד למדד המחירים לצרכן | J471: ישראל | K471: ישראל | L471: סחיר | M471: TASE | N471: נדל"ן מניב בחו"ל | O471: לא | P471: N/R | Q471: N/R | R471: N/R | S471: ILS | T471: 0.748 | U471: 15/07/2025 | V471: 0.06 | W471: 0.14593 | X471: החוב לא נחות | Y471: לא | Z471: 286700.84 | AA471: 1 | AB471: 95.56 | AD471: 273.971 | AG471: שווי הוגן | AH471: 0.001608 | AI471: 0.0011422638 | AJ471: 0.00026664919
... A502: 337 | B502: 9963 | C502: Energean plc | D502: 549300RVMKU0CYUZBB05 | E502: LEI | F502: ENOGLN 6.5% 30/4/27 | G502: USG3044DAA49 | H502: ISIN | I502: צמוד למט"ח | J502: חו"ל | K502: גלובלי | L502: סחיר | M502: אחר | N502: Energy Equipment & Services | O502: לא | P502: B+ | Q502: S&P | R502: נייר ערך | S502: USD | T502: 2.62 | U502: 30/04/2027 | V502: 0.065 | W502: 0.0848 | X502: החוב לא נחות | Y502: לא | Z502: 800000 | AA502: 3.681 | AB502: 94.329 | AD502: 2857.555 | AG502: שווי הוגן | AH502: 0.001778 | AI502: 0.011913956 | AJ502: 0.0027811846
A503: 337 | B503: 9963 | C503: Energean plc | D503: 549300RVMKU0CYUZBB05 | E503: LEI | F503: ENOIGA 5 3/8 30/03/28 | G503: IL0011736738 | H503: ISIN | I503: צמוד למט"ח | J503: חו"ל | K503: גלובלי | L503: סחיר | M503: אחר | N503: חיפושי נפט וגז | O503: לא | P503: Ba3 | Q503: Moodys | R503: נייר ערך | S503: USD | T503: 3.63 | U503: 30/03/2028 | V503: 0.05375 | W503: 0.0892 | X503: החוב לא נחות | Y503: לא | Z503: 400000 | AA503: 3.681 | AB503: 91.602 | AC503: 10.75 | AD503: 1388.319 | AG503: שווי הוגן | AH503: 0.00064 | AI503: 0.0057882924 | AJ503: 0.0013512145
A504: 337 | B504: 9963 | C504: Energean plc | D504: 549300RVMKU0CYUZBB05 | E504: LEI | F504: ENOIGA 5 7/8 30/03/31 | G504: IL0011736811 | H504: ISIN | I504: צמוד למט"ח | J504: חו"ל | K504: גלובלי | L504: סחיר | M504: אחר | N504: חיפושי נפט וגז | O504: לא | P504: Ba3 | Q504: Moodys | R504: נייר ערך | S504: USD | T504: 5.72 | U504: 30/03/2031 | V504: 0.05875 | W504: 0.0907 | X504: החוב לא נחות | Y504: לא | Z504: 656000 | AA504: 3.681 | AB504: 87.729 | AC504: 19.27 | AD504: 2189.357 | AG504: שווי הוגן | AH504: 0.00105 | AI504: 0.0091280461 | AJ504: 0.0021308441
A505: 337 | B505: 9963 | C505: Hyundai Capital America | D505: 549300RIPPWJB5Z0FK07 | E505: LEI | F505: HYNMTR 5.6 03/30/28 | G505: US44891CCD39 | H505: ISIN | I505: צמוד למט"ח | J505: חו"ל | K505: ארה"ב | L505: סחיר | M505: אחר | N505: Textiles, Apparel & Luxury Goods | O505: לא | P505: BBB+ | Q505: Moodys | R505: נייר ערך | S505: USD | T505: 3.45 | U505: 30/03/2028 | V505: 0.056 | W505: 0.0543 | X505: החוב לא נחות | Y505: לא | Z505: 530000 | AA505: 3.681 | AB505: 101.197 | AD505: 1974.283 | AG505: שווי הוגן | AH505: 0.000663 | AI505: 0.0082313419 | AJ505: 0.0019215181
A506: 337 | B506: 9963 | C506: ITHACA ENERGY NORTH | D506: 21380057TNFLXPXBIP34 | E506: LEI | F506: IAECN 9% 07/26 | G506: USG49774AB18 | H506: ISIN | I506: צמוד למט"ח | J506: חו"ל | K506: בריטניה | L506: סחיר | M506: אחר | N506: Energy Equipment & Services | O506: לא | P506: B3 | Q506: Moodys | R506: נייר ערך | S506: USD | T506: 1.16 | U506: 15/07/2026 | V506: 0.09 | W506: 0.08178 | X506: החוב לא נחות | Y506: לא | Z506: 1315000 | AA506: 3.681 | AB506: 100.85 | AD506: 4972.419 | AG506: שווי הוגן | AH506: 0.002104 | AI506: 0.020731419 | AJ506: 0.0048395266
A507: 337 | B507: 9963 | C507: JPMORGAN CHASE | D507: 8I5DZWZKVSZI1NUHU748 | E507: LEI | F507: JPM 4.912 07/25/33 | G507: US46647PDH64 | H507: ISIN | I507: צמוד למט"ח | J507: חו"ל | K507: ארה"ב | L507: סחיר | M507: אחר | N507: Banks | O507: לא | P507: A- | Q507: Moodys | R507: נייר ערך | S507: USD | T507: 6.63 | U507: 25/07/2033 | V507: 0.04912 | W507: 0.05599 | X507: החוב לא נחות | Y507: לא | Z507: 286000 | AA507: 3.681 | AB507: 97.836 | AD507: 1039.321 | AG507: שווי הוגן | AH507: 8.2e-05 | AI507: 0.0043332228 | AJ507: 0.0010115442
A508: 337 | B508: 9963 | C508: בנק לאומי לישראל בע"מ | D508: 520018078 | E508: ח.פ | F508: LUMIIT 3.275 01/29/31 | G508: IL0060404899 | H508: ISIN | I508: צמוד למט"ח | J508: ישראל | K508: ישראל | L508: סחיר | M508: אחר | N508: Banks | O508: לא | P508: BBB | Q508: S&P | R508: נייר ערך | S508: USD | T508: 1.69 | U508: 29/01/2031 | V508: 0.03275 | W508: 0.06581 | X508: החוב לא נחות | Y508: לא | Z508: 243000 | AA508: 3.681 | AB508: 92.834 | AD508: 835.347 | AG508: שווי הוגן | AH508: 0.000324 | AI508: 0.0034827966 | AJ508: 0.00081302137
A509: 337 | B509: 9963 | C509: לוויתן בונד בע"מ | D509: 516223864 | E509: ח.פ | F509: LVIATH 6.5 30/06/27 | G509: IL0011677825 | H509: ISIN | I509: צמוד למט"ח | J509: ישראל | K509: ישראל | L509: סחיר | M509: אחר | N509: Energy Equipment & Services | O509: לא | P509: BB- | Q509: אחר | R509: מנפיק | S509: USD | T509: 2.79 | U509: 30/06/2027 | V509: 0.065 | W509: 0.07799 | X509: החוב לא נחות | Y509: לא | Z509: 162000 | AA509: 3.681 | AB509: 96.843 | AD509: 587.186 | AG509: שווי הוגן | AH509: 0.00027 | AI509: 0.0024481457 | AJ509: 0.00057149325
A510: 337 | B510: 9963 | C510: AP MOLLER- MAERSK A/S | D510: 549300D2K6PKKKXVNN73 | E510: LEI | F510: MAERSK 5 7/8 14/09/33 | G510: USK0479SAG32 | H510: ISIN | I510: צמוד למט"ח | J510: חו"ל | K510: דנמרק | L510: סחיר | M510: אחר | N510: Transportation Infrastructure | O510: לא | P510: Baa1 | Q510: Moodys | R510: נייר ערך | S510: USD | T510: 7.02 | U510: 14/09/2033 | V510: 0.05875 | W510: 0.05588 | X510: החוב לא נחות | Y510: לא | Z510: 526000 | AA510: 3.681 | AB510: 102.749 | AD510: 1994.488 | AG510: שווי הוגן | AH510: 0.000701 | AI510: 0.0083155836 | AJ510: 0.0019411834
A511: 337 | B511: 9963 | C511: Macquarie Group TLD | D511: ACMHD8HWFMFUIQQ8Y590 | E511: LEI | F511: MQGAU 5.887 06/15/34 | G511: US55608KBN46 | H511: ISIN | I511: צמוד למט"ח | J511: חו"ל | K511: ארה"ב | L511: סחיר | M511: אחר | N511: Diversified Financial Services Financial Services | O511: לא | P511: BBB+ | Q511: Moodys | R511: נייר ערך | S511: USD | T511: 6.92 | U511: 15/06/2034 | V511: 0.05887 | W511: 0.05811 | X511: החוב לא נחות | Y511: לא | Z511: 544000 | AA511: 3.681 | AB511: 102.133 | AD511: 2079.56 | AG511: שווי הוגן | AH511: 0.000725 | AI511: 0.0086702718 | AJ511: 0.0020239816
A512: 337 | B512: 9963 | C512: בנק מזרחי טפחות בע"מ | D512: 520000522 | E512: ח.פ | F512: MZRHIT 3.077 04/07/31 | G512: IL0069508369 | H512: ISIN | I512: צמוד למט"ח | J512: ישראל | K512: ישראל | L512: סחיר | M512: אחר | N512: Banks | O512: לא | P512: BBB- | Q512: S&P מעלות | R512: מנפיק | S512: USD | T512: 1.87 | U512: 07/04/2031 | V512: 0.03077 | W512: 0.07118 | X512: החוב לא נחות | Y512: לא | Z512: 243000 | AA512: 3.681 | AB512: 91.664 | AD512: 833.145 | AG512: שווי הוגן | AH512: 0.000405 | AI512: 0.0034736183 | AJ512: 0.00081087877
A513: 337 | B513: 9963 | C513: OMEGA HEALTHCARE IN | D513: 549300OJ7ENK42CZ8E73 | E513: LEI | F513: OHI 3 3/8 01/02/31 | G513: US681936BM17 | H513: ISIN | I513: צמוד למט"ח | J513: חו"ל | K513: ארה"ב | L513: סחיר | M513: אחר | N513: Real Estate Management & Development | O513: לא | P513: BBB- | Q513: אחר | R513: מנפיק | S513: USD | T513: 5.85 | U513: 01/02/2031 | V513: 0.03375 | W513: 0.06157 | X513: החוב לא נחות | Y513: לא | Z513: 650000 | AA513: 3.681 | AB513: 85.454 | AD513: 2057.849 | AG513: שווי הוגן | AH513: 0.000929 | AI513: 0.0085797557 | AJ513: 0.0020028516
A514: 337 | B514: 9963 | C514: PROSPECT CAPITAL CORP | D514: 549300FSD8T39P5Q0O47 | E514: LEI | F514: PSEC 3.364% 11/26 | G514: US74348TAV44 | H514: ISIN | I514: צמוד למט"ח | J514: חו"ל | K514: ארה"ב | L514: סחיר | M514: אחר | N514: Diversified Financial Services Financial Services | O514: לא | P514: Baa3 | Q514: Moodys | R514: נייר ערך | S514: USD | T514: 2.39 | U514: 15/11/2026 | V514: 0.03364 | W514: 0.06959 | X514: החוב לא נחות | Y514: לא | Z514: 320000 | AA514: 3.681 | AB514: 91.462 | AD514: 1092.209 | AG514: שווי הוגן | AH514: 0.001067 | AI514: 0.0045537264 | AJ514: 0.0010630184
A515: 337 | B515: 9963 | C515: SANTANDER HOLDINGS USA | D515: 549300SMVCQN2P0O6I58 | E515: LEI | F515: SANUSA 6.565 06/12/29 | G515: US80282KBG04 | H515: ISIN | I515: צמוד למט"ח | J515: חו"ל | K515: ארה"ב | L515: סחיר | M515: אחר | N515: Banks | O515: לא | P515: Baa2 | Q515: Moodys | R515: נייר ערך | S515: USD | T515: 3.55 | U515: 12/06/2029 | V515: 0.06565 | W515: 0.06211 | X515: החוב לא נחות | Y515: לא | Z515: 298000 | AA515: 3.681 | AB515: 103.237 | AD515: 1154.05 | AG515: שווי הוגן | AH515: 0.000596 | AI515: 0.0048115607 | AJ515: 0.001123207
A516: 337 | B516: 9963 | C516: Summit Properties Limited | D516: 213800KLWIACHRBYR158 | E516: LEI | F516: SMTPLN 2 01/31/25 | G516: XS1757821688 | H516: ISIN | I516: צמוד למט"ח | J516: חו"ל | K516: גרמניה | L516: סחיר | M516: אחר | N516: Real Estate Management & Development | O516: לא | P516: Ba1 | Q516: אחר | R516: מנפיק | S516: EUR | T516: 0.77 | U516: 31/01/2025 | V516: 0.02 | W516: 0.0763 | X516: החוב לא נחות | Y516: לא | Z516: 214000 | AA516: 3.979 | AB516: 95.576 | AD516: 816.694 | AG516: שווי הוגן | AH516: 0.000713 | AI516: 0.003405029 | AJ516: 0.00079486735
...

Sheet מניות מבכ ויהש
A1: מספר קופה/קרן/ח.פ. עבור חברת ביטוח | B1: מספר מסלול | C1: שם מנפיק | D1: מספר מנפיק | E1: סוג מספר מזהה מנפיק | F1: שם נייר ערך | G1: מספר נייר ערך | H1: סוג מספר נייר ערך | I1: מאפיין עיקרי | J1: ישראל/חו"ל | K1: מדינה לפי חשיפה כלכלית | L1: סטאטוס סחירות | M1: זירת מסחר | N1: ענף מסחר | O1: בעל עניין/צד קשור | P1: מטבע פעילות | Q1: ערך נקוב (יחידות) | R1: שער חליפין | S1: שער נייר הערך | T1: סכום לקבל (במטבע הפעילות) | U1: שווי הוגן (באלפי ש"ח) | V1: שיעור מערך נקוב מונפק | W1: שיעור מנכסי אפיק ההשקעה | X1: שיעור מסך נכסי ההשקעה | Y1: שער נייר הערך
A2: 337 | B2: 1405 | C2: אלביט מערכות בע"מ | D2: 520043027 | E2: ח.פ | F2: אלביט מערכות | G2: IL0010811243 | H2: ISIN | I2: מניות | J2: ישראל | K2: ישראל | L2: סחיר | M2: TASE | N2: ביטחוניות | O2: לא | P2: ILS | Q2: 46 | R2: 1 | S2: 77500 | U2: 35.65 | V2: 1e-06 | W2: 0.28235929 | X2: 0.0033717065 | Y2: 77500 | Z2: =(U2-T2*R2)/R2/Q2*100000 -> 77500
A3: 337 | B3: 1405 | C3: הפניקס אחזקות בע"מ | D3: 520017450 | E3: ח.פ | F3: הפניקס | G3: IL0007670123 | H3: ISIN | I3: מניות | J3: ישראל | K3: ישראל | L3: סחיר | M3: TASE | N3: ביטוח | O3: לא | P3: ILS | Q3: 500 | R3: 1 | S3: 3810 | U3: 19.05 | V3: 2e-06 | W3: 0.15088203 | X3: 0.0018017113 | Y3: 3810 | Z3: =(U3-T3*R3)/R3/Q3*100000 -> 3810
A4: 337 | B4: 1405 | C4: בנק לאומי לישראל בע"מ | D4: 520018078 | E4: ח.פ | F4: לאומי | G4: IL0006046119 | H4: ISIN | I4: מניות | J4: ישראל | K4: ישראל | L4: סחיר | M4: TASE | N4: בנקים | O4: לא | P4: ILS | Q4: 600 | R4: 1 | S4: 3100 | T4: 0.144 | U4: 18.744 | V4: 0 | W4: 0.14845699 | X4: 0.0017727534 | Y4: 3100 | Z4: =(U4-T4*R4)/R4/Q4*100000 -> 3100
A5: 337 | B5: 1405 | C5: מבנה נדל"ן (כ.ד) בע"מ | D5: 520024126 | E5: ח.פ | F5: מבנה | G5: IL0002260193 | H5: ISIN | I5: מניות | J5: ישראל | K5: ישראל | L5: סחיר | M5: TASE | N5: נדל"ן מניב בישראל | O5: לא | P5: ILS | Q5: 1000 | R5: 1 | S5: 907.1 | U5: 9.071 | V5: 1e-06 | W5: 0.071845194 | X5: 0.00085791724 | Y5: 907.1 | Z5: =(U5-T5*R5)/R5/Q5*100000 -> 907.1
A6: 337 | B6: 1405 | C6: קבוצת עזריאלי בע"מ (לשעבר קנית מימון) | D6: 510960719 | E6: ח.פ | F6: עזריאלי קבוצה | G6: IL0011194789 | H6: ISIN | I6: מניות | J6: ישראל | K6: ישראל | L6: סחיר | M6: TASE | N6: נדל"ן מניב בישראל | O6: לא | P6: ILS | Q6: 50 | R6: 1 | S6: 26610 | U6: 13.305 | V6: 0 | W6: 0.10537981 | X6: 0.0012583606 | Y6: 26610 | Z6: =(U6-T6*R6)/R6/Q6*100000 -> 26610
A7: 337 | B7: 1405 | C7: פוקס-ויזל בע"מ | D7: 512157603 | E7: ח.פ | F7: פוקס- ויזל | G7: IL0010870223 | H7: ISIN | I7: מניות | J7: ישראל | K7: ישראל | L7: סחיר | M7: TASE | N7: רשתות שיווק | O7: לא | P7: ILS | Q7: 20 | R7: 1 | S7: 34140 | U7: 6.828 | V7: 1e-06 | W7: 0.054079923 | X7: 0.00064577873 | Y7: 34140 | Z7: =(U7-T7*R7)/R7/Q7*100000 -> 34140
A8: 337 | B8: 1405 | C8: רשת חנויות רמי לוי שיווק השיקמה 2006 בע"מ | D8: 513770669 | E8: ח.פ | F8: רמי לוי | G8: IL0011042491 | H8: ISIN | I8: מניות | J8: ישראל | K8: ישראל | L8: סחיר | M8: TASE | N8: רשתות שיווק | O8: לא | P8: ILS | Q8: 48 | R8: 1 | S8: 22050 | U8: 10.584 | V8: 3e-06 | W8: 0.083828633 | X8: 0.0010010138 | Y8: 22050 | Z8: =(U8-T8*R8)/R8/Q8*100000 -> 22050
A9: 337 | B9: 1405 | C9: רני צים מרכזי קניות בע"מ | D9: 514353671 | E9: ח.פ | F9: רני צים | G9: IL0011436198 | H9: ISIN | I9: מניות | J9: ישראל | K9: ישראל | L9: סחיר | M9: TASE | N9: נדל"ן מניב בישראל | O9: לא | P9: ILS | Q9: 1478 | R9: 1 | S9: 266.1705 | U9: 3.934 | V9: 1e-05 | W9: 0.03116198 | X9: 0.00037211117 | Y9: 266.2 | Z9: =(U9-T9*R9)/R9/Q9*100000 -> 266.1705
A10: 337 | B10: 1405 | C10: תדיראן גרופ בע"מ | D10: 520036732 | E10: ח.פ | F10: תדיראן גרופ | G10: IL0002580129 | H10: ISIN | I10: מניות | J10: ישראל | K10: ישראל | L10: סחיר | M10: TASE | N10: מסחר | O10: לא | P10: ILS | Q10: 30 | R10: 1 | S10: 30040 | T10: 0.079 | U10: 9.091 | V10: 3e-06 | W10: 0.072006135 | X10: 0.00085983906 | Y10: 30040 | Z10: =(U10-T10*R10)/R10/Q10*100000 -> 30040
A11: 337 | B11: 1477 | C11: או.פי.סי. אנרגיה בע"מ | D11: 514401702 | E11: ח.פ | F11: או פי סי אנרגיה | G11: IL0011415713 | H11: ISIN | I11: מניות | J11: ישראל | K11: ישראל | L11: סחיר | M11: TASE | N11: אנרגיה | O11: לא | P11: ILS | Q11: 382 | R11: 1 | S11: 2615.9686 | U11: 9.993 | V11: 2e-06 | W11: 0.0036216102 | X11: 0.0010019213 | Y11: 2616 | Z11: =(U11-T11*R11)/R11/Q11*100000 -> 2615.9686
A12: 337 | B12: 1477 | C12: אטראו שוקי הון בע"מ לשעבר לידר | D12: 513773564 | E12: ח.פ | F12: אטראו שוקי הון | G12: IL0010961063 | H12: ISIN | I12: מניות | J12: ישראל | K12: ישראל | L12: סחיר | M12: TASE | N12: שירותים פיננסיים | O12: לא | P12: ILS | Q12: 457 | R12: 1 | S12: 5664.9891 | U12: 25.889 | V12: 3.1e-05 | W12: 0.0093824599 | X12: 0.0025956648 | Y12: 5665 | Z12: =(U12-T12*R12)/R12/Q12*100000 -> 5664.9891
A13: 337 | B13: 1477 | C13: אי.טי.גי. איי גרופ בע"מ | D13: 513764399 | E13: ח.פ | F13: אי. טי. ג'י. איי | G13: IL0011761140 | H13: ISIN | I13: מניות | J13: ישראל | K13: ישראל | L13: סחיר | M13: TASE | N13: שירותים | O13: לא | P13: ILS | Q13: 185 | R13: 1 | S13: 1050.2703 | T13: 0.029 | U13: 1.972 | V13: 8e-06 | W13: 0.000714579 | X13: 0.00019768884 | Y13: 1050 | Z13: =(U13-T13*R13)/R13/Q13*100000 -> 1050.2703
A14: 337 | B14: 1477 | C14: איי.סי.אל גרופ בע"מ (דואלי) | D14: 520027830 | E14: ח.פ | F14: איי.סי.אל | G14: IL0002810146 | H14: ISIN | I14: מניות | J14: ישראל | K14: ישראל | L14: סחיר | M14: TASE | N14: כימיה, גומי ופלסטיק | O14: לא | P14: ILS | Q14: 2525 | R14: 1 | S14: 1951.0099 | U14: 49.263 | V14: 2e-06 | W14: 0.017853331 | X14: 0.0049391379 | Y14: 1951 | Z14: =(U14-T14*R14)/R14/Q14*100000 -> 1951.0099
A15: 337 | B15: 1477 | C15: אינרום תעשיות בנייה בע"מ | D15: 515001659 | E15: ח.פ | F15: אינרום חסום 06.08.24 | G15: IL0011323560 | H15: ISIN | I15: מניות | J15: ישראל | K15: ישראל | L15: חסום | M15: TASE | N15: מתכת ומוצרי בניה | O15: לא | P15: ILS | Q15: 1000 | R15: 1 | S15: 1172.3 | U15: 11.723 | V15: 7e-06 | W15: 0.0042484051 | X15: 0.0011753246 | Y15: 1172.264 | Z15: =(U15-T15*R15)/R15/Q15*100000 -> 1172.3
A16: 337 | B16: 1477 | C16: איסתא בע"מ | D16: 520042763 | E16: ח.פ | F16: איסתא | G16: IL0010810740 | H16: ISIN | I16: מניות | J16: ישראל | K16: ישראל | L16: סחיר | M16: TASE | N16: מלונאות ותיירות | O16: לא | P16: ILS | Q16: 113 | R16: 1 | S16: 8312.3894 | U16: 9.393 | V16: 7e-06 | W16: 0.003403961 | X16: 0.00094170847 | Y16: 8312 | Z16: =(U16-T16*R16)/R16/Q16*100000 -> 8312.3894
A17: 337 | B17: 1477 | C17: אלביט מערכות בע"מ | D17: 520043027 | E17: ח.פ | F17: אלביט מערכות | G17: IL0010811243 | H17: ISIN | I17: מניות | J17: ישראל | K17: ישראל | L17: סחיר | M17: TASE | N17: ביטחוניות | O17: לא | P17: ILS | Q17: 69 | R17: 1 | S17: 77500 | U17: 53.475 | V17: 2e-06 | W17: 0.019379894 | X17: 0.0053614628 | Y17: 77500 | Z17: =(U17-T17*R17)/R17/Q17*100000 -> 77500
A18: 337 | B18: 1477 | C18: אלקטרה נדל"ן בע"מ | D18: 510607328 | E18: ח.פ | F18: אלקטרה נדלן | G18: IL0010940448 | H18: ISIN | I18: מניות | J18: ישראל | K18: ישראל | L18: סחיר | M18: TASE | N18: נדל"ן מניב בחו"ל | O18: לא | P18: ILS | Q18: 417 | R18: 1 | S18: 3879.8561 | T18: 0.139 | U18: 16.318 | V18: 7e-06 | W18: 0.0059139608 | X18: 0.0016361019 | Y18: 3880 | Z18: =(U18-T18*R18)/R18/Q18*100000 -> 3879.8561
A19: 337 | B19: 1477 | C19: אמות השקעות בע"מ | D19: 520026683 | E19: ח.פ | F19: אמות | G19: IL0010972789 | H19: ISIN | I19: מניות | J19: ישראל | K19: ישראל | L19: סחיר | M19: TASE | N19: נדל"ן מניב בישראל | O19: לא | P19: ILS | Q19: 1860 | R19: 1 | S19: 1748.9785 | U19: 32.531 | V19: 4e-06 | W19: 0.011789716 | X19: 0.0032616342 | Y19: 1749 | Z19: =(U19-T19*R19)/R19/Q19*100000 -> 1748.9785
A20: 337 | B20: 1477 | C20: אנלייט אנרגיה מתחדשת בע"מ | D20: 520041146 | E20: ח.פ | F20: אנלייט אנרגיה | G20: IL0007200111 | H20: ISIN | I20: מניות | J20: ישראל | K20: ישראל | L20: סחיר | M20: TASE | N20: אנרגיה מתחדשת | O20: לא | P20: ILS | Q20: 949.3 | R20: 1 | S20: 6298.9571 | U20: 59.796 | V20: 8e-06 | W20: 0.021670837 | X20: 0.005995254 | Y20: 6299 | Z20: =(U20-T20*R20)/R20/Q20*100000 -> 6298.9571
A21: 337 | B21: 1477 | C21: אנרג'יקס אנרגיות מתחדשות בע"מ | D21: 513901371 | E21: ח.פ | F21: אנרג'יקס | G21: IL0011233553 | H21: ISIN | I21: מניות | J21: ישראל | K21: ישראל | L21: סחיר | M21: TASE | N21: אנרגיה מתחדשת | O21: לא | P21: ILS | Q21: 1032 | R21: 1 | S21: 1352.0349 | U21: 13.953 | V21: 2e-06 | W21: 0.0050565813 | X21: 0.0013989071 | Y21: 1352 | Z21: =(U21-T21*R21)/R21/Q21*100000 -> 1352.0349
A22: 337 | B22: 1477 | C22: ארגו פרופרטיז אן. וי | D22: 724500VWIAC6N6VHCK55 | E22: LEI | F22: ארגו פרופרטיז אן. וי | G22: NL0015000D84 | H22: ISIN | I22: מניות | J22: חו"ל | K22: גרמניה | L22: סחיר | M22: TASE | N22: נדל"ן מניב בחו"ל | O22: לא | P22: ILS | Q22: 112 | R22: 1 | S22: 7563.3929 | U22: 8.471 | V22: 6e-06 | W22: 0.0030698187 | X22: 0.00084926773 | Y22: 7563 | Z22: =(U22-T22*R22)/R22/Q22*100000 -> 7563.3929
A23: 337 | B23: 1477 | C23: ארד בע"מ | D23: 510007800 | E23: ח.פ | F23: ארד | G23: IL0010916513 | H23: ISIN | I23: מניות | J23: ישראל | K23: ישראל | L23: סחיר | M23: TASE | N23: אלקטרוניקה ואופטיקה | O23: לא | P23: ILS | Q23: 204 | R23: 1 | S23: 5100 | U23: 10.404 | V23: 8e-06 | W23: 0.0037705174 | X23: 0.0010431166 | Y23: 5100 | Z23: =(U23-T23*R23)/R23/Q23*100000 -> 5100
A24: 337 | B24: 1477 | C24: בזק החברה הישראלית לתקשורת בע"מ | D24: 520031931 | E24: ח.פ | F24: בזק | G24: IL0002300114 | H24: ISIN | I24: מניות | J24: ישראל | K24: ישראל | L24: סחיר | M24: TASE | N24: תקשורת ומדיה | O24: לא | P24: ILS | Q24: 11240 | R24: 1 | S24: 472.99822 | U24: 53.165 | V24: 4e-06 | W24: 0.019267619 | X24: 0.0053304019 | Y24: 473 | Z24: =(U24-T24*R24)/R24/Q24*100000 -> 472.99822
A25: 337 | B25: 1477 | C25: ביג מרכזי קניות (2004) בע"מ | D25: 513623314 | E25: ח.פ | F25: ביג | G25: IL0010972607 | H25: ISIN | I25: מניות | J25: ישראל | K25: ישראל | L25: סחיר | M25: TASE | N25: נדל"ן מניב בישראל | O25: לא | P25: ILS | Q25: 161 | R25: 1 | S25: 41029.814 | U25: 66.058 | V25: 7e-06 | W25: 0.023940212 | X25: 0.0066230784 | Y25: 41030 | Z25: =(U25-T25*R25)/R25/Q25*100000 -> 41029.814
A26: 337 | B26: 1477 | C26: הבנק הבינלאומי הראשון לישראל בע"מ | D26: 520029083 | E26: ח.פ | F26: בינלאומי 5 | G26: IL0005930388 | H26: ISIN | I26: מניות | J26: ישראל | K26: ישראל | L26: סחיר | M26: TASE | N26: בנקים | O26: לא | P26: ILS | Q26: 545 | R26: 1 | S26: 15440 | U26: 84.148 | V26: 5e-06 | W26: 0.030496107 | X26: 0.0084367717 | Y26: 15440 | Z26: =(U26-T26*R26)/R26/Q26*100000 -> 15440
A27: 337 | B27: 1477 | C27: בית בכפר בע"מ | D27: 511605719 | E27: ח.פ | F27: בית בכפר | G27: IL0011836561 | H27: ISIN | I27: מניות | J27: ישראל | K27: ישראל | L27: סחיר | M27: TASE | N27: נדל"ן מניב בישראל | O27: לא | P27: ILS | Q27: 542 | R27: 1 | S27: 1161.0701 | U27: 6.293 | V27: 8e-06 | W27: 0.0022805107 | X27: 0.00063090505 | Y27: 1161 | Z27: =(U27-T27*R27)/R27/Q27*100000 -> 1161.0701
A28: 337 | B28: 1477 | C28: מנועי בית שמש אחזקות (1997) בע"מ | D28: 520043480 | E28: ח.פ | F28: בית שמש | G28: IL0010815616 | H28: ISIN | I28: מניות | J28: ישראל | K28: ישראל | L28: סחיר | M28: TASE | N28: מתכת ומוצרי בניה | O28: לא | P28: ILS | Q28: 200 | R28: 1 | S28: 14790 | U28: 29.58 | V28: 2.3e-05 | W28: 0.010720098 | X28: 0.0029657236 | Y28: 14790 | Z28: =(U28-T28*R28)/R28/Q28*100000 -> 14790
A29: 337 | B29: 1477 | C29: חברת גב-ים לקרקעות בע"מ | D29: 520001736 | E29: ח.פ | F29: גב ים | G29: IL0007590198 | H29: ISIN | I29: מניות | J29: ישראל | K29: ישראל | L29: סחיר | M29: TASE | N29: נדל"ן מניב בישראל | O29: לא | P29: ILS | Q29: 348 | R29: 1 | S29: 2779.8851 | U29: 9.674 | V29: 0.000173 | W29: 0.0035061028 | X29: 0.00096996606 | Y29: 2780 | Z29: =(U29-T29*R29)/R29/Q29*100000 -> 2779.8851
A30: 337 | B30: 1477 | C30: בנק דיסקונט לישראל בע"מ | D30: 520007030 | E30: ח.פ | F30: דיסקונט | G30: IL0006912120 | H30: ISIN | I30: מניות | J30: ישראל | K30: ישראל | L30: סחיר | M30: TASE | N30: בנקים | O30: לא | P30: ILS | Q30: 4067 | R30: 1 | S30: 1946.0044 | T30: 0.604 | U30: 79.748 | V30: 3e-06 | W30: 0.028901541 | X30: 0.0079956339 | Y30: 1946 | Z30: =(U30-T30*R30)/R30/Q30*100000 -> 1946.0044
A31: 337 | B31: 1477 | C31: דיפלומט אחזקות בע"מ | D31: 510400740 | E31: ח.פ | F31: דיפלומט | G31: IL0011734915 | H31: ISIN | I31: מניות | J31: ישראל | K31: ישראל | L31: סחיר | M31: TASE | N31: מסחר | O31: לא | P31: ILS | Q31: 378 | R31: 1 | S31: 3408.9947 | U31: 12.886 | V31: 1.4e-05 | W31: 0.0046700271 | X31: 0.0012919666 | Y31: 3409 | Z31: =(U31-T31*R31)/R31/Q31*100000 -> 3408.9947
A32: 337 | B32: 1477 | C32: דנאל (אדיר יהושע) בע"מ | D32: 520037565 | E32: ח.פ | F32: דנאל כא | G32: IL0003140139 | H32: ISIN | I32: מניות | J32: ישראל | K32: ישראל | L32: סחיר | M32: TASE | N32: שירותים | O32: לא | P32: ILS | Q32: 15 | R32: 1 | S32: 33193.333 | U32: 4.979 | V32: 3e-06 | W32: 0.00180426 | X32: 0.00049914993 | Y32: 33190 | Z32: =(U32-T32*R32)/R32/Q32*100000 -> 33193.333
A33: 337 | B33: 1477 | C33: הפניקס אחזקות בע"מ | D33: 520017450 | E33: ח.פ | F33: הפניקס | G33: IL0007670123 | H33: ISIN | I33: מניות | J33: ישראל | K33: ישראל | L33: סחיר | M33: TASE | N33: ביטוח | O33: לא | P33: ILS | Q33: 2150 | R33: 1 | S33: 3810 | U33: 81.915 | V33: 8e-06 | W33: 0.029686844 | X33: 0.0082128887 | Y33: 3810 | Z33: =(U33-T33*R33)/R33/Q33*100000 -> 3810
A34: 337 | B34: 1477 | C34: וואן טכנולוגיות תוכנה(או.אס.טי)בע"מ | D34: 520034695 | E34: ח.פ | F34: וואן טכנולוגיות תוכנה | G34: IL0001610182 | H34: ISIN | I34: מניות | J34: ישראל | K34: ישראל | L34: סחיר | M34: TASE | N34: שירותי מידע | O34: לא | P34: ILS | Q34: 794 | R34: 1 | S34: 5624.937 | T34: 0.361 | U34: 45.023 | V34: 1.1e-05 | W34: 0.016316914 | X34: 0.004514087 | Y34: 5625 | Z34: =(U34-T34*R34)/R34/Q34*100000 -> 5624.937
A35: 337 | B35: 1477 | C35: חג'ג' אירופה דיוולופמנט צ.ש. בע"מ | D35: 515682292 | E35: ח.פ | F35: חג'ג' אירופה | G35: IL0011436354 | H35: ISIN | I35: מניות | J35: ישראל | K35: אירופה | L35: סחיר | M35: TASE | N35: בנייה | O35: לא | P35: ILS | Q35: 300 | R35: 1 | S35: 546.33333 | U35: 1.639 | V35: 7e-06 | W35: 0.00059406306 | X35: 0.00016434801 | Y35: 546.4 | Z35: =(U35-T35*R35)/R35/Q35*100000 -> 546.33333
A36: 337 | B36: 1477 | C36: קבוצת חג'ג' ייזום נדל"ן בע"מ | D36: 520033309 | E36: ח.פ | F36: חג'ג' נדלן | G36: IL0008230133 | H36: ISIN | I36: מניות | J36: ישראל | K36: ישראל | L36: סחיר | M36: TASE | N36: בנייה | O36: לא | P36: ILS | Q36: 432 | R36: 1 | S36: 1596.0648 | U36: 6.895 | V36: 7e-06 | W36: 0.0024987179 | X36: 0.00069127227 | Y36: 1596 | Z36: =(U36-T36*R36)/R36/Q36*100000 -> 1596.0648
A37: 337 | B37: 1477 | C37: חילן בע"מ | D37: 520039942 | E37: ח.פ | F37: חילן | G37: IL0010846983 | H37: ISIN | I37: מניות | J37: ישראל | K37: ישראל | L37: סחיר | M37: TASE | N37: שירותי מידע | O37: לא | P37: ILS | Q37: 87 | R37: 1 | S37: 23459.77 | U37: 20.41 | V37: 4e-06 | W37: 0.0073968679 | X37: 0.0020463493 | Y37: 23460 | Z37: =(U37-T37*R37)/R37/Q37*100000 -> 23459.77
A38: 337 | B38: 1477 | C38: קבוצת חמת בע"מ | D38: 520038530 | E38: ח.פ | F38: חמת | G38: IL0003840167 | H38: ISIN | I38: מניות | J38: ישראל | K38: ישראל | L38: סחיר | M38: TASE | N38: מתכת ומוצרי בניה | O38: לא | P38: ILS | Q38: 1062 | R38: 1 | S38: 1254.9906 | U38: 13.328 | V38: 2.9e-05 | W38: 0.0048302415 | X38: 0.0013362901 | Y38: 1255 | Z38: =(U38-T38*R38)/R38/Q38*100000 -> 1254.9906
A39: 337 | B39: 1477 | C39: טאואר סמיקונדקטור בע"מ | D39: 520041997 | E39: ח.פ | F39: טאואר | G39: IL0010823792 | H39: ISIN | I39: מניות | J39: ישראל | K39: ישראל | L39: סחיר | M39: TASE | N39: מוליכים למחצה | O39: לא | P39: ILS | Q39: 292 | R39: 1 | S39: 12309.932 | U39: 35.945 | V39: 3e-06 | W39: 0.013026913 | X39: 0.0036039056 | Y39: 12310 | Z39: =(U39-T39*R39)/R39/Q39*100000 -> 12309.932
A40: 337 | B40: 1477 | C40: טבע תעשיות פרמצבטיות בע"מ | D40: 520013954 | E40: ח.פ | F40: טבע | G40: IL0006290147 | H40: ISIN | I40: מניות | J40: ישראל | K40: ישראל | L40: סחיר | M40: TASE | N40: פארמה | O40: לא | P40: ILS | Q40: 2024 | R40: 1 | S40: 5173.0237 | U40: 104.702 | V40: 2e-06 | W40: 0.037944915 | X40: 0.01049749 | Y40: 5173 | Z40: =(U40-T40*R40)/R40/Q40*100000 -> 5173.0237
A41: 337 | B41: 1477 | C41: טיב טעם הולדינגס 1 בע"מ | D41: 520041187 | E41: ח.פ | F41: טיב טעם | G41: IL0001030100 | H41: ISIN | I41: מניות | J41: ישראל | K41: ישראל | L41: סחיר | M41: TASE | N41: רשתות שיווק | O41: לא | P41: ILS | Q41: 4200 | R41: 1 | S41: 511 | U41: 21.462 | V41: 3.9e-05 | W41: 0.0077780511 | X41: 0.0021518039 | Y41: 511 | Z41: =(U41-T41*R41)/R41/Q41*100000 -> 511
A42: 337 | B42: 1477 | C42: ישראמקו נגב 2 שותפות מוגבלת | D42: 550010003 | E42: ח.פ | F42: ישראמקו יהש | G42: IL0002320179 | H42: ISIN | I42: מניות | J42: ישראל | K42: ישראל | L42: סחיר | M42: TASE | N42: חיפושי נפט וגז | O42: לא | P42: ILS | Q42: 6100 | R42: 1 | S42: 179 | U42: 10.919 | V42: 2e-06 | W42: 0.0039571587 | X42: 0.001094751 | Y42: 179 | Z42: =(U42-T42*R42)/R42/Q42*100000 -> 179
A43: 337 | B43: 1477 | C43: ישרוטל בע"מ | D43: 520042482 | E43: ח.פ | F43: ישרוטל | G43: IL0010809858 | H43: ISIN | I43: מניות | J43: ישראל | K43: ישראל | L43: סחיר | M43: TASE | N43: מלונאות ותיירות | O43: לא | P43: ILS | Q43: 65 | R43: 1 | S43: 8847.6923 | U43: 5.751 | V43: 1e-06 | W43: 0.0020842945 | X43: 0.00057662169 | Y43: 8848 | Z43: =(U43-T43*R43)/R43/Q43*100000 -> 8847.6923
A44: 337 | B44: 1477 | C44: בנק לאומי לישראל בע"מ | D44: 520018078 | E44: ח.פ | F44: לאומי | G44: IL0006046119 | H44: ISIN | I44: מניות | J44: ישראל | K44: ישראל | L44: סחיר | M44: TASE | N44: בנקים | O44: לא | P44: ILS | Q44: 3313 | R44: 1 | S44: 3100 | T44: 0.794 | U44: 103.497 | V44: 2e-06 | W44: 0.037508439 | X44: 0.010376739 | Y44: 3100 | Z44: =(U44-T44*R44)/R44/Q44*100000 -> 3100
A45: 337 | B45: 1477 | C45: יוחננוף | D45: 511344186 | E45: ח.פ | F45: מ. יוחננוף | G45: IL0011612640 | H45: ISIN | I45: מניות | J45: ישראל | K45: ישראל | L45: סחיר | M45: TASE | N45: רשתות שיווק | O45: לא | P45: ILS | Q45: 46 | R45: 1 | S45: 18180.435 | U45: 8.363 | V45: 3e-06 | W45: 0.0030307653 | X45: 0.0008384636 | Y45: 18180 | Z45: =(U45-T45*R45)/R45/Q45*100000 -> 18180.435
A46: 337 | B46: 1477 | C46: מבנה נדל"ן (כ.ד) בע"מ | D46: 520024126 | E46: ח.פ | F46: מבנה | G46: IL0002260193 | H46: ISIN | I46: מניות | J46: ישראל | K46: ישראל | L46: סחיר | M46: TASE | N46: נדל"ן מניב בישראל | O46: לא | P46: ILS | Q46: 5224 | R46: 1 | S46: 907.10184 | U46: 47.387 | V46: 7e-06 | W46: 0.017173505 | X46: 0.0047510635 | Y46: 907.1 | Z46: =(U46-T46*R46)/R46/Q46*100000 -> 907.10184
A47: 337 | B47: 1477 | C47: בנק מזרחי טפחות בע"מ | D47: 520000522 | E47: ח.פ | F47: מזרחי טפחות | G47: IL0006954379 | H47: ISIN | I47: מניות | J47: ישראל | K47: ישראל | L47: סחיר | M47: TASE | N47: בנקים | O47: לא | P47: ILS | Q47: 653 | R47: 1 | S47: 14000 | U47: 91.42 | V47: 3e-06 | W47: 0.033131555 | X47: 0.0091658705 | Y47: 14000 | Z47: =(U47-T47*R47)/R47/Q47*100000 -> 14000
A48: 337 | B48: 1477 | C48: מטריקס אי.טי בע"מ | D48: 520039413 | E48: ח.פ | F48: מטריקס | G48: IL0004450156 | H48: ISIN | I48: מניות | J48: ישראל | K48: ישראל | L48: סחיר | M48: TASE | N48: שירותי מידע | O48: לא | P48: ILS | Q48: 235 | R48: 1 | S48: 8160 | T48: 0.298 | U48: 19.474 | V48: 4e-06 | W48: 0.0070577424 | X48: 0.0019525299 | Y48: 8160 | Z48: =(U48-T48*R48)/R48/Q48*100000 -> 8160
A49: 337 | B49: 1477 | C49: מליסרון בע"מ | D49: 520037789 | E49: ח.פ | F49: מליסרון | G49: IL0003230146 | H49: ISIN | I49: מניות | J49: ישראל | K49: ישראל | L49: סחיר | M49: TASE | N49: נדל"ן מניב בישראל | O49: לא | P49: ILS | Q49: 206 | R49: 1 | S49: 26900 | T49: 0.52 | U49: 55.934 | V49: 4e-06 | W49: 0.02027113 | X49: 0.0056080239 | Y49: 26900 | Z49: =(U49-T49*R49)/R49/Q49*100000 -> 26900
A50: 337 | B50: 1477 | C50: מנורה מבטחים החזקות בע"מ | D50: 520007469 | E50: ח.פ | F50: מנורה מבטחים החזקות | G50: IL0005660183 | H50: ISIN | I50: מניות | J50: ישראל | K50: ישראל | L50: סחיר | M50: TASE | N50: ביטוח | O50: לא | P50: ILS | Q50: 539 | R50: 1 | S50: 9800 | U50: 52.822 | V50: 9e-06 | W50: 0.01914324 | X50: 0.0052959923 | Y50: 9800 | Z50: =(U50-T50*R50)/R50/Q50*100000 -> 9800
A51: 337 | B51: 1477 | C51: נאוויטס פטרוליום, שותפות מוגבלת | D51: 550263107 | E51: ח.פ | F51: נאוויטס פט יהש | G51: IL0011419699 | H51: ISIN | I51: מניות | J51: חו"ל | K51: ארה"ב | L51: סחיר | M51: TASE | N51: חיפושי נפט וגז | O51: לא | P51: ILS | Q51: 1088 | R51: 1 | S51: 4170.0368 | U51: 45.37 | V51: 1.2e-05 | W51: 0.016442413 | X51: 0.0045488064 | Y51: 4170 | Z51: =(U51-T51*R51)/R51/Q51*100000 -> 4170.0368
A52: 337 | B52: 1477 | C52: נובה מכשירי מדידה בע"מ | D52: 511812463 | E52: ח.פ | F52: נובה | G52: IL0010845571 | H52: ISIN | I52: מניות | J52: ישראל | K52: ישראל | L52: סחיר | M52: TASE | N52: מוליכים למחצה | O52: לא | P52: ILS | Q52: 13 | R52: 1 | S52: 64723.077 | U52: 8.414 | V52: 0 | W52: 0.0030491758 | X52: 0.00084355686 | Y52: 64720 | Z52: =(U52-T52*R52)/R52/Q52*100000 -> 64723.077
A53: 337 | B53: 1477 | C53: ע.י נופר אנרגי' בע"מ | D53: 514599943 | E53: ח.פ | F53: נופר אנרגי | G53: IL0011708778 | H53: ISIN | I53: מניות | J53: ישראל | K53: ישראל | L53: סחיר | M53: TASE | N53: אנרגיה מתחדשת | O53: לא | P53: ILS | Q53: 958 | R53: 1 | S53: 8908.0376 | U53: 85.339 | V53: 2.7e-05 | W53: 0.030927607 | X53: 0.0085561466 | Y53: 8908 | Z53: =(U53-T53*R53)/R53/Q53*100000 -> 8908.0376
A54: 337 | B54: 1477 | C54: ניו-מד אנרג'י- שותפות מוגבלת | D54: 550013098 | E54: ח.פ | F54: ניו-מד אנרג'י יהש | G54: IL0004750209 | H54: ISIN | I54: מניות | J54: ישראל | K54: ישראל | L54: סחיר | M54: TASE | N54: חיפושי נפט וגז | O54: לא | P54: ILS | Q54: 1934 | R54: 1 | S54: 935.2637 | T54: 0.371 | U54: 18.459 | V54: 2e-06 | W54: 0.0066898278 | X54: 0.0018507461 | Y54: 935.3 | Z54: =(U54-T54*R54)/R54/Q54*100000 -> 935.2637
A55: 337 | B55: 1477 | C55: נייס מערכות בע"מ | D55: 520036872 | E55: ח.פ | F55: נייס | G55: IL0002730112 | H55: ISIN | I55: מניות | J55: ישראל | K55: ישראל | L55: סחיר | M55: TASE | N55: תוכנה ואינטרנט | O55: לא | P55: ILS | Q55: 100 | R55: 1 | S55: 95150 | U55: 95.15 | V55: 2e-06 | W55: 0.034483346 | X55: 0.0095398444 | Y55: 95150 | Z55: =(U55-T55*R55)/R55/Q55*100000 -> 95150
A56: 337 | B56: 1477 | C56: חברה לנכסים ולבנין בע"מ | D56: 520025438 | E56: ח.פ | F56: נכסים ובנין | G56: IL0006990175 | H56: ISIN | I56: מניות | J56: ישראל | K56: ישראל | L56: סחיר | M56: TASE | N56: נדל"ן מניב בישראל | O56: לא | P56: ILS | Q56: 137 | R56: 1 | S56: 22540.146 | U56: 30.88 | V56: 1.9e-05 | W56: 0.011191159 | X56: 0.003096043 | Y56: 22540 | Z56: =(U56-T56*R56)/R56/Q56*100000 -> 22540.146
A57: 337 | B57: 1477 | C57: נקסט ויז'ן | D57: 514259019 | E57: ח.פ | F57: נקסט ויז'ן | G57: IL0011765935 | H57: ISIN | I57: מניות | J57: ישראל | K57: ישראל | L57: סחיר | M57: TASE | N57: אלקטרוניקה ואופטיקה | O57: לא | P57: ILS | Q57: 3126 | R57: 1 | S57: 4273.0006 | U57: 133.574 | V57: 4e-05 | W57: 0.048408594 | X57: 0.013392275 | Y57: 4273 | Z57: =(U57-T57*R57)/R57/Q57*100000 -> 4273.0006
A58: 337 | B58: 1477 | C58: סולאיר אנרגיות מתחדשות בע"מ | D58: 516046307 | E58: ח.פ | F58: סולאיר | G58: IL0011722878 | H58: ISIN | I58: מניות | J58: ישראל | K58: ישראל | L58: סחיר | M58: TASE | N58: אנרגיה מתחדשת | O58: לא | P58: ILS | Q58: 891 | R58: 1 | S58: 3478.0022 | U58: 30.989 | V58: 6.4e-05 | W58: 0.011230727 | X58: 0.0031069895 | Y58: 3478 | Z58: =(U58-T58*R58)/R58/Q58*100000 -> 3478.0022
A59: 337 | B59: 1477 | C59: סלע קפיטל נדל"ן בע"מ | D59: 513992529 | E59: ח.פ | F59: סלע נדלן | G59: IL0011096448 | H59: ISIN | I59: מניות | J59: ישראל | K59: ישראל | L59: סחיר | M59: TASE | N59: נדל"ן מניב בישראל | O59: לא | P59: ILS | Q59: 1229 | R59: 1 | S59: 773.96257 | T59: 0.169 | U59: 9.681 | V59: 6e-06 | W59: 0.0035086578 | X59: 0.00097067291 | Y59: 774 | Z59: =(U59-T59*R59)/R59/Q59*100000 -> 773.96257
A60: 337 | B60: 1477 | C60: קבוצת סקופ מתכות בע"מ | D60: 520037425 | E60: ח.פ | F60: סקופ | G60: IL0002880198 | H60: ISIN | I60: מניות | J60: ישראל | K60: ישראל | L60: סחיר | M60: TASE | N60: מסחר | O60: לא | P60: ILS | Q60: 143 | R60: 1 | S60: 13100 | U60: 18.733 | V60: 1.2e-05 | W60: 0.0067890332 | X60: 0.0018781913 | Y60: 13100 | Z60: =(U60-T60*R60)/R60/Q60*100000 -> 13100
A61: 337 | B61: 1477 | C61: קבוצת עזריאלי בע"מ (לשעבר קנית מימון) | D61: 510960719 | E61: ח.פ | F61: עזריאלי קבוצה | G61: IL0011194789 | H61: ISIN | I61: מניות | J61: ישראל | K61: ישראל | L61: סחיר | M61: TASE | N61: נדל"ן מניב בישראל | O61: לא | P61: ILS | Q61: 240 | R61: 1 | S61: 26610 | U61: 63.864 | V61: 2e-06 | W61: 0.023144975 | X61: 0.0064030754 | Y61: 26610 | Z61: =(U61-T61*R61)/R61/Q61*100000 -> 26610
A62: 337 | B62: 1477 | C62: פוםוום בע"מ | D62: 515236735 | E62: ח.פ | F62: פוםוום | G62: IL0011734345 | H62: ISIN | I62: מניות | J62: ישראל | K62: ישראל | L62: סחיר | M62: TASE | N62: תוכנה ואינטרנט | O62: לא | P62: ILS | Q62: 2079 | R62: 1 | S62: 522.89562 | U62: 10.871 | V62: 0.000147 | W62: 0.003939796 | X62: 0.0010899476 | Y62: 522.9 | Z62: =(U62-T62*R62)/R62/Q62*100000 -> 522.89562
A63: 337 | B63: 1477 | C63: בנק הפועלים בע"מ | D63: 520000118 | E63: ח.פ | F63: פועלים | G63: IL0006625771 | H63: ISIN | I63: מניות | J63: ישראל | K63: ישראל | L63: סחיר | M63: TASE | N63: בנקים | O63: לא | P63: ILS | Q63: 2501 | R63: 1 | S63: 3500 | T63: 0.658 | U63: 88.193 | V63: 2e-06 | W63: 0.031962169 | X63: 0.008842359 | Y63: 3500 | Z63: =(U63-T63*R63)/R63/Q63*100000 -> 3500
A64: 337 | B64: 1477 | C64: פוקס-ויזל בע"מ | D64: 512157603 | E64: ח.פ | F64: פוקס- ויזל | G64: IL0010870223 | H64: ISIN | I64: מניות | J64: ישראל | K64: ישראל | L64: סחיר | M64: TASE | N64: רשתות שיווק | O64: לא | P64: ILS | Q64: 66 | R64: 1 | S64: 34139.394 | U64: 22.532 | V64: 5e-06 | W64: 0.0081659752 | X64: 0.0022591234 | Y64: 34140 | Z64: =(U64-T64*R64)/R64/Q64*100000 -> 34139.394
A65: 337 | B65: 1477 | C65: פורמולה מערכות (1985)בע"מ | D65: 520036690 | E65: ח.פ | F65: פורמולה מערכות | G65: IL0002560162 | H65: ISIN | I65: מניות | J65: ישראל | K65: ישראל | L65: סחיר | M65: TASE | N65: שירותי מידע | O65: לא | P65: ILS | Q65: 29 | R65: 1 | S65: 30031.034 | U65: 8.709 | V65: 2e-06 | W65: 0.0031561231 | X65: 0.00087314391 | Y65: 30030 | Z65: =(U65-T65*R65)/R65/Q65*100000 -> 30031.034
A66: 337 | B66: 1477 | C66: פז בית זיקוק לנפט-אשדוד בע"מ | D66: 513775163 | E66: ח.פ | F66: פז בית זיקוק אשדוד | G66: IL0011989105 | H66: ISIN | I66: מניות | J66: ישראל | K66: ישראל | L66: סחיר | M66: TASE | N66: אנרגיה | O66: לא | P66: ILS | Q66: 258 | R66: 1 | S66: 8896.124 | U66: 22.952 | V66: 2.1e-05 | W66: 0.0083179266 | X66: 0.0023011609 | Y66: 8896 | Z66: =(U66-T66*R66)/R66/Q66*100000 -> 8896.124
A67: 337 | B67: 1477 | C67: פתאל החזקות 1998 בע"מ | D67: 512607888 | E67: ח.פ | F67: פתאל החזקות | G67: IL0011434292 | H67: ISIN | I67: מניות | J67: ישראל | K67: ישראל | L67: סחיר | M67: TASE | N67: מלונאות ותיירות | O67: לא | P67: ILS | Q67: 30 | R67: 1 | S67: 48200 | U67: 14.46 | V67: 2e-06 | W67: 0.0052404538 | X67: 0.0014497756 | Y67: 48200 | Z67: =(U67-T67*R67)/R67/Q67*100000 -> 48200
A68: 337 | B68: 1477 | C68: קמטק בע"מ | D68: 511235434 | E68: ח.פ | F68: קמטק | G68: IL0010952641 | H68: ISIN | I68: מניות | J68: ישראל | K68: ישראל | L68: סחיר | M68: TASE | N68: מוליכים למחצה | O68: לא | P68: ILS | Q68: 330 | R68: 1 | S68: 30800 | U68: 101.64 | V68: 7e-06 | W68: 0.036835389 | X68: 0.010190539 | Y68: 30800 | Z68: =(U68-T68*R68)/R68/Q68*100000 -> 30800
A69: 337 | B69: 1477 | C69: קרסו מוטורס בע"מ | D69: 514065283 | E69: ח.פ | F69: קרסו מוטורס | G69: IL0011238503 | H69: ISIN | I69: מניות | J69: ישראל | K69: ישראל | L69: סחיר | M69: TASE | N69: מסחר | O69: לא | P69: ILS | Q69: 1053 | R69: 1 | S69: 1752.9915 | U69: 18.459 | V69: 1.2e-05 | W69: 0.0066897654 | X69: 0.0018507288 | Y69: 1753 | Z69: =(U69-T69*R69)/R69/Q69*100000 -> 1752.9915
A70: 337 | B70: 1477 | C70: ריט 1 בע"מ | D70: 513821488 | E70: ח.פ | F70: ריט 1 | G70: IL0010989205 | H70: ISIN | I70: מניות | J70: ישראל | K70: ישראל | L70: סחיר | M70: TASE | N70: נדל"ן מניב בישראל | O70: לא | P70: ILS | Q70: 1995 | R70: 1 | S70: 1566.015 | U70: 31.242 | V70: 1e-05 | W70: 0.011322316 | X70: 0.0031323275 | Y70: 1566 | Z70: =(U70-T70*R70)/R70/Q70*100000 -> 1566.015
A71: 337 | B71: 1477 | C71: ריטיילורס בע"מ | D71: 514211457 | E71: ח.פ | F71: ריטיילורס | G71: IL0011754889 | H71: ISIN | I71: מניות | J71: ישראל | K71: ישראל | L71: סחיר | M71: TASE | N71: רשתות שיווק | O71: לא | P71: ILS | Q71: 59 | R71: 1 | S71: 9247.4576 | U71: 5.456 | V71: 1e-06 | W71: 0.0019772131 | X71: 0.00054699754 | Y71: 9247 | Z71: =(U71-T71*R71)/R71/Q71*100000 -> 9247.4576
A72: 337 | B72: 1477 | C72: רשת חנויות רמי לוי שיווק השיקמה 2006 בע"מ | D72: 513770669 | E72: ח.פ | F72: רמי לוי | G72: IL0011042491 | H72: ISIN | I72: מניות | J72: ישראל | K72: ישראל | L72: סחיר | M72: TASE | N72: רשתות שיווק | O72: לא | P72: ILS | Q72: 73 | R72: 1 | S72: 22049.315 | U72: 16.096 | V72: 5e-06 | W72: 0.0058335383 | X72: 0.0016138529 | Y72: 22050 | Z72: =(U72-T72*R72)/R72/Q72*100000 -> 22049.315
A73: 337 | B73: 1477 | C73: רני צים מרכזי קניות בע"מ | D73: 514353671 | E73: ח.פ | F73: רני צים | G73: IL0011436198 | H73: ISIN | I73: מניות | J73: ישראל | K73: ישראל | L73: סחיר | M73: TASE | N73: נדל"ן מניב בישראל | O73: לא | P73: ILS | Q73: 2280 | R73: 1 | S73: 266.18421 | U73: 6.069 | V73: 1.6e-05 | W73: 0.0021995989 | X73: 0.00060852076 | Y73: 266.2 | Z73: =(U73-T73*R73)/R73/Q73*100000 -> 266.18421
A74: 337 | B74: 1477 | C74: רציו חיפושי נפט (1992) - שותפות מוגבלת | D74: 550012777 | E74: ח.פ | F74: רציו יהש | G74: IL0003940157 | H74: ISIN | I74: מניות | J74: ישראל | K74: ישראל | L74: סחיר | M74: TASE | N74: חיפושי נפט וגז | O74: לא | P74: ILS | Q74: 3923 | R74: 1 | S74: 302.80398 | U74: 11.879 | V74: 3e-06 | W74: 0.0043050161 | X74: 0.0011909861 | Y74: 302.8 | Z74: =(U74-T74*R74)/R74/Q74*100000 -> 302.80398
A75: 337 | B75: 1477 | C75: שופר-סל בע"מ | D75: 520022732 | E75: ח.פ | F75: שופרסל | G75: IL0007770378 | H75: ISIN | I75: מניות | J75: ישראל | K75: ישראל | L75: סחיר | M75: TASE | N75: רשתות שיווק | O75: לא | P75: ILS | Q75: 1543 | R75: 1 | S75: 2585.0292 | U75: 39.887 | V75: 6e-06 | W75: 0.014455299 | X75: 0.0039990697 | Y75: 2585 | Z75: =(U75-T75*R75)/R75/Q75*100000 -> 2585.0292
A76: 337 | B76: 1477 | C76: תדיראן גרופ בע"מ | D76: 520036732 | E76: ח.פ | F76: תדיראן גרופ | G76: IL0002580129 | H76: ISIN | I76: מניות | J76: ישראל | K76: ישראל | L76: סחיר | M76: TASE | N76: מסחר | O76: לא | P76: ILS | Q76: 101 | R76: 1 | S76: 30039.604 | T76: 0.267 | U76: 30.607 | V76: 1.2e-05 | W76: 0.01109245 | X76: 0.0030687348 | Y76: 30040 | Z76: =(U76-T76*R76)/R76/Q76*100000 -> 30039.604
A77: 337 | B77: 1477 | C77: amazon.com | D77: 549300LQHH5G4WPME241 | E77: LEI | F77: AMAZON.COM INC | G77: US0231351067 | H77: ISIN | I77: מניות | J77: חו"ל | K77: ארה"ב | L77: סחיר | M77: NASDAQ | N77: Textiles, Apparel & Luxury Goods | O77: לא | P77: USD | Q77: 29 | R77: 3.681 | S77: 18037.64 | U77: 19.255 | V77: 0 | W77: 0.0069783508 | X77: 0.0019305662 | Y77: 180.38 | Z77: =(U77-T77*R77)/R77/Q77*100000 -> 18037.64
A78: 337 | B78: 1477 | C78: APPLE COMPUTER INC | D78: HWUPKR0MPOU8FGXBT394 | E78: LEI | F78: APPLE INC | G78: US0378331005 | H78: ISIN | I78: מניות | J78: חו"ל | K78: ארה"ב | L78: סחיר | M78: NASDAQ | N78: Technology Hardware, Storage & Peripherals | O78: לא | P78: USD | Q78: 12 | R78: 3.681 | S78: 17148.873 | U78: 7.575 | V78: 0 | W78: 0.0027451188 | X78: 0.00075943925 | Y78: 171.48 | Z78: =(U78-T78*R78)/R78/Q78*100000 -> 17148.873
A79: 337 | B79: 1477 | C79: Bank of America | D79: 5493006QMFDDMYWIAM13 | E79: LEI | F79: Bank of Ameica Corp | G79: US0605051046 | H79: ISIN | I79: מניות | J79: חו"ל | K79: ארה"ב | L79: סחיר | M79: NYSE | N79: Banks | O79: לא | P79: USD | Q79: 66 | R79: 3.681 | S79: 3792.2007 | U79: 9.213 | V79: 0 | W79: 0.0033387099 | X79: 0.00092365669 | Y79: 3792 | Z79: =(U79-T79*R79)/R79/Q79*100000 -> 3792.2007
A80: 337 | B80: 1477 | C80: CATERPILLAR | D80: WRJR7GS4GTRECRRTVX92 | E80: LEI | F80: CATERPILLAR INC | G80: US1491231015 | H80: ISIN | I80: מניות | J80: חו"ל | L80: סחיר | M80: אחר | N80: Capital Markets | O80: לא | P80: USD | Q80: 15 | R80: 3.681 | S80: 36642.217 | U80: 20.232 | V80: 0 | W80: 0.0073324431 | X80: 0.0020285261 | Y80: 36643 | Z80: =(U80-T80*R80)/R80/Q80*100000 -> 36642.217
A81: 337 | B81: 1477 | C81: Meta Platforms Inc | D81: BQ4BKCS1HXDV9HN80Z93 | E81: LEI | F81: Facebook Inc | G81: US30303M1027 | H81: ISIN | I81: מניות | J81: חו"ל | K81: ארה"ב | L81: סחיר | M81: NASDAQ | N81: Diversified Telecommunication Services | O81: לא | P81: USD | Q81: 10 | R81: 3.681 | S81: 48557.457 | U81: 17.874 | V81: 0 | W81: 0.0064777952 | X81: 0.0017920871 | Y81: 48558 | Z81: =(U81-T81*R81)/R81/Q81*100000 -> 48557.457
A82: 337 | B82: 1477 | C82: ALPHABET INC | D82: 7ZW8QJWVPR4P1J1KQY45 | E82: LEI | F82: Google Us Class c | G82: US02079K1079 | H82: ISIN | I82: מניות | J82: חו"ל | K82: ארה"ב | L82: סחיר | M82: NASDAQ | N82: Diversified Telecommunication Services | O82: לא | P82: USD | Q82: 102 | R82: 3.681 | S82: 15226.042 | U82: 57.168 | V82: 0 | W82: 0.020718219 | X82: 0.0057317114 | Y82: 15226 | Z82: =(U82-T82*R82)/R82/Q82*100000 -> 15226.042
A83: 337 | B83: 1477 | C83: איתוראן איתור ושליטה בע"מ | D83: 520043811 | E83: ח.פ | F83: Ituran Location And Control 16 | G83: IL0010818685 | H83: ISIN | I83: מניות | J83: חול | K83: ישראל | L83: סחיר | M83: NASDAQ | N83: Technology Hardware, Storage & Peripherals | O83: לא | P83: USD | Q83: 147 | R83: 3.681 | S83: 2796.1536 | T83: 0.057 | U83: 15.34 | V83: 1.1e-05 | W83: 0.0055595139 | X83: 0.0015380438 | Y83: 27.96 | Z83: =(U83-T83*R83)/R83/Q83*100000 -> 2796.1536
A84: 337 | B84: 1477 | C84: Jacobs Solutions Inc | D84: 549300CZ8QS1GE53O776 | E84: LEI | F84: JACOBS SOLUTION | G84: US46982L1089 | H84: ISIN | I84: מניות | J84: חו"ל | K84: ארה"ב | L84: סחיר | M84: NYSE | N84: Commercial Services & Supplies | O84: לא | P84: USD | Q84: 35 | R84: 3.681 | S84: 15373.152 | U84: 19.806 | V84: 0 | W84: 0.0071778287 | X84: 0.0019857519 | Y84: 15373 | Z84: =(U84-T84*R84)/R84/Q84*100000 -> 15373.152
A85: 337 | B85: 1477 | C85: JPMORGAN CHASE | D85: 8I5DZWZKVSZI1NUHU748 | E85: LEI | F85: JPMORGAN CHASE & CO | G85: US46625H1005 | H85: ISIN | I85: מניות | J85: חו"ל | K85: ארה"ב | L85: סחיר | M85: NYSE | N85: Banks | O85: לא | P85: USD | Q85: 14 | R85: 3.681 | S85: 20029.495 | U85: 10.322 | V85: 0 | W85: 0.003740894 | X85: 0.0010349212 | Y85: 200.3 | Z85: =(U85-T85*R85)/R85/Q85*100000 -> 20029.495
A86: 337 | B86: 1477 | C86: MICROSOFT CORP | D86: INR2EJN1ERAN0W5ZP974 | E86: LEI | F86: Microsoft crop | G86: US5949181045 | H86: ISIN | I86: מניות | J86: חו"ל | K86: ארה"ב | L86: סחיר | M86: NASDAQ | N86: Software | O86: לא | P86: USD | Q86: 19 | R86: 3.681 | S86: 42072.377 | U86: 29.425 | V86: 0 | W86: 0.010663829 | X86: 0.0029501566 | Y86: 420.72 | Z86: =(U86-T86*R86)/R86/Q86*100000 -> 42072.377
A87: 337 | B87: 1477 | C87: MONDELEZ INTERNATIONAL | D87: 549300DV9GIB88LZ5P30 | E87: LEI | F87: MONDELEZ INTERNATIONAL INC | G87: US6092071058 | H87: ISIN | I87: מניות | J87: חו"ל | K87: ארה"ב | L87: סחיר | M87: NASDAQ | N87: Food Products | O87: לא | P87: USD | Q87: 60 | R87: 3.681 | S87: 7000.8426 | T87: 0.019 | U87: 15.532 | V87: 0 | W87: 0.0056289069 | X87: 0.0015572415 | Y87: 7000 | Z87: =(U87-T87*R87)/R87/Q87*100000 -> 7000.8426
A88: 337 | B88: 1477 | C88: NICE LTD | D88: 254900YTY4EF5Z4W0A51 | E88: LEI | F88: NICE SYS ADR | G88: US6536561086 | H88: ISIN | I88: מניות | J88: חו"ל | K88: ישראל | L88: סחיר | M88: NASDAQ | N88: Wireless Telecommunication Services | O88: לא | P88: USD | Q88: 18 | R88: 3.681 | S88: 26061.759 | U88: 17.268 | V88: 0 | W88: 0.00625816 | X88: 0.0017313249 | Y88: 26062 | Z88: =(U88-T88*R88)/R88/Q88*100000 -> 26061.759
A89: 337 | B89: 1477 | C89: אורמת טכנולגיות אינק | D89: 5493000TSHHWY24VHM09 | E89: LEI | F89: Ormat Technologies | G89: US6866881021 | H89: ISIN | I89: מניות | J89: חו"ל | K89: ארה"ב | L89: סחיר | M89: NYSE | N89: Water Utilities | O89: לא | P89: USD | Q89: 23 | R89: 3.681 | S89: 6619.1843 | U89: 5.604 | V89: 0 | W89: 0.0020308911 | X89: 0.00056184761 | Y89: 66.19 | Z89: =(U89-T89*R89)/R89/Q89*100000 -> 6619.1843
A90: 337 | B90: 1477 | C90: Palo alto networks inc | D90: 549300QXR2YVZV231H43 | E90: LEI | F90: PALO ALTO NETWORKS INC | G90: US6974351057 | H90: ISIN | I90: מניות | J90: חו"ל | K90: ארה"ב | L90: סחיר | M90: NASDAQ | N90: Software | O90: לא | P90: USD | Q90: 28 | R90: 3.681 | S90: 28413.281 | U90: 29.285 | V90: 0 | W90: 0.010613083 | X90: 0.0029361176 | Y90: 28413 | Z90: =(U90-T90*R90)/R90/Q90*100000 -> 28413.281
A91: 337 | B91: 1477 | C91: פריון נטוורק בע"מ לשעבר אינקרדימייל | D91: 512849498 | E91: ח.פ | F91: Perion Network LTD | G91: IL0010958192 | H91: ISIN | I91: מניות | J91: חו"ל | K91: ישראל | L91: סחיר | M91: NASDAQ | N91: תוכנה ואינטרנט | O91: לא | P91: USD | Q91: 62 | R91: 3.681 | S91: 2247.8113 | U91: 5.13 | V91: 1e-06 | W91: 0.0018593212 | X91: 0.00051438265 | Y91: 2248 | Z91: =(U91-T91*R91)/R91/Q91*100000 -> 2247.8113
A92: 337 | B92: 1477 | C92: PPHE HOTEL GROUP LTD | D92: 2138003H1BZGR6KM5823 | E92: LEI | F92: PP HOTEL GROUP LTD | G92: GG00B1Z5FH87 | H92: ISIN | I92: מניות | J92: חו"ל | K92: בריטניה | L92: סחיר | M92: LSE | N92: Diversified Consumer Services | O92: לא | P92: GBP | Q92: 310 | R92: 4.654 | S92: 1414.8772 | U92: 20.413 | V92: 1.5e-05 | W92: 0.0073977296 | X92: 0.0020465877 | Y92: 1415 | Z92: =(U92-T92*R92)/R92/Q92*100000 -> 1414.8772
A93: 337 | B93: 1477 | C93: RWE AG | D93: 529900GB7KCA94ACC940 | E93: LEI | F93: RWE AG | G93: DE0007037129R | H93: ISIN | I93: מניות | J93: חו"ל | K93: גרמניה | L93: סחיר | M93: FWB | N93: Water Utilities | O93: לא | P93: EUR | Q93: 190 | R93: 3.979 | S93: 3146.1224 | U93: 23.785 | V93: 0 | W93: 0.0086198116 | X93: 0.0023846776 | Y93: 3146 | Z93: =(U93-T93*R93)/R93/Q93*100000 -> 3146.1224
A94: 337 | B94: 1477 | C94: Saleforce.com Inc | D94: RCGZFPDMRW58VJ54VR07 | E94: LEI | F94: Saleforce | G94: US794466L3024 | H94: ISIN | I94: מניות | J94: חו"ל | K94: ארה"ב | L94: סחיר | M94: NASDAQ | N94: Software | O94: לא | P94: USD | Q94: 30 | R94: 3.681 | S94: 30118.51 | T94: 0.009 | U94: 33.293 | V94: 0 | W94: 0.012065742 | X94: 0.0033379968 | Y94: 30118 | Z94: =(U94-T94*R94)/R94/Q94*100000 -> 30118.51
A95: 337 | B95: 1477 | C95: SHL TELEMEDICINE LTD | D95: 512527383 | E95: ח.פ | F95: SHL TELEMEDICINE LTD | G95: IL0010855885 | H95: ISIN | I95: מניות | J95: ישראל | K95: ישראל | L95: סחיר | M95: SIX | N95: Health Care Equipment & Supplies | O95: לא | P95: CHF | Q95: 290 | R95: 4.074 | S95: 545.00364 | U95: 6.439 | V95: 4.2e-05 | W95: 0.0023335447 | X95: 0.00064557696 | Y95: 545 | Z95: =(U95-T95*R95)/R95/Q95*100000 -> 545.00364
A96: 337 | B96: 1477 | C96: TAIWAN Semiconductor | D96: 549300KB6NK5SBD14S87 | E96: LEI | F96: TAIWAN SEMICON ADR | G96: US8740391003 | H96: ISIN | I96: מניות | J96: חו"ל | K96: סין | L96: סחיר | M96: NYSE | N96: Semiconductors & Semiconductor Equipment | O96: לא | P96: USD | Q96: 100 | R96: 3.681 | S96: 13605.008 | T96: 0.044 | U96: 50.242 | V96: 0 | W96: 0.018208056 | X96: 0.005037273 | Y96: 13605 | Z96: =(U96-T96*R96)/R96/Q96*100000 -> 13605.008
A97: 337 | B97: 9962 | C97: או.פי.סי. אנרגיה בע"מ | D97: 514401702 | E97: ח.פ | F97: או פי סי אנרגיה | G97: IL0011415713 | H97: ISIN | I97: מניות | J97: ישראל | K97: ישראל | L97: סחיר | M97: TASE | N97: אנרגיה | O97: לא | P97: ILS | Q97: 1186 | R97: 1 | S97: 2616.0202 | U97: 31.026 | V97: 5e-06 | W97: 0.0065698574 | X97: 0.001005132 | Y97: 2616 | Z97: =(U97-T97*R97)/R97/Q97*100000 -> 2616.0202
A98: 337 | B98: 9962 | C98: אטראו שוקי הון בע"מ לשעבר לידר | D98: 513773564 | E98: ח.פ | F98: אטראו שוקי הון | G98: IL0010961063 | H98: ISIN | I98: מניות | J98: ישראל | K98: ישראל | L98: סחיר | M98: TASE | N98: שירותים פיננסיים | O98: לא | P98: ILS | Q98: 472 | R98: 1 | S98: 5665.0424 | U98: 26.739 | V98: 3.2e-05 | W98: 0.0056620726 | X98: 0.00086624866 | Y98: 5665 | Z98: =(U98-T98*R98)/R98/Q98*100000 -> 5665.0424
A99: 337 | B99: 9962 | C99: אי.טי.גי. איי גרופ בע"מ | D99: 513764399 | E99: ח.פ | F99: אי. טי. ג'י. איי | G99: IL0011761140 | H99: ISIN | I99: מניות | J99: ישראל | K99: ישראל | L99: סחיר | M99: TASE | N99: שירותים | O99: לא | P99: ILS | Q99: 462 | R99: 1 | S99: 1050 | T99: 0.073 | U99: 4.924 | V99: 2.1e-05 | W99: 0.0010426855 | X99: 0.00015952196 | Y99: 1050 | Z99: =(U99-T99*R99)/R99/Q99*100000 -> 1050
A100: 337 | B100: 9962 | C100: איי.סי.אל גרופ בע"מ (דואלי) | D100: 520027830 | E100: ח.פ | F100: איי.סי.אל | G100: IL0002810146 | H100: ISIN | I100: מניות | J100: ישראל | K100: ישראל | L100: סחיר | M100: TASE | N100: כימיה, גומי ופלסטיק | O100: לא | P100: ILS | Q100: 2574 | R100: 1 | S100: 1951.0101 | U100: 50.219 | V100: 2e-06 | W100: 0.010634065 | X100: 0.001626921 | Y100: 1951 | Z100: =(U100-T100*R100)/R100/Q100*100000 -> 1951.0101
...

Sheet קרנות סל
A1: מספר קופה/קרן/ח.פ. עבור חברת ביטוח | B1: מספר מסלול | C1: שם מנפיק | D1: מספר מנפיק | E1: סוג מספר מזהה מנפיק | F1: שם נייר ערך | G1: מספר נייר ערך | H1: סוג מספר נייר ערך | I1: מאפיין עיקרי | J1: ישראל/חו"ל | K1: מדינה לפי חשיפה כלכלית | L1: זירת מסחר | M1: סיווג הקרן | N1: בעל עניין/צד קשור | O1: מטבע פעילות | P1: ערך נקוב (יחידות) | Q1: שער חליפין | R1: שער נייר הערך | S1: סכום לקבל (במטבע הפעילות) | T1: שווי הוגן (באלפי ש"ח) | U1: שיעור מערך נקוב מונפק | V1: שיעור מנכסי אפיק ההשקעה | W1: שיעור מסך נכסי ההשקעה
A2: 337 | B2: 1477 | C2: הראל קרנות נאמנות בע"מ | D2: 511776783 | E2: ח.פ | F2: הראל סל תא 90 | G2: IL0011489312 | H2: ISIN | I2: עוקב אחר מדדי מניות בישראל | J2: ישראל | K2: ישראל | L2: TASE | M2: 125 מניות בארץ - מניות כללי-ת"א | N2: לא | O2: ILS | P2: 4230 | Q2: 1 | R2: 2053.0024 | T2: 86.842 | U2: 8.7e-05 | V2: 0.077850721 | W2: 0.0087068651
A3: 337 | B3: 1477 | C3: HSBC Holdings PLC | D3: MLU0ZO3ML4LN2LL2TL39 | E3: LEI | F3: Hsbc S&P 500 | G3: IE00B5KQNG97 | H3: ISIN | I3: עוקב אחר מדדי מניות בחו"ל | J3: חו"ל | K3: ארה"ב | L3: LSE | M3: Equity Funds | N3: לא | O3: USD | P3: 283 | Q3: 3.681 | R3: 5304.9611 | T3: 55.263 | U3: 2e-06 | V3: 0.049541707 | W3: 0.0055407702
A4: 337 | B4: 1477 | C4: LYXOR ETF | D4: 549300D36R80ZKQLJ385 | E4: LEI | F4: LYXOR S&P 500 UCITS ETF | G4: LU1135865084 | H4: ISIN | I4: עוקב אחר מדדי מניות בחו"ל | J4: חו"ל | K4: ארה"ב | L4: LSE | M4: Equity Funds | N4: לא | O4: EUR | P4: 241 | Q4: 3.979 | R4: 34404.9 | T4: 329.922 | U4: 2.7e-05 | V4: 0.29576322 | W4: 0.033078312
A5: 337 | B5: 1477 | C5: Invesco investment management limited | D5: 635400KFAN415FMIGG54 | E5: LEI | F5: Powershares QQQ NAS1 | G5: US46090E1038 | H5: ISIN | I5: עוקב אחר מדדי מניות בחו"ל | J5: חו"ל | K5: ארה"ב | L5: NASDAQ | M5: Equity Funds | N5: לא | O5: USD | P5: 177 | Q5: 3.681 | R5: 44400.684 | S5: 0.078 | T5: 289.574 | U5: 0 | V5: 0.25959317 | W5: 0.029033035
A6: 337 | B6: 1477 | C6: Vanguard Group | D6: QS6WHLCJOJSYY4PYNF72 | E6: LEI | F6: VANGUARD S&P 50 | G6: us9229083632 | H6: ISIN | I6: עוקב אחר מדדי מניות בחו"ל | J6: חו"ל | K6: ארה"ב | L6: NYSE | M6: Equity Funds | N6: לא | O6: USD | P6: 200 | Q6: 3.681 | R6: 48069.954 | T6: 353.891 | U6: 0 | V6: 0.31725119 | W6: 0.035481538
A7: 337 | B7: 9962 | C7: הראל קרנות נאמנות בע"מ | D7: 511776783 | E7: ח.פ | F7: הראל סל תא 90 | G7: IL0011489312 | H7: ISIN | I7: עוקב אחר מדדי מניות בישראל | J7: ישראל | K7: ישראל | L7: TASE | M7: 125 מניות בארץ - מניות כללי-ת"א | N7: לא | O7: ILS | P7: 10000 | Q7: 1 | R7: 2053 | T7: 205.3 | U7: 0.000205 | V7: 0.059381987 | W7: 0.0066510408
A8: 337 | B8: 9962 | C8: Invesco investment management limited | D8: 635400KFAN415FMIGG54 | E8: LEI | F8: Powershares QQQ NAS1 | G8: US46090E1038 | H8: ISIN | I8: עוקב אחר מדדי מניות בחו"ל | J8: חו"ל | K8: ארה"ב | L8: NASDAQ | M8: Equity Funds | N8: לא | O8: USD | P8: 420 | Q8: 3.681 | R8: 44400.958 | S8: 0.184 | T8: 687.125 | U8: 1e-06 | V8: 0.19874754 | W8: 0.022260589
A9: 337 | B9: 9962 | C9: Invesco investment management limited | D9: 635400KFAN415FMIGG54 | E9: LEI | F9: SOURCE S&P 500 UCITS EFT | G9: IE00B3YCGJ38 | H9: ISIN | I9: עוקב אחר מדדי מניות בחו"ל | J9: חו"ל | K9: ארה"ב | L9: LSE | M9: Equity Funds | N9: לא | O9: USD | P9: 290 | Q9: 3.681 | R9: 102523.96 | T9: 1094.433 | U9: 5.7e-05 | V9: 0.31655934 | W9: 0.035456023
A10: 337 | B10: 9962 | C10: Vanguard Group | D10: QS6WHLCJOJSYY4PYNF72 | E10: LEI | F10: VANGUARD S&P 50 | G10: us9229083632 | H10: ISIN | I10: עוקב אחר מדדי מניות בחו"ל | J10: חו"ל | K10: ארה"ב | L10: NYSE | M10: Equity Funds | N10: לא | O10: USD | P10: 831 | Q10: 3.681 | R10: 48070.016 | T10: 1470.419 | U10: 1e-06 | V10: 0.42531113 | W10: 0.047636695
A11: 337 | B11: 9964 | C11: Invesco investment management limited | D11: 635400KFAN415FMIGG54 | E11: LEI | F11: SOURCE S&P 500 UCITS EFT | G11: IE00B3YCGJ38 | H11: ISIN | I11: עוקב אחר מדדי מניות בחו"ל | J11: חו"ל | K11: ארה"ב | L11: LSE | M11: Equity Funds | N11: לא | O11: USD | P11: 268 | Q11: 3.681 | R11: 102523.95 | T11: 1011.407 | U11: 5.3e-05 | V11: 0.63187828 | W11: 0.029155892
A12: 337 | B12: 9964 | C12: Vanguard Group | D12: QS6WHLCJOJSYY4PYNF72 | E12: LEI | F12: VANGUARD S&P 50 | G12: us9229083632 | H12: ISIN | I12: עוקב אחר מדדי מניות בחו"ל | J12: חו"ל | K12: ארה"ב | L12: NYSE | M12: Equity Funds | N12: לא | O12: USD | P12: 333 | Q12: 3.681 | R12: 48069.993 | T12: 589.229 | U12: 0 | V12: 0.36812172 | W12: 0.016985735

Sheet קרנות נאמנות
A1: מספר קופה/קרן/ח.פ. עבור חברת ביטוח | B1: מספר מסלול | C1: שם מנפיק | D1: מספר מנפיק | E1: סוג מספר מזהה מנפיק | F1: שם נייר ערך | G1: מספר נייר ערך | H1: סוג מספר נייר ערך | I1: מאפיין עיקרי | J1: ישראל/חו"ל | K1: מדינה לפי חשיפה כלכלית | L1: סטאטוס סחירות | M1: זירת מסחר | N1: סיווג הקרן | O1: בעל עניין/צד קשור | P1: מטבע פעילות | Q1: ערך נקוב (יחידות) | R1: שער חליפין | S1: שער נייר הערך | T1: שווי הוגן (באלפי ש"ח) | U1: שיעור מערך נקוב מונפק | V1: שיעור מנכסי אפיק ההשקעה | W1: שיעור מסך נכסי ההשקעה
A2: 337 | B2: 9963 | C2: אי בי אי ניהול קרנות נאמנות בע"מ | D2: 510791031 | E2: ח.פ | F2: איביאי טכנולגיית עילית | G2: IL0011425381 | H2: ISIN | I2: מניות | J2: ישראל | K2: ישראל | L2: סחיר | M2: TASE | N2: מניות בישראל | O2: לא | P2: ILS | Q2: 4001213.1 | R2: 1 | S2: 62.3 | T2: 2492.756 | U2: 0.010925 | V2: 1 | W2: 0.0024261346
A3: 337 | B3: 9964 | C3: קסם קרנות נאמנות בע"מ | D3: 510938608 | E3: ח.פ | F3: קסם KTF ת"א 100 | G3: IL0051133457 | H3: ISIN | I3: מניות | J3: ישראל | L3: סחיר | M3: TASE | N3: מניות בישראל | O3: לא | P3: ILS | Q3: 42675 | R3: 1 | S3: 203.03 | T3: 86.643 | U3: 0.000366 | V3: 1 | W3: 0.0024976635

Sheet כתבי אופציה
A1: מספר קופה/קרן/ח.פ. עבור חברת ביטוח | B1: מספר מסלול | C1: שם מנפיק | D1: מספר מנפיק | E1: סוג מספר מזהה מנפיק | F1: שם נייר ערך | G1: מספר נייר ערך | H1: סוג מספר נייר ערך | I1: ישראל/חו"ל | J1: מדינה לפי חשיפה כלכלית | K1: סטאטוס סחירות | L1: זירת מסחר | M1: נכס בסיס (כתב אופציה) | N1: ענף מסחר | O1: תאריך פקיעה | P1: בעל עניין/צד קשור | Q1: מטבע פעילות | R1: שער מימוש | S1: יחס המרה | T1: ערך נקוב (יחידות) | U1: שער חליפין | V1: שער נייר הערך | W1: שווי הוגן (באלפי ש"ח) | X1: שיעור מנכסי אפיק ההשקעה | Y1: שיעור מסך נכסי ההשקעה
A2: 337 | B2: 1477 | C2: איידנטי הלת'קייר בע"מ | D2: 515679405 | E2: ח.פ | F2: איידנטי אופ' 2 | G2: IL0011774762 | H2: ISIN | I2: ישראל | J2: ישראל | K2: סחיר | L2: TASE | M2: אחר | N2: תוכנה ואינטרנט | O2: 16/06/2024 | P2: לא | Q2: ILS | R2: 1125 | S2: 0 | T2: 1398 | U2: 1 | V2: 95.4 | W2: 1.334 | X2: 0.2546055 | Y2: 0.00013371744
A3: 337 | B3: 1477 | C3: אלומיי קפיטל בע"מ | D3: 520039868 | E3: ח.פ | F3: אלומיי אופ 2 | G3: IL0012030826 | H3: ISIN | I3: ישראל | J3: ישראל | K3: סחיר | L3: TASE | M3: אחר | N3: אנרגיה מתחדשת | O3: 05/01/2028 | P3: לא | Q3: ILS | R3: 8000 | S3: 0 | T3: 102 | U3: 1 | V3: 827.5 | W3: 0.844 | X3: 0.16113149 | Y3: 8.4625388e-05
A4: 337 | B4: 1477 | C4: בית בכפר בע"מ | D4: 511605719 | E4: ח.פ | F4: בית בכפר אר 1 | G4: IL0011836645 | H4: ISIN | I4: ישראל | J4: ישראל | K4: סחיר | L4: TASE | M4: אחר | N4: נדל"ן מניב בישראל | O4: 30/01/2025 | P4: לא | Q4: ILS | R4: 20 | S4: 0 | T4: 675 | U4: 1 | V4: 21.9 | W4: 0.148 | X4: 0.028220202 | Y4: 1.4821098e-05
A5: 337 | B5: 1477 | C5: גרופ 107 בע"מ | D5: 516199445 | E5: ח.פ | F5: גרופ 107 אפ 1 | G5: IL0011801995 | H5: ISIN | I5: ישראל | J5: ישראל | K5: סחיר | L5: TASE | M5: אחר | N5: תוכנה ואינטרנט | O5: 01/09/2024 | P5: לא | Q5: ILS | R5: 514 | S5: 1 | T5: 3540 | U5: 1 | V5: 1.1 | W5: 0.039 | X5: 0.007433754 | Y5: 3.9041676e-06
A6: 337 | B6: 1477 | C6: זוז פאוור בע"מ | D6: 514881564 | E6: ח.פ | F6: זוז פאוור אופ 3 | G6: IL0011853210 | H6: ISIN | I6: ישראל | J6: ישראל | K6: סחיר | L6: TASE | M6: אחר | N6: קלינטק | O6: 20/03/2025 | P6: לא | Q6: ILS | R6: 4117.394 | S6: 1 | T6: 858.16 | U6: 1 | V6: 226 | W6: 1.939 | X6: 0.37024478 | Y6: 0.00019445056
A7: 337 | B7: 1477 | C7: טראקנט אנטרפרייז בע"מ | D7: 515446474 | E7: ח.פ | F7: טרקנט אופ 1 | G7: IL0011741019 | H7: ISIN | I7: ישראל | J7: ישראל | K7: סחיר | L7: TASE | M7: אחר | N7: תוכנה ואינטרנט | O7: 02/03/2025 | P7: לא | Q7: ILS | R7: 0 | S7: 0 | T7: 1850 | U7: 1 | V7: 47.9 | W7: 0.886 | X7: 0.16916849 | Y7: 8.8846381e-05
A8: 337 | B8: 1477 | C8: קונטיניואל בע"מ | D8: 514949973 | E8: ח.פ | F8: קונטיניואל אופ | G8: IL0011822785 | H8: ISIN | I8: ישראל | J8: ישראל | K8: סחיר | L8: TASE | M8: אחר | N8: תוכנה ואינטרנט | O8: 12/12/2024 | P8: לא | Q8: ILS | R8: 1656 | S8: 1 | T8: 2189 | U8: 1 | V8: 1 | W8: 0.022 | X8: 0.0041788617 | Y8: 2.1947157e-06
A9: 337 | B9: 1477 | C9: שמיים אימפרוב בע"מ | D9: 515181014 | E9: ח.פ | F9: שמיים אופ 1 | G9: IL0011762478 | H9: ISIN | I9: ישראל | J9: ישראל | K9: סחיר | L9: TASE | M9: אחר | N9: תוכנה ואינטרנט | O9: 01/06/2025 | P9: לא | Q9: ILS | R9: 0 | S9: 0 | T9: 73 | U9: 1 | V9: 36 | W9: 0.026 | X9: 0.0050169249 | Y9: 2.6348619e-06
A10: 337 | B10: 9962 | C10: אלומיי קפיטל בע"מ | D10: 520039868 | E10: ח.פ | F10: אלומיי אופ 2 | G10: IL0012030826 | H10: ISIN | I10: ישראל | J10: ישראל | K10: סחיר | L10: TASE | M10: אחר | N10: אנרגיה מתחדשת | O10: 05/01/2028 | P10: לא | Q10: ILS | R10: 8000 | S10: 0 | T10: 156 | U10: 1 | V10: 827.5 | W10: 1.291 | X10: 0.39240796 | Y10: 4.1820889e-05
A11: 337 | B11: 9962 | C11: בית בכפר בע"מ | D11: 511605719 | E11: ח.פ | F11: בית בכפר אר 1 | G11: IL0011836645 | H11: ISIN | I11: ישראל | J11: ישראל | K11: סחיר | L11: TASE | M11: אחר | N11: נדל"ן מניב בישראל | O11: 30/01/2025 | P11: לא | Q11: ILS | R11: 20 | S11: 0 | T11: 1575 | U11: 1 | V11: 21.9 | W11: 0.345 | X11: 0.10485035 | Y11: 1.1174429e-05
A12: 337 | B12: 9962 | C12: גרופ 107 בע"מ | D12: 516199445 | E12: ח.פ | F12: גרופ 107 אפ 1 | G12: IL0011801995 | H12: ISIN | I12: ישראל | J12: ישראל | K12: סחיר | L12: TASE | M12: אחר | N12: תוכנה ואינטרנט | O12: 01/09/2024 | P12: לא | Q12: ILS | R12: 514 | S12: 1 | T12: 250 | U12: 1 | V12: 1.1 | W12: 0.003 | X12: 0.00083594538 | Y12: 8.9090902e-08
A13: 337 | B13: 9962 | C13: זוז פאוור בע"מ | D13: 514881564 | E13: ח.פ | F13: זוז פאוור אופ 3 | G13: IL0011853210 | H13: ISIN | I13: ישראל | J13: ישראל | K13: סחיר | L13: TASE | M13: אחר | N13: קלינטק | O13: 20/03/2025 | P13: לא | Q13: ILS | R13: 4117.394 | S13: 1 | T13: 181.86 | U13: 1 | V13: 226 | W13: 0.411 | X13: 0.12493693 | Y13: 1.3315157e-05
... A27: 337 | B27: 9964 | C27: שמיים אימפרוב בע"מ | D27: 515181014 | E27: ח.פ | F27: שמיים אופ 1 | G27: IL0011762478 | H27: ISIN | I27: ישראל | J27: ישראל | K27: סחיר | L27: TASE | M27: אחר | N27: תוכנה ואינטרנט | O27: 01/06/2025 | P27: לא | Q27: ILS | R27: 0 | S27: 0 | T27: 438 | U27: 1 | V27: 36 | W27: 0.158 | X27: 0.051019639 | Y27: 4.545449e-06

Sheet אופציות
A1: מספר קופה/קרן/ח.פ. עבור חברת ביטוח | B1: מספר מסלול | C1: שם מנפיק | D1: מספר מנפיק | E1: סוג מספר מזהה מנפיק | F1: שם נייר ערך | G1: מספר נייר ערך | H1: סוג מספר נייר ערך | I1: מאפיין עיקרי | J1: ישראל/חו"ל | K1: מדינה לפי חשיפה כלכלית | L1: זירת מסחר | M1: ענף מסחר | N1: נכס בסיס | O1: תאריך פקיעה | P1: בעל עניין/צד קשור | Q1: מטבע פעילות | R1: שער מימוש | S1: ערך נקוב (יחידות) | T1: שער חליפין | U1: שער נייר הערך | V1: שווי הוגן (באלפי ש"ח) | W1: שיעור מנכסי אפיק ההשקעה | X1: שיעור מסך נכסי ההשקעה

Sheet חוזים עתידיים
A1: מספר קופה/קרן/ח.פ. עבור חברת ביטוח | B1: מספר מסלול | C1: שם מנפיק | D1: מספר מנפיק | E1: סוג מספר מזהה מנפיק | F1: שם נייר ערך | G1: מספר נייר ערך | H1: סוג מספר נייר ערך | I1: ישראל/חו"ל | J1: מדינה לפי חשיפה כלכלית | K1: זירת מסחר | L1: נכס בסיס | M1: בעל עניין/צד קשור | N1: מטבע פעילות | O1: ערך נקוב (יחידות) | P1: שער חליפין | Q1: שער נייר הערך | R1: שווי הוגן (באלפי ש"ח) | S1: שיעור מנכסי אפיק ההשקעה | T1: שיעור מסך נכסי ההשקעה
A2: 337 | B2: 1405 | C2: חוזים עתידיים בחול | D2: 10527 | E2: פנימי | F2: HWAM4_SP500 MIC EMIN FUTJUN24 | G2: HWAM4 INDEX | H2: אחר | I2: חו"ל | J2: ארה"ב | K2: CME | L2: מניות לרבות מדדי מניות | M2: לא | N2: USD | O2: 2 | P2: 3.681 | Q2: 5308.5 | R2: 4.52 | S2: 1 | T2: 0.00042751801
A3: 337 | B3: 1477 | C3: חוזים עתידיים בחול | D3: 10527 | E3: פנימי | F3: HWAM4_SP500 MIC EMIN FUTJUN24 | G3: HWAM4 INDEX | H3: אחר | I3: חו"ל | J3: ארה"ב | K3: CME | L3: מניות לרבות מדדי מניות | M3: לא | N3: USD | O3: 33 | P3: 3.681 | Q3: 5308.5 | R3: 74.584 | S3: 0.75649255 | T3: 0.0074779168
A4: 337 | B4: 1477 | C4: חוזים עתידיים בחול | D4: 10527 | E4: פנימי | F4: HWBM4_NASDAQ 100 MICRO EMINJUN24 | G4: HWBM4 | H4: אחר | I4: חו"ל | J4: ארה"ב | K4: CME | L4: מניות לרבות מדדי מניות | M4: לא | N4: USD | O4: 5 | P4: 3.681 | Q4: 18475 | R4: 9.451 | S4: 0.095862264 | T4: 0.00094759695
A5: 337 | B5: 1477 | C5: חוזים עתידיים בחול | D5: 10527 | E5: פנימי | F5: HWIM4_ DJIA MICR MIN CBOTJUN24 | G5: HWIM4 | H5: אחר | I5: חו"ל | J5: ארה"ב | K5: CME | L5: מניות לרבות מדדי מניות | M5: לא | N5: USD | O5: 4 | P5: 3.681 | Q5: 40176 | R5: 6.928 | S5: 0.070265471 | T5: 0.00069457306
A6: 337 | B6: 1477 | C6: חוזים עתידיים בחול | D6: 10527 | E6: פנימי | F6: MESM4_MSCI EMGMKT_JUN24 | G6: MESM4 | H6: אחר | I6: חו"ל | J6: שווקים מתעוררים | K6: CME | L6: מניות לרבות מדדי מניות | M6: לא | N6: USD | O6: 3 | P6: 3.681 | Q6: 1049 | R6: -4.141 | S6: -0.042002473 | T6: -0.00041519378
A7: 337 | B7: 1477 | C7: חוזים עתידיים בחול | D7: 10527 | E7: פנימי | F7: SXOM4_STOX EURP 600 JUN24 | G7: SXOM4 INDEX | H7: אחר | I7: חו"ל | J7: אירופה | K7: EUREX | L7: מניות לרבות מדדי מניות | M7: לא | N7: EUR | O7: 6 | P7: 3.979 | Q7: 510.8 | R7: 11.77 | S7: 0.11938219 | T7: 0.0011800911
A8: 337 | B8: 9962 | C8: חוזים עתידיים בחול | D8: 10527 | E8: פנימי | F8: HWAM4_SP500 MIC EMIN FUTJUN24 | G8: HWAM4 INDEX | H8: אחר | I8: חו"ל | J8: ארה"ב | K8: CME | L8: מניות לרבות מדדי מניות | M8: לא | N8: USD | O8: 53 | P8: 3.681 | Q8: 5308.5 | R8: 119.787 | S8: 0.75644564 | T8: 0.0038807058
A9: 337 | B9: 9962 | C9: חוזים עתידיים בחול | D9: 10527 | E9: פנימי | F9: HWBM4_NASDAQ 100 MICRO EMINJUN24 | G9: HWBM4 | H9: אחר | I9: חו"ל | J9: ארה"ב | K9: CME | L9: מניות לרבות מדדי מניות | M9: לא | N9: USD | O9: 8 | P9: 3.681 | Q9: 18475 | R9: 15.122 | S9: 0.095494598 | T9: 0.00048990492
A10: 337 | B10: 9962 | C10: חוזים עתידיים בחול | D10: 10527 | E10: פנימי | F10: HWIM4_ DJIA MICR MIN CBOTJUN24 | G10: HWIM4 | H10: אחר | I10: חו"ל | J10: ארה"ב | K10: CME | L10: מניות לרבות מדדי מניות | M10: לא | N10: USD | O10: 8 | P10: 3.681 | Q10: 40176 | R10: 13.855 | S10: 0.087494973 | T10: 0.00044886536
A11: 337 | B11: 9962 | C11: חוזים עתידיים בחול | D11: 10527 | E11: פנימי | F11: MESM4_MSCI EMGMKT_JUN24 | G11: MESM4 | H11: אחר | I11: חו"ל | J11: שווקים מתעוררים | K11: CME | L11: מניות לרבות מדדי מניות | M11: לא | N11: USD | O11: 3 | P11: 3.681 | Q11: 1049 | R11: -4.141 | S11: -0.026150862 | T11: -0.00013415875
A12: 337 | B12: 9962 | C12: חוזים עתידיים בחול | D12: 10527 | E12: פנימי | F12: SXOM4_STOX EURP 600 JUN24 | G12: SXOM4 INDEX | H12: אחר | I12: חו"ל | J12: אירופה | K12: EUREX | L12: מניות לרבות מדדי מניות | M12: לא | N12: EUR | O12: 7 | P12: 3.979 | Q12: 510.8 | R12: 13.732 | S12: 0.086715649 | T12: 0.00044486729
A13: 337 | B13: 9963 | C13: חוזים עתידיים בחול | D13: 10527 | E13: פנימי | F13: DMM4_ DJIA MINI E- CBOTJUN24 | G13: DMM4 | H13: אחר | I13: חו"ל | J13: ארה"ב | K13: CME | L13: מניות לרבות מדדי מניות | M13: לא | N13: USD | O13: 20 | P13: 3.681 | Q13: 40176 | R13: 346.382 | S13: 0.056281059 | T13: 0.00033712472
... A23: 337 | B23: 9964 | C23: חוזים עתידיים בחול | D23: 10527 | E23: פנימי | F23: SXOM4_STOX EURP 600 JUN24 | G23: SXOM4 INDEX | H23: אחר | I23: חו"ל | J23: אירופה | K23: EUREX | L23: מניות לרבות מדדי מניות | M23: לא | N23: EUR | O23: 1 | P23: 3.979 | Q23: 510.8 | R23: 1.962 | S23: 0.028739954 | T23: 5.6549914e-05

Sheet מוצרים מובנים
A1: מספר קופה/קרן/ח.פ. עבור חברת ביטוח | B1: מספר מסלול | C1: שם מנפיק | D1: מספר מנפיק | E1: סוג מספר מזהה מנפיק | F1: שם נייר ערך | G1: מספר נייר ערך | H1: סוג מספר נייר ערך | I1: מאפיין עיקרי | J1: ישראל/חו"ל | K1: מדינה לפי חשיפה כלכלית | L1: סטאטוס סחירות | M1: זירת מסחר | N1: נכס בסיס | O1: בעל עניין/צד קשור | P1: מח"מ | Q1: שיעור ריבית | R1: תשואה לפדיון | S1: דירוג | T1: שם מדרג | U1: דירוג נייר הערך/המנפיק | V1: מטבע פעילות | W1: ערך נקוב (יחידות) | X1: שער חליפין | Y1: שער נייר הערך | Z1: שווי הוגן (באלפי ש"ח) | AA1: שיעור מנכסי אפיק ההשקעה | AB1: שיעור מסך נכסי ההשקעה

Sheet לא סחיר איגרות חוב ממשלתיות
A1: מספר קופה/קרן/ח.פ. עבור חברת ביטוח | B1: מספר מסלול | C1: שם מנפיק | D1: שם נייר ערך | E1: מספר נייר ערך | F1: סוג מספר נייר ערך | G1: מאפיין עיקרי | H1: ישראל/חו"ל | I1: מדינה לפי חשיפה כלכלית | J1: תאריך רכישה | K1: דירוג | L1: שם מדרג | M1: מטבע פעילות | N1: מח"מ | O1: מועד פדיון | P1: שיעור ריבית | Q1: תשואה לפדיון | R1: ערך נקוב (יחידות) | S1: שער חליפין | T1: שער נייר הערך | U1: שווי הוגן (באלפי ש"ח) | V1: עלות מופחתת (באלפי ש"ח) | W1: השיטה שיושמה בדוח הכספי | X1: שיעור מנכסי אפיק ההשקעה | Y1: שיעור מסך נכסי ההשקעה

Sheet לא סחיר איגרות חוב מיועדות
A1: מספר קופה/קרן/ח.פ. עבור חברת ביטוח | B1: מספר מסלול | C1: מאפיין עיקרי | D1: שם נייר ערך | E1: מספר נייר ערך | F1: תאריך רכישה | G1: מח"מ | H1: סוג הצמדה | I1: מועד פדיון | J1: שיעור ריבית | K1: תשואה לפדיון | L1: ערך נקוב (יחידות) | M1: שער נייר הערך | N1: שווי הוגן (באלפי ש"ח) | O1: עלות מופחתת (באלפי ש"ח) | P1: השיטה שיושמה בדוח הכספי | Q1: שיעור מנכסי אפיק ההשקעה | R1: שיעור מסך נכסי ההשקעה

Sheet אפיק השקעה מובטח תשואה
A1: מספר קרן | B1: מספר מסלול | C1: מאפיין עיקרי | D1: חודש הנפקת שכבה | E1: חודש הבדיקה | F1: שווי הנכסים באפיק (באלפי ש"ח) | G1: שיעור מסך נכסי ההשקעה

Sheet לא סחיר ניירות ערך מסחריים
A1: מספר קופה/קרן/ח.פ. עבור חברת ביטוח | B1: מספר מסלול | C1: שם מנפיק | D1: מספר מנפיק | E1: סוג מספר מזהה מנפיק | F1: שם נייר ערך | G1: מספר נייר ערך | H1: סוג מספר נייר ערך | I1: מאפיין עיקרי | J1: ישראל/חו"ל | K1: מדינה לפי חשיפה כלכלית | L1: ענף מסחר | M1: בעל עניין/צד קשור | N1: תאריך רכישה | O1: דירוג | P1: שם מדרג | Q1: דירוג נייר הערך/המנפיק | R1: מטבע פעילות | S1: מח"מ | T1: סוג הצמדה | U1: ריבית עוגן | V1: מועד פדיון | W1: שיעור ריבית | X1: תשואה לפדיון | Y1: נחיתות חוזית | Z1: האם סווג כחוב בעייתי | AA1: סוג גורם משערך | AB1: תלות/אי-תלות המשערך | AC1: שם גורם משערך | AD1: תאריך שערוך אחרון | AE1: תאריך אחרון בו נבחנה בפועל ירידת ערך | AF1: ערך נקוב (יחידות) | AG1: שער חליפין | AH1: שער נייר הערך | AI1: שווי הוגן (באלפי ש"ח) | AJ1: עלות מופחתת (באלפי ש"ח) | AK1: עלות מופחתת (במטבע הפעילות) | AL1: השיטה שיושמה בדוח הכספי | AM1: שיעור מנכסי אפיק ההשקעה | AN1: שיעור מסך נכסי ההשקעה
A2: 337 | B2: 1405 | C2: אדמה פתרונות לחקלאות בע"מ | D2: 520043605 | E2: ח.פ | F2: אדמה נעמ סדרה 2 | G2: IL0011619835 | H2: ISIN | I2: צמוד למט"ח | J2: ישראל | K2: ישראל | L2: כימיה, גומי ופלסטיק | M2: לא | N2: 14/06/2023 | O2: AA- | P2: S&P מעלות | Q2: נייר ערך | R2: USD | S2: 0.04 | T2: צמוד למדד אחר | U2: Libor | V2: 15/11/2024 | W2: 0.063598 | X2: 0.0674 | Y2: החוב לא נחות | Z2: לא | AA2: חברת ציטוט | AB2: אי תלות | AC2: מרווח הוגן | AD2: 31/03/2024 | AF2: 5000 | AG2: 3.681 | AH2: 100.72806 | AI2: 18.539 | AL2: שווי הוגן | AM2: 0.35699856 | AN2: 0.0017534157
A3: 337 | B3: 1405 | C3: אורמת טכנולגיות אינק | D3: 5493000TSHHWY24VHM09 | E3: LEI | F3: אורמת נעמ 2 לא סחיר | G3: IL0012004680 | H3: ISIN | I3: צמוד למט"ח | J3: חו"ל | K3: ארה"ב | L3: אנרגיה מתחדשת | M3: לא | N3: 31/10/2023 | O3: AA- | P3: S&P מעלות | Q3: נייר ערך | R3: USD | S3: 0.02 | T3: צמוד למדד אחר | U3: SOFR | V3: 25/09/2028 | W3: 0.063982 | X3: 0.0572 | Y3: החוב לא נחות | Z3: לא | AA3: חברת ציטוט | AB3: אי תלות | AC3: מרווח הוגן | AD3: 31/03/2024 | AF3: 3000 | AG3: 3.681 | AH3: 101.2406 | AI3: 11.18 | AL3: שווי הוגן | AM3: 0.21528364 | AN3: 0.001057376
A4: 337 | B4: 1405 | C4: אלביט מערכות בע"מ | D4: 520043027 | E4: ח.פ | F4: אלביט מערכות נעמ1-ל | G4: IL0011991572 | H4: ISIN | I4: צמוד למט"ח | J4: ישראל | K4: ישראל | L4: ביטחוניות | M4: לא | N4: 31/08/2023 | O4: AA | P4: S&P מעלות | Q4: נייר ערך | R4: USD | S4: 0.05 | T4: צמוד למדד אחר | U4: SOFR | V4: 04/08/2028 | W4: 0.119823 | X4: 0.0562 | Y4: החוב לא נחות | Z4: לא | AA4: חברת ציטוט | AB4: אי תלות | AC4: מרווח הוגן | AD4: 31/03/2024 | AF4: 6000 | AG4: 3.681 | AH4: 100.5705 | AI4: 22.212 | AL4: שווי הוגן | AM4: 0.4277178 | AN4: 0.0021007566
A5: 337 | B5: 9962 | C5: אדמה פתרונות לחקלאות בע"מ | D5: 520043605 | E5: ח.פ | F5: אדמה נעמ סדרה 2 | G5: IL0011619835 | H5: ISIN | I5: צמוד למט"ח | J5: ישראל | K5: ישראל | L5: כימיה, גומי ופלסטיק | M5: לא | N5: 14/06/2023 | O5: AA- | P5: S&P מעלות | Q5: נייר ערך | R5: USD | S5: 0.04 | T5: צמוד למדד אחר | U5: Libor | V5: 15/11/2024 | W5: 0.063598 | X5: 0.0674 | Y5: החוב לא נחות | Z5: לא | AA5: חברת ציטוט | AB5: אי תלות | AC5: מרווח הוגן | AD5: 31/03/2024 | AF5: 14000 | AG5: 3.681 | AH5: 100.72962 | AI5: 51.91 | AL5: שווי הוגן | AM5: 0.39984916 | AN5: 0.0016817187
A6: 337 | B6: 9962 | C6: אורמת טכנולגיות אינק | D6: 5493000TSHHWY24VHM09 | E6: LEI | F6: אורמת נעמ 2 לא סחיר | G6: IL0012004680 | H6: ISIN | I6: צמוד למט"ח | J6: חו"ל | K6: ארה"ב | L6: אנרגיה מתחדשת | M6: לא | N6: 31/10/2023 | O6: AA- | P6: S&P מעלות | Q6: נייר ערך | R6: USD | S6: 0.02 | T6: צמוד למדד אחר | U6: SOFR | V6: 25/09/2028 | W6: 0.063982 | X6: 0.0572 | Y6: החוב לא נחות | Z6: לא | AA6: חברת ציטוט | AB6: אי תלות | AC6: מרווח הוגן | AD6: 31/03/2024 | AF6: 7000 | AG6: 3.681 | AH6: 101.2419 | AI6: 26.087 | AL6: שווי הוגן | AM6: 0.20093681 | AN6: 0.00084511665
A7: 337 | B7: 9962 | C7: אלביט מערכות בע"מ | D7: 520043027 | E7: ח.פ | F7: אלביט מערכות נעמ1-ל | G7: IL0011991572 | H7: ISIN | I7: צמוד למט"ח | J7: ישראל | K7: ישראל | L7: ביטחוניות | M7: לא | N7: 31/08/2023 | O7: AA | P7: S&P מעלות | Q7: נייר ערך | R7: USD | S7: 0.05 | T7: צמוד למדד אחר | U7: SOFR | V7: 04/08/2028 | W7: 0.119823 | X7: 0.0562 | Y7: החוב לא נחות | Z7: לא | AA7: חברת ציטוט | AB7: אי תלות | AC7: מרווח הוגן | AD7: 31/03/2024 | AF7: 14000 | AG7: 3.681 | AH7: 100.5705 | AI7: 51.828 | AL7: שווי הוגן | AM7: 0.39921404 | AN7: 0.0016790474
A8: 337 | B8: 9963 | C8: אדמה פתרונות לחקלאות בע"מ | D8: 520043605 | E8: ח.פ | F8: אדמה נעמ סדרה 2 | G8: IL0011619835 | H8: ISIN | I8: צמוד למט"ח | J8: ישראל | K8: ישראל | L8: כימיה, גומי ופלסטיק | M8: לא | N8: 14/06/2023 | O8: AA- | P8: S&P מעלות | Q8: נייר ערך | R8: USD | S8: 0.04 | T8: צמוד למדד אחר | U8: Libor | V8: 15/11/2024 | W8: 0.063598 | X8: 0.0674 | Y8: החוב לא נחות | Z8: לא | AA8: חברת ציטוט | AB8: אי תלות | AC8: מרווח הוגן | AD8: 31/03/2024 | AF8: 557000 | AG8: 3.681 | AH8: 100.72998 | AI8: 2065.284 | AL8: שווי הוגן | AM8: 0.42024741 | AN8: 0.0020100877
A9: 337 | B9: 9963 | C9: אורמת טכנולגיות אינק | D9: 5493000TSHHWY24VHM09 | E9: LEI | F9: אורמת נעמ 2 לא סחיר | G9: IL0012004680 | H9: ISIN | I9: צמוד למט"ח | J9: חו"ל | K9: ארה"ב | L9: אנרגיה מתחדשת | M9: לא | N9: 31/10/2023 | O9: AA- | P9: S&P מעלות | Q9: נייר ערך | R9: USD | S9: 0.02 | T9: צמוד למדד אחר | U9: SOFR | V9: 25/09/2028 | W9: 0.063982 | X9: 0.0572 | Y9: החוב לא נחות | Z9: לא | AA9: חברת ציטוט | AB9: אי תלות | AC9: מרווח הוגן | AD9: 31/03/2024 | AF9: 245000 | AG9: 3.681 | AH9: 101.24001 | AI9: 913.028 | AL9: שווי הוגן | AM9: 0.1857844 | AN9: 0.00088862637
A10: 337 | B10: 9963 | C10: אלביט מערכות בע"מ | D10: 520043027 | E10: ח.פ | F10: אלביט מערכות נעמ1-ל | G10: IL0011991572 | H10: ISIN | I10: צמוד למט"ח | J10: ישראל | K10: ישראל | L10: ביטחוניות | M10: לא | N10: 31/08/2023 | O10: AA | P10: S&P מעלות | Q10: נייר ערך | R10: USD | S10: 0.05 | T10: צמוד למדד אחר | U10: SOFR | V10: 04/08/2028 | W10: 0.119823 | X10: 0.0562 | Y10: החוב לא נחות | Z10: לא | AA10: חברת ציטוט | AB10: אי תלות | AC10: מרווח הוגן | AD10: 31/03/2024 | AF10: 523000 | AG10: 3.681 | AH10: 100.56998 | AI10: 1936.136 | AL10: שווי הוגן | AM10: 0.39396819 | AN10: 0.0018843914
A11: 337 | B11: 9964 | C11: אדמה פתרונות לחקלאות בע"מ | D11: 520043605 | E11: ח.פ | F11: אדמה נעמ סדרה 2 | G11: IL0011619835 | H11: ISIN | I11: צמוד למט"ח | J11: ישראל | K11: ישראל | L11: כימיה, גומי ופלסטיק | M11: לא | N11: 14/06/2023 | O11: AA- | P11: S&P מעלות | Q11: נייר ערך | R11: USD | S11: 0.04 | T11: צמוד למדד אחר | U11: Libor | V11: 15/11/2024 | W11: 0.063598 | X11: 0.0674 | Y11: החוב לא נחות | Z11: לא | AA11: חברת ציטוט | AB11: אי תלות | AC11: מרווח הוגן | AD11: 31/03/2024 | AF11: 17000 | AG11: 3.681 | AH11: 100.7303 | AI11: 63.034 | AL11: שווי הוגן | AM11: 0.40463183 | AN11: 0.0018170788
A12: 337 | B12: 9964 | C12: אורמת טכנולגיות אינק | D12: 5493000TSHHWY24VHM09 | E12: LEI | F12: אורמת נעמ 2 לא סחיר | G12: IL0012004680 | H12: ISIN | I12: צמוד למט"ח | J12: חו"ל | K12: ארה"ב | L12: אנרגיה מתחדשת | M12: לא | N12: 31/10/2023 | O12: AA- | P12: S&P מעלות | Q12: נייר ערך | R12: USD | S12: 0.02 | T12: צמוד למדד אחר | U12: SOFR | V12: 25/09/2028 | W12: 0.063982 | X12: 0.0572 | Y12: החוב לא נחות | Z12: לא | AA12: חברת ציטוט | AB12: אי תלות | AC12: מרווח הוגן | AD12: 31/03/2024 | AF12: 8000 | AG12: 3.681 | AH12: 101.23947 | AI12: 29.813 | AL12: שווי הוגן | AM12: 0.19137906 | AN12: 0.00085942527
A13: 337 | B13: 9964 | C13: אלביט מערכות בע"מ | D13: 520043027 | E13: ח.פ | F13: אלביט מערכות נעמ1-ל | G13: IL0011991572 | H13: ISIN | I13: צמוד למט"ח | J13: ישראל | K13: ישראל | L13: ביטחוניות | M13: לא | N13: 31/08/2023 | O13: AA | P13: S&P מעלות | Q13: נייר ערך | R13: USD | S13: 0.05 | T13: צמוד למדד אחר | U13: SOFR | V13: 04/08/2028 | W13: 0.119823 | X13: 0.0562 | Y13: החוב לא נחות | Z13: לא | AA13: חברת ציטוט | AB13: אי תלות | AC13: מרווח הוגן | AD13: 31/03/2024 | AF13: 17000 | AG13: 3.681 | AH13: 100.5705 | AI13: 62.934 | AL13: שווי הוגן | AM13: 0.40398911 | AN13: 0.0018141925

Sheet לא סחיר איגרות חוב
A1: מספר קופה/קרן/ח.פ. עבור חברת ביטוח | B1: מספר מסלול | C1: שם מנפיק | D1: מספר מנפיק | E1: סוג מספר מזהה מנפיק | F1: שם נייר ערך | G1: מספר נייר ערך | H1: סוג מספר נייר ערך | I1: מאפיין עיקרי | J1: ישראל/חו"ל | K1: מדינה לפי חשיפה כלכלית | L1: סטאטוס סחירות | M1: ענף מסחר | N1: בעל עניין/צד קשור | O1: תאריך רכישה | P1: דירוג | Q1: שם מדרג | R1: דירוג נייר הערך/המנפיק | S1: מטבע פעילות | T1: מח"מ | U1: מועד פדיון | V1: תשואה לפדיון | W1: שיעור ריבית | X1: נחיתות חוזית | Y1: האם סווג כחוב בעייתי | Z1: סוג גורם משערך | AA1: תלות/אי-תלות המשערך | AB1: תאריך שערוך אחרון | AC1: תאריך אחרון בו נבחנה בפועל ירידת ערך | AD1: ערך נקוב (יחידות) | AE1: שער חליפין | AF1: שער נייר הערך | AG1: שווי הוגן (באלפי ש"ח) | AH1: עלות מופחתת (באלפי ש"ח) | AI1: עלות מופחתת (במטבע הפעילות) | AJ1: השיטה שיושמה בדוח הכספי | AK1: שיעור מנכסי אפיק ההשקעה | AL1: שיעור מסך נכסי ההשקעה
A2: 337 | B2: 1405 | C2: י.ח.ק להשקעות שותפות מוגבלת | D2: 550016091 | E2: ח.פ | F2: י.ח.ק. אגח ב רמ | G2: IL0011817835 | H2: ISIN | I2: לא צמוד למדד המחירים לצרכן | J2: ישראל | K2: ישראל | L2: אחר | M2: השקעה ואחזקות | N2: לא | O2: 19/11/2021 | P2: A+ | Q2: S&P | R2: נייר ערך | S2: ILS | T2: 2.59 | U2: 31/12/2028 | V2: 0.058 | W2: 0.0286 | X2: החוב לא נחות | Y2: לא | Z2: חברת ציטוט | AA2: אי תלות | AB2: 31/03/2024 | AD2: 9285.72 | AE2: 1 | AF2: 93.541481 | AG2: 8.686 | AJ2: שווי הוגן | AK2: 0.039627368 | AL2: 0.00082149169
A3: 337 | B3: 1405 | C3: כלל תעשיות בע"מ | D3: 520021874 | E3: ח.פ | F3: כלל תעש אגח טז-רמ | G3: IL0060802381 | H3: ISIN | I3: לא צמוד למדד המחירים לצרכן | J3: ישראל | K3: ישראל | L3: אחר | M3: השקעה ואחזקות | N3: לא | O3: 27/10/2021 | P3: A | Q3: S&P מעלות | R3: מנפיק | S3: ILS | T3: 2.42 | U3: 30/06/2027 | V3: 0.0603 | W3: 0.0447 | X3: החוב לא נחות | Y3: לא | Z3: חברת ציטוט | AA3: אי תלות | AB3: 31/03/2024 | AD3: 37387.99 | AE3: 1 | AF3: 97.659703 | AG3: 36.513 | AJ3: שווי הוגן | AK3: 0.16658317 | AL3: 0.0034533378
A4: 337 | B4: 1405 | C4: לידר החזקות והשקעות בע"מ | D4: 520037664 | E4: ח.פ | F4: לידר אגח ח - רמ | G4: IL0031803617 | H4: ISIN | I4: לא צמוד למדד המחירים לצרכן | J4: ישראל | K4: ישראל | L4: אחר | M4: השקעה ואחזקות | N4: לא | O4: 01/03/2021 | P4: A1 | Q4: מידרוג Moodys | R4: נייר ערך | S4: ILS | T4: 2.29 | U4: 15/02/2028 | V4: 0.0508 | W4: 0.021 | X4: החוב לא נחות | Y4: לא | Z4: חברת ציטוט | AA4: אי תלות | AB4: 31/03/2024 | AD4: 30285.74 | AE4: 1 | AF4: 93.79992 | AG4: 28.408 | AJ4: שווי הוגן | AK4: 0.12960546 | AL4: 0.0026867747
A5: 337 | B5: 1405 | C5: מת"ם - מרכז תעשיות מדע חיפה בע"מ | D5: 510687403 | E5: ח.פ | F5: מתם מרכז תעשיות מדע חיפה אגח א ר.מ | G5: IL0011389991 | H5: ISIN | I5: לא צמוד למדד המחירים לצרכן | J5: ישראל | K5: ישראל | L5: אחר | M5: נדל"ן מניב בישראל | N5: לא | O5: 04/03/2024 | P5: Aa2 | Q5: מידרוג Moodys | R5: נייר ערך | S5: ILS | T5: 2.01 | U5: 20/07/2040 | V5: 0.0481 | W5: 0.031 | X5: החוב לא נחות | Y5: לא | Z5: חברת ציטוט | AA5: אי תלות | AB5: 31/03/2024 | AD5: 11799 | AE5: 1 | AF5: 96.796339 | AG5: 11.421 | AJ5: שווי הוגן | AK5: 0.052107812 | AL5: 0.0010802164
A6: 337 | B6: 1405 | C6: עוגן-אג"ח חברתית 2 בע"מ | D6: 516556545 | E6: ח.פ | F6: עוגן חברתית 2 אגחא-רמ | G6: IL0011968315 | H6: ISIN | I6: לא צמוד למדד המחירים לצרכן | J6: ישראל | K6: ישראל | L6: אחר | M6: שירותים פיננסיים | N6: לא | O6: 19/06/2023 | P6: Aa3 | Q6: מידרוג Moodys | R6: נייר ערך | S6: ILS | T6: 1.06 | U6: 15/03/2026 | V6: 0.067 | W6: 0.065 | X6: החוב לא נחות | Y6: לא | Z6: חברת ציטוט | AA6: אי תלות | AB6: 31/03/2024 | AD6: 9683.16 | AE6: 1 | AF6: 99.791804 | AG6: 9.663 | AJ6: שווי הוגן | AK6: 0.04408455 | AL6: 0.00091389091
A7: 337 | B7: 1405 | C7: רפאל-רשות לפיתוח אמצעי לחימה בע"מ | D7: 520042185 | E7: ח.פ | F7: רפאל אגח ג | G7: IL0011402760 | H7: ISIN | I7: צמוד למדד המחירים לצרכן | J7: ישראל | K7: ישראל | L7: אחר | M7: ביטחוניות | N7: לא | O7: 05/05/2021 | P7: Aaa | Q7: מידרוג Moodys | R7: נייר ערך | S7: ILS | T7: 5.09 | U7: 20/12/2037 | V7: 0.0216 | W7: 0.0214 | X7: החוב לא נחות | Y7: לא | Z7: חברת ציטוט | AA7: אי תלות | AB7: 31/03/2024 | AD7: 29865.86 | AE7: 1 | AF7: 113.35016 | AG7: 33.853 | AJ7: שווי הוגן | AK7: 0.15444677 | AL7: 0.0032017453
A8: 337 | B8: 1405 | C8: רפאל-רשות לפיתוח אמצעי לחימה בע"מ | D8: 520042185 | E8: ח.פ | F8: רפאל אגח סדרה ה 2020/2026 | G8: IL0011402927 | H8: ISIN | I8: לא צמוד למדד המחירים לצרכן | J8: ישראל | K8: ישראל | L8: אחר | M8: ביטחוניות | N8: לא | O8: 05/05/2021 | P8: Aaa | Q8: מידרוג Moodys | R8: נייר ערך | S8: ILS | T8: 1.43 | U8: 15/03/2026 | V8: 0.0451 | W8: 0.025 | X8: החוב לא נחות | Y8: כן | Z8: חברת ציטוט | AA8: אי תלות | AB8: 31/03/2024 | AD8: 31979.84 | AE8: 1 | AF8: 97.38948 | AG8: 31.145 | AJ8: שווי הוגן | AK8: 0.14209308 | AL8: 0.0029456482
A9: 337 | B9: 1405 | C9: רפאל-רשות לפיתוח אמצעי לחימה בע"מ | D9: 520042185 | E9: ח.פ | F9: רפאל סד' ד 2020/2034 | G9: IL0011402844 | H9: ISIN | I9: לא צמוד למדד המחירים לצרכן | J9: ישראל | K9: ישראל | L9: אחר | M9: ביטחוניות | N9: לא | O9: 05/05/2021 | P9: Aaa | Q9: מידרוג Moodys | R9: נייר ערך | S9: ILS | T9: 4.72 | U9: 20/09/2026 | V9: 0.0501 | W9: 0.0374 | X9: החוב לא נחות | Y9: לא | Z9: חברת ציטוט | AA9: אי תלות | AB9: 31/03/2024 | AD9: 62875.52 | AE9: 1 | AF9: 94.629834 | AG9: 59.499 | AJ9: שווי הוגן | AK9: 0.27145179 | AL9: 0.0056273076
A10: 337 | B10: 1477 | C10: י.ח.ק להשקעות שותפות מוגבלת | D10: 550016091 | E10: ח.פ | F10: י.ח.ק. אגח ב רמ | G10: IL0011817835 | H10: ISIN | I10: לא צמוד למדד המחירים לצרכן | J10: ישראל | K10: ישראל | L10: אחר | M10: השקעה ואחזקות | N10: לא | O10: 19/11/2021 | P10: A+ | Q10: S&P | R10: נייר ערך | S10: ILS | T10: 2.59 | U10: 31/12/2028 | V10: 0.058 | W10: 0.0286 | X10: החוב לא נחות | Y10: לא | Z10: חברת ציטוט | AA10: אי תלות | AB10: 31/03/2024 | AD10: 5714.28 | AE10: 1 | AF10: 93.537594 | AG10: 5.345 | AJ10: שווי הוגן | AK10: 0.40704919 | AL10: 0.00053590941
A11: 337 | B11: 1477 | C11: רפאל-רשות לפיתוח אמצעי לחימה בע"מ | D11: 520042185 | E11: ח.פ | F11: רפאל אגח סדרה ה 2020/2026 | G11: IL0011402927 | H11: ISIN | I11: לא צמוד למדד המחירים לצרכן | J11: ישראל | K11: ישראל | L11: אחר | M11: ביטחוניות | N11: לא | O11: 05/05/2021 | P11: Aaa | Q11: מידרוג Moodys | R11: נייר ערך | S11: ILS | T11: 1.43 | U11: 15/03/2026 | V11: 0.0451 | W11: 0.025 | X11: החוב לא נחות | Y11: כן | Z11: חברת ציטוט | AA11: אי תלות | AB11: 31/03/2024 | AD11: 7994.96 | AE11: 1 | AF11: 97.386353 | AG11: 7.786 | AJ11: שווי הוגן | AK11: 0.59295081 | AL11: 0.00078066222
A12: 337 | B12: 9962 | C12: י.ח.ק להשקעות שותפות מוגבלת | D12: 550016091 | E12: ח.פ | F12: י.ח.ק. אגח ב רמ | G12: IL0011817835 | H12: ISIN | I12: לא צמוד למדד המחירים לצרכן | J12: ישראל | K12: ישראל | L12: אחר | M12: השקעה ואחזקות | N12: לא | O12: 19/11/2021 | P12: A+ | Q12: S&P | R12: נייר ערך | S12: ILS | T12: 2.59 | U12: 31/12/2028 | V12: 0.058 | W12: 0.0286 | X12: החוב לא נחות | Y12: לא | Z12: חברת ציטוט | AA12: אי תלות | AB12: 31/03/2024 | AD12: 13571.43 | AE12: 1 | AF12: 93.542095 | AG12: 12.695 | AJ12: שווי הוגן | AK12: 0.045041275 | AL12: 0.00041126679
A13: 337 | B13: 9962 | C13: כלל תעשיות בע"מ | D13: 520021874 | E13: ח.פ | F13: כלל תעש אגח טז-רמ | G13: IL0060802381 | H13: ISIN | I13: לא צמוד למדד המחירים לצרכן | J13: ישראל | K13: ישראל | L13: אחר | M13: השקעה ואחזקות | N13: לא | O13: 27/10/2021 | P13: A | Q13: S&P מעלות | R13: מנפיק | S13: ILS | T13: 2.42 | U13: 30/06/2027 | V13: 0.0603 | W13: 0.0447 | X13: החוב לא נחות | Y13: לא | Z13: חברת ציטוט | AA13: אי תלות | AB13: 31/03/2024 | AD13: 84164.79 | AE13: 1 | AF13: 97.659603 | AG13: 82.195 | AJ13: שווי הוגן | AK13: 0.29163179 | AL13: 0.0026628569
... A20: 337 | B20: 9963 | C20: אלון חברת הדלק לישראל בע"מ | D20: 520041690 | E20: ח.פ | F20: אלון חברת הדלק אגח סד' א TA | G20: IL0011015679 | H20: ISIN | I20: צמוד למדד המחירים לצרכן | J20: ישראל | K20: ישראל | L20: אחר | M20: השקעה ואחזקות | N20: לא | O20: 31/08/2016 | P20: N/R | Q20: אחר | R20: נייר ערך | S20: ILS | T20: 0.01 | U20: 30/06/2024 | V20: 0.0001 | W20: 0.0535 | X20: החוב לא נחות | Y20: לא | Z20: אחר | AA20: אי-תלות | AB20: 31/03/2024 | AD20: 127573.24 | AE20: 1 | AF20: 0 | AG20: 0 | AJ20: שווי הוגן | AK20: 7.9780278e-11 | AL20: 1.2416373e-12
A21: 337 | B21: 9963 | C21: גלובל פיננס ג'י.אר 8 בע"מ | D21: 513739466 | E21: ח.פ | F21: גלובל פינס גיאר 8 סד ה 2019 | G21: 32003 | H21: פנימי | I21: צמוד למדד המחירים לצרכן | J21: ישראל | K21: ישראל | L21: אחר | M21: אג"ח מובנות | N21: לא | O21: 15/12/2014 | P21: N/R | Q21: אחר | R21: מנפיק | S21: ILS | T21: 0.01 | U21: 19/01/2019 | V21: 0.0001 | W21: 0.088 | X21: החוב לא נחות | Y21: לא | Z21: אחר | AB21: 31/03/2024 | AD21: 187658.1 | AE21: 1 | AF21: 0 | AG21: 0 | AJ21: שווי הוגן | AK21: 1.1735545e-10 | AL21: 1.8264277e-12
A22: 337 | B22: 9963 | C22: גמול חברה להשקעות בע"מ | D22: 520018136 | E22: ח.פ | F22: גמול אגח א חש 12/09 | G22: 1116649 | H22: פנימי | I22: אחר | J22: ישראל | K22: ישראל | L22: אחר | M22: אחר | N22: לא | O22: 15/12/2014 | P22: N/R | Q22: אחר | R22: נייר ערך | S22: ILS | T22: 0.01 | U22: 28/06/2019 | V22: 0.0001 | W22: 0.045 | X22: החוב לא נחות | Y22: לא | Z22: אחר | AB22: 29/07/2021 | AD22: 443.07 | AE22: 1 | AF22: 0 | AG22: 0 | AJ22: שווי הוגן | AK22: 2.77082e-13 | AL22: 4.3122855e-15
A23: 337 | B23: 9963 | C23: וי.אי.די. התפלת מי אשקלון | D23: 513102384 | E23: ח.פ | F23: התפלת מי אשקלון VID | G23: IL0010876832 | H23: ISIN | I23: צמוד למדד המחירים לצרכן | J23: ישראל | K23: ישראל | L23: אחר | M23: שירותים פיננסיים | N23: לא | O23: 15/12/2014 | P23: AA | Q23: S&P מעלות | R23: נייר ערך | S23: ILS | T23: 0.79 | U23: 22/10/2025 | V23: 0.0202 | W23: 0.0775 | X23: החוב לא נחות | Y23: לא | Z23: חברת ציטוט | AA23: אי תלות | AB23: 31/03/2024 | AD23: 214285.33 | AE23: 1 | AF23: 145.40986 | AG23: 311.592 | AJ23: שווי הוגן | AK23: 0.019485999 | AL23: 0.00030326471
A24: 337 | B24: 9963 | C24: י.ח.ק להשקעות שותפות מוגבלת | D24: 550016091 | E24: ח.פ | F24: י.ח.ק. אגח ב רמ | G24: IL0011817835 | H24: ISIN | I24: לא צמוד למדד המחירים לצרכן | J24: ישראל | K24: ישראל | L24: אחר | M24: השקעה ואחזקות | N24: לא | O24: 19/11/2021 | P24: A+ | Q24: S&P | R24: נייר ערך | S24: ILS | T24: 2.59 | U24: 31/12/2028 | V24: 0.058 | W24: 0.0286 | X24: החוב לא נחות | Y24: לא | Z24: חברת ציטוט | AA24: אי תלות | AB24: 31/03/2024 | AD24: 755714.38 | AE24: 1 | AF24: 93.539969 | AG24: 706.895 | AJ24: שווי הוגן | AK24: 0.044206997 | AL24: 0.00068800281
A25: 337 | B25: 9963 | C25: כלל תעשיות בע"מ | D25: 520021874 | E25: ח.פ | F25: כלל תעש אגח טז-רמ | G25: IL0060802381 | H25: ISIN | I25: לא צמוד למדד המחירים לצרכן | J25: ישראל | K25: ישראל | L25: אחר | M25: השקעה ואחזקות | N25: לא | O25: 27/10/2021 | P25: A | Q25: S&P מעלות | R25: מנפיק | S25: ILS | T25: 2.42 | U25: 30/06/2027 | V25: 0.0603 | W25: 0.0447 | X25: החוב לא נחות | Y25: לא | Z25: חברת ציטוט | AA25: אי תלות | AB25: 31/03/2024 | AD25: 3340567.4 | AE25: 1 | AF25: 97.659996 | AG25: 3262.398 | AJ25: שווי הוגן | AK25: 0.20402008 | AL25: 0.0031752075
A26: 337 | B26: 9963 | C26: בנק לאומי לישראל בע"מ | D26: 520018078 | E26: ח.פ | F26: לאומי שטר הון 6.60% 01/2027 | G26: 6401764 | H26: פנימי | I26: צמוד למדד המחירים לצרכן | J26: ישראל | K26: ישראל | L26: אחר | M26: בנקים | N26: לא | O26: 15/12/2014 | P26: AA+ | Q26: S&P מעלות | R26: מנפיק | S26: ILS | T26: 1.77 | U26: 24/01/2027 | V26: 0.01516 | W26: 0.066 | X26: החוב לא נחות | Y26: לא | Z26: חברת ציטוט | AA26: אי תלות | AB26: 31/03/2024 | AD26: 525000 | AE26: 1 | AF26: 150.7099 | AG26: 791.227 | AJ26: שווי הוגן | AK26: 0.049480871 | AL26: 0.00077008122
A27: 337 | B27: 9963 | C27: לידר החזקות והשקעות בע"מ | D27: 520037664 | E27: ח.פ | F27: לידר אגח ח - רמ | G27: IL0031803617 | H27: ISIN | I27: לא צמוד למדד המחירים לצרכן | J27: ישראל | K27: ישראל | L27: אחר | M27: השקעה ואחזקות | N27: לא | O27: 01/03/2021 | P27: A1 | Q27: מידרוג Moodys | R27: נייר ערך | S27: ILS | T27: 2.29 | U27: 15/02/2028 | V27: 0.0508 | W27: 0.021 | X27: החוב לא נחות | Y27: לא | Z27: חברת ציטוט | AA27: אי תלות | AB27: 31/03/2024 | AD27: 1246286.6 | AE27: 1 | AF27: 93.800011 | AG27: 1169.017 | AJ27: שווי הוגן | AK27: 0.073106626 | AL27: 0.0011377738
A28: 337 | B28: 9963 | C28: מת"ם - מרכז תעשיות מדע חיפה בע"מ | D28: 510687403 | E28: ח.פ | F28: מתם מרכז תעשיות מדע חיפה אגח א ר.מ | G28: IL0011389991 | H28: ISIN | I28: לא צמוד למדד המחירים לצרכן | J28: ישראל | K28: ישראל | L28: אחר | M28: נדל"ן מניב בישראל | N28: לא | O28: 04/03/2024 | P28: Aa2 | Q28: מידרוג Moodys | R28: נייר ערך | S28: ILS | T28: 2.01 | U28: 20/07/2040 | V28: 0.0481 | W28: 0.031 | X28: החוב לא נחות | Y28: לא | Z28: חברת ציטוט | AA28: אי תלות | AB28: 31/03/2024 | AD28: 1126308 | AE28: 1 | AF28: 96.799987 | AG28: 1090.266 | AJ28: שווי הוגן | AK28: 0.068181804 | AL28: 0.0010611278
A29: 337 | B29: 9963 | C29: עוגן-אג"ח חברתית 2 בע"מ | D29: 516556545 | E29: ח.פ | F29: עוגן חברתית 2 אגחא-רמ | G29: IL0011968315 | H29: ISIN | I29: לא צמוד למדד המחירים לצרכן | J29: ישראל | K29: ישראל | L29: אחר | M29: שירותים פיננסיים | N29: לא | O29: 19/06/2023 | P29: Aa3 | Q29: מידרוג Moodys | R29: נייר ערך | S29: ILS | T29: 1.06 | U29: 15/03/2026 | V29: 0.067 | W29: 0.065 | X29: החוב לא נחות | Y29: לא | Z29: חברת ציטוט | AA29: אי תלות | AB29: 31/03/2024 | AD29: 828282.21 | AE29: 1 | AF29: 99.790022 | AG29: 826.543 | AJ29: שווי הוגן | AK29: 0.051689379 | AL29: 0.0008044527
A30: 337 | B30: 9963 | C30: קאר אנד גו (סדרה א) בע"מ | D30: 513406835 | E30: ח.פ | F30: קאר אנד גו %7.4 (חודשי+קרן) 07 | G30: IL0010882020 | H30: ISIN | I30: אחר | J30: ישראל | K30: ישראל | L30: אחר | M30: שירותים | N30: לא | O30: 15/12/2014 | P30: D | Q30: S&P מעלות | R30: נייר ערך | S30: ILS | T30: 0.01 | U30: 10/08/2007 | V30: 0.0001 | W30: 0.074 | X30: החוב נחות | Y30: כן | Z30: אחר | AA30: אי-תלות | AB30: 28/12/2014 | AD30: 94232.8 | AE30: 1 | AF30: 0 | AG30: 0 | AJ30: שווי הוגן | AK30: 5.8930219e-09 | AL30: 9.1714342e-11
A31: 337 | B31: 9963 | C31: רפאל-רשות לפיתוח אמצעי לחימה בע"מ | D31: 520042185 | E31: ח.פ | F31: רפאל אגח ג | G31: IL0011402760 | H31: ISIN | I31: צמוד למדד המחירים לצרכן | J31: ישראל | K31: ישראל | L31: אחר | M31: ביטחוניות | N31: לא | O31: 05/05/2021 | P31: Aaa | Q31: מידרוג Moodys | R31: נייר ערך | S31: ILS | T31: 5.09 | U31: 20/12/2037 | V31: 0.0216 | W31: 0.0214 | X31: החוב לא נחות | Y31: לא | Z31: חברת ציטוט | AA31: אי תלות | AB31: 31/03/2024 | AD31: 1872118.3 | AE31: 1 | AF31: 113.35 | AG31: 2122.046 | AJ31: שווי הוגן | AK31: 0.13270607 | AL31: 0.0020653325
A32: 337 | B32: 9963 | C32: רפאל-רשות לפיתוח אמצעי לחימה בע"מ | D32: 520042185 | E32: ח.פ | F32: רפאל אגח סדרה ה 2020/2026 | G32: IL0011402927 | H32: ISIN | I32: לא צמוד למדד המחירים לצרכן | J32: ישראל | K32: ישראל | L32: אחר | M32: ביטחוניות | N32: לא | O32: 05/05/2021 | P32: Aaa | Q32: מידרוג Moodys | R32: נייר ערך | S32: ILS | T32: 1.43 | U32: 15/03/2026 | V32: 0.0451 | W32: 0.025 | X32: החוב לא נחות | Y32: כן | Z32: חברת ציטוט | AA32: אי תלות | AB32: 31/03/2024 | AD32: 2014729.8 | AE32: 1 | AF32: 97.389984 | AG32: 1962.145 | AJ32: שווי הוגן | AK32: 0.12270638 | AL32: 0.0019097052
A33: 337 | B33: 9963 | C33: רפאל-רשות לפיתוח אמצעי לחימה בע"מ | D33: 520042185 | E33: ח.פ | F33: רפאל סד' ד 2020/2034 | G33: IL0011402844 | H33: ISIN | I33: לא צמוד למדד המחירים לצרכן | J33: ישראל | K33: ישראל | L33: אחר | M33: ביטחוניות | N33: לא | O33: 05/05/2021 | P33: Aaa | Q33: מידרוג Moodys | R33: נייר ערך | S33: ILS | T33: 4.72 | U33: 20/09/2026 | V33: 0.0501 | W33: 0.0374 | X33: החוב לא נחות | Y33: לא | Z33: חברת ציטוט | AA33: אי תלות | AB33: 31/03/2024 | AD33: 3961157.1 | AE33: 1 | AF33: 94.630001 | AG33: 3748.443 | AJ33: שווי הוגן | AK33: 0.23441579 | AL33: 0.0036482624
A34: 337 | B34: 9964 | C34: י.ח.ק להשקעות שותפות מוגבלת | D34: 550016091 | E34: ח.פ | F34: י.ח.ק. אגח ב רמ | G34: IL0011817835 | H34: ISIN | I34: לא צמוד למדד המחירים לצרכן | J34: ישראל | K34: ישראל | L34: אחר | M34: השקעה ואחזקות | N34: לא | O34: 19/11/2021 | P34: A+ | Q34: S&P | R34: נייר ערך | S34: ILS | T34: 2.59 | U34: 31/12/2028 | V34: 0.058 | W34: 0.0286 | X34: החוב לא נחות | Y34: לא | Z34: חברת ציטוט | AA34: אי תלות | AB34: 31/03/2024 | AD34: 22857.14 | AE34: 1 | AF34: 93.541887 | AG34: 21.381 | AJ34: שווי הוגן | AK34: 0.04590136 | AL34: 0.00061633869
... A41: 337 | B41: 9964 | C41: רפאל-רשות לפיתוח אמצעי לחימה בע"מ | D41: 520042185 | E41: ח.פ | F41: רפאל סד' ד 2020/2034 | G41: IL0011402844 | H41: ISIN | I41: לא צמוד למדד המחירים לצרכן | J41: ישראל | K41: ישראל | L41: אחר | M41: ביטחוניות | N41: לא | O41: 05/05/2021 | P41: Aaa | Q41: מידרוג Moodys | R41: נייר ערך | S41: ILS | T41: 4.72 | U41: 20/09/2026 | V41: 0.0501 | W41: 0.0374 | X41: החוב לא נחות | Y41: לא | Z41: חברת ציטוט | AA41: אי תלות | AB41: 31/03/2024 | AD41: 117891.57 | AE41: 1 | AF41: 94.630176 | AG41: 111.561 | AJ41: שווי הוגן | AK41: 0.23950682 | AL41: 0.0032159684

Sheet לא סחיר מניות מבכ ויהש
A1: מספר קופה/קרן/ח.פ. עבור חברת ביטוח | B1: מספר מסלול | C1: שם מנפיק | D1: מספר מנפיק | E1: סוג מספר מזהה מנפיק | F1: שם נייר ערך | G1: מספר נייר ערך | H1: סוג מספר נייר ערך | I1: מאפיין עיקרי | J1: ישראל/חו"ל | K1: מדינה לפי חשיפה כלכלית | L1: סטאטוס סחירות | M1: ענף מסחר | N1: בעל עניין/צד קשור | O1: תאריך רכישה | P1: מטבע פעילות | Q1: סוג גורם משערך | R1: תלות/אי-תלות המשערך | S1: תאריך שערוך אחרון | T1: תאריך אחרון בו נבחנה בפועל ירידת ערך | U1: ערך נקוב (יחידות) | V1: שער חליפין | W1: שער נייר הערך | X1: שווי הוגן (באלפי ש"ח) | Y1: שיעור מנכסי אפיק ההשקעה | Z1: שיעור מסך נכסי ההשקעה
A2: 337 | B2: 1405 | C2: PROSPECT CAPITAL CORP | D2: 549300FSD8T39P5Q0O47 | E2: LEI | F2: מניות בכורה Prospect 5.5% 1025 | G2: US74348T5083 | H2: ISIN | I2: מניות לא סחירות | J2: חו"ל | K2: ארה"ב | L2: אחר | M2: שירותים פיננסיים | N2: לא | O2: 27/04/2021 | P2: USD | Q2: אחר | S2: 27/04/2021 | U2: 570 | V2: 3.681 | W2: 25 | X2: 52.454 | Y2: 1 | Z2: 0.0049610192
A3: 337 | B3: 1477 | C3: וויו (veev) גרופ | D3: 832652993 | E3: פנימי | F3: C וויו גרופ | G3: US9224741010 | H3: ISIN | I3: מניות לא סחירות | J3: ישראל | K3: ישראל | L3: אחר | M3: השקעות בהיי-טק | N3: לא | O3: 08/03/2021 | P3: ILS | Q3: אחר | R3: אי-תלות | S3: 28/11/2023 | U3: 9693 | V3: 1 | W3: 0 | X3: 0 | Y3: 8.777506e-09 | Z3: 9.7183092e-12
A4: 337 | B4: 1477 | C4: PROSPECT CAPITAL CORP | D4: 549300FSD8T39P5Q0O47 | E4: LEI | F4: מניות בכורה Prospect 5.5% 1025 | G4: US74348T5083 | H4: ISIN | I4: מניות לא סחירות | J4: חו"ל | K4: ארה"ב | L4: אחר | M4: שירותים פיננסיים | N4: לא | O4: 27/04/2021 | P4: USD | Q4: אחר | S4: 27/04/2021 | U4: 120 | V4: 3.681 | W4: 25 | X4: 11.043 | Y4: 0.99999999 | Z4: 0.0011071834
A5: 337 | B5: 9962 | C5: וויו (veev) גרופ | D5: 832652993 | E5: פנימי | F5: C וויו גרופ | G5: US9224741010 | H5: ISIN | I5: מניות לא סחירות | J5: ישראל | K5: ישראל | L5: אחר | M5: השקעות בהיי-טק | N5: לא | O5: 08/03/2021 | P5: ILS | Q5: אחר | R5: אי-תלות | S5: 28/11/2023 | U5: 30695 | V5: 1 | W5: 0 | X5: 0 | Y5: 7.412237e-09 | Z5: 9.9441645e-12
A6: 337 | B6: 9962 | C6: PROSPECT CAPITAL CORP | D6: 549300FSD8T39P5Q0O47 | E6: LEI | F6: מניות בכורה Prospect 5.5% 1025 | G6: US74348T5083 | H6: ISIN | I6: מניות לא סחירות | J6: חו"ל | K6: ארה"ב | L6: אחר | M6: שירותים פיננסיים | N6: לא | O6: 27/04/2021 | P6: USD | Q6: אחר | S6: 27/04/2021 | U6: 450 | V6: 3.681 | W6: 25 | X6: 41.411 | Y6: 0.99999999 | Z6: 0.0013415875
A7: 337 | B7: 9963 | C7: לוסיקס בע"מ | D7: 515374742 | E7: ח.פ | F7: Lusix | G7: 62020193 | H7: פנימי | I7: מניות לא סחירות | J7: ישראל | K7: ארה"ב | L7: אחר | M7: Water Utilities | N7: לא | O7: 10/02/2022 | P7: USD | Q7: אחר | S7: 11/10/2023 | U7: 237368 | V7: 3.681 | W7: 273.836 | X7: 2392.645 | Y7: 0.14339815 | Z7: 0.0023286989
A8: 337 | B8: 9963 | C8: UVEYE LTD | D8: 514234202 | E8: ח.פ | F8: UVEYE LTD | G8: 62018262 | H8: פנימי | I8: מניות לא סחירות | J8: ישראל | K8: ישראל | L8: אחר | M8: השקעות בהיי-טק | N8: לא | O8: 18/05/2021 | P8: USD | Q8: אחר | S8: 26/12/2022 | U8: 167852 | V8: 3.681 | W8: 830.053 | X8: 5128.591 | Y8: 0.30737139 | Z8: 0.0049915246
A9: 337 | B9: 9963 | C9: אדאקום טכנולוגיות בע"מ | D9: 520036419 | E9: ח.פ | F9: אדאקום | G9: IL0002390123 | H9: ISIN | I9: מניות לא סחירות | J9: ישראל | K9: ישראל | L9: אחר | M9: ביוטכנולוגיה | N9: לא | O9: 15/12/2014 | P9: ILS | Q9: אחר | R9: אי-תלות | S9: 31/03/2024 | U9: 20165 | V9: 1 | W9: 0 | X9: 0 | Y9: 1.2085472e-11 | Z9: 1.9626072e-13
A10: 337 | B10: 9963 | C10: ג'נריישן ניהול בע"מ | D10: 515785012 | E10: ח.פ | F10: ג'נריישן ניהול בע"מ | G10: 56093 | H10: פנימי | I10: מניות לא סחירות | J10: ישראל | K10: ישראל | L10: אחר | M10: נדל"ן מניב בישראל | N10: לא | O10: 16/08/2018 | P10: ILS | Q10: אחר | R10: אי-תלות | S10: 29/11/2023 | U10: 396.62 | V10: 1 | W10: 126084.28 | X10: 500.075 | Y10: 0.029970979 | Z10: 0.00048671049
A11: 337 | B11: 9963 | C11: מניבים קרן הריט החדשה בע"מ | D11: 515327120 | E11: ח.פ | F11: מניבים ניהול הר | G11: 36475 | H11: פנימי | I11: מניות לא סחירות | J11: ישראל | K11: ישראל | L11: אחר | M11: נדל"ן מניב בישראל | N11: לא | O11: 03/11/2015 | P11: ILS | Q11: אחר | S11: 18/07/2023 | U11: 38 | V11: 1 | W11: 763150 | X11: 289.997 | Y11: 0.017380365 | Z11: 0.00028224656
A12: 337 | B12: 9963 | C12: וויו (veev) גרופ | D12: 832652993 | E12: פנימי | F12: C וויו גרופ | G12: US9224741010 | H12: ISIN | I12: מניות לא סחירות | J12: ישראל | K12: ישראל | L12: אחר | M12: השקעות בהיי-טק | N12: לא | O12: 08/03/2021 | P12: ILS | Q12: אחר | R12: אי-תלות | S12: 28/11/2023 | U12: 2116317 | V12: 1 | W12: 0 | X12: 0 | Y12: 1.2683704e-09 | Z12: 2.0597565e-11
A13: 337 | B13: 9963 | C13: wefox | D13: 28503 | E13: פנימי | F13: TARGET GLOBAL-NICKEL (WEFOX) | G13: 62018396 | H13: פנימי | I13: מניות לא סחירות | J13: חו"ל | K13: גרמניה | L13: אחר | M13: Technology Hardware, Storage & Peripherals | N13: לא | O13: 03/07/2022 | P13: EUR | Q13: אחר | S13: 31/03/2024 | U13: 502500 | V13: 3.979 | W13: 150.571 | X13: 3010.67 | Y13: 0.18043821 | Z13: 0.0029302068
A14: 337 | B14: 9963 | C14: Verbit Inc | D14: 28460 | E14: פנימי | F14: Verbit Inc | G14: 620182700 | H14: פנימי | I14: מניות לא סחירות | J14: חו"ל | K14: גלובלי | L14: אחר | M14: Technology Hardware, Storage & Peripherals | N14: לא | O14: 20/03/2023 | P14: USD | Q14: אחר | S14: 21/03/2023 | U14: 3285 | V14: 3.681 | W14: 20229.372 | X14: 2446.153 | Y14: 0.14660506 | Z14: 0.0023807772
A15: 337 | B15: 9963 | C15: PROSPECT CAPITAL CORP | D15: 549300FSD8T39P5Q0O47 | E15: LEI | F15: מניות בכורה Prospect 5.5% 1025 | G15: US74348T5083 | H15: ISIN | I15: מניות לא סחירות | J15: חו"ל | K15: ארה"ב | L15: אחר | M15: שירותים פיננסיים | N15: לא | O15: 27/04/2021 | P15: USD | Q15: אחר | S15: 27/04/2021 | U15: 31700 | V15: 3.681 | W15: 25 | X15: 2917.193 | Y15: 0.17483584 | Z15: 0.0028392279
A16: 337 | B16: 9964 | C16: וויו (veev) גרופ | D16: 832652993 | E16: פנימי | F16: C וויו גרופ | G16: US9224741010 | H16: ISIN | I16: מניות לא סחירות | J16: ישראל | K16: ישראל | L16: אחר | M16: השקעות בהיי-טק | N16: לא | O16: 08/03/2021 | P16: ILS | Q16: אחר | R16: אי-תלות | S16: 28/11/2023 | U16: 24232 | V16: 1 | W16: 0 | X16: 0 | Y16: 3.0978794e-09 | Z16: 6.9853704e-12
A17: 337 | B17: 9964 | C17: PROSPECT CAPITAL CORP | D17: 549300FSD8T39P5Q0O47 | E17: LEI | F17: מניות בכורה Prospect 5.5% 1025 | G17: US74348T5083 | H17: ISIN | I17: מניות לא סחירות | J17: חו"ל | K17: ארה"ב | L17: אחר | M17: שירותים פיננסיים | N17: לא | O17: 27/04/2021 | P17: USD | Q17: אחר | S17: 27/04/2021 | U17: 850 | V17: 3.681 | W17: 25 | X17: 78.221 | Y17: 1 | Z17: 0.0022548878

Sheet קרנות השקעה
A1: מספר קופה/קרן/ח.פ. עבור חברת ביטוח | B1: מספר מסלול | C1: שם שותף כללי קרן השקעות | D1: מספר מזהה שותף כללי קרן השקעות | E1: סוג מספר מזהה שותף כללי קרן השקעות | F1: שם קרן השקעה | G1: מספר מזהה קרן השקעה | H1: סוג מספר מזהה קרן השקעות | I1: מאפיין עיקרי | J1: אסטרטגיית קרן ההשקעה | K1: ישראל/חו"ל | L1: מדינת התאגדות קרן השקעה | M1: מיקום משרד השותף הכללי | N1: מדינה לפי חשיפה כלכלית | O1: בעל עניין/צד קשור | P1: תאריך רכישה | Q1: מטבע פעילות | R1: סוג גורם משערך | S1: תלות/אי-תלות המשערך | T1: תאריך שערוך אחרון | U1: שער חליפין | V1: NAV (במטבע הדיווח של קרן ההשקעה) | W1: שווי הוגן (באלפי ש"ח) | X1: שיעור החזקה בקרן השקעה | Y1: שיעור מנכסי אפיק ההשקעה | Z1: שיעור מסך נכסי ההשקעה
A2: 337 | B2: 9962 | F2: Coller Credit Opportunities | G2: 62019286 | H2: פנימי | I2: קרן חוב | J2: Other | K2: חו"ל | N2: אירופה | O2: לא | P2: 02/09/2021 | Q2: USD | R2: דיווח מנהל הקרן | S2: אי-תלות | T2: 29/02/2024 | U2: 3.681 | V2: 12.596 | W2: 46.364 | Y2: 1 | Z2: 0.0015020481
A3: 337 | B3: 9963 | F3: Forma European Fund II LP | G3: 62018528 | H3: פנימי | I3: פרייבט אקוויטי | J3: Other | K3: ישראל | N3: אירופה | O3: לא | P3: 06/07/2021 | Q3: EUR | R3: דיווח מנהל הקרן | S3: אי-תלות | T3: 05/03/2024 | U3: 3.979 | V3: 372.851 | W3: 1483.61 | Y3: 0.0094662671 | Z3: 0.0014439589
A4: 337 | B4: 9963 | F4: KEDMA CAPITAL PARTNERS III LTD | G4: 62018080 | H4: פנימי | I4: פרייבט אקוויטי | J4: Other | K4: ישראל | N4: ישראל | O4: לא | P4: 04/04/2021 | Q4: USD | R4: דיווח מנהל הקרן | S4: אי-תלות | T4: 11/12/2023 | U4: 3.681 | V4: 735.072 | W4: 2705.8 | Y4: 0.017264528 | Z4: 0.0026334846
A5: 337 | B5: 9963 | F5: KLIRMARK FUND III | G5: 50000967 | H5: פנימי | I5: קרן חוב | J5: Other | K5: ישראל | N5: ישראל | O5: לא | P5: 13/11/2019 | Q5: ILS | R5: דיווח מנהל הקרן | S5: אי-תלות | T5: 31/03/2024 | U5: 1 | V5: 2275.56 | W5: 2275.56 | Y5: 0.014519357 | Z5: 0.0022147436
A6: 337 | B6: 9963 | F6: klirmark IV | G6: 50007947 | H6: פנימי | I6: קרן חוב | J6: Other | K6: ישראל | N6: ישראל | O6: לא | P6: 23/04/2023 | Q6: ILS | R6: דיווח מנהל הקרן | S6: אי-תלות | T6: 31/03/2024 | U6: 1 | V6: 1629.75 | W6: 1629.75 | Y6: 0.010398725 | Z6: 0.0015861934
A7: 337 | B7: 9963 | F7: Peregrine Ventures Growth General Partner LP | G7: 62018569 | H7: פנימי | I7: פרייבט אקוויטי | J7: Other | K7: ישראל | N7: גלובלי | O7: לא | P7: 07/07/2021 | Q7: USD | R7: דיווח מנהל הקרן | S7: אי-תלות | T7: 14/12/2023 | U7: 3.681 | V7: 410.495 | W7: 1511.031 | Y7: 0.0096412317 | Z7: 0.0014706475
A8: 337 | B8: 9963 | F8: Qumra Opportunity fund | G8: 62018254 | H8: פנימי | I8: פרייבט אקוויטי | J8: Growth Venture Capital | K8: חו"ל | N8: ישראל | O8: לא | P8: 11/05/2021 | Q8: USD | R8: דיווח מנהל הקרן | S8: אי-תלות | T8: 28/03/2024 | U8: 3.681 | V8: 301.931 | W8: 1111.408 | Y8: 0.0070914126 | Z8: 0.001081705
A9: 337 | B9: 9963 | F9: גרופ 11 קרן 5 | G9: 1181106 | H9: פנימי | I9: פרייבט אקוויטי | J9: Other | K9: ישראל | N9: ישראל | O9: לא | P9: 09/11/2021 | Q9: ILS | R9: דיווח מנהל הקרן | S9: אי-תלות | T9: 31/03/2024 | U9: 1 | V9: 1452 | W9: 1452 | Y9: 0.0092645793 | Z9: 0.001413194
A10: 337 | B10: 9963 | F10: יסודות נדל"ן ג' פיתוח ושותפות | G10: 50006691 | H10: פנימי | I10: קרן חוב | J10: Other | K10: ישראל | N10: ישראל | O10: לא | P10: 04/04/2021 | Q10: ILS | R10: דיווח מנהל הקרן | S10: אי-תלות | T10: 31/03/2024 | U10: 1 | V10: 3304.326 | W10: 3304.326 | Y10: 0.021083463 | Z10: 0.0032160146
A11: 337 | B11: 9963 | F11: קוגיטו קפיטל 2 | G11: 62020158 | H11: פנימי | I11: פרייבט אקוויטי | J11: Other | K11: ישראל | N11: ישראל | O11: לא | P11: 06/02/2022 | Q11: ILS | R11: דיווח מנהל הקרן | S11: אי-תלות | T11: 31/03/2024 | U11: 1 | V11: 2124.025 | W11: 2124.025 | Y11: 0.013552478 | Z11: 0.0020672585
A12: 337 | B12: 9963 | F12: קרן ברוש | G12: 50005 | H12: פנימי | I12: קרן גידור (Hedge Fund) | J12: Other | K12: ישראל | N12: ישראל | O12: לא | P12: 29/05/2017 | Q12: ILS | R12: דיווח מנהל הקרן | S12: אי-תלות | T12: 12/03/2024 | U12: 1 | V12: 8166.431 | W12: 8166.431 | Y12: 0.052106437 | Z12: 0.0079481756
A13: 337 | B13: 9963 | F13: תשתיות ישראל 4 -ע' ת"א | G13: 62017520 | H13: פנימי | I13: פרייבט אקוויטי | J13: Other | K13: ישראל | N13: ישראל | O13: לא | P13: 13/10/2020 | Q13: USD | R13: דיווח מנהל הקרן | S13: אי-תלות | T13: 28/03/2024 | U13: 3.681 | V13: 831.744 | W13: 3061.65 | Y13: 0.019535052 | Z13: 0.0029798243
... A62: 337 | B62: 9964 | F62: Coller Credit Opportunities | G62: 62019286 | H62: פנימי | I62: קרן חוב | J62: Other | K62: חו"ל | N62: אירופה | O62: לא | P62: 02/09/2021 | Q62: USD | R62: דיווח מנהל הקרן | S62: אי-תלות | T62: 29/02/2024 | U62: 3.681 | V62: 18.893 | W62: 69.546 | Y62: 1 | Z62: 0.0020048165

Sheet לא סחיר כתבי אופציה
A1: מספר קופה/קרן/ח.פ. עבור חברת ביטוח | B1: מספר מסלול | C1: שם מנפיק | D1: מספר מנפיק | E1: סוג מספר מזהה מנפיק | F1: שם נייר ערך | G1: מספר נייר ערך | H1: סוג מספר נייר ערך | I1: ישראל/חו"ל | J1: מדינה לפי חשיפה כלכלית | K1: סטאטוס סחירות | L1: נכס בסיס (כתב אופציה) | M1: ענף מסחר | N1: תאריך פקיעה | O1: בעל עניין/צד קשור | P1: תאריך רכישה | Q1: מטבע פעילות | R1: סוג גורם משערך | S1: תלות/אי-תלות המשערך | T1: תאריך שערוך אחרון | U1: שער מימוש | V1: יחס המרה | W1: ערך נקוב (יחידות) | X1: שער נייר הערך | Y1: שער חליפין | Z1: שווי הוגן (באלפי ש"ח) | AA1: שיעור מנכסי אפיק ההשקעה | AB1: שיעור מסך נכסי ההשקעה
A2: 337 | B2: 1477 | C2: בליץ טכנולוגיות בעמ | D2: 520038779 | E2: ח.פ | F2: בליץ אופציה לס 0621 | G2: 424999 | H2: פנימי | I2: ישראל | J2: ישראל | K2: אחר | L2: אחר | M2: אלקטרוניקה ואופטיקה | N2: 01/06/2024 | O2: לא | P2: 08/06/2021 | Q2: ILS | R2: אחר | T2: 11/02/2024 | U2: 350 | V2: 1 | W2: 1.94 | X2: 0 | Y2: 1 | Z2: 0 | AA2: 1.9670598e-11 | AB2: 1.9450655e-15
A3: 337 | B3: 1477 | C3: ע.י נופר אנרגי' בע"מ | D3: 514599943 | E3: ח.פ | F3: נופר אנרגי- כתבי אופציה | G3: 983730193 | H3: פנימי | I3: ישראל | J3: ישראל | K3: חסום | L3: אחר | M3: אנרגיה מתחדשת | N3: 02/01/2025 | O3: לא | P3: 03/01/2024 | Q3: ILS | R3: אחר | T3: 31/03/2024 | U3: 11200 | V3: 0 | W3: 178 | X3: 554.069 | Y3: 1 | Z3: 0.986 | AA3: 1 | AB3: 9.8881869e-05
A4: 337 | B4: 9962 | C4: בליץ טכנולוגיות בעמ | D4: 520038779 | E4: ח.פ | F4: בליץ אופציה לס 0621 | G4: 424999 | H4: פנימי | I4: ישראל | J4: ישראל | K4: אחר | L4: אחר | M4: אלקטרוניקה ואופטיקה | N4: 01/06/2024 | O4: לא | P4: 08/06/2021 | Q4: ILS | R4: אחר | T4: 11/02/2024 | U4: 350 | V4: 1 | W4: 6.42 | X4: 0 | Y4: 1 | Z4: 0 | AA4: 1.2069788e-10 | AB4: 2.0798676e-15
A5: 337 | B5: 9962 | C5: ע.י נופר אנרגי' בע"מ | D5: 514599943 | E5: ח.פ | F5: נופר אנרגי- כתבי אופציה | G5: 983730193 | H5: פנימי | I5: ישראל | J5: ישראל | K5: חסום | L5: אחר | M5: אנרגיה מתחדשת | N5: 02/01/2025 | O5: לא | P5: 03/01/2024 | Q5: ILS | R5: אחר | T5: 31/03/2024 | U5: 11200 | V5: 0 | W5: 96 | X5: 554.069 | Y5: 1 | Z5: 0.532 | AA5: 1 | AB5: 1.7232015e-05
A6: 337 | B6: 9963 | C6: בליץ טכנולוגיות בעמ | D6: 520038779 | E6: ח.פ | F6: בליץ אופציה לס 0621 | G6: 424999 | H6: פנימי | I6: ישראל | J6: ישראל | K6: אחר | L6: אחר | M6: אלקטרוניקה ואופטיקה | N6: 01/06/2024 | O6: לא | P6: 08/06/2021 | Q6: ILS | R6: אחר | T6: 11/02/2024 | U6: 350 | V6: 1 | W6: 403.1 | X6: 0 | Y6: 1 | Z6: 0 | AA6: 2.1979643e-10 | AB6: 3.9232678e-15
A7: 337 | B7: 9963 | C7: ע.י נופר אנרגי' בע"מ | D7: 514599943 | E7: ח.פ | F7: נופר אנרגי- כתבי אופציה | G7: 983730193 | H7: פנימי | I7: ישראל | J7: ישראל | K7: חסום | L7: אחר | M7: אנרגיה מתחדשת | N7: 02/01/2025 | O7: לא | P7: 03/01/2024 | Q7: ILS | R7: אחר | T7: 31/03/2024 | U7: 11200 | V7: 0 | W7: 3310 | X7: 554.069 | Y7: 1 | Z7: 18.34 | AA7: 1 | AB7: 1.7849552e-05
A8: 337 | B8: 9964 | C8: בליץ טכנולוגיות בעמ | D8: 520038779 | E8: ח.פ | F8: בליץ אופציה לס 0621 | G8: 424999 | H8: פנימי | I8: ישראל | J8: ישראל | K8: אחר | L8: אחר | M8: אלקטרוניקה ואופטיקה | N8: 01/06/2024 | O8: לא | P8: 08/06/2021 | Q8: ILS | R8: אחר | T8: 11/02/2024 | U8: 350 | V8: 1 | W8: 11.58 | X8: 0 | Y8: 1 | Z8: 0 | AA8: 1.8999917e-10 | AB8: 3.3381722e-15
A9: 337 | B9: 9964 | C9: ע.י נופר אנרגי' בע"מ | D9: 514599943 | E9: ח.פ | F9: נופר אנרגי- כתבי אופציה | G9: 983730193 | H9: פנימי | I9: ישראל | J9: ישראל | K9: חסום | L9: אחר | M9: אנרגיה מתחדשת | N9: 02/01/2025 | O9: לא | P9: 03/01/2024 | Q9: ILS | R9: אחר | T9: 31/03/2024 | U9: 11200 | V9: 0 | W9: 110 | X9: 554.069 | Y9: 1 | Z9: 0.609 | AA9: 1 | AB9: 1.7569404e-05

Sheet לא סחיר אופציות
A1: מספר קופה/קרן/ח.פ. עבור חברת ביטוח | B1: מספר מסלול | C1: שם מנפיק | D1: מספר מנפיק | E1: סוג מספר מזהה מנפיק | F1: שם נייר ערך | G1: מספר נייר ערך | H1: סוג מספר נייר ערך | I1: מאפיין עיקרי | J1: ישראל/חו"ל | K1: מדינה לפי חשיפה כלכלית | L1: ענף מסחר | M1: נכס בסיס | N1: תאריך פקיעה | O1: בעל עניין/צד קשור | P1: תאריך רכישה | Q1: מטבע פעילות | R1: סוג גורם משערך | S1: תלות/אי-תלות המשערך | T1: תאריך שערוך אחרון | U1: שער מימוש | V1: יחס המרה | W1: ערך נקוב (יחידות) | X1: שער נייר הערך | Y1: שער חליפין | Z1: שווי הוגן (בש"ח) | AA1: שיעור מנכסי אפיק ההשקעה | AB1: שיעור מסך נכסי ההשקעה

Sheet לא סחיר נגזרים אחרים
A1: מספר קופה/קרן/ח.פ. עבור חברת ביטוח | B1: מספר מסלול | C1: מאפיין עיקרי | D1: מספר עסקה (רגל 1) | E1: מטבע פעילות (רגל 1) | F1: שער חליפין | G1: ערך נקוב (רגל 1) | H1: שווי הוגן במטבע הנסחר (רגל 1) | I1: שיעור מנכסי אפיק ההשקעה (רגל 1) | J1: שיעור מסך נכסי ההשקעה (רגל 1) | K1: מספר עסקה (רגל 2) | L1: מטבע פעילות (רגל 2) | M1: שער חליפין | N1: ערך נקוב (רגל 2) | O1: שווי הוגן במטבע הנסחר (רגל 2) | P1: שיעור מנכסי ההשקעה (רגל 2) | Q1: שיעור מסך אפיק ההשקעה (רגל 2) | R1: שווי הוגן (נטו באלפי ש"ח) | S1: ישראל/חו"ל | T1: מדינה לפי חשיפה כלכלית | U1: סוג הנכס | V1: פקטור מוביל | W1: פקטור נוסף | X1: טיקר | Y1: בעל עניין/צד קשור | Z1: מועד ההתקשרות בעסקה | AA1: מועד סיום חוזי | AB1: תדירות Reset | AC1: סוג הסליקה | AD1: נספח התחשבנות בטחונות - CSA | AE1: גורם מצטט | AF1: ריבית עוגן | AG1: תקופת ריבית עוגן | AH1: שיעור ריבית עוגן | AI1: שער נכס הבסיס במועד ההתקשרות בעסקה | AJ1: שער הנגזר במועד ההתקשרות בעסקה | AK1: האם קיים קנס בגין יציאה מוקדמת | AL1: שיעור הקנס בגין יציאה מוקדמת | AM1: צד נגדי - Counterparty | AN1: שיעור מנכסי אפיק ההשקעה | AO1: שיעור מסך נכסי ההשקעה
A2: 891 | B2: 9963 | C2: Unfunded Forward | D2: 9929091 | E2: USD | F2: 3.681 | G2: -500000 | H2: 1804.2327 | I2: 1 | J2: 2e-06 | K2: 9929091 | L2: ILS | M2: 1 | N2: 1823000 | O2: -1796.1527 | P2: -2e-06 | Q2: 1 | R2: 8.08 | S2: ישראל | T2: ישראל | U2: מט"ח | V2: אחר | W2: אחר | X2: USD ILS | Y2: לא | Z2: 26/03/2024 | AA2: 28/06/2024 | AB2: רבעוני | AC2: No-delivery | AD2: לא | AE2: גורם אחר | AF2: Other | AG2: רבעוני | AH2: 0.05557 | AI2: -360.846 | AJ2: 362.982 | AK2: לא | AL2: NA | AM2: POALILIT | AN2: 1 | AO2: 0

Sheet הלוואות
A1: מספר קופה/קרן/ח.פ. עבור חברת ביטוח | B1: מספר מסלול | C1: מספר מזהה לווה | D1: סוג מספר מזהה לווה | E1: שם הלוואה | F1: מספר הלוואה | G1: מאפיין עיקרי | H1: מאפיין הלוואות מתואמות עבור זכויות מקרקעין | I1: ישראל/חו"ל | J1: מדינה לפי חשיפה כלכלית | K1: ענף מסחר | L1: בעל עניין/צד קשור | M1: קונסורציום/ סינדיקציה | N1: מספר קונסורציום/ סינדיקציה | O1: תאריך העמדת הלוואה | P1: דירוג | Q1: שם מדרג | R1: דירוג הלוואה/המנפיק | S1: מטבע פעילות | T1: מח"מ | U1: סוג הריבית | V1: שיעור ריבית | W1: סוג הצמדה | X1: ריבית עוגן | Y1: שיעור תוספת/הפחתה לריבית העוגן | Z1: תשואה לפדיון | AA1: מועד פדיון | AB1: נחיתות חוזית | AC1: סוג בטוחה | AD1: שווי הבטוחות העומדות כנגד ההלוואה | AE1: שיעור הבטוחות מהחוב | AF1: מועד עדכון אחרון לשווי הבטוחות | AG1: זכות חזרה | AH1: מבנה לוח סילוקין | AI1: יעוד הלוואה | AJ1: זכות פירעון מוקדם | AK1: סוג גורם משערך | AL1: שם גורם משערך | AM1: תלות/אי-תלות המשערך | AN1: תאריך שערוך אחרון | AO1: תאריך אחרון בו נבחנה בפועל ירידת ערך | AP1: שיעור ריבית בגין אי-ניצול מסגרת האשראי | AQ1: ערך נקוב | AR1: שער הלוואה | AS1: שער חליפין | AT1: שווי הוגן (באלפי ש"ח) | AU1: שווי הוגן (במטבע הפעילות) | AV1: עלות מופחתת (באלפי ש"ח) | AW1: עלות מופחתת (במטבע הפעילות) | AX1: האם סווג כחוב בעייתי | AY1: השיטה שיושמה בדוח הכספי | AZ1: שיעור מנכסי אפיק ההשקעה | BA1: שיעור מסך נכסי ההשקעה
A2: 337 | B2: 9963 | D2: ת"ז | E2: הלוואות לעמיתים | F2: 1000090 | G2: עמית/מבוטח | I2: ישראל | J2: ישראל | K2: אחר | L2: לא | M2: לא | O2: 15/12/2014 | P2: AA+ | Q2: פנימי | R2: הלוואה | S2: ILS | T2: 1.99 | U2: קבועה | V2: 0.055 | Z2: 0.0514 | AA2: 46112 | AB2: החוב לא נחות | AC2: חסכון עמיתים/מבוטחים | AG2: כן | AH2: בלון | AI2: לכל מטרה | AJ2: כן | AK2: חברת ציטוט | AL2: מרווח הוגן | AM2: אי-תלות | AN2: 31/03/2024 | AQ2: 47710883 | AR2: 100.199 | AS2: 1 | AT2: 47806.043 | AU2: 47806.043 | AX2: לא | AY2: שווי הוגן | AZ2: 1 | BA2: 0.046528382

Sheet לא סחיר מוצרים מובנים
A1: מספר קופה/קרן/ח.פ. עבור חברת ביטוח | B1: מספר מסלול | C1: שם מנפיק | D1: מספר מנפיק | E1: סוג מספר מזהה מנפיק | F1: שם נייר ערך | G1: מספר נייר ערך | H1: סוג מספר נייר ערך | I1: מאפיין עיקרי | J1: ישראל/חו"ל | K1: מדינה לפי חשיפה כלכלית | L1: בעל עניין/צד קשור | M1: נכס בסיס | N1: תאריך רכישה | O1: דירוג | P1: שם מדרג | Q1: דירוג נייר הערך/המנפיק | R1: מטבע פעילות | S1: מח"מ | T1: שיעור ריבית | U1: תשואה לפדיון | V1: סוג גורם משערך | W1: תלות/אי-תלות המשערך | X1: תאריך שערוך אחרון | Y1: ערך נקוב (יחידות) | Z1: שער חליפין | AA1: שער נייר הערך | AB1: שווי הוגן (באלפי ש"ח) | AC1: שיעור מנכסי אפיק ההשקעה | AD1: שיעור מסך נכסי ההשקעה

Sheet פיקדונות מעל 3 חודשים
A1: מספר קופה/קרן/ח.פ. עבור חברת ביטוח | B1: מספר מסלול | C1: שם הבנק | D1: מספר מזהה בנק | E1: סוג מספר מזהה בנק | F1: מאפיין עיקרי | G1: תאריך פקיעת פיקדון | H1: ישראל/חו"ל | I1: מדינה לפי חשיפה כלכלית | J1: בעל עניין/צד קשור | K1: דירוג הבנק | L1: שם מדרג | M1: מטבע פעילות | N1: מח"מ | O1: שיעור ריבית | P1: תשואה לפדיון | Q1: שווי מטבעי | R1: שער חליפין | S1: שער פיקדון | T1: שווי הוגן (באלפי ש"ח) | U1: שיעור מנכסי אפיק ההשקעה | V1: שיעור מסך נכסי ההשקעה

Sheet זכויות מקרקעין
A1: מספר קופה/קרן/ח.פ. עבור חברת ביטוח | B1: מספר מסלול | C1: שם הנכס | D1: מאפיין עיקרי | E1: מדינת מיקום נדל"ן | F1: בעל עניין/צד קשור | G1: תאריך רכישה | H1: שימוש עיקרי בנכס | I1: מחזור חיי הנכס | J1: כתובת הנכס | K1: שיעור תשואה בפועל במהלך הרבעון | L1: השיטה שבאמצעותה נקבע שווי הנכס | M1: סוג גורם משערך | N1: שם גורם משערך | O1: תלות/אי-תלות המשערך | P1: תאריך שערוך אחרון | Q1: מטבע פעילות | R1: שווי הוגן (במטבע הפעילות) | S1: שווי הוגן (באלפי ש"ח) | T1: עלות מופחתת (באלפי ש"ח) | U1: עלות מופחתת (במטבע הפעילות) | V1: השיטה שיושמה בדוח הכספי | W1: שיעור מנכסי אפיק ההשקעה | X1: שיעור מסך נכסי ההשקעה
A2: 337 | B2: 9963 | C2: זכויות בנכסי מקרקעין נדל"ן | D2: נדל"ן לא מניב | F2: לא | G2: 15/12/2014 | H2: אחר | I2: אחר | L2: אחר | M2: אחר | P2: 28/12/2023 | Q2: ILS | R2: 5150 | S2: 5150 | V2: שווי הוגן | W2: 1 | X2: 0.0050123616

Sheet השקעה בחברות מוחזקות
A1: מספר קופה/קרן/ח.פ. עבור חברת ביטוח | B1: מספר מסלול | C1: שם מנפיק | D1: מספר מנפיק | E1: סוג מספר מזהה מנפיק | F1: שם נייר ערך | G1: מספר נייר ערך | H1: סוג מספר נייר ערך | I1: מאפיין עיקרי | J1: ישראל/חו"ל | K1: מדינה לפי חשיפה כלכלית | L1: ענף מסחר | M1: בעל עניין/צד קשור | N1: מטבע פעילות | O1: סוג גורם משערך | P1: תלות/אי-תלות המשערך | Q1: תאריך שערוך אחרון | R1: תאריך אחרון בו נבחנה בפועל ירידת ערך | S1: שיעור אחזקה באמצעי שליטה | T1: שווי מאזני (באלפי ש"ח) | U1: שווי הוגן (באלפי ש"ח) | V1: שיעור מנכסי אפיק ההשקעה | W1: שיעור מסך נכסי ההשקעה

Sheet נכסים אחרים
A1: מספר קופה/קרן/ח.פ. עבור חברת ביטוח | B1: מספר מסלול | C1: שם הנכס האחר | D1: מספר הנכס האחר | E1: מאפיין עיקרי | F1: ישראל/חו"ל | G1: מדינה לפי חשיפה כלכלית | H1: בעל עניין/צד קשור | I1: תאריך עסקה | J1: מטבע פעילות | K1: תאריך שערוך אחרון | L1: שווי מטבעי | M1: שער חליפין | N1: שווי הוגן (באלפי ש"ח) | O1: עלות מופחתת (באלפי ש"ח) | P1: השיטה שיושמה בדוח הכספי | Q1: שיעור מנכסי אפיק ההשקעה | R1: שיעור מסך נכסי ההשקעה
A2: 337 | B2: 1405 | C2: ניכויי חברה מנהלת | D2: 28080000 | E2: חייבים וזכאים | G2: ישראל | H2: לא | I2: NA | J2: ILS | K2: 0 | L2: -13.612 | M2: 1 | N2: -13.612 | P2: שווי הוגן | Q2: 0.76723875 | R2: -0.0012873979
A3: 337 | B3: 1477 | C3: חייבים | D3: 27960000 | E3: חייבים וזכאים | G3: ישראל | H3: לא | I3: NA | J3: ILS | K3: 0 | L3: 0.05 | M3: 1 | N3: 0.05 | P3: שווי הוגן | Q3: 0.20859718 | R3: -0.00038955451
A4: 337 | B4: 1477 | C4: זכאים חברה מנהלת | D4: 28080000 | E4: חייבים וזכאים | G4: ישראל | H4: לא | I4: NA | J4: ILS | K4: 0 | L4: -14.79 | M4: 1 | N4: -14.79 | P4: שווי הוגן | Q4: 0.79140282 | R4: -0.001477942
A5: 337 | B5: 9962 | C5: זכאים חברה מנהלת | D5: 28080000 | E5: חייבים וזכאים | G5: ישראל | H5: לא | I5: NA | J5: ILS | K5: 0 | L5: -51.17 | M5: 1 | N5: -51.17 | P5: שווי הוגן | Q5: 0.30648769 | R5: -0.00064357616
A6: 337 | B6: 9962 | C6: זכאים מס עמיתים | D6: 28200000 | E6: חייבים וזכאים מס | G6: ישראל | H6: לא | I6: NA | J6: ILS | K6: 0 | L6: -1.736 | M6: 1 | N6: -1.736 | P6: שווי הוגן | Q6: 0.026781257 | R6: -5.6236445e-05
A7: 337 | B7: 9962 | C7: חייבים | D7: 27960000 | E7: חייבים וזכאים | G7: ישראל | H7: לא | I7: NA | J7: ILS | K7: 0 | L7: 0.08 | M7: 1 | N7: 0.08 | P7: שווי הוגן | Q7: 0.66673105 | R7: -0.0014000308
A8: 337 | B8: 9963 | C8: זכאים | D8: 28080000 | E8: חייבים וזכאים | G8: ישראל | H8: לא | I8: NA | J8: ILS | K8: 0 | L8: -3114.22 | M8: 1 | N8: -3114.22 | P8: שווי הוגן | Q8: 0.9490434 | R8: -0.003238271
A9: 337 | B9: 9963 | C9: זכאים מס עמיתים | D9: 28200000 | E9: חייבים וזכאים מס | G9: ישראל | H9: לא | I9: NA | J9: ILS | K9: 0 | L9: -25.908 | M9: 1 | N9: -25.908 | P9: שווי הוגן | Q9: 0.0073900971 | R9: -2.5216062e-05
A10: 337 | B10: 9964 | C10: חייבים | D10: 27960000 | E10: חייבים וזכאים | G10: ישראל | H10: לא | I10: NA | J10: ILS | K10: 0 | L10: 0.1 | M10: 1 | N10: 0.1 | P10: שווי הוגן | Q10: 0.72997017 | R10: -0.0012513242
A11: 337 | B11: 9964 | C11: זכאים חברה מנהלת | D11: 28080000 | E11: חייבים וזכאים | G11: ישראל | H11: לא | I11: NA | J11: ILS | K11: 0 | L11: -46.002 | M11: 1 | N11: -46.002 | P11: שווי הוגן | Q11: 0.27002983 | R11: -0.0004628886
A12: 337 | B12: 9963 | C12: חייבים | D12: 27960000 | E12: חייבים וזכאים | G12: ישראל | H12: לא | I12: NA | J12: ILS | K12: 0 | L12: 35.7 | M12: 1 | N12: 35.7 | P12: שווי הוגן | Q12: 0.043566505 | R12: -0.00014865511

Sheet מסגרות אשראי
A1: מספר קופה/קרן/ח.פ. עבור חברת ביטוח | B1: מספר מסלול | C1: מספר מזהה לווה | D1: סוג מספר מזהה לווה | E1: שם הלוואה | F1: מספר הלוואה | G1: תאריך העמדת מסגרת אשראי | H1: ישראל/חו"ל | I1: מדינה לפי חשיפה כלכלית | J1: בעל עניין/צד קשור | K1: דירוג | L1: שם מדרג | M1: דירוג הלוואה/המנפיק | N1: מטבע פעילות | O1: שער חליפין | P1: שיעור ריבית | Q1: סוג הריבית | R1: סכום מסגרת האשראי הראשוני (במטבע הפעילות) | S1: סכום מסגרת האשראי הראשוני (באלפי ש"ח) | T1: שיעור יתרת מסגרת אשראי

Sheet יתרות התחייבות להשקעה
A1: מספר קופה/קרן/ח.פ. עבור חברת ביטוח | B1: מספר מסלול | C1: מאפיין עיקרי | D1: שם שותף כללי קרן השקעות | E1: מספר מזהה שותף כללי קרן השקעות | F1: סוג מספר מזהה שותף כללי קרן השקעות | G1: שם קרן השקעה | H1: מספר מזהה קרן השקעה | I1: סוג מספר מזהה קרן השקעות | J1: מטבע פעילות | K1: תאריך העמדת התחייבות לקרן השקעה | L1: סכום המחויבות הראשוני (במטבע הדיווח של קרן ההשקעה) | M1: סכום המחויבות הראשוני (באלפי ש"ח) | N1: יתרת המחויבות לתקופת הדיווח (במטבע הדיווח של קרן ההשקעה) | O1: יתרת המחויבות לתקופת הדיווח (באלפי ש"ח) | P1: שיעור יתרת המחויבות | Q1: תאריך פקיעת מחויבות להשקעה
A2: 337 | B2: 9963 | C2: קרן השקעה אחרת | D2: Gatewood Capital GP LLC | G2: [GATEWOOD FUND (IBI) | H2: 62000698 | I2: פנימי | J2: USD | L2: 1200000 | M2: 4417.2 | N2: 341559.66 | O2: 1257.2811 | P2: 0.28463305 | Q2: 46424
A3: 337 | B3: 9963 | C3: קרן נדל"ן | D3: Alto Fund II GP, LLC | G3: ALTO FUND | H3: 60388022 | I3: פנימי | J3: USD | L3: 750000 | M3: 2760.75 | N3: 0 | O3: 0 | Q3: 0
A4: 337 | B4: 9963 | C4: קרן נדל"ן | D4: Alto Fund III GP, LLC | G4: ALTO III | H4: 62000073 | I4: פנימי | J4: USD | L4: 1327000 | M4: 4884.687 | N4: 67000 | O4: 246.627 | P4: 0.050489827 | Q4: 45655
A5: 337 | B5: 9963 | C5: קרן גידור (Hedge Fund) | D5: AMI GP L.P. Inc | G5: AMI OPPORTUNIT | H5: 60397874 | I5: פנימי | J5: USD | L5: 880000 | M5: 3239.28 | N5: 216319.07 | O5: 796.2705 | P5: 0.24581712 | Q5: 45622
A6: 337 | B6: 9963 | C6: קרן נדל"ן | D6: Apexus Logistics Re GP L.P. | G6: Apexus | H6: 62020409 | I6: פנימי | J6: USD | K6: 44665 | L6: 1300000 | M6: 4785.3 | N6: 0 | O6: 0 | Q6: 0
A7: 337 | B7: 9963 | C7: קרן השקעה אחרת | D7: ARKIN BIO CAPITAL, LIMITED PARTNERSHIP | G7: Arkin Bio Capital | H7: 62020128 | I7: פנימי | J7: USD | K7: 44581 | L7: 300000 | M7: 1104.3 | N7: 246187 | O7: 906.21435 | P7: 0.82062333 | Q7: 45572
A8: 337 | B8: 9963 | C8: קרן חוב | D8: Avenue Global Dislocation Opportunities GenPar, LLC, | G8: Avenue B-1 | H8: 62019567 | I8: פנימי | J8: USD | K8: 44481 | L8: 450000 | M8: 1656.45 | N8: 41622 | O8: 153.21058 | P8: 0.092493333 | Q8: 45616
A9: 337 | B9: 9963 | C9: קרן חוב | D9: Avenue Global Dislocation Opportunities GenPar, LLC, | G9: Avenue B-2 | H9: 62019575 | I9: פנימי | J9: USD | K9: 44481 | L9: 450000 | M9: 1656.45 | N9: 41622 | O9: 153.21058 | P9: 0.092493333 | Q9: 45616
A10: 337 | B10: 9963 | C10: קרן השקעה אחרת | D10: Bain Capital Distressed and Special Situations 2019 Investors, LLC | G10: BAIN CAPITAL DSS | H10: 62016845 | I10: פנימי | J10: USD | L10: 1000000 | M10: 3681 | N10: 182175.58 | O10: 670.58831 | P10: 0.18217558
A11: 337 | B11: 9963 | C11: קרן חוב | D11: Coller Credit Opportunities I General Partner, L.P. | G11: Coller Credit Opportunities | H11: 62019286 | I11: פנימי | J11: USD | K11: 44441 | L11: 950000 | M11: 3496.95 | N11: 448528.01 | O11: 1651.0316 | P11: 0.47213475 | Q11: 45987
A12: 337 | B12: 9963 | C12: קרן נדל"ן | D12: Crossroads Real Estate Partners II S.à r.l. | G12: Crossroads European Real Estate Fund II | H12: 62019765 | I12: פנימי | J12: EUR | L12: 585100 | M12: 2328.1714 | N12: 210963 | O12: 839.44287 | P12: 0.36055888
A13: 337 | B13: 9963 | C13: קרן השקעה אחרת | D13: HarbourVest GP LLC | G13: Dover Street XI L.P. Dover Street XI L.P | H13: 62021078 | I13: פנימי | J13: USD | K13: 45099 | L13: 900000 | M13: 3312.9 | N13: 729000 | O13: 2683.449 | P13: 0.81 | Q13: 46607
A14: 337 | B14: 9963 | C14: קרן נדל"ן | D14: American Landmark III | G14: ELECTRA 2 | H14: 62009865 | I14: פנימי | J14: USD | L14: 670000 | M14: 2466.27 | N14: 0 | O14: 0 | Q14: 0
A15: 337 | B15: 9963 | C15: קרן נדל"ן | D15: Electra America Hospitality AKA LLC | G15: Electra America Principal Hospitality | H15: 62020359 | I15: פנימי | J15: USD | K15: 44635 | L15: 2500000 | M15: 9202.5 | N15: 1192683 | O15: 4390.2661 | P15: 0.4770732
A16: 337 | B16: 9963 | C16: קרן חוב | D16: Electra Capital Advisors LLC | G16: Electra Capital PM Fund | H16: 62016969 | I16: פנימי | J16: USD | L16: 1150000 | M16: 4233.15 | N16: 0 | O16: 0 | Q16: 0
A17: 337 | B17: 9963 | C17: קרן נדל"ן | D17: FORMA EUROPEAN FUND II GENERAL PARTNER LTD | G17: Forma European Fund II LP Forma European Fund II | H17: 62018528 | I17: פנימי | J17: EUR | K17: 44382 | L17: 580000 | M17: 2307.878 | N17: 131377 | O17: 522.76222 | P17: 0.22651207
A18: 337 | B18: 9963 | C18: קרן נדל"ן | D18: FORMA FUND GENERAL PARTNER LTD | G18: FORMA FUND | H18: 62017942 | I18: פנימי | J18: EUR | L18: 1200000 | M18: 4774.92 | N18: 7401.8 | O18: 29.452502 | P18: 0.0061681667 | Q18: 45814
A19: 337 | B19: 9963 | C19: קרן אנרגיה ותשתיות | D19: EQT Infrastructure V (General Partner) S.à r.l. | G19: Fund EQT Infrastructure V | H19: 62018890 | I19: פנימי | J19: EUR | K19: 44417 | L19: 1150000 | M19: 4575.965 | N19: 229637.36 | O19: 913.75002 | P19: 0.19968466 | Q19: 46688
A20: 337 | B20: 9963 | C20: קרן השקעה אחרת | D20: Group 11 GP VI LLC | G20: Group 11 Fund VI, L.P | H20: 62020540 | I20: פנימי | J20: USD | K20: 44707 | L20: 300000 | M20: 1104.3 | N20: 15000 | O20: 55.215 | P20: 0.05 | Q20: 46538
A21: 337 | B21: 9963 | C21: קרן השקעה אחרת | D21: Group 11 GP IV LLC | G21: GROUP 11 IV | H21: 62017959 | I21: פנימי | J21: USD | K21: 44993 | L21: 230000 | M21: 846.63 | N21: 0 | O21: 0 | Q21: 0
A22: 337 | B22: 9963 | C22: קרן השקעה אחרת | D22: Group 11 GP V, LLC | G22: GROUP 11 V | H22: 62018130 | I22: פנימי | J22: USD | K22: 44306 | L22: 230000 | M22: 846.63 | N22: 0 | O22: 0 | Q22: 0
A23: 337 | B23: 9963 | C23: קרן השקעה אחרת | D23: Hanaco Growth GP, L.P. | G23: Hanaco Growth | H23: 62017876 | I23: פנימי | J23: USD | K23: 44258 | L23: 750000 | M23: 2760.75 | N23: 0 | O23: 0 | Q23: 0
A24: 337 | B24: 9963 | C24: קרן השקעה אחרת | D24: Hanaco II GP, L.P. | G24: Hanaco II L.P | H24: 62018734 | I24: פנימי | J24: USD | K24: 44403 | L24: 650000 | M24: 2392.65 | N24: 130000 | O24: 478.53 | P24: 0.2 | Q24: 46948
A25: 337 | B25: 9963 | C25: קרן השקעה אחרת | D25: HarbouVest Partners, LLC | G25: HARBOURVEST ACCESS CO INVEST V | H25: 62014352 | I25: פנימי | J25: USD | L25: 1000000 | M25: 3681 | N25: 225000 | O25: 828.225 | P25: 0.225 | Q25: 47392
A26: 337 | B26: 9963 | C26: קרן השקעה אחרת | D26: HarbourVest GP LLC | G26: HARBOURVEST ACCESS DOVER X | H26: 62015433 | I26: פנימי | J26: USD | L26: 1750000 | M26: 6441.75 | N26: 446250 | O26: 1642.6463 | P26: 0.255
A27: 337 | B27: 9963 | C27: קרן חוב | D27: HGI Multifamily Credit Fund GP LLC | G27: HGI Multifamily Credit Fund, LP | H27: 62021076 | I27: פנימי | J27: USD | K27: 44938 | L27: 1000000 | M27: 3681 | N27: 350000 | O27: 1288.35 | P27: 0.35 | Q27: 46203
A28: 337 | B28: 9963 | C28: קרן השקעה אחרת | D28: ISFM GPLP LTD | G28: ISF II | H28: 62000395 | I28: פנימי | J28: USD | L28: 1200000 | M28: 4417.2 | N28: 96000 | O28: 353.376 | P28: 0.08 | Q28: 46006
A29: 337 | B29: 9963 | C29: קרן השקעה אחרת | D29: Kedma Capital III G.P.L.P Limited Partnership | G29: KEDMA CAPITAL PARTNERS III LTD | H29: 62018080 | I29: פנימי | J29: USD | L29: 875000 | M29: 3220.875 | N29: 287834 | O29: 1059.517 | P29: 0.32895314
A30: 337 | B30: 9963 | C30: קרן השקעה אחרת | D30: Special Situations 2019 Investors, LLC | G30: KLIRMARK III | H30: 50000967 | I30: פנימי | J30: ILS | L30: 3600000 | M30: 3600 | N30: 1080000 | O30: 1080 | P30: 0.3 | Q30: 46691
A31: 337 | B31: 9963 | C31: קרן השקעה אחרת | D31: Klirmark Opportunity Fund | G31: Klirmark Opportunity Fund IV, L.P | H31: 50007947 | I31: פנימי | J31: ILS | K31: 45039 | L31: 5000000 | M31: 5000 | N31: 3500000 | O31: 3500 | P31: 0.7 | Q31: 47923
A32: 337 | B32: 9963 | C32: פרייבט אקוויטי | D32: LLCP LMM III GP L.P | G32: LLCP Lower Middle Market (LLM) III | H32: 62019021 | I32: פנימי | J32: USD | K32: 44431 | L32: 1500000 | M32: 5521.5 | N32: 772071.76 | O32: 2841.9961 | P32: 0.51471451 | Q32: 46727
A33: 337 | B33: 9963 | C33: קרן השקעה אחרת | D33: MACQUARIE INFRASTRUCTURE PARTNERS GP LLC | G33: MACQUARIE | H33: 62010970 | I33: פנימי | J33: USD | L33: 1300000 | M33: 4785.3 | N33: 74467.66 | O33: 274.11546 | P33: 0.057282815 | Q33: 47119
A34: 337 | B34: 9963 | C34: קרן חוב | D34: Madison Realty Capital Debt Fund VI GP LLC | G34: Madison Realty Capital Debt Fund VI LP | H34: 62021001 | I34: פנימי | J34: USD | K34: 44887 | L34: 1000000 | M34: 3681 | N34: 532235.09 | O34: 1959.1574 | P34: 0.53223509 | Q34: 46608
A35: 337 | B35: 9963 | C35: קרן נדל"ן | D35: Oak Street Real Estate Capital Fund VI, LP | G35: Oak Street Real Estate Capital Fund VI, LP | H35: 62021175 | I35: פנימי | J35: USD | K35: 45057 | L35: 800000 | M35: 2944.8 | N35: 728307.77 | O35: 2680.9009 | P35: 0.91038471 | Q35: 45747
A36: 337 | B36: 9963 | C36: פרייבט אקוויטי | D36: OEP VIII General Partner L.P | G36: One Equity Partners VIII, L.P. | H36: 62019740 | I36: פנימי | J36: USD | K36: 44518 | L36: 1250000 | M36: 4601.25 | N36: 111712 | O36: 411.21187 | P36: 0.0893696 | Q36: 49041
A37: 337 | B37: 9963 | C37: קרן השקעה אחרת | D37: Pagay Opportunity Manager Ltd. | G37: PAGAYA OPPORTUNITY | H37: 62018866 | I37: פנימי | J37: USD | K37: 44406 | L37: 1200000 | M37: 4417.2 | N37: 0 | O37: 0 | Q37: 0
A38: 337 | B38: 9963 | C38: קרן נדל"ן | D38: PAGAYA RE MANAGEMENT GP LLC | G38: Pagaya Smartresi F1 | H38: 62018486 | I38: פנימי | J38: USD | K38: 44381 | L38: 1515000 | M38: 5576.715 | N38: 0 | O38: 0 | Q38: 0
A39: 337 | B39: 9963 | C39: קרן אנרגיה ותשתיות | D39: Pantheon PGIF IV GP (LUX) S.à r.l | G39: Pantheon Global Infrastructure Fund IV (Luxembourg | H39: 62021282 | I39: פנימי | J39: USD | K39: 45132 | L39: 650000 | M39: 2392.65 | N39: 325333 | O39: 1197.5508 | P39: 0.50051231 | Q39: 46310
A40: 337 | B40: 9963 | C40: קרן השקעה אחרת | D40: PEREGRINE VENTURES GROWTH GENERAL PARTNER, LIMITED PARTNERSHIP | G40: Peregrin Growth | H40: 62018569 | I40: פנימי | J40: USD | K40: 44384 | L40: 600000 | M40: 2208.6 | N40: 223710 | O40: 823.47651 | P40: 0.37285 | Q40: 45549
A41: 337 | B41: 9963 | C41: פרייבט אקוויטי | D41: PGCO IV GP S.à r.l. | G41: PGCO IV I פנתאון | H41: 62014592 | I41: פנימי | J41: USD | L41: 1000000 | M41: 3681 | N41: 91751 | O41: 337.73543 | P41: 0.091751 | Q41: 46997
A42: 337 | B42: 9963 | C42: קרן השקעה אחרת | D42: Qumra Opportunity Fund GP, L.P. | G42: Qumra Opportunity | H42: 62018254 | I42: פנימי | J42: USD | K42: 44327 | L42: 450000 | M42: 1656.45 | N42: 117000 | O42: 430.677 | P42: 0.26 | Q42: 45775
