Workbook
Name Additional_Factor: 'אפשרויות בחירה'!$C$701:$C$850
Name Amoritization: 'אפשרויות בחירה'!$C$546:$C$550
Name Capsule: 'אפשרויות בחירה'!$C$926:$C$928
Name Company_Name: 'File Name Info'!$A$34:$A$120
Name Company_Name_ID: 'File Name Info'!$A$34:$B$120
Name Consortium: 'אפשרויות בחירה'!$C$514:$C$515
Name Country_list: 'אפשרויות בחירה'!$C$4:$C$85
Name Country_list_funds: 'אפשרויות בחירה'!$C$4:$C$103
Name CSA: 'אפשרויות בחירה'!$C$688:$C$689
Name Delivery: 'אפשרויות בחירה'!$C$666:$C$667
Name Dependence_Independence: 'אפשרויות בחירה'!$C$654:$C$655
Name Duration_Underlying_Interest_Rate: 'אפשרויות בחירה'!$C$680:$C$687
Name File_Type: 'File Name Info'!$A$10:$A$12
Name Full_File_Type: 'File Name Info'!$A$11:$B$13
Name Full_Type: 'File Name Info'!$A$2:$B$8
Name Full_Type_Nostro: 'File Name Info'!$A$3:$B$6
Name Full_Year: 'File Name Info'!$A$22:$B$31
Name Fund_Strategy: 'אפשרויות בחירה'!$C$597:$C$621
Name Fund_type: 'אפשרויות בחירה'!$C$328:$C$498
Name Holding_interest: 'אפשרויות בחירה'!$C$146:$C$147
Name In_the_books: 'אפשרויות בחירה'!$C$656:$C$657
Name Industry_Sector: 'אפשרויות בחירה'!$C$1129:$C$1245
Name Industry_sector_all: 'אפשרויות בחירה'!$C$202:$C$327
Name Industry_sectors: 'אפשרויות בחירה'!$C$202:$C$327
Name israel_abroad: 'אפשרויות בחירה'!$C$2:$C$3
Name Issuer_Number_Banks: 'אפשרויות בחירה'!$C$111:$C$113
Name Issuer_Number_Fund: 'אפשרויות בחירה'!$C$114:$C$117
Name issuer_number_loan: 'אפשרויות בחירה'!$C$118:$C$126
Name Issuer_Number_Type: 'אפשרויות בחירה'!$C$104:$C$110
Name Issuer_Number_Type_2: 'אפשרויות בחירה'!$C$1076:$C$1079
Name Issuer_Number_Type_3: 'אפשרויות בחירה'!$C$1081:$C$1085
Name Issuer_Number_Type_V2: 'אפשרויות בחירה'!$C$104:$C$110
Name Issuer_Type_TFunds: 'אפשרויות בחירה'!$C$1087:$C$1089
Name Leading_factor: 'אפשרויות בחירה'!$C$692:$C$700
Name Linked_Type: 'אפשרויות בחירה'!$C$516:$C$519
Name other_investments: 'אפשרויות בחירה'!$C$1000:$C$1033
Name Penalty: 'אפשרויות בחירה'!$C$851:$C$852
Name QTR: 'File Name Info'!$A$15:$A$19
Name Rating_Agency: 'אפשרויות בחירה'!$C$188:$C$201
Name real_estate_lifestage: 'אפשרויות בחירה'!$C$634:$C$642
Name real_estate_loans: 'אפשרויות בחירה'!$C$553:$C$591
Name Real_Estate_Main_Use: 'אפשרויות בחירה'!$C$622:$C$633
Name Recourse_Nonrecourse: 'אפשרויות בחירה'!$C$544:$C$545
Name Repayment_Rights: 'אפשרויות בחירה'!$C$551:$C$552
Name Reset_frequency: 'אפשרויות בחירה'!$C$658:$C$665
Name Security_ID_Number_Type: 'אפשרויות בחירה'!$C$1113:$C$1116
Name Security_Number_Loans: 'אפשרויות בחירה'!$C$131
Name Stock_Exchange: 'אפשרויות בחירה'!$C$1283:$C$1315
Name Stock_Exchange_Gov_Bonds: 'אפשרויות בחירה'!$C$148:$C$181
Name Subordination_Risk: 'אפשרויות בחירה'!$C$186:$C$187
Name Tradeable_Status: 'אפשרויות בחירה'!$C$1272:$C$1281
Name Tradeable_Status_All: 'אפשרויות בחירה'!$C$135:$C$145
Name tradeable_status_bonds: 'אפשרויות בחירה'!$C$1248:$C$1253
Name tradeable_status_funds: 'אפשרויות בחירה'!$C$1118:$C$1119
Name tradeable_status_stock: 'אפשרויות בחירה'!$C$1255:$C$1259
Name Tradeable_Status_v2: 'אפשרויות בחירה'!$C$1121:$C$1126
Name tradeable_status_warrants: 'אפשרויות בחירה'!$C$1261:$C$1265
Name tradeable_status_warrants_v2: 'אפשרויות בחירה'!$C$1267:$C$1269
Name Transaction: 'אפשרויות בחירה'!$C$643:$C$646
Name Type: 'File Name Info'!$A$2:$A$8

Sheet עמוד פתיחה
A1: קובץ דיווח עבור רשימת נכסים ברמת הנכס הבודד (חוזר גופים מוסדיים 2015-9-14)
A3: יש לבחור תחום: | D3: נכסי עמיתים - קופות גמל
A5: האם מדובר בקובץ לממומנה או לציבור: | D5: לממונה
A7: יש לבחור את רבעון הדיווח: | D7: 03
A9: יש לבחור את שנת הדיווח: | D9: 2024
A11: יש לבחור את הגוף המוסדי: | D11: סלייס גמל בע"מ
A13: ח.פ. הגוף המוסדי: | D13: =IFERROR(VLOOKUP(D11,'File Name Info'!A35:B121,2,0),"תא מחושב") -> 514767490
A15: שם קובץ לשמירה | D15: =IF(D5="לממונה",CONCATENATE(D13, "_",VLOOKUP(D3,Full_Type,2,0),"_",D7,VLOOKUP(D9,Full_Year,2,0),".xlxs"),IF(D5="לציבור",CONCATENATE(D13,"_",VLOOKUP(D3,Full_Type_Nostro,2,0),"_",VLOOKUP(D5,Full_File_Type,2,0),"_",D7,VLOOKUP(D9,Full_Year,2,0),".xlsx"),"שם קובץ לשמירה")) -> 514767490_gm_0324.xlxs
A17: פרטי האחראי על הדיווח בגוף המוסדי | B17: שם: | D17: אפרת ריינהרדט
B19: מספר טלפון:
B21: כתובת מייל: | D21: efrat@slice.co.il
A23: הוראות למילוי הדיווח: | D23: יש לדווח לפי ההנחיות בחלק ג' לנספח 5.4.3.2 שבפרק 3 שבחלק 4 לשער 5 בחוזר המאוחד - "רשימת נכסים ברמת הנכס הבודד".

Sheet סכום נכסים
C1: ידווח בקבצי נכסי הנוסטרו בלבד
B2: שווי הוגן | C2: עלות מופחתת | D2: השיטה שיושמה בדוח הכספי | E2: שיעור מסך נכסי השקעה
A3: מזומנים ושווי מזומנים | B3: =SUM('מזומנים ושווי מזומנים'!$O:$O) -> 127965.22 | D3: שווי הוגן | E3: =+B3/$B$30 -> 0.10969785
A4: איגרות חוב ממשלתיות | B4: =SUM('איגרות חוב ממשלתיות'!U:U) -> 254163.79 | D4: שווי הוגן | E4: =+B4/$B$30 -> 0.21788124
A5: ניירות ערך מסחריים | E5: =+B5/$B$30 -> 0
A6: איגרות חוב | E6: =+B6/$B$30 -> 0
A7: מניות, מניות בכורה ויחידות השתתפות | B7: =SUM('מניות מבכ ויהש'!U:U) -> 23153.063 | D7: שווי הוגן | E7: =+B7/$B$30 -> 0.019847902
A8: קרנות סל | B8: =SUM('קרנות סל'!T:T) -> 493851.76 | D8: שווי הוגן | E8: =+B8/$B$30 -> 0.42335312
A9: קרנות נאמנות | B9: =SUM('קרנות נאמנות'!T:T) -> 82248.895 | D9: שווי הוגן | E9: =+B9/$B$30 -> 0.070507648
A10: כתבי אופציה | E10: =+B10/$B$30 -> 0
A11: אופציות | E11: =+B11/$B$30 -> 0
A12: חוזים עתידיים | E12: =+B12/$B$30 -> 0
A13: מוצרים מובנים | E13: =+B13/$B$30 -> 0
A14: לא סחיר איגרות חוב ממשלתיות | E14: =+B14/$B$30 -> 0
A15: לא סחיר איגרות חוב מיועדות | E15: =+B15/$B$30 -> 0
A16: אפיק השקעה מובטח תשואה | E16: =+B16/$B$30 -> 0
A17: לא סחיר ניירות ערך מסחריים | E17: =+B17/$B$30 -> 0
A18: לא סחיר איגרות חוב | E18: =+B18/$B$30 -> 0
A19: לא סחיר מניות, מניות בכורה ויחידות השתתפות | E19: =+B19/$B$30 -> 0
A20: קרנות השקעה | B20: =SUM('קרנות השקעה'!W:W) -> 141585.03 | D20: שווי הוגן | E20: =+B20/$B$30 -> 0.12137339
A21: לא סחיר כתבי אופציה | E21: =+B21/$B$30 -> 0
A22: לא סחיר אופציות | E22: =+B22/$B$30 -> 0
A23: לא סחיר נגזרים אחרים | B23: =SUM('לא סחיר נגזרים אחרים'!R:R) -> 1058.4248 | D23: שווי הוגן | E23: =+B23/$B$30 -> 0.00090733188
A24: הלוואות | B24: =SUM(הלוואות!AT:AT) -> 42498.266 | D24: שווי הוגן | E24: =+B24/$B$30 -> 0.036431527
A25: לא סחיר מוצרים מובנים | E25: =+B25/$B$30 -> 0
A26: פיקדונות מעל 3 חודשים | E26: =+B26/$B$30 -> 0
A27: זכויות מקרקעין | E27: =+B27/$B$30 -> 0
A28: השקעה בחברות מוחזקות | E28: =+B28/$B$30 -> 0
A29: נכסים אחרים | E29: =+B29/$B$30 -> 0
A30: סך הכל נכסים | B30: =SUM(B3:B29) -> 1166524.5 | C30: =SUM(C3:C29) -> 0 | D30: =SUM(D3:D29) -> 0 | E30: =SUM(E3:E29) -> 1
A31: מסגרות אשראי
A32: יתרות התחייבויות להשקעה

Sheet מזומנים ושווי מזומנים
A1: מספר קופה/קרן/ח.פ. עבור חברת ביטוח | B1: מספר מסלול | C1: שם הבנק | D1: מספר מזהה בנק | E1: סוג מספר מזהה בנק | F1: מאפיין עיקרי | G1: ישראל/חו"ל | H1: בעל עניין/צד קשור | I1: דירוג הבנק | J1: שם מדרג | K1: מטבע פעילות | L1: שווי מטבעי | M1: שער חליפין | N1: שיעור ריבית | O1: שווי הוגן (באלפי ש"ח) | P1: שיעור מנכסי אפיק ההשקעה | Q1: שיעור מסך נכסי ההשקעה
A2: 7891 | B2: 7892 | C2: בנק לאומי לישראל בע"מ | D2: 10 | E2: סימול בנק | F2: מזומן ועו"ש בש"ח | G2: ישראל | H2: לא | I2: ilAAA | J2: S&P מעלות | K2: ILS | L2: 175.47464 | M2: 1 | O2: 175.47464 | P2: 1 | Q2: 0.080559322
A3: 7891 | B3: 7893 | C3: בנק לאומי לישראל בע"מ | D3: 10 | E3: סימול בנק | F3: מזומן ועו"ש בש"ח | G3: ישראל | H3: לא | I3: ilAAA | J3: S&P מעלות | K3: ILS | L3: 35.75117 | M3: 1 | O3: 35.75117 | P3: 1 | Q3: 0.032894699
A4: 7891 | B4: 7895 | C4: בנק הפועלים בע"מ | D4: 12 | E4: סימול בנק | F4: מזומן ועו"ש בש"ח | G4: ישראל | H4: לא | I4: ilAAA | J4: S&P מעלות | K4: ILS | L4: 23.27839 | M4: 1 | O4: 23.27839 | P4: 1 | Q4: 0.075035899
A5: 7891 | B5: 7896 | C5: בנק הפועלים בע"מ | D5: 12 | E5: סימול בנק | F5: מזומן ועו"ש בש"ח | G5: ישראל | H5: לא | I5: ilAAA | J5: S&P מעלות | K5: ILS | L5: 458.87737 | M5: 1 | O5: 458.87737 | P5: 0.88015165 | Q5: 0.028040601
A6: 7891 | B6: 7896 | C6: בנק הפועלים בע"מ | D6: 12 | E6: סימול בנק | F6: מזומן ועו"ש נקוב במט"ח | G6: ישראל | H6: לא | I6: ilAAA | J6: S&P מעלות | K6: USD | L6: 14.14112 | M6: 3.71 | O6: 52.46356 | P6: 0.10062795 | Q6: 0.0032058886
A7: 7891 | B7: 7896 | C7: בנק הפועלים בע"מ | D7: 12 | E7: סימול בנק | F7: מזומן ועו"ש נקוב במט"ח | G7: ישראל | H7: לא | I7: ilAAA | J7: S&P מעלות | K7: EUR | L7: 2.41325 | M7: 4.1524 | O7: 10.02078 | P7: 0.019220399 | Q7: 0.0006123394
A8: 7891 | B8: 7897 | C8: בנק הפועלים בע"מ | D8: 12 | E8: סימול בנק | F8: מזומן ועו"ש בש"ח | G8: ישראל | H8: לא | I8: ilAAA | J8: S&P מעלות | K8: ILS | L8: 93.16327 | M8: 1 | O8: 93.16327 | P8: 0.0055424686 | Q8: 0.0010199523
A9: 7891 | B9: 7897 | C9: בנק הפועלים בע"מ | D9: 12 | E9: סימול בנק | F9: מזומן ועו"ש נקוב במט"ח | G9: ישראל | H9: לא | I9: ilAAA | J9: S&P מעלות | K9: USD | L9: -0.00018 | M9: 3.71 | O9: -0.00067 | P9: -3.9859635e-08 | Q9: -7.335166e-09
A10: 7891 | B10: 7897 | C10: בנק הפועלים בע"מ | D10: 12 | E10: סימול בנק | F10: מזומן ועו"ש בש"ח | G10: ישראל | H10: לא | I10: ilAAA | J10: S&P מעלות | K10: ILS | L10: 13461.115 | M10: 1 | O10: 13461.115 | P10: 0.80082856 | Q10: 0.14737241
A11: 7891 | B11: 7897 | C11: בנק הפועלים בע"מ | D11: 12 | E11: סימול בנק | F11: מזומן ועו"ש נקוב במט"ח | G11: ישראל | H11: לא | I11: ilAAA | J11: S&P מעלות | K11: USD | L11: 855.80193 | M11: 3.71 | O11: 3175.0252 | P11: 0.18888858 | Q11: 0.034760204
A12: 7891 | B12: 7897 | C12: בנק הפועלים בע"מ | D12: 12 | E12: סימול בנק | F12: מזומן ועו"ש נקוב במט"ח | G12: ישראל | H12: לא | I12: ilAAA | J12: S&P מעלות | K12: EUR | L12: 19.18936 | M12: 4.1524 | O12: 79.6819 | P12: 0.0047404351 | Q12: 0.00087235815
A13: 7891 | B13: 7900 | C13: בנק הפועלים בע"מ | D13: 12 | E13: סימול בנק | F13: מזומן ועו"ש בש"ח | G13: ישראל | H13: לא | I13: ilAAA | J13: S&P מעלות | K13: ILS | L13: 286.74183 | M13: 1 | O13: 286.74183 | P13: 0.9529249 | Q13: 0.027287193
... A53: 11342 | B53: 11345 | C53: בנק לאומי לישראל בע"מ | D53: 10 | E53: סימול בנק | F53: מזומן ועו"ש נקוב במט"ח | G53: ישראל | H53: לא | I53: ilAAA | J53: S&P מעלות | K53: GBP | L53: 2e-05 | M53: 4.9748 | O53: 0.0001 | P53: 2.3806971e-07 | Q53: 5.0524326e-09
A54: 7891 | B54: 7894
A55: 7891 | B55: 7898
A56: 7891 | B56: 7899
A57: 7891 | B57: 7901
A58: 7891 | B58: 7902
A59: 11925 | B59: 11927
A60: 11925 | B60: 11929
A61: 11925 | B61: 11930
A62: 11925 | B62: 11932
A63: 11925 | B63: 11933
A64: 11925 | B64: 11935
A65: 11925 | B65: 11936
... A71: 11939 | B71: 11950

Sheet איגרות חוב ממשלתיות
A1: מספר קופה/קרן/ח.פ. עבור חברת ביטוח | B1: מספר מסלול | C1: שם מנפיק | D1: שם נייר ערך | E1: מספר נייר ערך | F1: מאפיין עיקרי | G1: ישראל/חו"ל | H1: מדינה לפי חשיפה כלכלית | I1: זירת מסחר | J1: דירוג | K1: שם מדרג | L1: מטבע פעילות | M1: מח"מ | N1: מועד פדיון | O1: שיעור ריבית | P1: תשואה לפדיון | Q1: סכום לקבל (במטבע הפעילות) | R1: ערך נקוב (יחידות) | S1: שער חליפין | T1: שער נייר הערך | U1: שווי הוגן (באלפי ש"ח) | V1: עלות מופחתת (באלפי ש"ח) | W1: השיטה שיושמה בדוח הכספי | X1: שיעור מערך נקוב מונפק | Y1: שיעור מנכסי אפיק ההשקעה | Z1: שיעור מסך נכסי ההשקעה
A2: 7891 | B2: 7897 | C2: מדינת ישראל | D2: ממשל שקלית 0229 | E2: IL0011948028 | F2: לא צמוד למדד המחירים לצרכן ריבית קבועה | G2: ישראל | H2: ישראל | I2: TASE | J2: RF | K2: אחר | L2: ILS | M2: 4.057 | N2: 47177 | O2: 0.0375 | P2: 0.0456 | Q2: 0 | R2: 3139910 | S2: 1 | T2: 99.02 | U2: 3109.1389 | W2: שווי הוגן | X2: 9.5246196e-05 | Y2: 0.59530917 | Z2: 0.03403888
A3: 7891 | B3: 7897 | C3: מדינת ישראל | D3: ממשל צמודה 1028 | E3: IL0011973265 | F3: צמוד למדד המחירים לצרכן בריבית קבועה | G3: ישראל | H3: ישראל | I3: TASE | J3: RF | K3: אחר | L3: ILS | M3: 3.975 | N3: 47057 | O3: 0.011 | P3: 0.018 | Q3: 0 | R3: 2060030 | S3: 1 | T3: 102.6 | U3: 2113.5908 | W3: שווי הוגן | X3: 0.00010098128 | Y3: 0.40469083 | Z3: 0.023139611
A4: 7891 | B4: 7900 | C4: מדינת ישראל | D4: ממשל שקלית 0229 | E4: IL0011948028 | F4: לא צמוד למדד המחירים לצרכן ריבית קבועה | G4: ישראל | H4: ישראל | I4: TASE | J4: RF | K4: אחר | L4: ILS | M4: 4.057 | N4: 47177 | O4: 0.0375 | P4: 0.0456 | Q4: 0 | R4: 1325500 | S4: 1 | T4: 99.02 | U4: 1312.5101 | W4: שווי הוגן | X4: 4.0207787e-05 | Y4: 0.59726397 | Z4: 0.12490231
A5: 7891 | B5: 7900 | C5: מדינת ישראל | D5: ממשל צמודה 1028 | E5: IL0011973265 | F5: צמוד למדד המחירים לצרכן בריבית קבועה | G5: ישראל | H5: ישראל | I5: TASE | J5: RF | K5: אחר | L5: ILS | M5: 3.975 | N5: 47057 | O5: 0.011 | P5: 0.018 | Q5: 0 | R5: 862600 | S5: 1 | T5: 102.6 | U5: 885.0276 | W5: שווי הוגן | X5: 4.2284069e-05 | Y5: 0.40273603 | Z5: 0.08422182
A6: 11925 | B6: 11926 | C6: מדינת ישראל | D6: ממשל שקלית 0229 | E6: IL0011948028 | F6: לא צמוד למדד המחירים לצרכן ריבית קבועה | G6: ישראל | H6: ישראל | I6: TASE | J6: RF | K6: אחר | L6: ILS | M6: 4.057 | N6: 47177 | O6: 0.0375 | P6: 0.0456 | Q6: 0 | R6: 2821600 | S6: 1 | T6: 99.02 | U6: 2793.9483 | W6: שווי הוגן | X6: 8.5590564e-05 | Y6: 0.59731925 | Z6: 0.11562341
A7: 11925 | B7: 11926 | C7: מדינת ישראל | D7: ממשל צמודה 1028 | E7: IL0011973265 | F7: צמוד למדד המחירים לצרכן בריבית קבועה | G7: ישראל | H7: ישראל | I7: TASE | J7: RF | K7: אחר | L7: ILS | M7: 3.975 | N7: 47057 | O7: 0.011 | P7: 0.018 | Q7: 0 | R7: 1835800 | S7: 1 | T7: 102.6 | U7: 1883.5308 | W7: שווי הוגן | X7: 8.9989676e-05 | Y7: 0.40268075 | Z7: 0.077947129
A8: 11925 | B8: 11928 | C8: מדינת ישראל | D8: ממשל שקלית 0229 | E8: IL0011948028 | F8: לא צמוד למדד המחירים לצרכן ריבית קבועה | G8: ישראל | H8: ישראל | I8: TASE | J8: RF | K8: אחר | L8: ILS | M8: 4.057 | N8: 47177 | O8: 0.0375 | P8: 0.0456 | Q8: 0 | R8: 3738230 | S8: 1 | T8: 99.02 | U8: 3701.5954 | W8: שווי הוגן | X8: 0.00011339567 | Y8: 0.59587329 | Z8: 0.028602018
A9: 11925 | B9: 11928 | C9: מדינת ישראל | D9: ממשל צמודה 1028 | E9: IL0011973265 | F9: צמוד למדד המחירים לצרכן בריבית קבועה | G9: ישראל | H9: ישראל | I9: TASE | J9: RF | K9: אחר | L9: ILS | M9: 3.975 | N9: 47057 | O9: 0.011 | P9: 0.018 | Q9: 0 | R9: 2446838 | S9: 1 | T9: 102.6 | U9: 2510.4558 | W9: שווי הוגן | X9: 0.00011994235 | Y9: 0.40412671 | Z9: 0.01939815
A10: 11939 | B10: 11942 | C10: מדינת ישראל | D10: ממשל שקלית 0229 | E10: IL0011948028 | F10: לא צמוד למדד המחירים לצרכן ריבית קבועה | G10: ישראל | H10: ישראל | I10: TASE | J10: RF | K10: אחר | L10: ILS | M10: 4.057 | N10: 47177 | O10: 0.0375 | P10: 0.0456 | Q10: 0 | R10: 5041152 | S10: 1 | T10: 99.02 | U10: 4991.7487 | W10: שווי הוגן | X10: 0.00015291857 | Y10: 0.60024365 | Z10: 0.017976467
A11: 11939 | B11: 11942 | C11: מדינת ישראל | D11: ממשל צמודה 1028 | E11: IL0011973265 | F11: צמוד למדד המחירים לצרכן בריבית קבועה | G11: ישראל | H11: ישראל | I11: TASE | J11: RF | K11: אחר | L11: ILS | M11: 3.975 | N11: 47057 | O11: 0.011 | P11: 0.018 | Q11: 0 | R11: 3240210 | S11: 1 | T11: 102.6 | U11: 3324.4555 | W11: שווי הוגן | X11: 0.0001588329 | Y11: 0.39975635 | Z11: 0.01197215
A12: 11939 | B12: 11979 | C12: מדינת ישראל | D12: ממשל שקלית 0229 | E12: IL0011948028 | F12: לא צמוד למדד המחירים לצרכן ריבית קבועה | G12: ישראל | H12: ישראל | I12: TASE | J12: RF | K12: אחר | L12: ILS | M12: 4.057 | N12: 47177 | O12: 0.0375 | P12: 0.0456 | Q12: 0 | R12: 2347870 | S12: 1 | T12: 99.02 | U12: 2324.8609 | W12: שווי הוגן | X12: 7.1220413e-05 | Y12: 0.59752086 | Z12: 0.071909663
A13: 11939 | B13: 11979 | C13: מדינת ישראל | D13: ממשל צמודה 1028 | E13: IL0011973265 | F13: צמוד למדד המחירים לצרכן בריבית קבועה | G13: ישראל | H13: ישראל | I13: TASE | J13: RF | K13: אחר | L13: ILS | M13: 3.975 | N13: 47057 | O13: 0.011 | P13: 0.018 | Q13: 0 | R13: 1526300 | S13: 1 | T13: 102.6 | U13: 1565.9838 | W13: שווי הוגן | X13: 7.4818195e-05 | Y13: 0.40247914 | Z13: 0.048437035
... A23: 11342 | B23: 11345 | C23: מדינת ישראל | D23: ממשל צמודה 1028 | E23: IL0011973265 | F23: צמוד למדד המחירים לצרכן בריבית קבועה | G23: ישראל | H23: ישראל | I23: TASE | J23: RF | K23: אחר | L23: ILS | M23: 3.975 | N23: 47057 | O23: 0.011 | P23: 0.018 | Q23: 0 | R23: 832764 | S23: 1 | T23: 102.6 | U23: 854.41586 | W23: שווי הוגן | X23: 4.0821529e-05 | Y23: 0.40236381 | Z23: 0.043168786
A24: 7891 | B24: 7892
A25: 7891 | B25: 7893
A26: 7891 | B26: 7894
A27: 7891 | B27: 7895
A28: 7891 | B28: 7896
A29: 7891 | B29: 7898
A30: 7891 | B30: 7899
A31: 7891 | B31: 7901
A32: 7891 | B32: 7902
A33: 11925 | B33: 11927
A34: 11925 | B34: 11929
A35: 11925 | B35: 11930
... A50: 11939 | B50: 11950

Sheet ניירות ערך מסחריים
A1: מספר קופה/קרן/ח.פ. עבור חברת ביטוח | B1: מספר מסלול | C1: שם מנפיק | D1: מספר מנפיק | E1: סוג מספר מזהה מנפיק | F1: שם נייר ערך | G1: מספר נייר ערך | H1: סוג מספר נייר ערך | I1: מאפיין עיקרי | J1: ישראל/חו"ל | K1: מדינה לפי חשיפה כלכלית | L1: זירת מסחר | M1: ענף מסחר | N1: בעל עניין/צד קשור | O1: דירוג | P1: שם מדרג | Q1: דירוג נייר הערך/המנפיק | R1: מטבע פעילות | S1: מח"מ | T1: ריבית עוגן | U1: מועד פדיון | V1: שיעור ריבית | W1: תשואה לפדיון | X1: נחיתות חוזית | Y1: האם סווג כחוב בעייתי | Z1: ערך נקוב (יחידות) | AA1: שער חליפין | AB1: שער נייר הערך | AC1: סכום לקבל (במטבע הפעילות) | AD1: שווי הוגן (באלפי ש"ח) | AE1: עלות מופחתת (באלפי ש"ח) | AF1: עלות מופחתת (במטבע הפעילות) | AG1: השיטה שיושמה בדוח הכספי | AH1: שיעור מערך נקוב מונפק | AI1: שיעור מנכסי אפיק ההשקעה | AJ1: שיעור מסך נכסי ההשקעה
A2: 7891 | B2: 7892
A3: 7891 | B3: 7893
A4: 7891 | B4: 7894
A5: 7891 | B5: 7895
A6: 7891 | B6: 7896
A7: 7891 | B7: 7897
A8: 7891 | B8: 7898
A9: 7891 | B9: 7899
A10: 7891 | B10: 7900
A11: 7891 | B11: 7901
A12: 7891 | B12: 7902
A13: 11925 | B13: 11926
... A39: 11342 | B39: 11345

Sheet איגרות חוב
A1: מספר קופה/קרן/ח.פ. עבור חברת ביטוח | B1: מספר מסלול | C1: שם מנפיק | D1: מספר מנפיק | E1: סוג מספר מזהה מנפיק | F1: שם נייר ערך | G1: מספר נייר ערך | H1: סוג מספר נייר ערך | I1: מאפיין עיקרי | J1: ישראל/חו"ל | K1: מדינה לפי חשיפה כלכלית | L1: סטאטוס סחירות | M1: זירת מסחר | N1: ענף מסחר | O1: בעל עניין/צד קשור | P1: דירוג | Q1: שם מדרג | R1: דירוג נייר הערך/המנפיק | S1: מטבע פעילות | T1: מח"מ | U1: מועד פדיון | V1: שיעור ריבית | W1: תשואה לפדיון | X1: נחיתות חוזית | Y1: האם סווג כחוב בעייתי | Z1: ערך נקוב (יחידות) | AA1: שער חליפין | AB1: שער נייר הערך | AC1: סכום לקבל (במטבע הפעילות) | AD1: שווי הוגן (באלפי ש"ח) | AE1: עלות מופחתת (באלפי ש"ח) | AF1: עלות מופחתת (במטבע הפעילות) | AG1: השיטה שיושמה בדוח הכספי | AH1: שיעור מערך נקוב מונפק | AI1: שיעור מנכסי אפיק ההשקעה | AJ1: שיעור מסך נכסי ההשקעה
A2: 7891 | B2: 7892
A3: 7891 | B3: 7893
A4: 7891 | B4: 7894
A5: 7891 | B5: 7895
A6: 7891 | B6: 7896
A7: 7891 | B7: 7897
A8: 7891 | B8: 7898
A9: 7891 | B9: 7899
A10: 7891 | B10: 7900
A11: 7891 | B11: 7901
A12: 7891 | B12: 7902
A13: 11925 | B13: 11926
... A39: 11342 | B39: 11345

Sheet מניות מבכ ויהש
A1: מספר קופה/קרן/ח.פ. עבור חברת ביטוח | B1: מספר מסלול | C1: שם מנפיק | D1: מספר מנפיק | E1: סוג מספר מזהה מנפיק | F1: שם נייר ערך | G1: מספר נייר ערך | H1: סוג מספר נייר ערך | I1: מאפיין עיקרי | J1: ישראל/חו"ל | K1: מדינה לפי חשיפה כלכלית | L1: סטאטוס סחירות | M1: זירת מסחר | N1: ענף מסחר | O1: בעל עניין/צד קשור | P1: מטבע פעילות | Q1: ערך נקוב (יחידות) | R1: שער חליפין | S1: שער נייר הערך | T1: סכום לקבל (במטבע הפעילות) | U1: שווי הוגן (באלפי ש"ח) | V1: שיעור מערך נקוב מונפק | W1: שיעור מנכסי אפיק ההשקעה | X1: שיעור מסך נכסי ההשקעה
A2: 11925 | B2: 11931 | C2: בזק החברה הישראלית לתקשורת בע" | D2: 520031931 | E2: ח.פ | F2: בזק | G2: IL0002300114 | H2: ISIN | I2: מניות | J2: ישראל | K2: ישראל | L2: סחיר | M2: TASE | N2: תקשורת ומדיה | O2: לא | P2: ILS | Q2: 105208 | R2: 1 | S2: 428.6 | T2: 15.46964 | U2: 466.39113 | V2: 3.8008937e-05 | W2: 0.02014382 | X2: 0.019910339
A3: 11925 | B3: 11931 | C3: ישראמקו נגב 2 שותפות מוגבלת | D3: 550010003 | E3: מספר שותפות | F3: ישראמקו יהש | G3: IL0002320179 | H3: ISIN | I3: יחידות השתתפות | J3: ישראל | K3: ישראל | L3: סחיר | M3: TASE | N3: חיפושי נפט וגז | O3: לא | P3: ILS | Q3: 423045 | R3: 1 | S3: 161.9 | T3: 0 | U3: 684.90985 | V3: 0.00016297558 | W3: 0.029581824 | X3: 0.029238951
A4: 11925 | B4: 11931 | C4: פורמולה מערכות (1985)בע"מ | D4: 520036690 | E4: ח.פ | F4: פורמולה מערכות | G4: IL0002560162 | H4: ISIN | I4: מניות | J4: ישראל | K4: ישראל | L4: סחיר | M4: TASE | N4: שירותי מידע | O4: לא | P4: ILS | Q4: 1962 | R4: 1 | S4: 29830 | T4: 0 | U4: 585.2646 | V4: 0.00012796208 | W4: 0.025278063 | X4: 0.024985073
A5: 11925 | B5: 11931 | C5: נייס בע"מ | D5: 520036872 | E5: ח.פ | F5: נייס | G5: IL0002730112 | H5: ISIN | I5: מניות | J5: ישראל | K5: ישראל | L5: סחיר | M5: TASE | N5: תוכנה ואינטרנט | O5: לא | P5: ILS | Q5: 330 | R5: 1 | S5: 64880 | T5: 0 | U5: 214.104 | V5: 5.2490017e-06 | W5: 0.0092473293 | X5: 0.0091401464
A6: 11925 | B6: 11931 | C6: מליסרון בע"מ | D6: 520037789 | E6: ח.פ | F6: מליסרון | G6: IL0003230146 | H6: ISIN | I6: מניות | J6: ישראל | K6: ישראל | L6: סחיר | M6: TASE | N6: נדל"ן מניב בישראל | O6: לא | P6: ILS | Q6: 1893 | R6: 1 | S6: 28210 | T6: 0 | U6: 534.0153 | V6: 3.9832574e-05 | W6: 0.023064564 | X6: 0.022797229
A7: 11925 | B7: 11931 | C7: רציו אנרגיות-שותפות מוגבלת | D7: 550012777 | E7: מספר שותפות | F7: רציו יהש | G7: IL0003940157 | H7: ISIN | I7: יחידות השתתפות | J7: ישראל | K7: ישראל | L7: סחיר | M7: TASE | N7: חיפושי נפט וגז | O7: לא | P7: ILS | Q7: 116729 | R7: 1 | S7: 303 | T7: 0 | U7: 353.68887 | V7: 0.00010386333 | W7: 0.015276116 | X7: 0.015099055
A8: 11925 | B8: 11931 | C8: מטריקס אי.טי בע"מ | D8: 520039413 | E8: ח.פ | F8: מטריקס | G8: IL0004450156 | H8: ISIN | I8: מניות | J8: ישראל | K8: ישראל | L8: סחיר | M8: TASE | N8: שירותי מידע | O8: לא | P8: ILS | Q8: 7053 | R8: 1 | S8: 7125 | T8: 5.78346 | U8: 508.30971 | V8: 0.00011103227 | W8: 0.021954318 | X8: 0.021699852
A9: 11925 | B9: 11931 | C9: ניו-מד אנרג'י- שותפות מוגבלת | D9: 550013098 | E9: מספר שותפות | F9: ניו-מד אנרג יהש | G9: IL0004750209 | H9: ISIN | I9: יחידות השתתפות | J9: ישראל | K9: ישראל | L9: סחיר | M9: TASE | N9: חיפושי נפט וגז | O9: לא | P9: ILS | Q9: 40344 | R9: 1 | S9: 1025 | T9: 0 | U9: 413.526 | V9: 3.4369991e-05 | W9: 0.017860531 | X9: 0.017653515
A10: 11925 | B10: 11931 | C10: מנורה מבטחים החזקות בע"מ | D10: 520007469 | E10: ח.פ | F10: מנורה מב החז | G10: IL0005660183 | H10: ISIN | I10: מניות | J10: ישראל | K10: ישראל | L10: סחיר | M10: TASE | N10: ביטוח | O10: לא | P10: ILS | Q10: 4741 | R10: 1 | S10: 10880 | T10: 0 | U10: 515.8208 | V10: 7.6454095e-05 | W10: 0.022278728 | X10: 0.022020502
A11: 11925 | B11: 11931 | C11: הבנק הבינלאומי הראשון לישראל ב | D11: 520029083 | E11: ח.פ | F11: בינלאומי | G11: IL0005930388 | H11: ISIN | I11: מניות | J11: ישראל | K11: ישראל | L11: סחיר | M11: TASE | N11: בנקים | O11: לא | P11: ILS | Q11: 3405 | R11: 1 | S11: 15410 | T11: 0 | U11: 524.7105 | V11: 3.3937991e-05 | W11: 0.022662682 | X11: 0.022400005
A12: 11925 | B12: 11931 | C12: בנק לאומי לישראל בע"מ | D12: 520018078 | E12: ח.פ | F12: לאומי | G12: IL0006046119 | H12: ISIN | I12: מניות | J12: ישראל | K12: ישראל | L12: סחיר | M12: TASE | N12: בנקים | O12: לא | P12: ILS | Q12: 14452 | R12: 1 | S12: 3644 | T12: 0 | U12: 526.63088 | V12: 9.5772947e-06 | W12: 0.022745624 | X12: 0.022481987
A13: 11925 | B13: 11931 | C13: ישרס חברה להשקעות בע"מ | D13: 520017807 | E13: ח.פ | F13: ישרס | G13: IL0006130343 | H13: ISIN | I13: מניות | J13: ישראל | K13: ישראל | L13: סחיר | M13: TASE | N13: נדל"ן מניב בישראל | O13: לא | P13: ILS | Q13: 908 | R13: 1 | S13: 73900 | T13: 0 | U13: 671.012 | V13: 0.00018174274 | W13: 0.028981565 | X13: 0.028645648
... A48: 11925 | B48: 11931 | C48: בתי זקוק לנפט בע"מ | D48: 520036658 | E48: ח.פ | F48: בזן | G48: IL0025902482 | H48: ISIN | I48: מניות | J48: ישראל | K48: ישראל | L48: סחיר | M48: TASE | N48: אנרגיה | O48: לא | P48: ILS | Q48: 738856 | R48: 1 | S48: 96.1 | T48: 0 | U48: 710.04062 | V48: 0.00023752322 | W48: 0.030667243 | X48: 0.030311789
A49: 7891 | B49: 7892
A50: 7891 | B50: 7893
A51: 7891 | B51: 7894
A52: 7891 | B52: 7895
A53: 7891 | B53: 7896
A54: 7891 | B54: 7897
A55: 7891 | B55: 7898
A56: 7891 | B56: 7899
A57: 7891 | B57: 7900
A58: 7891 | B58: 7901
A59: 7891 | B59: 7902
A60: 11925 | B60: 11926
... A85: 11342 | B85: 11345

Sheet קרנות סל
A1: מספר קופה/קרן/ח.פ. עבור חברת ביטוח | B1: מספר מסלול | C1: שם מנפיק | D1: מספר מנפיק | E1: סוג מספר מזהה מנפיק | F1: שם נייר ערך | G1: מספר נייר ערך | H1: סוג מספר נייר ערך | I1: מאפיין עיקרי | J1: ישראל/חו"ל | K1: מדינה לפי חשיפה כלכלית | L1: זירת מסחר | M1: סיווג הקרן | N1: בעל עניין/צד קשור | O1: מטבע פעילות | P1: ערך נקוב (יחידות) | Q1: שער חליפין | R1: שער נייר הערך | S1: סכום לקבל (במטבע הפעילות) | T1: שווי הוגן (באלפי ש"ח) | U1: שיעור מערך נקוב מונפק | V1: שיעור מנכסי אפיק ההשקעה | W1: שיעור מסך נכסי ההשקעה
A2: 7891 | B2: 7892 | C2: מיטב קרנות נאמנות בע"מ | D2: 513534974 | E2: ח.פ. | F2: תכ.תא35 | G2: IL0011437006 | H2: ISIN | I2: עוקב אחר מדדי מניות בישראל | J2: ישראל | K2: ישראל | L2: TASE | M2: Large & Mid Cap מניות בארץ - מניות לפי שווי שוק-מניות | N2: לא | O2: ILS | P2: 23974 | Q2: 1 | R2: 2092 | S2: 0 | T2: 501.53608 | U2: 0 | V2: 0.25042628 | W2: 0.23025211
A3: 7891 | B3: 7892 | C3: קסם קרנות נאמנות בע"מ | D3: 510938608 | E3: ח.פ. | F3: קסם.תא 35 | G3: IL0011465700 | H3: ISIN | I3: עוקב אחר מדדי מניות בישראל | J3: ישראל | K3: ישראל | L3: TASE | M3: Large & Mid Cap מניות בארץ - מניות לפי שווי שוק-מניות | N3: לא | O3: ILS | P3: 2412 | Q3: 1 | R3: 20810 | S3: 0 | T3: 501.9372 | U3: 0 | V3: 0.25062657 | W3: 0.23043626
A4: 7891 | B4: 7892 | C4: הראל קרנות נאמנות בע"מ | D4: 511776783 | E4: ח.פ. | F4: הרל.תא 35 | G4: IL0011489072 | H4: ISIN | I4: עוקב אחר מדדי מניות בישראל | J4: ישראל | K4: ישראל | L4: TASE | M4: Large & Mid Cap מניות בארץ - מניות לפי שווי שוק-מניות | N4: לא | O4: ILS | P4: 23830 | Q4: 1 | R4: 2094 | S4: 0 | T4: 499.0002 | U4: 0 | V4: 0.24916007 | W4: 0.22908791
A5: 7891 | B5: 7892 | C5: מגדל קרנות נאמנות בע"מ | D5: 511303661 | E5: ח.פ. | F5: MTF.תא35 | G5: IL0011501843 | H5: ISIN | I5: עוקב אחר מדדי מניות בישראל | J5: ישראל | K5: ישראל | L5: TASE | M5: Large & Mid Cap מניות בארץ - מניות לפי שווי שוק-מניות | N5: לא | O5: ILS | P5: 17559 | Q5: 1 | R5: 2849 | S5: 0 | T5: 500.25591 | U5: 0 | V5: 0.24978707 | W5: 0.22966439
A6: 7891 | B6: 7893 | C6: מיטב קרנות נאמנות בע"מ | D6: 513534974 | E6: ח.פ. | F6: תכ.תלבונד60 | G6: IL0011451015 | H6: ISIN | I6: עוקב אחר מדדים אחרים בישראל | J6: ישראל | K6: ישראל | L6: TASE | M6: אג"ח בארץ - חברות והמרה-תל בונד צמוד מדד-תל בונד צמודות | N6: לא | O6: ILS | P6: 72091 | Q6: 1 | R6: 365.33 | S6: 0 | T6: 263.37005 | U6: 0 | V6: 0.25056954 | W6: 0.24232713
A7: 7891 | B7: 7893 | C7: קסם קרנות נאמנות בע"מ | D7: 510938608 | E7: ח.פ. | F7: קסם.תלבונד 60 | G7: IL0011462327 | H7: ISIN | I7: עוקב אחר מדדים אחרים בישראל | J7: ישראל | K7: ישראל | L7: TASE | M7: אג"ח בארץ - חברות והמרה-תל בונד צמוד מדד-תל בונד צמודות | N7: לא | O7: ILS | P7: 7259 | Q7: 1 | R7: 3637.39 | S7: 0 | T7: 264.03814 | U7: 0 | V7: 0.25120516 | W7: 0.24294184
A8: 7891 | B8: 7893 | C8: אי.בי.אי קרנות נאמנות בעמ | D8: 513765339 | E8: ח.פ. | F8: IBI.תלבונד 60 | G8: IL0011480063 | H8: ISIN | I8: עוקב אחר מדדים אחרים בישראל | J8: ישראל | K8: ישראל | L8: TASE | M8: אג"ח בארץ - חברות והמרה-תל בונד צמוד מדד-תל בונד צמודות | N8: לא | O8: ILS | P8: 71580 | Q8: 1 | R8: 365.93 | S8: 0 | T8: 261.93269 | U8: 0 | V8: 0.24920204 | W8: 0.24100462
A9: 7891 | B9: 7893 | C9: הראל קרנות נאמנות בע"מ | D9: 511776783 | E9: ח.פ. | F9: הרל.תלבונד 60 | G9: IL0011504730 | H9: ISIN | I9: עוקב אחר מדדים אחרים בישראל | J9: ישראל | K9: ישראל | L9: TASE | M9: אג"ח בארץ - חברות והמרה-תל בונד צמוד מדד-תל בונד צמודות | N9: לא | O9: ILS | P9: 71827 | Q9: 1 | R9: 364.41 | S9: 0 | T9: 261.74477 | U9: 0 | V9: 0.24902326 | W9: 0.24083171
A10: 7891 | B10: 7895 | C10: מיטב קרנות נאמנות בע"מ | D10: 513534974 | E10: ח.פ. | F10: תכ.שחר | G10: IL0011451437 | H10: ISIN | I10: עוקב אחר מדדים אחרים בישראל | J10: ישראל | K10: ישראל | L10: TASE | M10: אג"ח בארץ - מדינה-אג"ח מדינה שקליות -שקליות ריבית קבועה ממשלתיות | N10: לא | O10: ILS | P10: 16140 | Q10: 1 | R10: 438.57 | S10: 0 | T10: 70.7852 | U10: 0 | V10: 1 | W10: =+T10/'סכום נכסים'!$B$30 -> 6.0680425e-05
A11: 7891 | B11: 7896 | C11: Amundi S&P 500 UCITS ETF | D11: 2138007NOUJ46G9POA93 | E11: LEI | F11: AMUNDI S&P 500 UCITS ETF | G11: LU1681048804 | H11: ISIN | I11: עוקב אחר מדדי מניות בחו"ל | J11: חו"ל | K11: ארה"ב | L11: NASDAQ | M11: Equity Funds | N11: לא | O11: EUR | P11: 7678 | Q11: 4.1524 | R11: 10076.66 | S11: 0 | T11: 3212.6536 | U11: 0 | V11: 0.20277569 | W11: 0.19631549
A12: 7891 | B12: 7896 | C12: Invesco | D12: ECPGFXU8A2SH | E12: LEI | F12: INVESCO S&P 500 ACC | G12: IE00B3YCGJ38 | H12: ISIN | I12: עוקב אחר מדדי מניות בחו"ל | J12: חו"ל | K12: ארה"ב | L12: LSE | M12: Equity Funds | N12: לא | O12: USD | P12: 761 | Q12: 3.71 | R12: 112716 | S12: 0 | T12: 3182.3221 | U12: 0 | V12: 0.20086123 | W12: 0.19446203
A13: 7891 | B13: 7896 | C13: iShares Core S&P 500 UCITS ETF | D13: 5493006ESS9BM09FB892 | E13: LEI | F13: ISHARES CORE S&P 500 | G13: IE00B5BMR087 | H13: ISIN | I13: עוקב אחר מדדי מניות בחו"ל | J13: חו"ל | K13: ארה"ב | L13: LSE | M13: Equity Funds | N13: לא | O13: USD | P13: 1415 | Q13: 3.71 | R13: 60718 | S13: 0 | T13: 3187.4825 | U13: 0 | V13: 0.20118694 | W13: 0.19477736
A14: 7891 | B14: 7896 | C14: Xtrackers S&P 500 Swap UCITS E | D14: 54930044TWZ26JPZ4913 | E14: LEI | F14: X S&P 500 SWAP | G14: LU0490618542 | H14: ISIN | I14: עוקב אחר מדדי מניות בחו"ל | J14: חו"ל | K14: ארה"ב | L14: LSE | M14: Equity Funds | N14: לא | O14: USD | P14: 7584 | Q14: 3.71 | R14: 11363 | S14: 0 | T14: 3197.1664 | U14: 0 | V14: 0.20179817 | W14: 0.19536912
A15: 7891 | B15: 7896 | C15: SPDR S&P 500 UCITC ETF | D15: 549300F1TODGOV4WQV40 | E15: LEI | F15: SPDR S&P 500 UCITS ETF ACC | G15: IE000XZSV718 | H15: ISIN | I15: עוקב אחר מדדי מניות בחו"ל | J15: חו"ל | K15: ארה"ב | L15: LSE | M15: Equity Funds | N15: לא | O15: USD | P15: 59300 | Q15: 3.71 | R15: 1392.6 | S15: 0 | T15: 3063.7618 | U15: 0 | V15: 0.19337796 | W15: 0.18721717
A16: 7891 | B16: 7897 | C16: קסם קרנות נאמנות בע"מ | D16: 510938608 | E16: ח.פ. | F16: קסם.תל ג-צמ 0-2 | G16: IL0011461337 | H16: ISIN | I16: עוקב אחר מדדים אחרים בישראל | J16: ישראל | K16: ישראל | L16: TASE | M16: אג"ח בארץ - מדינה-אג"ח מדינה צמוד מדד-צמודות מדד - ממשלתיות 0-2 שנים | N16: לא | O16: ILS | P16: 168180 | Q16: 1 | R16: 2555.88 | S16: 0 | T16: 4298.479 | U16: 0.015 | V16: 0.12409173 | W16: 0.047059786
A17: 7891 | B17: 7897 | C17: אי.בי.אי קרנות נאמנות בעמ | D17: 513765339 | E17: ח.פ. | F17: IBI.תלבונד 60 | G17: IL0011480063 | H17: ISIN | I17: עוקב אחר מדדים אחרים בישראל | J17: ישראל | K17: ישראל | L17: TASE | M17: אג"ח בארץ - חברות והמרה-תל בונד צמוד מדד-תל בונד צמודות | N17: לא | O17: ILS | P17: 1866800 | Q17: 1 | R17: 365.93 | S17: 0 | T17: 6831.1812 | U17: 0.001 | V17: 0.19720769 | W17: 0.074787833
A18: 7891 | B18: 7897 | C18: מגדל קרנות נאמנות בע"מ | D18: 511303661 | E18: ח.פ. | F18: MTF.תלבונד60 | G18: IL0011499964 | H18: ISIN | I18: עוקב אחר מדדים אחרים בישראל | J18: ישראל | K18: ישראל | L18: TASE | M18: אג"ח בארץ - חברות והמרה-תל בונד צמוד מדד-תל בונד צמודות | N18: לא | O18: ILS | P18: 1948507 | Q18: 1 | R18: 465.93 | S18: 0 | T18: 9078.6787 | U18: 0.013 | V18: 0.26209014 | W18: 0.099393455
A19: 7891 | B19: 7897 | C19: הראל קרנות נאמנות בע"מ | D19: 511776783 | E19: ח.פ. | F19: הרל.תלבונד 60 | G19: IL0011504730 | H19: ISIN | I19: עוקב אחר מדדים אחרים בישראל | J19: ישראל | K19: ישראל | L19: TASE | M19: אג"ח בארץ - חברות והמרה-תל בונד צמוד מדד-תל בונד צמודות | N19: לא | O19: ILS | P19: 2085400 | Q19: 1 | R19: 364.41 | S19: 0 | T19: 7599.4061 | U19: 0.007 | V19: 0.21938539 | W19: 0.083198366
A20: 7891 | B20: 7897 | C20: מור ניהול קרנות נאמנות | D20: 514884485 | E20: ח.פ. | F20: מו.סל תלבונד 60 | G20: IL0011953044 | H20: ISIN | I20: עוקב אחר מדדים אחרים בישראל | J20: ישראל | K20: ישראל | L20: TASE | M20: אג"ח בארץ - חברות והמרה-תל בונד צמוד מדד-תל בונד צמודות | N20: לא | O20: ILS | P20: 128090 | Q20: 1 | R20: 5333.58 | S20: 0 | T20: 6831.7826 | U20: 0.021 | V20: 0.19722505 | W20: 0.074794417
A21: 7891 | B21: 7900 | C21: מיטב קרנות נאמנות בע"מ | D21: 513534974 | E21: ח.פ. | F21: תכ.תא125 | G21: IL0011437188 | H21: ISIN | I21: עוקב אחר מדדי מניות בישראל | J21: ישראל | K21: ישראל | L21: TASE | M21: Large & Mid Cap מניות בארץ - מניות לפי שווי שוק-מניות | N21: לא | O21: ILS | P21: 15920 | Q21: 1 | R21: 2081 | S21: 0 | T21: 331.2952 | U21: 0 | V21: 0.041360981 | W21: 0.031527022
A22: 7891 | B22: 7900 | C22: מיטב קרנות נאמנות בע"מ | D22: 513534974 | E22: ח.פ. | F22: תכ.תלבונד60 | G22: IL0011451015 | H22: ISIN | I22: עוקב אחר מדדים אחרים בישראל | J22: ישראל | K22: ישראל | L22: TASE | M22: אג"ח בארץ - חברות והמרה-תל בונד צמוד מדד-תל בונד צמודות | N22: לא | O22: ILS | P22: 35244 | Q22: 1 | R22: 365.33 | S22: 0 | T22: 128.75691 | U22: 0 | V22: 0.016074824 | W22: 0.012252885
A23: 7891 | B23: 7900 | C23: מיטב קרנות נאמנות בע"מ | D23: 513534974 | E23: ח.פ. | F23: תכ.תלבונדשקלי | G23: IL0011451841 | H23: ISIN | I23: עוקב אחר מדדים אחרים בישראל | J23: ישראל | K23: ישראל | L23: TASE | M23: אג"ח בארץ - חברות והמרה-תל בונד שקלי-תל בונד- שקלי | N23: לא | O23: ILS | P23: 83680 | Q23: 1 | R23: 390.51 | S23: 0 | T23: 326.77877 | U23: 0 | V23: 0.040797121 | W23: 0.031097225
A24: 7891 | B24: 7900 | C24: קסם קרנות נאמנות בע"מ | D24: 510938608 | E24: ח.פ. | F24: קסם.תלבונד שקלי | G24: IL0011464141 | H24: ISIN | I24: עוקב אחר מדדים אחרים בישראל | J24: ישראל | K24: ישראל | L24: TASE | M24: אג"ח בארץ - חברות והמרה-תל בונד שקלי-תל בונד- שקלי | N24: לא | O24: ILS | P24: 11970 | Q24: 1 | R24: 3880.51 | S24: 0 | T24: 464.49705 | U24: 0 | V24: 0.057990739 | W24: 0.0442029
A25: 7891 | B25: 7900 | C25: קסם קרנות נאמנות בע"מ | D25: 510938608 | E25: ח.פ. | F25: SP500.קסם | G25: IL0011464711 | H25: ISIN | I25: עוקב אחר מדדי מניות בחו"ל | J25: ישראל | K25: ארה"ב | L25: TASE | M25: מניות בחו"ל - מניות גיאוגרפי - חשופת מט"ח-ארה"ב - מדד אחר | N25: לא | O25: ILS | P25: 2240 | Q25: 1 | R25: 23280 | S25: 0 | T25: 521.472 | U25: 0 | V25: 0.065103851 | W25: 0.049624803
A26: 7891 | B26: 7900 | C26: קסם קרנות נאמנות בע"מ | D26: 510938608 | E26: ח.פ. | F26: קסם.SP500ממ | G26: IL0011466047 | H26: ISIN | I26: עוקב אחר מדדי מניות בחו"ל | J26: ישראל | K26: ארה"ב | L26: TASE | M26: מניות בחו"ל - מניות גיאוגרפי - מנוטרלת מט"ח-ארה"ב - מדד אחר | N26: לא | O26: ILS | P26: 2965 | Q26: 1 | R26: 5505 | S26: 0 | T26: 163.22325 | U26: 0 | V26: 0.020377819 | W26: 0.015532803
A27: 7891 | B27: 7900 | C27: אי.בי.אי קרנות נאמנות בעמ | D27: 513765339 | E27: ח.פ. | F27: IBI.תלבונד 60 | G27: IL0011480063 | H27: ISIN | I27: עוקב אחר מדדים אחרים בישראל | J27: ישראל | K27: ישראל | L27: TASE | M27: אג"ח בארץ - חברות והמרה-תל בונד צמוד מדד-תל בונד צמודות | N27: לא | O27: ILS | P27: 176100 | Q27: 1 | R27: 365.93 | S27: 0 | T27: 644.40273 | U27: 0 | V27: 0.080451298 | W27: 0.061323252
A28: 7891 | B28: 7900 | C28: הראל קרנות נאמנות בע"מ | D28: 511776783 | E28: ח.פ. | F28: הרל.SP500 ממ | G28: IL0011491375 | H28: ISIN | I28: עוקב אחר מדדי מניות בחו"ל | J28: ישראל | K28: ארה"ב | L28: TASE | M28: מניות בחו"ל - מניות גיאוגרפי - מנוטרלת מט"ח-ארה"ב - מדד אחר | N28: לא | O28: ILS | P28: 7840 | Q28: 1 | R28: 5590 | S28: 0 | T28: 438.256 | U28: 0 | V28: 0.054714641 | W28: 0.041705725
A29: 7891 | B29: 7900 | C29: מגדל קרנות נאמנות בע"מ | D29: 511303661 | E29: ח.פ. | F29: MTF.תא125 | G29: IL0011502833 | H29: ISIN | I29: עוקב אחר מדדי מניות בישראל | J29: ישראל | K29: ישראל | L29: TASE | M29: Large & Mid Cap מניות בארץ - מניות לפי שווי שוק-מניות | N29: לא | O29: ILS | P29: 15810 | Q29: 1 | R29: 3265 | S29: 0 | T29: 516.1965 | U29: 0 | V29: 0.064445224 | W29: 0.049122771
A30: 7891 | B30: 7900 | C30: מגדל קרנות נאמנות בע"מ | D30: 511303661 | E30: ח.פ. | F30: SP500.MTFממ | G30: IL0011505729 | H30: ISIN | I30: עוקב אחר מדדי מניות בחו"ל | J30: ישראל | K30: ארה"ב | L30: TASE | M30: מניות בחו"ל - מניות גיאוגרפי - מנוטרלת מט"ח-ארה"ב - מדד אחר | N30: לא | O30: ILS | P30: 3130 | Q30: 1 | R30: 7341 | S30: 0 | T30: 229.7733 | U30: 0 | V30: 0.028686347 | W30: 0.0218659
A31: 7891 | B31: 7900 | C31: מגדל קרנות נאמנות בע"מ | D31: 511303661 | E31: ח.פ. | F31: STX600.MTFממ | G31: IL0011506149 | H31: ISIN | I31: עוקב אחר מדדי מניות בחו"ל | J31: ישראל | K31: ארה"ב | L31: TASE | M31: מניות בחו"ל - מניות גיאוגרפי - מנוטרלת מט"ח-אירופה - מדד אחר | N31: לא | O31: ILS | P31: 6020 | Q31: 1 | R31: 7671 | S31: 0 | T31: 461.7942 | U31: 0.001 | V31: 0.057653298 | W31: 0.043945689
A32: 7891 | B32: 7900 | C32: מור ניהול קרנות נאמנות | D32: 514884485 | E32: ח.פ. | F32: מו.SP500ממ | G32: IL0011658288 | H32: ISIN | I32: עוקב אחר מדדי מניות בחו"ל | J32: ישראל | K32: ארה"ב | L32: TASE | M32: מניות בחו"ל - מניות גיאוגרפי - מנוטרלת מט"ח-ארה"ב - מדד אחר | N32: לא | O32: ILS | P32: 3980 | Q32: 1 | R32: 9006 | S32: 0 | T32: 358.4388 | U32: 0 | V32: 0.044749759 | W32: 0.034110086
A33: 7891 | B33: 7900 | C33: מור ניהול קרנות נאמנות | D33: 514884485 | E33: ח.פ. | F33: מו.סל תא 125 | G33: IL0011961534 | H33: ISIN | I33: עוקב אחר מדדי מניות בישראל | J33: ישראל | K33: ישראל | L33: TASE | M33: Large & Mid Cap מניות בארץ - מניות לפי שווי שוק-מניות | N33: לא | O33: ILS | P33: 13280 | Q33: 1 | R33: 5753 | S33: 0 | T33: 763.9984 | U33: 0.002 | V33: 0.095382375 | W33: 0.072704326
A34: 7891 | B34: 7900 | C34: Invesco QQQ Trust Series 1 | D34: 549300VY6FEJBCIMET58 | E34: LEI | F34: INVESCO QQQ TRUST SERIES 1 | G34: US46090E1038 | H34: ISIN | I34: עוקב אחר מדדי מניות בחו"ל | J34: חו"ל | K34: ארה"ב | L34: NASDAQ | M34: Equity Funds | N34: לא | O34: USD | P34: 238 | Q34: 3.71 | R34: 48807 | S34: 0.12081941 | T34: 431.40429 | U34: 0 | V34: 0.053859231 | W34: 0.041053696
A35: 7891 | B35: 7900 | C35: iShares 0-5 Year High Yield Co | D35: 549300R96U5WQ7R5ID10 | E35: LEI | F35: ISHARES 0-5 YR HY CORP BOND | G35: US46434V4077 | H35: ISIN | I35: עוקב אחר מדדים אחרים בחו"ל | J35: חו"ל | K35: ארה"ב | L35: NYSE | M35: Bond/Fixed Income Funds | N35: לא | O35: USD | P35: 3380 | Q35: 3.71 | R35: 4342 | S35: 0 | T35: 544.47812 | U35: 0 | V35: 0.06797608 | W35: 0.051814133
A36: 7891 | B36: 7900 | C36: iShares U.S. Financial Service | D36: 549300O3BGVZIZJEZC19 | E36: LEI | F36: ISHARES U.S. FINANCIAL SERVI | G36: US4642877702 | H36: ISIN | I36: עוקב אחר מדדי מניות בחו"ל | J36: חו"ל | K36: ארה"ב | L36: NYSE | M36: Equity Funds | N36: לא | O36: USD | P36: 564 | Q36: 3.71 | R36: 7102 | S36: 0.13522911 | T36: 149.10679 | U36: 0 | V36: 0.018615431 | W36: 0.014189439
A37: 7891 | B37: 7900 | C37: Invesco | D37: ECPGFXU8A2SH | E37: LEI | F37: INVESCO S&P 500 ACC | G37: IE00B3YCGJ38 | H37: ISIN | I37: עוקב אחר מדדי מניות בחו"ל | J37: חו"ל | K37: ארה"ב | L37: LSE | M37: Equity Funds | N37: לא | O37: USD | P37: 189 | Q37: 3.71 | R37: 112716 | S37: 0 | T37: 790.35332 | U37: 0 | V37: 0.09867269 | W37: 0.075212338
A38: 7891 | B38: 7900 | C38: iShares Core S&P 500 UCITS ETF | D38: 5493006ESS9BM09FB892 | E38: LEI | F38: ISHARES CORE S&P 500 | G38: IE00B5BMR087 | H38: ISIN | I38: עוקב אחר מדדי מניות בחו"ל | J38: חו"ל | K38: ארה"ב | L38: LSE | M38: Equity Funds | N38: לא | O38: USD | P38: 331 | Q38: 3.71 | R38: 60718 | S38: 0 | T38: 745.62311 | U38: 0 | V38: 0.093088288 | W38: 0.07095568
A39: 11925 | B39: 11926 | C39: מיטב קרנות נאמנות בע"מ | D39: 513534974 | E39: ח.פ. | F39: תכ.תלבונד60 | G39: IL0011451015 | H39: ISIN | I39: עוקב אחר מדדים אחרים בישראל | J39: ישראל | K39: ישראל | L39: TASE | M39: אג"ח בארץ - חברות והמרה-תל בונד צמוד מדד-תל בונד צמודות | N39: לא | O39: ILS | P39: 82255 | Q39: 1 | R39: 365.33 | S39: 0 | T39: 300.50219 | U39: 0 | V39: 0.016970892 | W39: 0.012435838
A40: 11925 | B40: 11926 | C40: מיטב קרנות נאמנות בע"מ | D40: 513534974 | E40: ח.פ. | F40: תכ.תלבונדשקלי | G40: IL0011451841 | H40: ISIN | I40: עוקב אחר מדדים אחרים בישראל | J40: ישראל | K40: ישראל | L40: TASE | M40: אג"ח בארץ - חברות והמרה-תל בונד שקלי-תל בונד- שקלי | N40: לא | O40: ILS | P40: 321670 | Q40: 1 | R40: 390.51 | S40: 0 | T40: 1256.1535 | U40: 0 | V40: 0.0709414 | W40: 0.051984051
A41: 11925 | B41: 11926 | C41: קסם קרנות נאמנות בע"מ | D41: 510938608 | E41: ח.פ. | F41: קסם.תלבונד שקלי | G41: IL0011464141 | H41: ISIN | I41: עוקב אחר מדדים אחרים בישראל | J41: ישראל | K41: ישראל | L41: TASE | M41: אג"ח בארץ - חברות והמרה-תל בונד שקלי-תל בונד- שקלי | N41: לא | O41: ILS | P41: 30450 | Q41: 1 | R41: 3880.51 | S41: 0 | T41: 1181.6153 | U41: 0.001 | V41: 0.066731846 | W41: 0.048899397
A42: 11925 | B42: 11926 | C42: קסם קרנות נאמנות בע"מ | D42: 510938608 | E42: ח.פ. | F42: SP500.קסם | G42: IL0011464711 | H42: ISIN | I42: עוקב אחר מדדי מניות בחו"ל | J42: ישראל | K42: ארה"ב | L42: TASE | M42: מניות בחו"ל - מניות גיאוגרפי - חשופת מט"ח-ארה"ב - מדד אחר | N42: לא | O42: ILS | P42: 2651 | Q42: 1 | R42: 23280 | S42: 0 | T42: 617.1528 | U42: 0 | V42: 0.034853768 | W42: 0.025539954
A43: 11925 | B43: 11926 | C43: קסם קרנות נאמנות בע"מ | D43: 510938608 | E43: ח.פ. | F43: קסם.SP500ממ | G43: IL0011466047 | H43: ISIN | I43: עוקב אחר מדדי מניות בחו"ל | J43: ישראל | K43: ארה"ב | L43: TASE | M43: מניות בחו"ל - מניות גיאוגרפי - מנוטרלת מט"ח-ארה"ב - מדד אחר | N43: לא | O43: ILS | P43: 7817 | Q43: 1 | R43: 5505 | S43: 0 | T43: 430.32585 | U43: 0 | V43: 0.024302697 | W43: 0.017808397
A44: 11925 | B44: 11926 | C44: אי.בי.אי קרנות נאמנות בעמ | D44: 513765339 | E44: ח.פ. | F44: IBI.תא 125 | G44: IL0011488082 | H44: ISIN | I44: עוקב אחר מדדי מניות בישראל | J44: ישראל | K44: ישראל | L44: TASE | M44: Large & Mid Cap מניות בארץ - מניות לפי שווי שוק-מניות | N44: לא | O44: ILS | P44: 17800 | Q44: 1 | R44: 2073 | S44: 0 | T44: 368.994 | U44: 0 | V44: 0.020838974 | W44: 0.01527027
A45: 11925 | B45: 11926 | C45: הראל קרנות נאמנות בע"מ | D45: 511776783 | E45: ח.פ. | F45: הרל.SP500 ממ | G45: IL0011491375 | H45: ISIN | I45: עוקב אחר מדדי מניות בחו"ל | J45: ישראל | K45: ארה"ב | L45: TASE | M45: מניות בחו"ל - מניות גיאוגרפי - מנוטרלת מט"ח-ארה"ב - מדד אחר | N45: לא | O45: ILS | P45: 26840 | Q45: 1 | R45: 5590 | S45: 0 | T45: 1500.356 | U45: 0 | V45: 0.084732761 | W45: 0.062090008
... A49: 11925 | B49: 11926 | C49: מגדל קרנות נאמנות בע"מ | D49: 511303661 | E49: ח.פ. | F49: STX600.MTFממ | G49: IL0011506149 | H49: ISIN | I49: עוקב אחר מדדי מניות בחו"ל | J49: ישראל | K49: ארה"ב | L49: TASE | M49: מניות בחו"ל - מניות גיאוגרפי - מנוטרלת מט"ח-אירופה - מדד אחר | N49: לא | O49: ILS | P49: 5763 | Q49: 1 | R49: 7671 | S49: 0 | T49: 442.07973 | U49: 0.001 | V49: 0.024966499 | W49: 0.018294814
A50: 11925 | B50: 11926 | C50: מור ניהול קרנות נאמנות | D50: 514884485 | E50: ח.פ. | F50: מו.סל תא 125 | G50: IL0011961534 | H50: ISIN | I50: עוקב אחר מדדי מניות בישראל | J50: ישראל | K50: ישראל | L50: TASE | M50: Large & Mid Cap מניות בארץ - מניות לפי שווי שוק-מניות | N50: לא | O50: ILS | P50: 32128 | Q50: 1 | R50: 5753 | S50: 0 | T50: 1848.3238 | U50: 0.005 | V50: 0.10438428 | W50: 0.076490142
A51: 11925 | B51: 11926 | C51: Invesco QQQ Trust Series 1 | D51: 549300VY6FEJBCIMET58 | E51: LEI | F51: INVESCO QQQ TRUST SERIES 1 | G51: US46090E1038 | H51: ISIN | I51: עוקב אחר מדדי מניות בחו"ל | J51: חו"ל | K51: ארה"ב | L51: NASDAQ | M51: Equity Funds | N51: לא | O51: USD | P51: 204 | Q51: 3.71 | R51: 48807 | S51: 0.10356065 | T51: 369.77511 | U51: 0 | V51: 0.020883088 | W51: 0.015302595
A52: 11925 | B52: 11926 | C52: iShares 0-5 Year High Yield Co | D52: 549300R96U5WQ7R5ID10 | E52: LEI | F52: ISHARES 0-5 YR HY CORP BOND | G52: US46434V4077 | H52: ISIN | I52: עוקב אחר מדדים אחרים בחו"ל | J52: חו"ל | K52: ארה"ב | L52: NYSE | M52: Bond/Fixed Income Funds | N52: לא | O52: USD | P52: 7256 | Q52: 3.71 | R52: 4342 | S52: 0 | T52: 1168.856 | U52: 0 | V52: 0.066011263 | W52: 0.048371372
A53: 11925 | B53: 11926 | C53: iShares U.S. Financial Service | D53: 549300O3BGVZIZJEZC19 | E53: LEI | F53: ISHARES U.S. FINANCIAL SERVI | G53: US4642877702 | H53: ISIN | I53: עוקב אחר מדדי מניות בחו"ל | J53: חו"ל | K53: ארה"ב | L53: NYSE | M53: Equity Funds | N53: לא | O53: USD | P53: 1723 | Q53: 3.71 | R53: 7102 | S53: 0.41311051 | T53: 455.51592 | U53: 0 | V53: 0.025725309 | W53: 0.018850851
A54: 11925 | B54: 11926 | C54: Invesco | D54: ECPGFXU8A2SH | E54: LEI | F54: INVESCO S&P 500 ACC | G54: IE00B3YCGJ38 | H54: ISIN | I54: עוקב אחר מדדי מניות בחו"ל | J54: חו"ל | K54: ארה"ב | L54: LSE | M54: Equity Funds | N54: לא | O54: USD | P54: 493 | Q54: 3.71 | R54: 112716 | S54: 0 | T54: 2061.6094 | U54: 0 | V54: 0.11642961 | W54: 0.08531665
A55: 11925 | B55: 11926 | C55: iShares Core S&P 500 UCITS ETF | D55: 5493006ESS9BM09FB892 | E55: LEI | F55: ISHARES CORE S&P 500 | G55: IE00B5BMR087 | H55: ISIN | I55: עוקב אחר מדדי מניות בחו"ל | J55: חו"ל | K55: ארה"ב | L55: LSE | M55: Equity Funds | N55: לא | O55: USD | P55: 219 | Q55: 3.71 | R55: 60718 | S55: 0 | T55: 493.32768 | U55: 0 | V55: 0.027860732 | W55: 0.020415635
A56: 11925 | B56: 11926 | C56: BNP Paribas Easy S&P 500 UCITS | D56: 969500M16QGQY5B5T207 | E56: LEI | F56: BNP P S&P 500 UCITS ETF | G56: FR0011550177 | H56: ISIN | I56: עוקב אחר מדדי מניות בחו"ל | J56: חו"ל | K56: ארה"ב | L56: NASDAQ | M56: Equity Funds | N56: לא | O56: USD | P56: 24852 | Q56: 3.71 | R56: 2292.3 | S56: 0 | T56: 2113.5217 | U56: 0 | V56: 0.11936136 | W56: 0.087464961
A57: 11925 | B57: 11928 | C57: קסם קרנות נאמנות בע"מ | D57: 510938608 | E57: ח.פ. | F57: קסם.תל ג-צמ 0-2 | G57: IL0011461337 | H57: ISIN | I57: עוקב אחר מדדים אחרים בישראל | J57: ישראל | K57: ישראל | L57: TASE | M57: אג"ח בארץ - מדינה-אג"ח מדינה צמוד מדד-צמודות מדד - ממשלתיות 0-2 שנים | N57: לא | O57: ILS | P57: 235300 | Q57: 1 | R57: 2555.88 | S57: 0 | T57: 6013.9856 | U57: 0.021 | V57: 0.12264174 | W57: 0.046469726
A58: 11925 | B58: 11928 | C58: אי.בי.אי קרנות נאמנות בעמ | D58: 513765339 | E58: ח.פ. | F58: IBI.תלבונד 60 | G58: IL0011480063 | H58: ISIN | I58: עוקב אחר מדדים אחרים בישראל | J58: ישראל | K58: ישראל | L58: TASE | M58: אג"ח בארץ - חברות והמרה-תל בונד צמוד מדד-תל בונד צמודות | N58: לא | O58: ILS | P58: 2639550 | Q58: 1 | R58: 365.93 | S58: 0 | T58: 9658.9053 | U58: 0.002 | V58: 0.1969717 | W58: 0.074633814
A59: 11925 | B59: 11928 | C59: מגדל קרנות נאמנות בע"מ | D59: 511303661 | E59: ח.פ. | F59: MTF.תלבונד60 | G59: IL0011499964 | H59: ISIN | I59: עוקב אחר מדדים אחרים בישראל | J59: ישראל | K59: ישראל | L59: TASE | M59: אג"ח בארץ - חברות והמרה-תל בונד צמוד מדד-תל בונד צמודות | N59: לא | O59: ILS | P59: 2066400 | Q59: 1 | R59: 465.93 | S59: 0 | T59: 9627.9775 | U59: 0.014 | V59: 0.19634099 | W59: 0.074394837
A60: 11925 | B60: 11928 | C60: הראל קרנות נאמנות בע"מ | D60: 511776783 | E60: ח.פ. | F60: הרל.תלבונד 60 | G60: IL0011504730 | H60: ISIN | I60: עוקב אחר מדדים אחרים בישראל | J60: ישראל | K60: ישראל | L60: TASE | M60: אג"ח בארץ - חברות והמרה-תל בונד צמוד מדד-תל בונד צמודות | N60: לא | O60: ILS | P60: 3869700 | Q60: 1 | R60: 364.41 | S60: 0 | T60: 14101.574 | U60: 0.013 | V60: 0.28756995 | W60: 0.10896206
A61: 11925 | B61: 11928 | C61: מור ניהול קרנות נאמנות | D61: 514884485 | E61: ח.פ. | F61: מו.סל תלבונד 60 | G61: IL0011953044 | H61: ISIN | I61: עוקב אחר מדדים אחרים בישראל | J61: ישראל | K61: ישראל | L61: TASE | M61: אג"ח בארץ - חברות והמרה-תל בונד צמוד מדד-תל בונד צמודות | N61: לא | O61: ILS | P61: 180640 | Q61: 1 | R61: 5333.58 | S61: 0 | T61: 9634.5789 | U61: 0.03 | V61: 0.19647562 | W61: 0.074445846
A62: 11925 | B62: 11934 | C62: Amundi S&P 500 UCITS ETF | D62: 2138007NOUJ46G9POA93 | E62: LEI | F62: AMUNDI S&P 500 UCITS ETF | G62: LU1681048804 | H62: ISIN | I62: עוקב אחר מדדי מניות בחו"ל | J62: חו"ל | K62: ארה"ב | L62: NASDAQ | M62: Equity Funds | N62: לא | O62: EUR | P62: 14477 | Q62: 4.1524 | R62: 10076.66 | S62: 0 | T62: 6057.5131 | U62: 0 | V62: 0.20234258 | W62: 0.19827235
A63: 11925 | B63: 11934 | C63: Invesco | D63: ECPGFXU8A2SH | E63: LEI | F63: INVESCO S&P 500 ACC | G63: IE00B3YCGJ38 | H63: ISIN | I63: עוקב אחר מדדי מניות בחו"ל | J63: חו"ל | K63: ארה"ב | L63: LSE | M63: Equity Funds | N63: לא | O63: USD | P63: 1444 | Q63: 3.71 | R63: 112716 | S63: 0 | T63: 6038.4666 | U63: 0 | V63: 0.20170636 | W63: 0.19764893
A64: 11925 | B64: 11934 | C64: iShares Core S&P 500 UCITS ETF | D64: 5493006ESS9BM09FB892 | E64: LEI | F64: ISHARES CORE S&P 500 | G64: IE00B5BMR087 | H64: ISIN | I64: עוקב אחר מדדי מניות בחו"ל | J64: חו"ל | K64: ארה"ב | L64: LSE | M64: Equity Funds | N64: לא | O64: USD | P64: 2667 | Q64: 3.71 | R64: 60718 | S64: 0 | T64: 6007.785 | U64: 0 | V64: 0.20068149 | W64: 0.19664467
A65: 11925 | B65: 11934 | C65: Xtrackers S&P 500 Swap UCITS E | D65: 54930044TWZ26JPZ4913 | E65: LEI | F65: X S&P 500 SWAP | G65: LU0490618542 | H65: ISIN | I65: עוקב אחר מדדי מניות בחו"ל | J65: חו"ל | K65: ארה"ב | L65: LSE | M65: Equity Funds | N65: לא | O65: USD | P65: 14334 | Q65: 3.71 | R65: 11363 | S65: 0 | T65: 6042.7457 | U65: 0 | V65: 0.2018493 | W65: 0.19778899
A66: 11925 | B66: 11934 | C66: SPDR S&P 500 UCITC ETF | D66: 549300F1TODGOV4WQV40 | E66: LEI | F66: SPDR S&P 500 UCITS ETF ACC | G66: IE000XZSV718 | H66: ISIN | I66: עוקב אחר מדדי מניות בחו"ל | J66: חו"ל | K66: ארה"ב | L66: LSE | M66: Equity Funds | N66: לא | O66: USD | P66: 112075 | Q66: 3.71 | R66: 1392.6 | S66: 0 | T66: 5790.4064 | U66: 0 | V66: 0.19342027 | W66: 0.18952951
A67: 11939 | B67: 11942 | C67: מיטב קרנות נאמנות בע"מ | D67: 513534974 | E67: ח.פ. | F67: תכ.תלבונד60 | G67: IL0011451015 | H67: ISIN | I67: עוקב אחר מדדים אחרים בישראל | J67: ישראל | K67: ישראל | L67: TASE | M67: אג"ח בארץ - חברות והמרה-תל בונד צמוד מדד-תל בונד צמודות | N67: לא | O67: ILS | P67: 5815535 | Q67: 1 | R67: 365.33 | S67: 0 | T67: 21245.894 | U67: 0.004 | V67: 0.23460056 | W67: 0.076511487
A68: 11939 | B68: 11942 | C68: קסם קרנות נאמנות בע"מ | D68: 510938608 | E68: ח.פ. | F68: קסם.תל ג-צמ 0-2 | G68: IL0011461337 | H68: ISIN | I68: עוקב אחר מדדים אחרים בישראל | J68: ישראל | K68: ישראל | L68: TASE | M68: אג"ח בארץ - מדינה-אג"ח מדינה צמוד מדד-צמודות מדד - ממשלתיות 0-2 שנים | N68: לא | O68: ILS | P68: 409743 | Q68: 1 | R68: 2555.88 | S68: 0 | T68: 10472.539 | U68: 0.036 | V68: 0.11563946 | W68: 0.03771409
A69: 11939 | B69: 11942 | C69: אי.בי.אי קרנות נאמנות בעמ | D69: 513765339 | E69: ח.פ. | F69: IBI.תלבונד 60 | G69: IL0011480063 | H69: ISIN | I69: עוקב אחר מדדים אחרים בישראל | J69: ישראל | K69: ישראל | L69: TASE | M69: אג"ח בארץ - חברות והמרה-תל בונד צמוד מדד-תל בונד צמודות | N69: לא | O69: ILS | P69: 5812850 | Q69: 1 | R69: 365.93 | S69: 0 | T69: 21270.962 | U69: 0.004 | V69: 0.23487737 | W69: 0.076601763
A70: 11939 | B70: 11942 | C70: מגדל קרנות נאמנות בע"מ | D70: 511303661 | E70: ח.פ. | F70: MTF.תלבונד60 | G70: IL0011499964 | H70: ISIN | I70: עוקב אחר מדדים אחרים בישראל | J70: ישראל | K70: ישראל | L70: TASE | M70: אג"ח בארץ - חברות והמרה-תל בונד צמוד מדד-תל בונד צמודות | N70: לא | O70: ILS | P70: 4567250 | Q70: 1 | R70: 465.93 | S70: 0 | T70: 21280.188 | U70: 0.032 | V70: 0.23497924 | W70: 0.076634988
A71: 11939 | B71: 11942 | C71: הראל קרנות נאמנות בע"מ | D71: 511776783 | E71: ח.פ. | F71: הרל.תלבונד 60 | G71: IL0011504730 | H71: ISIN | I71: עוקב אחר מדדים אחרים בישראל | J71: ישראל | K71: ישראל | L71: TASE | M71: אג"ח בארץ - חברות והמרה-תל בונד צמוד מדד-תל בונד צמודות | N71: לא | O71: ILS | P71: 4470900 | Q71: 1 | R71: 364.41 | S71: 0 | T71: 16292.407 | U71: 0.014 | V71: 0.17990336 | W71: 0.058672808
A72: 11939 | B72: 11943 | C72: מיטב קרנות נאמנות בע"מ | D72: 513534974 | E72: ח.פ. | F72: תכ.תא125 | G72: IL0011437188 | H72: ISIN | I72: עוקב אחר מדדי מניות בישראל | J72: ישראל | K72: ישראל | L72: TASE | M72: Large & Mid Cap מניות בארץ - מניות לפי שווי שוק-מניות | N72: לא | O72: ILS | P72: 17840 | Q72: 1 | R72: 2081 | S72: 0 | T72: 371.2504 | U72: 0 | V72: 0.071165853 | W72: 0.064310251
A73: 11939 | B73: 11943 | C73: מיטב קרנות נאמנות בע"מ | D73: 513534974 | E73: ח.פ. | F73: תכ.NDX100ממ | G73: IL0011437345 | H73: ISIN | I73: עוקב אחר מדדי מניות בחו"ל | J73: ישראל | K73: ארה"ב | L73: TASE | M73: מניות בחו"ל - מניות גיאוגרפי - מנוטרלת מט"ח-ארה"ב - מדד אחר | N73: לא | O73: ILS | P73: 1965 | Q73: 1 | R73: 16380 | S73: 0 | T73: 321.867 | U73: 0 | V73: 0.061699434 | W73: 0.055755758
... A80: 11939 | B80: 11943 | C80: מגדל קרנות נאמנות בע"מ | D80: 511303661 | E80: ח.פ. | F80: SP500.MTFממ | G80: IL0011505729 | H80: ISIN | I80: עוקב אחר מדדי מניות בחו"ל | J80: ישראל | K80: ארה"ב | L80: TASE | M80: מניות בחו"ל - מניות גיאוגרפי - מנוטרלת מט"ח-ארה"ב - מדד אחר | N80: לא | O80: ILS | P80: 5790 | Q80: 1 | R80: 7341 | S80: 0 | T80: 425.0439 | U80: 0 | V80: 0.081477655 | W80: 0.073628688
A81: 11939 | B81: 11943 | C81: מור ניהול קרנות נאמנות | D81: 514884485 | E81: ח.פ. | F81: מו.SP500ממ | G81: IL0011658288 | H81: ISIN | I81: עוקב אחר מדדי מניות בחו"ל | J81: ישראל | K81: ארה"ב | L81: TASE | M81: מניות בחו"ל - מניות גיאוגרפי - מנוטרלת מט"ח-ארה"ב - מדד אחר | N81: לא | O81: ILS | P81: 1225 | Q81: 1 | R81: 9006 | S81: 0 | T81: 110.3235 | U81: 0 | V81: 0.021148169 | W81: 0.019110907
A82: 11939 | B82: 11943 | C82: מור ניהול קרנות נאמנות | D82: 514884485 | E82: ח.פ. | F82: מו.סל תא 125 | G82: IL0011961534 | H82: ISIN | I82: עוקב אחר מדדי מניות בישראל | J82: ישראל | K82: ישראל | L82: TASE | M82: Large & Mid Cap מניות בארץ - מניות לפי שווי שוק-מניות | N82: לא | O82: ILS | P82: 8816 | Q82: 1 | R82: 5753 | S82: 0 | T82: 507.18448 | U82: 0.001 | V82: 0.097223374 | W82: 0.087857579
A83: 11939 | B83: 11943 | C83: Invesco QQQ Trust Series 1 | D83: 549300VY6FEJBCIMET58 | E83: LEI | F83: INVESCO QQQ TRUST SERIES 1 | G83: US46090E1038 | H83: ISIN | I83: עוקב אחר מדדי מניות בחו"ל | J83: חו"ל | K83: ארה"ב | L83: NASDAQ | M83: Equity Funds | N83: לא | O83: USD | P83: 50 | Q83: 3.71 | R83: 48807 | S83: 0.029439353 | T83: 90.6462 | U83: 0 | V83: 0.017376181 | W83: 0.015702286
A84: 11939 | B84: 11943 | C84: iShares Core S&P 500 ETF | D84: 5493007M4YMN8XL48C14 | E84: LEI | F84: ISHARES S&P 500 INDEX FUND | G84: US4642872000 | H84: ISIN | I84: עוקב אחר מדדי מניות בחו"ל | J84: חו"ל | K84: ארה"ב | L84: NYSE | M84: Equity Funds | N84: לא | O84: USD | P84: 40 | Q84: 3.71 | R84: 57682 | S84: 0 | T84: 85.60009 | U84: 0 | V84: 0.016408881 | W84: 0.014828168
A85: 11939 | B85: 11943 | C85: Invesco | D85: ECPGFXU8A2SH | E85: LEI | F85: INVESCO S&P 500 ACC | G85: IE00B3YCGJ38 | H85: ISIN | I85: עוקב אחר מדדי מניות בחו"ל | J85: חו"ל | K85: ארה"ב | L85: LSE | M85: Equity Funds | N85: לא | O85: USD | P85: 121 | Q85: 3.71 | R85: 112716 | S85: 0 | T85: 505.9934 | U85: 0 | V85: 0.096995053 | W85: 0.087651253
A86: 11939 | B86: 11943 | C86: iShares Core S&P 500 UCITS ETF | D86: 5493006ESS9BM09FB892 | E86: LEI | F86: ISHARES CORE S&P 500 | G86: IE00B5BMR087 | H86: ISIN | I86: עוקב אחר מדדי מניות בחו"ל | J86: חו"ל | K86: ארה"ב | L86: LSE | M86: Equity Funds | N86: לא | O86: USD | P86: 203 | Q86: 3.71 | R86: 60718 | S86: 0 | T86: 457.28547 | U86: 0 | V86: 0.087658116 | W86: 0.079213769
A87: 11939 | B87: 11943 | C87: BNP Paribas Easy S&P 500 UCITS | D87: 969500M16QGQY5B5T207 | E87: LEI | F87: BNP P S&P 500 UCITS ETF | G87: FR0011550177 | H87: ISIN | I87: עוקב אחר מדדי מניות בחו"ל | J87: חו"ל | K87: ארה"ב | L87: NASDAQ | M87: Equity Funds | N87: לא | O87: USD | P87: 5444 | Q87: 3.71 | R87: 2292.3 | S87: 0 | T87: 462.98133 | U87: 0 | V87: 0.088749969 | W87: 0.08020044
A88: 11939 | B88: 11944 | C88: Franklin U.S. Low Volatility H | D88: 549300PKK8HNPP2M1496 | E88: LEI | F88: LEGG MASON LO VOL HI DIV ETF | G88: US52468L4068 | H88: ISIN | I88: עוקב אחר מדדי מניות בחו"ל | J88: חו"ל | K88: ארה"ב | L88: NASDAQ | M88: Equity Funds | N88: לא | O88: USD | P88: 9726 | Q88: 3.71 | R88: 4072 | S88: 0 | T88: 1469.3185 | U88: 0.001 | V88: 0.07491322 | W88: 0.063317439
A89: 11939 | B89: 11944 | C89: Invesco S&P 500 Low Volatility | D89: 549300FATA6ZCF8G1744 | E89: LEI | F89: INVESCO S&P 500 LOW VOLATIL | G89: US46138E3541 | H89: ISIN | I89: עוקב אחר מדדי מניות בחו"ל | J89: חו"ל | K89: ארה"ב | L89: NYSE | M89: Equity Funds | N89: לא | O89: USD | P89: 4721 | Q89: 3.71 | R89: 7173 | S89: 0 | T89: 1256.3445 | U89: 0 | V89: 0.064054739 | W89: 0.054139737
A90: 11939 | B90: 11944 | C90: SPDR Bloomberg Short Term High | D90: 549300YI2V5ELVW58659 | E90: LEI | F90: SPDR BLOOMBERG SHORT TERM HIGH | G90: US78468R4083 | H90: ISIN | I90: עוקב אחר מדדים אחרים בחו"ל | J90: חו"ל | K90: ארה"ב | L90: NYSE | M90: Bond/Fixed Income Funds | N90: לא | O90: USD | P90: 12248 | Q90: 3.71 | R90: 2575 | S90: 0 | T90: 1170.0821 | U90: 0 | V90: 0.059656648 | W90: 0.050422424
A91: 11939 | B91: 11944 | C91: Xtrackers MSCI Pacific ex Japa | D91: 549300IMXTZVDI0YUS81 | E91: LEI | F91: DB X-TRACKERS MSCI PAC X-JPN | G91: LU0322252338 | H91: ISIN | I91: עוקב אחר מדדי מניות בחו"ל | J91: חו"ל | K91: אסיה | L91: LSE | M91: Equity Funds | N91: לא | O91: USD | P91: 1076 | Q91: 3.71 | R91: 8062 | S91: 0 | T91: 321.83182 | U91: 0 | V91: 0.016408599 | W91: 0.01386872
A92: 11939 | B92: 11944 | C92: SPDR Portfolio High Yield Bond | D92: 549300B3SM8J1H4W2052 | E92: LEI | F92: SPDR BofA ML Crossover Corp Bo | G92: US78468R6062 | H92: ISIN | I92: עוקב אחר מדדים אחרים בחו"ל | J92: חו"ל | K92: ארה"ב | L92: NYSE | M92: Bond/Fixed Income Funds | N92: לא | O92: USD | P92: 13476 | Q92: 3.71 | R92: 2405 | S92: 0 | T92: 1202.4028 | U92: 0 | V92: 0.061304523 | W92: 0.051815225
A93: 11939 | B93: 11944 | C93: iShares JP Morgan USD EM Corp | D93: 549300357UC6D7NUY405 | E93: LEI | F93: ISHARES JPM USD EM CORP BND | G93: IE00B6TLBW47 | H93: ISIN | I93: עוקב אחר מדדים אחרים בחו"ל | J93: חו"ל | K93: ארה"ב | L93: LSE | M93: Bond/Fixed Income Funds | N93: לא | O93: USD | P93: 4116 | Q93: 3.71 | R93: 9208 | S93: 0 | T93: 1406.0947 | U93: 0 | V93: 0.071689757 | W93: 0.060592934
A94: 11939 | B94: 11944 | C94: Amundi USD Floating Rate Corpo | D94: 549300W6M26WPJCWRV83 | E94: LEI | F94: AMUNDI ETF FLOAT RATE USD CP | G94: LU1681040900 | H94: ISIN | I94: עוקב אחר מדדים אחרים בחו"ל | J94: חו"ל | K94: ארה"ב | L94: NASDAQ | M94: Bond/Fixed Income Funds | N94: לא | O94: USD | P94: 282 | Q94: 3.71 | R94: 12636.22 | S94: 0 | T94: 132.20266 | U94: 0 | V94: 0.0067403542 | W94: 0.005697018
... A123: 11939 | B123: 11979 | C123: מגדל קרנות נאמנות בע"מ | D123: 511303661 | E123: ח.פ. | F123: SP500.MTFממ | G123: IL0011505729 | H123: ISIN | I123: עוקב אחר מדדי מניות בחו"ל | J123: ישראל | K123: ארה"ב | L123: TASE | M123: מניות בחו"ל - מניות גיאוגרפי - מנוטרלת מט"ח-ארה"ב - מדד אחר | N123: לא | O123: ILS | P123: 9885 | Q123: 1 | R123: 7341 | S123: 0 | T123: 725.65785 | U123: 0 | V123: 0.031702774 | W123: 0.022445133
A124: 11939 | B124: 11979 | C124: מור ניהול קרנות נאמנות | D124: 514884485 | E124: ח.פ. | F124: מו.SP500ממ | G124: IL0011658288 | H124: ISIN | I124: עוקב אחר מדדי מניות בחו"ל | J124: ישראל | K124: ארה"ב | L124: TASE | M124: מניות בחו"ל - מניות גיאוגרפי - מנוטרלת מט"ח-ארה"ב - מדד אחר | N124: לא | O124: ILS | P124: 19200 | Q124: 1 | R124: 9006 | S124: 0 | T124: 1729.152 | U124: 0.001 | V124: 0.075543749 | W124: 0.053483948
A125: 11939 | B125: 11979 | C125: מור ניהול קרנות נאמנות | D125: 514884485 | E125: ח.פ. | F125: מו.NDX100ממ | G125: IL0011658445 | H125: ISIN | I125: עוקב אחר מדדי מניות בחו"ל | J125: ישראל | K125: ארה"ב | L125: TASE | M125: מניות בחו"ל - מניות גיאוגרפי - מנוטרלת מט"ח-ארה"ב - מדד אחר | N125: לא | O125: ILS | P125: 3000 | Q125: 1 | R125: 9469 | S125: 0 | T125: 284.07 | U125: 0 | V125: 0.012410542 | W125: 0.0087864948
A126: 11939 | B126: 11979 | C126: מור ניהול קרנות נאמנות | D126: 514884485 | E126: ח.פ. | F126: מו.סל תא 125 | G126: IL0011961534 | H126: ISIN | I126: עוקב אחר מדדי מניות בישראל | J126: ישראל | K126: ישראל | L126: TASE | M126: Large & Mid Cap מניות בארץ - מניות לפי שווי שוק-מניות | N126: לא | O126: ILS | P126: 22380 | Q126: 1 | R126: 5753 | S126: 0 | T126: 1287.5214 | U126: 0.004 | V126: 0.05624965 | W126: 0.039823987
A127: 11939 | B127: 11979 | C127: Invesco QQQ Trust Series 1 | D127: 549300VY6FEJBCIMET58 | E127: LEI | F127: INVESCO QQQ TRUST SERIES 1 | G127: US46090E1038 | H127: ISIN | I127: עוקב אחר מדדי מניות בחו"ל | J127: חו"ל | K127: ארה"ב | L127: NASDAQ | M127: Equity Funds | N127: לא | O127: USD | P127: 124 | Q127: 3.71 | R127: 48807 | S127: 0.10407008 | T127: 224.91782 | U127: 0 | V127: 0.0098262821 | W127: 0.0069568742
A128: 11939 | B128: 11979 | C128: iShares 0-5 Year High Yield Co | D128: 549300R96U5WQ7R5ID10 | E128: LEI | F128: ISHARES 0-5 YR HY CORP BOND | G128: US46434V4077 | H128: ISIN | I128: עוקב אחר מדדים אחרים בחו"ל | J128: חו"ל | K128: ארה"ב | L128: NYSE | M128: Bond/Fixed Income Funds | N128: לא | O128: USD | P128: 4802 | Q128: 3.71 | R128: 4342 | S128: 0 | T128: 773.54554 | U128: 0 | V128: 0.033794907 | W128: 0.023926335
A129: 11939 | B129: 11979 | C129: Invesco | D129: ECPGFXU8A2SH | E129: LEI | F129: INVESCO S&P 500 ACC | G129: IE00B3YCGJ38 | H129: ISIN | I129: עוקב אחר מדדי מניות בחו"ל | J129: חו"ל | K129: ארה"ב | L129: LSE | M129: Equity Funds | N129: לא | O129: USD | P129: 559 | Q129: 3.71 | R129: 112716 | S129: 0 | T129: 2337.6058 | U129: 0 | V129: 0.10212608 | W129: 0.072303874
A130: 11939 | B130: 11979 | C130: SPDR Portfolio High Yield Bond | D130: 549300B3SM8J1H4W2052 | E130: LEI | F130: SPDR BofA ML Crossover Corp Bo | G130: US78468R6062 | H130: ISIN | I130: עוקב אחר מדדים אחרים בחו"ל | J130: חו"ל | K130: ארה"ב | L130: NYSE | M130: Bond/Fixed Income Funds | N130: לא | O130: USD | P130: 15663 | Q130: 3.71 | R130: 2405 | S130: 0 | T130: 1397.539 | U130: 0 | V130: 0.061056134 | W130: 0.043226913
A131: 11939 | B131: 11979 | C131: Invesco S&P 500 Downside Hedge | D131: 0 | E131: LEI | F131: INVESCO S&P 500 DOWNSIDE HED | G131: US46090A7054 | H131: ISIN | I131: עוקב אחר מדדי מניות בחו"ל | J131: חו"ל | K131: ארה"ב | L131: NYSE | M131: Equity Funds | N131: לא | O131: USD | P131: 4256 | Q131: 3.71 | R131: 3821 | S131: 0 | T131: 603.32673 | U131: 0.001 | V131: 0.026358332 | W131: 0.018661341
A132: 11939 | B132: 11979 | C132: iShares Core S&P 500 UCITS ETF | D132: 5493006ESS9BM09FB892 | E132: LEI | F132: ISHARES CORE S&P 500 | G132: IE00B5BMR087 | H132: ISIN | I132: עוקב אחר מדדי מניות בחו"ל | J132: חו"ל | K132: ארה"ב | L132: LSE | M132: Equity Funds | N132: לא | O132: USD | P132: 1036 | Q132: 3.71 | R132: 60718 | S132: 0 | T132: 2333.7328 | U132: 0 | V132: 0.10195687 | W132: 0.072184077
A133: 11939 | B133: 11980 | C133: מיטב קרנות נאמנות בע"מ | D133: 513534974 | E133: ח.פ. | F133: תכ.תלבונד60 | G133: IL0011451015 | H133: ISIN | I133: עוקב אחר מדדים אחרים בישראל | J133: ישראל | K133: ישראל | L133: TASE | M133: אג"ח בארץ - חברות והמרה-תל בונד צמוד מדד-תל בונד צמודות | N133: לא | O133: ILS | P133: 69810 | Q133: 1 | R133: 365.33 | S133: 0 | T133: 255.03687 | U133: 0 | V133: 0.076224664 | W133: 0.050693173
A134: 11939 | B134: 11980 | C134: קסם קרנות נאמנות בע"מ | D134: 510938608 | E134: ח.פ. | F134: קסם.תלבונד 60 | G134: IL0011462327 | H134: ISIN | I134: עוקב אחר מדדים אחרים בישראל | J134: ישראל | K134: ישראל | L134: TASE | M134: אג"ח בארץ - חברות והמרה-תל בונד צמוד מדד-תל בונד צמודות | N134: לא | O134: ILS | P134: 5708 | Q134: 1 | R134: 3637.39 | S134: 0 | T134: 207.62222 | U134: 0 | V134: 0.062053514 | W134: 0.041268657
A135: 11939 | B135: 11980 | C135: אי.בי.אי קרנות נאמנות בעמ | D135: 513765339 | E135: ח.פ. | F135: IBI.תלבונד 60 | G135: IL0011480063 | H135: ISIN | I135: עוקב אחר מדדים אחרים בישראל | J135: ישראל | K135: ישראל | L135: TASE | M135: אג"ח בארץ - חברות והמרה-תל בונד צמוד מדד-תל בונד צמודות | N135: לא | O135: ILS | P135: 82400 | Q135: 1 | R135: 365.93 | S135: 0 | T135: 301.52632 | U135: 0 | V135: 0.090119293 | W135: 0.059933789
A136: 11939 | B136: 11980 | C136: הראל קרנות נאמנות בע"מ | D136: 511776783 | E136: ח.פ. | F136: הרל.תא 125 | G136: IL0011488991 | H136: ISIN | I136: עוקב אחר מדדי מניות בישראל | J136: ישראל | K136: ישראל | L136: TASE | M136: Large & Mid Cap מניות בארץ - מניות לפי שווי שוק-מניות | N136: לא | O136: ILS | P136: 15760 | Q136: 1 | R136: 2076 | S136: 0 | T136: 327.1776 | U136: 0 | V136: 0.097785871 | W136: 0.065032443
A137: 11939 | B137: 11980 | C137: מגדל קרנות נאמנות בע"מ | D137: 511303661 | E137: ח.פ. | F137: STX600.MTFממ | G137: IL0011506149 | H137: ISIN | I137: עוקב אחר מדדי מניות בחו"ל | J137: ישראל | K137: ארה"ב | L137: TASE | M137: מניות בחו"ל - מניות גיאוגרפי - מנוטרלת מט"ח-אירופה - מדד אחר | N137: לא | O137: ILS | P137: 2645 | Q137: 1 | R137: 7671 | S137: 0 | T137: 202.89795 | U137: 0.001 | V137: 0.060641538 | W137: 0.040329623
...

Sheet קרנות נאמנות
A1: מספר קופה/קרן/ח.פ. עבור חברת ביטוח | B1: מספר מסלול | C1: שם מנפיק | D1: מספר מנפיק | E1: סוג מספר מזהה מנפיק | F1: שם נייר ערך | G1: מספר נייר ערך | H1: סוג מספר נייר ערך | I1: מאפיין עיקרי | J1: ישראל/חו"ל | K1: מדינה לפי חשיפה כלכלית | L1: סטאטוס סחירות | M1: זירת מסחר | N1: סיווג הקרן | O1: בעל עניין/צד קשור | P1: מטבע פעילות | Q1: ערך נקוב (יחידות) | R1: שער חליפין | S1: שער נייר הערך | T1: שווי הוגן (באלפי ש"ח) | U1: שיעור מערך נקוב מונפק | V1: שיעור מנכסי אפיק ההשקעה | W1: שיעור מסך נכסי ההשקעה
A2: 7891 | B2: 7895 | C2: קסם קרנות נאמנות בע"מ | D2: 510938608 | E2: ח.פ. | F2: קסם תל גוב-שקלי | G2: IL0051180474 | H2: ISIN | I2: אג"ח ממשלתי | J2: ישראל | K2: ישראל | L2: סחיר | M2: TASE | N2: אג"ח בארץ - מדינה-אג"ח מדינה שקליות- ללא מניות | O2: לא | P2: ILS | Q2: 60260 | R2: 1 | S2: 119.67 | T2: 72.11314 | U2: 0.00066095174 | V2: =+T2/SUM(T2:T4) -> 0.33360006 | W2: =+T2/'סכום נכסים'!$B$30 -> 6.1818799e-05
A3: 7891 | B3: 7895 | C3: מגדל קרנות נאמנות בע"מ | D3: 511303661 | E3: ח.פ. | F3: מח גוב שקלי MTF | G3: IL0051233935 | H3: ISIN | I3: אג"ח ממשלתי | J3: ישראל | K3: ישראל | L3: סחיר | M3: TASE | N3: אג"ח בארץ - מדינה-אג"ח מדינה שקליות- ללא מניות | O3: לא | P3: ILS | Q3: 70740 | R3: 1 | S3: 100.91 | T3: 71.38373 | U3: 0.001465785 | V3: =+T3/SUM(T2:T4) -> 0.33022576 | W3: =+T3/'סכום נכסים'!$B$30 -> 6.1193514e-05
A4: 7891 | B4: 7895 | C4: מגדל קרנות נאמנות בע"מ | D4: 511303661 | E4: ח.פ. | F4: הראל תל גוב-שקל | G4: IL0051281116 | H4: ISIN | I4: אג"ח ממשלתי | J4: ישראל | K4: ישראל | L4: סחיר | M4: TASE | N4: אג"ח בארץ - מדינה-אג"ח מדינה שקליות- ללא מניות | O4: לא | P4: ILS | Q4: 16050 | R4: 1 | S4: 452.77 | T4: 72.66958 | U4: 0.0044582564 | V4: =+T4/SUM(T2:T4) -> 0.33617418 | W4: =+T4/'סכום נכסים'!$B$30 -> 6.2295805e-05
A5: 7891 | B5: 7897 | C5: אלטשולר שחם ניהול קרנות | D5: 511944670 | E5: ח.פ. | F5: אלטש כספ לא קנצ | G5: IL0051058209 | H5: ISIN | I5: אג"ח קונצרני | J5: ישראל | K5: ישראל | L5: סחיר | M5: TASE | N5: קרן כספית-כספית שקלית-כספית שקלית עם קונצרני | O5: לא | P5: ILS | Q5: 2843030 | R5: 1 | S5: 134.08 | T5: 3811.9346 | U5: 0.0014542178 | V5: 0.30154947 | W5: 0.041733094
A6: 7891 | B6: 7897 | C6: מור ניהול קרנות נאמנות | D6: 514884485 | E6: ח.פ. | F6: מור כספית | G6: IL0051198138 | H6: ISIN | I6: אג"ח קונצרני | J6: ישראל | K6: ישראל | L6: סחיר | M6: TASE | N6: קרן כספית-כספית שקלית-כספית שקלית עם קונצרני | O6: לא | P6: ILS | Q6: 4028370 | R6: 1 | S6: 110.23 | T6: 4440.4722 | U6: 0.00087828585 | V6: 0.35127099 | W6: 0.04861433
A7: 7891 | B7: 7897 | C7: קסם קרנות נאמנות בע"מ | D7: 510938608 | E7: ח.פ. | F7: קסם אקטכספיתפט | G7: IL0051278815 | H7: ISIN | I7: אג"ח קונצרני | J7: ישראל | K7: ישראל | L7: סחיר | M7: TASE | N7: קרן כספית-כספית שקלית-כספית שקלית עם קונצרני | O7: לא | P7: ILS | Q7: 4014224.4 | R7: 1 | S7: 109.33 | T7: 4388.7515 | U7: 0.00044526165 | V7: 0.34717954 | W7: 0.04804809
A8: 11925 | B8: 11928 | C8: אלטשולר שחם ניהול קרנות | D8: 511944670 | E8: ח.פ. | F8: אלטש כספ לא קנצ | G8: IL0051058209 | H8: ISIN | I8: אג"ח קונצרני | J8: ישראל | K8: ישראל | L8: סחיר | M8: TASE | N8: קרן כספית-כספית שקלית-כספית שקלית ללא קונצרני | O8: לא | P8: ILS | Q8: 4042470 | R8: 1 | S8: 134.08 | T8: 5420.1438 | U8: 0.0020677347 | V8: 0.27918357 | W8: 0.041881144
A9: 11925 | B9: 11928 | C9: מור ניהול קרנות נאמנות | D9: 514884485 | E9: ח.פ. | F9: מור כספית | G9: IL0051198138 | H9: ISIN | I9: אג"ח קונצרני | J9: ישראל | K9: ישראל | L9: סחיר | M9: TASE | N9: קרן כספית-כספית שקלית-כספית שקלית עם קונצרני | O9: לא | P9: ILS | Q9: 5300320 | R9: 1 | S9: 110.23 | T9: 5842.5427 | U9: 0.0011556029 | V9: 0.30094071 | W9: 0.045144997
A10: 11925 | B10: 11928 | C10: קסם קרנות נאמנות בע"מ | D10: 510938608 | E10: ח.פ. | F10: קסם אקטכספיתפט | G10: IL0051278815 | H10: ISIN | I10: אג"ח קונצרני | J10: ישראל | K10: ישראל | L10: סחיר | M10: TASE | N10: קרן כספית-כספית שקלית-כספית שקלית עם קונצרני | O10: לא | P10: ILS | Q10: 7455939.2 | R10: 1 | S10: 109.33 | T10: 8151.5784 | U10: 0.00082702 | V10: 0.41987572 | W10: 0.062986784
A11: 11939 | B11: 11942 | C11: אלטשולר שחם ניהול קרנות | D11: 511944670 | E11: ח.פ. | F11: אלטש כספ לא קנצ | G11: IL0051058209 | H11: ISIN | I11: אג"ח קונצרני | J11: ישראל | K11: ישראל | L11: סחיר | M11: TASE | N11: קרן כספית-כספית שקלית-כספית שקלית ללא קונצרני | O11: לא | P11: ILS | Q11: 6960638 | R11: 1 | S11: 134.08 | T11: 9332.8234 | U11: 0.0035603857 | V11: 0.27623647 | W11: 0.033609704
A12: 11939 | B12: 11942 | C12: מור ניהול קרנות נאמנות | D12: 514884485 | E12: ח.פ. | F12: מור כספית | G12: IL0051198138 | H12: ISIN | I12: אג"ח קונצרני | J12: ישראל | K12: ישראל | L12: סחיר | M12: TASE | N12: קרן כספית-כספית שקלית-כספית שקלית עם קונצרני | O12: לא | P12: ILS | Q12: 7587682 | R12: 1 | S12: 110.23 | T12: 8363.9019 | U12: 0.0016543053 | V12: 0.24755796 | W12: 0.030120388
A13: 11939 | B13: 11942 | C13: הראל קרנות נאמנות בע"מ | D13: 511776783 | E13: ח.פ. | F13: הראל כס מגמ ריב | G13: IL0051277908 | H13: ISIN | I13: אג"ח קונצרני | J13: ישראל | K13: ישראל | L13: סחיר | M13: TASE | N13: קרן כספית-כספית שקלית-כספית שקלית עם קונצרני | O13: לא | P13: ILS | Q13: 835445 | R13: 1 | S13: 1095.57 | T13: 9152.8848 | U13: 5.3721063e-05 | V13: 0.27091057 | W13: 0.032961702
A14: 11939 | B14: 11942 | C14: קסם קרנות נאמנות בע"מ | D14: 510938608 | E14: ח.פ. | F14: קסם אקטכספיתפט | G14: IL0051278815 | H14: ISIN | I14: אג"ח קונצרני | J14: ישראל | K14: ישראל | L14: סחיר | M14: TASE | N14: קרן כספית-כספית שקלית-כספית שקלית עם קונצרני | O14: לא | P14: ILS | Q14: 6344115.4 | R14: 1 | S14: 109.33 | T14: 6936.0213 | U14: 0.00070369542 | V14: 0.205295 | W14: 0.024978253
A15: 11939 | B15: 11943 | C15: קסם קרנות נאמנות בע"מ | D15: 510938608 | E15: ח.פ. | F15: STX EURO600 קסם | G15: IL0051256126 | H15: ISIN | I15: מניות | J15: ישראל | K15: אירופה | L15: סחיר | M15: TASE | N15: מניות בחו"ל - מניות גיאוגרפי - חשופת מט"ח-אירופה - מדד אחר | O15: לא | P15: ILS | Q15: 52760 | R15: 1 | S15: 164.9 | T15: 87.00124 | U15: 0.00060396677 | V15: 1 | W15: 0.015070884
A16: 11939 | B16: 11944 | C16: BlackRock Advantage Eurore | D16: 549300MQT7YRWQ7R2C91 | E16: LEI | F16: BLKR ADV EUR X UK-D USD HDG | G16: IE00BFZP7J29 | H16: ISIN | I16: מניות | J16: חו"ל | K16: בריטניה | L16: סחיר | M16: NYSE | N16: Equity Funds | O16: לא | P16: USD | Q16: 776.17 | R16: 3.71 | S16: 20302.1 | T16: 584.61738 | U16: 0 | V16: 0.21526149 | W16: 0.025192956
A17: 11939 | B17: 11944 | C17: BlackRock Global Funds - Fixed | D17: 549300CNEUCVQC88OL03 | E17: LEI | F17: BGF-FIX INC GL OP-D2 USD | G17: LU0278469043 | H17: ISIN | I17: אג"ח קונצרני | J17: חו"ל | K17: ארה"ב | L17: סחיר | M17: NYSE | N17: Bond/Fixed Income Funds | O17: לא | P17: USD | Q17: 9665.44 | R17: 3.71 | S17: 1743 | T17: 625.01858 | U17: 0 | V17: 0.23013758 | W17: 0.026933967
A18: 11939 | B18: 11944 | C18: BlackRock Sustainable Advantag | D18: 5493002MQ0TZR3NYON05 | E18: LEI | F18: BLKRK ADV US EQ-D USD ACC | G18: IE00BFZP7V49 | H18: ISIN | I18: מניות | J18: חו"ל | K18: ארה"ב | L18: סחיר | M18: NYSE | N18: Equity Funds | O18: לא | P18: USD | Q18: 1357.09 | R18: 3.71 | S18: 22248.6 | T18: 1120.1734 | U18: 0 | V18: 0.41245813 | W18: 0.048271706
A19: 11939 | B19: 11944 | C19: BlackRock Funds I ICAV | D19: 549300CTIHAGMB3T0563 | E19: LEI | F19: BLCKRCK I ICAV TAC-D USD ACC | G19: IE00BK4PZV64 | H19: ISIN | I19: מניות | J19: חו"ל | K19: ארה"ב | L19: סחיר | M19: NYSE | N19: Equity Funds | O19: לא | P19: USD | Q19: 824.95 | R19: 3.71 | S19: 12613.3 | T19: 386.03818 | U19: 0 | V19: 0.1421428 | W19: 0.016635569
A20: 11939 | B20: 11980 | C20: אי.בי.אי קרנות נאמנות בעמ | D20: 513765339 | E20: ח.פ. | F20: IBI.יSHILLERUSמ | G20: IL0051346893 | H20: ISIN | I20: מניות | J20: ישראל | K20: ארה"ב | L20: סחיר | M20: TASE | N20: מניות בחו"ל - מניות גיאוגרפי - מנוטרלת מט"ח-ארה"ב - מדד אחר | O20: לא | P20: ILS | Q20: 184320 | R20: 1 | S20: 122.16 | T20: 225.16531 | U20: 0.00019456984 | V20: 1 | W20: 0.044755662
A21: 11939 | B21: 11981 | C21: אי.בי.אי קרנות נאמנות בעמ | D21: 513765339 | E21: ח.פ. | F21: IBI.יSHILLERUSמ | G21: IL0051346893 | H21: ISIN | I21: מניות | J21: ישראל | K21: ארה"ב | L21: סחיר | M21: TASE | N21: מניות בחו"ל - מניות גיאוגרפי - מנוטרלת מט"ח-ארה"ב - מדד אחר | O21: לא | P21: ILS | Q21: 71630 | R21: 1 | S21: 122.16 | T21: 87.50321 | U21: 7.5613269e-05 | V21: 1 | W21: 0.030379424
A22: 11342 | B22: 11343 | C22: אי.בי.אי קרנות נאמנות בעמ | D22: 513765339 | E22: ח.פ. | F22: SHILLERCUSי.IBI | G22: IL0051307374 | H22: ISIN | I22: מניות | J22: ישראל | K22: ארה"ב | L22: סחיר | M22: TASE | N22: מניות בחו"ל - מניות גיאוגרפי - חשופת מט"ח-ארה"ב - מדד אחר | O22: לא | P22: ILS | Q22: 4952705 | R22: 1 | S22: 228.09 | T22: 11296.625 | U22: 0.004476648 | V22: 1 | W22: 0.024489696
A23: 11342 | B23: 11344 | C23: אי.בי.אי קרנות נאמנות בעמ | D23: 513765339 | E23: ח.פ. | F23: IBI.SHILLER נ $ | G23: IL0051371792 | H23: ISIN | I23: מניות | J23: ישראל | K23: ארה"ב | L23: סחיר | M23: TASE | N23: מניות בחו"ל - מניות גיאוגרפי - חשופת מט"ח-ארה"ב - מדד אחר | O23: לא | P23: USD | Q23: 15273 | R23: 3.71 | S23: 127.9 | T23: 72.47176 | U23: 8.7881559e-05 | V23: 1 | W23: 0.022984448
A24: 11342 | B24: 11345 | C24: קסם קרנות נאמנות בע"מ | D24: 510938608 | E24: ח.פ. | F24: קסם SPHLTCAREממ | G24: IL0051360563 | H24: ISIN | I24: מניות | J24: ישראל | K24: ארה"ב | L24: סחיר | M24: TASE | N24: מניות בחו"ל - מניות לפי ענפים בחו"ל - מנוטרלת מט"ח-ענפים אחרים | O24: לא | P24: ILS | Q24: 3686 | R24: 1 | S24: 14266.15 | T24: 525.85029 | U24: 6.5697823e-05 | V24: 0.30804445 | W24: 0.026568232
A25: 11342 | B25: 11345 | C25: אי.בי.אי קרנות נאמנות בעמ | D25: 513765339 | E25: ח.פ. | F25: IBI.SHILLER נ $ | G25: IL0051371792 | H25: ISIN | I25: מניות | J25: ישראל | K25: ארה"ב | L25: סחיר | M25: TASE | N25: מניות בחו"ל - מניות גיאוגרפי - חשופת מט"ח-ארה"ב - מדד אחר | O25: לא | P25: USD | Q25: 248933 | R25: 3.71 | S25: 127.9 | T25: 1181.2095 | U25: 0.0014323722 | V25: 0.69195555 | W25: 0.059679814
A26: 7891 | B26: 7892
A27: 7891 | B27: 7893
A28: 7891 | B28: 7894
A29: 7891 | B29: 7896
A30: 7891 | B30: 7898
A31: 7891 | B31: 7899
A32: 7891 | B32: 7900
A33: 7891 | B33: 7901
A34: 7891 | B34: 7902
A35: 11925 | B35: 11926
A36: 11925 | B36: 11927
A37: 11925 | B37: 11929
... A52: 11939 | B52: 11979

Sheet כתבי אופציה
A1: מספר קופה/קרן/ח.פ. עבור חברת ביטוח | B1: מספר מסלול | C1: שם מנפיק | D1: מספר מנפיק | E1: סוג מספר מזהה מנפיק | F1: שם נייר ערך | G1: מספר נייר ערך | H1: סוג מספר נייר ערך | I1: ישראל/חו"ל | J1: מדינה לפי חשיפה כלכלית | K1: סטאטוס סחירות | L1: זירת מסחר | M1: נכס בסיס (כתב אופציה) | N1: ענף מסחר | O1: תאריך פקיעה | P1: בעל עניין/צד קשור | Q1: מטבע פעילות | R1: שער מימוש | S1: יחס המרה | T1: ערך נקוב (יחידות) | U1: שער חליפין | V1: שער נייר הערך | W1: שווי הוגן (באלפי ש"ח) | X1: שיעור מנכסי אפיק ההשקעה | Y1: שיעור מסך נכסי ההשקעה
A2: 7891 | B2: 7892
A3: 7891 | B3: 7893
A4: 7891 | B4: 7894
A5: 7891 | B5: 7895
A6: 7891 | B6: 7896
A7: 7891 | B7: 7897
A8: 7891 | B8: 7898
A9: 7891 | B9: 7899
A10: 7891 | B10: 7900
A11: 7891 | B11: 7901
A12: 7891 | B12: 7902
A13: 11925 | B13: 11926
... A39: 11342 | B39: 11345

Sheet אופציות
A1: מספר קופה/קרן/ח.פ. עבור חברת ביטוח | B1: מספר מסלול | C1: שם מנפיק | D1: מספר מנפיק | E1: סוג מספר מזהה מנפיק | F1: שם נייר ערך | G1: מספר נייר ערך | H1: סוג מספר נייר ערך | I1: מאפיין עיקרי | J1: ישראל/חו"ל | K1: מדינה לפי חשיפה כלכלית | L1: זירת מסחר | M1: ענף מסחר | N1: נכס בסיס | O1: תאריך פקיעה | P1: בעל עניין/צד קשור | Q1: מטבע פעילות | R1: שער מימוש | S1: ערך נקוב (יחידות) | T1: שער חליפין | U1: שער נייר הערך | V1: שווי הוגן (באלפי ש"ח) | W1: שיעור מנכסי אפיק ההשקעה | X1: שיעור מסך נכסי ההשקעה
A2: 7891 | B2: 7892
A3: 7891 | B3: 7893
A4: 7891 | B4: 7894
A5: 7891 | B5: 7895
A6: 7891 | B6: 7896
A7: 7891 | B7: 7897
A8: 7891 | B8: 7898
A9: 7891 | B9: 7899
A10: 7891 | B10: 7900
A11: 7891 | B11: 7901
A12: 7891 | B12: 7902
A13: 11925 | B13: 11926
... A39: 11342 | B39: 11345

Sheet חוזים עתידיים
A1: מספר קופה/קרן/ח.פ. עבור חברת ביטוח | B1: מספר מסלול | C1: שם מנפיק | D1: מספר מנפיק | E1: סוג מספר מזהה מנפיק | F1: שם נייר ערך | G1: מספר נייר ערך | H1: סוג מספר נייר ערך | I1: ישראל/חו"ל | J1: מדינה לפי חשיפה כלכלית | K1: זירת מסחר | L1: נכס בסיס | M1: בעל עניין/צד קשור | N1: מטבע פעילות | O1: ערך נקוב (יחידות) | P1: שער חליפין | Q1: שער נייר הערך | R1: שווי הוגן (באלפי ש"ח) | S1: שיעור מנכסי אפיק ההשקעה | T1: שיעור מסך נכסי ההשקעה
A2: 7891 | B2: 7892
A3: 7891 | B3: 7893
A4: 7891 | B4: 7894
A5: 7891 | B5: 7895
A6: 7891 | B6: 7896
A7: 7891 | B7: 7897
A8: 7891 | B8: 7898
A9: 7891 | B9: 7899
A10: 7891 | B10: 7900
A11: 7891 | B11: 7901
A12: 7891 | B12: 7902
A13: 11925 | B13: 11926
... A39: 11342 | B39: 11345

Sheet מוצרים מובנים
A1: מספר קופה/קרן/ח.פ. עבור חברת ביטוח | B1: מספר מסלול | C1: שם מנפיק | D1: מספר מנפיק | E1: סוג מספר מזהה מנפיק | F1: שם נייר ערך | G1: מספר נייר ערך | H1: סוג מספר נייר ערך | I1: מאפיין עיקרי | J1: ישראל/חו"ל | K1: מדינה לפי חשיפה כלכלית | L1: סטאטוס סחירות | M1: זירת מסחר | N1: נכס בסיס | O1: בעל עניין/צד קשור | P1: מח"מ | Q1: שיעור ריבית | R1: תשואה לפדיון | S1: דירוג | T1: שם מדרג | U1: דירוג נייר הערך/המנפיק | V1: מטבע פעילות | W1: ערך נקוב (יחידות) | X1: שער חליפין | Y1: שער נייר הערך | Z1: שווי הוגן (באלפי ש"ח) | AA1: שיעור מנכסי אפיק ההשקעה | AB1: שיעור מסך נכסי ההשקעה
A2: 7891 | B2: 7892
A3: 7891 | B3: 7893
A4: 7891 | B4: 7894
A5: 7891 | B5: 7895
A6: 7891 | B6: 7896
A7: 7891 | B7: 7897
A8: 7891 | B8: 7898
A9: 7891 | B9: 7899
A10: 7891 | B10: 7900
A11: 7891 | B11: 7901
A12: 7891 | B12: 7902
A13: 11925 | B13: 11926
... A39: 11342 | B39: 11345

Sheet לא סחיר איגרות חוב ממשלתיות
A1: מספר קופה/קרן/ח.פ. עבור חברת ביטוח | B1: מספר מסלול | C1: שם מנפיק | D1: שם נייר ערך | E1: מספר נייר ערך | F1: סוג מספר נייר ערך | G1: מאפיין עיקרי | H1: ישראל/חו"ל | I1: מדינה לפי חשיפה כלכלית | J1: תאריך רכישה | K1: דירוג | L1: שם מדרג | M1: מטבע פעילות | N1: מח"מ | O1: מועד פדיון | P1: שיעור ריבית | Q1: תשואה לפדיון | R1: ערך נקוב (יחידות) | S1: שער חליפין | T1: שער נייר הערך | U1: שווי הוגן (באלפי ש"ח) | V1: עלות מופחתת (באלפי ש"ח) | W1: השיטה שיושמה בדוח הכספי | X1: שיעור מנכסי אפיק ההשקעה | Y1: שיעור מסך נכסי ההשקעה
A2: 7891 | B2: 7892
A3: 7891 | B3: 7893
A4: 7891 | B4: 7894
A5: 7891 | B5: 7895
A6: 7891 | B6: 7896
A7: 7891 | B7: 7897
A8: 7891 | B8: 7898
A9: 7891 | B9: 7899
A10: 7891 | B10: 7900
A11: 7891 | B11: 7901
A12: 7891 | B12: 7902
A13: 11925 | B13: 11926
... A39: 11342 | B39: 11345

Sheet לא סחיר איגרות חוב מיועדות
A1: מספר קופה/קרן/ח.פ. עבור חברת ביטוח | B1: מספר מסלול | C1: מאפיין עיקרי | D1: שם נייר ערך | E1: מספר נייר ערך | F1: תאריך רכישה | G1: מח"מ | H1: סוג הצמדה | I1: מועד פדיון | J1: שיעור ריבית | K1: תשואה לפדיון | L1: ערך נקוב (יחידות) | M1: שער נייר הערך | N1: שווי הוגן (באלפי ש"ח) | O1: עלות מופחתת (באלפי ש"ח) | P1: השיטה שיושמה בדוח הכספי | Q1: שיעור מנכסי אפיק ההשקעה | R1: שיעור מסך נכסי ההשקעה
A2: 7891 | B2: 7892
A3: 7891 | B3: 7893
A4: 7891 | B4: 7894
A5: 7891 | B5: 7895
A6: 7891 | B6: 7896
A7: 7891 | B7: 7897
A8: 7891 | B8: 7898
A9: 7891 | B9: 7899
A10: 7891 | B10: 7900
A11: 7891 | B11: 7901
A12: 7891 | B12: 7902
A13: 11925 | B13: 11926
... A39: 11342 | B39: 11345

Sheet אפיק השקעה מובטח תשואה
A1: מספר קרן | B1: מספר מסלול | C1: מאפיין עיקרי | D1: חודש הנפקת שכבה | E1: חודש הבדיקה | F1: שווי הנכסים באפיק (באלפי ש"ח) | G1: שיעור מסך נכסי ההשקעה
A2: 7891 | B2: 7892
A3: 7891 | B3: 7893
A4: 7891 | B4: 7894
A5: 7891 | B5: 7895
A6: 7891 | B6: 7896
A7: 7891 | B7: 7897
A8: 7891 | B8: 7898
A9: 7891 | B9: 7899
A10: 7891 | B10: 7900
A11: 7891 | B11: 7901
A12: 7891 | B12: 7902
A13: 11925 | B13: 11926
... A39: 11342 | B39: 11345

Sheet לא סחיר ניירות ערך מסחריים
A1: מספר קופה/קרן/ח.פ. עבור חברת ביטוח | B1: מספר מסלול | C1: שם מנפיק | D1: מספר מנפיק | E1: סוג מספר מזהה מנפיק | F1: שם נייר ערך | G1: מספר נייר ערך | H1: סוג מספר נייר ערך | I1: מאפיין עיקרי | J1: ישראל/חו"ל | K1: מדינה לפי חשיפה כלכלית | L1: ענף מסחר | M1: בעל עניין/צד קשור | N1: תאריך רכישה | O1: דירוג | P1: שם מדרג | Q1: דירוג נייר הערך/המנפיק | R1: מטבע פעילות | S1: מח"מ | T1: סוג הצמדה | U1: ריבית עוגן | V1: מועד פדיון | W1: שיעור ריבית | X1: תשואה לפדיון | Y1: נחיתות חוזית | Z1: האם סווג כחוב בעייתי | AA1: סוג גורם משערך | AB1: תלות/אי-תלות המשערך | AC1: שם גורם משערך | AD1: תאריך שערוך אחרון | AE1: תאריך אחרון בו נבחנה בפועל ירידת ערך | AF1: ערך נקוב (יחידות) | AG1: שער חליפין | AH1: שער נייר הערך | AI1: שווי הוגן (באלפי ש"ח) | AJ1: עלות מופחתת (באלפי ש"ח) | AK1: עלות מופחתת (במטבע הפעילות) | AL1: השיטה שיושמה בדוח הכספי | AM1: שיעור מנכסי אפיק ההשקעה | AN1: שיעור מסך נכסי ההשקעה
A2: 7891 | B2: 7892
A3: 7891 | B3: 7893
A4: 7891 | B4: 7894
A5: 7891 | B5: 7895
A6: 7891 | B6: 7896
A7: 7891 | B7: 7897
A8: 7891 | B8: 7898
A9: 7891 | B9: 7899
A10: 7891 | B10: 7900
A11: 7891 | B11: 7901
A12: 7891 | B12: 7902
A13: 11925 | B13: 11926
... A39: 11342 | B39: 11345

Sheet לא סחיר איגרות חוב
A1: מספר קופה/קרן/ח.פ. עבור חברת ביטוח | B1: מספר מסלול | C1: שם מנפיק | D1: מספר מנפיק | E1: סוג מספר מזהה מנפיק | F1: שם נייר ערך | G1: מספר נייר ערך | H1: סוג מספר נייר ערך | I1: מאפיין עיקרי | J1: ישראל/חו"ל | K1: מדינה לפי חשיפה כלכלית | L1: סטאטוס סחירות | M1: ענף מסחר | N1: בעל עניין/צד קשור | O1: תאריך רכישה | P1: דירוג | Q1: שם מדרג | R1: דירוג נייר הערך/המנפיק | S1: מטבע פעילות | T1: מח"מ | U1: מועד פדיון | V1: תשואה לפדיון | W1: שיעור ריבית | X1: נחיתות חוזית | Y1: האם סווג כחוב בעייתי | Z1: סוג גורם משערך | AA1: תלות/אי-תלות המשערך | AB1: תאריך שערוך אחרון | AC1: תאריך אחרון בו נבחנה בפועל ירידת ערך | AD1: ערך נקוב (יחידות) | AE1: שער חליפין | AF1: שער נייר הערך | AG1: שווי הוגן (באלפי ש"ח) | AH1: עלות מופחתת (באלפי ש"ח) | AI1: עלות מופחתת (במטבע הפעילות) | AJ1: השיטה שיושמה בדוח הכספי | AK1: שיעור מנכסי אפיק ההשקעה | AL1: שיעור מסך נכסי ההשקעה
A2: 7891 | B2: 7892
A3: 7891 | B3: 7893
A4: 7891 | B4: 7894
A5: 7891 | B5: 7895
A6: 7891 | B6: 7896
A7: 7891 | B7: 7897
A8: 7891 | B8: 7898
A9: 7891 | B9: 7899
A10: 7891 | B10: 7900
A11: 7891 | B11: 7901
A12: 7891 | B12: 7902
A13: 11925 | B13: 11926
... A39: 11342 | B39: 11345

Sheet לא סחיר מניות מבכ ויהש
A1: מספר קופה/קרן/ח.פ. עבור חברת ביטוח | B1: מספר מסלול | C1: שם מנפיק | D1: מספר מנפיק | E1: סוג מספר מזהה מנפיק | F1: שם נייר ערך | G1: מספר נייר ערך | H1: סוג מספר נייר ערך | I1: מאפיין עיקרי | J1: ישראל/חו"ל | K1: מדינה לפי חשיפה כלכלית | L1: סטאטוס סחירות | M1: ענף מסחר | N1: בעל עניין/צד קשור | O1: תאריך רכישה | P1: מטבע פעילות | Q1: סוג גורם משערך | R1: תלות/אי-תלות המשערך | S1: תאריך שערוך אחרון | T1: תאריך אחרון בו נבחנה בפועל ירידת ערך | U1: ערך נקוב (יחידות) | V1: שער חליפין | W1: שער נייר הערך | X1: שווי הוגן (באלפי ש"ח) | Y1: שיעור מנכסי אפיק ההשקעה | Z1: שיעור מסך נכסי ההשקעה
A2: 7891 | B2: 7892
A3: 7891 | B3: 7893
A4: 7891 | B4: 7894
A5: 7891 | B5: 7895
A6: 7891 | B6: 7896
A7: 7891 | B7: 7897
A8: 7891 | B8: 7898
A9: 7891 | B9: 7899
A10: 7891 | B10: 7900
A11: 7891 | B11: 7901
A12: 7891 | B12: 7902
A13: 11925 | B13: 11926
... A39: 11342 | B39: 11345

Sheet קרנות השקעה
A1: מספר קופה/קרן/ח.פ. עבור חברת ביטוח | B1: מספר מסלול | C1: שם שותף כללי קרן השקעות | D1: מספר מזהה שותף כללי קרן השקעות | E1: סוג מספר מזהה שותף כללי קרן השקעות | F1: שם קרן השקעה | G1: מספר מזהה קרן השקעה | H1: סוג מספר מזהה קרן השקעות | I1: מאפיין עיקרי | J1: אסטרטגיית קרן ההשקעה | K1: ישראל/חו"ל | L1: מדינת התאגדות קרן השקעה | M1: מיקום משרד השותף הכללי | N1: מדינה לפי חשיפה כלכלית | O1: בעל עניין/צד קשור | P1: תאריך רכישה | Q1: מטבע פעילות | R1: סוג גורם משערך | S1: תלות/אי-תלות המשערך | T1: תאריך שערוך אחרון | U1: שער חליפין | V1: NAV (במטבע הדיווח של קרן ההשקעה) | W1: שווי הוגן (באלפי ש"ח) | X1: שיעור החזקה בקרן השקעה | Y1: שיעור מנכסי אפיק ההשקעה | Z1: שיעור מסך נכסי ההשקעה
A2: 7891 | B2: 7897 | C2: Stepstone | F2: Stepstone_SCL E | G2: 11017960 | H2: פנימי | I2: קרן חוב | K2: חו"ל | N2: אירופה | O2: לא | P2: 43661 | Q2: EUR | R2: דיווח מנהל הקרן | S2: אי-תלות | T2: 45565 | U2: 4.1524 | V2: 1369.0646 | W2: 5684.9039 | X2: 0.0056397314 | Y2: 0.37379764 | Z2: 0.062238378
A3: 7891 | B3: 7897 | C3: Stepstone | F3: SCL Enhanched $ | G3: 11017989 | H3: פנימי | I3: קרן חוב | K3: חו"ל | N3: אירופה | O3: לא | P3: 43718 | Q3: USD | R3: דיווח מנהל הקרן | S3: אי-תלות | T3: 45565 | U3: 3.71 | V3: 462.94651 | W3: 1717.5315 | X3: 0.0029774805 | Y3: 0.11293229 | Z3: 0.018803551
A4: 7891 | B4: 7897 | C4: פניקס קפיטל/פולן | F4: POLLEN FUND | G4: 11019167 | H4: פנימי | I4: קרן חוב | K4: חו"ל | N4: ארה"ב | O4: לא | P4: 44404 | Q4: USD | R4: דיווח מנהל הקרן | S4: אי-תלות | T4: 45565 | U4: 3.71 | V4: 1419.7316 | W4: 5267.2044 | X4: 0.0654 | Y4: 0.34633278 | Z4: 0.057665401
A5: 7891 | B5: 7897 | C5: Ares Real Estate Enhanced Income Advisors LLC | F5: Ares Real Estat | G5: 11019503 | H5: פנימי | I5: קרן חוב | K5: חו"ל | N5: ארה"ב | O5: לא | P5: 44655 | Q5: USD | R5: דיווח מנהל הקרן | S5: אי-תלות | T5: 45565 | U5: 3.71 | V5: 674.05511 | W5: 2500.7445 | X5: 0.025 | Y5: 0.16443064 | Z5: 0.027378173
A6: 7891 | B6: 7897 | C6: הפניקס רילטק בע"מ | F6: Real Es_Dbt KYC | G6: 11020454 | H6: פנימי | I6: קרן חוב | K6: חו"ל | N6: ארה"ב | O6: לא | P6: 44530 | Q6: ILS | R6: דיווח מנהל הקרן | S6: אי-תלות | T6: 45565 | U6: 1 | V6: 38.12245 | W6: 38.12245 | Y6: 0.0025066531 | Z6: 0.00041736492
A7: 11925 | B7: 11928 | C7: Stepstone | F7: Stepstone_SCL E | G7: 11017960 | H7: פנימי | I7: קרן חוב | K7: חו"ל | N7: אירופה | O7: לא | P7: 43661 | Q7: EUR | R7: דיווח מנהל הקרן | S7: אי-תלות | T7: 45565 | U7: 4.1524 | V7: 2064.1691 | W7: 8571.2559 | X7: 0.0085031483 | Y7: 0.37379766 | Z7: 0.066229609
A8: 11925 | B8: 11928 | C8: Stepstone | F8: SCL Enhanched $ | G8: 11017989 | H8: פנימי | I8: קרן חוב | K8: חו"ל | N8: אירופה | O8: לא | P8: 43718 | Q8: USD | R8: דיווח מנהל הקרן | S8: אי-תלות | T8: 45565 | U8: 3.71 | V8: 697.9939 | W8: 2589.5574 | X8: 0.0044892082 | Y8: 0.11293217 | Z8: 0.020009363
A9: 11925 | B9: 11928 | C9: פניקס קפיטל/פולן | F9: POLLEN FUND | G9: 11019167 | H9: פנימי | I9: קרן חוב | K9: חו"ל | N9: ארה"ב | O9: לא | P9: 44404 | Q9: USD | R9: דיווח מנהל הקרן | S9: אי-תלות | T9: 45565 | U9: 3.71 | V9: 2140.5612 | W9: 7941.4822 | X9: 0.0654 | Y9: 0.34633285 | Z9: 0.061363383
A10: 11925 | B10: 11928 | C10: הפניקס רילטק בע"מ | F10: Real Es_Dbt KYC | G10: 11019396 | H10: פנימי | I10: קרן חוב | K10: חו"ל | N10: ארה"ב | O10: לא | P10: 44530 | Q10: USD | R10: דיווח מנהל הקרן | S10: אי-תלות | T10: 45565 | U10: 3.71 | V10: -0.00056603774 | W10: -0.0021 | Y10: -9.1582272e-08 | Z10: -1.6226581e-08
A11: 11925 | B11: 11928 | C11: Ares Real Estate Enhanced Income Advisors LLC | F11: Ares Real Estat | G11: 11019503 | H11: פנימי | I11: קרן חוב | K11: חו"ל | N11: ארה"ב | O11: לא | P11: 44655 | Q11: USD | R11: דיווח מנהל הקרן | S11: אי-תלות | T11: 45565 | U11: 3.71 | V11: 1016.288 | W11: 3770.4284 | X11: 0.025 | Y11: 0.16443067 | Z11: 0.029133887
A12: 11925 | B12: 11928 | C12: הפניקס רילטק בע"מ | F12: Real Es_Dbt KYC | G12: 11020454 | H12: פנימי | I12: קרן חוב | K12: חו"ל | N12: ארה"ב | O12: לא | P12: 44530 | Q12: ILS | R12: דיווח מנהל הקרן | S12: אי-תלות | T12: 45565 | U12: 1 | V12: 57.48028 | W12: 57.48028 | Y12: 0.0025067498 | Z12: 0.00044414687
A13: 11939 | B13: 11942 | C13: Stepstone | F13: Stepstone_SCL E | G13: 11017960 | H13: פנימי | I13: קרן חוב | K13: חו"ל | N13: אירופה | O13: לא | P13: 43661 | Q13: EUR | R13: דיווח מנהל הקרן | S13: אי-תלות | T13: 45565 | U13: 4.1524 | V13: 5310.575 | W13: 22051.632 | X13: 0.021876408 | Y13: 0.37379766 | Z13: 0.079413139
A14: 11939 | B14: 11942 | C14: Stepstone | F14: SCL Enhanched $ | G14: 11017989 | H14: פנימי | I14: קרן חוב | K14: חו"ל | N14: אירופה | O14: לא | P14: 43718 | Q14: USD | R14: דיווח מנהל הקרן | S14: אי-תלות | T14: 45565 | U14: 3.71 | V14: 1795.7588 | W14: 6662.265 | X14: 0.011549578 | Y14: 0.11293219 | Z14: 0.023992391
A15: 11939 | B15: 11942 | C15: פניקס קפיטל/פולן | F15: POLLEN FUND | G15: 11019167 | H15: פנימי | I15: קרן חוב | K15: חו"ל | N15: ארה"ב | O15: לא | P15: 44404 | Q15: USD | R15: דיווח מנהל הקרן | S15: אי-תלות | T15: 45565 | U15: 3.71 | V15: 5507.112 | W15: 20431.386 | X15: 0.0654 | Y15: 0.34633283 | Z15: 0.07357825
A16: 11939 | B16: 11942 | C16: הפניקס רילטק בע"מ | F16: Real Es_Dbt KYC | G16: 11019396 | H16: פנימי | I16: קרן חוב | K16: חו"ל | N16: ארה"ב | O16: לא | P16: 44530 | Q16: USD | R16: דיווח מנהל הקרן | S16: אי-תלות | T16: 45565 | U16: 3.71 | V16: -0.00050134771 | W16: -0.00186 | Y16: -3.1528898e-08 | Z16: -6.6982997e-09
A17: 11939 | B17: 11942 | C17: Ares Real Estate Enhanced Income Advisors LLC | F17: Ares Real Estat | G17: 11019503 | H17: פנימי | I17: קרן חוב | K17: חו"ל | N17: ארה"ב | O17: לא | P17: 44655 | Q17: USD | R17: דיווח מנהל הקרן | S17: אי-תלות | T17: 45565 | U17: 3.71 | V17: 2614.6469 | W17: 9700.34 | X17: 0.025 | Y17: 0.16443066 | Z17: 0.034933218
A18: 11939 | B18: 11942 | C18: הפניקס רילטק בע"מ | F18: Real Es_Dbt KYC | G18: 11020454 | H18: פנימי | I18: קרן חוב | K18: חו"ל | N18: ארה"ב | O18: לא | P18: 44530 | Q18: ILS | R18: דיווח מנהל הקרן | S18: אי-תלות | T18: 45565 | U18: 1 | V18: 147.87826 | W18: 147.87826 | Y18: 0.0025066874 | Z18: 0.00053254457
A19: 11939 | B19: 11979 | C19: קומריט השקעות בע"מ | F19: Comrit Inv_fund | G19: 11017147 | H19: פנימי | I19: (Hedge Fund) קרן גידור | K19: ישראל | N19: ישראל | O19: לא | P19: 43066 | Q19: USD | R19: דיווח מנהל הקרן | S19: אי-תלות | T19: 45565 | U19: 3.71 | V19: 107.166 | W19: 397.58586 | X19: 0.00026 | Y19: 1 | Z19: 0.012297624
A20: 11342 | B20: 11343 | C20: פניקס קפיטל | F20: Debt strateg In | G20: 11018811 | H20: פנימי | I20: קרן השקעה אחרת | K20: ישראל | N20: ישראל | O20: לא | P20: 44220 | Q20: ILS | R20: דיווח מנהל הקרן | S20: אי-תלות | T20: 45565 | U20: 1 | V20: 4429.8487 | W20: 4429.8487 | X20: 1 | Y20: 0.10055215 | Z20: 0.0096033684
A21: 11342 | B21: 11343 | C21: טנדם קפיטל השקעות בע"מ | F21: GB Fund | G21: 11019771 | H21: פנימי | I21: קרן חוב | K21: ישראל | N21: ישראל | O21: לא | P21: 44818 | Q21: ILS | R21: דיווח מנהל הקרן | S21: אי-תלות | T21: 45565 | U21: 1 | V21: 18221.564 | W21: 18221.564 | X21: 0.01037 | Y21: 0.41360721 | Z21: 0.039502114
A22: 11342 | B22: 11343 | C22: METROPOLITAN OFFSHORE PARTNERS FUND VII, LP | F22: Metropolitan | G22: 11019488 | H22: פנימי | I22: קרן השקעה אחרת | K22: חו"ל | N22: ארה"ב | O22: לא | P22: 44629 | Q22: USD | R22: דיווח מנהל הקרן | S22: אי-תלות | T22: 45565 | U22: 3.71 | V22: 5769.225 | W22: 21403.825 | X22: 0.0807 | Y22: 0.48584064 | Z22: 0.046400865
A23: 7891 | B23: 7892
A24: 7891 | B24: 7893
A25: 7891 | B25: 7894
A26: 7891 | B26: 7895
A27: 7891 | B27: 7896
A28: 7891 | B28: 7898
A29: 7891 | B29: 7899
A30: 7891 | B30: 7900
A31: 7891 | B31: 7901
A32: 7891 | B32: 7902
A33: 11925 | B33: 11926
A34: 11925 | B34: 11927
... A55: 11342 | B55: 11345

Sheet לא סחיר כתבי אופציה
A1: מספר קופה/קרן/ח.פ. עבור חברת ביטוח | B1: מספר מסלול | C1: שם מנפיק | D1: מספר מנפיק | E1: סוג מספר מזהה מנפיק | F1: שם נייר ערך | G1: מספר נייר ערך | H1: סוג מספר נייר ערך | I1: ישראל/חו"ל | J1: מדינה לפי חשיפה כלכלית | K1: סטאטוס סחירות | L1: נכס בסיס (כתב אופציה) | M1: ענף מסחר | N1: תאריך פקיעה | O1: בעל עניין/צד קשור | P1: תאריך רכישה | Q1: מטבע פעילות | R1: סוג גורם משערך | S1: תלות/אי-תלות המשערך | T1: תאריך שערוך אחרון | U1: שער מימוש | V1: יחס המרה | W1: ערך נקוב (יחידות) | X1: שער נייר הערך | Y1: שער חליפין | Z1: שווי הוגן (באלפי ש"ח) | AA1: שיעור מנכסי אפיק ההשקעה | AB1: שיעור מסך נכסי ההשקעה
A2: 7891 | B2: 7892
A3: 7891 | B3: 7893
A4: 7891 | B4: 7894
A5: 7891 | B5: 7895
A6: 7891 | B6: 7896
A7: 7891 | B7: 7897
A8: 7891 | B8: 7898
A9: 7891 | B9: 7899
A10: 7891 | B10: 7900
A11: 7891 | B11: 7901
A12: 7891 | B12: 7902
A13: 11925 | B13: 11926
... A39: 11342 | B39: 11345

Sheet לא סחיר אופציות
A1: מספר קופה/קרן/ח.פ. עבור חברת ביטוח | B1: מספר מסלול | C1: שם מנפיק | D1: מספר מנפיק | E1: סוג מספר מזהה מנפיק | F1: שם נייר ערך | G1: מספר נייר ערך | H1: סוג מספר נייר ערך | I1: מאפיין עיקרי | J1: ישראל/חו"ל | K1: מדינה לפי חשיפה כלכלית | L1: ענף מסחר | M1: נכס בסיס | N1: תאריך פקיעה | O1: בעל עניין/צד קשור | P1: תאריך רכישה | Q1: מטבע פעילות | R1: סוג גורם משערך | S1: תלות/אי-תלות המשערך | T1: תאריך שערוך אחרון | U1: שער מימוש | V1: יחס המרה | W1: ערך נקוב (יחידות) | X1: שער נייר הערך | Y1: שער חליפין | Z1: שווי הוגן (בש"ח) | AA1: שיעור מנכסי אפיק ההשקעה | AB1: שיעור מסך נכסי ההשקעה
A2: 7891 | B2: 7892
A3: 7891 | B3: 7893
A4: 7891 | B4: 7894
A5: 7891 | B5: 7895
A6: 7891 | B6: 7896
A7: 7891 | B7: 7897
A8: 7891 | B8: 7898
A9: 7891 | B9: 7899
A10: 7891 | B10: 7900
A11: 7891 | B11: 7901
A12: 7891 | B12: 7902
A13: 11925 | B13: 11926
... A39: 11342 | B39: 11345

Sheet לא סחיר נגזרים אחרים
A1: מספר קופה/קרן/ח.פ. עבור חברת ביטוח | B1: מספר מסלול | C1: מאפיין עיקרי | D1: מספר עסקה (רגל 1) | E1: מטבע פעילות (רגל 1) | F1: שער חליפין | G1: ערך נקוב (רגל 1) | H1: שווי הוגן במטבע הנסחר (רגל 1) | I1: שיעור מנכסי אפיק ההשקעה (רגל 1) | J1: שיעור מסך נכסי ההשקעה (רגל 1) | K1: מספר עסקה (רגל 2) | L1: מטבע פעילות (רגל 2) | M1: שער חליפין | N1: ערך נקוב (רגל 2) | O1: שווי הוגן במטבע הנסחר (רגל 2) | P1: שיעור מנכסי ההשקעה (רגל 2) | Q1: שיעור מסך אפיק ההשקעה (רגל 2) | R1: שווי הוגן (נטו באלפי ש"ח) | S1: ישראל/חו"ל | T1: מדינה לפי חשיפה כלכלית | U1: סוג הנכס | V1: פקטור מוביל | W1: פקטור נוסף | X1: טיקר | Y1: בעל עניין/צד קשור | Z1: מועד ההתקשרות בעסקה | AA1: מועד סיום חוזי | AB1: תדירות Reset | AC1: סוג הסליקה | AD1: נספח התחשבנות בטחונות - CSA | AE1: גורם מצטט | AF1: ריבית עוגן | AG1: תקופת ריבית עוגן | AH1: שיעור ריבית עוגן | AI1: שער נכס הבסיס במועד ההתקשרות בעסקה | AJ1: שער הנגזר במועד ההתקשרות בעסקה | AK1: האם קיים קנס בגין יציאה מוקדמת | AL1: שיעור הקנס בגין יציאה מוקדמת | AM1: צד נגדי - Counterparty | AN1: שיעור מנכסי אפיק ההשקעה | AO1: שיעור מסך נכסי ההשקעה
A2: 7891 | B2: 7897 | C2: Funded Swap | D2: FW EUR 225 | E2: EUR | F2: 4.1524 | G2: -1330891.5 | H2: -6.8240126 | I2: -0.0014995524 | J2: -7.4709351e-07 | N2: 0 | R2: -28.33603 | S2: ישראל | T2: ישראל | U2: מט"ח | V2: אחר | W2: מט"ח/₪ | X2: EUR | Y2: לא | Z2: 45547 | AA2: 45573 | AB2: חודשי | AC2: No-delivery | AD2: לא | AE2: הצד הנגדי | AF2: ללא | AG2: ללא | AI2: 4.134 | AN2: -0.17098407 | AO2: -0.00031022311
A3: 7891 | B3: 7897 | C3: Funded Swap | D3: FW EUR 227 | E3: EUR | F3: 4.1524 | G3: -39143.87 | H3: -0.20070802 | I3: -4.4104872e-05 | J3: -2.1973532e-08 | N3: 0 | R3: -0.83342 | S3: ישראל | T3: ישראל | U3: מט"ח | V3: אחר | W3: מט"ח/₪ | X3: EUR | Y3: לא | Z3: 45547 | AA3: 45573 | AB3: חודשי | AC3: No-delivery | AD3: לא | AE3: הצד הנגדי | AF3: ללא | AG3: ללא | AI3: 4.134 | AN3: -0.0050289875 | AO3: -9.1242896e-06
A4: 7891 | B4: 7897 | C4: Funded Swap | D4: FW $ 260 | E4: USD | F4: 3.71 | G4: -140917.93 | H4: 1.3070863 | I4: 0.00028722754 | J4: 1.4309992e-07 | N4: 0 | R4: 4.84929 | S4: ישראל | T4: ישראל | U4: מט"ח | V4: אחר | W4: מט"ח/₪ | X4: USD | Y4: לא | Z4: 45547 | AA4: 45573 | AB4: חודשי | AC4: No-delivery | AD4: לא | AE4: הצד הנגדי | AF4: ללא | AG4: ללא | AI4: 3.753 | AN4: 0.029261379 | AO4: 5.309007e-05
A5: 7891 | B5: 7897 | C5: Funded Swap | D5: FW $ 262 | E5: USD | F5: 3.71 | G5: -1080370.8 | H5: 10.602976 | I5: 0.0023299661 | J5: 1.1608147e-06 | N5: 0 | R5: 39.33704 | S5: ישראל | T5: ישראל | U5: מט"ח | V5: אחר | W5: מט"ח/₪ | X5: USD | Y5: לא | Z5: 45547 | AA5: 45573 | AB5: חודשי | AC5: No-delivery | AD5: לא | AE5: הצד הנגדי | AF5: ללא | AG5: ללא | AI5: 3.753 | AN5: 0.23736589 | AO5: 0.00043066226
A6: 7891 | B6: 7897 | C6: Funded Swap | D6: FW $ 266 | E6: USD | F6: 3.71 | G6: -2145082 | H6: 40.621655 | I6: 0.0089264637 | J6: 4.4472624e-06 | N6: 0 | R6: 150.70634 | S6: ישראל | T6: ישראל | U6: מט"ח | V6: אחר | W6: מט"ח/₪ | X6: USD | Y6: לא | Z6: 45558 | AA6: 45575 | AB6: חודשי | AC6: No-delivery | AD6: לא | AE6: הצד הנגדי | AF6: ללא | AG6: ללא | AI6: 3.779 | AN6: 0.90938578 | AO6: 0.0016499343
A7: 11925 | B7: 11928 | C7: Funded Swap | D7: FW EUR 225 | E7: EUR | F7: 4.1524 | G7: -2006612.8 | H7: -10.288705 | I7: -0.001499551 | J7: -7.9500243e-07 | N7: 0 | R7: -42.72282 | S7: ישראל | T7: ישראל | U7: מט"ח | V7: אחר | W7: מט"ח/₪ | X7: EUR | Y7: לא | Z7: 45547 | AA7: 45573 | AB7: חודשי | AC7: No-delivery | AD7: לא | AE7: הצד הנגדי | AF7: ללא | AG7: ללא | AI7: 4.134 | AN7: -0.1709839 | AO7: -0.00033011681
A8: 11925 | B8: 11928 | C8: Funded Swap | D8: FW EUR 227 | E8: EUR | F8: 4.1524 | G8: -59018.02 | H8: -0.30261054 | I8: -4.4104668e-05 | J8: -2.3382545e-08 | N8: 0 | R8: -1.25656 | S8: ישראל | T8: ישראל | U8: מט"ח | V8: אחר | W8: מט"ח/₪ | X8: EUR | Y8: לא | Z8: 45547 | AA8: 45573 | AB8: חודשי | AC8: No-delivery | AD8: לא | AE8: הצד הנגדי | AF8: ללא | AG8: ללא | AI8: 4.134 | AN8: -0.0050289641 | AO8: -9.709368e-06
A9: 11925 | B9: 11928 | C9: Funded Swap | D9: FW $ 260 | E9: USD | F9: 3.71 | G9: -212464.88 | H9: 1.9707224 | I9: 0.00028722746 | J9: 1.522766e-07 | N9: 0 | R9: 7.31138 | S9: ישראל | T9: ישראל | U9: מט"ח | V9: אחר | W9: מט"ח/₪ | X9: USD | Y9: לא | Z9: 45547 | AA9: 45573 | AB9: חודשי | AC9: No-delivery | AD9: לא | AE9: הצד הנגדי | AF9: ללא | AG9: ללא | AI9: 3.753 | AN9: 0.02926137 | AO9: 5.6494619e-05
A10: 11925 | B10: 11928 | C10: Funded Swap | D10: FW $ 262 | E10: USD | F10: 3.71 | G10: -1628897.4 | H10: 15.986326 | I10: 0.0023299638 | J10: 1.2352544e-06 | N10: 0 | R10: 59.30927 | S10: ישראל | T10: ישראל | U10: מט"ח | V10: אחר | W10: מט"ח/₪ | X10: USD | Y10: לא | Z10: 45547 | AA10: 45573 | AB10: חודשי | AC10: No-delivery | AD10: לא | AE10: הצד הנגדי | AF10: ללא | AG10: ללא | AI10: 3.753 | AN10: 0.23736566 | AO10: 0.00045827937
A11: 11925 | B11: 11928 | C11: Funded Swap | D11: FW $ 266 | E11: USD | F11: 3.71 | G11: -3234188 | H11: 61.246175 | I11: 0.0089264644 | J11: 4.7324573e-06 | N11: 0 | R11: 227.22331 | S11: ישראל | T11: ישראל | U11: מט"ח | V11: אחר | W11: מט"ח/₪ | X11: USD | Y11: לא | Z11: 45558 | AA11: 45575 | AB11: חודשי | AC11: No-delivery | AD11: לא | AE11: הצד הנגדי | AF11: ללא | AG11: ללא | AI11: 3.779 | AN11: 0.90938584 | AO11: 0.0017557416
A12: 11939 | B12: 11942 | C12: Funded Swap | D12: FW EUR 225 | E12: EUR | F12: 4.1524 | G12: -5162495.7 | H12: -26.470181 | I12: -0.001499551 | J12: -9.532538e-07 | N12: 0 | R12: -109.91478 | S12: ישראל | T12: ישראל | U12: מט"ח | V12: אחר | W12: מט"ח/₪ | X12: EUR | Y12: לא | Z12: 45547 | AA12: 45573 | AB12: חודשי | AC12: No-delivery | AD12: לא | AE12: הצד הנגדי | AF12: ללא | AG12: ללא | AI12: 4.134 | AN12: -0.1709839 | AO12: -0.00039582911
A13: 11939 | B13: 11942 | C13: Funded Swap | D13: FW EUR 227 | E13: EUR | F13: 4.1524 | G13: -151838.1 | H13: -0.77854012 | I13: -4.4104745e-05 | J13: -2.803707e-08 | N13: 0 | R13: -3.23281 | S13: ישראל | T13: ישראל | U13: מט"ח | V13: אחר | W13: מט"ח/₪ | X13: EUR | Y13: לא | Z13: 45547 | AA13: 45573 | AB13: חודשי | AC13: No-delivery | AD13: לא | AE13: הצד הנגדי | AF13: ללא | AG13: ללא | AI13: 4.134 | AN13: -0.005028973 | AO13: -1.1642113e-05
... A16: 11939 | B16: 11942 | C16: Funded Swap | D16: FW $ 266 | E16: USD | F16: 3.71 | G16: -8320731 | H16: 157.5706 | I16: 0.008926465 | J16: 5.6744898e-06 | N16: 0 | R16: 584.58692 | S16: ישראל | T16: ישראל | U16: מט"ח | V16: אחר | W16: מט"ח/₪ | X16: USD | Y16: לא | Z16: 45558 | AA16: 45575 | AB16: חודשי | AC16: No-delivery | AD16: לא | AE16: הצד הנגדי | AF16: ללא | AG16: ללא | AI16: 3.779 | AN16: 0.9093859 | AO16: 0.0021052357
A17: 7891 | B17: 7892
A18: 7891 | B18: 7893
A19: 7891 | B19: 7894
A20: 7891 | B20: 7895
A21: 7891 | B21: 7896
A22: 7891 | B22: 7898
A23: 7891 | B23: 7899
A24: 7891 | B24: 7900
A25: 7891 | B25: 7901
A26: 7891 | B26: 7902
A27: 11925 | B27: 11926
A28: 11925 | B28: 11927
... A51: 11342 | B51: 11345

Sheet הלוואות
A1: מספר קופה/קרן/ח.פ. עבור חברת ביטוח | B1: מספר מסלול | C1: מספר מזהה לווה | D1: סוג מספר מזהה לווה | E1: שם הלוואה | F1: מספר הלוואה | G1: מאפיין עיקרי | H1: מאפיין הלוואות מתואמות עבור זכויות מקרקעין | I1: ישראל/חו"ל | J1: מדינה לפי חשיפה כלכלית | K1: ענף מסחר | L1: בעל עניין/צד קשור | M1: קונסורציום/ סינדיקציה | N1: מספר קונסורציום/ סינדיקציה | O1: תאריך העמדת הלוואה | P1: דירוג | Q1: שם מדרג | R1: דירוג הלוואה/המנפיק | S1: מטבע פעילות | T1: מח"מ | U1: סוג הריבית | V1: שיעור ריבית | W1: סוג הצמדה | X1: ריבית עוגן | Y1: שיעור תוספת/הפחתה לריבית העוגן | Z1: תשואה לפדיון | AA1: מועד פדיון | AB1: נחיתות חוזית | AC1: סוג בטוחה | AD1: שווי הבטוחות העומדות כנגד ההלוואה | AE1: שיעור הבטוחות מהחוב | AF1: מועד עדכון אחרון לשווי הבטוחות | AG1: זכות חזרה | AH1: מבנה לוח סילוקין | AI1: יעוד הלוואה | AJ1: זכות פירעון מוקדם | AK1: סוג גורם משערך | AL1: שם גורם משערך | AM1: תלות/אי-תלות המשערך | AN1: תאריך שערוך אחרון | AO1: תאריך אחרון בו נבחנה בפועל ירידת ערך | AP1: שיעור ריבית בגין אי-ניצול מסגרת האשראי | AQ1: ערך נקוב | AR1: שער הלוואה | AS1: שער חליפין | AT1: שווי הוגן (באלפי ש"ח) | AU1: שווי הוגן (במטבע הפעילות) | AV1: עלות מופחתת (באלפי ש"ח) | AW1: עלות מופחתת (במטבע הפעילות) | AX1: האם סווג כחוב בעייתי | AY1: השיטה שיושמה בדוח הכספי | AZ1: שיעור מנכסי אפיק ההשקעה | BA1: שיעור מסך נכסי ההשקעה
A2: 7891 | B2: 7897 | E2: הלוואה 1 | F2: 11017953 | G2: תאגיד | I2: ישראל | K2: שירותים פיננסיים | L2: לא | M2: לא | P2: NR | Q2: NR | R2: NR | S2: ILS | T2: 0 | U2: אחר | V2: 0 | Z2: 0 | AB2: החוב לא נחות | AJ2: כן | AK2: חברת ציטוט | AM2: אי-תלות | AN2: 45565 | AO2: 45565 | AQ2: 13017.11 | AR2: 100 | AS2: 1 | AT2: 13.01711 | AU2: 13.01711 | AY2: שווי הוגן | AZ2: 0.0019562306 | BA2: 0.00014251144
A3: 7891 | B3: 7897 | E3: הלוואה 2 | F3: 11020124 | G3: תאגיד | I3: ישראל | K3: שירותים פיננסיים | L3: לא | M3: לא | P3: NR | Q3: NR | R3: NR | S3: ILS | T3: 0 | U3: אחר | V3: 0 | Z3: 0 | AB3: החוב לא נחות | AJ3: כן | AK3: חברת ציטוט | AM3: אי-תלות | AN3: 45565 | AO3: 45565 | AQ3: -570772.61 | AR3: 100 | AS3: 1 | AT3: -570.77261 | AU3: -570.77261 | AY3: שווי הוגן | AZ3: -0.085776553 | BA3: -0.0062488236
A4: 7891 | B4: 7897 | E4: הלוואה 3 | F4: 11020128 | G4: תאגיד | I4: ישראל | K4: שירותים פיננסיים | L4: לא | M4: לא | P4: NR | Q4: NR | R4: NR | S4: ILS | T4: 0 | U4: אחר | V4: 0 | Z4: 0 | AB4: החוב לא נחות | AJ4: כן | AK4: חברת ציטוט | AM4: אי-תלות | AN4: 45565 | AO4: 45565 | AQ4: -313150.61 | AR4: 100 | AS4: 1 | AT4: -313.15061 | AU4: -313.15061 | AY4: שווי הוגן | AZ4: -0.047060738 | BA4: -0.0034283757
A5: 7891 | B5: 7897 | E5: הלוואה 4 | F5: 14041911 | G5: תאגיד | I5: ישראל | K5: שירותים פיננסיים | L5: לא | M5: לא | P5: NR | Q5: NR | R5: NR | S5: ILS | T5: 25.23 | U5: משתנה | V5: 0.045 | Z5: 0.0479 | AB5: החוב לא נחות | AJ5: כן | AK5: חברת ציטוט | AM5: אי-תלות | AN5: 45565 | AO5: 45565 | AQ5: 247516.89 | AR5: 102.87 | AS5: 1 | AT5: 254.62062 | AU5: 254.62062 | AY5: שווי הוגן | AZ5: 0.038264764 | BA5: 0.0027875888
A6: 7891 | B6: 7897 | E6: הלוואה 5 | F6: 24041901 | G6: תאגיד | I6: ישראל | K6: שירותים פיננסיים | L6: לא | M6: לא | P6: NR | Q6: NR | R6: NR | S6: ILS | T6: 0.89 | U6: קבועה | V6: 0.069 | Z6: 0.0618 | AB6: החוב לא נחות | AJ6: כן | AK6: חברת ציטוט | AM6: אי-תלות | AN6: 45565 | AO6: 45565 | AQ6: 3236895.5 | AR6: 98.98 | AS6: 1 | AT6: 3203.8792 | AU6: 3203.8792 | AY6: שווי הוגן | AZ6: 0.48148371 | BA6: 0.035076098
A7: 7891 | B7: 7897 | E7: הלוואה 6 | F7: 24041911 | G7: תאגיד | I7: ישראל | K7: שירותים פיננסיים | L7: לא | M7: לא | P7: NR | Q7: NR | R7: NR | S7: ILS | T7: 2.08 | U7: משתנה | V7: 0.062 | Z7: 0.0945 | AB7: החוב לא נחות | AJ7: כן | AK7: חברת ציטוט | AM7: אי-תלות | AN7: 45565 | AO7: 45565 | AQ7: 3666693.6 | AR7: 100.37 | AS7: 1 | AT7: 3680.2604 | AU7: 3680.2604 | AY7: שווי הוגן | AZ7: 0.55307498 | BA7: 0.040291523
A8: 7891 | B8: 7897 | E8: הלוואה 7 | F8: 34041901 | G8: תאגיד | I8: ישראל | K8: שירותים פיננסיים | L8: לא | M8: לא | P8: NR | Q8: NR | R8: NR | S8: ILS | T8: 12.63 | U8: משתנה | V8: 0.057 | Z8: 0.0965 | AB8: החוב לא נחות | AJ8: כן | AK8: חברת ציטוט | AM8: אי-תלות | AN8: 45565 | AO8: 45565 | AQ8: 173978.19 | AR8: 98.27 | AS8: 1 | AT8: 170.96837 | AU8: 170.96837 | AY8: שווי הוגן | AZ8: 0.02569338 | BA8: 0.0018717632
A9: 7891 | B9: 7897 | E9: הלוואה 8 | F9: 34041911 | G9: תאגיד | I9: ישראל | K9: שירותים פיננסיים | L9: לא | M9: לא | P9: NR | Q9: NR | R9: NR | S9: ILS | T9: 1.25 | U9: קבועה | V9: 0.053 | Z9: 0.0607 | AB9: החוב לא נחות | AJ9: כן | AK9: חברת ציטוט | AM9: אי-תלות | AN9: 45565 | AO9: 45565 | AQ9: 215918.77 | AR9: 99.74 | AS9: 1 | AT9: 215.35738 | AU9: 215.35738 | AY9: שווי הוגן | AZ9: 0.032364226 | BA9: 0.0023577345
A10: 11925 | B10: 11928 | E10: הלוואה 1 | F10: 11017953 | G10: תאגיד | I10: ישראל | K10: שירותים פיננסיים | L10: לא | M10: לא | P10: NR | Q10: NR | R10: NR | S10: ILS | T10: 0 | U10: אחר | V10: 0 | Z10: 0 | AB10: החוב לא נחות | AJ10: כן | AK10: חברת ציטוט | AM10: אי-תלות | AN10: 45565 | AO10: 45565 | AQ10: 19626.06 | AR10: 100 | AS10: 1 | AT10: 19.62606 | AU10: 19.62606 | AY10: שווי הוגן | AZ10: 0.001956218 | BA10: 0.00015164945
A11: 11925 | B11: 11928 | E11: הלוואה 2 | F11: 11020124 | G11: תאגיד | I11: ישראל | K11: שירותים פיננסיים | L11: לא | M11: לא | P11: NR | Q11: NR | R11: NR | S11: ILS | T11: 0 | U11: אחר | V11: 0 | Z11: 0 | AB11: החוב לא נחות | AJ11: כן | AK11: חברת ציטוט | AM11: אי-תלות | AN11: 45565 | AO11: 45565 | AQ11: -860566.59 | AR11: 100 | AS11: 1 | AT11: -860.56659 | AU11: -860.56659 | AY11: שווי הוגן | AZ11: -0.085776556 | BA11: -0.0066495493
A12: 11925 | B12: 11928 | E12: הלוואה 3 | F12: 11020128 | G12: תאגיד | I12: ישראל | K12: שירותים פיננסיים | L12: לא | M12: לא | P12: NR | Q12: NR | R12: NR | S12: ILS | T12: 0 | U12: אחר | V12: 0 | Z12: 0 | AB12: החוב לא נחות | AJ12: כן | AK12: חברת ציטוט | AM12: אי-תלות | AN12: 45565 | AO12: 45565 | AQ12: -472144.18 | AR12: 100 | AS12: 1 | AT12: -472.14418 | AU12: -472.14418 | AY12: שווי הוגן | AZ12: -0.047060741 | BA12: -0.0036482313
A13: 11925 | B13: 11928 | E13: הלוואה 4 | F13: 14041911 | G13: תאגיד | I13: ישראל | K13: שירותים פיננסיים | L13: לא | M13: לא | P13: NR | Q13: NR | R13: NR | S13: ILS | T13: 25.23 | U13: משתנה | V13: 0.045 | Z13: 0.0479 | AB13: החוב לא נחות | AJ13: כן | AK13: חברת ציטוט | AM13: אי-תלות | AN13: 45565 | AO13: 45565 | AQ13: 373187.01 | AR13: 102.87 | AS13: 1 | AT13: 383.89748 | AU13: 383.89748 | AY13: שווי הוגן | AZ13: 0.038264794 | BA13: 0.0029663541
... A25: 11939 | B25: 11942 | E25: הלוואה 8 | F25: 34041911 | G25: תאגיד | I25: ישראל | K25: שירותים פיננסיים | L25: לא | M25: לא | P25: NR | Q25: NR | R25: NR | S25: ILS | T25: 1.25 | U25: קבועה | V25: 0.053 | Z25: 0.0607 | AB25: החוב לא נחות | AJ25: כן | AK25: חברת ציטוט | AM25: אי-תלות | AN25: 45565 | AO25: 45565 | AQ25: 837542.27 | AR25: 99.74 | AS25: 1 | AT25: 835.36466 | AU25: 835.36466 | AY25: שווי הוגן | AZ25: 0.032364135 | BA25: 0.0030083456
A26: 7891 | B26: 7892
A27: 7891 | B27: 7893
A28: 7891 | B28: 7894
A29: 7891 | B29: 7895
A30: 7891 | B30: 7896
A31: 7891 | B31: 7898
A32: 7891 | B32: 7899
A33: 7891 | B33: 7900
A34: 7891 | B34: 7901
A35: 7891 | B35: 7902
A36: 11925 | B36: 11926
A37: 11925 | B37: 11927
... A60: 11342 | B60: 11345

Sheet לא סחיר מוצרים מובנים
A1: מספר קופה/קרן/ח.פ. עבור חברת ביטוח | B1: מספר מסלול | C1: שם מנפיק | D1: מספר מנפיק | E1: סוג מספר מזהה מנפיק | F1: שם נייר ערך | G1: מספר נייר ערך | H1: סוג מספר נייר ערך | I1: מאפיין עיקרי | J1: ישראל/חו"ל | K1: מדינה לפי חשיפה כלכלית | L1: בעל עניין/צד קשור | M1: נכס בסיס | N1: תאריך רכישה | O1: דירוג | P1: שם מדרג | Q1: דירוג נייר הערך/המנפיק | R1: מטבע פעילות | S1: מח"מ | T1: שיעור ריבית | U1: תשואה לפדיון | V1: סוג גורם משערך | W1: תלות/אי-תלות המשערך | X1: תאריך שערוך אחרון | Y1: ערך נקוב (יחידות) | Z1: שער חליפין | AA1: שער נייר הערך | AB1: שווי הוגן (באלפי ש"ח) | AC1: שיעור מנכסי אפיק ההשקעה | AD1: שיעור מסך נכסי ההשקעה
A2: 7891 | B2: 7892
A3: 7891 | B3: 7893
A4: 7891 | B4: 7894
A5: 7891 | B5: 7895
A6: 7891 | B6: 7896
A7: 7891 | B7: 7897
A8: 7891 | B8: 7898
A9: 7891 | B9: 7899
A10: 7891 | B10: 7900
A11: 7891 | B11: 7901
A12: 7891 | B12: 7902
A13: 11925 | B13: 11926
... A39: 11342 | B39: 11345

Sheet פיקדונות מעל 3 חודשים
A1: מספר קופה/קרן/ח.פ. עבור חברת ביטוח | B1: מספר מסלול | C1: שם הבנק | D1: מספר מזהה בנק | E1: סוג מספר מזהה בנק | F1: מאפיין עיקרי | G1: תאריך פקיעת פיקדון | H1: ישראל/חו"ל | I1: מדינה לפי חשיפה כלכלית | J1: בעל עניין/צד קשור | K1: דירוג הבנק | L1: שם מדרג | M1: מטבע פעילות | N1: מח"מ | O1: שיעור ריבית | P1: תשואה לפדיון | Q1: שווי מטבעי | R1: שער חליפין | S1: שער פיקדון | T1: שווי הוגן (באלפי ש"ח) | U1: שיעור מנכסי אפיק ההשקעה | V1: שיעור מסך נכסי ההשקעה
A2: 7891 | B2: 7892
A3: 7891 | B3: 7893
A4: 7891 | B4: 7894
A5: 7891 | B5: 7895
A6: 7891 | B6: 7896
A7: 7891 | B7: 7897
A8: 7891 | B8: 7898
A9: 7891 | B9: 7899
A10: 7891 | B10: 7900
A11: 7891 | B11: 7901
A12: 7891 | B12: 7902
A13: 11925 | B13: 11926
... A39: 11342 | B39: 11345

Sheet זכויות מקרקעין
A1: מספר קופה/קרן/ח.פ. עבור חברת ביטוח | B1: מספר מסלול | C1: שם הנכס | D1: מאפיין עיקרי | E1: מדינת מיקום נדל"ן | F1: בעל עניין/צד קשור | G1: תאריך רכישה | H1: שימוש עיקרי בנכס | I1: מחזור חיי הנכס | J1: כתובת הנכס | K1: שיעור תשואה בפועל במהלך הרבעון | L1: השיטה שבאמצעותה נקבע שווי הנכס | M1: סוג גורם משערך | N1: שם גורם משערך | O1: תלות/אי-תלות המשערך | P1: תאריך שערוך אחרון | Q1: מטבע פעילות | R1: שווי הוגן (במטבע הפעילות) | S1: שווי הוגן (באלפי ש"ח) | T1: עלות מופחתת (באלפי ש"ח) | U1: עלות מופחתת (במטבע הפעילות) | V1: השיטה שיושמה בדוח הכספי | W1: שיעור מנכסי אפיק ההשקעה | X1: שיעור מסך נכסי ההשקעה
A2: 7891 | B2: 7892
A3: 7891 | B3: 7893
A4: 7891 | B4: 7894
A5: 7891 | B5: 7895
A6: 7891 | B6: 7896
A7: 7891 | B7: 7897
A8: 7891 | B8: 7898
A9: 7891 | B9: 7899
A10: 7891 | B10: 7900
A11: 7891 | B11: 7901
A12: 7891 | B12: 7902
A13: 11925 | B13: 11926
... A39: 11342 | B39: 11345

Sheet השקעה בחברות מוחזקות
A1: מספר קופה/קרן/ח.פ. עבור חברת ביטוח | B1: מספר מסלול | C1: שם מנפיק | D1: מספר מנפיק | E1: סוג מספר מזהה מנפיק | F1: שם נייר ערך | G1: מספר נייר ערך | H1: סוג מספר נייר ערך | I1: מאפיין עיקרי | J1: ישראל/חו"ל | K1: מדינה לפי חשיפה כלכלית | L1: ענף מסחר | M1: בעל עניין/צד קשור | N1: מטבע פעילות | O1: סוג גורם משערך | P1: תלות/אי-תלות המשערך | Q1: תאריך שערוך אחרון | R1: תאריך אחרון בו נבחנה בפועל ירידת ערך | S1: שיעור אחזקה באמצעי שליטה | T1: שווי מאזני (באלפי ש"ח) | U1: שווי הוגן (באלפי ש"ח) | V1: שיעור מנכסי אפיק ההשקעה | W1: שיעור מסך נכסי ההשקעה
A2: 7891 | B2: 7892
A3: 7891 | B3: 7893
A4: 7891 | B4: 7894
A5: 7891 | B5: 7895
A6: 7891 | B6: 7896
A7: 7891 | B7: 7897
A8: 7891 | B8: 7898
A9: 7891 | B9: 7899
A10: 7891 | B10: 7900
A11: 7891 | B11: 7901
A12: 7891 | B12: 7902
A13: 11925 | B13: 11926
... A39: 11342 | B39: 11345

Sheet נכסים אחרים
A1: מספר קופה/קרן/ח.פ. עבור חברת ביטוח | B1: מספר מסלול | C1: שם הנכס האחר | D1: מספר הנכס האחר | E1: מאפיין עיקרי | F1: ישראל/חו"ל | G1: מדינה לפי חשיפה כלכלית | H1: בעל עניין/צד קשור | I1: תאריך עסקה | J1: מטבע פעילות | K1: תאריך שערוך אחרון | L1: שווי מטבעי | M1: שער חליפין | N1: שווי הוגן (באלפי ש"ח) | O1: עלות מופחתת (באלפי ש"ח) | P1: השיטה שיושמה בדוח הכספי | Q1: שיעור מנכסי אפיק ההשקעה | R1: שיעור מסך נכסי ההשקעה
A2: 7891 | B2: 7892
A3: 7891 | B3: 7893
A4: 7891 | B4: 7894
A5: 7891 | B5: 7895
A6: 7891 | B6: 7896
A7: 7891 | B7: 7897
A8: 7891 | B8: 7898
A9: 7891 | B9: 7899
A10: 7891 | B10: 7900
A11: 7891 | B11: 7901
A12: 7891 | B12: 7902
A13: 11925 | B13: 11926
... A39: 11342 | B39: 11345

Sheet מסגרות אשראי
A1: מספר קופה/קרן/ח.פ. עבור חברת ביטוח | B1: מספר מסלול | C1: מספר מזהה לווה | D1: סוג מספר מזהה לווה | E1: שם הלוואה | F1: מספר הלוואה | G1: תאריך העמדת מסגרת אשראי | H1: ישראל/חו"ל | I1: מדינה לפי חשיפה כלכלית | J1: בעל עניין/צד קשור | K1: דירוג | L1: שם מדרג | M1: דירוג הלוואה/המנפיק | N1: מטבע פעילות | O1: שער חליפין | P1: שיעור ריבית | Q1: סוג הריבית | R1: סכום מסגרת האשראי הראשוני (במטבע הפעילות) | S1: סכום מסגרת האשראי הראשוני (באלפי ש"ח) | T1: שיעור יתרת מסגרת אשראי
A2: 7891 | B2: 7892
A3: 7891 | B3: 7893
A4: 7891 | B4: 7894
A5: 7891 | B5: 7895
A6: 7891 | B6: 7896
A7: 7891 | B7: 7897
A8: 7891 | B8: 7898
A9: 7891 | B9: 7899
A10: 7891 | B10: 7900
A11: 7891 | B11: 7901
A12: 7891 | B12: 7902
A13: 11925 | B13: 11926
... A39: 11342 | B39: 11345

Sheet יתרות התחייבות להשקעה
A1: מספר קופה/קרן/ח.פ. עבור חברת ביטוח | B1: מספר מסלול | C1: מאפיין עיקרי | D1: שם שותף כללי קרן השקעות | E1: מספר מזהה שותף כללי קרן השקעות | F1: סוג מספר מזהה שותף כללי קרן השקעות | G1: שם קרן השקעה | H1: מספר מזהה קרן השקעה | I1: סוג מספר מזהה קרן השקעות | J1: מטבע פעילות | K1: תאריך העמדת התחייבות לקרן השקעה | L1: סכום המחויבות הראשוני (במטבע הדיווח של קרן ההשקעה) | M1: סכום המחויבות הראשוני (באלפי ש"ח) | N1: יתרת המחויבות לתקופת הדיווח (במטבע הדיווח של קרן ההשקעה) | O1: יתרת המחויבות לתקופת הדיווח (באלפי ש"ח) | P1: שיעור יתרת המחויבות | Q1: תאריך פקיעת מחויבות להשקעה
A2: 7891 | B2: 7892
A3: 7891 | B3: 7893
A4: 7891 | B4: 7894
A5: 7891 | B5: 7895
A6: 7891 | B6: 7896
A7: 7891 | B7: 7897
A8: 7891 | B8: 7898
A9: 7891 | B9: 7899
A10: 7891 | B10: 7900
A11: 7891 | B11: 7901
A12: 7891 | B12: 7902
A13: 11925 | B13: 11926
... A39: 11342 | B39: 11345

Sheet אפשרויות בחירה
A1: שם גיליון (רלוונטי לגיליונות עם עמודה "מאפיין עיקרי") | B1: שם עמודה | C1: אפשרות בחירה | D1: הערות והסברים
B2: ישראל/חו"ל | C2: ישראל
C3: חו"ל
B4: מדינה לפי חשיפה כלכלית; מדינת התאגדות קרן השקעה, מיקום משרד השותף הכללי, מדינת מיקום נדל"ן | C4: ישראל
C5: אוסטריה
C6: אוסטרליה
C7: אזור תעלת פנמה
C8: אזרביג'אן
C9: איחוד האמירויות הערביות
C10: איטליה
C11: איי הבתולה הבריטיים | E11: נוסף במסגרת עדכון הרשימה
C12: איי הבתולה של ארצות הברית | E12: נוסף במסגרת עדכון הרשימה
C13: איי סיישל
C14: איי קיימן
C15: איי שלמה הבריטיים
C16: איסלנד
C17: אירלנד
C18: אנדורה
C19: אסטוניה
C20: ארגנטינה
C21: ארה"ב
C22: אתיופיה
C23: בהמס
C24: בולגריה
... C35: גרמניה
C36: ג'רזי (Jersey) | E36: נוסף במסגרת עדכון הרשימה
C37: גרנזי (Guernsey) | E37: נוסף במסגרת עדכון הרשימה
C38: דנמרק
C39: דרום אפריקה
C40: דרום קוריאה | E40: נוסף במסגרת עדכון הרשימה
C41: הודו
C42: הולנד
C43: הונג קונג
C44: הונגריה
C45: הונדורס
C46: טייוואן | E46: נוסף במסגרת עדכון הרשימה
C47: יוון
C48: יפן
C49: ירדן
C50: לוכסמבורג
C51: לטביה
C52: ליטא
C53: ליכטנשטיין
C54: מאוריציוס
C55: מולדובה
C56: מונקו
C57: מלדיבים
C58: מלטה
... C62: מרוקו
C63: נורבגיה | E63: נוסף במסגרת עדכון הרשימה
C64: ניו זילנד
C65: סין
C66: סינגפור
C67: סלובניה
C68: סלובקיה
C69: ספרד
C70: סרביה
C71: ערב הסעודית
C72: פולין
C73: פורטוגל
C74: פינלנד
C75: פנמה
... C93: גלובלי
C94: Emerging Markets - Americas | D94: שווקים מתעוררים לפי הגדרת MSCI | E94: נוסף במסגרת עדכון הרשימה
C95: Emerging Markets - Euope, Middle East & Africa | D95: לפי הגדרת MSCI | E95: נוסף במסגרת עדכון הרשימה
C96: Emerging Markets - Asia | D96: לפי הגדרת MSCI | E96: נוסף במסגרת עדכון הרשימה
C97: Developed Markets - Americas | D97: לפי הגדרת MSCI | E97: נוסף במסגרת עדכון הרשימה
C98: Developed Markets - Europe | D98: לפי הגדרת MSCI | E98: נוסף במסגרת עדכון הרשימה
C99: Developed Markets - Pacific | D99: לפי הגדרת MSCI | E99: נוסף במסגרת עדכון הרשימה
C100: Frontier Markets - Euope | D100: לפי הגדרת MSCI | E100: נוסף במסגרת עדכון הרשימה
C101: Frontier Markets - Africa | D101: לפי הגדרת MSCI | E101: נוסף במסגרת עדכון הרשימה
C102: Frontier Markets - Middle East | D102: לפי הגדרת MSCI | E102: נוסף במסגרת עדכון הרשימה
C103: Frontier Markets - Asia | D103: לפי הגדרת MSCI | E103: נוסף במסגרת עדכון הרשימה
B104: סוג מספר מזהה מנפיק | C104: ח.פ.
C105: מספר מנפיק
C106: מספר שותפות
C107: מספר תאגיד או שותפות בחו"ל
C108: פנימי
C109: LEI
C110: אחר
B111: סוג מספר מזהה בנק | C111: ח.פ.
C112: סימול בנק
C113: SWIFT
B114: סוג מספר מזהה מנהל קרן השקעות | C114: ח.פ.
C115: מספר שותפות
C116: מספר תאגיד או שותפות בחו"ל
C117: LEI
B118: סוג מספר מזהה לווה | C118: ח.פ.
C119: מרשם
C120: מספר תאגיד או שותפות בחו"ל
C121: פנימי
C122: מספר שותפות
C123: ת"ז
C124: דרכון
C125: LEI
C126: אחר
B127: סוג מספר נייר ערך | C127: ISIN
C128: OCC
C129: FIGI
C130: טיקר
...

Sheet מיפוי סעיפים
A1: שם גיליון | B1: שם סעיף | C1: מספר סעיף | D1: מידע שניתן לדווח רק לרשות
A2: מזומנים ושווי מזומנים | B2: מספר קופה/קרן/ח.פ. עבור חברת ביטוח | C2: 5.1
A3: מזומנים ושווי מזומנים | B3: מספר מסלול | C3: 5.2
A4: מזומנים ושווי מזומנים | B4: שם הבנק | C4: 5.4
A5: מזומנים ושווי מזומנים | B5: מספר מזהה בנק | C5: 5.7
A6: מזומנים ושווי מזומנים | B6: סוג מספר מזהה בנק | C6: 5.11
A7: מזומנים ושווי מזומנים | B7: מאפיין עיקרי | C7: 5.26
A8: מזומנים ושווי מזומנים | B8: ישראל/חו"ל | C8: 5.27
A9: מזומנים ושווי מזומנים | B9: בעל עניין/צד קשור | C9: 5.36
A10: מזומנים ושווי מזומנים | B10: דירוג הבנק | C10: 5.5
A11: מזומנים ושווי מזומנים | B11: שם מדרג | C11: 5.51
A12: מזומנים ושווי מזומנים | B12: מטבע פעילות | C12: 5.53
A13: מזומנים ושווי מזומנים | B13: שווי מטבעי | C13: 5.59
A14: מזומנים ושווי מזומנים | B14: שער חליפין | C14: 5.54
A15: מזומנים ושווי מזומנים | B15: שיעור ריבית | C15: 5.7 | D15: ü
A16: מזומנים ושווי מזומנים | B16: שווי הוגן (באלפי ש"ח) | C16: 5.63
A17: מזומנים ושווי מזומנים | B17: שיעור מנכסי אפיק ההשקעה | C17: 5.47
A18: מזומנים ושווי מזומנים | B18: שיעור מסך נכסי ההשקעה | C18: 5.48
A19: מזומנים ושווי מזומנים
A20: איגרות חוב ממשלתיות | B20: מספר קופה/קרן/ח.פ. עבור חברת ביטוח | C20: 5.1
A21: איגרות חוב ממשלתיות | B21: מספר מסלול | C21: 5.2
A22: איגרות חוב ממשלתיות | B22: שם מנפיק | C22: 5.3
A23: איגרות חוב ממשלתיות | B23: שם נייר ערך | C23: 5.14
A24: איגרות חוב ממשלתיות | B24: מספר נייר ערך | C24: 5.19
A25: איגרות חוב ממשלתיות | B25: מאפיין עיקרי | C25: 5.26
A26: איגרות חוב ממשלתיות | B26: ישראל/חו"ל | C26: 5.27
A27: איגרות חוב ממשלתיות | B27: מדינה לפי חשיפה כלכלית | C27: 5.28
A28: איגרות חוב ממשלתיות | B28: זירת מסחר | C28: 5.3
A29: איגרות חוב ממשלתיות | B29: דירוג | C29: 5.49
A30: איגרות חוב ממשלתיות | B30: שם מדרג | C30: 5.51
A31: איגרות חוב ממשלתיות | B31: מטבע פעילות | C31: 5.53
... A45: איגרות חוב ממשלתיות | B45: שיעור מסך נכסי ההשקעה | C45: 5.48
A46: איגרות חוב ממשלתיות
A47: ניירות ערך מסחריים | B47: מספר קופה/קרן/ח.פ. עבור חברת ביטוח | C47: 5.1
A48: ניירות ערך מסחריים | B48: מספר מסלול | C48: 5.2
A49: ניירות ערך מסחריים | B49: שם מנפיק | C49: 5.3
A50: ניירות ערך מסחריים | B50: מספר מנפיק | C50: 5.6
A51: ניירות ערך מסחריים | B51: סוג מספר מזהה מנפיק | C51: 5.1
A52: ניירות ערך מסחריים | B52: שם נייר ערך | C52: 5.14
A53: ניירות ערך מסחריים | B53: מספר נייר ערך | C53: 5.19
A54: ניירות ערך מסחריים | B54: סוג מספר נייר ערך | C54: 5.24
A55: ניירות ערך מסחריים | B55: מאפיין עיקרי | C55: 5.26
A56: ניירות ערך מסחריים | B56: ישראל/חו"ל | C56: 5.27
A57: ניירות ערך מסחריים | B57: מדינה לפי חשיפה כלכלית | C57: 5.28
A58: ניירות ערך מסחריים | B58: זירת מסחר | C58: 5.3
... A70: ניירות ערך מסחריים | B70: נחיתות חוזית | C70: 5.76
A71: ניירות ערך מסחריים | B71: האם סווג כחוב בעייתי | C71: 5.89 | D71: ü
A72: ניירות ערך מסחריים | B72: ערך נקוב (יחידות) | C72: 5.58
A73: ניירות ערך מסחריים | B73: סכום לקבל (במטבע הפעילות) | C73: 5.62
A74: ניירות ערך מסחריים | B74: שער חליפין | C74: 5.54
A75: ניירות ערך מסחריים | B75: שער נייר הערך | C75: 5.55
A76: ניירות ערך מסחריים | B76: שווי הוגן (באלפי ש"ח) | C76: 5.63
A77: ניירות ערך מסחריים | B77: עלות מופחתת (באלפי ש"ח) | C77: 5.65
A78: ניירות ערך מסחריים | B78: עלות מופחתת (במטבע הפעילות) | C78: 5.66
A79: ניירות ערך מסחריים | B79: השיטה שיושמה בדוח הכספי | C79: 5.68
A80: ניירות ערך מסחריים | B80: שיעור מערך נקוב מונפק | C80: 5.45
A81: ניירות ערך מסחריים | B81: שיעור מנכסי אפיק ההשקעה | C81: 5.47
A82: ניירות ערך מסחריים | B82: שיעור מסך נכסי ההשקעה | C82: 5.48
A83: ניירות ערך מסחריים
A84: איגרות חוב | B84: מספר קופה/קרן/ח.פ. עבור חברת ביטוח | C84: 5.1
A85: איגרות חוב | B85: מספר מסלול | C85: 5.2
A86: איגרות חוב | B86: שם מנפיק | C86: 5.3
A87: איגרות חוב | B87: מספר מנפיק | C87: 5.6
A88: איגרות חוב | B88: סוג מספר מזהה מנפיק | C88: 5.1
A89: איגרות חוב | B89: שם נייר ערך | C89: 5.14
A90: איגרות חוב | B90: מספר נייר ערך | C90: 5.19
A91: איגרות חוב | B91: סוג מספר נייר ערך | C91: 5.24
A92: איגרות חוב | B92: מאפיין עיקרי | C92: 5.26
A93: איגרות חוב | B93: ישראל/חו"ל | C93: 5.27
A94: איגרות חוב | B94: מדינה לפי חשיפה כלכלית | C94: 5.28
A95: איגרות חוב | B95: סטאטוס סחירות | C95: 5.29
... A107: איגרות חוב | B107: נחיתות חוזית | C107: 5.76
A108: איגרות חוב | B108: האם סווג כחוב בעייתי | C108: 5.89 | D108: ü
A109: איגרות חוב | B109: ערך נקוב (יחידות) | C109: 5.58
A110: איגרות חוב | B110: סכום לקבל (במטבע הפעילות) | C110: 5.62
A111: איגרות חוב | B111: שער חליפין | C111: 5.54
A112: איגרות חוב | B112: שער נייר הערך | C112: 5.55
A113: איגרות חוב | B113: עלות מופחתת (באלפי ש"ח) | C113: 5.65
A114: איגרות חוב | B114: עלות מופחתת (במטבע הפעילות) | C114: 5.66
A115: איגרות חוב | B115: השיטה שיושמה בדוח הכספי | C115: 5.68
A116: איגרות חוב | B116: שיעור מערך נקוב מונפק | C116: 5.45
A117: איגרות חוב | B117: שיעור מנכסי אפיק ההשקעה | C117: 5.47
A118: איגרות חוב | B118: שיעור מסך נכסי ההשקעה | C118: 5.48
A119: איגרות חוב
A120: מניות, מב"כ ויה"ש | B120: מספר קופה/קרן/ח.פ. עבור חברת ביטוח | C120: 5.1
A121: מניות, מב"כ ויה"ש | B121: מספר מסלול | C121: 5.2
A122: מניות, מב"כ ויה"ש | B122: שם מנפיק | C122: 5.3
A123: מניות, מב"כ ויה"ש | B123: מספר מנפיק | C123: 5.6
A124: מניות, מב"כ ויה"ש | B124: סוג מספר מזהה מנפיק | C124: 5.1
A125: מניות, מב"כ ויה"ש | B125: שם נייר ערך | C125: 5.14
A126: מניות, מב"כ ויה"ש | B126: מספר נייר ערך | C126: 5.19
A127: מניות, מב"כ ויה"ש | B127: סוג מספר נייר ערך | C127: 5.24
A128: מניות, מב"כ ויה"ש | B128: מאפיין עיקרי | C128: 5.26
A129: מניות, מב"כ ויה"ש | B129: ישראל/חו"ל | C129: 5.27
A130: מניות, מב"כ ויה"ש | B130: מדינה לפי חשיפה כלכלית | C130: 5.28
A131: מניות, מב"כ ויה"ש | B131: סטאטוס סחירות | C131: 5.29
... A143: מניות, מב"כ ויה"ש | B143: שיעור מסך נכסי ההשקעה | C143: 5.48
A144: מניות, מב"כ ויה"ש
A145: קרנות סל | B145: מספר קופה/קרן/ח.פ. עבור חברת ביטוח | C145: 5.1
A146: קרנות סל | B146: מספר מסלול | C146: 5.2
...

Sheet File Name Info
A2: סוג קובץ
A3: נכסי מבוטחים - חברת ביטוח | B3: in
A4: נכסי עמיתים - קופות גמל | B4: gm
A5: נכסי עמיתים - קרנות פנסיה | B5: pn
A6: נכסי אפיק השקעה מובטח תשואה | B6: ca
A7: נכסי נוסטרו - חברת ביטוח | B7: ni
A8: נכסי נוסטרו - חברה מנהלת | B8: nf
A10: יעוד הקובץ
A11: לממונה
A12: לציבור | B12: p
A15: רבעון
A16: 01
A17: 02
A18: 03
A19: 04
A21: שנה
A22: 2022 | B22: 22
A23: 2023 | B23: 23
A24: 2024 | B24: 24
A25: 2025 | B25: 25
A26: 2026 | B26: 26
A27: 2027 | B27: 27
A28: 2028 | B28: 28
A29: 2029 | B29: 29
A30: 2030 | B30: 30
A31: 2031 | B31: 31
A34: שם גוף מוסדי | B34: ח.פ.
A35: אי. אם. איי - עזר חברה לביטוח משכנתאות בע"מ | B35: 512310509
A36: איי. די. איי. חברה לביטוח בע"מ | B36: 513910703
A37: איי.אי.ג'י חברה לביטוח בע"מ | B37: 512304882
A38: איילון חברה לביטוח בע"מ | B38: 520030677
A39: אינפיניטי השתלמות, גמל ופנסיה בע"מ | B39: 513621110
A40: אלטשולר שחם גמל ופנסיה בע"מ | B40: 513173393
A41: אנליסט קופות גמל בע"מ | B41: 511880460
A42: ארם גמולים - חברה לניהול קופות גמל בע''מ | B42: 510773922
A43: אשרא - החברה הישראלית לביטוח יצוא בע"מ | B43: 520021916
A44: ב.ס.ס.ח. - החברה הישראלית לביטוח אשראי בע"מ | B44: 520044025
A45: ביטוח חקלאי אגודה מרכזית בע"מ | B45: 570003152
A46: גילעד גימלאות לעובדים דתיים בע"מ | B46: 520023094
... A121: תגמולים של עובדים בעירית ת"א-יפו א.ש. בע"מ | B121: 570002618
