Workbook
Name Additional_Factor: 'אפשרויות בחירה'!$C$701:$C$850
Name Amoritization: 'אפשרויות בחירה'!$C$546:$C$550
Name Capsule: 'אפשרויות בחירה'!$C$926:$C$928
Name Company_Name: 'File Name Info'!$A$34:$A$120
Name Company_Name_ID: 'File Name Info'!$A$34:$B$120
Name Consortium: 'אפשרויות בחירה'!$C$514:$C$515
Name Country_list: 'אפשרויות בחירה'!$C$4:$C$85
Name Country_list_funds: 'אפשרויות בחירה'!$C$4:$C$103
Name CSA: 'אפשרויות בחירה'!$C$688:$C$689
Name Delivery: 'אפשרויות בחירה'!$C$666:$C$667
Name Dependence_Independence: 'אפשרויות בחירה'!$C$654:$C$655
Name Duration_Underlying_Interest_Rate: 'אפשרויות בחירה'!$C$680:$C$687
Name File_Type: 'File Name Info'!$A$10:$A$12
Name Full_File_Type: 'File Name Info'!$A$11:$B$13
Name Full_Type: 'File Name Info'!$A$2:$B$8
Name Full_Type_Nostro: 'File Name Info'!$A$3:$B$6
Name Full_Year: 'File Name Info'!$A$22:$B$31
Name Fund_Strategy: 'אפשרויות בחירה'!$C$597:$C$621
Name Fund_type: 'אפשרויות בחירה'!$C$328:$C$498
Name Holding_interest: 'אפשרויות בחירה'!$C$146:$C$147
Name In_the_books: 'אפשרויות בחירה'!$C$656:$C$657
Name Industry_Sector: 'אפשרויות בחירה'!$C$1129:$C$1245
Name Industry_sector_all: 'אפשרויות בחירה'!$C$202:$C$327
Name Industry_sectors: 'אפשרויות בחירה'!$C$202:$C$327
Name israel_abroad: 'אפשרויות בחירה'!$C$2:$C$3
Name Issuer_Number_Banks: 'אפשרויות בחירה'!$C$111:$C$113
Name Issuer_Number_Fund: 'אפשרויות בחירה'!$C$114:$C$117
Name issuer_number_loan: 'אפשרויות בחירה'!$C$118:$C$126
Name Issuer_Number_Type: 'אפשרויות בחירה'!$C$104:$C$110
Name Issuer_Number_Type_2: 'אפשרויות בחירה'!$C$1076:$C$1079
Name Issuer_Number_Type_3: 'אפשרויות בחירה'!$C$1081:$C$1085
Name Issuer_Number_Type_V2: 'אפשרויות בחירה'!$C$104:$C$110
Name Issuer_Type_TFunds: 'אפשרויות בחירה'!$C$1087:$C$1089
Name Leading_factor: 'אפשרויות בחירה'!$C$692:$C$700
Name Linked_Type: 'אפשרויות בחירה'!$C$516:$C$519
Name other_investments: 'אפשרויות בחירה'!$C$1000:$C$1033
Name Penalty: 'אפשרויות בחירה'!$C$851:$C$852
Name QTR: 'File Name Info'!$A$15:$A$19
Name Rating_Agency: 'אפשרויות בחירה'!$C$188:$C$201
Name real_estate_lifestage: 'אפשרויות בחירה'!$C$634:$C$642
Name real_estate_loans: 'אפשרויות בחירה'!$C$553:$C$591
Name Real_Estate_Main_Use: 'אפשרויות בחירה'!$C$622:$C$633
Name Recourse_Nonrecourse: 'אפשרויות בחירה'!$C$544:$C$545
Name Repayment_Rights: 'אפשרויות בחירה'!$C$551:$C$552
Name Reset_frequency: 'אפשרויות בחירה'!$C$658:$C$665
Name Security_ID_Number_Type: 'אפשרויות בחירה'!$C$1113:$C$1116
Name Security_Number_Loans: 'אפשרויות בחירה'!$C$131
Name Stock_Exchange: 'אפשרויות בחירה'!$C$1283:$C$1315
Name Stock_Exchange_Gov_Bonds: 'אפשרויות בחירה'!$C$148:$C$181
Name Subordination_Risk: 'אפשרויות בחירה'!$C$186:$C$187
Name Tradeable_Status: 'אפשרויות בחירה'!$C$1272:$C$1281
Name Tradeable_Status_All: 'אפשרויות בחירה'!$C$135:$C$145
Name tradeable_status_bonds: 'אפשרויות בחירה'!$C$1248:$C$1253
Name tradeable_status_funds: 'אפשרויות בחירה'!$C$1118:$C$1119
Name tradeable_status_stock: 'אפשרויות בחירה'!$C$1255:$C$1259
Name Tradeable_Status_v2: 'אפשרויות בחירה'!$C$1121:$C$1126
Name tradeable_status_warrants: 'אפשרויות בחירה'!$C$1261:$C$1265
Name tradeable_status_warrants_v2: 'אפשרויות בחירה'!$C$1267:$C$1269
Name Transaction: 'אפשרויות בחירה'!$C$643:$C$646
Name Type: 'File Name Info'!$A$2:$A$8

Sheet עמוד פתיחה
A1: קובץ דיווח עבור רשימת נכסים ברמת הנכס הבודד (חוזר גופים מוסדיים 2015-9-14)
A3: יש לבחור תחום: | D3: נכסי מבוטחים - חברת ביטוח
A5: האם מדובר בקובץ לממומנה או לציבור: | D5: לציבור
A7: יש לבחור את רבעון הדיווח: | D7: 03
A9: יש לבחור את שנת הדיווח: | D9: 2024
A11: יש לבחור את הגוף המוסדי: | D11: הכשרה חברה לביטוח בע"מ
A13: ח.פ. הגוף המוסדי: | D13: =IFERROR(VLOOKUP(D11,'File Name Info'!A35:B121,2,0),"תא מחושב") -> 520042177
A15: שם קובץ לשמירה | D15: =IF(D5="לממונה",CONCATENATE(D13, "_",VLOOKUP(D3,Full_Type,2,0),"_",D7,VLOOKUP(D9,Full_Year,2,0),".xlxs"),IF(D5="לציבור",CONCATENATE(D13,"_",VLOOKUP(D3,Full_Type_Nostro,2,0),"_",VLOOKUP(D5,Full_File_Type,2,0),"_",D7,VLOOKUP(D9,Full_Year,2,0),".xlsx"),"שם קובץ לשמירה")) -> 520042177_in_p_0324.xlsx
A17: פרטי האחראי על הדיווח בגוף המוסדי | B17: שם: | D17: ליזה שלו
B19: מספר טלפון: | D19: 03-7962110
B21: כתובת מייל: | D21: lizas@hcsra.co.il
A23: הוראות למילוי הדיווח: | D23: יש לדווח לפי ההנחיות בחלק ג' לנספח 5.4.3.2 שבפרק 3 שבחלק 4 לשער 5 בחוזר המאוחד - "רשימת נכסים ברמת הנכס הבודד".

Sheet סכום נכסים
C1: ידווח בקבצי נכסי הנוסטרו בלבד
B2: שווי הוגן | C2: עלות מופחתת | D2: השיטה שיושמה בדוח הכספי | E2: שיעור מסך נכסי השקעה
A3: מזומנים ושווי מזומנים | B3: =SUM('מזומנים ושווי מזומנים'!O:O) -> 2084238.4 | E3: 0.08464
A4: איגרות חוב ממשלתיות | B4: 7520912.2 | E4: 0.3101
A5: ניירות ערך מסחריים | B5: 4061.68 | E5: 0.00017
A6: איגרות חוב | B6: 2722894.4 | E6: 0.11227
A7: מניות, מניות בכורה ויחידות השתתפות | B7: =SUM('מניות מבכ ויהש'!U:U) -> 3123900.7 | E7: 0.1288
A8: קרנות סל | B8: =SUM('קרנות סל'!T:T) -> 5013340.2 | E8: 0.20671
A9: קרנות נאמנות | B9: 812167.06 | E9: 0.03349
A10: כתבי אופציה | B10: 1374.08 | E10: 6e-05
A11: אופציות | B11: 211.802 | E11: 1e-05
A12: חוזים עתידיים | B12: 71535.546 | E12: 0.00295
A13: מוצרים מובנים
A14: לא סחיר איגרות חוב ממשלתיות
A15: לא סחיר איגרות חוב מיועדות | B15: 22310.024 | E15: 0.00092
A16: אפיק השקעה מובטח תשואה
A17: לא סחיר ניירות ערך מסחריים | B17: 24711.457 | E17: 0.00102
A18: לא סחיר איגרות חוב | B18: 157337.56 | E18: 0.00649
A19: לא סחיר מניות, מניות בכורה ויחידות השתתפות | B19: 445131.6 | E19: 0.01835
A20: קרנות השקעה | B20: 1622866.9 | E20: 0.06691
A21: לא סחיר כתבי אופציה | B21: 5684 | E21: 0.00023
A22: לא סחיר אופציות
A23: לא סחיר נגזרים אחרים | B23: =SUM('לא סחיר נגזרים אחרים'!R:R) -> -26609.275 | E23: -0.00119
A24: הלוואות | B24: 282669.06 | E24: 0.01166
A25: לא סחיר מוצרים מובנים
A26: פיקדונות מעל 3 חודשים | B26: 31274.332 | E26: 0.00129
A27: זכויות מקרקעין | B27: 366760 | E27: 0.01512
A28: השקעה בחברות מוחזקות
A29: נכסים אחרים
A30: סך הכל נכסים | B30: =SUM(B3:B29) -> 24286772 | C30: =SUM(C3:C29) -> 0 | D30: =SUM(D3:D29) -> 0 | E30: =SUM(E3:E29) -> 1
A31: מסגרות אשראי
A32: יתרות התחייבויות להשקעה | B32: =SUM('יתרות התחייבות להשקעה'!O:O) -> 356511.06 | E32: =B32/B30 -> 0.014679228

Sheet מזומנים ושווי מזומנים
A1: מספר קופה/קרן/ח.פ. עבור חברת ביטוח | B1: מספר מסלול | C1: שם הבנק | D1: מספר מזהה בנק | E1: סוג מספר מזהה בנק | F1: מאפיין עיקרי | G1: ישראל/חו"ל | H1: בעל עניין/צד קשור | I1: דירוג הבנק | J1: שם מדרג | K1: מטבע פעילות | L1: שווי מטבעי | M1: שער חליפין | N1: שיעור ריבית | O1: שווי הוגן (באלפי ש"ח) | P1: שיעור מנכסי אפיק ההשקעה | Q1: שיעור מסך נכסי ההשקעה
A2: 520042177 | B2: 12936 | C2: בנק מזרחי | D2: 20-61 | E2: סימול בנק | F2: מזומן ועו"ש בש"ח | G2: ישראל | H2: לא | I2: Aaa.il | J2: מידרוג Moodys | K2: ILS | L2: =1765.579+178.583890000009 -> 1944.1629 | M2: 1 | N2: 0.04 | O2: =L2 -> 1944.1629 | P2: =O2/SUMIF(B:B,B2,O:O) -> 0.8460081 | Q2: 0.018272656
A3: 520042177 | B3: 12936 | C3: בנק מזרחי | D3: 20-61 | E3: סימול בנק | F3: מזומן ועו"ש נקוב במט"ח | G3: ישראל | H3: לא | I3: ilAAA | J3: S&P מעלות | K3: USD | L3: 4.555 | M3: 3.71 | N3: 0.0474 | O3: 16.899 | P3: =O3/SUMIF(B:B,B3,O:O) -> 0.0073536487 | Q3: 0.00015882908
A4: 520042177 | B4: 12936 | C4: בנק מזרחי | D4: 20-61 | E4: סימול בנק | F4: בטחונות שוטפים | G4: חו"ל | H4: לא | I4: Aaa.il | J4: מידרוג Moodys | K4: USD | L4: 90.831 | M4: 3.71 | N4: 0.045 | O4: 336.981 | P4: =O4/SUMIF(B:B,B4,O:O) -> 0.14663826 | Q4: 0.0031671924
A5: 520042177 | B5: 12937 | C5: בנק מזרחי | D5: 20-61 | E5: סימול בנק | F5: מזומן ועו"ש נקוב במט"ח | G5: ישראל | H5: לא | I5: ilAAA | J5: S&P מעלות | K5: USD | L5: 14572.909 | M5: 3.71 | N5: 0.0474 | O5: 54065.492 | P5: =O5/SUMIF(B:B,B5,O:O) -> 0.43911083 | Q5: 0.050027142
A6: 520042177 | B6: 12937 | C6: בנק מזרחי | D6: 20-61 | E6: סימול בנק | F6: מזומן ועו"ש בש"ח | G6: ישראל | H6: לא | I6: Aaa.il | J6: מידרוג Moodys | K6: ILS | L6: =43251.25+924.830700000049 -> 44176.081 | M6: 1 | N6: 0.04 | O6: =L6 -> 44176.081 | P6: =O6/SUMIF(B:B,B6,O:O) -> 0.3587907 | Q6: 0.040876407
A7: 520042177 | B7: 12937 | C7: בנק מזרחי | D7: 20-61 | E7: סימול בנק | F7: מזומן ועו"ש נקוב במט"ח | G7: ישראל | H7: לא | I7: ilAAA | J7: S&P מעלות | K7: EUR | L7: 959.087 | M7: 4.152 | N7: 0.0306 | O7: 3982.514 | P7: =O7/SUMIF(B:B,B7,O:O) -> 0.032345309 | Q7: 0.0036850454
A8: 520042177 | B8: 12937 | C8: בנק מזרחי | D8: 20-61 | E8: סימול בנק | F8: מזומן ועו"ש נקוב במט"ח | G8: ישראל | H8: לא | I8: Aaa.il | J8: מידרוג Moodys | K8: CHF | L8: 0.083 | M8: 4.397 | N8: 0 | O8: 0.363 | P8: =O8/SUMIF(B:B,B8,O:O) -> 2.9482249e-06 | Q8: 3.358862e-07
A9: 520042177 | B9: 12937 | C9: בנק מזרחי | D9: 20-61 | E9: סימול בנק | F9: בטחונות שוטפים | G9: חו"ל | H9: לא | I9: Aaa.il | J9: מידרוג Moodys | K9: USD | L9: 5233.337 | M9: 3.71 | N9: 0.045 | O9: 19415.681 | P9: =O9/SUMIF(B:B,B9,O:O) -> 0.1576909 | Q9: 0.017965453
A10: 520042177 | B10: 12937 | C10: בנק מזרחי | D10: 20-61 | E10: סימול בנק | F10: בטחונות שוטפים | G10: חו"ל | H10: לא | I10: Aaa.il | J10: מידרוג Moodys | K10: EUR | L10: 357.577 | M10: 4.152 | N10: 0.0273 | O10: 1484.803 | P10: =O10/SUMIF(B:B,B10,O:O) -> 0.01205932 | Q10: 0.0013738976
A11: 520042177 | B11: 12938 | C11: בנק מזרחי | D11: 20-61 | E11: סימול בנק | F11: מזומן ועו"ש בש"ח | G11: ישראל | H11: לא | I11: Aaa.il | J11: מידרוג Moodys | K11: ILS | L11: =7417.587+61.5857900000119 -> 7479.1728 | M11: 1 | N11: 0.04 | O11: =L11 -> 7479.1728 | P11: =O11/SUMIF(B:B,B11,O:O) -> 0.42396375 | Q11: 0.03293345
A12: 520042177 | B12: 12938 | C12: בנק מזרחי | D12: 20-61 | E12: סימול בנק | F12: מזומן ועו"ש נקוב במט"ח | G12: ישראל | H12: לא | I12: ilAAA | J12: S&P מעלות | K12: USD | L12: 630.285 | M12: 3.71 | N12: 0.0474 | O12: 2338.358 | P12: =O12/SUMIF(B:B,B12,O:O) -> 0.13255196 | Q12: 0.01029662
A13: 520042177 | B13: 12938 | C13: בנק מזרחי | D13: 20-61 | E13: סימול בנק | F13: מזומן ועו"ש נקוב במט"ח | G13: ישראל | H13: לא | I13: ilAAA | J13: S&P מעלות | K13: EUR | L13: 191.838 | M13: 4.152 | N13: 0.0306 | O13: 796.586 | P13: =O13/SUMIF(B:B,B13,O:O) -> 0.045155206 | Q13: 0.0035076507
A14: 520042177 | B14: 12938 | C14: בנק מזרחי | D14: 20-61 | E14: סימול בנק | F14: בטחונות שוטפים | G14: חו"ל | H14: לא | I14: Aaa.il | J14: מידרוג Moodys | K14: USD | L14: 1576.39 | M14: 3.71 | N14: 0.045 | O14: 5848.406 | P14: =O14/SUMIF(B:B,B14,O:O) -> 0.33152224 | Q14: 0.025752606
A15: 520042177 | B15: 12938 | C15: בנק מזרחי | D15: 20-61 | E15: סימול בנק | F15: בטחונות שוטפים | G15: חו"ל | H15: לא | I15: Aaa.il | J15: מידרוג Moodys | K15: EUR | L15: 283.822 | M15: 4.152 | N15: 0.0273 | O15: 1178.544 | P15: =O15/SUMIF(B:B,B15,O:O) -> 0.066806844 | Q15: 0.0051895472
A16: 520042177 | B16: 13498 | C16: בנק מזרחי | D16: 20-61 | E16: סימול בנק | F16: מזומן ועו"ש בש"ח | G16: ישראל | H16: לא | I16: Aaa.il | J16: מידרוג Moodys | K16: ILS | L16: =53762.465+118.273149999906 -> 53880.738 | M16: 1 | N16: 0.04 | O16: =L16 -> 53880.738 | P16: =O16/SUMIF(B:B,B16,O:O) -> 0.90155552 | Q16: 0.0676231
A17: 520042177 | B17: 13498 | C17: בנק מזרחי | D17: 20-61 | E17: סימול בנק | F17: מזומן ועו"ש נקוב במט"ח | G17: ישראל | H17: לא | I17: ilAAA | J17: S&P מעלות | K17: USD | L17: 319.663 | M17: 3.71 | N17: 0.0474 | O17: 1185.95 | P17: =O17/SUMIF(B:B,B17,O:O) -> 0.019843822 | Q17: 0.0014884283
A18: 520042177 | B18: 13498 | C18: בנק מזרחי | D18: 20-61 | E18: סימול בנק | F18: מזומן ועו"ש נקוב במט"ח | G18: ישראל | H18: לא | I18: ilAAA | J18: S&P מעלות | K18: EUR | L18: 0.5 | M18: 4.152 | N18: 0.0306 | O18: 2.075 | P18: =O18/SUMIF(B:B,B18,O:O) -> 3.4719786e-05 | Q18: 2.6042318e-06
A19: 520042177 | B19: 13498 | C19: בנק מזרחי | D19: 20-61 | E19: סימול בנק | F19: בטחונות שוטפים | G19: חו"ל | H19: לא | I19: Aaa.il | J19: מידרוג Moodys | K19: USD | L19: 1265.615 | M19: 3.71 | N19: 0.045 | O19: 4695.43 | P19: =O19/SUMIF(B:B,B19,O:O) -> 0.07856594 | Q19: 0.0058930064
A20: 520042177 | B20: 13499 | C20: בנק מזרחי | D20: 20-61 | E20: סימול בנק | F20: מזומן ועו"ש בש"ח | G20: ישראל | H20: לא | I20: Aaa.il | J20: מידרוג Moodys | K20: ILS | L20: =394.269-35.8783700000022 -> 358.39063 | M20: 1 | N20: 0.04 | O20: =L20 -> 358.39063 | P20: =O20/SUMIF(B:B,B20,O:O) -> 0.95865428 | Q20: 0.011368991
A21: 520042177 | B21: 13499 | C21: בנק מזרחי | D21: 20-61 | E21: סימול בנק | F21: מזומן ועו"ש נקוב במט"ח | G21: ישראל | H21: לא | I21: ilAAA | J21: S&P מעלות | K21: USD | L21: 4.166 | M21: 3.71 | N21: 0.0474 | O21: 15.457 | P21: =O21/SUMIF(B:B,B21,O:O) -> 0.041345722 | Q21: 0.00049033226
A22: 520042177 | B22: 13500 | C22: בנק מזרחי | D22: 20-61 | E22: סימול בנק | F22: מזומן ועו"ש בש"ח | G22: ישראל | H22: לא | I22: Aaa.il | J22: מידרוג Moodys | K22: ILS | L22: =19289.376+1205.91317000001 -> 20495.289 | M22: 1 | N22: 0.04 | O22: =L22 -> 20495.289 | P22: =O22/SUMIF(B:B,B22,O:O) -> 0.80594198 | Q22: 0.068932415
A23: 520042177 | B23: 13500 | C23: בנק מזרחי | D23: 20-61 | E23: סימול בנק | F23: מזומן ועו"ש נקוב במט"ח | G23: ישראל | H23: לא | I23: ilAAA | J23: S&P מעלות | K23: USD | L23: 57.382 | M23: 3.71 | N23: 0.0474 | O23: 212.887 | P23: =O23/SUMIF(B:B,B23,O:O) -> 0.0083714149 | Q23: 0.00071600917
A24: 520042177 | B24: 13500 | C24: בנק מזרחי | D24: 20-61 | E24: סימול בנק | F24: מזומן ועו"ש נקוב במט"ח | G24: ישראל | H24: לא | I24: ilAAA | J24: S&P מעלות | K24: EUR | L24: 2.334 | M24: 4.152 | N24: 0.0306 | O24: 9.693 | P24: =O24/SUMIF(B:B,B24,O:O) -> 0.00038116054 | Q24: 3.2600755e-05
A25: 520042177 | B25: 13500 | C25: בנק מזרחי | D25: 20-61 | E25: סימול בנק | F25: בטחונות שוטפים | G25: חו"ל | H25: לא | I25: Aaa.il | J25: מידרוג Moodys | K25: USD | L25: 1270.178 | M25: 3.71 | N25: 0.045 | O25: 4712.36 | P25: =O25/SUMIF(B:B,B25,O:O) -> 0.18530545 | Q25: 0.01584922
A26: 520042177 | B26: 141 | C26: בנק מזרחי | D26: 20-61 | E26: סימול בנק | F26: מזומן ועו"ש בש"ח | G26: ישראל | H26: לא | I26: Aaa.il | J26: מידרוג Moodys | K26: ILS | L26: =7071.388+1026.88323000003 -> 8098.2712 | M26: 1 | N26: 0.04 | O26: =L26 -> 8098.2712 | P26: =O26/SUMIF(B:B,B26,O:O) -> 0.65584776 | Q26: 0.021732935
A27: 520042177 | B27: 141 | C27: בנק מזרחי | D27: 20-61 | E27: סימול בנק | F27: מזומן ועו"ש נקוב במט"ח | G27: ישראל | H27: לא | I27: ilAAA | J27: S&P מעלות | K27: USD | L27: 5.387 | M27: 3.71 | N27: 0.0474 | O27: 19.986 | P27: =O27/SUMIF(B:B,B27,O:O) -> 0.0016185891 | Q27: 5.3635452e-05
A28: 520042177 | B28: 141 | C28: בנק מזרחי | D28: 20-61 | E28: סימול בנק | F28: מזומן ועו"ש נקוב במט"ח | G28: ישראל | H28: לא | I28: ilAAA | J28: S&P מעלות | K28: EUR | L28: 0.095 | M28: 4.152 | N28: 0.0306 | O28: 0.394 | P28: =O28/SUMIF(B:B,B28,O:O) -> 3.1908541e-05 | Q28: 1.0573586e-06
A29: 520042177 | B29: 141 | C29: בנק מזרחי | D29: 20-61 | E29: סימול בנק | F29: בטחונות שוטפים | G29: חו"ל | H29: לא | I29: Aaa.il | J29: מידרוג Moodys | K29: USD | L29: 1139.93 | M29: 3.71 | N29: 0.045 | O29: 4229.14 | P29: =O29/SUMIF(B:B,B29,O:O) -> 0.34250174 | Q29: 0.011349537
A30: 520042177 | B30: 142 | C30: בנק מזרחי | D30: 20-61 | E30: סימול בנק | F30: מזומן ועו"ש בש"ח | G30: ישראל | H30: לא | I30: Aaa.il | J30: מידרוג Moodys | K30: ILS | L30: =75647.115+1562.70276999997 -> 77209.818 | M30: 1 | N30: 0.04 | O30: =L30 -> 77209.818 | P30: =O30/SUMIF(B:B,B30,O:O) -> 0.75627439 | Q30: 0.11826302
A31: 520042177 | B31: 142 | C31: בנק מזרחי | D31: 20-61 | E31: סימול בנק | F31: מזומן ועו"ש נקוב במט"ח | G31: ישראל | H31: לא | I31: ilAAA | J31: S&P מעלות | K31: EUR | L31: 1651.805 | M31: 4.152 | N31: 0.0306 | O31: 6858.953 | P31: =O31/SUMIF(B:B,B31,O:O) -> 0.06718382 | Q31: 0.010505924
A32: 520042177 | B32: 142 | C32: בנק מזרחי | D32: 20-61 | E32: סימול בנק | F32: מזומן ועו"ש נקוב במט"ח | G32: ישראל | H32: לא | I32: ilAAA | J32: S&P מעלות | K32: USD | L32: 528.857 | M32: 3.71 | N32: 0.0474 | O32: 1962.061 | P32: =O32/SUMIF(B:B,B32,O:O) -> 0.019218495 | Q32: 0.0030053077
A33: 520042177 | B33: 142 | C33: בנק מזרחי | D33: 20-61 | E33: סימול בנק | F33: מזומן ועו"ש נקוב במט"ח | G33: ישראל | H33: לא | I33: ilAAA | J33: S&P מעלות | K33: NOK | L33: 2416.106 | M33: 0.352 | N33: 0 | O33: 851.436 | P33: =O33/SUMIF(B:B,B33,O:O) -> 0.0083398622 | Q33: 0.0013041527
A34: 520042177 | B34: 142 | C34: בנק מזרחי | D34: 20-61 | E34: סימול בנק | F34: מזומן ועו"ש נקוב במט"ח | G34: ישראל | H34: לא | I34: ilAAA | J34: S&P מעלות | K34: GBP | L34: 16.53 | M34: 4.975 | N34: 0 | O34: 82.233 | P34: =O34/SUMIF(B:B,B34,O:O) -> 0.00080547673 | Q34: 0.00012595708
A35: 520042177 | B35: 142 | C35: בנק מזרחי | D35: 20-61 | E35: סימול בנק | F35: מזומן ועו"ש נקוב במט"ח | G35: ישראל | H35: לא | I35: Aaa.il | J35: מידרוג Moodys | K35: CHF | L35: 14.526 | M35: 4.397 | N35: 0 | O35: 63.863 | P35: =O35/SUMIF(B:B,B35,O:O) -> 0.00062554158 | Q35: 9.781957e-05
A36: 520042177 | B36: 142 | C36: בנק מזרחי | D36: 20-61 | E36: סימול בנק | F36: בטחונות שוטפים | G36: חו"ל | H36: לא | I36: Aaa.il | J36: מידרוג Moodys | K36: USD | L36: 3745.933 | M36: 3.71 | N36: 0.045 | O36: 13897.412 | P36: =O36/SUMIF(B:B,B36,O:O) -> 0.13612591 | Q36: 0.021286799
A37: 520042177 | B37: 142 | C37: בנק מזרחי | D37: 20-61 | E37: סימול בנק | F37: בטחונות שוטפים | G37: חו"ל | H37: לא | I37: Aaa.il | J37: מידרוג Moodys | K37: JPY | L37: 35329.627 | M37: 0.026 | N37: -0.0057 | O37: 919.595 | P37: =O37/SUMIF(B:B,B37,O:O) -> 0.0090074833 | Q37: 0.0014085525
A38: 520042177 | B38: 142 | C38: בנק מזרחי | D38: 20-61 | E38: סימול בנק | F38: בטחונות שוטפים | G38: חו"ל | H38: לא | I38: Aaa.il | J38: מידרוג Moodys | K38: EUR | L38: 59.475 | M38: 4.152 | N38: 0.0273 | O38: 246.964 | P38: =O38/SUMIF(B:B,B38,O:O) -> 0.0024190259 | Q38: 0.00037827713
A39: 520042177 | B39: 143 | C39: בנק מזרחי | D39: 20-61 | E39: סימול בנק | F39: מזומן ועו"ש בש"ח | G39: ישראל | H39: לא | I39: Aaa.il | J39: מידרוג Moodys | K39: ILS | L39: =109085.423-291.965530000161 -> 108793.46 | M39: 1 | N39: 0.04 | O39: =L39 -> 108793.46 | P39: =O39/SUMIF(B:B,B39,O:O) -> 0.53967737 | Q39: 0.038804236
A40: 520042177 | B40: 143 | C40: בנק מזרחי | D40: 20-61 | E40: סימול בנק | F40: מזומן ועו"ש נקוב במט"ח | G40: ישראל | H40: לא | I40: ilAAA | J40: S&P מעלות | K40: EUR | L40: 4061.565 | M40: 4.152 | N40: 0.0306 | O40: 16865.241 | P40: =O40/SUMIF(B:B,B40,O:O) -> 0.08366118 | Q40: 0.0060154609
A41: 520042177 | B41: 143 | C41: בנק מזרחי | D41: 20-61 | E41: סימול בנק | F41: מזומן ועו"ש נקוב במט"ח | G41: ישראל | H41: לא | I41: ilAAA | J41: S&P מעלות | K41: USD | L41: 2340.744 | M41: 3.71 | N41: 0.0474 | O41: 8684.158 | P41: =O41/SUMIF(B:B,B41,O:O) -> 0.043078359 | Q41: 0.0030974483
A42: 520042177 | B42: 143 | C42: בנק מזרחי | D42: 20-61 | E42: סימול בנק | F42: מזומן ועו"ש נקוב במט"ח | G42: ישראל | H42: לא | I42: ilAAA | J42: S&P מעלות | K42: NOK | L42: 7202.533 | M42: 0.352 | N42: 0 | O42: 2538.173 | P42: =O42/SUMIF(B:B,B42,O:O) -> 0.01259078 | Q42: 0.00090531053
A43: 520042177 | B43: 143 | C43: בנק מזרחי | D43: 20-61 | E43: סימול בנק | F43: מזומן ועו"ש נקוב במט"ח | G43: ישראל | H43: לא | I43: Aaa.il | J43: מידרוג Moodys | K43: CHF | L43: 46.804 | M43: 4.397 | N43: 0 | O43: 205.773 | P43: =O43/SUMIF(B:B,B43,O:O) -> 0.001020751 | Q43: 7.3394707e-05
A44: 520042177 | B44: 143 | C44: בנק מזרחי | D44: 20-61 | E44: סימול בנק | F44: מזומן ועו"ש נקוב במט"ח | G44: ישראל | H44: לא | I44: ilAAA | J44: S&P מעלות | K44: GBP | L44: 36.83 | M44: 4.975 | N44: 0 | O44: 183.222 | P44: =O44/SUMIF(B:B,B44,O:O) -> 0.00090888524 | Q44: 6.5351261e-05
A45: 520042177 | B45: 143 | C45: בנק מזרחי | D45: 20-61 | E45: סימול בנק | F45: בטחונות שוטפים | G45: חו"ל | H45: לא | I45: Aaa.il | J45: מידרוג Moodys | K45: USD | L45: 16099.41 | M45: 3.71 | N45: 0.045 | O45: 59728.81 | P45: =O45/SUMIF(B:B,B45,O:O) -> 0.29628884 | Q45: 0.021303954
A46: 520042177 | B46: 143 | C46: בנק מזרחי | D46: 20-61 | E46: סימול בנק | F46: בטחונות שוטפים | G46: חו"ל | H46: לא | I46: Aaa.il | J46: מידרוג Moodys | K46: JPY | L46: 153917.31 | M46: 0.026 | N46: -0.0057 | O46: 4006.314 | P46: =O46/SUMIF(B:B,B46,O:O) -> 0.019873594 | Q46: 0.0014289642
A47: 520042177 | B47: 143 | C47: בנק מזרחי | D47: 20-61 | E47: סימול בנק | F47: בטחונות שוטפים | G47: חו"ל | H47: לא | I47: Aaa.il | J47: מידרוג Moodys | K47: EUR | L47: 140.8 | M47: 4.152 | N47: 0.0273 | O47: 584.658 | P47: =O47/SUMIF(B:B,B47,O:O) -> 0.0029002359 | Q47: 0.00020853466
A48: 520042177 | B48: 14318 | C48: בנק מזרחי | D48: 20-61 | E48: סימול בנק | F48: מזומן ועו"ש בש"ח | G48: ישראל | H48: לא | I48: Aaa.il | J48: מידרוג Moodys | K48: ILS | L48: =338.532+2.27374000000009 -> 340.80574 | M48: 1 | N48: 0.04 | O48: =L48 -> 340.80574 | P48: =O48/SUMIF(B:B,B48,O:O) -> 0.95022023 | Q48: 0.14357079
A49: 520042177 | B49: 14318 | C49: בנק מזרחי | D49: 20-61 | E49: סימול בנק | F49: מזומן ועו"ש נקוב במט"ח | G49: ישראל | H49: לא | I49: ilAAA | J49: S&P מעלות | K49: USD | L49: 4.813 | M49: 3.71 | N49: 0.0474 | O49: 17.854 | P49: =O49/SUMIF(B:B,B49,O:O) -> 0.049779772 | Q49: 0.0075213312
A50: 520042177 | B50: 14406 | C50: בנק מזרחי | D50: 20-61 | E50: סימול בנק | F50: מזומן ועו"ש בש"ח | G50: ישראל | H50: לא | I50: Aaa.il | J50: מידרוג Moodys | K50: ILS | L50: =1156.361+19.9061399999991 -> 1176.2671 | M50: 1 | N50: 0.04 | O50: =L50 -> 1176.2671 | P50: =O50/SUMIF(B:B,B50,O:O) -> 0.98359295 | Q50: 0.07995172
A51: 520042177 | B51: 14406 | C51: בנק מזרחי | D51: 20-61 | E51: סימול בנק | F51: מזומן ועו"ש נקוב במט"ח | G51: ישראל | H51: לא | I51: ilAAA | J51: S&P מעלות | K51: USD | L51: 5.289 | M51: 3.71 | N51: 0.0474 | O51: 19.621 | P51: =O51/SUMIF(B:B,B51,O:O) -> 0.016407053 | Q51: 0.0013336534
A52: 520042177 | B52: 14425 | C52: בנק מזרחי | D52: 20-61 | E52: סימול בנק | F52: מזומן ועו"ש בש"ח | G52: ישראל | H52: לא | I52: Aaa.il | J52: מידרוג Moodys | K52: ILS | L52: =7038.908+562.764570000058 -> 7601.6726 | M52: 1 | N52: 0.04 | O52: =L52 -> 7601.6726 | P52: =O52/SUMIF(B:B,B52,O:O) -> 0.5926617 | Q52: 0.02020091
A53: 520042177 | B53: 14425 | C53: בנק מזרחי | D53: 20-61 | E53: סימול בנק | F53: מזומן ועו"ש נקוב במט"ח | G53: ישראל | H53: לא | I53: ilAAA | J53: S&P מעלות | K53: USD | L53: 920.986 | M53: 3.71 | N53: 0.0474 | O53: 3416.859 | P53: =O53/SUMIF(B:B,B53,O:O) -> 0.2663942 | Q53: 0.0090800622
A54: 520042177 | B54: 14425 | C54: בנק מזרחי | D54: 20-61 | E54: סימול בנק | F54: מזומן ועו"ש נקוב במט"ח | G54: ישראל | H54: לא | I54: ilAAA | J54: S&P מעלות | K54: EUR | L54: 68.297 | M54: 4.152 | N54: 0.0306 | O54: 283.595 | P54: =O54/SUMIF(B:B,B54,O:O) -> 0.022110384 | Q54: 0.00075363374
A55: 520042177 | B55: 14425 | C55: בנק מזרחי | D55: 20-61 | E55: סימול בנק | F55: מזומן ועו"ש נקוב במט"ח | G55: ישראל | H55: לא | I55: ilAAA | J55: S&P מעלות | K55: GBP | L55: 6.023 | M55: 4.975 | N55: 0 | O55: 29.963 | P55: =O55/SUMIF(B:B,B55,O:O) -> 0.0023360547 | Q55: 7.9624562e-05
A56: 520042177 | B56: 14425 | C56: בנק מזרחי | D56: 20-61 | E56: סימול בנק | F56: בטחונות שוטפים | G56: חו"ל | H56: לא | I56: Aaa.il | J56: מידרוג Moodys | K56: USD | L56: 402.759 | M56: 3.71 | N56: 0.045 | O56: 1494.237 | P56: =O56/SUMIF(B:B,B56,O:O) -> 0.11649766 | Q56: 0.0039708296
A57: 520042177 | B57: 15373 | C57: בנק מזרחי | D57: 20-61 | E57: סימול בנק | F57: מזומן ועו"ש בש"ח | G57: ישראל | H57: לא | I57: Aaa.il | J57: מידרוג Moodys | K57: ILS | L57: =505.971+132.431780000003 -> 638.40278 | M57: 1 | N57: 0.04 | O57: =L57 -> 638.40278 | P57: =O57/SUMIF(B:B,B57,O:O) -> 0.98173404 | Q57: 0.032572816
A58: 520042177 | B58: 15373 | C58: בנק מזרחי | D58: 20-61 | E58: סימול בנק | F58: מזומן ועו"ש נקוב במט"ח | G58: ישראל | H58: לא | I58: ilAAA | J58: S&P מעלות | K58: USD | L58: 3.202 | M58: 3.71 | N58: 0.0474 | O58: 11.878 | P58: =O58/SUMIF(B:B,B58,O:O) -> 0.018265956 | Q58: 0.00060604358
A59: 520042177 | B59: 35011 | C59: בנק מזרחי | D59: 20-61 | E59: סימול בנק | F59: מזומן ועו"ש נקוב במט"ח | G59: ישראל | H59: לא | I59: ilAAA | J59: S&P מעלות | K59: USD | L59: 217.255 | M59: 3.71 | N59: 0.0474 | O59: 806.017 | P59: =O59/SUMIF(B:B,B59,O:O) -> 0.19604437 | Q59: 0.011678654
A60: 520042177 | B60: 35011 | C60: בנק מזרחי | D60: 20-61 | E60: סימול בנק | F60: מזומן ועו"ש בש"ח | G60: ישראל | H60: לא | I60: Aaa.il | J60: מידרוג Moodys | K60: ILS | L60: 623.256 | M60: 1 | N60: 0.04 | O60: 623.256 | P60: =O60/SUMIF(B:B,B60,O:O) -> 0.15159212 | Q60: 0.0090305681
A61: 520042177 | B61: 35011 | C61: בנק מזרחי | D61: 20-61 | E61: סימול בנק | F61: מזומן ועו"ש נקוב במט"ח | G61: ישראל | H61: לא | I61: ilAAA | J61: S&P מעלות | K61: EUR | L61: 134.065 | M61: 4.152 | N61: 0.0306 | O61: 556.69 | P61: =O61/SUMIF(B:B,B61,O:O) -> 0.13540153 | Q61: 0.0080660707
A62: 520042177 | B62: 35011 | C62: בנק מזרחי | D62: 20-61 | E62: סימול בנק | F62: מזומן ועו"ש נקוב במט"ח | G62: ישראל | H62: לא | I62: ilAAA | J62: S&P מעלות | K62: GBP | L62: 29.194 | M62: 4.975 | N62: 0 | O62: 145.236 | P62: =O62/SUMIF(B:B,B62,O:O) -> 0.035325185 | Q62: 0.0021043738
A63: 520042177 | B63: 35011 | C63: בנק לאומי | D63: 10-800 | E63: סימול בנק | F63: מזומן ועו"ש בש"ח | G63: ישראל | H63: לא | I63: Aaa.il | J63: מידרוג Moodys | K63: ILS | L63: 19.45 | M63: 1 | N63: 0 | O63: 19.45 | P63: =O63/SUMIF(B:B,B63,O:O) -> 0.0047307475 | Q63: 0.00028181766
A64: 520042177 | B64: 35011 | C64: בנק לאומי | D64: 10-800 | E64: סימול בנק | F64: מזומן ועו"ש נקוב במט"ח | G64: ישראל | H64: לא | I64: ilAAA | J64: S&P מעלות | K64: USD | L64: 0.26 | M64: 3.71 | N64: 0 | O64: 0.965 | P64: =O64/SUMIF(B:B,B64,O:O) -> 0.00023471318 | Q64: 1.3982213e-05
A65: 520042177 | B65: 35011 | C65: בנק מזרחי | D65: 20-61 | E65: סימול בנק | F65: בטחונות שוטפים | G65: חו"ל | H65: לא | I65: Aaa.il | J65: מידרוג Moodys | K65: USD | L65: 394.859 | M65: 3.71 | N65: 0.045 | O65: 1464.927 | P65: =O65/SUMIF(B:B,B65,O:O) -> 0.35630847 | Q65: 0.021225825
A66: 520042177 | B66: 35011 | C66: בנק מזרחי | D66: 20-61 | E66: סימול בנק | F66: בטחונות שוטפים | G66: חו"ל | H66: לא | I66: Aaa.il | J66: מידרוג Moodys | K66: EUR | L66: 77.208 | M66: 4.152 | N66: 0.0273 | O66: 320.601 | P66: =O66/SUMIF(B:B,B66,O:O) -> 0.077978528 | Q66: 0.0046452969
A67: 520042177 | B67: 35011 | C67: בנק מזרחי | D67: 20-61 | E67: סימול בנק | F67: בטחונות שוטפים | G67: חו"ל | H67: לא | I67: Aaa.il | J67: מידרוג Moodys | K67: GBP | L67: 24.33 | M67: 4.975 | N67: 0.0417 | O67: 121.037 | P67: =O67/SUMIF(B:B,B67,O:O) -> 0.029439357 | Q67: 0.0017537463
A68: 520042177 | B68: 35011 | C68: בנק מזרחי | D68: 20-61 | E68: סימול בנק | F68: בטחונות שוטפים | G68: חו"ל | H68: לא | I68: Aaa.il | J68: מידרוג Moodys | K68: CHF | L68: 12.09 | M68: 4.397 | N68: 0.0024 | O68: 53.153 | P68: =O68/SUMIF(B:B,B68,O:O) -> 0.012928196 | Q68: 0.00077015189
A69: 520042177 | B69: 35011 | C69: בנק מזרחי | D69: 20-61 | E69: סימול בנק | F69: בטחונות שוטפים | G69: חו"ל | H69: לא | I69: Aaa.il | J69: מידרוג Moodys | K69: HKD | L69: 0.145 | M69: 0.478 | N69: 0.0124265 | O69: 0.069 | P69: =O69/SUMIF(B:B,B69,O:O) -> 1.67826e-05 | Q69: 9.9976446e-07
A70: 520042177 | B70: 35012 | C70: בנק מזרחי | D70: 20-61 | E70: סימול בנק | F70: מזומן ועו"ש נקוב במט"ח | G70: ישראל | H70: לא | I70: ilAAA | J70: S&P מעלות | K70: USD | L70: 22691.97 | M70: 3.71 | N70: 0.0474 | O70: 84187.209 | P70: =O70/SUMIF(B:B,B70,O:O) -> 0.45839295 | Q70: 0.046543938
A71: 520042177 | B71: 35012 | C71: בנק מזרחי | D71: 20-61 | E71: סימול בנק | F71: מזומן ועו"ש בש"ח | G71: ישראל | H71: לא | I71: Aaa.il | J71: מידרוג Moodys | K71: ILS | L71: =32755.334+9545.121 -> 42300.455 | M71: 1 | N71: 0.04 | O71: =L71 -> 42300.455 | P71: =O71/SUMIF(B:B,B71,O:O) -> 0.23032276 | Q71: 0.023386329
A72: 520042177 | B72: 35012 | C72: בנק מזרחי | D72: 20-61 | E72: סימול בנק | F72: מזומן ועו"ש נקוב במט"ח | G72: ישראל | H72: לא | I72: ilAAA | J72: S&P מעלות | K72: EUR | L72: 2868.01 | M72: 4.152 | N72: 0.0306 | O72: 11909.123 | P72: =O72/SUMIF(B:B,B72,O:O) -> 0.064844268 | Q72: 0.0065841058
A73: 520042177 | B73: 35012 | C73: בנק לאומי | D73: 10-800 | E73: סימול בנק | F73: מזומן ועו"ש נקוב במט"ח | G73: ישראל | H73: לא | I73: ilAAA | J73: S&P מעלות | K73: USD | L73: 618.513 | M73: 3.71 | N73: 0 | O73: 2294.681 | P73: =O73/SUMIF(B:B,B73,O:O) -> 0.012494363 | Q73: 0.0012686427
A74: 520042177 | B74: 35012 | C74: בנק מזרחי | D74: 20-61 | E74: סימול בנק | F74: פקדון במט"ח עד שלושה חודשים | G74: ישראל | H74: לא | I74: Aaa.il | J74: מידרוג Moodys | K74: USD | L74: 292.472 | M74: 3.71 | N74: 0.0585 | O74: 1085.071 | P74: =O74/SUMIF(B:B,B74,O:O) -> 0.005908129 | Q74: 0.00059989491
A75: 520042177 | B75: 35012 | C75: בנק לאומי | D75: 10-800 | E75: סימול בנק | F75: מזומן ועו"ש בש"ח | G75: ישראל | H75: לא | I75: Aaa.il | J75: מידרוג Moodys | K75: ILS | L75: 1026.485 | M75: 1 | N75: 0 | O75: 1026.485 | P75: =O75/SUMIF(B:B,B75,O:O) -> 0.0055891327 | Q75: 0.00056750491
A76: 520042177 | B76: 35012 | C76: בנק הפועלים | D76: 12-600 | E76: סימול בנק | F76: מזומן ועו"ש בש"ח | G76: ישראל | H76: לא | I76: Aaa.il | J76: מידרוג Moodys | K76: ILS | L76: 914.866 | M76: 1 | N76: 0 | O76: 914.866 | P76: =O76/SUMIF(B:B,B76,O:O) -> 0.0049813757 | Q76: 0.00050579497
A77: 520042177 | B77: 35012 | C77: בנק הפועלים | D77: 12-600 | E77: סימול בנק | F77: מזומן ועו"ש נקוב במט"ח | G77: ישראל | H77: לא | I77: ilAAA | J77: S&P מעלות | K77: USD | L77: 113.652 | M77: 3.71 | N77: 0 | O77: 421.648 | P77: =O77/SUMIF(B:B,B77,O:O) -> 0.0022958413 | Q77: 0.0002331133
A78: 520042177 | B78: 35012 | C78: בנק מזרחי | D78: 20-61 | E78: סימול בנק | F78: מזומן ועו"ש נקוב במט"ח | G78: ישראל | H78: לא | I78: ilAAA | J78: S&P מעלות | K78: GBP | L78: 36.014 | M78: 4.975 | N78: 0 | O78: 179.163 | P78: =O78/SUMIF(B:B,B78,O:O) -> 0.0009755289 | Q78: 9.9052478e-05
A79: 520042177 | B79: 35012 | C79: בנק לאומי | D79: 10-800 | E79: סימול בנק | F79: פח"ק/פר"י | G79: ישראל | H79: לא | I79: Aaa.il | J79: מידרוג Moodys | K79: ILS | L79: 4.135 | M79: 1 | N79: 0 | O79: 4.135 | P79: =O79/SUMIF(B:B,B79,O:O) -> 2.251476e-05 | Q79: 2.2860858e-06
A80: 520042177 | B80: 35012 | C80: בנק לאומי | D80: 10-800 | E80: סימול בנק | F80: מזומן ועו"ש נקוב במט"ח | G80: ישראל | H80: לא | I80: ilAAA | J80: S&P מעלות | K80: EUR | L80: 0.119 | M80: 4.152 | N80: 0 | O80: 0.493 | P80: =O80/SUMIF(B:B,B80,O:O) -> 2.6843475e-06 | Q80: 2.7256114e-07
A81: 520042177 | B81: 35012 | C81: בנק מזרחי | D81: 20-61 | E81: סימול בנק | F81: בטחונות שוטפים | G81: חו"ל | H81: לא | I81: Aaa.il | J81: מידרוג Moodys | K81: USD | L81: 8084.219 | M81: 3.71 | N81: 0.045 | O81: 29992.454 | P81: =O81/SUMIF(B:B,B81,O:O) -> 0.16330663 | Q81: 0.016581699
A82: 520042177 | B82: 35012 | C82: בנק מזרחי | D82: 20-61 | E82: סימול בנק | F82: בטחונות שוטפים | G82: חו"ל | H82: לא | I82: Aaa.il | J82: מידרוג Moodys | K82: EUR | L82: 1653.662 | M82: 4.152 | N82: 0.0273 | O82: 6866.668 | P82: =O82/SUMIF(B:B,B82,O:O) -> 0.037388485 | Q82: 0.0037963222
A83: 520042177 | B83: 35012 | C83: בנק מזרחי | D83: 20-61 | E83: סימול בנק | F83: בטחונות שוטפים | G83: חו"ל | H83: לא | I83: Aaa.il | J83: מידרוג Moodys | K83: GBP | L83: 497.299 | M83: 4.975 | N83: 0.0417 | O83: 2473.963 | P83: =O83/SUMIF(B:B,B83,O:O) -> 0.01347054 | Q83: 0.001367761
... A85: 520042177 | B85: 35012 | C85: בנק מזרחי | D85: 20-61 | E85: סימול בנק | F85: בטחונות שוטפים | G85: חו"ל | H85: לא | I85: Aaa.il | J85: מידרוג Moodys | K85: CHF | L85: 0.1 | M85: 4.397 | N85: 0.0024 | O85: 0.439 | P85: =O85/SUMIF(B:B,B85,O:O) -> 2.3903216e-06 | Q85: 2.4270657e-07
A86: 520042177 | B86: 57 | C86: בנק מזרחי | D86: 20-61 | E86: סימול בנק | F86: מזומן ועו"ש בש"ח | G86: ישראל | H86: לא | I86: Aaa.il | J86: מידרוג Moodys | K86: ILS | L86: =2051.592+3314.36480000009 -> 5365.9568 | M86: 1 | N86: 0.04 | O86: =L86 -> 5365.9568 | P86: =O86/SUMIF(B:B,B86,O:O) -> 0.47109187 | Q86: 0.014147343
A87: 520042177 | B87: 57 | C87: בנק מזרחי | D87: 20-61 | E87: סימול בנק | F87: מזומן ועו"ש נקוב במט"ח | G87: ישראל | H87: לא | I87: ilAAA | J87: S&P מעלות | K87: USD | L87: 366.132 | M87: 3.71 | N87: 0.0474 | O87: 1358.348 | P87: =O87/SUMIF(B:B,B87,O:O) -> 0.11925305 | Q87: 0.0035812839
A88: 520042177 | B88: 57 | C88: בנק מזרחי | D88: 20-61 | E88: סימול בנק | F88: פקדון במט"ח עד שלושה חודשים | G88: ישראל | H88: לא | I88: Aaa.il | J88: מידרוג Moodys | K88: USD | L88: 103.497 | M88: 3.71 | N88: 0.0585 | O88: 383.975 | P88: =O88/SUMIF(B:B,B88,O:O) -> 0.033710205 | Q88: 0.0010123499
A89: 520042177 | B89: 57 | C89: בנק מזרחי | D89: 20-61 | E89: סימול בנק | F89: מזומן ועו"ש נקוב במט"ח | G89: ישראל | H89: לא | I89: ilAAA | J89: S&P מעלות | K89: GBP | L89: 60.669 | M89: 4.975 | N89: 0 | O89: 301.816 | P89: =O89/SUMIF(B:B,B89,O:O) -> 0.026497244 | Q89: 0.00079573776
A90: 520042177 | B90: 57 | C90: בנק לאומי | D90: 10-800 | E90: סימול בנק | F90: מזומן ועו"ש נקוב במט"ח | G90: ישראל | H90: לא | I90: ilAAA | J90: S&P מעלות | K90: USD | L90: 10.072 | M90: 3.71 | N90: 0 | O90: 37.369 | P90: =O90/SUMIF(B:B,B90,O:O) -> 0.0032807257 | Q90: 9.8523353e-05
A91: 520042177 | B91: 57 | C91: בנק מזרחי | D91: 20-61 | E91: סימול בנק | F91: מזומן ועו"ש נקוב במט"ח | G91: ישראל | H91: לא | I91: ilAAA | J91: S&P מעלות | K91: EUR | L91: 7.695 | M91: 4.152 | N91: 0.0306 | O91: 31.953 | P91: =O91/SUMIF(B:B,B91,O:O) -> 0.0028052404 | Q91: 8.4244071e-05
A92: 520042177 | B92: 57 | C92: בנק לאומי | D92: 10-800 | E92: סימול בנק | F92: מזומן ועו"ש בש"ח | G92: ישראל | H92: לא | I92: Aaa.il | J92: מידרוג Moodys | K92: ILS | L92: 0.176 | M92: 1 | N92: 0 | O92: 0.176 | P92: =O92/SUMIF(B:B,B92,O:O) -> 1.5451516e-05 | Q92: 4.6402393e-07
A93: 520042177 | B93: 57 | C93: בנק מזרחי | D93: 20-61 | E93: סימול בנק | F93: בטחונות שוטפים | G93: חו"ל | H93: לא | I93: Aaa.il | J93: מידרוג Moodys | K93: USD | L93: 1054.043 | M93: 3.71 | N93: 0.045 | O93: 3910.5 | P93: =O93/SUMIF(B:B,B93,O:O) -> 0.34331338 | Q93: 0.010310032
A94: 520042177 | B94: 57 | C94: בנק מזרחי | D94: 20-61 | E94: סימול בנק | F94: בטחונות שוטפים | G94: חו"ל | H94: לא | I94: Aaa.il | J94: מידרוג Moodys | K94: EUR | L94: 0.09 | M94: 4.152 | N94: 0.0273 | O94: 0.374 | P94: =O94/SUMIF(B:B,B94,O:O) -> 3.2834472e-05 | Q94: 9.8605085e-07
A95: 520042177 | B95: 58 | C95: בנק מזרחי | D95: 20-61 | E95: סימול בנק | F95: מזומן ועו"ש בש"ח | G95: ישראל | H95: לא | I95: Aaa.il | J95: מידרוג Moodys | K95: ILS | L95: =9215.925+429.331360000011 -> 9645.2564 | M95: 1 | N95: 0.04 | O95: =L95 -> 9645.2564 | P95: =O95/SUMIF(B:B,B95,O:O) -> 0.38921933 | Q95: 0.025206555
A96: 520042177 | B96: 58 | C96: בנק מזרחי | D96: 20-61 | E96: סימול בנק | F96: מזומן ועו"ש נקוב במט"ח | G96: ישראל | H96: לא | I96: ilAAA | J96: S&P מעלות | K96: USD | L96: 632.56 | M96: 3.71 | N96: 0.0474 | O96: 2346.799 | P96: =O96/SUMIF(B:B,B96,O:O) -> 0.094701426 | Q96: 0.0061330375
A97: 520042177 | B97: 58 | C97: בנק לאומי | D97: 10-800 | E97: סימול בנק | F97: מזומן ועו"ש בש"ח | G97: ישראל | H97: לא | I97: Aaa.il | J97: מידרוג Moodys | K97: ILS | L97: 885.371 | M97: 1 | N97: 0 | O97: 885.371 | P97: =O97/SUMIF(B:B,B97,O:O) -> 0.03572777 | Q97: 0.0023137958
A98: 520042177 | B98: 58 | C98: בנק לאומי | D98: 10-800 | E98: סימול בנק | F98: מזומן ועו"ש נקוב במט"ח | G98: ישראל | H98: לא | I98: ilAAA | J98: S&P מעלות | K98: USD | L98: 153.023 | M98: 3.71 | N98: 0 | O98: 567.716 | P98: =O98/SUMIF(B:B,B98,O:O) -> 0.022909297 | Q98: 0.001483648
A99: 520042177 | B99: 58 | C99: בנק מזרחי | D99: 20-61 | E99: סימול בנק | F99: מזומן ועו"ש נקוב במט"ח | G99: ישראל | H99: לא | I99: ilAAA | J99: S&P מעלות | K99: EUR | L99: 101.583 | M99: 4.152 | N99: 0.0306 | O99: 421.812 | P99: =O99/SUMIF(B:B,B99,O:O) -> 0.017021568 | Q99: 0.0011023478
A100: 520042177 | B100: 58 | C100: בנק מזרחי | D100: 20-61 | E100: סימול בנק | F100: פקדון במט"ח עד שלושה חודשים | G100: ישראל | H100: לא | I100: Aaa.il | J100: מידרוג Moodys | K100: USD | L100: 73.619 | M100: 3.71 | N100: 0.0585 | O100: 273.128 | P100: =O100/SUMIF(B:B,B100,O:O) -> 0.011021656 | Q100: 0.00071378259
A101: 520042177 | B101: 58 | C101: בנק מזרחי | D101: 20-61 | E101: סימול בנק | F101: מזומן ועו"ש נקוב במט"ח | G101: ישראל | H101: לא | I101: ilAAA | J101: S&P מעלות | K101: GBP | L101: 45.754 | M101: 4.975 | N101: 0 | O101: 227.619 | P101: =O101/SUMIF(B:B,B101,O:O) -> 0.0091852109 | Q101: 0.00059485106
...

Sheet איגרות חוב ממשלתיות
A1: מספר קופה/קרן/ח.פ. עבור חברת ביטוח | B1: מספר מסלול | C1: שם מנפיק | D1: שם נייר ערך | E1: מספר נייר ערך | F1: מאפיין עיקרי | G1: ישראל/חו"ל | H1: מדינה לפי חשיפה כלכלית | I1: זירת מסחר | J1: דירוג | K1: שם מדרג | L1: מטבע פעילות | M1: מח"מ | N1: מועד פדיון | O1: שיעור ריבית | P1: תשואה לפדיון | Q1: סכום לקבל (במטבע הפעילות) | R1: ערך נקוב (יחידות) | S1: שער חליפין | T1: שער נייר הערך | U1: שווי הוגן (באלפי ש"ח) | V1: עלות מופחתת (באלפי ש"ח) | W1: השיטה שיושמה בדוח הכספי | X1: שיעור מערך נקוב מונפק | Y1: שיעור מנכסי אפיק ההשקעה | Z1: שיעור מסך נכסי ההשקעה
A2: 520042177 | B2: 12936 | C2: האוצר - ממשלתית צמודה | D2: ממשל צמודה 1025 | E2: IL0011359127 | F2: צמוד למדד המחירים לצרכן בריבית קבועה | G2: ישראל | H2: ישראל | I2: TASE | J2: ilRF | K2: S&P מעלות | L2: ILS | M2: 1.07 | N2: 31/10/2025 | O2: 0.00504 | P2: 0.013 | R2: 19500000 | S2: 1 | T2: 116.02 | U2: 22623.9 | W2: שווי הוגן | X2: 0.0009 | Y2: 0.27615 | Z2: 0.21264
A3: 520042177 | B3: 12936 | C3: האוצר - ממשלתית צמודה | D3: ממשל צמודה 1028 | E3: IL0011973265 | F3: צמוד למדד המחירים לצרכן בריבית קבועה | G3: ישראל | H3: ישראל | I3: TASE | J3: RF.il | K3: מידרוג Moodys | L3: ILS | M3: 3.97 | N3: 30/10/2028 | O3: 0.01026 | P3: 0.018 | R3: 12500000 | S3: 1 | T3: 102.6 | U3: 12825 | W3: שווי הוגן | X3: 0.00061 | Y3: 0.15654 | Z3: 0.12054
A4: 520042177 | B4: 12936 | C4: האוצר - ממשלתית שקלית | D4: ממשלתי שקלי 0425 | E4: IL0011626681 | F4: לא צמוד למדד המחירים לצרכן ריבית קבועה | G4: ישראל | H4: ישראל | I4: TASE | J4: RF.il | K4: מידרוג Moodys | L4: ILS | M4: 0.58 | N4: 30/04/2025 | O4: -0.00169 | P4: 0.0396 | R4: 11689889 | S4: 1 | T4: 98.27 | U4: 11487.654 | W4: שווי הוגן | X4: 0.00074 | Y4: 0.14022 | Z4: 0.10797
A5: 520042177 | B5: 12936 | C5: האוצר - ממשלתית שקלית | D5: ממשק0142 | E5: IL0011254005 | F5: לא צמוד למדד המחירים לצרכן ריבית קבועה | G5: ישראל | H5: ישראל | I5: TASE | J5: ilRF | K5: S&P מעלות | L5: ILS | M5: 11.32 | N5: 31/01/2042 | O5: 0.03673 | P5: 0.0517 | R5: 7227442 | S5: 1 | T5: 107.34 | U5: 7757.936 | W5: שווי הוגן | X5: 0.00033 | Y5: 0.09469 | Z5: 0.07291
A6: 520042177 | B6: 12936 | C6: האוצר - ממשלתית שקלית | D6: ממשל שקלית 0226 | E6: IL0011746976 | F6: לא צמוד למדד המחירים לצרכן ריבית קבועה | G6: ישראל | H6: ישראל | I6: TASE | J6: RF.il | K6: מידרוג Moodys | L6: ILS | M6: 1.4 | N6: 27/02/2026 | O6: 0.03966 | P6: 0.0438 | R6: 4685000 | S6: 1 | T6: 95.1 | U6: 4455.435 | W6: שווי הוגן | X6: 0.00017 | Y6: 0.05438 | Z6: 0.04188
A7: 520042177 | B7: 12936 | C7: האוצר - ממשלתית משתנה | D7: ממשלת משתנה 1130 | E7: IL0011665523 | F7: לא צמוד למדד המחירים לצרכן ריבית משתנה | G7: ישראל | H7: ישראל | I7: TASE | J7: ilRF | K7: S&P מעלות | L7: ILS | M7: 5.42 | N7: 29/11/2030 | O7: 0.00495 | P7: 0.0484 | R7: 4397500 | S7: 1 | T7: 97.9 | U7: 4305.153 | W7: שווי הוגן | X7: 0.00014 | Y7: 0.05255 | Z7: 0.04046
A8: 520042177 | B8: 12936 | C8: האוצר - ממשלתית שקלית | D8: ממשל שקלית 0330 | E8: IL0011609851 | F8: לא צמוד למדד המחירים לצרכן ריבית קבועה | G8: ישראל | H8: ישראל | I8: TASE | J8: ilRF | K8: S&P מעלות | L8: ILS | M8: 5.33 | N8: 31/03/2030 | O8: 0.03461 | P8: 0.0463 | R8: 3650000 | S8: 1 | T8: 83.24 | U8: 3038.26 | W8: שווי הוגן | X8: 0.0001 | Y8: 0.03709 | Z8: 0.02856
A9: 520042177 | B9: 12936 | C9: האוצר - ממשלתית משתנה | D9: ממשל משתנה 0526 | E9: IL0011417958 | F9: לא צמוד למדד המחירים לצרכן ריבית משתנה | G9: ישראל | H9: ישראל | I9: TASE | J9: ilRF | K9: S&P מעלות | L9: ILS | M9: 1.61 | N9: 31/05/2026 | O9: 0.00246 | P9: 0.047 | R9: 2380000 | S9: 1 | T9: 99.82 | U9: 2375.716 | W9: שווי הוגן | X9: 0.00011 | Y9: 0.029 | Z9: 0.02233
A10: 520042177 | B10: 12936 | C10: האוצר - ממשלתית שקלית | D10: ממשלתי 0825 | E10: IL0011355570 | F10: לא צמוד למדד המחירים לצרכן ריבית קבועה | G10: ישראל | H10: ישראל | I10: TASE | J10: ilRF | K10: S&P מעלות | L10: ILS | M10: 0.92 | N10: 31/08/2025 | O10: -0.00365 | P10: 0.0417 | R10: 1958268 | S10: 1 | T10: 98.02 | U10: 1919.494 | W10: שווי הוגן | X10: 8e-05 | Y10: 0.02343 | Z10: 0.01804
A11: 520042177 | B11: 12936 | C11: בנק ישראל- מק"מ | D11: מ.ק.מ. 315 | E11: IL0082503181 | F11: מק"מ קצר משנים עשר חודשים | G11: ישראל | H11: ישראל | I11: TASE | J11: ilRF | K11: S&P מעלות | L11: ILS | M11: 0.42 | N11: 05/03/2025 | O11: 0.04072 | P11: 0.0432 | R11: 1590000 | S11: 1 | T11: 98.22 | U11: 1561.698 | W11: שווי הוגן | X11: 0.00013 | Y11: 0.01906 | Z11: 0.01468
A12: 520042177 | B12: 12936 | C12: בנק ישראל- מק"מ | D12: מ.ק.מ. 815 | E12: IL0082508131 | F12: מק"מ קצר משנים עשר חודשים | G12: ישראל | H12: ישראל | I12: TASE | J12: RF.il | K12: מידרוג Moodys | L12: ILS | M12: 0.85 | N12: 06/08/2025 | O12: 0.04121 | P12: 0.0432 | R12: 1343000 | S12: 1 | T12: 96.48 | U12: 1295.726 | W12: שווי הוגן | X12: 0.00011 | Y12: 0.01582 | Z12: 0.01218
A13: 520042177 | B13: 12936 | C13: האוצר - ממשלתית צמודה | D13: ממשל צמודה 1131 | E13: IL0011722209 | F13: צמוד למדד המחירים לצרכן בריבית קבועה | G13: ישראל | H13: ישראל | I13: TASE | J13: RF.il | K13: מידרוג Moodys | L13: ILS | M13: 7.14 | N13: 30/11/2031 | O13: -0.00914 | P13: 0.0199 | R13: 1120000 | S13: 1 | T13: 101.1 | U13: 1132.32 | W13: שווי הוגן | X13: 4e-05 | Y13: 0.01382 | Z13: 0.01064
A14: 520042177 | B14: 12936 | C14: האוצר - ממשלתית צמודה | D14: ממשל צמודה 0529 | E14: IL0011570236 | F14: צמוד למדד המחירים לצרכן בריבית קבועה | G14: ישראל | H14: ישראל | I14: TASE | J14: RF.il | K14: מידרוג Moodys | L14: ILS | M14: 4.61 | N14: 31/05/2029 | O14: -0.01735 | P14: 0.0183 | R14: 969270 | S14: 1 | T14: 108.85 | U14: 1055.05 | W14: שווי הוגן | X14: 4e-05 | Y14: 0.01288 | Z14: 0.00992
A15: 520042177 | B15: 12936 | C15: בנק ישראל- מק"מ | D15: מ.ק.מ. 915 | E15: IL0082509121 | F15: מק"מ קצר משנים עשר חודשים | G15: ישראל | H15: ישראל | I15: TASE | J15: RF.il | K15: מידרוג Moodys | L15: ILS | M15: 0.92 | N15: 03/09/2025 | O15: 0.04253 | P15: 0.0429 | R15: 780000 | S15: 1 | T15: 96.2 | U15: 750.36 | W15: שווי הוגן | X15: 6e-05 | Y15: 0.00916 | Z15: 0.00705
A16: 520042177 | B16: 12936 | C16: האוצר - ממשלתית שקלית | D16: ממשל שקלית 0229 | E16: IL0011948028 | F16: לא צמוד למדד המחירים לצרכן ריבית קבועה | G16: ישראל | H16: ישראל | I16: TASE | J16: RF.il | K16: מידרוג Moodys | L16: ILS | M16: 4.06 | N16: 28/02/2029 | O16: 0.03504 | P16: 0.0456 | R16: 600000 | S16: 1 | T16: 99.02 | U16: 594.12 | W16: שווי הוגן | X16: 2e-05 | Y16: 0.00725 | Z16: 0.00558
A17: 520042177 | B17: 12936 | C17: האוצר - ממשלתית צמודה | D17: ממשל צמודה 0726 | E17: IL0011695645 | F17: צמוד למדד המחירים לצרכן בריבית קבועה | G17: ישראל | H17: ישראל | I17: TASE | J17: RF.il | K17: מידרוג Moodys | L17: ILS | M17: 1.83 | N17: 31/07/2026 | O17: 0.01508 | P17: 0.0157 | R17: 500000 | S17: 1 | T17: 112.44 | U17: 562.2 | W17: שווי הוגן | X17: 2e-05 | Y17: 0.00686 | Z17: 0.00528
A18: 520042177 | B18: 12936 | C18: האוצר - ממשלתית שקלית | D18: ממשק 1026 | E18: IL0010994569 | F18: לא צמוד למדד המחירים לצרכן ריבית קבועה | G18: ישראל | H18: ישראל | I18: TASE | J18: ilRF | K18: S&P מעלות | L18: ILS | M18: 1.91 | N18: 30/10/2026 | O18: 0.03708 | P18: 0.0432 | R18: 500000 | S18: 1 | T18: 109.5 | U18: 547.5 | W18: שווי הוגן | X18: 3e-05 | Y18: 0.00668 | Z18: 0.00515
A19: 520042177 | B19: 12936 | C19: בנק ישראל- מק"מ | D19: מ.ק.מ. 415 | E19: IL0082504171 | F19: מק"מ קצר משנים עשר חודשים | G19: ישראל | H19: ישראל | I19: TASE | J19: ilRF | K19: S&P מעלות | L19: ILS | M19: 0.5 | N19: 02/04/2025 | O19: 0.04241 | P19: 0.0432 | R19: 500000 | S19: 1 | T19: 97.9 | U19: 489.5 | W19: שווי הוגן | X19: 4e-05 | Y19: 0.00597 | Z19: 0.0046
A20: 520042177 | B20: 12936 | C20: בנק ישראל- מק"מ | D20: מ.ק.מ. 125 | E20: IL0082501284 | F20: מק"מ קצר משנים עשר חודשים | G20: ישראל | H20: ישראל | I20: TASE | J20: ilRF | K20: S&P מעלות | L20: ILS | M20: 0.27 | N20: 08/01/2025 | O20: 0.0398 | P20: 0.0432 | R20: 300000 | S20: 1 | T20: 98.86 | U20: 296.58 | W20: שווי הוגן | X20: 2e-05 | Y20: 0.00362 | Z20: 0.00279
A21: 520042177 | B21: 12936 | C21: ממשלת ארה"ב | D21: US TREASURY 4.0 15/02/34 | E21: US91282CJZ59 | F21: נקוב במט"ח | G21: חו"ל | H21: ארה"ב | I21: אחר | J21: AA+ | K21: Fitch | L21: USD | M21: 7.736 | N21: 15/02/2034 | O21: 0.03842 | P21: 0.03766 | R21: 750000 | S21: 3.71 | T21: =U21*1000/R21/S21*100 -> 102.51562 | U21: 2852.497 | W21: שווי הוגן | X21: 1e-05 | Y21: 0.03482 | Z21: 0.02681
A22: 520042177 | B22: 12937 | C22: האוצר - ממשלתית צמודה | D22: ממשל צמודה 1025 | E22: IL0011359127 | F22: צמוד למדד המחירים לצרכן בריבית קבועה | G22: ישראל | H22: ישראל | I22: TASE | J22: ilRF | K22: S&P מעלות | L22: ILS | M22: 1.07 | N22: 31/10/2025 | O22: 0.00131 | P22: 0.013 | R22: 102560594 | S22: 1 | T22: 116.02 | U22: 118990.8 | W22: שווי הוגן | X22: 0.00473 | Y22: 0.39823 | Z22: 0.11007
A23: 520042177 | B23: 12937 | C23: בנק ישראל- מק"מ | D23: מ.ק.מ. 915 | E23: IL0082509121 | F23: מק"מ קצר משנים עשר חודשים | G23: ישראל | H23: ישראל | I23: TASE | J23: RF.il | K23: מידרוג Moodys | L23: ILS | M23: 0.92 | N23: 03/09/2025 | O23: 0.04241 | P23: 0.0429 | R23: 49386000 | S23: 1 | T23: 96.2 | U23: 47509.332 | W23: שווי הוגן | X23: 0.00412 | Y23: 0.159 | Z23: 0.04395
A24: 520042177 | B24: 12937 | C24: האוצר - ממשלתית משתנה | D24: ממשל משתנה 0526 | E24: IL0011417958 | F24: לא צמוד למדד המחירים לצרכן ריבית משתנה | G24: ישראל | H24: ישראל | I24: TASE | J24: ilRF | K24: S&P מעלות | L24: ILS | M24: 1.61 | N24: 31/05/2026 | O24: 0.0005 | P24: 0.047 | R24: 44252501 | S24: 1 | T24: 99.82 | U24: 44172.846 | W24: שווי הוגן | X24: 0.00209 | Y24: 0.14783 | Z24: 0.04086
A25: 520042177 | B25: 12937 | C25: האוצר - ממשלתית שקלית | D25: ממשק0142 | E25: IL0011254005 | F25: לא צמוד למדד המחירים לצרכן ריבית קבועה | G25: ישראל | H25: ישראל | I25: TASE | J25: ilRF | K25: S&P מעלות | L25: ILS | M25: 11.32 | N25: 31/01/2042 | O25: 0.03769 | P25: 0.0517 | R25: 22673998 | S25: 1 | T25: 107.34 | U25: 24338.269 | W25: שווי הוגן | X25: 0.00103 | Y25: 0.08145 | Z25: 0.02251
A26: 520042177 | B26: 12937 | C26: בנק ישראל- מק"מ | D26: מ.ק.מ. 515 | E26: IL0082505160 | F26: מק"מ קצר משנים עשר חודשים | G26: ישראל | H26: ישראל | I26: TASE | J26: ilRF | K26: S&P מעלות | L26: ILS | M26: 0.6 | N26: 07/05/2025 | O26: 0.04218 | P26: 0.0429 | R26: 13163000 | S26: 1 | T26: 97.52 | U26: 12836.558 | W26: שווי הוגן | X26: 0.00094 | Y26: 0.04296 | Z26: 0.01187
A27: 520042177 | B27: 12937 | C27: האוצר - ממשלתית שקלית | D27: ממשלתי 0825 | E27: IL0011355570 | F27: לא צמוד למדד המחירים לצרכן ריבית קבועה | G27: ישראל | H27: ישראל | I27: TASE | J27: ilRF | K27: S&P מעלות | L27: ILS | M27: 0.92 | N27: 31/08/2025 | O27: 0.03173 | P27: 0.0417 | R27: 12745000 | S27: 1 | T27: 98.02 | U27: 12492.649 | W27: שווי הוגן | X27: 0.00054 | Y27: 0.04181 | Z27: 0.01156
A28: 520042177 | B28: 12937 | C28: בנק ישראל- מק"מ | D28: מ.ק.מ. 315 | E28: IL0082503181 | F28: מק"מ קצר משנים עשר חודשים | G28: ישראל | H28: ישראל | I28: TASE | J28: ilRF | K28: S&P מעלות | L28: ILS | M28: 0.42 | N28: 05/03/2025 | O28: 0.04071 | P28: 0.0432 | R28: 12250000 | S28: 1 | T28: 98.22 | U28: 12031.95 | W28: שווי הוגן | X28: 0.00102 | Y28: 0.04027 | Z28: 0.01113
A29: 520042177 | B29: 12937 | C29: האוצר - ממשלתית צמודה | D29: ממשלתי צמוד 0527 | E29: IL0011408478 | F29: צמוד למדד המחירים לצרכן בריבית קבועה | G29: ישראל | H29: ישראל | I29: TASE | J29: RF.il | K29: מידרוג Moodys | L29: ILS | M29: 2.64 | N29: 31/05/2027 | O29: -0.03607 | P29: 0.0163 | R29: 10000000 | S29: 1 | T29: 114.25 | U29: 11425 | W29: שווי הוגן | X29: 0.00045 | Y29: 0.03824 | Z29: 0.01057
A30: 520042177 | B30: 12937 | C30: האוצר - ממשלתית שקלית | D30: ממשל שקלית 0229 | E30: IL0011948028 | F30: לא צמוד למדד המחירים לצרכן ריבית קבועה | G30: ישראל | H30: ישראל | I30: TASE | J30: RF.il | K30: מידרוג Moodys | L30: ILS | M30: 4.06 | N30: 28/02/2029 | O30: 0.0387 | P30: 0.0456 | R30: 4500000 | S30: 1 | T30: 99.02 | U30: 4455.9 | W30: שווי הוגן | X30: 0.00014 | Y30: 0.01491 | Z30: 0.00412
A31: 520042177 | B31: 12937 | C31: האוצר - ממשלתית צמודה | D31: ממשל צמודה 1033 | E31: IL0012043795 | F31: צמוד למדד המחירים לצרכן בריבית קבועה | G31: ישראל | H31: ישראל | I31: TASE | J31: ilRF | K31: S&P מעלות | L31: ILS | M31: 8.43 | N31: 31/10/2033 | O31: 0.018 | P31: 0.0213 | R31: 2800000 | S31: 1 | T31: 100.1 | U31: 2802.8 | W31: שווי הוגן | X31: 0.00027 | Y31: 0.00938 | Z31: 0.00259
A32: 520042177 | B32: 12937 | C32: האוצר - ממשלתית משתנה | D32: ממשלת משתנה 1130 | E32: IL0011665523 | F32: לא צמוד למדד המחירים לצרכן ריבית משתנה | G32: ישראל | H32: ישראל | I32: TASE | J32: ilRF | K32: S&P מעלות | L32: ILS | M32: 5.42 | N32: 29/11/2030 | O32: 0.00515 | P32: 0.0484 | R32: 2861000 | S32: 1 | T32: 97.9 | U32: 2800.919 | W32: שווי הוגן | X32: 9e-05 | Y32: 0.00937 | Z32: 0.00259
A33: 520042177 | B33: 12937 | C33: האוצר - ממשלתית צמודה | D33: ממשל צמודה 1028 | E33: IL0011973265 | F33: צמוד למדד המחירים לצרכן בריבית קבועה | G33: ישראל | H33: ישראל | I33: TASE | J33: RF.il | K33: מידרוג Moodys | L33: ILS | M33: 3.97 | N33: 30/10/2028 | O33: 0.00918 | P33: 0.018 | R33: 2235000 | S33: 1 | T33: 102.6 | U33: 2293.11 | W33: שווי הוגן | X33: 0.00011 | Y33: 0.00767 | Z33: 0.00212
... A132: 520042177 | B132: 142 | C132: בנק ישראל- מק"מ | D132: מ.ק.מ. 615 | E132: IL0082506150 | F132: מק"מ קצר משנים עשר חודשים | G132: ישראל | H132: ישראל | I132: TASE | J132: ilRF | K132: S&P מעלות | L132: ILS | M132: 0.67 | N132: 04/06/2025 | O132: 0.0432 | P132: 0.0427 | R132: 8000000 | S132: 1 | T132: 97.22 | U132: 7777.6 | W132: שווי הוגן | X132: 0.00067 | Y132: 0.09496 | Z132: 0.01191
A133: 520042177 | B133: 142 | C133: ממשלת ארה"ב | D133: US TREASURY 0.5 28/02/26 | E133: US91282CBQ33 | F133: נקוב במט"ח | G133: חו"ל | H133: ארה"ב | I133: אחר | J133: AA+ | K133: Fitch | L133: USD | M133: 1.382 | N133: 28/02/2026 | O133: 0.05108 | P133: 0.03757 | R133: 6500000 | S133: 3.71 | T133: =U133*1000/R133/S133*100 -> 95.635468 | U133: 23062.493 | W133: שווי הוגן | X133: 9e-05 | Y133: 0.28158 | Z133: 0.03532
A134: 520042177 | B134: 143 | C134: האוצר - ממשלתית צמודה | D134: ממשלתי צמוד 0527 | E134: IL0011408478 | F134: צמוד למדד המחירים לצרכן בריבית קבועה | G134: ישראל | H134: ישראל | I134: TASE | J134: RF.il | K134: מידרוג Moodys | L134: ILS | M134: 2.64 | N134: 31/05/2027 | O134: -0.00894 | P134: 0.0163 | R134: 122350000 | S134: 1 | T134: 114.25 | U134: 139784.88 | W134: שווי הוגן | X134: 0.00549 | Y134: 0.11429 | Z134: 0.04986
A135: 520042177 | B135: 143 | C135: האוצר - ממשלתית שקלית | D135: ממשל שקלית 0335 | E135: IL0012023326 | F135: לא צמוד למדד המחירים לצרכן ריבית קבועה | G135: ישראל | H135: ישראל | I135: TASE | J135: ilRF | K135: S&P מעלות | L135: ILS | M135: 8.52 | N135: 30/03/2035 | O135: 0.04525 | P135: 0.0488 | R135: 111500000 | S135: 1 | T135: 94.93 | U135: 105846.95 | W135: שווי הוגן | X135: 0.00644 | Y135: 0.08654 | Z135: 0.03775
A136: 520042177 | B136: 143 | C136: בנק ישראל- מק"מ | D136: מ.ק.מ. 1214 | E136: IL0082412185 | F136: מק"מ קצר משנים עשר חודשים | G136: ישראל | H136: ישראל | I136: TASE | J136: ilRF | K136: S&P מעלות | L136: ILS | M136: 0.18 | N136: 04/12/2024 | O136: 0.04088 | P136: 0.0427 | R136: 95000000 | S136: 1 | T136: 99.27 | U136: 94306.5 | W136: שווי הוגן | X136: 0.00238 | Y136: 0.07711 | Z136: 0.03364
A137: 520042177 | B137: 143 | C137: בנק ישראל- מק"מ | D137: מ.ק.מ. 415 | E137: IL0082504171 | F137: מק"מ קצר משנים עשר חודשים | G137: ישראל | H137: ישראל | I137: TASE | J137: ilRF | K137: S&P מעלות | L137: ILS | M137: 0.5 | N137: 02/04/2025 | O137: 0.0409 | P137: 0.0432 | R137: 85000000 | S137: 1 | T137: 97.9 | U137: 83215 | W137: שווי הוגן | X137: 0.00708 | Y137: 0.06804 | Z137: 0.02968
A138: 520042177 | B138: 143 | C138: בנק ישראל- מק"מ | D138: מ.ק.מ. 915 | E138: IL0082509121 | F138: מק"מ קצר משנים עשר חודשים | G138: ישראל | H138: ישראל | I138: TASE | J138: RF.il | K138: מידרוג Moodys | L138: ILS | M138: 0.92 | N138: 03/09/2025 | O138: 0.04158 | P138: 0.0429 | R138: 85000000 | S138: 1 | T138: 96.2 | U138: 81770 | W138: שווי הוגן | X138: 0.00708 | Y138: 0.06686 | Z138: 0.02916
A139: 520042177 | B139: 143 | C139: בנק ישראל- מק"מ | D139: מ.ק.מ. 815 | E139: IL0082508131 | F139: מק"מ קצר משנים עשר חודשים | G139: ישראל | H139: ישראל | I139: TASE | J139: RF.il | K139: מידרוג Moodys | L139: ILS | M139: 0.85 | N139: 06/08/2025 | O139: 0.04039 | P139: 0.0432 | R139: 75000000 | S139: 1 | T139: 96.48 | U139: 72360 | W139: שווי הוגן | X139: 0.00625 | Y139: 0.05916 | Z139: 0.02581
A140: 520042177 | B140: 143 | C140: בנק ישראל- מק"מ | D140: מ.ק.מ. 315 | E140: IL0082503181 | F140: מק"מ קצר משנים עשר חודשים | G140: ישראל | H140: ישראל | I140: TASE | J140: ilRF | K140: S&P מעלות | L140: ILS | M140: 0.42 | N140: 05/03/2025 | O140: 0.03995 | P140: 0.0432 | R140: 70000000 | S140: 1 | T140: 98.22 | U140: 68754 | W140: שווי הוגן | X140: 0.00583 | Y140: 0.05622 | Z140: 0.02452
A141: 520042177 | B141: 143 | C141: האוצר - ממשלתית צמודה | D141: ממשל צמודה 0726 | E141: IL0011695645 | F141: צמוד למדד המחירים לצרכן בריבית קבועה | G141: ישראל | H141: ישראל | I141: TASE | J141: RF.il | K141: מידרוג Moodys | L141: ILS | M141: 1.83 | N141: 31/07/2026 | O141: 0.01401 | P141: 0.0157 | R141: 51500000 | S141: 1 | T141: 112.44 | U141: 57906.6 | W141: שווי הוגן | X141: 0.00255 | Y141: 0.04735 | Z141: 0.02065
A142: 520042177 | B142: 143 | C142: בנק ישראל- מק"מ | D142: מ.ק.מ. 215 | E142: IL0082502191 | F142: מק"מ קצר משנים עשר חודשים | G142: ישראל | H142: ישראל | I142: TASE | J142: ilRF | K142: S&P מעלות | L142: ILS | M142: 0.35 | N142: 05/02/2025 | O142: 0.04215 | P142: 0.0426 | R142: 55000000 | S142: 1 | T142: 98.56 | U142: 54208 | W142: שווי הוגן | X142: 0.00458 | Y142: 0.04432 | Z142: 0.01933
A143: 520042177 | B143: 143 | C143: האוצר - ממשלתית שקלית | D143: ממשל שקלית 0537 | E143: IL0011661803 | F143: לא צמוד למדד המחירים לצרכן ריבית קבועה | G143: ישראל | H143: ישראל | I143: TASE | J143: ilRF | K143: S&P מעלות | L143: ILS | M143: 11.26 | N143: 31/05/2037 | O143: 0.04479 | P143: 0.0504 | R143: 72000000 | S143: 1 | T143: 67.92 | U143: 48902.4 | W143: שווי הוגן | X143: 0.00224 | Y143: 0.03998 | Z143: 0.01744
A144: 520042177 | B144: 143 | C144: בנק ישראל- מק"מ | D144: מ.ק.מ. 515 | E144: IL0082505160 | F144: מק"מ קצר משנים עשר חודשים | G144: ישראל | H144: ישראל | I144: TASE | J144: ilRF | K144: S&P מעלות | L144: ILS | M144: 0.6 | N144: 07/05/2025 | O144: 0.04285 | P144: 0.0429 | R144: 50000000 | S144: 1 | T144: 97.52 | U144: 48760 | W144: שווי הוגן | X144: 0.00357 | Y144: 0.03987 | Z144: 0.01739
A145: 520042177 | B145: 143 | C145: האוצר - ממשלתית צמודה | D145: ממשל צמודה 1033 | E145: IL0012043795 | F145: צמוד למדד המחירים לצרכן בריבית קבועה | G145: ישראל | H145: ישראל | I145: TASE | J145: ilRF | K145: S&P מעלות | L145: ILS | M145: 8.43 | N145: 31/10/2033 | O145: 0.01954 | P145: 0.0213 | R145: 40000000 | S145: 1 | T145: 100.1 | U145: 40040 | W145: שווי הוגן | X145: 0.00393 | Y145: 0.03274 | Z145: 0.01428
... A156: 520042177 | B156: 143 | C156: בנק ישראל- מק"מ | D156: מ.ק.מ. 715 | E156: IL0082507141 | F156: מק"מ קצר משנים עשר חודשים | G156: ישראל | H156: ישראל | I156: TASE | J156: ilRF | K156: S&P מעלות | L156: ILS | M156: 0.75 | N156: 02/07/2025 | O156: 0.04164 | P156: 0.0428 | R156: 3672222 | S156: 1 | T156: 96.9 | U156: 3558.383 | W156: שווי הוגן | X156: 0.00031 | Y156: 0.00291 | Z156: 0.00127
A157: 520042177 | B157: 143 | C157: ממשלת ארה"ב | D157: US TREASURY 0.5 28/02/26 | E157: US91282CBQ33 | F157: נקוב במט"ח | G157: חו"ל | H157: ארה"ב | I157: אחר | J157: AA+ | K157: Fitch | L157: USD | M157: 1.382 | N157: 28/02/2026 | O157: 0.04317 | P157: 0.03757 | R157: 29500000 | S157: 3.71 | T157: =U157*1000/R157/S157*100 -> 95.635466 | U157: 104668.24 | W157: שווי הוגן | X157: 0.00041 | Y157: 0.08558 | Z157: 0.03733
A158: 520042177 | B158: 14318 | C158: בנק ישראל- מק"מ | D158: מ.ק.מ. 315 | E158: IL0082503181 | F158: מק"מ קצר משנים עשר חודשים | G158: ישראל | H158: ישראל | I158: TASE | J158: ilRF | K158: S&P מעלות | L158: ILS | M158: 0.42 | N158: 05/03/2025 | O158: 0.04286 | P158: 0.0432 | R158: 137557 | S158: 1 | T158: 98.22 | U158: 135.108 | W158: שווי הוגן | X158: 1e-05 | Y158: 1 | Z158: 0.05692
A159: 520042177 | B159: 14406 | C159: בנק ישראל- מק"מ | D159: מ.ק.מ. 715 | E159: IL0082507141 | F159: מק"מ קצר משנים עשר חודשים | G159: ישראל | H159: ישראל | I159: TASE | J159: ilRF | K159: S&P מעלות | L159: ILS | M159: 0.75 | N159: 02/07/2025 | O159: 0.04188 | P159: 0.0428 | R159: 709752 | S159: 1 | T159: 96.9 | U159: 687.75 | W159: שווי הוגן | X159: 6e-05 | Y159: 0.35578 | Z159: 0.04675
A160: 520042177 | B160: 14406 | C160: בנק ישראל- מק"מ | D160: מ.ק.מ. 815 | E160: IL0082508131 | F160: מק"מ קצר משנים עשר חודשים | G160: ישראל | H160: ישראל | I160: TASE | J160: RF.il | K160: מידרוג Moodys | L160: ILS | M160: 0.85 | N160: 06/08/2025 | O160: 0.04241 | P160: 0.0432 | R160: 633226 | S160: 1 | T160: 96.48 | U160: 610.936 | W160: שווי הוגן | X160: 5e-05 | Y160: 0.31605 | Z160: 0.04152
A161: 520042177 | B161: 14406 | C161: בנק ישראל- מק"מ | D161: מ.ק.מ. 315 | E161: IL0082503181 | F161: מק"מ קצר משנים עשר חודשים | G161: ישראל | H161: ישראל | I161: TASE | J161: ilRF | K161: S&P מעלות | L161: ILS | M161: 0.42 | N161: 05/03/2025 | O161: 0.04288 | P161: 0.0432 | R161: 437651 | S161: 1 | T161: 98.22 | U161: 429.861 | W161: שווי הוגן | X161: 4e-05 | Y161: 0.22237 | Z161: 0.02922
A162: 520042177 | B162: 14406 | C162: בנק ישראל- מק"מ | D162: מ.ק.מ. 915 | E162: IL0082509121 | F162: מק"מ קצר משנים עשר חודשים | G162: ישראל | H162: ישראל | I162: TASE | J162: RF.il | K162: מידרוג Moodys | L162: ILS | M162: 0.92 | N162: 03/09/2025 | O162: 0.04203 | P162: 0.0429 | R162: 212599 | S162: 1 | T162: 96.2 | U162: 204.52 | W162: שווי הוגן | X162: 2e-05 | Y162: 0.1058 | Z162: 0.0139
A163: 520042177 | B163: 14425 | C163: האוצר - ממשלתית צמודה | D163: ממשלתי צמוד 0527 | E163: IL0011408478 | F163: צמוד למדד המחירים לצרכן בריבית קבועה | G163: ישראל | H163: ישראל | I163: TASE | J163: RF.il | K163: מידרוג Moodys | L163: ILS | M163: 2.64 | N163: 31/05/2027 | O163: -0.01872 | P163: 0.0163 | R163: 15729153 | S163: 1 | T163: 114.25 | U163: 17970.557 | W163: שווי הוגן | X163: 0.00071 | Y163: 0.19888 | Z163: 0.04776
A164: 520042177 | B164: 14425 | C164: האוצר - ממשלתית צמודה | D164: ממשל צמודה 0726 | E164: IL0011695645 | F164: צמוד למדד המחירים לצרכן בריבית קבועה | G164: ישראל | H164: ישראל | I164: TASE | J164: RF.il | K164: מידרוג Moodys | L164: ILS | M164: 1.83 | N164: 31/07/2026 | O164: 0.01278 | P164: 0.0157 | R164: 10837373 | S164: 1 | T164: 112.44 | U164: 12185.542 | W164: שווי הוגן | X164: 0.00054 | Y164: 0.13486 | Z164: 0.03238
A165: 520042177 | B165: 14425 | C165: האוצר - ממשלתית משתנה | D165: ממשלת משתנה 1130 | E165: IL0011665523 | F165: לא צמוד למדד המחירים לצרכן ריבית משתנה | G165: ישראל | H165: ישראל | I165: TASE | J165: ilRF | K165: S&P מעלות | L165: ILS | M165: 5.42 | N165: 29/11/2030 | O165: 0.00468 | P165: 0.0484 | R165: 10711674 | S165: 1 | T165: 97.9 | U165: 10486.729 | W165: שווי הוגן | X165: 0.00034 | Y165: 0.11606 | Z165: 0.02787
A166: 520042177 | B166: 14425 | C166: האוצר - ממשלתית שקלית | D166: ממשל שקלית 0928 | E166: IL0011508798 | F166: לא צמוד למדד המחירים לצרכן ריבית קבועה | G166: ישראל | H166: ישראל | I166: TASE | J166: ilRF | K166: S&P מעלות | L166: ILS | M166: 3.86 | N166: 29/09/2028 | O166: 0.03557 | P166: 0.0451 | R166: 9878818 | S166: 1 | T166: 91.9 | U166: 9078.634 | W166: שווי הוגן | X166: 0.00029 | Y166: 0.10047 | Z166: 0.02413
A167: 520042177 | B167: 14425 | C167: האוצר - ממשלתית צמודה | D167: ממשל צמודה 0529 | E167: IL0011570236 | F167: צמוד למדד המחירים לצרכן בריבית קבועה | G167: ישראל | H167: ישראל | I167: TASE | J167: RF.il | K167: מידרוג Moodys | L167: ILS | M167: 4.61 | N167: 31/05/2029 | O167: 0.0127 | P167: 0.0183 | R167: 6741299 | S167: 1 | T167: 108.85 | U167: 7337.904 | W167: שווי הוגן | X167: 0.00025 | Y167: 0.08121 | Z167: 0.0195
A168: 520042177 | B168: 14425 | C168: האוצר - ממשלתית שקלית | D168: ממשל שקלית 0432 | E168: IL0011806606 | F168: לא צמוד למדד המחירים לצרכן ריבית קבועה | G168: ישראל | H168: ישראל | I168: TASE | J168: ilRF | K168: S&P מעלות | L168: ILS | M168: 7.17 | N168: 30/04/2032 | O168: 0.04709 | P168: 0.0475 | R168: 9018004 | S168: 1 | T168: 78.98 | U168: 7122.42 | W168: שווי הוגן | X168: 0.0003 | Y168: 0.07882 | Z168: 0.01893
A169: 520042177 | B169: 14425 | C169: בנק ישראל- מק"מ | D169: מ.ק.מ. 715 | E169: IL0082507141 | F169: מק"מ קצר משנים עשר חודשים | G169: ישראל | H169: ישראל | I169: TASE | J169: ilRF | K169: S&P מעלות | L169: ILS | M169: 0.75 | N169: 02/07/2025 | O169: 0.04148 | P169: 0.0428 | R169: 6393374 | S169: 1 | T169: 96.9 | U169: 6195.179 | W169: שווי הוגן | X169: 0.00053 | Y169: 0.06856 | Z169: 0.01646
... A273: 520042177 | B273: 8530 | C273: האוצר - ממשלתית משתנה | D273: ממשל משתנה 0526 | E273: IL0011417958 | F273: לא צמוד למדד המחירים לצרכן ריבית משתנה | G273: ישראל | H273: ישראל | I273: TASE | J273: ilRF | K273: S&P מעלות | L273: ILS | M273: 1.61 | N273: 31/05/2026 | O273: 0.00085 | P273: 0.047 | R273: 3321569 | S273: 1 | T273: 99.82 | U273: 3315.59 | W273: שווי הוגן | X273: 0.00016 | Y273: 0.00994 | Z273: 0.00958
A274: 520042177 | B274: 15108 | C274: בנק ישראל- מק"מ | D274: מ.ק.מ. 1214 | E274: IL0082412185 | F274: מק"מ קצר משנים עשר חודשים | G274: ישראל | H274: ישראל | I274: TASE | J274: ilRF | K274: S&P מעלות | L274: ILS | M274: 0.18 | N274: 04/12/2024 | O274: 0.04262 | P274: 0.0427 | R274: 46000000 | S274: 1 | T274: 99.27 | U274: 45664.2 | W274: שווי הוגן | X274: 0.00115 | Y274: 0.23312 | Z274: 0.07732
A275: 520042177 | B275: 15108 | C275: בנק ישראל- מק"מ | D275: מ.ק.מ. 1014 | E275: IL0082410106 | F275: מק"מ קצר משנים עשר חודשים | G275: ישראל | H275: ישראל | I275: TASE | J275: ilRF | K275: S&P מעלות | L275: ILS | M275: 0.01 | N275: 02/10/2024 | O275: 0.0421 | P275: 0.1157 | R275: 41000000 | S275: 1 | T275: 99.97 | U275: 40987.7 | W275: שווי הוגן | X275: 0.00093 | Y275: 0.20924 | Z275: 0.0694
A276: 520042177 | B276: 15108 | C276: בנק ישראל- מק"מ | D276: מ.ק.מ. 1114 | E276: IL0082411195 | F276: מק"מ קצר משנים עשר חודשים | G276: ישראל | H276: ישראל | I276: TASE | J276: ilRF | K276: S&P מעלות | L276: ILS | M276: 0.1 | N276: 06/11/2024 | O276: 0.04198 | P276: 0.0436 | R276: 32851995 | S276: 1 | T276: 99.58 | U276: 32714.017 | W276: שווי הוגן | X276: 0.00082 | Y276: 0.16701 | Z276: 0.05539
A277: 520042177 | B277: 15108 | C277: בנק ישראל- מק"מ | D277: מ.ק.מ. 125 | E277: IL0082501284 | F277: מק"מ קצר משנים עשר חודשים | G277: ישראל | H277: ישראל | I277: TASE | J277: ilRF | K277: S&P מעלות | L277: ILS | M277: 0.27 | N277: 08/01/2025 | O277: 0.04299 | P277: 0.0432 | R277: 30010601 | S277: 1 | T277: 98.86 | U277: 29668.48 | W277: שווי הוגן | X277: 0.0025 | Y277: 0.15146 | Z277: 0.05024
A278: 520042177 | B278: 15108 | C278: בנק ישראל- מק"מ | D278: מ.ק.מ. 215 | E278: IL0082502191 | F278: מק"מ קצר משנים עשר חודשים | G278: ישראל | H278: ישראל | I278: TASE | J278: ilRF | K278: S&P מעלות | L278: ILS | M278: 0.35 | N278: 05/02/2025 | O278: 0.0423 | P278: 0.0426 | R278: 28600000 | S278: 1 | T278: 98.56 | U278: 28188.16 | W278: שווי הוגן | X278: 0.00238 | Y278: 0.1439 | Z278: 0.04773
A279: 520042177 | B279: 15108 | C279: בנק ישראל- מק"מ | D279: מ.ק.מ. 315 | E279: IL0082503181 | F279: מק"מ קצר משנים עשר חודשים | G279: ישראל | H279: ישראל | I279: TASE | J279: ilRF | K279: S&P מעלות | L279: ILS | M279: 0.42 | N279: 05/03/2025 | O279: 0.04166 | P279: 0.0432 | R279: 19000000 | S279: 1 | T279: 98.22 | U279: 18661.8 | W279: שווי הוגן | X279: 0.00158 | Y279: 0.09527 | Z279: 0.0316
A280: 520042177 | B280: 9300 | C280: האוצר - ממשלתית צמודה | D280: ממשל צמודה 1025 | E280: IL0011359127 | F280: צמוד למדד המחירים לצרכן בריבית קבועה | G280: ישראל | H280: ישראל | I280: TASE | J280: ilRF | K280: S&P מעלות | L280: ILS | M280: 1.07 | N280: 31/10/2025 | O280: -0.0023 | P280: 0.013 | R280: 26333540 | S280: 1 | T280: 116.02 | U280: 30552.173 | W280: שווי הוגן | X280: 0.00121 | Y280: 0.12218 | Z280: 0.10004
A281: 520042177 | B281: 9300 | C281: האוצר - ממשלתית צמודה | D281: ממשל צמודה 0726 | E281: IL0011695645 | F281: צמוד למדד המחירים לצרכן בריבית קבועה | G281: ישראל | H281: ישראל | I281: TASE | J281: RF.il | K281: מידרוג Moodys | L281: ILS | M281: 1.83 | N281: 31/07/2026 | O281: 0.00706 | P281: 0.0157 | R281: 23050550 | S281: 1 | T281: 112.44 | U281: 25918.038 | W281: שווי הוגן | X281: 0.00114 | Y281: 0.10364 | Z281: 0.08486
A282: 520042177 | B282: 9300 | C282: האוצר - ממשלתית צמודה | D282: ממשל צמודה 0529 | E282: IL0011570236 | F282: צמוד למדד המחירים לצרכן בריבית קבועה | G282: ישראל | H282: ישראל | I282: TASE | J282: RF.il | K282: מידרוג Moodys | L282: ILS | M282: 4.61 | N282: 31/05/2029 | O282: 0.00444 | P282: 0.0183 | R282: 23237725 | S282: 1 | T282: 108.85 | U282: 25294.264 | W282: שווי הוגן | X282: 0.00086 | Y282: 0.10115 | Z282: 0.08282
A283: 520042177 | B283: 9300 | C283: האוצר - ממשלתית צמודה | D283: ממשלתי צמוד 0527 | E283: IL0011408478 | F283: צמוד למדד המחירים לצרכן בריבית קבועה | G283: ישראל | H283: ישראל | I283: TASE | J283: RF.il | K283: מידרוג Moodys | L283: ILS | M283: 2.64 | N283: 31/05/2027 | O283: -0.01291 | P283: 0.0163 | R283: 16134000 | S283: 1 | T283: 114.25 | U283: 18433.095 | W283: שווי הוגן | X283: 0.00072 | Y283: 0.07371 | Z283: 0.06035
A284: 520042177 | B284: 9300 | C284: האוצר - ממשלתית שקלית | D284: ממשל שקלית 0327 | E284: IL0011393449 | F284: לא צמוד למדד המחירים לצרכן ריבית קבועה | G284: ישראל | H284: ישראל | I284: TASE | J284: ilRF | K284: S&P מעלות | L284: ILS | M284: 2.44 | N284: 31/03/2027 | O284: 0.00786 | P284: 0.044 | R284: 16786192 | S284: 1 | T284: 95.44 | U284: 16020.742 | W284: שווי הוגן | X284: 0.00065 | Y284: 0.06407 | Z284: 0.05246
A285: 520042177 | B285: 9300 | C285: האוצר - ממשלתית שקלית | D285: ממשלתי 0825 | E285: IL0011355570 | F285: לא צמוד למדד המחירים לצרכן ריבית קבועה | G285: ישראל | H285: ישראל | I285: TASE | J285: ilRF | K285: S&P מעלות | L285: ILS | M285: 0.92 | N285: 31/08/2025 | O285: 0.01219 | P285: 0.0417 | R285: 15287041 | S285: 1 | T285: 98.02 | U285: 14984.358 | W285: שווי הוגן | X285: 0.00064 | Y285: 0.05992 | Z285: 0.04906
A286: 520042177 | B286: 9300 | C286: האוצר - ממשלתית צמודה | D286: ממשל צמודה 1028 | E286: IL0011973265 | F286: צמוד למדד המחירים לצרכן בריבית קבועה | G286: ישראל | H286: ישראל | I286: TASE | J286: RF.il | K286: מידרוג Moodys | L286: ILS | M286: 3.97 | N286: 30/10/2028 | O286: 0.01272 | P286: 0.018 | R286: 13901189 | S286: 1 | T286: 102.6 | U286: 14262.62 | W286: שווי הוגן | X286: 0.00068 | Y286: 0.05704 | Z286: 0.0467
A287: 520042177 | B287: 9300 | C287: האוצר - ממשלתית שקלית | D287: ממשל שקלית 0928 | E287: IL0011508798 | F287: לא צמוד למדד המחירים לצרכן ריבית קבועה | G287: ישראל | H287: ישראל | I287: TASE | J287: ilRF | K287: S&P מעלות | L287: ILS | M287: 3.86 | N287: 29/09/2028 | O287: 0.00238 | P287: 0.0451 | R287: 11385546 | S287: 1 | T287: 91.9 | U287: 10463.317 | W287: שווי הוגן | X287: 0.00034 | Y287: 0.04184 | Z287: 0.03426
A288: 520042177 | B288: 9300 | C288: האוצר - ממשלתית שקלית | D288: ממשל שקלית 0226 | E288: IL0011746976 | F288: לא צמוד למדד המחירים לצרכן ריבית קבועה | G288: ישראל | H288: ישראל | I288: TASE | J288: RF.il | K288: מידרוג Moodys | L288: ILS | M288: 1.4 | N288: 27/02/2026 | O288: 0.01565 | P288: 0.0438 | R288: 8765000 | S288: 1 | T288: 95.1 | U288: 8335.515 | W288: שווי הוגן | X288: 0.00032 | Y288: 0.03333 | Z288: 0.02729
A289: 520042177 | B289: 9300 | C289: בנק ישראל- מק"מ | D289: מ.ק.מ. 915 | E289: IL0082509121 | F289: מק"מ קצר משנים עשר חודשים | G289: ישראל | H289: ישראל | I289: TASE | J289: RF.il | K289: מידרוג Moodys | L289: ILS | M289: 0.92 | N289: 03/09/2025 | O289: 0.04194 | P289: 0.0429 | R289: 7710000 | S289: 1 | T289: 96.2 | U289: 7417.02 | W289: שווי הוגן | X289: 0.00064 | Y289: 0.02966 | Z289: 0.02429
A290: 520042177 | B290: 9300 | C290: האוצר - ממשלתית קצרה | D290: ממשל קצרה 11/24 | E290: IL0012023243 | F290: לא צמוד למדד המחירים לצרכן ריבית קבועה | G290: ישראל | H290: ישראל | I290: TASE | J290: ilRF | K290: S&P מעלות | L290: ILS | M290: 0.16 | N290: 29/11/2024 | O290: 0.04194 | P290: 0.0425 | R290: 6995000 | S290: 1 | T290: 99.33 | U290: 6948.134 | W290: שווי הוגן | X290: 0.00076 | Y290: 0.02779 | Z290: 0.02275
A291: 520042177 | B291: 9300 | C291: בנק ישראל- מק"מ | D291: מ.ק.מ. 1114 | E291: IL0082411195 | F291: מק"מ קצר משנים עשר חודשים | G291: ישראל | H291: ישראל | I291: TASE | J291: ilRF | K291: S&P מעלות | L291: ILS | M291: 0.1 | N291: 06/11/2024 | O291: 0.04178 | P291: 0.0436 | R291: 6218000 | S291: 1 | T291: 99.58 | U291: 6191.884 | W291: שווי הוגן | X291: 0.00016 | Y291: 0.02476 | Z291: 0.02027
... A318: 520042177 | B318: 9300 | C318: מדינת ישראל | D318: ISRAEL 1.5 18/01/27 | E318: XS1551294256 | F318: נקוב במט"ח | G318: חו"ל | H318: ישראל | I318: אחר | J318: Baa1 | K318: Moodys | L318: EUR | M318: 2.161 | N318: 18/01/2027 | O318: 0.04316 | P318: 0.03854 | R318: 600000 | S318: 4.1524 | T318: 95.368 | U318: 2376.036 | W318: שווי הוגן | X318: 0.00021 | Y318: 0.0095 | Z318: 0.00778
A319: 520042177 | B319: 9300 | C319: ממשלת ארה"ב | D319: US TREASURY 2 15/11/41 | E319: US912810TC27 | F319: נקוב במט"ח | G319: חו"ל | H319: ארה"ב | I319: אחר | J319: AA+ | K319: Fitch | L319: USD | M319: 13.621 | N319: 15/11/2041 | O319: 0.05092 | P319: 0.04157 | R319: 460000 | S319: 3.71 | T319: =U319*1000/R319/S319*100 -> 74.515587 | U319: 1271.683 | W319: שווי הוגן | X319: 1e-05 | Y319: 0.00509 | Z319: 0.00416
A320: 520042177 | B320: 9300 | C320: ממשלת ארה"ב | D320: US TREASURY 3.25 30/06/29 | E320: US91282CEV90 | F320: נקוב במט"ח | G320: חו"ל | H320: ארה"ב | I320: אחר | J320: AA+ | K320: Fitch | L320: USD | M320: 4.319 | N320: 30/06/2029 | O320: 0.04946 | P320: 0.03559 | R320: 300000 | S320: 3.71 | T320: 99.625 | U320: 1108.826 | W320: שווי הוגן | X320: 1e-05 | Y320: 0.00443 | Z320: 0.00363
A321: 520042177 | B321: 9300 | C321: ממשלת ארה"ב | D321: US TREASURY 3 15/11/2044 | E321: US912810RJ97 | F321: נקוב במט"ח | G321: חו"ל | H321: ארה"ב | I321: אחר | J321: AA+ | K321: Fitch | L321: USD | M321: 14.205 | N321: 15/11/2044 | O321: 0.04313 | P321: 0.04212 | R321: 350000 | S321: 3.71 | T321: 84.875 | U321: 1102.102 | W321: שווי הוגן | X321: 1e-05 | Y321: 0.00441 | Z321: 0.00361
A322: 520042177 | B322: 9300 | C322: ממשלת ארה"ב | D322: US TREASURY 2.75 15/11/42 | E322: US912810QY73 | F322: נקוב במט"ח | G322: חו"ל | H322: ארה"ב | I322: אחר | J322: AA+ | K322: Fitch | L322: USD | M322: 13.465 | N322: 15/11/2042 | O322: 0.04012 | P322: 0.04155 | R322: 309000 | S322: 3.71 | T322: 83.281 | U322: 954.728 | W322: שווי הוגן | X322: 1e-05 | Y322: 0.00382 | Z322: 0.00313
A323: 520042177 | B323: 9300 | C323: ממשלת ארה"ב | D323: US TREASURY 3.5 15/02/39 | E323: US912810QA97 | F323: נקוב במט"ח | G323: חו"ל | H323: ארה"ב | I323: אחר | J323: AA+ | K323: Fitch | L323: USD | M323: 11.063 | N323: 15/02/2039 | O323: 0.04863 | P323: 0.03894 | R323: 230000 | S323: 3.71 | T323: 96.172 | U323: 820.635 | W323: שווי הוגן | X323: 1e-05 | Y323: 0.00328 | Z323: 0.00269
A324: 520042177 | B324: 9300 | C324: ממשלת ארה"ב | D324: US TREASURY 0 14/11/24 | E324: US912797LD70 | F324: נקוב במט"ח | G324: חו"ל | H324: ארה"ב | I324: אחר | J324: Aaa | K324: Moodys | L324: USD | M324: 0.117 | N324: 14/11/2024 | O324: 0.05407 | P324: 0.04702 | R324: 200000 | S324: 3.71 | T324: 99.437 | U324: 737.821 | W324: שווי הוגן | X324: 0 | Y324: 0.00295 | Z324: 0.00242
A325: 520042177 | B325: 9300 | C325: ממשלת ארה"ב | D325: US TREASURY 3.625 15/02/2044 | E325: US912810RE01 | F325: נקוב במט"ח | G325: חו"ל | H325: ארה"ב | I325: אחר | J325: AA+ | K325: Fitch | L325: USD | M325: 13.48 | N325: 15/02/2044 | O325: 0.04129 | P325: 0.04193 | R325: 200000 | S325: 3.71 | T325: 93.063 | U325: 690.524 | W325: שווי הוגן | X325: 0 | Y325: 0.00276 | Z325: 0.00226
A326: 520042177 | B326: 9300 | C326: ממשלת ארה"ב | D326: US TREASURY 1.125 15/08/40 | E326: US912810SQ22 | F326: נקוב במט"ח | G326: חו"ל | H326: ארה"ב | I326: אחר | J326: AA+ | K326: Fitch | L326: USD | M326: 13.86 | N326: 15/08/2040 | O326: 0.04996 | P326: 0.04081 | R326: 240000 | S326: 3.71 | T326: 65.859 | U326: 586.412 | W326: שווי הוגן | X326: 0 | Y326: 0.00235 | Z326: 0.00192
A327: 520042177 | B327: 9300 | C327: מדינת ישראל | D327: ISRAEL 5.5 12/03/34 | E327: US46514BRL35 | F327: נקוב במט"ח | G327: חו"ל | H327: ישראל | I327: אחר | J327: Baa1 | K327: Moodys | L327: USD | M327: 7.271 | N327: 12/03/2034 | O327: 0.05826 | P327: 0.05491 | R327: 150000 | S327: 3.71 | T327: 100.079 | U327: 556.94 | W327: שווי הוגן | X327: 5e-05 | Y327: 0.00223 | Z327: 0.00182
A328: 520042177 | B328: 9300 | C328: מדינת ישראל | D328: ISRAEL 5.75 12/03/54 | E328: US46514BRM18 | F328: נקוב במט"ח | G328: חו"ל | H328: ישראל | I328: אחר | J328: Baa1 | K328: Moodys | L328: USD | M328: 13.723 | N328: 12/03/2054 | O328: 0.05851 | P328: 0.06105 | R328: 120000 | S328: 3.71 | T328: 95.216 | U328: 423.899 | W328: שווי הוגן | X328: 4e-05 | Y328: 0.0017 | Z328: 0.00139
A329: 520042177 | B329: 9300 | C329: ממשלת ארה"ב | D329: US TREASURY 4.375 15/02/2038 | E329: US912810PW27 | F329: נקוב במט"ח | G329: חו"ל | H329: ארה"ב | I329: אחר | J329: AA+ | K329: Fitch | L329: USD | M329: 10.107 | N329: 15/02/2038 | O329: 0.04956 | P329: 0.03839 | R329: 105000 | S329: 3.71 | T329: 106.156 | U329: 413.532 | W329: שווי הוגן | X329: 0 | Y329: 0.00165 | Z329: 0.00135
A330: 520042177 | B330: 9300 | C330: ממשלת ארה"ב | D330: US TREASURY 4.5 15/11/33 | E330: US91282CJJ18 | F330: נקוב במט"ח | G330: חו"ל | H330: ארה"ב | I330: אחר | J330: AA+ | K330: Fitch | L330: USD | M330: 7.371 | N330: 15/11/2033 | O330: 0.03916 | P330: 0.03755 | R330: 100000 | S330: 3.71 | T330: 107.578 | U330: 399.115 | W330: שווי הוגן | X330: 0 | Y330: 0.0016 | Z330: 0.00131
A331: 520042177 | B331: 9300 | C331: ממשלת ארה"ב | D331: US TREASURY 3.375 15/05/44 | E331: US912810RG58 | F331: נקוב במט"ח | G331: חו"ל | H331: ארה"ב | I331: אחר | J331: AA+ | K331: Fitch | L331: USD | M331: 13.656 | N331: 15/05/2044 | O331: 0.04677 | P331: 0.04195 | R331: 117000 | S331: 3.71 | T331: 90.469 | U331: 392.698 | W331: שווי הוגן | X331: 0 | Y331: 0.00157 | Z331: 0.00129
... A400: 520042177 | B400: 9302 | C400: האוצר - ממשלתית שקלית | D400: ממשל שקלית 0432 | E400: IL0011806606 | F400: לא צמוד למדד המחירים לצרכן ריבית קבועה | G400: ישראל | H400: ישראל | I400: TASE | J400: ilRF | K400: S&P מעלות | L400: ILS | M400: 7.17 | N400: 30/04/2032 | O400: 0.04203 | P400: 0.0475 | R400: 6000000 | S400: 1 | T400: 78.98 | U400: 4738.8 | W400: שווי הוגן | X400: 0.0002 | Y400: 0.00348 | Z400: 0.00142
A401: 520042177 | B401: 9302 | C401: מדינת ישראל | D401: ISRAEL 5 30/10/26 | E401: XS2711443932 | F401: נקוב במט"ח | G401: חו"ל | H401: ישראל | I401: אחר | J401: Baa1 | K401: Moodys | L401: EUR | M401: 1.863 | N401: 30/10/2026 | O401: 0.03367 | P401: 0.03854 | R401: 1000000 | S401: 4.1524 | T401: =U401*1000/R401/S401*100 -> 106.65584 | U401: 4428.777 | W401: שווי הוגן | X401: 0.00042 | Y401: 0.00325 | Z401: 0.00132
A402: 520042177 | B402: 9302 | C402: האוצר - ממשלתית צמודה | D402: ממשלתי צמוד 0545 | E402: IL0011348658 | F402: צמוד למדד המחירים לצרכן בריבית קבועה | G402: ישראל | H402: ישראל | I402: TASE | J402: ilRF | K402: S&P מעלות | L402: ILS | M402: 18.4 | N402: 31/05/2045 | O402: 0.00249 | P402: 0.0227 | R402: 3171612 | S402: 1 | T402: 92.5 | U402: 2933.741 | W402: שווי הוגן | X402: 0.00016 | Y402: 0.00215 | Z402: 0.00088
A403: 520042177 | B403: 9302 | C403: האוצר - ממשלתית שקלית | D403: ממשל שקלית 1152 | E403: IL0011840761 | F403: לא צמוד למדד המחירים לצרכן ריבית קבועה | G403: ישראל | H403: ישראל | I403: TASE | J403: ilRF | K403: S&P מעלות | L403: ILS | M403: 16.7 | N403: 29/11/2052 | O403: 0.03261 | P403: 0.0544 | R403: 3381621 | S403: 1 | T403: 64.7 | U403: 2187.909 | W403: שווי הוגן | X403: 0.00019 | Y403: 0.00161 | Z403: 0.00065
A404: 520042177 | B404: 9302 | C404: האוצר - ממשלתית שקלית | D404: ממשק0142 | E404: IL0011254005 | F404: לא צמוד למדד המחירים לצרכן ריבית קבועה | G404: ישראל | H404: ישראל | I404: TASE | J404: ilRF | K404: S&P מעלות | L404: ILS | M404: 11.32 | N404: 31/01/2042 | O404: 0.0335 | P404: 0.0517 | R404: 1627356 | S404: 1 | T404: 107.34 | U404: 1746.804 | W404: שווי הוגן | X404: 7e-05 | Y404: 0.00128 | Z404: 0.00052
A405: 520042177 | B405: 9302 | C405: האוצר - ממשלתית שקלית | D405: ממשק 1026 | E405: IL0010994569 | F405: לא צמוד למדד המחירים לצרכן ריבית קבועה | G405: ישראל | H405: ישראל | I405: TASE | J405: ilRF | K405: S&P מעלות | L405: ILS | M405: 1.91 | N405: 30/10/2026 | O405: 0.04444 | P405: 0.0432 | R405: 855000 | S405: 1 | T405: 109.5 | U405: 936.225 | W405: שווי הוגן | X405: 6e-05 | Y405: 0.00069 | Z405: 0.00028
...

Sheet ניירות ערך מסחריים
A1: מספר קופה/קרן/ח.פ. עבור חברת ביטוח | B1: מספר מסלול | C1: שם מנפיק | D1: מספר מנפיק | E1: סוג מספר מזהה מנפיק | F1: שם נייר ערך | G1: מספר נייר ערך | H1: סוג מספר נייר ערך | I1: מאפיין עיקרי | J1: ישראל/חו"ל | K1: מדינה לפי חשיפה כלכלית | L1: זירת מסחר | M1: ענף מסחר | N1: בעל עניין/צד קשור | O1: דירוג | P1: שם מדרג | Q1: דירוג נייר הערך/המנפיק | R1: מטבע פעילות | S1: מח"מ | T1: ריבית עוגן | U1: מועד פדיון | V1: שיעור ריבית | W1: תשואה לפדיון | X1: נחיתות חוזית | Y1: האם סווג כחוב בעייתי | Z1: ערך נקוב (יחידות) | AA1: שער חליפין | AB1: שער נייר הערך | AC1: סכום לקבל (במטבע הפעילות) | AD1: שווי הוגן (באלפי ש"ח) | AE1: עלות מופחתת (באלפי ש"ח) | AF1: עלות מופחתת (במטבע הפעילות) | AG1: השיטה שיושמה בדוח הכספי | AH1: שיעור מערך נקוב מונפק | AI1: שיעור מנכסי אפיק ההשקעה | AJ1: שיעור מסך נכסי ההשקעה
A2: 520042177 | B2: 9300 | C2: מזרחי טפחות הנפ | D2: 520032046 | E2: ח.פ. | F2: מז טפ הנפ מסחרי3 | G2: IL0012075474 | H2: ISIN | I2: אחר | J2: ישראל | K2: ישראל | L2: TASE | M2: בנקים | N2: לא | O2: ilAAA | P2: S&P מעלות | Q2: נייר ערך | R2: ILS | S2: 0.68 | T2: ריבית בנק ישראל | U2: 05/06/2025 | V2: -0.90053 | W2: 0.0441 | X2: החוב לא נחות | Y2: לא | Z2: 20000 | AA2: 1 | AB2: 1015.42 | AD2: 203.084 | AG2: שווי הוגן | AH2: 1e-05 | AI2: 1 | AJ2: 0.00066
A3: 520042177 | B3: 9301 | C3: מזרחי טפחות הנפ | D3: 520032046 | E3: ח.פ. | F3: מז טפ הנפ מסחרי3 | G3: IL0012075474 | H3: ISIN | I3: אחר | J3: ישראל | K3: ישראל | L3: TASE | M3: בנקים | N3: לא | O3: ilAAA | P3: S&P מעלות | Q3: נייר ערך | R3: ILS | S3: 0.68 | T3: ריבית בנק ישראל | U3: 05/06/2025 | V3: -0.90053 | W3: 0.0441 | X3: החוב לא נחות | Y3: לא | Z3: 50000 | AA3: 1 | AB3: 1015.42 | AD3: 507.71 | AG3: שווי הוגן | AH3: 2e-05 | AI3: 1 | AJ3: 0.0007
A4: 520042177 | B4: 9302 | C4: מזרחי טפחות הנפ | D4: 520032046 | E4: ח.פ. | F4: מז טפ הנפ מסחרי3 | G4: IL0012075474 | H4: ISIN | I4: אחר | J4: ישראל | K4: ישראל | L4: TASE | M4: בנקים | N4: לא | O4: ilAAA | P4: S&P מעלות | Q4: נייר ערך | R4: ILS | S4: 0.68 | T4: ריבית בנק ישראל | U4: 05/06/2025 | V4: -0.90053 | W4: 0.0441 | X4: החוב לא נחות | Y4: לא | Z4: 330000 | AA4: 1 | AB4: 1015.42 | AD4: 3350.886 | AG4: שווי הוגן | AH4: 0.00015 | AI4: 1 | AJ4: 0.001
A5: 520042177 | B5: 12936
A6: 520042177 | B6: 12937
A7: 520042177 | B7: 12938
A8: 520042177 | B8: 13498
A9: 520042177 | B9: 13499
A10: 520042177 | B10: 13500
A11: 520042177 | B11: 141
A12: 520042177 | B12: 142
A13: 520042177 | B13: 143
A14: 520042177 | B14: 14318
A15: 520042177 | B15: 14406
A16: 520042177 | B16: 14425
... A23: 520042177 | B23: 8530
A24: 520042177 | B24: 15108
A25: 520042177 | B25: 9629
A26: 520042177 | B26: 9630
A27: 520042177 | B27: 9631
A28: 520042177 | B28: 9719
A29: 520042177 | B29: 9720
A30: 520042177 | B30: 9721
A31: 520042177 | B31: 9888

Sheet איגרות חוב
A1: מספר קופה/קרן/ח.פ. עבור חברת ביטוח | B1: מספר מסלול | C1: שם מנפיק | D1: מספר מנפיק | E1: סוג מספר מזהה מנפיק | F1: שם נייר ערך | G1: מספר נייר ערך | H1: סוג מספר נייר ערך | I1: מאפיין עיקרי | J1: ישראל/חו"ל | K1: מדינה לפי חשיפה כלכלית | L1: סטאטוס סחירות | M1: זירת מסחר | N1: ענף מסחר | O1: בעל עניין/צד קשור | P1: דירוג | Q1: שם מדרג | R1: דירוג נייר הערך/המנפיק | S1: מטבע פעילות | T1: מח"מ | U1: מועד פדיון | V1: שיעור ריבית | W1: תשואה לפדיון | X1: נחיתות חוזית | Y1: האם סווג כחוב בעייתי | Z1: ערך נקוב (יחידות) | AA1: שער חליפין | AB1: שער נייר הערך | AC1: סכום לקבל (במטבע הפעילות) | AD1: שווי הוגן (באלפי ש"ח) | AE1: עלות מופחתת (באלפי ש"ח) | AF1: עלות מופחתת (במטבע הפעילות) | AG1: השיטה שיושמה בדוח הכספי | AH1: שיעור מערך נקוב מונפק | AI1: שיעור מנכסי אפיק ההשקעה | AJ1: שיעור מסך נכסי ההשקעה
A2: 520042177 | B2: 12936 | C2: סטרוברי אינק | D2: 842336054 | E2: מספר תאגיד או שותפות בחו"ל | F2: סטרברי אנ אגח א | G2: IL0012098997 | H2: ISIN | I2: לא צמוד למדד המחירים לצרכן | J2: ישראל | K2: ארה"ב | L2: סחיר | M2: TASE | N2: נדל"ן מניב בחו"ל | O2: לא | P2: ilA+ | Q2: S&P מעלות | R2: נייר ערך | S2: ILS | T2: 1.84 | U2: 30/09/2026 | V2: 0.07373 | W2: 0.0737 | X2: החוב לא נחות | Y2: לא | Z2: 686384.83 | AA2: 1 | AB2: 99.55 | AD2: 683.296 | AG2: שווי הוגן | AH2: 0.00372 | AI2: =AD2/SUMIF(B:B,B2,AD:AD) -> 0.039020784 | AJ2: 0.0064221124
A3: 520042177 | B3: 12936 | C3: אקסטל לימיטד | D3: 1811308 | E3: מספר תאגיד או שותפות בחו"ל | F3: אקסטל אגח ד | G3: IL0011831695 | H3: ISIN | I3: לא צמוד למדד המחירים לצרכן | J3: ישראל | K3: ארה"ב | L3: סחיר | M3: TASE | N3: בנייה | O3: לא | P3: A3.il | Q3: מידרוג Moodys | R3: נייר ערך | S3: ILS | T3: 2.51 | U3: 31/12/2027 | V3: 0.065 | W3: 0.0838 | X3: החוב לא נחות | Y3: לא | Z3: 542000 | AA3: 1 | AB3: 97.5 | AD3: 528.45 | AG3: שווי הוגן | AH3: 0.0009 | AI3: =AD3/SUMIF(B:B,B3,AD:AD) -> 0.030178039 | AJ3: 0.0049667572
A4: 520042177 | B4: 12936 | C4: דליה אנרגיה | D4: 516269248 | E4: ח.פ. | F4: דליה אגח ב | G4: IL0011935983 | H4: ISIN | I4: צמוד למדד המחירים לצרכן | J4: ישראל | K4: ישראל | L4: סחיר | M4: TASE | N4: אנרגיה | O4: לא | P4: A3.il | Q4: מידרוג Moodys | R4: נייר ערך | S4: ILS | T4: 5.98 | U4: 01/10/2034 | V4: 0.03523 | W4: 0.0426 | X4: החוב לא נחות | Y4: לא | Z4: 518000 | AA4: 1 | AB4: 101.08 | AD4: 523.594 | AG4: שווי הוגן | AH4: 0.00042 | AI4: =AD4/SUMIF(B:B,B4,AD:AD) -> 0.029900728 | AJ4: 0.004921117
A5: 520042177 | B5: 12936 | C5: אמות | D5: 520026683 | E5: ח.פ. | F5: אמות אג ו' | G5: IL0011586091 | H5: ISIN | I5: צמוד למדד המחירים לצרכן | J5: ישראל | K5: ישראל | L5: סחיר | M5: TASE | N5: נדל"ן מניב בישראל | O5: לא | P5: ilAA | Q5: S&P מעלות | R5: נייר ערך | S5: ILS | T5: 3.33 | U5: 31/10/2029 | V5: 0.02161 | W5: 0.0292 | X5: החוב לא נחות | Y5: לא | Z5: 449000 | AA5: 1 | AB5: 107.2 | AC5: 5.816 | AD5: 487.144 | AG5: שווי הוגן | AH5: 0.00019 | AI5: =AD5/SUMIF(B:B,B5,AD:AD) -> 0.027819189 | AJ5: 0.0045785334
A6: 520042177 | B6: 12936 | C6: סיאון | D6: 2409 | E6: מספר מנפיק | F6: סיאון אגח א | G6: IL0011940181 | H6: ISIN | I6: צמוד למט"ח | J6: ישראל | K6: ארה"ב | L6: סחיר | M6: TASE | N6: אשראי חוץ בנקאי | O6: לא | P6: A1.il | Q6: מידרוג Moodys | R6: נייר ערך | S6: ILS | T6: 1.77 | U6: 31/08/2026 | V6: 0.00272 | W6: 0.0815 | X6: החוב לא נחות | Y6: לא | Z6: 450000 | AA6: 1 | AB6: 104.6 | AD6: 470.7 | AG6: שווי הוגן | AH6: 0.00107 | AI6: =AD6/SUMIF(B:B,B6,AD:AD) -> 0.026880126 | AJ6: 0.0044239807
A7: 520042177 | B7: 12936 | C7: מימון ישיר קב | D7: 513893123 | E7: ח.פ. | F7: מימון ישיר אגח ו | G7: IL0011916595 | H7: ISIN | I7: צמוד למדד המחירים לצרכן | J7: ישראל | K7: ישראל | L7: סחיר | M7: TASE | N7: אשראי חוץ בנקאי | O7: לא | P7: A1.il | Q7: מידרוג Moodys | R7: נייר ערך | S7: ILS | T7: 1.66 | U7: 31/03/2027 | V7: 0.0354 | W7: 0.0322 | X7: החוב לא נחות | Y7: לא | Z7: 400000 | AA7: 1 | AB7: 107.7 | AD7: 430.8 | AG7: שווי הוגן | AH7: 0.00036 | AI7: =AD7/SUMIF(B:B,B7,AD:AD) -> 0.024601569 | AJ7: 0.0040489715
A8: 520042177 | B8: 12936 | C8: דה לסר | D8: 1427976 | E8: מספר תאגיד או שותפות בחו"ל | F8: דה לסר אגח ט | G8: IL0012056813 | H8: ISIN | I8: לא צמוד למדד המחירים לצרכן | J8: ישראל | K8: ארה"ב | L8: סחיר | M8: TASE | N8: נדל"ן מניב בחו"ל | O8: לא | P8: ilA- | Q8: S&P מעלות | R8: נייר ערך | S8: ILS | T8: 4.14 | U8: 30/06/2031 | V8: 0.07182 | W8: 0.0821 | X8: החוב לא נחות | Y8: לא | Z8: 376000 | AA8: 1 | AB8: 107.75 | AD8: 405.14 | AG8: שווי הוגן | AH8: 0.0007 | AI8: =AD8/SUMIF(B:B,B8,AD:AD) -> 0.023136211 | AJ8: 0.0038078002
A9: 520042177 | B9: 12936 | C9: ספנסר אקוויטי | D9: 1838863 | E9: מספר תאגיד או שותפות בחו"ל | F9: ספנסר אגח ד | G9: IL0011887887 | H9: ISIN | I9: לא צמוד למדד המחירים לצרכן | J9: ישראל | K9: ארה"ב | L9: סחיר | M9: TASE | N9: נדל"ן מניב בחו"ל | O9: לא | P9: ilA | Q9: S&P מעלות | R9: נייר ערך | S9: ILS | T9: 2.5 | U9: 31/08/2029 | V9: 0.03171 | W9: 0.073 | X9: החוב לא נחות | Y9: לא | Z9: 400000.87 | AA9: 1 | AB9: 100.76 | AD9: 403.041 | AG9: שווי הוגן | AH9: 0.00076 | AI9: =AD9/SUMIF(B:B,B9,AD:AD) -> 0.023016344 | AJ9: 0.0037880722
A10: 520042177 | B10: 12936 | C10: ווסטדייל אמריקה | D10: 1991033 | E10: מספר תאגיד או שותפות בחו"ל | F10: ווסטדייל אגח ג | G10: IL0012085119 | H10: ISIN | I10: לא צמוד למדד המחירים לצרכן | J10: ישראל | K10: ארה"ב | L10: סחיר | M10: TASE | N10: נדל"ן מניב בחו"ל | O10: לא | P10: ilAA- | Q10: S&P מעלות | R10: נייר ערך | S10: ILS | T10: 4.29 | U10: 30/10/2029 | V10: 0.07385 | W10: 0.0667 | X10: החוב לא נחות | Y10: לא | Z10: 379000 | AA10: 1 | AB10: 104.03 | AD10: 394.274 | AG10: שווי הוגן | AH10: 0.00091 | AI10: =AD10/SUMIF(B:B,B10,AD:AD) -> 0.022515689 | AJ10: 0.0037056736
A11: 520042177 | B11: 12936 | C11: אס.אר אקורד | D11: 520038670 | E11: ח.פ. | F11: אסאר אקורד אגח ב | G11: IL0042203724 | H11: ISIN | I11: צמוד למדד המחירים לצרכן | J11: ישראל | K11: ישראל | L11: סחיר | M11: TASE | N11: אשראי חוץ בנקאי | O11: לא | P11: A3.il | Q11: מידרוג Moodys | R11: נייר ערך | S11: ILS | T11: 1.46 | U11: 30/06/2027 | V11: 0.05908 | W11: 0.0434 | X11: החוב לא נחות | Y11: לא | Z11: 367476.19 | AA11: 1 | AB11: 104.83 | AD11: 385.225 | AG11: שווי הוגן | AH11: 0.00199 | AI11: =AD11/SUMIF(B:B,B11,AD:AD) -> 0.021998931 | AJ11: 0.0036206245
A12: 520042177 | B12: 12936 | C12: לאומי | D12: 520018078 | E12: ח.פ. | F12: לאומי התח נד403 | G12: IL0060404303 | H12: ISIN | I12: צמוד למדד המחירים לצרכן | J12: ישראל | K12: ישראל | L12: סחיר | M12: TASE | N12: בנקים | O12: לא | P12: ilAA- | Q12: S&P מעלות | R12: נייר ערך | S12: ILS | T12: 0.41 | U12: 28/02/2025 | V12: 0.0242 | W12: 0.0359 | X12: החוב נחות | Y12: לא | Z12: 300000 | AA12: 1 | AB12: 116.43 | AD12: 349.29 | AG12: שווי הוגן | AH12: 0.00021 | AI12: =AD12/SUMIF(B:B,B12,AD:AD) -> 0.019946801 | AJ12: 0.0032828813
A13: 520042177 | B13: 12936 | C13: אדמה | D13: 520043605 | E13: ח.פ. | F13: אדמה אגח 2 | G13: IL0011109159 | H13: ISIN | I13: צמוד למדד המחירים לצרכן | J13: ישראל | K13: ישראל | L13: סחיר | M13: TASE | N13: כימיה, גומי ופלסטיק | O13: לא | P13: ilAA- | Q13: S&P מעלות | R13: נייר ערך | S13: ILS | T13: 5.02 | U13: 30/11/2036 | V13: 0.00838 | W13: 0.0515 | X13: החוב לא נחות | Y13: לא | Z13: 234000.02 | AA13: 1 | AB13: 141.9 | AD13: 332.046 | AG13: שווי הוגן | AH13: 8e-05 | AI13: =AD13/SUMIF(B:B,B13,AD:AD) -> 0.018962053 | AJ13: 0.0031208096
A14: 520042177 | B14: 12936 | C14: אורון קבוצה | D14: 513432765 | E14: ח.פ. | F14: אורון קב אגח ג | G14: IL0011977639 | H14: ISIN | I14: לא צמוד למדד המחירים לצרכן | J14: ישראל | K14: ישראל | L14: חסום | M14: TASE | N14: בנייה | O14: לא | P14: Baa1.il | Q14: מידרוג Moodys | R14: נייר ערך | S14: ILS | T14: 2.83 | U14: 01/07/2029 | V14: 0.07069 | W14: 0.0631 | X14: החוב לא נחות | Y14: לא | Z14: 300000 | AA14: 1 | AB14: =AD14*1000/Z14*100 -> 106.06733 | AD14: =321.24-3.038 -> 318.202 | AG14: שווי הוגן | AH14: 0.00145 | AI14: =AD14/SUMIF(B:B,B14,AD:AD) -> 0.018171468 | AJ14: 0.0029906937
A15: 520042177 | B15: 12936 | C15: מזרחי טפחות הנפ | D15: 520032046 | E15: ח.פ. | F15: מז טפ הנפ הת 69 | G15: IL0012021593 | H15: ISIN | I15: צמוד למדד המחירים לצרכן | J15: ישראל | K15: ישראל | L15: סחיר | M15: TASE | N15: בנקים | O15: לא | P15: ilAA- | Q15: S&P מעלות | R15: נייר ערך | S15: ILS | T15: 4.42 | U15: 25/06/2029 | V15: 0.03422 | W15: 0.0309 | X15: החוב נחות | Y15: לא | Z15: 300000 | AA15: 1 | AB15: 105.66 | AD15: 316.98 | AG15: שווי הוגן | AH15: 0.00026 | AI15: =AD15/SUMIF(B:B,B15,AD:AD) -> 0.018101684 | AJ15: 0.0029792084
A16: 520042177 | B16: 12936 | C16: גב ים | D16: 520001736 | E16: ח.פ. | F16: גב ים אגח יא | G16: IL0012083395 | H16: ISIN | I16: צמוד למדד המחירים לצרכן | J16: ישראל | K16: ישראל | L16: סחיר | M16: TASE | N16: נדל"ן מניב בישראל | O16: לא | P16: ilAA | Q16: S&P מעלות | R16: נייר ערך | S16: ILS | T16: 3.74 | U16: 31/03/2030 | V16: 0.02854 | W16: 0.0307 | X16: החוב לא נחות | Y16: לא | Z16: 300000 | AA16: 1 | AB16: 103.53 | AD16: 310.59 | AG16: שווי הוגן | AH16: 0.0004 | AI16: =AD16/SUMIF(B:B,B16,AD:AD) -> 0.017736772 | AJ16: 0.0029191506
A17: 520042177 | B17: 12936 | C17: קרסו נדלן | D17: 510488190 | E17: ח.פ. | F17: קרסו נדלן אגח א | G17: IL0011900086 | H17: ISIN | I17: לא צמוד למדד המחירים לצרכן | J17: ישראל | K17: ישראל | L17: סחיר | M17: TASE | N17: בנייה | O17: לא | P17: ilA | Q17: S&P מעלות | R17: נייר ערך | S17: ILS | T17: 2.84 | U17: 30/11/2029 | V17: 0.05133 | W17: 0.0624 | X17: החוב לא נחות | Y17: לא | Z17: 300000 | AA17: 1 | AB17: 99.54 | AD17: 298.62 | AG17: שווי הוגן | AH17: 0.00043 | AI17: =AD17/SUMIF(B:B,B17,AD:AD) -> 0.017053204 | AJ17: 0.0028066478
A18: 520042177 | B18: 12936 | C18: פועלים | D18: 520000118 | E18: ח.פ. | F18: פועלים הת נדח ט | G18: IL0011998841 | H18: ISIN | I18: צמוד למדד המחירים לצרכן | J18: ישראל | K18: ישראל | L18: סחיר | M18: TASE | N18: בנקים | O18: לא | P18: ilAA- | Q18: S&P מעלות | R18: נייר ערך | S18: ILS | T18: 0.5 | U18: 03/04/2025 | V18: 0.0202 | W18: 0.0357 | X18: החוב נחות | Y18: לא | Z18: 250000 | AA18: 1 | AB18: 115.6 | AD18: 289 | AG18: שווי הוגן | AH18: 0.00024 | AI18: =AD18/SUMIF(B:B,B18,AD:AD) -> 0.016503838 | AJ18: 0.002716232
A19: 520042177 | B19: 12936 | C19: נמקו ריאלטי | D19: 1905761 | E19: מספר תאגיד או שותפות בחו"ל | F19: נמקו אגח ב | G19: IL0011602583 | H19: ISIN | I19: לא צמוד למדד המחירים לצרכן | J19: ישראל | K19: ארה"ב | L19: סחיר | M19: TASE | N19: נדל"ן מניב בחו"ל | O19: לא | P19: ilAA- | Q19: S&P מעלות | R19: נייר ערך | S19: ILS | T19: 3.44 | U19: 15/10/2032 | V19: 0.06455 | W19: 0.0659 | X19: החוב לא נחות | Y19: לא | Z19: 300000.67 | AA19: 1 | AB19: 95.42 | AD19: 286.261 | AG19: שווי הוגן | AH19: 0.00033 | AI19: =AD19/SUMIF(B:B,B19,AD:AD) -> 0.016347423 | AJ19: 0.0026904889
A20: 520042177 | B20: 12936 | C20: רימון | D20: 512467994 | E20: ח.פ. | F20: רימון אגח א | G20: IL0012110362 | H20: ISIN | I20: לא צמוד למדד המחירים לצרכן | J20: ישראל | K20: ישראל | L20: סחיר | M20: TASE | N20: בנייה | O20: לא | P20: A2.il | Q20: מידרוג Moodys | R20: נייר ערך | S20: ILS | T20: 4.26 | U20: 30/04/2032 | V20: 0.05354 | W20: 0.0582 | X20: החוב לא נחות | Y20: לא | Z20: 282000 | AA20: 1 | AB20: 100.66 | AD20: 283.861 | AG20: שווי הוגן | AH20: 0.00161 | AI20: =AD20/SUMIF(B:B,B20,AD:AD) -> 0.016210367 | AJ20: 0.002667932
A21: 520042177 | B21: 12936 | C21: יובלים קבוצה | D21: 514625094 | E21: ח.פ. | F21: יובלים אגח א | G21: IL0011766438 | H21: ISIN | I21: לא צמוד למדד המחירים לצרכן | J21: ישראל | K21: ישראל | L21: חסום | M21: TASE | N21: בנייה | O21: לא | Q21: NR | R21: NR | S21: ILS | T21: 0.48 | U21: 06/07/2025 | V21: 0.06285 | W21: 0.0715 | X21: החוב לא נחות | Y21: לא | Z21: 275000 | AA21: 1 | AB21: =AD21*1000/Z21*100 -> 97.876 | AD21: =272.938-3.779 -> 269.159 | AG21: שווי הוגן | AH21: 0.00275 | AI21: =AD21/SUMIF(B:B,B21,AD:AD) -> 0.015370784 | AJ21: 0.0025297519
A22: 520042177 | B22: 12936 | C22: עמרם | D22: 513201582 | E22: ח.פ. | F22: עמרם אברהם אגח א | G22: IL0011880445 | H22: ISIN | I22: לא צמוד למדד המחירים לצרכן | J22: ישראל | K22: ישראל | L22: חסום | M22: TASE | N22: בנייה | O22: לא | Q22: NR | R22: NR | S22: ILS | T22: 1.59 | U22: 31/05/2027 | V22: 0.06489 | W22: 0.0631 | X22: החוב לא נחות | Y22: לא | Z22: 85000 | AA22: 1 | AB22: =AD22*1000/Z22*100 -> 100.6635 | AD22: =85563.9726775956/1000 -> 85.563973 | AG22: שווי הוגן | AH22: 0.00107 | AI22: =AD22/SUMIF(B:B,B22,AD:AD) -> 0.0048862766 | AJ22: 0.0008041924
A23: 520042177 | B23: 12936 | C23: אאורה | D23: 520038274 | E23: ח.פ. | F23: אאורה אגח יז | G23: IL0011935801 | H23: ISIN | I23: צמוד למדד המחירים לצרכן | J23: ישראל | K23: ישראל | L23: חסום | M23: TASE | N23: בנייה | O23: לא | P23: A2.il | Q23: מידרוג Moodys | R23: נייר ערך | S23: ILS | T23: 2.82 | U23: 31/01/2029 | V23: 0.03268 | W23: 0.0322 | X23: החוב לא נחות | Y23: לא | Z23: 159000 | AA23: 1 | AB23: =AD23*1000/Z23*100 -> 108.96918 | AD23: =173261.001639344/1000 -> 173.261 | AG23: שווי הוגן | AH23: 0.00083 | AI23: =AD23/SUMIF(B:B,B23,AD:AD) -> 0.009894365 | AJ23: 0.0016284328
A24: 520042177 | B24: 12936 | C24: מנרב | D24: 520034505 | E24: ח.פ. | F24: מנרב אגח ד | G24: IL0015501690 | H24: ISIN | I24: צמוד למדד המחירים לצרכן | J24: ישראל | K24: ישראל | L24: סחיר | M24: TASE | N24: בנייה | O24: לא | P24: Baa1.il | Q24: מידרוג Moodys | R24: נייר ערך | S24: ILS | T24: 3.66 | U24: 15/04/2032 | V24: 0.04574 | W24: 0.0497 | X24: החוב לא נחות | Y24: לא | Z24: 262225.5 | AA24: 1 | AB24: 101.96 | AD24: 267.365 | AG24: שווי הוגן | AH24: 0.00055 | AI24: =AD24/SUMIF(B:B,B24,AD:AD) -> 0.015268334 | AJ24: 0.0025128906
A25: 520042177 | B25: 12936 | C25: נאוויטס פטרו | D25: 550263107 | E25: ח.פ. | F25: נאוויטס פט אגחה | G25: IL0011979122 | H25: ISIN | I25: לא צמוד למדד המחירים לצרכן | J25: ישראל | K25: ישראל | L25: סחיר | M25: TASE | N25: חיפושי נפט וגז | O25: לא | P25: ilA- | Q25: S&P מעלות | R25: נייר ערך | S25: ILS | T25: 3.12 | U25: 31/12/2028 | V25: 0.07274 | W25: 0.0674 | X25: החוב לא נחות | Y25: לא | Z25: 263512 | AA25: 1 | AB25: 101.22 | AD25: 266.727 | AG25: שווי הוגן | AH25: 0.00053 | AI25: =AD25/SUMIF(B:B,B25,AD:AD) -> 0.0152319 | AJ25: 0.0025068942
A26: 520042177 | B26: 12936 | C26: מימון ישיר קב | D26: 513893123 | E26: ח.פ. | F26: מימון ישיר אגח ה | G26: IL0011828311 | H26: ISIN | I26: צמוד למדד המחירים לצרכן | J26: ישראל | K26: ישראל | L26: חסום | M26: TASE | N26: אשראי חוץ בנקאי | O26: לא | P26: A1.il | Q26: מידרוג Moodys | R26: נייר ערך | S26: ILS | T26: 3.25 | U26: 31/07/2031 | V26: 0.02949 | W26: 0.0333 | X26: החוב לא נחות | Y26: לא | Z26: 195000 | AA26: 1 | AB26: =AD26*1000/Z26*100 -> 104.02142 | AD26: =202841.770491803/1000 -> 202.84177 | AG26: שווי הוגן | AH26: 0.00016 | AI26: =AD26/SUMIF(B:B,B26,AD:AD) -> 0.011583625 | AJ26: 0.0019064544
A27: 520042177 | B27: 12936 | C27: שובל הנדסה | D27: 512951518 | E27: ח.פ. | F27: שובל אגח א | G27: IL0012079278 | H27: ISIN | I27: לא צמוד למדד המחירים לצרכן | J27: ישראל | K27: ישראל | L27: סחיר | M27: TASE | N27: בנייה | O27: לא | Q27: NR | R27: NR | S27: ILS | T27: 2.5 | U27: 30/09/2027 | V27: 0.08135 | W27: 0.0676 | X27: החוב לא נחות | Y27: לא | Z27: 248000 | AA27: 1 | AB27: 102.79 | AD27: 254.919 | AG27: שווי הוגן | AH27: 0.00183 | AI27: =AD27/SUMIF(B:B,B27,AD:AD) -> 0.014557584 | AJ27: 0.002395914
A28: 520042177 | B28: 12936 | C28: סטרוברי | D28: 1863501 | E28: מספר תאגיד או שותפות בחו"ל | F28: סטרוברי אגח ג | G28: IL0011790198 | H28: ISIN | I28: לא צמוד למדד המחירים לצרכן | J28: ישראל | K28: ארה"ב | L28: סחיר | M28: TASE | N28: נדל"ן מניב בחו"ל | O28: לא | P28: ilAA- | Q28: S&P מעלות | R28: נייר ערך | S28: ILS | T28: 1.68 | U28: 31/07/2026 | V28: 0.07003 | W28: 0.0671 | X28: החוב לא נחות | Y28: לא | Z28: 256106.06 | AA28: 1 | AB28: 99.49 | AD28: 254.8 | AG28: שווי הוגן | AH28: 0.00125 | AI28: =AD28/SUMIF(B:B,B28,AD:AD) -> 0.014550789 | AJ28: 0.0023947956
A29: 520042177 | B29: 12936 | C29: מודיעין יהש | D29: 550012405 | E29: ח.פ. | F29: מודיעין אג ב | G29: IL0012104423 | H29: ISIN | I29: צמוד למט"ח | J29: ישראל | K29: ישראל | L29: סחיר | M29: TASE | N29: חיפושי נפט וגז | O29: לא | Q29: NR | R29: NR | S29: ILS | T29: 3.51 | U29: 01/10/2028 | V29: 0.07327 | W29: 0.0978 | X29: החוב לא נחות | Y29: לא | Z29: 265000 | AA29: 1 | AB29: 92.3 | AD29: 244.595 | AG29: שווי הוגן | AH29: 0.00507 | AI29: =AD29/SUMIF(B:B,B29,AD:AD) -> 0.013968015 | AJ29: 0.0022988816
A30: 520042177 | B30: 12936 | C30: נמקו ריאלטי | D30: 1905761 | E30: מספר תאגיד או שותפות בחו"ל | F30: נמקו אגח ג | G30: IL0011987612 | H30: ISIN | I30: לא צמוד למדד המחירים לצרכן | J30: ישראל | K30: ארה"ב | L30: סחיר | M30: TASE | N30: נדל"ן מניב בחו"ל | O30: לא | P30: ilAA | Q30: S&P מעלות | R30: נייר ערך | S30: ILS | T30: 2.45 | U30: 30/06/2027 | V30: 0.06684 | W30: 0.062 | X30: החוב לא נחות | Y30: לא | Z30: 232000 | AA30: 1 | AB30: 102.2 | AD30: 237.104 | AG30: שווי הוגן | AH30: 0.00057 | AI30: =AD30/SUMIF(B:B,B30,AD:AD) -> 0.013540228 | AJ30: 0.0022284757
A31: 520042177 | B31: 12936 | C31: דה לסר | D31: 1427976 | E31: מספר תאגיד או שותפות בחו"ל | F31: דה לסר אגח ח | G31: IL0011931925 | H31: ISIN | I31: לא צמוד למדד המחירים לצרכן | J31: ישראל | K31: ארה"ב | L31: סחיר | M31: TASE | N31: נדל"ן מניב בחו"ל | O31: לא | P31: ilA | Q31: S&P מעלות | R31: נייר ערך | S31: ILS | T31: 2.02 | U31: 31/12/2026 | V31: 0.07793 | W31: 0.0652 | X31: החוב לא נחות | Y31: לא | Z31: 214370 | AA31: 1 | AB31: 102.45 | AD31: 219.622 | AG31: שווי הוגן | AH31: 0.00061 | AI31: =AD31/SUMIF(B:B,B31,AD:AD) -> 0.012541889 | AJ31: 0.0020641672
A32: 520042177 | B32: 12936 | C32: להב | D32: 520034257 | E32: ח.פ. | F32: להב אגח ג | G32: IL0011933418 | H32: ISIN | I32: צמוד למדד המחירים לצרכן | J32: ישראל | K32: ישראל | L32: סחיר | M32: TASE | N32: השקעה ואחזקות | O32: לא | P32: A2.il | Q32: מידרוג Moodys | R32: נייר ערך | S32: ILS | T32: 3.02 | U32: 10/07/2028 | V32: 0.02897 | W32: 0.0341 | X32: החוב לא נחות | Y32: לא | Z32: 200000 | AA32: 1 | AB32: 108.68 | AD32: 217.36 | AG32: שווי הוגן | AH32: 0.00057 | AI32: =AD32/SUMIF(B:B,B32,AD:AD) -> 0.012412714 | AJ32: 0.0020429073
A33: 520042177 | B33: 12936 | C33: אפקון החזקות | D33: 520033473 | E33: ח.פ. | F33: אפקון החז אגח ד | G33: IL0057801685 | H33: ISIN | I33: צמוד למדד המחירים לצרכן | J33: ישראל | K33: ישראל | L33: סחיר | M33: TASE | N33: השקעה ואחזקות | O33: לא | P33: ilA- | Q33: S&P מעלות | R33: נייר ערך | S33: ILS | T33: 2.61 | U33: 01/04/2029 | V33: 0.03562 | W33: 0.033 | X33: החוב לא נחות | Y33: לא | Z33: 189333.33 | AA33: 1 | AB33: 114.19 | AD33: 216.2 | AG33: שווי הוגן | AH33: 0.00084 | AI33: =AD33/SUMIF(B:B,B33,AD:AD) -> 0.01234647 | AJ33: 0.0020320047
A34: 520042177 | B34: 12936 | C34: פתאל אירופה | D34: 515328250 | E34: ח.פ. | F34: פתאל אירו אגח ה | G34: IL0011988867 | H34: ISIN | I34: לא צמוד למדד המחירים לצרכן | J34: ישראל | K34: ישראל | L34: סחיר | M34: TASE | N34: נדל"ן מניב בחו"ל | O34: לא | P34: A2.il | Q34: מידרוג Moodys | R34: נייר ערך | S34: ILS | T34: 3.33 | U34: 01/07/2029 | V34: 0.06335 | W34: 0.063 | X34: החוב לא נחות | Y34: לא | Z34: 208000 | AA34: 1 | AB34: 102.14 | AD34: 212.451 | AG34: שווי הוגן | AH34: 0.0005 | AI34: =AD34/SUMIF(B:B,B34,AD:AD) -> 0.012132377 | AJ34: 0.0019967689
A35: 520042177 | B35: 12936 | C35: ביג | D35: 513623314 | E35: ח.פ. | F35: ביג אגח ח | G35: IL0011389249 | H35: ISIN | I35: צמוד למדד המחירים לצרכן | J35: ישראל | K35: ישראל | L35: סחיר | M35: TASE | N35: נדל"ן מניב בישראל | O35: לא | P35: ilAA | Q35: S&P מעלות | R35: נייר ערך | S35: ILS | T35: 1.43 | U35: 12/04/2026 | V35: 0.01593 | W35: 0.0258 | X35: החוב לא נחות | Y35: לא | Z35: 183000 | AA35: 1 | AB35: 115.21 | AD35: 210.834 | AG35: שווי הוגן | AH35: 0.00037 | AI35: =AD35/SUMIF(B:B,B35,AD:AD) -> 0.012040035 | AJ35: 0.0019815712
A36: 520042177 | B36: 12936 | C36: אפי קפיטל נדלן | D36: 513948216 | E36: ח.פ. | F36: אפי קפיטל אגח ג | G36: IL0011997447 | H36: ISIN | I36: לא צמוד למדד המחירים לצרכן | J36: ישראל | K36: ישראל | L36: חסום | M36: TASE | N36: בנייה | O36: לא | Q36: NR | R36: NR | S36: ILS | T36: 2.05 | U36: 30/06/2027 | V36: 0.0661 | W36: 0.0711 | X36: החוב לא נחות | Y36: לא | Z36: 100000 | AA36: 1 | AB36: =AD36*1000/Z36*100 -> 104.73071 | AD36: =104730.710382514/1000 -> 104.73071 | AG36: שווי הוגן | AH36: 0.00154 | AI36: =AD36/SUMIF(B:B,B36,AD:AD) -> 0.0059808259 | AJ36: 0.00098433533
A37: 520042177 | B37: 12936 | C37: נופר אנרג'י | D37: 514599943 | E37: ח.פ. | F37: נופר אנרג אגח א | G37: IL0011793408 | H37: ISIN | I37: צמוד למדד המחירים לצרכן | J37: ישראל | K37: ישראל | L37: סחיר | M37: TASE | N37: אנרגיה מתחדשת | O37: לא | Q37: NR | R37: NR | S37: ILS | T37: 2.49 | U37: 31/12/2027 | V37: 0.0406 | W37: 0.0314 | X37: החוב לא נחות | Y37: לא | Z37: 185714.29 | AA37: 1 | AB37: 109.1 | AD37: 202.614 | AG37: שווי הוגן | AH37: 0.00025 | AI37: =AD37/SUMIF(B:B,B37,AD:AD) -> 0.011570618 | AJ37: 0.0019043136
A38: 520042177 | B38: 12936 | C38: אפי נכסים | D38: 510560188 | E38: ח.פ. | F38: אפי נכסים אגח יג | G38: IL0011782922 | H38: ISIN | I38: צמוד למדד המחירים לצרכן | J38: ישראל | K38: ישראל | L38: סחיר | M38: TASE | N38: נדל"ן מניב בחו"ל | O38: לא | P38: A2.il | Q38: מידרוג Moodys | R38: נייר ערך | S38: ILS | T38: 4.14 | U38: 01/07/2029 | V38: 0.0335 | W38: 0.0339 | X38: החוב לא נחות | Y38: לא | Z38: 194000 | AA38: 1 | AB38: 103.89 | AD38: 201.547 | AG38: שווי הוגן | AH38: 0.00027 | AI38: =AD38/SUMIF(B:B,B38,AD:AD) -> 0.011509685 | AJ38: 0.0018942852
A39: 520042177 | B39: 12936 | C39: 1 ריט | D39: 513821488 | E39: ח.פ. | F39: ריט 1 אגח ז | G39: IL0011712713 | H39: ISIN | I39: צמוד למדד המחירים לצרכן | J39: ישראל | K39: ישראל | L39: סחיר | M39: TASE | N39: נדל"ן מניב בישראל | O39: לא | P39: ilAA | Q39: S&P מעלות | R39: נייר ערך | S39: ILS | T39: 6.65 | U39: 20/09/2034 | V39: 0.02784 | W39: 0.0339 | X39: החוב לא נחות | Y39: לא | Z39: 184300 | AA39: 1 | AB39: 109.06 | AD39: 200.998 | AG39: שווי הוגן | AH39: 0.00022 | AI39: =AD39/SUMIF(B:B,B39,AD:AD) -> 0.011478334 | AJ39: 0.0018891253
A40: 520042177 | B40: 12936 | C40: אמפא יובלים | D40: 516286432 | E40: ח.פ. | F40: אמפא יובל אגח א | G40: IL0011935157 | H40: ISIN | I40: לא צמוד למדד המחירים לצרכן | J40: ישראל | K40: ישראל | L40: סחיר | M40: TASE | N40: נדל"ן מניב בישראל | O40: לא | Q40: NR | R40: NR | S40: ILS | T40: 0.92 | U40: 15/12/2025 | V40: 0.08753 | W40: 0.0869 | X40: החוב לא נחות | Y40: לא | Z40: 200000 | AA40: 1 | AB40: 100.1 | AD40: 200.2 | AG40: שווי הוגן | AH40: 0.00182 | AI40: =AD40/SUMIF(B:B,B40,AD:AD) -> 0.011432762 | AJ40: 0.0018816251
A41: 520042177 | B41: 12936 | C41: פסיפיק אוק אסאואר(בי וי איי) הולדינג | D41: 1900288 | E41: מספר תאגיד או שותפות בחו"ל | F41: פסיפיק אגח ד | G41: IL0012060443 | H41: ISIN | I41: לא צמוד למדד המחירים לצרכן | J41: ישראל | K41: ארה"ב | L41: סחיר | M41: TASE | N41: נדל"ן מניב בחו"ל | O41: לא | P41: ilAA- | Q41: S&P מעלות | R41: נייר ערך | S41: ILS | T41: 2.96 | U41: 28/02/2029 | V41: 0.08433 | W41: 0.0969 | X41: החוב לא נחות | Y41: לא | Z41: 196000 | AA41: 1 | AB41: 100.91 | AD41: 197.784 | AG41: שווי הוגן | AH41: 0.00033 | AI41: =AD41/SUMIF(B:B,B41,AD:AD) -> 0.011294793 | AJ41: 0.0018589178
A42: 520042177 | B42: 12936 | C42: אמ.ג'י.ג'י | D42: 1981143 | E42: מספר תאגיד או שותפות בחו"ל | F42: אמ.ג'יג'י אגח ב | G42: IL0011608119 | H42: ISIN | I42: לא צמוד למדד המחירים לצרכן | J42: ישראל | K42: ארה"ב | L42: סחיר | M42: TASE | N42: אשראי חוץ בנקאי | O42: לא | P42: A1.il | Q42: מידרוג Moodys | R42: נייר ערך | S42: ILS | T42: 0.96 | U42: 21/09/2025 | V42: 0.07639 | W42: 0.0641 | X42: החוב לא נחות | Y42: לא | Z42: 200000.54 | AA42: 1 | AB42: 98.68 | AD42: 197.361 | AG42: שווי הוגן | AH42: 0.00032 | AI42: =AD42/SUMIF(B:B,B42,AD:AD) -> 0.011270637 | AJ42: 0.0018549421
A43: 520042177 | B43: 12936 | C43: נמקו ריאלטי | D43: 1905761 | E43: מספר תאגיד או שותפות בחו"ל | F43: נמקו אגח ד | G43: IL0012064734 | H43: ISIN | I43: לא צמוד למדד המחירים לצרכן | J43: ישראל | K43: ארה"ב | L43: סחיר | M43: TASE | N43: נדל"ן מניב בחו"ל | O43: לא | P43: ilAA | Q43: S&P מעלות | R43: נייר ערך | S43: ILS | T43: 3.93 | U43: 15/04/2029 | V43: 0.05245 | W43: 0.0617 | X43: החוב לא נחות | Y43: לא | Z43: 188000 | AA43: 1 | AB43: 103.18 | AD43: 193.978 | AG43: שווי הוגן | AH43: 0.00034 | AI43: =AD43/SUMIF(B:B,B43,AD:AD) -> 0.011077445 | AJ43: 0.0018231462
A44: 520042177 | B44: 12936 | C44: מהדרין | D44: 520018482 | E44: ח.פ. | F44: מהדרין אגח א | G44: IL0012114570 | H44: ISIN | I44: צמוד למדד המחירים לצרכן | J44: ישראל | K44: ישראל | L44: סחיר | M44: TASE | N44: מזון | O44: לא | Q44: NR | R44: NR | S44: ILS | T44: 4.58 | U44: 30/06/2030 | V44: 0.03516 | W44: 0.0389 | X44: החוב לא נחות | Y44: לא | Z44: 189000 | AA44: 1 | AB44: 101.18 | AD44: 191.23 | AG44: שווי הוגן | AH44: 0.00056 | AI44: =AD44/SUMIF(B:B,B44,AD:AD) -> 0.010920515 | AJ44: 0.0017973185
A45: 520042177 | B45: 12936 | C45: בית זיקוק אשדוד | D45: 513775163 | E45: ח.פ. | F45: בית זיקוק אגח 2 | G45: IL0011994881 | H45: ISIN | I45: לא צמוד למדד המחירים לצרכן | J45: ישראל | K45: ישראל | L45: סחיר | M45: TASE | N45: אנרגיה | O45: לא | P45: A3.il | Q45: מידרוג Moodys | R45: נייר ערך | S45: ILS | T45: 3 | U45: 30/04/2029 | V45: 0.0725 | W45: 0.064 | X45: החוב לא נחות | Y45: לא | Z45: 180000 | AA45: 1 | AB45: 105.92 | AD45: 190.656 | AG45: שווי הוגן | AH45: 0.00025 | AI45: =AD45/SUMIF(B:B,B45,AD:AD) -> 0.010887736 | AJ45: 0.0017919237
A46: 520042177 | B46: 12936 | C46: לוזון קבוצה | D46: 520039660 | E46: ח.פ. | F46: לוזון קב אגח יא | G46: IL0012069865 | H46: ISIN | I46: לא צמוד למדד המחירים לצרכן | J46: ישראל | K46: ישראל | L46: סחיר | M46: TASE | N46: בנייה | O46: לא | Q46: NR | R46: NR | S46: ILS | T46: 4.03 | U46: 01/12/2033 | V46: 0.0589 | W46: 0.0666 | X46: החוב לא נחות | Y46: לא | Z46: 183000 | AA46: 1 | AB46: 103.07 | AD46: 188.618 | AG46: שווי הוגן | AH46: 0.00067 | AI46: =AD46/SUMIF(B:B,B46,AD:AD) -> 0.010771353 | AJ46: 0.001772769
A47: 520042177 | B47: 12936 | C47: פתאל החזקות | D47: 512607888 | E47: ח.פ. | F47: פתאל החז אגח ד | G47: IL0011881922 | H47: ISIN | I47: צמוד למדד המחירים לצרכן | J47: ישראל | K47: ישראל | L47: סחיר | M47: TASE | N47: מלונאות ותיירות | O47: לא | P47: A2.il | Q47: מידרוג Moodys | R47: נייר ערך | S47: ILS | T47: 3.49 | U47: 31/12/2032 | V47: 0.04658 | W47: 0.0347 | X47: החוב לא נחות | Y47: לא | Z47: 168330 | AA47: 1 | AB47: 108.96 | AD47: 183.412 | AG47: שווי הוגן | AH47: 0.00039 | AI47: =AD47/SUMIF(B:B,B47,AD:AD) -> 0.010474055 | AJ47: 0.0017238393
A48: 520042177 | B48: 12936 | C48: אלמוגים החזקות | D48: 513988824 | E48: ח.פ. | F48: אלמוגים אגח ט | G48: IL0011892242 | H48: ISIN | I48: לא צמוד למדד המחירים לצרכן | J48: ישראל | K48: ישראל | L48: חסום | M48: TASE | N48: בנייה | O48: לא | Q48: NR | R48: NR | S48: ILS | T48: 1.61 | U48: 31/03/2027 | V48: 0.08593 | W48: 0.0699 | X48: החוב לא נחות | Y48: לא | Z48: 182700 | AA48: 1 | AB48: =AD48*1000/Z48*100 -> 99.218938 | AD48: =182.243-0.97 -> 181.273 | AG48: שווי הוגן | AH48: 0.00174 | AI48: =AD48/SUMIF(B:B,B48,AD:AD) -> 0.010351904 | AJ48: 0.0017037354
A49: 520042177 | B49: 12936 | C49: חג'ג' נדלן | D49: 520033309 | E49: ח.פ. | F49: חג'ג' אגח יד | G49: IL0012066069 | H49: ISIN | I49: לא צמוד למדד המחירים לצרכן | J49: ישראל | K49: ישראל | L49: סחיר | M49: TASE | N49: בנייה | O49: לא | Q49: NR | R49: NR | S49: ILS | T49: 2.52 | U49: 02/01/2028 | V49: 0.05678 | W49: 0.0806 | X49: החוב לא נחות | Y49: לא | Z49: 183000 | AA49: 1 | AB49: 98.98 | AD49: 181.133 | AG49: שווי הוגן | AH49: 0.00148 | AI49: =AD49/SUMIF(B:B,B49,AD:AD) -> 0.010343909 | AJ49: 0.0017024196
A50: 520042177 | B50: 12936 | C50: דה לסר | D50: 1427976 | E50: מספר תאגיד או שותפות בחו"ל | F50: דה לסר אגח ז | G50: IL0011789208 | H50: ISIN | I50: לא צמוד למדד המחירים לצרכן | J50: ישראל | K50: ארה"ב | L50: סחיר | M50: TASE | N50: נדל"ן מניב בחו"ל | O50: לא | P50: ilA- | Q50: S&P מעלות | R50: נייר ערך | S50: ILS | T50: 2.03 | U50: 30/06/2028 | V50: 0.0775 | W50: 0.0719 | X50: החוב לא נחות | Y50: לא | Z50: 173369.6 | AA50: 1 | AB50: 103.32 | AD50: 179.125 | AG50: שווי הוגן | AH50: 0.0004 | AI50: =AD50/SUMIF(B:B,B50,AD:AD) -> 0.010229239 | AJ50: 0.0016835469
A51: 520042177 | B51: 12936 | C51: חג'ג' אירופה | D51: 515682292 | E51: ח.פ. | F51: חגג אירופה ג | G51: IL0011826828 | H51: ISIN | I51: לא צמוד למדד המחירים לצרכן | J51: ישראל | K51: ישראל | L51: סחיר | M51: TASE | N51: בנייה | O51: לא | Q51: NR | R51: NR | S51: ILS | T51: 1.08 | U51: 01/01/2026 | V51: 0.035 | W51: 0.074 | X51: החוב לא נחות | Y51: לא | Z51: 175000 | AA51: 1 | AB51: =AD51*1000/Z51*100 -> 96.331429 | AD51: =169.663-1.083 -> 168.58 | AG51: שווי הוגן | AH51: 0.00312 | AI51: =AD51/SUMIF(B:B,B51,AD:AD) -> 0.0096270484 | AJ51: 0.0015844374
A52: 520042177 | B52: 12936 | C52: ישפרו | D52: 516291754 | E52: ח.פ. | F52: ישפרו אגח א | G52: IL0012022906 | H52: ISIN | I52: צמוד למדד המחירים לצרכן | J52: ישראל | K52: ישראל | L52: סחיר | M52: TASE | N52: נדל"ן מניב בישראל | O52: לא | Q52: NR | R52: NR | S52: ILS | T52: 2.99 | U52: 31/12/2027 | V52: 0.0454 | W52: 0.0382 | X52: החוב לא נחות | Y52: לא | Z52: 155000 | AA52: 1 | AB52: 107.58 | AD52: 166.749 | AG52: שווי הוגן | AH52: 0.00016 | AI52: =AD52/SUMIF(B:B,B52,AD:AD) -> 0.0095224861 | AJ52: 0.0015672283
A53: 520042177 | B53: 12936 | C53: רני צים | D53: 514353671 | E53: ח.פ. | F53: רני צים אגח ב | G53: IL0011718348 | H53: ISIN | I53: צמוד למדד המחירים לצרכן | J53: ישראל | K53: ישראל | L53: סחיר | M53: TASE | N53: נדל"ן מניב בישראל | O53: לא | P53: ilA- | Q53: S&P מעלות | R53: נייר ערך | S53: ILS | T53: 3.05 | U53: 01/03/2028 | V53: 0.03455 | W53: 0.0346 | X53: החוב לא נחות | Y53: לא | Z53: 147750.45 | AA53: 1 | AB53: 107.63 | AD53: 159.024 | AG53: שווי הוגן | AH53: 0.0005 | AI53: =AD53/SUMIF(B:B,B53,AD:AD) -> 0.0090813368 | AJ53: 0.0014946231
A54: 520042177 | B54: 12936 | C54: אדגר השקעות | D54: 520035171 | E54: ח.פ. | F54: אדגר אגח יא | G54: IL0018202817 | H54: ISIN | I54: צמוד למדד המחירים לצרכן | J54: ישראל | K54: ישראל | L54: סחיר | M54: TASE | N54: נדל"ן מניב בחו"ל | O54: לא | P54: A2.il | Q54: מידרוג Moodys | R54: נייר ערך | S54: ILS | T54: 3.19 | U54: 31/03/2030 | V54: 0.03595 | W54: 0.0361 | X54: החוב לא נחות | Y54: לא | Z54: 139000 | AA54: 1 | AB54: 111.09 | AD54: 154.415 | AG54: שווי הוגן | AH54: 0.00028 | AI54: =AD54/SUMIF(B:B,B54,AD:AD) -> 0.008818132 | AJ54: 0.0014513044
A55: 520042177 | B55: 12936 | C55: נאוויטס פטרו | D55: 550263107 | E55: ח.פ. | F55: נאוויטס פט אגח ו | G55: IL0012048257 | H55: ISIN | I55: לא צמוד למדד המחירים לצרכן | J55: ישראל | K55: ישראל | L55: סחיר | M55: TASE | N55: חיפושי נפט וגז | O55: לא | P55: ilA- | Q55: S&P מעלות | R55: נייר ערך | S55: ILS | T55: 3.75 | U55: 30/09/2029 | V55: 0.0551 | W55: 0.0657 | X55: החוב לא נחות | Y55: לא | Z55: 151597 | AA55: 1 | AB55: 100.86 | AD55: 152.901 | AG55: שווי הוגן | AH55: 0.00017 | AI55: =AD55/SUMIF(B:B,B55,AD:AD) -> 0.0087316724 | AJ55: 0.0014370747
A56: 520042177 | B56: 12936 | C56: אקסטל לימיטד | D56: 1811308 | E56: מספר תאגיד או שותפות בחו"ל | F56: אקסטל אגח ג | G56: IL0011750416 | H56: ISIN | I56: לא צמוד למדד המחירים לצרכן | J56: ישראל | K56: ארה"ב | L56: סחיר | M56: TASE | N56: בנייה | O56: לא | P56: A3.il | Q56: מידרוג Moodys | R56: נייר ערך | S56: ILS | T56: 0.97 | U56: 31/03/2026 | V56: 0.07516 | W56: 0.0721 | X56: החוב לא נחות | Y56: לא | Z56: 150053.5 | AA56: 1 | AB56: 99.95 | AD56: 149.978 | AG56: שווי הוגן | AH56: 0.00038 | AI56: =AD56/SUMIF(B:B,B56,AD:AD) -> 0.0085647495 | AJ56: 0.0014096022
A57: 520042177 | B57: 12936 | C57: נכסים ובנין | D57: 520025438 | E57: ח.פ. | F57: נכסים ובנ אגח י | G57: IL0011936304 | H57: ISIN | I57: צמוד למדד המחירים לצרכן | J57: ישראל | K57: ישראל | L57: סחיר | M57: TASE | N57: נדל"ן מניב בישראל | O57: לא | P57: ilA | Q57: S&P מעלות | R57: נייר ערך | S57: ILS | T57: 4.05 | U57: 01/07/2029 | V57: 0.03541 | W57: 0.039 | X57: החוב לא נחות | Y57: לא | Z57: 137520 | AA57: 1 | AB57: 106.27 | AD57: 146.143 | AG57: שווי הוגן | AH57: 8e-05 | AI57: =AD57/SUMIF(B:B,B57,AD:AD) -> 0.0083457453 | AJ57: 0.0013735581
A58: 520042177 | B58: 12936 | C58: וויי-בוקס | D58: 520038688 | E58: ח.פ. | F58: וויי בוקס אג ג | G58: IL0048601772 | H58: ISIN | I58: אג"ח להמרה לא צמוד למדד המחירים לצרכן | J58: ישראל | K58: ישראל | L58: סחיר | M58: TASE | N58: בנייה | O58: לא | Q58: NR | R58: NR | S58: ILS | T58: 1.22 | U58: 31/12/2025 | V58: 0.08673 | W58: 0.0843 | X58: החוב לא נחות | Y58: לא | Z58: 150000 | AA58: 1 | AB58: 96.7 | AD58: 145.05 | AG58: שווי הוגן | AH58: 0.00188 | AI58: =AD58/SUMIF(B:B,B58,AD:AD) -> 0.0082833277 | AJ58: 0.0013632853
A59: 520042177 | B59: 12936 | C59: רם אדרת | D59: 512947185 | E59: ח.פ. | F59: רם אדרת אגח ב | G59: IL0012094368 | H59: ISIN | I59: לא צמוד למדד המחירים לצרכן | J59: ישראל | K59: ישראל | L59: סחיר | M59: TASE | N59: בנייה | O59: לא | Q59: NR | R59: NR | S59: ILS | T59: 2.91 | U59: 30/06/2028 | V59: 0.07765 | W59: 0.0703 | X59: החוב לא נחות | Y59: לא | Z59: 137000 | AA59: 1 | AB59: 102.79 | AD59: 140.822 | AG59: שווי הוגן | AH59: 0.00229 | AI59: =AD59/SUMIF(B:B,B59,AD:AD) -> 0.0080418805 | AJ59: 0.0013235475
A60: 520042177 | B60: 12936 | C60: איסתא | D60: 520042763 | E60: ח.פ. | F60: איסתא אג א | G60: IL0011971285 | H60: ISIN | I60: אג"ח להמרה לא צמוד למדד המחירים לצרכן | J60: ישראל | K60: ישראל | L60: סחיר | M60: TASE | N60: מלונאות ותיירות | O60: לא | Q60: NR | R60: NR | S60: ILS | T60: 3.43 | U60: 30/06/2028 | V60: 0.05797 | W60: 0.05 | X60: החוב לא נחות | Y60: לא | Z60: 120000 | AA60: 1 | AB60: 100.9 | AD60: 121.08 | AG60: שווי הוגן | AH60: 0.0004 | AI60: =AD60/SUMIF(B:B,B60,AD:AD) -> 0.0069144799 | AJ60: 0.0011379978
A61: 520042177 | B61: 12936 | C61: אלה השקעות | D61: 520040015 | E61: ח.פ. | F61: אלה השק אגח א | G61: IL0011899502 | H61: ISIN | I61: צמוד למדד המחירים לצרכן | J61: ישראל | K61: ישראל | L61: סחיר | M61: TASE | N61: נדל"ן מניב בישראל | O61: לא | P61: ilA | Q61: S&P מעלות | R61: נייר ערך | S61: ILS | T61: 2.38 | U61: 01/07/2029 | V61: 0.02331 | W61: 0.0339 | X61: החוב לא נחות | Y61: לא | Z61: 100000 | AA61: 1 | AB61: 106.34 | AD61: 106.34 | AG61: שווי הוגן | AH61: 0.00053 | AI61: =AD61/SUMIF(B:B,B61,AD:AD) -> 0.0060727271 | AJ61: 0.00099946061
A62: 520042177 | B62: 12936 | C62: לוזון רונסון | D62: 560040545 | E62: ח.פ. | F62: לוזון רונ אגח א | G62: IL0012023409 | H62: ISIN | I62: לא צמוד למדד המחירים לצרכן | J62: ישראל | K62: ישראל | L62: סחיר | M62: TASE | N62: בנייה | O62: לא | Q62: NR | R62: NR | S62: ILS | T62: 3.45 | U62: 25/09/2030 | V62: 0.07779 | W62: 0.0679 | X62: החוב לא נחות | Y62: לא | Z62: 101000 | AA62: 1 | AB62: 105.11 | AD62: 106.161 | AG62: שווי הוגן | AH62: 0.00049 | AI62: =AD62/SUMIF(B:B,B62,AD:AD) -> 0.006062505 | AJ62: 0.00099777823
A63: 520042177 | B63: 12936 | C63: גפן מגורים | D63: 512781386 | E63: ח.פ. | F63: גפן מגורים אג א | G63: IL0011996860 | H63: ISIN | I63: לא צמוד למדד המחירים לצרכן | J63: ישראל | K63: ישראל | L63: סחיר | M63: TASE | N63: בנייה | O63: לא | Q63: NR | R63: NR | S63: ILS | T63: 3.6 | U63: 01/10/2028 | V63: 0.06367 | W63: 0.0173 | X63: החוב לא נחות | Y63: לא | Z63: 87949 | AA63: 1 | AB63: 120.3 | AD63: 105.803 | AG63: שווי הוגן | AH63: 0.00175 | AI63: =AD63/SUMIF(B:B,B63,AD:AD) -> 0.0060420608 | AJ63: 0.00099441349
A64: 520042177 | B64: 12936 | C64: ישרס | D64: 520017807 | E64: ח.פ. | F64: ישרס אג18 | G64: IL0061302803 | H64: ISIN | I64: צמוד למדד המחירים לצרכן | J64: ישראל | K64: ישראל | L64: סחיר | M64: TASE | N64: נדל"ן מניב בישראל | O64: לא | P64: ilAA | Q64: S&P מעלות | R64: נייר ערך | S64: ILS | T64: 4.75 | U64: 10/04/2030 | V64: 0.02485 | W64: 0.0292 | X64: החוב לא נחות | Y64: לא | Z64: 100000.08 | AA64: 1 | AB64: 104.22 | AD64: 104.22 | AG64: שווי הוגן | AH64: 0.00013 | AI64: =AD64/SUMIF(B:B,B64,AD:AD) -> 0.0059516609 | AJ64: 0.00097953531
A65: 520042177 | B65: 12936 | C65: יובלים קבוצה | D65: 514625094 | E65: ח.פ. | F65: יובלים אגח ד | G65: IL0012040239 | H65: ISIN | I65: לא צמוד למדד המחירים לצרכן | J65: ישראל | K65: ישראל | L65: סחיר | M65: TASE | N65: בנייה | O65: לא | Q65: NR | R65: NR | S65: ILS | T65: 2.78 | U65: 05/01/2028 | V65: 0.07855 | W65: 0.0709 | X65: החוב לא נחות | Y65: לא | Z65: 100000 | AA65: 1 | AB65: 103.54 | AD65: 103.54 | AG65: שווי הוגן | AH65: 0.00084 | AI65: =AD65/SUMIF(B:B,B65,AD:AD) -> 0.0059128283 | AJ65: 0.00097314417
A66: 520042177 | B66: 12936 | C66: עזריאלי קבוצה | D66: 510960719 | E66: ח.פ. | F66: עזריאלי אגח ז | G66: IL0011786725 | H66: ISIN | I66: צמוד למדד המחירים לצרכן | J66: ישראל | K66: ישראל | L66: סחיר | M66: TASE | N66: נדל"ן מניב בישראל | O66: לא | P66: ilAA+ | Q66: S&P מעלות | R66: נייר ערך | S66: ILS | T66: 6.92 | U66: 02/07/2036 | V66: 0.02837 | W66: 0.0334 | X66: החוב לא נחות | Y66: לא | Z66: 105840 | AA66: 1 | AB66: 96.33 | AD66: 101.956 | AG66: שווי הוגן | AH66: 4e-05 | AI66: =AD66/SUMIF(B:B,B66,AD:AD) -> 0.0058223713 | AJ66: 0.00095825659
A67: 520042177 | B67: 12936 | C67: מניף-פיננסים | D67: 512764408 | E67: ח.פ. | F67: מניף אגח א | G67: IL0011858839 | H67: ISIN | I67: לא צמוד למדד המחירים לצרכן | J67: ישראל | K67: ישראל | L67: סחיר | M67: TASE | N67: אשראי חוץ בנקאי | O67: לא | P67: A3.il | Q67: מידרוג Moodys | R67: נייר ערך | S67: ILS | T67: 1.45 | U67: 30/09/2026 | V67: 0.00311 | W67: 0.066 | X67: החוב לא נחות | Y67: לא | Z67: 100500 | AA67: 1 | AB67: 100.59 | AD67: 101.093 | AG67: שווי הוגן | AH67: 0.00042 | AI67: =AD67/SUMIF(B:B,B67,AD:AD) -> 0.0057730882 | AJ67: 0.00095014549
A68: 520042177 | B68: 12936 | C68: אפי נכסים | D68: 510560188 | E68: ח.פ. | F68: אפי נכסים אגחיד | G68: IL0011845307 | H68: ISIN | I68: צמוד למדד המחירים לצרכן | J68: ישראל | K68: ישראל | L68: סחיר | M68: TASE | N68: נדל"ן מניב בחו"ל | O68: לא | P68: A2.il | Q68: מידרוג Moodys | R68: נייר ערך | S68: ILS | T68: 5.16 | U68: 30/03/2031 | V68: 0.0137 | W68: 0.0366 | X68: החוב לא נחות | Y68: לא | Z68: 100000 | AA68: 1 | AB68: 100.74 | AD68: 100.74 | AG68: שווי הוגן | AH68: 0.00017 | AI68: =AD68/SUMIF(B:B,B68,AD:AD) -> 0.0057529295 | AJ68: 0.00094682774
A69: 520042177 | B69: 12936 | C69: איירפורט סיטי | D69: 511659401 | E69: ח.פ. | F69: ארפורט אג 9 | G69: IL0011609448 | H69: ISIN | I69: צמוד למדד המחירים לצרכן | J69: ישראל | K69: ישראל | L69: סחיר | M69: TASE | N69: נדל"ן מניב בישראל | O69: לא | P69: ilAA | Q69: S&P מעלות | R69: נייר ערך | S69: ILS | T69: 5.36 | U69: 30/08/2035 | V69: 0.03091 | W69: 0.0331 | X69: החוב לא נחות | Y69: לא | Z69: 92771.08 | AA69: 1 | AB69: 99.45 | AD69: 92.261 | AG69: שווי הוגן | AH69: 4e-05 | AI69: =AD69/SUMIF(B:B,B69,AD:AD) -> 0.0052687218 | AJ69: 0.00086713593
A70: 520042177 | B70: 12936 | C70: אלומיי קפיטל | D70: 520039868 | E70: ח.פ. | F70: אלומיי אגח ו | G70: IL0012030743 | H70: ISIN | I70: לא צמוד למדד המחירים לצרכן | J70: ישראל | K70: ישראל | L70: סחיר | M70: TASE | N70: אנרגיה מתחדשת | O70: לא | Q70: NR | R70: NR | S70: ILS | T70: 3.39 | U70: 31/03/2030 | V70: 0.05994 | W70: 0.0705 | X70: החוב לא נחות | Y70: לא | Z70: 96000 | AA70: 1 | AB70: 95.4 | AD70: 91.584 | AG70: שווי הוגן | AH70: 0.00037 | AI70: =AD70/SUMIF(B:B,B70,AD:AD) -> 0.0052300605 | AJ70: 0.00086077299
A71: 520042177 | B71: 12936 | C71: רמות בעיר | D71: 514328004 | E71: ח.פ. | F71: רמות בעיר אגח ב | G71: IL0011824013 | H71: ISIN | I71: לא צמוד למדד המחירים לצרכן | J71: ישראל | K71: ישראל | L71: סחיר | M71: TASE | N71: בנייה | O71: לא | Q71: NR | R71: NR | S71: ILS | T71: 1.4 | U71: 30/06/2026 | V71: 0.08453 | W71: 0.0483 | X71: החוב לא נחות | Y71: לא | Z71: 92000 | AA71: 1 | AB71: 98.89 | AD71: 90.979 | AG71: שווי הוגן | AH71: 0.00071 | AI71: =AD71/SUMIF(B:B,B71,AD:AD) -> 0.005195511 | AJ71: 0.00085508676
A72: 520042177 | B72: 12936 | C72: מימון ישיר קב | D72: 513893123 | E72: ח.פ. | F72: מימון ישיר אגח ד | G72: IL0011756603 | H72: ISIN | I72: צמוד למדד המחירים לצרכן | J72: ישראל | K72: ישראל | L72: סחיר | M72: TASE | N72: אשראי חוץ בנקאי | O72: לא | P72: A1.il | Q72: מידרוג Moodys | R72: נייר ערך | S72: ILS | T72: 0.66 | U72: 01/02/2026 | V72: 0.01639 | W72: 0.0271 | X72: החוב לא נחות | Y72: לא | Z72: 72000 | AA72: 1 | AB72: 113.12 | AD72: 81.446 | AG72: שווי הוגן | AH72: 0.00024 | AI72: =AD72/SUMIF(B:B,B72,AD:AD) -> 0.0046511128 | AJ72: 0.0007654887
A73: 520042177 | B73: 12936 | C73: אפי נכסים | D73: 510560188 | E73: ח.פ. | F73: אפריקה נכס אגחח | G73: IL0011422313 | H73: ISIN | I73: צמוד למדד המחירים לצרכן | J73: ישראל | K73: ישראל | L73: סחיר | M73: TASE | N73: נדל"ן מניב בחו"ל | O73: לא | P73: A2.il | Q73: מידרוג Moodys | R73: נייר ערך | S73: ILS | T73: 1.46 | U73: 15/10/2026 | V73: 0.02649 | W73: 0.0311 | X73: החוב לא נחות | Y73: לא | Z73: 50000 | AA73: 1 | AB73: 116.88 | AD73: 58.44 | AG73: שווי הוגן | AH73: 4e-05 | AI73: =AD73/SUMIF(B:B,B73,AD:AD) -> 0.0033373159 | AJ73: 0.00054926159
A74: 520042177 | B74: 12936 | C74: גבאי מניבים | D74: 520032178 | E74: ח.פ. | F74: גבאי מניבים אגח יב | G74: IL0077102627 | H74: ISIN | I74: לא צמוד למדד המחירים לצרכן | J74: ישראל | K74: ישראל | L74: סחיר | M74: TASE | N74: בנייה | O74: לא | Q74: NR | R74: NR | S74: ILS | T74: 1.65 | U74: 30/06/2027 | V74: 0.0419 | W74: 0.0724 | X74: החוב לא נחות | Y74: לא | Z74: 59195 | AA74: 1 | AB74: 96.4 | AD74: 57.064 | AG74: שווי הוגן | AH74: 0.00074 | AI74: =AD74/SUMIF(B:B,B74,AD:AD) -> 0.0032587371 | AJ74: 0.00053632895
A75: 520042177 | B75: 12936 | C75: רותם שני | D75: 512287517 | E75: ח.פ. | F75: רותם שני אגח א | G75: IL0011739963 | H75: ISIN | I75: לא צמוד למדד המחירים לצרכן | J75: ישראל | K75: ישראל | L75: סחיר | M75: TASE | N75: בנייה | O75: לא | Q75: NR | R75: NR | S75: ILS | T75: 0.54 | U75: 30/06/2025 | V75: 0.04039 | W75: 0.0727 | X75: החוב לא נחות | Y75: לא | Z75: 47093.33 | AA75: 1 | AB75: 99.72 | AD75: 46.961 | AG75: שווי הוגן | AH75: 0.00081 | AI75: =AD75/SUMIF(B:B,B75,AD:AD) -> 0.002681788 | AJ75: 0.00044137361
A76: 520042177 | B76: 12936 | C76: ספנסר אקוויטי | D76: 1838863 | E76: מספר תאגיד או שותפות בחו"ל | F76: ספנסר אג2 | G76: IL0011398984 | H76: ISIN | I76: לא צמוד למדד המחירים לצרכן | J76: ישראל | K76: ארה"ב | L76: סחיר | M76: TASE | N76: נדל"ן מניב בחו"ל | O76: לא | P76: ilA | Q76: S&P מעלות | R76: נייר ערך | S76: ILS | T76: 1.86 | U76: 31/03/2028 | V76: 0.06943 | W76: 0.0708 | X76: החוב לא נחות | Y76: לא | Z76: 39701 | AA76: 1 | AB76: 97.67 | AD76: 38.776 | AG76: שווי הוגן | AH76: 0.00014 | AI76: =AD76/SUMIF(B:B,B76,AD:AD) -> 0.0022143696 | AJ76: 0.00036444503
A77: 520042177 | B77: 12936 | C77: ירושלים הנפקות | D77: 513682146 | E77: ח.פ. | F77: ירושלים הנפ נד17 | G77: IL0011763120 | H77: ISIN | I77: צמוד למדד המחירים לצרכן | J77: ישראל | K77: ישראל | L77: סחיר | M77: TASE | N77: בנקים | O77: לא | P77: ilA- | Q77: S&P מעלות | R77: נייר ערך | S77: ILS | T77: 2.63 | U77: 31/05/2027 | V77: 0.0122 | W77: 0.0347 | X77: החוב נחות | Y77: לא | Z77: 30744 | AA77: 1 | AB77: 108.22 | AD77: 33.271 | AG77: שווי הוגן | AH77: 0.00022 | AI77: =AD77/SUMIF(B:B,B77,AD:AD) -> 0.0018999972 | AJ77: 0.00031270504
A78: 520042177 | B78: 12936 | C78: גבאי מניבים | D78: 520032178 | E78: ח.פ. | F78: גבאי מניבים אגח יג | G78: IL0077102965 | H78: ISIN | I78: לא צמוד למדד המחירים לצרכן | J78: ישראל | K78: ישראל | L78: סחיר | M78: TASE | N78: בנייה | O78: לא | Q78: NR | R78: NR | S78: ILS | T78: 1.63 | U78: 30/06/2027 | V78: 0.0625 | W78: 0.0764 | X78: החוב לא נחות | Y78: לא | Z78: 29858.25 | AA78: 1 | AB78: 99.6 | AD78: 29.739 | AG78: שווי הוגן | AH78: 0.0004 | AI78: =AD78/SUMIF(B:B,B78,AD:AD) -> 0.0016982963 | AJ78: 0.00027950874
A79: 520042177 | B79: 12936 | C79: גב ים | D79: 520001736 | E79: ח.פ. | F79: גב ים אגח י | G79: IL0075902846 | H79: ISIN | I79: צמוד למדד המחירים לצרכן | J79: ישראל | K79: ישראל | L79: סחיר | M79: TASE | N79: נדל"ן מניב בישראל | O79: לא | P79: ilAA | Q79: S&P מעלות | R79: נייר ערך | S79: ILS | T79: 5.14 | U79: 01/07/2035 | V79: 0.03493 | W79: 0.0332 | X79: החוב לא נחות | Y79: לא | Z79: 17011 | AA79: 1 | AB79: 97.54 | AD79: 16.593 | AG79: שווי הוגן | AH79: 1e-05 | AI79: =AD79/SUMIF(B:B,B79,AD:AD) -> 0.00094757157 | AJ79: 0.00015595307
A80: 520042177 | B80: 12936 | C80: מליסרון | D80: 520037789 | E80: ח.פ. | F80: מליסרון אגח כ | G80: IL0032304227 | H80: ISIN | I80: צמוד למדד המחירים לצרכן | J80: ישראל | K80: ישראל | L80: סחיר | M80: TASE | N80: נדל"ן מניב בישראל | O80: לא | P80: ilAA | Q80: S&P מעלות | R80: נייר ערך | S80: ILS | T80: 5.3 | U80: 01/07/2030 | V80: 0.02745 | W80: 0.0303 | X80: החוב לא נחות | Y80: לא | Z80: 494.27 | AA80: 1 | AB80: 97.92 | AD80: 0.484 | AG80: שווי הוגן | AH80: 0 | AI80: =AD80/SUMIF(B:B,B80,AD:AD) -> 2.7639646e-05 | AJ80: 4.5489838e-06
A81: 520042177 | B81: 12936 | C81: גיבוי אחזקות | D81: 520039314 | E81: ח.פ. | F81: גיבוי אחזקות אגח א (הסדר חוב) | G81: 4480133 | H81: פנימי | I81: לא צמוד למדד המחירים לצרכן | J81: ישראל | K81: ישראל | L81: אחר | M81: TASE | N81: אשראי חוץ בנקאי | O81: לא | P81: NR | Q81: מידרוג Moodys | R81: נייר ערך | S81: ILS | T81: 0.01 | U81: 04/12/2022 | V81: 0.03426 | W81: 9.99 | X81: החוב לא נחות | Y81: כן | Z81: 75000 | AA81: 1 | AB81: 25 | AD81: 18.75 | AG81: שווי הוגן | AH81: 0.00738 | AI81: =AD81/SUMIF(B:B,B81,AD:AD) -> 0.0010707507 | AJ81: 0.00017622613
A82: 520042177 | B82: 12936 | C82: אאורה | D82: 520038274 | E82: ח.פ. | F82: אאורה אגח יז | G82: IL0011935801 | H82: ISIN | I82: צמוד למדד המחירים לצרכן | J82: ישראל | K82: ישראל | L82: חסום | M82: TASE | N82: בנייה | O82: לא | P82: A2.il | Q82: מידרוג Moodys | R82: נייר ערך | S82: ILS | T82: 2.82 | U82: 31/01/2029 | V82: 0.03268 | W82: 0.0322 | X82: החוב לא נחות | Y82: לא | Z82: 91000 | AA82: 1 | AB82: =AD82*1000/Z82*100 -> 108.99 | AD82: =99180.9/1000 -> 99.1809 | AG82: שווי הוגן | AI82: =AD82/SUMIF(B:B,B82,AD:AD) -> 0.0056638945 | AJ82: 0.00093217418
A83: 520042177 | B83: 12936 | C83: אפי קפיטל נדלן | D83: 513948216 | E83: ח.פ. | F83: אפי קפיטל אגח ג | G83: IL0011997447 | H83: ISIN | I83: לא צמוד למדד המחירים לצרכן | J83: ישראל | K83: ישראל | L83: חסום | M83: TASE | N83: בנייה | O83: לא | Q83: NR | R83: NR | S83: ILS | T83: 2.05 | U83: 30/06/2027 | V83: 0.0661 | W83: 0.0711 | X83: החוב לא נחות | Y83: לא | Z83: 100000 | AA83: 1 | AB83: =AD83*1000/Z83*100 -> 105.22 | AD83: =105220/1000 -> 105.22 | AG83: שווי הוגן | AI83: =AD83/SUMIF(B:B,B83,AD:AD) -> 0.0060087676 | AJ83: 0.00098893403
A84: 520042177 | B84: 12936 | C84: עמרם | D84: 513201582 | E84: ח.פ. | F84: עמרם אברהם אגח א | G84: IL0011880445 | H84: ISIN | I84: לא צמוד למדד המחירים לצרכן | J84: ישראל | K84: ישראל | L84: חסום | M84: TASE | N84: בנייה | O84: לא | Q84: NR | R84: NR | S84: ILS | T84: 1.59 | U84: 31/05/2027 | V84: 0.06489 | W84: 0.0631 | X84: החוב לא נחות | Y84: לא | Z84: 183222.22 | AA84: 1 | AB84: =AD84*1000/Z84*100 -> 101.67 | AD84: =186282.031074/1000 -> 186.28203 | AG84: שווי הוגן | AI84: =AD84/SUMIF(B:B,B84,AD:AD) -> 0.010637953 | AJ84: 0.0017508139
A85: 520042177 | B85: 12936 | C85: מימון ישיר קב | D85: 513893123 | E85: ח.פ. | F85: מימון ישיר אגח ה | G85: IL0011828311 | H85: ISIN | I85: צמוד למדד המחירים לצרכן | J85: ישראל | K85: ישראל | L85: חסום | M85: TASE | N85: אשראי חוץ בנקאי | O85: לא | P85: A1.il | Q85: מידרוג Moodys | R85: נייר ערך | S85: ILS | T85: 3.25 | U85: 31/07/2031 | V85: 0.02949 | W85: 0.0333 | X85: החוב לא נחות | Y85: לא | Z85: 55000 | AA85: 1 | AB85: =AD85*1000/Z85*100 -> 104.54 | AD85: =57497/1000 -> 57.497 | AG85: שווי הוגן | AI85: =AD85/SUMIF(B:B,B85,AD:AD) -> 0.0032834643 | AJ85: 0.00054039859
A86: 520042177 | B86: 12936 | C86: VIATRIS | D86: 5247 | E86: מספר מנפיק | F86: VTRS 3.95 15/06/26 | G86: US62854AAN46 | H86: ISIN | I86: צמוד למט"ח | J86: חו"ל | K86: ארה"ב | L86: סחיר | M86: אחר | N86: Pharmaceuticals | O86: לא | P86: BBB- | Q86: S&P | R86: נייר ערך | S86: USD | T86: 1.609 | U86: 15/06/2026 | V86: 0.05816 | W86: 0.045 | X86: החוב לא נחות | Y86: לא | Z86: 34000 | AA86: 3.71 | AB86: 100.123 | AD86: 126.295 | AG86: שווי הוגן | AH86: 2e-05 | AI86: =AD86/SUMIF(B:B,B86,AD:AD) -> 0.0072122914 | AJ86: 0.0011870122
A87: 520042177 | B87: 12936 | C87: לאומי | D87: 520018078 | E87: ח.פ. | F87: LUMIIT 3.275 29/01/31 | G87: IL0060404899 | H87: ISIN | I87: צמוד למט"ח | J87: חו"ל | K87: ישראל | L87: סחיר | M87: TASE | N87: Banks | O87: לא | P87: BBB- | Q87: S&P | R87: נייר ערך | S87: USD | T87: 1.253 | U87: 29/01/2031 | V87: 0.05638 | W87: 0.0795 | X87: החוב לא נחות | Y87: לא | Z87: 27000 | AA87: 3.71 | AB87: 95.29 | AD87: 95.452 | AG87: שווי הוגן | AH87: 4e-05 | AI87: =AD87/SUMIF(B:B,B87,AD:AD) -> 0.0054509493 | AJ87: 0.00089712727
A88: 520042177 | B88: 12936 | C88: מזרחי טפחות | D88: 520000522 | E88: ח.פ. | F88: MZRHIT 3.077 07/04/31 | G88: IL0069508369 | H88: ISIN | I88: צמוד למט"ח | J88: חו"ל | K88: ישראל | L88: סחיר | M88: TASE | N88: Banks | O88: לא | P88: BBB- | Q88: S&P | R88: נייר ערך | S88: USD | T88: 1.437 | U88: 07/04/2031 | V88: 0.05642 | W88: 0.07433 | X88: החוב לא נחות | Y88: לא | Z88: 27000 | AA88: 3.71 | AB88: 95.181 | AD88: 95.342 | AG88: שווי הוגן | AH88: 4e-05 | AI88: =AD88/SUMIF(B:B,B88,AD:AD) -> 0.0054446675 | AJ88: 0.00089609341
A89: 520042177 | B89: 12936 | C89: LEVIATHAN BOND | D89: 5338 | E89: מספר מנפיק | F89: LVIATH 6.125 30/06/25 | G89: IL0011677742 | H89: ISIN | I89: צמוד למט"ח | J89: חו"ל | K89: ישראל | L89: סחיר | M89: אחר | N89: Energy Equipment & Services | O89: לא | P89: BB- | Q89: S&P | R89: נייר ערך | S89: USD | T89: 0.698 | U89: 30/06/2025 | V89: 0.06125 | W89: 0.08032 | X89: החוב לא נחות | Y89: לא | Z89: 18000 | AA89: 3.71 | AB89: 99.778 | AD89: 66.632 | AG89: שווי הוגן | AH89: 3e-05 | AI89: =AD89/SUMIF(B:B,B89,AD:AD) -> 0.003805134 | AJ89: 0.00062625596
A90: 520042177 | B90: 12936 | C90: LEVIATHAN BOND | D90: 5338 | E90: מספר מנפיק | F90: LVIATH 6.5 30/06/27 | G90: IL0011677825 | H90: ISIN | I90: צמוד למט"ח | J90: חו"ל | K90: ישראל | L90: סחיר | M90: אחר | N90: Energy Equipment & Services | O90: לא | P90: BB- | Q90: S&P | R90: נייר ערך | S90: USD | T90: 2.405 | U90: 30/06/2027 | V90: 0.065 | W90: 0.08487 | X90: החוב לא נחות | Y90: לא | Z90: 18000 | AA90: 3.71 | AB90: 96.223 | AD90: 64.258 | AG90: שווי הוגן | AH90: 3e-05 | AI90: =AD90/SUMIF(B:B,B90,AD:AD) -> 0.0036695627 | AJ90: 0.00060394339
A91: 520042177 | B91: 12937 | C91: סטרוברי אינק | D91: 842336054 | E91: מספר תאגיד או שותפות בחו"ל | F91: סטרברי אנ אגח א | G91: IL0012098997 | H91: ISIN | I91: לא צמוד למדד המחירים לצרכן | J91: ישראל | K91: ארה"ב | L91: סחיר | M91: TASE | N91: נדל"ן מניב בחו"ל | O91: לא | P91: ilA+ | Q91: S&P מעלות | R91: נייר ערך | S91: ILS | T91: 1.84 | U91: 30/09/2026 | V91: 0.07374 | W91: 0.0737 | X91: החוב לא נחות | Y91: לא | Z91: 9283890.1 | AA91: 1 | AB91: 99.55 | AD91: 9242.113 | AG91: שווי הוגן | AH91: 0.05034 | AI91: =AD91/SUMIF(B:B,B91,AD:AD) -> 0.034745929 | AJ91: 0.0085517857
A92: 520042177 | B92: 12937 | C92: בית זיקוק אשדוד | D92: 513775163 | E92: ח.פ. | F92: בית זיקוק אגח 2 | G92: IL0011994881 | H92: ISIN | I92: לא צמוד למדד המחירים לצרכן | J92: ישראל | K92: ישראל | L92: סחיר | M92: TASE | N92: אנרגיה | O92: לא | P92: A3.il | Q92: מידרוג Moodys | R92: נייר ערך | S92: ILS | T92: 3 | U92: 30/04/2029 | V92: 0.0725 | W92: 0.064 | X92: החוב לא נחות | Y92: לא | Z92: 6732584 | AA92: 1 | AB92: 105.92 | AD92: 7131.153 | AG92: שווי הוגן | AH92: 0.00935 | AI92: =AD92/SUMIF(B:B,B92,AD:AD) -> 0.026809728 | AJ92: 0.006598501
A93: 520042177 | B93: 12937 | C93: מגה אור | D93: 513257873 | E93: ח.פ. | F93: מגה אור אגח יב | G93: IL0012112830 | H93: ISIN | I93: צמוד למדד המחירים לצרכן | J93: ישראל | K93: ישראל | L93: סחיר | M93: TASE | N93: נדל"ן מניב בישראל | O93: לא | P93: ilAA- | Q93: S&P מעלות | R93: נייר ערך | S93: ILS | T93: 5.66 | U93: 01/05/2033 | V93: 0.02702 | W93: 0.0322 | X93: החוב לא נחות | Y93: לא | Z93: 4971000 | AA93: 1 | AB93: 100.92 | AD93: 5016.733 | AG93: שווי הוגן | AH93: 0.01392 | AI93: =AD93/SUMIF(B:B,B93,AD:AD) -> 0.018860519 | AJ93: 0.0046420148
A94: 520042177 | B94: 12937 | C94: מימון ישיר קב | D94: 513893123 | E94: ח.פ. | F94: מימון ישיר אגח ו | G94: IL0011916595 | H94: ISIN | I94: צמוד למדד המחירים לצרכן | J94: ישראל | K94: ישראל | L94: סחיר | M94: TASE | N94: אשראי חוץ בנקאי | O94: לא | P94: A1.il | Q94: מידרוג Moodys | R94: נייר ערך | S94: ILS | T94: 1.66 | U94: 31/03/2027 | V94: 0.03497 | W94: 0.0322 | X94: החוב לא נחות | Y94: לא | Z94: 4648000 | AA94: 1 | AB94: 107.7 | AD94: 5005.896 | AG94: שווי הוגן | AH94: 0.00416 | AI94: =AD94/SUMIF(B:B,B94,AD:AD) -> 0.018819777 | AJ94: 0.0046319873
A95: 520042177 | B95: 12937 | C95: אדמה | D95: 520043605 | E95: ח.פ. | F95: אדמה אגח 2 | G95: IL0011109159 | H95: ISIN | I95: צמוד למדד המחירים לצרכן | J95: ישראל | K95: ישראל | L95: סחיר | M95: TASE | N95: כימיה, גומי ופלסטיק | O95: לא | P95: ilAA- | Q95: S&P מעלות | R95: נייר ערך | S95: ILS | T95: 5.02 | U95: 30/11/2036 | V95: 0.0162 | W95: 0.0515 | X95: החוב לא נחות | Y95: לא | Z95: 3500000.4 | AA95: 1 | AB95: 141.9 | AD95: 4966.501 | AG95: שווי הוגן | AH95: 0.00126 | AI95: =AD95/SUMIF(B:B,B95,AD:AD) -> 0.018671671 | AJ95: 0.0045955348
A96: 520042177 | B96: 12937 | C96: אקסטל לימיטד | D96: 1811308 | E96: מספר תאגיד או שותפות בחו"ל | F96: אקסטל אגח ד | G96: IL0011831695 | H96: ISIN | I96: לא צמוד למדד המחירים לצרכן | J96: ישראל | K96: ארה"ב | L96: סחיר | M96: TASE | N96: בנייה | O96: לא | P96: A3.il | Q96: מידרוג Moodys | R96: נייר ערך | S96: ILS | T96: 2.51 | U96: 31/12/2027 | V96: 0.065 | W96: 0.0838 | X96: החוב לא נחות | Y96: לא | Z96: 5000000 | AA96: 1 | AB96: 97.5 | AD96: 4875 | AG96: שווי הוגן | AH96: 0.00833 | AI96: =AD96/SUMIF(B:B,B96,AD:AD) -> 0.018327671 | AJ96: 0.0045108684
A97: 520042177 | B97: 12937 | C97: רימון | D97: 512467994 | E97: ח.פ. | F97: רימון אגח א | G97: IL0012110362 | H97: ISIN | I97: לא צמוד למדד המחירים לצרכן | J97: ישראל | K97: ישראל | L97: סחיר | M97: TASE | N97: בנייה | O97: לא | P97: A2.il | Q97: מידרוג Moodys | R97: נייר ערך | S97: ILS | T97: 4.26 | U97: 30/04/2032 | V97: 0.05354 | W97: 0.0582 | X97: החוב לא נחות | Y97: לא | Z97: 4699000 | AA97: 1 | AB97: 100.66 | AD97: 4730.013 | AG97: שווי הוגן | AH97: 0.02685 | AI97: =AD97/SUMIF(B:B,B97,AD:AD) -> 0.017782589 | AJ97: 0.004376711
... A105: 520042177 | B105: 12937 | C105: אס.אר אקורד | D105: 520038670 | E105: ח.פ. | F105: אסאר אקורד אגח ב | G105: IL0042203724 | H105: ISIN | I105: צמוד למדד המחירים לצרכן | J105: ישראל | K105: ישראל | L105: סחיר | M105: TASE | N105: אשראי חוץ בנקאי | O105: לא | P105: A3.il | Q105: מידרוג Moodys | R105: נייר ערך | S105: ILS | T105: 1.46 | U105: 30/06/2027 | V105: 0.05744 | W105: 0.0434 | X105: החוב לא נחות | Y105: לא | Z105: 3538000 | AA105: 1 | AB105: 104.83 | AD105: 3708.885 | AG105: שווי הוגן | AH105: 0.01912 | AI105: =AD105/SUMIF(B:B,B105,AD:AD) -> 0.013943636 | AJ105: 0.0034318548
A106: 520042177 | B106: 12937 | C106: מימון ישיר קב | D106: 513893123 | E106: ח.פ. | F106: מימון ישיר אגח ה | G106: IL0011828311 | H106: ISIN | I106: צמוד למדד המחירים לצרכן | J106: ישראל | K106: ישראל | L106: חסום | M106: TASE | N106: אשראי חוץ בנקאי | O106: לא | P106: A1.il | Q106: מידרוג Moodys | R106: נייר ערך | S106: ILS | T106: 3.25 | U106: 31/07/2031 | V106: 0.02921 | W106: 0.0333 | X106: החוב לא נחות | Y106: לא | Z106: 1811000 | AA106: 1 | AB106: =AD106*1000/Z106*100 -> 104.02141 | AD106: =1883827.78797814/1000 -> 1883.8278 | AG106: שווי הוגן | AH106: 0.00221 | AI106: =AD106/SUMIF(B:B,B106,AD:AD) -> 0.0070822924 | AJ106: 0.0017431178
A107: 520042177 | B107: 12937 | C107: מנרב | D107: 520034505 | E107: ח.פ. | F107: מנרב אגח ד | G107: IL0015501690 | H107: ISIN | I107: צמוד למדד המחירים לצרכן | J107: ישראל | K107: ישראל | L107: סחיר | M107: TASE | N107: בנייה | O107: לא | P107: Baa1.il | Q107: מידרוג Moodys | R107: נייר ערך | S107: ILS | T107: 3.66 | U107: 15/04/2032 | V107: 0.04619 | W107: 0.0497 | X107: החוב לא נחות | Y107: לא | Z107: 3448141.2 | AA107: 1 | AB107: 101.96 | AD107: 3515.725 | AG107: שווי הוגן | AH107: 0.00723 | AI107: =AD107/SUMIF(B:B,B107,AD:AD) -> 0.013217446 | AJ107: 0.0032531226
...

Sheet מניות מבכ ויהש
A1: מספר קופה/קרן/ח.פ. עבור חברת ביטוח | B1: מספר מסלול | C1: שם מנפיק | D1: מספר מנפיק | E1: סוג מספר מזהה מנפיק | F1: שם נייר ערך | G1: מספר נייר ערך | H1: סוג מספר נייר ערך | I1: מאפיין עיקרי | J1: ישראל/חו"ל | K1: מדינה לפי חשיפה כלכלית | L1: סטאטוס סחירות | M1: זירת מסחר | N1: ענף מסחר | O1: בעל עניין/צד קשור | P1: מטבע פעילות | Q1: ערך נקוב (יחידות) | R1: שער חליפין | S1: שער נייר הערך | T1: סכום לקבל (במטבע הפעילות) | U1: שווי הוגן (באלפי ש"ח) | V1: שיעור מערך נקוב מונפק | W1: שיעור מנכסי אפיק ההשקעה | X1: שיעור מסך נכסי ההשקעה
A2: 520042177 | B2: 12937 | C2: לאומי | D2: 520018078 | E2: ח.פ. | F2: לאומי | G2: IL0006046119 | H2: ISIN | I2: מניות | J2: ישראל | K2: ישראל | L2: סחיר | M2: TASE | N2: בנקים | O2: לא | P2: ILS | Q2: 185574 | R2: 1 | S2: 3644 | U2: 6762.317 | V2: 0.00011 | W2: =U2/SUMIF(B:B,B2,U:U) -> 0.043195288 | X2: 0.0062572147
A3: 520042177 | B3: 12937 | C3: טבע | D3: 520013954 | E3: ח.פ. | F3: טבע | G3: IL0006290147 | H3: ISIN | I3: מניות | J3: ישראל | K3: ישראל | L3: סחיר | M3: TASE | N3: פארמה | O3: לא | P3: ILS | Q3: 100940 | R3: 1 | S3: 6629 | U3: 6691.313 | V3: 8e-05 | W3: =U3/SUMIF(B:B,B3,U:U) -> 0.042741739 | X3: 0.0061915143
A4: 520042177 | B4: 12937 | C4: פועלים | D4: 520000118 | E4: ח.פ. | F4: פועלים | G4: IL0006625771 | H4: ISIN | I4: מניות | J4: ישראל | K4: ישראל | L4: סחיר | M4: TASE | N4: בנקים | O4: לא | P4: ILS | Q4: 147475 | R4: 1 | S4: 3729 | U4: 5499.343 | V4: 0.00011 | W4: =U4/SUMIF(B:B,B4,U:U) -> 0.035127857 | X4: 0.0050885769
A5: 520042177 | B5: 12937 | C5: מזרחי טפחות | D5: 520000522 | E5: ח.פ. | F5: מזרחי | G5: IL0006954379 | H5: ISIN | I5: מניות | J5: ישראל | K5: ישראל | L5: סחיר | M5: TASE | N5: בנקים | O5: לא | P5: ILS | Q5: 30000 | R5: 1 | S5: 14550 | U5: 4365 | V5: 0.00012 | W5: =U5/SUMIF(B:B,B5,U:U) -> 0.027882075 | X5: 0.0040389621
A6: 520042177 | B6: 12937 | C6: עזריאלי קבוצה | D6: 510960719 | E6: ח.פ. | F6: עזריאלי קבוצה | G6: IL0011194789 | H6: ISIN | I6: מניות | J6: ישראל | K6: ישראל | L6: סחיר | M6: TASE | N6: נדל"ן מניב בישראל | O6: לא | P6: ILS | Q6: 16323 | R6: 1 | S6: 25940 | U6: 4234.186 | V6: 0.00013 | W6: =U6/SUMIF(B:B,B6,U:U) -> 0.027046482 | X6: 0.0039179191
A7: 520042177 | B7: 12937 | C7: נייס | D7: 520036872 | E7: ח.פ. | F7: נייס | G7: IL0002730112 | H7: ISIN | I7: מניות | J7: ישראל | K7: ישראל | L7: סחיר | M7: TASE | N7: תוכנה ואינטרנט | O7: לא | P7: ILS | Q7: 6000 | R7: 1 | S7: 64880 | U7: 3892.8 | V7: 8e-05 | W7: =U7/SUMIF(B:B,B7,U:U) -> 0.024865829 | X7: 0.0036020325
A8: 520042177 | B8: 12937 | C8: דיסקונט | D8: 520007030 | E8: ח.פ. | F8: דיסקונט | G8: IL0006912120 | H8: ISIN | I8: מניות | J8: ישראל | K8: ישראל | L8: סחיר | M8: TASE | N8: בנקים | O8: לא | P8: ILS | Q8: 185749 | R8: 1 | S8: 2085 | U8: 3872.867 | V8: 0.00015 | W8: =U8/SUMIF(B:B,B8,U:U) -> 0.024738504 | X8: 0.0035835884
A9: 520042177 | B9: 12937 | C9: דוראל אנרגיה | D9: 515364891 | E9: ח.פ. | F9: דוראל אנרגיה | G9: IL0011667685 | H9: ISIN | I9: מניות | J9: ישראל | K9: ישראל | L9: סחיר | M9: TASE | N9: אנרגיה מתחדשת | O9: לא | P9: ILS | Q9: 248056 | R9: 1 | S9: 1472 | U9: 3651.384 | V9: 0.00139 | W9: =U9/SUMIF(B:B,B9,U:U) -> 0.023323749 | X9: 0.0033786487
A10: 520042177 | B10: 12937 | C10: נובה | D10: 511812463 | E10: ח.פ. | F10: נובה | G10: IL0010845571 | H10: ISIN | I10: מניות | J10: ישראל | K10: ישראל | L10: סחיר | M10: TASE | N10: מוליכים למחצה | O10: לא | P10: ILS | Q10: 4350 | R10: 1 | S10: 77890 | U10: 3388.215 | V10: 0.00015 | W10: =U10/SUMIF(B:B,B10,U:U) -> 0.021642718 | X10: 0.0031351368
A11: 520042177 | B11: 12937 | C11: או.פי.סי אנרגיה | D11: 514401702 | E11: ח.פ. | F11: או.פי.סי אנרגיה | G11: IL0011415713 | H11: ISIN | I11: מניות | J11: ישראל | K11: ישראל | L11: סחיר | M11: TASE | N11: אנרגיה | O11: לא | P11: ILS | Q11: 107927 | R11: 1 | S11: 3016 | U11: 3255.078 | V11: 0.00042 | W11: =U11/SUMIF(B:B,B11,U:U) -> 0.020792286 | X11: 0.0030119443
A12: 520042177 | B12: 12937 | C12: הפניקס | D12: 520017450 | E12: ח.פ. | F12: פניקס 1 | G12: IL0007670123 | H12: ISIN | I12: מניות | J12: ישראל | K12: ישראל | L12: סחיר | M12: TASE | N12: ביטוח | O12: לא | P12: ILS | Q12: 72615 | R12: 1 | S12: 4200 | U12: 3049.83 | V12: 0.00028 | W12: =U12/SUMIF(B:B,B12,U:U) -> 0.019481235 | X12: 0.002822027
A13: 520042177 | B13: 12937 | C13: נכסים ובנין | D13: 520025438 | E13: ח.פ. | F13: נכסים בנין | G13: IL0006990175 | H13: ISIN | I13: מניות | J13: ישראל | K13: ישראל | L13: סחיר | M13: TASE | N13: נדל"ן מניב בישראל | O13: לא | P13: ILS | Q13: 11857 | R13: 1 | S13: 25580 | U13: 3033.021 | V13: 0.00161 | W13: =U13/SUMIF(B:B,B13,U:U) -> 0.019373865 | X13: 0.0028064735
... A23: 520042177 | B23: 12937 | C23: אלקטרה נדל"ן | D23: 510607328 | E23: ח.פ. | F23: אלקטרה נדלן | G23: IL0010940448 | H23: ISIN | I23: מניות | J23: ישראל | K23: ישראל | L23: סחיר | M23: TASE | N23: נדל"ן מניב בחו"ל | O23: לא | P23: ILS | Q23: 52443 | R23: 1 | S23: 4288 | U23: 2248.756 | V23: 0.00086 | W23: =U23/SUMIF(B:B,B23,U:U) -> 0.014364257 | X23: 0.0020807882
A24: 520042177 | B24: 12937 | C24: בזק | D24: 520031931 | E24: ח.פ. | F24: בזק | G24: IL0002300114 | H24: ISIN | I24: מניות | J24: ישראל | K24: ישראל | L24: סחיר | M24: TASE | N24: תקשורת ומדיה | O24: לא | P24: ILS | Q24: 462548 | R24: 1 | S24: 428.6 | T24: 68.012 | U24: 2050.493 | V24: 0.00017 | W24: =U24/SUMIF(B:B,B24,U:U) -> 0.013097824 | X24: 0.0018973342
A25: 520042177 | B25: 12937 | C25: איי.סי.אל | D25: 520027830 | E25: ח.פ. | F25: איי.סי.אל | G25: IL0002810146 | H25: ISIN | I25: מניות | J25: ישראל | K25: ישראל | L25: סחיר | M25: TASE | N25: כימיה, גומי ופלסטיק | O25: לא | P25: ILS | Q25: 121600 | R25: 1 | S25: 1588 | U25: 1931.008 | V25: 9e-05 | W25: =U25/SUMIF(B:B,B25,U:U) -> 0.012334596 | X25: 0.0017867739
A26: 520042177 | B26: 12937 | C26: מנורה מב החזקות | D26: 520007469 | E26: ח.פ. | F26: מנורה 1 | G26: IL0005660183 | H26: ISIN | I26: מניות | J26: ישראל | K26: ישראל | L26: סחיר | M26: TASE | N26: ביטוח | O26: לא | P26: ILS | Q26: 16837 | R26: 1 | S26: 10880 | U26: 1831.866 | V26: 0.00027 | W26: =U26/SUMIF(B:B,B26,U:U) -> 0.011701312 | X26: 0.0016950372
A27: 520042177 | B27: 12937 | C27: בינלאומי | D27: 520029083 | E27: ח.פ. | F27: בינלאומי 5 | G27: IL0005930388 | H27: ISIN | I27: מניות | J27: ישראל | K27: ישראל | L27: סחיר | M27: TASE | N27: בנקים | O27: לא | P27: ILS | Q27: 11808 | R27: 1 | S27: 15410 | U27: 1819.613 | V27: 0.00012 | W27: =U27/SUMIF(B:B,B27,U:U) -> 0.011623044 | X27: 0.0016836994
A28: 520042177 | B28: 12937 | C28: תאת טכנולוגיות | D28: 520035791 | E28: ח.פ. | F28: תאת טכנולוגיה | G28: IL0010827264 | H28: ISIN | I28: מניות | J28: ישראל | K28: ישראל | L28: חסום | M28: TASE | N28: חשמל | O28: לא | P28: ILS | Q28: 5847 | R28: 1 | S28: =U28*1000/Q28*100 -> 5651.7067 | U28: =330455.288196721/1000 -> 330.45529 | V28: 0.00252 | W28: =U28/SUMIF(B:B,B28,U:U) -> 0.0021108314 | X28: 0.00030577237
A29: 520042177 | B29: 12937 | C29: ישראמקו יהש | D29: 550010003 | E29: ח.פ. | F29: ישראמקו יהש | G29: IL0002320179 | H29: ISIN | I29: מניות | J29: ישראל | K29: ישראל | L29: סחיר | M29: TASE | N29: חיפושי נפט וגז | O29: לא | P29: ILS | Q29: 957767 | R29: 1 | S29: 161.9 | U29: 1550.625 | V29: 0.00037 | W29: =U29/SUMIF(B:B,B29,U:U) -> 0.0099048437 | X29: 0.0014348031
A30: 520042177 | B30: 12937 | C30: מליסרון | D30: 520037789 | E30: ח.פ. | F30: מליסרון | G30: IL0003230146 | H30: ISIN | I30: מניות | J30: ישראל | K30: ישראל | L30: סחיר | M30: TASE | N30: נדל"ן מניב בישראל | O30: לא | P30: ILS | Q30: 5376 | R30: 1 | S30: 28210 | U30: 1516.57 | V30: 0.00011 | W30: =U30/SUMIF(B:B,B30,U:U) -> 0.0096873124 | X30: 0.0014032918
A31: 520042177 | B31: 12937 | C31: פוקס | D31: 512157603 | E31: ח.פ. | F31: פוקס | G31: IL0010870223 | H31: ISIN | I31: מניות | J31: ישראל | K31: ישראל | L31: סחיר | M31: TASE | N31: רשתות שיווק | O31: לא | P31: ILS | Q31: 5239 | R31: 1 | S31: 28150 | U31: 1474.779 | V31: 0.00038 | W31: =U31/SUMIF(B:B,B31,U:U) -> 0.0094203663 | X31: 0.0013646223
A32: 520042177 | B32: 12937 | C32: ביג | D32: 513623314 | E32: ח.פ. | F32: ביג | G32: IL0010972607 | H32: ISIN | I32: מניות | J32: ישראל | K32: ישראל | L32: סחיר | M32: TASE | N32: נדל"ן מניב בישראל | O32: לא | P32: ILS | Q32: 3339 | R32: 1 | S32: 41490 | U32: 1385.351 | V32: 0.00014 | W32: =U32/SUMIF(B:B,B32,U:U) -> 0.0088491319 | X32: 0.0012818741
A33: 520042177 | B33: 12937 | C33: סולאיר | D33: 516046307 | E33: ח.פ. | F33: סולאיר | G33: IL0011722878 | H33: ISIN | I33: מניות | J33: ישראל | K33: ישראל | L33: סחיר | M33: TASE | N33: אנרגיה מתחדשת | O33: לא | P33: ILS | Q33: 41231 | R33: 1 | S33: 3230 | U33: 1331.761 | V33: 0.00249 | W33: =U33/SUMIF(B:B,B33,U:U) -> 0.0085068179 | X33: 0.0012322869
A34: 520042177 | B34: 12937 | C34: ארגו פרופרטיז | D34: 70252750 | E34: מספר תאגיד או שותפות בחו"ל | F34: ארגו פרופרטיז | G34: NL0015000D84 | H34: ISIN | I34: מניות | J34: ישראל | K34: הולנד | L34: סחיר | M34: TASE | N34: נדל"ן מניב בחו"ל | O34: לא | P34: ILS | Q34: 14200 | R34: 1 | S34: 9080 | U34: 1289.36 | V34: 0.00069 | W34: =U34/SUMIF(B:B,B34,U:U) -> 0.0082359754 | X34: 0.001193053
A35: 520042177 | B35: 12937 | C35: דלק קידוחים יהש | D35: 550013098 | E35: ח.פ. | F35: ניו-מד אנרג'י יהש | G35: IL0004750209 | H35: ISIN | I35: מניות | J35: ישראל | K35: ישראל | L35: סחיר | M35: TASE | N35: חיפושי נפט וגז | O35: לא | P35: ILS | Q35: 121705 | R35: 1 | S35: 1025 | U35: 1247.476 | V35: 0.0001 | W35: =U35/SUMIF(B:B,B35,U:U) -> 0.0079684352 | X35: 0.0011542974
A36: 520042177 | B36: 12937 | C36: אלקטרה | D36: 520028911 | E36: ח.פ. | F36: אלקטרה | G36: IL0007390375 | H36: ISIN | I36: מניות | J36: ישראל | K36: ישראל | L36: סחיר | M36: TASE | N36: השקעה ואחזקות | O36: לא | P36: ILS | Q36: 784 | R36: 1 | S36: 148500 | T36: 7.842 | U36: 1172.082 | V36: 0.00019 | W36: =U36/SUMIF(B:B,B36,U:U) -> 0.007486845 | X36: 0.0010845349
A37: 520042177 | B37: 12937 | C37: רציו יהש | D37: 550012777 | E37: ח.פ. | F37: רציו יהש | G37: IL0003940157 | H37: ISIN | I37: מניות | J37: ישראל | K37: ישראל | L37: סחיר | M37: TASE | N37: חיפושי נפט וגז | O37: לא | P37: ILS | Q37: 358449 | R37: 1 | S37: 303 | U37: 1086.1 | V37: 0.00032 | W37: =U37/SUMIF(B:B,B37,U:U) -> 0.0069376224 | X37: 0.0010049752
A38: 520042177 | B38: 12937 | C38: 1 ריט | D38: 513821488 | E38: ח.פ. | F38: ריט 1 | G38: IL0010989205 | H38: ISIN | I38: מניות | J38: ישראל | K38: ישראל | L38: סחיר | M38: TASE | N38: נדל"ן מניב בישראל | O38: לא | P38: ILS | Q38: 70830 | R38: 1 | S38: 1513 | U38: 1071.658 | V38: 0.00036 | W38: =U38/SUMIF(B:B,B38,U:U) -> 0.006845372 | X38: 0.00099161193
A39: 520042177 | B39: 12937 | C39: אנרג'יקס | D39: 513901371 | E39: ח.פ. | F39: אנרג'יקס | G39: IL0011233553 | H39: ISIN | I39: מניות | J39: ישראל | K39: ישראל | L39: סחיר | M39: TASE | N39: אנרגיה מתחדשת | O39: לא | P39: ILS | Q39: 78576 | R39: 1 | S39: 1348 | U39: 1059.204 | V39: 0.00014 | W39: =U39/SUMIF(B:B,B39,U:U) -> 0.0067658203 | X39: 0.00098008817
A40: 520042177 | B40: 12937 | C40: קרסו מוטורס | D40: 514065283 | E40: ח.פ. | F40: קרסו | G40: IL0011238503 | H40: ISIN | I40: מניות | J40: ישראל | K40: ישראל | L40: סחיר | M40: TASE | N40: מסחר | O40: לא | P40: ILS | Q40: 51554 | R40: 1 | S40: 1991 | U40: 1026.44 | V40: 0.00057 | W40: =U40/SUMIF(B:B,B40,U:U) -> 0.0065565354 | X40: 0.00094977143
A41: 520042177 | B41: 12937 | C41: ישרוטל | D41: 520042482 | E41: ח.פ. | F41: ישרוטל | G41: IL0010809858 | H41: ISIN | I41: מניות | J41: ישראל | K41: ישראל | L41: סחיר | M41: TASE | N41: מלונאות ותיירות | O41: לא | P41: ILS | Q41: 13366 | R41: 1 | S41: 7454 | U41: 996.302 | V41: 0.00022 | W41: =U41/SUMIF(B:B,B41,U:U) -> 0.0063640246 | X41: 0.00092188455
A42: 520042177 | B42: 12937 | C42: ריטיילורס | D42: 514211457 | E42: ח.פ. | F42: ריטיילורס | G42: IL0011754889 | H42: ISIN | I42: מניות | J42: ישראל | K42: ישראל | L42: סחיר | M42: TASE | N42: רשתות שיווק | O42: לא | P42: ILS | Q42: 15041 | R42: 1 | S42: 6601 | U42: 992.856 | V42: 0.00031 | W42: =U42/SUMIF(B:B,B42,U:U) -> 0.0063420127 | X42: 0.00091869594
A43: 520042177 | B43: 12937 | C43: אורמת טכנו | D43: 880326081 | E43: ח.פ. | F43: אורמת טכנו | G43: US6866881021 | H43: ISIN | I43: מניות | J43: ישראל | K43: ישראל | L43: סחיר | M43: TASE | N43: אנרגיה מתחדשת | O43: לא | P43: ILS | Q43: 3474 | R43: 1 | S43: 28560 | U43: 992.174 | V43: 6e-05 | W43: =U43/SUMIF(B:B,B43,U:U) -> 0.0063376564 | X43: 0.00091806488
A44: 520042177 | B44: 12937 | C44: חילן | D44: 520039942 | E44: ח.פ. | F44: חילן | G44: IL0010846983 | H44: ISIN | I44: מניות | J44: ישראל | K44: ישראל | L44: סחיר | M44: TASE | N44: שירותי מידע | O44: לא | P44: ILS | Q44: 4883 | R44: 1 | S44: 19560 | U44: 955.115 | V44: 0.00021 | W44: =U44/SUMIF(B:B,B44,U:U) -> 0.0061009366 | X44: 0.00088377396
A45: 520042177 | B45: 12937 | C45: בית בכפר | D45: 511605719 | E45: ח.פ. | F45: בית בכפר | G45: IL0011836561 | H45: ISIN | I45: מניות | J45: ישראל | K45: ישראל | L45: סחיר | M45: TASE | N45: נדל"ן מניב בישראל | O45: לא | P45: ILS | Q45: 84105 | R45: 1 | S45: 1130 | U45: 950.387 | V45: 0.0012 | W45: =U45/SUMIF(B:B,B45,U:U) -> 0.0060707358 | X45: 0.00087939911
A46: 520042177 | B46: 12937 | C46: פתאל החזקות | D46: 512607888 | E46: ח.פ. | F46: פתאל החזקות | G46: IL0011434292 | H46: ISIN | I46: מניות | J46: ישראל | K46: ישראל | L46: סחיר | M46: TASE | N46: מלונאות ותיירות | O46: לא | P46: ILS | Q46: 2217 | R46: 1 | S46: 42630 | U46: 945.107 | V46: 0.00013 | W46: =U46/SUMIF(B:B,B46,U:U) -> 0.006037009 | X46: 0.00087451349
A47: 520042177 | B47: 12937 | C47: איסתא | D47: 520042763 | E47: ח.פ. | F47: איסתא | G47: IL0010810740 | H47: ISIN | I47: מניות | J47: ישראל | K47: ישראל | L47: סחיר | M47: TASE | N47: מלונאות ותיירות | O47: לא | P47: ILS | Q47: 11023 | R47: 1 | S47: 7743 | U47: 853.511 | V47: 0.00064 | W47: =U47/SUMIF(B:B,B47,U:U) -> 0.0054519262 | X47: 0.00078975913
A48: 520042177 | B48: 12937 | C48: וואן טכנולוגיות | D48: 520034695 | E48: ח.פ. | F48: וואן תוכנה | G48: IL0001610182 | H48: ISIN | I48: מניות | J48: ישראל | K48: ישראל | L48: סחיר | M48: TASE | N48: שירותי מידע | O48: לא | P48: ILS | Q48: 12698 | R48: 1 | S48: 5029 | U48: 638.582 | V48: 0.00018 | W48: =U48/SUMIF(B:B,B48,U:U) -> 0.0040790358 | X48: 0.00059088397
... A52: 520042177 | B52: 12937 | C52: אמות | D52: 520026683 | E52: ח.פ. | F52: אמות | G52: IL0010972789 | H52: ISIN | I52: מניות | J52: ישראל | K52: ישראל | L52: סחיר | M52: TASE | N52: נדל"ן מניב בישראל | O52: לא | P52: ILS | Q52: 32342 | R52: 1 | S52: 1609 | U52: 520.383 | V52: 7e-05 | W52: =U52/SUMIF(B:B,B52,U:U) -> 0.0033240224 | X52: 0.00048151368
A53: 520042177 | B53: 12937 | C53: אנרג'יאן | D53: 10758801 | E53: מספר תאגיד או שותפות בחו"ל | F53: אנרג'יאן | G53: GB00BG12Y042 | H53: ISIN | I53: מניות | J53: ישראל | K53: בריטניה | L53: סחיר | M53: TASE | N53: חיפושי נפט וגז | O53: לא | P53: ILS | Q53: 11083 | R53: 1 | S53: 4556 | T53: =12.375-39.8909999999996/1000/R53 -> 12.335109 | U53: =517.317-39.8909999999996/1000 -> 517.27711 | V53: 6e-05 | W53: =U53/SUMIF(B:B,B53,U:U) -> 0.0033041831 | X53: 0.00047863978
A54: 520042177 | B54: 12937 | C54: מטריקס | D54: 520039413 | E54: ח.פ. | F54: מטריקס | G54: IL0004450156 | H54: ISIN | I54: מניות | J54: ישראל | K54: ישראל | L54: סחיר | M54: TASE | N54: שירותי מידע | O54: לא | P54: ILS | Q54: 6548 | R54: 1 | S54: 7125 | T54: 10.38 | U54: 476.925 | V54: 0.0001 | W54: =U54/SUMIF(B:B,B54,U:U) -> 0.0030464281 | X54: 0.00044130172
A55: 520042177 | B55: 12937 | C55: מבנה | D55: 520024126 | E55: ח.פ. | F55: מבני תעשיה | G55: IL0002260193 | H55: ISIN | I55: מניות | J55: ישראל | K55: ישראל | L55: סחיר | M55: TASE | N55: נדל"ן מניב בישראל | O55: לא | P55: ILS | Q55: 49651 | R55: 1 | S55: 954 | U55: 473.671 | V55: 7e-05 | W55: =U55/SUMIF(B:B,B55,U:U) -> 0.0030256427 | X55: 0.00043829078
A56: 520042177 | B56: 12937 | C56: תדיראן גרופ | D56: 520036732 | E56: ח.פ. | F56: תדיראן הולדינגס | G56: IL0002580129 | H56: ISIN | I56: מניות | J56: ישראל | K56: ישראל | L56: סחיר | M56: TASE | N56: מסחר | O56: לא | P56: ILS | Q56: 2106 | R56: 1 | S56: 19990 | U56: 420.989 | V56: 0.00025 | W56: =U56/SUMIF(B:B,B56,U:U) -> 0.0026891287 | X56: 0.00038954379
A57: 520042177 | B57: 12937 | C57: מקס סטוק | D57: 513618967 | E57: ח.פ. | F57: מקס סטוק | G57: IL0011685588 | H57: ISIN | I57: מניות | J57: ישראל | K57: ישראל | L57: סחיר | M57: TASE | N57: רשתות שיווק | O57: לא | P57: ILS | Q57: 38191 | R57: 1 | S57: 1049 | U57: 400.624 | V57: 0.00027 | W57: =U57/SUMIF(B:B,B57,U:U) -> 0.0025590443 | X57: 0.00037069992
A58: 520042177 | B58: 12937 | C58: אל על | D58: 520017146 | E58: ח.פ. | F58: אלעל | G58: IL0010878242 | H58: ISIN | I58: מניות | J58: ישראל | K58: ישראל | L58: סחיר | M58: TASE | N58: שירותים | O58: לא | P58: ILS | Q58: 51695 | R58: 1 | S58: 644.6 | U58: 333.226 | V58: 0.00013 | W58: =U58/SUMIF(B:B,B58,U:U) -> 0.0021285298 | X58: 0.00030833613
A59: 520042177 | B59: 12937 | C59: סלקום | D59: 511930125 | E59: ח.פ. | F59: סלקום | G59: IL0011015349 | H59: ISIN | I59: מניות | J59: ישראל | K59: ישראל | L59: סחיר | M59: TASE | N59: תקשורת ומדיה | O59: לא | P59: ILS | Q59: 19499 | R59: 1 | S59: 1670 | U59: 325.633 | V59: 0.00012 | W59: =U59/SUMIF(B:B,B59,U:U) -> 0.0020800284 | X59: 0.00030131028
A60: 520042177 | B60: 12937 | C60: אינרום בנייה | D60: 515001659 | E60: ח.פ. | F60: אינרום | G60: IL0011323560 | H60: ISIN | I60: מניות | J60: ישראל | K60: ישראל | L60: סחיר | M60: TASE | N60: מתכת ומוצרי בניה | O60: לא | P60: ILS | Q60: 18409 | R60: 1 | S60: 1271 | U60: 233.978 | V60: 0.00013 | W60: =U60/SUMIF(B:B,B60,U:U) -> 0.0014945687 | X60: 0.00021650132
A61: 520042177 | B61: 12937 | C61: חג'ג' נדלן | D61: 520033309 | E61: ח.פ. | F61: חג'ג' נדל"ן | G61: IL0008230133 | H61: ISIN | I61: מניות | J61: ישראל | K61: ישראל | L61: סחיר | M61: TASE | N61: בנייה | O61: לא | P61: ILS | Q61: 14346.46 | R61: 1 | S61: 1628 | U61: 233.56 | V61: 0.00023 | W61: =U61/SUMIF(B:B,B61,U:U) -> 0.0014918986 | X61: 0.00021611455
A62: 520042177 | B62: 12937 | C62: שגריר רכב | D62: 515158665 | E62: ח.פ. | F62: שגריר | G62: IL0011383796 | H62: ISIN | I62: מניות | J62: ישראל | K62: ישראל | L62: סחיר | M62: TASE | N62: שירותים | O62: לא | P62: ILS | Q62: 22569 | R62: 1 | S62: 974.5 | U62: 219.935 | V62: 0.00217 | W62: =U62/SUMIF(B:B,B62,U:U) -> 0.0014048669 | X62: 0.00020350725
A63: 520042177 | B63: 12937 | C63: 11 גרופ | D63: 1992 | E63: מספר מנפיק | F63: גרופ 11 | G63: 1181106 | H63: פנימי | I63: TASE UP | J63: ישראל | K63: ארה"ב | M63: TASE-UP | N63: השקעות בהיי-טק | O63: לא | P63: ILS | Q63: 575 | R63: 1 | S63: 400000 | U63: 2300 | V63: 0.0119 | W63: =U63/SUMIF(B:B,B63,U:U) -> 0.014691586 | X63: 0.0021282046
A64: 520042177 | B64: 12937 | C64: גרופ(VEEV) וויו | D64: 1837 | E64: מספר מנפיק | F64: וויו גרופ TASE UP | G64: 1171107 | H64: פנימי | I64: חברה בפירוק | J64: ישראל | K64: ארה"ב | L64: אחר | M64: TASE-UP | N64: רובוטיקה ותלת מימד | O64: לא | P64: ILS | Q64: 2423263 | R64: 1 | S64: 0 | U64: 0 | V64: 0.01635 | W64: =U64/SUMIF(B:B,B64,U:U) -> 0 | X64: 0
A65: 520042177 | B65: 12937 | C65: תאת טכנולוגיות | D65: 520035791 | E65: ח.פ. | F65: תאת טכנולוגיה | G65: IL0010827264 | H65: ISIN | I65: מניות | J65: ישראל | K65: ישראל | L65: חסום | M65: TASE | N65: חשמל | O65: לא | P65: ILS | Q65: 20403 | R65: 1 | S65: =U65*1000/Q65*100 -> 6800 | U65: =1387404/1000 -> 1387.404 | W65: =U65/SUMIF(B:B,B65,U:U) -> 0.0088622457 | X65: 0.0012837737
A66: 520042177 | B66: 12937 | C66: GOOGLE | D66: 960 | E66: מספר מנפיק | F66: GOOG GOOGLE C Class | G66: US02079K1079 | H66: ISIN | I66: מניות | J66: חו"ל | K66: ארה"ב | L66: סחיר | M66: NYSE | N66: Communications Equipment | O66: לא | P66: USD | Q66: 9583 | R66: 3.71 | S66: 16719 | U66: 5944.094 | V66: 0 | W66: =U66/SUMIF(B:B,B66,U:U) -> 0.037968769 | X66: 0.0055001078
A67: 520042177 | B67: 12937 | C67: TSMC-TAIWAN SEMICONDUCTOR | D67: 5088 | E67: מספר מנפיק | F67: TSM - TAIWAN SEMICONDUCTOR | G67: us8740391003 | H67: ISIN | I67: מניות | J67: חו"ל | K67: Emerging Markets - Asia | L67: סחיר | M67: NYSE | N67: Semiconductors & Semiconductor Equipment | O67: לא | P67: USD | Q67: 8000 | R67: 3.71 | S67: 17367 | T67: =3.136+3345.5499998/1000/R67 -> 4.0377655 | U67: =5166.159+3345.5499998/1000 -> 5169.5045 | V67: 0 | W67: =U67/SUMIF(B:B,B67,U:U) -> 0.033020965 | X67: 0.0047833753
A68: 520042177 | B68: 12937 | C68: MICROSOFT | D68: 5083 | E68: מספר מנפיק | F68: MSFT - MICROSOFT | G68: us5949181045 | H68: ISIN | I68: מניות | J68: חו"ל | K68: ארה"ב | L68: סחיר | M68: NYSE | N68: Software | O68: לא | P68: USD | Q68: 2500 | R68: 3.71 | S68: 43030 | U68: 3991.033 | V68: 0 | W68: =U68/SUMIF(B:B,B68,U:U) -> 0.025493306 | X68: 0.0036929281
A69: 520042177 | B69: 12937 | C69: Bank of America | D69: 2180 | E69: מספר מנפיק | F69: BANK OF AMERICA - BAC | G69: US0605051046 | H69: ISIN | I69: מניות | J69: חו"ל | K69: ארה"ב | L69: סחיר | M69: NYSE | N69: Banks | O69: לא | P69: USD | Q69: 25000 | R69: 3.71 | S69: 3968 | U69: 3680.32 | V69: 0 | W69: =U69/SUMIF(B:B,B69,U:U) -> 0.023508582 | X69: 0.0034054234
A70: 520042177 | B70: 12937 | C70: Chevron | D70: 5369 | E70: מספר מנפיק | F70: Chevron Corp | G70: US1667641005 | H70: ISIN | I70: מניות | J70: חו"ל | K70: ארה"ב | L70: סחיר | M70: NYSE | N70: Energy Equipment & Services | O70: לא | P70: USD | Q70: 6000 | R70: 3.71 | S70: 14727 | U70: 3278.23 | V70: 0 | W70: =U70/SUMIF(B:B,B70,U:U) -> 0.020940173 | X70: 0.003033367
A71: 520042177 | B71: 12937 | C71: META | D71: 5097 | E71: מספר מנפיק | F71: META | G71: US30303M1027 | H71: ISIN | I71: מניות | J71: חו"ל | K71: ארה"ב | L71: סחיר | M71: TASE | N71: Communications Equipment | O71: לא | P71: USD | Q71: 1011 | R71: 3.71 | S71: 57244 | U71: 2147.114 | V71: 0 | W71: =U71/SUMIF(B:B,B71,U:U) -> 0.013715004 | X71: 0.0019867382
A72: 520042177 | B72: 12937 | C72: APPLE | D72: 930 | E72: מספר מנפיק | F72: AAPL - Apple | G72: US0378331005 | H72: ISIN | I72: מניות | J72: חו"ל | K72: ארה"ב | L72: סחיר | M72: NYSE | N72: Technology Hardware, Storage & Peripherals | O72: לא | P72: USD | Q72: 2416 | R72: 3.71 | S72: 23300 | U72: 2088.463 | V72: 0 | W72: =U72/SUMIF(B:B,B72,U:U) -> 0.013340363 | X72: 0.001932468
A73: 520042177 | B73: 12937 | C73: JP MORGAN | D73: 4809 | E73: מספר מנפיק | F73: JPM - JP MORGAN | G73: US46625H1005 | H73: ISIN | I73: מניות | J73: חו"ל | K73: ארה"ב | L73: סחיר | M73: NYSE | N73: Banks | O73: לא | P73: USD | Q73: 2588 | R73: 3.71 | S73: 21086 | U73: 2024.568 | V73: 0 | W73: =U73/SUMIF(B:B,B73,U:U) -> 0.012932224 | X73: 0.0018733456
A74: 520042177 | B74: 12937 | C74: PARK PLAZA HOTEL | D74: 5123 | E74: מספר מנפיק | F74: PARK PLAZA HOTEL- PPHE | G74: GG00B1Z5FH87 | H74: ISIN | I74: מניות | J74: חו"ל | K74: בריטניה | L74: סחיר | M74: LSE | N74: Real Estate Management & Development | O74: לא | P74: GBP | Q74: 32521 | R74: 4.9748 | S74: 1230 | T74: =5.51-13.8200001999976/1000/R74 -> 5.507222 | U74: =2017.371-13.8200001999976/1000 -> 2017.3572 | V74: 0.00078 | W74: =U74/SUMIF(B:B,B74,U:U) -> 0.012886164 | X74: 0.0018666734
A75: 520042177 | B75: 12937 | C75: PALO | D75: 4723 | E75: מספר מנפיק | F75: PALO ALTO NETWORKS-PANW | G75: US6974351057 | H75: ISIN | I75: מניות | J75: חו"ל | K75: ארה"ב | L75: סחיר | M75: NYSE | N75: Software | O75: לא | P75: USD | Q75: 1370 | R75: 3.71 | S75: 34180 | U75: 1737.267 | V75: 0 | W75: =U75/SUMIF(B:B,B75,U:U) -> 0.011097047 | X75: 0.0016075042
A76: 520042177 | B76: 12937 | C76: JACOBS SOLUTIONS | D76: 5377 | E76: מספר מנפיק | F76: JACOB SOLUTIONS | G76: US46982L1089 | H76: ISIN | I76: מניות | J76: חו"ל | K76: ארה"ב | L76: סחיר | M76: NYSE | N76: Industrial Conglomerates | O76: לא | P76: USD | Q76: 2700 | R76: 3.71 | S76: 15553 | U76: 1557.944 | V76: 2e-05 | W76: =U76/SUMIF(B:B,B76,U:U) -> 0.0099515949 | X76: 0.0014415754
A77: 520042177 | B77: 12937 | C77: SHL TELEMEDICINE | D77: 5261 | E77: מספר מנפיק | F77: SHL TELEMEDICINE LTD | G77: IL0010855885 | H77: ISIN | I77: מניות | J77: חו"ל | K77: ישראל | L77: סחיר | M77: אחר | N77: Health Care Equipment & Supplies | O77: לא | P77: CHF | Q77: 102936 | R77: 4.3965 | S77: 273 | U77: 1235.484 | V77: 0.00628 | W77: =U77/SUMIF(B:B,B77,U:U) -> 0.0078918345 | X77: 0.0011432012
A78: 520042177 | B78: 12937 | C78: Odysight | D78: 515950400 | E78: ח.פ. | F78: Odysight | G78: US81063V2043 | H78: ISIN | I78: מניות | J78: חו"ל | K78: ישראל | L78: סחיר | M78: NYSE | N78: Aerospace & Defense | O78: לא | P78: USD | Q78: 78000 | R78: 3.71 | S78: =U78*1000/Q78/R78*100 -> 533.78775 | U78: =1089.194+455.481 -> 1544.675 | V78: -0.01468 | W78: =U78/SUMIF(B:B,B78,U:U) -> 0.0098668372 | X78: 0.0014292976
A79: 520042177 | B79: 12937 | C79: ITURAN LOCATION | D79: 5169 | E79: מספר מנפיק | F79: ITURAN LOCATION | G79: IL0010818685 | H79: ISIN | I79: מניות | J79: חו"ל | K79: ישראל | L79: סחיר | M79: NYSE | N79: Technology Hardware, Storage & Peripherals | O79: לא | P79: USD | Q79: 10812 | R79: 3.71 | S79: 2654 | T79: =3.173+4193.49/1000/R79 -> 4.3033208 | U79: =1076.357+4193.49/1000 -> 1080.5505 | V79: 0.00054 | W79: =U79/SUMIF(B:B,B79,U:U) -> 0.0069021741 | X79: 0.00099984021
A80: 520042177 | B80: 12937 | C80: CATERPILLAR | D80: 4923 | E80: מספר מנפיק | F80: CATERPILLAR | G80: US1491231015 | H80: ISIN | I80: מניות | J80: חו"ל | K80: ארה"ב | L80: סחיר | M80: NYSE | N80: Other | O80: לא | P80: USD | Q80: 688 | R80: 3.71 | S80: 39112 | U80: 998.326 | V80: 0 | W80: =U80/SUMIF(B:B,B80,U:U) -> 0.0063769532 | X80: 0.00092375737
A81: 520042177 | B81: 12938 | C81: לאומי | D81: 520018078 | E81: ח.פ. | F81: לאומי | G81: IL0006046119 | H81: ISIN | I81: מניות | J81: ישראל | K81: ישראל | L81: סחיר | M81: TASE | N81: בנקים | O81: לא | P81: ILS | Q81: 78240 | R81: 1 | S81: 3644 | U81: 2851.066 | V81: 5e-05 | W81: =U81/SUMIF(B:B,B81,U:U) -> 0.048239881 | X81: 0.012554255
A82: 520042177 | B82: 12938 | C82: טבע | D82: 520013954 | E82: ח.פ. | F82: טבע | G82: IL0006290147 | H82: ISIN | I82: מניות | J82: ישראל | K82: ישראל | L82: סחיר | M82: TASE | N82: פארמה | O82: לא | P82: ILS | Q82: 42821 | R82: 1 | S82: 6629 | U82: 2838.604 | V82: 3e-05 | W82: =U82/SUMIF(B:B,B82,U:U) -> 0.048029025 | X82: 0.01249938
A83: 520042177 | B83: 12938 | C83: עזריאלי קבוצה | D83: 510960719 | E83: ח.פ. | F83: עזריאלי קבוצה | G83: IL0011194789 | H83: ISIN | I83: מניות | J83: ישראל | K83: ישראל | L83: סחיר | M83: TASE | N83: נדל"ן מניב בישראל | O83: לא | P83: ILS | Q83: 9575 | R83: 1 | S83: 25940 | U83: 2483.755 | V83: 8e-05 | W83: =U83/SUMIF(B:B,B83,U:U) -> 0.042024999 | X83: 0.010936854
A84: 520042177 | B84: 12938 | C84: פועלים | D84: 520000118 | E84: ח.פ. | F84: פועלים | G84: IL0006625771 | H84: ISIN | I84: מניות | J84: ישראל | K84: ישראל | L84: סחיר | M84: TASE | N84: בנקים | O84: לא | P84: ILS | Q84: 58971 | R84: 1 | S84: 3729 | U84: 2199.029 | V84: 4e-05 | W84: =U84/SUMIF(B:B,B84,U:U) -> 0.037207451 | X84: 0.0096831045
A85: 520042177 | B85: 12938 | C85: דוראל אנרגיה | D85: 515364891 | E85: ח.פ. | F85: דוראל אנרגיה | G85: IL0011667685 | H85: ISIN | I85: מניות | J85: ישראל | K85: ישראל | L85: סחיר | M85: TASE | N85: אנרגיה מתחדשת | O85: לא | P85: ILS | Q85: 146942 | R85: 1 | S85: 1472 | U85: 2162.986 | V85: 0.00083 | W85: =U85/SUMIF(B:B,B85,U:U) -> 0.036597605 | X85: 0.0095243944
A86: 520042177 | B86: 12938 | C86: או.פי.סי אנרגיה | D86: 514401702 | E86: ח.פ. | F86: או.פי.סי אנרגיה | G86: IL0011415713 | H86: ISIN | I86: מניות | J86: ישראל | K86: ישראל | L86: סחיר | M86: TASE | N86: אנרגיה | O86: לא | P86: ILS | Q86: 68338 | R86: 1 | S86: 3016 | U86: 2061.074 | V86: 0.00027 | W86: =U86/SUMIF(B:B,B86,U:U) -> 0.03487326 | X86: 0.0090756397
A87: 520042177 | B87: 12938 | C87: נכסים ובנין | D87: 520025438 | E87: ח.פ. | F87: נכסים בנין | G87: IL0006990175 | H87: ISIN | I87: מניות | J87: ישראל | K87: ישראל | L87: סחיר | M87: TASE | N87: נדל"ן מניב בישראל | O87: לא | P87: ILS | Q87: 7690 | R87: 1 | S87: 25580 | U87: 1967.102 | V87: 0.00104 | W87: =U87/SUMIF(B:B,B87,U:U) -> 0.033283259 | X87: 0.0086618477
A88: 520042177 | B88: 12938 | C88: מזרחי טפחות | D88: 520000522 | E88: ח.פ. | F88: מזרחי | G88: IL0006954379 | H88: ISIN | I88: מניות | J88: ישראל | K88: ישראל | L88: סחיר | M88: TASE | N88: בנקים | O88: לא | P88: ILS | Q88: 13361 | R88: 1 | S88: 14550 | U88: 1944.026 | V88: 5e-05 | W88: =U88/SUMIF(B:B,B88,U:U) -> 0.032892814 | X88: 0.0085602359
A89: 520042177 | B89: 12938 | C89: אלקטרה נדל"ן | D89: 510607328 | E89: ח.פ. | F89: אלקטרה נדלן | G89: IL0010940448 | H89: ISIN | I89: מניות | J89: ישראל | K89: ישראל | L89: סחיר | M89: TASE | N89: נדל"ן מניב בחו"ל | O89: לא | P89: ILS | Q89: 42648 | R89: 1 | S89: 4288 | U89: 1828.746 | V89: 0.0007 | W89: =U89/SUMIF(B:B,B89,U:U) -> 0.030942283 | X89: 0.0080526172
A90: 520042177 | B90: 12938 | C90: דיסקונט | D90: 520007030 | E90: ח.פ. | F90: דיסקונט | G90: IL0006912120 | H90: ISIN | I90: מניות | J90: ישראל | K90: ישראל | L90: סחיר | M90: TASE | N90: בנקים | O90: לא | P90: ILS | Q90: 80000 | R90: 1 | S90: 2085 | U90: 1668 | V90: 6e-05 | W90: =U90/SUMIF(B:B,B90,U:U) -> 0.028222469 | X90: 0.0073447955
A91: 520042177 | B91: 12938 | C91: אלביט מערכות | D91: 520043027 | E91: ח.פ. | F91: אלביט מערכות | G91: IL0010811243 | H91: ISIN | I91: מניות | J91: ישראל | K91: ישראל | L91: סחיר | M91: TASE | N91: ביטחוניות | O91: לא | P91: ILS | Q91: 1904 | R91: 1 | S91: 74080 | U91: 1410.483 | V91: 4e-05 | W91: =U91/SUMIF(B:B,B91,U:U) -> 0.023865295 | X91: 0.0062108568
... A98: 520042177 | B98: 12938 | C98: נקסט ויז'ן | D98: 514259019 | E98: ח.פ. | F98: נקסט ויז'ן | G98: IL0011765935 | H98: ISIN | I98: מניות | J98: ישראל | K98: ישראל | L98: סחיר | M98: TASE | N98: אלקטרוניקה ואופטיקה | O98: לא | P98: ILS | Q98: 25820 | R98: 1 | S98: 3950 | U98: 1019.89 | V98: 0.00032 | W98: =U98/SUMIF(B:B,B98,U:U) -> 0.017256483 | X98: 0.0044909374
A99: 520042177 | B99: 12938 | C99: תאת טכנולוגיות | D99: 520035791 | E99: ח.פ. | F99: תאת טכנולוגיה | G99: IL0010827264 | H99: ISIN | I99: מניות | J99: ישראל | K99: ישראל | L99: חסום | M99: TASE | N99: חשמל | O99: לא | P99: ILS | Q99: 2972 | R99: 1 | S99: =U99*1000/Q99*100 -> 5651.5372 | U99: =167963.684371585/1000 -> 167.96368 | V99: 0.00128 | W99: =U99/SUMIF(B:B,B99,U:U) -> 0.0028419364 | X99: 0.00073960367
A100: 520042177 | B100: 12938 | C100: טאואר | D100: 520041997 | E100: ח.פ. | F100: טאואר | G100: IL0010823792 | H100: ISIN | I100: מניות | J100: ישראל | K100: ישראל | L100: סחיר | M100: TASE | N100: מוליכים למחצה | O100: לא | P100: ILS | Q100: 5500 | R100: 1 | S100: 16470 | U100: 905.85 | V100: 5e-05 | W100: =U100/SUMIF(B:B,B100,U:U) -> 0.015326933 | X100: 0.0039887788
A101: 520042177 | B101: 12938 | C101: בית שמש | D101: 520043480 | E101: ח.פ. | F101: בית שמש | G101: IL0010815616 | H101: ISIN | I101: מניות | J101: ישראל | K101: ישראל | L101: סחיר | M101: TASE | N101: מתכת ומוצרי בניה | O101: לא | P101: ILS | Q101: 3576 | R101: 1 | S101: 24950 | U101: 892.212 | V101: 0.0004 | W101: =U101/SUMIF(B:B,B101,U:U) -> 0.015096178 | X101: 0.0039287258
A102: 520042177 | B102: 12938 | C102: ישראמקו יהש | D102: 550010003 | E102: ח.פ. | F102: ישראמקו יהש | G102: IL0002320179 | H102: ISIN | I102: מניות | J102: ישראל | K102: ישראל | L102: סחיר | M102: TASE | N102: חיפושי נפט וגז | O102: לא | P102: ILS | Q102: 538925 | R102: 1 | S102: 161.9 | U102: 872.52 | V102: 0.00021 | W102: =U102/SUMIF(B:B,B102,U:U) -> 0.014762991 | X102: 0.003842015
A103: 520042177 | B103: 12938 | C103: בזק | D103: 520031931 | E103: ח.פ. | F103: בזק | G103: IL0002300114 | H103: ISIN | I103: מניות | J103: ישראל | K103: ישראל | L103: סחיר | M103: TASE | N103: תקשורת ומדיה | O103: לא | P103: ILS | Q103: 185805 | R103: 1 | S103: 428.6 | T103: 27.321 | U103: 823.681 | V103: 7e-05 | W103: =U103/SUMIF(B:B,B103,U:U) -> 0.013936638 | X103: 0.0036269595
A104: 520042177 | B104: 12938 | C104: בינלאומי | D104: 520029083 | E104: ח.פ. | F104: בינלאומי 5 | G104: IL0005930388 | H104: ISIN | I104: מניות | J104: ישראל | K104: ישראל | L104: סחיר | M104: TASE | N104: בנקים | O104: לא | P104: ILS | Q104: 4841 | R104: 1 | S104: 15410 | U104: 745.998 | V104: 5e-05 | W104: =U104/SUMIF(B:B,B104,U:U) -> 0.012622245 | X104: 0.0032848937
A105: 520042177 | B105: 12938 | C105: מנורה מב החזקות | D105: 520007469 | E105: ח.פ. | F105: מנורה 1 | G105: IL0005660183 | H105: ISIN | I105: מניות | J105: ישראל | K105: ישראל | L105: סחיר | M105: TASE | N105: ביטוח | O105: לא | P105: ILS | Q105: 6546 | R105: 1 | S105: 10880 | U105: 712.205 | V105: 0.0001 | W105: =U105/SUMIF(B:B,B105,U:U) -> 0.01205047 | X105: 0.0031360912
A106: 520042177 | B106: 12938 | C106: איי.סי.אל | D106: 520027830 | E106: ח.פ. | F106: איי.סי.אל | G106: IL0002810146 | H106: ISIN | I106: מניות | J106: ישראל | K106: ישראל | L106: סחיר | M106: TASE | N106: כימיה, גומי ופלסטיק | O106: לא | P106: ILS | Q106: 42927 | R106: 1 | S106: 1588 | U106: 681.681 | V106: 3e-05 | W106: =U106/SUMIF(B:B,B106,U:U) -> 0.011534005 | X106: 0.0030016832
A107: 520042177 | B107: 12938 | C107: פתאל החזקות | D107: 512607888 | E107: ח.פ. | F107: פתאל החזקות | G107: IL0011434292 | H107: ISIN | I107: מניות | J107: ישראל | K107: ישראל | L107: סחיר | M107: TASE | N107: מלונאות ותיירות | O107: לא | P107: ILS | Q107: 1500 | R107: 1 | S107: 42630 | U107: 639.45 | V107: 9e-05 | W107: =U107/SUMIF(B:B,B107,U:U) -> 0.010819459 | X107: 0.0028157251
A108: 520042177 | B108: 12938 | C108: ארגו פרופרטיז | D108: 70252750 | E108: מספר תאגיד או שותפות בחו"ל | F108: ארגו פרופרטיז | G108: NL0015000D84 | H108: ISIN | I108: מניות | J108: ישראל | K108: הולנד | L108: סחיר | M108: TASE | N108: נדל"ן מניב בחו"ל | O108: לא | P108: ILS | Q108: 6584 | R108: 1 | S108: 9080 | U108: 597.827 | V108: 0.00032 | W108: =U108/SUMIF(B:B,B108,U:U) -> 0.0101152 | X108: 0.0026324443
A109: 520042177 | B109: 12938 | C109: מליסרון | D109: 520037789 | E109: ח.פ. | F109: מליסרון | G109: IL0003230146 | H109: ISIN | I109: מניות | J109: ישראל | K109: ישראל | L109: סחיר | M109: TASE | N109: נדל"ן מניב בישראל | O109: לא | P109: ILS | Q109: 2106 | R109: 1 | S109: 28210 | U109: 594.103 | V109: 4e-05 | W109: =U109/SUMIF(B:B,B109,U:U) -> 0.01005219 | X109: 0.0026160462
A110: 520042177 | B110: 12938 | C110: פוקס | D110: 512157603 | E110: ח.פ. | F110: פוקס | G110: IL0010870223 | H110: ISIN | I110: מניות | J110: ישראל | K110: ישראל | L110: סחיר | M110: TASE | N110: רשתות שיווק | O110: לא | P110: ILS | Q110: 2079 | R110: 1 | S110: 28150 | U110: 585.239 | V110: 0.00015 | W110: =U110/SUMIF(B:B,B110,U:U) -> 0.009902212 | X110: 0.0025770149
A111: 520042177 | B111: 12938 | C111: סולאיר | D111: 516046307 | E111: ח.פ. | F111: סולאיר | G111: IL0011722878 | H111: ISIN | I111: מניות | J111: ישראל | K111: ישראל | L111: סחיר | M111: TASE | N111: אנרגיה מתחדשת | O111: לא | P111: ILS | Q111: 17320 | R111: 1 | S111: 3230 | U111: 559.436 | V111: 0.00105 | W111: =U111/SUMIF(B:B,B111,U:U) -> 0.0094656266 | X111: 0.0024633951
A112: 520042177 | B112: 12938 | C112: ביג | D112: 513623314 | E112: ח.פ. | F112: ביג | G112: IL0010972607 | H112: ISIN | I112: מניות | J112: ישראל | K112: ישראל | L112: סחיר | M112: TASE | N112: נדל"ן מניב בישראל | O112: לא | P112: ILS | Q112: 1291 | R112: 1 | S112: 41490 | U112: 535.636 | V112: 5e-05 | W112: =U112/SUMIF(B:B,B112,U:U) -> 0.0090629319 | X112: 0.0023585953
A113: 520042177 | B113: 12938 | C113: נופר אנרג'י | D113: 514599943 | E113: ח.פ. | F113: נופר אנרג'י | G113: IL0011708778 | H113: ISIN | I113: מניות | J113: ישראל | K113: ישראל | L113: סחיר | M113: TASE | N113: אנרגיה מתחדשת | O113: לא | P113: ILS | Q113: 5908 | R113: 1 | S113: 8722 | U113: 515.296 | V113: 0.00017 | W113: =U113/SUMIF(B:B,B113,U:U) -> 0.0087187802 | X113: 0.002269031
A114: 520042177 | B114: 12938 | C114: נאוויטס פטרו | D114: 550263107 | E114: ח.פ. | F114: נאוויטס פטר יהש | G114: IL0011419699 | H114: ISIN | I114: מניות | J114: ישראל | K114: ישראל | L114: סחיר | M114: TASE | N114: חיפושי נפט וגז | O114: לא | P114: ILS | Q114: 9267 | R114: 1 | S114: 5205 | U114: 482.347 | V114: 9e-05 | W114: =U114/SUMIF(B:B,B114,U:U) -> 0.0081612849 | X114: 0.0021239449
A115: 520042177 | B115: 12938 | C115: אלקטרה | D115: 520028911 | E115: ח.פ. | F115: אלקטרה | G115: IL0007390375 | H115: ISIN | I115: מניות | J115: ישראל | K115: ישראל | L115: סחיר | M115: TASE | N115: השקעה ואחזקות | O115: לא | P115: ILS | Q115: 300 | R115: 1 | S115: 148500 | T115: 3.17 | U115: 448.67 | V115: 7e-05 | W115: =U115/SUMIF(B:B,B115,U:U) -> 0.0075914719 | X115: 0.0019756531
A116: 520042177 | B116: 12938 | C116: 1 ריט | D116: 513821488 | E116: ח.פ. | F116: ריט 1 | G116: IL0010989205 | H116: ISIN | I116: מניות | J116: ישראל | K116: ישראל | L116: סחיר | M116: TASE | N116: נדל"ן מניב בישראל | O116: לא | P116: ILS | Q116: 28582 | R116: 1 | S116: 1513 | U116: 432.446 | V116: 0.00015 | W116: =U116/SUMIF(B:B,B116,U:U) -> 0.0073169627 | X116: 0.0019042131
A117: 520042177 | B117: 12938 | C117: רציו יהש | D117: 550012777 | E117: ח.פ. | F117: רציו יהש | G117: IL0003940157 | H117: ISIN | I117: מניות | J117: ישראל | K117: ישראל | L117: סחיר | M117: TASE | N117: חיפושי נפט וגז | O117: לא | P117: ILS | Q117: 142378 | R117: 1 | S117: 303 | U117: 431.405 | V117: 0.00013 | W117: =U117/SUMIF(B:B,B117,U:U) -> 0.0072993491 | X117: 0.0018996292
A118: 520042177 | B118: 12938 | C118: אנרג'יקס | D118: 513901371 | E118: ח.פ. | F118: אנרג'יקס | G118: IL0011233553 | H118: ISIN | I118: מניות | J118: ישראל | K118: ישראל | L118: סחיר | M118: TASE | N118: אנרגיה מתחדשת | O118: לא | P118: ILS | Q118: 31789 | R118: 1 | S118: 1348 | U118: 428.516 | V118: 6e-05 | W118: =U118/SUMIF(B:B,B118,U:U) -> 0.0072504673 | X118: 0.0018869079
...

Sheet קרנות סל
A1: מספר קופה/קרן/ח.פ. עבור חברת ביטוח | B1: מספר מסלול | C1: שם מנפיק | D1: מספר מנפיק | E1: סוג מספר מזהה מנפיק | F1: שם נייר ערך | G1: מספר נייר ערך | H1: סוג מספר נייר ערך | I1: מאפיין עיקרי | J1: ישראל/חו"ל | K1: מדינה לפי חשיפה כלכלית | L1: זירת מסחר | M1: סיווג הקרן | N1: בעל עניין/צד קשור | O1: מטבע פעילות | P1: ערך נקוב (יחידות) | Q1: שער חליפין | R1: שער נייר הערך | S1: סכום לקבל (במטבע הפעילות) | T1: שווי הוגן (באלפי ש"ח) | U1: שיעור מערך נקוב מונפק | V1: שיעור מנכסי אפיק ההשקעה | W1: שיעור מסך נכסי ההשקעה
A2: 520042177 | B2: 12937 | C2: VANGURUARD | D2: 4922 | E2: מספר מנפיק | F2: VOO US_VANGUARD S&P 500 | G2: US9229083632 | H2: ISIN | I2: עוקב אחר מדדי מניות בחו"ל | J2: חו"ל | K2: ארה"ב | L2: NYSE | M2: S&P 500 - מניות בחו"ל - מניות גיאוגרפי - חשופת מט"ח-ארה"ב | N2: לא | O2: USD | P2: 22000 | Q2: 3.71 | R2: 52767 | S2: 36.049 | T2: 43202.168 | U2: 0 | V2: 0.82728 | W2: 0.04
A3: 520042177 | B3: 12937 | C3: Invesco Capital Management LLC | D3: 1290 | E3: מספר מנפיק | F3: QQQ - Nasdaq 100 | G3: US46090E1038 | H3: ISIN | I3: עוקב אחר מדדי מניות בחו"ל | J3: חו"ל | K3: ארה"ב | L3: NASDAQ | M3: NASDAQ 100 - מניות בחו"ל - מניות גיאוגרפי - חשופת מט"ח-ארה"ב | N3: לא | O3: USD | P3: 5000 | Q3: 3.71 | R3: 48807 | S3: =2.546+162.45/1000/Q3 -> 2.5897871 | T3: =9063.146+162.45/1000 -> 9063.3085 | U3: 0 | V3: 0.17346 | W3: 0.00839
A4: 520042177 | B4: 12938 | C4: VANGURUARD | D4: 4922 | E4: מספר מנפיק | F4: VOO US_VANGUARD S&P 500 | G4: US9229083632 | H4: ISIN | I4: עוקב אחר מדדי מניות בחו"ל | J4: חו"ל | K4: ארה"ב | L4: NYSE | M4: S&P 500 - מניות בחו"ל - מניות גיאוגרפי - חשופת מט"ח-ארה"ב | N4: לא | O4: USD | P4: 7450 | Q4: 3.71 | R4: 52767 | S4: 12.208 | T4: 14629.825 | U4: 0 | V4: 0.30704 | W4: 0.06444
A5: 520042177 | B5: 12938 | C5: STATE STREET-SPDRS | D5: 4640 | E5: מספר מנפיק | F5: SPY - S&P 500 | G5: US78462F1030 | H5: ISIN | I5: עוקב אחר מדדי מניות בחו"ל | J5: חו"ל | K5: ארה"ב | L5: NYSE | M5: S&P 500 - מניות בחו"ל - מניות גיאוגרפי - חשופת מט"ח-ארה"ב | N5: לא | O5: USD | P5: 6560 | Q5: 3.71 | R5: 57376 | S5: =8.616+549.64/1000/Q5 -> 8.7641509 | T5: =13995.906+549.64/1000 -> 13996.456 | U5: 0 | V5: 0.29367 | W5: 0.06164
A6: 520042177 | B6: 12938 | C6: Invesco Capital Management LLC | D6: 1290 | E6: מספר מנפיק | F6: QQQ - Nasdaq 100 | G6: US46090E1038 | H6: ISIN | I6: עוקב אחר מדדי מניות בחו"ל | J6: חו"ל | K6: ארה"ב | L6: NASDAQ | M6: NASDAQ 100 - מניות בחו"ל - מניות גיאוגרפי - חשופת מט"ח-ארה"ב | N6: לא | O6: USD | P6: 7517 | Q6: 3.71 | R6: 48807 | S6: =3.828+244.22/1000/Q6 -> 3.8938275 | T6: =13625.533+244.22/1000 -> 13625.777 | U6: 0 | V6: 0.28581 | W6: 0.05999
A7: 520042177 | B7: 12938 | C7: SOURCE | D7: 4585 | E7: מספר מנפיק | F7: SPXS LN - S&P 500 | G7: IE00B3YCGJ38 | H7: ISIN | I7: עוקב אחר מדדי מניות בחו"ל | J7: חו"ל | K7: ארה"ב | L7: LSE | M7: S&P 500 - מניות בחו"ל - מניות גיאוגרפי - חשופת מט"ח-ארה"ב | N7: לא | O7: USD | P7: 1300 | Q7: 3.71 | R7: 112716 | T7: 5436.293 | U7: 0 | V7: 0.114 | W7: 0.02393
A8: 520042177 | B8: 13498 | C8: מגדל קרנות נאמנ | D8: 511303661 | E8: ח.פ. | F8: MTF סל (4A) ת"א 125 | G8: IL0011502833 | H8: ISIN | I8: עוקב אחר מדדי מניות בישראל | J8: ישראל | K8: ישראל | L8: TASE | M8: 125 מניות בארץ - מניות כללי-ת"א | N8: לא | O8: ILS | P8: 463944 | Q8: 1 | R8: 3265 | T8: 15147.772 | U8: 0.00663 | V8: 0.04536 | W8: 0.01901
A9: 520042177 | B9: 13498 | C9: קסם קרנות נאמנו | D9: 510938608 | E9: ח.פ. | F9: קסם S&P 500 (4A) ETF מנוטרלת | G9: IL0011466047 | H9: ISIN | I9: עוקב אחר מדדי מניות בחו"ל | J9: ישראל | K9: ישראל | L9: TASE | M9: S&P 500 - מניות בחו"ל - מניות גיאוגרפי - מנוטרלת מט"ח-ארה"ב | N9: לא | O9: ILS | P9: 262576.23 | Q9: 1 | R9: 5505 | T9: 14454.821 | U9: 0.00346 | V9: 0.04329 | W9: 0.01814
A10: 520042177 | B10: 13498 | C10: מגדל קרנות נאמנ | D10: 511303661 | E10: ח.פ. | F10: MTF סל (SP500 (4A מנוטרלת מט"ח | G10: IL0011505729 | H10: ISIN | I10: עוקב אחר מדדי מניות בחו"ל | J10: ישראל | K10: ישראל | L10: TASE | M10: S&P 500 - מניות בחו"ל - מניות גיאוגרפי - מנוטרלת מט"ח-ארה"ב | N10: לא | O10: ILS | P10: 184869 | Q10: 1 | R10: 7341 | T10: 13571.233 | U10: 0.00596 | V10: 0.04064 | W10: 0.01703
A11: 520042177 | B11: 13498 | C11: איביאי ק.נאמנות | D11: 513765339 | E11: ח.פ. | F11: פסגות ETF ת"א 125 | G11: IL0011488082 | H11: ISIN | I11: עוקב אחר מדדי מניות בישראל | J11: ישראל | K11: ישראל | L11: TASE | M11: 125 מניות בארץ - מניות כללי-ת"א | N11: לא | O11: ILS | P11: 612219 | Q11: 1 | R11: 2073 | T11: 12691.3 | U11: 0.00153 | V11: 0.03801 | W11: 0.01593
A12: 520042177 | B12: 13498 | C12: מגדל קרנות נאמנ | D12: 511303661 | E12: ח.פ. | F12: מגדל S&P (4D) MTF | G12: IL0011503336 | H12: ISIN | I12: עוקב אחר מדדי מניות בחו"ל | J12: ישראל | K12: ישראל | L12: TASE | M12: S&P 500 - מניות בחו"ל - מניות גיאוגרפי - חשופת מט"ח-ארה"ב | N12: לא | O12: ILS | P12: 135816 | Q12: 1 | R12: 9106 | T12: 12367.405 | U12: 0.00156 | V12: 0.03704 | W12: 0.01552
A13: 520042177 | B13: 13498 | C13: מיטב קרנות נאמנ | D13: 513534974 | E13: ח.פ. | F13: תכלית סל (4A) ת"א 125 | G13: IL0011437188 | H13: ISIN | I13: עוקב אחר מדדי מניות בישראל | J13: ישראל | K13: ישראל | L13: TASE | M13: 125 מניות בארץ - מניות כללי-ת"א | N13: לא | O13: ILS | P13: 571100 | Q13: 1 | R13: 2081 | T13: 11884.591 | U13: 0.0013 | V13: 0.03559 | W13: 0.01492
A14: 520042177 | B14: 13498 | C14: הראל קרנות מדד | D14: 511776783 | E14: ח.פ. | F14: הראל S&P500 | G14: IL0011490203 | H14: ISIN | I14: עוקב אחר מדדי מניות בחו"ל | J14: ישראל | K14: ישראל | L14: TASE | M14: S&P 500 - מניות בחו"ל - מניות גיאוגרפי - חשופת מט"ח-ארה"ב | N14: לא | O14: ILS | P14: 471200 | Q14: 1 | R14: 2470 | T14: 11638.64 | U14: 0.00124 | V14: 0.03485 | W14: 0.01461
A15: 520042177 | B15: 13498 | C15: הראל קרנות מדד | D15: 511776783 | E15: ח.פ. | F15: הראל S&P500 מנוטרל | G15: IL0011491375 | H15: ISIN | I15: עוקב אחר מדדי מניות בחו"ל | J15: ישראל | K15: ישראל | L15: TASE | M15: S&P 500 - מניות בחו"ל - מניות גיאוגרפי - מנוטרלת מט"ח-ארה"ב | N15: לא | O15: ILS | P15: 160000 | Q15: 1 | R15: 5590 | T15: 8944 | U15: 0.00132 | V15: 0.02678 | W15: 0.01123
A16: 520042177 | B16: 13498 | C16: קסם קרנות נאמנו | D16: 510938608 | E16: ח.פ. | F16: קסם ETF ת"א 125 | G16: IL0011463564 | H16: ISIN | I16: עוקב אחר מדדי מניות בישראל | J16: ישראל | K16: ישראל | L16: TASE | M16: 125 מניות בארץ - מניות כללי-ת"א | N16: לא | O16: ILS | P16: 40626 | Q16: 1 | R16: 20710 | T16: 8413.645 | U16: 0.00115 | V16: 0.0252 | W16: 0.01056
A17: 520042177 | B17: 13498 | C17: מיטב קרנות נאמנ | D17: 513534974 | E17: ח.פ. | F17: תכלית סל S&P 500 מנוטרלת מט"ח | G17: IL0011438178 | H17: ISIN | I17: עוקב אחר מדדי מניות בחו"ל | J17: ישראל | K17: ישראל | L17: TASE | M17: S&P 500 - מניות בחו"ל - מניות גיאוגרפי - מנוטרלת מט"ח-ארה"ב | N17: לא | O17: ILS | P17: 145000 | Q17: 1 | R17: 5069 | T17: 7350.05 | U17: 0.00113 | V17: 0.02201 | W17: 0.00922
A18: 520042177 | B18: 13498 | C18: מיטב קרנות נאמנ | D18: 513534974 | E18: ח.פ. | F18: תכלית סל 600 4STOXX | G18: IL0011447245 | H18: ISIN | I18: עוקב אחר מדדי מניות בחו"ל | J18: ישראל | K18: ישראל | L18: TASE | M18: STOXX EUROPE 600 -מניות בחו"ל - מניות גיאוגרפי - חשופת מט"ח-אירופה כללי | N18: לא | O18: ILS | P18: 192903 | Q18: 1 | R18: 2795 | T18: 5391.639 | U18: 0.00351 | V18: 0.01615 | W18: 0.00677
... A65: 520042177 | B65: 13498 | C65: הראל קרנות מדד | D65: 511776783 | E65: ח.פ. | F65: הראל סל (00) תל בונד 20 | G65: IL0011504409 | H65: ISIN | I65: עוקב אחר מדדים אחרים בישראל | J65: ישראל | K65: ישראל | L65: TASE | M65: 20 אג"ח בארץ - חברות והמרה-תל בונד צמוד מדד-תל בונד | N65: לא | O65: ILS | P65: 70000 | Q65: 1 | R65: 373.22 | T65: 261.254 | U65: 0.00029 | V65: 0.00078 | W65: 0.00033
A66: 520042177 | B66: 13498 | C66: STATE STREET-SPDRS | D66: 4640 | E66: מספר מנפיק | F66: SPY - S&P 500 | G66: US78462F1030 | H66: ISIN | I66: עוקב אחר מדדי מניות בחו"ל | J66: חו"ל | K66: ארה"ב | L66: NYSE | M66: S&P 500 - מניות בחו"ל - מניות גיאוגרפי - חשופת מט"ח-ארה"ב | N66: לא | O66: USD | P66: 10868 | Q66: 3.71 | R66: 57376 | S66: =14.274+910.58/1000/Q66 -> 14.519439 | T66: =23187.12+910.58/1000 -> 23188.031 | U66: 0 | V66: 0.06948 | W66: 0.02912
A67: 520042177 | B67: 13498 | C67: אינבסקו אינבס | D67: 2355 | E67: מספר מנפיק | F67: INVESCO S&P 500 UCITS ETF | G67: IE00B3YCGJ38 | H67: ISIN | I67: עוקב אחר מדדי מניות בחו"ל | J67: חו"ל | K67: אירופה | L67: TASE | M67: S&P 500 - מניות בחו"ל - מניות גיאוגרפי - חשופת מט"ח-ארה"ב | N67: לא | O67: ILS | P67: 3693 | Q67: 1 | R67: 418000 | T67: 15436.74 | U67: 0.00927 | V67: 0.04623 | W67: 0.01937
A68: 520042177 | B68: 13498 | C68: VANGURUARD | D68: 4922 | E68: מספר מנפיק | F68: VOO US_VANGUARD S&P 500 | G68: US9229083632 | H68: ISIN | I68: עוקב אחר מדדי מניות בחו"ל | J68: חו"ל | K68: ארה"ב | L68: NYSE | M68: S&P 500 - מניות בחו"ל - מניות גיאוגרפי - חשופת מט"ח-ארה"ב | N68: לא | O68: USD | P68: 7000 | Q68: 3.71 | R68: 52767 | S68: 11.47 | T68: 13746.144 | U68: 0 | V68: 0.0412 | W68: 0.01727
A69: 520042177 | B69: 13498 | C69: Invesco Capital Management LLC | D69: 1290 | E69: מספר מנפיק | F69: QQQ - Nasdaq 100 | G69: US46090E1038 | H69: ISIN | I69: עוקב אחר מדדי מניות בחו"ל | J69: חו"ל | K69: ארה"ב | L69: NASDAQ | M69: NASDAQ 100 - מניות בחו"ל - מניות גיאוגרפי - חשופת מט"ח-ארה"ב | N69: לא | O69: USD | P69: 5970 | Q69: 3.71 | R69: 48807 | S69: =3.04+193.96/1000/Q69 -> 3.0922803 | T69: =10821.396+193.96/1000 -> 10821.59 | U69: 0 | V69: 0.03242 | W69: 0.01359
A70: 520042177 | B70: 13498 | C70: ISHARES | D70: 4601 | E70: מספר מנפיק | F70: DAXEX GY - DAX | G70: DE0005933931 | H70: ISIN | I70: עוקב אחר מדדי מניות בחו"ל | J70: חו"ל | K70: ארה"ב | L70: FWB | M70: Equity Funds | N70: לא | O70: EUR | P70: 8200 | Q70: 4.1524 | R70: 16098 | T70: 5481.317 | U70: 0 | V70: 0.01642 | W70: 0.00688
A71: 520042177 | B71: 13498 | C71: ISHARES | D71: 4601 | E71: מספר מנפיק | F71: IWM - RUSSELL 2000 | G71: US4642876555 | H71: ISIN | I71: עוקב אחר מדדי מניות בחו"ל | J71: חו"ל | K71: ארה"ב | L71: NYSE | M71: RUSSELL 2000 - מניות בחו"ל - מניות גיאוגרפי - חשופת מט"ח-ארה"ב | N71: לא | O71: USD | P71: 6370 | Q71: 3.71 | R71: 22089 | T71: 5220.227 | U71: 0 | V71: 0.01563 | W71: 0.00655
A72: 520042177 | B72: 13498 | C72: Guggenheim Funds | D72: 4205 | E72: מספר מנפיק | F72: RSP-S&P 500 EQUAL WEI | G72: US46137V3574 | H72: ISIN | I72: עוקב אחר מדדי מניות בחו"ל | J72: חו"ל | K72: ארה"ב | L72: NYSE | M72: S&P 500 - מניות בחו"ל - מניות גיאוגרפי - חשופת מט"ח-ארה"ב | N72: לא | O72: USD | P72: 7200 | Q72: 3.71 | R72: 17916 | T72: 4785.722 | U72: 0 | V72: 0.01433 | W72: 0.00601
A73: 520042177 | B73: 13498 | C73: ISHARES | D73: 4601 | E73: מספר מנפיק | F73: ISHARES MSCI EMR | G73: US46434G7640 | H73: ISIN | I73: עוקב אחר מדדי מניות בחו"ל | J73: חו"ל | K73: ארה"ב | L73: אחר | M73: MSCI EMERGING MARKETS - מניות בחו"ל - מניות גיאוגרפי - חשופת מט"ח-שווקים מתעוררים כללי | N73: לא | O73: USD | P73: 15030 | Q73: 3.71 | R73: 6111 | T73: 3407.573 | U73: 0 | V73: 0.0102 | W73: 0.00428
A74: 520042177 | B74: 13498 | C74: Invesco Management S.A | D74: 5224 | E74: מספר מנפיק | F74: Invesco NASDAQ 100 ETF | G74: US46138G6492 | H74: ISIN | I74: עוקב אחר מדדי מניות בחו"ל | J74: חו"ל | K74: ארה"ב | L74: אחר | M74: NASDAQ 100 - מניות בחו"ל - מניות גיאוגרפי - חשופת מט"ח-ארה"ב | N74: לא | O74: USD | P74: 3760 | Q74: 3.71 | R74: 20085 | T74: 2801.777 | U74: 0 | V74: 0.00839 | W74: 0.00352
A75: 520042177 | B75: 13498 | C75: קסם קרנות נאמנו | D75: 510938608 | E75: ח.פ. | F75: קסם DAX 30 ETF | G75: IL0011465130 | H75: ISIN | I75: עוקב אחר מדדי מניות בחו"ל | J75: חו"ל | K75: ישראל | L75: TASE | M75: DAX 30 - מניות בחו"ל - מניות גיאוגרפי - חשופת מט"ח-אירופה גרמניה | N75: לא | O75: ILS | P75: 40031.04 | Q75: 1 | R75: 6991 | T75: 2798.57 | U75: 0.00284 | V75: 0.00838 | W75: 0.00351
A76: 520042177 | B76: 13498 | C76: הראל קרנות מדד | D76: 511776783 | E76: ח.פ. | F76: הראל סל STOXX Europe 60 | G76: IL0011498719 | H76: ISIN | I76: עוקב אחר מדדי מניות בחו"ל | J76: חו"ל | K76: ישראל | L76: TASE | M76: מניות בחו"ל - מניות גיאוגרפי - חשופת מט"ח-אירופה - מדד אחר | N76: לא | O76: ILS | P76: 66000 | Q76: 1 | R76: 2830 | T76: 1867.8 | U76: 0.00246 | V76: 0.00559 | W76: 0.00234
A77: 520042177 | B77: 13498 | C77: מיטב קרנות נאמנ | D77: 513534974 | E77: ח.פ. | F77: תכלית סל (4A)י NIKKEI 225 מנוטרלת מט"ח | G77: IL0011444689 | H77: ISIN | I77: עוקב אחר מדדי מניות בחו"ל | J77: חו"ל | K77: ישראל | L77: TASE | M77: NIKKEI 225 - מניות בחו"ל - מניות גיאוגרפי - מנוטרלת מט"ח-אסיה יפן | N77: לא | O77: ILS | P77: 4617 | Q77: 1 | R77: 37710 | T77: 1741.071 | U77: 0.00118 | V77: 0.00521 | W77: 0.00219
A78: 520042177 | B78: 13498 | C78: BlackRock | D78: 2235 | E78: מספר מנפיק | F78: SOXX - SEMICONDUCTOR | G78: US4642875235 | H78: ISIN | I78: עוקב אחר מדדי מניות בחו"ל | J78: חו"ל | K78: ארה"ב | L78: NYSE | M78: Equity Funds | N78: לא | O78: USD | P78: 1830 | Q78: 3.71 | R78: 23059 | T78: 1565.545 | U78: 0 | V78: 0.00469 | W78: 0.00196
A79: 520042177 | B79: 13498 | C79: STATE STREET-SPDRS | D79: 4640 | E79: מספר מנפיק | F79: HEALTH CARE XLV | G79: us81369y2090 | H79: ISIN | I79: עוקב אחר מדדי מניות בחו"ל | J79: חו"ל | K79: ארה"ב | L79: NYSE | M79: Equity Funds | N79: לא | O79: USD | P79: 2070 | Q79: 3.71 | R79: 15402 | T79: 1182.827 | U79: 0 | V79: 0.00354 | W79: 0.00148
A80: 520042177 | B80: 13498 | C80: BlackRock | D80: 2235 | E80: מספר מנפיק | F80: AAXJ-ISHARES ASIA | G80: US4642881829 | H80: ISIN | I80: עוקב אחר מדדי מניות בחו"ל | J80: חו"ל | K80: ארה"ב | L80: NASDAQ | M80: Equity Funds | N80: לא | O80: USD | P80: 4020 | Q80: 3.71 | R80: 7845 | T80: 1170.019 | U80: 0 | V80: 0.0035 | W80: 0.00147
A81: 520042177 | B81: 13498 | C81: VANGURUARD | D81: 4922 | E81: מספר מנפיק | F81: VCSH-VANGUARD S/T corp bond ETF | G81: US92206C4096 | H81: ISIN | I81: עוקב אחר מדדים אחרים בחו"ל | J81: חו"ל | K81: ארה"ב | L81: NYSE | M81: Bond/Fixed Income Funds | N81: לא | O81: USD | P81: 3400 | Q81: 3.71 | R81: 7942 | T81: 1001.804 | U81: 0 | V81: 0.003 | W81: 0.00126
... A121: 520042177 | B121: 13500 | C121: הראל קרנות מדד | D121: 511776783 | E121: ח.פ. | F121: הראל NASDAQ100 | G121: IL0011490385 | H121: ISIN | I121: עוקב אחר מדדי מניות בחו"ל | J121: ישראל | K121: ישראל | L121: TASE | M121: NASDAQ 100 - מניות בחו"ל - מניות גיאוגרפי - חשופת מט"ח-ארה"ב | N121: לא | O121: ILS | P121: 20000 | Q121: 1 | R121: 7865 | T121: 1573 | U121: 0.0002 | V121: 0.00736 | W121: 0.00529
A122: 520042177 | B122: 13500 | C122: הראל קרנות מדד | D122: 511776783 | E122: ח.פ. | F122: הראל סל (4A) ת"א 90 | G122: IL0011489312 | H122: ISIN | I122: עוקב אחר מדדי מניות בישראל | J122: ישראל | L122: TASE | N122: לא | O122: ILS | P122: 75625 | Q122: 1 | R122: 2013 | T122: 1522.331 | U122: 0.0003 | V122: 0.00712 | W122: 0.00512
A123: 520042177 | B123: 13500 | C123: מיטב קרנות נאמנ | D123: 513534974 | E123: ח.פ. | F123: תכלית DAX30 מנוטרל | G123: IL0011438251 | H123: ISIN | I123: עוקב אחר מדדי מניות בחו"ל | J123: ישראל | K123: ישראל | L123: TASE | M123: DAX 30 - מניות בחו"ל - מניות גיאוגרפי - מנוטרלת מט"ח-אירופה גרמניה | N123: לא | O123: ILS | P123: 8215 | Q123: 1 | R123: 16810 | T123: 1380.942 | U123: 0.00028 | V123: 0.00646 | W123: 0.00464
A124: 520042177 | B124: 13500 | C124: קסם קרנות נאמנו | D124: 510938608 | E124: ח.פ. | F124: MSCI AC Far East EX Japan (4D) ETF | G124: IL0011458382 | H124: ISIN | I124: עוקב אחר מדדי מניות בחו"ל | J124: ישראל | K124: ישראל | L124: TASE | M124: MSCI AC WORLD INDEX - מניות בחו"ל - מניות כללי בחו"ל - חשופת מט"ח-מניות כללי בחו"ל | N124: לא | O124: ILS | P124: 58700 | Q124: 1 | R124: 2330 | T124: 1367.71 | U124: 0.00194 | V124: 0.0064 | W124: 0.0046
A125: 520042177 | B125: 13500 | C125: מגדל קרנות נאמנ | D125: 511303661 | E125: ח.פ. | F125: MTF סל (4A) ת"א 90 | G125: IL0011502593 | H125: ISIN | I125: עוקב אחר מדדי מניות בישראל | J125: ישראל | K125: ישראל | L125: TASE | M125: 90 מניות בארץ - מניות כללי-ת"א | N125: לא | O125: ILS | P125: 40000 | Q125: 1 | R125: 3034 | T125: 1213.6 | U125: 0.00078 | V125: 0.00568 | W125: 0.00408
A126: 520042177 | B126: 13500 | C126: מגדל קרנות נאמנ | D126: 511303661 | E126: ח.פ. | F126: מגדל MTF DAX30 מנוטרל | G126: IL0011504169 | H126: ISIN | I126: עוקב אחר מדדי מניות בחו"ל | J126: ישראל | K126: ישראל | L126: TASE | M126: DAX 30 - מניות בחו"ל - מניות גיאוגרפי - מנוטרלת מט"ח-אירופה גרמניה | N126: לא | O126: ILS | P126: 23500 | Q126: 1 | R126: 4602 | T126: 1081.47 | U126: 0.00338 | V126: 0.00506 | W126: 0.00364
A127: 520042177 | B127: 13500 | C127: מגדל קרנות נאמנ | D127: 511303661 | E127: ח.פ. | F127: MTF סל (STOXX Europe 600 (4A שקלי | G127: IL0011506149 | H127: ISIN | I127: עוקב אחר מדדי מניות בחו"ל | J127: ישראל | K127: ישראל | L127: TASE | M127: STOXX EUROPE 600 - מניות בחו"ל - מניות גיאוגרפי - מנוטרלת מט"ח-אירופה כללי | N127: לא | O127: ILS | P127: 11275 | Q127: 1 | R127: 7671 | T127: 864.905 | U127: 0.00276 | V127: 0.00404 | W127: 0.00291
A128: 520042177 | B128: 13500 | C128: מיטב קרנות נאמנ | D128: 513534974 | E128: ח.פ. | F128: תכלית סל (A4) ת"א 35 | G128: IL0011437006 | H128: ISIN | I128: עוקב אחר מדדי מניות בישראל | J128: ישראל | K128: ישראל | L128: TASE | M128: 35 מניות בארץ - מניות כללי-ת"א | N128: לא | O128: ILS | P128: 26500 | Q128: 1 | R128: 2092 | T128: 554.38 | U128: 0.0001 | V128: 0.00259 | W128: 0.00186
A129: 520042177 | B129: 13500 | C129: מגדל קרנות נאמנ | D129: 511303661 | E129: ח.פ. | F129: MTF סל (Nasdaq 100 (4D | G129: IL0011813875 | H129: ISIN | I129: עוקב אחר מדדי מניות בחו"ל | J129: ישראל | K129: ישראל | L129: TASE | M129: NASDAQ 100 - מניות בחו"ל - מניות גיאוגרפי - חשופת מט"ח-ארה"ב | N129: לא | O129: ILS | P129: 5200 | Q129: 1 | R129: 10350 | T129: 538.2 | U129: 0.00052 | V129: 0.00252 | W129: 0.00181
A130: 520042177 | B130: 13500 | C130: קסם קרנות נאמנו | D130: 510938608 | E130: ח.פ. | F130: קסם STOXX Europe 600 (4D) ETF | G130: IL0011462087 | H130: ISIN | I130: עוקב אחר מדדי מניות בחו"ל | J130: ישראל | K130: ישראל | L130: TASE | M130: STOXX EUROPE 600 -מניות בחו"ל - מניות גיאוגרפי - חשופת מט"ח-אירופה כללי | N130: לא | O130: ILS | P130: 1055 | Q130: 1 | R130: 50740 | T130: 535.307 | U130: 0.00054 | V130: 0.0025 | W130: 0.0018
A131: 520042177 | B131: 13500 | C131: קסם קרנות נאמנו | D131: 510938608 | E131: ח.פ. | F131: קסם STOX600 מנוטרל | G131: IL0011461824 | H131: ISIN | I131: עוקב אחר מדדי מניות בחו"ל | J131: ישראל | K131: ישראל | L131: TASE | M131: STOXX EUROPE 600 - מניות בחו"ל - מניות גיאוגרפי - מנוטרלת מט"ח-אירופה כללי | N131: לא | O131: ILS | P131: 4621 | Q131: 1 | R131: 11540 | T131: 533.263 | U131: 0.00057 | V131: 0.00249 | W131: 0.00179
A132: 520042177 | B132: 13500 | C132: מיטב קרנות נאמנ | D132: 513534974 | E132: ח.פ. | F132: תכלית סל (4D) ‏‏EURO STOXX 50 | G132: IL0011444275 | H132: ISIN | I132: עוקב אחר מדדי מניות בחו"ל | J132: ישראל | K132: ישראל | L132: TASE | M132: EURO STOXX 50 - מניות בחו"ל - מניות גיאוגרפי - חשופת מט"ח-אירופה כללי | N132: לא | O132: ILS | P132: 1900 | Q132: 1 | R132: 26500 | T132: 503.5 | U132: 0.00078 | V132: 0.00235 | W132: 0.00169
A133: 520042177 | B133: 13500 | C133: הראל קרנות מדד | D133: 511776783 | E133: ח.פ. | F133: הראל סל (A4) ת"א 35 | G133: IL0011489072 | H133: ISIN | I133: עוקב אחר מדדי מניות בישראל | J133: ישראל | K133: ישראל | L133: TASE | M133: 35 מניות בארץ - מניות כללי-ת"א | N133: לא | O133: ILS | P133: 23849 | Q133: 1 | R133: 2094 | T133: 499.398 | U133: 0.00028 | V133: 0.00234 | W133: 0.00168
A134: 520042177 | B134: 13500 | C134: מור קרנות נאמנ | D134: 514884485 | E134: ח.פ. | F134: מור סל (4A) ת"א-125 | G134: IL0011961534 | H134: ISIN | I134: עוקב אחר מדדי מניות בישראל | J134: ישראל | K134: ישראל | L134: TASE | M134: 125 מניות בארץ - מניות כללי-ת"א | N134: לא | O134: ILS | P134: 8300 | Q134: 1 | R134: 5753 | T134: 477.499 | U134: 0.00132 | V134: 0.00223 | W134: 0.00161
... A136: 520042177 | B136: 13500 | C136: אינבסקו אינבס | D136: 2355 | E136: מספר מנפיק | F136: INVESCO S&P 500 UCITS ETF | G136: IE00B3YCGJ38 | H136: ISIN | I136: עוקב אחר מדדי מניות בחו"ל | J136: חו"ל | K136: אירופה | L136: TASE | M136: S&P 500 - מניות בחו"ל - מניות גיאוגרפי - חשופת מט"ח-ארה"ב | N136: לא | O136: ILS | P136: 2550 | Q136: 1 | R136: 418000 | T136: 10659 | U136: 0.0064 | V136: 0.04985 | W136: 0.03585
A137: 520042177 | B137: 13500 | C137: STATE STREET-SPDRS | D137: 4640 | E137: מספר מנפיק | F137: SPY - S&P 500 | G137: US78462F1030 | H137: ISIN | I137: עוקב אחר מדדי מניות בחו"ל | J137: חו"ל | K137: ארה"ב | L137: NYSE | M137: S&P 500 - מניות בחו"ל - מניות גיאוגרפי - חשופת מט"ח-ארה"ב | N137: לא | O137: USD | P137: 3725 | Q137: 3.71 | R137: 57376 | S137: =4.892+312.1/1000/Q137 -> 4.976124 | T137: =7947.37+312.1/1000 -> 7947.6821 | U137: 0 | V137: 0.03719 | W137: 0.02675
A138: 520042177 | B138: 13500 | C138: VANGURUARD | D138: 4922 | E138: מספר מנפיק | F138: VOO US_VANGUARD S&P 500 | G138: US9229083632 | H138: ISIN | I138: עוקב אחר מדדי מניות בחו"ל | J138: חו"ל | K138: ארה"ב | L138: NYSE | M138: S&P 500 - מניות בחו"ל - מניות גיאוגרפי - חשופת מט"ח-ארה"ב | N138: לא | O138: USD | P138: 3595 | Q138: 3.71 | R138: 52767 | S138: 5.891 | T138: 7059.627 | U138: 0 | V138: 0.03304 | W138: 0.02376
A139: 520042177 | B139: 13500 | C139: Invesco Capital Management LLC | D139: 1290 | E139: מספר מנפיק | F139: QQQ - Nasdaq 100 | G139: US46090E1038 | H139: ISIN | I139: עוקב אחר מדדי מניות בחו"ל | J139: חו"ל | K139: ארה"ב | L139: NASDAQ | M139: NASDAQ 100 - מניות בחו"ל - מניות גיאוגרפי - חשופת מט"ח-ארה"ב | N139: לא | O139: USD | P139: 3500 | Q139: 3.71 | R139: 48807 | S139: =1.783+113.71/1000/Q139 -> 1.8136496 | T139: =6344.202+113.71/1000 -> 6344.3157 | U139: 0 | V139: 0.02968 | W139: 0.02134
A140: 520042177 | B140: 13500 | C140: Guggenheim Funds | D140: 4205 | E140: מספר מנפיק | F140: RSP-S&P 500 EQUAL WEI | G140: US46137V3574 | H140: ISIN | I140: עוקב אחר מדדי מניות בחו"ל | J140: חו"ל | K140: ארה"ב | L140: NYSE | M140: S&P 500 - מניות בחו"ל - מניות גיאוגרפי - חשופת מט"ח-ארה"ב | N140: לא | O140: USD | P140: 7500 | Q140: 3.71 | R140: 17916 | T140: 4985.127 | U140: 0 | V140: 0.02331 | W140: 0.01677
A141: 520042177 | B141: 13500 | C141: ISHARES | D141: 4601 | E141: מספר מנפיק | F141: DAXEX GY - DAX | G141: DE0005933931 | H141: ISIN | I141: עוקב אחר מדדי מניות בחו"ל | J141: חו"ל | K141: ארה"ב | L141: FWB | M141: Equity Funds | N141: לא | O141: EUR | P141: 7100 | Q141: 4.1524 | R141: 16098 | T141: 4746.019 | U141: 0 | V141: 0.0222 | W141: 0.01596
A142: 520042177 | B142: 13500 | C142: ISHARES | D142: 4601 | E142: מספר מנפיק | F142: ISHARES MSCI EMR | G142: US46434G7640 | H142: ISIN | I142: עוקב אחר מדדי מניות בחו"ל | J142: חו"ל | K142: ארה"ב | L142: אחר | M142: MSCI EMERGING MARKETS - מניות בחו"ל - מניות גיאוגרפי - חשופת מט"ח-שווקים מתעוררים כללי | N142: לא | O142: USD | P142: 18100 | Q142: 3.71 | R142: 6111 | T142: 4103.598 | U142: 0 | V142: 0.01919 | W142: 0.0138
A143: 520042177 | B143: 13500 | C143: ISHARES | D143: 4601 | E143: מספר מנפיק | F143: IWM - RUSSELL 2000 | G143: US4642876555 | H143: ISIN | I143: עוקב אחר מדדי מניות בחו"ל | J143: חו"ל | K143: ארה"ב | L143: NYSE | M143: RUSSELL 2000 - מניות בחו"ל - מניות גיאוגרפי - חשופת מט"ח-ארה"ב | N143: לא | O143: USD | P143: 4270 | Q143: 3.71 | R143: 22089 | T143: 3499.273 | U143: 0 | V143: 0.01636 | W143: 0.01177
A144: 520042177 | B144: 13500 | C144: קסם קרנות נאמנו | D144: 510938608 | E144: ח.פ. | F144: קסם DAX 30 ETF | G144: IL0011465130 | H144: ISIN | I144: עוקב אחר מדדי מניות בחו"ל | J144: חו"ל | K144: ישראל | L144: TASE | M144: DAX 30 - מניות בחו"ל - מניות גיאוגרפי - חשופת מט"ח-אירופה גרמניה | N144: לא | O144: ILS | P144: 46641.12 | Q144: 1 | R144: 6991 | T144: 3260.681 | U144: 0.0033 | V144: 0.01525 | W144: 0.01097
A145: 520042177 | B145: 13500 | C145: הראל קרנות מדד | D145: 511776783 | E145: ח.פ. | F145: הראל סל STOXX Europe 60 | G145: IL0011498719 | H145: ISIN | I145: עוקב אחר מדדי מניות בחו"ל | J145: חו"ל | K145: ישראל | L145: TASE | M145: מניות בחו"ל - מניות גיאוגרפי - חשופת מט"ח-אירופה - מדד אחר | N145: לא | O145: ILS | P145: 92960 | Q145: 1 | R145: 2830 | T145: 2630.768 | U145: 0.00347 | V145: 0.0123 | W145: 0.00885
A146: 520042177 | B146: 13500 | C146: BlackRock | D146: 2235 | E146: מספר מנפיק | F146: AAXJ-ISHARES ASIA | G146: US4642881829 | H146: ISIN | I146: עוקב אחר מדדי מניות בחו"ל | J146: חו"ל | K146: ארה"ב | L146: NASDAQ | M146: Equity Funds | N146: לא | O146: USD | P146: 8560 | Q146: 3.71 | R146: 7845 | T146: 2491.384 | U146: 0 | V146: 0.01165 | W146: 0.00838
A147: 520042177 | B147: 13500 | C147: STATE STREET-SPDRS | D147: 4640 | E147: מספר מנפיק | F147: HEALTH CARE XLV | G147: us81369y2090 | H147: ISIN | I147: עוקב אחר מדדי מניות בחו"ל | J147: חו"ל | K147: ארה"ב | L147: NYSE | M147: Equity Funds | N147: לא | O147: USD | P147: 2500 | Q147: 3.71 | R147: 15402 | T147: 1428.536 | U147: 0 | V147: 0.00668 | W147: 0.0048
A148: 520042177 | B148: 13500 | C148: אינבסקו אינבס | D148: 2355 | E148: מספר מנפיק | F148: Invesco Russell 2000 UCITS ETF | G148: IE00B60SX402 | H148: ISIN | I148: עוקב אחר מדדי מניות בחו"ל | J148: חו"ל | K148: ארה"ב | L148: TASE | M148: RUSSELL 2000 - מניות בחו"ל - מניות גיאוגרפי - חשופת מט"ח-ארה"ב | N148: לא | O148: ILS | P148: 2950 | Q148: 1 | R148: 41260 | T148: 1217.17 | U148: 0.0311 | V148: 0.00569 | W148: 0.00409
A149: 520042177 | B149: 13500 | C149: ISHARES | D149: 4601 | E149: מספר מנפיק | F149: ISHARES NASDAQ 100 | G149: IE00B53SZB19 | H149: ISIN | I149: עוקב אחר מדדי מניות בחו"ל | J149: חו"ל | K149: ארה"ב | L149: LSE | M149: NASDAQ 100 - מניות בחו"ל - מניות גיאוגרפי - חשופת מט"ח-ארה"ב | N149: לא | O149: USD | P149: 230 | Q149: 3.71 | R149: 114221 | T149: 974.648 | U149: 0 | V149: 0.00456 | W149: 0.00328
A150: 520042177 | B150: 13500 | C150: Invesco Management S.A | D150: 5224 | E150: מספר מנפיק | F150: Invesco NASDAQ 100 ETF | G150: US46138G6492 | H150: ISIN | I150: עוקב אחר מדדי מניות בחו"ל | J150: חו"ל | K150: ארה"ב | L150: אחר | M150: NASDAQ 100 - מניות בחו"ל - מניות גיאוגרפי - חשופת מט"ח-ארה"ב | N150: לא | O150: USD | P150: 1060 | Q150: 3.71 | R150: 20085 | T150: 789.863 | U150: 0 | V150: 0.00369 | W150: 0.00266
A151: 520042177 | B151: 13500 | C151: ISHARES | D151: 4601 | E151: מספר מנפיק | F151: MCHI CHINA INDEX | G151: US46429B6719 | H151: ISIN | I151: עוקב אחר מדדי מניות בחו"ל | J151: חו"ל | K151: ארה"ב | L151: NASDAQ | M151: Equity Funds | N151: לא | O151: USD | P151: 2750 | Q151: 3.71 | R151: 5091 | T151: 519.409 | U151: 0 | V151: 0.00243 | W151: 0.00175
... A157: 520042177 | B157: 142 | C157: מגדל קרנות נאמנ | D157: 511303661 | E157: ח.פ. | F157: MTF סל (SP500 (4A מנוטרלת מט"ח | G157: IL0011505729 | H157: ISIN | I157: עוקב אחר מדדי מניות בחו"ל | J157: ישראל | K157: ישראל | L157: TASE | M157: S&P 500 - מניות בחו"ל - מניות גיאוגרפי - מנוטרלת מט"ח-ארה"ב | N157: לא | O157: ILS | P157: 45000 | Q157: 1 | R157: 7341 | T157: 3303.45 | U157: 0.00145 | V157: 0.01747 | W157: 0.00506
A158: 520042177 | B158: 142 | C158: Invesco Capital Management LLC | D158: 1290 | E158: מספר מנפיק | F158: QQQ - Nasdaq 100 | G158: US46090E1038 | H158: ISIN | I158: עוקב אחר מדדי מניות בחו"ל | J158: חו"ל | K158: ארה"ב | L158: NASDAQ | M158: NASDAQ 100 - מניות בחו"ל - מניות גיאוגרפי - חשופת מט"ח-ארה"ב | N158: לא | O158: USD | P158: 24925 | Q158: 3.71 | R158: 48807 | S158: =12.694+809.8/1000/Q158 -> 12.912275 | T158: =45179.782+809.8/1000 -> 45180.592 | U158: 0 | V158: 0.23904 | W158: 0.06922
A159: 520042177 | B159: 142 | C159: SOURCE | D159: 4585 | E159: מספר מנפיק | F159: SPXS LN - S&P 500 | G159: IE00B3YCGJ38 | H159: ISIN | I159: עוקב אחר מדדי מניות בחו"ל | J159: חו"ל | K159: ארה"ב | L159: LSE | M159: S&P 500 - מניות בחו"ל - מניות גיאוגרפי - חשופת מט"ח-ארה"ב | N159: לא | O159: USD | P159: 9575 | Q159: 3.71 | R159: 112716 | T159: 40040.386 | U159: 0 | V159: 0.21179 | W159: 0.06133
A160: 520042177 | B160: 142 | C160: VANGURUARD | D160: 4922 | E160: מספר מנפיק | F160: VOO US_VANGUARD S&P 500 | G160: US9229083632 | H160: ISIN | I160: עוקב אחר מדדי מניות בחו"ל | J160: חו"ל | K160: ארה"ב | L160: NYSE | M160: S&P 500 - מניות בחו"ל - מניות גיאוגרפי - חשופת מט"ח-ארה"ב | N160: לא | O160: USD | P160: 17000 | Q160: 3.71 | R160: 52767 | S160: 27.856 | T160: 33383.493 | U160: 0 | V160: 0.17673 | W160: 0.05117
A161: 520042177 | B161: 142 | C161: STATE STREET-SPDRS | D161: 4640 | E161: מספר מנפיק | F161: XLE - Energy Select | G161: us81369y5069 | H161: ISIN | I161: עוקב אחר מדדי מניות בחו"ל | J161: חו"ל | K161: ארה"ב | L161: NYSE | M161: Equity Funds | N161: לא | O161: USD | P161: 26150 | Q161: 3.71 | R161: 8780 | T161: 8518.049 | U161: 0 | V161: 0.04506 | W161: 0.01305
A162: 520042177 | B162: 142 | C162: LYXOR | D162: 4617 | E162: מספר מנפיק | F162: Lyxor STOXX Europe 600 Banks UCITS ETF | G162: LU1834983477 | H162: ISIN | I162: עוקב אחר מדדי מניות בחו"ל | J162: חו"ל | K162: צרפת | L162: אחר | M162: Equity Funds | N162: לא | O162: EUR | P162: 63000 | Q162: 4.1524 | R162: 3230 | T162: 8449.719 | U162: 7e-05 | V162: 0.04469 | W162: 0.01294
A163: 520042177 | B163: 142 | C163: GLOBAL X | D163: 5099 | E163: מספר מנפיק | F163: GLOBAL X COPPER | G163: US37954Y8306 | H163: ISIN | I163: עוקב אחר מדדי מניות בחו"ל | J163: חו"ל | K163: ארה"ב | L163: NYSE | M163: Equity Funds | N163: לא | O163: USD | P163: 37750 | Q163: 3.71 | R163: 4727 | T163: 6620.282 | U163: 1e-05 | V163: 0.03502 | W163: 0.01014
A164: 520042177 | B164: 142 | C164: VANECK VECTORS | D164: 4816 | E164: מספר מנפיק | F164: SMH US-VANECK VECTORS | G164: US92189F6768 | H164: ISIN | I164: עוקב אחר מדדי מניות בחו"ל | J164: חו"ל | K164: ארה"ב | L164: NASDAQ | M164: Equity Funds | N164: לא | O164: USD | P164: 6775 | Q164: 3.71 | R164: 24545 | T164: 6169.447 | U164: 0 | V164: 0.03263 | W164: 0.00945
A165: 520042177 | B165: 143 | C165: מגדל קרנות נאמנ | D165: 511303661 | E165: ח.פ. | F165: MTF סל (SP500 (4A מנוטרלת מט"ח | G165: IL0011505729 | H165: ISIN | I165: עוקב אחר מדדי מניות בחו"ל | J165: ישראל | K165: ישראל | L165: TASE | M165: S&P 500 - מניות בחו"ל - מניות גיאוגרפי - מנוטרלת מט"ח-ארה"ב | N165: לא | O165: ILS | P165: 580000 | Q165: 1 | R165: 7341 | T165: 42577.8 | U165: 0.01871 | V165: 0.18088 | W165: 0.01519
